Workbook

Sheet Read me
G4: European Commission
G6: Directorate-General for Economic and Financial Affairs
G7: Unit C2 - Sustainability of public finances
G8: ECFIN-Secretariat-C2@ec.europa.eu
C16: FILE DESCRIPTION
C18: Data reported in this file are based on the European Commission (EC) 2026 spring forecast (SF 2026) and macroeconomic and budgetary projections from the joint EC-EPC Ageing Report 2024 (AR 2024) as well as from updated projections endorsed by the EPC in case of Czechia.
C22: This file contains a simplified version of the EC model used to calculate the general governement debt ratio dynamics for EU countries under different scenarios. A detailed description of the EC's general governement debt projections can be found in the "Debt Sustainability Monitor 2023" (DSM, March 2024).
C27: HOW TO USE THIS TOOL TO CALCULATE NEW DEBT PROJECTIONS
C29: This tool can be used to calculate debt projections under different macroeconomic and structural primary balance adjustment assumptions. Debt projections for each scenario will update automatically with changes in the macroeconomic assumptions or the adjustment parameters. The fulfilment of DSA-based criteria, the safeguards and the benchmark will be automatically calculated in the sheet "Criteria results". Formulas are fully visible. To assess the impact of alternative fiscal paths or to check the robustness of underlying macroeconomic assumptions, the user can modify the content of key cells in the sheets "Criteria results" and "Input data" (see below). Note that, for a proper functioning of the file, you should make sure that Excel is in "Automatic" computation mode, i.e. in the File menu, Option tab, click on "Formulas", "Calculation Options" and "Automatic".
C31: The spreadsheet is composed of the following elements:
D33: The grey sheet "Criteria results" contains three types of cells identified by different colours:
F34: Cells with a yellow background and a red frame can be modified to see the impact of a different duration or pace of adjustment.
F35: Cells with a white or pale red (in case the deficit resilience safeguard is binding) background provide results obtained with the adjustment chosen in the yellow cells. To replicate the Commission's calculations, the underlying formulas should not be modified.
F37: Cells with a pale blue background correspond to the Commission's prior guidance provided to the Member State. Those are hard numbers that do not depend on the adjustment chosen in the file.
D39: "Criteria results" contains five tables. Table 1 "Adjustment input data": the user can set the duration of the plan in cell F5 (4 years without extension or 7 years with extension), the yearly adjustment pace under the scenario that does not take into account the deficit resilience safeguard (F7) and for the scenario that automatically applies that safeguard (F6). Note that the country cell (F4) cannot be changed.
D40: The adjustement in F7 needs to be selected first so that the message on line 13 signals that the two DSA-based criteria are fulfilled. As a second step, the adjustment in F6 can be selected (and cannot be lower than in F7) so that line 12 reports compliance with the requirements.
D41: Table 2 "DSA-based criteria and deficit resilience safeguard" reports whether the chosen adjustment fulfils the DSA-based criteria (cells H12:I13) and whether the deficit resillience safeguard is binding.
D42: Table 3 "Main fiscal variables with automatic deficit resilience safeguard" reports the annual adjustment over the adjustment period, in terms of change in SPB (line 18), level of the structural balance (line 19) and SPB level at the end of the adjustment (line 20). This table reports the results for the scenario that automatically applies the deficit resillience safeguard. For this reason, the SB is highlighted in red if it is lower than -1.5% of GDP.
D43: Table 4 "Main fiscal variables without automatic deficit resilience safeguard" reports the annual adjustment over the adjustment period, in terms of change in SPB (line 25), level of the structural balance (line 26) and SPB level at the end of the adjustment (line 27). This table reports the results for the scenario without the deficit resillience safeguard.
D44: Table 5 "Technical information" reports the SPB level at the end of the adjustment period that fulfils the DSA-based criteria and takes into account the deficit resilience safeguard, both without and with extension.
D46: The sheet "Input data" in light blue presents the input data, including fiscal and GDP growth assumptions as well as additional fiscal parameters. Unless stated otherwise below, the user can change all values in this tab.
D47: Coloured cells indicate data sources as follows (this colour-coding holds in the other spreadsheets):
F48: Cells in light grey indicate Commission forecast (available in the AMECO database)
F49: Cells in light blue indicate values from the Ageing Report 2024
F50: Cells in light orange provide parameters needed to compute the decomposition of government debt according to its maturity structure (i.e. short-term and long-term debt, maturing, rolled-over and non-maturing debt). These are fixed shares which the user cannot change.
F51: Cells in dark orange indicate financial market prices.
D52: Non coloured parameters in cells C50:C70 were calibrated based on different data sources. Data sources are given in corresponding cells of column E.
C54: The next spreadsheets present the no-fiscal-policy-change baseline and the adjustment scenario, with and without the impact of the deficit resilience safeguard. Each deterministic projection provides a single path for debt until 10 years after the end of the adjustment period under certain assumptions for budgetary, macroeconomic and financial variables.
D56: The sheet in blue provides, as a reference, the baseline no-fiscal-policy-change scenario. The background colour coding is the same as in the sheet "Input data".
D58: The sheet in orange presents the scenario that automatically corrects the yearly adjustment path to account for the deficit resillience safeguard.
D60: The sheet in green presents the adjustment scenarios without the deficit resilience safeguard. This scenario is computed automatically based on the yearly adjustment path set in "Criteria results" (see above).
C62: Within the orange sheet and each green sheet, the background of the SPB line has three colours. Each colour corresponds to a specific period of the projections:
E63: Light grey indicates the pre-plan period, corresponding to the EC forecast
E64: Mild grey indicates the period during which the SPB adjusts according to the path set in sheet "Criteria results"
E65: Dark grey indicates the period in which the SPB, net of changes in cost of ageing, remains constant at its value of end of adjustment.
C68: WHERE ARE THE MAIN RESULTS LOCATED?
C69: The fullfilment of the criteria is checked in the sheet "Criteria results". Debt projections can be found in line 57 of each scenario.
D71: The 'FASTOP reporting' sheet in violet provides help for preparing reporting tables. It readily provides all the tables foreseen by the guidance notice on the "Information Requirements for the Medium-Term Fiscal-Structural Plans" once the parameters are set in the rest of this file. This sheet is meant to be an assistance. The need for a thorough scrutiny of the figures before submitting such tables remains.

Sheet Criteria results
U2: 4 | V2: -1.5
D3: Table 1 - Adjustment input data | U3: 7 | V3: -1.48
D4: Country | F4: CZ | V4: -1.46
D5: Number of years of adjustment | F5: 4 | V5: -1.44
C6: 2. | D6: Annual adjustment (with safeguard) | F6: 0.46 | V6: -1.42
C7: 1. | D7: Annual adjustment (without safeguard) | F7: 0.46 | V7: -1.4
V8: -1.38
H9: Table 2 - DSA-based criteria and deficit resilience safeguard | V9: -1.36
H10: DSA-based criteria | J10: Deficit resilience safeguard | V10: -1.34
H11: Deficit below 3% of GDP | I11: ="Debt below 60% of GDP in T+"&10+F5 -> Debt below 60% of GDP in T+14 | V11: -1.32
C12: 2. | D12: Adjustment scenario with automatic deficit resilience safeguard * (sheet "Adjustment scenario") | H12: =IF(MIN(OFFSET('Adjustment scenario'!$D$77,0,$F$5,1,11))>-3,"ok","Not met") -> ok | I12: =IF(OFFSET('Adjustment scenario'!$D$57,0,$F$5+10,1,1)<60,"ok","Not met") -> ok | J12: =IF(AND($F$5=4,COUNTIF(G18:J18,">" & F6)=0),"Not binding",IF(AND($F$5=7,COUNTIF(G18:M18,">" & F6)=0),"Not binding","Binding")) -> Not binding | K12: =IF(OR($H$13="Not met",$I$13="Not met"),"Please adjust cell F7 so that both DSA-based criteria are met", IF($F$6<$F$7,"The adjustment in F6 cannot be lower than in F7", IF(AND($H$12="ok",$I$12="ok",$H$13="ok",$I$13="ok",$F$6>=$F$7, OR(AND($F$5=4,$G$18>=$H$18,$H$18>=$I$18,$I$18>=$J$18,OR($J$18>=0.4,$J$19>-1.5)), AND($F$5=7,$G$18>=$H$18,$H$18>=$I$18,$I$18>=$J$18,$J$18>=$K$18,$K$18>=$L$18,$L$18>=$M$18,OR($M$18>=0.25,$M$19>-1.5)))), "OK"&CHAR(10)&"The adjustment in F6 fulfills all requirements including the deficit resilience safeguard", "NOT OK"&CHAR(10)&"The adjustment in F6 does not fulfill all requirements"))) -> OK The adjustment in F6 fulfills all requirements including the deficit resilience safeguard | V12: -1.3
C13: 1. | D13: Adjustment scenario without deficit resilience safeguard (sheet "Adjust. no safeguard") | H13: =IF(MIN(OFFSET('Adjust. no safeguard'!$D$77,0,$F$5,1,11))>-3,"ok","Not met") -> ok | I13: =IF(OFFSET('Adjust. no safeguard'!$D$57,0,$F$5+10,1,1)<60,"ok","Not met") -> ok | K13: =IF(AND($H$13="ok",$I$13="ok"), "OK"&CHAR(10)&"The adjustment in F7 ensures that the debt and deficit remain"&CHAR(10)&"below the Treaty reference values over the medium term", "NOT OK"&CHAR(10)&"The adjustment in F7 does not ensure that the debt and deficit remain"&CHAR(10)&"below the Treaty reference values over the medium term") -> OK The adjustment in F7 ensures that the debt and deficit remain below the Treaty reference values over the medium term | V13: -1.28
D14: * Under a plan without (with) extension, an adjustment of 0.40 pps (0.25 pps) of GDP in SPB terms is applied if the structural deficit in the previous year exceeds 1.5% of GDP. | V14: -1.26
V15: -1.24
G16: Table 3 - Main fiscal variables with automatic deficit resilience safeguard * | V16: -1.22
G17: ='Input data'!$C$5+1 -> 2027 | H17: =G17+1 -> 2028 | I17: =H17+1 -> 2029 | J17: =I17+1 -> 2030 | K17: =J17+1 -> 2031 | L17: =K17+1 -> 2032 | M17: =L17+1 -> 2033 | V17: -1.2
D18: Annual adjustment (change in SPB) | G18: ='Adjustment scenario'!E12-'Adjustment scenario'!D12 -> 0.46 | H18: ='Adjustment scenario'!F12-'Adjustment scenario'!E12 -> 0.46 | I18: ='Adjustment scenario'!G12-'Adjustment scenario'!F12 -> 0.46 | J18: ='Adjustment scenario'!H12-'Adjustment scenario'!G12 -> 0.46 | K18: ='Adjustment scenario'!I12-'Adjustment scenario'!H12 -> 0 | L18: ='Adjustment scenario'!J12-'Adjustment scenario'!I12 -> 0 | M18: ='Adjustment scenario'!K12-'Adjustment scenario'!J12 -> 0 | V18: -1.18
D19: Structural balance | G19: ='Adjustment scenario'!E78 -> -2.1823295 | H19: ='Adjustment scenario'!F78 -> -1.8742338 | I19: ='Adjustment scenario'!G78 -> -1.5129912 | J19: ='Adjustment scenario'!H78 -> -1.134607 | K19: ='Adjustment scenario'!I78 -> -1.3068405 | L19: ='Adjustment scenario'!J78 -> -1.3831522 | M19: ='Adjustment scenario'!K78 -> -1.4587376 | V19: -1.16
D20: SPB at the end of the adjustment | J20: =IF(F5=4,'Adjustment scenario'!H12,"") -> 0.507241 | M20: =IF(F5=7,'Adjustment scenario'!K12,"") | V20: -1.14
D21: * The structural balance is flagged in red if it is below -1.5% of GDP. | V21: -1.12
V22: -1.1
G23: Table 4 - Main fiscal variables without automatic deficit resilience safeguard | V23: -1.08
G24: ='Input data'!$C$5+1 -> 2027 | H24: =G24+1 -> 2028 | I24: =H24+1 -> 2029 | J24: =I24+1 -> 2030 | K24: =J24+1 -> 2031 | L24: =K24+1 -> 2032 | M24: =L24+1 -> 2033 | V24: -1.06
D25: Annual adjustment (change in SPB) | G25: ='Adjust. no safeguard'!E12-'Adjust. no safeguard'!D12 -> 0.46 | H25: ='Adjust. no safeguard'!F12-'Adjust. no safeguard'!E12 -> 0.46 | I25: ='Adjust. no safeguard'!G12-'Adjust. no safeguard'!F12 -> 0.46 | J25: ='Adjust. no safeguard'!H12-'Adjust. no safeguard'!G12 -> 0.46 | K25: ='Adjust. no safeguard'!I12-'Adjust. no safeguard'!H12 -> 0 | L25: ='Adjust. no safeguard'!J12-'Adjust. no safeguard'!I12 -> 0 | M25: ='Adjust. no safeguard'!K12-'Adjust. no safeguard'!J12 -> 0 | V25: -1.04
D26: Structural balance | G26: ='Adjust. no safeguard'!E78 -> -2.1823295 | H26: ='Adjust. no safeguard'!F78 -> -1.8742338 | I26: ='Adjust. no safeguard'!G78 -> -1.5129912 | J26: ='Adjust. no safeguard'!H78 -> -1.134607 | K26: ='Adjust. no safeguard'!I78 -> -1.3068405 | L26: ='Adjust. no safeguard'!J78 -> -1.3831522 | M26: ='Adjust. no safeguard'!K78 -> -1.4587376 | V26: -1.02
D27: SPB at the end of the adjustment | J27: =IF(F5=4,'Adjust. no safeguard'!H12,"") -> 0.507241 | M27: =IF(F5=7,'Adjust. no safeguard'!K12,"") | V27: -1
V28: -0.98
V29: -0.96
V30: -0.94
G31: Table 5 - Technical information* | V31: -0.92
G32: Without extension | H32: With extension | V32: -0.9
D33: Number of years of adjustment | G33: 4 | H33: 7 | V33: -0.88
D34: SPB at the end of the adjustment | G34: 0.507241 | H34: 0.907241 | V34: -0.86
D35: * The technical information provides the structural primary balance necessary to ensure that the deficit remains below 3% of GDP and debt remains below 60% of GDP over the medium term in the absence of additional fiscal measures beyond the adjustment period. In line with the deficit resilience safeguard, and when necessary, an adjustment of 0.4 pps (0.25 pps in case of extension) in structural primary terms is applied until the structural balance is at least equal to -1.5% of GDP. Note that the SPB at the end of the adjustment period may be lower than the SPB at the beginning of the plan, indicating that the Member State does not need to adjust. | V35: -0.84
V36: -0.82
V37: -0.8
V38: -0.78
V39: -0.76
V40: -0.74
V41: -0.72
V42: -0.7
V43: -0.68
V44: -0.66
V45: -0.64
V46: -0.62
V47: -0.6
... V152: 1.5

Sheet Prior guidance
B3: Country | D3: CZ | F3: Czechia
B6: Main budgetary, macroeconomic and financial variables
B8: Budgetary variables: initial conditions | D8: 2025 | F8: 2026
B9: Government budget balance (% of GDP) | D9: -2.147432 | F9: -2.7944635
B10: Government debt (% of GDP) | D10: 44.25023 | F10: 45.838496
B11: Net expenditure growth (%) | D11: 4.9156095 | F11: 6.3502551
B12: Structural primary balance (% of GDP) | D12: -0.5110157 | F12: -1.332759
B14: Main assumptions for a plan without extension (4 years) | D14: Assumption | F14: Period
B15: Change in the cost of ageing (pps) | D15: 0.9 | F15: 2030-2040
B16: Stock-flow adjustment (% of GDP) | D16: 0.060711421 | F16: 2027-2040 average
B17: Real GDP growth (%) | D17: 1.364418 | F17: 2027-2040 average
B18: Inflation (change in the GDP deflator, %) | D18: 2.5559991 | F18: 2027-2040 average
B19: Nominal implicit interest rate (%) | D19: 2.5559991 | F19: 2027-2040 average
B21: Main assumptions for a plan with extension (7 years) | D21: Assumption | F21: Period
B22: Change in the cost of ageing (pps) | D22: 1.2 | F22: 2033-2043
B23: Stock-flow adjustment (% of GDP) | D23: 0.049997641 | F23: 2027-2043 average
B24: Real GDP growth (%) | D24: 1.4065908 | F24: 2027-2043 average
B25: Inflation (change in the GDP deflator, %) | D25: 2.4968816 | F25: 2027-2043 average
B26: Nominal implicit interest rate (%) | D26: 4.3128754 | F26: 2027-2043 average
B31: Technical information
B33: For a plan without extension (4 years) Czechia | D33: With the deficit resilience safeguard | F33: Without the deficit resilience safeguard
B34: Minimum level for the structural primary balance in 2030 (% of GDP) | D34: 0.507241 | F34: 0.507241
B35: Difference with 2026 structural primary balance (pps) | D35: 1.84 | F35: 1.84
B37: For a plan with extension (7 years) Czechia | D37: With the deficit resilience safeguard | F37: Without the deficit resilience safeguard
B38: Minimum level for the structural primary balance in 2033 (% of GDP) | D38: 0.907241 | F38: 0.907241
B39: Difference with 2026 structural primary balance (pps) | D39: 2.24 | F39: 2.24

Sheet Input data
B3: Country | C3: CZ
B4: Base for last forecast and T+10, T+30 years | C4: 2025
B5: Last year before the adjustment | C5: 2026
B6: Last year of adjustment | C6: =C5+'Criteria results'!$F$5 -> 2030
B8: Key assumptions
C9: 2025 | D9: 2026 | E9: 2027 | F9: 2028 | G9: 2029 | H9: 2030 | I9: 2031 | J9: 2032 | K9: 2033 | L9: 2034 | M9: 2035 | N9: 2036 | O9: 2037 | P9: 2038 | Q9: 2039 | R9: 2040 | S9: 2041 | T9: 2042 | U9: 2043
B10: Fiscal assumptions (% of GDP)
B11: Key fiscal variables (based on the Commission 2026 spring forecast ("SF 2026")
B12: Debt | C12: 44.25023 | D12: 45.8385
B13: Structural primary balance ('+' means 'surplus') | C13: -0.5110157 | D13: -1.332759
B14: One-off and other temporary measures | C14: -0.1168709 | D14: 0 | E14: 0 | F14: 0 | G14: 0 | H14: 0 | I14: 0 | J14: 0 | K14: 0 | L14: 0 | M14: 0 | N14: 0 | O14: 0 | P14: 0 | Q14: 0 | R14: 0 | S14: 0 | T14: 0 | U14: 0
B15: Stock-flow adjustments (without exchange rate effect) | C15: 1.388104 | D15: 0.7474777 | E15: 0.85 | F15: 0 | G15: 0 | H15: 0 | I15: 0 | J15: 0 | K15: 0 | L15: 0 | M15: 0 | N15: 0 | O15: 0 | P15: 0 | Q15: 0 | R15: 0 | S15: 0 | T15: 0 | U15: 0
B16: Stock-flow adjustment (total) | C16: 1.334119 | D16: 0.7014194 | E16: 0.8499599 | F16: 0 | G16: 0 | H16: 0 | I16: 0 | J16: 0 | K16: 0 | L16: 0 | M16: 0 | N16: 0 | O16: 0 | P16: 0 | Q16: 0 | R16: 0 | S16: 0 | T16: 0 | U16: 0
B17: Subject to an excessive deficit procedure (EDP) (0-no/1-yes) | C17: 0 | D17: 0
B19: Cost of ageing and selected public revenue (based on the Commission-Council 2024 Ageing Report ("AR 2024"))
B20: Total ageing cost (net of taxes on pensions) | C20: =(C21+C22+C23+C24-C25) -> 19.8 | D20: =(D21+D22+D23+D24-D25) -> 19.7 | E20: =(E21+E22+E23+E24-E25) -> 19.8 | F20: =(F21+F22+F23+F24-F25) -> 19.9 | G20: =(G21+G22+G23+G24-G25) -> 20 | H20: =(H21+H22+H23+H24-H25) -> 20 | I20: =(I21+I22+I23+I24-I25) -> 20.1 | J20: =(J21+J22+J23+J24-J25) -> 20.1 | ... U20: =(U21+U22+U23+U24-U25) -> 21.3
B21: of which: Public pensions expenditure | C21: 8.2 | D21: 8 | E21: 7.9 | F21: 8 | G21: 8 | H21: 8 | I21: 8 | J21: 8 | K21: 8 | L21: 8.1 | M21: 8.1 | N21: 8.2 | O21: 8.2 | P21: 8.3 | Q21: 8.3 | R21: 8.4 | S21: 8.5 | T21: 8.5 | U21: 8.6
B22: Health care expenditure | C22: 5.9 | D22: 5.9 | E22: 6 | F22: 6 | G22: 6 | H22: 6 | I22: 6.1 | J22: 6.1 | K22: 6.1 | L22: 6.2 | M22: 6.2 | N22: 6.2 | O22: 6.2 | P22: 6.3 | Q22: 6.3 | R22: 6.3 | S22: 6.3 | T22: 6.4 | U22: 6.4
B23: Long-term care expenditure | C23: 1.5 | D23: 1.5 | E23: 1.6 | F23: 1.6 | G23: 1.7 | H23: 1.7 | I23: 1.7 | J23: 1.8 | K23: 1.8 | L23: 1.9 | M23: 1.9 | N23: 1.9 | O23: 2 | P23: 2 | Q23: 2 | R23: 2 | S23: 2.1 | T23: 2.1 | U23: 2.1
B24: Education & unemployment benefits expenditure | C24: 4.2 | D24: 4.3 | E24: 4.3 | F24: 4.3 | G24: 4.3 | H24: 4.3 | I24: 4.3 | J24: 4.2 | K24: 4.2 | L24: 4.2 | M24: 4.2 | N24: 4.2 | O24: 4.2 | P24: 4.2 | Q24: 4.2 | R24: 4.2 | S24: 4.2 | T24: 4.2 | U24: 4.2
B25: Taxes on pensions | C25: 0 | D25: 0 | E25: 0 | F25: 0 | G25: 0 | H25: 0 | I25: 0 | J25: 0 | K25: 0 | L25: 0 | M25: 0 | N25: 0 | O25: 0 | P25: 0 | Q25: 0 | R25: 0 | S25: 0 | T25: 0 | U25: 0
B26: Property income | C26: 1.037865 | D26: 1.023357 | E26: 1.008848 | F26: 0.9943401 | G26: 0.9798318 | H26: 0.9653235 | I26: 0.9508152 | J26: 0.9363069 | K26: 0.9217986 | L26: 0.9072903 | M26: 0.892782 | N26: 0.8782737 | O26: 0.8637654 | P26: 0.8492571 | Q26: 0.8347487 | R26: 0.8202404 | S26: 0.8057321 | T26: 0.7912238 | U26: 0.7767155
B28: Real GDP growth assumptions (based on SF 2026 T+10 projections and AR 2024 projections)
B29: Actual GDP
B30: Growth rate | C30: 2.580467 | D30: 1.79727 | E30: 2.151977 | F30: 1.373251 | G30: 1.123538 | H30: 1.157076 | I30: 1.226085 | J30: 1.236268 | K30: 1.244196 | L30: 1.209247 | M30: 1.140828 | N30: 1.257218 | O30: 1.373611 | P30: 1.490002 | Q30: 1.519997 | R30: 1.600002 | S30: 1.600005 | T30: 1.6 | U30: 1.61
B31: Level (CZK bn) | C31: 6479.806
B32: Potential GDP
B33: Growth rate | C33: 1.560683 | D33: 1.64766 | E33: 1.492104 | F33: 1.456502 | G33: 1.234396 | H33: 1.212544 | I33: 1.226088 | J33: 1.236266 | K33: 1.2442 | L33: 1.209244 | M33: 1.140822 | N33: 1.257215 | O33: 1.373607 | P33: 1.49 | Q33: 1.52 | R33: 1.6 | S33: 1.6 | T33: 1.6 | U33: 1.61
B34: Level (CZK bn) | C34: 6515.4565
B36: Interest rates (SF 2026, %)
B37: Nominal implicit interest rate on debt | C37: 3.196961 | D37: 3.078103 | E37: 2.999835
B38: Short-term nominal interest rate | C38: 3.6 | D38: 3.649853 | E38: 4.267191
B39: Long-term nominal interest rate | C39: 4.29 | D39: 4.701964 | E39: 4.915649
D40: Bloomberg data, country-specific forward market rates.
B41: Inflation (SF 2026, %)
B42: GDP deflator (national currency) | C42: 3.512605 | D42: 2.656677 | E42: 3.068664
B44: Net primary expenditure growth (SF 2026, %)
B45: Net primary expenditure growth | C45: 4.9156095 | D45: 6.3502551
B47: Additional parameters
E48: Sources
B49: Fiscal multiplier | C49: 0.6 | E49: DSM 2025
B50: Budget balance semi-elasticity | C50: 0.395 | E50: Mourre, G. et al. (2019), "The Semi-Elasticities Underlying the Cyclically-Adjusted Budget Balance: An Update and Further Analysis", European Economy, Discussion Paper, No. 098.
B52: Long-term nominal interest rate (T+10 convergence value) | C52: 5.88651 | E52: Bloomberg data, country-specific forward market rates.
B53: Short-term nominal interest rate (T+10 convergence value) | C53: 4.39095 | E53: Bloomberg data, country-specific forward market rates.
B54: Long-term nominal interest rate (T+30 convergence value) | C54: 4 | E54: DSM 2025
B55: Short-term nominal interest rate (T+30 convergence value) | C55: 2 | E55: DSM 2025
B57: Share of short-term debt in total government debt | C57: 0.0390272 | E57: Eurostat, average shares over the 3 last available years.
B58: Share of long-term debt in total government debt | C58: =1-C57 -> 0.9609728 | E58: Eurostat, average shares over the 3 last available years.
B59: Share of long-term debt that matures every year (T+10 convergence value) | C59: 0.07564793 | E59: ECB, country-specific historical average shares over the 6 last available years. For post-programme countries (CY, El , IE and PT), the redemption profile of official loans has been taken into account for the computation of the share of long-term debt that matures every year. For these countries, changing this parameter would not affect debt projections.
B61: GDP deflator (national currency) (T+10 convergence value) | C61: 2.34 | E61: Bloomberg data, inflation swaps.
B62: GDP deflator (national currency) (T+30 convergence value) | C62: 2 | E62: Central bank inflation target
B64: Share of primary expenditure in GDP in 2025 | C64: 41.891709 | E64: SF26
B66: Share of outstanding debt in total debt in 2025 | C66: 0.83727768 | E66: Derived from the model and made consistent with the short-term forecast.
B67: Share of rolled-over long-term debt in 2025 | C67: 0.061058349 | E67: Derived from the model and made consistent with the short-term forecast.
B68: Share of rolled-over short-term debt in 2025 | C68: 0.021804273 | E68: Derived from the model and made consistent with the short-term forecast.
B69: Share of new long-term debt in 2025 | C69: 0.076743036 | E69: Derived from the model and made consistent with the short-term forecast.
B70: Share of new short-term debt in 2025 | C70: 0.0031167024 | E70: Derived from the model and made consistent with the short-term forecast.

Sheet Baseline NFPC
B3: Country | C3: ='Input data'!C3 -> CZ
B4: Key years
B5: ='Input data'!B5 -> Last year before the adjustment | C5: =+'Input data'!C5 -> 2026
B6: Last year of adjustment | C6: =+C5+'Criteria results'!$F$5 -> 2030
B9: Key assumptions
C10: ='Input data'!$C$5-1 -> 2025 | D10: =C10+1 -> 2026 | E10: =D10+1 -> 2027 | F10: =E10+1 -> 2028 | G10: =F10+1 -> 2029 | H10: =G10+1 -> 2030 | I10: =H10+1 -> 2031 | J10: =I10+1 -> 2032 | K10: =J10+1 -> 2033 | ... U10: =T10+1 -> 2043
B11: Fiscal assumptions (% of GDP)
B12: Structural primary balance ('+' means 'surplus') | C12: ='Input data'!C13 -> -0.5110157 | D12: ='Input data'!D13 -> -1.332759 | E12: =D12 -> -1.332759 | F12: =E12 -> -1.332759 | G12: =F12 -> -1.332759 | H12: =G12 -> -1.332759 | I12: =H12 -> -1.332759 | J12: =I12 -> -1.332759 | K12: =J12 -> -1.332759 | L12: =K12 -> -1.332759 | ... U12: =T12 -> -1.332759
B13: One-off and other temporary measures | C13: ='Input data'!C14 -> -0.1168709 | D13: ='Input data'!D14 -> 0 | E13: ='Input data'!E14 -> 0 | F13: ='Input data'!F14 -> 0 | G13: ='Input data'!G14 -> 0 | H13: ='Input data'!H14 -> 0 | I13: ='Input data'!I14 -> 0 | J13: ='Input data'!J14 -> 0 | ... U13: ='Input data'!U14 -> 0
B14: Stock flow adjustments (without exchange rate effect) | C14: ='Input data'!C15 -> 1.388104 | D14: ='Input data'!D15 -> 0.7474777 | E14: ='Input data'!E15 -> 0.85 | F14: ='Input data'!F15 -> 0 | G14: ='Input data'!G15 -> 0 | H14: ='Input data'!H15 -> 0 | I14: ='Input data'!I15 -> 0 | J14: ='Input data'!J15 -> 0 | ... U14: ='Input data'!U15 -> 0
B16: ='Input data'!B19 -> Cost of ageing and selected public revenue (based on the Commission-Council 2024 Ageing Report ("AR 2024"))
B17: Total ageing cost (net of taxes on pensions) | C17: ='Input data'!C20 -> 19.8 | D17: ='Input data'!D20 -> 19.7 | E17: ='Input data'!E20 -> 19.8 | F17: ='Input data'!F20 -> 19.9 | G17: ='Input data'!G20 -> 20 | H17: ='Input data'!H20 -> 20 | I17: ='Input data'!I20 -> 20.1 | J17: ='Input data'!J20 -> 20.1 | ... U17: ='Input data'!U20 -> 21.3
B18: ='Input data'!B26 -> Property income | C18: ='Input data'!C26 -> 1.037865 | D18: ='Input data'!D26 -> 1.023357 | E18: ='Input data'!E26 -> 1.008848 | F18: ='Input data'!F26 -> 0.9943401 | G18: ='Input data'!G26 -> 0.9798318 | H18: ='Input data'!H26 -> 0.9653235 | I18: ='Input data'!I26 -> 0.9508152 | ... U18: ='Input data'!U26 -> 0.7767155
B20: GDP growth assumptions
B21: Actual GDP (real)
B22: Level | C22: ='Input data'!C31 -> 6479.806 | D22: =C22*(D23/100+1) -> 6596.2656 | E22: =D22*(E23/100+1) -> 6738.2157 | F22: =E22*(F23/100+1) -> 6830.7484 | G22: =F22*(G23/100+1) -> 6907.4944 | H22: =G22*(H23/100+1) -> 6987.4194 | I22: =H22*(I23/100+1) -> 7073.0911 | J22: =I22*(J23/100+1) -> 7160.5334 | K22: =J22*(K23/100+1) -> 7249.6245 | ... U22: =T22*(U23/100+1) -> 8363.8374
B23: Growth rate | C23: =+'Input data'!C30 -> 2.580467 | D23: =+'Input data'!D30 -> 1.79727 | E23: =+'Input data'!E30 -> 2.151977 | F23: =+'Input data'!F30 -> 1.373251 | G23: =+'Input data'!G30 -> 1.123538 | H23: =+'Input data'!H30 -> 1.157076 | I23: =+'Input data'!I30 -> 1.226085 | J23: =+'Input data'!J30 -> 1.236268 | ... U23: =+'Input data'!U30 -> 1.61
B25: Potential GDP (real)
B26: Level | C26: ='Input data'!C34 -> 6515.4565 | D26: =+C26*(1+'Input data'!D33/100) -> 6622.8091 | E26: =+D26*(1+'Input data'!E33/100) -> 6721.6283 | F26: =+E26*(1+'Input data'!F33/100) -> 6819.529 | G26: =+F26*(1+'Input data'!G33/100) -> 6903.7089 | H26: =+G26*(1+'Input data'!H33/100) -> 6987.4195 | I26: =+H26*(1+'Input data'!I33/100) -> 7073.0914 | J26: =+I26*(1+'Input data'!J33/100) -> 7160.5336 | K26: =+J26*(1+'Input data'!K33/100) -> 7249.6249 | ... U26: =+T26*(1+'Input data'!U33/100) -> 8363.8361
B28: Output gap
B29: Output gap | C29: =100*(C22/C26-1) -> -0.54716846 | D29: =100*(D22/D26-1) -> -0.40078891 | E29: =100*(E22/E26-1) -> 0.24677703 | F29: =100*(F22/F26-1) -> 0.16451868 | G29: =100*(G22/G26-1) -> 0.054832264 | H29: =100*(H22/H26-1) -> -1.2698694e-06 | I29: =100*(I22/I26-1) -> -4.2335323e-06 | J29: =100*(J22/J26-1) -> -2.2579557e-06 | ... U29: =100*(U22/U26-1) -> 1.5501551e-05
B31: Actual GDP (nominal, national currency)
B32: Growth rate | C32: =100*((1+C23/100)*(1+C41/100)-1) -> 6.1837136 | D32: =100*((1+D23/100)*(1+D41/100)-1) -> 4.5016947 | E32: =100*((1+E23/100)*(1+E41/100)-1) -> 5.2866779 | F32: =100*((1+F23/100)*(1+F41/100)-1) -> 4.3917217 | G32: =100*((1+G23/100)*(1+G41/100)-1) -> 4.0424669 | H32: =100*((1+H23/100)*(1+H41/100)-1) -> 3.9848361 | I32: =100*((1+I23/100)*(1+I41/100)-1) -> 3.9635744 | J32: =100*((1+J23/100)*(1+J41/100)-1) -> 3.8818238 | ... U32: =100*((1+U23/100)*(1+U41/100)-1) -> 3.8494844
B34: Interest rate
B35: Nominal implicit interest rate on debt | C35: ='Input data'!C37 -> 3.196961 | D35: ='Input data'!D37 -> 3.078103 | E35: =IF(E$10<='Input data'!$C$4+2,'Input data'!E37,E96) -> 2.999835 | F35: =IF(F$10<='Input data'!$C$4+2,'Input data'!F37,F96) -> 3.2787529 | G35: =IF(G$10<='Input data'!$C$4+2,'Input data'!G37,G96) -> 3.515114 | H35: =IF(H$10<='Input data'!$C$4+2,'Input data'!H37,H96) -> 3.7446797 | I35: =IF(I$10<='Input data'!$C$4+2,'Input data'!I37,I96) -> 3.9632939 | J35: =IF(J$10<='Input data'!$C$4+2,'Input data'!J37,J96) -> 4.173594 | K35: =IF(K$10<='Input data'!$C$4+2,'Input data'!K37,K96) -> 4.3733956 | L35: =IF(L$10<='Input data'!$C$4+2,'Input data'!L37,L96) -> 4.5637138 | ... U35: =IF(U$10<='Input data'!$C$4+2,'Input data'!U37,U96) -> 5.1509376
B36: Long-term interest rate | C36: ='Input data'!C39 -> 4.29 | D36: ='Input data'!D39 -> 4.701964 | E36: =_xlfn.LET(_xlpm.lastForecast,INDEX('Input data'!$E$39:$G$39,MATCH('Input data'!$C$4+2,'Input data'!$E$9:$G$9)), _xlpm.Tplus10,'Input data'!$C$52, _xlpm.Tplus30,'Input data'!$C$54, IF(E$10<='Input data'!$C$4+2,'Input data'!E$39, IF(E$10<'Input data'!$C$4+10,_xlpm.lastForecast+(_xlpm.Tplus10-_xlpm.lastForecast)/8*(E$10-('Input data'!$C$4+2)), IF(E$10='Input data'!$C$4+10,_xlpm.Tplus10, _xlpm.Tplus10+(_xlpm.Tplus30-_xlpm.Tplus10)/20*(E$10-('Input data'!$C$4+10)))))) -> 4.915649 | F36: =_xlfn.LET(_xlpm.lastForecast,INDEX('Input data'!$E$39:$G$39,MATCH('Input data'!$C$4+2,'Input data'!$E$9:$G$9)), _xlpm.Tplus10,'Input data'!$C$52, _xlpm.Tplus30,'Input data'!$C$54, IF(F$10<='Input data'!$C$4+2,'Input data'!F$39, IF(F$10<'Input data'!$C$4+10,_xlpm.lastForecast+(_xlpm.Tplus10-_xlpm.lastForecast)/8*(F$10-('Input data'!$C$4+2)), IF(F$10='Input data'!$C$4+10,_xlpm.Tplus10, _xlpm.Tplus10+(_xlpm.Tplus30-_xlpm.Tplus10)/20*(F$10-('Input data'!$C$4+10)))))) -> 5.0370066 | G36: =_xlfn.LET(_xlpm.lastForecast,INDEX('Input data'!$E$39:$G$39,MATCH('Input data'!$C$4+2,'Input data'!$E$9:$G$9)), _xlpm.Tplus10,'Input data'!$C$52, _xlpm.Tplus30,'Input data'!$C$54, IF(G$10<='Input data'!$C$4+2,'Input data'!G$39, IF(G$10<'Input data'!$C$4+10,_xlpm.lastForecast+(_xlpm.Tplus10-_xlpm.lastForecast)/8*(G$10-('Input data'!$C$4+2)), IF(G$10='Input data'!$C$4+10,_xlpm.Tplus10, _xlpm.Tplus10+(_xlpm.Tplus30-_xlpm.Tplus10)/20*(G$10-('Input data'!$C$4+10)))))) -> 5.1583642 | H36: =_xlfn.LET(_xlpm.lastForecast,INDEX('Input data'!$E$39:$G$39,MATCH('Input data'!$C$4+2,'Input data'!$E$9:$G$9)), _xlpm.Tplus10,'Input data'!$C$52, _xlpm.Tplus30,'Input data'!$C$54, IF(H$10<='Input data'!$C$4+2,'Input data'!H$39, IF(H$10<'Input data'!$C$4+10,_xlpm.lastForecast+(_xlpm.Tplus10-_xlpm.lastForecast)/8*(H$10-('Input data'!$C$4+2)), IF(H$10='Input data'!$C$4+10,_xlpm.Tplus10, _xlpm.Tplus10+(_xlpm.Tplus30-_xlpm.Tplus10)/20*(H$10-('Input data'!$C$4+10)))))) -> 5.2797219 | I36: =_xlfn.LET(_xlpm.lastForecast,INDEX('Input data'!$E$39:$G$39,MATCH('Input data'!$C$4+2,'Input data'!$E$9:$G$9)), _xlpm.Tplus10,'Input data'!$C$52, _xlpm.Tplus30,'Input data'!$C$54, IF(I$10<='Input data'!$C$4+2,'Input data'!I$39, IF(I$10<'Input data'!$C$4+10,_xlpm.lastForecast+(_xlpm.Tplus10-_xlpm.lastForecast)/8*(I$10-('Input data'!$C$4+2)), IF(I$10='Input data'!$C$4+10,_xlpm.Tplus10, _xlpm.Tplus10+(_xlpm.Tplus30-_xlpm.Tplus10)/20*(I$10-('Input data'!$C$4+10)))))) -> 5.4010795 | J36: =_xlfn.LET(_xlpm.lastForecast,INDEX('Input data'!$E$39:$G$39,MATCH('Input data'!$C$4+2,'Input data'!$E$9:$G$9)), _xlpm.Tplus10,'Input data'!$C$52, _xlpm.Tplus30,'Input data'!$C$54, IF(J$10<='Input data'!$C$4+2,'Input data'!J$39, IF(J$10<'Input data'!$C$4+10,_xlpm.lastForecast+(_xlpm.Tplus10-_xlpm.lastForecast)/8*(J$10-('Input data'!$C$4+2)), IF(J$10='Input data'!$C$4+10,_xlpm.Tplus10, _xlpm.Tplus10+(_xlpm.Tplus30-_xlpm.Tplus10)/20*(J$10-('Input data'!$C$4+10)))))) -> 5.5224371 | K36: =_xlfn.LET(_xlpm.lastForecast,INDEX('Input data'!$E$39:$G$39,MATCH('Input data'!$C$4+2,'Input data'!$E$9:$G$9)), _xlpm.Tplus10,'Input data'!$C$52, _xlpm.Tplus30,'Input data'!$C$54, IF(K$10<='Input data'!$C$4+2,'Input data'!K$39, IF(K$10<'Input data'!$C$4+10,_xlpm.lastForecast+(_xlpm.Tplus10-_xlpm.lastForecast)/8*(K$10-('Input data'!$C$4+2)), IF(K$10='Input data'!$C$4+10,_xlpm.Tplus10, _xlpm.Tplus10+(_xlpm.Tplus30-_xlpm.Tplus10)/20*(K$10-('Input data'!$C$4+10)))))) -> 5.6437948 | L36: =_xlfn.LET(_xlpm.lastForecast,INDEX('Input data'!$E$39:$G$39,MATCH('Input data'!$C$4+2,'Input data'!$E$9:$G$9)), _xlpm.Tplus10,'Input data'!$C$52, _xlpm.Tplus30,'Input data'!$C$54, IF(L$10<='Input data'!$C$4+2,'Input data'!L$39, IF(L$10<'Input data'!$C$4+10,_xlpm.lastForecast+(_xlpm.Tplus10-_xlpm.lastForecast)/8*(L$10-('Input data'!$C$4+2)), IF(L$10='Input data'!$C$4+10,_xlpm.Tplus10, _xlpm.Tplus10+(_xlpm.Tplus30-_xlpm.Tplus10)/20*(L$10-('Input data'!$C$4+10)))))) -> 5.7651524 | ... U36: =_xlfn.LET(_xlpm.lastForecast,INDEX('Input data'!$E$39:$G$39,MATCH('Input data'!$C$4+2,'Input data'!$E$9:$G$9)), _xlpm.Tplus10,'Input data'!$C$52, _xlpm.Tplus30,'Input data'!$C$54, IF(U$10<='Input data'!$C$4+2,'Input data'!U$39, IF(U$10<'Input data'!$C$4+10,_xlpm.lastForecast+(_xlpm.Tplus10-_xlpm.lastForecast)/8*(U$10-('Input data'!$C$4+2)), IF(U$10='Input data'!$C$4+10,_xlpm.Tplus10, _xlpm.Tplus10+(_xlpm.Tplus30-_xlpm.Tplus10)/20*(U$10-('Input data'!$C$4+10)))))) -> 5.131906
B37: Short-term interest rate | C37: ='Input data'!C$38 -> 3.6 | D37: ='Input data'!D$38 -> 3.649853 | E37: =_xlfn.LET(_xlpm.lastForecast,INDEX('Input data'!$E$38:$G$38,MATCH('Input data'!$C$4+2,'Input data'!$E$9:$G$9)), _xlpm.Tplus10,'Input data'!$C$53, _xlpm.Tplus30,'Input data'!$C$55, IF(E$10<='Input data'!$C$4+2,'Input data'!E$38, IF(E$10<'Input data'!$C$4+10,_xlpm.lastForecast+(_xlpm.Tplus10-_xlpm.lastForecast)/8*(E$10-('Input data'!$C$4+2)), IF(E$10='Input data'!$C$4+10,_xlpm.Tplus10, _xlpm.Tplus10+(_xlpm.Tplus30-_xlpm.Tplus10)/20*(E$10-('Input data'!$C$4+10)))))) -> 4.267191 | F37: =_xlfn.LET(_xlpm.lastForecast,INDEX('Input data'!$E$38:$G$38,MATCH('Input data'!$C$4+2,'Input data'!$E$9:$G$9)), _xlpm.Tplus10,'Input data'!$C$53, _xlpm.Tplus30,'Input data'!$C$55, IF(F$10<='Input data'!$C$4+2,'Input data'!F$38, IF(F$10<'Input data'!$C$4+10,_xlpm.lastForecast+(_xlpm.Tplus10-_xlpm.lastForecast)/8*(F$10-('Input data'!$C$4+2)), IF(F$10='Input data'!$C$4+10,_xlpm.Tplus10, _xlpm.Tplus10+(_xlpm.Tplus30-_xlpm.Tplus10)/20*(F$10-('Input data'!$C$4+10)))))) -> 4.2826609 | G37: =_xlfn.LET(_xlpm.lastForecast,INDEX('Input data'!$E$38:$G$38,MATCH('Input data'!$C$4+2,'Input data'!$E$9:$G$9)), _xlpm.Tplus10,'Input data'!$C$53, _xlpm.Tplus30,'Input data'!$C$55, IF(G$10<='Input data'!$C$4+2,'Input data'!G$38, IF(G$10<'Input data'!$C$4+10,_xlpm.lastForecast+(_xlpm.Tplus10-_xlpm.lastForecast)/8*(G$10-('Input data'!$C$4+2)), IF(G$10='Input data'!$C$4+10,_xlpm.Tplus10, _xlpm.Tplus10+(_xlpm.Tplus30-_xlpm.Tplus10)/20*(G$10-('Input data'!$C$4+10)))))) -> 4.2981308 | H37: =_xlfn.LET(_xlpm.lastForecast,INDEX('Input data'!$E$38:$G$38,MATCH('Input data'!$C$4+2,'Input data'!$E$9:$G$9)), _xlpm.Tplus10,'Input data'!$C$53, _xlpm.Tplus30,'Input data'!$C$55, IF(H$10<='Input data'!$C$4+2,'Input data'!H$38, IF(H$10<'Input data'!$C$4+10,_xlpm.lastForecast+(_xlpm.Tplus10-_xlpm.lastForecast)/8*(H$10-('Input data'!$C$4+2)), IF(H$10='Input data'!$C$4+10,_xlpm.Tplus10, _xlpm.Tplus10+(_xlpm.Tplus30-_xlpm.Tplus10)/20*(H$10-('Input data'!$C$4+10)))))) -> 4.3136006 | I37: =_xlfn.LET(_xlpm.lastForecast,INDEX('Input data'!$E$38:$G$38,MATCH('Input data'!$C$4+2,'Input data'!$E$9:$G$9)), _xlpm.Tplus10,'Input data'!$C$53, _xlpm.Tplus30,'Input data'!$C$55, IF(I$10<='Input data'!$C$4+2,'Input data'!I$38, IF(I$10<'Input data'!$C$4+10,_xlpm.lastForecast+(_xlpm.Tplus10-_xlpm.lastForecast)/8*(I$10-('Input data'!$C$4+2)), IF(I$10='Input data'!$C$4+10,_xlpm.Tplus10, _xlpm.Tplus10+(_xlpm.Tplus30-_xlpm.Tplus10)/20*(I$10-('Input data'!$C$4+10)))))) -> 4.3290705 | J37: =_xlfn.LET(_xlpm.lastForecast,INDEX('Input data'!$E$38:$G$38,MATCH('Input data'!$C$4+2,'Input data'!$E$9:$G$9)), _xlpm.Tplus10,'Input data'!$C$53, _xlpm.Tplus30,'Input data'!$C$55, IF(J$10<='Input data'!$C$4+2,'Input data'!J$38, IF(J$10<'Input data'!$C$4+10,_xlpm.lastForecast+(_xlpm.Tplus10-_xlpm.lastForecast)/8*(J$10-('Input data'!$C$4+2)), IF(J$10='Input data'!$C$4+10,_xlpm.Tplus10, _xlpm.Tplus10+(_xlpm.Tplus30-_xlpm.Tplus10)/20*(J$10-('Input data'!$C$4+10)))))) -> 4.3445404 | K37: =_xlfn.LET(_xlpm.lastForecast,INDEX('Input data'!$E$38:$G$38,MATCH('Input data'!$C$4+2,'Input data'!$E$9:$G$9)), _xlpm.Tplus10,'Input data'!$C$53, _xlpm.Tplus30,'Input data'!$C$55, IF(K$10<='Input data'!$C$4+2,'Input data'!K$38, IF(K$10<'Input data'!$C$4+10,_xlpm.lastForecast+(_xlpm.Tplus10-_xlpm.lastForecast)/8*(K$10-('Input data'!$C$4+2)), IF(K$10='Input data'!$C$4+10,_xlpm.Tplus10, _xlpm.Tplus10+(_xlpm.Tplus30-_xlpm.Tplus10)/20*(K$10-('Input data'!$C$4+10)))))) -> 4.3600103 | L37: =_xlfn.LET(_xlpm.lastForecast,INDEX('Input data'!$E$38:$G$38,MATCH('Input data'!$C$4+2,'Input data'!$E$9:$G$9)), _xlpm.Tplus10,'Input data'!$C$53, _xlpm.Tplus30,'Input data'!$C$55, IF(L$10<='Input data'!$C$4+2,'Input data'!L$38, IF(L$10<'Input data'!$C$4+10,_xlpm.lastForecast+(_xlpm.Tplus10-_xlpm.lastForecast)/8*(L$10-('Input data'!$C$4+2)), IF(L$10='Input data'!$C$4+10,_xlpm.Tplus10, _xlpm.Tplus10+(_xlpm.Tplus30-_xlpm.Tplus10)/20*(L$10-('Input data'!$C$4+10)))))) -> 4.3754801 | ... U37: =_xlfn.LET(_xlpm.lastForecast,INDEX('Input data'!$E$38:$G$38,MATCH('Input data'!$C$4+2,'Input data'!$E$9:$G$9)), _xlpm.Tplus10,'Input data'!$C$53, _xlpm.Tplus30,'Input data'!$C$55, IF(U$10<='Input data'!$C$4+2,'Input data'!U$38, IF(U$10<'Input data'!$C$4+10,_xlpm.lastForecast+(_xlpm.Tplus10-_xlpm.lastForecast)/8*(U$10-('Input data'!$C$4+2)), IF(U$10='Input data'!$C$4+10,_xlpm.Tplus10, _xlpm.Tplus10+(_xlpm.Tplus30-_xlpm.Tplus10)/20*(U$10-('Input data'!$C$4+10)))))) -> 3.43457
B38: Share of long-term debt that matures every year | C38: 0.06796828 | D38: 0.06823518 | E38: 0.06905882 | F38: =IF(F$10>='Input data'!$C$4+10,'Input data'!$C$59, IF(OR($C$3="EL",$C$3="CY",$C$3="IE",$C$3="PT"),VLOOKUP($C$3,$B$110:$R$114,MATCH(F$10,$B$110:$R$110,0),0),$E$38+('Input data'!$C$59-$E$38)/('Input data'!$C$4+10-$E$10)*(F$10-$E$10))) -> 0.069882459 | G38: =IF(G$10>='Input data'!$C$4+10,'Input data'!$C$59, IF(OR($C$3="EL",$C$3="CY",$C$3="IE",$C$3="PT"),VLOOKUP($C$3,$B$110:$R$114,MATCH(G$10,$B$110:$R$110,0),0),$E$38+('Input data'!$C$59-$E$38)/('Input data'!$C$4+10-$E$10)*(G$10-$E$10))) -> 0.070706098 | H38: =IF(H$10>='Input data'!$C$4+10,'Input data'!$C$59, IF(OR($C$3="EL",$C$3="CY",$C$3="IE",$C$3="PT"),VLOOKUP($C$3,$B$110:$R$114,MATCH(H$10,$B$110:$R$110,0),0),$E$38+('Input data'!$C$59-$E$38)/('Input data'!$C$4+10-$E$10)*(H$10-$E$10))) -> 0.071529736 | I38: =IF(I$10>='Input data'!$C$4+10,'Input data'!$C$59, IF(OR($C$3="EL",$C$3="CY",$C$3="IE",$C$3="PT"),VLOOKUP($C$3,$B$110:$R$114,MATCH(I$10,$B$110:$R$110,0),0),$E$38+('Input data'!$C$59-$E$38)/('Input data'!$C$4+10-$E$10)*(I$10-$E$10))) -> 0.072353375 | J38: =IF(J$10>='Input data'!$C$4+10,'Input data'!$C$59, IF(OR($C$3="EL",$C$3="CY",$C$3="IE",$C$3="PT"),VLOOKUP($C$3,$B$110:$R$114,MATCH(J$10,$B$110:$R$110,0),0),$E$38+('Input data'!$C$59-$E$38)/('Input data'!$C$4+10-$E$10)*(J$10-$E$10))) -> 0.073177014 | K38: =IF(K$10>='Input data'!$C$4+10,'Input data'!$C$59, IF(OR($C$3="EL",$C$3="CY",$C$3="IE",$C$3="PT"),VLOOKUP($C$3,$B$110:$R$114,MATCH(K$10,$B$110:$R$110,0),0),$E$38+('Input data'!$C$59-$E$38)/('Input data'!$C$4+10-$E$10)*(K$10-$E$10))) -> 0.074000652 | L38: =IF(L$10>='Input data'!$C$4+10,'Input data'!$C$59, IF(OR($C$3="EL",$C$3="CY",$C$3="IE",$C$3="PT"),VLOOKUP($C$3,$B$110:$R$114,MATCH(L$10,$B$110:$R$110,0),0),$E$38+('Input data'!$C$59-$E$38)/('Input data'!$C$4+10-$E$10)*(L$10-$E$10))) -> 0.074824291 | M38: =IF(M$10>='Input data'!$C$4+10,'Input data'!$C$59, IF(OR($C$3="EL",$C$3="CY",$C$3="IE",$C$3="PT"),VLOOKUP($C$3,$B$110:$R$114,MATCH(M$10,$B$110:$R$110,0),0),$E$38+('Input data'!$C$59-$E$38)/('Input data'!$C$4+10-$E$10)*(M$10-$E$10))) -> 0.07564793 | ... U38: =IF(U$10>='Input data'!$C$4+10,'Input data'!$C$59, IF(OR($C$3="EL",$C$3="CY",$C$3="IE",$C$3="PT"),VLOOKUP($C$3,$B$110:$R$114,MATCH(U$10,$B$110:$R$110,0),0),$E$38+('Input data'!$C$59-$E$38)/('Input data'!$C$4+10-$E$10)*(U$10-$E$10))) -> 0.07564793
B40: Inflation and exchange rate
B41: GDP deflator (national currency) | C41: ='Input data'!C42 -> 3.512605 | D41: ='Input data'!D42 -> 2.656677 | E41: =_xlfn.LET(_xlpm.lastForecast,INDEX('Input data'!$E$42:$G$42,MATCH('Input data'!$C$4+2,'Input data'!$E$9:$G$9)), _xlpm.Tplus10,'Input data'!$C$61, _xlpm.Tplus30,'Input data'!$C$62, IF(E$10<='Input data'!$C$4+2,'Input data'!E$42, IF(E$10<'Input data'!$C$4+10,_xlpm.lastForecast+(_xlpm.Tplus10-_xlpm.lastForecast)/8*(E$10-('Input data'!$C$4+2)), IF(E$10='Input data'!$C$4+10,_xlpm.Tplus10, _xlpm.Tplus10+(_xlpm.Tplus30-_xlpm.Tplus10)/20*(E$10-('Input data'!$C$4+10)))))) -> 3.068664 | F41: =_xlfn.LET(_xlpm.lastForecast,INDEX('Input data'!$E$42:$G$42,MATCH('Input data'!$C$4+2,'Input data'!$E$9:$G$9)), _xlpm.Tplus10,'Input data'!$C$61, _xlpm.Tplus30,'Input data'!$C$62, IF(F$10<='Input data'!$C$4+2,'Input data'!F$42, IF(F$10<'Input data'!$C$4+10,_xlpm.lastForecast+(_xlpm.Tplus10-_xlpm.lastForecast)/8*(F$10-('Input data'!$C$4+2)), IF(F$10='Input data'!$C$4+10,_xlpm.Tplus10, _xlpm.Tplus10+(_xlpm.Tplus30-_xlpm.Tplus10)/20*(F$10-('Input data'!$C$4+10)))))) -> 2.977581 | G41: =_xlfn.LET(_xlpm.lastForecast,INDEX('Input data'!$E$42:$G$42,MATCH('Input data'!$C$4+2,'Input data'!$E$9:$G$9)), _xlpm.Tplus10,'Input data'!$C$61, _xlpm.Tplus30,'Input data'!$C$62, IF(G$10<='Input data'!$C$4+2,'Input data'!G$42, IF(G$10<'Input data'!$C$4+10,_xlpm.lastForecast+(_xlpm.Tplus10-_xlpm.lastForecast)/8*(G$10-('Input data'!$C$4+2)), IF(G$10='Input data'!$C$4+10,_xlpm.Tplus10, _xlpm.Tplus10+(_xlpm.Tplus30-_xlpm.Tplus10)/20*(G$10-('Input data'!$C$4+10)))))) -> 2.886498 | H41: =_xlfn.LET(_xlpm.lastForecast,INDEX('Input data'!$E$42:$G$42,MATCH('Input data'!$C$4+2,'Input data'!$E$9:$G$9)), _xlpm.Tplus10,'Input data'!$C$61, _xlpm.Tplus30,'Input data'!$C$62, IF(H$10<='Input data'!$C$4+2,'Input data'!H$42, IF(H$10<'Input data'!$C$4+10,_xlpm.lastForecast+(_xlpm.Tplus10-_xlpm.lastForecast)/8*(H$10-('Input data'!$C$4+2)), IF(H$10='Input data'!$C$4+10,_xlpm.Tplus10, _xlpm.Tplus10+(_xlpm.Tplus30-_xlpm.Tplus10)/20*(H$10-('Input data'!$C$4+10)))))) -> 2.795415 | I41: =_xlfn.LET(_xlpm.lastForecast,INDEX('Input data'!$E$42:$G$42,MATCH('Input data'!$C$4+2,'Input data'!$E$9:$G$9)), _xlpm.Tplus10,'Input data'!$C$61, _xlpm.Tplus30,'Input data'!$C$62, IF(I$10<='Input data'!$C$4+2,'Input data'!I$42, IF(I$10<'Input data'!$C$4+10,_xlpm.lastForecast+(_xlpm.Tplus10-_xlpm.lastForecast)/8*(I$10-('Input data'!$C$4+2)), IF(I$10='Input data'!$C$4+10,_xlpm.Tplus10, _xlpm.Tplus10+(_xlpm.Tplus30-_xlpm.Tplus10)/20*(I$10-('Input data'!$C$4+10)))))) -> 2.704332 | J41: =_xlfn.LET(_xlpm.lastForecast,INDEX('Input data'!$E$42:$G$42,MATCH('Input data'!$C$4+2,'Input data'!$E$9:$G$9)), _xlpm.Tplus10,'Input data'!$C$61, _xlpm.Tplus30,'Input data'!$C$62, IF(J$10<='Input data'!$C$4+2,'Input data'!J$42, IF(J$10<'Input data'!$C$4+10,_xlpm.lastForecast+(_xlpm.Tplus10-_xlpm.lastForecast)/8*(J$10-('Input data'!$C$4+2)), IF(J$10='Input data'!$C$4+10,_xlpm.Tplus10, _xlpm.Tplus10+(_xlpm.Tplus30-_xlpm.Tplus10)/20*(J$10-('Input data'!$C$4+10)))))) -> 2.613249 | K41: =_xlfn.LET(_xlpm.lastForecast,INDEX('Input data'!$E$42:$G$42,MATCH('Input data'!$C$4+2,'Input data'!$E$9:$G$9)), _xlpm.Tplus10,'Input data'!$C$61, _xlpm.Tplus30,'Input data'!$C$62, IF(K$10<='Input data'!$C$4+2,'Input data'!K$42, IF(K$10<'Input data'!$C$4+10,_xlpm.lastForecast+(_xlpm.Tplus10-_xlpm.lastForecast)/8*(K$10-('Input data'!$C$4+2)), IF(K$10='Input data'!$C$4+10,_xlpm.Tplus10, _xlpm.Tplus10+(_xlpm.Tplus30-_xlpm.Tplus10)/20*(K$10-('Input data'!$C$4+10)))))) -> 2.522166 | L41: =_xlfn.LET(_xlpm.lastForecast,INDEX('Input data'!$E$42:$G$42,MATCH('Input data'!$C$4+2,'Input data'!$E$9:$G$9)), _xlpm.Tplus10,'Input data'!$C$61, _xlpm.Tplus30,'Input data'!$C$62, IF(L$10<='Input data'!$C$4+2,'Input data'!L$42, IF(L$10<'Input data'!$C$4+10,_xlpm.lastForecast+(_xlpm.Tplus10-_xlpm.lastForecast)/8*(L$10-('Input data'!$C$4+2)), IF(L$10='Input data'!$C$4+10,_xlpm.Tplus10, _xlpm.Tplus10+(_xlpm.Tplus30-_xlpm.Tplus10)/20*(L$10-('Input data'!$C$4+10)))))) -> 2.431083 | ... U41: =_xlfn.LET(_xlpm.lastForecast,INDEX('Input data'!$E$42:$G$42,MATCH('Input data'!$C$4+2,'Input data'!$E$9:$G$9)), _xlpm.Tplus10,'Input data'!$C$61, _xlpm.Tplus30,'Input data'!$C$62, IF(U$10<='Input data'!$C$4+2,'Input data'!U$42, IF(U$10<'Input data'!$C$4+10,_xlpm.lastForecast+(_xlpm.Tplus10-_xlpm.lastForecast)/8*(U$10-('Input data'!$C$4+2)), IF(U$10='Input data'!$C$4+10,_xlpm.Tplus10, _xlpm.Tplus10+(_xlpm.Tplus30-_xlpm.Tplus10)/20*(U$10-('Input data'!$C$4+10)))))) -> 2.204
B42: Exchange rate composite change (weighted by share of debt in each currency) | C42: 0.9986759 | D42: 0.9989123 | E42: 0.9999991 | F42: 1 | G42: 1 | H42: 1 | I42: 1 | J42: 1 | K42: 1 | L42: 1 | M42: 1 | N42: 1 | O42: 1 | P42: 1 | Q42: 1 | R42: 1 | S42: 1 | T42: 1 | U42: 1
B44: Intermediate calculations (growth rate equation)
B46: Fiscal multiplier | C46: ='Input data'!C49 -> 0.6
B47: Budget balance semi-elasticity | C47: ='Input data'!C50 -> 0.395
B49: Auxiliary variable to control the closure of the output gap | C49: 0 | D49: =IF(AND(ABS((D12-C12)-('Input data'!D13-'Input data'!C13))>0.0001,ABS(D12-C12)>0.0001,D$10>$C$5),4,IF(C49=4,3,IF(C49=3,2,IF(C49=2,1,0)))) -> 0 | E49: =IF(AND(ABS(E12-D12)>0.0001,E$10>$C$5),4,IF(D49=4,3,IF(D49=3,2,IF(D49=2,1,0)))) -> 0 | F49: =IF(AND(ABS(F12-E12)>0.0001,F$10>$C$5),4,IF(E49=4,3,IF(E49=3,2,IF(E49=2,1,0)))) -> 0 | G49: =IF(AND(ABS(G12-F12)>0.0001,G$10>$C$5),4,IF(F49=4,3,IF(F49=3,2,IF(F49=2,1,0)))) -> 0 | H49: =IF(AND(ABS(H12-G12)>0.0001,H$10>$C$5),4,IF(G49=4,3,IF(G49=3,2,IF(G49=2,1,0)))) -> 0 | I49: =IF(AND(ABS(I12-H12)>0.0001,I$10>$C$5),4,IF(H49=4,3,IF(H49=3,2,IF(H49=2,1,0)))) -> 0 | J49: =IF(AND(ABS(J12-I12)>0.0001,J$10>$C$5),4,IF(I49=4,3,IF(I49=3,2,IF(I49=2,1,0)))) -> 0 | K49: =IF(AND(ABS(K12-J12)>0.0001,K$10>$C$5),4,IF(J49=4,3,IF(J49=3,2,IF(J49=2,1,0)))) -> 0 | L49: =IF(AND(ABS(L12-K12)>0.0001,L$10>$C$5),4,IF(K49=4,3,IF(K49=3,2,IF(K49=2,1,0)))) -> 0 | ... U49: =IF(AND(ABS(U12-T12)>0.0001,U$10>$C$5),4,IF(T49=4,3,IF(T49=3,2,IF(T49=2,1,0)))) -> 0
B50: OG intermediate auxiliary value | C50: 0 | D50: =IF(C49=4,2/3*C29,IF(C49=3,1/3*#REF!,0)) -> 0 | E50: =IF(D49=4,2/3*D29,IF(D49=3,1/3*C29,0)) -> 0 | F50: =IF(E49=4,2/3*E29,IF(E49=3,1/3*D29,0)) -> 0 | G50: =IF(F49=4,2/3*F29,IF(F49=3,1/3*E29,0)) -> 0 | H50: =IF(G49=4,2/3*G29,IF(G49=3,1/3*F29,0)) -> 0 | I50: =IF(H49=4,2/3*H29,IF(H49=3,1/3*G29,0)) -> 0 | J50: =IF(I49=4,2/3*I29,IF(I49=3,1/3*H29,0)) -> 0 | K50: =IF(J49=4,2/3*J29,IF(J49=3,1/3*I29,0)) -> 0 | L50: =IF(K49=4,2/3*K29,IF(K49=3,1/3*J29,0)) -> 0 | ... U50: =IF(T49=4,2/3*T29,IF(T49=3,1/3*S29,0)) -> 0
B51: GDP intermediate growth rate - only feedback effect and no closure of the OG | C51: 0 | D51: ='Input data'!D30-$C$46*((D12-C12)-('Input data'!D13-'Input data'!C13)) -> 1.79727 | E51: ='Input data'!E30-$C$46*((E12-D12)-('Input data'!E13-'Input data'!D13)) -> 2.9516324 | F51: ='Input data'!F30-$C$46*((F12-E12)) -> 1.373251 | G51: ='Input data'!G30-$C$46*((G12-F12)) -> 1.123538 | H51: ='Input data'!H30-$C$46*((H12-G12)) -> 1.157076 | I51: ='Input data'!I30-$C$46*((I12-H12)) -> 1.226085 | J51: ='Input data'!J30-$C$46*((J12-I12)) -> 1.236268 | K51: ='Input data'!K30-$C$46*((K12-J12)) -> 1.244196 | L51: ='Input data'!L30-$C$46*((L12-K12)) -> 1.209247 | M51: ='Input data'!M30-$C$46*((M12-L12)) -> 1.140828 | ... U51: ='Input data'!U30-$C$46*((U12-T12)) -> 1.61
B53: Debt projections
C55: ='Input data'!$C$5-1 -> 2025 | D55: =C55+1 -> 2026 | E55: =D55+1 -> 2027 | F55: =E55+1 -> 2028 | G55: =F55+1 -> 2029 | H55: =G55+1 -> 2030 | I55: =H55+1 -> 2031 | J55: =I55+1 -> 2032 | K55: =J55+1 -> 2033 | ... U55: =T55+1 -> 2043
B56: Gross debt | C56: =+'Input data'!C12 -> 44.25023 | D56: =+C56+D57 -> 45.838496 | E56: =+D56+E57 -> 47.042627 | F56: =+E56+F57 -> 48.037875 | G56: =+F56+G57 -> 49.449014 | H56: =+G56+H57 -> 51.025602 | I56: =+H56+I57 -> 52.830767 | J56: =+I56+J57 -> 54.798962 | K56: =+J56+K57 -> 56.937192 | ... U56: =+T56+U57 -> 91.692976
B57: Change in debt (-1+2+3) | D57: =-D58+D66+D71 -> 1.5882664 | E57: =-E58+E66+E71 -> 1.2041305 | F57: =-F58+F66+F71 -> 0.9952478 | G57: =-G58+G66+G71 -> 1.4111389 | H57: =-H58+H66+H71 -> 1.5765889 | I57: =-I58+I66+I71 -> 1.8051648 | J57: =-J58+J66+J71 -> 1.9681944 | K57: =-K58+K66+K71 -> 2.13823 | ... U57: =-U58+U66+U71 -> 4.2749271
B58: (1) Primary balance (1.1 + 1.2 - 1.3 -1.4 -1.5 - 1.6 -1.7) | D58: =D59+D60-D61-D62-D63-D64-D65 -> -1.4910706 | E58: =E59+E60-E61-E62-E63-E64-E65 -> -1.3497911 | F58: =F59+F60-F61-F62-F63-F64-F65 -> -1.496791 | G58: =G59+G60-G61-G62-G63-G64-G65 -> -1.6546255 | H58: =H59+H60-H61-H62-H63-H64-H65 -> -1.690793 | I58: =I59+I60-I61-I62-I63-I64-I65 -> -1.8053025 | J58: =J59+J60-J61-J62-J63-J64-J65 -> -1.81981 | K58: =K59+K60-K61-K62-K63-K64-K65 -> -1.8343199 | ... U58: =U59+U60-U61-U62-U63-U64-U65 -> -3.1793944
B59: (1.1) Structural primary balance (before ageing cost) | D59: =D12 -> -1.332759 | E59: =IF(E12="",D59,E12) -> -1.332759 | F59: =IF(F12="",E59,F12) -> -1.332759 | G59: =IF(G12="",F59,G12) -> -1.332759 | H59: =IF(H12="",G59,H12) -> -1.332759 | I59: =IF(I12="",H59,I12) -> -1.332759 | J59: =IF(J12="",I59,J12) -> -1.332759 | K59: =IF(K12="",J59,K12) -> -1.332759 | L59: =IF(L12="",K59,L12) -> -1.332759 | ... U59: =IF(U12="",T59,U12) -> -1.332759
B60: (1.2) Cumulated budgetary effort (in terms of primary balance) | D60: 0 | E60: 0 | F60: 0 | G60: 0 | H60: 0 | I60: 0 | J60: 0 | K60: 0 | L60: 0 | M60: 0 | N60: 0 | O60: 0 | P60: 0 | Q60: 0 | R60: 0 | S60: 0 | T60: 0 | U60: 0
B61: (1.3) Cyclical component | D61: =-$C$47*D29 -> 0.15831162 | E61: =-$C$47*E29 -> -0.097476927 | F61: =-$C$47*F29 -> -0.064984879 | G61: =-$C$47*G29 -> -0.021658744 | H61: =-$C$47*H29 -> 5.0159843e-07 | I61: =-$C$47*I29 -> 1.6722452e-06 | J61: =-$C$47*J29 -> 8.9189251e-07 | K61: =-$C$47*K29 -> 2.4524757e-06 | ... U61: =-$C$47*U29 -> -6.1231125e-06
B62: (1.4) One-off and other temporary measures | D62: =-D13 -> 0 | E62: =-E13 -> 0 | F62: =-F13 -> 0 | G62: =-G13 -> 0 | H62: =-H13 -> 0 | I62: =-I13 -> 0 | J62: =-J13 -> 0 | K62: =-K13 -> 0 | ... U62: =-U13 -> 0
B63: (1.5) Cost of ageing | D63: =IF(D$55<=$C$5,0,HLOOKUP(D$55,'Input data'!$C$9:$AZ$26,12,FALSE)-HLOOKUP($C$5,'Input data'!$C$9:$AZ$26,12,FALSE)) -> 0 | E63: =IF(E$55<=$C$5,0,HLOOKUP(E$55,'Input data'!$C$9:$AZ$26,12,FALSE)-HLOOKUP($C$5,'Input data'!$C$9:$AZ$26,12,FALSE)) -> 0.1 | F63: =IF(F$55<=$C$5,0,HLOOKUP(F$55,'Input data'!$C$9:$AZ$26,12,FALSE)-HLOOKUP($C$5,'Input data'!$C$9:$AZ$26,12,FALSE)) -> 0.2 | G63: =IF(G$55<=$C$5,0,HLOOKUP(G$55,'Input data'!$C$9:$AZ$26,12,FALSE)-HLOOKUP($C$5,'Input data'!$C$9:$AZ$26,12,FALSE)) -> 0.3 | H63: =IF(H$55<=$C$5,0,HLOOKUP(H$55,'Input data'!$C$9:$AZ$26,12,FALSE)-HLOOKUP($C$5,'Input data'!$C$9:$AZ$26,12,FALSE)) -> 0.3 | I63: =IF(I$55<=$C$5,0,HLOOKUP(I$55,'Input data'!$C$9:$AZ$26,12,FALSE)-HLOOKUP($C$5,'Input data'!$C$9:$AZ$26,12,FALSE)) -> 0.4 | J63: =IF(J$55<=$C$5,0,HLOOKUP(J$55,'Input data'!$C$9:$AZ$26,12,FALSE)-HLOOKUP($C$5,'Input data'!$C$9:$AZ$26,12,FALSE)) -> 0.4 | K63: =IF(K$55<=$C$5,0,HLOOKUP(K$55,'Input data'!$C$9:$AZ$26,12,FALSE)-HLOOKUP($C$5,'Input data'!$C$9:$AZ$26,12,FALSE)) -> 0.4 | ... U63: =IF(U$55<=$C$5,0,HLOOKUP(U$55,'Input data'!$C$9:$AZ$26,12,FALSE)-HLOOKUP($C$5,'Input data'!$C$9:$AZ$26,12,FALSE)) -> 1.6
B64: (1.6) Property incomes | D64: =IF(D$55<=$C$5,0,-HLOOKUP(D$55,'Input data'!$C$9:$AZ$26,18,FALSE)+HLOOKUP($C$5,'Input data'!$C$9:$AZ$26,18,FALSE)) -> 0 | E64: =IF(E$55<=$C$5,0,-HLOOKUP(E$55,'Input data'!$C$9:$AZ$26,18,FALSE)+HLOOKUP($C$5,'Input data'!$C$9:$AZ$26,18,FALSE)) -> 0.014509 | F64: =IF(F$55<=$C$5,0,-HLOOKUP(F$55,'Input data'!$C$9:$AZ$26,18,FALSE)+HLOOKUP($C$5,'Input data'!$C$9:$AZ$26,18,FALSE)) -> 0.0290169 | G64: =IF(G$55<=$C$5,0,-HLOOKUP(G$55,'Input data'!$C$9:$AZ$26,18,FALSE)+HLOOKUP($C$5,'Input data'!$C$9:$AZ$26,18,FALSE)) -> 0.0435252 | H64: =IF(H$55<=$C$5,0,-HLOOKUP(H$55,'Input data'!$C$9:$AZ$26,18,FALSE)+HLOOKUP($C$5,'Input data'!$C$9:$AZ$26,18,FALSE)) -> 0.0580335 | I64: =IF(I$55<=$C$5,0,-HLOOKUP(I$55,'Input data'!$C$9:$AZ$26,18,FALSE)+HLOOKUP($C$5,'Input data'!$C$9:$AZ$26,18,FALSE)) -> 0.0725418 | J64: =IF(J$55<=$C$5,0,-HLOOKUP(J$55,'Input data'!$C$9:$AZ$26,18,FALSE)+HLOOKUP($C$5,'Input data'!$C$9:$AZ$26,18,FALSE)) -> 0.0870501 | K64: =IF(K$55<=$C$5,0,-HLOOKUP(K$55,'Input data'!$C$9:$AZ$26,18,FALSE)+HLOOKUP($C$5,'Input data'!$C$9:$AZ$26,18,FALSE)) -> 0.1015584 | ... U64: =IF(U$55<=$C$5,0,-HLOOKUP(U$55,'Input data'!$C$9:$AZ$26,18,FALSE)+HLOOKUP($C$5,'Input data'!$C$9:$AZ$26,18,FALSE)) -> 0.2466415
B65: (1.7) Revenues | D65: 0 | E65: 0 | F65: 0 | G65: 0 | H65: 0 | I65: 0 | J65: 0 | K65: 0 | L65: 0 | M65: 0 | N65: 0 | O65: 0 | P65: 0 | Q65: 0 | R65: 0 | S65: 0 | T65: 0 | U65: 0
B66: (2) Snowball effect (2.1 + 2.2 + 2.3 + 2.4) | D66: =SUM(D67:D70) -> -0.6042236 | E66: =SUM(E67:E70) -> -0.9956205 | F66: =SUM(F67:F70) -> -0.50154322 | G66: =SUM(G67:G70) -> -0.24348654 | H66: =SUM(H67:H70) -> -0.11420413 | I66: =SUM(I67:I70) -> -0.00013765131 | J66: =SUM(J67:J70) -> 0.14838442 | K66: =SUM(K67:K70) -> 0.30391012 | ... U66: =SUM(U67:U70) -> 1.0955327
B67: (2.1) Interest expenditure | D67: =C56*D35/100*(1/(1+D32/100)) -> 1.3033929 | E67: =D56*E35/100*(1/(1+E32/100)) -> 1.3060335 | F67: =E56*F35/100*(1/(1+F32/100)) -> 1.4775228 | G67: =F56*G35/100*(1/(1+G32/100)) -> 1.6229777 | H67: =G56*H35/100*(1/(1+H32/100)) -> 1.7807473 | I67: =H56*I35/100*(1/(1+I32/100)) -> 1.9451953 | J67: =I56*J35/100*(1/(1+J32/100)) -> 2.1225481 | K67: =J56*K35/100*(1/(1+K32/100)) -> 2.3088897 | ... U67: =T56*U35/100*(1/(1+U32/100)) -> 4.335938
B68: (2.2) Growth effect | D68: =-C56*(D23/100)*(1/(1+D32/100)) -> -0.76103657 | E68: =-D56*(E23/100)*(1/(1+E32/100)) -> -0.93690286 | F68: =-E56*(F23/100)*(1/(1+F32/100)) -> -0.6188358 | G68: =-F56*(G23/100)*(1/(1+G32/100)) -> -0.51875334 | H68: =-G56*(H23/100)*(1/(1+H32/100)) -> -0.55023664 | I68: =-H56*(I23/100)*(1/(1+I32/100)) -> -0.60176582 | J68: =-I56*(J23/100)*(1/(1+J32/100)) -> -0.62872392 | K68: =-J56*(K23/100)*(1/(1+K32/100)) -> -0.65686061 | ... U68: =-T56*(U23/100)*(1/(1+U32/100)) -> -1.3552601
B69: (2.3) Inflation effect | D69: =-C56*D41/100*(1/(1+D41/100)) -> -1.1451624 | E69: =-D56*E41/100*(1/(1+E41/100)) -> -1.3647499 | F69: =-E56*F41/100*(1/(1+F41/100)) -> -1.3602304 | G69: =-F56*G41/100*(1/(1+G41/100)) -> -1.3477107 | H69: =-G56*H41/100*(1/(1+H41/100)) -> -1.3447148 | I69: =-H56*I41/100*(1/(1+I41/100)) -> -1.3435672 | J69: =-I56*J41/100*(1/(1+J41/100)) -> -1.3454398 | K69: =-J56*K41/100*(1/(1+K41/100)) -> -1.348119 | ... U69: =-T56*U41/100*(1/(1+U41/100)) -> -1.8851452
B70: (2.4) Exchange rate effect linked to the interest rate | D70: -0.0014175065 | E70: -1.2590616e-06 | F70: 1.4316675e-07 | G70: -2.5639873e-07 | H70: 0 | I70: 0 | J70: 0 | K70: 0 | L70: 0 | M70: 0 | N70: 0 | O70: 0 | P70: 0 | Q70: 0 | R70: 0 | S70: 0 | T70: 0 | U70: 0
B71: (3 ) Stock flow adjustments (3.1 + 3.2) | D71: ='Input data'!D16 -> 0.7014194 | E71: ='Input data'!E16 -> 0.8499599 | F71: ='Input data'!F16 -> 0 | G71: ='Input data'!G16 -> 0 | H71: ='Input data'!H16 -> 0 | I71: ='Input data'!I16 -> 0 | J71: ='Input data'!J16 -> 0 | K71: ='Input data'!K16 -> 0 | ... U71: ='Input data'!U16 -> 0
B72: (3.1) Base | D72: =D14 -> 0.7474777 | E72: =E14 -> 0.85 | F72: =F14 -> 0 | G72: =G14 -> 0 | H72: =H14 -> 0 | I72: =I14 -> 0 | J72: =J14 -> 0 | K72: =K14 -> 0 | ... U72: =U14 -> 0
B73: (3.2) Adjustment due to the exchange rate effect linked to debt value | D73: =+D71-D72 -> -0.0460583 | E73: =+E71-E72 -> -4.01e-05 | F73: =+F71-F72 -> 0 | G73: =+G71-G72 -> 0 | H73: =+H71-H72 -> 0 | I73: =+I71-I72 -> 0 | J73: =+J71-J72 -> 0 | K73: =+K71-K72 -> 0 | ... U73: =+U71-U72 -> 0
B75: Other budgetary variables
B76: Headline balance | C76: -2.147432 | D76: =D58-D67 -> -2.7944635 | E76: =E58-E67 -> -2.6558245 | F76: =F58-F67 -> -2.9743138 | G76: =G58-G67 -> -3.2776032 | H76: =H58-H67 -> -3.4715403 | I76: =I58-I67 -> -3.7504978 | J76: =J58-J67 -> -3.9423581 | K76: =K58-K67 -> -4.1432096 | ... U76: =U58-U67 -> -7.5153323
B77: Structural balance | C77: -1.81443 | D77: =D59-D67-D70-D63-D64-D65 -> -2.6347344 | E77: =E59-E67-E70-E63-E64-E65 -> -2.7533002 | F77: =F59-F67-F70-F63-F64-F65 -> -3.0392988 | G77: =G59-G67-G70-G63-G64-G65 -> -3.2992617 | H77: =H59-H67-H70-H63-H64-H65 -> -3.4715398 | I77: =I59-I67-I70-I63-I64-I65 -> -3.7504961 | J77: =J59-J67-J70-J63-J64-J65 -> -3.9423572 | K77: =K59-K67-K70-K63-K64-K65 -> -4.1432071 | ... U77: =U59-U67-U70-U63-U64-U65 -> -7.5153385
B78: Net expenditure growth | C78: ='Input data'!C45 -> 4.9156095 | D78: ='Input data'!D45 -> 6.3502551 | E78: ='Input data'!E33+E41-(E$12-D$12-(E$63-D63))/'Input data'!$C$64*100 -> 4.7994787 | F78: ='Input data'!F33+F41-(F$12-E$12-(F$63-E63))/'Input data'!$C$64*100 -> 4.6727937 | G78: ='Input data'!G33+G41-(G$12-F$12-(G$63-F63))/'Input data'!$C$64*100 -> 4.3596047 | H78: ='Input data'!H33+H41-(H$12-G$12-(H$63-G63))/'Input data'!$C$64*100 -> 4.007959 | I78: ='Input data'!I33+I41-(I$12-H$12-(I$63-H63))/'Input data'!$C$64*100 -> 4.1691307 | J78: ='Input data'!J33+J41-(J$12-I$12-(J$63-I63))/'Input data'!$C$64*100 -> 3.849515 | K78: ='Input data'!K33+K41-(K$12-J$12-(K$63-J63))/'Input data'!$C$64*100 -> 3.766366 | L78: ='Input data'!L33+L41-(L$12-K$12-(L$63-K63))/'Input data'!$C$64*100 -> 4.3564592 | ... U78: ='Input data'!U33+U41-(U$12-T$12-(U$63-T63))/'Input data'!$C$64*100 -> 4.0527107
B81: Debt decomposition and IIR
B83: Auxiliary variable identifying whether debt is increasing | D83: =IF(C$10<_xlfn.NUMBERVALUE(RIGHT('Input data'!$B$66,4)),"", IF((D87-C87*D42/((1+D23/100)*(1+D41/100)))>0,1,0)) -> 1 | E83: =IF((E87-D87*E42/((1+E23/100)*(1+E41/100)))>0,1,0) -> 1 | F83: =IF((F87-E87*F42/((1+F23/100)*(1+F41/100)))>0,1,0) -> 1 | G83: =IF((G87-F87*G42/((1+G23/100)*(1+G41/100)))>0,1,0) -> 1 | H83: =IF((H87-G87*H42/((1+H23/100)*(1+H41/100)))>0,1,0) -> 1 | I83: =IF((I87-H87*I42/((1+I23/100)*(1+I41/100)))>0,1,0) -> 1 | J83: =IF((J87-I87*J42/((1+J23/100)*(1+J41/100)))>0,1,0) -> 1 | K83: =IF((K87-J87*K42/((1+K23/100)*(1+K41/100)))>0,1,0) -> 1 | L83: =IF((L87-K87*L42/((1+L23/100)*(1+L41/100)))>0,1,0) -> 1 | ... U83: =IF((U87-T87*U42/((1+U23/100)*(1+U41/100)))>0,1,0) -> 1
B84: Auxiliary variable identifying whether some debt is rolled over even though debt is decreasing | D84: =IF(C$10<_xlfn.NUMBERVALUE(RIGHT('Input data'!$B$66,4)),"", IF(AND(D83=0,ABS(D87-C87*D42/((1+D23/100)*(1+D41/100)))<((C93*C87*D42/((1+D23/100)*(1+D41/100))+(D38*C87*C94*D42/((1+D23/100)*(1+D41/100)))))),1,0)) -> 0 | E84: =IF(AND(E83=0,ABS(E87-D87*E42/((1+E23/100)*(1+E41/100)))<((D93*D87*E42/((1+E23/100)*(1+E41/100))+(E38*D87*D94*E42/((1+E23/100)*(1+E41/100)))))),1,0) -> 0 | F84: =IF(AND(F83=0,ABS(F87-E87*F42/((1+F23/100)*(1+F41/100)))<((E93*E87*F42/((1+F23/100)*(1+F41/100))+(F38*E87*E94*F42/((1+F23/100)*(1+F41/100)))))),1,0) -> 0 | G84: =IF(AND(G83=0,ABS(G87-F87*G42/((1+G23/100)*(1+G41/100)))<((F93*F87*G42/((1+G23/100)*(1+G41/100))+(G38*F87*F94*G42/((1+G23/100)*(1+G41/100)))))),1,0) -> 0 | H84: =IF(AND(H83=0,ABS(H87-G87*H42/((1+H23/100)*(1+H41/100)))<((G93*G87*H42/((1+H23/100)*(1+H41/100))+(H38*G87*G94*H42/((1+H23/100)*(1+H41/100)))))),1,0) -> 0 | I84: =IF(AND(I83=0,ABS(I87-H87*I42/((1+I23/100)*(1+I41/100)))<((H93*H87*I42/((1+I23/100)*(1+I41/100))+(I38*H87*H94*I42/((1+I23/100)*(1+I41/100)))))),1,0) -> 0 | J84: =IF(AND(J83=0,ABS(J87-I87*J42/((1+J23/100)*(1+J41/100)))<((I93*I87*J42/((1+J23/100)*(1+J41/100))+(J38*I87*I94*J42/((1+J23/100)*(1+J41/100)))))),1,0) -> 0 | K84: =IF(AND(K83=0,ABS(K87-J87*K42/((1+K23/100)*(1+K41/100)))<((J93*J87*K42/((1+K23/100)*(1+K41/100))+(K38*J87*J94*K42/((1+K23/100)*(1+K41/100)))))),1,0) -> 0 | L84: =IF(AND(L83=0,ABS(L87-K87*L42/((1+L23/100)*(1+L41/100)))<((K93*K87*L42/((1+L23/100)*(1+L41/100))+(L38*K87*K94*L42/((1+L23/100)*(1+L41/100)))))),1,0) -> 0 | ... U84: =IF(AND(U83=0,ABS(U87-T87*U42/((1+U23/100)*(1+U41/100)))<((T93*T87*U42/((1+U23/100)*(1+U41/100))+(U38*T87*T94*U42/((1+U23/100)*(1+U41/100)))))),1,0) -> 0
C86: ='Input data'!$C$5-1 -> 2025 | D86: =C86+1 -> 2026 | E86: =D86+1 -> 2027 | F86: =E86+1 -> 2028 | G86: =F86+1 -> 2029 | H86: =G86+1 -> 2030 | I86: =H86+1 -> 2031 | J86: =I86+1 -> 2032 | K86: =J86+1 -> 2033 | ... U86: =T86+1 -> 2043
B87: Gross debt | C87: =C56 -> 44.25023 | D87: =D56 -> 45.838496 | E87: =D87*(1+E101/100)*E42-E59-E60+E61+E62+E63+E64+E65+E72 -> 47.042628 | F87: =E87*(1+F101/100)*F42-F59-F60+F61+F62+F63+F64+F65+F72 -> 48.037876 | G87: =F87*(1+G101/100)*G42-G59-G60+G61+G62+G63+G64+G65+G72 -> 49.449015 | H87: =G87*(1+H101/100)*H42-H59-H60+H61+H62+H63+H64+H65+H72 -> 51.025604 | I87: =H87*(1+I101/100)*I42-I59-I60+I61+I62+I63+I64+I65+I72 -> 52.830768 | J87: =I87*(1+J101/100)*J42-J59-J60+J61+J62+J63+J64+J65+J72 -> 54.798963 | K87: =J87*(1+K101/100)*K42-K59-K60+K61+K62+K63+K64+K65+K72 -> 56.937193 | L87: =K87*(1+L101/100)*L42-L59-L60+L61+L62+L63+L64+L65+L72 -> 59.577012 | ... U87: =T87*(1+U101/100)*U42-U59-U60+U61+U62+U63+U64+U65+U72 -> 91.692978
B88: Of which Outstanding debt | C88: =IF(C$10<_xlfn.NUMBERVALUE(RIGHT('Input data'!$B$66,4)),"", IF(C$10=_xlfn.NUMBERVALUE(RIGHT('Input data'!$B$66,4)),'Input data'!$C66*C$87, IF(C87=0,0,IF(C83=1,B87*C42/((1+C23/100)*(1+C41/100))-C89-C90,IF(AND(C83=0,C84=1),(1-B93-C38*B94)*B87*C42/((1+C23/100)*(1+C41/100)),C87))))) -> 37.04973 | D88: =IF(D$10<_xlfn.NUMBERVALUE(RIGHT('Input data'!$B$66,4)),"", IF(D$10=_xlfn.NUMBERVALUE(RIGHT('Input data'!$B$66,4)),'Input data'!$C66*D$87, IF(D87=0,0,IF(D83=1,C87*D42/((1+D23/100)*(1+D41/100))-D89-D90,IF(AND(D83=0,D84=1),(1-C93-D38*C94)*C87*D42/((1+D23/100)*(1+D41/100)),D87))))) -> 38.429584 | E88: =IF(E$10<_xlfn.NUMBERVALUE(RIGHT('Input data'!$B$66,4)),"", IF(E$10=_xlfn.NUMBERVALUE(RIGHT('Input data'!$B$66,4)),'Input data'!$C66*E$87, IF(E87=0,0,IF(E83=1,D87*E42/((1+E23/100)*(1+E41/100))-E89-E90,IF(AND(E83=0,E84=1),(1-D93-E38*D94)*D87*E42/((1+E23/100)*(1+E41/100)),E87))))) -> 39.475992 | F88: =IF(F$10<_xlfn.NUMBERVALUE(RIGHT('Input data'!$B$66,4)),"", IF(F$10=_xlfn.NUMBERVALUE(RIGHT('Input data'!$B$66,4)),'Input data'!$C66*F$87, IF(F87=0,0,IF(F83=1,E87*F42/((1+F23/100)*(1+F41/100))-F89-F90,IF(AND(F83=0,F84=1),(1-E93-F38*E94)*E87*F42/((1+F23/100)*(1+F41/100)),F87))))) -> 40.783534 | G88: =IF(G$10<_xlfn.NUMBERVALUE(RIGHT('Input data'!$B$66,4)),"", IF(G$10=_xlfn.NUMBERVALUE(RIGHT('Input data'!$B$66,4)),'Input data'!$C66*G$87, IF(G87=0,0,IF(G83=1,F87*G42/((1+G23/100)*(1+G41/100))-G89-G90,IF(AND(G83=0,G84=1),(1-F93-G38*F94)*F87*G42/((1+G23/100)*(1+G41/100)),G87))))) -> 41.717157 | H88: =IF(H$10<_xlfn.NUMBERVALUE(RIGHT('Input data'!$B$66,4)),"", IF(H$10=_xlfn.NUMBERVALUE(RIGHT('Input data'!$B$66,4)),'Input data'!$C66*H$87, IF(H87=0,0,IF(H83=1,G87*H42/((1+H23/100)*(1+H41/100))-H89-H90,IF(AND(H83=0,H84=1),(1-G93-H38*G94)*G87*H42/((1+H23/100)*(1+H41/100)),H87))))) -> 42.895268 | I88: =IF(I$10<_xlfn.NUMBERVALUE(RIGHT('Input data'!$B$66,4)),"", IF(I$10=_xlfn.NUMBERVALUE(RIGHT('Input data'!$B$66,4)),'Input data'!$C66*I$87, IF(I87=0,0,IF(I83=1,H87*I42/((1+I23/100)*(1+I41/100))-I89-I90,IF(AND(I83=0,I84=1),(1-H93-I38*H94)*H87*I42/((1+I23/100)*(1+I41/100)),I87))))) -> 44.199997 | J88: =IF(J$10<_xlfn.NUMBERVALUE(RIGHT('Input data'!$B$66,4)),"", IF(J$10=_xlfn.NUMBERVALUE(RIGHT('Input data'!$B$66,4)),'Input data'!$C66*J$87, IF(J87=0,0,IF(J83=1,I87*J42/((1+J23/100)*(1+J41/100))-J89-J90,IF(AND(J83=0,J84=1),(1-I93-J38*I94)*I87*J42/((1+J23/100)*(1+J41/100)),J87))))) -> 45.726132 | ... R88: =IF(R$10<_xlfn.NUMBERVALUE(RIGHT('Input data'!$B$66,4)),"", IF(R$10=_xlfn.NUMBERVALUE(RIGHT('Input data'!$B$66,4)),'Input data'!$C66*R$87, IF(R87=0,0,IF(R83=1,Q87*R42/((1+R23/100)*(1+R41/100))-R89-R90,IF(AND(R83=0,R84=1),(1-Q93-R38*Q94)*Q87*R42/((1+R23/100)*(1+R41/100)),R87))))) -> 65.03785 | S88: =IF(S87=0,0,IF(S83=1,R87*S42/((1+S23/100)*(1+S41/100))-S89-S90,IF(AND(S83=0,S84=1),(1-R93-S38*R94)*R87*S42/((1+S23/100)*(1+S41/100)),S87))) -> 68.169277 | T88: =IF(T87=0,0,IF(T83=1,S87*T42/((1+T23/100)*(1+T41/100))-T89-T90,IF(AND(T83=0,T84=1),(1-S93-T38*S94)*S87*T42/((1+T23/100)*(1+T41/100)),T87))) -> 71.54274 | U88: =IF(U87=0,0,IF(U83=1,T87*U42/((1+U23/100)*(1+U41/100))-U89-U90,IF(AND(U83=0,U84=1),(1-T93-U38*T94)*T87*U42/((1+U23/100)*(1+U41/100)),U87))) -> 75.059109
B89: Rolled over long-term debt | C89: =IF(C$10<_xlfn.NUMBERVALUE(RIGHT('Input data'!$B$66,4)),"", IF(C$10=_xlfn.NUMBERVALUE(RIGHT('Input data'!$B$66,4)),'Input data'!$C67*C$87, IF(C87=0,0,IF(C83=1,C38*B87*B94*C42/((1+C23/100)*(1+C41/100)),IF(AND(C83=0,C84=1),(C38*B87*B94*C42/((1+C23/100)*(1+C41/100)))*(1-ABS(C87-B87*C42/((1+C23/100)*(1+C41/100)))/((C38*B87*B94*C42/((1+C23/100)*(1+C41/100)))+(B93*B87*C42/((1+C23/100)*(1+C41/100))))),0))))) -> 2.701846 | D89: =IF(D$10<_xlfn.NUMBERVALUE(RIGHT('Input data'!$B$66,4)),"", IF(D$10=_xlfn.NUMBERVALUE(RIGHT('Input data'!$B$66,4)),'Input data'!$C67*D$87, IF(D87=0,0,IF(D83=1,D38*C87*C94*D42/((1+D23/100)*(1+D41/100)),IF(AND(D83=0,D84=1),(D38*C87*C94*D42/((1+D23/100)*(1+D41/100)))*(1-ABS(D87-C87*D42/((1+D23/100)*(1+D41/100)))/((D38*C87*C94*D42/((1+D23/100)*(1+D41/100)))+(C93*C87*D42/((1+D23/100)*(1+D41/100))))),0))))) -> 2.8142827 | E89: =IF(E$10<_xlfn.NUMBERVALUE(RIGHT('Input data'!$B$66,4)),"", IF(E$10=_xlfn.NUMBERVALUE(RIGHT('Input data'!$B$66,4)),'Input data'!$C67*E$87, IF(E87=0,0,IF(E83=1,E38*D87*D94*E42/((1+E23/100)*(1+E41/100)),IF(AND(E83=0,E84=1),(E38*D87*D94*E42/((1+E23/100)*(1+E41/100)))*(1-ABS(E87-D87*E42/((1+E23/100)*(1+E41/100)))/((E38*D87*D94*E42/((1+E23/100)*(1+E41/100)))+(D93*D87*E42/((1+E23/100)*(1+E41/100))))),0))))) -> 2.9283971 | F89: =IF(F$10<_xlfn.NUMBERVALUE(RIGHT('Input data'!$B$66,4)),"", IF(F$10=_xlfn.NUMBERVALUE(RIGHT('Input data'!$B$66,4)),'Input data'!$C67*F$87, IF(F87=0,0,IF(F83=1,F38*E87*E94*F42/((1+F23/100)*(1+F41/100)),IF(AND(F83=0,F84=1),(F38*E87*E94*F42/((1+F23/100)*(1+F41/100)))*(1-ABS(F87-E87*F42/((1+F23/100)*(1+F41/100)))/((F38*E87*E94*F42/((1+F23/100)*(1+F41/100)))+(E93*E87*F42/((1+F23/100)*(1+F41/100))))),0))))) -> 3.0641865 | G89: =IF(G$10<_xlfn.NUMBERVALUE(RIGHT('Input data'!$B$66,4)),"", IF(G$10=_xlfn.NUMBERVALUE(RIGHT('Input data'!$B$66,4)),'Input data'!$C67*G$87, IF(G87=0,0,IF(G83=1,G38*F87*F94*G42/((1+G23/100)*(1+G41/100)),IF(AND(G83=0,G84=1),(G38*F87*F94*G42/((1+G23/100)*(1+G41/100)))*(1-ABS(G87-F87*G42/((1+G23/100)*(1+G41/100)))/((G38*F87*F94*G42/((1+G23/100)*(1+G41/100)))+(F93*F87*G42/((1+G23/100)*(1+G41/100))))),0))))) -> 3.1740845 | H89: =IF(H$10<_xlfn.NUMBERVALUE(RIGHT('Input data'!$B$66,4)),"", IF(H$10=_xlfn.NUMBERVALUE(RIGHT('Input data'!$B$66,4)),'Input data'!$C67*H$87, IF(H87=0,0,IF(H83=1,H38*G87*G94*H42/((1+H23/100)*(1+H41/100)),IF(AND(H83=0,H84=1),(H38*G87*G94*H42/((1+H23/100)*(1+H41/100)))*(1-ABS(H87-G87*H42/((1+H23/100)*(1+H41/100)))/((H38*G87*G94*H42/((1+H23/100)*(1+H41/100)))+(G93*G87*H42/((1+H23/100)*(1+H41/100))))),0))))) -> 3.3046693 | I89: =IF(I$10<_xlfn.NUMBERVALUE(RIGHT('Input data'!$B$66,4)),"", IF(I$10=_xlfn.NUMBERVALUE(RIGHT('Input data'!$B$66,4)),'Input data'!$C67*I$87, IF(I87=0,0,IF(I83=1,I38*H87*H94*I42/((1+I23/100)*(1+I41/100)),IF(AND(I83=0,I84=1),(I38*H87*H94*I42/((1+I23/100)*(1+I41/100)))*(1-ABS(I87-H87*I42/((1+I23/100)*(1+I41/100)))/((I38*H87*H94*I42/((1+I23/100)*(1+I41/100)))+(H93*H87*I42/((1+I23/100)*(1+I41/100))))),0))))) -> 3.4474539 | J89: =IF(J$10<_xlfn.NUMBERVALUE(RIGHT('Input data'!$B$66,4)),"", IF(J$10=_xlfn.NUMBERVALUE(RIGHT('Input data'!$B$66,4)),'Input data'!$C67*J$87, IF(J87=0,0,IF(J83=1,J38*I87*I94*J42/((1+J23/100)*(1+J41/100)),IF(AND(J83=0,J84=1),(J38*I87*I94*J42/((1+J23/100)*(1+J41/100)))*(1-ABS(J87-I87*J42/((1+J23/100)*(1+J41/100)))/((J38*I87*I94*J42/((1+J23/100)*(1+J41/100)))+(I93*I87*J42/((1+J23/100)*(1+J41/100))))),0))))) -> 3.6102922 | ... R89: =IF(R$10<_xlfn.NUMBERVALUE(RIGHT('Input data'!$B$66,4)),"", IF(R$10=_xlfn.NUMBERVALUE(RIGHT('Input data'!$B$66,4)),'Input data'!$C67*R$87, IF(R87=0,0,IF(R83=1,R38*Q87*Q94*R42/((1+R23/100)*(1+R41/100)),IF(AND(R83=0,R84=1),(R38*Q87*Q94*R42/((1+R23/100)*(1+R41/100)))*(1-ABS(R87-Q87*R42/((1+R23/100)*(1+R41/100)))/((R38*Q87*Q94*R42/((1+R23/100)*(1+R41/100)))+(Q93*Q87*R42/((1+R23/100)*(1+R41/100))))),0))))) -> 5.3226242 | S89: =IF(S87=0,0,IF(S83=1,S38*R87*R94*S42/((1+S23/100)*(1+S41/100)),IF(AND(S83=0,S84=1),(S38*R87*R94*S42/((1+S23/100)*(1+S41/100)))*(1-ABS(S87-R87*S42/((1+S23/100)*(1+S41/100)))/((S38*R87*R94*S42/((1+S23/100)*(1+S41/100)))+(R93*R87*S42/((1+S23/100)*(1+S41/100))))),0))) -> 5.5788967 | T89: =IF(T87=0,0,IF(T83=1,T38*S87*S94*T42/((1+T23/100)*(1+T41/100)),IF(AND(T83=0,T84=1),(T38*S87*S94*T42/((1+T23/100)*(1+T41/100)))*(1-ABS(T87-S87*T42/((1+T23/100)*(1+T41/100)))/((T38*S87*S94*T42/((1+T23/100)*(1+T41/100)))+(S93*S87*T42/((1+T23/100)*(1+T41/100))))),0))) -> 5.8549771 | U89: =IF(U87=0,0,IF(U83=1,U38*T87*T94*U42/((1+U23/100)*(1+U41/100)),IF(AND(U83=0,U84=1),(U38*T87*T94*U42/((1+U23/100)*(1+U41/100)))*(1-ABS(U87-T87*U42/((1+U23/100)*(1+U41/100)))/((U38*T87*T94*U42/((1+U23/100)*(1+U41/100)))+(T93*T87*U42/((1+U23/100)*(1+U41/100))))),0))) -> 6.1427528
B90: Rolled over short-term debt | C90: =IF(C$10<_xlfn.NUMBERVALUE(RIGHT('Input data'!$B$66,4)),"", IF(C$10=_xlfn.NUMBERVALUE(RIGHT('Input data'!$B$66,4)),'Input data'!$C68*C$87, IF(C87=0,0,IF(C83=1,(1-B94)*B87*C42/((1+C23/100)*(1+C41/100)),IF(AND(C83=0,C84=1),(B93*B87*C42/((1+C23/100)*(1+C41/100)))*(1-ABS(C87-B87*C42/((1+C23/100)*(1+C41/100)))/((C38*B87*B94*C42/((1+C23/100)*(1+C41/100)))+(B93*B87*C42/((1+C23/100)*(1+C41/100))))),0))))) -> 0.9648441 | D90: =IF(D$10<_xlfn.NUMBERVALUE(RIGHT('Input data'!$B$66,4)),"", IF(D$10=_xlfn.NUMBERVALUE(RIGHT('Input data'!$B$66,4)),'Input data'!$C68*D$87, IF(D87=0,0,IF(D83=1,(1-C94)*C87*D42/((1+D23/100)*(1+D41/100)),IF(AND(D83=0,D84=1),(C93*C87*D42/((1+D23/100)*(1+D41/100)))*(1-ABS(D87-C87*D42/((1+D23/100)*(1+D41/100)))/((D38*C87*C94*D42/((1+D23/100)*(1+D41/100)))+(C93*C87*D42/((1+D23/100)*(1+D41/100))))),0))))) -> 1.0541067 | E90: =IF(E$10<_xlfn.NUMBERVALUE(RIGHT('Input data'!$B$66,4)),"", IF(E$10=_xlfn.NUMBERVALUE(RIGHT('Input data'!$B$66,4)),'Input data'!$C68*E$87, IF(E87=0,0,IF(E83=1,(1-D94)*D87*E42/((1+E23/100)*(1+E41/100)),IF(AND(E83=0,E84=1),(D93*D87*E42/((1+E23/100)*(1+E41/100)))*(1-ABS(E87-D87*E42/((1+E23/100)*(1+E41/100)))/((E38*D87*D94*E42/((1+E23/100)*(1+E41/100)))+(D93*D87*E42/((1+E23/100)*(1+E41/100))))),0))))) -> 1.1324152 | F90: =IF(F$10<_xlfn.NUMBERVALUE(RIGHT('Input data'!$B$66,4)),"", IF(F$10=_xlfn.NUMBERVALUE(RIGHT('Input data'!$B$66,4)),'Input data'!$C68*F$87, IF(F87=0,0,IF(F83=1,(1-E94)*E87*F42/((1+F23/100)*(1+F41/100)),IF(AND(F83=0,F84=1),(E93*E87*F42/((1+F23/100)*(1+F41/100)))*(1-ABS(F87-E87*F42/((1+F23/100)*(1+F41/100)))/((F38*E87*E94*F42/((1+F23/100)*(1+F41/100)))+(E93*E87*F42/((1+F23/100)*(1+F41/100))))),0))))) -> 1.2158413 | G90: =IF(G$10<_xlfn.NUMBERVALUE(RIGHT('Input data'!$B$66,4)),"", IF(G$10=_xlfn.NUMBERVALUE(RIGHT('Input data'!$B$66,4)),'Input data'!$C68*G$87, IF(G87=0,0,IF(G83=1,(1-F94)*F87*G42/((1+G23/100)*(1+G41/100)),IF(AND(G83=0,G84=1),(F93*F87*G42/((1+G23/100)*(1+G41/100)))*(1-ABS(G87-F87*G42/((1+G23/100)*(1+G41/100)))/((G38*F87*F94*G42/((1+G23/100)*(1+G41/100)))+(F93*F87*G42/((1+G23/100)*(1+G41/100))))),0))))) -> 1.28017 | H90: =IF(H$10<_xlfn.NUMBERVALUE(RIGHT('Input data'!$B$66,4)),"", IF(H$10=_xlfn.NUMBERVALUE(RIGHT('Input data'!$B$66,4)),'Input data'!$C68*H$87, IF(H87=0,0,IF(H83=1,(1-G94)*G87*H42/((1+H23/100)*(1+H41/100)),IF(AND(H83=0,H84=1),(G93*G87*H42/((1+H23/100)*(1+H41/100)))*(1-ABS(H87-G87*H42/((1+H23/100)*(1+H41/100)))/((H38*G87*G94*H42/((1+H23/100)*(1+H41/100)))+(G93*G87*H42/((1+H23/100)*(1+H41/100))))),0))))) -> 1.354126 | I90: =IF(I$10<_xlfn.NUMBERVALUE(RIGHT('Input data'!$B$66,4)),"", IF(I$10=_xlfn.NUMBERVALUE(RIGHT('Input data'!$B$66,4)),'Input data'!$C68*I$87, IF(I87=0,0,IF(I83=1,(1-H94)*H87*I42/((1+I23/100)*(1+I41/100)),IF(AND(I83=0,I84=1),(H93*H87*I42/((1+I23/100)*(1+I41/100)))*(1-ABS(I87-H87*I42/((1+I23/100)*(1+I41/100)))/((I38*H87*H94*I42/((1+I23/100)*(1+I41/100)))+(H93*H87*I42/((1+I23/100)*(1+I41/100))))),0))))) -> 1.4328196 | J90: =IF(J$10<_xlfn.NUMBERVALUE(RIGHT('Input data'!$B$66,4)),"", IF(J$10=_xlfn.NUMBERVALUE(RIGHT('Input data'!$B$66,4)),'Input data'!$C68*J$87, IF(J87=0,0,IF(J83=1,(1-I94)*I87*J42/((1+J23/100)*(1+J41/100)),IF(AND(J83=0,J84=1),(I93*I87*J42/((1+J23/100)*(1+J41/100)))*(1-ABS(J87-I87*J42/((1+J23/100)*(1+J41/100)))/((J38*I87*I94*J42/((1+J23/100)*(1+J41/100)))+(I93*I87*J42/((1+J23/100)*(1+J41/100))))),0))))) -> 1.5201803 | ... R90: =IF(R$10<_xlfn.NUMBERVALUE(RIGHT('Input data'!$B$66,4)),"", IF(R$10=_xlfn.NUMBERVALUE(RIGHT('Input data'!$B$66,4)),'Input data'!$C68*R$87, IF(R87=0,0,IF(R83=1,(1-Q94)*Q87*R42/((1+R23/100)*(1+R41/100)),IF(AND(R83=0,R84=1),(Q93*Q87*R42/((1+R23/100)*(1+R41/100)))*(1-ABS(R87-Q87*R42/((1+R23/100)*(1+R41/100)))/((R38*Q87*Q94*R42/((1+R23/100)*(1+R41/100)))+(Q93*Q87*R42/((1+R23/100)*(1+R41/100))))),0))))) -> 2.4967457 | S90: =IF(S87=0,0,IF(S83=1,(1-R94)*R87*S42/((1+S23/100)*(1+S41/100)),IF(AND(S83=0,S84=1),(R93*R87*S42/((1+S23/100)*(1+S41/100)))*(1-ABS(S87-R87*S42/((1+S23/100)*(1+S41/100)))/((S38*R87*R94*S42/((1+S23/100)*(1+S41/100)))+(R93*R87*S42/((1+S23/100)*(1+S41/100))))),0))) -> 2.6477811 | T90: =IF(T87=0,0,IF(T83=1,(1-S94)*S87*T42/((1+T23/100)*(1+T41/100)),IF(AND(T83=0,T84=1),(S93*S87*T42/((1+T23/100)*(1+T41/100)))*(1-ABS(T87-S87*T42/((1+T23/100)*(1+T41/100)))/((T38*S87*S94*T42/((1+T23/100)*(1+T41/100)))+(S93*S87*T42/((1+T23/100)*(1+T41/100))))),0))) -> 2.8088931 | U90: =IF(U87=0,0,IF(U83=1,(1-T94)*T87*U42/((1+U23/100)*(1+U41/100)),IF(AND(U83=0,U84=1),(T93*T87*U42/((1+U23/100)*(1+U41/100)))*(1-ABS(U87-T87*U42/((1+U23/100)*(1+U41/100)))/((U38*T87*T94*U42/((1+U23/100)*(1+U41/100)))+(T93*T87*U42/((1+U23/100)*(1+U41/100))))),0))) -> 2.9757831
B91: New long-term debt | C91: =IF(C$10<_xlfn.NUMBERVALUE(RIGHT('Input data'!$B$66,4)),"", IF(C$10=_xlfn.NUMBERVALUE(RIGHT('Input data'!$B$66,4)),'Input data'!$C69*C$87, IF(C87=0,0,IF(C83=1,'Input data'!$C$58*(C87-B87*C42/((1+C23/100)*(1+C41/100))),0)))) -> 3.395897 | D91: =IF(D$10<_xlfn.NUMBERVALUE(RIGHT('Input data'!$B$66,4)),"", IF(D$10=_xlfn.NUMBERVALUE(RIGHT('Input data'!$B$66,4)),'Input data'!$C69*D$87, IF(D87=0,0,IF(D83=1,'Input data'!$C$58*(D87-C87*D42/((1+D23/100)*(1+D41/100))),0)))) -> 3.4023463 | E91: =IF(E$10<_xlfn.NUMBERVALUE(RIGHT('Input data'!$B$66,4)),"", IF(E$10=_xlfn.NUMBERVALUE(RIGHT('Input data'!$B$66,4)),'Input data'!$C69*E$87, IF(E87=0,0,IF(E83=1,'Input data'!$C$58*(E87-D87*E42/((1+E23/100)*(1+E41/100))),0)))) -> 3.3690009 | F91: =IF(F$10<_xlfn.NUMBERVALUE(RIGHT('Input data'!$B$66,4)),"", IF(F$10=_xlfn.NUMBERVALUE(RIGHT('Input data'!$B$66,4)),'Input data'!$C69*F$87, IF(F87=0,0,IF(F83=1,'Input data'!$C$58*(F87-E87*F42/((1+F23/100)*(1+F41/100))),0)))) -> 2.8582347 | G91: =IF(G$10<_xlfn.NUMBERVALUE(RIGHT('Input data'!$B$66,4)),"", IF(G$10=_xlfn.NUMBERVALUE(RIGHT('Input data'!$B$66,4)),'Input data'!$C69*G$87, IF(G87=0,0,IF(G83=1,'Input data'!$C$58*(G87-F87*G42/((1+G23/100)*(1+G41/100))),0)))) -> 3.1496875 | H91: =IF(H$10<_xlfn.NUMBERVALUE(RIGHT('Input data'!$B$66,4)),"", IF(H$10=_xlfn.NUMBERVALUE(RIGHT('Input data'!$B$66,4)),'Input data'!$C69*H$87, IF(H87=0,0,IF(H83=1,'Input data'!$C$58*(H87-G87*H42/((1+H23/100)*(1+H41/100))),0)))) -> 3.3360558 | I91: =IF(I$10<_xlfn.NUMBERVALUE(RIGHT('Input data'!$B$66,4)),"", IF(I$10=_xlfn.NUMBERVALUE(RIGHT('Input data'!$B$66,4)),'Input data'!$C69*I$87, IF(I87=0,0,IF(I83=1,'Input data'!$C$58*(I87-H87*I42/((1+I23/100)*(1+I41/100))),0)))) -> 3.6041264 | J91: =IF(J$10<_xlfn.NUMBERVALUE(RIGHT('Input data'!$B$66,4)),"", IF(J$10=_xlfn.NUMBERVALUE(RIGHT('Input data'!$B$66,4)),'Input data'!$C69*J$87, IF(J87=0,0,IF(J83=1,'Input data'!$C$58*(J87-I87*J42/((1+J23/100)*(1+J41/100))),0)))) -> 3.788499 | ... R91: =IF(R$10<_xlfn.NUMBERVALUE(RIGHT('Input data'!$B$66,4)),"", IF(R$10=_xlfn.NUMBERVALUE(RIGHT('Input data'!$B$66,4)),'Input data'!$C69*R$87, IF(R87=0,0,IF(R83=1,'Input data'!$C$58*(R87-Q87*R42/((1+R23/100)*(1+R41/100))),0)))) -> 6.244566 | S91: =IF(S87=0,0,IF(S83=1,'Input data'!$C$58*(S87-R87*S42/((1+S23/100)*(1+S41/100))),0)) -> 6.6344145 | T91: =IF(T87=0,0,IF(T83=1,'Input data'!$C$58*(T87-S87*T42/((1+T23/100)*(1+T41/100))),0)) -> 6.929998 | U91: =IF(U87=0,0,IF(U83=1,'Input data'!$C$58*(U87-T87*U42/((1+U23/100)*(1+U41/100))),0)) -> 7.22203
B92: New short-term debt | C92: =IF(C$10<_xlfn.NUMBERVALUE(RIGHT('Input data'!$B$66,4)),"", IF(C$10=_xlfn.NUMBERVALUE(RIGHT('Input data'!$B$66,4)),'Input data'!$C70*C$87, IF(C87=0,0,IF(C83=1,'Input data'!$C$57*(C87-B87*C42/((1+C23/100)*(1+C41/100))),0)))) -> 0.1379148 | D92: =IF(D$10<_xlfn.NUMBERVALUE(RIGHT('Input data'!$B$66,4)),"", IF(D$10=_xlfn.NUMBERVALUE(RIGHT('Input data'!$B$66,4)),'Input data'!$C70*D$87, IF(D87=0,0,IF(D83=1,'Input data'!$C$57*(D87-C87*D42/((1+D23/100)*(1+D41/100))),0)))) -> 0.1381767 | E92: =IF(E$10<_xlfn.NUMBERVALUE(RIGHT('Input data'!$B$66,4)),"", IF(E$10=_xlfn.NUMBERVALUE(RIGHT('Input data'!$B$66,4)),'Input data'!$C70*E$87, IF(E87=0,0,IF(E83=1,'Input data'!$C$57*(E87-D87*E42/((1+E23/100)*(1+E41/100))),0)))) -> 0.13682247 | F92: =IF(F$10<_xlfn.NUMBERVALUE(RIGHT('Input data'!$B$66,4)),"", IF(F$10=_xlfn.NUMBERVALUE(RIGHT('Input data'!$B$66,4)),'Input data'!$C70*F$87, IF(F87=0,0,IF(F83=1,'Input data'!$C$57*(F87-E87*F42/((1+F23/100)*(1+F41/100))),0)))) -> 0.11607914 | G92: =IF(G$10<_xlfn.NUMBERVALUE(RIGHT('Input data'!$B$66,4)),"", IF(G$10=_xlfn.NUMBERVALUE(RIGHT('Input data'!$B$66,4)),'Input data'!$C70*G$87, IF(G87=0,0,IF(G83=1,'Input data'!$C$57*(G87-F87*G42/((1+G23/100)*(1+G41/100))),0)))) -> 0.12791568 | H92: =IF(H$10<_xlfn.NUMBERVALUE(RIGHT('Input data'!$B$66,4)),"", IF(H$10=_xlfn.NUMBERVALUE(RIGHT('Input data'!$B$66,4)),'Input data'!$C70*H$87, IF(H87=0,0,IF(H83=1,'Input data'!$C$57*(H87-G87*H42/((1+H23/100)*(1+H41/100))),0)))) -> 0.1354845 | I92: =IF(I$10<_xlfn.NUMBERVALUE(RIGHT('Input data'!$B$66,4)),"", IF(I$10=_xlfn.NUMBERVALUE(RIGHT('Input data'!$B$66,4)),'Input data'!$C70*I$87, IF(I87=0,0,IF(I83=1,'Input data'!$C$57*(I87-H87*I42/((1+I23/100)*(1+I41/100))),0)))) -> 0.14637143 | J92: =IF(J$10<_xlfn.NUMBERVALUE(RIGHT('Input data'!$B$66,4)),"", IF(J$10=_xlfn.NUMBERVALUE(RIGHT('Input data'!$B$66,4)),'Input data'!$C70*J$87, IF(J87=0,0,IF(J83=1,'Input data'!$C$57*(J87-I87*J42/((1+J23/100)*(1+J41/100))),0)))) -> 0.1538592 | ... R92: =IF(R$10<_xlfn.NUMBERVALUE(RIGHT('Input data'!$B$66,4)),"", IF(R$10=_xlfn.NUMBERVALUE(RIGHT('Input data'!$B$66,4)),'Input data'!$C70*R$87, IF(R87=0,0,IF(R83=1,'Input data'!$C$57*(R87-Q87*R42/((1+R23/100)*(1+R41/100))),0)))) -> 0.25360544 | S92: =IF(S87=0,0,IF(S83=1,'Input data'!$C$57*(S87-R87*S42/((1+S23/100)*(1+S41/100))),0)) -> 0.26943803 | T92: =IF(T87=0,0,IF(T83=1,'Input data'!$C$57*(T87-S87*T42/((1+T23/100)*(1+T41/100))),0)) -> 0.28144232 | U92: =IF(U87=0,0,IF(U83=1,'Input data'!$C$57*(U87-T87*U42/((1+U23/100)*(1+U41/100))),0)) -> 0.29330238
B93: Share of short-term debt in total government debt | C93: =IF(C$10<_xlfn.NUMBERVALUE(RIGHT('Input data'!$B$66,4)),"",IF(C87<>0,(C90+C92)/(C88+C89+C90+C91+C92),0)) -> 0.024920974 | D93: =IF(D87<>0,(D90+D92)/(D88+D89+D90+D91+D92),0) -> 0.026010526 | E93: =IF(E87<>0,(E90+E92)/(E88+E89+E90+E91+E92),0) -> 0.026980586 | F93: =IF(F87<>0,(F90+F92)/(F88+F89+F90+F91+F92),0) -> 0.027726464 | G93: =IF(G87<>0,(G90+G92)/(G88+G89+G90+G91+G92),0) -> 0.028475505 | H93: =IF(H87<>0,(H90+H92)/(H88+H89+H90+H91+H92),0) -> 0.029193392 | I93: =IF(I87<>0,(I90+I92)/(I88+I89+I90+I91+I92),0) -> 0.029891502 | J93: =IF(J87<>0,(J90+J92)/(J88+J89+J90+J91+J92),0) -> 0.030548744 | K93: =IF(K87<>0,(K90+K92)/(K88+K89+K90+K91+K92),0) -> 0.031165705 | ... U93: =IF(U87<>0,(U90+U92)/(U88+U89+U90+U91+U92),0) -> 0.035652518
B94: Share of long-term debt in total government debt | C94: =IF(C$10<_xlfn.NUMBERVALUE(RIGHT('Input data'!$B$66,4)),"",IF(C87<>0,(C88+C89+C91)/(C88+C89+C90+C91+C92),1)) -> 0.97507903 | D94: =IF(D87<>0,(D88+D89+D91)/(D88+D89+D90+D91+D92),1) -> 0.97398947 | E94: =IF(E87<>0,(E88+E89+E91)/(E88+E89+E90+E91+E92),1) -> 0.97301941 | F94: =IF(F87<>0,(F88+F89+F91)/(F88+F89+F90+F91+F92),1) -> 0.97227354 | G94: =IF(G87<>0,(G88+G89+G91)/(G88+G89+G90+G91+G92),1) -> 0.97152449 | H94: =IF(H87<>0,(H88+H89+H91)/(H88+H89+H90+H91+H92),1) -> 0.97080661 | I94: =IF(I87<>0,(I88+I89+I91)/(I88+I89+I90+I91+I92),1) -> 0.9701085 | J94: =IF(J87<>0,(J88+J89+J91)/(J88+J89+J90+J91+J92),1) -> 0.96945126 | K94: =IF(K87<>0,(K88+K89+K91)/(K88+K89+K90+K91+K92),1) -> 0.96883429 | ... U94: =IF(U87<>0,(U88+U89+U91)/(U88+U89+U90+U91+U92),1) -> 0.96434748
B96: IIR | C96: =C35 -> 3.196961 | D96: =D35 -> 3.078103 | E96: =E98+E99 -> 2.999835 | F96: =F98+F99 -> 3.2787529 | G96: =G98+G99 -> 3.515114 | H96: =H98+H99 -> 3.7446797 | I96: =I98+I99 -> 3.9632939 | J96: =J98+J99 -> 4.173594 | K96: =K98+K99 -> 4.3733956 | L96: =L98+L99 -> 4.5637138 | ... U96: =U98+U99 -> 5.1509376
B97: Long-term implicit interest rate | D97: =IF(C$10<_xlfn.NUMBERVALUE(RIGHT('Input data'!$B$66,4)),"", ((D35*C87)-(D37*(C90+C92)))/(C88+C89+C91)) -> 3.0634901 | E97: =IF(E$10<='Input data'!$C$4+2,((E35*D87)-(E37*(D90+D92)))/(D88+D89+D91),IF(D87>0,(D97*D88+E36*(D91+D89))/(D88+D89+D91),E36)) -> 2.9659901 | F97: =IF(F$10<='Input data'!$C$4+2,((F35*E87)-(F37*(E90+E92)))/(E88+E89+E91),IF(E87>0,(E97*E88+F36*(E91+E89))/(E88+E89+E91),F36)) -> 3.2509158 | G97: =IF(G$10<='Input data'!$C$4+2,((G35*F87)-(G37*(F90+F92)))/(F88+F89+F91),IF(F87>0,(F97*F88+G36*(F91+F89))/(F88+F89+F91),G36)) -> 3.4927846 | H97: =IF(H$10<='Input data'!$C$4+2,((H35*G87)-(H37*(G90+G92)))/(G88+G89+G91),IF(G87>0,(G97*G88+H36*(G91+G89))/(G88+G89+G91),H36)) -> 3.7280045 | I97: =IF(I$10<='Input data'!$C$4+2,((I35*H87)-(I37*(H90+H92)))/(H88+H89+H91),IF(H87>0,(H97*H88+I36*(H91+H89))/(H88+H89+H91),I36)) -> 3.9522946 | J97: =IF(J$10<='Input data'!$C$4+2,((J35*I87)-(J37*(I90+I92)))/(I88+I89+I91),IF(I87>0,(I97*I88+J36*(I91+I89))/(I88+I89+I91),J36)) -> 4.1683267 | K97: =IF(K$10<='Input data'!$C$4+2,((K35*J87)-(K37*(J90+J92)))/(J88+J89+J91),IF(J87>0,(J97*J88+K36*(J91+J89))/(J88+J89+J91),K36)) -> 4.3738174 | L97: =IF(L$10<='Input data'!$C$4+2,((L35*K87)-(L37*(K90+K92)))/(K88+K89+K91),IF(K87>0,(K97*K88+L36*(K91+K89))/(K88+K89+K91),L36)) -> 4.569769 | ... U97: =IF(U$10<='Input data'!$C$4+2,((U35*T87)-(U37*(T90+T92)))/(T88+T89+T91),IF(T87>0,(T97*T88+U36*(T91+T89))/(T88+T89+T91),U36)) -> 5.2138369
B98: Nominal implicit interest rate on debt (Excel approximation) | D98: =IF(C$10<_xlfn.NUMBERVALUE(RIGHT('Input data'!$B$66,4)),"", D35) -> 3.078103 | E98: =IF(E$10<='Input data'!$C$4+2,E35,(E97*(D88+D89+D91)+E37*(D90+D92))/D87) -> 2.999835 | F98: =IF(F$10<='Input data'!$C$4+2,F35,(F97*(E88+E89+E91)+F37*(E90+E92))/E87) -> 3.2787529 | G98: =IF(G$10<='Input data'!$C$4+2,G35,(G97*(F88+F89+F91)+G37*(F90+F92))/F87) -> 3.515114 | H98: =IF(H$10<='Input data'!$C$4+2,H35,(H97*(G88+G89+G91)+H37*(G90+G92))/G87) -> 3.7446797 | I98: =IF(I$10<='Input data'!$C$4+2,I35,(I97*(H88+H89+H91)+I37*(H90+H92))/H87) -> 3.9632939 | J98: =IF(J$10<='Input data'!$C$4+2,J35,(J97*(I88+I89+I91)+J37*(I90+I92))/I87) -> 4.173594 | K98: =IF(K$10<='Input data'!$C$4+2,K35,(K97*(J88+J89+J91)+K37*(J90+J92))/J87) -> 4.3733956 | L98: =IF(L$10<='Input data'!$C$4+2,L35,(L97*(K88+K89+K91)+L37*(K90+K92))/K87) -> 4.5637138 | ... U98: =IF(U$10<='Input data'!$C$4+2,U35,(U97*(T88+T89+T91)+U37*(T90+T92))/T87) -> 5.1509376
B99: Diff. STATA | E99: =E108 -> 0 | F99: =F108 -> 0 | G99: =G108 -> 0 | H99: =H108 -> 0 | I99: =I108 -> 0 | J99: =J108 -> 0 | K99: =K108 -> 0 | L99: =L108 -> 0 | ... U99: =U108 -> 0
B101: (i - g) | C101: =((1+C96/100)/((1+C23/100)*(1+C41/100))-1)*100 -> -2.8128161 | D101: =((1+D96/100)/((1+D23/100)*(1+D41/100))-1)*100 -> -1.3622666 | E101: =((1+E96/100)/((1+E23/100)*(1+E41/100))-1)*100 -> -2.1720155 | F101: =((1+F96/100)/((1+F23/100)*(1+F41/100))-1)*100 -> -1.0661466 | G101: =((1+G96/100)/((1+G23/100)*(1+G41/100))-1)*100 -> -0.50686314 | H101: =((1+H96/100)/((1+H23/100)*(1+H41/100))-1)*100 -> -0.23095331 | I101: =((1+I96/100)/((1+I23/100)*(1+I41/100))-1)*100 -> -0.00026976911 | J101: =((1+J96/100)/((1+J23/100)*(1+J41/100))-1)*100 -> 0.28086744 | ... U101: =((1+U96/100)/((1+U23/100)*(1+U41/100))-1)*100 -> 1.2532111
B104: Per memo - STATA results
B106: Debt | C106: 44.25023 | D106: 45.8385 | E106: 47.04263 | F106: 48.03787 | G106: 49.44901 | H106: 51.02559 | I106: 52.83076 | J106: 54.79895 | K106: 56.93718 | L106: 59.57699 | M106: 62.45602 | N106: 65.50816 | O106: 68.71608 | P106: 72.16214 | Q106: 75.69213 | R106: 79.35538 | S106: 83.2998 | T106: 87.41805 | U106: 91.69298
B107: IIR | C107: 3.196961 | D107: 3.078103 | E107: 2.999835 | F107: 3.278753 | G107: 3.515114 | H107: 3.744679 | I107: 3.963294 | J107: 4.173594 | K107: 4.373395 | L107: 4.563714 | M107: 4.750954 | N107: 4.893939 | O107: 5.002471 | P107: 5.080944 | Q107: 5.133857 | R107: 5.163935 | S107: 5.174979 | T107: 5.169841 | U107: 5.150938
B108: IIR difference STATA - Excel | C108: 0 | D108: 0 | E108: 0 | F108: 0 | G108: 0 | H108: 0 | I108: 0 | J108: 0 | K108: 0 | L108: 0 | M108: 0 | N108: 0 | O108: 0 | P108: 0 | Q108: 0 | R108: 0 | S108: 0 | T108: 0 | U108: 0
B110: Share of long-term debt that matures every year | C110: 2025 | D110: 2026 | E110: 2027 | F110: 2028 | G110: 2029 | H110: 2030 | I110: 2031 | J110: 2032 | K110: 2033 | L110: 2034 | M110: 2035 | N110: 2036 | O110: 2037 | P110: 2038 | Q110: 2039 | R110: 2040 | S110: 2041 | T110: 2042 | U110: 2043
B111: CY | C111: 0.09159693 | D111: 0.08986207 | E111: 0.09073563 | F111: 0.09160918 | G111: 0.09248274 | H111: 0.0933563 | I111: 0.09422986 | J111: 0.09510342 | K111: 0.09597697 | L111: 0.09685053 | M111: 0.09772409 | N111: 0.09772409 | O111: 0.09772409 | P111: 0.09772409 | Q111: 0.09772409 | R111: 0.09772409 | S111: 0.09772409 | T111: 0.09772409 | U111: 0.09772409
B112: EL | C112: 0.02404821 | D112: 0.06459868 | E112: 0.06184427 | F112: 0.05908987 | G112: 0.05633546 | H112: 0.05358105 | I112: 0.05082665 | J112: 0.04807224 | K112: 0.04531784 | L112: 0.04256343 | M112: 0.03980902 | N112: 0.03980902 | O112: 0.03980902 | P112: 0.03980902 | Q112: 0.03980902 | R112: 0.03980902 | S112: 0.03980902 | T112: 0.03980902 | U112: 0.03980902
B113: IE | C113: 0.07888601 | D113: 0.08127556 | E113: 0.07849738 | F113: 0.07571919 | G113: 0.07294101 | H113: 0.07016283 | I113: 0.06738464 | J113: 0.06460646 | K113: 0.06182827 | L113: 0.05905009 | M113: 0.0562719 | N113: 0.0562719 | O113: 0.0562719 | P113: 0.0562719 | Q113: 0.0562719 | R113: 0.0562719 | S113: 0.0562719 | T113: 0.0562719 | U113: 0.0562719
B114: PT | C114: 0.07868656 | D114: 0.06579277 | E114: 0.06604191 | F114: 0.06629105 | G114: 0.06654019 | H114: 0.06678933 | I114: 0.06703846 | J114: 0.0672876 | K114: 0.06753674 | L114: 0.06778588 | M114: 0.06803502 | N114: 0.06803502 | O114: 0.06803502 | P114: 0.06803502 | Q114: 0.06803502 | R114: 0.06803502 | S114: 0.06803502 | T114: 0.06803502 | U114: 0.06803502

Sheet Adjustment scenario
B3: Country | C3: ='Input data'!C3 -> CZ
B4: Key years
B5: ='Input data'!B5 -> Last year before the adjustment | C5: =+'Input data'!C5 -> 2026
B6: Last year of adjustment | C6: =+C5+'Criteria results'!$F$5 -> 2030
B7: Last year of no-fiscal-policy-change projections | C7: =C5+'Criteria results'!$F$5+10 -> 2040
B9: Key assumptions
C10: ='Input data'!$C$5-1 -> 2025 | D10: =C10+1 -> 2026 | E10: =D10+1 -> 2027 | F10: =E10+1 -> 2028 | G10: =F10+1 -> 2029 | H10: =G10+1 -> 2030 | I10: =H10+1 -> 2031 | J10: =I10+1 -> 2032 | K10: =J10+1 -> 2033 | ... U10: =T10+1 -> 2043
B11: Fiscal assumptions (% of GDP)
B12: Structural primary balance ('+' means 'surplus') | C12: ='Input data'!C13 -> -0.5110157 | D12: ='Input data'!D13 -> -1.332759 | E12: =IF(E10<=$C$6, IF(AND(D78<=-1.5,'Criteria results'!$F$5=4,'Criteria results'!$F$6<0.4),D12+0.4, IF(AND(D78<=-1.5,'Criteria results'!$F$5=7,'Criteria results'!$F$6<0.25),D12+0.25, D12+'Criteria results'!$F$6)),D12) -> -0.872759 | F12: =IF(F10<=$C$6, IF(AND(E78<=-1.5,'Criteria results'!$F$5=4,'Criteria results'!$F$6<0.4),E12+0.4, IF(AND(E78<=-1.5,'Criteria results'!$F$5=7,'Criteria results'!$F$6<0.25),E12+0.25, E12+'Criteria results'!$F$6)),E12) -> -0.412759 | G12: =IF(G10<=$C$6, IF(AND(F78<=-1.5,'Criteria results'!$F$5=4,'Criteria results'!$F$6<0.4),F12+0.4, IF(AND(F78<=-1.5,'Criteria results'!$F$5=7,'Criteria results'!$F$6<0.25),F12+0.25, F12+'Criteria results'!$F$6)),F12) -> 0.047241 | H12: =IF(H10<=$C$6, IF(AND(G78<=-1.5,'Criteria results'!$F$5=4,'Criteria results'!$F$6<0.4),G12+0.4, IF(AND(G78<=-1.5,'Criteria results'!$F$5=7,'Criteria results'!$F$6<0.25),G12+0.25, G12+'Criteria results'!$F$6)),G12) -> 0.507241 | I12: =IF(I10<=$C$6, IF(AND(H78<=-1.5,'Criteria results'!$F$5=4,'Criteria results'!$F$6<0.4),H12+0.4, IF(AND(H78<=-1.5,'Criteria results'!$F$5=7,'Criteria results'!$F$6<0.25),H12+0.25, H12+'Criteria results'!$F$6)),H12) -> 0.507241 | J12: =IF(J10<=$C$6, IF(AND(I78<=-1.5,'Criteria results'!$F$5=4,'Criteria results'!$F$6<0.4),I12+0.4, IF(AND(I78<=-1.5,'Criteria results'!$F$5=7,'Criteria results'!$F$6<0.25),I12+0.25, I12+'Criteria results'!$F$6)),I12) -> 0.507241 | K12: =IF(K10<=$C$6, IF(AND(J78<=-1.5,'Criteria results'!$F$5=4,'Criteria results'!$F$6<0.4),J12+0.4, IF(AND(J78<=-1.5,'Criteria results'!$F$5=7,'Criteria results'!$F$6<0.25),J12+0.25, J12+'Criteria results'!$F$6)),J12) -> 0.507241 | L12: =K12 -> 0.507241 | M12: =L12 -> 0.507241 | N12: =M12 -> 0.507241 | O12: =N12 -> 0.507241 | P12: =O12 -> 0.507241 | Q12: =P12 -> 0.507241 | R12: =Q12 -> 0.507241 | S12: =R12 -> 0.507241 | ... U12: =T12 -> 0.507241
B13: Annual change in SPB | E13: =E12-D12 -> 0.46 | F13: =F12-E12 -> 0.46 | G13: =G12-F12 -> 0.46 | H13: =H12-G12 -> 0.46 | I13: =I12-H12 -> 0 | J13: =J12-I12 -> 0 | K13: =K12-J12 -> 0 | L13: =L12-K12 -> 0 | ... U13: =U12-T12 -> 0
B14: One-off and other temporary measures | C14: ='Input data'!C14 -> -0.1168709 | D14: ='Input data'!D14 -> 0 | E14: ='Input data'!E14 -> 0 | F14: ='Input data'!F14 -> 0 | G14: ='Input data'!G14 -> 0 | H14: ='Input data'!H14 -> 0 | I14: ='Input data'!I14 -> 0 | J14: ='Input data'!J14 -> 0 | ... U14: ='Input data'!U14 -> 0
B15: Stock flow adjustments (without exchange rate effect) | C15: ='Input data'!C15 -> 1.388104 | D15: ='Input data'!D15 -> 0.7474777 | E15: ='Input data'!E15 -> 0.85 | F15: ='Input data'!F15 -> 0 | G15: ='Input data'!G15 -> 0 | H15: ='Input data'!H15 -> 0 | I15: ='Input data'!I15 -> 0 | J15: ='Input data'!J15 -> 0 | ... U15: ='Input data'!U15 -> 0
B17: ='Input data'!B19 -> Cost of ageing and selected public revenue (based on the Commission-Council 2024 Ageing Report ("AR 2024"))
B18: Total ageing cost (net of taxes on pensions) | C18: ='Input data'!C20 -> 19.8 | D18: ='Input data'!D20 -> 19.7 | E18: ='Input data'!E20 -> 19.8 | F18: ='Input data'!F20 -> 19.9 | G18: ='Input data'!G20 -> 20 | H18: ='Input data'!H20 -> 20 | I18: ='Input data'!I20 -> 20.1 | J18: ='Input data'!J20 -> 20.1 | ... U18: ='Input data'!U20 -> 21.3
B19: Property income | C19: ='Input data'!C26 -> 1.037865 | D19: ='Input data'!D26 -> 1.023357 | E19: ='Input data'!E26 -> 1.008848 | F19: ='Input data'!F26 -> 0.9943401 | G19: ='Input data'!G26 -> 0.9798318 | H19: ='Input data'!H26 -> 0.9653235 | I19: ='Input data'!I26 -> 0.9508152 | J19: ='Input data'!J26 -> 0.9363069 | ... U19: ='Input data'!U26 -> 0.7767155
B21: GDP growth assumptions
B22: Actual GDP (real)
B23: Level | C23: ='Baseline NFPC'!C22 -> 6479.806 | D23: ='Baseline NFPC'!D22 -> 6596.2656 | E23: =IF(AND(E50>1,D50>1), IF(E$10<='Input data'!$C$4+2, E27*(1+('Baseline NFPC'!E$29+E51)/100)-D23*$C$47*(E12-D12)/100, E27*(1+E51/100)-D23*$C$47*(E12-D12)/100), IF(E50=1,E27,D23*(1+E52/100))) -> 6720.01 | F23: =IF(AND(F50>1,E50>1), IF(F$10<='Input data'!$C$4+2, F27*(1+('Baseline NFPC'!F$29+F51)/100)-E23*$C$47*(F12-E12)/100, F27*(1+F51/100)-E23*$C$47*(F12-E12)/100), IF(F50=1,F27,E23*(1+F52/100))) -> 6799.8872 | G23: =IF(AND(G50>1,F50>1), IF(G$10<='Input data'!$C$4+2, G27*(1+('Baseline NFPC'!G$29+G51)/100)-F23*$C$47*(G12-F12)/100, G27*(1+G51/100)-F23*$C$47*(G12-F12)/100), IF(G50=1,G27,F23*(1+G52/100))) -> 6871.6851 | H23: =IF(AND(H50>1,G50>1), H27*(1+H51/100)-G23*$C$47*(H12-G12)/100, IF(H50=1,H27,G23*(1+H52/100))) -> 6946.8455 | I23: =IF(AND(I50>1,H50>1), I27*(1+I51/100)-H23*$C$47*(I12-H12)/100, IF(I50=1,I27,H23*(1+I52/100))) -> 7045.7104 | J23: =IF(AND(J50>1,I50>1), J27*(1+J51/100)-I23*$C$47*(J12-I12)/100, IF(J50=1,J27,I23*(1+J52/100))) -> 7146.6739 | K23: =IF(AND(K50>1,J50>1), K27*(1+K51/100)-J23*$C$47*(K12-J12)/100, IF(K50=1,K27,J23*(1+K52/100))) -> 7249.6249 | L23: =IF(AND(L50>1,K50>1), L27*(1+L51/100)-K23*$C$47*(L12-K12)/100, IF(L50=1,L27,K23*(1+L52/100))) -> 7337.2908 | M23: =IF(AND(M50>1,L50>1), M27*(1+M51/100)-L23*$C$47*(M12-L12)/100, IF(M50=1,M27,L23*(1+M52/100))) -> 7420.9967 | N23: =IF(AND(N50>1,M50>1), N27*(1+N51/100)-M23*$C$47*(N12-M12)/100, IF(N50=1,N27,M23*(1+N52/100))) -> 7514.2948 | O23: =IF(AND(O50>1,N50>1), O27*(1+O51/100)-N23*$C$47*(O12-N12)/100, IF(O50=1,O27,N23*(1+O52/100))) -> 7617.512 | ... U23: =IF(AND(U50>1,T50>1), U27*(1+U51/100)-T23*$C$47*(U12-T12)/100, IF(U50=1,U27,T23*(1+U52/100))) -> 8363.8379
B24: Growth rate | C24: ='Baseline NFPC'!C23 -> 2.580467 | D24: ='Baseline NFPC'!D23 -> 1.79727 | E24: =100*(E23/D23-1) -> 1.875977 | F24: =100*(F23/E23-1) -> 1.188646 | G24: =100*(G23/F23-1) -> 1.0558694 | H24: =100*(H23/G23-1) -> 1.0937696 | I24: =100*(I23/H23-1) -> 1.4231627 | J24: =100*(J23/I23-1) -> 1.4329775 | K24: =100*(K23/J23-1) -> 1.4405454 | L24: =100*(L23/K23-1) -> 1.209247 | ... U24: =100*(U23/T23-1) -> 1.61
B26: Potential GDP (real)
B27: Level | C27: ='Input data'!C34 -> 6515.4565 | D27: =+C27*(1+'Input data'!D33/100) -> 6622.8091 | E27: =+D27*(1+'Input data'!E33/100) -> 6721.6283 | F27: =+E27*(1+'Input data'!F33/100) -> 6819.529 | G27: =+F27*(1+'Input data'!G33/100) -> 6903.7089 | H27: =+G27*(1+'Input data'!H33/100) -> 6987.4195 | I27: =+H27*(1+'Input data'!I33/100) -> 7073.0914 | J27: =+I27*(1+'Input data'!J33/100) -> 7160.5336 | K27: =+J27*(1+'Input data'!K33/100) -> 7249.6249 | ... U27: =+T27*(1+'Input data'!U33/100) -> 8363.8361
B29: Output gap
B30: Output gap | C30: =100*(C23/C27-1) -> -0.54716846 | D30: =100*(D23/D27-1) -> -0.40078891 | E30: =100*(E23/E27-1) -> -0.024075392 | F30: =100*(F23/F27-1) -> -0.28802253 | G30: =100*(G23/G27-1) -> -0.46386438 | H30: =100*(H23/H27-1) -> -0.58067146 | I30: =100*(I23/I27-1) -> -0.38711431 | J30: =100*(J23/J27-1) -> -0.19355715 | ... U30: =100*(U23/U27-1) -> 2.1710351e-05
B32: Actual GDP (nominal, national currency)
B33: Growth rate | C33: =100*((1+C24/100)*(1+C42/100)-1) -> 6.1837136 | D33: =100*((1+D24/100)*(1+D42/100)-1) -> 4.5016947 | E33: =100*((1+E24/100)*(1+E42/100)-1) -> 5.0022084 | F33: =100*((1+F24/100)*(1+F42/100)-1) -> 4.2016199 | G33: =100*((1+G24/100)*(1+G42/100)-1) -> 3.972845 | H33: =100*((1+H24/100)*(1+H42/100)-1) -> 3.91976 | I33: =100*((1+I24/100)*(1+I42/100)-1) -> 4.1659817 | J33: =100*((1+J24/100)*(1+J42/100)-1) -> 4.0836738 | ... U33: =100*((1+U24/100)*(1+U42/100)-1) -> 3.8494844
B35: Interest rates
B36: Nominal implicit interest rate on debt | C36: ='Input data'!C37 -> 3.196961 | D36: ='Input data'!D37 -> 3.078103 | E36: =IF(E$10<='Input data'!$C$4+2,'Input data'!E37,E99) -> 2.999835 | F36: =IF(F$10<='Input data'!$C$4+2,'Input data'!F37,F99) -> 3.2612235 | G36: =IF(G$10<='Input data'!$C$4+2,'Input data'!G37,G99) -> 3.466152 | H36: =H99 -> 3.6527919 | I36: =I99 -> 3.8227404 | J36: =J99 -> 3.9924506 | K36: =K99 -> 4.1585065 | L36: =L99 -> 4.3211098 | M36: =M99 -> 4.4916417 | N36: =N99 -> 4.6319413 | O36: =O99 -> 4.748543 | ... U36: =U99 -> 5.025283
B37: Long-term interest rate | C37: ='Input data'!C$39 -> 4.29 | D37: ='Input data'!D$39 -> 4.701964 | E37: ='Baseline NFPC'!E36 -> 4.915649 | F37: ='Baseline NFPC'!F36 -> 5.0370066 | G37: ='Baseline NFPC'!G36 -> 5.1583642 | H37: ='Baseline NFPC'!H36 -> 5.2797219 | I37: ='Baseline NFPC'!I36 -> 5.4010795 | J37: ='Baseline NFPC'!J36 -> 5.5224371 | K37: ='Baseline NFPC'!K36 -> 5.6437948 | L37: ='Baseline NFPC'!L36 -> 5.7651524 | ... U37: ='Baseline NFPC'!U36 -> 5.131906
B38: Short-term interest rate | C38: ='Input data'!C$38 -> 3.6 | D38: ='Input data'!D$38 -> 3.649853 | E38: ='Baseline NFPC'!E37 -> 4.267191 | F38: ='Baseline NFPC'!F37 -> 4.2826609 | G38: ='Baseline NFPC'!G37 -> 4.2981308 | H38: ='Baseline NFPC'!H37 -> 4.3136006 | I38: ='Baseline NFPC'!I37 -> 4.3290705 | J38: ='Baseline NFPC'!J37 -> 4.3445404 | K38: ='Baseline NFPC'!K37 -> 4.3600103 | L38: ='Baseline NFPC'!L37 -> 4.3754801 | ... U38: ='Baseline NFPC'!U37 -> 3.43457
B39: Share of long-term debt that matures every year | C39: ='Baseline NFPC'!C38 -> 0.06796828 | D39: ='Baseline NFPC'!D38 -> 0.06823518 | E39: ='Baseline NFPC'!E38 -> 0.06905882 | F39: ='Baseline NFPC'!F38 -> 0.069882459 | G39: ='Baseline NFPC'!G38 -> 0.070706098 | H39: ='Baseline NFPC'!H38 -> 0.071529736 | I39: ='Baseline NFPC'!I38 -> 0.072353375 | J39: ='Baseline NFPC'!J38 -> 0.073177014 | ... U39: ='Baseline NFPC'!U38 -> 0.07564793
B41: Inflation and exchange rate
B42: GDP deflator (National currency) | C42: ='Input data'!C42 -> 3.512605 | D42: ='Input data'!D42 -> 2.656677 | E42: ='Baseline NFPC'!E41 -> 3.068664 | F42: ='Baseline NFPC'!F41 -> 2.977581 | G42: ='Baseline NFPC'!G41 -> 2.886498 | H42: ='Baseline NFPC'!H41 -> 2.795415 | I42: ='Baseline NFPC'!I41 -> 2.704332 | J42: ='Baseline NFPC'!J41 -> 2.613249 | K42: ='Baseline NFPC'!K41 -> 2.522166 | L42: ='Baseline NFPC'!L41 -> 2.431083 | ... U42: ='Baseline NFPC'!U41 -> 2.204
B43: Exchange rate composite change (weighted by share of debt in each currency) | C43: ='Baseline NFPC'!C42 -> 0.9986759 | D43: ='Baseline NFPC'!D42 -> 0.9989123 | E43: ='Baseline NFPC'!E42 -> 0.9999991 | F43: ='Baseline NFPC'!F42 -> 1 | G43: ='Baseline NFPC'!G42 -> 1 | H43: ='Baseline NFPC'!H42 -> 1 | I43: ='Baseline NFPC'!I42 -> 1 | J43: ='Baseline NFPC'!J42 -> 1 | ... U43: ='Baseline NFPC'!U42 -> 1
B45: Intermediate calculations (growth rate equation)
B47: Fiscal multiplier | C47: ='Input data'!C49 -> 0.6
B48: Budget balance semi-elasticity | C48: ='Input data'!C50 -> 0.395
B50: Auxiliary variable to control the closure of the output gap | C50: 0 | D50: =IF(AND(ABS((D12-C12)-('Input data'!D13-'Input data'!C13))>0.0001,ABS(D12-C12)>0.0001,D$10>$C$5),4,IF(C50=4,3,IF(C50=3,2,IF(C50=2,1,0)))) -> 0 | E50: =IF(AND(ABS((E12-D12)-('Baseline NFPC'!E12-'Baseline NFPC'!D12))>0.0001,ABS(E12-D12)>0.0001,E$10>$C$5),4,IF(D50=4,3,IF(D50=3,2,IF(D50=2,1,0)))) -> 4 | F50: =IF(AND(ABS((F12-E12)-('Baseline NFPC'!F12-'Baseline NFPC'!E12))>0.0001,ABS(F12-E12)>0.0001,F$10>$C$5),4,IF(E50=4,3,IF(E50=3,2,IF(E50=2,1,0)))) -> 4 | G50: =IF(AND(ABS((G12-F12)-('Baseline NFPC'!G12-'Baseline NFPC'!F12))>0.0001,ABS(G12-F12)>0.0001,G$10>$C$5),4,IF(F50=4,3,IF(F50=3,2,IF(F50=2,1,0)))) -> 4 | H50: =IF(AND(ABS((H12-G12)-('Baseline NFPC'!H12-'Baseline NFPC'!G12))>0.0001,ABS(H12-G12)>0.0001,H$10>$C$5),4,IF(G50=4,3,IF(G50=3,2,IF(G50=2,1,0)))) -> 4 | I50: =IF(AND(ABS((I12-H12)-('Baseline NFPC'!I12-'Baseline NFPC'!H12))>0.0001,ABS(I12-H12)>0.0001,I$10>$C$5),4,IF(H50=4,3,IF(H50=3,2,IF(H50=2,1,0)))) -> 3 | J50: =IF(AND(ABS((J12-I12)-('Baseline NFPC'!J12-'Baseline NFPC'!I12))>0.0001,ABS(J12-I12)>0.0001,J$10>$C$5),4,IF(I50=4,3,IF(I50=3,2,IF(I50=2,1,0)))) -> 2 | K50: =IF(AND(ABS((K12-J12)-('Baseline NFPC'!K12-'Baseline NFPC'!J12))>0.0001,ABS(K12-J12)>0.0001,K$10>$C$5),4,IF(J50=4,3,IF(J50=3,2,IF(J50=2,1,0)))) -> 1 | L50: =IF(AND(ABS((L12-K12)-('Baseline NFPC'!L12-'Baseline NFPC'!K12))>0.0001,ABS(L12-K12)>0.0001,L$10>$C$5),4,IF(K50=4,3,IF(K50=3,2,IF(K50=2,1,0)))) -> 0 | ... U50: =IF(AND(ABS((U12-T12)-('Baseline NFPC'!U12-'Baseline NFPC'!T12))>0.0001,ABS(U12-T12)>0.0001,U$10>$C$5),4,IF(T50=4,3,IF(T50=3,2,IF(T50=2,1,0)))) -> 0
B51: OG intermediate auxiliary value | C51: 0 | D51: 0 | E51: =IF(D50=4, IF(E$10<='Input data'!$C$4+2,2/3*(D30-'Baseline NFPC'!D29),2/3*D30), IF(D50=3, IF(E$10<='Input data'!$C$4+2,1/3*(C30-'Baseline NFPC'!C29),1/3*C30), 0)) -> 0 | F51: =IF(E50=4, IF(F$10<='Input data'!$C$4+2,2/3*(E30-'Baseline NFPC'!E29),2/3*E30), IF(E50=3, IF(F$10<='Input data'!$C$4+2,1/3*(D30-'Baseline NFPC'!D29),1/3*D30), 0)) -> -0.016050261 | G51: =IF(F50=4, IF(G$10<='Input data'!$C$4+2,2/3*(F30-'Baseline NFPC'!F29),2/3*F30), IF(F50=3, IF(G$10<='Input data'!$C$4+2,1/3*(E30-'Baseline NFPC'!E29),1/3*E30), 0)) -> -0.19201502 | H51: =IF(G50=4,2/3*G30,IF(G50=3,1/3*F30,0)) -> -0.30924292 | I51: =IF(H50=4,2/3*H30,IF(H50=3,1/3*G30,0)) -> -0.38711431 | J51: =IF(I50=4,2/3*I30,IF(I50=3,1/3*H30,0)) -> -0.19355715 | K51: =IF(J50=4,2/3*J30,IF(J50=3,1/3*I30,0)) -> 0 | L51: =IF(K50=4,2/3*K30,IF(K50=3,1/3*J30,0)) -> 0 | M51: =IF(L50=4,2/3*L30,IF(L50=3,1/3*K30,0)) -> 0 | N51: =IF(M50=4,2/3*M30,IF(M50=3,1/3*L30,0)) -> 0 | O51: =IF(N50=4,2/3*N30,IF(N50=3,1/3*M30,0)) -> 0 | ... U51: =IF(T50=4,2/3*T30,IF(T50=3,1/3*S30,0)) -> 0
B52: GDP intermediate growth rate - only feedback effect and no closure of the OG | C52: 0 | D52: ='Input data'!D30-$C$47*((D12-C12)-('Input data'!D13-'Input data'!C13)) -> 1.79727 | E52: ='Input data'!E30-$C$47*(E12-D12) -> 1.875977 | F52: ='Input data'!F30-$C$47*(F12-E12) -> 1.097251 | G52: ='Input data'!G30-$C$47*(G12-F12) -> 0.847538 | H52: ='Input data'!H30-$C$47*(H12-G12) -> 0.881076 | I52: ='Input data'!I30-$C$47*(I12-H12) -> 1.226085 | J52: ='Input data'!J30-$C$47*(J12-I12) -> 1.236268 | K52: ='Input data'!K30-$C$47*(K12-J12) -> 1.244196 | L52: ='Input data'!L30-$C$47*(L12-K12) -> 1.209247 | ... U52: ='Input data'!U30-$C$47*(U12-T12) -> 1.61
B54: Debt projections
C56: ='Input data'!$C$5-1 -> 2025 | D56: =C56+1 -> 2026 | E56: =D56+1 -> 2027 | F56: =E56+1 -> 2028 | G56: =F56+1 -> 2029 | H56: =G56+1 -> 2030 | I56: =H56+1 -> 2031 | J56: =I56+1 -> 2032 | K56: =J56+1 -> 2033 | ... U56: =T56+1 -> 2043
B57: Gross debt | C57: =+'Input data'!C12 -> 44.25023 | D57: =+C57+D58 -> 45.838496 | E57: =+D57+E58 -> 46.696592 | F57: =+E57+F58 -> 46.801694 | G57: =+F57+G58 -> 46.709599 | H57: =+G57+H58 -> 46.311727 | I57: =+H57+I58 -> 45.919301 | J57: =+I57+J58 -> 45.577286 | K57: =+J57+K58 -> 45.283454 | ... U57: =+T57+U58 -> 54.272639
B58: Change in debt (-1+2+3) | D58: =-D59+D67+D72 -> 1.5882664 | E58: =-E59+E67+E72 -> 0.85809545 | F58: =-F59+F67+F72 -> 0.10510172 | G58: =-G59+G67+G72 -> -0.092094248 | H58: =-H59+H67+H72 -> -0.39787194 | I58: =-I59+I67+I72 -> -0.3924261 | J58: =-J59+J67+J72 -> -0.34201487 | K58: =-K59+K67+K72 -> -0.29383227 | ... U58: =-U59+U67+U72 -> 1.5779749
B59: (1) Primary balance (1.1 + 1.2 - 1.3 -1.4 -1.5 - 1.6 -1.7) | D59: =D60+D61-D62-D63-D64-D65-D66 -> -1.4910706 | E59: =E60+E61-E62-E63-E64-E65-E66 -> -0.88226878 | F59: =F60+F61-F62-F63-F64-F65-F66 -> -0.5265279 | G59: =G60+G61-G62-G63-G64-G65-G66 -> -0.13598543 | H59: =H60+H61-H62-H63-H64-H65-H66 -> 0.27787577 | I59: =I60+I61-I62-I63-I64-I65-I66 -> 0.23982255 | J59: =J60+J61-J62-J63-J64-J65-J66 -> 0.30176932 | K59: =K60+K61-K62-K63-K64-K65-K66 -> 0.3637161 | ... U59: =U60+U61-U62-U63-U64-U65-U66 -> -0.98135842
B60: (1.1) Structural primary balance (before ageing cost) | D60: =D12 -> -1.332759 | E60: =IF(E12="",D60,E12) -> -0.872759 | F60: =IF(F12="",E60,F12) -> -0.412759 | G60: =IF(G12="",F60,G12) -> 0.047241 | H60: =IF(H12="",G60,H12) -> 0.507241 | I60: =IF(I12="",H60,I12) -> 0.507241 | J60: =IF(J12="",I60,J12) -> 0.507241 | K60: =IF(K12="",J60,K12) -> 0.507241 | L60: =IF(L12="",K60,L12) -> 0.507241 | ... U60: =IF(U12="",T60,U12) -> 0.507241
B61: (1.2) Cumulated budgetary effort (in terms of primary balance) | D61: 0 | E61: 0 | F61: 0 | G61: 0 | H61: 0 | I61: 0 | J61: 0 | K61: 0 | L61: 0 | M61: 0 | N61: 0 | O61: 0 | P61: 0 | Q61: 0 | R61: 0 | S61: 0 | T61: 0 | U61: 0
B62: (1.3) Cyclical component | D62: =-$C$48*D30 -> 0.15831162 | E62: =-$C$48*E30 -> 0.0095097798 | F62: =-$C$48*F30 -> 0.1137689 | G62: =-$C$48*G30 -> 0.18322643 | H62: =-$C$48*H30 -> 0.22936523 | I62: =-$C$48*I30 -> 0.15291015 | J62: =-$C$48*J30 -> 0.076455076 | K62: =-$C$48*K30 -> 0 | ... U62: =-$C$48*U30 -> -8.5755887e-06
B63: (1.4) One-off and other temporary measures | D63: =-D14 -> 0 | E63: =-E14 -> 0 | F63: =-F14 -> 0 | G63: =-G14 -> 0 | H63: =-H14 -> 0 | I63: =-I14 -> 0 | J63: =-J14 -> 0 | K63: =-K14 -> 0 | ... U63: =-U14 -> 0
B64: (1.5) Cost of ageing | D64: =IF(D$56<=$C$6,0,HLOOKUP(D$56,'Input data'!$C$9:$AZ$26,12,FALSE)-HLOOKUP($C$6,'Input data'!$C$9:$AZ$26,12,FALSE)) -> 0 | E64: =IF(E$56<=$C$6,0,HLOOKUP(E$56,'Input data'!$C$9:$AZ$26,12,FALSE)-HLOOKUP($C$6,'Input data'!$C$9:$AZ$26,12,FALSE)) -> 0 | F64: =IF(F$56<=$C$6,0,HLOOKUP(F$56,'Input data'!$C$9:$AZ$26,12,FALSE)-HLOOKUP($C$6,'Input data'!$C$9:$AZ$26,12,FALSE)) -> 0 | G64: =IF(G$56<=$C$6,0,HLOOKUP(G$56,'Input data'!$C$9:$AZ$26,12,FALSE)-HLOOKUP($C$6,'Input data'!$C$9:$AZ$26,12,FALSE)) -> 0 | H64: =IF(H$56<=$C$6,0,HLOOKUP(H$56,'Input data'!$C$9:$AZ$26,12,FALSE)-HLOOKUP($C$6,'Input data'!$C$9:$AZ$26,12,FALSE)) -> 0 | I64: =IF(I$56<=$C$6,0,HLOOKUP(I$56,'Input data'!$C$9:$AZ$26,12,FALSE)-HLOOKUP($C$6,'Input data'!$C$9:$AZ$26,12,FALSE)) -> 0.1 | J64: =IF(J$56<=$C$6,0,HLOOKUP(J$56,'Input data'!$C$9:$AZ$26,12,FALSE)-HLOOKUP($C$6,'Input data'!$C$9:$AZ$26,12,FALSE)) -> 0.1 | K64: =IF(K$56<=$C$6,0,HLOOKUP(K$56,'Input data'!$C$9:$AZ$26,12,FALSE)-HLOOKUP($C$6,'Input data'!$C$9:$AZ$26,12,FALSE)) -> 0.1 | ... U64: =IF(U$56<=$C$6,0,HLOOKUP(U$56,'Input data'!$C$9:$AZ$26,12,FALSE)-HLOOKUP($C$6,'Input data'!$C$9:$AZ$26,12,FALSE)) -> 1.3
B65: (1.6) Property incomes | D65: =IF(D$56<=$C$5,0,-HLOOKUP(D$56,'Input data'!$C$9:$AZ$26,18,FALSE)+HLOOKUP($C$6,'Input data'!$C$9:$AZ$26,18,FALSE)) -> 0 | E65: =IF(E$56<=$C$6,0,-HLOOKUP(E$56,'Input data'!$C$9:$AZ$26,18,FALSE)+HLOOKUP($C$6,'Input data'!$C$9:$AZ$26,18,FALSE)) -> 0 | F65: =IF(F$56<=$C$6,0,-HLOOKUP(F$56,'Input data'!$C$9:$AZ$26,18,FALSE)+HLOOKUP($C$6,'Input data'!$C$9:$AZ$26,18,FALSE)) -> 0 | G65: =IF(G$56<=$C$6,0,-HLOOKUP(G$56,'Input data'!$C$9:$AZ$26,18,FALSE)+HLOOKUP($C$6,'Input data'!$C$9:$AZ$26,18,FALSE)) -> 0 | H65: =IF(H$56<=$C$6,0,-HLOOKUP(H$56,'Input data'!$C$9:$AZ$26,18,FALSE)+HLOOKUP($C$6,'Input data'!$C$9:$AZ$26,18,FALSE)) -> 0 | I65: =IF(I$56<=$C$6,0,-HLOOKUP(I$56,'Input data'!$C$9:$AZ$26,18,FALSE)+HLOOKUP($C$6,'Input data'!$C$9:$AZ$26,18,FALSE)) -> 0.0145083 | J65: =IF(J$56<=$C$6,0,-HLOOKUP(J$56,'Input data'!$C$9:$AZ$26,18,FALSE)+HLOOKUP($C$6,'Input data'!$C$9:$AZ$26,18,FALSE)) -> 0.0290166 | K65: =IF(K$56<=$C$6,0,-HLOOKUP(K$56,'Input data'!$C$9:$AZ$26,18,FALSE)+HLOOKUP($C$6,'Input data'!$C$9:$AZ$26,18,FALSE)) -> 0.0435249 | L65: =IF(L$56<=$C$6,0,-HLOOKUP(L$56,'Input data'!$C$9:$AZ$26,18,FALSE)+HLOOKUP($C$6,'Input data'!$C$9:$AZ$26,18,FALSE)) -> 0.0580332 | ... U65: =IF(U$56<=$C$6,0,-HLOOKUP(U$56,'Input data'!$C$9:$AZ$26,18,FALSE)+HLOOKUP($C$6,'Input data'!$C$9:$AZ$26,18,FALSE)) -> 0.188608
B66: (1.7) Revenues | D66: 0 | E66: 0 | F66: 0 | G66: 0 | H66: 0 | I66: 0 | J66: 0 | K66: 0 | L66: 0 | M66: 0 | N66: 0 | O66: 0 | P66: 0 | Q66: 0 | R66: 0 | S66: 0 | T66: 0 | U66: 0
B67: (2) Snowball effect (2.1 + 2.2 + 2.3) | D67: =SUM(D68:D71) -> -0.6042236 | E67: =SUM(E68:E71) -> -0.87413323 | F67: =SUM(F68:F71) -> -0.42142618 | G67: =SUM(G68:G71) -> -0.22807968 | H67: =SUM(H68:H71) -> -0.11999616 | I67: =SUM(I68:I71) -> -0.15260355 | J67: =SUM(J68:J71) -> -0.040245547 | K67: =SUM(K68:K71) -> 0.069883826 | ... U67: =SUM(U68:U71) -> 0.59661648
B68: (2.1) Interest expenditure | D68: =C57*D36/100*(1/(1+D33/100)) -> 1.3033929 | E68: =D57*E36/100*(1/(1+E33/100)) -> 1.3095718 | F68: =E57*F36/100*(1/(1+F33/100)) -> 1.4614746 | G68: =F57*G36/100*(1/(1+G33/100)) -> 1.5602322 | H68: =G57*H36/100*(1/(1+H33/100)) -> 1.641848 | I68: =H57*I36/100*(1/(1+I33/100)) -> 1.6995732 | J68: =I57*J36/100*(1/(1+J33/100)) -> 1.7613766 | K68: =J57*K36/100*(1/(1+K33/100)) -> 1.8224537 | ... U68: =T57*U36/100*(1/(1+U33/100)) -> 2.5498981
B69: (2.2) Growth effect | D69: =-C57*(D24/100)*(1/(1+D33/100)) -> -0.76103657 | E69: =-D57*(E24/100)*(1/(1+E33/100)) -> -0.81895387 | F69: =-E57*(F24/100)*(1/(1+F33/100)) -> -0.53267613 | G69: =-F57*(G24/100)*(1/(1+G33/100)) -> -0.47528251 | H69: =-G57*(H24/100)*(1/(1+H33/100)) -> -0.49162489 | I69: =-H57*(I24/100)*(1/(1+I33/100)) -> -0.63273174 | J69: =-I57*(J24/100)*(1/(1+J33/100)) -> -0.63219643 | K69: =-J57*(K24/100)*(1/(1+K33/100)) -> -0.63131495 | ... U69: =-T57*(U24/100)*(1/(1+U33/100)) -> -0.81693625
B70: (2.3) Inflation effect | D70: =-C57*D42/100*(1/(1+D42/100)) -> -1.1451624 | E70: =-D57*E42/100*(1/(1+E42/100)) -> -1.3647499 | F70: =-E57*F42/100*(1/(1+F42/100)) -> -1.3502248 | G70: =-F57*G42/100*(1/(1+G42/100)) -> -1.3130294 | H70: =-G57*H42/100*(1/(1+H42/100)) -> -1.2702192 | I70: =-H57*I42/100*(1/(1+I42/100)) -> -1.219445 | J70: =-I57*J42/100*(1/(1+J42/100)) -> -1.1694257 | K70: =-J57*K42/100*(1/(1+K42/100)) -> -1.1212549 | ... U70: =-T57*U42/100*(1/(1+U42/100)) -> -1.1363453
B71: (2.4) Exchange rate effect linked to the interest rate | D71: ='Baseline NFPC'!D70 -> -0.0014175065 | E71: ='Baseline NFPC'!E70 -> -1.2590616e-06 | F71: ='Baseline NFPC'!F70 -> 1.4316675e-07 | G71: 0 | H71: 0 | I71: 0 | J71: 0 | K71: 0 | L71: 0 | M71: 0 | N71: 0 | O71: 0 | P71: 0 | Q71: 0 | R71: 0 | S71: 0 | T71: 0 | U71: 0
B72: (3 ) Stock flow adjustments (3.1 + 3.2) | D72: ='Input data'!D16 -> 0.7014194 | E72: ='Input data'!E16 -> 0.8499599 | F72: ='Input data'!F16 -> 0 | G72: ='Input data'!G16 -> 0 | H72: ='Input data'!H16 -> 0 | I72: ='Input data'!I16 -> 0 | J72: ='Input data'!J16 -> 0 | K72: ='Input data'!K16 -> 0 | ... U72: ='Input data'!U16 -> 0
B73: (3.1) Base | D73: =D15 -> 0.7474777 | E73: =E15 -> 0.85 | F73: =F15 -> 0 | G73: =G15 -> 0 | H73: =H15 -> 0 | I73: =I15 -> 0 | J73: =J15 -> 0 | K73: =K15 -> 0 | ... U73: =U15 -> 0
B74: (3.2) Adjustment due to the exchange rate effect linked to debt value | D74: =+D72-D73 -> -0.0460583 | E74: =+E72-E73 -> -4.01e-05 | F74: =+F72-F73 -> 0 | G74: =+G72-G73 -> 0 | H74: =+H72-H73 -> 0 | I74: =+I72-I73 -> 0 | J74: =+J72-J73 -> 0 | K74: =+K72-K73 -> 0 | ... U74: =+U72-U73 -> 0
B76: Other budgetary variables
B77: Headline balance | C77: ='Baseline NFPC'!C76 -> -2.147432 | D77: =D59-D68 -> -2.7944635 | E77: =E59-E68 -> -2.1918405 | F77: =F59-F68 -> -1.9880025 | G77: =G59-G68 -> -1.6962176 | H77: =H59-H68 -> -1.3639722 | I77: =I59-I68 -> -1.4597507 | J77: =J59-J68 -> -1.4596072 | K77: =K59-K68 -> -1.4587376 | ... U77: =U59-U68 -> -3.5312565
B78: Structural balance | C78: ='Baseline NFPC'!C77 -> -1.81443 | D78: =D60-D68-D71-D64-D65-D66 -> -2.6347344 | E78: =E60-E68-E71-E64-E65-E66 -> -2.1823295 | F78: =F60-F68-F71-F64-F65-F66 -> -1.8742338 | G78: =G60-G68-G71-G64-G65-G66 -> -1.5129912 | H78: =H60-H68-H71-H64-H65-H66 -> -1.134607 | I78: =I60-I68-I71-I64-I65-I66 -> -1.3068405 | J78: =J60-J68-J71-J64-J65-J66 -> -1.3831522 | K78: =K60-K68-K71-K64-K65-K66 -> -1.4587376 | ... U78: =U60-U68-U71-U64-U65-U66 -> -3.5312651
B79: Net expenditure growth | C79: ='Input data'!C45 -> 4.9156095 | D79: ='Input data'!D45 -> 6.3502551 | E79: ='Input data'!E33+E42-(E$12-D$12-(E$64-D64))/'Input data'!$C$64*100 -> 3.4626987 | F79: ='Input data'!F33+F42-(F$12-E$12-(F$64-E64))/'Input data'!$C$64*100 -> 3.3360137 | G79: ='Input data'!G33+G42-(G$12-F$12-(G$64-F64))/'Input data'!$C$64*100 -> 3.0228247 | H79: ='Input data'!H33+H42-(H$12-G$12-(H$64-G64))/'Input data'!$C$64*100 -> 2.9098897 | I79: ='Input data'!I33+I42-(I$12-H$12-(I$64-H64))/'Input data'!$C$64*100 -> 4.1691307 | J79: ='Input data'!J33+J42-(J$12-I$12-(J$64-I64))/'Input data'!$C$64*100 -> 3.849515 | K79: ='Input data'!K33+K42-(K$12-J$12-(K$64-J64))/'Input data'!$C$64*100 -> 3.766366 | L79: ='Input data'!L33+L42-(L$12-K$12-(L$64-K64))/'Input data'!$C$64*100 -> 4.3564592 | ... U79: ='Input data'!U33+U42-(U$12-T$12-(U$64-T64))/'Input data'!$C$64*100 -> 4.0527107
B81: Average net expenditure growth over the adjustment period: | C81: =IF('Criteria results'!$F$5=4,AVERAGE(E79:H79),AVERAGE(E79:K79)) -> 3.1828567
B83: Debt decomposition and IIR
B85: Auxiliary variable identifying whether debt is increasing | D85: =IF((D90-C90*D43/((1+D24/100)*(1+D42/100)))>0,1,0) -> 1 | E85: =IF((E90-D90*E43/((1+E24/100)*(1+E42/100)))>0,1,0) -> 1 | F85: =IF((F90-E90*F43/((1+F24/100)*(1+F42/100)))>0,1,0) -> 1 | G85: =IF((G90-F90*G43/((1+G24/100)*(1+G42/100)))>0,1,0) -> 1 | H85: =IF((H90-G90*H43/((1+H24/100)*(1+H42/100)))>0,1,0) -> 1 | I85: =IF((I90-H90*I43/((1+I24/100)*(1+I42/100)))>0,1,0) -> 1 | J85: =IF((J90-I90*J43/((1+J24/100)*(1+J42/100)))>0,1,0) -> 1 | K85: =IF((K90-J90*K43/((1+K24/100)*(1+K42/100)))>0,1,0) -> 1 | ... U85: =IF((U90-T90*U43/((1+U24/100)*(1+U42/100)))>0,1,0) -> 1
B86: Auxiliary variable identifying whether some debt is rolled over even though debt is decreasing | D86: =IF(AND(D85=0,ABS(D90-C90*D43/((1+D24/100)*(1+D42/100)))<((C96*C90*D43/((1+D24/100)*(1+D42/100))+(D39*C90*C97*D43/((1+D24/100)*(1+D42/100)))))),1,0) -> 0 | E86: =IF(AND(E85=0,ABS(E90-D90*E43/((1+E24/100)*(1+E42/100)))<((D96*D90*E43/((1+E24/100)*(1+E42/100))+(E39*D90*D97*E43/((1+E24/100)*(1+E42/100)))))),1,0) -> 0 | F86: =IF(AND(F85=0,ABS(F90-E90*F43/((1+F24/100)*(1+F42/100)))<((E96*E90*F43/((1+F24/100)*(1+F42/100))+(F39*E90*E97*F43/((1+F24/100)*(1+F42/100)))))),1,0) -> 0 | G86: =IF(AND(G85=0,ABS(G90-F90*G43/((1+G24/100)*(1+G42/100)))<((F96*F90*G43/((1+G24/100)*(1+G42/100))+(G39*F90*F97*G43/((1+G24/100)*(1+G42/100)))))),1,0) -> 0 | H86: =IF(AND(H85=0,ABS(H90-G90*H43/((1+H24/100)*(1+H42/100)))<((G96*G90*H43/((1+H24/100)*(1+H42/100))+(H39*G90*G97*H43/((1+H24/100)*(1+H42/100)))))),1,0) -> 0 | I86: =IF(AND(I85=0,ABS(I90-H90*I43/((1+I24/100)*(1+I42/100)))<((H96*H90*I43/((1+I24/100)*(1+I42/100))+(I39*H90*H97*I43/((1+I24/100)*(1+I42/100)))))),1,0) -> 0 | J86: =IF(AND(J85=0,ABS(J90-I90*J43/((1+J24/100)*(1+J42/100)))<((I96*I90*J43/((1+J24/100)*(1+J42/100))+(J39*I90*I97*J43/((1+J24/100)*(1+J42/100)))))),1,0) -> 0 | K86: =IF(AND(K85=0,ABS(K90-J90*K43/((1+K24/100)*(1+K42/100)))<((J96*J90*K43/((1+K24/100)*(1+K42/100))+(K39*J90*J97*K43/((1+K24/100)*(1+K42/100)))))),1,0) -> 0 | ... U86: =IF(AND(U85=0,ABS(U90-T90*U43/((1+U24/100)*(1+U42/100)))<((T96*T90*U43/((1+U24/100)*(1+U42/100))+(U39*T90*T97*U43/((1+U24/100)*(1+U42/100)))))),1,0) -> 0
C89: ='Input data'!$C$5-1 -> 2025 | D89: =C89+1 -> 2026 | E89: =D89+1 -> 2027 | F89: =E89+1 -> 2028 | G89: =F89+1 -> 2029 | H89: =G89+1 -> 2030 | I89: =H89+1 -> 2031 | J89: =I89+1 -> 2032 | K89: =J89+1 -> 2033 | ... U89: =T89+1 -> 2043
B90: Gross debt | C90: =C57 -> 44.25023 | D90: =D57 -> 45.838496 | E90: =D90*(1+E104/100)*E43-E60-E61+E62+E63+E64+E65+E66+E73 -> 46.696593 | F90: =E90*(1+F104/100)*F43-F60-F61+F62+F63+F64+F65+F66+F73 -> 46.801694 | G90: =F90*(1+G104/100)*G43-G60-G61+G62+G63+G64+G65+G66+G73 -> 46.7096 | H90: =G90*(1+H104/100)*H43-H60-H61+H62+H63+H64+H65+H66+H73 -> 46.311728 | I90: =H90*(1+I104/100)*I43-I60-I61+I62+I63+I64+I65+I66+I73 -> 45.919302 | J90: =I90*(1+J104/100)*J43-J60-J61+J62+J63+J64+J65+J66+J73 -> 45.577287 | K90: =J90*(1+K104/100)*K43-K60-K61+K62+K63+K64+K65+K66+K73 -> 45.283455 | L90: =K90*(1+L104/100)*L43-L60-L61+L62+L63+L64+L65+L66+L73 -> 45.518773 | ... U90: =T90*(1+U104/100)*U43-U60-U61+U62+U63+U64+U65+U66+U73 -> 54.27264
B91: Of which Outstanding debt | C91: ='Baseline NFPC'!C88 -> 37.04973 | D91: ='Baseline NFPC'!D88 -> 38.429584 | E91: =IF(E90=0,0,IF(E85=1,D90*E43/((1+E24/100)*(1+E42/100))-E92-E93,IF(AND(E85=0,E86=1),(1-D96-E39*D97)*D90*E43/((1+E24/100)*(1+E42/100)),E90))) -> 39.58294 | F91: =IF(F90=0,0,IF(F85=1,E90*F43/((1+F24/100)*(1+F42/100))-F92-F93,IF(AND(F85=0,F86=1),(1-E96-F39*E97)*E90*F43/((1+F24/100)*(1+F42/100)),F90))) -> 40.562487 | G91: =IF(G90=0,0,IF(G85=1,F90*G43/((1+G24/100)*(1+G42/100))-G92-G93,IF(AND(G85=0,G86=1),(1-F96-G39*F97)*F90*G43/((1+G24/100)*(1+G42/100)),G90))) -> 40.685533 | H91: =IF(H90=0,0,IF(H85=1,G90*H43/((1+H24/100)*(1+H42/100))-H92-H93,IF(AND(H85=0,H86=1),(1-G96-H39*G97)*G90*H43/((1+H24/100)*(1+H42/100)),H90))) -> 40.572551 | I91: =IF(I90=0,0,IF(I85=1,H90*I43/((1+I24/100)*(1+I42/100))-I92-I93,IF(AND(I85=0,I86=1),(1-H96-I39*H97)*H90*I43/((1+I24/100)*(1+I42/100)),I90))) -> 40.082628 | J91: =IF(J90=0,0,IF(J85=1,I90*J43/((1+J24/100)*(1+J42/100))-J92-J93,IF(AND(J85=0,J86=1),(1-I96-J39*I97)*I90*J43/((1+J24/100)*(1+J42/100)),J90))) -> 39.724933 | K91: =IF(K90=0,0,IF(K85=1,J90*K43/((1+K24/100)*(1+K42/100))-K92-K93,IF(AND(K85=0,K86=1),(1-J96-K39*J97)*J90*K43/((1+K24/100)*(1+K42/100)),K90))) -> 39.412359 | L91: =IF(L90=0,0,IF(L85=1,K90*L43/((1+L24/100)*(1+L42/100))-L92-L93,IF(AND(L85=0,L86=1),(1-K96-L39*K97)*K90*L43/((1+L24/100)*(1+L42/100)),L90))) -> 39.234425 | ... U91: =IF(U90=0,0,IF(U85=1,T90*U43/((1+U24/100)*(1+U42/100))-U92-U93,IF(AND(U85=0,U86=1),(1-T96-U39*T97)*T90*U43/((1+U24/100)*(1+U42/100)),U90))) -> 45.35844
B92: Rolled over long-term debt | C92: ='Baseline NFPC'!C89 -> 2.701846 | D92: ='Baseline NFPC'!D89 -> 2.8142827 | E92: =IF(E90=0,0,IF(E85=1,E39*D90*D97*E43/((1+E24/100)*(1+E42/100)),IF(AND(E85=0,E86=1),(E39*D90*D97*E43/((1+E24/100)*(1+E42/100)))*(1-ABS(E90-D90*E43/((1+E24/100)*(1+E42/100)))/((E39*D90*D97*E43/((1+E24/100)*(1+E42/100)))+(D96*D90*E43/((1+E24/100)*(1+E42/100))))),0))) -> 2.9363306 | F92: =IF(F90=0,0,IF(F85=1,F39*E90*E97*F43/((1+F24/100)*(1+F42/100)),IF(AND(F85=0,F86=1),(F39*E90*E97*F43/((1+F24/100)*(1+F42/100)))*(1-ABS(F90-E90*F43/((1+F24/100)*(1+F42/100)))/((F39*E90*E97*F43/((1+F24/100)*(1+F42/100)))+(E96*E90*F43/((1+F24/100)*(1+F42/100))))),0))) -> 3.0475786 | G92: =IF(G90=0,0,IF(G85=1,G39*F90*F97*G43/((1+G24/100)*(1+G42/100)),IF(AND(G85=0,G86=1),(G39*F90*F97*G43/((1+G24/100)*(1+G42/100)))*(1-ABS(G90-F90*G43/((1+G24/100)*(1+G42/100)))/((G39*F90*F97*G43/((1+G24/100)*(1+G42/100)))+(F96*F90*G43/((1+G24/100)*(1+G42/100))))),0))) -> 3.0955926 | H92: =IF(H90=0,0,IF(H85=1,H39*G90*G97*H43/((1+H24/100)*(1+H42/100)),IF(AND(H85=0,H86=1),(H39*G90*G97*H43/((1+H24/100)*(1+H42/100)))*(1-ABS(H90-G90*H43/((1+H24/100)*(1+H42/100)))/((H39*G90*G97*H43/((1+H24/100)*(1+H42/100)))+(G96*G90*H43/((1+H24/100)*(1+H42/100))))),0))) -> 3.1257263 | I92: =IF(I90=0,0,IF(I85=1,I39*H90*H97*I43/((1+I24/100)*(1+I42/100)),IF(AND(I85=0,I86=1),(I39*H90*H97*I43/((1+I24/100)*(1+I42/100)))*(1-ABS(I90-H90*I43/((1+I24/100)*(1+I42/100)))/((I39*H90*H97*I43/((1+I24/100)*(1+I42/100)))+(H96*H90*I43/((1+I24/100)*(1+I42/100))))),0))) -> 3.1263127 | J92: =IF(J90=0,0,IF(J85=1,J39*I90*I97*J43/((1+J24/100)*(1+J42/100)),IF(AND(J85=0,J86=1),(J39*I90*I97*J43/((1+J24/100)*(1+J42/100)))*(1-ABS(J90-I90*J43/((1+J24/100)*(1+J42/100)))/((J39*I90*I97*J43/((1+J24/100)*(1+J42/100)))+(I96*I90*J43/((1+J24/100)*(1+J42/100))))),0))) -> 3.1364694 | K92: =IF(K90=0,0,IF(K85=1,K39*J90*J97*K43/((1+K24/100)*(1+K42/100)),IF(AND(K85=0,K86=1),(K39*J90*J97*K43/((1+K24/100)*(1+K42/100)))*(1-ABS(K90-J90*K43/((1+K24/100)*(1+K42/100)))/((K39*J90*J97*K43/((1+K24/100)*(1+K42/100)))+(J96*J90*K43/((1+K24/100)*(1+K42/100))))),0))) -> 3.1496138 | L92: =IF(L90=0,0,IF(L85=1,L39*K90*K97*L43/((1+L24/100)*(1+L42/100)),IF(AND(L85=0,L86=1),(L39*K90*K97*L43/((1+L24/100)*(1+L42/100)))*(1-ABS(L90-K90*L43/((1+L24/100)*(1+L42/100)))/((L39*K90*K97*L43/((1+L24/100)*(1+L42/100)))+(K96*K90*L43/((1+L24/100)*(1+L42/100))))),0))) -> 3.173114 | ... U92: =IF(U90=0,0,IF(U85=1,U39*T90*T97*U43/((1+U24/100)*(1+U42/100)),IF(AND(U85=0,U86=1),(U39*T90*T97*U43/((1+U24/100)*(1+U42/100)))*(1-ABS(U90-T90*U43/((1+U24/100)*(1+U42/100)))/((U39*T90*T97*U43/((1+U24/100)*(1+U42/100)))+(T96*T90*U43/((1+U24/100)*(1+U42/100))))),0))) -> 3.7120835
B93: Rolled over short-term debt | C93: ='Baseline NFPC'!C90 -> 0.9648441 | D93: ='Baseline NFPC'!D90 -> 1.0541067 | E93: =IF(E90=0,0,IF(E85=1,(1-D97)*D90*E43/((1+E24/100)*(1+E42/100)),IF(AND(E85=0,E86=1),(D96*D90*E43/((1+E24/100)*(1+E42/100)))*(1-ABS(E90-D90*E43/((1+E24/100)*(1+E42/100)))/((E39*D90*D97*E43/((1+E24/100)*(1+E42/100)))+(D96*D90*E43/((1+E24/100)*(1+E42/100))))),0))) -> 1.1354831 | F93: =IF(F90=0,0,IF(F85=1,(1-E97)*E90*F43/((1+F24/100)*(1+F42/100)),IF(AND(F85=0,F86=1),(E96*E90*F43/((1+F24/100)*(1+F42/100)))*(1-ABS(F90-E90*F43/((1+F24/100)*(1+F42/100)))/((F39*E90*E97*F43/((1+F24/100)*(1+F42/100)))+(E96*E90*F43/((1+F24/100)*(1+F42/100))))),0))) -> 1.2036258 | G93: =IF(G90=0,0,IF(G85=1,(1-F97)*F90*G43/((1+G24/100)*(1+G42/100)),IF(AND(G85=0,G86=1),(F96*F90*G43/((1+G24/100)*(1+G42/100)))*(1-ABS(G90-F90*G43/((1+G24/100)*(1+G42/100)))/((G39*F90*F97*G43/((1+G24/100)*(1+G42/100)))+(F96*F90*G43/((1+G24/100)*(1+G42/100))))),0))) -> 1.2322563 | H93: =IF(H90=0,0,IF(H85=1,(1-G97)*G90*H43/((1+H24/100)*(1+H42/100)),IF(AND(H85=0,H86=1),(G96*G90*H43/((1+H24/100)*(1+H42/100)))*(1-ABS(H90-G90*H43/((1+H24/100)*(1+H42/100)))/((H39*G90*G97*H43/((1+H24/100)*(1+H42/100)))+(G96*G90*H43/((1+H24/100)*(1+H42/100))))),0))) -> 1.2494784 | I93: =IF(I90=0,0,IF(I85=1,(1-H97)*H90*I43/((1+I24/100)*(1+I42/100)),IF(AND(I85=0,I86=1),(H96*H90*I43/((1+I24/100)*(1+I42/100)))*(1-ABS(I90-H90*I43/((1+I24/100)*(1+I42/100)))/((I39*H90*H97*I43/((1+I24/100)*(1+I42/100)))+(H96*H90*I43/((1+I24/100)*(1+I42/100))))),0))) -> 1.2506102 | J93: =IF(J90=0,0,IF(J85=1,(1-I97)*I90*J43/((1+J24/100)*(1+J42/100)),IF(AND(J85=0,J86=1),(I96*I90*J43/((1+J24/100)*(1+J42/100)))*(1-ABS(J90-I90*J43/((1+J24/100)*(1+J42/100)))/((J39*I90*I97*J43/((1+J24/100)*(1+J42/100)))+(I96*I90*J43/((1+J24/100)*(1+J42/100))))),0))) -> 1.2562779 | K93: =IF(K90=0,0,IF(K85=1,(1-J97)*J90*K43/((1+K24/100)*(1+K42/100)),IF(AND(K85=0,K86=1),(J96*J90*K43/((1+K24/100)*(1+K42/100)))*(1-ABS(K90-J90*K43/((1+K24/100)*(1+K42/100)))/((K39*J90*J97*K43/((1+K24/100)*(1+K42/100)))+(J96*J90*K43/((1+K24/100)*(1+K42/100))))),0))) -> 1.2627446 | L93: =IF(L90=0,0,IF(L85=1,(1-K97)*K90*L43/((1+L24/100)*(1+L42/100)),IF(AND(L85=0,L86=1),(K96*K90*L43/((1+L24/100)*(1+L42/100)))*(1-ABS(L90-K90*L43/((1+L24/100)*(1+L42/100)))/((L39*K90*K97*L43/((1+L24/100)*(1+L42/100)))+(K96*K90*L43/((1+L24/100)*(1+L42/100))))),0))) -> 1.2729608 | ... U93: =IF(U90=0,0,IF(U85=1,(1-T97)*T90*U43/((1+U24/100)*(1+U42/100)),IF(AND(U85=0,U86=1),(T96*T90*U43/((1+U24/100)*(1+U42/100)))*(1-ABS(U90-T90*U43/((1+U24/100)*(1+U42/100)))/((U39*T90*T97*U43/((1+U24/100)*(1+U42/100)))+(T96*T90*U43/((1+U24/100)*(1+U42/100))))),0))) -> 1.6708595
B94: New long-term debt | C94: ='Baseline NFPC'!C91 -> 3.395897 | D94: ='Baseline NFPC'!D91 -> 3.4023463 | E94: =IF(E90=0,0,IF(E85=1,'Input data'!$C$58*(E90-D90*E43/((1+E24/100)*(1+E42/100))),0)) -> 2.9231249 | F94: =IF(F90=0,0,IF(F85=1,'Input data'!$C$58*(F90-E90*F43/((1+F24/100)*(1+F42/100))),0)) -> 1.9104164 | G94: =IF(G90=0,0,IF(G85=1,'Input data'!$C$58*(G90-F90*G43/((1+G24/100)*(1+G42/100))),0)) -> 1.630019 | H94: =IF(H90=0,0,IF(H85=1,'Input data'!$C$58*(H90-G90*H43/((1+H24/100)*(1+H42/100))),0)) -> 1.3107402 | I94: =IF(I90=0,0,IF(I85=1,'Input data'!$C$58*(I90-H90*I43/((1+I24/100)*(1+I42/100))),0)) -> 1.4027807 | J94: =IF(J90=0,0,IF(J85=1,'Input data'!$C$58*(J90-I90*J43/((1+J24/100)*(1+J42/100))),0)) -> 1.4026429 | K94: =IF(K90=0,0,IF(K85=1,'Input data'!$C$58*(K90-J90*K43/((1+K24/100)*(1+K42/100))),0)) -> 1.4018072 | L94: =IF(L90=0,0,IF(L85=1,'Input data'!$C$58*(L90-K90*L43/((1+L24/100)*(1+L42/100))),0)) -> 1.7665307 | ... U94: =IF(U90=0,0,IF(U85=1,'Input data'!$C$58*(U90-T90*U43/((1+U24/100)*(1+U42/100))),0)) -> 3.3934415
B95: New short-term debt | C95: ='Baseline NFPC'!C92 -> 0.1379148 | D95: ='Baseline NFPC'!D92 -> 0.1381767 | E95: =IF(E90=0,0,IF(E85=1,'Input data'!$C$57*(E90-D90*E43/((1+E24/100)*(1+E42/100))),0)) -> 0.11871447 | F95: =IF(F90=0,0,IF(F85=1,'Input data'!$C$57*(F90-E90*F43/((1+F24/100)*(1+F42/100))),0)) -> 0.077586173 | G95: =IF(G90=0,0,IF(G85=1,'Input data'!$C$57*(G90-F90*G43/((1+G24/100)*(1+G42/100))),0)) -> 0.066198626 | H95: =IF(H90=0,0,IF(H85=1,'Input data'!$C$57*(H90-G90*H43/((1+H24/100)*(1+H42/100))),0)) -> 0.053232017 | I95: =IF(I90=0,0,IF(I85=1,'Input data'!$C$57*(I90-H90*I43/((1+I24/100)*(1+I42/100))),0)) -> 0.056969982 | J95: =IF(J90=0,0,IF(J85=1,'Input data'!$C$57*(J90-I90*J43/((1+J24/100)*(1+J42/100))),0)) -> 0.056964385 | K95: =IF(K90=0,0,IF(K85=1,'Input data'!$C$57*(K90-J90*K43/((1+K24/100)*(1+K42/100))),0)) -> 0.056930445 | L95: =IF(L90=0,0,IF(L85=1,'Input data'!$C$57*(L90-K90*L43/((1+L24/100)*(1+L42/100))),0)) -> 0.071742662 | ... U95: =IF(U90=0,0,IF(U85=1,'Input data'!$C$57*(U90-T90*U43/((1+U24/100)*(1+U42/100))),0)) -> 0.13781506
B96: Share of short-term debt in total government debt | C96: ='Baseline NFPC'!C93 -> 0.024920974 | D96: ='Baseline NFPC'!D93 -> 0.026010526 | E96: =IF(E90<>0,(E93+E95)/(E91+E92+E93+E94+E95),0) -> 0.026858439 | F96: =IF(F90<>0,(F93+F95)/(F91+F92+F93+F94+F95),0) -> 0.027375333 | G96: =IF(G90<>0,(G93+G95)/(G91+G92+G93+G94+G95),0) -> 0.02779846 | H96: =IF(H90<>0,(H93+H95)/(H91+H92+H93+H94+H95),0) -> 0.028129169 | I96: =IF(I90<>0,(I93+I95)/(I91+I92+I93+I94+I95),0) -> 0.028475612 | J96: =IF(J90<>0,(J93+J95)/(J91+J92+J93+J94+J95),0) -> 0.028813525 | K96: =IF(K90<>0,(K93+K95)/(K91+K92+K93+K94+K95),0) -> 0.029142543 | L96: =IF(L90<>0,(L93+L95)/(L91+L92+L93+L94+L95),0) -> 0.029541735 | ... U96: =IF(U90<>0,(U93+U95)/(U91+U92+U93+U94+U95),0) -> 0.033325715
B97: Share of long-term debt in total government debt | C97: ='Baseline NFPC'!C94 -> 0.97507903 | D97: ='Baseline NFPC'!D94 -> 0.97398947 | E97: =IF(E90<>0,(E91+E92+E94)/(E91+E92+E93+E94+E95),1) -> 0.97314156 | F97: =IF(F90<>0,(F91+F92+F94)/(F91+F92+F93+F94+F95),1) -> 0.97262467 | G97: =IF(G90<>0,(G91+G92+G94)/(G91+G92+G93+G94+G95),1) -> 0.97220154 | H97: =IF(H90<>0,(H91+H92+H94)/(H91+H92+H93+H94+H95),1) -> 0.97187083 | I97: =IF(I90<>0,(I91+I92+I94)/(I91+I92+I93+I94+I95),1) -> 0.97152439 | J97: =IF(J90<>0,(J91+J92+J94)/(J91+J92+J93+J94+J95),1) -> 0.97118647 | K97: =IF(K90<>0,(K91+K92+K94)/(K91+K92+K93+K94+K95),1) -> 0.97085746 | L97: =IF(L90<>0,(L91+L92+L94)/(L91+L92+L93+L94+L95),1) -> 0.97045827 | ... U97: =IF(U90<>0,(U91+U92+U94)/(U91+U92+U93+U94+U95),1) -> 0.96667429
B99: IIR | C99: ='Baseline NFPC'!C96 -> 3.196961 | D99: ='Baseline NFPC'!D96 -> 3.078103 | E99: =E101+E102 -> 2.999835 | F99: =F101+F102 -> 3.2612235 | G99: =G101+G102 -> 3.466152 | H99: =H101+H102 -> 3.6527919 | I99: =I101+I102 -> 3.8227404 | J99: =J101+J102 -> 3.9924506 | K99: =K101+K102 -> 4.1585065 | L99: =L101+L102 -> 4.3211098 | ... U99: =U101+U102 -> 5.025283
B100: Long-term implicit interest rate | E100: =IF(D$10<'Input data'!$C$4+2,((E36*D90)-(E38*(D93+D95)))/(D91+D92+D94), IF(D$10>'Input data'!$C$4+2,IF(D90>0,(D100*D91+E37*(D94+D92))/(D91+D92+D94),E37), IF(D90>0,(D100*D91+ ('Baseline NFPC'!E97*('Baseline NFPC'!D88+'Baseline NFPC'!D89+'Baseline NFPC'!D91)-'Baseline NFPC'!D97*'Baseline NFPC'!D88)/('Baseline NFPC'!D89+'Baseline NFPC'!D91) *(D94+D92))/(D91+D92+D94),E37))) -> 2.9659901 | F100: =IF(E$10<'Input data'!$C$4+2,((F36*E90)-(F38*(E93+E95)))/(E91+E92+E94), IF(E$10>'Input data'!$C$4+2,IF(E90>0,(E100*E91+F37*(E94+E92))/(E91+E92+E94),F37), IF(E90>0,(E100*E91+ ('Baseline NFPC'!F97*('Baseline NFPC'!E88+'Baseline NFPC'!E89+'Baseline NFPC'!E91)-'Baseline NFPC'!E97*'Baseline NFPC'!E88)/('Baseline NFPC'!E89+'Baseline NFPC'!E91) *(E94+E92))/(E91+E92+E94),F37))) -> 3.2330321 | G100: =IF(F$10<'Input data'!$C$4+2,((G36*F90)-(G38*(F93+F95)))/(F91+F92+F94), IF(F$10>'Input data'!$C$4+2,IF(F90>0,(F100*F91+G37*(F94+F92))/(F91+F92+F94),G37), IF(F90>0,(F100*F91+ ('Baseline NFPC'!G97*('Baseline NFPC'!F88+'Baseline NFPC'!F89+'Baseline NFPC'!F91)-'Baseline NFPC'!F97*'Baseline NFPC'!F88)/('Baseline NFPC'!F89+'Baseline NFPC'!F91) *(F94+F92))/(F91+F92+F94),G37))) -> 3.4427352 | H100: =IF(G90>0,(G100*G91+H37*(G94+G92))/(G91+G92+G94),H37) -> 3.6338972 | I100: =IF(H90>0,(H100*H91+I37*(H94+H92))/(H91+H92+H94),I37) -> 3.8080855 | J100: =IF(I90>0,(I100*I91+J37*(I94+I92))/(I91+I92+I94),J37) -> 3.9821308 | K100: =IF(J90>0,(J100*J91+K37*(J94+J92))/(J91+J92+J94),K37) -> 4.1525282 | L100: =IF(K90>0,(K100*K91+L37*(K94+K92))/(K91+K92+K94),L37) -> 4.3194777 | M100: =IF(L90>0,(L100*L91+M37*(L94+L92))/(L91+L92+L94),M37) -> 4.4947068 | N100: =IF(M90>0,(M100*M91+N37*(M94+M92))/(M91+M92+M94),N37) -> 4.64307 | O100: =IF(N90>0,(N100*N91+O37*(N94+N92))/(N91+N92+N94),O37) -> 4.7672255 | ... U100: =IF(T90>0,(T100*T91+U37*(T94+T92))/(T91+T92+T94),U37) -> 5.0794471
B101: Nominal implicit interest rate on debt (Excel approximation) | E101: =(E100*(D91+D92+D94)+E38*(D93+D95))/D90 -> 2.999835 | F101: =(F100*(E91+E92+E94)+F38*(E93+E95))/E90 -> 3.2612235 | G101: =(G100*(F91+F92+F94)+G38*(F93+F95))/F90 -> 3.466152 | H101: =(H100*(G91+G92+G94)+H38*(G93+G95))/G90 -> 3.6527919 | I101: =(I100*(H91+H92+H94)+I38*(H93+H95))/H90 -> 3.8227404 | J101: =(J100*(I91+I92+I94)+J38*(I93+I95))/I90 -> 3.9924506 | K101: =(K100*(J91+J92+J94)+K38*(J93+J95))/J90 -> 4.1585065 | L101: =(L100*(K91+K92+K94)+L38*(K93+K95))/K90 -> 4.3211098 | ... U101: =(U100*(T91+T92+T94)+U38*(T93+T95))/T90 -> 5.025283
B102: Diff. STATA | E102: ='Adjust. no safeguard'!E104 -> 0 | F102: ='Adjust. no safeguard'!F104 -> 0 | G102: ='Adjust. no safeguard'!G104 -> 0 | H102: ='Adjust. no safeguard'!H104 -> 0 | I102: ='Adjust. no safeguard'!I104 -> 0 | J102: ='Adjust. no safeguard'!J104 -> 0 | K102: ='Adjust. no safeguard'!K104 -> 0 | L102: ='Adjust. no safeguard'!L104 -> 0 | ... U102: ='Adjust. no safeguard'!U104 -> 0
B104: (i - g) | C104: =((1+C99/100)/((1+C24/100)*(1+C42/100))-1)*100 -> -2.8128161 | D104: =((1+D99/100)/((1+D24/100)*(1+D42/100))-1)*100 -> -1.3622666 | E104: =((1+E99/100)/((1+E24/100)*(1+E42/100))-1)*100 -> -1.9069822 | F104: =((1+F99/100)/((1+F24/100)*(1+F42/100))-1)*100 -> -0.9024777 | G104: =((1+G99/100)/((1+G24/100)*(1+G42/100))-1)*100 -> -0.4873321 | H104: =((1+H99/100)/((1+H24/100)*(1+H42/100))-1)*100 -> -0.25689829 | I104: =((1+I99/100)/((1+I24/100)*(1+I42/100))-1)*100 -> -0.32951383 | J104: =((1+J99/100)/((1+J24/100)*(1+J42/100))-1)*100 -> -0.087644076 | ... U104: =((1+U99/100)/((1+U24/100)*(1+U42/100))-1)*100 -> 1.1322142

Sheet Adjust. no safeguard
B3: Country | C3: ='Input data'!C3 -> CZ
B4: Key years
B5: ='Input data'!B5 -> Last year before the adjustment | C5: =+'Input data'!C5 -> 2026
B6: Last year of adjustment | C6: =+C5+'Criteria results'!$F$5 -> 2030
B7: Last year of no-fiscal-policy-change projections | C7: =C5+'Criteria results'!$F$5+10 -> 2040
B9: Key assumptions
C10: ='Input data'!$C$5-1 -> 2025 | D10: =C10+1 -> 2026 | E10: =D10+1 -> 2027 | F10: =E10+1 -> 2028 | G10: =F10+1 -> 2029 | H10: =G10+1 -> 2030 | I10: =H10+1 -> 2031 | J10: =I10+1 -> 2032 | K10: =J10+1 -> 2033 | ... U10: =T10+1 -> 2043
B11: Fiscal assumptions (% of GDP)
B12: Structural primary balance ('+' means 'surplus') | C12: ='Input data'!C13 -> -0.5110157 | D12: ='Input data'!D13 -> -1.332759 | E12: =IF(E10<=$C$6,D12+'Criteria results'!$F$7,D12) -> -0.872759 | F12: =IF(F10<=$C$6,E12+'Criteria results'!$F$7,E12) -> -0.412759 | G12: =IF(G10<=$C$6,F12+'Criteria results'!$F$7,F12) -> 0.047241 | H12: =IF(H10<=$C$6,G12+'Criteria results'!$F$7,G12) -> 0.507241 | I12: =IF(I10<=$C$6,H12+'Criteria results'!$F$7,H12) -> 0.507241 | J12: =IF(J10<=$C$6,I12+'Criteria results'!$F$7,I12) -> 0.507241 | K12: =IF(K10<=$C$6,J12+'Criteria results'!$F$7,J12) -> 0.507241 | L12: =K12 -> 0.507241 | M12: =L12 -> 0.507241 | N12: =M12 -> 0.507241 | O12: =N12 -> 0.507241 | P12: =O12 -> 0.507241 | Q12: =P12 -> 0.507241 | R12: =Q12 -> 0.507241 | S12: =R12 -> 0.507241 | ... U12: =T12 -> 0.507241
B13: Annual change in SPB | E13: =E12-D12 -> 0.46 | F13: =F12-E12 -> 0.46 | G13: =G12-F12 -> 0.46 | H13: =H12-G12 -> 0.46 | I13: =I12-H12 -> 0 | J13: =J12-I12 -> 0 | K13: =K12-J12 -> 0 | L13: =L12-K12 -> 0 | ... U13: =U12-T12 -> 0
B14: One-off and other temporary measures | C14: ='Input data'!C14 -> -0.1168709 | D14: ='Input data'!D14 -> 0 | E14: ='Input data'!E14 -> 0 | F14: ='Input data'!F14 -> 0 | G14: ='Input data'!G14 -> 0 | H14: ='Input data'!H14 -> 0 | I14: ='Input data'!I14 -> 0 | J14: ='Input data'!J14 -> 0 | ... U14: ='Input data'!U14 -> 0
B15: Stock flow adjustments (without exchange rate effect) | C15: ='Input data'!C15 -> 1.388104 | D15: ='Input data'!D15 -> 0.7474777 | E15: ='Input data'!E15 -> 0.85 | F15: ='Input data'!F15 -> 0 | G15: ='Input data'!G15 -> 0 | H15: ='Input data'!H15 -> 0 | I15: ='Input data'!I15 -> 0 | J15: ='Input data'!J15 -> 0 | ... U15: ='Input data'!U15 -> 0
B17: ='Input data'!B19 -> Cost of ageing and selected public revenue (based on the Commission-Council 2024 Ageing Report ("AR 2024"))
B18: Total ageing cost (net of taxes on pensions) | C18: ='Input data'!C20 -> 19.8 | D18: ='Input data'!D20 -> 19.7 | E18: ='Input data'!E20 -> 19.8 | F18: ='Input data'!F20 -> 19.9 | G18: ='Input data'!G20 -> 20 | H18: ='Input data'!H20 -> 20 | I18: ='Input data'!I20 -> 20.1 | J18: ='Input data'!J20 -> 20.1 | ... U18: ='Input data'!U20 -> 21.3
B19: Property income | C19: ='Input data'!C26 -> 1.037865 | D19: ='Input data'!D26 -> 1.023357 | E19: ='Input data'!E26 -> 1.008848 | F19: ='Input data'!F26 -> 0.9943401 | G19: ='Input data'!G26 -> 0.9798318 | H19: ='Input data'!H26 -> 0.9653235 | I19: ='Input data'!I26 -> 0.9508152 | J19: ='Input data'!J26 -> 0.9363069 | ... U19: ='Input data'!U26 -> 0.7767155
B21: GDP growth assumptions
B22: Actual GDP (real)
B23: Level | C23: ='Baseline NFPC'!C22 -> 6479.806 | D23: ='Baseline NFPC'!D22 -> 6596.2656 | E23: =IF(AND(E50>1,D50>1), IF(E$10<='Input data'!$C$4+2, E27*(1+('Baseline NFPC'!E$29+E51)/100)-D23*$C$47*(E12-D12)/100, E27*(1+E51/100)-D23*$C$47*(E12-D12)/100), IF(E50=1,E27,D23*(1+E52/100))) -> 6720.01 | F23: =IF(AND(F50>1,E50>1), IF(F$10<='Input data'!$C$4+2, F27*(1+('Baseline NFPC'!F$29+F51)/100)-E23*$C$47*(F12-E12)/100, F27*(1+F51/100)-E23*$C$47*(F12-E12)/100), IF(F50=1,F27,E23*(1+F52/100))) -> 6799.8872 | G23: =IF(AND(G50>1,F50>1), IF(G$10<='Input data'!$C$4+2, G27*(1+('Baseline NFPC'!G$29+G51)/100)-F23*$C$47*(G12-F12)/100, G27*(1+G51/100)-F23*$C$47*(G12-F12)/100), IF(G50=1,G27,F23*(1+G52/100))) -> 6871.6851 | H23: =IF(AND(H50>1,G50>1), IF(H$10<='Input data'!$C$4+2, H27*(1+('Baseline NFPC'!H$29+H51)/100)-G23*$C$47*(H12-G12)/100, H27*(1+H51/100)-G23*$C$47*(H12-G12)/100), IF(H50=1,H27,G23*(1+H52/100))) -> 6946.8455 | I23: =IF(AND(I50>1,H50>1), IF(I$10<='Input data'!$C$4+2, I27*(1+('Baseline NFPC'!I$29+I51)/100)-H23*$C$47*(I12-H12)/100, I27*(1+I51/100)-H23*$C$47*(I12-H12)/100), IF(I50=1,I27,H23*(1+I52/100))) -> 7045.7104 | J23: =IF(AND(J50>1,I50>1), IF(J$10<='Input data'!$C$4+2, J27*(1+('Baseline NFPC'!J$29+J51)/100)-I23*$C$47*(J12-I12)/100, J27*(1+J51/100)-I23*$C$47*(J12-I12)/100), IF(J50=1,J27,I23*(1+J52/100))) -> 7146.6739 | K23: =IF(AND(K50>1,J50>1), IF(K$10<='Input data'!$C$4+2, K27*(1+('Baseline NFPC'!K$29+K51)/100)-J23*$C$47*(K12-J12)/100, K27*(1+K51/100)-J23*$C$47*(K12-J12)/100), IF(K50=1,K27,J23*(1+K52/100))) -> 7249.6249 | L23: =IF(AND(L50>1,K50>1), IF(L$10<='Input data'!$C$4+2, L27*(1+('Baseline NFPC'!L$29+L51)/100)-K23*$C$47*(L12-K12)/100, L27*(1+L51/100)-K23*$C$47*(L12-K12)/100), IF(L50=1,L27,K23*(1+L52/100))) -> 7337.2908 | ... U23: =IF(AND(U50>1,T50>1), IF(U$10<='Input data'!$C$4+2, U27*(1+('Baseline NFPC'!U$29+U51)/100)-T23*$C$47*(U12-T12)/100, U27*(1+U51/100)-T23*$C$47*(U12-T12)/100), IF(U50=1,U27,T23*(1+U52/100))) -> 8363.8379
B24: Growth rate | C24: ='Baseline NFPC'!C23 -> 2.580467 | D24: ='Baseline NFPC'!D23 -> 1.79727 | E24: =100*(E23/D23-1) -> 1.875977 | F24: =100*(F23/E23-1) -> 1.188646 | G24: =100*(G23/F23-1) -> 1.0558694 | H24: =100*(H23/G23-1) -> 1.0937696 | I24: =100*(I23/H23-1) -> 1.4231627 | J24: =100*(J23/I23-1) -> 1.4329775 | K24: =100*(K23/J23-1) -> 1.4405454 | L24: =100*(L23/K23-1) -> 1.209247 | ... U24: =100*(U23/T23-1) -> 1.61
B26: Potential GDP (real)
B27: Level | C27: ='Input data'!C34 -> 6515.4565 | D27: =+C27*(1+'Input data'!D33/100) -> 6622.8091 | E27: =+D27*(1+'Input data'!E33/100) -> 6721.6283 | F27: =+E27*(1+'Input data'!F33/100) -> 6819.529 | G27: =+F27*(1+'Input data'!G33/100) -> 6903.7089 | H27: =+G27*(1+'Input data'!H33/100) -> 6987.4195 | I27: =+H27*(1+'Input data'!I33/100) -> 7073.0914 | J27: =+I27*(1+'Input data'!J33/100) -> 7160.5336 | K27: =+J27*(1+'Input data'!K33/100) -> 7249.6249 | ... U27: =+T27*(1+'Input data'!U33/100) -> 8363.8361
B29: Output gap
B30: Output gap | C30: =100*(C23/C27-1) -> -0.54716846 | D30: =100*(D23/D27-1) -> -0.40078891 | E30: =100*(E23/E27-1) -> -0.024075392 | F30: =100*(F23/F27-1) -> -0.28802253 | G30: =100*(G23/G27-1) -> -0.46386438 | H30: =100*(H23/H27-1) -> -0.58067146 | I30: =100*(I23/I27-1) -> -0.38711431 | J30: =100*(J23/J27-1) -> -0.19355715 | ... U30: =100*(U23/U27-1) -> 2.1710351e-05
B32: Actual GDP (nominal, national currency)
B33: Growth rate | C33: =100*((1+C24/100)*(1+C42/100)-1) -> 6.1837136 | D33: =100*((1+D24/100)*(1+D42/100)-1) -> 4.5016947 | E33: =100*((1+E24/100)*(1+E42/100)-1) -> 5.0022084 | F33: =100*((1+F24/100)*(1+F42/100)-1) -> 4.2016199 | G33: =100*((1+G24/100)*(1+G42/100)-1) -> 3.972845 | H33: =100*((1+H24/100)*(1+H42/100)-1) -> 3.91976 | I33: =100*((1+I24/100)*(1+I42/100)-1) -> 4.1659817 | J33: =100*((1+J24/100)*(1+J42/100)-1) -> 4.0836738 | ... U33: =100*((1+U24/100)*(1+U42/100)-1) -> 3.8494844
B35: Interest rates
B36: Nominal implicit interest rate on debt | C36: ='Input data'!C37 -> 3.196961 | D36: ='Input data'!D37 -> 3.078103 | E36: =IF(E$10<='Input data'!$C$4+2,'Input data'!E37,E101) -> 2.999835 | F36: =IF(F$10<='Input data'!$C$4+2,'Input data'!F37,F101) -> 3.2612235 | G36: =IF(G$10<='Input data'!$C$4+2,'Input data'!G37,G101) -> 3.466152 | H36: =IF(H$10<='Input data'!$C$4+2,'Input data'!H37,H101) -> 3.6527919 | I36: =IF(I$10<='Input data'!$C$4+2,'Input data'!I37,I101) -> 3.8227404 | J36: =IF(J$10<='Input data'!$C$4+2,'Input data'!J37,J101) -> 3.9924506 | K36: =IF(K$10<='Input data'!$C$4+2,'Input data'!K37,K101) -> 4.1585065 | L36: =IF(L$10<='Input data'!$C$4+2,'Input data'!L37,L101) -> 4.3211098 | ... U36: =IF(U$10<='Input data'!$C$4+2,'Input data'!U37,U101) -> 5.025283
B37: Long-term interest rate | C37: ='Input data'!C$39 -> 4.29 | D37: ='Input data'!D$39 -> 4.701964 | E37: ='Baseline NFPC'!E36 -> 4.915649 | F37: ='Baseline NFPC'!F36 -> 5.0370066 | G37: ='Baseline NFPC'!G36 -> 5.1583642 | H37: ='Baseline NFPC'!H36 -> 5.2797219 | I37: ='Baseline NFPC'!I36 -> 5.4010795 | J37: ='Baseline NFPC'!J36 -> 5.5224371 | K37: ='Baseline NFPC'!K36 -> 5.6437948 | L37: ='Baseline NFPC'!L36 -> 5.7651524 | ... U37: ='Baseline NFPC'!U36 -> 5.131906
B38: Short-term interest rate | C38: ='Input data'!C$38 -> 3.6 | D38: ='Input data'!D$38 -> 3.649853 | E38: ='Baseline NFPC'!E37 -> 4.267191 | F38: ='Baseline NFPC'!F37 -> 4.2826609 | G38: ='Baseline NFPC'!G37 -> 4.2981308 | H38: ='Baseline NFPC'!H37 -> 4.3136006 | I38: ='Baseline NFPC'!I37 -> 4.3290705 | J38: ='Baseline NFPC'!J37 -> 4.3445404 | K38: ='Baseline NFPC'!K37 -> 4.3600103 | L38: ='Baseline NFPC'!L37 -> 4.3754801 | ... U38: ='Baseline NFPC'!U37 -> 3.43457
B39: Share of long-term debt that matures every year | C39: ='Baseline NFPC'!C38 -> 0.06796828 | D39: ='Baseline NFPC'!D38 -> 0.06823518 | E39: ='Baseline NFPC'!E38 -> 0.06905882 | F39: ='Baseline NFPC'!F38 -> 0.069882459 | G39: ='Baseline NFPC'!G38 -> 0.070706098 | H39: ='Baseline NFPC'!H38 -> 0.071529736 | I39: ='Baseline NFPC'!I38 -> 0.072353375 | J39: ='Baseline NFPC'!J38 -> 0.073177014 | ... U39: ='Baseline NFPC'!U38 -> 0.07564793
B41: Inflation and exchange rate
B42: GDP deflator (National currency) | C42: ='Input data'!C42 -> 3.512605 | D42: ='Input data'!D42 -> 2.656677 | E42: ='Baseline NFPC'!E41 -> 3.068664 | F42: ='Baseline NFPC'!F41 -> 2.977581 | G42: ='Baseline NFPC'!G41 -> 2.886498 | H42: ='Baseline NFPC'!H41 -> 2.795415 | I42: ='Baseline NFPC'!I41 -> 2.704332 | J42: ='Baseline NFPC'!J41 -> 2.613249 | K42: ='Baseline NFPC'!K41 -> 2.522166 | L42: ='Baseline NFPC'!L41 -> 2.431083 | ... U42: ='Baseline NFPC'!U41 -> 2.204
B43: Exchange rate composite change (weighted by share of debt in each currency) | C43: ='Baseline NFPC'!C42 -> 0.9986759 | D43: ='Baseline NFPC'!D42 -> 0.9989123 | E43: ='Baseline NFPC'!E42 -> 0.9999991 | F43: ='Baseline NFPC'!F42 -> 1 | G43: ='Baseline NFPC'!G42 -> 1 | H43: ='Baseline NFPC'!H42 -> 1 | I43: ='Baseline NFPC'!I42 -> 1 | J43: ='Baseline NFPC'!J42 -> 1 | ... U43: ='Baseline NFPC'!U42 -> 1
B45: Intermediate calculations (growth rate equation)
B47: Fiscal multiplier | C47: ='Input data'!C49 -> 0.6
B48: Budget balance semi-elasticity | C48: ='Input data'!C50 -> 0.395
B50: Auxiliary variable to control the closure of the output gap | C50: 0 | D50: =IF(AND(ABS((D12-C12)-('Input data'!D13-'Input data'!C13))>0.0001,ABS(D12-C12)>0.0001,D$10>$C$5),4,IF(C50=4,3,IF(C50=3,2,IF(C50=2,1,0)))) -> 0 | E50: =IF(AND(ABS((E12-D12)-('Baseline NFPC'!E12-'Baseline NFPC'!D12))>0.0001,ABS(E12-D12)>0.0001,E$10>$C$5),4,IF(D50=4,3,IF(D50=3,2,IF(D50=2,1,0)))) -> 4 | F50: =IF(AND(ABS((F12-E12)-('Baseline NFPC'!F12-'Baseline NFPC'!E12))>0.0001,ABS(F12-E12)>0.0001,F$10>$C$5),4,IF(E50=4,3,IF(E50=3,2,IF(E50=2,1,0)))) -> 4 | G50: =IF(AND(ABS((G12-F12)-('Baseline NFPC'!G12-'Baseline NFPC'!F12))>0.0001,ABS(G12-F12)>0.0001,G$10>$C$5),4,IF(F50=4,3,IF(F50=3,2,IF(F50=2,1,0)))) -> 4 | H50: =IF(AND(ABS((H12-G12)-('Baseline NFPC'!H12-'Baseline NFPC'!G12))>0.0001,ABS(H12-G12)>0.0001,H$10>$C$5),4,IF(G50=4,3,IF(G50=3,2,IF(G50=2,1,0)))) -> 4 | I50: =IF(AND(ABS((I12-H12)-('Baseline NFPC'!I12-'Baseline NFPC'!H12))>0.0001,ABS(I12-H12)>0.0001,I$10>$C$5),4,IF(H50=4,3,IF(H50=3,2,IF(H50=2,1,0)))) -> 3 | J50: =IF(AND(ABS((J12-I12)-('Baseline NFPC'!J12-'Baseline NFPC'!I12))>0.0001,ABS(J12-I12)>0.0001,J$10>$C$5),4,IF(I50=4,3,IF(I50=3,2,IF(I50=2,1,0)))) -> 2 | K50: =IF(AND(ABS((K12-J12)-('Baseline NFPC'!K12-'Baseline NFPC'!J12))>0.0001,ABS(K12-J12)>0.0001,K$10>$C$5),4,IF(J50=4,3,IF(J50=3,2,IF(J50=2,1,0)))) -> 1 | L50: =IF(AND(ABS((L12-K12)-('Baseline NFPC'!L12-'Baseline NFPC'!K12))>0.0001,ABS(L12-K12)>0.0001,L$10>$C$5),4,IF(K50=4,3,IF(K50=3,2,IF(K50=2,1,0)))) -> 0 | ... U50: =IF(AND(ABS((U12-T12)-('Baseline NFPC'!U12-'Baseline NFPC'!T12))>0.0001,ABS(U12-T12)>0.0001,U$10>$C$5),4,IF(T50=4,3,IF(T50=3,2,IF(T50=2,1,0)))) -> 0
B51: OG intermediate auxiliary value | C51: 0 | D51: 0 | E51: =IF(D50=4, IF(E$10<='Input data'!$C$4+2,2/3*(D30-'Baseline NFPC'!D29),2/3*D30), IF(D50=3, IF(E$10<='Input data'!$C$4+2,1/3*(C30-'Baseline NFPC'!C29),1/3*C30), 0)) -> 0 | F51: =IF(E50=4, IF(F$10<='Input data'!$C$4+2,2/3*(E30-'Baseline NFPC'!E29),2/3*E30), IF(E50=3, IF(F$10<='Input data'!$C$4+2,1/3*(D30-'Baseline NFPC'!D29),1/3*D30), 0)) -> -0.016050261 | G51: =IF(F50=4, IF(G$10<='Input data'!$C$4+2,2/3*(F30-'Baseline NFPC'!F29),2/3*F30), IF(F50=3, IF(G$10<='Input data'!$C$4+2,1/3*(E30-'Baseline NFPC'!E29),1/3*E30), 0)) -> -0.19201502 | H51: =IF(G50=4, IF(H$10<='Input data'!$C$4+2,2/3*(G30-'Baseline NFPC'!G29),2/3*G30), IF(G50=3, IF(H$10<='Input data'!$C$4+2,1/3*(F30-'Baseline NFPC'!F29),1/3*F30), 0)) -> -0.30924292 | I51: =IF(H50=4, IF(I$10<='Input data'!$C$4+2,2/3*(H30-'Baseline NFPC'!H29),2/3*H30), IF(H50=3, IF(I$10<='Input data'!$C$4+2,1/3*(G30-'Baseline NFPC'!G29),1/3*G30), 0)) -> -0.38711431 | J51: =IF(I50=4, IF(J$10<='Input data'!$C$4+2,2/3*(I30-'Baseline NFPC'!I29),2/3*I30), IF(I50=3, IF(J$10<='Input data'!$C$4+2,1/3*(H30-'Baseline NFPC'!H29),1/3*H30), 0)) -> -0.19355715 | K51: =IF(J50=4, IF(K$10<='Input data'!$C$4+2,2/3*(J30-'Baseline NFPC'!J29),2/3*J30), IF(J50=3, IF(K$10<='Input data'!$C$4+2,1/3*(I30-'Baseline NFPC'!I29),1/3*I30), 0)) -> 0 | L51: =IF(K50=4, IF(L$10<='Input data'!$C$4+2,2/3*(K30-'Baseline NFPC'!K29),2/3*K30), IF(K50=3, IF(L$10<='Input data'!$C$4+2,1/3*(J30-'Baseline NFPC'!J29),1/3*J30), 0)) -> 0 | ... U51: =IF(T50=4, IF(U$10<='Input data'!$C$4+2,2/3*(T30-'Baseline NFPC'!T29),2/3*T30), IF(T50=3, IF(U$10<='Input data'!$C$4+2,1/3*(S30-'Baseline NFPC'!S29),1/3*S30), 0)) -> 0
B52: GDP intermediate growth rate - only feedback effect and no closure of the OG | C52: 0 | D52: ='Input data'!D30-$C$47*((D12-C12)-('Input data'!D13-'Input data'!C13)) -> 1.79727 | E52: ='Input data'!E30-$C$47*(E12-D12) -> 1.875977 | F52: ='Input data'!F30-$C$47*(F12-E12) -> 1.097251 | G52: ='Input data'!G30-$C$47*(G12-F12) -> 0.847538 | H52: ='Input data'!H30-$C$47*(H12-G12) -> 0.881076 | I52: ='Input data'!I30-$C$47*(I12-H12) -> 1.226085 | J52: ='Input data'!J30-$C$47*(J12-I12) -> 1.236268 | K52: ='Input data'!K30-$C$47*(K12-J12) -> 1.244196 | L52: ='Input data'!L30-$C$47*(L12-K12) -> 1.209247 | ... U52: ='Input data'!U30-$C$47*(U12-T12) -> 1.61
B54: Debt projections
C56: ='Input data'!$C$5-1 -> 2025 | D56: =C56+1 -> 2026 | E56: =D56+1 -> 2027 | F56: =E56+1 -> 2028 | G56: =F56+1 -> 2029 | H56: =G56+1 -> 2030 | I56: =H56+1 -> 2031 | J56: =I56+1 -> 2032 | K56: =J56+1 -> 2033 | ... U56: =T56+1 -> 2043
B57: Gross debt | C57: =+'Input data'!C12 -> 44.25023 | D57: =+C57+D58 -> 45.838496 | E57: =+D57+E58 -> 46.696592 | F57: =+E57+F58 -> 46.801694 | G57: =+F57+G58 -> 46.709599 | H57: =+G57+H58 -> 46.311727 | I57: =+H57+I58 -> 45.919301 | J57: =+I57+J58 -> 45.577286 | K57: =+J57+K58 -> 45.283454 | ... U57: =+T57+U58 -> 54.272639
B58: Change in debt (-1+2+3) | D58: =-D59+D67+D72 -> 1.5882664 | E58: =-E59+E67+E72 -> 0.85809545 | F58: =-F59+F67+F72 -> 0.10510172 | G58: =-G59+G67+G72 -> -0.092094248 | H58: =-H59+H67+H72 -> -0.39787194 | I58: =-I59+I67+I72 -> -0.3924261 | J58: =-J59+J67+J72 -> -0.34201487 | K58: =-K59+K67+K72 -> -0.29383227 | ... U58: =-U59+U67+U72 -> 1.5779749
B59: (1) Primary balance (1.1 + 1.2 - 1.3 -1.4 -1.5 - 1.6 -1.7) | D59: =D60+D61-D62-D63-D64-D65-D66 -> -1.4910706 | E59: =E60+E61-E62-E63-E64-E65-E66 -> -0.88226878 | F59: =F60+F61-F62-F63-F64-F65-F66 -> -0.5265279 | G59: =G60+G61-G62-G63-G64-G65-G66 -> -0.13598543 | H59: =H60+H61-H62-H63-H64-H65-H66 -> 0.27787577 | I59: =I60+I61-I62-I63-I64-I65-I66 -> 0.23982255 | J59: =J60+J61-J62-J63-J64-J65-J66 -> 0.30176932 | K59: =K60+K61-K62-K63-K64-K65-K66 -> 0.3637161 | ... U59: =U60+U61-U62-U63-U64-U65-U66 -> -0.98135842
B60: (1.1) Structural primary balance (before ageing cost) | D60: =D12 -> -1.332759 | E60: =IF(E12="",D60,E12) -> -0.872759 | F60: =IF(F12="",E60,F12) -> -0.412759 | G60: =IF(G12="",F60,G12) -> 0.047241 | H60: =IF(H12="",G60,H12) -> 0.507241 | I60: =IF(I12="",H60,I12) -> 0.507241 | J60: =IF(J12="",I60,J12) -> 0.507241 | K60: =IF(K12="",J60,K12) -> 0.507241 | L60: =IF(L12="",K60,L12) -> 0.507241 | ... U60: =IF(U12="",T60,U12) -> 0.507241
B61: (1.2) Cumulated budgetary effort (in terms of primary balance) | D61: 0 | E61: 0 | F61: 0 | G61: 0 | H61: 0 | I61: 0 | J61: 0 | K61: 0 | L61: 0 | M61: 0 | N61: 0 | O61: 0 | P61: 0 | Q61: 0 | R61: 0 | S61: 0 | T61: 0 | U61: 0
B62: (1.3) Cyclical component | D62: =-$C$48*D30 -> 0.15831162 | E62: =-$C$48*E30 -> 0.0095097798 | F62: =-$C$48*F30 -> 0.1137689 | G62: =-$C$48*G30 -> 0.18322643 | H62: =-$C$48*H30 -> 0.22936523 | I62: =-$C$48*I30 -> 0.15291015 | J62: =-$C$48*J30 -> 0.076455076 | K62: =-$C$48*K30 -> 0 | ... U62: =-$C$48*U30 -> -8.5755887e-06
B63: (1.4) One-off and other temporary measures | D63: =-D14 -> 0 | E63: =-E14 -> 0 | F63: =-F14 -> 0 | G63: =-G14 -> 0 | H63: =-H14 -> 0 | I63: =-I14 -> 0 | J63: =-J14 -> 0 | K63: =-K14 -> 0 | ... U63: =-U14 -> 0
B64: (1.5) Cost of ageing | D64: =IF(D$56<=$C$6,0,HLOOKUP(D$56,'Input data'!$C$9:$AZ$26,12,FALSE)-HLOOKUP($C$6,'Input data'!$C$9:$AZ$26,12,FALSE)) -> 0 | E64: =IF(E$56<=$C$6,0,HLOOKUP(E$56,'Input data'!$C$9:$AZ$26,12,FALSE)-HLOOKUP($C$6,'Input data'!$C$9:$AZ$26,12,FALSE)) -> 0 | F64: =IF(F$56<=$C$6,0,HLOOKUP(F$56,'Input data'!$C$9:$AZ$26,12,FALSE)-HLOOKUP($C$6,'Input data'!$C$9:$AZ$26,12,FALSE)) -> 0 | G64: =IF(G$56<=$C$6,0,HLOOKUP(G$56,'Input data'!$C$9:$AZ$26,12,FALSE)-HLOOKUP($C$6,'Input data'!$C$9:$AZ$26,12,FALSE)) -> 0 | H64: =IF(H$56<=$C$6,0,HLOOKUP(H$56,'Input data'!$C$9:$AZ$26,12,FALSE)-HLOOKUP($C$6,'Input data'!$C$9:$AZ$26,12,FALSE)) -> 0 | I64: =IF(I$56<=$C$6,0,HLOOKUP(I$56,'Input data'!$C$9:$AZ$26,12,FALSE)-HLOOKUP($C$6,'Input data'!$C$9:$AZ$26,12,FALSE)) -> 0.1 | J64: =IF(J$56<=$C$6,0,HLOOKUP(J$56,'Input data'!$C$9:$AZ$26,12,FALSE)-HLOOKUP($C$6,'Input data'!$C$9:$AZ$26,12,FALSE)) -> 0.1 | K64: =IF(K$56<=$C$6,0,HLOOKUP(K$56,'Input data'!$C$9:$AZ$26,12,FALSE)-HLOOKUP($C$6,'Input data'!$C$9:$AZ$26,12,FALSE)) -> 0.1 | ... U64: =IF(U$56<=$C$6,0,HLOOKUP(U$56,'Input data'!$C$9:$AZ$26,12,FALSE)-HLOOKUP($C$6,'Input data'!$C$9:$AZ$26,12,FALSE)) -> 1.3
B65: (1.6) Property incomes | D65: =IF(D$56<=$C$5,0,-HLOOKUP(D$56,'Input data'!$C$9:$AZ$26,18,FALSE)+HLOOKUP($C$6,'Input data'!$C$9:$AZ$26,18,FALSE)) -> 0 | E65: =IF(E$56<=$C$6,0,-HLOOKUP(E$56,'Input data'!$C$9:$AZ$26,18,FALSE)+HLOOKUP($C$6,'Input data'!$C$9:$AZ$26,18,FALSE)) -> 0 | F65: =IF(F$56<=$C$6,0,-HLOOKUP(F$56,'Input data'!$C$9:$AZ$26,18,FALSE)+HLOOKUP($C$6,'Input data'!$C$9:$AZ$26,18,FALSE)) -> 0 | G65: =IF(G$56<=$C$6,0,-HLOOKUP(G$56,'Input data'!$C$9:$AZ$26,18,FALSE)+HLOOKUP($C$6,'Input data'!$C$9:$AZ$26,18,FALSE)) -> 0 | H65: =IF(H$56<=$C$6,0,-HLOOKUP(H$56,'Input data'!$C$9:$AZ$26,18,FALSE)+HLOOKUP($C$6,'Input data'!$C$9:$AZ$26,18,FALSE)) -> 0 | I65: =IF(I$56<=$C$6,0,-HLOOKUP(I$56,'Input data'!$C$9:$AZ$26,18,FALSE)+HLOOKUP($C$6,'Input data'!$C$9:$AZ$26,18,FALSE)) -> 0.0145083 | J65: =IF(J$56<=$C$6,0,-HLOOKUP(J$56,'Input data'!$C$9:$AZ$26,18,FALSE)+HLOOKUP($C$6,'Input data'!$C$9:$AZ$26,18,FALSE)) -> 0.0290166 | K65: =IF(K$56<=$C$6,0,-HLOOKUP(K$56,'Input data'!$C$9:$AZ$26,18,FALSE)+HLOOKUP($C$6,'Input data'!$C$9:$AZ$26,18,FALSE)) -> 0.0435249 | L65: =IF(L$56<=$C$6,0,-HLOOKUP(L$56,'Input data'!$C$9:$AZ$26,18,FALSE)+HLOOKUP($C$6,'Input data'!$C$9:$AZ$26,18,FALSE)) -> 0.0580332 | ... U65: =IF(U$56<=$C$6,0,-HLOOKUP(U$56,'Input data'!$C$9:$AZ$26,18,FALSE)+HLOOKUP($C$6,'Input data'!$C$9:$AZ$26,18,FALSE)) -> 0.188608
B66: (1.7) Revenues | D66: 0 | E66: 0 | F66: 0 | G66: 0 | H66: 0 | I66: 0 | J66: 0 | K66: 0 | L66: 0 | M66: 0 | N66: 0 | O66: 0 | P66: 0 | Q66: 0 | R66: 0 | S66: 0 | T66: 0 | U66: 0
B67: (2) Snowball effect (2.1 + 2.2 + 2.3) | D67: =SUM(D68:D71) -> -0.6042236 | E67: =SUM(E68:E71) -> -0.87413323 | F67: =SUM(F68:F71) -> -0.42142618 | G67: =SUM(G68:G71) -> -0.22807968 | H67: =SUM(H68:H71) -> -0.11999616 | I67: =SUM(I68:I71) -> -0.15260355 | J67: =SUM(J68:J71) -> -0.040245547 | K67: =SUM(K68:K71) -> 0.069883826 | ... U67: =SUM(U68:U71) -> 0.59661648
B68: (2.1) Interest expenditure | D68: =C57*D36/100*(1/(1+D33/100)) -> 1.3033929 | E68: =D57*E36/100*(1/(1+E33/100)) -> 1.3095718 | F68: =E57*F36/100*(1/(1+F33/100)) -> 1.4614746 | G68: =F57*G36/100*(1/(1+G33/100)) -> 1.5602322 | H68: =G57*H36/100*(1/(1+H33/100)) -> 1.641848 | I68: =H57*I36/100*(1/(1+I33/100)) -> 1.6995732 | J68: =I57*J36/100*(1/(1+J33/100)) -> 1.7613766 | K68: =J57*K36/100*(1/(1+K33/100)) -> 1.8224537 | ... U68: =T57*U36/100*(1/(1+U33/100)) -> 2.5498981
B69: (2.2) Growth effect | D69: =-C57*(D24/100)*(1/(1+D33/100)) -> -0.76103657 | E69: =-D57*(E24/100)*(1/(1+E33/100)) -> -0.81895387 | F69: =-E57*(F24/100)*(1/(1+F33/100)) -> -0.53267613 | G69: =-F57*(G24/100)*(1/(1+G33/100)) -> -0.47528251 | H69: =-G57*(H24/100)*(1/(1+H33/100)) -> -0.49162489 | I69: =-H57*(I24/100)*(1/(1+I33/100)) -> -0.63273174 | J69: =-I57*(J24/100)*(1/(1+J33/100)) -> -0.63219643 | K69: =-J57*(K24/100)*(1/(1+K33/100)) -> -0.63131495 | ... U69: =-T57*(U24/100)*(1/(1+U33/100)) -> -0.81693625
B70: (2.3) Inflation effect | D70: =-C57*D42/100*(1/(1+D42/100)) -> -1.1451624 | E70: =-D57*E42/100*(1/(1+E42/100)) -> -1.3647499 | F70: =-E57*F42/100*(1/(1+F42/100)) -> -1.3502248 | G70: =-F57*G42/100*(1/(1+G42/100)) -> -1.3130294 | H70: =-G57*H42/100*(1/(1+H42/100)) -> -1.2702192 | I70: =-H57*I42/100*(1/(1+I42/100)) -> -1.219445 | J70: =-I57*J42/100*(1/(1+J42/100)) -> -1.1694257 | K70: =-J57*K42/100*(1/(1+K42/100)) -> -1.1212549 | ... U70: =-T57*U42/100*(1/(1+U42/100)) -> -1.1363453
B71: (2.4) Exchange rate effect linked to the interest rate | D71: ='Baseline NFPC'!D70 -> -0.0014175065 | E71: ='Baseline NFPC'!E70 -> -1.2590616e-06 | F71: ='Baseline NFPC'!F70 -> 1.4316675e-07 | G71: 0 | H71: 0 | I71: 0 | J71: 0 | K71: 0 | L71: 0 | M71: 0 | N71: 0 | O71: 0 | P71: 0 | Q71: 0 | R71: 0 | S71: 0 | T71: 0 | U71: 0
B72: (3 ) Stock flow adjustments (3.1 + 3.2) | D72: ='Input data'!D16 -> 0.7014194 | E72: ='Input data'!E16 -> 0.8499599 | F72: ='Input data'!F16 -> 0 | G72: ='Input data'!G16 -> 0 | H72: ='Input data'!H16 -> 0 | I72: ='Input data'!I16 -> 0 | J72: ='Input data'!J16 -> 0 | K72: ='Input data'!K16 -> 0 | ... U72: ='Input data'!U16 -> 0
B73: (3.1) Base | D73: =D15 -> 0.7474777 | E73: =E15 -> 0.85 | F73: =F15 -> 0 | G73: =G15 -> 0 | H73: =H15 -> 0 | I73: =I15 -> 0 | J73: =J15 -> 0 | K73: =K15 -> 0 | ... U73: =U15 -> 0
B74: (3.2) Adjustment due to the exchange rate effect linked to debt value | D74: =+D72-D73 -> -0.0460583 | E74: =+E72-E73 -> -4.01e-05 | F74: =+F72-F73 -> 0 | G74: =+G72-G73 -> 0 | H74: =+H72-H73 -> 0 | I74: =+I72-I73 -> 0 | J74: =+J72-J73 -> 0 | K74: =+K72-K73 -> 0 | ... U74: =+U72-U73 -> 0
B76: Other budgetary variables
B77: Headline balance | C77: ='Baseline NFPC'!C76 -> -2.147432 | D77: =D59-D68 -> -2.7944635 | E77: =E59-E68 -> -2.1918405 | F77: =F59-F68 -> -1.9880025 | G77: =G59-G68 -> -1.6962176 | H77: =H59-H68 -> -1.3639722 | I77: =I59-I68 -> -1.4597507 | J77: =J59-J68 -> -1.4596072 | K77: =K59-K68 -> -1.4587376 | ... U77: =U59-U68 -> -3.5312565
B78: Structural balance | C78: ='Baseline NFPC'!C77 -> -1.81443 | D78: =D60-D68-D71-D64-D65-D66 -> -2.6347344 | E78: =E60-E68-E71-E64-E65-E66 -> -2.1823295 | F78: =F60-F68-F71-F64-F65-F66 -> -1.8742338 | G78: =G60-G68-G71-G64-G65-G66 -> -1.5129912 | H78: =H60-H68-H71-H64-H65-H66 -> -1.134607 | I78: =I60-I68-I71-I64-I65-I66 -> -1.3068405 | J78: =J60-J68-J71-J64-J65-J66 -> -1.3831522 | K78: =K60-K68-K71-K64-K65-K66 -> -1.4587376 | ... U78: =U60-U68-U71-U64-U65-U66 -> -3.5312651
B79: Net expenditure growth | C79: ='Input data'!C45 -> 4.9156095 | D79: ='Input data'!D45 -> 6.3502551 | E79: ='Input data'!E33+E42-(E$12-D$12-(E$64-D64))/'Input data'!$C$64*100 -> 3.4626987 | F79: ='Input data'!F33+F42-(F$12-E$12-(F$64-E64))/'Input data'!$C$64*100 -> 3.3360137 | G79: ='Input data'!G33+G42-(G$12-F$12-(G$64-F64))/'Input data'!$C$64*100 -> 3.0228247 | H79: ='Input data'!H33+H42-(H$12-G$12-(H$64-G64))/'Input data'!$C$64*100 -> 2.9098897 | I79: ='Input data'!I33+I42-(I$12-H$12-(I$64-H64))/'Input data'!$C$64*100 -> 4.1691307 | J79: ='Input data'!J33+J42-(J$12-I$12-(J$64-I64))/'Input data'!$C$64*100 -> 3.849515 | K79: ='Input data'!K33+K42-(K$12-J$12-(K$64-J64))/'Input data'!$C$64*100 -> 3.766366 | L79: ='Input data'!L33+L42-(L$12-K$12-(L$64-K64))/'Input data'!$C$64*100 -> 4.3564592 | ... U79: ='Input data'!U33+U42-(U$12-T$12-(U$64-T64))/'Input data'!$C$64*100 -> 4.0527107
B81: Average net expenditure growth over the adjustment period: | C81: =IF('Criteria results'!$F$5=4,AVERAGE(E79:H79),AVERAGE(E79:K79)) -> 3.1828567
B83: Debt decreasing? (For criterion 1) | I83: =IF(I57<H57,0,1) -> 0 | J83: =IF(J57<I57,0,1) -> 0 | K83: =IF(K57<J57,0,1) -> 0 | L83: =IF(L57<K57,0,1) -> 1 | M83: =IF(M57<L57,0,1) -> 1 | N83: =IF(N57<M57,0,1) -> 1 | O83: =IF(O57<N57,0,1) -> 1 | P83: =IF(P57<O57,0,1) -> 1 | ... U83: =IF(U57<T57,0,1) -> 1
B85: Debt decomposition and IIR
B87: Auxiliary variable identifying whether debt is increasing | D87: =IF((D92-C92*D43/((1+D24/100)*(1+D42/100)))>0,1,0) -> 1 | E87: =IF((E92-D92*E43/((1+E24/100)*(1+E42/100)))>0,1,0) -> 1 | F87: =IF((F92-E92*F43/((1+F24/100)*(1+F42/100)))>0,1,0) -> 1 | G87: =IF((G92-F92*G43/((1+G24/100)*(1+G42/100)))>0,1,0) -> 1 | H87: =IF((H92-G92*H43/((1+H24/100)*(1+H42/100)))>0,1,0) -> 1 | I87: =IF((I92-H92*I43/((1+I24/100)*(1+I42/100)))>0,1,0) -> 1 | J87: =IF((J92-I92*J43/((1+J24/100)*(1+J42/100)))>0,1,0) -> 1 | K87: =IF((K92-J92*K43/((1+K24/100)*(1+K42/100)))>0,1,0) -> 1 | ... U87: =IF((U92-T92*U43/((1+U24/100)*(1+U42/100)))>0,1,0) -> 1
B88: Auxiliary variable identifying whether some debt is rolled over even though debt is decreasing | D88: =IF(AND(D87=0,ABS(D92-C92*D43/((1+D24/100)*(1+D42/100)))<((C98*C92*D43/((1+D24/100)*(1+D42/100))+(D39*C92*C99*D43/((1+D24/100)*(1+D42/100)))))),1,0) -> 0 | E88: =IF(AND(E87=0,ABS(E92-D92*E43/((1+E24/100)*(1+E42/100)))<((D98*D92*E43/((1+E24/100)*(1+E42/100))+(E39*D92*D99*E43/((1+E24/100)*(1+E42/100)))))),1,0) -> 0 | F88: =IF(AND(F87=0,ABS(F92-E92*F43/((1+F24/100)*(1+F42/100)))<((E98*E92*F43/((1+F24/100)*(1+F42/100))+(F39*E92*E99*F43/((1+F24/100)*(1+F42/100)))))),1,0) -> 0 | G88: =IF(AND(G87=0,ABS(G92-F92*G43/((1+G24/100)*(1+G42/100)))<((F98*F92*G43/((1+G24/100)*(1+G42/100))+(G39*F92*F99*G43/((1+G24/100)*(1+G42/100)))))),1,0) -> 0 | H88: =IF(AND(H87=0,ABS(H92-G92*H43/((1+H24/100)*(1+H42/100)))<((G98*G92*H43/((1+H24/100)*(1+H42/100))+(H39*G92*G99*H43/((1+H24/100)*(1+H42/100)))))),1,0) -> 0 | I88: =IF(AND(I87=0,ABS(I92-H92*I43/((1+I24/100)*(1+I42/100)))<((H98*H92*I43/((1+I24/100)*(1+I42/100))+(I39*H92*H99*I43/((1+I24/100)*(1+I42/100)))))),1,0) -> 0 | J88: =IF(AND(J87=0,ABS(J92-I92*J43/((1+J24/100)*(1+J42/100)))<((I98*I92*J43/((1+J24/100)*(1+J42/100))+(J39*I92*I99*J43/((1+J24/100)*(1+J42/100)))))),1,0) -> 0 | K88: =IF(AND(K87=0,ABS(K92-J92*K43/((1+K24/100)*(1+K42/100)))<((J98*J92*K43/((1+K24/100)*(1+K42/100))+(K39*J92*J99*K43/((1+K24/100)*(1+K42/100)))))),1,0) -> 0 | ... U88: =IF(AND(U87=0,ABS(U92-T92*U43/((1+U24/100)*(1+U42/100)))<((T98*T92*U43/((1+U24/100)*(1+U42/100))+(U39*T92*T99*U43/((1+U24/100)*(1+U42/100)))))),1,0) -> 0
C91: ='Input data'!$C$5-1 -> 2025 | D91: =C91+1 -> 2026 | E91: =D91+1 -> 2027 | F91: =E91+1 -> 2028 | G91: =F91+1 -> 2029 | H91: =G91+1 -> 2030 | I91: =H91+1 -> 2031 | J91: =I91+1 -> 2032 | K91: =J91+1 -> 2033 | ... U91: =T91+1 -> 2043
B92: Gross debt | C92: =C57 -> 44.25023 | D92: =D57 -> 45.838496 | E92: =D92*(1+E106/100)*E43-E60-E61+E62+E63+E64+E65+E66+E73 -> 46.696593 | F92: =E92*(1+F106/100)*F43-F60-F61+F62+F63+F64+F65+F66+F73 -> 46.801694 | G92: =F92*(1+G106/100)*G43-G60-G61+G62+G63+G64+G65+G66+G73 -> 46.7096 | H92: =G92*(1+H106/100)*H43-H60-H61+H62+H63+H64+H65+H66+H73 -> 46.311728 | I92: =H92*(1+I106/100)*I43-I60-I61+I62+I63+I64+I65+I66+I73 -> 45.919302 | J92: =I92*(1+J106/100)*J43-J60-J61+J62+J63+J64+J65+J66+J73 -> 45.577287 | K92: =J92*(1+K106/100)*K43-K60-K61+K62+K63+K64+K65+K66+K73 -> 45.283455 | L92: =K92*(1+L106/100)*L43-L60-L61+L62+L63+L64+L65+L66+L73 -> 45.518773 | ... U92: =T92*(1+U106/100)*U43-U60-U61+U62+U63+U64+U65+U66+U73 -> 54.27264
B93: Of which Outstanding debt | C93: ='Baseline NFPC'!C88 -> 37.04973 | D93: ='Baseline NFPC'!D88 -> 38.429584 | E93: =IF(E92=0,0,IF(E87=1,D92*E43/((1+E24/100)*(1+E42/100))-E94-E95,IF(AND(E87=0,E88=1),(1-D98-E39*D99)*D92*E43/((1+E24/100)*(1+E42/100)),E92))) -> 39.58294 | F93: =IF(F92=0,0,IF(F87=1,E92*F43/((1+F24/100)*(1+F42/100))-F94-F95,IF(AND(F87=0,F88=1),(1-E98-F39*E99)*E92*F43/((1+F24/100)*(1+F42/100)),F92))) -> 40.562487 | G93: =IF(G92=0,0,IF(G87=1,F92*G43/((1+G24/100)*(1+G42/100))-G94-G95,IF(AND(G87=0,G88=1),(1-F98-G39*F99)*F92*G43/((1+G24/100)*(1+G42/100)),G92))) -> 40.685533 | H93: =IF(H92=0,0,IF(H87=1,G92*H43/((1+H24/100)*(1+H42/100))-H94-H95,IF(AND(H87=0,H88=1),(1-G98-H39*G99)*G92*H43/((1+H24/100)*(1+H42/100)),H92))) -> 40.572551 | I93: =IF(I92=0,0,IF(I87=1,H92*I43/((1+I24/100)*(1+I42/100))-I94-I95,IF(AND(I87=0,I88=1),(1-H98-I39*H99)*H92*I43/((1+I24/100)*(1+I42/100)),I92))) -> 40.082628 | J93: =IF(J92=0,0,IF(J87=1,I92*J43/((1+J24/100)*(1+J42/100))-J94-J95,IF(AND(J87=0,J88=1),(1-I98-J39*I99)*I92*J43/((1+J24/100)*(1+J42/100)),J92))) -> 39.724933 | K93: =IF(K92=0,0,IF(K87=1,J92*K43/((1+K24/100)*(1+K42/100))-K94-K95,IF(AND(K87=0,K88=1),(1-J98-K39*J99)*J92*K43/((1+K24/100)*(1+K42/100)),K92))) -> 39.412359 | L93: =IF(L92=0,0,IF(L87=1,K92*L43/((1+L24/100)*(1+L42/100))-L94-L95,IF(AND(L87=0,L88=1),(1-K98-L39*K99)*K92*L43/((1+L24/100)*(1+L42/100)),L92))) -> 39.234425 | ... U93: =IF(U92=0,0,IF(U87=1,T92*U43/((1+U24/100)*(1+U42/100))-U94-U95,IF(AND(U87=0,U88=1),(1-T98-U39*T99)*T92*U43/((1+U24/100)*(1+U42/100)),U92))) -> 45.35844
B94: Rolled over long-term debt | C94: ='Baseline NFPC'!C89 -> 2.701846 | D94: ='Baseline NFPC'!D89 -> 2.8142827 | E94: =IF(E92=0,0,IF(E87=1,E39*D92*D99*E43/((1+E24/100)*(1+E42/100)),IF(AND(E87=0,E88=1),(E39*D92*D99*E43/((1+E24/100)*(1+E42/100)))*(1-ABS(E92-D92*E43/((1+E24/100)*(1+E42/100)))/((E39*D92*D99*E43/((1+E24/100)*(1+E42/100)))+(D98*D92*E43/((1+E24/100)*(1+E42/100))))),0))) -> 2.9363306 | F94: =IF(F92=0,0,IF(F87=1,F39*E92*E99*F43/((1+F24/100)*(1+F42/100)),IF(AND(F87=0,F88=1),(F39*E92*E99*F43/((1+F24/100)*(1+F42/100)))*(1-ABS(F92-E92*F43/((1+F24/100)*(1+F42/100)))/((F39*E92*E99*F43/((1+F24/100)*(1+F42/100)))+(E98*E92*F43/((1+F24/100)*(1+F42/100))))),0))) -> 3.0475786 | G94: =IF(G92=0,0,IF(G87=1,G39*F92*F99*G43/((1+G24/100)*(1+G42/100)),IF(AND(G87=0,G88=1),(G39*F92*F99*G43/((1+G24/100)*(1+G42/100)))*(1-ABS(G92-F92*G43/((1+G24/100)*(1+G42/100)))/((G39*F92*F99*G43/((1+G24/100)*(1+G42/100)))+(F98*F92*G43/((1+G24/100)*(1+G42/100))))),0))) -> 3.0955926 | H94: =IF(H92=0,0,IF(H87=1,H39*G92*G99*H43/((1+H24/100)*(1+H42/100)),IF(AND(H87=0,H88=1),(H39*G92*G99*H43/((1+H24/100)*(1+H42/100)))*(1-ABS(H92-G92*H43/((1+H24/100)*(1+H42/100)))/((H39*G92*G99*H43/((1+H24/100)*(1+H42/100)))+(G98*G92*H43/((1+H24/100)*(1+H42/100))))),0))) -> 3.1257263 | I94: =IF(I92=0,0,IF(I87=1,I39*H92*H99*I43/((1+I24/100)*(1+I42/100)),IF(AND(I87=0,I88=1),(I39*H92*H99*I43/((1+I24/100)*(1+I42/100)))*(1-ABS(I92-H92*I43/((1+I24/100)*(1+I42/100)))/((I39*H92*H99*I43/((1+I24/100)*(1+I42/100)))+(H98*H92*I43/((1+I24/100)*(1+I42/100))))),0))) -> 3.1263127 | J94: =IF(J92=0,0,IF(J87=1,J39*I92*I99*J43/((1+J24/100)*(1+J42/100)),IF(AND(J87=0,J88=1),(J39*I92*I99*J43/((1+J24/100)*(1+J42/100)))*(1-ABS(J92-I92*J43/((1+J24/100)*(1+J42/100)))/((J39*I92*I99*J43/((1+J24/100)*(1+J42/100)))+(I98*I92*J43/((1+J24/100)*(1+J42/100))))),0))) -> 3.1364694 | K94: =IF(K92=0,0,IF(K87=1,K39*J92*J99*K43/((1+K24/100)*(1+K42/100)),IF(AND(K87=0,K88=1),(K39*J92*J99*K43/((1+K24/100)*(1+K42/100)))*(1-ABS(K92-J92*K43/((1+K24/100)*(1+K42/100)))/((K39*J92*J99*K43/((1+K24/100)*(1+K42/100)))+(J98*J92*K43/((1+K24/100)*(1+K42/100))))),0))) -> 3.1496138 | L94: =IF(L92=0,0,IF(L87=1,L39*K92*K99*L43/((1+L24/100)*(1+L42/100)),IF(AND(L87=0,L88=1),(L39*K92*K99*L43/((1+L24/100)*(1+L42/100)))*(1-ABS(L92-K92*L43/((1+L24/100)*(1+L42/100)))/((L39*K92*K99*L43/((1+L24/100)*(1+L42/100)))+(K98*K92*L43/((1+L24/100)*(1+L42/100))))),0))) -> 3.173114 | ... U94: =IF(U92=0,0,IF(U87=1,U39*T92*T99*U43/((1+U24/100)*(1+U42/100)),IF(AND(U87=0,U88=1),(U39*T92*T99*U43/((1+U24/100)*(1+U42/100)))*(1-ABS(U92-T92*U43/((1+U24/100)*(1+U42/100)))/((U39*T92*T99*U43/((1+U24/100)*(1+U42/100)))+(T98*T92*U43/((1+U24/100)*(1+U42/100))))),0))) -> 3.7120835
B95: Rolled over short-term debt | C95: ='Baseline NFPC'!C90 -> 0.9648441 | D95: ='Baseline NFPC'!D90 -> 1.0541067 | E95: =IF(E92=0,0,IF(E87=1,(1-D99)*D92*E43/((1+E24/100)*(1+E42/100)),IF(AND(E87=0,E88=1),(D98*D92*E43/((1+E24/100)*(1+E42/100)))*(1-ABS(E92-D92*E43/((1+E24/100)*(1+E42/100)))/((E39*D92*D99*E43/((1+E24/100)*(1+E42/100)))+(D98*D92*E43/((1+E24/100)*(1+E42/100))))),0))) -> 1.1354831 | F95: =IF(F92=0,0,IF(F87=1,(1-E99)*E92*F43/((1+F24/100)*(1+F42/100)),IF(AND(F87=0,F88=1),(E98*E92*F43/((1+F24/100)*(1+F42/100)))*(1-ABS(F92-E92*F43/((1+F24/100)*(1+F42/100)))/((F39*E92*E99*F43/((1+F24/100)*(1+F42/100)))+(E98*E92*F43/((1+F24/100)*(1+F42/100))))),0))) -> 1.2036258 | G95: =IF(G92=0,0,IF(G87=1,(1-F99)*F92*G43/((1+G24/100)*(1+G42/100)),IF(AND(G87=0,G88=1),(F98*F92*G43/((1+G24/100)*(1+G42/100)))*(1-ABS(G92-F92*G43/((1+G24/100)*(1+G42/100)))/((G39*F92*F99*G43/((1+G24/100)*(1+G42/100)))+(F98*F92*G43/((1+G24/100)*(1+G42/100))))),0))) -> 1.2322563 | H95: =IF(H92=0,0,IF(H87=1,(1-G99)*G92*H43/((1+H24/100)*(1+H42/100)),IF(AND(H87=0,H88=1),(G98*G92*H43/((1+H24/100)*(1+H42/100)))*(1-ABS(H92-G92*H43/((1+H24/100)*(1+H42/100)))/((H39*G92*G99*H43/((1+H24/100)*(1+H42/100)))+(G98*G92*H43/((1+H24/100)*(1+H42/100))))),0))) -> 1.2494784 | I95: =IF(I92=0,0,IF(I87=1,(1-H99)*H92*I43/((1+I24/100)*(1+I42/100)),IF(AND(I87=0,I88=1),(H98*H92*I43/((1+I24/100)*(1+I42/100)))*(1-ABS(I92-H92*I43/((1+I24/100)*(1+I42/100)))/((I39*H92*H99*I43/((1+I24/100)*(1+I42/100)))+(H98*H92*I43/((1+I24/100)*(1+I42/100))))),0))) -> 1.2506102 | J95: =IF(J92=0,0,IF(J87=1,(1-I99)*I92*J43/((1+J24/100)*(1+J42/100)),IF(AND(J87=0,J88=1),(I98*I92*J43/((1+J24/100)*(1+J42/100)))*(1-ABS(J92-I92*J43/((1+J24/100)*(1+J42/100)))/((J39*I92*I99*J43/((1+J24/100)*(1+J42/100)))+(I98*I92*J43/((1+J24/100)*(1+J42/100))))),0))) -> 1.2562779 | K95: =IF(K92=0,0,IF(K87=1,(1-J99)*J92*K43/((1+K24/100)*(1+K42/100)),IF(AND(K87=0,K88=1),(J98*J92*K43/((1+K24/100)*(1+K42/100)))*(1-ABS(K92-J92*K43/((1+K24/100)*(1+K42/100)))/((K39*J92*J99*K43/((1+K24/100)*(1+K42/100)))+(J98*J92*K43/((1+K24/100)*(1+K42/100))))),0))) -> 1.2627446 | L95: =IF(L92=0,0,IF(L87=1,(1-K99)*K92*L43/((1+L24/100)*(1+L42/100)),IF(AND(L87=0,L88=1),(K98*K92*L43/((1+L24/100)*(1+L42/100)))*(1-ABS(L92-K92*L43/((1+L24/100)*(1+L42/100)))/((L39*K92*K99*L43/((1+L24/100)*(1+L42/100)))+(K98*K92*L43/((1+L24/100)*(1+L42/100))))),0))) -> 1.2729608 | ... U95: =IF(U92=0,0,IF(U87=1,(1-T99)*T92*U43/((1+U24/100)*(1+U42/100)),IF(AND(U87=0,U88=1),(T98*T92*U43/((1+U24/100)*(1+U42/100)))*(1-ABS(U92-T92*U43/((1+U24/100)*(1+U42/100)))/((U39*T92*T99*U43/((1+U24/100)*(1+U42/100)))+(T98*T92*U43/((1+U24/100)*(1+U42/100))))),0))) -> 1.6708595
B96: New long-term debt | C96: ='Baseline NFPC'!C91 -> 3.395897 | D96: ='Baseline NFPC'!D91 -> 3.4023463 | E96: =IF(E92=0,0,IF(E87=1,'Input data'!$C$58*(E92-D92*E43/((1+E24/100)*(1+E42/100))),0)) -> 2.9231249 | F96: =IF(F92=0,0,IF(F87=1,'Input data'!$C$58*(F92-E92*F43/((1+F24/100)*(1+F42/100))),0)) -> 1.9104164 | G96: =IF(G92=0,0,IF(G87=1,'Input data'!$C$58*(G92-F92*G43/((1+G24/100)*(1+G42/100))),0)) -> 1.630019 | H96: =IF(H92=0,0,IF(H87=1,'Input data'!$C$58*(H92-G92*H43/((1+H24/100)*(1+H42/100))),0)) -> 1.3107402 | I96: =IF(I92=0,0,IF(I87=1,'Input data'!$C$58*(I92-H92*I43/((1+I24/100)*(1+I42/100))),0)) -> 1.4027807 | J96: =IF(J92=0,0,IF(J87=1,'Input data'!$C$58*(J92-I92*J43/((1+J24/100)*(1+J42/100))),0)) -> 1.4026429 | K96: =IF(K92=0,0,IF(K87=1,'Input data'!$C$58*(K92-J92*K43/((1+K24/100)*(1+K42/100))),0)) -> 1.4018072 | L96: =IF(L92=0,0,IF(L87=1,'Input data'!$C$58*(L92-K92*L43/((1+L24/100)*(1+L42/100))),0)) -> 1.7665307 | ... U96: =IF(U92=0,0,IF(U87=1,'Input data'!$C$58*(U92-T92*U43/((1+U24/100)*(1+U42/100))),0)) -> 3.3934415
B97: New short-term debt | C97: ='Baseline NFPC'!C92 -> 0.1379148 | D97: ='Baseline NFPC'!D92 -> 0.1381767 | E97: =IF(E92=0,0,IF(E87=1,'Input data'!$C$57*(E92-D92*E43/((1+E24/100)*(1+E42/100))),0)) -> 0.11871447 | F97: =IF(F92=0,0,IF(F87=1,'Input data'!$C$57*(F92-E92*F43/((1+F24/100)*(1+F42/100))),0)) -> 0.077586173 | G97: =IF(G92=0,0,IF(G87=1,'Input data'!$C$57*(G92-F92*G43/((1+G24/100)*(1+G42/100))),0)) -> 0.066198626 | H97: =IF(H92=0,0,IF(H87=1,'Input data'!$C$57*(H92-G92*H43/((1+H24/100)*(1+H42/100))),0)) -> 0.053232017 | I97: =IF(I92=0,0,IF(I87=1,'Input data'!$C$57*(I92-H92*I43/((1+I24/100)*(1+I42/100))),0)) -> 0.056969982 | J97: =IF(J92=0,0,IF(J87=1,'Input data'!$C$57*(J92-I92*J43/((1+J24/100)*(1+J42/100))),0)) -> 0.056964385 | K97: =IF(K92=0,0,IF(K87=1,'Input data'!$C$57*(K92-J92*K43/((1+K24/100)*(1+K42/100))),0)) -> 0.056930445 | L97: =IF(L92=0,0,IF(L87=1,'Input data'!$C$57*(L92-K92*L43/((1+L24/100)*(1+L42/100))),0)) -> 0.071742662 | ... U97: =IF(U92=0,0,IF(U87=1,'Input data'!$C$57*(U92-T92*U43/((1+U24/100)*(1+U42/100))),0)) -> 0.13781506
B98: Share of short-term debt in total government debt | C98: ='Baseline NFPC'!C93 -> 0.024920974 | D98: ='Baseline NFPC'!D93 -> 0.026010526 | E98: =IF(E92<>0,(E95+E97)/(E93+E94+E95+E96+E97),0) -> 0.026858439 | F98: =IF(F92<>0,(F95+F97)/(F93+F94+F95+F96+F97),0) -> 0.027375333 | G98: =IF(G92<>0,(G95+G97)/(G93+G94+G95+G96+G97),0) -> 0.02779846 | H98: =IF(H92<>0,(H95+H97)/(H93+H94+H95+H96+H97),0) -> 0.028129169 | I98: =IF(I92<>0,(I95+I97)/(I93+I94+I95+I96+I97),0) -> 0.028475612 | J98: =IF(J92<>0,(J95+J97)/(J93+J94+J95+J96+J97),0) -> 0.028813525 | K98: =IF(K92<>0,(K95+K97)/(K93+K94+K95+K96+K97),0) -> 0.029142543 | L98: =IF(L92<>0,(L95+L97)/(L93+L94+L95+L96+L97),0) -> 0.029541735 | ... U98: =IF(U92<>0,(U95+U97)/(U93+U94+U95+U96+U97),0) -> 0.033325715
B99: Share of long-term debt in total government debt | C99: ='Baseline NFPC'!C94 -> 0.97507903 | D99: ='Baseline NFPC'!D94 -> 0.97398947 | E99: =IF(E92<>0,(E93+E94+E96)/(E93+E94+E95+E96+E97),1) -> 0.97314156 | F99: =IF(F92<>0,(F93+F94+F96)/(F93+F94+F95+F96+F97),1) -> 0.97262467 | G99: =IF(G92<>0,(G93+G94+G96)/(G93+G94+G95+G96+G97),1) -> 0.97220154 | H99: =IF(H92<>0,(H93+H94+H96)/(H93+H94+H95+H96+H97),1) -> 0.97187083 | I99: =IF(I92<>0,(I93+I94+I96)/(I93+I94+I95+I96+I97),1) -> 0.97152439 | J99: =IF(J92<>0,(J93+J94+J96)/(J93+J94+J95+J96+J97),1) -> 0.97118647 | K99: =IF(K92<>0,(K93+K94+K96)/(K93+K94+K95+K96+K97),1) -> 0.97085746 | L99: =IF(L92<>0,(L93+L94+L96)/(L93+L94+L95+L96+L97),1) -> 0.97045827 | ... U99: =IF(U92<>0,(U93+U94+U96)/(U93+U94+U95+U96+U97),1) -> 0.96667429
B101: IIR | C101: ='Baseline NFPC'!C96 -> 3.196961 | D101: ='Baseline NFPC'!D96 -> 3.078103 | E101: ='Baseline NFPC'!E96 -> 2.999835 | F101: =F103+F104 -> 3.2612235 | G101: =G103+G104 -> 3.466152 | H101: =H103+H104 -> 3.6527919 | I101: =I103+I104 -> 3.8227404 | J101: =J103+J104 -> 3.9924506 | K101: =K103+K104 -> 4.1585065 | L101: =L103+L104 -> 4.3211098 | M101: =M103+M104 -> 4.4916417 | ... U101: =U103+U104 -> 5.025283
B102: Long-term implicit interest rate | E102: =IF(D$10<'Input data'!$C$4+2,((E36*D92)-(E38*(D95+D97)))/(D93+D94+D96), IF(D$10>'Input data'!$C$4+2,IF(D92>0,(D102*D93+E37*(D96+D94))/(D93+D94+D96),E37), IF(D92>0,(D102*D93+ ('Baseline NFPC'!E97*('Baseline NFPC'!D88+'Baseline NFPC'!D89+'Baseline NFPC'!D91)-'Baseline NFPC'!D97*'Baseline NFPC'!D88)/('Baseline NFPC'!D89+'Baseline NFPC'!D91) *(D96+D94))/(D93+D94+D96),E37))) -> 2.9659901 | F102: =IF(E$10<'Input data'!$C$4+2,((F36*E92)-(F38*(E95+E97)))/(E93+E94+E96), IF(E$10>'Input data'!$C$4+2,IF(E92>0,(E102*E93+F37*(E96+E94))/(E93+E94+E96),F37), IF(E92>0,(E102*E93+ ('Baseline NFPC'!F97*('Baseline NFPC'!E88+'Baseline NFPC'!E89+'Baseline NFPC'!E91)-'Baseline NFPC'!E97*'Baseline NFPC'!E88)/('Baseline NFPC'!E89+'Baseline NFPC'!E91) *(E96+E94))/(E93+E94+E96),F37))) -> 3.2330321 | G102: =IF(F$10<'Input data'!$C$4+2,((G36*F92)-(G38*(F95+F97)))/(F93+F94+F96), IF(F$10>'Input data'!$C$4+2,IF(F92>0,(F102*F93+G37*(F96+F94))/(F93+F94+F96),G37), IF(F92>0,(F102*F93+ ('Baseline NFPC'!G97*('Baseline NFPC'!F88+'Baseline NFPC'!F89+'Baseline NFPC'!F91)-'Baseline NFPC'!F97*'Baseline NFPC'!F88)/('Baseline NFPC'!F89+'Baseline NFPC'!F91) *(F96+F94))/(F93+F94+F96),G37))) -> 3.4427352 | H102: =IF(G92>0,(G102*G93+H37*(G96+G94))/(G93+G94+G96),H37) -> 3.6338972 | I102: =IF(H92>0,(H102*H93+I37*(H96+H94))/(H93+H94+H96),I37) -> 3.8080855 | J102: =IF(I92>0,(I102*I93+J37*(I96+I94))/(I93+I94+I96),J37) -> 3.9821308 | K102: =IF(J92>0,(J102*J93+K37*(J96+J94))/(J93+J94+J96),K37) -> 4.1525282 | L102: =IF(K92>0,(K102*K93+L37*(K96+K94))/(K93+K94+K96),L37) -> 4.3194777 | M102: =IF(L92>0,(L102*L93+M37*(L96+L94))/(L93+L94+L96),M37) -> 4.4947068 | N102: =IF(M92>0,(M102*M93+N37*(M96+M94))/(M93+M94+M96),N37) -> 4.64307 | O102: =IF(N92>0,(N102*N93+O37*(N96+N94))/(N93+N94+N96),O37) -> 4.7672255 | ... U102: =IF(T92>0,(T102*T93+U37*(T96+T94))/(T93+T94+T96),U37) -> 5.0794471
B103: Nominal implicit interest rate on debt (Excel approximation) | E103: =(E102*(D93+D94+D96)+E38*(D95+D97))/D92 -> 2.999835 | F103: =(F102*(E93+E94+E96)+F38*(E95+E97))/E92 -> 3.2612235 | G103: =(G102*(F93+F94+F96)+G38*(F95+F97))/F92 -> 3.466152 | H103: =(H102*(G93+G94+G96)+H38*(G95+G97))/G92 -> 3.6527919 | I103: =(I102*(H93+H94+H96)+I38*(H95+H97))/H92 -> 3.8227404 | J103: =(J102*(I93+I94+I96)+J38*(I95+I97))/I92 -> 3.9924506 | K103: =(K102*(J93+J94+J96)+K38*(J95+J97))/J92 -> 4.1585065 | L103: =(L102*(K93+K94+K96)+L38*(K95+K97))/K92 -> 4.3211098 | ... U103: =(U102*(T93+T94+T96)+U38*(T95+T97))/T92 -> 5.025283
B104: Diff. STATA | D104: =IF('Criteria results'!$F$5=4,D115,D120) -> 0 | E104: =IF('Criteria results'!$F$5=4,E115,E120) -> 0 | F104: =IF('Criteria results'!$F$5=4,F115,F120) -> 0 | G104: =IF('Criteria results'!$F$5=4,G115,G120) -> 0 | H104: =IF('Criteria results'!$F$5=4,H115,H120) -> 0 | I104: =IF('Criteria results'!$F$5=4,I115,I120) -> 0 | J104: =IF('Criteria results'!$F$5=4,J115,J120) -> 0 | K104: =IF('Criteria results'!$F$5=4,K115,K120) -> 0 | ... U104: =IF('Criteria results'!$F$5=4,U115,U120) -> 0
B106: (i - g) | C106: =((1+C101/100)/((1+C24/100)*(1+C42/100))-1)*100 -> -2.8128161 | D106: =((1+D101/100)/((1+D24/100)*(1+D42/100))-1)*100 -> -1.3622666 | E106: =((1+E101/100)/((1+E24/100)*(1+E42/100))-1)*100 -> -1.9069822 | F106: =((1+F101/100)/((1+F24/100)*(1+F42/100))-1)*100 -> -0.9024777 | G106: =((1+G101/100)/((1+G24/100)*(1+G42/100))-1)*100 -> -0.4873321 | H106: =((1+H101/100)/((1+H24/100)*(1+H42/100))-1)*100 -> -0.25689829 | I106: =((1+I101/100)/((1+I24/100)*(1+I42/100))-1)*100 -> -0.32951383 | J106: =((1+J101/100)/((1+J24/100)*(1+J42/100))-1)*100 -> -0.087644076 | ... U106: =((1+U101/100)/((1+U24/100)*(1+U42/100))-1)*100 -> 1.1322142
B110: Per memo - STATA results
B112: No extension (annual adjustment of 0.46)
B113: Debt | C113: 44.250233 | D113: 45.838497 | E113: 46.696594 | F113: 46.801701 | G113: 46.709599 | H113: 46.311726 | I113: 45.9193 | J113: 45.577286 | K113: 45.283459 | L113: 45.51878 | M113: 45.916859 | N113: 46.449821 | O113: 47.108704 | P113: 47.984657 | Q113: 48.911644 | R113: 49.956993 | S113: 51.25272 | T113: 52.694733 | U113: 54.272717
B114: IIR | C114: 3.1969614 | D114: 3.0781028 | E114: 2.9998355 | F114: 3.261224 | G114: 3.4661522 | H114: 3.652792 | I114: 3.8227403 | J114: 3.9924507 | K114: 4.1585069 | L114: 4.3211098 | M114: 4.491642 | N114: 4.6319418 | O114: 4.7485433 | P114: 4.8425188 | Q114: 4.916307 | R114: 4.9690509 | S114: 5.0036383 | T114: 5.0219998 | U114: 5.0252833
B115: IIR difference STATA - Excel | C115: 0 | D115: 0 | E115: 0 | F115: 0 | G115: 0 | H115: 0 | I115: 0 | J115: 0 | K115: 0 | L115: 0 | M115: 0 | N115: 0 | O115: 0 | P115: 0 | Q115: 0 | R115: 0 | S115: 0 | T115: 0 | U115: 0
B117: Extension (annual adjustment of 0.32)
B118: Debt | C118: 44.250233 | D118: 45.838497 | E118: 46.766987 | F118: 47.073238 | G118: 47.318947 | H118: 47.399693 | I118: 47.289162 | J118: 46.980232 | K118: 46.465614 | L118: 46.228088 | M118: 46.079475 | N118: 45.988274 | O118: 46.091789 | P118: 46.404011 | Q118: 46.759098 | R118: 47.226139 | S118: 47.936302 | T118: 48.785942 | U118: 49.765648
B119: IIR | C119: 3.1969614 | D119: 3.0781028 | E119: 2.9998355 | F119: 3.2652888 | G119: 3.4777515 | H119: 3.6750441 | I119: 3.8586292 | J119: 4.0299006 | K119: 4.1900754 | L119: 4.3401456 | M119: 4.4971328 | N119: 4.6255221 | O119: 4.7322459 | P119: 4.8197145 | Q119: 4.8899488 | R119: 4.9413939 | S119: 4.9765019 | T119: 4.9968076 | U119: 5.0029402
B120: IIR difference STATA - Excel | D120: 0 | E120: 0 | F120: 0 | G120: 0 | H120: 0 | I120: 0 | J120: 0 | K120: 0 | L120: 0 | M120: 0 | N120: 0 | O120: 0 | P120: 0 | Q120: 0 | R120: 0 | S120: 0 | T120: 0 | U120: 0

Sheet FASTOP reporting
C2: Table 7a: Debt and headline balance projections and key underlying assumptions (under the planned fiscal path)
D4: line | E4: =F4-1 -> 2024 | F4: ='Input data'!$C$5-1 -> 2025 | G4: =F4+1 -> 2026 | H4: =G4+1 -> 2027 | I4: =H4+1 -> 2028 | J4: =I4+1 -> 2029 | K4: =J4+1 -> 2030 | L4: =K4+1 -> 2031 | M4: =L4+1 -> 2032 | N4: =M4+1 -> 2033 | ... X4: =W4+1 -> 2043
B5: 1 | C5: Gross debt | D5: 57 | E5: (% GDP) | F5: =INDEX(OFFSET('Adjustment scenario'!$C$1:$U$1,$D5-1,0),MATCH(F$4,'Adjustment scenario'!$C$10:$U$10,0)) -> 44.25023 | G5: =INDEX(OFFSET('Adjustment scenario'!$C$1:$U$1,$D5-1,0),MATCH(G$4,'Adjustment scenario'!$C$10:$U$10,0)) -> 45.838496 | H5: =INDEX(OFFSET('Adjustment scenario'!$C$1:$U$1,$D5-1,0),MATCH(H$4,'Adjustment scenario'!$C$10:$U$10,0)) -> 46.696592 | I5: =INDEX(OFFSET('Adjustment scenario'!$C$1:$U$1,$D5-1,0),MATCH(I$4,'Adjustment scenario'!$C$10:$U$10,0)) -> 46.801694 | J5: =INDEX(OFFSET('Adjustment scenario'!$C$1:$U$1,$D5-1,0),MATCH(J$4,'Adjustment scenario'!$C$10:$U$10,0)) -> 46.709599 | K5: =INDEX(OFFSET('Adjustment scenario'!$C$1:$U$1,$D5-1,0),MATCH(K$4,'Adjustment scenario'!$C$10:$U$10,0)) -> 46.311727 | L5: =INDEX(OFFSET('Adjustment scenario'!$C$1:$U$1,$D5-1,0),MATCH(L$4,'Adjustment scenario'!$C$10:$U$10,0)) -> 45.919301 | M5: =INDEX(OFFSET('Adjustment scenario'!$C$1:$U$1,$D5-1,0),MATCH(M$4,'Adjustment scenario'!$C$10:$U$10,0)) -> 45.577286 | ... X5: =INDEX(OFFSET('Adjustment scenario'!$C$1:$U$1,$D5-1,0),MATCH(X$4,'Adjustment scenario'!$C$10:$U$10,0)) -> 54.272639
B6: 2 | C6: General government balance | D6: 77 | E6: (% GDP) | F6: =INDEX(OFFSET('Adjustment scenario'!$C$1:$U$1,$D6-1,0),MATCH(F$4,'Adjustment scenario'!$C$10:$U$10,0)) -> -2.147432 | G6: =INDEX(OFFSET('Adjustment scenario'!$C$1:$U$1,$D6-1,0),MATCH(G$4,'Adjustment scenario'!$C$10:$U$10,0)) -> -2.7944635 | H6: =INDEX(OFFSET('Adjustment scenario'!$C$1:$U$1,$D6-1,0),MATCH(H$4,'Adjustment scenario'!$C$10:$U$10,0)) -> -2.1918405 | I6: =INDEX(OFFSET('Adjustment scenario'!$C$1:$U$1,$D6-1,0),MATCH(I$4,'Adjustment scenario'!$C$10:$U$10,0)) -> -1.9880025 | J6: =INDEX(OFFSET('Adjustment scenario'!$C$1:$U$1,$D6-1,0),MATCH(J$4,'Adjustment scenario'!$C$10:$U$10,0)) -> -1.6962176 | K6: =INDEX(OFFSET('Adjustment scenario'!$C$1:$U$1,$D6-1,0),MATCH(K$4,'Adjustment scenario'!$C$10:$U$10,0)) -> -1.3639722 | L6: =INDEX(OFFSET('Adjustment scenario'!$C$1:$U$1,$D6-1,0),MATCH(L$4,'Adjustment scenario'!$C$10:$U$10,0)) -> -1.4597507 | M6: =INDEX(OFFSET('Adjustment scenario'!$C$1:$U$1,$D6-1,0),MATCH(M$4,'Adjustment scenario'!$C$10:$U$10,0)) -> -1.4596072 | ... X6: =INDEX(OFFSET('Adjustment scenario'!$C$1:$U$1,$D6-1,0),MATCH(X$4,'Adjustment scenario'!$C$10:$U$10,0)) -> -3.5312565
B7: 3 | C7: Structural primary balance | D7: 12 | E7: (% pot. GDP) | F7: =INDEX(OFFSET('Adjustment scenario'!$C$1:$U$1,$D7-1,0),MATCH(F$4,'Adjustment scenario'!$C$10:$U$10,0)) -> -0.5110157 | G7: =INDEX(OFFSET('Adjustment scenario'!$C$1:$U$1,$D7-1,0),MATCH(G$4,'Adjustment scenario'!$C$10:$U$10,0)) -> -1.332759 | H7: =INDEX(OFFSET('Adjustment scenario'!$C$1:$U$1,$D7-1,0),MATCH(H$4,'Adjustment scenario'!$C$10:$U$10,0)) -> -0.872759 | I7: =INDEX(OFFSET('Adjustment scenario'!$C$1:$U$1,$D7-1,0),MATCH(I$4,'Adjustment scenario'!$C$10:$U$10,0)) -> -0.412759 | J7: =INDEX(OFFSET('Adjustment scenario'!$C$1:$U$1,$D7-1,0),MATCH(J$4,'Adjustment scenario'!$C$10:$U$10,0)) -> 0.047241 | K7: =INDEX(OFFSET('Adjustment scenario'!$C$1:$U$1,$D7-1,0),MATCH(K$4,'Adjustment scenario'!$C$10:$U$10,0)) -> 0.507241 | L7: =INDEX(OFFSET('Adjustment scenario'!$C$1:$U$1,$D7-1,0),MATCH(L$4,'Adjustment scenario'!$C$10:$U$10,0)) -> 0.507241 | M7: =INDEX(OFFSET('Adjustment scenario'!$C$1:$U$1,$D7-1,0),MATCH(M$4,'Adjustment scenario'!$C$10:$U$10,0)) -> 0.507241 | ... X7: =INDEX(OFFSET('Adjustment scenario'!$C$1:$U$1,$D7-1,0),MATCH(X$4,'Adjustment scenario'!$C$10:$U$10,0)) -> 0.507241
B8: 4 | C8: Cyclical component | D8: 62 | E8: (% pot. GDP) | F8: =INDEX(OFFSET('Adjustment scenario'!$C$1:$U$1,$D8-1,0),MATCH(F$4,'Adjustment scenario'!$C$10:$U$10,0)) -> 0 | G8: =INDEX(OFFSET('Adjustment scenario'!$C$1:$U$1,$D8-1,0),MATCH(G$4,'Adjustment scenario'!$C$10:$U$10,0)) -> 0.15831162 | H8: =INDEX(OFFSET('Adjustment scenario'!$C$1:$U$1,$D8-1,0),MATCH(H$4,'Adjustment scenario'!$C$10:$U$10,0)) -> 0.0095097798 | I8: =INDEX(OFFSET('Adjustment scenario'!$C$1:$U$1,$D8-1,0),MATCH(I$4,'Adjustment scenario'!$C$10:$U$10,0)) -> 0.1137689 | J8: =INDEX(OFFSET('Adjustment scenario'!$C$1:$U$1,$D8-1,0),MATCH(J$4,'Adjustment scenario'!$C$10:$U$10,0)) -> 0.18322643 | K8: =INDEX(OFFSET('Adjustment scenario'!$C$1:$U$1,$D8-1,0),MATCH(K$4,'Adjustment scenario'!$C$10:$U$10,0)) -> 0.22936523 | L8: =INDEX(OFFSET('Adjustment scenario'!$C$1:$U$1,$D8-1,0),MATCH(L$4,'Adjustment scenario'!$C$10:$U$10,0)) -> 0.15291015 | M8: =INDEX(OFFSET('Adjustment scenario'!$C$1:$U$1,$D8-1,0),MATCH(M$4,'Adjustment scenario'!$C$10:$U$10,0)) -> 0.076455076 | ... X8: =INDEX(OFFSET('Adjustment scenario'!$C$1:$U$1,$D8-1,0),MATCH(X$4,'Adjustment scenario'!$C$10:$U$10,0)) -> -8.5755887e-06
B9: 5 | C9: One-off measures | D9: 14 | E9: (% GDP) | F9: =INDEX(OFFSET('Adjustment scenario'!$C$1:$U$1,$D9-1,0),MATCH(F$4,'Adjustment scenario'!$C$10:$U$10,0)) -> -0.1168709 | G9: =INDEX(OFFSET('Adjustment scenario'!$C$1:$U$1,$D9-1,0),MATCH(G$4,'Adjustment scenario'!$C$10:$U$10,0)) -> 0 | H9: =INDEX(OFFSET('Adjustment scenario'!$C$1:$U$1,$D9-1,0),MATCH(H$4,'Adjustment scenario'!$C$10:$U$10,0)) -> 0 | I9: =INDEX(OFFSET('Adjustment scenario'!$C$1:$U$1,$D9-1,0),MATCH(I$4,'Adjustment scenario'!$C$10:$U$10,0)) -> 0 | J9: =INDEX(OFFSET('Adjustment scenario'!$C$1:$U$1,$D9-1,0),MATCH(J$4,'Adjustment scenario'!$C$10:$U$10,0)) -> 0 | K9: =INDEX(OFFSET('Adjustment scenario'!$C$1:$U$1,$D9-1,0),MATCH(K$4,'Adjustment scenario'!$C$10:$U$10,0)) -> 0 | L9: =INDEX(OFFSET('Adjustment scenario'!$C$1:$U$1,$D9-1,0),MATCH(L$4,'Adjustment scenario'!$C$10:$U$10,0)) -> 0 | M9: =INDEX(OFFSET('Adjustment scenario'!$C$1:$U$1,$D9-1,0),MATCH(M$4,'Adjustment scenario'!$C$10:$U$10,0)) -> 0 | ... X9: =INDEX(OFFSET('Adjustment scenario'!$C$1:$U$1,$D9-1,0),MATCH(X$4,'Adjustment scenario'!$C$10:$U$10,0)) -> 0
B10: 6 | C10: Interest expenditure | D10: 68 | E10: (% GDP) | F10: =INDEX(OFFSET('Adjustment scenario'!$C$1:$U$1,$D10-1,0),MATCH(F$4,'Adjustment scenario'!$C$10:$U$10,0)) -> 0 | G10: =INDEX(OFFSET('Adjustment scenario'!$C$1:$U$1,$D10-1,0),MATCH(G$4,'Adjustment scenario'!$C$10:$U$10,0)) -> 1.3033929 | H10: =INDEX(OFFSET('Adjustment scenario'!$C$1:$U$1,$D10-1,0),MATCH(H$4,'Adjustment scenario'!$C$10:$U$10,0)) -> 1.3095718 | I10: =INDEX(OFFSET('Adjustment scenario'!$C$1:$U$1,$D10-1,0),MATCH(I$4,'Adjustment scenario'!$C$10:$U$10,0)) -> 1.4614746 | J10: =INDEX(OFFSET('Adjustment scenario'!$C$1:$U$1,$D10-1,0),MATCH(J$4,'Adjustment scenario'!$C$10:$U$10,0)) -> 1.5602322 | K10: =INDEX(OFFSET('Adjustment scenario'!$C$1:$U$1,$D10-1,0),MATCH(K$4,'Adjustment scenario'!$C$10:$U$10,0)) -> 1.641848 | L10: =INDEX(OFFSET('Adjustment scenario'!$C$1:$U$1,$D10-1,0),MATCH(L$4,'Adjustment scenario'!$C$10:$U$10,0)) -> 1.6995732 | M10: =INDEX(OFFSET('Adjustment scenario'!$C$1:$U$1,$D10-1,0),MATCH(M$4,'Adjustment scenario'!$C$10:$U$10,0)) -> 1.7613766 | ... X10: =INDEX(OFFSET('Adjustment scenario'!$C$1:$U$1,$D10-1,0),MATCH(X$4,'Adjustment scenario'!$C$10:$U$10,0)) -> 2.5498981
B11: 7 | C11: Long-term interest rate | D11: 37 | E11: (%) | F11: =INDEX(OFFSET('Adjustment scenario'!$C$1:$U$1,$D11-1,0),MATCH(F$4,'Adjustment scenario'!$C$10:$U$10,0)) -> 4.29 | G11: =INDEX(OFFSET('Adjustment scenario'!$C$1:$U$1,$D11-1,0),MATCH(G$4,'Adjustment scenario'!$C$10:$U$10,0)) -> 4.701964 | H11: =INDEX(OFFSET('Adjustment scenario'!$C$1:$U$1,$D11-1,0),MATCH(H$4,'Adjustment scenario'!$C$10:$U$10,0)) -> 4.915649 | I11: =INDEX(OFFSET('Adjustment scenario'!$C$1:$U$1,$D11-1,0),MATCH(I$4,'Adjustment scenario'!$C$10:$U$10,0)) -> 5.0370066 | J11: =INDEX(OFFSET('Adjustment scenario'!$C$1:$U$1,$D11-1,0),MATCH(J$4,'Adjustment scenario'!$C$10:$U$10,0)) -> 5.1583642 | K11: =INDEX(OFFSET('Adjustment scenario'!$C$1:$U$1,$D11-1,0),MATCH(K$4,'Adjustment scenario'!$C$10:$U$10,0)) -> 5.2797219 | L11: =INDEX(OFFSET('Adjustment scenario'!$C$1:$U$1,$D11-1,0),MATCH(L$4,'Adjustment scenario'!$C$10:$U$10,0)) -> 5.4010795 | M11: =INDEX(OFFSET('Adjustment scenario'!$C$1:$U$1,$D11-1,0),MATCH(M$4,'Adjustment scenario'!$C$10:$U$10,0)) -> 5.5224371 | ... X11: =INDEX(OFFSET('Adjustment scenario'!$C$1:$U$1,$D11-1,0),MATCH(X$4,'Adjustment scenario'!$C$10:$U$10,0)) -> 5.131906
B12: 8 | C12: Short-term interest rate | D12: 38 | E12: (%) | F12: =INDEX(OFFSET('Adjustment scenario'!$C$1:$U$1,$D12-1,0),MATCH(F$4,'Adjustment scenario'!$C$10:$U$10,0)) -> 3.6 | G12: =INDEX(OFFSET('Adjustment scenario'!$C$1:$U$1,$D12-1,0),MATCH(G$4,'Adjustment scenario'!$C$10:$U$10,0)) -> 3.649853 | H12: =INDEX(OFFSET('Adjustment scenario'!$C$1:$U$1,$D12-1,0),MATCH(H$4,'Adjustment scenario'!$C$10:$U$10,0)) -> 4.267191 | I12: =INDEX(OFFSET('Adjustment scenario'!$C$1:$U$1,$D12-1,0),MATCH(I$4,'Adjustment scenario'!$C$10:$U$10,0)) -> 4.2826609 | J12: =INDEX(OFFSET('Adjustment scenario'!$C$1:$U$1,$D12-1,0),MATCH(J$4,'Adjustment scenario'!$C$10:$U$10,0)) -> 4.2981308 | K12: =INDEX(OFFSET('Adjustment scenario'!$C$1:$U$1,$D12-1,0),MATCH(K$4,'Adjustment scenario'!$C$10:$U$10,0)) -> 4.3136006 | L12: =INDEX(OFFSET('Adjustment scenario'!$C$1:$U$1,$D12-1,0),MATCH(L$4,'Adjustment scenario'!$C$10:$U$10,0)) -> 4.3290705 | M12: =INDEX(OFFSET('Adjustment scenario'!$C$1:$U$1,$D12-1,0),MATCH(M$4,'Adjustment scenario'!$C$10:$U$10,0)) -> 4.3445404 | ... X12: =INDEX(OFFSET('Adjustment scenario'!$C$1:$U$1,$D12-1,0),MATCH(X$4,'Adjustment scenario'!$C$10:$U$10,0)) -> 3.43457
B13: 9 | C13: Implicit average interest rate | D13: 36 | E13: (%) | F13: =INDEX(OFFSET('Adjustment scenario'!$C$1:$U$1,$D13-1,0),MATCH(F$4,'Adjustment scenario'!$C$10:$U$10,0)) -> 3.196961 | G13: =INDEX(OFFSET('Adjustment scenario'!$C$1:$U$1,$D13-1,0),MATCH(G$4,'Adjustment scenario'!$C$10:$U$10,0)) -> 3.078103 | H13: =INDEX(OFFSET('Adjustment scenario'!$C$1:$U$1,$D13-1,0),MATCH(H$4,'Adjustment scenario'!$C$10:$U$10,0)) -> 2.999835 | I13: =INDEX(OFFSET('Adjustment scenario'!$C$1:$U$1,$D13-1,0),MATCH(I$4,'Adjustment scenario'!$C$10:$U$10,0)) -> 3.2612235 | J13: =INDEX(OFFSET('Adjustment scenario'!$C$1:$U$1,$D13-1,0),MATCH(J$4,'Adjustment scenario'!$C$10:$U$10,0)) -> 3.466152 | K13: =INDEX(OFFSET('Adjustment scenario'!$C$1:$U$1,$D13-1,0),MATCH(K$4,'Adjustment scenario'!$C$10:$U$10,0)) -> 3.6527919 | L13: =INDEX(OFFSET('Adjustment scenario'!$C$1:$U$1,$D13-1,0),MATCH(L$4,'Adjustment scenario'!$C$10:$U$10,0)) -> 3.8227404 | M13: =INDEX(OFFSET('Adjustment scenario'!$C$1:$U$1,$D13-1,0),MATCH(M$4,'Adjustment scenario'!$C$10:$U$10,0)) -> 3.9924506 | ... X13: =INDEX(OFFSET('Adjustment scenario'!$C$1:$U$1,$D13-1,0),MATCH(X$4,'Adjustment scenario'!$C$10:$U$10,0)) -> 5.025283
B14: 10 | C14: Stock-flow adjustment | D14: 72 | E14: (% GDP) | F14: =INDEX(OFFSET('Adjustment scenario'!$C$1:$U$1,$D14-1,0),MATCH(F$4,'Adjustment scenario'!$C$10:$U$10,0)) -> 0 | G14: =INDEX(OFFSET('Adjustment scenario'!$C$1:$U$1,$D14-1,0),MATCH(G$4,'Adjustment scenario'!$C$10:$U$10,0)) -> 0.7014194 | H14: =INDEX(OFFSET('Adjustment scenario'!$C$1:$U$1,$D14-1,0),MATCH(H$4,'Adjustment scenario'!$C$10:$U$10,0)) -> 0.8499599 | I14: =INDEX(OFFSET('Adjustment scenario'!$C$1:$U$1,$D14-1,0),MATCH(I$4,'Adjustment scenario'!$C$10:$U$10,0)) -> 0 | J14: =INDEX(OFFSET('Adjustment scenario'!$C$1:$U$1,$D14-1,0),MATCH(J$4,'Adjustment scenario'!$C$10:$U$10,0)) -> 0 | K14: =INDEX(OFFSET('Adjustment scenario'!$C$1:$U$1,$D14-1,0),MATCH(K$4,'Adjustment scenario'!$C$10:$U$10,0)) -> 0 | L14: =INDEX(OFFSET('Adjustment scenario'!$C$1:$U$1,$D14-1,0),MATCH(L$4,'Adjustment scenario'!$C$10:$U$10,0)) -> 0 | M14: =INDEX(OFFSET('Adjustment scenario'!$C$1:$U$1,$D14-1,0),MATCH(M$4,'Adjustment scenario'!$C$10:$U$10,0)) -> 0 | ... X14: =INDEX(OFFSET('Adjustment scenario'!$C$1:$U$1,$D14-1,0),MATCH(X$4,'Adjustment scenario'!$C$10:$U$10,0)) -> 0
B15: 11 | C15: Potential GDP | D15: 27 | E15: (growth rate) | F15: ='Input data'!C$33 -> 1.560683 | G15: =(INDEX(OFFSET('Adjustment scenario'!$C$1:$U$1,$D15-1,0),MATCH(G$4,'Adjustment scenario'!$C$10:$U$10,0))/INDEX(OFFSET('Adjustment scenario'!$C$1:$U$1,$D15-1,0),MATCH(F$4,'Adjustment scenario'!$C$10:$U$10,0))-1)*100 -> 1.64766 | H15: =(INDEX(OFFSET('Adjustment scenario'!$C$1:$U$1,$D15-1,0),MATCH(H$4,'Adjustment scenario'!$C$10:$U$10,0))/INDEX(OFFSET('Adjustment scenario'!$C$1:$U$1,$D15-1,0),MATCH(G$4,'Adjustment scenario'!$C$10:$U$10,0))-1)*100 -> 1.492104 | I15: =(INDEX(OFFSET('Adjustment scenario'!$C$1:$U$1,$D15-1,0),MATCH(I$4,'Adjustment scenario'!$C$10:$U$10,0))/INDEX(OFFSET('Adjustment scenario'!$C$1:$U$1,$D15-1,0),MATCH(H$4,'Adjustment scenario'!$C$10:$U$10,0))-1)*100 -> 1.456502 | J15: =(INDEX(OFFSET('Adjustment scenario'!$C$1:$U$1,$D15-1,0),MATCH(J$4,'Adjustment scenario'!$C$10:$U$10,0))/INDEX(OFFSET('Adjustment scenario'!$C$1:$U$1,$D15-1,0),MATCH(I$4,'Adjustment scenario'!$C$10:$U$10,0))-1)*100 -> 1.234396 | K15: =(INDEX(OFFSET('Adjustment scenario'!$C$1:$U$1,$D15-1,0),MATCH(K$4,'Adjustment scenario'!$C$10:$U$10,0))/INDEX(OFFSET('Adjustment scenario'!$C$1:$U$1,$D15-1,0),MATCH(J$4,'Adjustment scenario'!$C$10:$U$10,0))-1)*100 -> 1.212544 | L15: =(INDEX(OFFSET('Adjustment scenario'!$C$1:$U$1,$D15-1,0),MATCH(L$4,'Adjustment scenario'!$C$10:$U$10,0))/INDEX(OFFSET('Adjustment scenario'!$C$1:$U$1,$D15-1,0),MATCH(K$4,'Adjustment scenario'!$C$10:$U$10,0))-1)*100 -> 1.226088 | M15: =(INDEX(OFFSET('Adjustment scenario'!$C$1:$U$1,$D15-1,0),MATCH(M$4,'Adjustment scenario'!$C$10:$U$10,0))/INDEX(OFFSET('Adjustment scenario'!$C$1:$U$1,$D15-1,0),MATCH(L$4,'Adjustment scenario'!$C$10:$U$10,0))-1)*100 -> 1.236266 | N15: =(INDEX(OFFSET('Adjustment scenario'!$C$1:$U$1,$D15-1,0),MATCH(N$4,'Adjustment scenario'!$C$10:$U$10,0))/INDEX(OFFSET('Adjustment scenario'!$C$1:$U$1,$D15-1,0),MATCH(M$4,'Adjustment scenario'!$C$10:$U$10,0))-1)*100 -> 1.2442 | ... X15: =(INDEX(OFFSET('Adjustment scenario'!$C$1:$U$1,$D15-1,0),MATCH(X$4,'Adjustment scenario'!$C$10:$U$10,0))/INDEX(OFFSET('Adjustment scenario'!$C$1:$U$1,$D15-1,0),MATCH(W$4,'Adjustment scenario'!$C$10:$U$10,0))-1)*100 -> 1.61
B16: 12 | C16: Real GDP | D16: 24 | E16: (growth rate) | F16: =INDEX(OFFSET('Adjustment scenario'!$C$1:$U$1,$D16-1,0),MATCH(F$4,'Adjustment scenario'!$C$10:$U$10,0)) -> 2.580467 | G16: =INDEX(OFFSET('Adjustment scenario'!$C$1:$U$1,$D16-1,0),MATCH(G$4,'Adjustment scenario'!$C$10:$U$10,0)) -> 1.79727 | H16: =INDEX(OFFSET('Adjustment scenario'!$C$1:$U$1,$D16-1,0),MATCH(H$4,'Adjustment scenario'!$C$10:$U$10,0)) -> 1.875977 | I16: =INDEX(OFFSET('Adjustment scenario'!$C$1:$U$1,$D16-1,0),MATCH(I$4,'Adjustment scenario'!$C$10:$U$10,0)) -> 1.188646 | J16: =INDEX(OFFSET('Adjustment scenario'!$C$1:$U$1,$D16-1,0),MATCH(J$4,'Adjustment scenario'!$C$10:$U$10,0)) -> 1.0558694 | K16: =INDEX(OFFSET('Adjustment scenario'!$C$1:$U$1,$D16-1,0),MATCH(K$4,'Adjustment scenario'!$C$10:$U$10,0)) -> 1.0937696 | L16: =INDEX(OFFSET('Adjustment scenario'!$C$1:$U$1,$D16-1,0),MATCH(L$4,'Adjustment scenario'!$C$10:$U$10,0)) -> 1.4231627 | M16: =INDEX(OFFSET('Adjustment scenario'!$C$1:$U$1,$D16-1,0),MATCH(M$4,'Adjustment scenario'!$C$10:$U$10,0)) -> 1.4329775 | ... X16: =INDEX(OFFSET('Adjustment scenario'!$C$1:$U$1,$D16-1,0),MATCH(X$4,'Adjustment scenario'!$C$10:$U$10,0)) -> 1.61
B17: 13 | C17: GDP deflator | D17: 42 | E17: (growth rate) | F17: =INDEX(OFFSET('Adjustment scenario'!$C$1:$U$1,$D17-1,0),MATCH(F$4,'Adjustment scenario'!$C$10:$U$10,0)) -> 3.512605 | G17: =INDEX(OFFSET('Adjustment scenario'!$C$1:$U$1,$D17-1,0),MATCH(G$4,'Adjustment scenario'!$C$10:$U$10,0)) -> 2.656677 | H17: =INDEX(OFFSET('Adjustment scenario'!$C$1:$U$1,$D17-1,0),MATCH(H$4,'Adjustment scenario'!$C$10:$U$10,0)) -> 3.068664 | I17: =INDEX(OFFSET('Adjustment scenario'!$C$1:$U$1,$D17-1,0),MATCH(I$4,'Adjustment scenario'!$C$10:$U$10,0)) -> 2.977581 | J17: =INDEX(OFFSET('Adjustment scenario'!$C$1:$U$1,$D17-1,0),MATCH(J$4,'Adjustment scenario'!$C$10:$U$10,0)) -> 2.886498 | K17: =INDEX(OFFSET('Adjustment scenario'!$C$1:$U$1,$D17-1,0),MATCH(K$4,'Adjustment scenario'!$C$10:$U$10,0)) -> 2.795415 | L17: =INDEX(OFFSET('Adjustment scenario'!$C$1:$U$1,$D17-1,0),MATCH(L$4,'Adjustment scenario'!$C$10:$U$10,0)) -> 2.704332 | M17: =INDEX(OFFSET('Adjustment scenario'!$C$1:$U$1,$D17-1,0),MATCH(M$4,'Adjustment scenario'!$C$10:$U$10,0)) -> 2.613249 | ... X17: =INDEX(OFFSET('Adjustment scenario'!$C$1:$U$1,$D17-1,0),MATCH(X$4,'Adjustment scenario'!$C$10:$U$10,0)) -> 2.204
B18: 14 | C18: Nominal GDP | D18: 33 | E18: (growth rate) | F18: =INDEX(OFFSET('Adjustment scenario'!$C$1:$U$1,$D18-1,0),MATCH(F$4,'Adjustment scenario'!$C$10:$U$10,0)) -> 6.1837136 | G18: =INDEX(OFFSET('Adjustment scenario'!$C$1:$U$1,$D18-1,0),MATCH(G$4,'Adjustment scenario'!$C$10:$U$10,0)) -> 4.5016947 | H18: =INDEX(OFFSET('Adjustment scenario'!$C$1:$U$1,$D18-1,0),MATCH(H$4,'Adjustment scenario'!$C$10:$U$10,0)) -> 5.0022084 | I18: =INDEX(OFFSET('Adjustment scenario'!$C$1:$U$1,$D18-1,0),MATCH(I$4,'Adjustment scenario'!$C$10:$U$10,0)) -> 4.2016199 | J18: =INDEX(OFFSET('Adjustment scenario'!$C$1:$U$1,$D18-1,0),MATCH(J$4,'Adjustment scenario'!$C$10:$U$10,0)) -> 3.972845 | K18: =INDEX(OFFSET('Adjustment scenario'!$C$1:$U$1,$D18-1,0),MATCH(K$4,'Adjustment scenario'!$C$10:$U$10,0)) -> 3.91976 | L18: =INDEX(OFFSET('Adjustment scenario'!$C$1:$U$1,$D18-1,0),MATCH(L$4,'Adjustment scenario'!$C$10:$U$10,0)) -> 4.1659817 | M18: =INDEX(OFFSET('Adjustment scenario'!$C$1:$U$1,$D18-1,0),MATCH(M$4,'Adjustment scenario'!$C$10:$U$10,0)) -> 4.0836738 | ... X18: =INDEX(OFFSET('Adjustment scenario'!$C$1:$U$1,$D18-1,0),MATCH(X$4,'Adjustment scenario'!$C$10:$U$10,0)) -> 3.8494844
C20: Table 7b: Debt projections and key stressed variables, deterministic scenarios and stochastic simulations
C22: Financial stress scenario | E22: =F22-1 -> -1
B23: 1 | C23: Gross debt | D23: 56 | E23: (% GDP)
B24: 2 | C24: Long-term interest rate | D24: 36 | E24: (%)
B25: 3 | C25: Short-term interest rate | D25: 37 | E25: (%)
C26: Lower SPB scenario | E26: =F26-1 -> -1
B27: 4 | C27: Gross debt | D27: 56 | E27: (% GDP)
B28: 5 | C28: Structural primary balance | D28: 12 | E28: (% pot. GDP)
C29: Adverse 'r-g' scenario | E29: =F29-1 -> -1
B30: 6 | C30: Gross debt | D30: 57 | E30: (% GDP)
B31: 7 | C31: Long-term interest rate | D31: 37 | E31: (%)
B32: 8 | C32: Short-term interest rate | D32: 38 | E32: (%)
B33: 9 | C33: Real GDP | D33: 23 | E33: (growth rate)
B34: 10 | C34: Potential GDP | D34: 27 | E34: (growth rate)
C35: Stochastic simulations | E35: =F35-1 -> -1
B36: 11 | C36: Probability of debt being below its value in T+4/7 | D36: approximation | E36: (%)
C38: Table 7c: Debt and headline balance projections and underlying assumptions (under 'no-fiscal-policy-change' baseline)
F40: ='Input data'!$C$5-1 -> 2025 | G40: =F40+1 -> 2026 | H40: =G40+1 -> 2027 | I40: =H40+1 -> 2028 | J40: =I40+1 -> 2029 | K40: =J40+1 -> 2030 | L40: =K40+1 -> 2031 | M40: =L40+1 -> 2032 | N40: =M40+1 -> 2033 | ... X40: =W40+1 -> 2043
B41: 1 | C41: Gross debt | D41: 56 | E41: (% GDP) | F41: =INDEX(OFFSET('Baseline NFPC'!$C$1:$U$1,$D41-1,0),MATCH(F$4,'Baseline NFPC'!$C$10:$U$10,0)) -> 44.25023 | G41: =INDEX(OFFSET('Baseline NFPC'!$C$1:$U$1,$D41-1,0),MATCH(G$4,'Baseline NFPC'!$C$10:$U$10,0)) -> 45.838496 | H41: =INDEX(OFFSET('Baseline NFPC'!$C$1:$U$1,$D41-1,0),MATCH(H$4,'Baseline NFPC'!$C$10:$U$10,0)) -> 47.042627 | I41: =INDEX(OFFSET('Baseline NFPC'!$C$1:$U$1,$D41-1,0),MATCH(I$4,'Baseline NFPC'!$C$10:$U$10,0)) -> 48.037875 | J41: =INDEX(OFFSET('Baseline NFPC'!$C$1:$U$1,$D41-1,0),MATCH(J$4,'Baseline NFPC'!$C$10:$U$10,0)) -> 49.449014 | K41: =INDEX(OFFSET('Baseline NFPC'!$C$1:$U$1,$D41-1,0),MATCH(K$4,'Baseline NFPC'!$C$10:$U$10,0)) -> 51.025602 | L41: =INDEX(OFFSET('Baseline NFPC'!$C$1:$U$1,$D41-1,0),MATCH(L$4,'Baseline NFPC'!$C$10:$U$10,0)) -> 52.830767 | M41: =INDEX(OFFSET('Baseline NFPC'!$C$1:$U$1,$D41-1,0),MATCH(M$4,'Baseline NFPC'!$C$10:$U$10,0)) -> 54.798962 | ... X41: =INDEX(OFFSET('Baseline NFPC'!$C$1:$U$1,$D41-1,0),MATCH(X$4,'Baseline NFPC'!$C$10:$U$10,0)) -> 91.692976
B42: 2 | C42: General government balance | D42: 76 | E42: (% GDP) | F42: =INDEX(OFFSET('Baseline NFPC'!$C$1:$U$1,$D42-1,0),MATCH(F$4,'Baseline NFPC'!$C$10:$U$10,0)) -> -2.147432 | G42: =INDEX(OFFSET('Baseline NFPC'!$C$1:$U$1,$D42-1,0),MATCH(G$4,'Baseline NFPC'!$C$10:$U$10,0)) -> -2.7944635 | H42: =INDEX(OFFSET('Baseline NFPC'!$C$1:$U$1,$D42-1,0),MATCH(H$4,'Baseline NFPC'!$C$10:$U$10,0)) -> -2.6558245 | I42: =INDEX(OFFSET('Baseline NFPC'!$C$1:$U$1,$D42-1,0),MATCH(I$4,'Baseline NFPC'!$C$10:$U$10,0)) -> -2.9743138 | J42: =INDEX(OFFSET('Baseline NFPC'!$C$1:$U$1,$D42-1,0),MATCH(J$4,'Baseline NFPC'!$C$10:$U$10,0)) -> -3.2776032 | K42: =INDEX(OFFSET('Baseline NFPC'!$C$1:$U$1,$D42-1,0),MATCH(K$4,'Baseline NFPC'!$C$10:$U$10,0)) -> -3.4715403 | L42: =INDEX(OFFSET('Baseline NFPC'!$C$1:$U$1,$D42-1,0),MATCH(L$4,'Baseline NFPC'!$C$10:$U$10,0)) -> -3.7504978 | M42: =INDEX(OFFSET('Baseline NFPC'!$C$1:$U$1,$D42-1,0),MATCH(M$4,'Baseline NFPC'!$C$10:$U$10,0)) -> -3.9423581 | ... X42: =INDEX(OFFSET('Baseline NFPC'!$C$1:$U$1,$D42-1,0),MATCH(X$4,'Baseline NFPC'!$C$10:$U$10,0)) -> -7.5153323
B43: 3 | C43: Structural primary balance | D43: 12 | E43: (% pot. GDP) | F43: =INDEX(OFFSET('Baseline NFPC'!$C$1:$U$1,$D43-1,0),MATCH(F$4,'Baseline NFPC'!$C$10:$U$10,0)) -> -0.5110157 | G43: =INDEX(OFFSET('Baseline NFPC'!$C$1:$U$1,$D43-1,0),MATCH(G$4,'Baseline NFPC'!$C$10:$U$10,0)) -> -1.332759 | H43: =INDEX(OFFSET('Baseline NFPC'!$C$1:$U$1,$D43-1,0),MATCH(H$4,'Baseline NFPC'!$C$10:$U$10,0)) -> -1.332759 | I43: =INDEX(OFFSET('Baseline NFPC'!$C$1:$U$1,$D43-1,0),MATCH(I$4,'Baseline NFPC'!$C$10:$U$10,0)) -> -1.332759 | J43: =INDEX(OFFSET('Baseline NFPC'!$C$1:$U$1,$D43-1,0),MATCH(J$4,'Baseline NFPC'!$C$10:$U$10,0)) -> -1.332759 | K43: =INDEX(OFFSET('Baseline NFPC'!$C$1:$U$1,$D43-1,0),MATCH(K$4,'Baseline NFPC'!$C$10:$U$10,0)) -> -1.332759 | L43: =INDEX(OFFSET('Baseline NFPC'!$C$1:$U$1,$D43-1,0),MATCH(L$4,'Baseline NFPC'!$C$10:$U$10,0)) -> -1.332759 | M43: =INDEX(OFFSET('Baseline NFPC'!$C$1:$U$1,$D43-1,0),MATCH(M$4,'Baseline NFPC'!$C$10:$U$10,0)) -> -1.332759 | ... X43: =INDEX(OFFSET('Baseline NFPC'!$C$1:$U$1,$D43-1,0),MATCH(X$4,'Baseline NFPC'!$C$10:$U$10,0)) -> -1.332759
B44: 4 | C44: Cyclical component | D44: 61 | E44: (% pot. GDP) | F44: =INDEX(OFFSET('Baseline NFPC'!$C$1:$U$1,$D44-1,0),MATCH(F$4,'Baseline NFPC'!$C$10:$U$10,0)) -> 0 | G44: =INDEX(OFFSET('Baseline NFPC'!$C$1:$U$1,$D44-1,0),MATCH(G$4,'Baseline NFPC'!$C$10:$U$10,0)) -> 0.15831162 | H44: =INDEX(OFFSET('Baseline NFPC'!$C$1:$U$1,$D44-1,0),MATCH(H$4,'Baseline NFPC'!$C$10:$U$10,0)) -> -0.097476927 | I44: =INDEX(OFFSET('Baseline NFPC'!$C$1:$U$1,$D44-1,0),MATCH(I$4,'Baseline NFPC'!$C$10:$U$10,0)) -> -0.064984879 | J44: =INDEX(OFFSET('Baseline NFPC'!$C$1:$U$1,$D44-1,0),MATCH(J$4,'Baseline NFPC'!$C$10:$U$10,0)) -> -0.021658744 | K44: =INDEX(OFFSET('Baseline NFPC'!$C$1:$U$1,$D44-1,0),MATCH(K$4,'Baseline NFPC'!$C$10:$U$10,0)) -> 5.0159843e-07 | L44: =INDEX(OFFSET('Baseline NFPC'!$C$1:$U$1,$D44-1,0),MATCH(L$4,'Baseline NFPC'!$C$10:$U$10,0)) -> 1.6722452e-06 | M44: =INDEX(OFFSET('Baseline NFPC'!$C$1:$U$1,$D44-1,0),MATCH(M$4,'Baseline NFPC'!$C$10:$U$10,0)) -> 8.9189251e-07 | ... X44: =INDEX(OFFSET('Baseline NFPC'!$C$1:$U$1,$D44-1,0),MATCH(X$4,'Baseline NFPC'!$C$10:$U$10,0)) -> -6.1231125e-06
B45: 5 | C45: Interest expenditure | D45: 67 | E45: (% GDP) | F45: =INDEX(OFFSET('Baseline NFPC'!$C$1:$U$1,$D45-1,0),MATCH(F$4,'Baseline NFPC'!$C$10:$U$10,0)) -> 0 | G45: =INDEX(OFFSET('Baseline NFPC'!$C$1:$U$1,$D45-1,0),MATCH(G$4,'Baseline NFPC'!$C$10:$U$10,0)) -> 1.3033929 | H45: =INDEX(OFFSET('Baseline NFPC'!$C$1:$U$1,$D45-1,0),MATCH(H$4,'Baseline NFPC'!$C$10:$U$10,0)) -> 1.3060335 | I45: =INDEX(OFFSET('Baseline NFPC'!$C$1:$U$1,$D45-1,0),MATCH(I$4,'Baseline NFPC'!$C$10:$U$10,0)) -> 1.4775228 | J45: =INDEX(OFFSET('Baseline NFPC'!$C$1:$U$1,$D45-1,0),MATCH(J$4,'Baseline NFPC'!$C$10:$U$10,0)) -> 1.6229777 | K45: =INDEX(OFFSET('Baseline NFPC'!$C$1:$U$1,$D45-1,0),MATCH(K$4,'Baseline NFPC'!$C$10:$U$10,0)) -> 1.7807473 | L45: =INDEX(OFFSET('Baseline NFPC'!$C$1:$U$1,$D45-1,0),MATCH(L$4,'Baseline NFPC'!$C$10:$U$10,0)) -> 1.9451953 | M45: =INDEX(OFFSET('Baseline NFPC'!$C$1:$U$1,$D45-1,0),MATCH(M$4,'Baseline NFPC'!$C$10:$U$10,0)) -> 2.1225481 | ... X45: =INDEX(OFFSET('Baseline NFPC'!$C$1:$U$1,$D45-1,0),MATCH(X$4,'Baseline NFPC'!$C$10:$U$10,0)) -> 4.335938
B46: 6 | C46: Long-term interest rate | D46: 36 | E46: (%) | F46: =INDEX(OFFSET('Baseline NFPC'!$C$1:$U$1,$D46-1,0),MATCH(F$4,'Baseline NFPC'!$C$10:$U$10,0)) -> 4.29 | G46: =INDEX(OFFSET('Baseline NFPC'!$C$1:$U$1,$D46-1,0),MATCH(G$4,'Baseline NFPC'!$C$10:$U$10,0)) -> 4.701964 | H46: =INDEX(OFFSET('Baseline NFPC'!$C$1:$U$1,$D46-1,0),MATCH(H$4,'Baseline NFPC'!$C$10:$U$10,0)) -> 4.915649 | I46: =INDEX(OFFSET('Baseline NFPC'!$C$1:$U$1,$D46-1,0),MATCH(I$4,'Baseline NFPC'!$C$10:$U$10,0)) -> 5.0370066 | J46: =INDEX(OFFSET('Baseline NFPC'!$C$1:$U$1,$D46-1,0),MATCH(J$4,'Baseline NFPC'!$C$10:$U$10,0)) -> 5.1583642 | K46: =INDEX(OFFSET('Baseline NFPC'!$C$1:$U$1,$D46-1,0),MATCH(K$4,'Baseline NFPC'!$C$10:$U$10,0)) -> 5.2797219 | L46: =INDEX(OFFSET('Baseline NFPC'!$C$1:$U$1,$D46-1,0),MATCH(L$4,'Baseline NFPC'!$C$10:$U$10,0)) -> 5.4010795 | M46: =INDEX(OFFSET('Baseline NFPC'!$C$1:$U$1,$D46-1,0),MATCH(M$4,'Baseline NFPC'!$C$10:$U$10,0)) -> 5.5224371 | ... X46: =INDEX(OFFSET('Baseline NFPC'!$C$1:$U$1,$D46-1,0),MATCH(X$4,'Baseline NFPC'!$C$10:$U$10,0)) -> 5.131906
