Workbook

Sheet Read me
G4: European Commission
G6: Directorate-General for Economic and Financial Affairs
G7: Unit C2 - Sustainability of public finances
G8: ECFIN-Secretariat-C2@ec.europa.eu
C16: FILE DESCRIPTION
C18: Data reported in this file are based on the European Commission (EC) 2025 spring forecast (SF 2025) and macroeconomic and budgetary projections from the joint EC-EPC Ageing Report 2024 (AR 2024).
C22: This file contains a simplified version of the EC model used to calculate the general governement debt ratio dynamics for EU countries under different scenarios. A detailed description of the EC's general governement debt projections can be found in the "Debt Sustainability Monitor 2023" (DSM, March 2024).
C27: HOW TO USE THIS TOOL TO CALCULATE NEW DEBT PROJECTIONS
C29: This tool can be used to calculate debt projections under different macroeconomic and structural primary balance adjustment assumptions. Debt projections for each scenario will update automatically with changes in the macroeconomic assumptions or the adjustment parameters. The fulfilment of DSA-based criteria, the safeguards and the benchmark will be automatically calculated in the sheet "Criteria results". Formulas are fully visible. To assess the impact of alternative adjustment paths compared with the reference trajectory calculated by the EC or to check its robustness to underlying macroeconomic assumptions, the user can modify the content of key cells in the sheets "Criteria results" and "Input data" (see below). Note that, for a proper functioning of the file, you should make sure that Excel is in "Automatic" computation mode, i.e. in the File menu, Option tab, click on "Formulas", "Calculation Options" and "Automatic".
C31: The spreadsheet is composed of the following elements:
D33: The grey sheet "Criteria results" contains three types of cells identified by different colours:
F34: Cells with a yellow background and a red frame can be modified to see the impact of a different duration or pace of adjustment.
F35: Cells with a white or grey background provide results obtained with the adjustment chosen in the yellow cells. To replicate the Commission's calculations, the underlying formulas should not be modified.
F37: Cells with a pale blue background correspond to the Commission's prior guidance provided to the Member State. Those are hard numbers that do not depend on the adjustment chosen in the file.
D39: The sheet "Criteria results" contains six tables: Table 1 "Adjustment input data": the user can set the duration of the plan (4 years under no extension or 7 years under extension) and the yearly adjustment pace in cells F5 and F6 in yellow. Note that the country cell (F4) cannot be changed.
D40: To the right of Table 1, a message automatically signals whether the chosen adjustment is sufficient to fulfill all the requirements, summarising the results from Tables 2 and 3.
D41: Table 2 "DSA-based criteria" reports whether the chosen adjustment fulfils each of the DSA-based criteria.
D42: Table 3 "Safeguards and benchmark" reports whether (i) the chosen adjustment ensures that the debt sustainability safeguard is met, (ii) the 'deficit benchmark', i.e. the minimum adjustment of 0.5 pp. of GDP as a benchmark when the country is in EDP and/or the deficit exceeds 3% of GDP, is binding, and (iii) the deficit resilience safeguard is binding.
D43: Table 4 "Main fiscal variables" reports the annual adjustment over the adjustment period, in terms of change in SPB (line 19) and net primary expenditure growth (line 20). The table also reports the headline balance, the structural balance and debt (lines 21 to 23). The average annual adjustment is reported in cells G24 (average change in SPB over the 4-year plan period), G25 (average change in SPB over the 4-year or 7-year adjustment period), G26 (average net primary expenditure growth over the plan period) and G27 (average net primary expenditure growth over the adjustment period).
D44: Table 5 "DSA-based adjustment" summarises the key characteristics of the adjustment path that complies with the DSA-based criteria before applying the safeguards and benchmark, for a plan both with and without extension.
D45: Table 6 "Reference trajectory" reports the net expenditure growth and the corresponding annual change in SPB that are consistent with all requirements including the safeguards and benchmark, both without and with extension.
D47: The sheet "Input data" in light blue presents the input data, including fiscal and GDP growth assumptions as well as additional fiscal parameters. Unless stated otherwise below, the user can change all values in this tab.
D48: Coloured cells indicate data sources as follows (this colour-coding holds in the other spreadsheets):
F49: Cells in light grey indicate a Commission forecast (available in the AMECO database)
F50: Cells in light red indicate whether the country is subject to an ongoing excessive deficit procedure (EDP) or whether the Commission's November 2024 report under Art. 126(3) of the Treaty recommends opening an EDP. If neither of these conditions are met, the deficit benchmark is not relevant and therefore not applied.
F51: Cells in light blue indicate values from the Ageing Report 2024
F52: Cells in light orange provide parameters needed to compute the decomposition of government debt according to its maturity structure (i.e. short-term and long-term debt, maturing, rolled-over and non-maturing debt). These are fixed shares which the user cannot change.
F53: Cells in dark orange indicate financial market prices.
D54: Non-coloured parameters in cells C49:C70 were calibrated based on different data sources. The data sources are indicated in the corresponding cells of column E. The last part of the sheet "Input data" (cells C73:G77) provides the parameters measuring the size of the cone of the fanchart that results from the stochastic analysis. For reproducibility reasons, these parameters are kept constant.
C56: The next spreadsheets present the deterministic and stochastic projections. Each deterministic projection provides a single path for debt until 2038 or 2041 under certain assumptions for budgetary, macroeconomic and financial variables, while the outcome of the stochastic projections is a distribution of debt paths resulting from a wide set of shocks. The sheets are grouped in four blocs, identified by their colour coding:
D58: The sheet in blue provides, as a reference, the baseline no-fiscal-policy-change scenario. The background colour coding is the same as in the sheet "Input data".
D60: The sheet in orange presents the scenario that automatically corrects the yearly adjustment path to account for the deficit benchmark and the deficit resillience safeguard. By contrast, the yearly adjustment profile is not automatically adjusted to ensure that the debt sustainability safeguard is met. However, the sheet "Criteria results" indicates whether that safeguard is met.
D62: The sheets in green present the deterministic projections that are used to compute the DSA-based requirements (in the sheet "Criteria results"). They include four scenarios:
D63: · Adjustment scenario without safeguard and benchmark
D64: · Financial stress scenario
D65: · Lower SPB scenario
D66: · Adverse 'r-g' scenario
D68: Each scenario is computed automatically based on the yearly adjustment path set in "Criteria results" (see above).
D70: The sheet in dark green presents the stochastic projections surrounding the adjustment scenario without safeguard and benchmark .
C72: Within the orange sheet and each green sheet, the background of the SPB line has three colours. Each colour corresponds to a specific period of the projections:
E73: Light grey indicates the pre-plan period, corresponding to the EC forecast
E74: Mild grey indicates the period during which the SPB adjusts according to the path set in sheet "Criteria results"
E75: Dark grey indicates the period in which the SPB, net of changes in cost of ageing, remains constant at its value of end of adjustment.
D77: In the sheets associated with the stress-test scenarios, i.e. "Financial stress", "Lower SPB" and "Adverse (r-g)", initial shocks are identified as follows:
E78: All variables that are shocked turn very dark grey.
E79: Additionally, for the lower SPB scenario, the cells get thick black borders in the years when the SPB is gradually reduced.
C81: WHERE ARE THE MAIN RESULTS LOCATED?
C82: Debt projections can be found in line 56 or 57 of each scenario. The corresponding net expenditure growth is located in line 79 or 80 in the baseline and adjustment scenario (and Adj. no safeguard) sheets. The average net expenditure growth over the adjustment period is computed in cell D81 of the sheet "Adjustment scenario". As a reminder, these numbers are also available in Table 4 in "Criteria results".
D84: The 'FASTOP reporting' sheet in violet provides help for preparing reporting tables. It readily provides all the tables envisaged in the guidance notice on the "Information Requirements for the Medium-Term Fiscal-Structural Plans" once the parameters are set in the rest of this file. Note that the probability of a declining debt ratio in table 7c derived from the stochastic simulations is only an approximation since the stochastic analysis is not an integral part of this Excel file. For a precise figure, the simulations need to be run. This sheet is therefore only meant to provide assistance. The figures still need to be thoroughly scrutinised before submitting the tables.

Sheet Criteria results
U2: 4 | V2: 0
D3: Table 1 - Adjustment input data | H3: =IF(OR(AND($G$12="ok",$G$13="ok",$G$14="ok",$G$15="ok",$H$12="ok",$I$12="ok",$L$12<>"Not met"), AND($I$12="ok",$J$12="ok",$J$13="ok",$J$14="ok",$J$15="ok",$L$12<>"Not met")), "OK"&CHAR(10)&"adjustment"&CHAR(10)&"complies with all requirements", "NOT OK"&CHAR(10)&"adjustment does not"&CHAR(10)&"comply with all requirements") -> NOT OK adjustment does not comply with all requirements | U3: 7 | V3: 0.02
D4: Country | F4: DE | V4: 0.04
D5: Number of years of adjustment | F5: 4 | V5: 0.06
D6: Annual adjustment (when benchmark not binding) | F6: 0.54 | V6: 0.08
V7: 0.1
V8: 0.12
G9: Table 2 - DSA-based criteria | L9: Table 3 - Safeguards and benchmark | V9: 0.14
L10: Debt sustainability safeguard * | N10: Deficit benchmark ** | P10: Deficit resilience safeguard | V10: 0.16
G11: Criterion 1 (Debt decreasing under deterministic scenarios) | H11: Criterion 2 * (Debt declining with sufficient probability) | I11: Criterion 3 (Deficit below 3% of GDP) | J11: ="Debt below 60% of GDP in T+"&10+F5&" **" -> Debt below 60% of GDP in T+14 ** | L11: Debt declines by 1pp (0.5pp) of GDP on average as long as debt exceeds 90% (60%) of GDP | M11: Average change in debt | N11: 0.5 pp. of GDP adjustment if deficit in previous year > 3% of GDP | O11: Number of years the benchmark applies | P11: 0.40 pp. (0.25 pp.) of GDP adjustment under plan without (with) extension if structural deficit in previous year > 1.5% of GDP | Q11: Number of years the deficit resilience safeguard applies (over the adjustment horizon) | V11: 0.18
D12: Adjustment scenario | G12: =IF(OR('Adjust. no safeguard'!D57>60,'Adjust. no safeguard'!D77<-3),IF(SUM(OFFSET('Adjust. no safeguard'!$D$83,0,$F$5+1,1,10))=0,"ok","Not met"),"") -> ok | H12: =IF(OR('Adjust. no safeguard'!D57>60,'Adjust. no safeguard'!D77<-3),IF($F$5=4,IF(Stochastic!$M$17<Stochastic!$H$17,"ok","Not met"),IF(Stochastic!$P$17<Stochastic!$K$17,"ok","Not met")),"") -> ok | I12: =IF(MIN(OFFSET('Adjust. no safeguard'!$D$77,0,$F$5,1,11))>-3.05,"ok","Not met") -> ok | J12: =IF(OFFSET('Adjust. no safeguard'!$D$57,0,$F$5+10,1,1)<60,"ok","Not met") -> ok | L12: =_xlfn.LET(_xlpm.debtChange,OFFSET('Adjustment scenario'!D58,0,1,1,$F$5), _xlpm.debt6090,OFFSET('Adjustment scenario'!D85,0,1,1,$F$5), _xlpm.debt90,OFFSET('Adjustment scenario'!D84,0,1,1,$F$5), _xlpm.EDP,OFFSET('Adjustment scenario'!D87,0,1,1,$F$5), IF(AND(MAX(_xlpm.debt90)=0,MAX(_xlpm.debt6090)=0),"Debt below 60% of GDP over the adjustment period", IF(MIN(_xlpm.EDP)=1,"Not applicable, reference year is the last year of adjustment", IFERROR(IF(AND(_xlfn.MAXIFS(_xlpm.debt90,_xlpm.EDP,0)=0,_xlfn.MAXIFS(_xlpm.debt6090,_xlpm.EDP,0)=1),IF(AVERAGEIFS(_xlpm.debtChange,_xlpm.EDP,0)<-0.5,"ok","Not met"), IF(AND(_xlfn.MAXIFS(_xlpm.debt90,_xlpm.EDP,0)=1,_xlfn.MAXIFS(_xlpm.debt6090,_xlpm.EDP,0)=0),IF(AVERAGEIFS(_xlpm.debtChange,_xlpm.EDP,0)<-1,"ok","Not met"), IF(AND(_xlfn.MAXIFS(_xlpm.debt90,_xlpm.EDP,0)=1,_xlfn.MAXIFS(_xlpm.debt6090,_xlpm.EDP,0)=1),IF(AND(AVERAGEIFS(_xlpm.debtChange,_xlpm.debt90,1,_xlpm.EDP,0)<-1,AVERAGEIFS(_xlpm.debtChange,_xlpm.debt6090,1,_xlpm.EDP,0)<-0.5),"ok","Not met")))), "Not applicable, debt below 60% of GDP by EDP correction")))) -> Not met | M12: =_xlfn.LET(_xlpm.debtChange,OFFSET('Adjustment scenario'!D58,0,1,1,$F$5), _xlpm.debt6090,OFFSET('Adjustment scenario'!D85,0,1,1,$F$5), _xlpm.debt90,OFFSET('Adjustment scenario'!D84,0,1,1,$F$5), _xlpm.EDP,OFFSET('Adjustment scenario'!D87,0,1,1,$F$5), IF(AND(MAX(_xlpm.debt90)=0,MAX(_xlpm.debt6090)=0),"Debt below 60% of GDP over the adjustment period", IF(MIN(_xlpm.EDP)=1,"Not applicable, reference year is the last year of adjustment", IFERROR(IF(OR(_xlfn.MAXIFS(_xlpm.debt90,_xlpm.EDP,0)=1,_xlfn.MAXIFS(_xlpm.debt6090,_xlpm.EDP,0)=1),AVERAGEIFS(_xlpm.debtChange,_xlpm.EDP,0)), "Not applicable, debt below 60% of GDP by EDP correction")))) -> 0.1144713 | N12: =IF(AND(O12=0,F6<0.5),"not relevant","ok") -> ok | O12: =IF(AND('Input data'!$D$17=1,F6<0.5),COUNTIFS('Adjustment scenario'!D77:F77,"<="&-3.05),0)+IF(AND(F5=4,J19>0.4,J19>F6),1,COUNTIFS(J19:M19,">" & F6,J19:M19,">"&0.4)) -> 0 | P12: =IF(OR(AND(F5=4,Q12=0,F6<0.4),AND(F5=7,Q12=0,F6<0.25)),"not relevant, (over the adjustment horizon)","ok") -> ok | Q12: =IF(AND('Criteria results'!$F$5=4,'Criteria results'!$F$6<=0.4),COUNTIFS('Adjustment scenario'!E13:H13,0.4,'Adjustment scenario'!D88:G88,0),IF(AND('Criteria results'!$F$5=7,'Criteria results'!$F$6<=0.25),COUNTIFS('Adjustment scenario'!E13:K13,0.25,'Adjustment scenario'!D88:J88,0),0)) -> 0 | V12: 0.2
D13: Financial stress scenario | G13: =IF(OR('Adjustment scenario'!D57>60,'Adjustment scenario'!D77<-3),IF(SUM(OFFSET('Financial stress'!$D$75,0,$F$5+1,1,10))=0,"ok","Not met"),"") -> ok | J13: =IF(OR('Adjustment scenario'!D57>60,'Adjustment scenario'!D77<-3),IF(OFFSET('Financial stress'!$D$56,0,$F$5+10,1,1)<60,"ok","Not met"),"") -> ok | V13: 0.22
D14: Lower SPB scenario | G14: =IF(OR('Adjustment scenario'!D57>60,'Adjustment scenario'!D77<-3),IF(SUM(OFFSET('Lower SPB'!$D$75,0,$F$5+1,1,10))=0,"ok","Not met"),"") -> ok | J14: =IF(OR('Adjustment scenario'!D57>60,'Adjustment scenario'!D77<-3),IF(OFFSET('Lower SPB'!$D$56,0,$F$5+10,1,1)<60,"ok","Not met"),"") -> ok | V14: 0.24
D15: Adverse r-g scenario | G15: =IF(OR('Adjustment scenario'!D57>60,'Adjustment scenario'!D77<-3),IF(SUM(OFFSET('Adverse (r-g)'!$D$76,0,$F$5+1,1,10))=0,"ok","Not met"),"") -> ok | J15: =IF(OR('Adjustment scenario'!D57>60,'Adjustment scenario'!D77<-3),IF(OFFSET('Adverse (r-g)'!$D$57,0,$F$5+10,1,1)<60,"ok","Not met"),"") -> ok | V15: 0.26
D16: * The stochastic simulations are provided mainly for information, as the Excel worksheet only allows for an approximation of what is done in the Commission's Stata model. Indeed, in this Excel worksheet, the size of the cone of the fanchart is assumed to be constant over different adjustment paths. In ther Stata model, it is a non linear function of the level of debt, as shocks (in particular interest rate shocks) have different impacts according to the level of debt ratio. ** In case a smaller adjustment than the one implied by criterion 1 and criterion 2 is sufficient to ensure that debt is brought (and/or remains) below 60% of GDP under the adjustment scenario and all deterministic stress tests while ensuring that the criterion 3 is met, then that smaller, 'eased-up' adjustment is chosen. | L16: * The average change in debt is computed from the year before the start of the reference trajectory or the year in which the excessive deficit procedure is projected to be abrogated, whichever occurs last, until the end of the adjustment period. ** The deficit benchmark is applied in terms of change in SPB during the transitory period of 2025-2027 and in terms of change in SB thereafter. | V16: 0.28
G17: Table 4 - Main fiscal variables | V17: 0.3
G18: ='Input data'!$C$5+1 -> 2025 | H18: =G18+1 -> 2026 | I18: =H18+1 -> 2027 | J18: =I18+1 -> 2028 | K18: =J18+1 -> 2029 | L18: =K18+1 -> 2030 | M18: =L18+1 -> 2031 | V18: 0.32
D19: Annual adjustment (change in SPB) | G19: ='Adjustment scenario'!E12-'Adjustment scenario'!D12 -> 0.54 | H19: ='Adjustment scenario'!F12-'Adjustment scenario'!E12 -> 0.54 | I19: ='Adjustment scenario'!G12-'Adjustment scenario'!F12 -> 0.54 | J19: ='Adjustment scenario'!H12-'Adjustment scenario'!G12 -> 0.54 | K19: ='Adjustment scenario'!I12-'Adjustment scenario'!H12 -> 0 | L19: ='Adjustment scenario'!J12-'Adjustment scenario'!I12 -> 0 | M19: ='Adjustment scenario'!K12-'Adjustment scenario'!J12 -> 0 | V19: 0.34
D20: Net primary expenditure growth | G20: ='Adjustment scenario'!E79 -> 1.5922609 | H20: ='Adjustment scenario'!F79 -> 1.399332 | I20: ='Adjustment scenario'!G79 -> 1.5162552 | J20: ='Adjustment scenario'!H79 -> 1.6324232 | K20: ='Adjustment scenario'!I79 -> 2.8591299 | L20: ='Adjustment scenario'!J79 -> 2.8467243 | M20: ='Adjustment scenario'!K79 -> 2.8318391 | V20: 0.36
D21: Headline balance | G21: ='Adjustment scenario'!E77 -> -2.5116656 | H21: ='Adjustment scenario'!F77 -> -1.9842799 | I21: ='Adjustment scenario'!G77 -> -1.4261346 | J21: ='Adjustment scenario'!H77 -> -0.88301955 | K21: ='Adjustment scenario'!I77 -> -0.78476589 | L21: ='Adjustment scenario'!J77 -> -0.68035836 | M21: ='Adjustment scenario'!K77 -> -0.56994003 | V21: 0.38
D22: Structural balance | G22: ='Adjustment scenario'!E78 -> -1.5749913 | H22: ='Adjustment scenario'!F78 -> -1.0526772 | I22: ='Adjustment scenario'!G78 -> -0.60562267 | J22: ='Adjustment scenario'!H78 -> -0.13632773 | K22: ='Adjustment scenario'!I78 -> -0.28697134 | L22: ='Adjustment scenario'!J78 -> -0.43146109 | M22: ='Adjustment scenario'!K78 -> -0.56994003 | V22: 0.4
D23: Debt | G23: ='Adjustment scenario'!E57 -> 63.69213 | H23: ='Adjustment scenario'!F57 -> 64.202561 | I23: ='Adjustment scenario'!G57 -> 63.836882 | J23: ='Adjustment scenario'!H57 -> 62.913564 | K23: ='Adjustment scenario'!I57 -> 61.63591 | L23: ='Adjustment scenario'!J57 -> 60.30467 | M23: ='Adjustment scenario'!K57 -> 58.916634 | V23: 0.42
D24: Average annual adjustment over the plan period | G24: =AVERAGE(G19:J19) -> 0.54 | V24: 0.44
D25: Average annual adjustment over the adjustment period | G25: =IF(F5=4,AVERAGE(G19:J19),AVERAGE(G19:M19)) -> 0.54 | V25: 0.46
D26: Average net primary expenditure growth over the plan period | G26: =AVERAGE(G20:J20) -> 1.5350678 | V26: 0.48
D27: Average net primary expenditure growth over the adjustment period | G27: =IF(F5=4,AVERAGE(G20:J20),AVERAGE(G20:M20)) -> 1.5350678 | V27: 0.5
D28: In case of a plan with no extension, both the plan period and the adjustment period last 4 years. In case of a plan with extension, the plan period remains 4 years while the adjustment period lasts 7 years. Morever, in case of extension, if neither the deficit benchmark nor the deficit resilience safeguard are binding, the values in G24 and G25 (and G26 and G27) are the same. However, if the benchmark or the safeguard is binding, the values in those cells can be different. | V28: 0.52
V29: 0.54
G30: Table 5 - DSA-based adjustment * | V30: 0.56
G31: No extension | H31: Extension | V31: 0.58
D32: Number of years of adjustment | G32: 4 | H32: 7 | V32: 0.6
D33: Annual adjustment | G33: 0.54 | H33: 0.26 | V33: 0.62
D34: Probability that debt decreases | G34: 84.21 | H34: 72.41 | V34: 0.64
D35: * The adjustment in this table does not account for the minimum adjustment of 0.5 pp. of GDP as a benchmark nor for the debt sustainability and deficit resillience safeguards. | V35: 0.66
V36: 0.68
H37: Table 6 - Reference trajectory | V37: 0.7
G38: Average (2025-2028) | H38: 2025 | I38: 2026 | J38: 2027 | K38: 2028 | L38: 2029 | M38: 2030 | N38: 2031 | V38: 0.72
D39: Adjustment in a plan without extension | V39: 0.74
D40: Net primary expenditure growth | G40: 0.70959811 | H40: 0.76679117 | I40: 0.57386227 | J40: 0.69078552 | K40: 0.80695347 | V40: 0.76
D41: Annual change in SPB | G41: 0.9399995 | H41: 0.9399994 | I41: 0.9399996 | J41: 0.94 | K41: 0.939999 | V41: 0.78
D42: Adjustment in a plan with extension | V42: 0.8
D43: Net primary expenditure growth | G43: 1.7001618 | H43: 1.7573548 | I43: 1.5644259 | J43: 1.6813492 | K43: 1.7975171 | L43: 1.9098398 | M43: 1.8974341 | N43: 1.882549 | V43: 0.82
D44: Annual change in SPB | G44: 0.46000003 | H44: 0.4599998 | I44: 0.4600001 | J44: 0.4600001 | K44: 0.4600001 | L44: 0.4599999 | M44: 0.46 | N44: 0.46 | V44: 0.84
V45: 0.86
V46: 0.88
V47: 0.9
V48: 0.92
V49: 0.94
V50: 0.96
V51: 0.98
V52: 1
V53: 1.02
V54: 1.04
V55: 1.06
V56: 1.08
... V82: 1.6

Sheet Input data
B3: Country | C3: DE
B5: Last year before the adjustment | C5: 2024
B6: Last year of adjustment | C6: =C5+'Criteria results'!$F$5 -> 2028
B8: Key assumptions
C9: 2023 | D9: 2024 | E9: 2025 | F9: 2026 | G9: 2027 | H9: 2028 | I9: 2029 | J9: 2030 | K9: 2031 | L9: 2032 | M9: 2033 | N9: 2034 | O9: 2035 | P9: 2036 | Q9: 2037 | R9: 2038 | S9: 2039 | T9: 2040 | U9: 2041
B10: Fiscal assumptions (% of GDP)
B11: Key fiscal variables (based on the Commission 2025 spring forecast ("SF 2025")
B12: Debt | C12: 62.88549 | D12: 62.45568
B13: Structural primary balance ('+' means 'surplus') | C13: -1.260914 | D13: -1.015287
B14: One-off and other temporary measures | C14: 0 | D14: 0 | E14: 0 | F14: 0 | G14: 0 | H14: 0 | I14: 0 | J14: 0 | K14: 0 | L14: 0 | M14: 0 | N14: 0 | O14: 0 | P14: 0 | Q14: 0 | R14: 0 | S14: 0 | T14: 0 | U14: 0
B15: Stock-flow adjustments (without exchange rate effect) | C15: -1.000485 | D15: -1.439456 | E15: 0.0857679 | F15: 0.1097981 | G15: 0 | H15: 0 | I15: 0 | J15: 0 | K15: 0 | L15: 0 | M15: 0 | N15: 0 | O15: 0 | P15: 0 | Q15: 0 | R15: 0 | S15: 0 | T15: 0 | U15: 0
B16: Stock-flow adjustment (total) | C16: -1.016181 | D16: -1.440114 | E16: 0.069708 | F16: 0.0988673 | G16: 0 | H16: 0 | I16: 0 | J16: 0 | K16: 0 | L16: 0 | M16: 0 | N16: 0 | O16: 0 | P16: 0 | Q16: 0 | R16: 0 | S16: 0 | T16: 0 | U16: 0
B17: Subject to an excessive deficit procedure (EDP) (0-no/1-yes) | C17: 0 | D17: 0
B19: Cost of ageing and selected public revenue (based on the Commission-Council 2024 Ageing Report ("AR 2024"))
B20: Total ageing cost (net of taxes on pensions) | C20: =(C21+C22+C23+C24-C25) -> 23.1 | D20: =(D21+D22+D23+D24-D25) -> 23.3 | E20: =(E21+E22+E23+E24-E25) -> 23.4 | F20: =(F21+F22+F23+F24-F25) -> 23.4 | G20: =(G21+G22+G23+G24-G25) -> 23.6 | H20: =(H21+H22+H23+H24-H25) -> 23.7 | I20: =(I21+I22+I23+I24-I25) -> 23.8 | J20: =(J21+J22+J23+J24-J25) -> 23.9 | ... U20: =(U21+U22+U23+U24-U25) -> 24.4
B21: of which: Public pensions expenditure | C21: 10.2 | D21: 10.4 | E21: 10.5 | F21: 10.5 | G21: 10.6 | H21: 10.7 | I21: 10.7 | J21: 10.8 | K21: 10.9 | L21: 11 | M21: 11.1 | N21: 11.1 | O21: 11.2 | P21: 11.2 | Q21: 11.2 | R21: 11.2 | S21: 11.1 | T21: 11.1 | U21: 11.1
B22: Health care expenditure | C22: 7.7 | D22: 7.7 | E22: 7.7 | F22: 7.7 | G22: 7.7 | H22: 7.7 | I22: 7.7 | J22: 7.7 | K22: 7.7 | L22: 7.7 | M22: 7.7 | N22: 7.7 | O22: 7.8 | P22: 7.8 | Q22: 7.8 | R22: 7.8 | S22: 7.9 | T22: 7.9 | U22: 7.9
B23: Long-term care expenditure | C23: 1.9 | D23: 1.9 | E23: 2 | F23: 2 | G23: 2.1 | H23: 2.1 | I23: 2.2 | J23: 2.2 | K23: 2.2 | L23: 2.2 | M23: 2.2 | N23: 2.2 | O23: 2.2 | P23: 2.2 | Q23: 2.2 | R23: 2.2 | S23: 2.3 | T23: 2.3 | U23: 2.3
B24: Education & unemployment benefits expenditure | C24: 4.3 | D24: 4.3 | E24: 4.3 | F24: 4.3 | G24: 4.3 | H24: 4.3 | I24: 4.4 | J24: 4.4 | K24: 4.4 | L24: 4.5 | M24: 4.5 | N24: 4.5 | O24: 4.5 | P24: 4.6 | Q24: 4.6 | R24: 4.6 | S24: 4.5 | T24: 4.5 | U24: 4.5
B25: Taxes on pensions | C25: 1 | D25: 1 | E25: 1.1 | F25: 1.1 | G25: 1.1 | H25: 1.1 | I25: 1.2 | J25: 1.2 | K25: 1.2 | L25: 1.2 | M25: 1.2 | N25: 1.2 | O25: 1.3 | P25: 1.3 | Q25: 1.3 | R25: 1.3 | S25: 1.3 | T25: 1.4 | U25: 1.4
B26: Property income | C26: 0.7164173 | D26: 0.7117602 | E26: 0.7071032 | F26: 0.7024462 | G26: 0.6977891 | H26: 0.6931321 | I26: 0.6884751 | J26: 0.683818 | K26: 0.679161 | L26: 0.674504 | M26: 0.669847 | N26: 0.6651899 | O26: 0.6605328 | P26: 0.6558758 | Q26: 0.6512188 | R26: 0.6465617 | S26: 0.6419046 | T26: 0.6372476 | U26: 0.6325905
B28: Real GDP growth assumptions (based on SF 2025 T+10 projections and AR 2024 projections)
B29: Actual GDP
B30: Growth rate | C30: -0.2664383 | D30: -0.2385261 | E30: 0.1721611 | F30: 0.6262352 | G30: 0.8551665 | H30: 0.9583591 | I30: 1.057734 | J30: 0.6338005 | K30: 0.6071447 | L30: 0.5866577 | M30: 0.5846138 | N30: 0.6761528 | O30: 0.8807697 | P30: 1.085386 | Q30: 1.290001 | R30: 1.379999 | S30: 1.470005 | T30: 1.549998 | U30: 1.560002
B31: Level (EUR bn) | C31: 3615.547
B32: Potential GDP
B33: Growth rate | C33: 0.7097368 | D33: 0.4504604 | E33: 0.267331 | F33: 0.3478621 | G33: 0.4530171 | H33: 0.5574168 | I33: 0.6579712 | J33: 0.6337973 | K33: 0.6071439 | L33: 0.5866582 | M33: 0.5846142 | N33: 0.6761505 | O33: 0.880767 | P33: 1.085383 | Q33: 1.29 | R33: 1.38 | S33: 1.47 | T33: 1.55 | U33: 1.56
B34: Level (EUR bn) | C34: 3640.494
B36: Interest rates (SF 2025, %)
B37: Nominal implicit interest rate on debt | C37: 1.422372 | D37: 1.725464 | E37: 1.8 | F37: 1.800295
B38: Short-term nominal interest rate | C38: 3.43 | D38: 3.570833 | E38: 1.999333 | F38: 1.720833
B39: Long-term nominal interest rate | C39: 2.43 | D39: 2.3225 | E39: 2.544438 | F39: 2.698655
D40: Bloomberg data, country-specific forward market rates.
B41: Inflation (SF 2025, %)
B42: GDP deflator (national currency) | C42: 6.142918 | D42: 3.106014 | E42: 2.439314 | F42: 2.165854
B44: Net primary expenditure growth (SF 2025, %)
B45: Net primary expenditure growth | C45: 6.0601922 | D45: 3.9721583
B47: Additional parameters
E48: Sources
B49: Fiscal multiplier | C49: 0.75 | E49: Carnot, N. and de Castro, F. (2015), “The Discretionary Fiscal Effort: an Assessment of Fiscal Policy and its Output Effect”, European Economy, Economic Papers, No. 543.
B50: Budget balance semi-elasticity | C50: 0.504 | E50: Mourre, G. et al. (2019), "The Semi-Elasticities Underlying the Cyclically-Adjusted Budget Balance: An Update and Further Analysis", European Economy, Discussion Paper, No. 098.
B52: Long-term nominal interest rate (T+10 convergence value) | C52: 3.3043 | E52: Bloomberg data, country-specific forward market rates.
B53: Short-term nominal interest rate (T+10 convergence value) | C53: 2.97658 | E53: Bloomberg data, country-specific forward market rates.
B54: Long-term nominal interest rate (T+30 convergence value) | C54: 4 | E54: DSM 2023
B55: Short-term nominal interest rate (T+30 convergence value) | C55: 2 | E55: DSM 2023
B57: Share of short-term debt in total government debt | C57: 0.1010264 | E57: Eurostat, average shares over the 3 last available years.
B58: Share of long-term debt in total government debt | C58: =1-C57 -> 0.8989736 | E58: Eurostat, average shares over the 3 last available years.
B59: Share of long-term debt that matures every year (T+10 convergence value) | C59: 0.1244153 | E59: ECB, country-specific historical average shares over the 6 last available years. For post-programme countries (CY, El , IE and PT), the redemption profile of official loans has been taken into account for the computation of the share of long-term debt that matures every year. For these countries, changing this parameter would not affect debt projections.
B61: GDP deflator (national currency) (T+10 convergence value) | C61: 2.26 | E61: Bloomberg data, inflation swaps.
B62: GDP deflator (national currency) (T+30 convergence value) | C62: 2 | E62: Central bank inflation target
B64: Share of primary expenditure in GDP in 2024 | C64: 48.457259 | E64: SF25
B66: Share of outstanding debt in total debt in 2024 | C66: 0.76892782 | E66: Derived from the model and made consistent with the short-term forecast.
B67: Share of rolled-over long-term debt in 2024 | C67: 0.10285854 | E67: Derived from the model and made consistent with the short-term forecast.
B68: Share of rolled-over short-term debt in 2024 | C68: 0.10708795 | E68: Derived from the model and made consistent with the short-term forecast.
B69: Share of new long-term debt in 2024 | C69: 0.018991371 | E69: Derived from the model and made consistent with the short-term forecast.
B70: Share of new short-term debt in 2024 | C70: 0.0021342446 | E70: Derived from the model and made consistent with the short-term forecast.
B72: Stochastic projections: ranges around adjustment scenario
C73: T+1 | D73: T+2 | E73: T+3 | F73: T+4 | G73: T+5
B74: Difference between debt level in 50th and 10th percentiles of the distribution | C74: 0 | D74: -3.518383 | E74: -4.8580818 | F74: -5.8735733 | G74: -6.8722954
B75: Difference between debt level in 50th and 30th percentiles of the distribution | C75: 0 | D75: -1.4924431 | E75: -2.0756226 | F75: -2.4244576 | G75: -2.7306862
B76: Difference between debt level in 70th and 50th percentiles of the distribution | C76: 0 | D76: 1.4053764 | E76: 1.9895439 | F76: 2.4352112 | G76: 2.8511276
B77: Difference between debt level in 90th and 50th percentiles of the distribution | C77: 0 | D77: 3.4817314 | E77: 4.8496399 | F77: 5.9628143 | G77: 7.0062294

Sheet Baseline NFPC
B3: Country | C3: ='Input data'!C3 -> DE
B4: Key years
B5: ='Input data'!B5 -> Last year before the adjustment | C5: =+'Input data'!C5 -> 2024
B6: Last year of adjustment | C6: =+C5+'Criteria results'!$F$5 -> 2028
B9: Key assumptions
C10: ='Input data'!$C$5-1 -> 2023 | D10: =C10+1 -> 2024 | E10: =D10+1 -> 2025 | F10: =E10+1 -> 2026 | G10: =F10+1 -> 2027 | H10: =G10+1 -> 2028 | I10: =H10+1 -> 2029 | J10: =I10+1 -> 2030 | K10: =J10+1 -> 2031 | ... U10: =T10+1 -> 2041
B11: Fiscal assumptions (% of GDP)
B12: Structural primary balance ('+' means 'surplus') | C12: ='Input data'!C13 -> -1.260914 | D12: ='Input data'!D13 -> -1.015287 | E12: =D12 -> -1.015287 | F12: =E12 -> -1.015287 | G12: =F12 -> -1.015287 | H12: =G12 -> -1.015287 | I12: =H12 -> -1.015287 | J12: =I12 -> -1.015287 | K12: =J12 -> -1.015287 | L12: =K12 -> -1.015287 | ... U12: =T12 -> -1.015287
B13: One-off and other temporary measures | C13: ='Input data'!C14 -> 0 | D13: ='Input data'!D14 -> 0 | E13: ='Input data'!E14 -> 0 | F13: ='Input data'!F14 -> 0 | G13: ='Input data'!G14 -> 0 | H13: ='Input data'!H14 -> 0 | I13: ='Input data'!I14 -> 0 | J13: ='Input data'!J14 -> 0 | ... U13: ='Input data'!U14 -> 0
B14: Stock flow adjustments (without exchange rate effect) | C14: ='Input data'!C15 -> -1.000485 | D14: ='Input data'!D15 -> -1.439456 | E14: ='Input data'!E15 -> 0.0857679 | F14: ='Input data'!F15 -> 0.1097981 | G14: ='Input data'!G15 -> 0 | H14: ='Input data'!H15 -> 0 | I14: ='Input data'!I15 -> 0 | J14: ='Input data'!J15 -> 0 | ... U14: ='Input data'!U15 -> 0
B16: ='Input data'!B19 -> Cost of ageing and selected public revenue (based on the Commission-Council 2024 Ageing Report ("AR 2024"))
B17: Total ageing cost (net of taxes on pensions) | C17: ='Input data'!C20 -> 23.1 | D17: ='Input data'!D20 -> 23.3 | E17: ='Input data'!E20 -> 23.4 | F17: ='Input data'!F20 -> 23.4 | G17: ='Input data'!G20 -> 23.6 | H17: ='Input data'!H20 -> 23.7 | I17: ='Input data'!I20 -> 23.8 | J17: ='Input data'!J20 -> 23.9 | ... U17: ='Input data'!U20 -> 24.4
B18: ='Input data'!B26 -> Property income | C18: ='Input data'!C26 -> 0.7164173 | D18: ='Input data'!D26 -> 0.7117602 | E18: ='Input data'!E26 -> 0.7071032 | F18: ='Input data'!F26 -> 0.7024462 | G18: ='Input data'!G26 -> 0.6977891 | H18: ='Input data'!H26 -> 0.6931321 | I18: ='Input data'!I26 -> 0.6884751 | ... U18: ='Input data'!U26 -> 0.6325905
B20: GDP growth assumptions
B21: Actual GDP (real)
B22: Level | C22: ='Input data'!C31 -> 3615.547 | D22: =C22*(D23/100+1) -> 3606.923 | E22: =D22*(E23/100+1) -> 3613.1327 | F22: =E22*(F23/100+1) -> 3635.7594 | G22: =F22*(G23/100+1) -> 3666.8512 | H22: =G22*(H23/100+1) -> 3701.9928 | I22: =H22*(I23/100+1) -> 3741.15 | J22: =I22*(J23/100+1) -> 3764.8615 | K22: =J22*(K23/100+1) -> 3787.7196 | ... U22: =T22*(U23/100+1) -> 4227.9738
B23: Growth rate | C23: =+'Input data'!C30 -> -0.2664383 | D23: =+'Input data'!D30 -> -0.2385261 | E23: =+'Input data'!E30 -> 0.1721611 | F23: =+'Input data'!F30 -> 0.6262352 | G23: =+'Input data'!G30 -> 0.8551665 | H23: =+'Input data'!H30 -> 0.9583591 | I23: =+'Input data'!I30 -> 1.057734 | J23: =+'Input data'!J30 -> 0.6338005 | ... U23: =+'Input data'!U30 -> 1.560002
B25: Potential GDP (real)
B26: Level | C26: ='Input data'!C34 -> 3640.494 | D26: =+C26*(1+'Input data'!D33/100) -> 3656.893 | E26: =+D26*(1+'Input data'!E33/100) -> 3666.669 | F26: =+E26*(1+'Input data'!F33/100) -> 3679.4239 | G26: =+F26*(1+'Input data'!G33/100) -> 3696.0924 | H26: =+G26*(1+'Input data'!H33/100) -> 3716.695 | I26: =+H26*(1+'Input data'!I33/100) -> 3741.1498 | J26: =+I26*(1+'Input data'!J33/100) -> 3764.8611 | K26: =+J26*(1+'Input data'!K33/100) -> 3787.7192 | ... U26: =+T26*(1+'Input data'!U33/100) -> 4227.9728
B28: Output gap
B29: Output gap | C29: =100*(C22/C26-1) -> -0.68526414 | D29: =100*(D22/D26-1) -> -1.3664607 | E29: =100*(E22/E26-1) -> -1.4600799 | F29: =100*(F22/F26-1) -> -1.1867222 | G29: =100*(G22/G26-1) -> -0.79113725 | H29: =100*(H22/H26-1) -> -0.3955719 | I29: =100*(I22/I26-1) -> 6.7522622e-06 | J29: =100*(J22/J26-1) -> 9.9321087e-06 | ... U29: =100*(U22/U26-1) -> 2.2689539e-05
B31: Actual GDP (nominal, national currency)
B32: Growth rate | C32: =100*((1+C23/100)*(1+C41/100)-1) -> 5.8601126 | D32: =100*((1+D23/100)*(1+D41/100)-1) -> 2.8600792 | E32: =100*((1+E23/100)*(1+E41/100)-1) -> 2.6156746 | F32: =100*((1+F23/100)*(1+F41/100)-1) -> 2.8056525 | G32: =100*((1+G23/100)*(1+G41/100)-1) -> 3.051411 | H32: =100*((1+H23/100)*(1+H41/100)-1) -> 3.1687318 | I32: =100*((1+I23/100)*(1+I41/100)-1) -> 3.2821752 | J32: =100*((1+J23/100)*(1+J41/100)-1) -> 2.860753 | ... U32: =100*((1+U23/100)*(1+U41/100)-1) -> 3.7628384
B34: Interest rate
B35: Nominal implicit interest rate on debt | C35: ='Input data'!C37 -> 1.422372 | D35: ='Input data'!D37 -> 1.725464 | E35: ='Input data'!E37 -> 1.8 | F35: ='Input data'!F37 -> 1.800295 | G35: =G96 -> 1.9501148 | H35: =H96 -> 2.0904195 | I35: =I96 -> 2.2226873 | J35: =J96 -> 2.3480787 | K35: =K96 -> 2.4691227 | L35: =L96 -> 2.5861719 | M35: =M96 -> 2.7002512 | N35: =N96 -> 2.8108522 | ... U35: =U96 -> 3.2216387
B36: Long-term interest rate | C36: ='Input data'!C39 -> 2.43 | D36: ='Input data'!D39 -> 2.3225 | E36: ='Input data'!E39 -> 2.544438 | F36: ='Input data'!F39 -> 2.698655 | G36: =F36+($N$36-$F$36)/($N$10-$F$10) -> 2.7743606 | H36: =G36+($N$36-$F$36)/($N$10-$F$10) -> 2.8500662 | I36: =H36+($N$36-$F$36)/($N$10-$F$10) -> 2.9257719 | J36: =I36+($N$36-$F$36)/($N$10-$F$10) -> 3.0014775 | K36: =J36+($N$36-$F$36)/($N$10-$F$10) -> 3.0771831 | L36: =K36+($N$36-$F$36)/($N$10-$F$10) -> 3.1528887 | M36: =L36+($N$36-$F$36)/($N$10-$F$10) -> 3.2285944 | N36: ='Input data'!$C$52 -> 3.3043 | O36: =$N$36+('Input data'!$C$54-'Input data'!$C$52)/20*(O$10-$N$10) -> 3.339085 | P36: =$N$36+('Input data'!$C$54-'Input data'!$C$52)/20*(P$10-$N$10) -> 3.37387 | Q36: =$N$36+('Input data'!$C$54-'Input data'!$C$52)/20*(Q$10-$N$10) -> 3.408655 | R36: =$N$36+('Input data'!$C$54-'Input data'!$C$52)/20*(R$10-$N$10) -> 3.44344 | S36: =$N$36+('Input data'!$C$54-'Input data'!$C$52)/20*(S$10-$N$10) -> 3.478225 | T36: =$N$36+('Input data'!$C$54-'Input data'!$C$52)/20*(T$10-$N$10) -> 3.51301 | U36: =$N$36+('Input data'!$C$54-'Input data'!$C$52)/20*(U$10-$N$10) -> 3.547795
B37: Short-term interest rate | C37: ='Input data'!C$38 -> 3.43 | D37: ='Input data'!D$38 -> 3.570833 | E37: ='Input data'!E$38 -> 1.999333 | F37: ='Input data'!F$38 -> 1.720833 | G37: =F37+($N$37-$F$37)/($N$10-$F$10) -> 1.8778014 | H37: =G37+($N$37-$F$37)/($N$10-$F$10) -> 2.0347698 | I37: =H37+($N$37-$F$37)/($N$10-$F$10) -> 2.1917381 | J37: =I37+($N$37-$F$37)/($N$10-$F$10) -> 2.3487065 | K37: =J37+($N$37-$F$37)/($N$10-$F$10) -> 2.5056749 | L37: =K37+($N$37-$F$37)/($N$10-$F$10) -> 2.6626432 | M37: =L37+($N$37-$F$37)/($N$10-$F$10) -> 2.8196116 | N37: ='Input data'!$C$53 -> 2.97658 | O37: =$N$37+('Input data'!$C$55-'Input data'!$C$53)/20*(O$10-$N$10) -> 2.927751 | P37: =$N$37+('Input data'!$C$55-'Input data'!$C$53)/20*(P$10-$N$10) -> 2.878922 | Q37: =$N$37+('Input data'!$C$55-'Input data'!$C$53)/20*(Q$10-$N$10) -> 2.830093 | R37: =$N$37+('Input data'!$C$55-'Input data'!$C$53)/20*(R$10-$N$10) -> 2.781264 | S37: =$N$37+('Input data'!$C$55-'Input data'!$C$53)/20*(S$10-$N$10) -> 2.732435 | T37: =$N$37+('Input data'!$C$55-'Input data'!$C$53)/20*(T$10-$N$10) -> 2.683606 | U37: =$N$37+('Input data'!$C$55-'Input data'!$C$53)/20*(U$10-$N$10) -> 2.634777
B38: Share of long-term debt that matures every year | C38: 0.12643541 | D38: 0.11798594 | E38: 0.11258884 | F38: =IF(OR($C$3="EL",$C$3="CY",$C$3="IE",$C$3="PT"),VLOOKUP($C$3,$B$110:$R$114,MATCH(F$10,$B$110:$R$110,0),0),$E$38+('Input data'!$C$59-$E$38)/($N$10-$E$10)*(F10-$E$10)) -> 0.11390289 | G38: =IF(OR($C$3="EL",$C$3="CY",$C$3="IE",$C$3="PT"),VLOOKUP($C$3,$B$110:$R$114,MATCH(G$10,$B$110:$R$110,0),0),$E$38+('Input data'!$C$59-$E$38)/($N$10-$E$10)*(G10-$E$10)) -> 0.11521694 | H38: =IF(OR($C$3="EL",$C$3="CY",$C$3="IE",$C$3="PT"),VLOOKUP($C$3,$B$110:$R$114,MATCH(H$10,$B$110:$R$110,0),0),$E$38+('Input data'!$C$59-$E$38)/($N$10-$E$10)*(H10-$E$10)) -> 0.11653099 | I38: =IF(OR($C$3="EL",$C$3="CY",$C$3="IE",$C$3="PT"),VLOOKUP($C$3,$B$110:$R$114,MATCH(I$10,$B$110:$R$110,0),0),$E$38+('Input data'!$C$59-$E$38)/($N$10-$E$10)*(I10-$E$10)) -> 0.11784504 | J38: =IF(OR($C$3="EL",$C$3="CY",$C$3="IE",$C$3="PT"),VLOOKUP($C$3,$B$110:$R$114,MATCH(J$10,$B$110:$R$110,0),0),$E$38+('Input data'!$C$59-$E$38)/($N$10-$E$10)*(J10-$E$10)) -> 0.1191591 | K38: =IF(OR($C$3="EL",$C$3="CY",$C$3="IE",$C$3="PT"),VLOOKUP($C$3,$B$110:$R$114,MATCH(K$10,$B$110:$R$110,0),0),$E$38+('Input data'!$C$59-$E$38)/($N$10-$E$10)*(K10-$E$10)) -> 0.12047315 | L38: =IF(OR($C$3="EL",$C$3="CY",$C$3="IE",$C$3="PT"),VLOOKUP($C$3,$B$110:$R$114,MATCH(L$10,$B$110:$R$110,0),0),$E$38+('Input data'!$C$59-$E$38)/($N$10-$E$10)*(L10-$E$10)) -> 0.1217872 | M38: =IF(OR($C$3="EL",$C$3="CY",$C$3="IE",$C$3="PT"),VLOOKUP($C$3,$B$110:$R$114,MATCH(M$10,$B$110:$R$110,0),0),$E$38+('Input data'!$C$59-$E$38)/($N$10-$E$10)*(M10-$E$10)) -> 0.12310125 | N38: =IF(OR($C$3="EL",$C$3="CY",$C$3="IE",$C$3="PT"),VLOOKUP($C$3,$B$110:$R$114,MATCH(N$10,$B$110:$R$110,0),0),'Input data'!$C$59) -> 0.1244153 | O38: =IF(OR($C$3="EL",$C$3="CY",$C$3="IE",$C$3="PT"),VLOOKUP($C$3,$B$110:$R$114,MATCH(O$10,$B$110:$R$110,0),0),'Input data'!$C$59) -> 0.1244153 | P38: =IF(OR($C$3="EL",$C$3="CY",$C$3="IE",$C$3="PT"),VLOOKUP($C$3,$B$110:$R$114,MATCH(P$10,$B$110:$R$110,0),0),'Input data'!$C$59) -> 0.1244153 | Q38: =IF(OR($C$3="EL",$C$3="CY",$C$3="IE",$C$3="PT"),VLOOKUP($C$3,$B$110:$R$114,MATCH(Q$10,$B$110:$R$110,0),0),'Input data'!$C$59) -> 0.1244153 | R38: =IF(OR($C$3="EL",$C$3="CY",$C$3="IE",$C$3="PT"),VLOOKUP($C$3,$B$110:$R$114,MATCH(R$10,$B$110:$R$110,0),0),'Input data'!$C$59) -> 0.1244153 | S38: =IF(OR($C$3="EL",$C$3="CY",$C$3="IE",$C$3="PT"),VLOOKUP($C$3,$B$110:$U$114,MATCH(S$10,$B$110:$U$110,0),0),'Input data'!$C$59) -> 0.1244153 | T38: =IF(OR($C$3="EL",$C$3="CY",$C$3="IE",$C$3="PT"),VLOOKUP($C$3,$B$110:$U$114,MATCH(T$10,$B$110:$U$110,0),0),'Input data'!$C$59) -> 0.1244153 | U38: =IF(OR($C$3="EL",$C$3="CY",$C$3="IE",$C$3="PT"),VLOOKUP($C$3,$B$110:$U$114,MATCH(U$10,$B$110:$U$110,0),0),'Input data'!$C$59) -> 0.1244153
B40: Inflation and exchange rate
B41: GDP deflator (national currency) | C41: ='Input data'!C42 -> 6.142918 | D41: ='Input data'!D42 -> 3.106014 | E41: ='Input data'!E42 -> 2.439314 | F41: ='Input data'!F42 -> 2.165854 | G41: =$F$41+($N$41-$F$41)/($N$10-$F$10)*(G10-$F$10) -> 2.1776222 | H41: =$F$41+($N$41-$F$41)/($N$10-$F$10)*(H10-$F$10) -> 2.1893905 | I41: =$F$41+($N$41-$F$41)/($N$10-$F$10)*(I10-$F$10) -> 2.2011587 | J41: =$F$41+($N$41-$F$41)/($N$10-$F$10)*(J10-$F$10) -> 2.212927 | K41: =$F$41+($N$41-$F$41)/($N$10-$F$10)*(K10-$F$10) -> 2.2246952 | L41: =$F$41+($N$41-$F$41)/($N$10-$F$10)*(L10-$F$10) -> 2.2364635 | M41: =$F$41+($N$41-$F$41)/($N$10-$F$10)*(M10-$F$10) -> 2.2482317 | N41: ='Input data'!$C$61 -> 2.26 | O41: =$N$41+('Input data'!$C$62-'Input data'!$C$61)/20*(O$10-$N$10) -> 2.247 | P41: =$N$41+('Input data'!$C$62-'Input data'!$C$61)/20*(P$10-$N$10) -> 2.234 | Q41: =$N$41+('Input data'!$C$62-'Input data'!$C$61)/20*(Q$10-$N$10) -> 2.221 | R41: =$N$41+('Input data'!$C$62-'Input data'!$C$61)/20*(R$10-$N$10) -> 2.208 | S41: =$N$41+('Input data'!$C$62-'Input data'!$C$61)/20*(S$10-$N$10) -> 2.195 | T41: =$N$41+('Input data'!$C$62-'Input data'!$C$61)/20*(T$10-$N$10) -> 2.182 | U41: =$N$41+('Input data'!$C$62-'Input data'!$C$61)/20*(U$10-$N$10) -> 2.169
B42: Exchange rate composite change (weighted by share of debt in each currency) | C42: 0.9997445 | D42: 0.9999892 | E42: 0.9997361 | F42: 0.9998241 | G42: 1 | H42: 1 | I42: 1 | J42: 1 | K42: 1 | L42: 1 | M42: 1 | N42: 1 | O42: 1 | P42: 1 | Q42: 1 | R42: 1 | S42: 1 | T42: 1 | U42: 1
B44: Intermediate calculations (growth rate equation)
B46: Fiscal multiplier | C46: ='Input data'!C49 -> 0.75
B47: Budget balance semi-elasticity | C47: ='Input data'!C50 -> 0.504
B49: Auxiliary variable to control the closure of the output gap | C49: 0 | D49: =IF(AND(ABS((D12-C12)-('Input data'!D13-'Input data'!C13))>0.0001,ABS(D12-C12)>0.0001,D$10>$C$5),4,IF(C49=4,3,IF(C49=3,2,IF(C49=2,1,0)))) -> 0 | E49: =IF(AND(ABS(E12-D12)>0.0001,E$10>$C$5),4,IF(D49=4,3,IF(D49=3,2,IF(D49=2,1,0)))) -> 0 | F49: =IF(AND(ABS(F12-E12)>0.0001,F$10>$C$5),4,IF(E49=4,3,IF(E49=3,2,IF(E49=2,1,0)))) -> 0 | G49: =IF(AND(ABS(G12-F12)>0.0001,G$10>$C$5),4,IF(F49=4,3,IF(F49=3,2,IF(F49=2,1,0)))) -> 0 | H49: =IF(AND(ABS(H12-G12)>0.0001,H$10>$C$5),4,IF(G49=4,3,IF(G49=3,2,IF(G49=2,1,0)))) -> 0 | I49: =IF(AND(ABS(I12-H12)>0.0001,I$10>$C$5),4,IF(H49=4,3,IF(H49=3,2,IF(H49=2,1,0)))) -> 0 | J49: =IF(AND(ABS(J12-I12)>0.0001,J$10>$C$5),4,IF(I49=4,3,IF(I49=3,2,IF(I49=2,1,0)))) -> 0 | K49: =IF(AND(ABS(K12-J12)>0.0001,K$10>$C$5),4,IF(J49=4,3,IF(J49=3,2,IF(J49=2,1,0)))) -> 0 | L49: =IF(AND(ABS(L12-K12)>0.0001,L$10>$C$5),4,IF(K49=4,3,IF(K49=3,2,IF(K49=2,1,0)))) -> 0 | ... U49: =IF(AND(ABS(U12-T12)>0.0001,U$10>$C$5),4,IF(T49=4,3,IF(T49=3,2,IF(T49=2,1,0)))) -> 0
B50: OG intermediate auxiliary value | C50: 0 | D50: =IF(C49=4,2/3*C29,IF(C49=3,1/3*#REF!,0)) -> 0 | E50: =IF(D49=4,2/3*D29,IF(D49=3,1/3*C29,0)) -> 0 | F50: =IF(E49=4,2/3*E29,IF(E49=3,1/3*D29,0)) -> 0 | G50: =IF(F49=4,2/3*F29,IF(F49=3,1/3*E29,0)) -> 0 | H50: =IF(G49=4,2/3*G29,IF(G49=3,1/3*F29,0)) -> 0 | I50: =IF(H49=4,2/3*H29,IF(H49=3,1/3*G29,0)) -> 0 | J50: =IF(I49=4,2/3*I29,IF(I49=3,1/3*H29,0)) -> 0 | K50: =IF(J49=4,2/3*J29,IF(J49=3,1/3*I29,0)) -> 0 | L50: =IF(K49=4,2/3*K29,IF(K49=3,1/3*J29,0)) -> 0 | ... U50: =IF(T49=4,2/3*T29,IF(T49=3,1/3*S29,0)) -> 0
B51: GDP intermediate growth rate - only feedback effect and no closure of the OG | C51: 0 | D51: ='Input data'!D30-$C$46*((D12-C12)-('Input data'!D13-'Input data'!C13)) -> -0.2385261 | E51: ='Input data'!E30-$C$46*((E12-D12)-('Input data'!E13-'Input data'!D13)) -> 0.93362635 | F51: ='Input data'!F30-$C$46*((F12-E12)) -> 0.6262352 | G51: ='Input data'!G30-$C$46*((G12-F12)) -> 0.8551665 | H51: ='Input data'!H30-$C$46*((H12-G12)) -> 0.9583591 | I51: ='Input data'!I30-$C$46*((I12-H12)) -> 1.057734 | J51: ='Input data'!J30-$C$46*((J12-I12)) -> 0.6338005 | K51: ='Input data'!K30-$C$46*((K12-J12)) -> 0.6071447 | L51: ='Input data'!L30-$C$46*((L12-K12)) -> 0.5866577 | M51: ='Input data'!M30-$C$46*((M12-L12)) -> 0.5846138 | ... U51: ='Input data'!U30-$C$46*((U12-T12)) -> 1.560002
B53: Debt projections
C55: ='Input data'!$C$5-1 -> 2023 | D55: =C55+1 -> 2024 | E55: =D55+1 -> 2025 | F55: =E55+1 -> 2026 | G55: =F55+1 -> 2027 | H55: =G55+1 -> 2028 | I55: =H55+1 -> 2029 | J55: =I55+1 -> 2030 | K55: =J55+1 -> 2031 | ... U55: =T55+1 -> 2041
B56: Gross debt | C56: =+'Input data'!C12 -> 62.88549 | D56: =+C56+D57 -> 62.455679 | E56: =+D56+E57 -> 63.884472 | F56: =+E56+F57 -> 65.081113 | G56: =+F56+G57 -> 66.113591 | H56: =+G56+H57 -> 67.05586 | I56: =+H56+I57 -> 67.906557 | J56: =+I56+J57 -> 69.211324 | K56: =+J56+K57 -> 70.706019 | ... U56: =+T56+U57 -> 89.352287
B57: Change in debt (-1+2+3) | D57: =-D58+D66+D71 -> -0.42981088 | E57: =-E58+E66+E71 -> 1.4287934 | F57: =-F58+F66+F71 -> 1.1966404 | G57: =-G58+G66+G71 -> 1.0324784 | H57: =-H58+H66+H71 -> 0.94226871 | I57: =-I58+I66+I71 -> 0.85069718 | J57: =-J58+J66+J71 -> 1.3047671 | K57: =-K58+K66+K71 -> 1.494695 | ... U57: =-U58+U66+U71 -> 1.7374694
B58: (1) Primary balance (1.1 + 1.2 - 1.3 -1.4 -1.5 - 1.6 -1.7) | D58: =D59+D60-D61-D62-D63-D64-D65 -> -1.7039832 | E58: =E59+E60-E61-E62-E63-E64-E65 -> -1.8558243 | F58: =F59+F60-F61-F62-F63-F64-F65 -> -1.722709 | G58: =G59+G60-G61-G62-G63-G64-G65 -> -1.7279913 | H58: =H59+H60-H61-H62-H63-H64-H65 -> -1.6332833 | I58: =I59+I60-I61-I62-I63-I64-I65 -> -1.5385687 | J58: =J59+J60-J61-J62-J63-J64-J65 -> -1.6432242 | K58: =K59+K60-K61-K62-K63-K64-K65 -> -1.7478808 | ... U58: =U59+U60-U61-U62-U63-U64-U65 -> -2.1944453
B59: (1.1) Structural primary balance (before ageing cost) | D59: =D12 -> -1.015287 | E59: =IF(E12="",D59,E12) -> -1.015287 | F59: =IF(F12="",E59,F12) -> -1.015287 | G59: =IF(G12="",F59,G12) -> -1.015287 | H59: =IF(H12="",G59,H12) -> -1.015287 | I59: =IF(I12="",H59,I12) -> -1.015287 | J59: =IF(J12="",I59,J12) -> -1.015287 | K59: =IF(K12="",J59,K12) -> -1.015287 | L59: =IF(L12="",K59,L12) -> -1.015287 | ... U59: =IF(U12="",T59,U12) -> -1.015287
B60: (1.2) Cumulated budgetary effort (in terms of primary balance) | D60: 0 | E60: 0 | F60: 0 | G60: 0 | H60: 0 | I60: 0 | J60: 0 | K60: 0 | L60: 0 | M60: 0 | N60: 0 | O60: 0 | P60: 0 | Q60: 0 | R60: 0 | S60: 0 | T60: 0 | U60: 0
B61: (1.3) Cyclical component | D61: =-$C$47*D29 -> 0.68869622 | E61: =-$C$47*E29 -> 0.73588028 | F61: =-$C$47*F29 -> 0.59810798 | G61: =-$C$47*G29 -> 0.39873318 | H61: =-$C$47*H29 -> 0.19936824 | I61: =-$C$47*I29 -> -3.4031402e-06 | J61: =-$C$47*J29 -> -5.0057828e-06 | K61: =-$C$47*K29 -> -5.4065496e-06 | ... U61: =-$C$47*U29 -> -1.1435528e-05
B62: (1.4) One-off and other temporary measures | D62: =-D13 -> 0 | E62: =-E13 -> 0 | F62: =-F13 -> 0 | G62: =-G13 -> 0 | H62: =-H13 -> 0 | I62: =-I13 -> 0 | J62: =-J13 -> 0 | K62: =-K13 -> 0 | ... U62: =-U13 -> 0
B63: (1.5) Cost of ageing | D63: =IF(D$55<=$C$5,0,HLOOKUP(D$55,'Input data'!$C$9:$AZ$26,12,FALSE)-HLOOKUP($C$5,'Input data'!$C$9:$AZ$26,12,FALSE)) -> 0 | E63: =IF(E$55<=$C$5,0,HLOOKUP(E$55,'Input data'!$C$9:$AZ$26,12,FALSE)-HLOOKUP($C$5,'Input data'!$C$9:$AZ$26,12,FALSE)) -> 0.1 | F63: =IF(F$55<=$C$5,0,HLOOKUP(F$55,'Input data'!$C$9:$AZ$26,12,FALSE)-HLOOKUP($C$5,'Input data'!$C$9:$AZ$26,12,FALSE)) -> 0.1 | G63: =IF(G$55<=$C$5,0,HLOOKUP(G$55,'Input data'!$C$9:$AZ$26,12,FALSE)-HLOOKUP($C$5,'Input data'!$C$9:$AZ$26,12,FALSE)) -> 0.3 | H63: =IF(H$55<=$C$5,0,HLOOKUP(H$55,'Input data'!$C$9:$AZ$26,12,FALSE)-HLOOKUP($C$5,'Input data'!$C$9:$AZ$26,12,FALSE)) -> 0.4 | I63: =IF(I$55<=$C$5,0,HLOOKUP(I$55,'Input data'!$C$9:$AZ$26,12,FALSE)-HLOOKUP($C$5,'Input data'!$C$9:$AZ$26,12,FALSE)) -> 0.5 | J63: =IF(J$55<=$C$5,0,HLOOKUP(J$55,'Input data'!$C$9:$AZ$26,12,FALSE)-HLOOKUP($C$5,'Input data'!$C$9:$AZ$26,12,FALSE)) -> 0.6 | K63: =IF(K$55<=$C$5,0,HLOOKUP(K$55,'Input data'!$C$9:$AZ$26,12,FALSE)-HLOOKUP($C$5,'Input data'!$C$9:$AZ$26,12,FALSE)) -> 0.7 | ... U63: =IF(U$55<=$C$5,0,HLOOKUP(U$55,'Input data'!$C$9:$AZ$26,12,FALSE)-HLOOKUP($C$5,'Input data'!$C$9:$AZ$26,12,FALSE)) -> 1.1
B64: (1.6) Property incomes | D64: =IF(D$55<=$C$5,0,-HLOOKUP(D$55,'Input data'!$C$9:$AZ$26,18,FALSE)+HLOOKUP($C$5,'Input data'!$C$9:$AZ$26,18,FALSE)) -> 0 | E64: =IF(E$55<=$C$5,0,-HLOOKUP(E$55,'Input data'!$C$9:$AZ$26,18,FALSE)+HLOOKUP($C$5,'Input data'!$C$9:$AZ$26,18,FALSE)) -> 0.004657 | F64: =IF(F$55<=$C$5,0,-HLOOKUP(F$55,'Input data'!$C$9:$AZ$26,18,FALSE)+HLOOKUP($C$5,'Input data'!$C$9:$AZ$26,18,FALSE)) -> 0.009314 | G64: =IF(G$55<=$C$5,0,-HLOOKUP(G$55,'Input data'!$C$9:$AZ$26,18,FALSE)+HLOOKUP($C$5,'Input data'!$C$9:$AZ$26,18,FALSE)) -> 0.0139711 | H64: =IF(H$55<=$C$5,0,-HLOOKUP(H$55,'Input data'!$C$9:$AZ$26,18,FALSE)+HLOOKUP($C$5,'Input data'!$C$9:$AZ$26,18,FALSE)) -> 0.0186281 | I64: =IF(I$55<=$C$5,0,-HLOOKUP(I$55,'Input data'!$C$9:$AZ$26,18,FALSE)+HLOOKUP($C$5,'Input data'!$C$9:$AZ$26,18,FALSE)) -> 0.0232851 | J64: =IF(J$55<=$C$5,0,-HLOOKUP(J$55,'Input data'!$C$9:$AZ$26,18,FALSE)+HLOOKUP($C$5,'Input data'!$C$9:$AZ$26,18,FALSE)) -> 0.0279422 | K64: =IF(K$55<=$C$5,0,-HLOOKUP(K$55,'Input data'!$C$9:$AZ$26,18,FALSE)+HLOOKUP($C$5,'Input data'!$C$9:$AZ$26,18,FALSE)) -> 0.0325992 | ... U64: =IF(U$55<=$C$5,0,-HLOOKUP(U$55,'Input data'!$C$9:$AZ$26,18,FALSE)+HLOOKUP($C$5,'Input data'!$C$9:$AZ$26,18,FALSE)) -> 0.0791697
B65: (1.7) Revenues | D65: 0 | E65: 0 | F65: 0 | G65: 0 | H65: 0 | I65: 0 | J65: 0 | K65: 0 | L65: 0 | M65: 0 | N65: 0 | O65: 0 | P65: 0 | Q65: 0 | R65: 0 | S65: 0 | T65: 0 | U65: 0
B66: (2) Snowball effect (2.1 + 2.2 + 2.3) | D66: =SUM(D67:D70) -> -0.6936801 | E66: =SUM(E67:E70) -> -0.4967389 | F66: =SUM(F67:F70) -> -0.6249359 | G66: =SUM(G67:G70) -> -0.69551287 | H66: =SUM(H67:H70) -> -0.69101463 | I66: =SUM(I67:I70) -> -0.68787152 | J66: =SUM(J67:J70) -> -0.33845709 | K66: =SUM(K67:K70) -> -0.25318583 | ... U66: =SUM(U67:U70) -> -0.4569759
B67: (2.1) Interest expenditure | D67: =C56*D35/100*(1/(1+D32/100)) -> 1.0548956 | E67: =D56*E35/100*(1/(1+E32/100)) -> 1.0955463 | F67: =E56*F35/100*(1/(1+F32/100)) -> 1.1187215 | G67: =F56*G35/100*(1/(1+G32/100)) -> 1.231576 | H67: =G56*H35/100*(1/(1+H32/100)) -> 1.339603 | I67: =H56*I35/100*(1/(1+I32/100)) -> 1.4430778 | J67: =I56*J35/100*(1/(1+J32/100)) -> 1.5501533 | K67: =J56*K35/100*(1/(1+K32/100)) -> 1.6616333 | ... U67: =T56*U35/100*(1/(1+U32/100)) -> 2.7202734
B68: (2.2) Growth effect | D68: =-C56*(D23/100)*(1/(1+D32/100)) -> 0.14582752 | E68: =-D56*(E23/100)*(1/(1+E32/100)) -> -0.10478359 | F68: =-E56*(F23/100)*(1/(1+F32/100)) -> -0.38914889 | G68: =-F56*(G23/100)*(1/(1+G32/100)) -> -0.54007206 | H68: =-G56*(H23/100)*(1/(1+H32/100)) -> -0.61414501 | I68: =-H56*(I23/100)*(1/(1+I32/100)) -> -0.68673285 | J68: =-I56*(J23/100)*(1/(1+J32/100)) -> -0.41842208 | K68: =-J56*(K23/100)*(1/(1+K32/100)) -> -0.40858716 | ... U68: =-T56*(U23/100)*(1/(1+U32/100)) -> -1.3172278
B69: (2.3) Inflation effect | D69: =-C56*D41/100*(1/(1+D41/100)) -> -1.894392 | E69: =-D56*E41/100*(1/(1+E41/100)) -> -1.4872123 | F69: =-E56*F41/100*(1/(1+F41/100)) -> -1.354312 | G69: =-F56*G41/100*(1/(1+G41/100)) -> -1.3870168 | H69: =-G56*H41/100*(1/(1+H41/100)) -> -1.4164726 | I69: =-H56*I41/100*(1/(1+I41/100)) -> -1.4442164 | J69: =-I56*J41/100*(1/(1+J41/100)) -> -1.4701883 | K69: =-J56*K41/100*(1/(1+K41/100)) -> -1.506232 | ... U69: =-T56*U41/100*(1/(1+U41/100)) -> -1.8600215
B70: (2.4) Exchange rate effect linked to the interest rate | D70: -1.1222575e-05 | E70: -0.00028926533 | F70: -0.00019655417 | G70: 0 | H70: 0 | I70: 0 | J70: 0 | K70: 0 | L70: 0 | M70: 0 | N70: 0 | O70: 0 | P70: 0 | Q70: 0 | R70: 0 | S70: 0 | T70: 0 | U70: 0
B71: (3 ) Stock flow adjustments (3.1 + 3.2) | D71: ='Input data'!D16 -> -1.440114 | E71: ='Input data'!E16 -> 0.069708 | F71: ='Input data'!F16 -> 0.0988673 | G71: ='Input data'!G16 -> 0 | H71: ='Input data'!H16 -> 0 | I71: ='Input data'!I16 -> 0 | J71: ='Input data'!J16 -> 0 | K71: ='Input data'!K16 -> 0 | ... U71: ='Input data'!U16 -> 0
B72: (3.1) Base | D72: =D14 -> -1.439456 | E72: =E14 -> 0.0857679 | F72: =F14 -> 0.1097981 | G72: =G14 -> 0 | H72: =H14 -> 0 | I72: =I14 -> 0 | J72: =J14 -> 0 | K72: =K14 -> 0 | ... U72: =U14 -> 0
B73: (3.2) Adjustment due to the exchange rate effect linked to debt value | D73: =+D71-D72 -> -0.000658 | E73: =+E71-E72 -> -0.0160599 | F73: =+F71-F72 -> -0.0109308 | G73: =+G71-G72 -> 0 | H73: =+H71-H72 -> 0 | I73: =+I71-I72 -> 0 | J73: =+J71-J72 -> 0 | K73: =+K71-K72 -> 0 | ... U73: =+U71-U72 -> 0
B75: Other budgetary variables
B76: Headline balance | C76: -2.479937 | D76: =D58-D67-D70 -> -2.7588676 | E76: =E58-E67-E70 -> -2.9510813 | F76: =F58-F67-F70 -> -2.841234 | G76: =G58-G67-G70 -> -2.9595673 | H76: =H58-H67-H70 -> -2.9728863 | I76: =I58-I67-I70 -> -2.9816465 | J76: =J58-J67-J70 -> -3.1933775 | K76: =K58-K67-K70 -> -3.4095141 | ... U76: =U58-U67-U70 -> -4.9147186
B77: Structural balance | C77: -2.134562 | D77: =D59-D67-D70-D63-D64-D65 -> -2.0701714 | E77: =E59-E67-E70-E63-E64-E65 -> -2.215201 | F77: =F59-F67-F70-F63-F64-F65 -> -2.243126 | G77: =G59-G67-G70-G63-G64-G65 -> -2.5608341 | H77: =H59-H67-H70-H63-H64-H65 -> -2.7735181 | I77: =I59-I67-I70-I63-I64-I65 -> -2.9816499 | J77: =J59-J67-J70-J63-J64-J65 -> -3.1933825 | K77: =K59-K67-K70-K63-K64-K65 -> -3.4095195 | ... U77: =U59-U67-U70-U63-U64-U65 -> -4.9147301
B78: Net expenditure growth | C78: ='Input data'!C45 -> 6.0601922 | D78: ='Input data'!D45 -> 3.9721583 | E78: ='Input data'!E33+E41-(E$12-D$12)/'Input data'!$C$64*100 -> 2.706645 | F78: ='Input data'!F33+F41-(F$12-E$12)/'Input data'!$C$64*100 -> 2.5137161 | G78: ='Input data'!G33+G41-(G$12-F$12)/'Input data'!$C$64*100 -> 2.6306393 | H78: ='Input data'!H33+H41-(H$12-G$12)/'Input data'!$C$64*100 -> 2.7468073 | I78: ='Input data'!I33+I41-(I$12-H$12)/'Input data'!$C$64*100 -> 2.8591299 | J78: ='Input data'!J33+J41-(J$12-I$12)/'Input data'!$C$64*100 -> 2.8467243 | K78: ='Input data'!K33+K41-(K$12-J$12)/'Input data'!$C$64*100 -> 2.8318391 | L78: ='Input data'!L33+L41-(L$12-K$12)/'Input data'!$C$64*100 -> 2.8231217 | ... U78: ='Input data'!U33+U41-(U$12-T$12)/'Input data'!$C$64*100 -> 3.729
B81: Debt decomposition and IIR
B83: Auxiliary variable identifying whether debt is increasing | E83: =IF((E87-D87*E42/((1+E23/100)*(1+E41/100)))>0,1,0) -> 1 | F83: =IF((F87-E87*F42/((1+F23/100)*(1+F41/100)))>0,1,0) -> 1 | G83: =IF((G87-F87*G42/((1+G23/100)*(1+G41/100)))>0,1,0) -> 1 | H83: =IF((H87-G87*H42/((1+H23/100)*(1+H41/100)))>0,1,0) -> 1 | I83: =IF((I87-H87*I42/((1+I23/100)*(1+I41/100)))>0,1,0) -> 1 | J83: =IF((J87-I87*J42/((1+J23/100)*(1+J41/100)))>0,1,0) -> 1 | K83: =IF((K87-J87*K42/((1+K23/100)*(1+K41/100)))>0,1,0) -> 1 | L83: =IF((L87-K87*L42/((1+L23/100)*(1+L41/100)))>0,1,0) -> 1 | ... U83: =IF((U87-T87*U42/((1+U23/100)*(1+U41/100)))>0,1,0) -> 1
B84: Auxiliary variable identifying whether some debt is rolled over even though debt is decreasing | E84: =IF(AND(E83=0,ABS(E87-D87*E42/((1+E23/100)*(1+E41/100)))<((D93*D87*E42/((1+E23/100)*(1+E41/100))+(E38*D87*D94*E42/((1+E23/100)*(1+E41/100)))))),1,0) -> 0 | F84: =IF(AND(F83=0,ABS(F87-E87*F42/((1+F23/100)*(1+F41/100)))<((E93*E87*F42/((1+F23/100)*(1+F41/100))+(F38*E87*E94*F42/((1+F23/100)*(1+F41/100)))))),1,0) -> 0 | G84: =IF(AND(G83=0,ABS(G87-F87*G42/((1+G23/100)*(1+G41/100)))<((F93*F87*G42/((1+G23/100)*(1+G41/100))+(G38*F87*F94*G42/((1+G23/100)*(1+G41/100)))))),1,0) -> 0 | H84: =IF(AND(H83=0,ABS(H87-G87*H42/((1+H23/100)*(1+H41/100)))<((G93*G87*H42/((1+H23/100)*(1+H41/100))+(H38*G87*G94*H42/((1+H23/100)*(1+H41/100)))))),1,0) -> 0 | I84: =IF(AND(I83=0,ABS(I87-H87*I42/((1+I23/100)*(1+I41/100)))<((H93*H87*I42/((1+I23/100)*(1+I41/100))+(I38*H87*H94*I42/((1+I23/100)*(1+I41/100)))))),1,0) -> 0 | J84: =IF(AND(J83=0,ABS(J87-I87*J42/((1+J23/100)*(1+J41/100)))<((I93*I87*J42/((1+J23/100)*(1+J41/100))+(J38*I87*I94*J42/((1+J23/100)*(1+J41/100)))))),1,0) -> 0 | K84: =IF(AND(K83=0,ABS(K87-J87*K42/((1+K23/100)*(1+K41/100)))<((J93*J87*K42/((1+K23/100)*(1+K41/100))+(K38*J87*J94*K42/((1+K23/100)*(1+K41/100)))))),1,0) -> 0 | L84: =IF(AND(L83=0,ABS(L87-K87*L42/((1+L23/100)*(1+L41/100)))<((K93*K87*L42/((1+L23/100)*(1+L41/100))+(L38*K87*K94*L42/((1+L23/100)*(1+L41/100)))))),1,0) -> 0 | ... U84: =IF(AND(U83=0,ABS(U87-T87*U42/((1+U23/100)*(1+U41/100)))<((T93*T87*U42/((1+U23/100)*(1+U41/100))+(U38*T87*T94*U42/((1+U23/100)*(1+U41/100)))))),1,0) -> 0
C86: ='Input data'!$C$5-1 -> 2023 | D86: =C86+1 -> 2024 | E86: =D86+1 -> 2025 | F86: =E86+1 -> 2026 | G86: =F86+1 -> 2027 | H86: =G86+1 -> 2028 | I86: =H86+1 -> 2029 | J86: =I86+1 -> 2030 | K86: =J86+1 -> 2031 | ... U86: =T86+1 -> 2041
B87: Gross debt | C87: =C56 -> 62.88549 | D87: =D56 -> 62.455679 | E87: =D87*(1+E101/100)*E42-E59-E60+E61+E62+E63+E64+E65+E72 -> 63.884471 | F87: =E87*(1+F101/100)*F42-F59-F60+F61+F62+F63+F64+F65+F72 -> 65.081111 | G87: =F87*(1+G101/100)*G42-G59-G60+G61+G62+G63+G64+G65+G72 -> 66.113589 | H87: =G87*(1+H101/100)*H42-H59-H60+H61+H62+H63+H64+H65+H72 -> 67.055858 | I87: =H87*(1+I101/100)*I42-I59-I60+I61+I62+I63+I64+I65+I72 -> 67.906555 | J87: =I87*(1+J101/100)*J42-J59-J60+J61+J62+J63+J64+J65+J72 -> 69.211322 | K87: =J87*(1+K101/100)*K42-K59-K60+K61+K62+K63+K64+K65+K72 -> 70.706017 | L87: =K87*(1+L101/100)*L42-L59-L60+L61+L62+L63+L64+L65+L72 -> 72.486618 | ... U87: =T87*(1+U101/100)*U42-U59-U60+U61+U62+U63+U64+U65+U72 -> 89.352285
B88: Of which Outstanding debt | D88: ='Input data'!$C$66*D$87 -> 48.023909 | E88: =IF(E87=0,0,IF(E83=1,D87*E42/((1+E23/100)*(1+E41/100))-E89-E90,IF(AND(E83=0,E84=1),(1-D93-E38*D94)*D87*E42/((1+E23/100)*(1+E41/100)),E87))) -> 48.099202 | F88: =IF(F87=0,0,IF(F83=1,E87*F42/((1+F23/100)*(1+F41/100))-F89-F90,IF(AND(F83=0,F84=1),(1-E93-F38*E94)*E87*F42/((1+F23/100)*(1+F41/100)),F87))) -> 49.061691 | G88: =IF(G87=0,0,IF(G83=1,F87*G42/((1+G23/100)*(1+G41/100))-G89-G90,IF(AND(G83=0,G84=1),(1-F93-G38*F94)*F87*G42/((1+G23/100)*(1+G41/100)),G87))) -> 49.816082 | H88: =IF(H87=0,0,IF(H83=1,G87*H42/((1+H23/100)*(1+H41/100))-H89-H90,IF(AND(H83=0,H84=1),(1-G93-H38*G94)*G87*H42/((1+H23/100)*(1+H41/100)),H87))) -> 50.492653 | I88: =IF(I87=0,0,IF(I83=1,H87*I42/((1+I23/100)*(1+I41/100))-I89-I90,IF(AND(I83=0,I84=1),(1-H93-I38*H94)*H87*I42/((1+I23/100)*(1+I41/100)),I87))) -> 51.098025 | J88: =IF(J87=0,0,IF(J83=1,I87*J42/((1+J23/100)*(1+J41/100))-J89-J90,IF(AND(J83=0,J84=1),(1-I93-J38*I94)*I87*J42/((1+J23/100)*(1+J41/100)),J87))) -> 51.898254 | K88: =IF(K87=0,0,IF(K83=1,J87*K42/((1+K23/100)*(1+K41/100))-K89-K90,IF(AND(K83=0,K84=1),(1-J93-K38*J94)*J87*K42/((1+K23/100)*(1+K41/100)),K87))) -> 52.8422 | L88: =IF(L87=0,0,IF(L83=1,K87*L42/((1+L23/100)*(1+L41/100))-L89-L90,IF(AND(L83=0,L84=1),(1-K93-L38*K94)*K87*L42/((1+L23/100)*(1+L41/100)),L87))) -> 53.925569 | ... U88: =IF(U87=0,0,IF(U83=1,T87*U42/((1+U23/100)*(1+U41/100))-U89-U90,IF(AND(U83=0,U84=1),(1-T93-U38*T94)*T87*U42/((1+U23/100)*(1+U41/100)),U87))) -> 66.20019
B89: Rolled over long-term debt | D89: ='Input data'!$C$67*D$87 -> 6.4240999 | E89: =IF(E87=0,0,IF(E83=1,E38*D87*D94*E42/((1+E23/100)*(1+E41/100)),IF(AND(E83=0,E84=1),(E38*D87*D94*E42/((1+E23/100)*(1+E41/100)))*(1-ABS(E87-D87*E42/((1+E23/100)*(1+E41/100)))/((E38*D87*D94*E42/((1+E23/100)*(1+E41/100)))+(D93*D87*E42/((1+E23/100)*(1+E41/100))))),0))) -> 6.1025076 | F89: =IF(F87=0,0,IF(F83=1,F38*E87*E94*F42/((1+F23/100)*(1+F41/100)),IF(AND(F83=0,F84=1),(F38*E87*E94*F42/((1+F23/100)*(1+F41/100)))*(1-ABS(F87-E87*F42/((1+F23/100)*(1+F41/100)))/((F38*E87*E94*F42/((1+F23/100)*(1+F41/100)))+(E93*E87*F42/((1+F23/100)*(1+F41/100))))),0))) -> 6.3066095 | G89: =IF(G87=0,0,IF(G83=1,G38*F87*F94*G42/((1+G23/100)*(1+G41/100)),IF(AND(G83=0,G84=1),(G38*F87*F94*G42/((1+G23/100)*(1+G41/100)))*(1-ABS(G87-F87*G42/((1+G23/100)*(1+G41/100)))/((G38*F87*F94*G42/((1+G23/100)*(1+G41/100)))+(F93*F87*G42/((1+G23/100)*(1+G41/100))))),0))) -> 6.4870779 | H89: =IF(H87=0,0,IF(H83=1,H38*G87*G94*H42/((1+H23/100)*(1+H41/100)),IF(AND(H83=0,H84=1),(H38*G87*G94*H42/((1+H23/100)*(1+H41/100)))*(1-ABS(H87-G87*H42/((1+H23/100)*(1+H41/100)))/((H38*G87*G94*H42/((1+H23/100)*(1+H41/100)))+(G93*G87*H42/((1+H23/100)*(1+H41/100))))),0))) -> 6.6600628 | I89: =IF(I87=0,0,IF(I83=1,I38*H87*H94*I42/((1+I23/100)*(1+I41/100)),IF(AND(I83=0,I84=1),(I38*H87*H94*I42/((1+I23/100)*(1+I41/100)))*(1-ABS(I87-H87*I42/((1+I23/100)*(1+I41/100)))/((I38*H87*H94*I42/((1+I23/100)*(1+I41/100)))+(H93*H87*I42/((1+I23/100)*(1+I41/100))))),0))) -> 6.8260672 | J89: =IF(J87=0,0,IF(J83=1,J38*I87*I94*J42/((1+J23/100)*(1+J41/100)),IF(AND(J83=0,J84=1),(J38*I87*I94*J42/((1+J23/100)*(1+J41/100)))*(1-ABS(J87-I87*J42/((1+J23/100)*(1+J41/100)))/((J38*I87*I94*J42/((1+J23/100)*(1+J41/100)))+(I93*I87*J42/((1+J23/100)*(1+J41/100))))),0))) -> 7.0207332 | K89: =IF(K87=0,0,IF(K83=1,K38*J87*J94*K42/((1+K23/100)*(1+K41/100)),IF(AND(K83=0,K84=1),(K38*J87*J94*K42/((1+K23/100)*(1+K41/100)))*(1-ABS(K87-J87*K42/((1+K23/100)*(1+K41/100)))/((K38*J87*J94*K42/((1+K23/100)*(1+K41/100)))+(J93*J87*K42/((1+K23/100)*(1+K41/100))))),0))) -> 7.2380576 | L89: =IF(L87=0,0,IF(L83=1,L38*K87*K94*L42/((1+L23/100)*(1+L41/100)),IF(AND(L83=0,L84=1),(L38*K87*K94*L42/((1+L23/100)*(1+L41/100)))*(1-ABS(L87-K87*L42/((1+L23/100)*(1+L41/100)))/((L38*K87*K94*L42/((1+L23/100)*(1+L41/100)))+(K93*K87*L42/((1+L23/100)*(1+L41/100))))),0))) -> 7.478192 | ... U89: =IF(U87=0,0,IF(U83=1,U38*T87*T94*U42/((1+U23/100)*(1+U41/100)),IF(AND(U83=0,U84=1),(U38*T87*T94*U42/((1+U23/100)*(1+U41/100)))*(1-ABS(U87-T87*U42/((1+U23/100)*(1+U41/100)))/((U38*T87*T94*U42/((1+U23/100)*(1+U41/100)))+(T93*T87*U42/((1+U23/100)*(1+U41/100))))),0))) -> 9.4066473
B90: Rolled over short-term debt | D90: ='Input data'!$C$68*D$87 -> 6.6882509 | E90: =IF(E87=0,0,IF(E83=1,(1-D94)*D87*E42/((1+E23/100)*(1+E41/100)),IF(AND(E83=0,E84=1),(D93*D87*E42/((1+E23/100)*(1+E41/100)))*(1-ABS(E87-D87*E42/((1+E23/100)*(1+E41/100)))/((E38*D87*D94*E42/((1+E23/100)*(1+E41/100)))+(D93*D87*E42/((1+E23/100)*(1+E41/100))))),0))) -> 6.6459114 | F90: =IF(F87=0,0,IF(F83=1,(1-E94)*E87*F42/((1+F23/100)*(1+F41/100)),IF(AND(F83=0,F84=1),(E93*E87*F42/((1+F23/100)*(1+F41/100)))*(1-ABS(F87-E87*F42/((1+F23/100)*(1+F41/100)))/((F38*E87*E94*F42/((1+F23/100)*(1+F41/100)))+(E93*E87*F42/((1+F23/100)*(1+F41/100))))),0))) -> 6.7617784 | G90: =IF(G87=0,0,IF(G83=1,(1-F94)*F87*G42/((1+G23/100)*(1+G41/100)),IF(AND(G83=0,G84=1),(F93*F87*G42/((1+G23/100)*(1+G41/100)))*(1-ABS(G87-F87*G42/((1+G23/100)*(1+G41/100)))/((G38*F87*F94*G42/((1+G23/100)*(1+G41/100)))+(F93*F87*G42/((1+G23/100)*(1+G41/100))))),0))) -> 6.8508626 | H90: =IF(H87=0,0,IF(H83=1,(1-G94)*G87*H42/((1+H23/100)*(1+H41/100)),IF(AND(H83=0,H84=1),(G93*G87*H42/((1+H23/100)*(1+H41/100)))*(1-ABS(H87-G87*H42/((1+H23/100)*(1+H41/100)))/((H38*G87*G94*H42/((1+H23/100)*(1+H41/100)))+(G93*G87*H42/((1+H23/100)*(1+H41/100))))),0))) -> 6.9302558 | I90: =IF(I87=0,0,IF(I83=1,(1-H94)*H87*I42/((1+I23/100)*(1+I41/100)),IF(AND(I83=0,I84=1),(H93*H87*I42/((1+I23/100)*(1+I41/100)))*(1-ABS(I87-H87*I42/((1+I23/100)*(1+I41/100)))/((I38*H87*H94*I42/((1+I23/100)*(1+I41/100)))+(H93*H87*I42/((1+I23/100)*(1+I41/100))))),0))) -> 7.0008167 | J90: =IF(J87=0,0,IF(J83=1,(1-I94)*I87*J42/((1+J23/100)*(1+J41/100)),IF(AND(J83=0,J84=1),(I93*I87*J42/((1+J23/100)*(1+J41/100)))*(1-ABS(J87-I87*J42/((1+J23/100)*(1+J41/100)))/((J38*I87*I94*J42/((1+J23/100)*(1+J41/100)))+(I93*I87*J42/((1+J23/100)*(1+J41/100))))),0))) -> 7.098958 | K90: =IF(K87=0,0,IF(K83=1,(1-J94)*J87*K42/((1+K23/100)*(1+K41/100)),IF(AND(K83=0,K84=1),(J93*J87*K42/((1+K23/100)*(1+K41/100)))*(1-ABS(K87-J87*K42/((1+K23/100)*(1+K41/100)))/((K38*J87*J94*K42/((1+K23/100)*(1+K41/100)))+(J93*J87*K42/((1+K23/100)*(1+K41/100))))),0))) -> 7.2162462 | L90: =IF(L87=0,0,IF(L83=1,(1-K94)*K87*L42/((1+L23/100)*(1+L41/100)),IF(AND(L83=0,L84=1),(K93*K87*L42/((1+L23/100)*(1+L41/100)))*(1-ABS(L87-K87*L42/((1+L23/100)*(1+L41/100)))/((L38*K87*K94*L42/((1+L23/100)*(1+L41/100)))+(K93*K87*L42/((1+L23/100)*(1+L41/100))))),0))) -> 7.3521718 | ... U90: =IF(U87=0,0,IF(U83=1,(1-T94)*T87*U42/((1+U23/100)*(1+U41/100)),IF(AND(U83=0,U84=1),(T93*T87*U42/((1+U23/100)*(1+U41/100)))*(1-ABS(U87-T87*U42/((1+U23/100)*(1+U41/100)))/((U38*T87*T94*U42/((1+U23/100)*(1+U41/100)))+(T93*T87*U42/((1+U23/100)*(1+U41/100))))),0))) -> 8.8307295
B91: New long-term debt | D91: ='Input data'!$C$69*D$87 -> 1.186119 | E91: =IF(E87=0,0,IF(E83=1,'Input data'!$C$58*(E87-D87*E42/((1+E23/100)*(1+E41/100))),0)) -> 2.7300474 | F91: =IF(F87=0,0,IF(F83=1,'Input data'!$C$58*(F87-E87*F42/((1+F23/100)*(1+F41/100))),0)) -> 2.6528997 | G91: =IF(G87=0,0,IF(G83=1,'Input data'!$C$58*(G87-F87*G42/((1+G23/100)*(1+G41/100))),0)) -> 2.6605728 | H91: =IF(H87=0,0,IF(H83=1,'Input data'!$C$58*(H87-G87*H42/((1+H23/100)*(1+H41/100))),0)) -> 2.6725463 | I91: =IF(I87=0,0,IF(I83=1,'Input data'!$C$58*(I87-H87*I42/((1+I23/100)*(1+I41/100))),0)) -> 2.6804214 | J91: =IF(J87=0,0,IF(J83=1,'Input data'!$C$58*(J87-I87*J42/((1+J23/100)*(1+J41/100))),0)) -> 2.870762 | K91: =IF(K87=0,0,IF(K83=1,'Input data'!$C$58*(K87-J87*K42/((1+K23/100)*(1+K41/100))),0)) -> 3.0650631 | L91: =IF(L87=0,0,IF(L83=1,'Input data'!$C$58*(L87-K87*L42/((1+L23/100)*(1+L41/100))),0)) -> 3.353787 | ... U91: =IF(U87=0,0,IF(U83=1,'Input data'!$C$58*(U87-T87*U42/((1+U23/100)*(1+U41/100))),0)) -> 4.4182023
B92: New short-term debt | D92: ='Input data'!$C$70*D$87 -> 0.1332957 | E92: =IF(E87=0,0,IF(E83=1,'Input data'!$C$57*(E87-D87*E42/((1+E23/100)*(1+E41/100))),0)) -> 0.30680196 | F92: =IF(F87=0,0,IF(F83=1,'Input data'!$C$57*(F87-E87*F42/((1+F23/100)*(1+F41/100))),0)) -> 0.29813212 | G92: =IF(G87=0,0,IF(G83=1,'Input data'!$C$57*(G87-F87*G42/((1+G23/100)*(1+G41/100))),0)) -> 0.29899442 | H92: =IF(H87=0,0,IF(H83=1,'Input data'!$C$57*(H87-G87*H42/((1+H23/100)*(1+H41/100))),0)) -> 0.30034 | I92: =IF(I87=0,0,IF(I83=1,'Input data'!$C$57*(I87-H87*I42/((1+I23/100)*(1+I41/100))),0)) -> 0.301225 | J92: =IF(J87=0,0,IF(J83=1,'Input data'!$C$57*(J87-I87*J42/((1+J23/100)*(1+J41/100))),0)) -> 0.32261543 | K92: =IF(K87=0,0,IF(K83=1,'Input data'!$C$57*(K87-J87*K42/((1+K23/100)*(1+K41/100))),0)) -> 0.34445093 | L92: =IF(L87=0,0,IF(L83=1,'Input data'!$C$57*(L87-K87*L42/((1+L23/100)*(1+L41/100))),0)) -> 0.37689764 | ... U92: =IF(U87=0,0,IF(U83=1,'Input data'!$C$57*(U87-T87*U42/((1+U23/100)*(1+U41/100))),0)) -> 0.49651633
B93: Share of short-term debt in total government debt | D93: =IF(D87<>0,(D90+D92)/(D88+D89+D90+D91+D92),0) -> 0.10922221 | E93: =IF(E87<>0,(E90+E92)/(E88+E89+E90+E91+E92),0) -> 0.10883261 | F93: =IF(F87<>0,(F90+F92)/(F88+F89+F90+F91+F92),0) -> 0.10847864 | G93: =IF(G87<>0,(G90+G92)/(G88+G89+G90+G91+G92),0) -> 0.10814504 | H93: =IF(H87<>0,(H90+H92)/(H88+H89+H90+H91+H92),0) -> 0.10782944 | I93: =IF(I87<>0,(I90+I92)/(I88+I89+I90+I91+I92),0) -> 0.10753073 | J93: =IF(J87<>0,(J90+J92)/(J88+J89+J90+J91+J92),0) -> 0.10723063 | K93: =IF(K87<>0,(K90+K92)/(K88+K89+K90+K91+K92),0) -> 0.10693145 | ... U93: =IF(U87<>0,(U90+U92)/(U88+U89+U90+U91+U92),0) -> 0.10438732
B94: Share of long-term debt in total government debt | D94: =IF(D87<>0,(D88+D89+D91)/(D88+D89+D90+D91+D92),1) -> 0.89077779 | E94: =IF(E87<>0,(E88+E89+E91)/(E88+E89+E90+E91+E92),1) -> 0.89116739 | F94: =IF(F87<>0,(F88+F89+F91)/(F88+F89+F90+F91+F92),1) -> 0.89152136 | G94: =IF(G87<>0,(G88+G89+G91)/(G88+G89+G90+G91+G92),1) -> 0.89185496 | H94: =IF(H87<>0,(H88+H89+H91)/(H88+H89+H90+H91+H92),1) -> 0.89217056 | I94: =IF(I87<>0,(I88+I89+I91)/(I88+I89+I90+I91+I92),1) -> 0.89246927 | J94: =IF(J87<>0,(J88+J89+J91)/(J88+J89+J90+J91+J92),1) -> 0.89276937 | K94: =IF(K87<>0,(K88+K89+K91)/(K88+K89+K90+K91+K92),1) -> 0.89306855 | ... U94: =IF(U87<>0,(U88+U89+U91)/(U88+U89+U90+U91+U92),1) -> 0.89561268
B96: IIR | C96: =C35 -> 1.422372 | D96: =D35 -> 1.725464 | E96: =E98+E99 -> 1.8 | F96: =F98+F99 -> 1.800295 | G96: =G98+G99 -> 1.9501148 | H96: =H98+H99 -> 2.0904195 | I96: =I98+I99 -> 2.2226873 | J96: =J98+J99 -> 2.3480787 | K96: =K98+K99 -> 2.4691227 | L96: =L98+L99 -> 2.5861719 | ... U96: =U98+U99 -> 3.2216387
B97: Long-term implicit interest rate | E97: =((E35*D87)-(E37*(D90+D92)))/(D88+D89+D91) -> 1.775559 | F97: =((F35*E87)-(F37*(E90+E92)))/(E88+E89+E91) -> 1.8099992 | G97: =IF(F87>0,(F97*F88+G36*(F91+F89))/(F88+F89+F91),G36) -> 1.9589138 | H97: =IF(G87>0,(G97*G88+H36*(G91+G89))/(G88+G89+G91),H36) -> 2.0971675 | I97: =IF(H87>0,(H97*H88+I36*(H91+H89))/(H88+H89+H91),I36) -> 2.2264279 | J97: =IF(I87>0,(I97*I88+J36*(I91+I89))/(I88+I89+I91),J36) -> 2.348003 | K97: =IF(J87>0,(J97*J88+K36*(J91+J89))/(J88+J89+J91),K36) -> 2.4647324 | L97: =IF(K87>0,(K97*K88+L36*(K91+K89))/(K88+K89+K91),L36) -> 2.5770156 | M97: =IF(L87>0,(L97*L88+M36*(L91+L89))/(L88+L89+L91),M36) -> 2.686005 | N97: =IF(M87>0,(M97*M88+N36*(M91+M89))/(M88+M89+M91),N36) -> 2.7911338 | ... U97: =IF(T87>0,(T97*T88+U36*(T91+T89))/(T88+T89+T91),U36) -> 3.290183
B98: Nominal implicit interest rate on debt (Excel approximation) | E98: =E35 -> 1.8 | F98: =F35 -> 1.800295 | G98: =(G97*(F88+F89+F91)+G37*(F90+F92))/F87 -> 1.9501148 | H98: =(H97*(G88+G89+G91)+H37*(G90+G92))/G87 -> 2.0904195 | I98: =(I97*(H88+H89+H91)+I37*(H90+H92))/H87 -> 2.2226873 | J98: =(J97*(I88+I89+I91)+J37*(I90+I92))/I87 -> 2.3480787 | K98: =(K97*(J88+J89+J91)+K37*(J90+J92))/J87 -> 2.4691227 | L98: =(L97*(K88+K89+K91)+L37*(K90+K92))/K87 -> 2.5861719 | M98: =(M97*(L88+L89+L91)+M37*(L90+L92))/L87 -> 2.7002512 | N98: =(N97*(M88+M89+M91)+N37*(M90+M92))/M87 -> 2.8108522 | ... U98: =(U97*(T88+T89+T91)+U37*(T90+T92))/T87 -> 3.2216387
B99: Diff. STATA | E99: =E108 -> 0 | F99: =F108 -> 0 | G99: =G108 -> 0 | H99: =H108 -> 0 | I99: =I108 -> 0 | J99: =J108 -> 0 | K99: =K108 -> 0 | L99: =L108 -> 0 | ... U99: =U108 -> 0
B101: (i - g) | C101: =((1+C96/100)/((1+C23/100)*(1+C41/100))-1)*100 -> -4.19208 | D101: =((1+D96/100)/((1+D23/100)*(1+D41/100))-1)*100 -> -1.1030667 | E101: =((1+E96/100)/((1+E23/100)*(1+E41/100))-1)*100 -> -0.79488309 | F101: =((1+F96/100)/((1+F23/100)*(1+F41/100))-1)*100 -> -0.97792049 | G101: =((1+G96/100)/((1+G23/100)*(1+G41/100))-1)*100 -> -1.0686862 | H101: =((1+H96/100)/((1+H23/100)*(1+H41/100))-1)*100 -> -1.045193 | I101: =((1+I96/100)/((1+I23/100)*(1+I41/100))-1)*100 -> -1.0258186 | J101: =((1+J96/100)/((1+J23/100)*(1+J41/100))-1)*100 -> -0.49841592 | ... U101: =((1+U96/100)/((1+U23/100)*(1+U41/100))-1)*100 -> -0.52157376
B104: Per memo - STATA results
B106: Debt | C106: 62.88549 | D106: 62.45568 | E106: 63.88447 | F106: 65.08111 | G106: 66.11359 | H106: 67.05585 | I106: 67.90656 | J106: 69.21133 | K106: 70.70602 | L106: 72.48663 | M106: 74.44111 | N106: 76.40131 | O106: 78.37682 | P106: 80.35704 | Q106: 82.23203 | R106: 84.08512 | S106: 85.91139 | T106: 87.61489 | U106: 89.35237
B107: IIR | C107: 1.422372 | D107: 1.725464 | E107: 1.8 | F107: 1.800295 | G107: 1.950115 | H107: 2.09042 | I107: 2.222687 | J107: 2.348079 | K107: 2.469123 | L107: 2.586172 | M107: 2.700252 | N107: 2.810853 | O107: 2.889679 | P107: 2.960013 | Q107: 3.023169 | R107: 3.07992 | S107: 3.131374 | T107: 3.178448 | U107: 3.221639
B108: IIR difference STATA - Excel | C108: 0 | D108: 0 | E108: 0 | F108: 0 | G108: 0 | H108: 0 | I108: 0 | J108: 0 | K108: 0 | L108: 0 | M108: 0 | N108: 0 | O108: 0 | P108: 0 | Q108: 0 | R108: 0 | S108: 0 | T108: 0 | U108: 0
B110: Share of long-term debt that matures every year | C110: 2023 | D110: 2024 | E110: 2025 | F110: 2026 | G110: 2027 | H110: 2028 | I110: 2029 | J110: 2030 | K110: 2031 | L110: 2032 | M110: 2033 | N110: 2034 | O110: 2035 | P110: 2036 | Q110: 2037 | R110: 2038 | S110: 2039 | T110: 2040 | U110: 2041
B111: CY | C111: 0.05937805 | D111: 0.09169554 | E111: 0.08451591 | F111: 0.1404329 | G111: 0.14147037 | H111: 0.15140739 | I111: 0.1509275 | J111: 0.1379912 | K111: 0.14570739 | L111: 0.0780102 | M111: 0.07585958 | N111: 0.07335232 | O111: 0.07245227 | P111: 0.07198851 | Q111: 0.07458982 | R111: 0.07062773 | S111: 0.0704017 | T111: 0.070434 | U111: 0.07019778
B112: EL | C112: 0.03982564 | D112: 0.03791508 | E112: 0.01981472 | F112: 0.02496022 | G112: 0.02607325 | H112: 0.03576462 | I112: 0.03694787 | J112: 0.04385737 | K112: 0.05444719 | L112: 0.05561963 | M112: 0.08569329 | N112: 0.07261707 | O112: 0.08712784 | P112: 0.08623692 | Q112: 0.10092765 | R112: 0.11955323 | S112: 0.10196508 | T112: 0.11242462 | U112: 0.11769373
B113: IE | C113: 0.04688698 | D113: 0.05422807 | E113: 0.07889056 | F113: 0.0774466 | G113: 0.07572981 | H113: 0.07418959 | I113: 0.07262341 | J113: 0.07096033 | K113: 0.0695057 | L113: 0.06791538 | M113: 0.06633688 | N113: 0.06451785 | O113: 0.0645418 | P113: 0.06458708 | Q113: 0.06458341 | R113: 0.06457916 | S113: 0.06457386 | T113: 0.06456866 | U113: 0.06456653
B114: PT | C114: 0.04646669 | D114: 0.04920361 | E114: 0.06591027 | F114: 0.077817 | G114: 0.07721673 | H114: 0.07475628 | I114: 0.07115402 | J114: 0.06275227 | K114: 0.09885626 | L114: 0.07792318 | M114: 0.07872086 | N114: 0.06429625 | O114: 0.08357329 | P114: 0.08621118 | Q114: 0.06346242 | R114: 0.07531911 | S114: 0.06068811 | T114: 0.06391206 | U114: 0.06064803

Sheet Adjustment scenario
B3: Country | C3: ='Input data'!C3 -> DE
B4: Key years
B5: ='Input data'!B5 -> Last year before the adjustment | C5: =+'Input data'!C5 -> 2024
B6: Last year of adjustment | C6: =+C5+'Criteria results'!$F$5 -> 2028
B7: Last year of no-fiscal-policy-change projections | C7: =C5+'Criteria results'!$F$5+10 -> 2038
B9: Key assumptions
C10: ='Input data'!$C$5-1 -> 2023 | D10: =C10+1 -> 2024 | E10: =D10+1 -> 2025 | F10: =E10+1 -> 2026 | G10: =F10+1 -> 2027 | H10: =G10+1 -> 2028 | I10: =H10+1 -> 2029 | J10: =I10+1 -> 2030 | K10: =J10+1 -> 2031 | ... U10: =T10+1 -> 2041
B11: Fiscal assumptions (% of GDP)
B12: Structural primary balance ('+' means 'surplus') | C12: ='Input data'!C13 -> -1.260914 | D12: ='Input data'!D13 -> -1.015287 | E12: =IF(E10<=$C$6, IF(AND(D87=1,D77<=-3.05,'Criteria results'!$F$6<0.5),D12+0.5, IF(AND(D78<=-1.55,'Criteria results'!$F$5=4,'Criteria results'!$F$6<0.4),D12+0.4, IF(AND(D78<=-1.55,'Criteria results'!$F$5=7,'Criteria results'!$F$6<0.25),D12+0.25, D12+'Criteria results'!$F$6))),D12) -> -0.475287 | F12: =IF(F10<=$C$6, IF(AND(E87=1,E77<=-3.05,'Criteria results'!$F$6<0.5),E12+0.5, IF(AND(E78<=-1.55,'Criteria results'!$F$5=4,'Criteria results'!$F$6<0.4),E12+0.4, IF(AND(E78<=-1.55,'Criteria results'!$F$5=7,'Criteria results'!$F$6<0.25),E12+0.25, E12+'Criteria results'!$F$6))),E12) -> 0.064713 | G12: =IF(G10<=$C$6, IF(AND(F87=1,F77<=-3.05,'Criteria results'!$F$6<0.5),F12+0.5, IF(AND(F78<=-1.55,'Criteria results'!$F$5=4,'Criteria results'!$F$6<0.4),F12+0.4, IF(AND(F78<=-1.55,'Criteria results'!$F$5=7,'Criteria results'!$F$6<0.25),F12+0.25, F12+'Criteria results'!$F$6))),F12) -> 0.604713 | H12: =IF(H10<=$C$6, IF(AND(G87=1,G77<=-3.05,'Criteria results'!$F$6<0.5+H91),G12+0.5+H91, IF(AND(G78<=-1.55,'Criteria results'!$F$5=4,'Criteria results'!$F$6<0.4),G12+0.4, IF(AND(G78<=-1.55,'Criteria results'!$F$5=7,'Criteria results'!$F$6<0.25),G12+0.25, G12+'Criteria results'!$F$6))),G12) -> 1.144713 | I12: =IF(I10<=$C$6, IF(AND(H87=1,H77<=-3.05,'Criteria results'!$F$6<0.5+I91),H12+0.5+I91, IF(AND(H78<=-1.55,'Criteria results'!$F$5=4,'Criteria results'!$F$6<0.4),H12+0.4, IF(AND(H78<=-1.55,'Criteria results'!$F$5=7,'Criteria results'!$F$6<0.25),H12+0.25, H12+'Criteria results'!$F$6))),H12) -> 1.144713 | J12: =IF(J10<=$C$6, IF(AND(I87=1,I77<=-3.05,'Criteria results'!$F$6<0.5+J91),I12+0.5+J91, IF(AND(I78<=-1.55,'Criteria results'!$F$5=4,'Criteria results'!$F$6<0.4),I12+0.4, IF(AND(I78<=-1.55,'Criteria results'!$F$5=7,'Criteria results'!$F$6<0.25),I12+0.25, I12+'Criteria results'!$F$6))),I12) -> 1.144713 | K12: =IF(K10<=$C$6, IF(AND(J87=1,J77<=-3.05,'Criteria results'!$F$6<0.5+K91),J12+0.5+K91, IF(AND(J78<=-1.55,'Criteria results'!$F$5=4,'Criteria results'!$F$6<0.4),J12+0.4, IF(AND(J78<=-1.55,'Criteria results'!$F$5=7,'Criteria results'!$F$6<0.25),J12+0.25, J12+'Criteria results'!$F$6))),J12) -> 1.144713 | L12: =K12 -> 1.144713 | M12: =L12 -> 1.144713 | N12: =M12 -> 1.144713 | O12: =N12 -> 1.144713 | P12: =O12 -> 1.144713 | Q12: =P12 -> 1.144713 | R12: =Q12 -> 1.144713 | S12: =R12 -> 1.144713 | ... U12: =T12 -> 1.144713
B13: Annual change in SPB | E13: =E12-D12 -> 0.54 | F13: =F12-E12 -> 0.54 | G13: =G12-F12 -> 0.54 | H13: =H12-G12 -> 0.54 | I13: =I12-H12 -> 0 | J13: =J12-I12 -> 0 | K13: =K12-J12 -> 0 | L13: =L12-K12 -> 0 | ... U13: =U12-T12 -> 0
B14: One-off and other temporary measures | C14: ='Input data'!C14 -> 0 | D14: ='Input data'!D14 -> 0 | E14: ='Input data'!E14 -> 0 | F14: ='Input data'!F14 -> 0 | G14: ='Input data'!G14 -> 0 | H14: ='Input data'!H14 -> 0 | I14: ='Input data'!I14 -> 0 | J14: ='Input data'!J14 -> 0 | ... U14: ='Input data'!U14 -> 0
B15: Stock flow adjustments (without exchange rate effect) | C15: ='Input data'!C15 -> -1.000485 | D15: ='Input data'!D15 -> -1.439456 | E15: ='Input data'!E15 -> 0.0857679 | F15: ='Input data'!F15 -> 0.1097981 | G15: ='Input data'!G15 -> 0 | H15: ='Input data'!H15 -> 0 | I15: ='Input data'!I15 -> 0 | J15: ='Input data'!J15 -> 0 | ... U15: ='Input data'!U15 -> 0
B17: ='Input data'!B19 -> Cost of ageing and selected public revenue (based on the Commission-Council 2024 Ageing Report ("AR 2024"))
B18: Total ageing cost (net of taxes on pensions) | C18: ='Input data'!C20 -> 23.1 | D18: ='Input data'!D20 -> 23.3 | E18: ='Input data'!E20 -> 23.4 | F18: ='Input data'!F20 -> 23.4 | G18: ='Input data'!G20 -> 23.6 | H18: ='Input data'!H20 -> 23.7 | I18: ='Input data'!I20 -> 23.8 | J18: ='Input data'!J20 -> 23.9 | ... U18: ='Input data'!U20 -> 24.4
B19: Property income | C19: ='Input data'!C26 -> 0.7164173 | D19: ='Input data'!D26 -> 0.7117602 | E19: ='Input data'!E26 -> 0.7071032 | F19: ='Input data'!F26 -> 0.7024462 | G19: ='Input data'!G26 -> 0.6977891 | H19: ='Input data'!H26 -> 0.6931321 | I19: ='Input data'!I26 -> 0.6884751 | J19: ='Input data'!J26 -> 0.683818 | ... U19: ='Input data'!U26 -> 0.6325905
B21: GDP growth assumptions
B22: Actual GDP (real)
B23: Level | C23: ='Baseline NFPC'!C22 -> 3615.547 | D23: ='Baseline NFPC'!D22 -> 3606.923 | E23: =IF(AND(E50>1,D50>1), E27*(1+('Baseline NFPC'!E$29+E51)/100)-D23*$C$47*(E12-D12)/100, IF(E50=1,E27,D23*(1+E52/100))) -> 3598.5247 | F23: =IF(AND(F50>1,E50>1), F27*(1+('Baseline NFPC'!F$29+F51)/100)-E23*$C$47*(F12-E12)/100, IF(F50=1,F27,E23*(1+F52/100))) -> 3611.4128 | G23: =IF(AND(G50>1,F50>1), G27*(1+G51/100)-F23*$C$47*(G12-F12)/100, IF(G50=1,G27,F23*(1+G52/100))) -> 3635.92 | H23: =IF(AND(H50>1,G50>1), H27*(1+H51/100)-G23*$C$47*(H12-G12)/100, IF(H50=1,H27,G23*(1+H52/100))) -> 3661.631 | I23: =IF(AND(I50>1,H50>1), I27*(1+I51/100)-H23*$C$47*(I12-H12)/100, IF(I50=1,I27,H23*(1+I52/100))) -> 3704.1989 | J23: =IF(AND(J50>1,I50>1), J27*(1+J51/100)-I23*$C$47*(J12-I12)/100, IF(J50=1,J27,I23*(1+J52/100))) -> 3746.2686 | K23: =IF(AND(K50>1,J50>1), K27*(1+K51/100)-J23*$C$47*(K12-J12)/100, IF(K50=1,K27,J23*(1+K52/100))) -> 3787.7192 | L23: =IF(AND(L50>1,K50>1), L27*(1+L51/100)-K23*$C$47*(L12-K12)/100, IF(L50=1,L27,K23*(1+L52/100))) -> 3809.9402 | M23: =IF(AND(M50>1,L50>1), M27*(1+M51/100)-L23*$C$47*(M12-L12)/100, IF(M50=1,M27,L23*(1+M52/100))) -> 3832.2136 | N23: =IF(AND(N50>1,M50>1), N27*(1+N51/100)-M23*$C$47*(N12-M12)/100, IF(N50=1,N27,M23*(1+N52/100))) -> 3858.1252 | ... U23: =IF(AND(U50>1,T50>1), U27*(1+U51/100)-T23*$C$47*(U12-T12)/100, IF(U50=1,U27,T23*(1+U52/100))) -> 4227.9733
B24: Growth rate | C24: ='Baseline NFPC'!C23 -> -0.2664383 | D24: ='Baseline NFPC'!D23 -> -0.2385261 | E24: =100*(E23/D23-1) -> -0.2328389 | F24: =100*(F23/E23-1) -> 0.35815102 | G24: =100*(G23/F23-1) -> 0.67860352 | H24: =100*(H23/G23-1) -> 0.70713923 | I24: =100*(I23/H23-1) -> 1.1625397 | J24: =100*(J23/I23-1) -> 1.1357286 | K24: =100*(K23/J23-1) -> 1.1064518 | L24: =100*(L23/K23-1) -> 0.5866577 | ... U24: =100*(U23/T23-1) -> 1.560002
B26: Potential GDP (real)
B27: Level | C27: ='Input data'!C34 -> 3640.494 | D27: =+C27*(1+'Input data'!D33/100) -> 3656.893 | E27: =+D27*(1+'Input data'!E33/100) -> 3666.669 | F27: =+E27*(1+'Input data'!F33/100) -> 3679.4239 | G27: =+F27*(1+'Input data'!G33/100) -> 3696.0924 | H27: =+G27*(1+'Input data'!H33/100) -> 3716.695 | I27: =+H27*(1+'Input data'!I33/100) -> 3741.1498 | J27: =+I27*(1+'Input data'!J33/100) -> 3764.8611 | K27: =+J27*(1+'Input data'!K33/100) -> 3787.7192 | ... U27: =+T27*(1+'Input data'!U33/100) -> 4227.9728
B29: Output gap
B30: Output gap | C30: =100*(C23/C27-1) -> -0.68526414 | D30: =100*(D23/D27-1) -> -1.3664607 | E30: =100*(E23/E27-1) -> -1.8584807 | F30: =100*(F23/F27-1) -> -1.848418 | G30: =100*(G23/G27-1) -> -1.6279999 | H30: =100*(H23/H27-1) -> -1.4815314 | I30: =100*(I23/I27-1) -> -0.98768759 | J30: =100*(J23/J27-1) -> -0.4938438 | ... U30: =100*(U23/U27-1) -> 1.1962257e-05
B32: Actual GDP (nominal, national currency)
B33: Growth rate | C33: =100*((1+C24/100)*(1+C42/100)-1) -> 5.8601126 | D33: =100*((1+D24/100)*(1+D42/100)-1) -> 2.8600792 | E33: =100*((1+E24/100)*(1+E42/100)-1) -> 2.2007954 | F33: =100*((1+F24/100)*(1+F42/100)-1) -> 2.531762 | G33: =100*((1+G24/100)*(1+G42/100)-1) -> 2.8710032 | H33: =100*((1+H24/100)*(1+H42/100)-1) -> 2.9120118 | I33: =100*((1+I24/100)*(1+I42/100)-1) -> 3.3892878 | J33: =100*((1+J24/100)*(1+J42/100)-1) -> 3.3737884 | ... U33: =100*((1+U24/100)*(1+U42/100)-1) -> 3.7628384
B35: Interest rates
B36: Nominal implicit interest rate on debt | C36: ='Input data'!C37 -> 1.422372 | D36: ='Input data'!D37 -> 1.725464 | E36: ='Input data'!E37 -> 1.8 | F36: =F109 -> 1.7990942 | G36: =G109 -> 1.9393065 | H36: =H109 -> 2.0651773 | I36: =I109 -> 2.1807763 | J36: =J109 -> 2.2924541 | K36: =K109 -> 2.4006192 | L36: =L109 -> 2.5056322 | M36: =M109 -> 2.6113354 | ... U36: =U109 -> 3.1415413
B37: Long-term interest rate | C37: ='Input data'!C$39 -> 2.43 | D37: ='Input data'!D$39 -> 2.3225 | E37: ='Input data'!E$39 -> 2.544438 | F37: ='Input data'!F$39 -> 2.698655 | G37: ='Baseline NFPC'!G36 -> 2.7743606 | H37: ='Baseline NFPC'!H36 -> 2.8500662 | I37: ='Baseline NFPC'!I36 -> 2.9257719 | J37: ='Baseline NFPC'!J36 -> 3.0014775 | K37: ='Baseline NFPC'!K36 -> 3.0771831 | L37: ='Baseline NFPC'!L36 -> 3.1528887 | M37: ='Baseline NFPC'!M36 -> 3.2285944 | N37: ='Baseline NFPC'!N36 -> 3.3043 | ... U37: ='Baseline NFPC'!U36 -> 3.547795
B38: Short-term interest rate | C38: ='Input data'!C$38 -> 3.43 | D38: ='Input data'!D$38 -> 3.570833 | E38: ='Input data'!E$38 -> 1.999333 | F38: ='Input data'!F$38 -> 1.720833 | G38: ='Baseline NFPC'!G37 -> 1.8778014 | H38: ='Baseline NFPC'!H37 -> 2.0347698 | I38: ='Baseline NFPC'!I37 -> 2.1917381 | J38: ='Baseline NFPC'!J37 -> 2.3487065 | K38: ='Baseline NFPC'!K37 -> 2.5056749 | L38: ='Baseline NFPC'!L37 -> 2.6626432 | M38: ='Baseline NFPC'!M37 -> 2.8196116 | N38: ='Baseline NFPC'!N37 -> 2.97658 | ... U38: ='Baseline NFPC'!U37 -> 2.634777
B39: Share of long-term debt that matures every year | C39: ='Baseline NFPC'!C38 -> 0.12643541 | D39: ='Baseline NFPC'!D38 -> 0.11798594 | E39: ='Baseline NFPC'!E38 -> 0.11258884 | F39: ='Baseline NFPC'!F38 -> 0.11390289 | G39: ='Baseline NFPC'!G38 -> 0.11521694 | H39: ='Baseline NFPC'!H38 -> 0.11653099 | I39: ='Baseline NFPC'!I38 -> 0.11784504 | J39: ='Baseline NFPC'!J38 -> 0.1191591 | ... U39: ='Baseline NFPC'!U38 -> 0.1244153
B41: Inflation and exchange rate
B42: GDP deflator (National currency) | C42: ='Input data'!C42 -> 6.142918 | D42: ='Input data'!D42 -> 3.106014 | E42: ='Input data'!E42 -> 2.439314 | F42: ='Input data'!F42 -> 2.165854 | G42: ='Baseline NFPC'!G41 -> 2.1776222 | H42: ='Baseline NFPC'!H41 -> 2.1893905 | I42: ='Baseline NFPC'!I41 -> 2.2011587 | J42: ='Baseline NFPC'!J41 -> 2.212927 | K42: ='Baseline NFPC'!K41 -> 2.2246952 | L42: ='Baseline NFPC'!L41 -> 2.2364635 | M42: ='Baseline NFPC'!M41 -> 2.2482317 | N42: ='Baseline NFPC'!N41 -> 2.26 | ... U42: ='Baseline NFPC'!U41 -> 2.169
B43: Exchange rate composite change (weighted by share of debt in each currency) | C43: ='Baseline NFPC'!C42 -> 0.9997445 | D43: ='Baseline NFPC'!D42 -> 0.9999892 | E43: ='Baseline NFPC'!E42 -> 0.9997361 | F43: ='Baseline NFPC'!F42 -> 0.9998241 | G43: ='Baseline NFPC'!G42 -> 1 | H43: ='Baseline NFPC'!H42 -> 1 | I43: ='Baseline NFPC'!I42 -> 1 | J43: ='Baseline NFPC'!J42 -> 1 | ... U43: ='Baseline NFPC'!U42 -> 1
B45: Intermediate calculations (growth rate equation)
B47: Fiscal multiplier | C47: ='Input data'!C49 -> 0.75
B48: Budget balance semi-elasticity | C48: ='Input data'!C50 -> 0.504
B50: Auxiliary variable to control the closure of the output gap | C50: 0 | D50: =IF(AND(ABS((D12-C12)-('Input data'!D13-'Input data'!C13))>0.0001,ABS(D12-C12)>0.0001,D$10>$C$5),4,IF(C50=4,3,IF(C50=3,2,IF(C50=2,1,0)))) -> 0 | E50: =IF(AND(ABS((E12-D12)-('Baseline NFPC'!E12-'Baseline NFPC'!D12))>0.0001,ABS(E12-D12)>0.0001,E$10>$C$5),4,IF(D50=4,3,IF(D50=3,2,IF(D50=2,1,0)))) -> 4 | F50: =IF(AND(ABS((F12-E12)-('Baseline NFPC'!F12-'Baseline NFPC'!E12))>0.0001,ABS(F12-E12)>0.0001,F$10>$C$5),4,IF(E50=4,3,IF(E50=3,2,IF(E50=2,1,0)))) -> 4 | G50: =IF(AND(ABS((G12-F12)-('Baseline NFPC'!G12-'Baseline NFPC'!F12))>0.0001,ABS(G12-F12)>0.0001,G$10>$C$5),4,IF(F50=4,3,IF(F50=3,2,IF(F50=2,1,0)))) -> 4 | H50: =IF(AND(ABS((H12-G12)-('Baseline NFPC'!H12-'Baseline NFPC'!G12))>0.0001,ABS(H12-G12)>0.0001,H$10>$C$5),4,IF(G50=4,3,IF(G50=3,2,IF(G50=2,1,0)))) -> 4 | I50: =IF(AND(ABS((I12-H12)-('Baseline NFPC'!I12-'Baseline NFPC'!H12))>0.0001,ABS(I12-H12)>0.0001,I$10>$C$5),4,IF(H50=4,3,IF(H50=3,2,IF(H50=2,1,0)))) -> 3 | J50: =IF(AND(ABS((J12-I12)-('Baseline NFPC'!J12-'Baseline NFPC'!I12))>0.0001,ABS(J12-I12)>0.0001,J$10>$C$5),4,IF(I50=4,3,IF(I50=3,2,IF(I50=2,1,0)))) -> 2 | K50: =IF(AND(ABS((K12-J12)-('Baseline NFPC'!K12-'Baseline NFPC'!J12))>0.0001,ABS(K12-J12)>0.0001,K$10>$C$5),4,IF(J50=4,3,IF(J50=3,2,IF(J50=2,1,0)))) -> 1 | L50: =IF(AND(ABS((L12-K12)-('Baseline NFPC'!L12-'Baseline NFPC'!K12))>0.0001,ABS(L12-K12)>0.0001,L$10>$C$5),4,IF(K50=4,3,IF(K50=3,2,IF(K50=2,1,0)))) -> 0 | ... U50: =IF(AND(ABS((U12-T12)-('Baseline NFPC'!U12-'Baseline NFPC'!T12))>0.0001,ABS(U12-T12)>0.0001,U$10>$C$5),4,IF(T50=4,3,IF(T50=3,2,IF(T50=2,1,0)))) -> 0
B51: OG intermediate auxiliary value | C51: 0 | D51: =IF(C50=4,2/3*(C30-'Baseline NFPC'!C29),IF(C50=3,1/3*(#REF!-'Baseline NFPC'!#REF!),0)) -> 0 | E51: =IF(D50=4,2/3*(D30-'Baseline NFPC'!D29),IF(D50=3,1/3*(C30-'Baseline NFPC'!C29),0)) -> 0 | F51: =IF(E50=4,2/3*(E30-'Baseline NFPC'!E29),IF(E50=3,1/3*(D30-'Baseline NFPC'!D29),0)) -> -0.26560052 | G51: =IF(F50=4,2/3*F30,IF(F50=3,1/3*E30,0)) -> -1.2322787 | H51: =IF(G50=4,2/3*G30,IF(G50=3,1/3*F30,0)) -> -1.0853333 | I51: =IF(H50=4,2/3*H30,IF(H50=3,1/3*G30,0)) -> -0.98768759 | J51: =IF(I50=4,2/3*I30,IF(I50=3,1/3*H30,0)) -> -0.4938438 | K51: =IF(J50=4,2/3*J30,IF(J50=3,1/3*I30,0)) -> 0 | L51: =IF(K50=4,2/3*K30,IF(K50=3,1/3*J30,0)) -> 0 | M51: =IF(L50=4,2/3*L30,IF(L50=3,1/3*K30,0)) -> 0 | N51: =IF(M50=4,2/3*M30,IF(M50=3,1/3*L30,0)) -> 0 | ... U51: =IF(T50=4,2/3*T30,IF(T50=3,1/3*S30,0)) -> 0
B52: GDP intermediate growth rate - only feedback effect and no closure of the OG | C52: 0 | D52: ='Input data'!D30-$C$47*((D12-C12)-('Input data'!D13-'Input data'!C13)) -> -0.2385261 | E52: ='Input data'!E30-$C$47*(E12-D12) -> -0.2328389 | F52: ='Input data'!F30-$C$47*(F12-E12) -> 0.2212352 | G52: ='Input data'!G30-$C$47*(G12-F12) -> 0.4501665 | H52: ='Input data'!H30-$C$47*(H12-G12) -> 0.5533591 | I52: ='Input data'!I30-$C$47*(I12-H12) -> 1.057734 | J52: ='Input data'!J30-$C$47*(J12-I12) -> 0.6338005 | K52: ='Input data'!K30-$C$47*(K12-J12) -> 0.6071447 | L52: ='Input data'!L30-$C$47*(L12-K12) -> 0.5866577 | ... U52: ='Input data'!U30-$C$47*(U12-T12) -> 1.560002
B54: Debt projections
C56: ='Input data'!$C$5-1 -> 2023 | D56: =C56+1 -> 2024 | E56: =D56+1 -> 2025 | F56: =E56+1 -> 2026 | G56: =F56+1 -> 2027 | H56: =G56+1 -> 2028 | I56: =H56+1 -> 2029 | J56: =I56+1 -> 2030 | K56: =J56+1 -> 2031 | ... U56: =T56+1 -> 2041
B57: Gross debt | C57: =+'Input data'!C12 -> 62.88549 | D57: =+C57+D58 -> 62.455679 | E57: =+D57+E58 -> 63.69213 | F57: =+E57+F58 -> 64.202561 | G57: =+F57+G58 -> 63.836882 | H57: =+G57+H58 -> 62.913564 | I57: =+H57+I58 -> 61.63591 | J57: =+I57+J58 -> 60.30467 | K57: =+J57+K58 -> 58.916634 | ... U57: =+T57+U58 -> 52.285467
B58: Change in debt (-1+2+3) | D58: =-D59+D67+D72 -> -0.42981088 | E58: =-E59+E67+E72 -> 1.2364509 | F58: =-F59+F67+F72 -> 0.51043146 | G58: =-G59+G67+G72 -> -0.36567993 | H58: =-H59+H67+H72 -> -0.92331721 | I58: =-I59+I67+I72 -> -1.2776545 | J58: =-J59+J67+J72 -> -1.3312398 | K58: =-K59+K67+K72 -> -1.3880363 | ... U58: =-U59+U67+U72 -> -0.70144532
B59: (1) Primary balance (1.1 + 1.2 - 1.3 -1.4 -1.5 - 1.6 -1.7) | D59: =D60+D61-D62-D63-D64-D65-D66 -> -1.7039832 | E59: =E60+E61-E62-E63-E64-E65-E66 -> -1.4119613 | F59: =F60+F61-F62-F63-F64-F65-F66 -> -0.86688967 | G59: =G60+G61-G62-G63-G64-G65-G66 -> -0.21579894 | H59: =H60+H61-H62-H63-H64-H65-H66 -> 0.39802118 | I59: =I60+I61-I62-I63-I64-I65-I66 -> 0.54226145 | J59: =J60+J61-J62-J63-J64-J65-J66 -> 0.68650163 | K59: =K60+K61-K62-K63-K64-K65-K66 -> 0.8307419 | ... U59: =U60+U61-U62-U63-U64-U65-U66 -> 0.38417743
B60: (1.1) Structural primary balance (before ageing cost) | D60: =D12 -> -1.015287 | E60: =IF(E12="",D60,E12) -> -0.475287 | F60: =IF(F12="",E60,F12) -> 0.064713 | G60: =IF(G12="",F60,G12) -> 0.604713 | H60: =IF(H12="",G60,H12) -> 1.144713 | I60: =IF(I12="",H60,I12) -> 1.144713 | J60: =IF(J12="",I60,J12) -> 1.144713 | K60: =IF(K12="",J60,K12) -> 1.144713 | L60: =IF(L12="",K60,L12) -> 1.144713 | ... U60: =IF(U12="",T60,U12) -> 1.144713
B61: (1.2) Cumulated budgetary effort (in terms of primary balance) | D61: 0 | E61: 0 | F61: 0 | G61: 0 | H61: 0 | I61: 0 | J61: 0 | K61: 0 | L61: 0 | M61: 0 | N61: 0 | O61: 0 | P61: 0 | Q61: 0 | R61: 0 | S61: 0 | T61: 0 | U61: 0
B62: (1.3) Cyclical component | D62: =-$C$48*D30 -> 0.68869622 | E62: =-$C$48*E30 -> 0.93667427 | F62: =-$C$48*F30 -> 0.93160267 | G62: =-$C$48*G30 -> 0.82051194 | H62: =-$C$48*H30 -> 0.74669182 | I62: =-$C$48*I30 -> 0.49779455 | J62: =-$C$48*J30 -> 0.24889727 | K62: =-$C$48*K30 -> 0 | ... U62: =-$C$48*U30 -> -6.0289775e-06
B63: (1.4) One-off and other temporary measures | D63: =-D14 -> 0 | E63: =-E14 -> 0 | F63: =-F14 -> 0 | G63: =-G14 -> 0 | H63: =-H14 -> 0 | I63: =-I14 -> 0 | J63: =-J14 -> 0 | K63: =-K14 -> 0 | ... U63: =-U14 -> 0
B64: (1.5) Cost of ageing | D64: =IF(D$56<=$C$6,0,HLOOKUP(D$56,'Input data'!$C$9:$AZ$26,12,FALSE)-HLOOKUP($C$6,'Input data'!$C$9:$AZ$26,12,FALSE)) -> 0 | E64: =IF(E$56<=$C$6,0,HLOOKUP(E$56,'Input data'!$C$9:$AZ$26,12,FALSE)-HLOOKUP($C$6,'Input data'!$C$9:$AZ$26,12,FALSE)) -> 0 | F64: =IF(F$56<=$C$6,0,HLOOKUP(F$56,'Input data'!$C$9:$AZ$26,12,FALSE)-HLOOKUP($C$6,'Input data'!$C$9:$AZ$26,12,FALSE)) -> 0 | G64: =IF(G$56<=$C$6,0,HLOOKUP(G$56,'Input data'!$C$9:$AZ$26,12,FALSE)-HLOOKUP($C$6,'Input data'!$C$9:$AZ$26,12,FALSE)) -> 0 | H64: =IF(H$56<=$C$6,0,HLOOKUP(H$56,'Input data'!$C$9:$AZ$26,12,FALSE)-HLOOKUP($C$6,'Input data'!$C$9:$AZ$26,12,FALSE)) -> 0 | I64: =IF(I$56<=$C$6,0,HLOOKUP(I$56,'Input data'!$C$9:$AZ$26,12,FALSE)-HLOOKUP($C$6,'Input data'!$C$9:$AZ$26,12,FALSE)) -> 0.1 | J64: =IF(J$56<=$C$6,0,HLOOKUP(J$56,'Input data'!$C$9:$AZ$26,12,FALSE)-HLOOKUP($C$6,'Input data'!$C$9:$AZ$26,12,FALSE)) -> 0.2 | K64: =IF(K$56<=$C$6,0,HLOOKUP(K$56,'Input data'!$C$9:$AZ$26,12,FALSE)-HLOOKUP($C$6,'Input data'!$C$9:$AZ$26,12,FALSE)) -> 0.3 | ... U64: =IF(U$56<=$C$6,0,HLOOKUP(U$56,'Input data'!$C$9:$AZ$26,12,FALSE)-HLOOKUP($C$6,'Input data'!$C$9:$AZ$26,12,FALSE)) -> 0.7
B65: (1.6) Property incomes | D65: =IF(D$56<=$C$5,0,-HLOOKUP(D$56,'Input data'!$C$9:$AZ$26,18,FALSE)+HLOOKUP($C$6,'Input data'!$C$9:$AZ$26,18,FALSE)) -> 0 | E65: =IF(E$56<=$C$6,0,-HLOOKUP(E$56,'Input data'!$C$9:$AZ$26,18,FALSE)+HLOOKUP($C$6,'Input data'!$C$9:$AZ$26,18,FALSE)) -> 0 | F65: =IF(F$56<=$C$6,0,-HLOOKUP(F$56,'Input data'!$C$9:$AZ$26,18,FALSE)+HLOOKUP($C$6,'Input data'!$C$9:$AZ$26,18,FALSE)) -> 0 | G65: =IF(G$56<=$C$6,0,-HLOOKUP(G$56,'Input data'!$C$9:$AZ$26,18,FALSE)+HLOOKUP($C$6,'Input data'!$C$9:$AZ$26,18,FALSE)) -> 0 | H65: =IF(H$56<=$C$6,0,-HLOOKUP(H$56,'Input data'!$C$9:$AZ$26,18,FALSE)+HLOOKUP($C$6,'Input data'!$C$9:$AZ$26,18,FALSE)) -> 0 | I65: =IF(I$56<=$C$6,0,-HLOOKUP(I$56,'Input data'!$C$9:$AZ$26,18,FALSE)+HLOOKUP($C$6,'Input data'!$C$9:$AZ$26,18,FALSE)) -> 0.004657 | J65: =IF(J$56<=$C$6,0,-HLOOKUP(J$56,'Input data'!$C$9:$AZ$26,18,FALSE)+HLOOKUP($C$6,'Input data'!$C$9:$AZ$26,18,FALSE)) -> 0.0093141 | K65: =IF(K$56<=$C$6,0,-HLOOKUP(K$56,'Input data'!$C$9:$AZ$26,18,FALSE)+HLOOKUP($C$6,'Input data'!$C$9:$AZ$26,18,FALSE)) -> 0.0139711 | L65: =IF(L$56<=$C$6,0,-HLOOKUP(L$56,'Input data'!$C$9:$AZ$26,18,FALSE)+HLOOKUP($C$6,'Input data'!$C$9:$AZ$26,18,FALSE)) -> 0.0186281 | ... U65: =IF(U$56<=$C$6,0,-HLOOKUP(U$56,'Input data'!$C$9:$AZ$26,18,FALSE)+HLOOKUP($C$6,'Input data'!$C$9:$AZ$26,18,FALSE)) -> 0.0605416
B66: (1.7) Revenues | D66: 0 | E66: 0 | F66: 0 | G66: 0 | H66: 0 | I66: 0 | J66: 0 | K66: 0 | L66: 0 | M66: 0 | N66: 0 | O66: 0 | P66: 0 | Q66: 0 | R66: 0 | S66: 0 | T66: 0 | U66: 0
B67: (2) Snowball effect (2.1 + 2.2 + 2.3) | D67: =SUM(D68:D71) -> -0.6936801 | E67: =SUM(E68:E71) -> -0.24521838 | F67: =SUM(F68:F71) -> -0.45532551 | G67: =SUM(G68:G71) -> -0.58147887 | H67: =SUM(H68:H71) -> -0.52529603 | I67: =SUM(I68:I71) -> -0.73539304 | J67: =SUM(J68:J71) -> -0.64473813 | K67: =SUM(K68:K71) -> -0.55729441 | ... U67: =SUM(U68:U71) -> -0.31726789
B68: (2.1) Interest expenditure | D68: =C57*D36/100*(1/(1+D33/100)) -> 1.0548956 | E68: =D57*E36/100*(1/(1+E33/100)) -> 1.0999936 | F68: =E57*F36/100*(1/(1+F33/100)) -> 1.1175868 | G68: =F57*G36/100*(1/(1+G33/100)) -> 1.2103357 | H68: =G57*H36/100*(1/(1+H33/100)) -> 1.2810407 | I68: =H57*I36/100*(1/(1+I33/100)) -> 1.3270273 | J68: =I57*J36/100*(1/(1+J33/100)) -> 1.36686 | K68: =J57*K36/100*(1/(1+K33/100)) -> 1.4006819 | ... U68: =T57*U36/100*(1/(1+U33/100)) -> 1.6042408
B69: (2.2) Growth effect | D69: =-C57*(D24/100)*(1/(1+D33/100)) -> 0.14582752 | E69: =-D57*(E24/100)*(1/(1+E33/100)) -> 0.14228961 | F69: =-E57*(F24/100)*(1/(1+F33/100)) -> -0.22248131 | G69: =-F57*(G24/100)*(1/(1+G33/100)) -> -0.42352153 | H69: =-G57*(H24/100)*(1/(1+H33/100)) -> -0.43864231 | I69: =-H57*(I24/100)*(1/(1+I33/100)) -> -0.7074187 | J69: =-I57*(J24/100)*(1/(1+J33/100)) -> -0.67717035 | K69: =-J57*(K24/100)*(1/(1+K33/100)) -> -0.64557807 | ... U69: =-T57*(U24/100)*(1/(1+U33/100)) -> -0.79662132
B70: (2.3) Inflation effect | D70: =-C57*D42/100*(1/(1+D42/100)) -> -1.894392 | E70: =-D57*E42/100*(1/(1+E42/100)) -> -1.4872123 | F70: =-E57*F42/100*(1/(1+F42/100)) -> -1.3502344 | G70: =-F57*G42/100*(1/(1+G42/100)) -> -1.368293 | H70: =-G57*H42/100*(1/(1+H42/100)) -> -1.3676944 | I70: =-H57*I42/100*(1/(1+I42/100)) -> -1.3550017 | J70: =-I57*J42/100*(1/(1+J42/100)) -> -1.3344278 | K70: =-J57*K42/100*(1/(1+K42/100)) -> -1.3123983 | ... U70: =-T57*U42/100*(1/(1+U42/100)) -> -1.1248873
B71: (2.4) Exchange rate effect linked to the interest rate | D71: ='Baseline NFPC'!D70 -> -1.1222575e-05 | E71: ='Baseline NFPC'!E70 -> -0.00028926533 | F71: ='Baseline NFPC'!F70 -> -0.00019655417 | G71: 0 | H71: 0 | I71: 0 | J71: 0 | K71: 0 | L71: 0 | M71: 0 | N71: 0 | O71: 0 | P71: 0 | Q71: 0 | R71: 0 | S71: 0 | T71: 0 | U71: 0
B72: (3 ) Stock flow adjustments (3.1 + 3.2) | D72: ='Input data'!D16 -> -1.440114 | E72: ='Input data'!E16 -> 0.069708 | F72: ='Input data'!F16 -> 0.0988673 | G72: ='Input data'!G16 -> 0 | H72: ='Input data'!H16 -> 0 | I72: ='Input data'!I16 -> 0 | J72: ='Input data'!J16 -> 0 | K72: ='Input data'!K16 -> 0 | ... U72: ='Input data'!U16 -> 0
B73: (3.1) Base | D73: =D15 -> -1.439456 | E73: =E15 -> 0.0857679 | F73: =F15 -> 0.1097981 | G73: =G15 -> 0 | H73: =H15 -> 0 | I73: =I15 -> 0 | J73: =J15 -> 0 | K73: =K15 -> 0 | ... U73: =U15 -> 0
B74: (3.2) Adjustment due to the exchange rate effect linked to debt value | D74: =+D72-D73 -> -0.000658 | E74: =+E72-E73 -> -0.0160599 | F74: =+F72-F73 -> -0.0109308 | G74: =+G72-G73 -> 0 | H74: =+H72-H73 -> 0 | I74: =+I72-I73 -> 0 | J74: =+J72-J73 -> 0 | K74: =+K72-K73 -> 0 | ... U74: =+U72-U73 -> 0
B76: Other budgetary variables
B77: Headline balance | C77: ='Baseline NFPC'!C76 -> -2.479937 | D77: =D59-D68-D71 -> -2.7588676 | E77: =E59-E68-E71 -> -2.5116656 | F77: =F59-F68-F71 -> -1.9842799 | G77: =G59-G68-G71 -> -1.4261346 | H77: =H59-H68-H71 -> -0.88301955 | I77: =I59-I68-I71 -> -0.78476589 | J77: =J59-J68-J71 -> -0.68035836 | K77: =K59-K68-K71 -> -0.56994003 | ... U77: =U59-U68-U71 -> -1.2200633
B78: Structural balance | C78: ='Baseline NFPC'!C77 -> -2.134562 | D78: =D60-D68-D71-D64-D65-D66 -> -2.0701714 | E78: =E60-E68-E71-E64-E65-E66 -> -1.5749913 | F78: =F60-F68-F71-F64-F65-F66 -> -1.0526772 | G78: =G60-G68-G71-G64-G65-G66 -> -0.60562267 | H78: =H60-H68-H71-H64-H65-H66 -> -0.13632773 | I78: =I60-I68-I71-I64-I65-I66 -> -0.28697134 | J78: =J60-J68-J71-J64-J65-J66 -> -0.43146109 | K78: =K60-K68-K71-K64-K65-K66 -> -0.56994003 | ... U78: =U60-U68-U71-U64-U65-U66 -> -1.2200694
B79: Net expenditure growth | C79: ='Input data'!C45 -> 6.0601922 | D79: ='Input data'!D45 -> 3.9721583 | E79: ='Input data'!E33+E42-(E$12-D$12)/'Input data'!$C$64*100 -> 1.5922609 | F79: ='Input data'!F33+F42-(F$12-E$12)/'Input data'!$C$64*100 -> 1.399332 | G79: ='Input data'!G33+G42-(G$12-F$12)/'Input data'!$C$64*100 -> 1.5162552 | H79: ='Input data'!H33+H42-(H$12-G$12)/'Input data'!$C$64*100 -> 1.6324232 | I79: ='Input data'!I33+I42-(I$12-H$12)/'Input data'!$C$64*100 -> 2.8591299 | J79: ='Input data'!J33+J42-(J$12-I$12)/'Input data'!$C$64*100 -> 2.8467243 | K79: ='Input data'!K33+K42-(K$12-J$12)/'Input data'!$C$64*100 -> 2.8318391 | L79: ='Input data'!L33+L42-(L$12-K$12)/'Input data'!$C$64*100 -> 2.8231217 | ... U79: ='Input data'!U33+U42-(U$12-T$12)/'Input data'!$C$64*100 -> 3.729
B81: Average net primary expenditure growth
B83: Debt increasing? (For criterion 1) | I83: =IF(I57<H57,0,1) -> 0 | J83: =IF(J57<I57,0,1) -> 0 | K83: =IF(K57<J57,0,1) -> 0 | L83: =IF(L57<K57,0,1) -> 0 | M83: =IF(M57<L57,0,1) -> 0 | N83: =IF(N57<M57,0,1) -> 0 | O83: =IF(O57<N57,0,1) -> 0 | P83: =IF(P57<O57,0,1) -> 0 | ... U83: =IF(U57<T57,0,1) -> 0
B84: Debt above 90% (for debt sustainability safeguard) | D84: =IF(D57>90,1,0) -> 0 | E84: =IF(E57>90,1,0) -> 0 | F84: =IF(F57>90,1,0) -> 0 | G84: =IF(G57>90,1,0) -> 0 | H84: =IF(H57>90,1,0) -> 0 | I84: =IF(I57>90,1,0) -> 0 | J84: =IF(J57>90,1,0) -> 0 | K84: =IF(K57>90,1,0) -> 0 | ... U84: =IF(U57>90,1,0) -> 0
B85: Debt between 60% and 90% (for debt sustainability safeguard) | D85: =IF(AND(D57>60,D57<=90),1,0) -> 1 | E85: =IF(AND(E57>60,E57<=90),1,0) -> 1 | F85: =IF(AND(F57>60,F57<=90),1,0) -> 1 | G85: =IF(AND(G57>60,G57<=90),1,0) -> 1 | H85: =IF(AND(H57>60,H57<=90),1,0) -> 1 | I85: =IF(AND(I57>60,I57<=90),1,0) -> 1 | J85: =IF(AND(J57>60,J57<=90),1,0) -> 1 | K85: =IF(AND(K57>60,K57<=90),1,0) -> 0 | ... U85: =IF(AND(U57>60,U57<=90),1,0) -> 0
B86: Debt above 60% (for debt sustainability safeguard) | D86: =IF(D57>60,1,0) -> 1 | E86: =IF(E57>60,1,0) -> 1 | F86: =IF(F57>60,1,0) -> 1 | G86: =IF(G57>60,1,0) -> 1 | H86: =IF(H57>60,1,0) -> 1 | I86: =IF(I57>60,1,0) -> 1 | J86: =IF(J57>60,1,0) -> 1 | K86: =IF(K57>60,1,0) -> 0 | ... U86: =IF(U57>60,1,0) -> 0
B87: Deficit exceeding 3% / under EDP (for deficit benchmark and debt sustainability safeguard) | D87: ='Input data'!D17 -> 0 | E87: =IF(D87=0,0,IF(AND(C77>-3.05,D77>-3.05),0,1)) -> 0 | F87: =IF(E87=0,0,IF(AND(D77>-3.05,E77>-3.05),0,1)) -> 0 | G87: =IF(F87=0,0,IF(AND(E77>-3.05,F77>-3.05),0,1)) -> 0 | H87: =IF(G87=0,0,IF(AND(F77>-3.05,G77>-3.05),0,1)) -> 0 | I87: =IF(H87=0,0,IF(AND(G77>-3.05,H77>-3.05),0,1)) -> 0 | J87: =IF(I87=0,0,IF(AND(H77>-3.05,I77>-3.05),0,1)) -> 0 | K87: =IF(J87=0,0,IF(AND(I77>-3.05,J77>-3.05),0,1)) -> 0 | L87: =IF(K87=0,0,IF(AND(J77>-3.05,K77>-3.05),0,1)) -> 0 | ... U87: =IF(T87=0,0,IF(AND(S77>-3.05,T77>-3.05),0,1)) -> 0
B88: Structural balance ensuring safety margin (for deficit resilience safeguard) | D88: =IF(D78>=-1.55,1,0) -> 0 | E88: =IF(E78>=-1.55,1,0) -> 0 | F88: =IF(F78>=-1.55,1,0) -> 1 | G88: =IF(G78>=-1.55,1,0) -> 1 | H88: =IF(H78>=-1.55,1,0) -> 1 | I88: =IF(I78>=-1.55,1,0) -> 1 | J88: =IF(J78>=-1.55,1,0) -> 1 | K88: =IF(K78>=-1.55,1,0) -> 1 | ... U88: =IF(U78>=-1.55,1,0) -> 1
B90: Approximation of interest payments in % GDP | D90: =C57*D36/100*(1/((1+'Input data'!D30/100)*(1+D42/100))) -> 1.0548956 | E90: =D57*E36/100*(1/((1+'Input data'!E30/100)*(1+E42/100))) -> 1.0955463 | F90: =E57*F36/100*(1/((1+'Input data'!F30/100)*(1+F42/100))) -> 1.1146094 | G90: =F57*G36/100*(1/((1+'Input data'!G30/100)*(1+G42/100))) -> 1.2082168 | H90: =G57*H36/100*(1/((1+'Input data'!H30/100)*(1+H42/100))) -> 1.277853 | I90: =H57*I36/100*(1/((1+'Input data'!I30/100)*(1+I42/100))) -> 1.3284036 | J90: =I57*J36/100*(1/((1+'Input data'!J30/100)*(1+J42/100))) -> 1.3736774 | K90: =J57*K36/100*(1/((1+'Input data'!K30/100)*(1+K42/100))) -> 1.4076334 | ... U90: =T57*U36/100*(1/((1+'Input data'!U30/100)*(1+U42/100))) -> 1.6042408
B91: Change in interest payments (for deficit benchmark in SB terms from 2028 onwards) | E91: =E90-D90 -> 0.040650657 | F91: =F90-E90 -> 0.019063071 | G91: =G90-F90 -> 0.093607412 | H91: =H90-G90 -> 0.069636269 | I91: =I90-H90 -> 0.050550537 | J91: =J90-I90 -> 0.045273849 | K91: =K90-J90 -> 0.033955993 | L91: =L90-K90 -> 0.027885922 | ... U91: =U90-T90 -> 0.0020938673
B93: Debt decomposition and IIR
B95: Auxiliary variable identifying whether debt is increasing | D95: =IF((D100-C100*D43/((1+D24/100)*(1+D42/100)))>0,1,0) -> 1 | E95: =IF((E100-D100*E43/((1+E24/100)*(1+E42/100)))>0,1,0) -> 1 | F95: =IF((F100-E100*F43/((1+F24/100)*(1+F42/100)))>0,1,0) -> 1 | G95: =IF((G100-F100*G43/((1+G24/100)*(1+G42/100)))>0,1,0) -> 1 | H95: =IF((H100-G100*H43/((1+H24/100)*(1+H42/100)))>0,1,0) -> 1 | I95: =IF((I100-H100*I43/((1+I24/100)*(1+I42/100)))>0,1,0) -> 1 | J95: =IF((J100-I100*J43/((1+J24/100)*(1+J42/100)))>0,1,0) -> 1 | K95: =IF((K100-J100*K43/((1+K24/100)*(1+K42/100)))>0,1,0) -> 1 | ... U95: =IF((U100-T100*U43/((1+U24/100)*(1+U42/100)))>0,1,0) -> 1
B96: Auxiliary variable identifying whether some debt is rolled over even though debt is decreasing | D96: =IF(AND(D95=0,ABS(D100-C100*D43/((1+D24/100)*(1+D42/100)))<((C106*C100*D43/((1+D24/100)*(1+D42/100))+(D39*C100*C107*D43/((1+D24/100)*(1+D42/100)))))),1,0) -> 0 | E96: =IF(AND(E95=0,ABS(E100-D100*E43/((1+E24/100)*(1+E42/100)))<((D106*D100*E43/((1+E24/100)*(1+E42/100))+(E39*D100*D107*E43/((1+E24/100)*(1+E42/100)))))),1,0) -> 0 | F96: =IF(AND(F95=0,ABS(F100-E100*F43/((1+F24/100)*(1+F42/100)))<((E106*E100*F43/((1+F24/100)*(1+F42/100))+(F39*E100*E107*F43/((1+F24/100)*(1+F42/100)))))),1,0) -> 0 | G96: =IF(AND(G95=0,ABS(G100-F100*G43/((1+G24/100)*(1+G42/100)))<((F106*F100*G43/((1+G24/100)*(1+G42/100))+(G39*F100*F107*G43/((1+G24/100)*(1+G42/100)))))),1,0) -> 0 | H96: =IF(AND(H95=0,ABS(H100-G100*H43/((1+H24/100)*(1+H42/100)))<((G106*G100*H43/((1+H24/100)*(1+H42/100))+(H39*G100*G107*H43/((1+H24/100)*(1+H42/100)))))),1,0) -> 0 | I96: =IF(AND(I95=0,ABS(I100-H100*I43/((1+I24/100)*(1+I42/100)))<((H106*H100*I43/((1+I24/100)*(1+I42/100))+(I39*H100*H107*I43/((1+I24/100)*(1+I42/100)))))),1,0) -> 0 | J96: =IF(AND(J95=0,ABS(J100-I100*J43/((1+J24/100)*(1+J42/100)))<((I106*I100*J43/((1+J24/100)*(1+J42/100))+(J39*I100*I107*J43/((1+J24/100)*(1+J42/100)))))),1,0) -> 0 | K96: =IF(AND(K95=0,ABS(K100-J100*K43/((1+K24/100)*(1+K42/100)))<((J106*J100*K43/((1+K24/100)*(1+K42/100))+(K39*J100*J107*K43/((1+K24/100)*(1+K42/100)))))),1,0) -> 0 | ... U96: =IF(AND(U95=0,ABS(U100-T100*U43/((1+U24/100)*(1+U42/100)))<((T106*T100*U43/((1+U24/100)*(1+U42/100))+(U39*T100*T107*U43/((1+U24/100)*(1+U42/100)))))),1,0) -> 0
C99: ='Input data'!$C$5-1 -> 2023 | D99: =C99+1 -> 2024 | E99: =D99+1 -> 2025 | F99: =E99+1 -> 2026 | G99: =F99+1 -> 2027 | H99: =G99+1 -> 2028 | I99: =H99+1 -> 2029 | J99: =I99+1 -> 2030 | K99: =J99+1 -> 2031 | ... U99: =T99+1 -> 2041
B100: Gross debt | C100: =C57 -> 62.88549 | D100: =D57 -> 62.455679 | E100: =D100*(1+E114/100)*E43-E60-E61+E62+E63+E64+E65+E66+E73 -> 63.692062 | F100: =E100*(1+F114/100)*F43-F60-F61+F62+F63+F64+F65+F66+F73 -> 64.202498 | G100: =F100*(1+G114/100)*G43-G60-G61+G62+G63+G64+G65+G66+G73 -> 63.836818 | H100: =G100*(1+H114/100)*H43-H60-H61+H62+H63+H64+H65+H66+H73 -> 62.913502 | I100: =H100*(1+I114/100)*I43-I60-I61+I62+I63+I64+I65+I66+I73 -> 61.635848 | J100: =I100*(1+J114/100)*J43-J60-J61+J62+J63+J64+J65+J66+J73 -> 60.304609 | K100: =J100*(1+K114/100)*K43-K60-K61+K62+K63+K64+K65+K66+K73 -> 58.916573 | L100: =K100*(1+L114/100)*L43-L60-L61+L62+L63+L64+L65+L66+L73 -> 58.101077 | ... U100: =T100*(1+U114/100)*U43-U60-U61+U62+U63+U64+U65+U66+U73 -> 52.285409
B101: Of which Outstanding debt | D101: ='Input data'!$C$66*D$100 -> 48.023909 | E101: =IF(E100=0,0,IF(E95=1,D100*E43/((1+E24/100)*(1+E42/100))-E102-E103,IF(AND(E95=0,E96=1),(1-D106-E39*D107)*D100*E43/((1+E24/100)*(1+E42/100)),E100))) -> 48.294459 | F101: =IF(F100=0,0,IF(F95=1,E100*F43/((1+F24/100)*(1+F42/100))-F102-F103,IF(AND(F95=0,F96=1),(1-E106-F39*E107)*E100*F43/((1+F24/100)*(1+F42/100)),F100))) -> 49.041541 | G101: =IF(G100=0,0,IF(G95=1,F100*G43/((1+G24/100)*(1+G42/100))-G102-G103,IF(AND(G95=0,G96=1),(1-F106-G39*F107)*F100*G43/((1+G24/100)*(1+G42/100)),G100))) -> 49.221291 | H101: =IF(H100=0,0,IF(H95=1,G100*H43/((1+H24/100)*(1+H42/100))-H102-H103,IF(AND(H95=0,H96=1),(1-G106-H39*G107)*G100*H43/((1+H24/100)*(1+H42/100)),H100))) -> 48.858093 | I101: =IF(I100=0,0,IF(I95=1,H100*I43/((1+I24/100)*(1+I42/100))-I102-I103,IF(AND(I95=0,I96=1),(1-H106-I39*H107)*H100*I43/((1+I24/100)*(1+I42/100)),I100))) -> 47.863456 | J101: =IF(J100=0,0,IF(J95=1,I100*J43/((1+J24/100)*(1+J42/100))-J102-J103,IF(AND(J95=0,J96=1),(1-I106-J39*I107)*I100*J43/((1+J24/100)*(1+J42/100)),J100))) -> 46.833513 | K101: =IF(K100=0,0,IF(K95=1,J100*K43/((1+K24/100)*(1+K42/100))-K102-K103,IF(AND(K95=0,K96=1),(1-J106-K39*J107)*J100*K43/((1+K24/100)*(1+K42/100)),K100))) -> 45.765794 | L101: =IF(L100=0,0,IF(L95=1,K100*L43/((1+L24/100)*(1+L42/100))-L102-L103,IF(AND(L95=0,L96=1),(1-K106-L39*K107)*K100*L43/((1+L24/100)*(1+L42/100)),L100))) -> 44.874626 | ... U101: =IF(U100=0,0,IF(U95=1,T100*U43/((1+U24/100)*(1+U42/100))-U102-U103,IF(AND(U95=0,U96=1),(1-T106-U39*T107)*T100*U43/((1+U24/100)*(1+U42/100)),U100))) -> 39.931997
B102: Rolled over long-term debt | D102: ='Input data'!$C$67*D$100 -> 6.4240999 | E102: =IF(E100=0,0,IF(E95=1,E39*D100*D107*E43/((1+E24/100)*(1+E42/100)),IF(AND(E95=0,E96=1),(E39*D100*D107*E43/((1+E24/100)*(1+E42/100)))*(1-ABS(E100-D100*E43/((1+E24/100)*(1+E42/100)))/((E39*D100*D107*E43/((1+E24/100)*(1+E42/100)))+(D106*D100*E43/((1+E24/100)*(1+E42/100))))),0))) -> 6.1272805 | F102: =IF(F100=0,0,IF(F95=1,F39*E100*E107*F43/((1+F24/100)*(1+F42/100)),IF(AND(F95=0,F96=1),(F39*E100*E107*F43/((1+F24/100)*(1+F42/100)))*(1-ABS(F100-E100*F43/((1+F24/100)*(1+F42/100)))/((F39*E100*E107*F43/((1+F24/100)*(1+F42/100)))+(E106*E100*F43/((1+F24/100)*(1+F42/100))))),0))) -> 6.3040194 | G102: =IF(G100=0,0,IF(G95=1,G39*F100*F107*G43/((1+G24/100)*(1+G42/100)),IF(AND(G95=0,G96=1),(G39*F100*F107*G43/((1+G24/100)*(1+G42/100)))*(1-ABS(G100-F100*G43/((1+G24/100)*(1+G42/100)))/((G39*F100*F107*G43/((1+G24/100)*(1+G42/100)))+(F106*F100*G43/((1+G24/100)*(1+G42/100))))),0))) -> 6.409624 | H102: =IF(H100=0,0,IF(H95=1,H39*G100*G107*H43/((1+H24/100)*(1+H42/100)),IF(AND(H95=0,H96=1),(H39*G100*G107*H43/((1+H24/100)*(1+H42/100)))*(1-ABS(H100-G100*H43/((1+H24/100)*(1+H42/100)))/((H39*G100*G107*H43/((1+H24/100)*(1+H42/100)))+(G106*G100*H43/((1+H24/100)*(1+H42/100))))),0))) -> 6.4444616 | I102: =IF(I100=0,0,IF(I95=1,I39*H100*H107*I43/((1+I24/100)*(1+I42/100)),IF(AND(I95=0,I96=1),(I39*H100*H107*I43/((1+I24/100)*(1+I42/100)))*(1-ABS(I100-H100*I43/((1+I24/100)*(1+I42/100)))/((I39*H100*H107*I43/((1+I24/100)*(1+I42/100)))+(H106*H100*I43/((1+I24/100)*(1+I42/100))))),0))) -> 6.3939686 | J102: =IF(J100=0,0,IF(J95=1,J39*I100*I107*J43/((1+J24/100)*(1+J42/100)),IF(AND(J95=0,J96=1),(J39*I100*I107*J43/((1+J24/100)*(1+J42/100)))*(1-ABS(J100-I100*J43/((1+J24/100)*(1+J42/100)))/((J39*I100*I107*J43/((1+J24/100)*(1+J42/100)))+(I106*I100*J43/((1+J24/100)*(1+J42/100))))),0))) -> 6.3355812 | K102: =IF(K100=0,0,IF(K95=1,K39*J100*J107*K43/((1+K24/100)*(1+K42/100)),IF(AND(K95=0,K96=1),(K39*J100*J107*K43/((1+K24/100)*(1+K42/100)))*(1-ABS(K100-J100*K43/((1+K24/100)*(1+K42/100)))/((K39*J100*J107*K43/((1+K24/100)*(1+K42/100)))+(J106*J100*K43/((1+K24/100)*(1+K42/100))))),0))) -> 6.2687673 | L102: =IF(L100=0,0,IF(L95=1,L39*K100*K107*L43/((1+L24/100)*(1+L42/100)),IF(AND(L95=0,L96=1),(L39*K100*K107*L43/((1+L24/100)*(1+L42/100)))*(1-ABS(L100-K100*L43/((1+L24/100)*(1+L42/100)))/((L39*K100*K107*L43/((1+L24/100)*(1+L42/100)))+(K106*K100*L43/((1+L24/100)*(1+L42/100))))),0))) -> 6.2230418 | ... U102: =IF(U100=0,0,IF(U95=1,U39*T100*T107*U43/((1+U24/100)*(1+U42/100)),IF(AND(U95=0,U96=1),(U39*T100*T107*U43/((1+U24/100)*(1+U42/100)))*(1-ABS(U100-T100*U43/((1+U24/100)*(1+U42/100)))/((U39*T100*T107*U43/((1+U24/100)*(1+U42/100)))+(T106*T100*U43/((1+U24/100)*(1+U42/100))))),0))) -> 5.6740958
B103: Rolled over short-term debt | D103: ='Input data'!$C$68*D$100 -> 6.6882509 | E103: =IF(E100=0,0,IF(E95=1,(1-D107)*D100*E43/((1+E24/100)*(1+E42/100)),IF(AND(E95=0,E96=1),(D106*D100*E43/((1+E24/100)*(1+E42/100)))*(1-ABS(E100-D100*E43/((1+E24/100)*(1+E42/100)))/((E39*D100*D107*E43/((1+E24/100)*(1+E42/100)))+(D106*D100*E43/((1+E24/100)*(1+E42/100))))),0))) -> 6.6728902 | F103: =IF(F100=0,0,IF(F95=1,(1-E107)*E100*F43/((1+F24/100)*(1+F42/100)),IF(AND(F95=0,F96=1),(E106*E100*F43/((1+F24/100)*(1+F42/100)))*(1-ABS(F100-E100*F43/((1+F24/100)*(1+F42/100)))/((F39*E100*E107*F43/((1+F24/100)*(1+F42/100)))+(E106*E100*F43/((1+F24/100)*(1+F42/100))))),0))) -> 6.76286 | G103: =IF(G100=0,0,IF(G95=1,(1-F107)*F100*G43/((1+G24/100)*(1+G42/100)),IF(AND(G95=0,G96=1),(F106*F100*G43/((1+G24/100)*(1+G42/100)))*(1-ABS(G100-F100*G43/((1+G24/100)*(1+G42/100)))/((G39*F100*F107*G43/((1+G24/100)*(1+G42/100)))+(F106*F100*G43/((1+G24/100)*(1+G42/100))))),0))) -> 6.7797697 | H103: =IF(H100=0,0,IF(H95=1,(1-G107)*G100*H43/((1+H24/100)*(1+H42/100)),IF(AND(H95=0,H96=1),(G106*G100*H43/((1+H24/100)*(1+H42/100)))*(1-ABS(H100-G100*H43/((1+H24/100)*(1+H42/100)))/((H39*G100*G107*H43/((1+H24/100)*(1+H42/100)))+(G106*G100*H43/((1+H24/100)*(1+H42/100))))),0))) -> 6.7279287 | I103: =IF(I100=0,0,IF(I95=1,(1-H107)*H100*I43/((1+I24/100)*(1+I42/100)),IF(AND(I95=0,I96=1),(H106*H100*I43/((1+I24/100)*(1+I42/100)))*(1-ABS(I100-H100*I43/((1+I24/100)*(1+I42/100)))/((I39*H100*H107*I43/((1+I24/100)*(1+I42/100)))+(H106*H100*I43/((1+I24/100)*(1+I42/100))))),0))) -> 6.5936588 | J103: =IF(J100=0,0,IF(J95=1,(1-I107)*I100*J43/((1+J24/100)*(1+J42/100)),IF(AND(J95=0,J96=1),(I106*I100*J43/((1+J24/100)*(1+J42/100)))*(1-ABS(J100-I100*J43/((1+J24/100)*(1+J42/100)))/((J39*I100*I107*J43/((1+J24/100)*(1+J42/100)))+(I106*I100*J43/((1+J24/100)*(1+J42/100))))),0))) -> 6.4551574 | K103: =IF(K100=0,0,IF(K95=1,(1-J107)*J100*K43/((1+K24/100)*(1+K42/100)),IF(AND(K95=0,K96=1),(J106*J100*K43/((1+K24/100)*(1+K42/100)))*(1-ABS(K100-J100*K43/((1+K24/100)*(1+K42/100)))/((K39*J100*J107*K43/((1+K24/100)*(1+K42/100)))+(J106*J100*K43/((1+K24/100)*(1+K42/100))))),0))) -> 6.3120732 | L103: =IF(L100=0,0,IF(L95=1,(1-K107)*K100*L43/((1+L24/100)*(1+L42/100)),IF(AND(L95=0,L96=1),(K106*K100*L43/((1+L24/100)*(1+L42/100)))*(1-ABS(L100-K100*L43/((1+L24/100)*(1+L42/100)))/((L39*K100*K107*L43/((1+L24/100)*(1+L42/100)))+(K106*K100*L43/((1+L24/100)*(1+L42/100))))),0))) -> 6.1939759 | ... U103: =IF(U100=0,0,IF(U95=1,(1-T107)*T100*U43/((1+U24/100)*(1+U42/100)),IF(AND(U95=0,U96=1),(T106*T100*U43/((1+U24/100)*(1+U42/100)))*(1-ABS(U100-T100*U43/((1+U24/100)*(1+U42/100)))/((U39*T100*T107*U43/((1+U24/100)*(1+U42/100)))+(T106*T100*U43/((1+U24/100)*(1+U42/100))))),0))) -> 5.4592544
B104: New long-term debt | D104: ='Input data'!$C$69*D$100 -> 1.186119 | E104: =IF(E100=0,0,IF(E95=1,'Input data'!$C$58*(E100-D100*E43/((1+E24/100)*(1+E42/100))),0)) -> 2.3350232 | F104: =IF(F100=0,0,IF(F95=1,'Input data'!$C$58*(F100-E100*F43/((1+F24/100)*(1+F42/100))),0)) -> 1.8825197 | G104: =IF(G100=0,0,IF(G95=1,'Input data'!$C$58*(G100-F100*G43/((1+G24/100)*(1+G42/100))),0)) -> 1.2820563 | H104: =IF(H100=0,0,IF(H95=1,'Input data'!$C$58*(H100-G100*H43/((1+H24/100)*(1+H42/100))),0)) -> 0.79381012 | I104: =IF(I100=0,0,IF(I95=1,'Input data'!$C$58*(I100-H100*I43/((1+I24/100)*(1+I42/100))),0)) -> 0.70548263 | J104: =IF(J100=0,0,IF(J95=1,'Input data'!$C$58*(J100-I100*J43/((1+J24/100)*(1+J42/100))),0)) -> 0.61162297 | K104: =IF(K100=0,0,IF(K95=1,'Input data'!$C$58*(K100-J100*K43/((1+K24/100)*(1+K42/100))),0)) -> 0.51235976 | L104: =IF(L100=0,0,IF(L95=1,'Input data'!$C$58*(L100-K100*L43/((1+L24/100)*(1+L42/100))),0)) -> 0.7276591 | ... U104: =IF(U100=0,0,IF(U95=1,'Input data'!$C$58*(U100-T100*U43/((1+U24/100)*(1+U42/100))),0)) -> 1.0968031
B105: New short-term debt | D105: ='Input data'!$C$70*D$100 -> 0.1332957 | E105: =IF(E100=0,0,IF(E95=1,'Input data'!$C$57*(E100-D100*E43/((1+E24/100)*(1+E42/100))),0)) -> 0.26240925 | F105: =IF(F100=0,0,IF(F95=1,'Input data'!$C$57*(F100-E100*F43/((1+F24/100)*(1+F42/100))),0)) -> 0.21155704 | G105: =IF(G100=0,0,IF(G95=1,'Input data'!$C$57*(G100-F100*G43/((1+G24/100)*(1+G42/100))),0)) -> 0.14407712 | H105: =IF(H100=0,0,IF(H95=1,'Input data'!$C$57*(H100-G100*H43/((1+H24/100)*(1+H42/100))),0)) -> 0.089208158 | I105: =IF(I100=0,0,IF(I95=1,'Input data'!$C$57*(I100-H100*I43/((1+I24/100)*(1+I42/100))),0)) -> 0.079281939 | J105: =IF(J100=0,0,IF(J95=1,'Input data'!$C$57*(J100-I100*J43/((1+J24/100)*(1+J42/100))),0)) -> 0.068734017 | K105: =IF(K100=0,0,IF(K95=1,'Input data'!$C$57*(K100-J100*K43/((1+K24/100)*(1+K42/100))),0)) -> 0.057578845 | L105: =IF(L100=0,0,IF(L95=1,'Input data'!$C$57*(L100-K100*L43/((1+L24/100)*(1+L42/100))),0)) -> 0.081774124 | ... U105: =IF(U100=0,0,IF(U95=1,'Input data'!$C$57*(U100-T100*U43/((1+U24/100)*(1+U42/100))),0)) -> 0.12325843
B106: Share of short-term debt in total government debt | D106: =IF(D100<>0,(D103+D105)/(D101+D102+D103+D104+D105),0) -> 0.10922221 | E106: =IF(E100<>0,(E103+E105)/(E101+E102+E103+E104+E105),0) -> 0.10888797 | F106: =IF(F100<>0,(F103+F105)/(F101+F102+F103+F104+F105),0) -> 0.10863155 | G106: =IF(G100<>0,(G103+G105)/(G101+G102+G103+G104+G105),0) -> 0.10846165 | H106: =IF(H100<>0,(H103+H105)/(H101+H102+H103+H104+H105),0) -> 0.1083573 | I106: =IF(I100<>0,(I103+I105)/(I101+I102+I103+I104+I105),0) -> 0.10826396 | J106: =IF(J100<>0,(J103+J105)/(J101+J102+J103+J104+J105),0) -> 0.1081823 | K106: =IF(K100<>0,(K103+K105)/(K101+K102+K103+K104+K105),0) -> 0.10811308 | ... U106: =IF(U100<>0,(U103+U105)/(U101+U102+U103+U104+U105),0) -> 0.10676999
B107: Share of long-term debt in total government debt | D107: =IF(D100<>0,(D101+D102+D104)/(D101+D102+D103+D104+D105),1) -> 0.89077779 | E107: =IF(E100<>0,(E101+E102+E104)/(E101+E102+E103+E104+E105),1) -> 0.89111203 | F107: =IF(F100<>0,(F101+F102+F104)/(F101+F102+F103+F104+F105),1) -> 0.89136845 | G107: =IF(G100<>0,(G101+G102+G104)/(G101+G102+G103+G104+G105),1) -> 0.89153835 | H107: =IF(H100<>0,(H101+H102+H104)/(H101+H102+H103+H104+H105),1) -> 0.8916427 | I107: =IF(I100<>0,(I101+I102+I104)/(I101+I102+I103+I104+I105),1) -> 0.89173604 | J107: =IF(J100<>0,(J101+J102+J104)/(J101+J102+J103+J104+J105),1) -> 0.8918177 | K107: =IF(K100<>0,(K101+K102+K104)/(K101+K102+K103+K104+K105),1) -> 0.89188692 | ... U107: =IF(U100<>0,(U101+U102+U104)/(U101+U102+U103+U104+U105),1) -> 0.89323001
B109: IIR | C109: ='Baseline NFPC'!C96 -> 1.422372 | D109: ='Baseline NFPC'!D96 -> 1.725464 | E109: ='Baseline NFPC'!E96 -> 1.8 | F109: =F111+F112 -> 1.7990942 | G109: =G111+G112 -> 1.9393065 | H109: =H111+H112 -> 2.0651773 | I109: =I111+I112 -> 2.1807763 | J109: =J111+J112 -> 2.2924541 | K109: =K111+K112 -> 2.4006192 | L109: =L111+L112 -> 2.5056322 | M109: =M111+M112 -> 2.6113354 | ... U109: =U111+U112 -> 3.1415413
B110: Long-term implicit interest rate | E110: =((E36*D100)-(E38*(D103+D105)))/(D101+D102+D104) -> 1.775559 | F110: =IF(E100>0,(E110*E101+ ('Baseline NFPC'!F97*('Baseline NFPC'!E88+'Baseline NFPC'!E89+'Baseline NFPC'!E91)-'Baseline NFPC'!E97*'Baseline NFPC'!E88)/('Baseline NFPC'!E89+'Baseline NFPC'!E91) *(E104+E102))/(E101+E102+E104),F37) -> 1.8086572 | G110: =IF(F100>0,(F110*F101+G37*(F104+F102))/(F101+F102+F104),G37) -> 1.9468022 | H110: =IF(G100>0,(G110*G101+H37*(G104+G102))/(G101+G102+G104),H37) -> 2.0688766 | I110: =IF(H100>0,(H110*H101+I37*(H104+H102))/(H101+H102+H104),I37) -> 2.1794442 | J110: =IF(I100>0,(I110*I101+J37*(I104+I102))/(I101+I102+I104),J37) -> 2.2856246 | K110: =IF(J100>0,(J110*J101+K37*(J104+J102))/(J101+J102+J104),K37) -> 2.3878754 | L110: =IF(K100>0,(K110*K101+L37*(K104+K102))/(K101+K102+K104),L37) -> 2.4865996 | M110: =IF(L100>0,(L110*L101+M37*(L104+L102))/(L101+L102+L104),M37) -> 2.5861143 | N110: =IF(M100>0,(M110*M101+N37*(M104+M102))/(M101+M102+M104),N37) -> 2.6850607 | ... U110: =IF(T100>0,(T110*T101+U37*(T104+T102))/(T101+T102+T104),U37) -> 3.2022033
B111: Nominal implicit interest rate on debt (Excel approximation) | E111: =(E110*(D101+D102+D104)+E38*(D103+D105))/D100 -> 1.8 | F111: =(F110*(E101+E102+E104)+F38*(E103+E105))/E100 -> 1.7990942 | G111: =(G110*(F101+F102+F104)+G38*(F103+F105))/F100 -> 1.9393065 | H111: =(H110*(G101+G102+G104)+H38*(G103+G105))/G100 -> 2.0651773 | I111: =(I110*(H101+H102+H104)+I38*(H103+H105))/H100 -> 2.1807763 | J111: =(J110*(I101+I102+I104)+J38*(I103+I105))/I100 -> 2.2924541 | K111: =(K110*(J101+J102+J104)+K38*(J103+J105))/J100 -> 2.4006192 | L111: =(L110*(K101+K102+K104)+L38*(K103+K105))/K100 -> 2.5056322 | ... U111: =(U110*(T101+T102+T104)+U38*(T103+T105))/T100 -> 3.1415413
B112: Diff. STATA | E112: ='Adjust. no safeguard'!E104 -> 0 | F112: ='Adjust. no safeguard'!F104 -> 0 | G112: ='Adjust. no safeguard'!G104 -> 0 | H112: ='Adjust. no safeguard'!H104 -> 0 | I112: ='Adjust. no safeguard'!I104 -> 0 | J112: ='Adjust. no safeguard'!J104 -> 0 | K112: ='Adjust. no safeguard'!K104 -> 0 | L112: ='Adjust. no safeguard'!L104 -> 0 | ... U112: ='Adjust. no safeguard'!U104 -> 0
B114: (i - g) | C114: =((1+C109/100)/((1+C24/100)*(1+C42/100))-1)*100 -> -4.19208 | D114: =((1+D109/100)/((1+D24/100)*(1+D42/100))-1)*100 -> -1.1030667 | E114: =((1+E109/100)/((1+E24/100)*(1+E42/100))-1)*100 -> -0.39216469 | F114: =((1+F109/100)/((1+F24/100)*(1+F42/100))-1)*100 -> -0.71457644 | G114: =((1+G109/100)/((1+G24/100)*(1+G42/100))-1)*100 -> -0.9056942 | H114: =((1+H109/100)/((1+H24/100)*(1+H42/100))-1)*100 -> -0.82287233 | I114: =((1+I109/100)/((1+I24/100)*(1+I42/100))-1)*100 -> -1.1688943 | J114: =((1+J109/100)/((1+J24/100)*(1+J42/100))-1)*100 -> -1.046043 | ... U114: =((1+U109/100)/((1+U24/100)*(1+U42/100))-1)*100 -> -0.59876651

Sheet Adjust. no safeguard
B3: Country | C3: ='Input data'!C3 -> DE
B4: Key years
B5: ='Input data'!B5 -> Last year before the adjustment | C5: =+'Input data'!C5 -> 2024
B6: Last year of adjustment | C6: =+C5+'Criteria results'!$F$5 -> 2028
B7: Last year of no-fiscal-policy-change projections | C7: =C5+'Criteria results'!$F$5+10 -> 2038
B9: Key assumptions
C10: ='Input data'!$C$5-1 -> 2023 | D10: =C10+1 -> 2024 | E10: =D10+1 -> 2025 | F10: =E10+1 -> 2026 | G10: =F10+1 -> 2027 | H10: =G10+1 -> 2028 | I10: =H10+1 -> 2029 | J10: =I10+1 -> 2030 | K10: =J10+1 -> 2031 | ... U10: =T10+1 -> 2041
B11: Fiscal assumptions (% of GDP)
B12: Structural primary balance ('+' means 'surplus') | C12: ='Input data'!C13 -> -1.260914 | D12: ='Input data'!D13 -> -1.015287 | E12: =IF(E10<=$C$6,D12+'Criteria results'!$F$6,D12) -> -0.475287 | F12: =IF(F10<=$C$6,E12+'Criteria results'!$F$6,E12) -> 0.064713 | G12: =IF(G10<=$C$6,F12+'Criteria results'!$F$6,F12) -> 0.604713 | H12: =IF(H10<=$C$6,G12+'Criteria results'!$F$6,G12) -> 1.144713 | I12: =IF(I10<=$C$6,H12+'Criteria results'!$F$6,H12) -> 1.144713 | J12: =IF(J10<=$C$6,I12+'Criteria results'!$F$6,I12) -> 1.144713 | K12: =IF(K10<=$C$6,J12+'Criteria results'!$F$6,J12) -> 1.144713 | L12: =K12 -> 1.144713 | M12: =L12 -> 1.144713 | N12: =M12 -> 1.144713 | O12: =N12 -> 1.144713 | P12: =O12 -> 1.144713 | Q12: =P12 -> 1.144713 | R12: =Q12 -> 1.144713 | S12: =R12 -> 1.144713 | ... U12: =T12 -> 1.144713
B13: Annual change in SPB | E13: =E12-D12 -> 0.54 | F13: =F12-E12 -> 0.54 | G13: =G12-F12 -> 0.54 | H13: =H12-G12 -> 0.54 | I13: =I12-H12 -> 0 | J13: =J12-I12 -> 0 | K13: =K12-J12 -> 0 | L13: =L12-K12 -> 0 | ... U13: =U12-T12 -> 0
B14: One-off and other temporary measures | C14: ='Input data'!C14 -> 0 | D14: ='Input data'!D14 -> 0 | E14: ='Input data'!E14 -> 0 | F14: ='Input data'!F14 -> 0 | G14: ='Input data'!G14 -> 0 | H14: ='Input data'!H14 -> 0 | I14: ='Input data'!I14 -> 0 | J14: ='Input data'!J14 -> 0 | ... U14: ='Input data'!U14 -> 0
B15: Stock flow adjustments (without exchange rate effect) | C15: ='Input data'!C15 -> -1.000485 | D15: ='Input data'!D15 -> -1.439456 | E15: ='Input data'!E15 -> 0.0857679 | F15: ='Input data'!F15 -> 0.1097981 | G15: ='Input data'!G15 -> 0 | H15: ='Input data'!H15 -> 0 | I15: ='Input data'!I15 -> 0 | J15: ='Input data'!J15 -> 0 | ... U15: ='Input data'!U15 -> 0
B17: ='Input data'!B19 -> Cost of ageing and selected public revenue (based on the Commission-Council 2024 Ageing Report ("AR 2024"))
B18: Total ageing cost (net of taxes on pensions) | C18: ='Input data'!C20 -> 23.1 | D18: ='Input data'!D20 -> 23.3 | E18: ='Input data'!E20 -> 23.4 | F18: ='Input data'!F20 -> 23.4 | G18: ='Input data'!G20 -> 23.6 | H18: ='Input data'!H20 -> 23.7 | I18: ='Input data'!I20 -> 23.8 | J18: ='Input data'!J20 -> 23.9 | ... U18: ='Input data'!U20 -> 24.4
B19: Property income | C19: ='Input data'!C26 -> 0.7164173 | D19: ='Input data'!D26 -> 0.7117602 | E19: ='Input data'!E26 -> 0.7071032 | F19: ='Input data'!F26 -> 0.7024462 | G19: ='Input data'!G26 -> 0.6977891 | H19: ='Input data'!H26 -> 0.6931321 | I19: ='Input data'!I26 -> 0.6884751 | J19: ='Input data'!J26 -> 0.683818 | ... U19: ='Input data'!U26 -> 0.6325905
B21: GDP growth assumptions
B22: Actual GDP (real)
B23: Level | C23: ='Baseline NFPC'!C22 -> 3615.547 | D23: ='Baseline NFPC'!D22 -> 3606.923 | E23: =IF(AND(E50>1,D50>1), E27*(1+('Baseline NFPC'!E$29+E51)/100)-D23*$C$47*(E12-D12)/100, IF(E50=1,E27,D23*(1+E52/100))) -> 3598.5247 | F23: =IF(AND(F50>1,E50>1), F27*(1+('Baseline NFPC'!F$29+F51)/100)-E23*$C$47*(F12-E12)/100, IF(F50=1,F27,E23*(1+F52/100))) -> 3611.4128 | G23: =IF(AND(G50>1,F50>1), G27*(1+G51/100)-F23*$C$47*(G12-F12)/100, IF(G50=1,G27,F23*(1+G52/100))) -> 3635.92 | H23: =IF(AND(H50>1,G50>1), H27*(1+H51/100)-G23*$C$47*(H12-G12)/100, IF(H50=1,H27,G23*(1+H52/100))) -> 3661.631 | I23: =IF(AND(I50>1,H50>1), I27*(1+I51/100)-H23*$C$47*(I12-H12)/100, IF(I50=1,I27,H23*(1+I52/100))) -> 3704.1989 | J23: =IF(AND(J50>1,I50>1), J27*(1+J51/100)-I23*$C$47*(J12-I12)/100, IF(J50=1,J27,I23*(1+J52/100))) -> 3746.2686 | K23: =IF(AND(K50>1,J50>1), K27*(1+K51/100)-J23*$C$47*(K12-J12)/100, IF(K50=1,K27,J23*(1+K52/100))) -> 3787.7192 | L23: =IF(AND(L50>1,K50>1), L27*(1+L51/100)-K23*$C$47*(L12-K12)/100, IF(L50=1,L27,K23*(1+L52/100))) -> 3809.9402 | M23: =IF(AND(M50>1,L50>1), M27*(1+M51/100)-L23*$C$47*(M12-L12)/100, IF(M50=1,M27,L23*(1+M52/100))) -> 3832.2136 | N23: =IF(AND(N50>1,M50>1), N27*(1+N51/100)-M23*$C$47*(N12-M12)/100, IF(N50=1,N27,M23*(1+N52/100))) -> 3858.1252 | ... U23: =IF(AND(U50>1,T50>1), U27*(1+U51/100)-T23*$C$47*(U12-T12)/100, IF(U50=1,U27,T23*(1+U52/100))) -> 4227.9733
B24: Growth rate | C24: ='Baseline NFPC'!C23 -> -0.2664383 | D24: ='Baseline NFPC'!D23 -> -0.2385261 | E24: =100*(E23/D23-1) -> -0.2328389 | F24: =100*(F23/E23-1) -> 0.35815102 | G24: =100*(G23/F23-1) -> 0.67860352 | H24: =100*(H23/G23-1) -> 0.70713923 | I24: =100*(I23/H23-1) -> 1.1625397 | J24: =100*(J23/I23-1) -> 1.1357286 | K24: =100*(K23/J23-1) -> 1.1064518 | L24: =100*(L23/K23-1) -> 0.5866577 | ... U24: =100*(U23/T23-1) -> 1.560002
B26: Potential GDP (real)
B27: Level | C27: ='Input data'!C34 -> 3640.494 | D27: =+C27*(1+'Input data'!D33/100) -> 3656.893 | E27: =+D27*(1+'Input data'!E33/100) -> 3666.669 | F27: =+E27*(1+'Input data'!F33/100) -> 3679.4239 | G27: =+F27*(1+'Input data'!G33/100) -> 3696.0924 | H27: =+G27*(1+'Input data'!H33/100) -> 3716.695 | I27: =+H27*(1+'Input data'!I33/100) -> 3741.1498 | J27: =+I27*(1+'Input data'!J33/100) -> 3764.8611 | K27: =+J27*(1+'Input data'!K33/100) -> 3787.7192 | ... U27: =+T27*(1+'Input data'!U33/100) -> 4227.9728
B29: Output gap
B30: Output gap | C30: =100*(C23/C27-1) -> -0.68526414 | D30: =100*(D23/D27-1) -> -1.3664607 | E30: =100*(E23/E27-1) -> -1.8584807 | F30: =100*(F23/F27-1) -> -1.848418 | G30: =100*(G23/G27-1) -> -1.6279999 | H30: =100*(H23/H27-1) -> -1.4815314 | I30: =100*(I23/I27-1) -> -0.98768759 | J30: =100*(J23/J27-1) -> -0.4938438 | ... U30: =100*(U23/U27-1) -> 1.1962257e-05
B32: Actual GDP (nominal, national currency)
B33: Growth rate | C33: =100*((1+C24/100)*(1+C42/100)-1) -> 5.8601126 | D33: =100*((1+D24/100)*(1+D42/100)-1) -> 2.8600792 | E33: =100*((1+E24/100)*(1+E42/100)-1) -> 2.2007954 | F33: =100*((1+F24/100)*(1+F42/100)-1) -> 2.531762 | G33: =100*((1+G24/100)*(1+G42/100)-1) -> 2.8710032 | H33: =100*((1+H24/100)*(1+H42/100)-1) -> 2.9120118 | I33: =100*((1+I24/100)*(1+I42/100)-1) -> 3.3892878 | J33: =100*((1+J24/100)*(1+J42/100)-1) -> 3.3737884 | ... U33: =100*((1+U24/100)*(1+U42/100)-1) -> 3.7628384
B35: Interest rates
B36: Nominal implicit interest rate on debt | C36: ='Input data'!C37 -> 1.422372 | D36: ='Input data'!D37 -> 1.725464 | E36: ='Input data'!E37 -> 1.8 | F36: =F101 -> 1.7990942 | G36: =G101 -> 1.9393065 | H36: =H101 -> 2.0651773 | I36: =I101 -> 2.1807763 | J36: =J101 -> 2.2924541 | K36: =K101 -> 2.4006192 | L36: =L101 -> 2.5056322 | M36: =M101 -> 2.6113354 | ... U36: =U101 -> 3.1415413
B37: Long-term interest rate | C37: ='Input data'!C$39 -> 2.43 | D37: ='Input data'!D$39 -> 2.3225 | E37: ='Input data'!E$39 -> 2.544438 | F37: ='Input data'!F$39 -> 2.698655 | G37: ='Baseline NFPC'!G36 -> 2.7743606 | H37: ='Baseline NFPC'!H36 -> 2.8500662 | I37: ='Baseline NFPC'!I36 -> 2.9257719 | J37: ='Baseline NFPC'!J36 -> 3.0014775 | K37: ='Baseline NFPC'!K36 -> 3.0771831 | L37: ='Baseline NFPC'!L36 -> 3.1528887 | M37: ='Baseline NFPC'!M36 -> 3.2285944 | N37: ='Baseline NFPC'!N36 -> 3.3043 | ... U37: ='Baseline NFPC'!U36 -> 3.547795
B38: Short-term interest rate | C38: ='Input data'!C$38 -> 3.43 | D38: ='Input data'!D$38 -> 3.570833 | E38: ='Input data'!E$38 -> 1.999333 | F38: ='Input data'!F$38 -> 1.720833 | G38: ='Baseline NFPC'!G37 -> 1.8778014 | H38: ='Baseline NFPC'!H37 -> 2.0347698 | I38: ='Baseline NFPC'!I37 -> 2.1917381 | J38: ='Baseline NFPC'!J37 -> 2.3487065 | K38: ='Baseline NFPC'!K37 -> 2.5056749 | L38: ='Baseline NFPC'!L37 -> 2.6626432 | M38: ='Baseline NFPC'!M37 -> 2.8196116 | N38: ='Baseline NFPC'!N37 -> 2.97658 | ... U38: ='Baseline NFPC'!U37 -> 2.634777
B39: Share of long-term debt that matures every year | C39: ='Baseline NFPC'!C38 -> 0.12643541 | D39: ='Baseline NFPC'!D38 -> 0.11798594 | E39: ='Baseline NFPC'!E38 -> 0.11258884 | F39: ='Baseline NFPC'!F38 -> 0.11390289 | G39: ='Baseline NFPC'!G38 -> 0.11521694 | H39: ='Baseline NFPC'!H38 -> 0.11653099 | I39: ='Baseline NFPC'!I38 -> 0.11784504 | J39: ='Baseline NFPC'!J38 -> 0.1191591 | ... U39: ='Baseline NFPC'!U38 -> 0.1244153
B41: Inflation and exchange rate
B42: GDP deflator (National currency) | C42: ='Input data'!C42 -> 6.142918 | D42: ='Input data'!D42 -> 3.106014 | E42: ='Input data'!E42 -> 2.439314 | F42: ='Input data'!F42 -> 2.165854 | G42: ='Baseline NFPC'!G41 -> 2.1776222 | H42: ='Baseline NFPC'!H41 -> 2.1893905 | I42: ='Baseline NFPC'!I41 -> 2.2011587 | J42: ='Baseline NFPC'!J41 -> 2.212927 | K42: ='Baseline NFPC'!K41 -> 2.2246952 | L42: ='Baseline NFPC'!L41 -> 2.2364635 | M42: ='Baseline NFPC'!M41 -> 2.2482317 | N42: ='Baseline NFPC'!N41 -> 2.26 | ... U42: ='Baseline NFPC'!U41 -> 2.169
B43: Exchange rate composite change (weighted by share of debt in each currency) | C43: ='Baseline NFPC'!C42 -> 0.9997445 | D43: ='Baseline NFPC'!D42 -> 0.9999892 | E43: ='Baseline NFPC'!E42 -> 0.9997361 | F43: ='Baseline NFPC'!F42 -> 0.9998241 | G43: ='Baseline NFPC'!G42 -> 1 | H43: ='Baseline NFPC'!H42 -> 1 | I43: ='Baseline NFPC'!I42 -> 1 | J43: ='Baseline NFPC'!J42 -> 1 | ... U43: ='Baseline NFPC'!U42 -> 1
B45: Intermediate calculations (growth rate equation)
B47: Fiscal multiplier | C47: ='Input data'!C49 -> 0.75
B48: Budget balance semi-elasticity | C48: ='Input data'!C50 -> 0.504
B50: Auxiliary variable to control the closure of the output gap | C50: 0 | D50: =IF(AND(ABS((D12-C12)-('Input data'!D13-'Input data'!C13))>0.0001,ABS(D12-C12)>0.0001,D$10>$C$5),4,IF(C50=4,3,IF(C50=3,2,IF(C50=2,1,0)))) -> 0 | E50: =IF(AND(ABS((E12-D12)-('Baseline NFPC'!E12-'Baseline NFPC'!D12))>0.0001,ABS(E12-D12)>0.0001,E$10>$C$5),4,IF(D50=4,3,IF(D50=3,2,IF(D50=2,1,0)))) -> 4 | F50: =IF(AND(ABS((F12-E12)-('Baseline NFPC'!F12-'Baseline NFPC'!E12))>0.0001,ABS(F12-E12)>0.0001,F$10>$C$5),4,IF(E50=4,3,IF(E50=3,2,IF(E50=2,1,0)))) -> 4 | G50: =IF(AND(ABS((G12-F12)-('Baseline NFPC'!G12-'Baseline NFPC'!F12))>0.0001,ABS(G12-F12)>0.0001,G$10>$C$5),4,IF(F50=4,3,IF(F50=3,2,IF(F50=2,1,0)))) -> 4 | H50: =IF(AND(ABS((H12-G12)-('Baseline NFPC'!H12-'Baseline NFPC'!G12))>0.0001,ABS(H12-G12)>0.0001,H$10>$C$5),4,IF(G50=4,3,IF(G50=3,2,IF(G50=2,1,0)))) -> 4 | I50: =IF(AND(ABS((I12-H12)-('Baseline NFPC'!I12-'Baseline NFPC'!H12))>0.0001,ABS(I12-H12)>0.0001,I$10>$C$5),4,IF(H50=4,3,IF(H50=3,2,IF(H50=2,1,0)))) -> 3 | J50: =IF(AND(ABS((J12-I12)-('Baseline NFPC'!J12-'Baseline NFPC'!I12))>0.0001,ABS(J12-I12)>0.0001,J$10>$C$5),4,IF(I50=4,3,IF(I50=3,2,IF(I50=2,1,0)))) -> 2 | K50: =IF(AND(ABS((K12-J12)-('Baseline NFPC'!K12-'Baseline NFPC'!J12))>0.0001,ABS(K12-J12)>0.0001,K$10>$C$5),4,IF(J50=4,3,IF(J50=3,2,IF(J50=2,1,0)))) -> 1 | L50: =IF(AND(ABS((L12-K12)-('Baseline NFPC'!L12-'Baseline NFPC'!K12))>0.0001,ABS(L12-K12)>0.0001,L$10>$C$5),4,IF(K50=4,3,IF(K50=3,2,IF(K50=2,1,0)))) -> 0 | ... U50: =IF(AND(ABS((U12-T12)-('Baseline NFPC'!U12-'Baseline NFPC'!T12))>0.0001,ABS(U12-T12)>0.0001,U$10>$C$5),4,IF(T50=4,3,IF(T50=3,2,IF(T50=2,1,0)))) -> 0
B51: OG intermediate auxiliary value | C51: 0 | D51: =IF(C50=4,2/3*(C30-'Baseline NFPC'!C29),IF(C50=3,1/3*(#REF!-'Baseline NFPC'!#REF!),0)) -> 0 | E51: =IF(D50=4,2/3*(D30-'Baseline NFPC'!D29),IF(D50=3,1/3*(C30-'Baseline NFPC'!C29),0)) -> 0 | F51: =IF(E50=4,2/3*(E30-'Baseline NFPC'!E29),IF(E50=3,1/3*(D30-'Baseline NFPC'!D29),0)) -> -0.26560052 | G51: =IF(F50=4,2/3*F30,IF(F50=3,1/3*E30,0)) -> -1.2322787 | H51: =IF(G50=4,2/3*G30,IF(G50=3,1/3*F30,0)) -> -1.0853333 | I51: =IF(H50=4,2/3*H30,IF(H50=3,1/3*G30,0)) -> -0.98768759 | J51: =IF(I50=4,2/3*I30,IF(I50=3,1/3*H30,0)) -> -0.4938438 | K51: =IF(J50=4,2/3*J30,IF(J50=3,1/3*I30,0)) -> 0 | L51: =IF(K50=4,2/3*K30,IF(K50=3,1/3*J30,0)) -> 0 | M51: =IF(L50=4,2/3*L30,IF(L50=3,1/3*K30,0)) -> 0 | N51: =IF(M50=4,2/3*M30,IF(M50=3,1/3*L30,0)) -> 0 | ... U51: =IF(T50=4,2/3*T30,IF(T50=3,1/3*S30,0)) -> 0
B52: GDP intermediate growth rate - only feedback effect and no closure of the OG | C52: 0 | D52: ='Input data'!D30-$C$47*((D12-C12)-('Input data'!D13-'Input data'!C13)) -> -0.2385261 | E52: ='Input data'!E30-$C$47*(E12-D12) -> -0.2328389 | F52: ='Input data'!F30-$C$47*(F12-E12) -> 0.2212352 | G52: ='Input data'!G30-$C$47*(G12-F12) -> 0.4501665 | H52: ='Input data'!H30-$C$47*(H12-G12) -> 0.5533591 | I52: ='Input data'!I30-$C$47*(I12-H12) -> 1.057734 | J52: ='Input data'!J30-$C$47*(J12-I12) -> 0.6338005 | K52: ='Input data'!K30-$C$47*(K12-J12) -> 0.6071447 | L52: ='Input data'!L30-$C$47*(L12-K12) -> 0.5866577 | ... U52: ='Input data'!U30-$C$47*(U12-T12) -> 1.560002
B54: Debt projections
C56: ='Input data'!$C$5-1 -> 2023 | D56: =C56+1 -> 2024 | E56: =D56+1 -> 2025 | F56: =E56+1 -> 2026 | G56: =F56+1 -> 2027 | H56: =G56+1 -> 2028 | I56: =H56+1 -> 2029 | J56: =I56+1 -> 2030 | K56: =J56+1 -> 2031 | ... U56: =T56+1 -> 2041
B57: Gross debt | C57: =+'Input data'!C12 -> 62.88549 | D57: =+C57+D58 -> 62.455679 | E57: =+D57+E58 -> 63.69213 | F57: =+E57+F58 -> 64.202561 | G57: =+F57+G58 -> 63.836882 | H57: =+G57+H58 -> 62.913564 | I57: =+H57+I58 -> 61.63591 | J57: =+I57+J58 -> 60.30467 | K57: =+J57+K58 -> 58.916634 | ... U57: =+T57+U58 -> 52.285467
B58: Change in debt (-1+2+3) | D58: =-D59+D67+D72 -> -0.42981088 | E58: =-E59+E67+E72 -> 1.2364509 | F58: =-F59+F67+F72 -> 0.51043146 | G58: =-G59+G67+G72 -> -0.36567993 | H58: =-H59+H67+H72 -> -0.92331721 | I58: =-I59+I67+I72 -> -1.2776545 | J58: =-J59+J67+J72 -> -1.3312398 | K58: =-K59+K67+K72 -> -1.3880363 | ... U58: =-U59+U67+U72 -> -0.70144532
B59: (1) Primary balance (1.1 + 1.2 - 1.3 -1.4 -1.5 - 1.6 -1.7) | D59: =D60+D61-D62-D63-D64-D65-D66 -> -1.7039832 | E59: =E60+E61-E62-E63-E64-E65-E66 -> -1.4119613 | F59: =F60+F61-F62-F63-F64-F65-F66 -> -0.86688967 | G59: =G60+G61-G62-G63-G64-G65-G66 -> -0.21579894 | H59: =H60+H61-H62-H63-H64-H65-H66 -> 0.39802118 | I59: =I60+I61-I62-I63-I64-I65-I66 -> 0.54226145 | J59: =J60+J61-J62-J63-J64-J65-J66 -> 0.68650163 | K59: =K60+K61-K62-K63-K64-K65-K66 -> 0.8307419 | ... U59: =U60+U61-U62-U63-U64-U65-U66 -> 0.38417743
B60: (1.1) Structural primary balance (before ageing cost) | D60: =D12 -> -1.015287 | E60: =IF(E12="",D60,E12) -> -0.475287 | F60: =IF(F12="",E60,F12) -> 0.064713 | G60: =IF(G12="",F60,G12) -> 0.604713 | H60: =IF(H12="",G60,H12) -> 1.144713 | I60: =IF(I12="",H60,I12) -> 1.144713 | J60: =IF(J12="",I60,J12) -> 1.144713 | K60: =IF(K12="",J60,K12) -> 1.144713 | L60: =IF(L12="",K60,L12) -> 1.144713 | ... U60: =IF(U12="",T60,U12) -> 1.144713
B61: (1.2) Cumulated budgetary effort (in terms of primary balance) | D61: 0 | E61: 0 | F61: 0 | G61: 0 | H61: 0 | I61: 0 | J61: 0 | K61: 0 | L61: 0 | M61: 0 | N61: 0 | O61: 0 | P61: 0 | Q61: 0 | R61: 0 | S61: 0 | T61: 0 | U61: 0
B62: (1.3) Cyclical component | D62: =-$C$48*D30 -> 0.68869622 | E62: =-$C$48*E30 -> 0.93667427 | F62: =-$C$48*F30 -> 0.93160267 | G62: =-$C$48*G30 -> 0.82051194 | H62: =-$C$48*H30 -> 0.74669182 | I62: =-$C$48*I30 -> 0.49779455 | J62: =-$C$48*J30 -> 0.24889727 | K62: =-$C$48*K30 -> 0 | ... U62: =-$C$48*U30 -> -6.0289775e-06
B63: (1.4) One-off and other temporary measures | D63: =-D14 -> 0 | E63: =-E14 -> 0 | F63: =-F14 -> 0 | G63: =-G14 -> 0 | H63: =-H14 -> 0 | I63: =-I14 -> 0 | J63: =-J14 -> 0 | K63: =-K14 -> 0 | ... U63: =-U14 -> 0
B64: (1.5) Cost of ageing | D64: =IF(D$56<=$C$6,0,HLOOKUP(D$56,'Input data'!$C$9:$AZ$26,12,FALSE)-HLOOKUP($C$6,'Input data'!$C$9:$AZ$26,12,FALSE)) -> 0 | E64: =IF(E$56<=$C$6,0,HLOOKUP(E$56,'Input data'!$C$9:$AZ$26,12,FALSE)-HLOOKUP($C$6,'Input data'!$C$9:$AZ$26,12,FALSE)) -> 0 | F64: =IF(F$56<=$C$6,0,HLOOKUP(F$56,'Input data'!$C$9:$AZ$26,12,FALSE)-HLOOKUP($C$6,'Input data'!$C$9:$AZ$26,12,FALSE)) -> 0 | G64: =IF(G$56<=$C$6,0,HLOOKUP(G$56,'Input data'!$C$9:$AZ$26,12,FALSE)-HLOOKUP($C$6,'Input data'!$C$9:$AZ$26,12,FALSE)) -> 0 | H64: =IF(H$56<=$C$6,0,HLOOKUP(H$56,'Input data'!$C$9:$AZ$26,12,FALSE)-HLOOKUP($C$6,'Input data'!$C$9:$AZ$26,12,FALSE)) -> 0 | I64: =IF(I$56<=$C$6,0,HLOOKUP(I$56,'Input data'!$C$9:$AZ$26,12,FALSE)-HLOOKUP($C$6,'Input data'!$C$9:$AZ$26,12,FALSE)) -> 0.1 | J64: =IF(J$56<=$C$6,0,HLOOKUP(J$56,'Input data'!$C$9:$AZ$26,12,FALSE)-HLOOKUP($C$6,'Input data'!$C$9:$AZ$26,12,FALSE)) -> 0.2 | K64: =IF(K$56<=$C$6,0,HLOOKUP(K$56,'Input data'!$C$9:$AZ$26,12,FALSE)-HLOOKUP($C$6,'Input data'!$C$9:$AZ$26,12,FALSE)) -> 0.3 | ... U64: =IF(U$56<=$C$6,0,HLOOKUP(U$56,'Input data'!$C$9:$AZ$26,12,FALSE)-HLOOKUP($C$6,'Input data'!$C$9:$AZ$26,12,FALSE)) -> 0.7
B65: (1.6) Property incomes | D65: =IF(D$56<=$C$5,0,-HLOOKUP(D$56,'Input data'!$C$9:$AZ$26,18,FALSE)+HLOOKUP($C$6,'Input data'!$C$9:$AZ$26,18,FALSE)) -> 0 | E65: =IF(E$56<=$C$6,0,-HLOOKUP(E$56,'Input data'!$C$9:$AZ$26,18,FALSE)+HLOOKUP($C$6,'Input data'!$C$9:$AZ$26,18,FALSE)) -> 0 | F65: =IF(F$56<=$C$6,0,-HLOOKUP(F$56,'Input data'!$C$9:$AZ$26,18,FALSE)+HLOOKUP($C$6,'Input data'!$C$9:$AZ$26,18,FALSE)) -> 0 | G65: =IF(G$56<=$C$6,0,-HLOOKUP(G$56,'Input data'!$C$9:$AZ$26,18,FALSE)+HLOOKUP($C$6,'Input data'!$C$9:$AZ$26,18,FALSE)) -> 0 | H65: =IF(H$56<=$C$6,0,-HLOOKUP(H$56,'Input data'!$C$9:$AZ$26,18,FALSE)+HLOOKUP($C$6,'Input data'!$C$9:$AZ$26,18,FALSE)) -> 0 | I65: =IF(I$56<=$C$6,0,-HLOOKUP(I$56,'Input data'!$C$9:$AZ$26,18,FALSE)+HLOOKUP($C$6,'Input data'!$C$9:$AZ$26,18,FALSE)) -> 0.004657 | J65: =IF(J$56<=$C$6,0,-HLOOKUP(J$56,'Input data'!$C$9:$AZ$26,18,FALSE)+HLOOKUP($C$6,'Input data'!$C$9:$AZ$26,18,FALSE)) -> 0.0093141 | K65: =IF(K$56<=$C$6,0,-HLOOKUP(K$56,'Input data'!$C$9:$AZ$26,18,FALSE)+HLOOKUP($C$6,'Input data'!$C$9:$AZ$26,18,FALSE)) -> 0.0139711 | L65: =IF(L$56<=$C$6,0,-HLOOKUP(L$56,'Input data'!$C$9:$AZ$26,18,FALSE)+HLOOKUP($C$6,'Input data'!$C$9:$AZ$26,18,FALSE)) -> 0.0186281 | ... U65: =IF(U$56<=$C$6,0,-HLOOKUP(U$56,'Input data'!$C$9:$AZ$26,18,FALSE)+HLOOKUP($C$6,'Input data'!$C$9:$AZ$26,18,FALSE)) -> 0.0605416
B66: (1.7) Revenues | D66: 0 | E66: 0 | F66: 0 | G66: 0 | H66: 0 | I66: 0 | J66: 0 | K66: 0 | L66: 0 | M66: 0 | N66: 0 | O66: 0 | P66: 0 | Q66: 0 | R66: 0 | S66: 0 | T66: 0 | U66: 0
B67: (2) Snowball effect (2.1 + 2.2 + 2.3) | D67: =SUM(D68:D71) -> -0.6936801 | E67: =SUM(E68:E71) -> -0.24521838 | F67: =SUM(F68:F71) -> -0.45532551 | G67: =SUM(G68:G71) -> -0.58147887 | H67: =SUM(H68:H71) -> -0.52529603 | I67: =SUM(I68:I71) -> -0.73539304 | J67: =SUM(J68:J71) -> -0.64473813 | K67: =SUM(K68:K71) -> -0.55729441 | ... U67: =SUM(U68:U71) -> -0.31726789
B68: (2.1) Interest expenditure | D68: =C57*D36/100*(1/(1+D33/100)) -> 1.0548956 | E68: =D57*E36/100*(1/(1+E33/100)) -> 1.0999936 | F68: =E57*F36/100*(1/(1+F33/100)) -> 1.1175868 | G68: =F57*G36/100*(1/(1+G33/100)) -> 1.2103357 | H68: =G57*H36/100*(1/(1+H33/100)) -> 1.2810407 | I68: =H57*I36/100*(1/(1+I33/100)) -> 1.3270273 | J68: =I57*J36/100*(1/(1+J33/100)) -> 1.36686 | K68: =J57*K36/100*(1/(1+K33/100)) -> 1.4006819 | ... U68: =T57*U36/100*(1/(1+U33/100)) -> 1.6042408
B69: (2.2) Growth effect | D69: =-C57*(D24/100)*(1/(1+D33/100)) -> 0.14582752 | E69: =-D57*(E24/100)*(1/(1+E33/100)) -> 0.14228961 | F69: =-E57*(F24/100)*(1/(1+F33/100)) -> -0.22248131 | G69: =-F57*(G24/100)*(1/(1+G33/100)) -> -0.42352153 | H69: =-G57*(H24/100)*(1/(1+H33/100)) -> -0.43864231 | I69: =-H57*(I24/100)*(1/(1+I33/100)) -> -0.7074187 | J69: =-I57*(J24/100)*(1/(1+J33/100)) -> -0.67717035 | K69: =-J57*(K24/100)*(1/(1+K33/100)) -> -0.64557807 | ... U69: =-T57*(U24/100)*(1/(1+U33/100)) -> -0.79662132
B70: (2.3) Inflation effect | D70: =-C57*D42/100*(1/(1+D42/100)) -> -1.894392 | E70: =-D57*E42/100*(1/(1+E42/100)) -> -1.4872123 | F70: =-E57*F42/100*(1/(1+F42/100)) -> -1.3502344 | G70: =-F57*G42/100*(1/(1+G42/100)) -> -1.368293 | H70: =-G57*H42/100*(1/(1+H42/100)) -> -1.3676944 | I70: =-H57*I42/100*(1/(1+I42/100)) -> -1.3550017 | J70: =-I57*J42/100*(1/(1+J42/100)) -> -1.3344278 | K70: =-J57*K42/100*(1/(1+K42/100)) -> -1.3123983 | ... U70: =-T57*U42/100*(1/(1+U42/100)) -> -1.1248873
B71: (2.4) Exchange rate effect linked to the interest rate | D71: ='Baseline NFPC'!D70 -> -1.1222575e-05 | E71: ='Baseline NFPC'!E70 -> -0.00028926533 | F71: ='Baseline NFPC'!F70 -> -0.00019655417 | G71: 0 | H71: 0 | I71: 0 | J71: 0 | K71: 0 | L71: 0 | M71: 0 | N71: 0 | O71: 0 | P71: 0 | Q71: 0 | R71: 0 | S71: 0 | T71: 0 | U71: 0
B72: (3 ) Stock flow adjustments (3.1 + 3.2) | D72: ='Input data'!D16 -> -1.440114 | E72: ='Input data'!E16 -> 0.069708 | F72: ='Input data'!F16 -> 0.0988673 | G72: ='Input data'!G16 -> 0 | H72: ='Input data'!H16 -> 0 | I72: ='Input data'!I16 -> 0 | J72: ='Input data'!J16 -> 0 | K72: ='Input data'!K16 -> 0 | ... U72: ='Input data'!U16 -> 0
B73: (3.1) Base | D73: =D15 -> -1.439456 | E73: =E15 -> 0.0857679 | F73: =F15 -> 0.1097981 | G73: =G15 -> 0 | H73: =H15 -> 0 | I73: =I15 -> 0 | J73: =J15 -> 0 | K73: =K15 -> 0 | ... U73: =U15 -> 0
B74: (3.2) Adjustment due to the exchange rate effect linked to debt value | D74: =+D72-D73 -> -0.000658 | E74: =+E72-E73 -> -0.0160599 | F74: =+F72-F73 -> -0.0109308 | G74: =+G72-G73 -> 0 | H74: =+H72-H73 -> 0 | I74: =+I72-I73 -> 0 | J74: =+J72-J73 -> 0 | K74: =+K72-K73 -> 0 | ... U74: =+U72-U73 -> 0
B76: Other budgetary variables
B77: Headline balance | C77: ='Baseline NFPC'!C76 -> -2.479937 | D77: =D59-D68-D71 -> -2.7588676 | E77: =E59-E68-E71 -> -2.5116656 | F77: =F59-F68-F71 -> -1.9842799 | G77: =G59-G68-G71 -> -1.4261346 | H77: =H59-H68-H71 -> -0.88301955 | I77: =I59-I68-I71 -> -0.78476589 | J77: =J59-J68-J71 -> -0.68035836 | K77: =K59-K68-K71 -> -0.56994003 | ... U77: =U59-U68-U71 -> -1.2200633
B78: Structural balance | C78: ='Baseline NFPC'!C77 -> -2.134562 | D78: =D60-D68-D71-D64-D65-D66 -> -2.0701714 | E78: =E60-E68-E71-E64-E65-E66 -> -1.5749913 | F78: =F60-F68-F71-F64-F65-F66 -> -1.0526772 | G78: =G60-G68-G71-G64-G65-G66 -> -0.60562267 | H78: =H60-H68-H71-H64-H65-H66 -> -0.13632773 | I78: =I60-I68-I71-I64-I65-I66 -> -0.28697134 | J78: =J60-J68-J71-J64-J65-J66 -> -0.43146109 | K78: =K60-K68-K71-K64-K65-K66 -> -0.56994003 | ... U78: =U60-U68-U71-U64-U65-U66 -> -1.2200694
B79: Net expenditure growth | C79: ='Input data'!C45 -> 6.0601922 | D79: ='Input data'!D45 -> 3.9721583 | E79: ='Input data'!E33+E42-(E$12-D$12)/'Input data'!$C$64*100 -> 1.5922609 | F79: ='Input data'!F33+F42-(F$12-E$12)/'Input data'!$C$64*100 -> 1.399332 | G79: ='Input data'!G33+G42-(G$12-F$12)/'Input data'!$C$64*100 -> 1.5162552 | H79: ='Input data'!H33+H42-(H$12-G$12)/'Input data'!$C$64*100 -> 1.6324232 | I79: ='Input data'!I33+I42-(I$12-H$12)/'Input data'!$C$64*100 -> 2.8591299 | J79: ='Input data'!J33+J42-(J$12-I$12)/'Input data'!$C$64*100 -> 2.8467243 | K79: ='Input data'!K33+K42-(K$12-J$12)/'Input data'!$C$64*100 -> 2.8318391 | L79: ='Input data'!L33+L42-(L$12-K$12)/'Input data'!$C$64*100 -> 2.8231217 | ... U79: ='Input data'!U33+U42-(U$12-T$12)/'Input data'!$C$64*100 -> 3.729
B81: Average net primary expenditure growth
B83: Debt decreasing? (For criterion 1) | I83: =IF(I57<H57,0,1) -> 0 | J83: =IF(J57<I57,0,1) -> 0 | K83: =IF(K57<J57,0,1) -> 0 | L83: =IF(L57<K57,0,1) -> 0 | M83: =IF(M57<L57,0,1) -> 0 | N83: =IF(N57<M57,0,1) -> 0 | O83: =IF(O57<N57,0,1) -> 0 | P83: =IF(P57<O57,0,1) -> 0 | ... U83: =IF(U57<T57,0,1) -> 0
B85: Debt decomposition and IIR
B87: Auxiliary variable identifying whether debt is increasing | D87: =IF((D92-C92*D43/((1+D24/100)*(1+D42/100)))>0,1,0) -> 1 | E87: =IF((E92-D92*E43/((1+E24/100)*(1+E42/100)))>0,1,0) -> 1 | F87: =IF((F92-E92*F43/((1+F24/100)*(1+F42/100)))>0,1,0) -> 1 | G87: =IF((G92-F92*G43/((1+G24/100)*(1+G42/100)))>0,1,0) -> 1 | H87: =IF((H92-G92*H43/((1+H24/100)*(1+H42/100)))>0,1,0) -> 1 | I87: =IF((I92-H92*I43/((1+I24/100)*(1+I42/100)))>0,1,0) -> 1 | J87: =IF((J92-I92*J43/((1+J24/100)*(1+J42/100)))>0,1,0) -> 1 | K87: =IF((K92-J92*K43/((1+K24/100)*(1+K42/100)))>0,1,0) -> 1 | ... U87: =IF((U92-T92*U43/((1+U24/100)*(1+U42/100)))>0,1,0) -> 1
B88: Auxiliary variable identifying whether some debt is rolled over even though debt is decreasing | D88: =IF(AND(D87=0,ABS(D92-C92*D43/((1+D24/100)*(1+D42/100)))<((C98*C92*D43/((1+D24/100)*(1+D42/100))+(D39*C92*C99*D43/((1+D24/100)*(1+D42/100)))))),1,0) -> 0 | E88: =IF(AND(E87=0,ABS(E92-D92*E43/((1+E24/100)*(1+E42/100)))<((D98*D92*E43/((1+E24/100)*(1+E42/100))+(E39*D92*D99*E43/((1+E24/100)*(1+E42/100)))))),1,0) -> 0 | F88: =IF(AND(F87=0,ABS(F92-E92*F43/((1+F24/100)*(1+F42/100)))<((E98*E92*F43/((1+F24/100)*(1+F42/100))+(F39*E92*E99*F43/((1+F24/100)*(1+F42/100)))))),1,0) -> 0 | G88: =IF(AND(G87=0,ABS(G92-F92*G43/((1+G24/100)*(1+G42/100)))<((F98*F92*G43/((1+G24/100)*(1+G42/100))+(G39*F92*F99*G43/((1+G24/100)*(1+G42/100)))))),1,0) -> 0 | H88: =IF(AND(H87=0,ABS(H92-G92*H43/((1+H24/100)*(1+H42/100)))<((G98*G92*H43/((1+H24/100)*(1+H42/100))+(H39*G92*G99*H43/((1+H24/100)*(1+H42/100)))))),1,0) -> 0 | I88: =IF(AND(I87=0,ABS(I92-H92*I43/((1+I24/100)*(1+I42/100)))<((H98*H92*I43/((1+I24/100)*(1+I42/100))+(I39*H92*H99*I43/((1+I24/100)*(1+I42/100)))))),1,0) -> 0 | J88: =IF(AND(J87=0,ABS(J92-I92*J43/((1+J24/100)*(1+J42/100)))<((I98*I92*J43/((1+J24/100)*(1+J42/100))+(J39*I92*I99*J43/((1+J24/100)*(1+J42/100)))))),1,0) -> 0 | K88: =IF(AND(K87=0,ABS(K92-J92*K43/((1+K24/100)*(1+K42/100)))<((J98*J92*K43/((1+K24/100)*(1+K42/100))+(K39*J92*J99*K43/((1+K24/100)*(1+K42/100)))))),1,0) -> 0 | ... U88: =IF(AND(U87=0,ABS(U92-T92*U43/((1+U24/100)*(1+U42/100)))<((T98*T92*U43/((1+U24/100)*(1+U42/100))+(U39*T92*T99*U43/((1+U24/100)*(1+U42/100)))))),1,0) -> 0
C91: ='Input data'!$C$5-1 -> 2023 | D91: =C91+1 -> 2024 | E91: =D91+1 -> 2025 | F91: =E91+1 -> 2026 | G91: =F91+1 -> 2027 | H91: =G91+1 -> 2028 | I91: =H91+1 -> 2029 | J91: =I91+1 -> 2030 | K91: =J91+1 -> 2031 | ... U91: =T91+1 -> 2041
B92: Gross debt | C92: =C57 -> 62.88549 | D92: =D57 -> 62.455679 | E92: =D92*(1+E106/100)*E43-E60-E61+E62+E63+E64+E65+E66+E73 -> 63.692062 | F92: =E92*(1+F106/100)*F43-F60-F61+F62+F63+F64+F65+F66+F73 -> 64.202498 | G92: =F92*(1+G106/100)*G43-G60-G61+G62+G63+G64+G65+G66+G73 -> 63.836818 | H92: =G92*(1+H106/100)*H43-H60-H61+H62+H63+H64+H65+H66+H73 -> 62.913502 | I92: =H92*(1+I106/100)*I43-I60-I61+I62+I63+I64+I65+I66+I73 -> 61.635848 | J92: =I92*(1+J106/100)*J43-J60-J61+J62+J63+J64+J65+J66+J73 -> 60.304609 | K92: =J92*(1+K106/100)*K43-K60-K61+K62+K63+K64+K65+K66+K73 -> 58.916573 | L92: =K92*(1+L106/100)*L43-L60-L61+L62+L63+L64+L65+L66+L73 -> 58.101077 | ... U92: =T92*(1+U106/100)*U43-U60-U61+U62+U63+U64+U65+U66+U73 -> 52.285409
B93: Of which Outstanding debt | D93: ='Input data'!$C$66*D$92 -> 48.023909 | E93: =IF(E92=0,0,IF(E87=1,D92*E43/((1+E24/100)*(1+E42/100))-E94-E95,IF(AND(E87=0,E88=1),(1-D98-E39*D99)*D92*E43/((1+E24/100)*(1+E42/100)),E92))) -> 48.294459 | F93: =IF(F92=0,0,IF(F87=1,E92*F43/((1+F24/100)*(1+F42/100))-F94-F95,IF(AND(F87=0,F88=1),(1-E98-F39*E99)*E92*F43/((1+F24/100)*(1+F42/100)),F92))) -> 49.041541 | G93: =IF(G92=0,0,IF(G87=1,F92*G43/((1+G24/100)*(1+G42/100))-G94-G95,IF(AND(G87=0,G88=1),(1-F98-G39*F99)*F92*G43/((1+G24/100)*(1+G42/100)),G92))) -> 49.221291 | H93: =IF(H92=0,0,IF(H87=1,G92*H43/((1+H24/100)*(1+H42/100))-H94-H95,IF(AND(H87=0,H88=1),(1-G98-H39*G99)*G92*H43/((1+H24/100)*(1+H42/100)),H92))) -> 48.858093 | I93: =IF(I92=0,0,IF(I87=1,H92*I43/((1+I24/100)*(1+I42/100))-I94-I95,IF(AND(I87=0,I88=1),(1-H98-I39*H99)*H92*I43/((1+I24/100)*(1+I42/100)),I92))) -> 47.863456 | J93: =IF(J92=0,0,IF(J87=1,I92*J43/((1+J24/100)*(1+J42/100))-J94-J95,IF(AND(J87=0,J88=1),(1-I98-J39*I99)*I92*J43/((1+J24/100)*(1+J42/100)),J92))) -> 46.833513 | K93: =IF(K92=0,0,IF(K87=1,J92*K43/((1+K24/100)*(1+K42/100))-K94-K95,IF(AND(K87=0,K88=1),(1-J98-K39*J99)*J92*K43/((1+K24/100)*(1+K42/100)),K92))) -> 45.765794 | L93: =IF(L92=0,0,IF(L87=1,K92*L43/((1+L24/100)*(1+L42/100))-L94-L95,IF(AND(L87=0,L88=1),(1-K98-L39*K99)*K92*L43/((1+L24/100)*(1+L42/100)),L92))) -> 44.874626 | ... U93: =IF(U92=0,0,IF(U87=1,T92*U43/((1+U24/100)*(1+U42/100))-U94-U95,IF(AND(U87=0,U88=1),(1-T98-U39*T99)*T92*U43/((1+U24/100)*(1+U42/100)),U92))) -> 39.931997
B94: Rolled over long-term debt | D94: ='Input data'!$C$67*D$92 -> 6.4240999 | E94: =IF(E92=0,0,IF(E87=1,E39*D92*D99*E43/((1+E24/100)*(1+E42/100)),IF(AND(E87=0,E88=1),(E39*D92*D99*E43/((1+E24/100)*(1+E42/100)))*(1-ABS(E92-D92*E43/((1+E24/100)*(1+E42/100)))/((E39*D92*D99*E43/((1+E24/100)*(1+E42/100)))+(D98*D92*E43/((1+E24/100)*(1+E42/100))))),0))) -> 6.1272805 | F94: =IF(F92=0,0,IF(F87=1,F39*E92*E99*F43/((1+F24/100)*(1+F42/100)),IF(AND(F87=0,F88=1),(F39*E92*E99*F43/((1+F24/100)*(1+F42/100)))*(1-ABS(F92-E92*F43/((1+F24/100)*(1+F42/100)))/((F39*E92*E99*F43/((1+F24/100)*(1+F42/100)))+(E98*E92*F43/((1+F24/100)*(1+F42/100))))),0))) -> 6.3040194 | G94: =IF(G92=0,0,IF(G87=1,G39*F92*F99*G43/((1+G24/100)*(1+G42/100)),IF(AND(G87=0,G88=1),(G39*F92*F99*G43/((1+G24/100)*(1+G42/100)))*(1-ABS(G92-F92*G43/((1+G24/100)*(1+G42/100)))/((G39*F92*F99*G43/((1+G24/100)*(1+G42/100)))+(F98*F92*G43/((1+G24/100)*(1+G42/100))))),0))) -> 6.409624 | H94: =IF(H92=0,0,IF(H87=1,H39*G92*G99*H43/((1+H24/100)*(1+H42/100)),IF(AND(H87=0,H88=1),(H39*G92*G99*H43/((1+H24/100)*(1+H42/100)))*(1-ABS(H92-G92*H43/((1+H24/100)*(1+H42/100)))/((H39*G92*G99*H43/((1+H24/100)*(1+H42/100)))+(G98*G92*H43/((1+H24/100)*(1+H42/100))))),0))) -> 6.4444616 | I94: =IF(I92=0,0,IF(I87=1,I39*H92*H99*I43/((1+I24/100)*(1+I42/100)),IF(AND(I87=0,I88=1),(I39*H92*H99*I43/((1+I24/100)*(1+I42/100)))*(1-ABS(I92-H92*I43/((1+I24/100)*(1+I42/100)))/((I39*H92*H99*I43/((1+I24/100)*(1+I42/100)))+(H98*H92*I43/((1+I24/100)*(1+I42/100))))),0))) -> 6.3939686 | J94: =IF(J92=0,0,IF(J87=1,J39*I92*I99*J43/((1+J24/100)*(1+J42/100)),IF(AND(J87=0,J88=1),(J39*I92*I99*J43/((1+J24/100)*(1+J42/100)))*(1-ABS(J92-I92*J43/((1+J24/100)*(1+J42/100)))/((J39*I92*I99*J43/((1+J24/100)*(1+J42/100)))+(I98*I92*J43/((1+J24/100)*(1+J42/100))))),0))) -> 6.3355812 | K94: =IF(K92=0,0,IF(K87=1,K39*J92*J99*K43/((1+K24/100)*(1+K42/100)),IF(AND(K87=0,K88=1),(K39*J92*J99*K43/((1+K24/100)*(1+K42/100)))*(1-ABS(K92-J92*K43/((1+K24/100)*(1+K42/100)))/((K39*J92*J99*K43/((1+K24/100)*(1+K42/100)))+(J98*J92*K43/((1+K24/100)*(1+K42/100))))),0))) -> 6.2687673 | L94: =IF(L92=0,0,IF(L87=1,L39*K92*K99*L43/((1+L24/100)*(1+L42/100)),IF(AND(L87=0,L88=1),(L39*K92*K99*L43/((1+L24/100)*(1+L42/100)))*(1-ABS(L92-K92*L43/((1+L24/100)*(1+L42/100)))/((L39*K92*K99*L43/((1+L24/100)*(1+L42/100)))+(K98*K92*L43/((1+L24/100)*(1+L42/100))))),0))) -> 6.2230418 | ... U94: =IF(U92=0,0,IF(U87=1,U39*T92*T99*U43/((1+U24/100)*(1+U42/100)),IF(AND(U87=0,U88=1),(U39*T92*T99*U43/((1+U24/100)*(1+U42/100)))*(1-ABS(U92-T92*U43/((1+U24/100)*(1+U42/100)))/((U39*T92*T99*U43/((1+U24/100)*(1+U42/100)))+(T98*T92*U43/((1+U24/100)*(1+U42/100))))),0))) -> 5.6740958
B95: Rolled over short-term debt | D95: ='Input data'!$C$68*D$92 -> 6.6882509 | E95: =IF(E92=0,0,IF(E87=1,(1-D99)*D92*E43/((1+E24/100)*(1+E42/100)),IF(AND(E87=0,E88=1),(D98*D92*E43/((1+E24/100)*(1+E42/100)))*(1-ABS(E92-D92*E43/((1+E24/100)*(1+E42/100)))/((E39*D92*D99*E43/((1+E24/100)*(1+E42/100)))+(D98*D92*E43/((1+E24/100)*(1+E42/100))))),0))) -> 6.6728902 | F95: =IF(F92=0,0,IF(F87=1,(1-E99)*E92*F43/((1+F24/100)*(1+F42/100)),IF(AND(F87=0,F88=1),(E98*E92*F43/((1+F24/100)*(1+F42/100)))*(1-ABS(F92-E92*F43/((1+F24/100)*(1+F42/100)))/((F39*E92*E99*F43/((1+F24/100)*(1+F42/100)))+(E98*E92*F43/((1+F24/100)*(1+F42/100))))),0))) -> 6.76286 | G95: =IF(G92=0,0,IF(G87=1,(1-F99)*F92*G43/((1+G24/100)*(1+G42/100)),IF(AND(G87=0,G88=1),(F98*F92*G43/((1+G24/100)*(1+G42/100)))*(1-ABS(G92-F92*G43/((1+G24/100)*(1+G42/100)))/((G39*F92*F99*G43/((1+G24/100)*(1+G42/100)))+(F98*F92*G43/((1+G24/100)*(1+G42/100))))),0))) -> 6.7797697 | H95: =IF(H92=0,0,IF(H87=1,(1-G99)*G92*H43/((1+H24/100)*(1+H42/100)),IF(AND(H87=0,H88=1),(G98*G92*H43/((1+H24/100)*(1+H42/100)))*(1-ABS(H92-G92*H43/((1+H24/100)*(1+H42/100)))/((H39*G92*G99*H43/((1+H24/100)*(1+H42/100)))+(G98*G92*H43/((1+H24/100)*(1+H42/100))))),0))) -> 6.7279287 | I95: =IF(I92=0,0,IF(I87=1,(1-H99)*H92*I43/((1+I24/100)*(1+I42/100)),IF(AND(I87=0,I88=1),(H98*H92*I43/((1+I24/100)*(1+I42/100)))*(1-ABS(I92-H92*I43/((1+I24/100)*(1+I42/100)))/((I39*H92*H99*I43/((1+I24/100)*(1+I42/100)))+(H98*H92*I43/((1+I24/100)*(1+I42/100))))),0))) -> 6.5936588 | J95: =IF(J92=0,0,IF(J87=1,(1-I99)*I92*J43/((1+J24/100)*(1+J42/100)),IF(AND(J87=0,J88=1),(I98*I92*J43/((1+J24/100)*(1+J42/100)))*(1-ABS(J92-I92*J43/((1+J24/100)*(1+J42/100)))/((J39*I92*I99*J43/((1+J24/100)*(1+J42/100)))+(I98*I92*J43/((1+J24/100)*(1+J42/100))))),0))) -> 6.4551574 | K95: =IF(K92=0,0,IF(K87=1,(1-J99)*J92*K43/((1+K24/100)*(1+K42/100)),IF(AND(K87=0,K88=1),(J98*J92*K43/((1+K24/100)*(1+K42/100)))*(1-ABS(K92-J92*K43/((1+K24/100)*(1+K42/100)))/((K39*J92*J99*K43/((1+K24/100)*(1+K42/100)))+(J98*J92*K43/((1+K24/100)*(1+K42/100))))),0))) -> 6.3120732 | L95: =IF(L92=0,0,IF(L87=1,(1-K99)*K92*L43/((1+L24/100)*(1+L42/100)),IF(AND(L87=0,L88=1),(K98*K92*L43/((1+L24/100)*(1+L42/100)))*(1-ABS(L92-K92*L43/((1+L24/100)*(1+L42/100)))/((L39*K92*K99*L43/((1+L24/100)*(1+L42/100)))+(K98*K92*L43/((1+L24/100)*(1+L42/100))))),0))) -> 6.1939759 | ... U95: =IF(U92=0,0,IF(U87=1,(1-T99)*T92*U43/((1+U24/100)*(1+U42/100)),IF(AND(U87=0,U88=1),(T98*T92*U43/((1+U24/100)*(1+U42/100)))*(1-ABS(U92-T92*U43/((1+U24/100)*(1+U42/100)))/((U39*T92*T99*U43/((1+U24/100)*(1+U42/100)))+(T98*T92*U43/((1+U24/100)*(1+U42/100))))),0))) -> 5.4592544
B96: New long-term debt | D96: ='Input data'!$C$69*D$92 -> 1.186119 | E96: =IF(E92=0,0,IF(E87=1,'Input data'!$C$58*(E92-D92*E43/((1+E24/100)*(1+E42/100))),0)) -> 2.3350232 | F96: =IF(F92=0,0,IF(F87=1,'Input data'!$C$58*(F92-E92*F43/((1+F24/100)*(1+F42/100))),0)) -> 1.8825197 | G96: =IF(G92=0,0,IF(G87=1,'Input data'!$C$58*(G92-F92*G43/((1+G24/100)*(1+G42/100))),0)) -> 1.2820563 | H96: =IF(H92=0,0,IF(H87=1,'Input data'!$C$58*(H92-G92*H43/((1+H24/100)*(1+H42/100))),0)) -> 0.79381012 | I96: =IF(I92=0,0,IF(I87=1,'Input data'!$C$58*(I92-H92*I43/((1+I24/100)*(1+I42/100))),0)) -> 0.70548263 | J96: =IF(J92=0,0,IF(J87=1,'Input data'!$C$58*(J92-I92*J43/((1+J24/100)*(1+J42/100))),0)) -> 0.61162297 | K96: =IF(K92=0,0,IF(K87=1,'Input data'!$C$58*(K92-J92*K43/((1+K24/100)*(1+K42/100))),0)) -> 0.51235976 | L96: =IF(L92=0,0,IF(L87=1,'Input data'!$C$58*(L92-K92*L43/((1+L24/100)*(1+L42/100))),0)) -> 0.7276591 | ... U96: =IF(U92=0,0,IF(U87=1,'Input data'!$C$58*(U92-T92*U43/((1+U24/100)*(1+U42/100))),0)) -> 1.0968031
B97: New short-term debt | D97: ='Input data'!$C$70*D$92 -> 0.1332957 | E97: =IF(E92=0,0,IF(E87=1,'Input data'!$C$57*(E92-D92*E43/((1+E24/100)*(1+E42/100))),0)) -> 0.26240925 | F97: =IF(F92=0,0,IF(F87=1,'Input data'!$C$57*(F92-E92*F43/((1+F24/100)*(1+F42/100))),0)) -> 0.21155704 | G97: =IF(G92=0,0,IF(G87=1,'Input data'!$C$57*(G92-F92*G43/((1+G24/100)*(1+G42/100))),0)) -> 0.14407712 | H97: =IF(H92=0,0,IF(H87=1,'Input data'!$C$57*(H92-G92*H43/((1+H24/100)*(1+H42/100))),0)) -> 0.089208158 | I97: =IF(I92=0,0,IF(I87=1,'Input data'!$C$57*(I92-H92*I43/((1+I24/100)*(1+I42/100))),0)) -> 0.079281939 | J97: =IF(J92=0,0,IF(J87=1,'Input data'!$C$57*(J92-I92*J43/((1+J24/100)*(1+J42/100))),0)) -> 0.068734017 | K97: =IF(K92=0,0,IF(K87=1,'Input data'!$C$57*(K92-J92*K43/((1+K24/100)*(1+K42/100))),0)) -> 0.057578845 | L97: =IF(L92=0,0,IF(L87=1,'Input data'!$C$57*(L92-K92*L43/((1+L24/100)*(1+L42/100))),0)) -> 0.081774124 | ... U97: =IF(U92=0,0,IF(U87=1,'Input data'!$C$57*(U92-T92*U43/((1+U24/100)*(1+U42/100))),0)) -> 0.12325843
B98: Share of short-term debt in total government debt | D98: =IF(D92<>0,(D95+D97)/(D93+D94+D95+D96+D97),0) -> 0.10922221 | E98: =IF(E92<>0,(E95+E97)/(E93+E94+E95+E96+E97),0) -> 0.10888797 | F98: =IF(F92<>0,(F95+F97)/(F93+F94+F95+F96+F97),0) -> 0.10863155 | G98: =IF(G92<>0,(G95+G97)/(G93+G94+G95+G96+G97),0) -> 0.10846165 | H98: =IF(H92<>0,(H95+H97)/(H93+H94+H95+H96+H97),0) -> 0.1083573 | I98: =IF(I92<>0,(I95+I97)/(I93+I94+I95+I96+I97),0) -> 0.10826396 | J98: =IF(J92<>0,(J95+J97)/(J93+J94+J95+J96+J97),0) -> 0.1081823 | K98: =IF(K92<>0,(K95+K97)/(K93+K94+K95+K96+K97),0) -> 0.10811308 | ... U98: =IF(U92<>0,(U95+U97)/(U93+U94+U95+U96+U97),0) -> 0.10676999
B99: Share of long-term debt in total government debt | D99: =IF(D92<>0,(D93+D94+D96)/(D93+D94+D95+D96+D97),1) -> 0.89077779 | E99: =IF(E92<>0,(E93+E94+E96)/(E93+E94+E95+E96+E97),1) -> 0.89111203 | F99: =IF(F92<>0,(F93+F94+F96)/(F93+F94+F95+F96+F97),1) -> 0.89136845 | G99: =IF(G92<>0,(G93+G94+G96)/(G93+G94+G95+G96+G97),1) -> 0.89153835 | H99: =IF(H92<>0,(H93+H94+H96)/(H93+H94+H95+H96+H97),1) -> 0.8916427 | I99: =IF(I92<>0,(I93+I94+I96)/(I93+I94+I95+I96+I97),1) -> 0.89173604 | J99: =IF(J92<>0,(J93+J94+J96)/(J93+J94+J95+J96+J97),1) -> 0.8918177 | K99: =IF(K92<>0,(K93+K94+K96)/(K93+K94+K95+K96+K97),1) -> 0.89188692 | ... U99: =IF(U92<>0,(U93+U94+U96)/(U93+U94+U95+U96+U97),1) -> 0.89323001
B101: IIR | C101: ='Baseline NFPC'!C96 -> 1.422372 | D101: ='Baseline NFPC'!D96 -> 1.725464 | E101: ='Baseline NFPC'!E96 -> 1.8 | F101: =F103+F104 -> 1.7990942 | G101: =G103+G104 -> 1.9393065 | H101: =H103+H104 -> 2.0651773 | I101: =I103+I104 -> 2.1807763 | J101: =J103+J104 -> 2.2924541 | K101: =K103+K104 -> 2.4006192 | L101: =L103+L104 -> 2.5056322 | M101: =M103+M104 -> 2.6113354 | ... U101: =U103+U104 -> 3.1415413
B102: Long-term implicit interest rate | E102: =((E36*D92)-(E38*(D95+D97)))/(D93+D94+D96) -> 1.775559 | F102: =IF(E92>0,(E102*E93+ ('Baseline NFPC'!F97*('Baseline NFPC'!E88+'Baseline NFPC'!E89+'Baseline NFPC'!E91)-'Baseline NFPC'!E97*'Baseline NFPC'!E88)/('Baseline NFPC'!E89+'Baseline NFPC'!E91) *(E96+E94))/(E93+E94+E96),F37) -> 1.8086572 | G102: =IF(F92>0,(F102*F93+G37*(F96+F94))/(F93+F94+F96),G37) -> 1.9468022 | H102: =IF(G92>0,(G102*G93+H37*(G96+G94))/(G93+G94+G96),H37) -> 2.0688766 | I102: =IF(H92>0,(H102*H93+I37*(H96+H94))/(H93+H94+H96),I37) -> 2.1794442 | J102: =IF(I92>0,(I102*I93+J37*(I96+I94))/(I93+I94+I96),J37) -> 2.2856246 | K102: =IF(J92>0,(J102*J93+K37*(J96+J94))/(J93+J94+J96),K37) -> 2.3878754 | L102: =IF(K92>0,(K102*K93+L37*(K96+K94))/(K93+K94+K96),L37) -> 2.4865996 | M102: =IF(L92>0,(L102*L93+M37*(L96+L94))/(L93+L94+L96),M37) -> 2.5861143 | N102: =IF(M92>0,(M102*M93+N37*(M96+M94))/(M93+M94+M96),N37) -> 2.6850607 | ... U102: =IF(T92>0,(T102*T93+U37*(T96+T94))/(T93+T94+T96),U37) -> 3.2022033
B103: Nominal implicit interest rate on debt (Excel approximation) | E103: =(E102*(D93+D94+D96)+E38*(D95+D97))/D92 -> 1.8 | F103: =(F102*(E93+E94+E96)+F38*(E95+E97))/E92 -> 1.7990942 | G103: =(G102*(F93+F94+F96)+G38*(F95+F97))/F92 -> 1.9393065 | H103: =(H102*(G93+G94+G96)+H38*(G95+G97))/G92 -> 2.0651773 | I103: =(I102*(H93+H94+H96)+I38*(H95+H97))/H92 -> 2.1807763 | J103: =(J102*(I93+I94+I96)+J38*(I95+I97))/I92 -> 2.2924541 | K103: =(K102*(J93+J94+J96)+K38*(J95+J97))/J92 -> 2.4006192 | L103: =(L102*(K93+K94+K96)+L38*(K95+K97))/K92 -> 2.5056322 | ... U103: =(U102*(T93+T94+T96)+U38*(T95+T97))/T92 -> 3.1415413
B104: Diff. STATA | E104: =IF('Criteria results'!$F$5=4,E115,E120) -> 0 | F104: =IF('Criteria results'!$F$5=4,F115,F120) -> 0 | G104: =IF('Criteria results'!$F$5=4,G115,G120) -> 0 | H104: =IF('Criteria results'!$F$5=4,H115,H120) -> 0 | I104: =IF('Criteria results'!$F$5=4,I115,I120) -> 0 | J104: =IF('Criteria results'!$F$5=4,J115,J120) -> 0 | K104: =IF('Criteria results'!$F$5=4,K115,K120) -> 0 | L104: =IF('Criteria results'!$F$5=4,L115,L120) -> 0 | ... U104: =IF('Criteria results'!$F$5=4,U115,U120) -> 0
B106: (i - g) | C106: =((1+C101/100)/((1+C24/100)*(1+C42/100))-1)*100 -> -4.19208 | D106: =((1+D101/100)/((1+D24/100)*(1+D42/100))-1)*100 -> -1.1030667 | E106: =((1+E101/100)/((1+E24/100)*(1+E42/100))-1)*100 -> -0.39216469 | F106: =((1+F101/100)/((1+F24/100)*(1+F42/100))-1)*100 -> -0.71457644 | G106: =((1+G101/100)/((1+G24/100)*(1+G42/100))-1)*100 -> -0.9056942 | H106: =((1+H101/100)/((1+H24/100)*(1+H42/100))-1)*100 -> -0.82287233 | I106: =((1+I101/100)/((1+I24/100)*(1+I42/100))-1)*100 -> -1.1688943 | J106: =((1+J101/100)/((1+J24/100)*(1+J42/100))-1)*100 -> -1.046043 | ... U106: =((1+U101/100)/((1+U24/100)*(1+U42/100))-1)*100 -> -0.59876651
B110: Per memo - STATA results
B112: No extension (annual adjustment of 0.54)
B113: Debt | C113: 62.885487 | D113: 62.455677 | E113: 63.692066 | F113: 64.202499 | G113: 63.836819 | H113: 62.913509 | I113: 61.635853 | J113: 60.304611 | K113: 58.916573 | L113: 58.101078 | M113: 57.447086 | N113: 56.799232 | O113: 56.191807 | P113: 55.623192 | Q113: 54.992081 | R113: 54.359505 | S113: 53.723274 | T113: 52.986897 | U113: 52.285461
B114: IIR | C114: 1.4223719 | D114: 1.7254641 | E114: 1.7999998 | F114: 1.7990947 | G114: 1.9393069 | H114: 2.0651777 | I114: 2.1807766 | J114: 2.2924545 | K114: 2.4006197 | L114: 2.5056326 | M114: 2.6113355 | N114: 2.7165153 | O114: 2.7928731 | P114: 2.8633289 | Q114: 2.9285152 | R114: 2.9883094 | S114: 3.0434349 | T114: 3.0945251 | U114: 3.1415417
B115: IIR difference STATA - Excel | C115: 0 | D115: 0 | E115: 0 | F115: 0 | G115: 0 | H115: 0 | I115: 0 | J115: 0 | K115: 0 | L115: 0 | M115: 0 | N115: 0 | O115: 0 | P115: 0 | Q115: 0 | R115: 0 | S115: 0 | T115: 0 | U115: 0
B117: Extension (annual adjustment of 0.26)
B118: Debt | C118: 62.885487 | D118: 62.455677 | E118: 63.737305 | F118: 64.547554 | G118: 64.745628 | H118: 64.654449 | I118: 64.285561 | J118: 63.723866 | K118: 62.972622 | L118: 62.27401 | M118: 61.624283 | N118: 60.863892 | O118: 60.280903 | P118: 59.730137 | Q118: 59.110237 | R118: 58.486855 | S118: 57.857788 | T118: 57.126945 | U118: 56.432251
B119: IIR | C119: 1.4223719 | D119: 1.7254641 | E119: 1.7999998 | F119: 1.7995735 | G119: 1.9441919 | H119: 2.076129 | I119: 2.1993477 | J119: 2.3155866 | K119: 2.4261115 | L119: 2.531873 | M119: 2.6368513 | N119: 2.7401619 | O119: 2.8138633 | P119: 2.8818839 | Q119: 2.9448495 | R119: 3.0027013 | S119: 3.0561316 | T119: 3.1057453 | U119: 3.1515381
B120: IIR difference STATA - Excel | D120: 0 | E120: 0 | F120: 0 | G120: 0 | H120: 0 | I120: 0 | J120: 0 | K120: 0 | L120: 0 | M120: 0 | N120: 0 | O120: 0 | P120: 0 | Q120: 0 | R120: 0 | S120: 0 | T120: 0 | U120: 0

Sheet Financial stress
B3: Country | C3: ='Input data'!C3 -> DE
B4: Key years
B5: ='Input data'!B5 -> Last year before the adjustment | C5: =+'Input data'!C5 -> 2024
B6: Last year of adjustment | C6: =+C5+'Criteria results'!F5 -> 2028
B7: Last year of no-fiscal-policy-change projections | C7: =C5+'Criteria results'!F5+10 -> 2038
B9: Key assumptions
C10: ='Input data'!$C$5-1 -> 2023 | D10: =C10+1 -> 2024 | E10: =D10+1 -> 2025 | F10: =E10+1 -> 2026 | G10: =F10+1 -> 2027 | H10: =G10+1 -> 2028 | I10: =H10+1 -> 2029 | J10: =I10+1 -> 2030 | K10: =J10+1 -> 2031 | ... U10: =T10+1 -> 2041
B11: Fiscal assumptions (% of GDP)
B12: Structural primary balance ('+' means 'surplus') | C12: ='Input data'!C13 -> -1.260914 | D12: ='Input data'!D13 -> -1.015287 | E12: ='Adjust. no safeguard'!E12 -> -0.475287 | F12: ='Adjust. no safeguard'!F12 -> 0.064713 | G12: ='Adjust. no safeguard'!G12 -> 0.604713 | H12: ='Adjust. no safeguard'!H12 -> 1.144713 | I12: ='Adjust. no safeguard'!I12 -> 1.144713 | J12: ='Adjust. no safeguard'!J12 -> 1.144713 | K12: ='Adjust. no safeguard'!K12 -> 1.144713 | L12: =IF(L10<=$C$6,K12+'Criteria results'!$F$6,K12) -> 1.144713 | M12: =IF(M10<=$C$6,L12+'Criteria results'!$F$6,L12) -> 1.144713 | N12: =IF(N10<=$C$6,M12+'Criteria results'!$F$6,M12) -> 1.144713 | O12: =IF(O10<=$C$6,N12+'Criteria results'!$F$6,N12) -> 1.144713 | P12: =IF(P10<=$C$6,O12+'Criteria results'!$F$6,O12) -> 1.144713 | Q12: =IF(Q10<=$C$6,P12+'Criteria results'!$F$6,P12) -> 1.144713 | R12: =IF(R10<=$C$6,Q12+'Criteria results'!$F$6,Q12) -> 1.144713 | S12: =IF(S10<=$C$6,R12+'Criteria results'!$F$6,R12) -> 1.144713 | ... U12: =IF(U10<=$C$6,T12+'Criteria results'!$F$6,T12) -> 1.144713
B13: One-off and other temporary measures | C13: ='Input data'!C14 -> 0 | D13: ='Input data'!D14 -> 0 | E13: ='Input data'!E14 -> 0 | F13: ='Input data'!F14 -> 0 | G13: ='Input data'!G14 -> 0 | H13: ='Input data'!H14 -> 0 | I13: ='Input data'!I14 -> 0 | J13: ='Input data'!J14 -> 0 | ... U13: ='Input data'!U14 -> 0
B14: Stock flow adjustments (without exchange rate effect) | C14: ='Input data'!C15 -> -1.000485 | D14: ='Input data'!D15 -> -1.439456 | E14: ='Input data'!E15 -> 0.0857679 | F14: ='Input data'!F15 -> 0.1097981 | G14: ='Input data'!G15 -> 0 | H14: ='Input data'!H15 -> 0 | I14: ='Input data'!I15 -> 0 | J14: ='Input data'!J15 -> 0 | ... U14: ='Input data'!U15 -> 0
B16: ='Input data'!B19 -> Cost of ageing and selected public revenue (based on the Commission-Council 2024 Ageing Report ("AR 2024"))
B17: Total ageing cost (net of taxes on pensions) | C17: ='Input data'!C20 -> 23.1 | D17: ='Input data'!D20 -> 23.3 | E17: ='Input data'!E20 -> 23.4 | F17: ='Input data'!F20 -> 23.4 | G17: ='Input data'!G20 -> 23.6 | H17: ='Input data'!H20 -> 23.7 | I17: ='Input data'!I20 -> 23.8 | J17: ='Input data'!J20 -> 23.9 | ... U17: ='Input data'!U20 -> 24.4
B18: Property income | C18: ='Input data'!C26 -> 0.7164173 | D18: ='Input data'!D26 -> 0.7117602 | E18: ='Input data'!E26 -> 0.7071032 | F18: ='Input data'!F26 -> 0.7024462 | G18: ='Input data'!G26 -> 0.6977891 | H18: ='Input data'!H26 -> 0.6931321 | I18: ='Input data'!I26 -> 0.6884751 | J18: ='Input data'!J26 -> 0.683818 | ... U18: ='Input data'!U26 -> 0.6325905
B20: GDP growth assumptions
B21: Actual GDP (real)
B22: Level | C22: ='Baseline NFPC'!C22 -> 3615.547 | D22: ='Baseline NFPC'!D22 -> 3606.923 | E22: =IF(AND(E49>1,D49>1), E26*(1+('Baseline NFPC'!E$29+E50)/100)-D22*$C$46*(E12-D12)/100, IF(E49=1,E26,D22*(1+E51/100))) -> 3598.5247 | F22: =IF(AND(F49>1,E49>1), F26*(1+('Baseline NFPC'!F$29+F50)/100)-E22*$C$46*(F12-E12)/100, IF(F49=1,F26,E22*(1+F51/100))) -> 3611.4128 | G22: =IF(AND(G49>1,F49>1), G26*(1+G50/100)-F22*$C$46*(G12-F12)/100, IF(G49=1,G26,F22*(1+G51/100))) -> 3635.92 | H22: =IF(AND(H49>1,G49>1), H26*(1+H50/100)-G22*$C$46*(H12-G12)/100, IF(H49=1,H26,G22*(1+H51/100))) -> 3661.631 | I22: =IF(AND(I49>1,H49>1), I26*(1+I50/100)-H22*$C$46*(I12-H12)/100, IF(I49=1,I26,H22*(1+I51/100))) -> 3704.1989 | J22: =IF(AND(J49>1,I49>1), J26*(1+J50/100)-I22*$C$46*(J12-I12)/100, IF(J49=1,J26,I22*(1+J51/100))) -> 3746.2686 | K22: =IF(AND(K49>1,J49>1), K26*(1+K50/100)-J22*$C$46*(K12-J12)/100, IF(K49=1,K26,J22*(1+K51/100))) -> 3787.7192 | L22: =IF(AND(L49>1,K49>1), L26*(1+L50/100)-K22*$C$46*(L12-K12)/100, IF(L49=1,L26,K22*(1+L51/100))) -> 3809.9402 | M22: =IF(AND(M49>1,L49>1), M26*(1+M50/100)-L22*$C$46*(M12-L12)/100, IF(M49=1,M26,L22*(1+M51/100))) -> 3832.2136 | N22: =IF(AND(N49>1,M49>1), N26*(1+N50/100)-M22*$C$46*(N12-M12)/100, IF(N49=1,N26,M22*(1+N51/100))) -> 3858.1252 | ... U22: =IF(AND(U49>1,T49>1), U26*(1+U50/100)-T22*$C$46*(U12-T12)/100, IF(U49=1,U26,T22*(1+U51/100))) -> 4227.9733
B23: Growth rate | C23: ='Baseline NFPC'!C23 -> -0.2664383 | D23: ='Baseline NFPC'!D23 -> -0.2385261 | E23: =100*(E22/D22-1) -> -0.2328389 | F23: =100*(F22/E22-1) -> 0.35815102 | G23: =100*(G22/F22-1) -> 0.67860352 | H23: =100*(H22/G22-1) -> 0.70713923 | I23: =100*(I22/H22-1) -> 1.1625397 | J23: =100*(J22/I22-1) -> 1.1357286 | K23: =100*(K22/J22-1) -> 1.1064518 | L23: =100*(L22/K22-1) -> 0.5866577 | ... U23: =100*(U22/T22-1) -> 1.560002
B25: Potential GDP (real)
B26: Level | C26: ='Input data'!C34 -> 3640.494 | D26: =+C26*(1+'Input data'!D33/100) -> 3656.893 | E26: =+D26*(1+'Input data'!E33/100) -> 3666.669 | F26: =+E26*(1+'Input data'!F33/100) -> 3679.4239 | G26: =+F26*(1+'Input data'!G33/100) -> 3696.0924 | H26: =+G26*(1+'Input data'!H33/100) -> 3716.695 | I26: =+H26*(1+'Input data'!I33/100) -> 3741.1498 | J26: =+I26*(1+'Input data'!J33/100) -> 3764.8611 | K26: =+J26*(1+'Input data'!K33/100) -> 3787.7192 | ... U26: =+T26*(1+'Input data'!U33/100) -> 4227.9728
B28: Output gap
B29: Output gap | C29: =100*(C22/C26-1) -> -0.68526414 | D29: =100*(D22/D26-1) -> -1.3664607 | E29: =100*(E22/E26-1) -> -1.8584807 | F29: =100*(F22/F26-1) -> -1.848418 | G29: =100*(G22/G26-1) -> -1.6279999 | H29: =100*(H22/H26-1) -> -1.4815314 | I29: =100*(I22/I26-1) -> -0.98768759 | J29: =100*(J22/J26-1) -> -0.4938438 | ... U29: =100*(U22/U26-1) -> 1.1962257e-05
B31: Actual GDP (nominal, national currency)
B32: Growth rate | C32: =100*((1+C23/100)*(1+C41/100)-1) -> 5.8601126 | D32: =100*((1+D23/100)*(1+D41/100)-1) -> 2.8600792 | E32: =100*((1+E23/100)*(1+E41/100)-1) -> 2.2007954 | F32: =100*((1+F23/100)*(1+F41/100)-1) -> 2.531762 | G32: =100*((1+G23/100)*(1+G41/100)-1) -> 2.8710032 | H32: =100*((1+H23/100)*(1+H41/100)-1) -> 2.9120118 | I32: =100*((1+I23/100)*(1+I41/100)-1) -> 3.3892878 | J32: =100*((1+J23/100)*(1+J41/100)-1) -> 3.3737884 | ... U32: =100*((1+U23/100)*(1+U41/100)-1) -> 3.7628384
B34: Interest rates
B35: Nominal implicit interest rate on debt | C35: ='Input data'!C37 -> 1.422372 | D35: ='Input data'!D37 -> 1.725464 | E35: ='Input data'!E37 -> 1.8 | F35: =F92 -> 1.7990942 | G35: =G92 -> 1.9393065 | H35: =H92 -> 2.0651773 | I35: =I92 -> 2.4041848 | J35: =J92 -> 2.3938496 | K35: =K92 -> 2.4894683 | L35: =L92 -> 2.5835007 | M35: =M92 -> 2.6791781 | ... U35: =U92 -> 3.1621008
B36: Long-term interest rate | C36: ='Input data'!C$39 -> 2.43 | D36: ='Input data'!D$39 -> 2.3225 | E36: ='Input data'!E$39 -> 2.544438 | F36: ='Input data'!F$39 -> 2.698655 | G36: =F36+($N$36-$F$36)/($N$10-$F$10) -> 2.7743606 | H36: =G36+($N$36-$F$36)/($N$10-$F$10) -> 2.8500662 | I36: =IF('Criteria results'!$F$5=4, IF(H56>90,F36+('Input data'!$C$52-$F$36)/($N$10-$F$10)*(I10-$F$10)+1+0.06*(H56-90), F36+('Input data'!$C$52-$F$36)/($N$10-$F$10)*(I10-$F$10)+1), F36+('Input data'!$C$52-$F$36)/($N$10-$F$10)*(I10-$F$10)) -> 3.9257719 | J36: =$F$36+('Input data'!$C$52-$F$36)/($N$10-$F$10)*(J10-$F$10) -> 3.0014775 | K36: =$F$36+('Input data'!$C$52-$F$36)/($N$10-$F$10)*(K10-$F$10) -> 3.0771831 | L36: =IF('Criteria results'!$F$5=7, IF(K56>90,F36+('Input data'!$C$52-$F$36)/($N$10-$F$10)*(L10-$F$10)+1+0.06*(K56-90), F36+('Input data'!$C$52-$F$36)/($N$10-$F$10)*(L10-$F$10)+1), F36+('Input data'!$C$52-$F$36)/($N$10-$F$10)*(L10-$F$10)) -> 3.1528887 | M36: =$F$36+('Input data'!$C$52-$F$36)/($N$10-$F$10)*(M10-$F$10) -> 3.2285944 | N36: ='Baseline NFPC'!N36 -> 3.3043 | O36: ='Baseline NFPC'!O36 -> 3.339085 | P36: ='Baseline NFPC'!P36 -> 3.37387 | Q36: ='Baseline NFPC'!Q36 -> 3.408655 | R36: ='Baseline NFPC'!R36 -> 3.44344 | S36: ='Baseline NFPC'!S36 -> 3.478225 | T36: ='Baseline NFPC'!T36 -> 3.51301 | U36: ='Baseline NFPC'!U36 -> 3.547795
B37: Short-term interest rate | C37: ='Input data'!C$38 -> 3.43 | D37: ='Input data'!D$38 -> 3.570833 | E37: ='Input data'!E$38 -> 1.999333 | F37: ='Input data'!F$38 -> 1.720833 | G37: =F37+($N$37-$F$37)/($N$10-$F$10) -> 1.8778014 | H37: =G37+($N$37-$F$37)/($N$10-$F$10) -> 2.0347698 | I37: =IF('Criteria results'!$F$5=4, IF(H56>90,F37+('Input data'!$C$53-$F$37)/($N$10-$F$10)*(I10-$F$10)+1+0.06*(H56-90), F37+('Input data'!$C$53-$F$37)/($N$10-$F$10)*(I10-$F$10)+1), F37+('Input data'!$C$53-$F$37)/($N$10-$F$10)*(I10-$F$10)) -> 3.1917381 | J37: =$F$37+('Input data'!$C$53-$F$37)/($N$10-$F$10)*(J10-$F$10) -> 2.3487065 | K37: =$F$37+('Input data'!$C$53-$F$37)/($N$10-$F$10)*(K10-$F$10) -> 2.5056749 | L37: =IF('Criteria results'!$F$5=7, IF(K56>90,F37+('Input data'!$C$53-$F$37)/($N$10-$F$10)*(L10-$F$10)+1+0.06*(K56-90), F37+('Input data'!$C$53-$F$37)/($N$10-$F$10)*(L10-$F$10)+1), F37+('Input data'!$C$53-$F$37)/($N$10-$F$10)*(L10-$F$10)) -> 2.6626432 | M37: =$F$37+('Input data'!$C$53-$F$37)/($N$10-$F$10)*(M10-$F$10) -> 2.8196116 | N37: ='Baseline NFPC'!N37 -> 2.97658 | O37: ='Baseline NFPC'!O37 -> 2.927751 | P37: ='Baseline NFPC'!P37 -> 2.878922 | Q37: ='Baseline NFPC'!Q37 -> 2.830093 | R37: ='Baseline NFPC'!R37 -> 2.781264 | S37: ='Baseline NFPC'!S37 -> 2.732435 | T37: ='Baseline NFPC'!T37 -> 2.683606 | U37: ='Baseline NFPC'!U37 -> 2.634777
B38: Share of long-term debt that matures every year | C38: ='Baseline NFPC'!C38 -> 0.12643541 | D38: ='Baseline NFPC'!D38 -> 0.11798594 | E38: ='Baseline NFPC'!E38 -> 0.11258884 | F38: ='Baseline NFPC'!F38 -> 0.11390289 | G38: ='Baseline NFPC'!G38 -> 0.11521694 | H38: ='Baseline NFPC'!H38 -> 0.11653099 | I38: ='Baseline NFPC'!I38 -> 0.11784504 | J38: ='Baseline NFPC'!J38 -> 0.1191591 | ... U38: ='Baseline NFPC'!U38 -> 0.1244153
B40: Inflation and exchange rate
B41: GDP deflator (National currency) | C41: ='Input data'!C42 -> 6.142918 | D41: ='Input data'!D42 -> 3.106014 | E41: ='Input data'!E42 -> 2.439314 | F41: ='Input data'!F42 -> 2.165854 | G41: ='Baseline NFPC'!G41 -> 2.1776222 | H41: ='Baseline NFPC'!H41 -> 2.1893905 | I41: ='Baseline NFPC'!I41 -> 2.2011587 | J41: ='Baseline NFPC'!J41 -> 2.212927 | K41: ='Baseline NFPC'!K41 -> 2.2246952 | L41: ='Baseline NFPC'!L41 -> 2.2364635 | M41: ='Baseline NFPC'!M41 -> 2.2482317 | N41: ='Baseline NFPC'!N41 -> 2.26 | ... U41: ='Baseline NFPC'!U41 -> 2.169
B42: Exchange rate composite change (weighted by share of debt in each currency) | C42: ='Baseline NFPC'!C42 -> 0.9997445 | D42: ='Baseline NFPC'!D42 -> 0.9999892 | E42: ='Baseline NFPC'!E42 -> 0.9997361 | F42: ='Baseline NFPC'!F42 -> 0.9998241 | G42: ='Baseline NFPC'!G42 -> 1 | H42: ='Baseline NFPC'!H42 -> 1 | I42: ='Baseline NFPC'!I42 -> 1 | J42: ='Baseline NFPC'!J42 -> 1 | ... U42: ='Baseline NFPC'!U42 -> 1
B44: Intermediate calculations (growth rate equation)
B46: Fiscal multiplier | C46: ='Input data'!C49 -> 0.75
B47: Budget balance semi-elasticity | C47: ='Input data'!C50 -> 0.504
B49: Auxiliary variable to control the closure of the output gap | D49: =IF(AND(ABS((D12-C12)-('Input data'!D13-'Input data'!C13))>0.0001,ABS(D12-C12)>0.0001,D$10>$C$5),4,IF(C49=4,3,IF(C49=3,2,IF(C49=2,1,0)))) -> 0 | E49: =IF(AND(ABS((E12-D12)-('Baseline NFPC'!E12-'Baseline NFPC'!D12))>0.0001,ABS(E12-D12)>0.0001,E$10>$C$5),4,IF(D49=4,3,IF(D49=3,2,IF(D49=2,1,0)))) -> 4 | F49: =IF(AND(ABS((F12-E12)-('Baseline NFPC'!F12-'Baseline NFPC'!E12))>0.0001,ABS(F12-E12)>0.0001,F$10>$C$5),4,IF(E49=4,3,IF(E49=3,2,IF(E49=2,1,0)))) -> 4 | G49: =IF(AND(ABS((G12-F12)-('Baseline NFPC'!G12-'Baseline NFPC'!F12))>0.0001,ABS(G12-F12)>0.0001,G$10>$C$5),4,IF(F49=4,3,IF(F49=3,2,IF(F49=2,1,0)))) -> 4 | H49: =IF(AND(ABS((H12-G12)-('Baseline NFPC'!H12-'Baseline NFPC'!G12))>0.0001,ABS(H12-G12)>0.0001,H$10>$C$5),4,IF(G49=4,3,IF(G49=3,2,IF(G49=2,1,0)))) -> 4 | I49: =IF(AND(ABS((I12-H12)-('Baseline NFPC'!I12-'Baseline NFPC'!H12))>0.0001,ABS(I12-H12)>0.0001,I$10>$C$5),4,IF(H49=4,3,IF(H49=3,2,IF(H49=2,1,0)))) -> 3 | J49: =IF(AND(ABS((J12-I12)-('Baseline NFPC'!J12-'Baseline NFPC'!I12))>0.0001,ABS(J12-I12)>0.0001,J$10>$C$5),4,IF(I49=4,3,IF(I49=3,2,IF(I49=2,1,0)))) -> 2 | K49: =IF(AND(ABS((K12-J12)-('Baseline NFPC'!K12-'Baseline NFPC'!J12))>0.0001,ABS(K12-J12)>0.0001,K$10>$C$5),4,IF(J49=4,3,IF(J49=3,2,IF(J49=2,1,0)))) -> 1 | L49: =IF(AND(ABS((L12-K12)-('Baseline NFPC'!L12-'Baseline NFPC'!K12))>0.0001,ABS(L12-K12)>0.0001,L$10>$C$5),4,IF(K49=4,3,IF(K49=3,2,IF(K49=2,1,0)))) -> 0 | ... U49: =IF(AND(ABS((U12-T12)-('Baseline NFPC'!U12-'Baseline NFPC'!T12))>0.0001,ABS(U12-T12)>0.0001,U$10>$C$5),4,IF(T49=4,3,IF(T49=3,2,IF(T49=2,1,0)))) -> 0
B50: OG intermediate auxiliary value | D50: =IF(C49=4,2/3*(C29-'Baseline NFPC'!C29),IF(C49=3,1/3*(#REF!-'Baseline NFPC'!#REF!),0)) -> 0 | E50: =IF(D49=4,2/3*(D29-'Baseline NFPC'!D29),IF(D49=3,1/3*(C29-'Baseline NFPC'!C29),0)) -> 0 | F50: =IF(E49=4,2/3*(E29-'Baseline NFPC'!E29),IF(E49=3,1/3*(D29-'Baseline NFPC'!D29),0)) -> -0.26560052 | G50: =IF(F49=4,2/3*F29,IF(F49=3,1/3*E29,0)) -> -1.2322787 | H50: =IF(G49=4,2/3*G29,IF(G49=3,1/3*F29,0)) -> -1.0853333 | I50: =IF(H49=4,2/3*H29,IF(H49=3,1/3*G29,0)) -> -0.98768759 | J50: =IF(I49=4,2/3*I29,IF(I49=3,1/3*H29,0)) -> -0.4938438 | K50: =IF(J49=4,2/3*J29,IF(J49=3,1/3*I29,0)) -> 0 | L50: =IF(K49=4,2/3*K29,IF(K49=3,1/3*J29,0)) -> 0 | M50: =IF(L49=4,2/3*L29,IF(L49=3,1/3*K29,0)) -> 0 | N50: =IF(M49=4,2/3*M29,IF(M49=3,1/3*L29,0)) -> 0 | ... U50: =IF(T49=4,2/3*T29,IF(T49=3,1/3*S29,0)) -> 0
B51: GDP intermediate growth rate - only feedback effect and no closure of the OG | D51: ='Input data'!D30-$C$46*((D12-C12)-('Input data'!D13-'Input data'!C13)) -> -0.2385261 | E51: ='Input data'!E30-$C$46*(E12-D12) -> -0.2328389 | F51: ='Input data'!F30-$C$46*(F12-E12) -> 0.2212352 | G51: ='Input data'!G30-$C$46*(G12-F12) -> 0.4501665 | H51: ='Input data'!H30-$C$46*(H12-G12) -> 0.5533591 | I51: ='Input data'!I30-$C$46*(I12-H12) -> 1.057734 | J51: ='Input data'!J30-$C$46*(J12-I12) -> 0.6338005 | K51: ='Input data'!K30-$C$46*(K12-J12) -> 0.6071447 | L51: ='Input data'!L30-$C$46*(L12-K12) -> 0.5866577 | ... U51: ='Input data'!U30-$C$46*(U12-T12) -> 1.560002
B53: Debt projections
C55: ='Input data'!$C$5-1 -> 2023 | D55: =C55+1 -> 2024 | E55: =D55+1 -> 2025 | F55: =E55+1 -> 2026 | G55: =F55+1 -> 2027 | H55: =G55+1 -> 2028 | I55: =H55+1 -> 2029 | J55: =I55+1 -> 2030 | K55: =J55+1 -> 2031 | ... U55: =T55+1 -> 2041
B56: Gross debt | C56: =+'Input data'!C12 -> 62.88549 | D56: =+C56+D57 -> 62.455679 | E56: =+D56+E57 -> 63.69213 | F56: =+E56+F57 -> 64.202561 | G56: =+F56+G57 -> 63.836882 | H56: =+G56+H57 -> 62.913564 | I56: =+H56+I57 -> 61.771856 | J56: =+I56+J57 -> 60.499784 | K56: =+J56+K57 -> 59.161953 | ... U56: =+T56+U57 -> 52.756277
B57: Change in debt (-1+2+3) | D57: =-D58+D66+D71 -> -0.42981088 | E57: =-E58+E66+E71 -> 1.2364509 | F57: =-F58+F66+F71 -> 0.51043146 | G57: =-G58+G66+G71 -> -0.36567993 | H57: =-H58+H66+H71 -> -0.92331721 | I57: =-I58+I66+I71 -> -1.1417079 | J57: =-J58+J66+J71 -> -1.2720721 | K57: =-K58+K66+K71 -> -1.3378312 | ... U57: =-U58+U66+U71 -> -0.69362701
B58: (1) Primary balance (1.1 + 1.2 - 1.3 -1.4 -1.5 - 1.6 -1.7) | D58: =D59+D60-D61-D62-D63-D64-D65 -> -1.7039832 | E58: =E59+E60-E61-E62-E63-E64-E65 -> -1.4119613 | F58: =F59+F60-F61-F62-F63-F64-F65 -> -0.86688967 | G58: =G59+G60-G61-G62-G63-G64-G65 -> -0.21579894 | H58: =H59+H60-H61-H62-H63-H64-H65 -> 0.39802118 | I58: =I59+I60-I61-I62-I63-I64-I65 -> 0.54226145 | J58: =J59+J60-J61-J62-J63-J64-J65 -> 0.68650163 | K58: =K59+K60-K61-K62-K63-K64-K65 -> 0.8307419 | ... U58: =U59+U60-U61-U62-U63-U64-U65 -> 0.38417743
B59: (1.1) Structural primary balance (before ageing cost) | D59: =D12 -> -1.015287 | E59: =IF(E12="",D59,E12) -> -0.475287 | F59: =IF(F12="",E59,F12) -> 0.064713 | G59: =IF(G12="",F59,G12) -> 0.604713 | H59: =IF(H12="",G59,H12) -> 1.144713 | I59: =IF(I12="",H59,I12) -> 1.144713 | J59: =IF(J12="",I59,J12) -> 1.144713 | K59: =IF(K12="",J59,K12) -> 1.144713 | L59: =IF(L12="",K59,L12) -> 1.144713 | ... U59: =IF(U12="",T59,U12) -> 1.144713
B60: (1.2) Cumulated budgetary effort (in terms of primary balance) | D60: 0 | E60: 0 | F60: 0 | G60: 0 | H60: 0 | I60: 0 | J60: 0 | K60: 0 | L60: 0 | M60: 0 | N60: 0 | O60: 0 | P60: 0 | Q60: 0 | R60: 0 | S60: 0 | T60: 0 | U60: 0
B61: (1.3) Cyclical component | D61: =-$C$47*D29 -> 0.68869622 | E61: =-$C$47*E29 -> 0.93667427 | F61: =-$C$47*F29 -> 0.93160267 | G61: =-$C$47*G29 -> 0.82051194 | H61: =-$C$47*H29 -> 0.74669182 | I61: =-$C$47*I29 -> 0.49779455 | J61: =-$C$47*J29 -> 0.24889727 | K61: =-$C$47*K29 -> 0 | ... U61: =-$C$47*U29 -> -6.0289775e-06
B62: (1.4) One-off and other temporary measures | D62: =-D13 -> 0 | E62: =-E13 -> 0 | F62: =-F13 -> 0 | G62: =-G13 -> 0 | H62: =-H13 -> 0 | I62: =-I13 -> 0 | J62: =-J13 -> 0 | K62: =-K13 -> 0 | ... U62: =-U13 -> 0
B63: (1.5) Cost of ageing | D63: =IF(D$55<=$C$6,0,HLOOKUP(D$55,'Input data'!$C$9:$AZ$26,12,FALSE)-HLOOKUP($C$6,'Input data'!$C$9:$AZ$26,12,FALSE)) -> 0 | E63: =IF(E$55<=$C$6,0,HLOOKUP(E$55,'Input data'!$C$9:$AZ$26,12,FALSE)-HLOOKUP($C$6,'Input data'!$C$9:$AZ$26,12,FALSE)) -> 0 | F63: =IF(F$55<=$C$6,0,HLOOKUP(F$55,'Input data'!$C$9:$AZ$26,12,FALSE)-HLOOKUP($C$6,'Input data'!$C$9:$AZ$26,12,FALSE)) -> 0 | G63: =IF(G$55<=$C$6,0,HLOOKUP(G$55,'Input data'!$C$9:$AZ$26,12,FALSE)-HLOOKUP($C$6,'Input data'!$C$9:$AZ$26,12,FALSE)) -> 0 | H63: =IF(H$55<=$C$6,0,HLOOKUP(H$55,'Input data'!$C$9:$AZ$26,12,FALSE)-HLOOKUP($C$6,'Input data'!$C$9:$AZ$26,12,FALSE)) -> 0 | I63: =IF(I$55<=$C$6,0,HLOOKUP(I$55,'Input data'!$C$9:$AZ$26,12,FALSE)-HLOOKUP($C$6,'Input data'!$C$9:$AZ$26,12,FALSE)) -> 0.1 | J63: =IF(J$55<=$C$6,0,HLOOKUP(J$55,'Input data'!$C$9:$AZ$26,12,FALSE)-HLOOKUP($C$6,'Input data'!$C$9:$AZ$26,12,FALSE)) -> 0.2 | K63: =IF(K$55<=$C$6,0,HLOOKUP(K$55,'Input data'!$C$9:$AZ$26,12,FALSE)-HLOOKUP($C$6,'Input data'!$C$9:$AZ$26,12,FALSE)) -> 0.3 | ... U63: =IF(U$55<=$C$6,0,HLOOKUP(U$55,'Input data'!$C$9:$AZ$26,12,FALSE)-HLOOKUP($C$6,'Input data'!$C$9:$AZ$26,12,FALSE)) -> 0.7
B64: (1.6) Property incomes | D64: =IF(D$55<=$C$5,0,-HLOOKUP(D$55,'Input data'!$C$9:$AZ$26,18,FALSE)+HLOOKUP($C$6,'Input data'!$C$9:$AZ$26,18,FALSE)) -> 0 | E64: =IF(E$55<=$C$6,0,-HLOOKUP(E$55,'Input data'!$C$9:$AZ$26,18,FALSE)+HLOOKUP($C$6,'Input data'!$C$9:$AZ$26,18,FALSE)) -> 0 | F64: =IF(F$55<=$C$6,0,-HLOOKUP(F$55,'Input data'!$C$9:$AZ$26,18,FALSE)+HLOOKUP($C$6,'Input data'!$C$9:$AZ$26,18,FALSE)) -> 0 | G64: =IF(G$55<=$C$6,0,-HLOOKUP(G$55,'Input data'!$C$9:$AZ$26,18,FALSE)+HLOOKUP($C$6,'Input data'!$C$9:$AZ$26,18,FALSE)) -> 0 | H64: =IF(H$55<=$C$6,0,-HLOOKUP(H$55,'Input data'!$C$9:$AZ$26,18,FALSE)+HLOOKUP($C$6,'Input data'!$C$9:$AZ$26,18,FALSE)) -> 0 | I64: =IF(I$55<=$C$6,0,-HLOOKUP(I$55,'Input data'!$C$9:$AZ$26,18,FALSE)+HLOOKUP($C$6,'Input data'!$C$9:$AZ$26,18,FALSE)) -> 0.004657 | J64: =IF(J$55<=$C$6,0,-HLOOKUP(J$55,'Input data'!$C$9:$AZ$26,18,FALSE)+HLOOKUP($C$6,'Input data'!$C$9:$AZ$26,18,FALSE)) -> 0.0093141 | K64: =IF(K$55<=$C$6,0,-HLOOKUP(K$55,'Input data'!$C$9:$AZ$26,18,FALSE)+HLOOKUP($C$6,'Input data'!$C$9:$AZ$26,18,FALSE)) -> 0.0139711 | L64: =IF(L$55<=$C$6,0,-HLOOKUP(L$55,'Input data'!$C$9:$AZ$26,18,FALSE)+HLOOKUP($C$6,'Input data'!$C$9:$AZ$26,18,FALSE)) -> 0.0186281 | ... U64: =IF(U$55<=$C$6,0,-HLOOKUP(U$55,'Input data'!$C$9:$AZ$26,18,FALSE)+HLOOKUP($C$6,'Input data'!$C$9:$AZ$26,18,FALSE)) -> 0.0605416
B65: (1.7) Revenues | D65: 0 | E65: 0 | F65: 0 | G65: 0 | H65: 0 | I65: 0 | J65: 0 | K65: 0 | L65: 0 | M65: 0 | N65: 0 | O65: 0 | P65: 0 | Q65: 0 | R65: 0 | S65: 0 | T65: 0 | U65: 0
B66: (2) Snowball effect (2.1 + 2.2 + 2.3) | D66: =SUM(D67:D70) -> -0.6936801 | E66: =SUM(E67:E70) -> -0.24521838 | F66: =SUM(F67:F70) -> -0.45532551 | G66: =SUM(G67:G70) -> -0.58147887 | H66: =SUM(H67:H70) -> -0.52529603 | I66: =SUM(I67:I70) -> -0.59944644 | J66: =SUM(J67:J70) -> -0.5855705 | K66: =SUM(K67:K70) -> -0.50708926 | ... U66: =SUM(U67:U70) -> -0.30944959
B67: (2.1) Interest expenditure | D67: =C56*D35/100*(1/(1+D32/100)) -> 1.0548956 | E67: =D56*E35/100*(1/(1+E32/100)) -> 1.0999936 | F67: =E56*F35/100*(1/(1+F32/100)) -> 1.1175868 | G67: =F56*G35/100*(1/(1+G32/100)) -> 1.2103357 | H67: =G56*H35/100*(1/(1+H32/100)) -> 1.2810407 | I67: =H56*I35/100*(1/(1+I32/100)) -> 1.4629739 | J67: =I56*J35/100*(1/(1+J32/100)) -> 1.4304645 | K67: =J56*K35/100*(1/(1+K32/100)) -> 1.4572221 | ... U67: =T56*U35/100*(1/(1+U32/100)) -> 1.6288489
B68: (2.2) Growth effect | D68: =-C56*(D23/100)*(1/(1+D32/100)) -> 0.14582752 | E68: =-D56*(E23/100)*(1/(1+E32/100)) -> 0.14228961 | F68: =-E56*(F23/100)*(1/(1+F32/100)) -> -0.22248131 | G68: =-F56*(G23/100)*(1/(1+G32/100)) -> -0.42352153 | H68: =-G56*(H23/100)*(1/(1+H32/100)) -> -0.43864231 | I68: =-H56*(I23/100)*(1/(1+I32/100)) -> -0.7074187 | J68: =-I56*(J23/100)*(1/(1+J32/100)) -> -0.67866394 | K68: =-J56*(K23/100)*(1/(1+K32/100)) -> -0.64766682 | ... U68: =-T56*(U23/100)*(1/(1+U32/100)) -> -0.80358208
B69: (2.3) Inflation effect | D69: =-C56*D41/100*(1/(1+D41/100)) -> -1.894392 | E69: =-D56*E41/100*(1/(1+E41/100)) -> -1.4872123 | F69: =-E56*F41/100*(1/(1+F41/100)) -> -1.3502344 | G69: =-F56*G41/100*(1/(1+G41/100)) -> -1.368293 | H69: =-G56*H41/100*(1/(1+H41/100)) -> -1.3676944 | I69: =-H56*I41/100*(1/(1+I41/100)) -> -1.3550017 | J69: =-I56*J41/100*(1/(1+J41/100)) -> -1.337371 | K69: =-J56*K41/100*(1/(1+K41/100)) -> -1.3166445 | ... U69: =-T56*U41/100*(1/(1+U41/100)) -> -1.1347164
B70: (2.4) Exchange rate effect linked to the interest rate | D70: ='Baseline NFPC'!D70 -> -1.1222575e-05 | E70: ='Baseline NFPC'!E70 -> -0.00028926533 | F70: ='Baseline NFPC'!F70 -> -0.00019655417 | G70: ='Baseline NFPC'!G70 -> 0 | H70: ='Baseline NFPC'!H70 -> 0 | I70: ='Baseline NFPC'!I70 -> 0 | J70: ='Baseline NFPC'!J70 -> 0 | K70: ='Baseline NFPC'!K70 -> 0 | ... U70: ='Baseline NFPC'!U70 -> 0
B71: (3 ) Stock flow adjustments (3.1 + 3.2) | D71: ='Input data'!D16 -> -1.440114 | E71: ='Input data'!E16 -> 0.069708 | F71: ='Input data'!F16 -> 0.0988673 | G71: ='Input data'!G16 -> 0 | H71: ='Input data'!H16 -> 0 | I71: ='Input data'!I16 -> 0 | J71: ='Input data'!J16 -> 0 | K71: ='Input data'!K16 -> 0 | ... U71: ='Input data'!U16 -> 0
B72: (3.1) Base | D72: =D14 -> -1.439456 | E72: =E14 -> 0.0857679 | F72: =F14 -> 0.1097981 | G72: =G14 -> 0 | H72: =H14 -> 0 | I72: =I14 -> 0 | J72: =J14 -> 0 | K72: =K14 -> 0 | ... U72: =U14 -> 0
B73: (3.2) Adjustment due to the exchange rate effect linked to debt value | D73: =+D71-D72 -> -0.000658 | E73: =+E71-E72 -> -0.0160599 | F73: =+F71-F72 -> -0.0109308 | G73: =+G71-G72 -> 0 | H73: =+H71-H72 -> 0 | I73: =+I71-I72 -> 0 | J73: =+J71-J72 -> 0 | K73: =+K71-K72 -> 0 | ... U73: =+U71-U72 -> 0
B75: Debt increasing? (For criterion 1) | I75: =IF(I56<H56,0,1) -> 0 | J75: =IF(J56<I56,0,1) -> 0 | K75: =IF(K56<J56,0,1) -> 0 | L75: =IF(L56<K56,0,1) -> 0 | M75: =IF(M56<L56,0,1) -> 0 | N75: =IF(N56<M56,0,1) -> 0 | O75: =IF(O56<N56,0,1) -> 0 | P75: =IF(P56<O56,0,1) -> 0 | ... U75: =IF(U56<T56,0,1) -> 0
B77: Debt decomposition and IIR
B79: Auxiliary variable identifying whether debt is increasing | D79: =IF((D83-C83*D42/((1+D23/100)*(1+D41/100)))>0,1,0) -> 1 | E79: =IF((E83-D83*E42/((1+E23/100)*(1+E41/100)))>0,1,0) -> 1 | F79: =IF((F83-E83*F42/((1+F23/100)*(1+F41/100)))>0,1,0) -> 1 | G79: =IF((G83-F83*G42/((1+G23/100)*(1+G41/100)))>0,1,0) -> 1 | H79: =IF((H83-G83*H42/((1+H23/100)*(1+H41/100)))>0,1,0) -> 1 | I79: =IF((I83-H83*I42/((1+I23/100)*(1+I41/100)))>0,1,0) -> 1 | J79: =IF((J83-I83*J42/((1+J23/100)*(1+J41/100)))>0,1,0) -> 1 | K79: =IF((K83-J83*K42/((1+K23/100)*(1+K41/100)))>0,1,0) -> 1 | ... U79: =IF((U83-T83*U42/((1+U23/100)*(1+U41/100)))>0,1,0) -> 1
B80: Auxiliary variable identifying whether some debt is rolled over even though debt is decreasing | D80: =IF(AND(D79=0,ABS(D83-C83*D42/((1+D23/100)*(1+D41/100)))<((C89*C83*D42/((1+D23/100)*(1+D41/100))+(D38*C83*C90*D42/((1+D23/100)*(1+D41/100)))))),1,0) -> 0 | E80: =IF(AND(E79=0,ABS(E83-D83*E42/((1+E23/100)*(1+E41/100)))<((D89*D83*E42/((1+E23/100)*(1+E41/100))+(E38*D83*D90*E42/((1+E23/100)*(1+E41/100)))))),1,0) -> 0 | F80: =IF(AND(F79=0,ABS(F83-E83*F42/((1+F23/100)*(1+F41/100)))<((E89*E83*F42/((1+F23/100)*(1+F41/100))+(F38*E83*E90*F42/((1+F23/100)*(1+F41/100)))))),1,0) -> 0 | G80: =IF(AND(G79=0,ABS(G83-F83*G42/((1+G23/100)*(1+G41/100)))<((F89*F83*G42/((1+G23/100)*(1+G41/100))+(G38*F83*F90*G42/((1+G23/100)*(1+G41/100)))))),1,0) -> 0 | H80: =IF(AND(H79=0,ABS(H83-G83*H42/((1+H23/100)*(1+H41/100)))<((G89*G83*H42/((1+H23/100)*(1+H41/100))+(H38*G83*G90*H42/((1+H23/100)*(1+H41/100)))))),1,0) -> 0 | I80: =IF(AND(I79=0,ABS(I83-H83*I42/((1+I23/100)*(1+I41/100)))<((H89*H83*I42/((1+I23/100)*(1+I41/100))+(I38*H83*H90*I42/((1+I23/100)*(1+I41/100)))))),1,0) -> 0 | J80: =IF(AND(J79=0,ABS(J83-I83*J42/((1+J23/100)*(1+J41/100)))<((I89*I83*J42/((1+J23/100)*(1+J41/100))+(J38*I83*I90*J42/((1+J23/100)*(1+J41/100)))))),1,0) -> 0 | K80: =IF(AND(K79=0,ABS(K83-J83*K42/((1+K23/100)*(1+K41/100)))<((J89*J83*K42/((1+K23/100)*(1+K41/100))+(K38*J83*J90*K42/((1+K23/100)*(1+K41/100)))))),1,0) -> 0 | ... U80: =IF(AND(U79=0,ABS(U83-T83*U42/((1+U23/100)*(1+U41/100)))<((T89*T83*U42/((1+U23/100)*(1+U41/100))+(U38*T83*T90*U42/((1+U23/100)*(1+U41/100)))))),1,0) -> 0
C82: ='Input data'!$C$5-1 -> 2023 | D82: =C82+1 -> 2024 | E82: =D82+1 -> 2025 | F82: =E82+1 -> 2026 | G82: =F82+1 -> 2027 | H82: =G82+1 -> 2028 | I82: =H82+1 -> 2029 | J82: =I82+1 -> 2030 | K82: =J82+1 -> 2031 | ... U82: =T82+1 -> 2041
B83: Gross debt | C83: =C56 -> 62.88549 | D83: =D56 -> 62.455679 | E83: =D83*(1+E97/100)*E42-E59-E60+E61+E62+E63+E64+E65+E72 -> 63.692062 | F83: =E83*(1+F97/100)*F42-F59-F60+F61+F62+F63+F64+F65+F72 -> 64.202498 | G83: =F83*(1+G97/100)*G42-G59-G60+G61+G62+G63+G64+G65+G72 -> 63.836818 | H83: =G83*(1+H97/100)*H42-H59-H60+H61+H62+H63+H64+H65+H72 -> 62.913502 | I83: =H83*(1+I97/100)*I42-I59-I60+I61+I62+I63+I64+I65+I72 -> 61.771794 | J83: =I83*(1+J97/100)*J42-J59-J60+J61+J62+J63+J64+J65+J72 -> 60.499723 | K83: =J83*(1+K97/100)*K42-K59-K60+K61+K62+K63+K64+K65+K72 -> 59.161892 | L83: =K83*(1+L97/100)*L42-L59-L60+L61+L62+L63+L64+L65+L72 -> 58.390405 | ... U83: =T83*(1+U97/100)*U42-U59-U60+U61+U62+U63+U64+U65+U72 -> 52.756219
B84: Of which Outstanding debt | D84: ='Input data'!$C$66*D$83 -> 48.023909 | E84: =IF(E83=0,0,IF(E79=1,D83*E42/((1+E23/100)*(1+E41/100))-E85-E86,IF(AND(E79=0,E80=1),(1-D89-E38*D90)*D83*E42/((1+E23/100)*(1+E41/100)),E83))) -> 48.294459 | F84: =IF(F83=0,0,IF(F79=1,E83*F42/((1+F23/100)*(1+F41/100))-F85-F86,IF(AND(F79=0,F80=1),(1-E89-F38*E90)*E83*F42/((1+F23/100)*(1+F41/100)),F83))) -> 49.041541 | G84: =IF(G83=0,0,IF(G79=1,F83*G42/((1+G23/100)*(1+G41/100))-G85-G86,IF(AND(G79=0,G80=1),(1-F89-G38*F90)*F83*G42/((1+G23/100)*(1+G41/100)),G83))) -> 49.221291 | H84: =IF(H83=0,0,IF(H79=1,G83*H42/((1+H23/100)*(1+H41/100))-H85-H86,IF(AND(H79=0,H80=1),(1-G89-H38*G90)*G83*H42/((1+H23/100)*(1+H41/100)),H83))) -> 48.858093 | I84: =IF(I83=0,0,IF(I79=1,H83*I42/((1+I23/100)*(1+I41/100))-I85-I86,IF(AND(I79=0,I80=1),(1-H89-I38*H90)*H83*I42/((1+I23/100)*(1+I41/100)),I83))) -> 47.863456 | J84: =IF(J83=0,0,IF(J79=1,I83*J42/((1+J23/100)*(1+J41/100))-J85-J86,IF(AND(J79=0,J80=1),(1-I89-J38*I90)*I83*J42/((1+J23/100)*(1+J41/100)),J83))) -> 46.937649 | K84: =IF(K83=0,0,IF(K79=1,J83*K42/((1+K23/100)*(1+K41/100))-K85-K86,IF(AND(K79=0,K80=1),(1-J89-K38*J90)*J83*K42/((1+K23/100)*(1+K41/100)),K83))) -> 45.915056 | L84: =IF(L83=0,0,IF(L79=1,K83*L42/((1+L23/100)*(1+L41/100))-L85-L86,IF(AND(L79=0,L80=1),(1-K89-L38*K90)*K83*L42/((1+L23/100)*(1+L41/100)),L83))) -> 45.062961 | ... U84: =IF(U83=0,0,IF(U79=1,T83*U42/((1+U23/100)*(1+U41/100))-U85-U86,IF(AND(U79=0,U80=1),(1-T89-U38*T90)*T83*U42/((1+U23/100)*(1+U41/100)),U83))) -> 40.283215
B85: Rolled over long-term debt | D85: ='Input data'!$C$67*D$83 -> 6.4240999 | E85: =IF(E83=0,0,IF(E79=1,E38*D83*D90*E42/((1+E23/100)*(1+E41/100)),IF(AND(E79=0,E80=1),(E38*D83*D90*E42/((1+E23/100)*(1+E41/100)))*(1-ABS(E83-D83*E42/((1+E23/100)*(1+E41/100)))/((E38*D83*D90*E42/((1+E23/100)*(1+E41/100)))+(D89*D83*E42/((1+E23/100)*(1+E41/100))))),0))) -> 6.1272805 | F85: =IF(F83=0,0,IF(F79=1,F38*E83*E90*F42/((1+F23/100)*(1+F41/100)),IF(AND(F79=0,F80=1),(F38*E83*E90*F42/((1+F23/100)*(1+F41/100)))*(1-ABS(F83-E83*F42/((1+F23/100)*(1+F41/100)))/((F38*E83*E90*F42/((1+F23/100)*(1+F41/100)))+(E89*E83*F42/((1+F23/100)*(1+F41/100))))),0))) -> 6.3040194 | G85: =IF(G83=0,0,IF(G79=1,G38*F83*F90*G42/((1+G23/100)*(1+G41/100)),IF(AND(G79=0,G80=1),(G38*F83*F90*G42/((1+G23/100)*(1+G41/100)))*(1-ABS(G83-F83*G42/((1+G23/100)*(1+G41/100)))/((G38*F83*F90*G42/((1+G23/100)*(1+G41/100)))+(F89*F83*G42/((1+G23/100)*(1+G41/100))))),0))) -> 6.409624 | H85: =IF(H83=0,0,IF(H79=1,H38*G83*G90*H42/((1+H23/100)*(1+H41/100)),IF(AND(H79=0,H80=1),(H38*G83*G90*H42/((1+H23/100)*(1+H41/100)))*(1-ABS(H83-G83*H42/((1+H23/100)*(1+H41/100)))/((H38*G83*G90*H42/((1+H23/100)*(1+H41/100)))+(G89*G83*H42/((1+H23/100)*(1+H41/100))))),0))) -> 6.4444616 | I85: =IF(I83=0,0,IF(I79=1,I38*H83*H90*I42/((1+I23/100)*(1+I41/100)),IF(AND(I79=0,I80=1),(I38*H83*H90*I42/((1+I23/100)*(1+I41/100)))*(1-ABS(I83-H83*I42/((1+I23/100)*(1+I41/100)))/((I38*H83*H90*I42/((1+I23/100)*(1+I41/100)))+(H89*H83*I42/((1+I23/100)*(1+I41/100))))),0))) -> 6.3939686 | J85: =IF(J83=0,0,IF(J79=1,J38*I83*I90*J42/((1+J23/100)*(1+J41/100)),IF(AND(J79=0,J80=1),(J38*I83*I90*J42/((1+J23/100)*(1+J41/100)))*(1-ABS(J83-I83*J42/((1+J23/100)*(1+J41/100)))/((J38*I83*I90*J42/((1+J23/100)*(1+J41/100)))+(I89*I83*J42/((1+J23/100)*(1+J41/100))))),0))) -> 6.3496686 | K85: =IF(K83=0,0,IF(K79=1,K38*J83*J90*K42/((1+K23/100)*(1+K41/100)),IF(AND(K79=0,K80=1),(K38*J83*J90*K42/((1+K23/100)*(1+K41/100)))*(1-ABS(K83-J83*K42/((1+K23/100)*(1+K41/100)))/((K38*J83*J90*K42/((1+K23/100)*(1+K41/100)))+(J89*J83*K42/((1+K23/100)*(1+K41/100))))),0))) -> 6.2892125 | L85: =IF(L83=0,0,IF(L79=1,L38*K83*K90*L42/((1+L23/100)*(1+L41/100)),IF(AND(L79=0,L80=1),(L38*K83*K90*L42/((1+L23/100)*(1+L41/100)))*(1-ABS(L83-K83*L42/((1+L23/100)*(1+L41/100)))/((L38*K83*K90*L42/((1+L23/100)*(1+L41/100)))+(K89*K83*L42/((1+L23/100)*(1+L41/100))))),0))) -> 6.2491594 | ... U85: =IF(U83=0,0,IF(U79=1,U38*T83*T90*U42/((1+U23/100)*(1+U41/100)),IF(AND(U79=0,U80=1),(U38*T83*T90*U42/((1+U23/100)*(1+U41/100)))*(1-ABS(U83-T83*U42/((1+U23/100)*(1+U41/100)))/((U38*T83*T90*U42/((1+U23/100)*(1+U41/100)))+(T89*T83*U42/((1+U23/100)*(1+U41/100))))),0))) -> 5.7240017
B86: Rolled over short-term debt | D86: ='Input data'!$C$68*D$83 -> 6.6882509 | E86: =IF(E83=0,0,IF(E79=1,(1-D90)*D83*E42/((1+E23/100)*(1+E41/100)),IF(AND(E79=0,E80=1),(D89*D83*E42/((1+E23/100)*(1+E41/100)))*(1-ABS(E83-D83*E42/((1+E23/100)*(1+E41/100)))/((E38*D83*D90*E42/((1+E23/100)*(1+E41/100)))+(D89*D83*E42/((1+E23/100)*(1+E41/100))))),0))) -> 6.6728902 | F86: =IF(F83=0,0,IF(F79=1,(1-E90)*E83*F42/((1+F23/100)*(1+F41/100)),IF(AND(F79=0,F80=1),(E89*E83*F42/((1+F23/100)*(1+F41/100)))*(1-ABS(F83-E83*F42/((1+F23/100)*(1+F41/100)))/((F38*E83*E90*F42/((1+F23/100)*(1+F41/100)))+(E89*E83*F42/((1+F23/100)*(1+F41/100))))),0))) -> 6.76286 | G86: =IF(G83=0,0,IF(G79=1,(1-F90)*F83*G42/((1+G23/100)*(1+G41/100)),IF(AND(G79=0,G80=1),(F89*F83*G42/((1+G23/100)*(1+G41/100)))*(1-ABS(G83-F83*G42/((1+G23/100)*(1+G41/100)))/((G38*F83*F90*G42/((1+G23/100)*(1+G41/100)))+(F89*F83*G42/((1+G23/100)*(1+G41/100))))),0))) -> 6.7797697 | H86: =IF(H83=0,0,IF(H79=1,(1-G90)*G83*H42/((1+H23/100)*(1+H41/100)),IF(AND(H79=0,H80=1),(G89*G83*H42/((1+H23/100)*(1+H41/100)))*(1-ABS(H83-G83*H42/((1+H23/100)*(1+H41/100)))/((H38*G83*G90*H42/((1+H23/100)*(1+H41/100)))+(G89*G83*H42/((1+H23/100)*(1+H41/100))))),0))) -> 6.7279287 | I86: =IF(I83=0,0,IF(I79=1,(1-H90)*H83*I42/((1+I23/100)*(1+I41/100)),IF(AND(I79=0,I80=1),(H89*H83*I42/((1+I23/100)*(1+I41/100)))*(1-ABS(I83-H83*I42/((1+I23/100)*(1+I41/100)))/((I38*H83*H90*I42/((1+I23/100)*(1+I41/100)))+(H89*H83*I42/((1+I23/100)*(1+I41/100))))),0))) -> 6.5936588 | J86: =IF(J83=0,0,IF(J79=1,(1-I90)*I83*J42/((1+J23/100)*(1+J41/100)),IF(AND(J79=0,J80=1),(I89*I83*J42/((1+J23/100)*(1+J41/100)))*(1-ABS(J83-I83*J42/((1+J23/100)*(1+J41/100)))/((J38*I83*I90*J42/((1+J23/100)*(1+J41/100)))+(I89*I83*J42/((1+J23/100)*(1+J41/100))))),0))) -> 6.4684433 | K86: =IF(K83=0,0,IF(K79=1,(1-J90)*J83*K42/((1+K23/100)*(1+K41/100)),IF(AND(K79=0,K80=1),(J89*J83*K42/((1+K23/100)*(1+K41/100)))*(1-ABS(K83-J83*K42/((1+K23/100)*(1+K41/100)))/((K38*J83*J90*K42/((1+K23/100)*(1+K41/100)))+(J89*J83*K42/((1+K23/100)*(1+K41/100))))),0))) -> 6.3311449 | L86: =IF(L83=0,0,IF(L79=1,(1-K90)*K83*L42/((1+L23/100)*(1+L41/100)),IF(AND(L79=0,L80=1),(K89*K83*L42/((1+L23/100)*(1+L41/100)))*(1-ABS(L83-K83*L42/((1+L23/100)*(1+L41/100)))/((L38*K83*K90*L42/((1+L23/100)*(1+L41/100)))+(K89*K83*L42/((1+L23/100)*(1+L41/100))))),0))) -> 6.2180761 | ... U86: =IF(U83=0,0,IF(U79=1,(1-T90)*T83*U42/((1+U23/100)*(1+U41/100)),IF(AND(U79=0,U80=1),(T89*T83*U42/((1+U23/100)*(1+U41/100)))*(1-ABS(U83-T83*U42/((1+U23/100)*(1+U41/100)))/((U38*T83*T90*U42/((1+U23/100)*(1+U41/100)))+(T89*T83*U42/((1+U23/100)*(1+U41/100))))),0))) -> 5.5043325
B87: New long-term debt | D87: ='Input data'!$C$69*D$83 -> 1.186119 | E87: =IF(E83=0,0,IF(E79=1,'Input data'!$C$58*(E83-D83*E42/((1+E23/100)*(1+E41/100))),0)) -> 2.3350232 | F87: =IF(F83=0,0,IF(F79=1,'Input data'!$C$58*(F83-E83*F42/((1+F23/100)*(1+F41/100))),0)) -> 1.8825197 | G87: =IF(G83=0,0,IF(G79=1,'Input data'!$C$58*(G83-F83*G42/((1+G23/100)*(1+G41/100))),0)) -> 1.2820563 | H87: =IF(H83=0,0,IF(H79=1,'Input data'!$C$58*(H83-G83*H42/((1+H23/100)*(1+H41/100))),0)) -> 0.79381012 | I87: =IF(I83=0,0,IF(I79=1,'Input data'!$C$58*(I83-H83*I42/((1+I23/100)*(1+I41/100))),0)) -> 0.82769491 | J87: =IF(J83=0,0,IF(J79=1,'Input data'!$C$58*(J83-I83*J42/((1+J23/100)*(1+J41/100))),0)) -> 0.66880168 | K87: =IF(K83=0,0,IF(K79=1,'Input data'!$C$58*(K83-J83*K42/((1+K23/100)*(1+K41/100))),0)) -> 0.56318779 | L87: =IF(L83=0,0,IF(L79=1,'Input data'!$C$58*(L83-K83*L42/((1+L23/100)*(1+L41/100))),0)) -> 0.77330463 | ... U87: =IF(U83=0,0,IF(U79=1,'Input data'!$C$58*(U83-T83*U42/((1+U23/100)*(1+U41/100))),0)) -> 1.1189252
B88: New short-term debt | D88: ='Input data'!$C$70*D$83 -> 0.1332957 | E88: =IF(E83=0,0,IF(E79=1,'Input data'!$C$57*(E83-D83*E42/((1+E23/100)*(1+E41/100))),0)) -> 0.26240925 | F88: =IF(F83=0,0,IF(F79=1,'Input data'!$C$57*(F83-E83*F42/((1+F23/100)*(1+F41/100))),0)) -> 0.21155704 | G88: =IF(G83=0,0,IF(G79=1,'Input data'!$C$57*(G83-F83*G42/((1+G23/100)*(1+G41/100))),0)) -> 0.14407712 | H88: =IF(H83=0,0,IF(H79=1,'Input data'!$C$57*(H83-G83*H42/((1+H23/100)*(1+H41/100))),0)) -> 0.089208158 | I88: =IF(I83=0,0,IF(I79=1,'Input data'!$C$57*(I83-H83*I42/((1+I23/100)*(1+I41/100))),0)) -> 0.093016121 | J88: =IF(J83=0,0,IF(J79=1,'Input data'!$C$57*(J83-I83*J42/((1+J23/100)*(1+J41/100))),0)) -> 0.075159744 | K88: =IF(K83=0,0,IF(K79=1,'Input data'!$C$57*(K83-J83*K42/((1+K23/100)*(1+K41/100))),0)) -> 0.063290885 | L88: =IF(L83=0,0,IF(L79=1,'Input data'!$C$57*(L83-K83*L42/((1+L23/100)*(1+L41/100))),0)) -> 0.086903757 | ... U88: =IF(U83=0,0,IF(U79=1,'Input data'!$C$57*(U83-T83*U42/((1+U23/100)*(1+U41/100))),0)) -> 0.1257445
B89: Share of short-term debt in total government debt | D89: =IF(D83<>0,(D86+D88)/(D84+D85+D86+D87+D88),0) -> 0.10922221 | E89: =IF(E83<>0,(E86+E88)/(E84+E85+E86+E87+E88),0) -> 0.10888797 | F89: =IF(F83<>0,(F86+F88)/(F84+F85+F86+F87+F88),0) -> 0.10863155 | G89: =IF(G83<>0,(G86+G88)/(G84+G85+G86+G87+G88),0) -> 0.10846165 | H89: =IF(H83<>0,(H86+H88)/(H84+H85+H86+H87+H88),0) -> 0.1083573 | I89: =IF(I83<>0,(I86+I88)/(I84+I85+I86+I87+I88),0) -> 0.10824803 | J89: =IF(J83<>0,(J86+J88)/(J84+J85+J86+J87+J88),0) -> 0.10815922 | K89: =IF(K83<>0,(K86+K88)/(K84+K85+K86+K87+K88),0) -> 0.10808369 | ... U89: =IF(U83<>0,(U86+U88)/(U84+U85+U86+U87+U88),0) -> 0.10671874
B90: Share of long-term debt in total government debt | D90: =IF(D83<>0,(D84+D85+D87)/(D84+D85+D86+D87+D88),1) -> 0.89077779 | E90: =IF(E83<>0,(E84+E85+E87)/(E84+E85+E86+E87+E88),1) -> 0.89111203 | F90: =IF(F83<>0,(F84+F85+F87)/(F84+F85+F86+F87+F88),1) -> 0.89136845 | G90: =IF(G83<>0,(G84+G85+G87)/(G84+G85+G86+G87+G88),1) -> 0.89153835 | H90: =IF(H83<>0,(H84+H85+H87)/(H84+H85+H86+H87+H88),1) -> 0.8916427 | I90: =IF(I83<>0,(I84+I85+I87)/(I84+I85+I86+I87+I88),1) -> 0.89175197 | J90: =IF(J83<>0,(J84+J85+J87)/(J84+J85+J86+J87+J88),1) -> 0.89184078 | K90: =IF(K83<>0,(K84+K85+K87)/(K84+K85+K86+K87+K88),1) -> 0.89191631 | ... U90: =IF(U83<>0,(U84+U85+U87)/(U84+U85+U86+U87+U88),1) -> 0.89328126
B92: IIR | C92: =C103 -> 1.4223719 | D92: =D103 -> 1.7254641 | E92: =E94+E95 -> 1.8 | F92: =F94+F95 -> 1.7990942 | G92: =G94+G95 -> 1.9393065 | H92: =H94+H95 -> 2.0651773 | I92: =I94+I95 -> 2.4041848 | J92: =J94+J95 -> 2.3938496 | K92: =K94+K95 -> 2.4894683 | L92: =L94+L95 -> 2.5835007 | ... U92: =U94+U95 -> 3.1621008
B93: Long-term implicit interest rate | E93: =((E35*D83)-(E37*(D86+D88)))/(D84+D85+D87) -> 1.775559 | F93: =IF(E83>0,(E93*E84+ ('Baseline NFPC'!F97*('Baseline NFPC'!E88+'Baseline NFPC'!E89+'Baseline NFPC'!E91)-'Baseline NFPC'!E97*'Baseline NFPC'!E88)/('Baseline NFPC'!E89+'Baseline NFPC'!E91) *(E87+E85))/(E84+E85+E87),F36) -> 1.8086572 | G93: =IF(F83>0,(F93*F84+G36*(F87+F85))/(F84+F85+F87),G36) -> 1.9468022 | H93: =IF(G83>0,(G93*G84+H36*(G87+G85))/(G84+G85+G87),H36) -> 2.0688766 | I93: =IF(H83>0,(H93*H84+I36*(H87+H85))/(H84+H85+H87),I36) -> 2.308477 | J93: =IF(I83>0,(I93*I84+J36*(I87+I85))/(I84+I85+I87),J36) -> 2.3993294 | K93: =IF(J83>0,(J93*J84+K36*(J87+J85))/(J84+J85+J87),K36) -> 2.4875029 | L93: =IF(K83>0,(K93*K84+L36*(K87+K85))/(K84+K85+K87),L36) -> 2.5739101 | M93: =IF(L83>0,(L93*L84+M36*(L87+L85))/(L84+L85+L87),M36) -> 2.6621785 | N93: =IF(M83>0,(M93*M84+N36*(M87+M85))/(M84+M85+M87),N36) -> 2.7510419 | ... U93: =IF(T83>0,(T93*T84+U36*(T87+T85))/(T84+T85+T87),U36) -> 3.2251902
B94: Nominal implicit interest rate on debt (Excel approximation) | E94: =(E93*(D84+D85+D87)+E37*(D86+D88))/D83 -> 1.8 | F94: =(F93*(E84+E85+E87)+F37*(E86+E88))/E83 -> 1.7990942 | G94: =(G93*(F84+F85+F87)+G37*(F86+F88))/F83 -> 1.9393065 | H94: =(H93*(G84+G85+G87)+H37*(G86+G88))/G83 -> 2.0651773 | I94: =(I93*(H84+H85+H87)+I37*(H86+H88))/H83 -> 2.4041848 | J94: =(J93*(I84+I85+I87)+J37*(I86+I88))/I83 -> 2.3938496 | K94: =(K93*(J84+J85+J87)+K37*(J86+J88))/J83 -> 2.4894683 | L94: =(L93*(K84+K85+K87)+L37*(K86+K88))/K83 -> 2.5835007 | ... U94: =(U93*(T84+T85+T87)+U37*(T86+T88))/T83 -> 3.1621008
B95: Diff. STATA | E95: =IF('Criteria results'!$F$5=4,E104,E109) -> 0 | F95: =IF('Criteria results'!$F$5=4,F104,F109) -> 0 | G95: =IF('Criteria results'!$F$5=4,G104,G109) -> 0 | H95: =IF('Criteria results'!$F$5=4,H104,H109) -> 0 | I95: =IF('Criteria results'!$F$5=4,I104,I109) -> 0 | J95: =IF('Criteria results'!$F$5=4,J104,J109) -> 0 | K95: =IF('Criteria results'!$F$5=4,K104,K109) -> 0 | L95: =IF('Criteria results'!$F$5=4,L104,L109) -> 0 | ... U95: =IF('Criteria results'!$F$5=4,U104,U109) -> 0
B97: (i - g) | C97: =((1+C92/100)/((1+C23/100)*(1+C41/100))-1)*100 -> -4.1920801 | D97: =((1+D92/100)/((1+D23/100)*(1+D41/100))-1)*100 -> -1.1030666 | E97: =((1+E92/100)/((1+E23/100)*(1+E41/100))-1)*100 -> -0.39216469 | F97: =((1+F92/100)/((1+F23/100)*(1+F41/100))-1)*100 -> -0.71457644 | G97: =((1+G92/100)/((1+G23/100)*(1+G41/100))-1)*100 -> -0.9056942 | H97: =((1+H92/100)/((1+H23/100)*(1+H41/100))-1)*100 -> -0.82287233 | I97: =((1+I92/100)/((1+I23/100)*(1+I41/100))-1)*100 -> -0.95280953 | J97: =((1+J92/100)/((1+J23/100)*(1+J41/100))-1)*100 -> -0.94795677 | ... U97: =((1+U92/100)/((1+U23/100)*(1+U41/100))-1)*100 -> -0.57895255
B99: Per memo - STATA results
B101: No extension (annual adjustment of 0.54)
B102: Debt | C102: 62.885487 | D102: 62.455677 | E102: 63.692066 | F102: 64.202499 | G102: 63.836819 | H102: 62.913509 | I102: 61.771801 | J102: 60.499725 | K102: 59.161896 | L102: 58.390411 | M102: 57.774277 | N102: 57.158703 | O102: 56.578255 | P102: 56.031887 | Q102: 55.418804 | R102: 54.800995 | S102: 54.176708 | T102: 53.449883 | U102: 52.756264
B103: IIR | C103: 1.4223719 | D103: 1.7254641 | E103: 1.7999998 | F103: 1.7990947 | G103: 1.9393069 | H103: 2.0651777 | I103: 2.4041853 | J103: 2.3938501 | K103: 2.4894686 | L103: 2.5835011 | M103: 2.6791782 | N103: 2.7753685 | O103: 2.843787 | P103: 2.9072466 | Q103: 2.9662895 | R103: 3.020771 | S103: 3.07131 | T103: 3.1184459 | U103: 3.1621013
B104: IIR difference STATA - Excel | E104: 0 | F104: 0 | G104: 0 | H104: 0 | I104: 0 | J104: 0 | K104: 0 | L104: 0 | M104: 0 | N104: 0 | O104: 0 | P104: 0 | Q104: 0 | R104: 0 | S104: 0 | T104: 0 | U104: 0
