Workbook

Sheet Read me
G4: European Commission
G6: Directorate-General for Economic and Financial Affairs
G7: Unit C2 - Sustainability of public finances
G8: ECFIN-Secretariat-C2@ec.europa.eu
C16: FILE DESCRIPTION
C18: Data reported in this file are based on the European Commission (EC) 2024 autumn forecast (AF 2024) and macroeconomic and budgetary projections from the joint EC-EPC Ageing Report 2024 (AR 2024).
C22: This file contains a simplified version of the EC model used to calculate the general governement debt ratio dynamics for EU countries under different scenarios. A detailed description of the EC's general governement debt projections can be found in the "Debt Sustainability Monitor 2023" (DSM, March 2024).
C27: HOW TO USE THIS TOOL TO CALCULATE NEW DEBT PROJECTIONS
C29: This tool can be used to calculate debt projections under different macroeconomic and structural primary balance adjustment assumptions. Debt projections for each scenario will update automatically with changes in the macroeconomic assumptions or the adjustment parameters. The fulfilment of DSA-based criteria, the safeguards and the benchmark will be automatically calculated in the sheet "Criteria results". Formulas are fully visible. To assess the impact of alternative adjustment paths compared with the reference trajectory calculated by the EC or to check its robustness to underlying macroeconomic assumptions, the user can modify the content of key cells in the sheets "Criteria results" and "Input data" (see below). Note that, for a proper functioning of the file, you should make sure that Excel is in "Automatic" computation mode, i.e. in the File menu, Option tab, click on "Formulas", "Calculation Options" and "Automatic".
C31: The spreadsheet is composed of the following elements:
D33: The grey sheet "Criteria results" contains three types of cells identified by different colours:
F34: Cells with a yellow background and a red frame can be modified to see the impact of a different duration or pace of adjustment.
F35: Cells with a white or grey background provide results obtained with the adjustment chosen in the yellow cells. To replicate the Commission's calculations, the underlying formulas should not be modified.
F37: Cells with a pale blue background correspond to the Commission's prior guidance provided to the Member State. Those are hard numbers that do not depend on the adjustment chosen in the file.
D39: The sheet "Criteria results" contains six tables: Table 1 "Adjustment input data": the user can set the duration of the plan (4 years under no extension or 7 years under extension) and the yearly adjustment pace in cells F5 and F6 in yellow. Note that the country cell (F4) cannot be changed.
D40: To the right of Table 1, a message automatically signals whether the chosen adjustment is sufficient to fulfill all the requirements, summarising the results from Tables 2 and 3.
D41: Table 2 "DSA-based criteria" reports whether the chosen adjustment fulfils each of the DSA-based criteria.
D42: Table 3 "Safeguards and benchmark" reports whether (i) the chosen adjustment ensures that the debt sustainability safeguard is met, (ii) the 'deficit benchmark', i.e. the minimum adjustment of 0.5 pp. of GDP as a benchmark when the country is in EDP and/or the deficit exceeds 3% of GDP, is binding, and (iii) the deficit resilience safeguard is binding.
D43: Table 4 "Main fiscal variables" reports the annual adjustment over the adjustment period, in terms of change in SPB (line 19) and net primary expenditure growth (line 20). The table also reports the headline balance, the structural balance and debt (lines 21 to 23). The average annual adjustment is reported in cells G24 (average change in SPB over the 4-year plan period), G25 (average change in SPB over the 4-year or 7-year adjustment period), G26 (average net primary expenditure growth over the plan period) and G27 (average net primary expenditure growth over the adjustment period).
D44: Table 5 "DSA-based adjustment" summarises the key characteristics of the adjustment path that complies with the DSA-based criteria before applying the safeguards and benchmark, for a plan both with and without extension.
D45: Table 6 "Reference trajectory" reports the net expenditure growth and the corresponding annual change in SPB that are consistent with all requirements including the safeguards and benchmark, both without and with extension.
D47: The sheet "Input data" in light blue presents the input data, including fiscal and GDP growth assumptions as well as additional fiscal parameters. Unless stated otherwise below, the user can change all values in this tab.
D48: Coloured cells indicate data sources as follows (this colour-coding holds in the other spreadsheets):
F49: Cells in light grey indicate a Commission forecast (available in the AMECO database)
F50: Cells in light red indicate whether the country is subject to an ongoing excessive deficit procedure (EDP) or whether the Commission's November 2024 report under Art. 126(3) of the Treaty recommends opening an EDP. If neither of these conditions are met, the deficit benchmark is not relevant and therefore not applied.
F51: Cells in light blue indicate values from the Ageing Report 2024
F52: Cells in light orange provide parameters needed to compute the decomposition of government debt according to its maturity structure (i.e. short-term and long-term debt, maturing, rolled-over and non-maturing debt). These are fixed shares which the user cannot change.
F53: Cells in dark orange indicate financial market prices.
D54: Non-coloured parameters in cells C49:C70 were calibrated based on different data sources. The data sources are indicated in the corresponding cells of column E. The last part of the sheet "Input data" (cells C73:G77) provides the parameters measuring the size of the cone of the fanchart that results from the stochastic analysis. For reproducibility reasons, these parameters are kept constant.
C56: The next spreadsheets present the deterministic and stochastic projections. Each deterministic projection provides a single path for debt until 2038 or 2041 under certain assumptions for budgetary, macroeconomic and financial variables, while the outcome of the stochastic projections is a distribution of debt paths resulting from a wide set of shocks. The sheets are grouped in four blocs, identified by their colour coding:
D58: The sheet in blue provides, as a reference, the baseline no-fiscal-policy-change scenario. The background colour coding is the same as in the sheet "Input data".
D60: The sheet in orange presents the scenario that automatically corrects the yearly adjustment path to account for the deficit benchmark and the deficit resillience safeguard. By contrast, the yearly adjustment profile is not automatically adjusted to ensure that the debt sustainability safeguard is met. However, the sheet "Criteria results" indicates whether that safeguard is met.
D62: The sheets in green present the deterministic projections that are used to compute the DSA-based requirements (in the sheet "Criteria results"). They include four scenarios:
D63: · Adjustment scenario without safeguard and benchmark
D64: · Financial stress scenario
D65: · Lower SPB scenario
D66: · Adverse 'r-g' scenario
D68: Each scenario is computed automatically based on the yearly adjustment path set in "Criteria results" (see above).
D70: The sheet in dark green presents the stochastic projections surrounding the adjustment scenario without safeguard and benchmark .
C72: Within the orange sheet and each green sheet, the background of the SPB line has three colours. Each colour corresponds to a specific period of the projections:
E73: Light grey indicates the pre-plan period, corresponding to the EC forecast
E74: Mild grey indicates the period during which the SPB adjusts according to the path set in sheet "Criteria results"
E75: Dark grey indicates the period in which the SPB, net of changes in cost of ageing, remains constant at its value of end of adjustment.
D77: In the sheets associated with the stress-test scenarios, i.e. "Financial stress", "Lower SPB" and "Adverse (r-g)", initial shocks are identified as follows:
E78: All variables that are shocked turn very dark grey.
E79: Additionally, for the lower SPB scenario, the cells get thick black borders in the years when the SPB is gradually reduced.
C81: WHERE ARE THE MAIN RESULTS LOCATED?
C82: Debt projections can be found in line 56 or 57 of each scenario. The corresponding net expenditure growth is located in line 79 or 80 in the baseline and adjustment scenario (and Adj. no safeguard) sheets. The average net expenditure growth over the adjustment period is computed in cell D81 of the sheet "Adjustment scenario". As a reminder, these numbers are also available in Table 4 in "Criteria results".
D84: The 'FASTOP reporting' sheet in violet provides help for preparing reporting tables. It readily provides all the tables envisaged in the guidance notice on the "Information Requirements for the Medium-Term Fiscal-Structural Plans" once the parameters are set in the rest of this file. Note that the probability of a declining debt ratio in table 7c derived from the stochastic simulations is only an approximation since the stochastic analysis is not an integral part of this Excel file. For a precise figure, the simulations need to be run. This sheet is therefore only meant to provide assistance. The figures still need to be thoroughly scrutinised before submitting the tables.

Sheet Criteria results
U2: 4 | V2: 0
D3: Table 1 - Adjustment input data | H3: =IF(OR(AND($G$12="ok",$G$13="ok",$G$14="ok",$G$15="ok",$H$12="ok",$I$12="ok",$L$12<>"Not met"), AND($I$12="ok",$J$12="ok",$J$13="ok",$J$14="ok",$J$15="ok",$L$12<>"Not met")), "OK"&CHAR(10)&"adjustment"&CHAR(10)&"complies with all requirements", "NOT OK"&CHAR(10)&"adjustment does not"&CHAR(10)&"comply with all requirements") -> #NAME? | U3: 7 | V3: 0.02
D4: Country | F4: HU | V4: 0.04
D5: Number of years of adjustment | F5: 4 | V5: 0.06
D6: Annual adjustment (when benchmark not binding) | F6: 0.54 | V6: 0.08
V7: 0.1
V8: 0.12
G9: Table 2 - DSA-based criteria | L9: Table 3 - Safeguards and benchmark | V9: 0.14
L10: Debt sustainability safeguard * | N10: Deficit benchmark ** | P10: Deficit resilience safeguard | V10: 0.16
G11: Criterion 1 (Debt decreasing under deterministic scenarios) | H11: Criterion 2 * (Debt declining with sufficient probability) | I11: Criterion 3 (Deficit below 3% of GDP) | J11: ="Debt below 60% of GDP in T+"&10+F5&" **" -> Debt below 60% of GDP in T+14 ** | L11: Debt declines by 1pp (0.5pp) of GDP on average as long as debt exceeds 90% (60%) of GDP | M11: Average change in debt | N11: 0.5 pp. of GDP adjustment if deficit in previous year > 3% of GDP | O11: Number of years the benchmark applies | P11: 0.40 pp. (0.25 pp.) of GDP adjustment under plan without (with) extension if structural deficit in previous year > 1.5% of GDP | Q11: Number of years the deficit resilience safeguard applies (over the adjustment horizon) | V11: 0.18
D12: Adjustment scenario | G12: =IF(OR('Adjust. no safeguard'!F57>60,'Adjust. no safeguard'!F77<-3),IF(SUM(OFFSET('Adjust. no safeguard'!$F$83,0,$F$5+1,1,10))=0,"ok","Not met"),"") -> ok | H12: =IF(OR('Adjust. no safeguard'!F57>60,'Adjust. no safeguard'!F77<-3),IF($F$5=4,IF(Stochastic!$O$17<Stochastic!$J$17,"ok","Not met"),IF(Stochastic!$R$17<Stochastic!$M$17,"ok","Not met")),"") -> ok | I12: =IF(MIN(OFFSET('Adjust. no safeguard'!$F$77,0,$F$5,1,11))>-3.05,"ok","Not met") -> ok | J12: =IF(OFFSET('Adjust. no safeguard'!$F$57,0,$F$5+10,1,1)<60,"ok","Not met") -> ok | L12: =_xlfn.LET(_xlpm.debtChange,OFFSET('Adjustment scenario'!F58,0,1,1,$F$5), _xlpm.debt6090,OFFSET('Adjustment scenario'!F85,0,1,1,$F$5), _xlpm.debt90,OFFSET('Adjustment scenario'!F84,0,1,1,$F$5), _xlpm.EDP,OFFSET('Adjustment scenario'!F87,0,1,1,$F$5), IF(AND(MAX(_xlpm.debt90)=0,MAX(_xlpm.debt6090)=0),"Debt below 60% of GDP over the adjustment period", IF(MIN(_xlpm.EDP)=1,"Not applicable, reference year is the last year of adjustment", IFERROR(IF(AND(MAX(_xlpm.debt90)=0,MAX(_xlpm.debt6090)=1),IF(AVERAGEIFS(_xlpm.debtChange,_xlpm.debt6090,1,_xlpm.EDP,0)<-0.5,"ok","Not met"), IF(AND(MAX(_xlpm.debt90)=1,MAX(_xlpm.debt6090)=0),IF(AVERAGEIFS(_xlpm.debtChange,_xlpm.EDP,0)<-1,"ok","Not met"), IF(AND(MAX(_xlpm.debt90)=1,MAX(_xlpm.debt6090)=1),IF(AND(AVERAGEIFS(_xlpm.debtChange,_xlpm.debt90,1,_xlpm.EDP,0)<-1,AVERAGEIFS(_xlpm.debtChange,_xlpm.debt6090,1,_xlpm.EDP,0)<-0.5),"ok","Not met")))), "Not applicable, debt below 60% of GDP by EDP correction")))) -> #NAME? | M12: =_xlfn.LET(_xlpm.debtChange,OFFSET('Adjustment scenario'!F58,0,1,1,$F$5), _xlpm.debt60,OFFSET('Adjustment scenario'!F86,0,1,1,$F$5), _xlpm.debt6090,OFFSET('Adjustment scenario'!F85,0,1,1,$F$5), _xlpm.debt90,OFFSET('Adjustment scenario'!F84,0,1,1,$F$5), _xlpm.EDP,OFFSET('Adjustment scenario'!F87,0,1,1,$F$5), IF(AND(MAX(_xlpm.debt90)=0,MAX(_xlpm.debt6090)=0),"Debt below 60% of GDP over the adjustment period", IF(MIN(_xlpm.EDP)=1,"Not applicable, reference year is the last year of adjustment", IFERROR(IF(AND(MAX(_xlpm.debt90)=0,MAX(_xlpm.debt6090)=1),AVERAGEIFS(_xlpm.debtChange,_xlpm.debt60,1,_xlpm.EDP,0), IF(AND(MAX(_xlpm.debt90)=1,MAX(_xlpm.debt6090)=0),AVERAGEIFS(_xlpm.debtChange,_xlpm.EDP,0), IF(AND(MAX(_xlpm.debt90)=1,MAX(_xlpm.debt6090)=1),AVERAGEIFS(_xlpm.debtChange,_xlpm.debt60,1,_xlpm.EDP,0)))), "Not applicable, debt below 60% of GDP by EDP correction")))) -> #NAME? | N12: =IF(AND(O12=0,F6<0.5),"not relevant","ok") -> ok | O12: =IF(AND('Input data'!$F$17=1,F6<0.5),COUNTIFS('Adjustment scenario'!F77:H77,"<="&-3.05),0)+IF(AND(F5=4,J19>0.4,J19>F6),1,COUNTIFS(J19:M19,">" & F6,J19:M19,">"&0.4)) -> 0 | P12: =IF(OR(AND(F5=4,Q12=0,F6<0.4),AND(F5=7,Q12=0,F6<0.25)),"not relevant, (over the adjustment horizon)","ok") -> ok | Q12: =IF(AND('Criteria results'!$F$5=4,'Criteria results'!$F$6<=0.4),COUNTIFS('Adjustment scenario'!G13:J13,0.4,'Adjustment scenario'!F88:I88,0),IF(AND('Criteria results'!$F$5=7,'Criteria results'!$F$6<=0.25),COUNTIFS('Adjustment scenario'!G13:M13,0.25,'Adjustment scenario'!F88:L88,0),0)) -> 0 | V12: 0.2
D13: Financial stress scenario | G13: =IF(OR('Adjustment scenario'!F57>60,'Adjustment scenario'!F77<-3),IF(SUM(OFFSET('Financial stress'!$F$75,0,$F$5+1,1,10))=0,"ok","Not met"),"") -> ok | J13: =IF(OR('Adjustment scenario'!F57>60,'Adjustment scenario'!F77<-3),IF(OFFSET('Financial stress'!$F$56,0,$F$5+10,1,1)<60,"ok","Not met"),"") -> ok | V13: 0.22
D14: Lower SPB scenario | G14: =IF(OR('Adjustment scenario'!F57>60,'Adjustment scenario'!F77<-3),IF(SUM(OFFSET('Lower SPB'!$F$75,0,$F$5+1,1,10))=0,"ok","Not met"),"") -> Not met | J14: =IF(OR('Adjustment scenario'!F57>60,'Adjustment scenario'!F77<-3),IF(OFFSET('Lower SPB'!$F$56,0,$F$5+10,1,1)<60,"ok","Not met"),"") -> ok | V14: 0.24
D15: Adverse r-g scenario | G15: =IF(OR('Adjustment scenario'!F57>60,'Adjustment scenario'!F77<-3),IF(SUM(OFFSET('Adverse (r-g)'!$F$76,0,$F$5+1,1,10))=0,"ok","Not met"),"") -> Not met | J15: =IF(OR('Adjustment scenario'!F57>60,'Adjustment scenario'!F77<-3),IF(OFFSET('Adverse (r-g)'!$F$57,0,$F$5+10,1,1)<60,"ok","Not met"),"") -> ok | V15: 0.26
D16: * The stochastic simulations are provided mainly for information, as the Excel worksheet only allows for an approximation of what is done in the Commission's Stata model. Indeed, in this Excel worksheet, the size of the cone of the fanchart is assumed to be constant over different adjustment paths. In ther Stata model, it is a non linear function of the level of debt, as shocks (in particular interest rate shocks) have different impacts according to the level of debt ratio. ** In case a smaller adjustment than the one implied by criterion 1 and criterion 2 is sufficient to ensure that debt is brought (and/or remains) below 60% of GDP under the adjustment scenario and all deterministic stress tests while ensuring that the criterion 3 is met, then that smaller, 'eased-up' adjustment is chosen. | L16: * The average change in debt is computed from the year before the start of the reference trajectory or the year in which the excessive deficit procedure is projected to be abrogated, whichever occurs last, until the end of the adjustment period. ** The deficit benchmark is applied in terms of change in SPB during the transitory period of 2025-2027 and in terms of change in SB thereafter. | V16: 0.28
G17: Table 4 - Main fiscal variables | V17: 0.3
G18: 2025 | H18: 2026 | I18: 2027 | J18: 2028 | K18: 2029 | L18: 2030 | M18: 2031 | V18: 0.32
D19: Annual adjustment (change in SPB) | G19: ='Adjustment scenario'!G12-'Adjustment scenario'!F12 -> 0.54 | H19: ='Adjustment scenario'!H12-'Adjustment scenario'!G12 -> 0.54 | I19: ='Adjustment scenario'!I12-'Adjustment scenario'!H12 -> 0.54 | J19: ='Adjustment scenario'!J12-'Adjustment scenario'!I12 -> 0.54 | K19: ='Adjustment scenario'!K12-'Adjustment scenario'!J12 -> 0 | L19: ='Adjustment scenario'!L12-'Adjustment scenario'!K12 -> 0 | M19: ='Adjustment scenario'!M12-'Adjustment scenario'!L12 -> 0 | V19: 0.34
D20: Net primary expenditure growth | G20: ='Adjustment scenario'!G79 -> 4.3473229 | H20: ='Adjustment scenario'!H79 -> 3.9515589 | I20: ='Adjustment scenario'!I79 -> 3.8782647 | J20: ='Adjustment scenario'!J79 -> 3.7186626 | K20: ='Adjustment scenario'!K79 -> 4.8725166 | L20: ='Adjustment scenario'!L79 -> 5.0202485 | M20: ='Adjustment scenario'!M79 -> 5.0859394 | V20: 0.36
D21: Headline balance | G21: ='Adjustment scenario'!G77 -> -3.5621614 | H21: ='Adjustment scenario'!H77 -> -2.4665795 | I21: ='Adjustment scenario'!I77 -> -2.0229571 | J21: ='Adjustment scenario'!J77 -> -1.5377055 | K21: ='Adjustment scenario'!K77 -> -1.3886474 | L21: ='Adjustment scenario'!L77 -> -1.2540637 | M21: ='Adjustment scenario'!M77 -> -1.1441947 | V21: 0.38
D22: Structural balance | G22: ='Adjustment scenario'!G78 -> -2.8066042 | H22: ='Adjustment scenario'!H78 -> -2.1796804 | I22: ='Adjustment scenario'!I78 -> -1.6524516 | J22: ='Adjustment scenario'!J78 -> -1.111623 | K22: ='Adjustment scenario'!K78 -> -1.1045924 | L22: ='Adjustment scenario'!L78 -> -1.1120362 | M22: ='Adjustment scenario'!M78 -> -1.1441947 | V22: 0.4
D23: Debt | G23: ='Adjustment scenario'!G57 -> 73.48544 | H23: ='Adjustment scenario'!H57 -> 71.299226 | I23: ='Adjustment scenario'!I57 -> 69.930407 | J23: ='Adjustment scenario'!J57 -> 68.203983 | K23: ='Adjustment scenario'!K57 -> 66.186518 | L23: ='Adjustment scenario'!L57 -> 64.043964 | M23: ='Adjustment scenario'!M57 -> 61.862434 | V23: 0.42
D24: Average annual adjustment over the plan period | G24: =AVERAGE(G19:J19) -> 0.54 | V24: 0.44
D25: Average annual adjustment over the adjustment period | G25: =IF(F5=4,AVERAGE(G19:J19),AVERAGE(G19:M19)) -> 0.54 | V25: 0.46
D26: Average net primary expenditure growth over the plan period | G26: =AVERAGE(G20:J20) -> 3.9739523 | V26: 0.48
D27: Average net primary expenditure growth over the adjustment period | G27: =IF(F5=4,AVERAGE(G20:J20),AVERAGE(G20:M20)) -> 3.9739523 | V27: 0.5
D28: In case of a plan with no extension, both the plan period and the adjustment period last 4 years. In case of a plan with extension, the plan period remains 4 years while the adjustment period lasts 7 years. Morever, in case of extension, if neither the deficit benchmark nor the deficit resilience safeguard are binding, the values in G24 and G25 (and G26 and G27) are the same. However, if the benchmark or the safeguard is binding, the values in those cells can be different. | V28: 0.52
V29: 0.54
G30: Table 5 - DSA-based adjustment * | V30: 0.56
G31: No extension | H31: Extension | V31: 0.58
D32: Number of years of adjustment | G32: 4 | H32: 7 | V32: 0.6
D33: Annual adjustment | G33: 0.7 | H33: 0.44 | V33: 0.62
D34: Probability that debt decreases | G34: 73.52 | H34: 72.809999 | V34: 0.64
D35: * The adjustment in this table does not account for the minimum adjustment of 0.5 pp. of GDP as a benchmark nor for the debt sustainability and deficit resillience safeguards. | V35: 0.66
V36: 0.68
H37: Table 6 - Reference trajectory | V37: 0.7
G38: Average (2025-28) | H38: 2025 | I38: 2026 | J38: 2027 | K38: 2028 | L38: 2029 | M38: 2030 | N38: 2031 | V38: 0.72
D39: Adjustment in a plan without extension | V39: 0.74
D40: Net primary expenditure growth | G40: 3.4713476 | H40: 3.9759682 | I40: 3.3802042 | J40: 3.33191 | K40: 3.1973079 | V40: 0.76
D41: Annual change in SPB | G41: 0.7 | H41: 0.7 | I41: 0.7 | J41: 0.7 | K41: 0.7 | V41: 0.78
D42: Adjustment in a plan with extension | V42: 0.8
D43: Net primary expenditure growth | G43: 4.00517 | H43: 4.4401615 | I43: 3.8443975 | J43: 3.9353614 | K43: 3.8007593 | L43: 3.7262912 | M43: 3.8990231 | N43: 3.9897139 | V43: 0.82
D44: Annual change in SPB | G44: 0.47 | H44: 0.5 | I44: 0.5 | J44: 0.44 | K44: 0.44 | L44: 0.44 | M44: 0.44 | N44: 0.44 | V44: 0.84
V45: 0.86
V46: 0.88
V47: 0.9
V48: 0.92
V49: 0.94
V50: 0.96
V51: 0.98
V52: 1
V53: 1.02
V54: 1.04
V55: 1.06
V56: 1.08
... V82: 1.6

Sheet Input data
B3: Country | C3: HU
B5: Last year before the adjustment | C5: 2024
B6: Last year of adjustment | C6: =C5+'Criteria results'!$F$5 -> 2028
B8: Key assumptions
C9: 2021 | D9: 2022 | E9: 2023 | F9: 2024 | G9: 2025 | H9: 2026 | I9: 2027 | J9: 2028 | K9: 2029 | L9: 2030 | M9: 2031 | N9: 2032 | O9: 2033 | P9: 2034 | Q9: 2035 | R9: 2036 | S9: 2037 | T9: 2038 | U9: 2039 | V9: 2040 | W9: 2041
B10: Fiscal assumptions (% of GDP)
B11: Key fiscal variables (based on the Commission 2024 autumn forecast ("AF 2024") T+2 forecast
B12: Debt | C12: 76.21938 | D12: 73.84293 | E12: 73.438 | F12: 74.041486
B13: Structural primary balance ('+' means 'surplus') | C13: -5.106841 | D13: -4.391969 | E13: -1.706974 | F13: 0.64244146
B14: One-off and other temporary measures | C14: -0.1079972 | D14: 0 | E14: 0 | F14: 0 | G14: 0 | H14: 0 | I14: 0 | J14: 0 | K14: 0 | L14: 0 | M14: 0 | N14: 0 | O14: 0 | P14: 0 | Q14: 0 | R14: 0 | S14: 0 | T14: 0 | U14: 0 | V14: 0 | W14: 0
B15: Stock-flow adjustments (without exchange rate effect) | C15: -0.1371056 | D15: 1.066777 | E15: 2.471388 | F15: 0.243711 | G15: -0.9088278 | H15: -0.250576 | I15: 0 | J15: 0 | K15: 0 | L15: 0 | M15: 0 | N15: 0 | O15: 0 | P15: 0 | Q15: 0 | R15: 0 | S15: 0 | T15: 0 | U15: 0 | V15: 0 | W15: 0
B16: Stock-flow adjustment (total) | C16: -0.0193077 | D16: 3.539191 | E16: 1.717452 | F16: 0.9714689 | G16: -0.3984276 | H16: -0.2505763 | I16: 0 | J16: 0 | K16: 0 | L16: 0 | M16: 0 | N16: 0 | O16: 0 | P16: 0 | Q16: 0 | R16: 0 | S16: 0 | T16: 0 | U16: 0 | V16: 0 | W16: 0
B17: Subject to an excessive deficit procedure (EDP) (0-no/1-yes) | D17: 0 | E17: 0 | F17: 1
B19: Cost of ageing and selected public revenue (based on the Commission-Council 2024 Ageing Report ("AR 2024"))
B20: Total ageing cost (net of taxes on pensions) | C20: =(C21+C22+C23+C24-C25) -> 0 | D20: =(D21+D22+D23+D24-D25) -> 16.0166 | E20: =(E21+E22+E23+E24-E25) -> 16.12175 | F20: =(F21+F22+F23+F24-F25) -> 16.12852 | G20: =(G21+G22+G23+G24-G25) -> 16.01381 | H20: =(H21+H22+H23+H24-H25) -> 15.92993 | I20: =(I21+I22+I23+I24-I25) -> 15.87402 | J20: =(J21+J22+J23+J24-J25) -> 15.87527 | ... W20: =(W21+W22+W23+W24-W25) -> 17.97964
B21: of which: Public pensions expenditure | C21: 0 | D21: 7.73961 | E21: 7.86712 | F21: 7.89282 | G21: 7.79042 | H21: 7.7091 | I21: 7.64957 | J21: 7.64073 | K21: 7.63699 | L21: 7.65466 | M21: 7.696 | N21: 7.75746 | O21: 7.84465 | P21: 7.95741 | Q21: 8.10221 | R21: 8.27487 | S21: 8.45598 | T21: 8.64171 | U21: 8.83856 | V21: 9.04742 | W21: 9.27667
B22: Health care expenditure | C22: 0 | D22: 4.25848 | E22: 4.26197 | F22: 4.27172 | G22: 4.29311 | H22: 4.31251 | I22: 4.33105 | J22: 4.34864 | K22: 4.36339 | L22: 4.3789 | M22: 4.39651 | N22: 4.4114 | O22: 4.42883 | P22: 4.44454 | Q22: 4.46141 | R22: 4.47899 | S22: 4.49627 | T22: 4.51363 | U22: 4.53049 | V22: 4.54811 | W22: 4.57039
B23: Long-term care expenditure | C23: 0 | D23: 0.54632 | E23: 0.55473 | F23: 0.55762 | G23: 0.55987 | H23: 0.56281 | I23: 0.57183 | J23: 0.57813 | K23: 0.58609 | L23: 0.59515 | M23: 0.6043 | N23: 0.61316 | O23: 0.62216 | P23: 0.63245 | Q23: 0.64295 | R23: 0.65212 | S23: 0.6596 | T23: 0.66717 | U23: 0.67515 | V23: 0.68309 | W23: 0.69041
B24: Education & unemployment benefits expenditure | C24: 0 | D24: 3.47219 | E24: 3.43793 | F24: 3.40636 | G24: 3.37041 | H24: 3.34551 | I24: 3.32157 | J24: 3.30777 | K24: 3.30112 | L24: 3.3021 | M24: 3.31313 | N24: 3.32796 | O24: 3.34261 | P24: 3.35719 | Q24: 3.37113 | R24: 3.38353 | S24: 3.39415 | T24: 3.40517 | U24: 3.41745 | V24: 3.43035 | W24: 3.44217
B25: Taxes on pensions | C25: 0 | D25: 0 | E25: 0 | F25: 0 | G25: 0 | H25: 0 | I25: 0 | J25: 0 | K25: 0 | L25: 0 | M25: 0 | N25: 0 | O25: 0 | P25: 0 | Q25: 0 | R25: 0 | S25: 0 | T25: 0 | U25: 0 | V25: 0 | W25: 0
B26: Property income | C26: 0.5353987 | D26: 1.178846 | E26: 2.102853 | F26: 2.07289 | G26: 2.042928 | H26: 2.012965 | I26: 1.983002 | J26: 1.953039 | K26: 1.923076 | L26: 1.893113 | M26: 1.86315 | N26: 1.833187 | O26: 1.803224 | P26: 1.773262 | Q26: 1.743299 | R26: 1.713336 | S26: 1.683373 | T26: 1.65341 | U26: 1.623447 | V26: 1.593484 | W26: 1.563521
B28: Real GDP growth assumptions (based on AF 2024 T+10 projections and AR 2024 projections)
B29: Actual GDP
B30: Growth rate | C30: 7.121139 | D30: 4.260908 | E30: -0.9462205 | F30: 0.584996 | G30: 1.621716 | H30: 3.054951 | I30: 1.70229 | J30: 1.604467 | K30: 1.566761 | L30: 1.78318 | M30: 1.910635 | N30: 1.917179 | O30: 1.834443 | P30: 1.853186 | Q30: 1.822487 | R30: 1.791788 | S30: 1.761082 | T30: 1.707647 | U30: 1.65297 | V30: 1.61876 | W30: 1.601132
B31: Level (billions, national currency) | C31: 133.9938
B32: Potential GDP
B33: Growth rate | C33: 3.162016 | D33: 2.736387 | E33: 1.87314 | F33: 1.38942 | G33: 1.533798 | H33: 1.720744 | I33: 1.709217 | J33: 1.611382 | K33: 1.573681 | L33: 1.78318 | M33: 1.910638 | N33: 1.917176 | O33: 1.834446 | P33: 1.853183 | Q33: 1.822484 | R33: 1.791785 | S33: 1.761086 | T33: 1.70765 | U33: 1.652967 | V33: 1.618756 | W33: 1.601132
B34: Level (billions, national currency) | C34: 132.9781
B36: Interest rates (AF 2024, %)
B37: Nominal implicit interest rate on debt | C37: 3.238231 | D37: 4.417456 | E37: 7.284665 | F37: 7.231643 | G37: 5.674904 | H37: 5.648431
B38: Short-term nominal interest rate | D38: 10.32 | E38: 15.97 | F38: 7.275548 | G38: 5.939488 | H38: 5.742086
B39: Long-term nominal interest rate | D39: 7.57 | E39: 7.51 | F39: 6.52395 | G39: 6.731379 | H39: 6.82931
F40: Bloomberg data, country-specific forward market rates.
B41: Inflation (AF 2024, %)
B42: GDP deflator (national currency) | C42: 6.261158 | D42: 14.22793 | E42: 14.56683 | F42: 7.183265 | G42: 4.066847 | H42: 3.484137
B44: Net primary expenditure growth (AF 2024, %)
B45: Net primary expenditure growth | C45: 0 | D45: 22.282169 | E45: 8.9931862 | F45: 4.6
B47: Additional parameters
E48: Sources
B49: Fiscal multiplier | C49: 0.75 | E49: Carnot, N. and de Castro, F. (2015), “The Discretionary Fiscal Effort: an Assessment of Fiscal Policy and its Output Effect”, European Economy, Economic Papers, No. 543.
B50: Budget balance semi-elasticity | C50: 0.453 | E50: Mourre, G. et al. (2019), "The Semi-Elasticities Underlying the Cyclically-Adjusted Budget Balance: An Update and Further Analysis", European Economy, Discussion Paper, No. 098.
B52: Long-term nominal interest rate (T+10 convergence value) | C52: 6.92618 | E52: Bloomberg data, country-specific forward market rates.
B53: Short-term nominal interest rate (T+10 convergence value) | C53: 6.5021 | E53: Bloomberg data, country-specific forward market rates.
B54: Long-term nominal interest rate (T+30 convergence value) | C54: 5 | E54: DSM 2023
B55: Short-term nominal interest rate (T+30 convergence value) | C55: 2.5 | E55: DSM 2023
B57: Share of short-term debt in total government debt | C57: 0.0847883 | E57: Eurostat, average shares over the 3 last available years.
B58: Share of long-term debt in total government debt | C58: =1-C57 -> 0.9152117 | E58: Eurostat, average shares over the 3 last available years.
B59: Share of long-term debt that matures every year (T+10 convergence value) | C59: 0.07807573 | E59: ECB, country-specific historical average shares over the 6 last available years. For post-programme countries (CY, El , IE and PT), the redemption profile of official loans has been taken into account for the computation of the share of long-term debt that matures every year. For these countries, changing this parameter would not affect debt projections.
B61: GDP deflator (national currency) (T+10 convergence value) | C61: 2.99 | E61: Bloomberg data, inflation swaps.
B62: GDP deflator (national currency) (T+30 convergence value) | C62: 3 | E62: Central bank inflation target
B64: Share of primary expenditure in GDP in 2024 | C64: 43.085492 | E64: AF24
B66: Share of outstanding debt in total debt in 2023 | C66: 0.74843187 | E66: Derived from the model and made consistent with the short-term forecast.
B67: Share of rolled-over long-term debt in 2023 | C67: 0.039773156 | E67: Derived from the model and made consistent with the short-term forecast.
B68: Share of rolled-over short-term debt in 2023 | C68: 0.087578352 | E68: Derived from the model and made consistent with the short-term forecast.
B69: Share of new long-term debt in 2023 | C69: 0.11179496 | E69: Derived from the model and made consistent with the short-term forecast.
B70: Share of new short-term debt in 2023 | C70: 0.012421662 | E70: Derived from the model and made consistent with the short-term forecast.
B72: Stochastic projections: ranges around adjustment scenario
C73: T+1 | D73: T+2 | E73: T+3 | F73: T+4 | G73: T+5
B74: Difference between debt level in 50th and 10th percentiles of the distribution | C74: -9.2076187 | D74: -12.748482 | E74: -15.09272 | F74: -17.353012 | G74: -19.164528
B75: Difference between debt level in 50th and 30th percentiles of the distribution | C75: -3.7122269 | D75: -5.1973953 | E75: -6.2927971 | F75: -7.2161179 | G75: -7.9201393
B76: Difference between debt level in 70th and 50th percentiles of the distribution | C76: 3.8456268 | D76: 5.3306885 | E76: 6.6725349 | F76: 7.75457 | G76: 8.5676231
B77: Difference between debt level in 90th and 50th percentiles of the distribution | C77: 9.5460968 | D77: 13.837753 | E77: 16.688374 | F77: 19.306145 | G77: 21.600536

Sheet Baseline NFPC
B3: Country | C3: ='Input data'!C3 -> HU
B4: Key years
B5: ='Input data'!B5 -> Last year before the adjustment | C5: =+'Input data'!C5 -> 2024
B6: Last year of adjustment | C6: =+C5+'Criteria results'!$F$5 -> 2028
B9: Key assumptions
C10: 2021 | D10: 2022 | E10: 2023 | F10: 2024 | G10: 2025 | H10: 2026 | I10: 2027 | J10: 2028 | K10: 2029 | L10: 2030 | M10: 2031 | N10: 2032 | O10: 2033 | P10: 2034 | Q10: 2035 | R10: 2036 | S10: 2037 | T10: 2038 | U10: 2039 | V10: 2040 | W10: 2041
B11: Fiscal assumptions (% of GDP)
B12: Structural primary balance ('+' means 'surplus') | C12: ='Input data'!C13 -> -5.106841 | D12: ='Input data'!D13 -> -4.391969 | E12: ='Input data'!E13 -> -1.706974 | F12: ='Input data'!F13 -> 0.64244146 | G12: =F12 -> 0.64244146 | H12: =G12 -> 0.64244146 | I12: =H12 -> 0.64244146 | J12: =I12 -> 0.64244146 | K12: =J12 -> 0.64244146 | L12: =K12 -> 0.64244146 | M12: =L12 -> 0.64244146 | N12: =M12 -> 0.64244146 | ... W12: =V12 -> 0.64244146
B13: One-off and other temporary measures | C13: ='Input data'!C14 -> -0.1079972 | D13: ='Input data'!D14 -> 0 | E13: ='Input data'!E14 -> 0 | F13: ='Input data'!F14 -> 0 | G13: ='Input data'!G14 -> 0 | H13: ='Input data'!H14 -> 0 | I13: ='Input data'!I14 -> 0 | J13: ='Input data'!J14 -> 0 | ... W13: ='Input data'!W14 -> 0
B14: Stock flow adjustments (without exchange rate effect) | C14: ='Input data'!C15 -> -0.1371056 | D14: ='Input data'!D15 -> 1.066777 | E14: ='Input data'!E15 -> 2.471388 | F14: ='Input data'!F15 -> 0.243711 | G14: ='Input data'!G15 -> -0.9088278 | H14: ='Input data'!H15 -> -0.250576 | I14: ='Input data'!I15 -> 0 | J14: ='Input data'!J15 -> 0 | ... W14: ='Input data'!W15 -> 0
B16: ='Input data'!B19 -> Cost of ageing and selected public revenue (based on the Commission-Council 2024 Ageing Report ("AR 2024"))
B17: Total ageing cost (net of taxes on pensions) | C17: ='Input data'!C20 -> 0 | D17: ='Input data'!D20 -> 16.0166 | E17: ='Input data'!E20 -> 16.12175 | F17: ='Input data'!F20 -> 16.12852 | G17: ='Input data'!G20 -> 16.01381 | H17: ='Input data'!H20 -> 15.92993 | I17: ='Input data'!I20 -> 15.87402 | J17: ='Input data'!J20 -> 15.87527 | ... W17: ='Input data'!W20 -> 17.97964
B18: ='Input data'!B26 -> Property income | C18: ='Input data'!C26 -> 0.5353987 | D18: ='Input data'!D26 -> 1.178846 | E18: ='Input data'!E26 -> 2.102853 | F18: ='Input data'!F26 -> 2.07289 | G18: ='Input data'!G26 -> 2.042928 | H18: ='Input data'!H26 -> 2.012965 | I18: ='Input data'!I26 -> 1.983002 | ... W18: ='Input data'!W26 -> 1.563521
B20: GDP growth assumptions
B21: Actual GDP (real)
B22: Level | C22: ='Input data'!C31 -> 133.9938 | D22: =C22*(D23/100+1) -> 139.70315 | E22: =D22*(E23/100+1) -> 138.38125 | F22: =E22*(F23/100+1) -> 139.19078 | G22: =F22*(G23/100+1) -> 141.44806 | H22: =G22*(H23/100+1) -> 145.76923 | I22: =H22*(I23/100+1) -> 148.25064 | J22: =I22*(J23/100+1) -> 150.62927 | K22: =J22*(K23/100+1) -> 152.98927 | ... W22: =V22*(W23/100+1) -> 188.86761
B23: Growth rate | C23: =+'Input data'!C30 -> 7.121139 | D23: =+'Input data'!D30 -> 4.260908 | E23: =+'Input data'!E30 -> -0.9462205 | F23: =+'Input data'!F30 -> 0.584996 | G23: =+'Input data'!G30 -> 1.621716 | H23: =+'Input data'!H30 -> 3.054951 | I23: =+'Input data'!I30 -> 1.70229 | J23: =+'Input data'!J30 -> 1.604467 | ... W23: =+'Input data'!W30 -> 1.601132
B25: Potential GDP (real)
B26: Level | C26: ='Input data'!C34 -> 132.9781 | D26: =+C26*(1+'Input data'!D33/100) -> 136.6169 | E26: =+D26*(1+'Input data'!E33/100) -> 139.17592 | F26: =+E26*(1+'Input data'!F33/100) -> 141.10966 | G26: =+F26*(1+'Input data'!G33/100) -> 143.274 | H26: =+G26*(1+'Input data'!H33/100) -> 145.73938 | I26: =+H26*(1+'Input data'!I33/100) -> 148.23038 | J26: =+I26*(1+'Input data'!J33/100) -> 150.61893 | K26: =+J26*(1+'Input data'!K33/100) -> 152.9892 | ... W26: =+V26*(1+'Input data'!W33/100) -> 188.8675
B28: Output gap
B29: Output gap | C29: =100*(C22/C26-1) -> 0.76380998 | D29: =100*(D22/D26-1) -> 2.2590596 | E29: =100*(E22/E26-1) -> -0.5709813 | F29: =100*(F22/F26-1) -> -1.3598515 | G29: =100*(G22/G26-1) -> -1.2744391 | H29: =100*(H22/H26-1) -> 0.020481993 | I29: =100*(I22/I26-1) -> 0.013670006 | J29: =100*(J22/J26-1) -> 0.0068637352 | ... W29: =100*(W22/W26-1) -> 5.637904e-05
B31: Actual GDP (nominal, national currency)
B32: Growth rate | C32: =100*((1+C23/100)*(1+C41/100)-1) -> 13.828163 | D32: =100*((1+D23/100)*(1+D41/100)-1) -> 19.095077 | E32: =100*((1+E23/100)*(1+E41/100)-1) -> 13.482775 | F32: =100*((1+F23/100)*(1+F41/100)-1) -> 7.8102828 | G32: =100*((1+G23/100)*(1+G41/100)-1) -> 5.7545157 | H32: =100*((1+H23/100)*(1+H41/100)-1) -> 6.6455267 | I32: =100*((1+I23/100)*(1+I41/100)-1) -> 5.1829185 | J32: =100*((1+J23/100)*(1+J41/100)-1) -> 5.0189895 | ... W32: =100*((1+W23/100)*(1+W41/100)-1) -> 4.6425619
B34: Interest rate
B35: Nominal implicit interest rate on debt | C35: ='Input data'!C37 -> 3.238231 | D35: ='Input data'!D37 -> 4.417456 | E35: ='Input data'!E37 -> 7.284665 | F35: ='Input data'!F37 -> 7.231643 | G35: ='Input data'!G37 -> 5.674904 | H35: ='Input data'!H37 -> 5.648431 | I35: =I96 -> 5.773885 | J35: =J96 -> 5.8928417 | K35: =K96 -> 6.002884 | L35: =L96 -> 6.1046284 | M35: =M96 -> 6.1987976 | N35: =N96 -> 6.2860989 | O35: =O96 -> 6.3670321 | P35: =P96 -> 6.4420993 | ... W35: =W96 -> 6.3394094
B36: Long-term interest rate | E36: ='Input data'!E39 -> 7.51 | F36: ='Input data'!F39 -> 6.52395 | G36: ='Input data'!G39 -> 6.731379 | H36: ='Input data'!H39 -> 6.82931 | I36: =H36+($P$36-$H$36)/($P$10-$H$10) -> 6.8414188 | J36: =I36+($P$36-$H$36)/($P$10-$H$10) -> 6.8535275 | K36: =J36+($P$36-$H$36)/($P$10-$H$10) -> 6.8656362 | L36: =K36+($P$36-$H$36)/($P$10-$H$10) -> 6.877745 | M36: =L36+($P$36-$H$36)/($P$10-$H$10) -> 6.8898537 | N36: =M36+($P$36-$H$36)/($P$10-$H$10) -> 6.9019625 | O36: =N36+($P$36-$H$36)/($P$10-$H$10) -> 6.9140712 | P36: ='Input data'!$C$52 -> 6.92618 | Q36: =$P$36+('Input data'!$C$54-'Input data'!$C$52)/20*(Q$10-$P$10) -> 6.829871 | R36: =$P$36+('Input data'!$C$54-'Input data'!$C$52)/20*(R$10-$P$10) -> 6.733562 | S36: =$P$36+('Input data'!$C$54-'Input data'!$C$52)/20*(S$10-$P$10) -> 6.637253 | T36: =$P$36+('Input data'!$C$54-'Input data'!$C$52)/20*(T$10-$P$10) -> 6.540944 | U36: =$P$36+('Input data'!$C$54-'Input data'!$C$52)/20*(U$10-$P$10) -> 6.444635 | V36: =$P$36+('Input data'!$C$54-'Input data'!$C$52)/20*(V$10-$P$10) -> 6.348326 | W36: =$P$36+('Input data'!$C$54-'Input data'!$C$52)/20*(W$10-$P$10) -> 6.252017
B37: Short-term interest rate | E37: ='Input data'!E$38 -> 15.97 | F37: ='Input data'!F$38 -> 7.275548 | G37: ='Input data'!G$38 -> 5.939488 | H37: ='Input data'!H$38 -> 5.742086 | I37: =H37+($P$37-$H$37)/($P$10-$H$10) -> 5.8370877 | J37: =I37+($P$37-$H$37)/($P$10-$H$10) -> 5.9320895 | K37: =J37+($P$37-$H$37)/($P$10-$H$10) -> 6.0270912 | L37: =K37+($P$37-$H$37)/($P$10-$H$10) -> 6.122093 | M37: =L37+($P$37-$H$37)/($P$10-$H$10) -> 6.2170947 | N37: =M37+($P$37-$H$37)/($P$10-$H$10) -> 6.3120965 | O37: =N37+($P$37-$H$37)/($P$10-$H$10) -> 6.4070982 | P37: ='Input data'!$C$53 -> 6.5021 | Q37: =$P$37+('Input data'!$C$55-'Input data'!$C$53)/20*(Q$10-$P$10) -> 6.301995 | R37: =$P$37+('Input data'!$C$55-'Input data'!$C$53)/20*(R$10-$P$10) -> 6.10189 | S37: =$P$37+('Input data'!$C$55-'Input data'!$C$53)/20*(S$10-$P$10) -> 5.901785 | T37: =$P$37+('Input data'!$C$55-'Input data'!$C$53)/20*(T$10-$P$10) -> 5.70168 | U37: =$P$37+('Input data'!$C$55-'Input data'!$C$53)/20*(U$10-$P$10) -> 5.501575 | V37: =$P$37+('Input data'!$C$55-'Input data'!$C$53)/20*(V$10-$P$10) -> 5.30147 | W37: =$P$37+('Input data'!$C$55-'Input data'!$C$53)/20*(W$10-$P$10) -> 5.101365
B38: Share of long-term debt that matures every year | C38: 0.07935879 | D38: 0.06020197 | E38: 0.05046041 | F38: 0.06743385 | G38: =IF(OR($C$3="EL",$C$3="CY",$C$3="IE",$C$3="PT"),VLOOKUP($C$3,$B$110:$T$114,MATCH(G$10,$B$110:$T$110,0),0),$F$38+('Input data'!$C$59-$F$38)/($P$10-$F$10)*(G10-$F$10)) -> 0.068498038 | H38: =IF(OR($C$3="EL",$C$3="CY",$C$3="IE",$C$3="PT"),VLOOKUP($C$3,$B$110:$T$114,MATCH(H$10,$B$110:$T$110,0),0),$F$38+('Input data'!$C$59-$F$38)/($P$10-$F$10)*(H10-$F$10)) -> 0.069562226 | I38: =IF(OR($C$3="EL",$C$3="CY",$C$3="IE",$C$3="PT"),VLOOKUP($C$3,$B$110:$T$114,MATCH(I$10,$B$110:$T$110,0),0),$F$38+('Input data'!$C$59-$F$38)/($P$10-$F$10)*(I10-$F$10)) -> 0.070626414 | J38: =IF(OR($C$3="EL",$C$3="CY",$C$3="IE",$C$3="PT"),VLOOKUP($C$3,$B$110:$T$114,MATCH(J$10,$B$110:$T$110,0),0),$F$38+('Input data'!$C$59-$F$38)/($P$10-$F$10)*(J10-$F$10)) -> 0.071690602 | K38: =IF(OR($C$3="EL",$C$3="CY",$C$3="IE",$C$3="PT"),VLOOKUP($C$3,$B$110:$T$114,MATCH(K$10,$B$110:$T$110,0),0),$F$38+('Input data'!$C$59-$F$38)/($P$10-$F$10)*(K10-$F$10)) -> 0.07275479 | L38: =IF(OR($C$3="EL",$C$3="CY",$C$3="IE",$C$3="PT"),VLOOKUP($C$3,$B$110:$T$114,MATCH(L$10,$B$110:$T$110,0),0),$F$38+('Input data'!$C$59-$F$38)/($P$10-$F$10)*(L10-$F$10)) -> 0.073818978 | M38: =IF(OR($C$3="EL",$C$3="CY",$C$3="IE",$C$3="PT"),VLOOKUP($C$3,$B$110:$T$114,MATCH(M$10,$B$110:$T$110,0),0),$F$38+('Input data'!$C$59-$F$38)/($P$10-$F$10)*(M10-$F$10)) -> 0.074883166 | N38: =IF(OR($C$3="EL",$C$3="CY",$C$3="IE",$C$3="PT"),VLOOKUP($C$3,$B$110:$T$114,MATCH(N$10,$B$110:$T$110,0),0),$F$38+('Input data'!$C$59-$F$38)/($P$10-$F$10)*(N10-$F$10)) -> 0.075947354 | O38: =IF(OR($C$3="EL",$C$3="CY",$C$3="IE",$C$3="PT"),VLOOKUP($C$3,$B$110:$T$114,MATCH(O$10,$B$110:$T$110,0),0),$F$38+('Input data'!$C$59-$F$38)/($P$10-$F$10)*(O10-$F$10)) -> 0.077011542 | P38: =IF(OR($C$3="EL",$C$3="CY",$C$3="IE",$C$3="PT"),VLOOKUP($C$3,$B$110:$T$114,MATCH(P$10,$B$110:$T$110,0),0),'Input data'!$C$59) -> 0.07807573 | Q38: =IF(OR($C$3="EL",$C$3="CY",$C$3="IE",$C$3="PT"),VLOOKUP($C$3,$B$110:$T$114,MATCH(Q$10,$B$110:$T$110,0),0),'Input data'!$C$59) -> 0.07807573 | R38: =IF(OR($C$3="EL",$C$3="CY",$C$3="IE",$C$3="PT"),VLOOKUP($C$3,$B$110:$T$114,MATCH(R$10,$B$110:$T$110,0),0),'Input data'!$C$59) -> 0.07807573 | S38: =IF(OR($C$3="EL",$C$3="CY",$C$3="IE",$C$3="PT"),VLOOKUP($C$3,$B$110:$T$114,MATCH(S$10,$B$110:$T$110,0),0),'Input data'!$C$59) -> 0.07807573 | T38: =IF(OR($C$3="EL",$C$3="CY",$C$3="IE",$C$3="PT"),VLOOKUP($C$3,$B$110:$T$114,MATCH(T$10,$B$110:$T$110,0),0),'Input data'!$C$59) -> 0.07807573 | U38: =IF(OR($C$3="EL",$C$3="CY",$C$3="IE",$C$3="PT"),VLOOKUP($C$3,$B$110:$W$114,MATCH(U$10,$B$110:$W$110,0),0),'Input data'!$C$59) -> 0.07807573 | V38: =IF(OR($C$3="EL",$C$3="CY",$C$3="IE",$C$3="PT"),VLOOKUP($C$3,$B$110:$W$114,MATCH(V$10,$B$110:$W$110,0),0),'Input data'!$C$59) -> 0.07807573 | W38: =IF(OR($C$3="EL",$C$3="CY",$C$3="IE",$C$3="PT"),VLOOKUP($C$3,$B$110:$W$114,MATCH(W$10,$B$110:$W$110,0),0),'Input data'!$C$59) -> 0.07807573
B40: Inflation and exchange rate
B41: GDP deflator (national currency) | C41: ='Input data'!C42 -> 6.261158 | D41: ='Input data'!D42 -> 14.22793 | E41: ='Input data'!E42 -> 14.56683 | F41: ='Input data'!F42 -> 7.183265 | G41: ='Input data'!G42 -> 4.066847 | H41: ='Input data'!H42 -> 3.484137 | I41: =$H$41+($P$41-$H$41)/($P$10-$H$10)*(I10-$H$10) -> 3.4223699 | J41: =$H$41+($P$41-$H$41)/($P$10-$H$10)*(J10-$H$10) -> 3.3606027 | K41: =$H$41+($P$41-$H$41)/($P$10-$H$10)*(K10-$H$10) -> 3.2988356 | L41: =$H$41+($P$41-$H$41)/($P$10-$H$10)*(L10-$H$10) -> 3.2370685 | M41: =$H$41+($P$41-$H$41)/($P$10-$H$10)*(M10-$H$10) -> 3.1753014 | N41: =$H$41+($P$41-$H$41)/($P$10-$H$10)*(N10-$H$10) -> 3.1135343 | O41: =$H$41+($P$41-$H$41)/($P$10-$H$10)*(O10-$H$10) -> 3.0517671 | P41: ='Input data'!$C$61 -> 2.99 | Q41: =$P$41+('Input data'!$C$62-'Input data'!$C$61)/20*(Q$10-$P$10) -> 2.9905 | R41: =$P$41+('Input data'!$C$62-'Input data'!$C$61)/20*(R$10-$P$10) -> 2.991 | S41: =$P$41+('Input data'!$C$62-'Input data'!$C$61)/20*(S$10-$P$10) -> 2.9915 | T41: =$P$41+('Input data'!$C$62-'Input data'!$C$61)/20*(T$10-$P$10) -> 2.992 | U41: =$P$41+('Input data'!$C$62-'Input data'!$C$61)/20*(U$10-$P$10) -> 2.9925 | V41: =$P$41+('Input data'!$C$62-'Input data'!$C$61)/20*(V$10-$P$10) -> 2.993 | W41: =$P$41+('Input data'!$C$62-'Input data'!$C$61)/20*(W$10-$P$10) -> 2.9935
B42: Exchange rate composite change (weighted by share of debt in each currency) | C42: 1.001704 | D42: 1.038632 | E42: 0.9884134 | F42: 1.010684 | G42: 1.007245 | H42: 1 | I42: 1 | J42: 1 | K42: 1 | L42: 1 | M42: 1 | N42: 1 | O42: 1 | P42: 1 | Q42: 1 | R42: 1 | S42: 1 | T42: 1 | U42: 1 | V42: 1 | W42: 1
B44: Intermediate calculations (growth rate equation)
B46: Fiscal multiplier | C46: ='Input data'!C49 -> 0.75
B47: Budget balance semi-elasticity | C47: ='Input data'!C50 -> 0.453
B49: Auxiliary variable to control the closure of the output gap | D49: =IF(AND(ABS((D12-C12)-('Input data'!D13-'Input data'!C13))>0.0001,ABS(D12-C12)>0.0001,D$10>$C$5),4,IF(C49=4,3,IF(C49=3,2,IF(C49=2,1,0)))) -> 0 | E49: =IF(AND(ABS((E12-D12)-('Input data'!E13-'Input data'!D13))>0.0001,ABS(E12-D12)>0.0001,E$10>$C$5),4,IF(D49=4,3,IF(D49=3,2,IF(D49=2,1,0)))) -> 0 | F49: =IF(AND(ABS((F12-E12)-('Input data'!F13-'Input data'!E13))>0.0001,ABS(F12-E12)>0.0001,F$10>$C$5),4,IF(E49=4,3,IF(E49=3,2,IF(E49=2,1,0)))) -> 0 | G49: =IF(AND(ABS(G12-F12)>0.0001,G$10>$C$5),4,IF(F49=4,3,IF(F49=3,2,IF(F49=2,1,0)))) -> 0 | H49: =IF(AND(ABS(H12-G12)>0.0001,H$10>$C$5),4,IF(G49=4,3,IF(G49=3,2,IF(G49=2,1,0)))) -> 0 | I49: =IF(AND(ABS(I12-H12)>0.0001,I$10>$C$5),4,IF(H49=4,3,IF(H49=3,2,IF(H49=2,1,0)))) -> 0 | J49: =IF(AND(ABS(J12-I12)>0.0001,J$10>$C$5),4,IF(I49=4,3,IF(I49=3,2,IF(I49=2,1,0)))) -> 0 | K49: =IF(AND(ABS(K12-J12)>0.0001,K$10>$C$5),4,IF(J49=4,3,IF(J49=3,2,IF(J49=2,1,0)))) -> 0 | L49: =IF(AND(ABS(L12-K12)>0.0001,L$10>$C$5),4,IF(K49=4,3,IF(K49=3,2,IF(K49=2,1,0)))) -> 0 | M49: =IF(AND(ABS(M12-L12)>0.0001,M$10>$C$5),4,IF(L49=4,3,IF(L49=3,2,IF(L49=2,1,0)))) -> 0 | N49: =IF(AND(ABS(N12-M12)>0.0001,N$10>$C$5),4,IF(M49=4,3,IF(M49=3,2,IF(M49=2,1,0)))) -> 0 | ... W49: =IF(AND(ABS(W12-V12)>0.0001,W$10>$C$5),4,IF(V49=4,3,IF(V49=3,2,IF(V49=2,1,0)))) -> 0
B50: OG intermediate auxiliary value | D50: =IF(C49=4,2/3*C29,IF(C49=3,1/3*B29,0)) -> 0 | E50: =IF(D49=4,2/3*D29,IF(D49=3,1/3*C29,0)) -> 0 | F50: =IF(E49=4,2/3*E29,IF(E49=3,1/3*D29,0)) -> 0 | G50: =IF(F49=4,2/3*F29,IF(F49=3,1/3*E29,0)) -> 0 | H50: =IF(G49=4,2/3*G29,IF(G49=3,1/3*F29,0)) -> 0 | I50: =IF(H49=4,2/3*H29,IF(H49=3,1/3*G29,0)) -> 0 | J50: =IF(I49=4,2/3*I29,IF(I49=3,1/3*H29,0)) -> 0 | K50: =IF(J49=4,2/3*J29,IF(J49=3,1/3*I29,0)) -> 0 | ... W50: =IF(V49=4,2/3*V29,IF(V49=3,1/3*U29,0)) -> 0
B51: GDP intermediate growth rate - only feedback effect and no closure of the OG | D51: ='Input data'!D30-$C$46*((D12-C12)-('Input data'!D13-'Input data'!C13)) -> 4.260908 | E51: ='Input data'!E30-$C$46*((E12-D12)-('Input data'!E13-'Input data'!D13)) -> -0.9462205 | F51: ='Input data'!F30-$C$46*((F12-E12)-('Input data'!F13-'Input data'!E13)) -> 0.584996 | G51: ='Input data'!G30-$C$46*((G12-F12)-('Input data'!G13-'Input data'!F13)) -> 1.1398849 | H51: ='Input data'!H30-$C$46*((H12-G12)) -> 3.054951 | I51: ='Input data'!I30-$C$46*((I12-H12)) -> 1.70229 | J51: ='Input data'!J30-$C$46*((J12-I12)) -> 1.604467 | K51: ='Input data'!K30-$C$46*((K12-J12)) -> 1.566761 | L51: ='Input data'!L30-$C$46*((L12-K12)) -> 1.78318 | M51: ='Input data'!M30-$C$46*((M12-L12)) -> 1.910635 | N51: ='Input data'!N30-$C$46*((N12-M12)) -> 1.917179 | O51: ='Input data'!O30-$C$46*((O12-N12)) -> 1.834443 | ... W51: ='Input data'!W30-$C$46*((W12-V12)) -> 1.601132
B53: Debt projections
C55: 2021 | D55: 2022 | E55: 2023 | F55: 2024 | G55: 2025 | H55: 2026 | I55: 2027 | J55: 2028 | K55: 2029 | L55: 2030 | M55: 2031 | N55: 2032 | O55: 2033 | P55: 2034 | Q55: 2035 | R55: 2036 | S55: 2037 | T55: 2038 | U55: 2039 | V55: 2040 | W55: 2041
B56: Gross debt | C56: =+'Input data'!C12 -> 76.21938 | D56: =+C56+D57 -> 73.842909 | E56: =+D56+E57 -> 73.437974 | F56: =+E56+F57 -> 74.041486 | G56: =+F56+G57 -> 73.466416 | H56: =+G56+H57 -> 71.738571 | I56: =+H56+I57 -> 71.328386 | J56: =+I56+J57 -> 71.142952 | K56: =+J56+K57 -> 71.145504 | ... W56: =+V56+W57 -> 88.591971
B57: Change in debt (-1+2+3) | D57: =-D58+D66+D71 -> -2.376471 | E57: =-E58+E66+E71 -> -0.40493547 | F57: =-F58+F66+F71 -> 0.60351226 | G57: =-G58+G66+G71 -> -0.57506998 | H57: =-H58+H66+H71 -> -1.7278445 | I57: =-I58+I66+I71 -> -0.41018539 | J57: =-J58+J66+J71 -> -0.18543359 | K57: =-K58+K66+K71 -> 0.0025516631 | ... W57: =-W58+W66+W71 -> 3.1042611
B58: (1) Primary balance (1.1 + 1.2 - 1.3 -1.4 -1.5 - 1.6 -1.7) | D58: =D59+D60-D61-D62-D63-D64-D65 -> -3.368615 | E58: =E59+E60-E61-E62-E63-E64-E65 -> -1.9656285 | F58: =F59+F60-F61-F62-F63-F64-F65 -> 0.026428741 | G58: =G59+G60-G61-G62-G63-G64-G65 -> 0.14986855 | H58: =H59+H60-H61-H62-H63-H64-H65 -> 0.7903848 | I58: =I59+I60-I61-I62-I63-I64-I65 -> 0.81324597 | J58: =J59+J60-J61-J62-J63-J64-J65 -> 0.77894973 | K58: =K59+K60-K61-K62-K63-K64-K65 -> 0.73358032 | ... W58: =W59+W60-W61-W62-W63-W64-W65 -> -1.718022
B59: (1.1) Structural primary balance (before ageing cost) | D59: =D12 -> -4.391969 | E59: =E12 -> -1.706974 | F59: =F12 -> 0.64244146 | G59: =IF(G12="",F59,G12) -> 0.64244146 | H59: =IF(H12="",G59,H12) -> 0.64244146 | I59: =IF(I12="",H59,I12) -> 0.64244146 | J59: =IF(J12="",I59,J12) -> 0.64244146 | K59: =IF(K12="",J59,K12) -> 0.64244146 | L59: =IF(L12="",K59,L12) -> 0.64244146 | M59: =IF(M12="",L59,M12) -> 0.64244146 | N59: =IF(N12="",M59,N12) -> 0.64244146 | ... W59: =IF(W12="",V59,W12) -> 0.64244146
B60: (1.2) Cumulated budgetary effort (in terms of primary balance) | D60: 0 | E60: 0 | F60: 0 | G60: 0 | H60: 0 | I60: 0 | J60: 0 | K60: 0 | L60: 0 | M60: 0 | N60: 0 | O60: 0 | P60: 0 | Q60: 0 | R60: 0 | S60: 0 | T60: 0 | U60: 0 | V60: 0 | W60: 0
B61: (1.3) Cyclical component | D61: =-$C$47*D29 -> -1.023354 | E61: =-$C$47*E29 -> 0.25865453 | F61: =-$C$47*F29 -> 0.61601271 | G61: =-$C$47*G29 -> 0.5773209 | H61: =-$C$47*H29 -> -0.0092783427 | I61: =-$C$47*I29 -> -0.0061925125 | J61: =-$C$47*J29 -> -0.0031092721 | K61: =-$C$47*K29 -> -2.2867068e-05 | ... W61: =-$C$47*W29 -> -2.5539705e-05
B62: (1.4) One-off and other temporary measures | D62: =-D13 -> 0 | E62: =-E13 -> 0 | F62: =-F13 -> 0 | G62: =-G13 -> 0 | H62: =-H13 -> 0 | I62: =-I13 -> 0 | J62: =-J13 -> 0 | K62: =-K13 -> 0 | ... W62: =-W13 -> 0
B63: (1.5) Cost of ageing | D63: =IF(D$55<=$C$5,0,HLOOKUP(D$55,'Input data'!$C$9:$BB$26,12,FALSE)-HLOOKUP($C$5,'Input data'!$C$9:$BB$26,12,FALSE)) -> 0 | E63: =IF(E$55<=$C$5,0,HLOOKUP(E$55,'Input data'!$C$9:$BB$26,12,FALSE)-HLOOKUP($C$5,'Input data'!$C$9:$BB$26,12,FALSE)) -> 0 | F63: =IF(F$55<=$C$5,0,HLOOKUP(F$55,'Input data'!$C$9:$BB$26,12,FALSE)-HLOOKUP($C$5,'Input data'!$C$9:$BB$26,12,FALSE)) -> 0 | G63: =IF(G$55<=$C$5,0,HLOOKUP(G$55,'Input data'!$C$9:$BB$26,12,FALSE)-HLOOKUP($C$5,'Input data'!$C$9:$BB$26,12,FALSE)) -> -0.11471 | H63: =IF(H$55<=$C$5,0,HLOOKUP(H$55,'Input data'!$C$9:$BB$26,12,FALSE)-HLOOKUP($C$5,'Input data'!$C$9:$BB$26,12,FALSE)) -> -0.19859 | I63: =IF(I$55<=$C$5,0,HLOOKUP(I$55,'Input data'!$C$9:$BB$26,12,FALSE)-HLOOKUP($C$5,'Input data'!$C$9:$BB$26,12,FALSE)) -> -0.2545 | J63: =IF(J$55<=$C$5,0,HLOOKUP(J$55,'Input data'!$C$9:$BB$26,12,FALSE)-HLOOKUP($C$5,'Input data'!$C$9:$BB$26,12,FALSE)) -> -0.25325 | K63: =IF(K$55<=$C$5,0,HLOOKUP(K$55,'Input data'!$C$9:$BB$26,12,FALSE)-HLOOKUP($C$5,'Input data'!$C$9:$BB$26,12,FALSE)) -> -0.24093 | ... W63: =IF(W$55<=$C$5,0,HLOOKUP(W$55,'Input data'!$C$9:$BB$26,12,FALSE)-HLOOKUP($C$5,'Input data'!$C$9:$BB$26,12,FALSE)) -> 1.85112
B64: (1.6) Property incomes | D64: =IF(D$55<=$C$5,0,-HLOOKUP(D$55,'Input data'!$C$9:$BB$26,18,FALSE)+HLOOKUP($C$5,'Input data'!$C$9:$BB$26,18,FALSE)) -> 0 | E64: =IF(E$55<=$C$5,0,-HLOOKUP(E$55,'Input data'!$C$9:$BB$26,18,FALSE)+HLOOKUP($C$5,'Input data'!$C$9:$BB$26,18,FALSE)) -> 0 | F64: =IF(F$55<=$C$5,0,-HLOOKUP(F$55,'Input data'!$C$9:$BB$26,18,FALSE)+HLOOKUP($C$5,'Input data'!$C$9:$BB$26,18,FALSE)) -> 0 | G64: =IF(G$55<=$C$5,0,-HLOOKUP(G$55,'Input data'!$C$9:$BB$26,18,FALSE)+HLOOKUP($C$5,'Input data'!$C$9:$BB$26,18,FALSE)) -> 0.029962 | H64: =IF(H$55<=$C$5,0,-HLOOKUP(H$55,'Input data'!$C$9:$BB$26,18,FALSE)+HLOOKUP($C$5,'Input data'!$C$9:$BB$26,18,FALSE)) -> 0.059925 | I64: =IF(I$55<=$C$5,0,-HLOOKUP(I$55,'Input data'!$C$9:$BB$26,18,FALSE)+HLOOKUP($C$5,'Input data'!$C$9:$BB$26,18,FALSE)) -> 0.089888 | J64: =IF(J$55<=$C$5,0,-HLOOKUP(J$55,'Input data'!$C$9:$BB$26,18,FALSE)+HLOOKUP($C$5,'Input data'!$C$9:$BB$26,18,FALSE)) -> 0.119851 | K64: =IF(K$55<=$C$5,0,-HLOOKUP(K$55,'Input data'!$C$9:$BB$26,18,FALSE)+HLOOKUP($C$5,'Input data'!$C$9:$BB$26,18,FALSE)) -> 0.149814 | ... W64: =IF(W$55<=$C$5,0,-HLOOKUP(W$55,'Input data'!$C$9:$BB$26,18,FALSE)+HLOOKUP($C$5,'Input data'!$C$9:$BB$26,18,FALSE)) -> 0.509369
B65: (1.7) Revenues | D65: 0 | E65: 0 | F65: 0 | G65: 0 | H65: 0 | I65: 0 | J65: 0 | K65: 0 | L65: 0 | M65: 0 | N65: 0 | O65: 0 | P65: 0 | Q65: 0 | R65: 0 | S65: 0 | T65: 0 | U65: 0 | V65: 0 | W65: 0
B66: (2) Snowball effect (2.1 + 2.2 + 2.3) | D66: =SUM(D67:D70) -> -9.284277 | E66: =SUM(E67:E70) -> -4.088016 | F66: =SUM(F67:F70) -> -0.3415279 | G66: =SUM(G67:G70) -> -0.026773823 | H66: =SUM(H67:H70) -> -0.68688343 | I66: =SUM(I67:I70) -> 0.40306058 | J66: =SUM(J67:J70) -> 0.59351614 | K66: =SUM(K67:K70) -> 0.73613199 | ... W66: =SUM(W67:W70) -> 1.3862391
B67: (2.1) Interest expenditure | D67: =C56*D35/100*(1/(1+D32/100)) -> 2.8271173 | E67: =D56*E35/100*(1/(1+E32/100)) -> 4.7401102 | F67: =E56*F35/100*(1/(1+F32/100)) -> 4.9260348 | G67: =F56*G35/100*(1/(1+G32/100)) -> 3.9731478 | H67: =G56*H35/100*(1/(1+H32/100)) -> 3.8911147 | I67: =H56*I35/100*(1/(1+I32/100)) -> 3.9379993 | J67: =I56*J35/100*(1/(1+J32/100)) -> 4.0023894 | K67: =J56*K35/100*(1/(1+K32/100)) -> 4.0704723 | ... W67: =V56*W35/100*(1/(1+W32/100)) -> 5.1789786
B68: (2.2) Growth effect | D68: =-C56*(D23/100)*(1/(1+D32/100)) -> -2.7269286 | E68: =-D56*(E23/100)*(1/(1+E32/100)) -> 0.6157029 | F68: =-E56*(F23/100)*(1/(1+F32/100)) -> -0.3984863 | G68: =-F56*(G23/100)*(1/(1+G32/100)) -> -1.1354055 | H68: =-G56*(H23/100)*(1/(1+H32/100)) -> -2.1045074 | I68: =-H56*(I23/100)*(1/(1+I32/100)) -> -1.1610236 | J68: =-I56*(J23/100)*(1/(1+J32/100)) -> -1.0897462 | K68: =-J56*(K23/100)*(1/(1+K32/100)) -> -1.0623989 | ... W68: =-V56*(W23/100)*(1/(1+W32/100)) -> -1.3080443
B69: (2.3) Inflation effect | D69: =-C56*D41/100*(1/(1+D41/100)) -> -9.4936852 | E69: =-D56*E41/100*(1/(1+E41/100)) -> -9.3889052 | F69: =-E56*F41/100*(1/(1+F41/100)) -> -4.9217051 | G69: =-F56*G41/100*(1/(1+G41/100)) -> -2.8934805 | H69: =-G56*H41/100*(1/(1+H41/100)) -> -2.4734908 | I69: =-H56*I41/100*(1/(1+I41/100)) -> -2.3739151 | J69: =-I56*J41/100*(1/(1+J41/100)) -> -2.3191271 | K69: =-J56*K41/100*(1/(1+K41/100)) -> -2.2719414 | ... W69: =-V56*W41/100*(1/(1+W41/100)) -> -2.4846952
B70: (2.4) Exchange rate effect linked to the interest rate | D70: 0.10921937 | E70: -0.05492389 | F70: 0.052628707 | G70: 0.028964404 | H70: 0 | I70: 0 | J70: 0 | K70: 0 | L70: 0 | M70: 0 | N70: 0 | O70: 0 | P70: 0 | Q70: 0 | R70: 0 | S70: 0 | T70: 0 | U70: 0 | V70: 0 | W70: 0
B71: (3 ) Stock flow adjustments (3.1 + 3.2) | D71: ='Input data'!D16 -> 3.539191 | E71: ='Input data'!E16 -> 1.717452 | F71: ='Input data'!F16 -> 0.9714689 | G71: ='Input data'!G16 -> -0.3984276 | H71: ='Input data'!H16 -> -0.2505763 | I71: ='Input data'!I16 -> 0 | J71: ='Input data'!J16 -> 0 | K71: ='Input data'!K16 -> 0 | ... W71: ='Input data'!W16 -> 0
B72: (3.1) Base | D72: =D14 -> 1.066777 | E72: =E14 -> 2.471388 | F72: =F14 -> 0.243711 | G72: =G14 -> -0.9088278 | H72: =H14 -> -0.250576 | I72: =I14 -> 0 | J72: =J14 -> 0 | K72: =K14 -> 0 | ... W72: =W14 -> 0
B73: (3.2) Adjustment due to the exchange rate effect linked to debt value | D73: =+D71-D72 -> 2.472414 | E73: =+E71-E72 -> -0.753936 | F73: =+F71-F72 -> 0.7277579 | G73: =+G71-G72 -> 0.5104002 | H73: =+H71-H72 -> -3e-07 | I73: =+I71-I72 -> 0 | J73: =+J71-J72 -> 0 | K73: =+K71-K72 -> 0 | ... W73: =+W71-W72 -> 0
B75: Other budgetary variables
B76: Headline balance | D76: =D58-D67 -> -6.1957323 | E76: =E58-E67 -> -6.7057387 | F76: =F58-F67 -> -4.8996061 | G76: =G58-G67 -> -3.8232793 | H76: =H58-H67 -> -3.1007299 | I76: =I58-I67 -> -3.1247533 | J76: =J58-J67 -> -3.2234396 | K76: =K58-K67 -> -3.336892 | ... W76: =W58-W67 -> -6.8970006
B77: Structural balance | D77: =D59-D67-D63-D64-D65 -> -7.2190863 | E77: =E59-E67-E63-E64-E65 -> -6.4470842 | F77: =F59-F67-F63-F64-F65 -> -4.2835934 | G77: =G59-G67-G63-G64-G65 -> -3.2459584 | H77: =H59-H67-H63-H64-H65 -> -3.1100083 | I77: =I59-I67-I63-I64-I65 -> -3.1309458 | J77: =J59-J67-J63-J64-J65 -> -3.2265489 | K77: =K59-K67-K63-K64-K65 -> -3.3369149 | ... W77: =W59-W67-W63-W64-W65 -> -6.8970262
B78: Net expenditure growth | D78: ='Input data'!D45 -> 22.282169 | E78: ='Input data'!E45 -> 8.9931862 | F78: ='Input data'!F45 -> 4.6 | G78: ='Input data'!G33+G41-(G$12-F$12)/'Input data'!$C$64*100 -> 5.600645 | H78: ='Input data'!H33+H41-(H$12-G$12)/'Input data'!$C$64*100 -> 5.204881 | I78: ='Input data'!I33+I41-(I$12-H$12)/'Input data'!$C$64*100 -> 5.1315869 | J78: ='Input data'!J33+J41-(J$12-I$12)/'Input data'!$C$64*100 -> 4.9719847 | K78: ='Input data'!K33+K41-(K$12-J$12)/'Input data'!$C$64*100 -> 4.8725166 | L78: ='Input data'!L33+L41-(L$12-K$12)/'Input data'!$C$64*100 -> 5.0202485 | M78: ='Input data'!M33+M41-(M$12-L$12)/'Input data'!$C$64*100 -> 5.0859394 | N78: ='Input data'!N33+N41-(N$12-M$12)/'Input data'!$C$64*100 -> 5.0307103 | ... W78: ='Input data'!W33+W41-(W$12-V$12)/'Input data'!$C$64*100 -> 4.594632
B81: Debt decomposition and IIR
B83: Auxiliary variable identifying whether debt is increasing | F83: =IF((F87-E87*F42/((1+F23/100)*(1+F41/100)))>0,1,0) -> 1 | G83: =IF((G87-F87*G42/((1+G23/100)*(1+G41/100)))>0,1,0) -> 1 | H83: =IF((H87-G87*H42/((1+H23/100)*(1+H41/100)))>0,1,0) -> 1 | I83: =IF((I87-H87*I42/((1+I23/100)*(1+I41/100)))>0,1,0) -> 1 | J83: =IF((J87-I87*J42/((1+J23/100)*(1+J41/100)))>0,1,0) -> 1 | K83: =IF((K87-J87*K42/((1+K23/100)*(1+K41/100)))>0,1,0) -> 1 | L83: =IF((L87-K87*L42/((1+L23/100)*(1+L41/100)))>0,1,0) -> 1 | M83: =IF((M87-L87*M42/((1+M23/100)*(1+M41/100)))>0,1,0) -> 1 | ... W83: =IF((W87-V87*W42/((1+W23/100)*(1+W41/100)))>0,1,0) -> 1
B84: Auxiliary variable identifying whether some debt is rolled over even though debt is decreasing | F84: =IF(AND(F83=0,ABS(F87-E87*F42/((1+F23/100)*(1+F41/100)))<((E93*E87*F42/((1+F23/100)*(1+F41/100))+(F38*E87*E94*F42/((1+F23/100)*(1+F41/100)))))),1,0) -> 0 | G84: =IF(AND(G83=0,ABS(G87-F87*G42/((1+G23/100)*(1+G41/100)))<((F93*F87*G42/((1+G23/100)*(1+G41/100))+(G38*F87*F94*G42/((1+G23/100)*(1+G41/100)))))),1,0) -> 0 | H84: =IF(AND(H83=0,ABS(H87-G87*H42/((1+H23/100)*(1+H41/100)))<((G93*G87*H42/((1+H23/100)*(1+H41/100))+(H38*G87*G94*H42/((1+H23/100)*(1+H41/100)))))),1,0) -> 0 | I84: =IF(AND(I83=0,ABS(I87-H87*I42/((1+I23/100)*(1+I41/100)))<((H93*H87*I42/((1+I23/100)*(1+I41/100))+(I38*H87*H94*I42/((1+I23/100)*(1+I41/100)))))),1,0) -> 0 | J84: =IF(AND(J83=0,ABS(J87-I87*J42/((1+J23/100)*(1+J41/100)))<((I93*I87*J42/((1+J23/100)*(1+J41/100))+(J38*I87*I94*J42/((1+J23/100)*(1+J41/100)))))),1,0) -> 0 | K84: =IF(AND(K83=0,ABS(K87-J87*K42/((1+K23/100)*(1+K41/100)))<((J93*J87*K42/((1+K23/100)*(1+K41/100))+(K38*J87*J94*K42/((1+K23/100)*(1+K41/100)))))),1,0) -> 0 | L84: =IF(AND(L83=0,ABS(L87-K87*L42/((1+L23/100)*(1+L41/100)))<((K93*K87*L42/((1+L23/100)*(1+L41/100))+(L38*K87*K94*L42/((1+L23/100)*(1+L41/100)))))),1,0) -> 0 | M84: =IF(AND(M83=0,ABS(M87-L87*M42/((1+M23/100)*(1+M41/100)))<((L93*L87*M42/((1+M23/100)*(1+M41/100))+(M38*L87*L94*M42/((1+M23/100)*(1+M41/100)))))),1,0) -> 0 | ... W84: =IF(AND(W83=0,ABS(W87-V87*W42/((1+W23/100)*(1+W41/100)))<((V93*V87*W42/((1+W23/100)*(1+W41/100))+(W38*V87*V94*W42/((1+W23/100)*(1+W41/100)))))),1,0) -> 0
C86: 2021 | D86: 2022 | E86: 2023 | F86: 2024 | G86: 2025 | H86: 2026 | I86: 2027 | J86: 2028 | K86: 2029 | L86: 2030 | M86: 2031 | N86: 2032 | O86: 2033 | P86: 2034 | Q86: 2035 | R86: 2036 | S86: 2037 | T86: 2038 | U86: 2039 | V86: 2040 | W86: 2041
B87: Gross debt | C87: =C56 -> 76.21938 | D87: =D56 -> 73.842909 | E87: =E56 -> 73.437974 | F87: =F56 -> 74.041486 | G87: =G56 -> 73.466416 | H87: =G87*(1+H101/100)*H42-H59-H60+H61+H62+H63+H64+H65+H72 -> 71.738572 | I87: =H87*(1+I101/100)*I42-I59-I60+I61+I62+I63+I64+I65+I72 -> 71.328386 | J87: =I87*(1+J101/100)*J42-J59-J60+J61+J62+J63+J64+J65+J72 -> 71.142953 | K87: =J87*(1+K101/100)*K42-K59-K60+K61+K62+K63+K64+K65+K72 -> 71.145504 | L87: =K87*(1+L101/100)*L42-L59-L60+L61+L62+L63+L64+L65+L72 -> 71.180229 | M87: =L87*(1+M101/100)*M42-M59-M60+M61+M62+M63+M64+M65+M72 -> 71.341221 | N87: =M87*(1+N101/100)*N42-N59-N60+N61+N62+N63+N64+N65+N72 -> 71.731623 | O87: =N87*(1+O101/100)*O42-O59-O60+O61+O62+O63+O64+O65+O72 -> 72.442482 | ... W87: =V87*(1+W101/100)*W42-W59-W60+W61+W62+W63+W64+W65+W72 -> 88.591971
B88: Of which Outstanding debt | E88: ='Input data'!$C$66*E$87 -> 54.96332 | F88: =IF(F87=0,0,IF(F83=1,E87*F42/((1+F23/100)*(1+F41/100))-F89-F90,IF(AND(F83=0,F84=1),(1-E93-F38*E94)*E87*F42/((1+F23/100)*(1+F41/100)),F87))) -> 57.782728 | G88: =IF(G87=0,0,IF(G83=1,F87*G42/((1+G23/100)*(1+G41/100))-G89-G90,IF(AND(G83=0,G84=1),(1-F93-G38*F94)*F87*G42/((1+G23/100)*(1+G41/100)),G87))) -> 59.190556 | H88: =IF(H87=0,0,IF(H83=1,G87*H42/((1+H23/100)*(1+H41/100))-H89-H90,IF(AND(H83=0,H84=1),(1-G93-H38*G94)*G87*H42/((1+H23/100)*(1+H41/100)),H87))) -> 57.791531 | I88: =IF(I87=0,0,IF(I83=1,H87*I42/((1+I23/100)*(1+I41/100))-I89-I90,IF(AND(I83=0,I84=1),(1-H93-I38*H94)*H87*I42/((1+I23/100)*(1+I41/100)),I87))) -> 57.185804 | J88: =IF(J87=0,0,IF(J83=1,I87*J42/((1+J23/100)*(1+J41/100))-J89-J90,IF(AND(J83=0,J84=1),(1-I93-J38*I94)*I87*J42/((1+J23/100)*(1+J41/100)),J87))) -> 56.918384 | K88: =IF(K87=0,0,IF(K83=1,J87*K42/((1+K23/100)*(1+K41/100))-K89-K90,IF(AND(K83=0,K84=1),(1-J93-K38*J94)*J87*K42/((1+K23/100)*(1+K41/100)),K87))) -> 56.795818 | L88: =IF(L87=0,0,IF(L83=1,K87*L42/((1+L23/100)*(1+L41/100))-L89-L90,IF(AND(L83=0,L84=1),(1-K93-L38*K94)*K87*L42/((1+L23/100)*(1+L41/100)),L87))) -> 56.680915 | M88: =IF(M87=0,0,IF(M83=1,L87*M42/((1+M23/100)*(1+M41/100))-M89-M90,IF(AND(M83=0,M84=1),(1-L93-M38*L94)*L87*M42/((1+M23/100)*(1+M41/100)),M87))) -> 56.641109 | ... W88: =IF(W87=0,0,IF(W83=1,V87*W42/((1+W23/100)*(1+W41/100))-W89-W90,IF(AND(W83=0,W84=1),(1-V93-W38*V94)*V87*W42/((1+W23/100)*(1+W41/100)),W87))) -> 68.509997
B89: Rolled over long-term debt | E89: ='Input data'!$C$67*E$87 -> 2.9208599 | F89: =IF(F87=0,0,IF(F83=1,F38*E87*E94*F42/((1+F23/100)*(1+F41/100)),IF(AND(F83=0,F84=1),(F38*E87*E94*F42/((1+F23/100)*(1+F41/100)))*(1-ABS(F87-E87*F42/((1+F23/100)*(1+F41/100)))/((F38*E87*E94*F42/((1+F23/100)*(1+F41/100)))+(E93*E87*F42/((1+F23/100)*(1+F41/100))))),0))) -> 4.1782685 | G89: =IF(G87=0,0,IF(G83=1,G38*F87*F94*G42/((1+G23/100)*(1+G41/100)),IF(AND(G83=0,G84=1),(G38*F87*F94*G42/((1+G23/100)*(1+G41/100)))*(1-ABS(G87-F87*G42/((1+G23/100)*(1+G41/100)))/((G38*F87*F94*G42/((1+G23/100)*(1+G41/100)))+(F93*F87*G42/((1+G23/100)*(1+G41/100))))),0))) -> 4.3525801 | H89: =IF(H87=0,0,IF(H83=1,H38*G87*G94*H42/((1+H23/100)*(1+H41/100)),IF(AND(H83=0,H84=1),(H38*G87*G94*H42/((1+H23/100)*(1+H41/100)))*(1-ABS(H87-G87*H42/((1+H23/100)*(1+H41/100)))/((H38*G87*G94*H42/((1+H23/100)*(1+H41/100)))+(G93*G87*H42/((1+H23/100)*(1+H41/100))))),0))) -> 4.3206624 | I89: =IF(I87=0,0,IF(I83=1,I38*H87*H94*I42/((1+I23/100)*(1+I41/100)),IF(AND(I83=0,I84=1),(I38*H87*H94*I42/((1+I23/100)*(1+I41/100)))*(1-ABS(I87-H87*I42/((1+I23/100)*(1+I41/100)))/((I38*H87*H94*I42/((1+I23/100)*(1+I41/100)))+(H93*H87*I42/((1+I23/100)*(1+I41/100))))),0))) -> 4.3457532 | J89: =IF(J87=0,0,IF(J83=1,J38*I87*I94*J42/((1+J23/100)*(1+J41/100)),IF(AND(J83=0,J84=1),(J38*I87*I94*J42/((1+J23/100)*(1+J41/100)))*(1-ABS(J87-I87*J42/((1+J23/100)*(1+J41/100)))/((J38*I87*I94*J42/((1+J23/100)*(1+J41/100)))+(I93*I87*J42/((1+J23/100)*(1+J41/100))))),0))) -> 4.3956392 | K89: =IF(K87=0,0,IF(K83=1,K38*J87*J94*K42/((1+K23/100)*(1+K41/100)),IF(AND(K83=0,K84=1),(K38*J87*J94*K42/((1+K23/100)*(1+K41/100)))*(1-ABS(K87-J87*K42/((1+K23/100)*(1+K41/100)))/((K38*J87*J94*K42/((1+K23/100)*(1+K41/100)))+(J93*J87*K42/((1+K23/100)*(1+K41/100))))),0))) -> 4.4563916 | L89: =IF(L87=0,0,IF(L83=1,L38*K87*K94*L42/((1+L23/100)*(1+L41/100)),IF(AND(L83=0,L84=1),(L38*K87*K94*L42/((1+L23/100)*(1+L41/100)))*(1-ABS(L87-K87*L42/((1+L23/100)*(1+L41/100)))/((L38*K87*K94*L42/((1+L23/100)*(1+L41/100)))+(K93*K87*L42/((1+L23/100)*(1+L41/100))))),0))) -> 4.5176128 | M89: =IF(M87=0,0,IF(M83=1,M38*L87*L94*M42/((1+M23/100)*(1+M41/100)),IF(AND(M83=0,M84=1),(M38*L87*L94*M42/((1+M23/100)*(1+M41/100)))*(1-ABS(M87-L87*M42/((1+M23/100)*(1+M41/100)))/((M38*L87*L94*M42/((1+M23/100)*(1+M41/100)))+(L93*L87*M42/((1+M23/100)*(1+M41/100))))),0))) -> 4.5847891 | ... W89: =IF(W87=0,0,IF(W83=1,W38*V87*V94*W42/((1+W23/100)*(1+W41/100)),IF(AND(W83=0,W84=1),(W38*V87*V94*W42/((1+W23/100)*(1+W41/100)))*(1-ABS(W87-V87*W42/((1+W23/100)*(1+W41/100)))/((W38*V87*V94*W42/((1+W23/100)*(1+W41/100)))+(V93*V87*W42/((1+W23/100)*(1+W41/100))))),0))) -> 5.8019603
B90: Rolled over short-term debt | E90: ='Input data'!$C$68*$E$87 -> 6.4315767 | F90: =IF(F87=0,0,IF(F83=1,(1-E94)*E87*F42/((1+F23/100)*(1+F41/100)),IF(AND(F83=0,F84=1),(E93*E87*F42/((1+F23/100)*(1+F41/100)))*(1-ABS(F87-E87*F42/((1+F23/100)*(1+F41/100)))/((F38*E87*E94*F42/((1+F23/100)*(1+F41/100)))+(E93*E87*F42/((1+F23/100)*(1+F41/100))))),0))) -> 6.8845562 | G90: =IF(G87=0,0,IF(G83=1,(1-F94)*F87*G42/((1+G23/100)*(1+G41/100)),IF(AND(G83=0,G84=1),(F93*F87*G42/((1+G23/100)*(1+G41/100)))*(1-ABS(G87-F87*G42/((1+G23/100)*(1+G41/100)))/((G38*F87*F94*G42/((1+G23/100)*(1+G41/100)))+(F93*F87*G42/((1+G23/100)*(1+G41/100))))),0))) -> 6.9767054 | H90: =IF(H87=0,0,IF(H83=1,(1-G94)*G87*H42/((1+H23/100)*(1+H41/100)),IF(AND(H83=0,H84=1),(G93*G87*H42/((1+H23/100)*(1+H41/100)))*(1-ABS(H87-G87*H42/((1+H23/100)*(1+H41/100)))/((H38*G87*G94*H42/((1+H23/100)*(1+H41/100)))+(G93*G87*H42/((1+H23/100)*(1+H41/100))))),0))) -> 6.7762246 | I90: =IF(I87=0,0,IF(I83=1,(1-H94)*H87*I42/((1+I23/100)*(1+I41/100)),IF(AND(I83=0,I84=1),(H93*H87*I42/((1+I23/100)*(1+I41/100)))*(1-ABS(I87-H87*I42/((1+I23/100)*(1+I41/100)))/((I38*H87*H94*I42/((1+I23/100)*(1+I41/100)))+(H93*H87*I42/((1+I23/100)*(1+I41/100))))),0))) -> 6.6720761 | J90: =IF(J87=0,0,IF(J83=1,(1-I94)*I87*J42/((1+J23/100)*(1+J41/100)),IF(AND(J83=0,J84=1),(I93*I87*J42/((1+J23/100)*(1+J41/100)))*(1-ABS(J87-I87*J42/((1+J23/100)*(1+J41/100)))/((J38*I87*I94*J42/((1+J23/100)*(1+J41/100)))+(I93*I87*J42/((1+J23/100)*(1+J41/100))))),0))) -> 6.6054897 | K90: =IF(K87=0,0,IF(K83=1,(1-J94)*J87*K42/((1+K23/100)*(1+K41/100)),IF(AND(K83=0,K84=1),(J93*J87*K42/((1+K23/100)*(1+K41/100)))*(1-ABS(K87-J87*K42/((1+K23/100)*(1+K41/100)))/((K38*J87*J94*K42/((1+K23/100)*(1+K41/100)))+(J93*J87*K42/((1+K23/100)*(1+K41/100))))),0))) -> 6.5564029 | L90: =IF(L87=0,0,IF(L83=1,(1-K94)*K87*L42/((1+L23/100)*(1+L41/100)),IF(AND(L83=0,L84=1),(K93*K87*L42/((1+L23/100)*(1+L41/100)))*(1-ABS(L87-K87*L42/((1+L23/100)*(1+L41/100)))/((L38*K87*K94*L42/((1+L23/100)*(1+L41/100)))+(K93*K87*L42/((1+L23/100)*(1+L41/100))))),0))) -> 6.5088165 | M90: =IF(M87=0,0,IF(M83=1,(1-L94)*L87*M42/((1+M23/100)*(1+M41/100)),IF(AND(M83=0,M84=1),(L93*L87*M42/((1+M23/100)*(1+M41/100)))*(1-ABS(M87-L87*M42/((1+M23/100)*(1+M41/100)))/((M38*L87*L94*M42/((1+M23/100)*(1+M41/100)))+(L93*L87*M42/((1+M23/100)*(1+M41/100))))),0))) -> 6.4702769 | ... W90: =IF(W87=0,0,IF(W83=1,(1-V94)*V87*W42/((1+W23/100)*(1+W41/100)),IF(AND(W83=0,W84=1),(V93*V87*W42/((1+W23/100)*(1+W41/100)))*(1-ABS(W87-V87*W42/((1+W23/100)*(1+W41/100)))/((W38*V87*V94*W42/((1+W23/100)*(1+W41/100)))+(V93*V87*W42/((1+W23/100)*(1+W41/100))))),0))) -> 7.383013
B91: New long-term debt | E91: ='Input data'!$C$69*E$87 -> 8.209995 | F91: =IF(F87=0,0,IF(F83=1,'Input data'!$C$58*(F87-E87*F42/((1+F23/100)*(1+F41/100))),0)) -> 4.755379 | G91: =IF(G87=0,0,IF(G83=1,'Input data'!$C$58*(G87-F87*G42/((1+G23/100)*(1+G41/100))),0)) -> 2.6967397 | H91: =IF(H87=0,0,IF(H83=1,'Input data'!$C$58*(H87-G87*H42/((1+H23/100)*(1+H41/100))),0)) -> 2.6084942 | I91: =IF(I87=0,0,IF(I83=1,'Input data'!$C$58*(I87-H87*I42/((1+I23/100)*(1+I41/100))),0)) -> 2.8598108 | J91: =IF(J87=0,0,IF(J83=1,'Input data'!$C$58*(J87-I87*J42/((1+J23/100)*(1+J41/100))),0)) -> 2.9501297 | K91: =IF(K87=0,0,IF(K83=1,'Input data'!$C$58*(K87-J87*K42/((1+K23/100)*(1+K41/100))),0)) -> 3.0539626 | L91: =IF(L87=0,0,IF(L83=1,'Input data'!$C$58*(L87-K87*L42/((1+L23/100)*(1+L41/100))),0)) -> 3.1784245 | M91: =IF(M87=0,0,IF(M83=1,'Input data'!$C$58*(M87-L87*M42/((1+M23/100)*(1+M41/100))),0)) -> 3.3359886 | ... W91: =IF(W87=0,0,IF(W83=1,'Input data'!$C$58*(W87-V87*W42/((1+W23/100)*(1+W41/100))),0)) -> 6.3122157
B92: New short-term debt | E92: ='Input data'!$C$70*E$87 -> 0.91222167 | F92: =IF(F87=0,0,IF(F83=1,'Input data'!$C$57*(F87-E87*F42/((1+F23/100)*(1+F41/100))),0)) -> 0.44055435 | G92: =IF(G87=0,0,IF(G83=1,'Input data'!$C$57*(G87-F87*G42/((1+G23/100)*(1+G41/100))),0)) -> 0.24983507 | H92: =IF(H87=0,0,IF(H83=1,'Input data'!$C$57*(H87-G87*H42/((1+H23/100)*(1+H41/100))),0)) -> 0.24165971 | I92: =IF(I87=0,0,IF(I83=1,'Input data'!$C$57*(I87-H87*I42/((1+I23/100)*(1+I41/100))),0)) -> 0.26494252 | J92: =IF(J87=0,0,IF(J83=1,'Input data'!$C$57*(J87-I87*J42/((1+J23/100)*(1+J41/100))),0)) -> 0.27330997 | K92: =IF(K87=0,0,IF(K83=1,'Input data'!$C$57*(K87-J87*K42/((1+K23/100)*(1+K41/100))),0)) -> 0.2829294 | L92: =IF(L87=0,0,IF(L83=1,'Input data'!$C$57*(L87-K87*L42/((1+L23/100)*(1+L41/100))),0)) -> 0.29445997 | M92: =IF(M87=0,0,IF(M83=1,'Input data'!$C$57*(M87-L87*M42/((1+M23/100)*(1+M41/100))),0)) -> 0.30905724 | ... W92: =IF(W87=0,0,IF(W83=1,'Input data'!$C$57*(W87-V87*W42/((1+W23/100)*(1+W41/100))),0)) -> 0.58478496
B93: Share of short-term debt in total government debt | E93: =IF(E87<>0,(E90+E92)/(E88+E89+E90+E91+E92),0) -> 0.10000001 | F93: =IF(F87<>0,(F90+F92)/(F88+F89+F90+F91+F92),0) -> 0.098932517 | G93: =IF(G87<>0,(G90+G92)/(G88+G89+G90+G91+G92),0) -> 0.098365224 | H93: =IF(H87<>0,(H90+H92)/(H88+H89+H90+H91+H92),0) -> 0.097825816 | I93: =IF(I87<>0,(I90+I92)/(I88+I89+I90+I91+I92),0) -> 0.097254669 | J93: =IF(J87<>0,(J90+J92)/(J88+J89+J90+J91+J92),0) -> 0.096689826 | K93: =IF(K87<>0,(K90+K92)/(K88+K89+K90+K91+K92),0) -> 0.096131616 | L93: =IF(L87<>0,(L90+L92)/(L88+L89+L90+L91+L92),0) -> 0.095578176 | ... W93: =IF(W87<>0,(W90+W92)/(W88+W89+W90+W91+W92),0) -> 0.08993815
B94: Share of long-term debt in total government debt | E94: =IF(E87<>0,(E88+E89+E91)/(E88+E89+E90+E91+E92),1) -> 0.89999999 | F94: =IF(F87<>0,(F88+F89+F91)/(F88+F89+F90+F91+F92),1) -> 0.90106748 | G94: =IF(G87<>0,(G88+G89+G91)/(G88+G89+G90+G91+G92),1) -> 0.90163478 | H94: =IF(H87<>0,(H88+H89+H91)/(H88+H89+H90+H91+H92),1) -> 0.90217418 | I94: =IF(I87<>0,(I88+I89+I91)/(I88+I89+I90+I91+I92),1) -> 0.90274533 | J94: =IF(J87<>0,(J88+J89+J91)/(J88+J89+J90+J91+J92),1) -> 0.90331017 | K94: =IF(K87<>0,(K88+K89+K91)/(K88+K89+K90+K91+K92),1) -> 0.90386838 | L94: =IF(L87<>0,(L88+L89+L91)/(L88+L89+L90+L91+L92),1) -> 0.90442182 | ... W94: =IF(W87<>0,(W88+W89+W91)/(W88+W89+W90+W91+W92),1) -> 0.91006185
B96: IIR | C96: =C35 -> 3.238231 | D96: =D35 -> 4.417456 | E96: =E35 -> 7.284665 | F96: =F98+F99 -> 7.231643 | G96: =G98+G99 -> 5.674904 | H96: =H98+H99 -> 5.648431 | I96: =I98+I99 -> 5.773885 | J96: =J98+J99 -> 5.8928417 | K96: =K98+K99 -> 6.002884 | L96: =L98+L99 -> 6.1046284 | M96: =M98+M99 -> 6.1987976 | ... W96: =W98+W99 -> 6.3394094
B97: Long-term implicit interest rate | F97: =((F35*E87)-(F37*(E90+E92)))/(E88+E89+E91) -> 7.2267647 | G97: =((G35*F87)-(G37*(F90+F92)))/(F88+F89+F91) -> 5.6458541 | H97: =((H35*G87)-(H37*(G90+G92)))/(G88+G89+G91) -> 5.6382136 | I97: =IF(H87>0,(H97*H88+I36*(H91+H89))/(H88+H89+H91),I36) -> 5.7670317 | J97: =IF(I87>0,(I97*I88+J36*(I91+I89))/(I88+I89+I91),J36) -> 5.8886134 | K97: =IF(J87>0,(J97*J88+K36*(J91+J89))/(J88+J89+J91),K36) -> 6.0002929 | L97: =IF(K87>0,(K97*K88+L36*(K91+K89))/(K88+K89+K91),L36) -> 6.102771 | M97: =IF(L87>0,(L97*L88+M36*(L91+L89))/(L88+L89+L91),M36) -> 6.196864 | N97: =IF(M87>0,(M97*M88+N36*(M91+M89))/(M88+M89+M91),N36) -> 6.283369 | O97: =IF(N87>0,(N97*N88+O36*(N91+N89))/(N88+N89+N91),O36) -> 6.3628518 | P97: =IF(O87>0,(O97*O88+P36*(O91+O89))/(O88+O89+O91),P36) -> 6.4358791 | ... W97: =IF(V87>0,(V97*V88+W36*(V91+V89))/(V88+V89+V91),W36) -> 6.4624112
B98: Nominal implicit interest rate on debt (Excel approximation) | F98: =F35 -> 7.231643 | G98: =G35 -> 5.674904 | H98: =H35 -> 5.648431 | I98: =(I97*(H88+H89+H91)+I37*(H90+H92))/H87 -> 5.773885 | J98: =(J97*(I88+I89+I91)+J37*(I90+I92))/I87 -> 5.8928417 | K98: =(K97*(J88+J89+J91)+K37*(J90+J92))/J87 -> 6.002884 | L98: =(L97*(K88+K89+K91)+L37*(K90+K92))/K87 -> 6.1046284 | M98: =(M97*(L88+L89+L91)+M37*(L90+L92))/L87 -> 6.1987976 | N98: =(N97*(M88+M89+M91)+N37*(M90+M92))/M87 -> 6.2860989 | O98: =(O97*(N88+N89+N91)+O37*(N90+N92))/N87 -> 6.3670321 | P98: =(P97*(O88+O89+O91)+P37*(O90+O92))/O87 -> 6.4420993 | ... W98: =(W97*(V88+V89+V91)+W37*(V90+V92))/V87 -> 6.3394094
B99: Diff. STATA | F99: =F108 -> 0 | G99: =G108 -> 0 | H99: =H108 -> 0 | I99: =I108 -> 0 | J99: =J108 -> 0 | K99: =K108 -> 0 | L99: =L108 -> 0 | M99: =M108 -> 0 | ... W99: =W108 -> 0
B101: (i - g) | C101: =((1+C96/100)/((1+C23/100)*(1+C41/100))-1)*100 -> -9.3034373 | D101: =((1+D96/100)/((1+D23/100)*(1+D41/100))-1)*100 -> -12.324289 | E101: =((1+E96/100)/((1+E23/100)*(1+E41/100))-1)*100 -> -5.4617189 | F101: =((1+F96/100)/((1+F23/100)*(1+F41/100))-1)*100 -> -0.53672043 | G101: =((1+G96/100)/((1+G23/100)*(1+G41/100))-1)*100 -> -0.075279725 | H101: =((1+H96/100)/((1+H23/100)*(1+H41/100))-1)*100 -> -0.9349625 | I101: =((1+I96/100)/((1+I23/100)*(1+I41/100))-1)*100 -> 0.5618464 | J101: =((1+J96/100)/((1+J23/100)*(1+J41/100))-1)*100 -> 0.83208968 | ... W101: =((1+W96/100)/((1+W23/100)*(1+W41/100))-1)*100 -> 1.6215654
B104: Per memo - STATA results
B106: Debt | C106: 76.21938 | D106: 73.84293 | E106: 73.438 | F106: 74.50443 | G106: 74.39194 | H106: 73.26106 | I106: 73.45168 | J106: 73.86253 | K106: 74.45743 | L106: 75.07331 | M106: 75.80584 | N106: 76.76265 | O106: 78.03969 | P106: 79.58701 | Q106: 81.41872 | R106: 83.55301 | S106: 85.98828 | T106: 88.74363 | U106: 91.82892 | V106: 95.23598 | W106: 98.96857
B107: IIR | C107: 3.238231 | D107: 4.417456 | E107: 7.284665 | F107: 7.231643 | G107: 5.674904 | H107: 5.648431 | I107: 5.780293 | J107: 5.904333 | K107: 6.018301 | L107: 6.122937 | M107: 6.219087 | N107: 6.307562 | O107: 6.38897 | P107: 6.463423 | Q107: 6.491458 | R107: 6.501651 | S107: 6.495914 | T107: 6.476009 | U107: 6.443615 | V107: 6.400291 | W107: 6.34746
B108: IIR difference STATA - Excel | D108: 0 | E108: 0 | F108: 0 | G108: 0 | H108: 0 | I108: 0 | J108: 0 | K108: 0 | L108: 0 | M108: 0 | N108: 0 | O108: 0 | P108: 0 | Q108: 0 | R108: 0 | S108: 0 | T108: 0 | U108: 0 | V108: 0 | W108: 0
B110: Share of long-term debt that matures every year | C110: 2021 | D110: 2022 | E110: 2023 | F110: 2024 | G110: 2025 | H110: 2026 | I110: 2027 | J110: 2028 | K110: 2029 | L110: 2030 | M110: 2031 | N110: 2032 | O110: 2033 | P110: 2034 | Q110: 2035 | R110: 2036 | S110: 2037 | T110: 2038 | U110: 2039 | V110: 2040 | W110: 2041
B111: CY | C111: 0.03801916 | D111: 0.07859744 | E111: 0.05947547 | F111: 0.09705473 | G111: 0.11813094 | H111: 0.13979355 | I111: 0.13858428 | J111: 0.14522678 | K111: 0.14229576 | L111: 0.12855515 | M111: 0.13228095 | N111: 0.07521692 | O111: 0.07473234 | P111: 0.06874014 | Q111: 0.06808882 | R111: 0.06765935 | S111: 0.06918122 | T111: 0.06660881 | U111: 0.06640882 | V111: 0.06636027 | W111: 0.06617871
B112: EL | C112: 0.00753015 | D112: 0.05389102 | E112: 0.03984522 | F112: 0.03790162 | G112: 0.01552437 | H112: 0.02926531 | I112: 0.02611486 | J112: 0.03788087 | K112: 0.03700117 | L112: 0.04402761 | M112: 0.05211363 | N112: 0.05015698 | O112: 0.07996842 | P112: 0.06411481 | Q112: 0.06853133 | R112: 0.07630271 | S112: 0.08870138 | T112: 0.098649 | U112: 0.08660599 | V112: 0.09284776 | W112: 0.09772447
B113: IE | C113: 0.001 | D113: 0.07537306 | E113: 0.04688205 | F113: 0.05421672 | G113: 0.06791541 | H113: 0.07361571 | I113: 0.06348117 | J113: 0.07188008 | K113: 0.0779188 | L113: 0.07335137 | M113: 0.09382516 | N113: 0.09915761 | O113: 0.10572949 | P113: 0.07905033 | Q113: 0.08422854 | R113: 0.07314158 | S113: 0.07356939 | T113: 0.07406277 | U113: 0.07459016 | V113: 0.07512754 | W113: 0.0758928
B114: PT | C114: 0.08381841 | D114: 0.06939163 | E114: 0.0532381 | F114: 0.04919325 | G114: 0.05654676 | H114: 0.06345828 | I114: 0.06433408 | J114: 0.06334076 | K114: 0.06114409 | L114: 0.05390277 | M114: 0.09325509 | N114: 0.07285002 | O114: 0.07453417 | P114: 0.06143648 | Q114: 0.08242282 | R114: 0.0853176 | S114: 0.06039476 | T114: 0.07369029 | U114: 0.05733009 | V114: 0.06101423 | W114: 0.05730975

Sheet Adjustment scenario
B3: Country | C3: ='Input data'!C3 -> HU
B4: Key years
B5: ='Input data'!B5 -> Last year before the adjustment | C5: =+'Input data'!C5 -> 2024
B6: Last year of adjustment | C6: =+C5+'Criteria results'!$F$5 -> 2028
B7: Last year of no-fiscal-policy-change projections | C7: =C5+'Criteria results'!$F$5+10 -> 2038
B9: Key assumptions
C10: 2021 | D10: 2022 | E10: 2023 | F10: 2024 | G10: 2025 | H10: 2026 | I10: 2027 | J10: 2028 | K10: 2029 | L10: 2030 | M10: 2031 | N10: 2032 | O10: 2033 | P10: 2034 | Q10: 2035 | R10: 2036 | S10: 2037 | T10: 2038 | U10: 2039 | V10: 2040 | W10: 2041
B11: Fiscal assumptions (% of GDP)
B12: Structural primary balance ('+' means 'surplus') | C12: ='Input data'!C13 -> -5.106841 | D12: ='Input data'!D13 -> -4.391969 | E12: ='Input data'!E13 -> -1.706974 | F12: ='Input data'!F13 -> 0.64244146 | G12: =IF(G10<=$C$6, IF(AND(F87=1,F77<=-3.05,'Criteria results'!$F$6<0.5),F12+0.5, IF(AND(F78<=-1.55,'Criteria results'!$F$5=4,'Criteria results'!$F$6<0.4),F12+0.4, IF(AND(F78<=-1.55,'Criteria results'!$F$5=7,'Criteria results'!$F$6<0.25),F12+0.25, F12+'Criteria results'!$F$6))),F12) -> 1.1824415 | H12: =IF(H10<=$C$6, IF(AND(G87=1,G77<=-3.05,'Criteria results'!$F$6<0.5),G12+0.5, IF(AND(G78<=-1.55,'Criteria results'!$F$5=4,'Criteria results'!$F$6<0.4),G12+0.4, IF(AND(G78<=-1.55,'Criteria results'!$F$5=7,'Criteria results'!$F$6<0.25),G12+0.25, G12+'Criteria results'!$F$6))),G12) -> 1.7224415 | I12: =IF(I10<=$C$6, IF(AND(H87=1,H77<=-3.05,'Criteria results'!$F$6<0.5),H12+0.5, IF(AND(H78<=-1.55,'Criteria results'!$F$5=4,'Criteria results'!$F$6<0.4),H12+0.4, IF(AND(H78<=-1.55,'Criteria results'!$F$5=7,'Criteria results'!$F$6<0.25),H12+0.25, H12+'Criteria results'!$F$6))),H12) -> 2.2624415 | J12: =IF(J10<=$C$6, IF(AND(I87=1,I77<=-3.05,'Criteria results'!$F$6<0.5+J91),I12+0.5+J91, IF(AND(I78<=-1.55,'Criteria results'!$F$5=4,'Criteria results'!$F$6<0.4),I12+0.4, IF(AND(I78<=-1.55,'Criteria results'!$F$5=7,'Criteria results'!$F$6<0.25),I12+0.25, I12+'Criteria results'!$F$6))),I12) -> 2.8024415 | K12: =IF(K10<=$C$6, IF(AND(J87=1,J77<=-3.05,'Criteria results'!$F$6<0.5+K91),J12+0.5+K91, IF(AND(J78<=-1.55,'Criteria results'!$F$5=4,'Criteria results'!$F$6<0.4),J12+0.4, IF(AND(J78<=-1.55,'Criteria results'!$F$5=7,'Criteria results'!$F$6<0.25),J12+0.25, J12+'Criteria results'!$F$6))),J12) -> 2.8024415 | L12: =IF(L10<=$C$6, IF(AND(K87=1,K77<=-3.05,'Criteria results'!$F$6<0.5+L91),K12+0.5+L91, IF(AND(K78<=-1.55,'Criteria results'!$F$5=4,'Criteria results'!$F$6<0.4),K12+0.4, IF(AND(K78<=-1.55,'Criteria results'!$F$5=7,'Criteria results'!$F$6<0.25),K12+0.25, K12+'Criteria results'!$F$6))),K12) -> 2.8024415 | M12: =IF(M10<=$C$6, IF(AND(L87=1,L77<=-3.05,'Criteria results'!$F$6<0.5+M91),L12+0.5+M91, IF(AND(L78<=-1.55,'Criteria results'!$F$5=4,'Criteria results'!$F$6<0.4),L12+0.4, IF(AND(L78<=-1.55,'Criteria results'!$F$5=7,'Criteria results'!$F$6<0.25),L12+0.25, L12+'Criteria results'!$F$6))),L12) -> 2.8024415 | N12: =M12 -> 2.8024415 | O12: =N12 -> 2.8024415 | P12: =O12 -> 2.8024415 | Q12: =P12 -> 2.8024415 | R12: =Q12 -> 2.8024415 | S12: =R12 -> 2.8024415 | T12: =S12 -> 2.8024415 | U12: =T12 -> 2.8024415 | ... W12: =V12 -> 2.8024415
B13: Annual change in SPB | G13: =G12-F12 -> 0.54 | H13: =H12-G12 -> 0.54 | I13: =I12-H12 -> 0.54 | J13: =J12-I12 -> 0.54 | K13: =K12-J12 -> 0 | L13: =L12-K12 -> 0 | M13: =M12-L12 -> 0 | N13: =N12-M12 -> 0 | ... W13: =W12-V12 -> 0
B14: One-off and other temporary measures | C14: ='Input data'!C14 -> -0.1079972 | D14: ='Input data'!D14 -> 0 | E14: ='Input data'!E14 -> 0 | F14: ='Input data'!F14 -> 0 | G14: ='Input data'!G14 -> 0 | H14: ='Input data'!H14 -> 0 | I14: ='Input data'!I14 -> 0 | J14: ='Input data'!J14 -> 0 | ... W14: ='Input data'!W14 -> 0
B15: Stock flow adjustments (without exchange rate effect) | C15: ='Input data'!C15 -> -0.1371056 | D15: ='Input data'!D15 -> 1.066777 | E15: ='Input data'!E15 -> 2.471388 | F15: ='Input data'!F15 -> 0.243711 | G15: ='Input data'!G15 -> -0.9088278 | H15: ='Input data'!H15 -> -0.250576 | I15: ='Input data'!I15 -> 0 | J15: ='Input data'!J15 -> 0 | ... W15: ='Input data'!W15 -> 0
B17: ='Input data'!B19 -> Cost of ageing and selected public revenue (based on the Commission-Council 2024 Ageing Report ("AR 2024"))
B18: Total ageing cost (net of taxes on pensions) | C18: ='Input data'!C20 -> 0 | D18: ='Input data'!D20 -> 16.0166 | E18: ='Input data'!E20 -> 16.12175 | F18: ='Input data'!F20 -> 16.12852 | G18: ='Input data'!G20 -> 16.01381 | H18: ='Input data'!H20 -> 15.92993 | I18: ='Input data'!I20 -> 15.87402 | J18: ='Input data'!J20 -> 15.87527 | ... W18: ='Input data'!W20 -> 17.97964
B19: Property income | C19: ='Input data'!C26 -> 0.5353987 | D19: ='Input data'!D26 -> 1.178846 | E19: ='Input data'!E26 -> 2.102853 | F19: ='Input data'!F26 -> 2.07289 | G19: ='Input data'!G26 -> 2.042928 | H19: ='Input data'!H26 -> 2.012965 | I19: ='Input data'!I26 -> 1.983002 | J19: ='Input data'!J26 -> 1.953039 | ... W19: ='Input data'!W26 -> 1.563521
B21: GDP growth assumptions
B22: Actual GDP (real)
B23: Level | C23: ='Input data'!C31 -> 133.9938 | D23: ='Baseline NFPC'!D22 -> 139.70315 | E23: ='Baseline NFPC'!E22 -> 138.38125 | F23: ='Baseline NFPC'!F22 -> 139.19078 | G23: =IF(AND(G50>1,F50>1), G27*(1+('Baseline NFPC'!G$29+G51)/100)-F23*$C$47*(G12-F12)/100, IF(G50=1,G27,F23*(1+G52/100))) -> 140.88433 | H23: =IF(AND(H50>1,G50>1), H27*(1+('Baseline NFPC'!H$29+H51)/100)-G23*$C$47*(H12-G12)/100, IF(H50=1,H27,G23*(1+H52/100))) -> 144.81636 | I23: =IF(AND(I50>1,H50>1), I27*(1+I51/100)-H23*$C$47*(I12-H12)/100, IF(I50=1,I27,H23*(1+I52/100))) -> 147.01801 | J23: =IF(AND(J50>1,I50>1), J27*(1+J51/100)-I23*$C$47*(J12-I12)/100, IF(J50=1,J27,I23*(1+J52/100))) -> 149.20224 | K23: =IF(AND(K50>1,J50>1), K27*(1+K51/100)-J23*$C$47*(K12-J12)/100, IF(K50=1,K27,J23*(1+K52/100))) -> 152.02987 | L23: =IF(AND(L50>1,K50>1), L27*(1+L51/100)-K23*$C$47*(L12-K12)/100, IF(L50=1,L27,K23*(1+L52/100))) -> 155.22905 | M23: =IF(AND(M50>1,L50>1), M27*(1+M51/100)-L23*$C$47*(M12-L12)/100, IF(M50=1,M27,L23*(1+M52/100))) -> 158.69246 | N23: =IF(AND(N50>1,M50>1), N27*(1+N51/100)-M23*$C$47*(N12-M12)/100, IF(N50=1,N27,M23*(1+N52/100))) -> 161.73488 | O23: =IF(AND(O50>1,N50>1), O27*(1+O51/100)-N23*$C$47*(O12-N12)/100, IF(O50=1,O27,N23*(1+O52/100))) -> 164.70182 | P23: =IF(AND(P50>1,O50>1), P27*(1+P51/100)-O23*$C$47*(P12-O12)/100, IF(P50=1,P27,O23*(1+P52/100))) -> 167.75405 | ... W23: =IF(AND(W50>1,V50>1), W27*(1+W51/100)-V23*$C$47*(W12-V12)/100, IF(W50=1,W27,V23*(1+W52/100))) -> 188.86752
B24: Growth rate | C24: =+'Input data'!C30 -> 7.121139 | D24: ='Baseline NFPC'!D23 -> 4.260908 | E24: ='Baseline NFPC'!E23 -> -0.9462205 | F24: ='Baseline NFPC'!F23 -> 0.584996 | G24: =100*(G23/F23-1) -> 1.216716 | H24: =100*(H23/G23-1) -> 2.7909618 | I24: =100*(I23/H23-1) -> 1.5203043 | J24: =100*(J23/I23-1) -> 1.4856906 | K24: =100*(K23/J23-1) -> 1.8951652 | L24: =100*(L23/K23-1) -> 2.1043109 | M24: =100*(M23/L23-1) -> 2.2311598 | N24: =100*(N23/M23-1) -> 1.917179 | ... W24: =100*(W23/V23-1) -> 1.601132
B26: Potential GDP (real)
B27: Level | C27: ='Input data'!C34 -> 132.9781 | D27: =+C27*(1+'Input data'!D33/100) -> 136.6169 | E27: =+D27*(1+'Input data'!E33/100) -> 139.17592 | F27: =+E27*(1+'Input data'!F33/100) -> 141.10966 | G27: =+F27*(1+'Input data'!G33/100) -> 143.274 | H27: =+G27*(1+'Input data'!H33/100) -> 145.73938 | I27: =+H27*(1+'Input data'!I33/100) -> 148.23038 | J27: =+I27*(1+'Input data'!J33/100) -> 150.61893 | K27: =+J27*(1+'Input data'!K33/100) -> 152.9892 | ... W27: =+V27*(1+'Input data'!W33/100) -> 188.8675
B29: Output gap
B30: Output gap | C30: =100*(C23/C27-1) -> 0.76380998 | D30: =100*(D23/D27-1) -> 2.2590596 | E30: =100*(E23/E27-1) -> -0.5709813 | F30: =100*(F23/F27-1) -> -1.3598515 | G30: =100*(G23/G27-1) -> -1.6678968 | H30: =100*(H23/H27-1) -> -0.63333134 | I30: =100*(I23/I27-1) -> -0.81789301 | J30: =100*(J23/J27-1) -> -0.94057946 | ... W30: =100*(W23/W27-1) -> 8.8436136e-06
B32: Actual GDP (nominal, national currency)
B33: Growth rate | C33: =100*((1+C24/100)*(1+C42/100)-1) -> 13.828163 | D33: =100*((1+D24/100)*(1+D42/100)-1) -> 19.095077 | E33: =100*((1+E24/100)*(1+E42/100)-1) -> 13.482775 | F33: =100*((1+F24/100)*(1+F42/100)-1) -> 7.8102828 | G33: =100*((1+G24/100)*(1+G42/100)-1) -> 5.333045 | H33: =100*((1+H24/100)*(1+H42/100)-1) -> 6.3723398 | I33: =100*((1+I24/100)*(1+I42/100)-1) -> 4.9947046 | J33: =100*((1+J24/100)*(1+J42/100)-1) -> 4.8962215 | ... W33: =100*((1+W24/100)*(1+W42/100)-1) -> 4.6425619
B35: Interest rates
B36: Nominal implicit interest rate on debt | C36: ='Input data'!C37 -> 3.238231 | D36: ='Input data'!D37 -> 4.417456 | E36: ='Input data'!E37 -> 7.284665 | F36: ='Input data'!F37 -> 7.231643 | G36: ='Input data'!G37 -> 5.674904 | H36: =H109 -> 5.6484363 | I36: =I109 -> 5.7650421 | J36: =J109 -> 5.8711309 | K36: =K109 -> 5.9643176 | L36: =L109 -> 6.0503547 | M36: =M109 -> 6.1300808 | N36: =N109 -> 6.2043184 | O36: =O109 -> 6.2751747 | ... W36: =W109 -> 6.2915575
B37: Long-term interest rate | D37: ='Input data'!D$39 -> 7.57 | E37: ='Input data'!E$39 -> 7.51 | F37: ='Input data'!F$39 -> 6.52395 | G37: ='Input data'!G$39 -> 6.731379 | H37: ='Input data'!H$39 -> 6.82931 | I37: ='Baseline NFPC'!I36 -> 6.8414188 | J37: ='Baseline NFPC'!J36 -> 6.8535275 | K37: ='Baseline NFPC'!K36 -> 6.8656362 | L37: ='Baseline NFPC'!L36 -> 6.877745 | M37: ='Baseline NFPC'!M36 -> 6.8898537 | N37: ='Baseline NFPC'!N36 -> 6.9019625 | O37: ='Baseline NFPC'!O36 -> 6.9140712 | P37: ='Baseline NFPC'!P36 -> 6.92618 | ... W37: ='Baseline NFPC'!W36 -> 6.252017
B38: Short-term interest rate | D38: ='Input data'!D$38 -> 10.32 | E38: ='Input data'!E$38 -> 15.97 | F38: ='Input data'!F$38 -> 7.275548 | G38: ='Input data'!G$38 -> 5.939488 | H38: ='Input data'!H$38 -> 5.742086 | I38: ='Baseline NFPC'!I37 -> 5.8370877 | J38: ='Baseline NFPC'!J37 -> 5.9320895 | K38: ='Baseline NFPC'!K37 -> 6.0270912 | L38: ='Baseline NFPC'!L37 -> 6.122093 | M38: ='Baseline NFPC'!M37 -> 6.2170947 | N38: ='Baseline NFPC'!N37 -> 6.3120965 | O38: ='Baseline NFPC'!O37 -> 6.4070982 | P38: ='Baseline NFPC'!P37 -> 6.5021 | ... W38: ='Baseline NFPC'!W37 -> 5.101365
B39: Share of long-term debt that matures every year | C39: ='Baseline NFPC'!C38 -> 0.07935879 | D39: ='Baseline NFPC'!D38 -> 0.06020197 | E39: ='Baseline NFPC'!E38 -> 0.05046041 | F39: ='Baseline NFPC'!F38 -> 0.06743385 | G39: ='Baseline NFPC'!G38 -> 0.068498038 | H39: ='Baseline NFPC'!H38 -> 0.069562226 | I39: ='Baseline NFPC'!I38 -> 0.070626414 | J39: ='Baseline NFPC'!J38 -> 0.071690602 | ... W39: ='Baseline NFPC'!W38 -> 0.07807573
B41: Inflation and exchange rate
B42: GDP deflator (National currency) | C42: ='Input data'!C42 -> 6.261158 | D42: ='Input data'!D42 -> 14.22793 | E42: ='Input data'!E42 -> 14.56683 | F42: ='Input data'!F42 -> 7.183265 | G42: ='Input data'!G42 -> 4.066847 | H42: ='Input data'!H42 -> 3.484137 | I42: ='Baseline NFPC'!I41 -> 3.4223699 | J42: ='Baseline NFPC'!J41 -> 3.3606027 | K42: ='Baseline NFPC'!K41 -> 3.2988356 | L42: ='Baseline NFPC'!L41 -> 3.2370685 | M42: ='Baseline NFPC'!M41 -> 3.1753014 | N42: ='Baseline NFPC'!N41 -> 3.1135343 | O42: ='Baseline NFPC'!O41 -> 3.0517671 | P42: ='Baseline NFPC'!P41 -> 2.99 | ... W42: ='Baseline NFPC'!W41 -> 2.9935
B43: Exchange rate composite change (weighted by share of debt in each currency) | C43: ='Baseline NFPC'!C42 -> 1.001704 | D43: ='Baseline NFPC'!D42 -> 1.038632 | E43: ='Baseline NFPC'!E42 -> 0.9884134 | F43: ='Baseline NFPC'!F42 -> 1.010684 | G43: ='Baseline NFPC'!G42 -> 1.007245 | H43: ='Baseline NFPC'!H42 -> 1 | I43: ='Baseline NFPC'!I42 -> 1 | J43: ='Baseline NFPC'!J42 -> 1 | ... W43: ='Baseline NFPC'!W42 -> 1
B45: Intermediate calculations (growth rate equation)
B47: Fiscal multiplier | C47: ='Input data'!C49 -> 0.75
B48: Budget balance semi-elasticity | C48: ='Input data'!C50 -> 0.453
B50: Auxiliary variable to control the closure of the output gap | C50: 0 | D50: =IF(AND(ABS((D12-C12)-('Input data'!D13-'Input data'!C13))>0.0001,ABS(D12-C12)>0.0001,D$10>$C$5),4,IF(C50=4,3,IF(C50=3,2,IF(C50=2,1,0)))) -> 0 | E50: =IF(AND(ABS((E12-D12)-('Input data'!E13-'Input data'!D13))>0.0001,ABS(E12-D12)>0.0001,E$10>$C$5),4,IF(D50=4,3,IF(D50=3,2,IF(D50=2,1,0)))) -> 0 | F50: =IF(AND(ABS((F12-E12)-('Input data'!F13-'Input data'!E13))>0.0001,ABS(F12-E12)>0.0001,F$10>$C$5),4,IF(E50=4,3,IF(E50=3,2,IF(E50=2,1,0)))) -> 0 | G50: =IF(AND(ABS((G12-F12)-('Baseline NFPC'!G12-'Baseline NFPC'!F12))>0.0001,ABS(G12-F12)>0.0001,G$10>$C$5),4,IF(F50=4,3,IF(F50=3,2,IF(F50=2,1,0)))) -> 4 | H50: =IF(AND(ABS((H12-G12)-('Baseline NFPC'!H12-'Baseline NFPC'!G12))>0.0001,ABS(H12-G12)>0.0001,H$10>$C$5),4,IF(G50=4,3,IF(G50=3,2,IF(G50=2,1,0)))) -> 4 | I50: =IF(AND(ABS((I12-H12)-('Baseline NFPC'!I12-'Baseline NFPC'!H12))>0.0001,ABS(I12-H12)>0.0001,I$10>$C$5),4,IF(H50=4,3,IF(H50=3,2,IF(H50=2,1,0)))) -> 4 | J50: =IF(AND(ABS((J12-I12)-('Baseline NFPC'!J12-'Baseline NFPC'!I12))>0.0001,ABS(J12-I12)>0.0001,J$10>$C$5),4,IF(I50=4,3,IF(I50=3,2,IF(I50=2,1,0)))) -> 4 | K50: =IF(AND(ABS((K12-J12)-('Baseline NFPC'!K12-'Baseline NFPC'!J12))>0.0001,ABS(K12-J12)>0.0001,K$10>$C$5),4,IF(J50=4,3,IF(J50=3,2,IF(J50=2,1,0)))) -> 3 | L50: =IF(AND(ABS((L12-K12)-('Baseline NFPC'!L12-'Baseline NFPC'!K12))>0.0001,ABS(L12-K12)>0.0001,L$10>$C$5),4,IF(K50=4,3,IF(K50=3,2,IF(K50=2,1,0)))) -> 2 | M50: =IF(AND(ABS((M12-L12)-('Baseline NFPC'!M12-'Baseline NFPC'!L12))>0.0001,ABS(M12-L12)>0.0001,M$10>$C$5),4,IF(L50=4,3,IF(L50=3,2,IF(L50=2,1,0)))) -> 1 | N50: =IF(AND(ABS((N12-M12)-('Baseline NFPC'!N12-'Baseline NFPC'!M12))>0.0001,ABS(N12-M12)>0.0001,N$10>$C$5),4,IF(M50=4,3,IF(M50=3,2,IF(M50=2,1,0)))) -> 0 | ... W50: =IF(AND(ABS((W12-V12)-('Baseline NFPC'!W12-'Baseline NFPC'!V12))>0.0001,ABS(W12-V12)>0.0001,W$10>$C$5),4,IF(V50=4,3,IF(V50=3,2,IF(V50=2,1,0)))) -> 0
B51: OG intermediate auxiliary value | C51: 0 | D51: 0 | E51: =IF(D50=4,2/3*(D30-'Baseline NFPC'!D29),IF(D50=3,1/3*(C30-'Baseline NFPC'!C29),0)) -> 0 | F51: =IF(E50=4,2/3*(E30-'Baseline NFPC'!E29),IF(E50=3,1/3*(D30-'Baseline NFPC'!D29),0)) -> 0 | G51: =IF(F50=4,2/3*(F30-'Baseline NFPC'!F29),IF(F50=3,1/3*(E30-'Baseline NFPC'!E29),0)) -> 0 | H51: =IF(G50=4,2/3*(G30-'Baseline NFPC'!G29),IF(G50=3,1/3*(F30-'Baseline NFPC'!F29),0)) -> -0.26230517 | I51: =IF(H50=4,2/3*H30,IF(H50=3,1/3*G30,0)) -> -0.42222089 | J51: =IF(I50=4,2/3*I30,IF(I50=3,1/3*H30,0)) -> -0.545262 | K51: =IF(J50=4,2/3*J30,IF(J50=3,1/3*I30,0)) -> -0.62705298 | L51: =IF(K50=4,2/3*K30,IF(K50=3,1/3*J30,0)) -> -0.31352649 | M51: =IF(L50=4,2/3*L30,IF(L50=3,1/3*K30,0)) -> 0 | N51: =IF(M50=4,2/3*M30,IF(M50=3,1/3*L30,0)) -> 0 | O51: =IF(N50=4,2/3*N30,IF(N50=3,1/3*M30,0)) -> 0 | P51: =IF(O50=4,2/3*O30,IF(O50=3,1/3*N30,0)) -> 0 | ... W51: =IF(V50=4,2/3*V30,IF(V50=3,1/3*U30,0)) -> 0
B52: GDP intermediate growth rate - only feedback effect and no closure of the OG | D52: ='Input data'!D30-$C$47*((D12-C12)-('Input data'!D13-'Input data'!C13)) -> 4.260908 | E52: ='Input data'!E30-$C$47*((E12-D12)-('Input data'!E13-'Input data'!D13)) -> -0.9462205 | F52: ='Input data'!F30-$C$47*((F12-E12)-('Input data'!F13-'Input data'!E13)) -> 0.584996 | G52: ='Input data'!G30-$C$47*(G12-F12) -> 1.216716 | H52: ='Input data'!H30-$C$47*(H12-G12) -> 2.649951 | I52: ='Input data'!I30-$C$47*(I12-H12) -> 1.29729 | J52: ='Input data'!J30-$C$47*(J12-I12) -> 1.199467 | K52: ='Input data'!K30-$C$47*(K12-J12) -> 1.566761 | L52: ='Input data'!L30-$C$47*(L12-K12) -> 1.78318 | M52: ='Input data'!M30-$C$47*(M12-L12) -> 1.910635 | N52: ='Input data'!N30-$C$47*(N12-M12) -> 1.917179 | ... W52: ='Input data'!W30-$C$47*(W12-V12) -> 1.601132
B54: Debt projections
C56: 2021 | D56: 2022 | E56: 2023 | F56: 2024 | G56: 2025 | H56: 2026 | I56: 2027 | J56: 2028 | K56: 2029 | L56: 2030 | M56: 2031 | N56: 2032 | O56: 2033 | P56: 2034 | Q56: 2035 | R56: 2036 | S56: 2037 | T56: 2038 | U56: 2039 | V56: 2040 | W56: 2041
B57: Gross debt | C57: =+'Input data'!C12 -> 76.21938 | D57: =+C57+D58 -> 73.842909 | E57: =+D57+E58 -> 73.437974 | F57: =+E57+F58 -> 74.041486 | G57: =+F57+G58 -> 73.48544 | H57: =+G57+H58 -> 71.299226 | I57: =+H57+I58 -> 69.930407 | J57: =+I57+J58 -> 68.203983 | K57: =+J57+K58 -> 66.186518 | ... W57: =+V57+W58 -> 55.283325
B58: Change in debt (-1+2+3) | D58: =-D59+D67+D72 -> -2.376471 | E58: =-E59+E67+E72 -> -0.40493547 | F58: =-F59+F67+F72 -> 0.60351226 | G58: =-G59+G67+G72 -> -0.55604531 | H58: =-H59+H67+H72 -> -2.1862145 | I58: =-I59+I67+I72 -> -1.3688194 | J58: =-J59+J67+J72 -> -1.7264232 | K58: =-K59+K67+K72 -> -2.0174652 | ... W58: =-W59+W67+W72 -> 0.55388893
B59: (1) Primary balance (1.1 + 1.2 - 1.3 -1.4 -1.5 - 1.6 -1.7) | D59: =D60+D61-D62-D63-D64-D65-D66 -> -3.368615 | E59: =E60+E61-E62-E63-E64-E65-E66 -> -1.9656285 | F59: =F60+F61-F62-F63-F64-F65-F66 -> 0.026428741 | G59: =G60+G61-G62-G63-G64-G65-G66 -> 0.42688419 | H59: =H60+H61-H62-H63-H64-H65-H66 -> 1.4355424 | I59: =I60+I61-I62-I63-I64-I65-I66 -> 1.8919359 | J59: =J60+J61-J62-J63-J64-J65-J66 -> 2.376359 | K59: =K60+K61-K62-K63-K64-K65-K66 -> 2.4761035 | ... W59: =W60+W61-W62-W63-W64-W65-W66 -> 0.30855746
B60: (1.1) Structural primary balance (before ageing cost) | D60: =D12 -> -4.391969 | E60: =E12 -> -1.706974 | F60: =F12 -> 0.64244146 | G60: =IF(G12="",F60,G12) -> 1.1824415 | H60: =IF(H12="",G60,H12) -> 1.7224415 | I60: =IF(I12="",H60,I12) -> 2.2624415 | J60: =IF(J12="",I60,J12) -> 2.8024415 | K60: =IF(K12="",J60,K12) -> 2.8024415 | L60: =IF(L12="",K60,L12) -> 2.8024415 | M60: =IF(M12="",L60,M12) -> 2.8024415 | N60: =IF(N12="",M60,N12) -> 2.8024415 | ... W60: =IF(W12="",V60,W12) -> 2.8024415
B61: (1.2) Cumulated budgetary effort (in terms of primary balance) | D61: 0 | E61: 0 | F61: 0 | G61: 0 | H61: 0 | I61: 0 | J61: 0 | K61: 0 | L61: 0 | M61: 0 | N61: 0 | O61: 0 | P61: 0 | Q61: 0 | R61: 0 | S61: 0 | T61: 0 | U61: 0 | V61: 0 | W61: 0
B62: (1.3) Cyclical component | D62: =-$C$48*D30 -> -1.023354 | E62: =-$C$48*E30 -> 0.25865453 | F62: =-$C$48*F30 -> 0.61601271 | G62: =-$C$48*G30 -> 0.75555726 | H62: =-$C$48*H30 -> 0.2868991 | I62: =-$C$48*I30 -> 0.37050553 | J62: =-$C$48*J30 -> 0.4260825 | K62: =-$C$48*K30 -> 0.284055 | ... W62: =-$C$48*W30 -> -4.006157e-06
B63: (1.4) One-off and other temporary measures | D63: =-D14 -> 0 | E63: =-E14 -> 0 | F63: =-F14 -> 0 | G63: =-G14 -> 0 | H63: =-H14 -> 0 | I63: =-I14 -> 0 | J63: =-J14 -> 0 | K63: =-K14 -> 0 | ... W63: =-W14 -> 0
B64: (1.5) Cost of ageing | D64: =IF(D$56<=$C$6,0,HLOOKUP(D$56,'Input data'!$C$9:$BB$26,12,FALSE)-HLOOKUP($C$6,'Input data'!$C$9:$BB$26,12,FALSE)) -> 0 | E64: =IF(E$56<=$C$6,0,HLOOKUP(E$56,'Input data'!$C$9:$BB$26,12,FALSE)-HLOOKUP($C$6,'Input data'!$C$9:$BB$26,12,FALSE)) -> 0 | F64: =IF(F$56<=$C$6,0,HLOOKUP(F$56,'Input data'!$C$9:$BB$26,12,FALSE)-HLOOKUP($C$6,'Input data'!$C$9:$BB$26,12,FALSE)) -> 0 | G64: =IF(G$56<=$C$6,0,HLOOKUP(G$56,'Input data'!$C$9:$BB$26,12,FALSE)-HLOOKUP($C$6,'Input data'!$C$9:$BB$26,12,FALSE)) -> 0 | H64: =IF(H$56<=$C$6,0,HLOOKUP(H$56,'Input data'!$C$9:$BB$26,12,FALSE)-HLOOKUP($C$6,'Input data'!$C$9:$BB$26,12,FALSE)) -> 0 | I64: =IF(I$56<=$C$6,0,HLOOKUP(I$56,'Input data'!$C$9:$BB$26,12,FALSE)-HLOOKUP($C$6,'Input data'!$C$9:$BB$26,12,FALSE)) -> 0 | J64: =IF(J$56<=$C$6,0,HLOOKUP(J$56,'Input data'!$C$9:$BB$26,12,FALSE)-HLOOKUP($C$6,'Input data'!$C$9:$BB$26,12,FALSE)) -> 0 | K64: =IF(K$56<=$C$6,0,HLOOKUP(K$56,'Input data'!$C$9:$BB$26,12,FALSE)-HLOOKUP($C$6,'Input data'!$C$9:$BB$26,12,FALSE)) -> 0.01232 | ... W64: =IF(W$56<=$C$6,0,HLOOKUP(W$56,'Input data'!$C$9:$BB$26,12,FALSE)-HLOOKUP($C$6,'Input data'!$C$9:$BB$26,12,FALSE)) -> 2.10437
B65: (1.6) Property incomes | D65: =IF(D$56<=$C$5,0,-HLOOKUP(D$56,'Input data'!$C$9:$BB$26,18,FALSE)+HLOOKUP($C$6,'Input data'!$C$9:$BB$26,18,FALSE)) -> 0 | E65: =IF(E$56<=$C$5,0,-HLOOKUP(E$56,'Input data'!$C$9:$BB$26,18,FALSE)+HLOOKUP($C$6,'Input data'!$C$9:$BB$26,18,FALSE)) -> 0 | F65: =IF(F$56<=$C$5,0,-HLOOKUP(F$56,'Input data'!$C$9:$BB$26,18,FALSE)+HLOOKUP($C$6,'Input data'!$C$9:$BB$26,18,FALSE)) -> 0 | G65: =IF(G$56<=$C$6,0,-HLOOKUP(G$56,'Input data'!$C$9:$BB$26,18,FALSE)+HLOOKUP($C$6,'Input data'!$C$9:$BB$26,18,FALSE)) -> 0 | H65: =IF(H$56<=$C$6,0,-HLOOKUP(H$56,'Input data'!$C$9:$BB$26,18,FALSE)+HLOOKUP($C$6,'Input data'!$C$9:$BB$26,18,FALSE)) -> 0 | I65: =IF(I$56<=$C$6,0,-HLOOKUP(I$56,'Input data'!$C$9:$BB$26,18,FALSE)+HLOOKUP($C$6,'Input data'!$C$9:$BB$26,18,FALSE)) -> 0 | J65: =IF(J$56<=$C$6,0,-HLOOKUP(J$56,'Input data'!$C$9:$BB$26,18,FALSE)+HLOOKUP($C$6,'Input data'!$C$9:$BB$26,18,FALSE)) -> 0 | K65: =IF(K$56<=$C$6,0,-HLOOKUP(K$56,'Input data'!$C$9:$BB$26,18,FALSE)+HLOOKUP($C$6,'Input data'!$C$9:$BB$26,18,FALSE)) -> 0.029963 | L65: =IF(L$56<=$C$6,0,-HLOOKUP(L$56,'Input data'!$C$9:$BB$26,18,FALSE)+HLOOKUP($C$6,'Input data'!$C$9:$BB$26,18,FALSE)) -> 0.059926 | M65: =IF(M$56<=$C$6,0,-HLOOKUP(M$56,'Input data'!$C$9:$BB$26,18,FALSE)+HLOOKUP($C$6,'Input data'!$C$9:$BB$26,18,FALSE)) -> 0.089889 | N65: =IF(N$56<=$C$6,0,-HLOOKUP(N$56,'Input data'!$C$9:$BB$26,18,FALSE)+HLOOKUP($C$6,'Input data'!$C$9:$BB$26,18,FALSE)) -> 0.119852 | ... W65: =IF(W$56<=$C$6,0,-HLOOKUP(W$56,'Input data'!$C$9:$BB$26,18,FALSE)+HLOOKUP($C$6,'Input data'!$C$9:$BB$26,18,FALSE)) -> 0.389518
B66: (1.7) Revenues | D66: 0 | E66: 0 | F66: 0 | G66: 0 | H66: 0 | I66: 0 | J66: 0 | K66: 0 | L66: 0 | M66: 0 | N66: 0 | O66: 0 | P66: 0 | Q66: 0 | R66: 0 | S66: 0 | T66: 0 | U66: 0 | V66: 0 | W66: 0
B67: (2) Snowball effect (2.1 + 2.2 + 2.3) | D67: =SUM(D68:D71) -> -9.284277 | E67: =SUM(E68:E71) -> -4.088016 | F67: =SUM(F68:F71) -> -0.3415279 | G67: =SUM(G68:G71) -> 0.26926648 | H67: =SUM(H68:H71) -> -0.50009587 | I67: =SUM(I68:I71) -> 0.52311653 | J67: =SUM(J68:J71) -> 0.6499358 | K67: =SUM(K68:K71) -> 0.45863829 | ... W67: =SUM(W68:W71) -> 0.86244639
B68: (2.1) Interest expenditure | D68: =C57*D36/100*(1/(1+D33/100)) -> 2.8271173 | E68: =D57*E36/100*(1/(1+E33/100)) -> 4.7401102 | F68: =E57*F36/100*(1/(1+F33/100)) -> 4.9260348 | G68: =F57*G36/100*(1/(1+G33/100)) -> 3.9890456 | H68: =G57*H36/100*(1/(1+H33/100)) -> 3.9021218 | I68: =H57*I36/100*(1/(1+I33/100)) -> 3.9148931 | J68: =I57*J36/100*(1/(1+J33/100)) -> 3.9140644 | K68: =J57*K36/100*(1/(1+K33/100)) -> 3.8647508 | ... W68: =V57*W36/100*(1/(1+W33/100)) -> 3.2905673
B69: (2.2) Growth effect | D69: =-C57*(D24/100)*(1/(1+D33/100)) -> -2.7269286 | E69: =-D57*(E24/100)*(1/(1+E33/100)) -> 0.6157029 | F69: =-E57*(F24/100)*(1/(1+F33/100)) -> -0.3984863 | G69: =-F57*(G24/100)*(1/(1+G33/100)) -> -0.85526304 | H69: =-G57*(H24/100)*(1/(1+H33/100)) -> -1.9280864 | I69: =-H57*(I24/100)*(1/(1+I33/100)) -> -1.0323999 | J69: =-I57*(J24/100)*(1/(1+J33/100)) -> -0.99045461 | K69: =-J57*(K24/100)*(1/(1+K33/100)) -> -1.2280267 | ... W69: =-V57*(W24/100)*(1/(1+W33/100)) -> -0.83741309
B70: (2.3) Inflation effect | D70: =-C57*D42/100*(1/(1+D42/100)) -> -9.4936852 | E70: =-D57*E42/100*(1/(1+E42/100)) -> -9.3889052 | F70: =-E57*F42/100*(1/(1+F42/100)) -> -4.9217051 | G70: =-F57*G42/100*(1/(1+G42/100)) -> -2.8934805 | H70: =-G57*H42/100*(1/(1+H42/100)) -> -2.4741313 | I70: =-H57*I42/100*(1/(1+I42/100)) -> -2.3593766 | J70: =-I57*J42/100*(1/(1+J42/100)) -> -2.273674 | K70: =-J57*K42/100*(1/(1+K42/100)) -> -2.1780858 | ... W70: =-V57*W42/100*(1/(1+W42/100)) -> -1.5907078
B71: (2.4) Exchange rate effect linked to the interest rate | D71: ='Baseline NFPC'!D70 -> 0.10921937 | E71: ='Baseline NFPC'!E70 -> -0.05492389 | F71: ='Baseline NFPC'!F70 -> 0.052628707 | G71: ='Baseline NFPC'!G70 -> 0.028964404 | H71: 0 | I71: 0 | J71: 0 | K71: 0 | L71: 0 | M71: 0 | N71: 0 | O71: 0 | P71: 0 | Q71: 0 | R71: 0 | S71: 0 | T71: 0 | U71: 0 | V71: 0 | W71: 0
B72: (3 ) Stock flow adjustments (3.1 + 3.2) | D72: ='Input data'!D16 -> 3.539191 | E72: ='Input data'!E16 -> 1.717452 | F72: ='Input data'!F16 -> 0.9714689 | G72: ='Input data'!G16 -> -0.3984276 | H72: ='Input data'!H16 -> -0.2505763 | I72: ='Input data'!I16 -> 0 | J72: ='Input data'!J16 -> 0 | K72: ='Input data'!K16 -> 0 | ... W72: ='Input data'!W16 -> 0
B73: (3.1) Base | D73: =D15 -> 1.066777 | E73: =E15 -> 2.471388 | F73: =F15 -> 0.243711 | G73: =G15 -> -0.9088278 | H73: =H15 -> -0.250576 | I73: =I15 -> 0 | J73: =J15 -> 0 | K73: =K15 -> 0 | ... W73: =W15 -> 0
B74: (3.2) Adjustment due to the exchange rate effect linked to debt value | D74: =+D72-D73 -> 2.472414 | E74: =+E72-E73 -> -0.753936 | F74: =+F72-F73 -> 0.7277579 | G74: =+G72-G73 -> 0.5104002 | H74: =+H72-H73 -> -3e-07 | I74: =+I72-I73 -> 0 | J74: =+J72-J73 -> 0 | K74: =+K72-K73 -> 0 | ... W74: =+W72-W73 -> 0
B76: Other budgetary variables
B77: Headline balance | D77: =D59-D68 -> -6.1957323 | E77: =E59-E68 -> -6.7057387 | F77: =F59-F68 -> -4.8996061 | G77: =G59-G68 -> -3.5621614 | H77: =H59-H68 -> -2.4665795 | I77: =I59-I68 -> -2.0229571 | J77: =J59-J68 -> -1.5377055 | K77: =K59-K68 -> -1.3886474 | ... W77: =W59-W68 -> -2.9820098
B78: Structural balance | D78: =D60-D68-D64-D65-D66 -> -7.2190863 | E78: =E60-E68-E64-E65-E66 -> -6.4470842 | F78: =F60-F68-F64-F65-F66 -> -4.2835934 | G78: =G60-G68-G64-G65-G66 -> -2.8066042 | H78: =H60-H68-H64-H65-H66 -> -2.1796804 | I78: =I60-I68-I64-I65-I66 -> -1.6524516 | J78: =J60-J68-J64-J65-J66 -> -1.111623 | K78: =K60-K68-K64-K65-K66 -> -1.1045924 | ... W78: =W60-W68-W64-W65-W66 -> -2.9820139
B79: Net expenditure growth | D79: ='Input data'!D45 -> 22.282169 | E79: ='Input data'!E45 -> 8.9931862 | F79: ='Input data'!F45 -> 4.6 | G79: ='Input data'!G33+G42-(G$12-F$12)/'Input data'!$C$64*100 -> 4.3473229 | H79: ='Input data'!H33+H42-(H$12-G$12)/'Input data'!$C$64*100 -> 3.9515589 | I79: ='Input data'!I33+I42-(I$12-H$12)/'Input data'!$C$64*100 -> 3.8782647 | J79: ='Input data'!J33+J42-(J$12-I$12)/'Input data'!$C$64*100 -> 3.7186626 | K79: ='Input data'!K33+K42-(K$12-J$12)/'Input data'!$C$64*100 -> 4.8725166 | L79: ='Input data'!L33+L42-(L$12-K$12)/'Input data'!$C$64*100 -> 5.0202485 | M79: ='Input data'!M33+M42-(M$12-L$12)/'Input data'!$C$64*100 -> 5.0859394 | N79: ='Input data'!N33+N42-(N$12-M$12)/'Input data'!$C$64*100 -> 5.0307103 | ... W79: ='Input data'!W33+W42-(W$12-V$12)/'Input data'!$C$64*100 -> 4.594632
B81: Average net primary expenditure growth | D81: =AVERAGE(OFFSET($G$79,0,0,1,'Criteria results'!F5)) -> 3.9739523
B83: Debt increasing? (For criterion 1) | K83: =IF(K57<J57,0,1) -> 0 | L83: =IF(L57<K57,0,1) -> 0 | M83: =IF(M57<L57,0,1) -> 0 | N83: =IF(N57<M57,0,1) -> 0 | O83: =IF(O57<N57,0,1) -> 0 | P83: =IF(P57<O57,0,1) -> 0 | Q83: =IF(Q57<P57,0,1) -> 0 | R83: =IF(R57<Q57,0,1) -> 0 | ... W83: =IF(W57<V57,0,1) -> 1
B84: Debt above 90% (for debt sustainability safeguard) | F84: =IF(F57>90,1,0) -> 0 | G84: =IF(G57>90,1,0) -> 0 | H84: =IF(H57>90,1,0) -> 0 | I84: =IF(I57>90,1,0) -> 0 | J84: =IF(J57>90,1,0) -> 0 | K84: =IF(K57>90,1,0) -> 0 | L84: =IF(L57>90,1,0) -> 0 | M84: =IF(M57>90,1,0) -> 0 | ... W84: =IF(W57>90,1,0) -> 0
B85: Debt between 60% and 90% (for debt sustainability safeguard) | F85: =IF(AND(F57>60,F57<=90),1,0) -> 1 | G85: =IF(AND(G57>60,G57<=90),1,0) -> 1 | H85: =IF(AND(H57>60,H57<=90),1,0) -> 1 | I85: =IF(AND(I57>60,I57<=90),1,0) -> 1 | J85: =IF(AND(J57>60,J57<=90),1,0) -> 1 | K85: =IF(AND(K57>60,K57<=90),1,0) -> 1 | L85: =IF(AND(L57>60,L57<=90),1,0) -> 1 | M85: =IF(AND(M57>60,M57<=90),1,0) -> 1 | ... W85: =IF(AND(W57>60,W57<=90),1,0) -> 0
B86: Debt above 60% (for debt sustainability safeguard) | F86: =IF(F57>60,1,0) -> 1 | G86: =IF(G57>60,1,0) -> 1 | H86: =IF(H57>60,1,0) -> 1 | I86: =IF(I57>60,1,0) -> 1 | J86: =IF(J57>60,1,0) -> 1 | K86: =IF(K57>60,1,0) -> 1 | L86: =IF(L57>60,1,0) -> 1 | M86: =IF(M57>60,1,0) -> 1 | ... W86: =IF(W57>60,1,0) -> 0
B87: Deficit exceeding 3% / under EDP (for deficit benchmark and debt sustainability safeguard) | F87: ='Input data'!F17 -> 1 | G87: =IF(F87=0,0,IF(AND(E77>-3.05,F77>-3.05),0,1)) -> 1 | H87: =IF(G87=0,0,IF(AND(F77>-3.05,G77>-3.05),0,1)) -> 1 | I87: =IF(H87=0,0,IF(AND(G77>-3.05,H77>-3.05),0,1)) -> 1 | J87: =IF(I87=0,0,IF(AND(H77>-3.05,I77>-3.05),0,1)) -> 0 | K87: =IF(J87=0,0,IF(AND(I77>-3.05,J77>-3.05),0,1)) -> 0 | L87: =IF(K87=0,0,IF(AND(J77>-3.05,K77>-3.05),0,1)) -> 0 | M87: =IF(L87=0,0,IF(AND(K77>-3.05,L77>-3.05),0,1)) -> 0 | N87: =IF(M87=0,0,IF(AND(L77>-3.05,M77>-3.05),0,1)) -> 0 | ... W87: =IF(V87=0,0,IF(AND(U77>-3.05,V77>-3.05),0,1)) -> 0
B88: Structural balance ensuring safety margin (for deficit resilience safeguard) | F88: =IF(F78>=-1.55,1,0) -> 0 | G88: =IF(G78>=-1.55,1,0) -> 0 | H88: =IF(H78>=-1.55,1,0) -> 0 | I88: =IF(I78>=-1.55,1,0) -> 0 | J88: =IF(J78>=-1.55,1,0) -> 1 | K88: =IF(K78>=-1.55,1,0) -> 1 | L88: =IF(L78>=-1.55,1,0) -> 1 | M88: =IF(M78>=-1.55,1,0) -> 1 | ... W88: =IF(W78>=-1.55,1,0) -> 0
B90: Approximation of interest payments in % GDP | F90: =E57*F36/100*(1/((1+'Input data'!F30/100)*(1+F42/100))) -> 4.9260348 | G90: =F57*G36/100*(1/((1+'Input data'!G30/100)*(1+G42/100))) -> 3.9731478 | H90: =G57*H36/100*(1/((1+'Input data'!H30/100)*(1+H42/100))) -> 3.892126 | I90: =H57*I36/100*(1/((1+'Input data'!I30/100)*(1+I42/100))) -> 3.9078878 | J90: =I57*J36/100*(1/((1+'Input data'!J30/100)*(1+J42/100))) -> 3.9094888 | K90: =J57*K36/100*(1/((1+'Input data'!K30/100)*(1+K42/100))) -> 3.877247 | L90: =K57*L36/100*(1/((1+'Input data'!L30/100)*(1+L42/100))) -> 3.8109977 | M90: =L57*M36/100*(1/((1+'Input data'!M30/100)*(1+M42/100))) -> 3.7337836 | ... W90: =V57*W36/100*(1/((1+'Input data'!W30/100)*(1+W42/100))) -> 3.2905673
B91: Change in interest payments (for deficit benchmark in SB terms from 2028 onwards) | G91: =G90-F90 -> -0.952887 | H91: =H90-G90 -> -0.081021817 | I91: =I90-H90 -> 0.015761758 | J91: =J90-I90 -> 0.0016010851 | K91: =K90-J90 -> -0.032241809 | L91: =L90-K90 -> -0.066249307 | M91: =M90-L90 -> -0.077214112 | N91: =N90-M90 -> -0.081554483 | ... W91: =W90-V90 -> -0.0040956312
B93: Debt decomposition and IIR
B95: Auxiliary variable identifying whether debt is increasing | F95: =IF((F100-E100*F43/((1+F24/100)*(1+F42/100)))>0,1,0) -> 1 | G95: =IF((G100-F100*G43/((1+G24/100)*(1+G42/100)))>0,1,0) -> 1 | H95: =IF((H100-G100*H43/((1+H24/100)*(1+H42/100)))>0,1,0) -> 1 | I95: =IF((I100-H100*I43/((1+I24/100)*(1+I42/100)))>0,1,0) -> 1 | J95: =IF((J100-I100*J43/((1+J24/100)*(1+J42/100)))>0,1,0) -> 1 | K95: =IF((K100-J100*K43/((1+K24/100)*(1+K42/100)))>0,1,0) -> 1 | L95: =IF((L100-K100*L43/((1+L24/100)*(1+L42/100)))>0,1,0) -> 1 | M95: =IF((M100-L100*M43/((1+M24/100)*(1+M42/100)))>0,1,0) -> 1 | ... W95: =IF((W100-V100*W43/((1+W24/100)*(1+W42/100)))>0,1,0) -> 1
B96: Auxiliary variable identifying whether some debt is rolled over even though debt is decreasing | F96: =IF(AND(F95=0,ABS(F100-E100*F43/((1+F24/100)*(1+F42/100)))<((E106*E100*F43/((1+F24/100)*(1+F42/100))+(F39*E100*E107*F43/((1+F24/100)*(1+F42/100)))))),1,0) -> 0 | G96: =IF(AND(G95=0,ABS(G100-F100*G43/((1+G24/100)*(1+G42/100)))<((F106*F100*G43/((1+G24/100)*(1+G42/100))+(G39*F100*F107*G43/((1+G24/100)*(1+G42/100)))))),1,0) -> 0 | H96: =IF(AND(H95=0,ABS(H100-G100*H43/((1+H24/100)*(1+H42/100)))<((G106*G100*H43/((1+H24/100)*(1+H42/100))+(H39*G100*G107*H43/((1+H24/100)*(1+H42/100)))))),1,0) -> 0 | I96: =IF(AND(I95=0,ABS(I100-H100*I43/((1+I24/100)*(1+I42/100)))<((H106*H100*I43/((1+I24/100)*(1+I42/100))+(I39*H100*H107*I43/((1+I24/100)*(1+I42/100)))))),1,0) -> 0 | J96: =IF(AND(J95=0,ABS(J100-I100*J43/((1+J24/100)*(1+J42/100)))<((I106*I100*J43/((1+J24/100)*(1+J42/100))+(J39*I100*I107*J43/((1+J24/100)*(1+J42/100)))))),1,0) -> 0 | K96: =IF(AND(K95=0,ABS(K100-J100*K43/((1+K24/100)*(1+K42/100)))<((J106*J100*K43/((1+K24/100)*(1+K42/100))+(K39*J100*J107*K43/((1+K24/100)*(1+K42/100)))))),1,0) -> 0 | L96: =IF(AND(L95=0,ABS(L100-K100*L43/((1+L24/100)*(1+L42/100)))<((K106*K100*L43/((1+L24/100)*(1+L42/100))+(L39*K100*K107*L43/((1+L24/100)*(1+L42/100)))))),1,0) -> 0 | M96: =IF(AND(M95=0,ABS(M100-L100*M43/((1+M24/100)*(1+M42/100)))<((L106*L100*M43/((1+M24/100)*(1+M42/100))+(M39*L100*L107*M43/((1+M24/100)*(1+M42/100)))))),1,0) -> 0 | ... W96: =IF(AND(W95=0,ABS(W100-V100*W43/((1+W24/100)*(1+W42/100)))<((V106*V100*W43/((1+W24/100)*(1+W42/100))+(W39*V100*V107*W43/((1+W24/100)*(1+W42/100)))))),1,0) -> 0
C99: 2021 | D99: 2022 | E99: 2023 | F99: 2024 | G99: 2025 | H99: 2026 | I99: 2027 | J99: 2028 | K99: 2029 | L99: 2030 | M99: 2031 | N99: 2032 | O99: 2033 | P99: 2034 | Q99: 2035 | R99: 2036 | S99: 2037 | T99: 2038 | U99: 2039 | V99: 2040 | W99: 2041
B100: Gross debt | C100: =C57 -> 76.21938 | D100: =D57 -> 73.842909 | E100: =E57 -> 73.437974 | F100: =F57 -> 74.041486 | G100: =G57 -> 73.48544 | H100: =G100*(1+H114/100)*H43-H60-H61+H62+H63+H64+H65+H66+H73 -> 71.299226 | I100: =H100*(1+I114/100)*I43-I60-I61+I62+I63+I64+I65+I66+I73 -> 69.930407 | J100: =I100*(1+J114/100)*J43-J60-J61+J62+J63+J64+J65+J66+J73 -> 68.203984 | K100: =J100*(1+K114/100)*K43-K60-K61+K62+K63+K64+K65+K66+K73 -> 66.186519 | L100: =K100*(1+L114/100)*L43-L60-L61+L62+L63+L64+L65+L66+L73 -> 64.043964 | M100: =L100*(1+M114/100)*M43-M60-M61+M62+M63+M64+M65+M66+M73 -> 61.862434 | N100: =M100*(1+N114/100)*N43-N60-N61+N62+N63+N64+N65+N66+N73 -> 60.070269 | O100: =N100*(1+O114/100)*O43-O60-O61+O62+O63+O64+O65+O66+O73 -> 58.543638 | ... W100: =V100*(1+W114/100)*W43-W60-W61+W62+W63+W64+W65+W66+W73 -> 55.283325
B101: Of which Outstanding debt | E101: ='Input data'!$C$66*E$100 -> 54.96332 | F101: =IF(F100=0,0,IF(F95=1,E100*F43/((1+F24/100)*(1+F42/100))-F102-F103,IF(AND(F95=0,F96=1),(1-E106-F39*E107)*E100*F43/((1+F24/100)*(1+F42/100)),F100))) -> 57.782728 | G101: =IF(G100=0,0,IF(G95=1,F100*G43/((1+G24/100)*(1+G42/100))-G102-G103,IF(AND(G95=0,G96=1),(1-F106-G39*F107)*F100*G43/((1+G24/100)*(1+G42/100)),G100))) -> 59.427396 | H101: =IF(H100=0,0,IF(H95=1,G100*H43/((1+H24/100)*(1+H42/100))-H102-H103,IF(AND(H95=0,H96=1),(1-G106-H39*G107)*G100*H43/((1+H24/100)*(1+H42/100)),H100))) -> 57.951691 | I101: =IF(I100=0,0,IF(I95=1,H100*I43/((1+I24/100)*(1+I42/100))-I102-I103,IF(AND(I95=0,I96=1),(1-H106-I39*H107)*H100*I43/((1+I24/100)*(1+I42/100)),I100))) -> 56.926949 | J101: =IF(J100=0,0,IF(J95=1,I100*J43/((1+J24/100)*(1+J42/100))-J102-J103,IF(AND(J95=0,J96=1),(1-I106-J39*I107)*I100*J43/((1+J24/100)*(1+J42/100)),J100))) -> 55.846119 | K101: =IF(K100=0,0,IF(K95=1,J100*K43/((1+K24/100)*(1+K42/100))-K102-K103,IF(AND(K95=0,K96=1),(1-J106-K39*J107)*J100*K43/((1+K24/100)*(1+K42/100)),K100))) -> 54.236103 | L101: =IF(L100=0,0,IF(L95=1,K100*L43/((1+L24/100)*(1+L42/100))-L102-L103,IF(AND(L95=0,L96=1),(1-K106-L39*K107)*K100*L43/((1+L24/100)*(1+L42/100)),L100))) -> 52.510398 | M101: =IF(M100=0,0,IF(M95=1,L100*M43/((1+M24/100)*(1+M42/100))-M102-M103,IF(AND(M95=0,M96=1),(1-L106-M39*L107)*L100*M43/((1+M24/100)*(1+M42/100)),M100))) -> 50.733046 | ... W101: =IF(W100=0,0,IF(W95=1,V100*W43/((1+W24/100)*(1+W42/100))-W102-W103,IF(AND(W95=0,W96=1),(1-V106-W39*V107)*V100*W43/((1+W24/100)*(1+W42/100)),W100))) -> 43.708928
B102: Rolled over long-term debt | E102: ='Input data'!$C$67*E$100 -> 2.9208599 | F102: =IF(F100=0,0,IF(F95=1,F39*E100*E107*F43/((1+F24/100)*(1+F42/100)),IF(AND(F95=0,F96=1),(F39*E100*E107*F43/((1+F24/100)*(1+F42/100)))*(1-ABS(F100-E100*F43/((1+F24/100)*(1+F42/100)))/((F39*E100*E107*F43/((1+F24/100)*(1+F42/100)))+(E106*E100*F43/((1+F24/100)*(1+F42/100))))),0))) -> 4.1782685 | G102: =IF(G100=0,0,IF(G95=1,G39*F100*F107*G43/((1+G24/100)*(1+G42/100)),IF(AND(G95=0,G96=1),(G39*F100*F107*G43/((1+G24/100)*(1+G42/100)))*(1-ABS(G100-F100*G43/((1+G24/100)*(1+G42/100)))/((G39*F100*F107*G43/((1+G24/100)*(1+G42/100)))+(F106*F100*G43/((1+G24/100)*(1+G42/100))))),0))) -> 4.3699962 | H102: =IF(H100=0,0,IF(H95=1,H39*G100*G107*H43/((1+H24/100)*(1+H42/100)),IF(AND(H95=0,H96=1),(H39*G100*G107*H43/((1+H24/100)*(1+H42/100)))*(1-ABS(H100-G100*H43/((1+H24/100)*(1+H42/100)))/((H39*G100*G107*H43/((1+H24/100)*(1+H42/100)))+(G106*G100*H43/((1+H24/100)*(1+H42/100))))),0))) -> 4.3326364 | I102: =IF(I100=0,0,IF(I95=1,I39*H100*H107*I43/((1+I24/100)*(1+I42/100)),IF(AND(I95=0,I96=1),(I39*H100*H107*I43/((1+I24/100)*(1+I42/100)))*(1-ABS(I100-H100*I43/((1+I24/100)*(1+I42/100)))/((I39*H100*H107*I43/((1+I24/100)*(1+I42/100)))+(H106*H100*I43/((1+I24/100)*(1+I42/100))))),0))) -> 4.3260819 | J102: =IF(J100=0,0,IF(J95=1,J39*I100*I107*J43/((1+J24/100)*(1+J42/100)),IF(AND(J95=0,J96=1),(J39*I100*I107*J43/((1+J24/100)*(1+J42/100)))*(1-ABS(J100-I100*J43/((1+J24/100)*(1+J42/100)))/((J39*I100*I107*J43/((1+J24/100)*(1+J42/100)))+(I106*I100*J43/((1+J24/100)*(1+J42/100))))),0))) -> 4.3128313 | K102: =IF(K100=0,0,IF(K95=1,K39*J100*J107*K43/((1+K24/100)*(1+K42/100)),IF(AND(K95=0,K96=1),(K39*J100*J107*K43/((1+K24/100)*(1+K42/100)))*(1-ABS(K100-J100*K43/((1+K24/100)*(1+K42/100)))/((K39*J100*J107*K43/((1+K24/100)*(1+K42/100)))+(J106*J100*K43/((1+K24/100)*(1+K42/100))))),0))) -> 4.2555478 | L102: =IF(L100=0,0,IF(L95=1,L39*K100*K107*L43/((1+L24/100)*(1+L42/100)),IF(AND(L95=0,L96=1),(L39*K100*K107*L43/((1+L24/100)*(1+L42/100)))*(1-ABS(L100-K100*L43/((1+L24/100)*(1+L42/100)))/((L39*K100*K107*L43/((1+L24/100)*(1+L42/100)))+(K106*K100*L43/((1+L24/100)*(1+L42/100))))),0))) -> 4.185212 | M102: =IF(M100=0,0,IF(M95=1,M39*L100*L107*M43/((1+M24/100)*(1+M42/100)),IF(AND(M95=0,M96=1),(M39*L100*L107*M43/((1+M24/100)*(1+M42/100)))*(1-ABS(M100-L100*M43/((1+M24/100)*(1+M42/100)))/((M39*L100*L107*M43/((1+M24/100)*(1+M42/100)))+(L106*L100*M43/((1+M24/100)*(1+M42/100))))),0))) -> 4.1065636 | ... W102: =IF(W100=0,0,IF(W95=1,W39*V100*V107*W43/((1+W24/100)*(1+W42/100)),IF(AND(W95=0,W96=1),(W39*V100*V107*W43/((1+W24/100)*(1+W42/100)))*(1-ABS(W100-V100*W43/((1+W24/100)*(1+W42/100)))/((W39*V100*V107*W43/((1+W24/100)*(1+W42/100)))+(V106*V100*W43/((1+W24/100)*(1+W42/100))))),0))) -> 3.7016125
B103: Rolled over short-term debt | E103: ='Input data'!$C$68*E$100 -> 6.4315767 | F103: =IF(F100=0,0,IF(F95=1,(1-E107)*E100*F43/((1+F24/100)*(1+F42/100)),IF(AND(F95=0,F96=1),(E106*E100*F43/((1+F24/100)*(1+F42/100)))*(1-ABS(F100-E100*F43/((1+F24/100)*(1+F42/100)))/((F39*E100*E107*F43/((1+F24/100)*(1+F42/100)))+(E106*E100*F43/((1+F24/100)*(1+F42/100))))),0))) -> 6.8845562 | G103: =IF(G100=0,0,IF(G95=1,(1-F107)*F100*G43/((1+G24/100)*(1+G42/100)),IF(AND(G95=0,G96=1),(F106*F100*G43/((1+G24/100)*(1+G42/100)))*(1-ABS(G100-F100*G43/((1+G24/100)*(1+G42/100)))/((G39*F100*F107*G43/((1+G24/100)*(1+G42/100)))+(F106*F100*G43/((1+G24/100)*(1+G42/100))))),0))) -> 7.0046214 | H103: =IF(H100=0,0,IF(H95=1,(1-G107)*G100*H43/((1+H24/100)*(1+H42/100)),IF(AND(H95=0,H96=1),(G106*G100*H43/((1+H24/100)*(1+H42/100)))*(1-ABS(H100-G100*H43/((1+H24/100)*(1+H42/100)))/((H39*G100*G107*H43/((1+H24/100)*(1+H42/100)))+(G106*G100*H43/((1+H24/100)*(1+H42/100))))),0))) -> 6.7988959 | I103: =IF(I100=0,0,IF(I95=1,(1-H107)*H100*I43/((1+I24/100)*(1+I42/100)),IF(AND(I95=0,I96=1),(H106*H100*I43/((1+I24/100)*(1+I42/100)))*(1-ABS(I100-H100*I43/((1+I24/100)*(1+I42/100)))/((I39*H100*H107*I43/((1+I24/100)*(1+I42/100)))+(H106*H100*I43/((1+I24/100)*(1+I42/100))))),0))) -> 6.6544185 | J103: =IF(J100=0,0,IF(J95=1,(1-I107)*I100*J43/((1+J24/100)*(1+J42/100)),IF(AND(J95=0,J96=1),(I106*I100*J43/((1+J24/100)*(1+J42/100)))*(1-ABS(J100-I100*J43/((1+J24/100)*(1+J42/100)))/((J39*I100*I107*J43/((1+J24/100)*(1+J42/100)))+(I106*I100*J43/((1+J24/100)*(1+J42/100))))),0))) -> 6.5073284 | K103: =IF(K100=0,0,IF(K95=1,(1-J107)*J100*K43/((1+K24/100)*(1+K42/100)),IF(AND(K95=0,K96=1),(J106*J100*K43/((1+K24/100)*(1+K42/100)))*(1-ABS(K100-J100*K43/((1+K24/100)*(1+K42/100)))/((K39*J100*J107*K43/((1+K24/100)*(1+K42/100)))+(J106*J100*K43/((1+K24/100)*(1+K42/100))))),0))) -> 6.3062201 | L103: =IF(L100=0,0,IF(L95=1,(1-K107)*K100*L43/((1+L24/100)*(1+L42/100)),IF(AND(L95=0,L96=1),(K106*K100*L43/((1+L24/100)*(1+L42/100)))*(1-ABS(L100-K100*L43/((1+L24/100)*(1+L42/100)))/((L39*K100*K107*L43/((1+L24/100)*(1+L42/100)))+(K106*K100*L43/((1+L24/100)*(1+L42/100))))),0))) -> 6.0942907 | M103: =IF(M100=0,0,IF(M95=1,(1-L107)*L100*M43/((1+M24/100)*(1+M42/100)),IF(AND(M95=0,M96=1),(L106*L100*M43/((1+M24/100)*(1+M42/100)))*(1-ABS(M100-L100*M43/((1+M24/100)*(1+M42/100)))/((M39*L100*L107*M43/((1+M24/100)*(1+M42/100)))+(L106*L100*M43/((1+M24/100)*(1+M42/100))))),0))) -> 5.87863 | ... W103: =IF(W100=0,0,IF(W95=1,(1-V107)*V100*W43/((1+W24/100)*(1+W42/100)),IF(AND(W95=0,W96=1),(V106*V100*W43/((1+W24/100)*(1+W42/100)))*(1-ABS(W100-V100*W43/((1+W24/100)*(1+W42/100)))/((W39*V100*V107*W43/((1+W24/100)*(1+W42/100)))+(V106*V100*W43/((1+W24/100)*(1+W42/100))))),0))) -> 4.8907752
B104: New long-term debt | E104: ='Input data'!$C$69*E$100 -> 8.209995 | F104: =IF(F100=0,0,IF(F95=1,'Input data'!$C$58*(F100-E100*F43/((1+F24/100)*(1+F42/100))),0)) -> 4.755379 | G104: =IF(G100=0,0,IF(G95=1,'Input data'!$C$58*(G100-F100*G43/((1+G24/100)*(1+G42/100))),0)) -> 2.4559041 | H104: =IF(H100=0,0,IF(H95=1,'Input data'!$C$58*(H100-G100*H43/((1+H24/100)*(1+H42/100))),0)) -> 2.0281123 | I104: =IF(I100=0,0,IF(I95=1,'Input data'!$C$58*(I100-H100*I43/((1+I24/100)*(1+I42/100))),0)) -> 1.8514341 | J104: =IF(J100=0,0,IF(J95=1,'Input data'!$C$58*(J100-I100*J43/((1+J24/100)*(1+J42/100))),0)) -> 1.407326 | K104: =IF(K100=0,0,IF(K95=1,'Input data'!$C$58*(K100-J100*K43/((1+K24/100)*(1+K42/100))),0)) -> 1.2709063 | L104: =IF(L100=0,0,IF(L95=1,'Input data'!$C$58*(L100-K100*L43/((1+L24/100)*(1+L42/100))),0)) -> 1.1477338 | M104: =IF(M100=0,0,IF(M95=1,'Input data'!$C$58*(M100-L100*M43/((1+M24/100)*(1+M42/100))),0)) -> 1.0471804 | ... W104: =IF(W100=0,0,IF(W95=1,'Input data'!$C$58*(W100-V100*W43/((1+W24/100)*(1+W42/100))),0)) -> 2.7291703
B105: New short-term debt | E105: ='Input data'!$C$70*E$100 -> 0.91222167 | F105: =IF(F100=0,0,IF(F95=1,'Input data'!$C$57*(F100-E100*F43/((1+F24/100)*(1+F42/100))),0)) -> 0.44055435 | G105: =IF(G100=0,0,IF(G95=1,'Input data'!$C$57*(G100-F100*G43/((1+G24/100)*(1+G42/100))),0)) -> 0.22752324 | H105: =IF(H100=0,0,IF(H95=1,'Input data'!$C$57*(H100-G100*H43/((1+H24/100)*(1+H42/100))),0)) -> 0.18789117 | I105: =IF(I100=0,0,IF(I95=1,'Input data'!$C$57*(I100-H100*I43/((1+I24/100)*(1+I42/100))),0)) -> 0.1715231 | J105: =IF(J100=0,0,IF(J95=1,'Input data'!$C$57*(J100-I100*J43/((1+J24/100)*(1+J42/100))),0)) -> 0.13037943 | K105: =IF(K100=0,0,IF(K95=1,'Input data'!$C$57*(K100-J100*K43/((1+K24/100)*(1+K42/100))),0)) -> 0.11774105 | L105: =IF(L100=0,0,IF(L95=1,'Input data'!$C$57*(L100-K100*L43/((1+L24/100)*(1+L42/100))),0)) -> 0.10632993 | M105: =IF(M100=0,0,IF(M95=1,'Input data'!$C$57*(M100-L100*M43/((1+M24/100)*(1+M42/100))),0)) -> 0.097014321 | ... W105: =IF(W100=0,0,IF(W95=1,'Input data'!$C$57*(W100-V100*W43/((1+W24/100)*(1+W42/100))),0)) -> 0.25283955
B106: Share of short-term debt in total government debt | E106: ='Baseline NFPC'!E$93 -> 0.10000001 | F106: =IF(F100<>0,(F103+F105)/(F101+F102+F103+F104+F105),0) -> 0.098932517 | G106: =IF(G100<>0,(G103+G105)/(G101+G102+G103+G104+G105),0) -> 0.09841602 | H106: =IF(H100<>0,(H103+H105)/(H101+H102+H103+H104+H105),0) -> 0.097992466 | I106: =IF(I100<>0,(I103+I105)/(I101+I102+I103+I104+I105),0) -> 0.097610494 | J106: =IF(J100<>0,(J103+J105)/(J101+J102+J103+J104+J105),0) -> 0.097321409 | K106: =IF(K100<>0,(K103+K105)/(K101+K102+K103+K104+K105),0) -> 0.097058454 | L106: =IF(L100<>0,(L103+L105)/(L101+L102+L103+L104+L105),0) -> 0.096818189 | M106: =IF(M100<>0,(M103+M105)/(M101+M102+M103+M104+M105),0) -> 0.096595686 | ... W106: =IF(W100<>0,(W103+W105)/(W101+W102+W103+W104+W105),0) -> 0.09304098
B107: Share of long-term debt in total government debt | E107: ='Baseline NFPC'!E$94 -> 0.89999999 | F107: =IF(F100<>0,(F101+F102+F104)/(F101+F102+F103+F104+F105),1) -> 0.90106748 | G107: =IF(G100<>0,(G101+G102+G104)/(G101+G102+G103+G104+G105),1) -> 0.90158398 | H107: =IF(H100<>0,(H101+H102+H104)/(H101+H102+H103+H104+H105),1) -> 0.90200753 | I107: =IF(I100<>0,(I101+I102+I104)/(I101+I102+I103+I104+I105),1) -> 0.90238951 | J107: =IF(J100<>0,(J101+J102+J104)/(J101+J102+J103+J104+J105),1) -> 0.90267859 | K107: =IF(K100<>0,(K101+K102+K104)/(K101+K102+K103+K104+K105),1) -> 0.90294155 | L107: =IF(L100<>0,(L101+L102+L104)/(L101+L102+L103+L104+L105),1) -> 0.90318181 | M107: =IF(M100<>0,(M101+M102+M104)/(M101+M102+M103+M104+M105),1) -> 0.90340431 | ... W107: =IF(W100<>0,(W101+W102+W104)/(W101+W102+W103+W104+W105),1) -> 0.90695902
B109: IIR | C109: ='Baseline NFPC'!C96 -> 3.238231 | D109: ='Baseline NFPC'!D96 -> 4.417456 | E109: ='Baseline NFPC'!E96 -> 7.284665 | F109: ='Baseline NFPC'!F96 -> 7.231643 | G109: ='Baseline NFPC'!G96 -> 5.674904 | H109: =H111+H112 -> 5.6484363 | I109: =I111+I112 -> 5.7650421 | J109: =J111+J112 -> 5.8711309 | K109: =K111+K112 -> 5.9643176 | L109: =L111+L112 -> 6.0503547 | M109: =M111+M112 -> 6.1300808 | N109: =N111+N112 -> 6.2043184 | O109: =O111+O112 -> 6.2751747 | ... W109: =W111+W112 -> 6.2915575
B110: Long-term implicit interest rate | F110: =((F36*E100)-(F38*(E103+E105)))/(E101+E102+E104) -> 7.2267647 | G110: =((G36*F100)-(G38*(F103+F105)))/(F101+F102+F104) -> 5.6458541 | H110: =IF(G100>0,(G110*G101+ ('Baseline NFPC'!H97*(G101+G102+G104)-'Baseline NFPC'!G97*G101)/(G102+G104) *(G104+G102))/(G101+G102+G104),H37) -> 5.6382136 | I110: =IF(H100>0,(H110*H101+I37*(H104+H102))/(H101+H102+H104),I37) -> 5.7572152 | J110: =IF(I100>0,(I110*I101+J37*(I104+I102))/(I101+I102+I104),J37) -> 5.864537 | K110: =IF(J100>0,(J110*J101+K37*(J104+J102))/(J101+J102+J104),K37) -> 5.9575497 | L110: =IF(K100>0,(K110*K101+L37*(K104+K102))/(K101+K102+K104),L37) -> 6.0426434 | M110: =IF(L100>0,(L110*L101+M37*(L104+L102))/(L101+L102+L104),M37) -> 6.1207531 | N110: =IF(M100>0,(M110*M101+N37*(M104+M102))/(M101+M102+M104),N37) -> 6.1927944 | O110: =IF(N100>0,(N110*N101+O37*(N104+N102))/(N101+N102+N104),O37) -> 6.2611071 | P110: =IF(O100>0,(O110*O101+P37*(O104+O102))/(O101+O102+O104),P37) -> 6.326152 | ... W110: =IF(V100>0,(V110*V101+W37*(V104+V102))/(V101+V102+V104),W37) -> 6.4143354
B111: Nominal implicit interest rate on debt (Excel approximation) | F111: =(F110*(E101+E102+E104)+F38*(E103+E105))/E100 -> 7.231643 | G111: =(G110*(F101+F102+F104)+G38*(F103+F105))/F100 -> 5.674904 | H111: =(H110*(G101+G102+G104)+H38*(G103+G105))/G100 -> 5.6484363 | I111: =(I110*(H101+H102+H104)+I38*(H103+H105))/H100 -> 5.7650421 | J111: =(J110*(I101+I102+I104)+J38*(I103+I105))/I100 -> 5.8711309 | K111: =(K110*(J101+J102+J104)+K38*(J103+J105))/J100 -> 5.9643176 | L111: =(L110*(K101+K102+K104)+L38*(K103+K105))/K100 -> 6.0503547 | M111: =(M110*(L101+L102+L104)+M38*(L103+L105))/L100 -> 6.1300808 | ... W111: =(W110*(V101+V102+V104)+W38*(V103+V105))/V100 -> 6.2915575
B112: Diff. STATA | F112: ='Adjust. no safeguard'!F104 -> 0 | G112: ='Adjust. no safeguard'!G104 -> 0 | H112: ='Adjust. no safeguard'!H104 -> 0 | I112: ='Adjust. no safeguard'!I104 -> 0 | J112: ='Adjust. no safeguard'!J104 -> 0 | K112: ='Adjust. no safeguard'!K104 -> 0 | L112: ='Adjust. no safeguard'!L104 -> 0 | M112: ='Adjust. no safeguard'!M104 -> 0 | ... W112: ='Adjust. no safeguard'!W104 -> 0
B114: (i - g) | C114: =((1+C109/100)/((1+C24/100)*(1+C42/100))-1)*100 -> -9.3034373 | D114: =((1+D109/100)/((1+D24/100)*(1+D42/100))-1)*100 -> -12.324289 | E114: =((1+E109/100)/((1+E24/100)*(1+E42/100))-1)*100 -> -5.4617189 | F114: =((1+F109/100)/((1+F24/100)*(1+F42/100))-1)*100 -> -0.53672043 | G114: =((1+G109/100)/((1+G24/100)*(1+G42/100))-1)*100 -> 0.32455059 | H114: =((1+H109/100)/((1+H24/100)*(1+H42/100))-1)*100 -> -0.68053735 | I114: =((1+I109/100)/((1+I24/100)*(1+I42/100))-1)*100 -> 0.73369173 | J114: =((1+J109/100)/((1+J24/100)*(1+J42/100))-1)*100 -> 0.92940372 | ... W114: =((1+W109/100)/((1+W24/100)*(1+W42/100))-1)*100 -> 1.5758364

Sheet Adjust. no safeguard
B3: Country | C3: ='Input data'!C3 -> HU
B4: Key years
B5: ='Input data'!B5 -> Last year before the adjustment | C5: =+'Input data'!C5 -> 2024
B6: Last year of adjustment | C6: =+C5+'Criteria results'!$F$5 -> 2028
B7: Last year of no-fiscal-policy-change projections | C7: =C5+'Criteria results'!$F$5+10 -> 2038
B9: Key assumptions
C10: 2021 | D10: 2022 | E10: 2023 | F10: 2024 | G10: 2025 | H10: 2026 | I10: 2027 | J10: 2028 | K10: 2029 | L10: 2030 | M10: 2031 | N10: 2032 | O10: 2033 | P10: 2034 | Q10: 2035 | R10: 2036 | S10: 2037 | T10: 2038 | U10: 2039 | V10: 2040 | W10: 2041
B11: Fiscal assumptions (% of GDP)
B12: Structural primary balance ('+' means 'surplus') | C12: ='Input data'!C13 -> -5.106841 | D12: ='Input data'!D13 -> -4.391969 | E12: ='Input data'!E13 -> -1.706974 | F12: ='Input data'!F13 -> 0.64244146 | G12: =IF(G10<=$C$6,F12+'Criteria results'!$F$6,F12) -> 1.1824415 | H12: =IF(H10<=$C$6,G12+'Criteria results'!$F$6,G12) -> 1.7224415 | I12: =IF(I10<=$C$6,H12+'Criteria results'!$F$6,H12) -> 2.2624415 | J12: =IF(J10<=$C$6,I12+'Criteria results'!$F$6,I12) -> 2.8024415 | K12: =IF(K10<=$C$6,J12+'Criteria results'!$F$6,J12) -> 2.8024415 | L12: =IF(L10<=$C$6,K12+'Criteria results'!$F$6,K12) -> 2.8024415 | M12: =IF(M10<=$C$6,L12+'Criteria results'!$F$6,L12) -> 2.8024415 | N12: =M12 -> 2.8024415 | O12: =N12 -> 2.8024415 | P12: =O12 -> 2.8024415 | Q12: =P12 -> 2.8024415 | R12: =Q12 -> 2.8024415 | S12: =R12 -> 2.8024415 | T12: =S12 -> 2.8024415 | U12: =T12 -> 2.8024415 | ... W12: =V12 -> 2.8024415
B13: Annual change in SPB | G13: =G12-F12 -> 0.54 | H13: =H12-G12 -> 0.54 | I13: =I12-H12 -> 0.54 | J13: =J12-I12 -> 0.54 | K13: =K12-J12 -> 0 | L13: =L12-K12 -> 0 | M13: =M12-L12 -> 0 | N13: =N12-M12 -> 0 | ... W13: =W12-V12 -> 0
B14: One-off and other temporary measures | C14: ='Input data'!C14 -> -0.1079972 | D14: ='Input data'!D14 -> 0 | E14: ='Input data'!E14 -> 0 | F14: ='Input data'!F14 -> 0 | G14: ='Input data'!G14 -> 0 | H14: ='Input data'!H14 -> 0 | I14: ='Input data'!I14 -> 0 | J14: ='Input data'!J14 -> 0 | ... W14: ='Input data'!W14 -> 0
B15: Stock flow adjustments (without exchange rate effect) | C15: ='Input data'!C15 -> -0.1371056 | D15: ='Input data'!D15 -> 1.066777 | E15: ='Input data'!E15 -> 2.471388 | F15: ='Input data'!F15 -> 0.243711 | G15: ='Input data'!G15 -> -0.9088278 | H15: ='Input data'!H15 -> -0.250576 | I15: ='Input data'!I15 -> 0 | J15: ='Input data'!J15 -> 0 | ... W15: ='Input data'!W15 -> 0
B17: ='Input data'!B19 -> Cost of ageing and selected public revenue (based on the Commission-Council 2024 Ageing Report ("AR 2024"))
B18: Total ageing cost (net of taxes on pensions) | C18: ='Input data'!C20 -> 0 | D18: ='Input data'!D20 -> 16.0166 | E18: ='Input data'!E20 -> 16.12175 | F18: ='Input data'!F20 -> 16.12852 | G18: ='Input data'!G20 -> 16.01381 | H18: ='Input data'!H20 -> 15.92993 | I18: ='Input data'!I20 -> 15.87402 | J18: ='Input data'!J20 -> 15.87527 | ... W18: ='Input data'!W20 -> 17.97964
B19: Property income | C19: ='Input data'!C26 -> 0.5353987 | D19: ='Input data'!D26 -> 1.178846 | E19: ='Input data'!E26 -> 2.102853 | F19: ='Input data'!F26 -> 2.07289 | G19: ='Input data'!G26 -> 2.042928 | H19: ='Input data'!H26 -> 2.012965 | I19: ='Input data'!I26 -> 1.983002 | J19: ='Input data'!J26 -> 1.953039 | ... W19: ='Input data'!W26 -> 1.563521
B21: GDP growth assumptions
B22: Actual GDP (real)
B23: Level | C23: ='Input data'!C31 -> 133.9938 | D23: ='Baseline NFPC'!D22 -> 139.70315 | E23: ='Baseline NFPC'!E22 -> 138.38125 | F23: ='Baseline NFPC'!F22 -> 139.19078 | G23: =IF(AND(G50>1,F50>1), G27*(1+('Baseline NFPC'!G$29+G51)/100)-F23*$C$47*(G12-F12)/100, IF(G50=1,G27,F23*(1+G52/100))) -> 140.88433 | H23: =IF(AND(H50>1,G50>1), H27*(1+('Baseline NFPC'!H$29+H51)/100)-G23*$C$47*(H12-G12)/100, IF(H50=1,H27,G23*(1+H52/100))) -> 144.81636 | I23: =IF(AND(I50>1,H50>1), I27*(1+I51/100)-H23*$C$47*(I12-H12)/100, IF(I50=1,I27,H23*(1+I52/100))) -> 147.01801 | J23: =IF(AND(J50>1,I50>1), J27*(1+J51/100)-I23*$C$47*(J12-I12)/100, IF(J50=1,J27,I23*(1+J52/100))) -> 149.20224 | K23: =IF(AND(K50>1,J50>1), K27*(1+K51/100)-J23*$C$47*(K12-J12)/100, IF(K50=1,K27,J23*(1+K52/100))) -> 152.02987 | L23: =IF(AND(L50>1,K50>1), L27*(1+L51/100)-K23*$C$47*(L12-K12)/100, IF(L50=1,L27,K23*(1+L52/100))) -> 155.22905 | M23: =IF(AND(M50>1,L50>1), M27*(1+M51/100)-L23*$C$47*(M12-L12)/100, IF(M50=1,M27,L23*(1+M52/100))) -> 158.69246 | N23: =IF(AND(N50>1,M50>1), N27*(1+N51/100)-M23*$C$47*(N12-M12)/100, IF(N50=1,N27,M23*(1+N52/100))) -> 161.73488 | O23: =IF(AND(O50>1,N50>1), O27*(1+O51/100)-N23*$C$47*(O12-N12)/100, IF(O50=1,O27,N23*(1+O52/100))) -> 164.70182 | P23: =IF(AND(P50>1,O50>1), P27*(1+P51/100)-O23*$C$47*(P12-O12)/100, IF(P50=1,P27,O23*(1+P52/100))) -> 167.75405 | ... W23: =IF(AND(W50>1,V50>1), W27*(1+W51/100)-V23*$C$47*(W12-V12)/100, IF(W50=1,W27,V23*(1+W52/100))) -> 188.86752
B24: Growth rate | C24: =+'Input data'!C30 -> 7.121139 | D24: ='Baseline NFPC'!D23 -> 4.260908 | E24: ='Baseline NFPC'!E23 -> -0.9462205 | F24: ='Baseline NFPC'!F23 -> 0.584996 | G24: =100*(G23/F23-1) -> 1.216716 | H24: =100*(H23/G23-1) -> 2.7909618 | I24: =100*(I23/H23-1) -> 1.5203043 | J24: =100*(J23/I23-1) -> 1.4856906 | K24: =100*(K23/J23-1) -> 1.8951652 | L24: =100*(L23/K23-1) -> 2.1043109 | M24: =100*(M23/L23-1) -> 2.2311598 | N24: =100*(N23/M23-1) -> 1.917179 | ... W24: =100*(W23/V23-1) -> 1.601132
B26: Potential GDP (real)
B27: Level | C27: ='Input data'!C34 -> 132.9781 | D27: =+C27*(1+'Input data'!D33/100) -> 136.6169 | E27: =+D27*(1+'Input data'!E33/100) -> 139.17592 | F27: =+E27*(1+'Input data'!F33/100) -> 141.10966 | G27: =+F27*(1+'Input data'!G33/100) -> 143.274 | H27: =+G27*(1+'Input data'!H33/100) -> 145.73938 | I27: =+H27*(1+'Input data'!I33/100) -> 148.23038 | J27: =+I27*(1+'Input data'!J33/100) -> 150.61893 | K27: =+J27*(1+'Input data'!K33/100) -> 152.9892 | ... W27: =+V27*(1+'Input data'!W33/100) -> 188.8675
B29: Output gap
B30: Output gap | C30: =100*(C23/C27-1) -> 0.76380998 | D30: =100*(D23/D27-1) -> 2.2590596 | E30: =100*(E23/E27-1) -> -0.5709813 | F30: =100*(F23/F27-1) -> -1.3598515 | G30: =100*(G23/G27-1) -> -1.6678968 | H30: =100*(H23/H27-1) -> -0.63333134 | I30: =100*(I23/I27-1) -> -0.81789301 | J30: =100*(J23/J27-1) -> -0.94057946 | ... W30: =100*(W23/W27-1) -> 8.8436136e-06
B32: Actual GDP (nominal, national currency)
B33: Growth rate | C33: =100*((1+C24/100)*(1+C42/100)-1) -> 13.828163 | D33: =100*((1+D24/100)*(1+D42/100)-1) -> 19.095077 | E33: =100*((1+E24/100)*(1+E42/100)-1) -> 13.482775 | F33: =100*((1+F24/100)*(1+F42/100)-1) -> 7.8102828 | G33: =100*((1+G24/100)*(1+G42/100)-1) -> 5.333045 | H33: =100*((1+H24/100)*(1+H42/100)-1) -> 6.3723398 | I33: =100*((1+I24/100)*(1+I42/100)-1) -> 4.9947046 | J33: =100*((1+J24/100)*(1+J42/100)-1) -> 4.8962215 | ... W33: =100*((1+W24/100)*(1+W42/100)-1) -> 4.6425619
B35: Interest rates
B36: Nominal implicit interest rate on debt | C36: ='Input data'!C37 -> 3.238231 | D36: ='Input data'!D37 -> 4.417456 | E36: ='Input data'!E37 -> 7.284665 | F36: ='Input data'!F37 -> 7.231643 | G36: ='Input data'!G37 -> 5.674904 | H36: =H101 -> 5.6484363 | I36: =I101 -> 5.7650421 | J36: =J101 -> 5.8711309 | K36: =K101 -> 5.9643176 | L36: =L101 -> 6.0503547 | M36: =M101 -> 6.1300808 | N36: =N101 -> 6.2043184 | O36: =O101 -> 6.2751747 | ... W36: =W101 -> 6.2915575
B37: Long-term interest rate | D37: ='Input data'!D$39 -> 7.57 | E37: ='Input data'!E$39 -> 7.51 | F37: ='Input data'!F$39 -> 6.52395 | G37: ='Input data'!G$39 -> 6.731379 | H37: ='Input data'!H$39 -> 6.82931 | I37: ='Baseline NFPC'!I36 -> 6.8414188 | J37: ='Baseline NFPC'!J36 -> 6.8535275 | K37: ='Baseline NFPC'!K36 -> 6.8656362 | L37: ='Baseline NFPC'!L36 -> 6.877745 | M37: ='Baseline NFPC'!M36 -> 6.8898537 | N37: ='Baseline NFPC'!N36 -> 6.9019625 | O37: ='Baseline NFPC'!O36 -> 6.9140712 | P37: ='Baseline NFPC'!P36 -> 6.92618 | ... W37: ='Baseline NFPC'!W36 -> 6.252017
B38: Short-term interest rate | D38: ='Input data'!D$38 -> 10.32 | E38: ='Input data'!E$38 -> 15.97 | F38: ='Input data'!F$38 -> 7.275548 | G38: ='Input data'!G$38 -> 5.939488 | H38: ='Input data'!H$38 -> 5.742086 | I38: ='Baseline NFPC'!I37 -> 5.8370877 | J38: ='Baseline NFPC'!J37 -> 5.9320895 | K38: ='Baseline NFPC'!K37 -> 6.0270912 | L38: ='Baseline NFPC'!L37 -> 6.122093 | M38: ='Baseline NFPC'!M37 -> 6.2170947 | N38: ='Baseline NFPC'!N37 -> 6.3120965 | O38: ='Baseline NFPC'!O37 -> 6.4070982 | P38: ='Baseline NFPC'!P37 -> 6.5021 | ... W38: ='Baseline NFPC'!W37 -> 5.101365
B39: Share of long-term debt that matures every year | C39: ='Baseline NFPC'!C38 -> 0.07935879 | D39: ='Baseline NFPC'!D38 -> 0.06020197 | E39: ='Baseline NFPC'!E38 -> 0.05046041 | F39: ='Baseline NFPC'!F38 -> 0.06743385 | G39: ='Baseline NFPC'!G38 -> 0.068498038 | H39: ='Baseline NFPC'!H38 -> 0.069562226 | I39: ='Baseline NFPC'!I38 -> 0.070626414 | J39: ='Baseline NFPC'!J38 -> 0.071690602 | ... W39: ='Baseline NFPC'!W38 -> 0.07807573
B41: Inflation and exchange rate
B42: GDP deflator (National currency) | C42: ='Input data'!C42 -> 6.261158 | D42: ='Input data'!D42 -> 14.22793 | E42: ='Input data'!E42 -> 14.56683 | F42: ='Input data'!F42 -> 7.183265 | G42: ='Input data'!G42 -> 4.066847 | H42: ='Input data'!H42 -> 3.484137 | I42: ='Baseline NFPC'!I41 -> 3.4223699 | J42: ='Baseline NFPC'!J41 -> 3.3606027 | K42: ='Baseline NFPC'!K41 -> 3.2988356 | L42: ='Baseline NFPC'!L41 -> 3.2370685 | M42: ='Baseline NFPC'!M41 -> 3.1753014 | N42: ='Baseline NFPC'!N41 -> 3.1135343 | O42: ='Baseline NFPC'!O41 -> 3.0517671 | P42: ='Baseline NFPC'!P41 -> 2.99 | ... W42: ='Baseline NFPC'!W41 -> 2.9935
B43: Exchange rate composite change (weighted by share of debt in each currency) | C43: ='Baseline NFPC'!C42 -> 1.001704 | D43: ='Baseline NFPC'!D42 -> 1.038632 | E43: ='Baseline NFPC'!E42 -> 0.9884134 | F43: ='Baseline NFPC'!F42 -> 1.010684 | G43: ='Baseline NFPC'!G42 -> 1.007245 | H43: ='Baseline NFPC'!H42 -> 1 | I43: ='Baseline NFPC'!I42 -> 1 | J43: ='Baseline NFPC'!J42 -> 1 | ... W43: ='Baseline NFPC'!W42 -> 1
B45: Intermediate calculations (growth rate equation)
B47: Fiscal multiplier | C47: ='Input data'!C49 -> 0.75
B48: Budget balance semi-elasticity | C48: ='Input data'!C50 -> 0.453
B50: Auxiliary variable to control the closure of the output gap | C50: 0 | D50: =IF(AND(ABS((D12-C12)-('Input data'!D13-'Input data'!C13))>0.0001,ABS(D12-C12)>0.0001,D$10>$C$5),4,IF(C50=4,3,IF(C50=3,2,IF(C50=2,1,0)))) -> 0 | E50: =IF(AND(ABS((E12-D12)-('Input data'!E13-'Input data'!D13))>0.0001,ABS(E12-D12)>0.0001,E$10>$C$5),4,IF(D50=4,3,IF(D50=3,2,IF(D50=2,1,0)))) -> 0 | F50: =IF(AND(ABS((F12-E12)-('Input data'!F13-'Input data'!E13))>0.0001,ABS(F12-E12)>0.0001,F$10>$C$5),4,IF(E50=4,3,IF(E50=3,2,IF(E50=2,1,0)))) -> 0 | G50: =IF(AND(ABS((G12-F12)-('Baseline NFPC'!G12-'Baseline NFPC'!F12))>0.0001,ABS(G12-F12)>0.0001,G$10>$C$5),4,IF(F50=4,3,IF(F50=3,2,IF(F50=2,1,0)))) -> 4 | H50: =IF(AND(ABS((H12-G12)-('Baseline NFPC'!H12-'Baseline NFPC'!G12))>0.0001,ABS(H12-G12)>0.0001,H$10>$C$5),4,IF(G50=4,3,IF(G50=3,2,IF(G50=2,1,0)))) -> 4 | I50: =IF(AND(ABS((I12-H12)-('Baseline NFPC'!I12-'Baseline NFPC'!H12))>0.0001,ABS(I12-H12)>0.0001,I$10>$C$5),4,IF(H50=4,3,IF(H50=3,2,IF(H50=2,1,0)))) -> 4 | J50: =IF(AND(ABS((J12-I12)-('Baseline NFPC'!J12-'Baseline NFPC'!I12))>0.0001,ABS(J12-I12)>0.0001,J$10>$C$5),4,IF(I50=4,3,IF(I50=3,2,IF(I50=2,1,0)))) -> 4 | K50: =IF(AND(ABS((K12-J12)-('Baseline NFPC'!K12-'Baseline NFPC'!J12))>0.0001,ABS(K12-J12)>0.0001,K$10>$C$5),4,IF(J50=4,3,IF(J50=3,2,IF(J50=2,1,0)))) -> 3 | L50: =IF(AND(ABS((L12-K12)-('Baseline NFPC'!L12-'Baseline NFPC'!K12))>0.0001,ABS(L12-K12)>0.0001,L$10>$C$5),4,IF(K50=4,3,IF(K50=3,2,IF(K50=2,1,0)))) -> 2 | M50: =IF(AND(ABS((M12-L12)-('Baseline NFPC'!M12-'Baseline NFPC'!L12))>0.0001,ABS(M12-L12)>0.0001,M$10>$C$5),4,IF(L50=4,3,IF(L50=3,2,IF(L50=2,1,0)))) -> 1 | N50: =IF(AND(ABS((N12-M12)-('Baseline NFPC'!N12-'Baseline NFPC'!M12))>0.0001,ABS(N12-M12)>0.0001,N$10>$C$5),4,IF(M50=4,3,IF(M50=3,2,IF(M50=2,1,0)))) -> 0 | ... W50: =IF(AND(ABS((W12-V12)-('Baseline NFPC'!W12-'Baseline NFPC'!V12))>0.0001,ABS(W12-V12)>0.0001,W$10>$C$5),4,IF(V50=4,3,IF(V50=3,2,IF(V50=2,1,0)))) -> 0
B51: OG intermediate auxiliary value | C51: 0 | D51: 0 | E51: =IF(D50=4,2/3*(D30-'Baseline NFPC'!D29),IF(D50=3,1/3*(C30-'Baseline NFPC'!C29),0)) -> 0 | F51: =IF(E50=4,2/3*(E30-'Baseline NFPC'!E29),IF(E50=3,1/3*(D30-'Baseline NFPC'!D29),0)) -> 0 | G51: =IF(F50=4,2/3*(F30-'Baseline NFPC'!F29),IF(F50=3,1/3*(E30-'Baseline NFPC'!E29),0)) -> 0 | H51: =IF(G50=4,2/3*(G30-'Baseline NFPC'!G29),IF(G50=3,1/3*(F30-'Baseline NFPC'!F29),0)) -> -0.26230517 | I51: =IF(H50=4,2/3*H30,IF(H50=3,1/3*G30,0)) -> -0.42222089 | J51: =IF(I50=4,2/3*I30,IF(I50=3,1/3*H30,0)) -> -0.545262 | K51: =IF(J50=4,2/3*J30,IF(J50=3,1/3*I30,0)) -> -0.62705298 | L51: =IF(K50=4,2/3*K30,IF(K50=3,1/3*J30,0)) -> -0.31352649 | M51: =IF(L50=4,2/3*L30,IF(L50=3,1/3*K30,0)) -> 0 | N51: =IF(M50=4,2/3*M30,IF(M50=3,1/3*L30,0)) -> 0 | O51: =IF(N50=4,2/3*N30,IF(N50=3,1/3*M30,0)) -> 0 | P51: =IF(O50=4,2/3*O30,IF(O50=3,1/3*N30,0)) -> 0 | ... W51: =IF(V50=4,2/3*V30,IF(V50=3,1/3*U30,0)) -> 0
B52: GDP intermediate growth rate - only feedback effect and no closure of the OG | D52: ='Input data'!D30-$C$47*((D12-C12)-('Input data'!D13-'Input data'!C13)) -> 4.260908 | E52: ='Input data'!E30-$C$47*((E12-D12)-('Input data'!E13-'Input data'!D13)) -> -0.9462205 | F52: ='Input data'!F30-$C$47*((F12-E12)-('Input data'!F13-'Input data'!E13)) -> 0.584996 | G52: ='Input data'!G30-$C$47*(G12-F12) -> 1.216716 | H52: ='Input data'!H30-$C$47*(H12-G12) -> 2.649951 | I52: ='Input data'!I30-$C$47*(I12-H12) -> 1.29729 | J52: ='Input data'!J30-$C$47*(J12-I12) -> 1.199467 | K52: ='Input data'!K30-$C$47*(K12-J12) -> 1.566761 | L52: ='Input data'!L30-$C$47*(L12-K12) -> 1.78318 | M52: ='Input data'!M30-$C$47*(M12-L12) -> 1.910635 | N52: ='Input data'!N30-$C$47*(N12-M12) -> 1.917179 | ... W52: ='Input data'!W30-$C$47*(W12-V12) -> 1.601132
B54: Debt projections
C56: 2021 | D56: 2022 | E56: 2023 | F56: 2024 | G56: 2025 | H56: 2026 | I56: 2027 | J56: 2028 | K56: 2029 | L56: 2030 | M56: 2031 | N56: 2032 | O56: 2033 | P56: 2034 | Q56: 2035 | R56: 2036 | S56: 2037 | T56: 2038 | U56: 2039 | V56: 2040 | W56: 2041
B57: Gross debt | C57: =+'Input data'!C12 -> 76.21938 | D57: =+C57+D58 -> 73.842909 | E57: =+D57+E58 -> 73.437974 | F57: =+E57+F58 -> 74.041486 | G57: =+F57+G58 -> 73.48544 | H57: =+G57+H58 -> 71.299226 | I57: =+H57+I58 -> 69.930407 | J57: =+I57+J58 -> 68.203983 | K57: =+J57+K58 -> 66.186518 | ... W57: =+V57+W58 -> 55.283325
B58: Change in debt (-1+2+3) | D58: =-D59+D67+D72 -> -2.376471 | E58: =-E59+E67+E72 -> -0.40493547 | F58: =-F59+F67+F72 -> 0.60351226 | G58: =-G59+G67+G72 -> -0.55604531 | H58: =-H59+H67+H72 -> -2.1862145 | I58: =-I59+I67+I72 -> -1.3688194 | J58: =-J59+J67+J72 -> -1.7264232 | K58: =-K59+K67+K72 -> -2.0174652 | ... W58: =-W59+W67+W72 -> 0.55388893
B59: (1) Primary balance (1.1 + 1.2 - 1.3 -1.4 -1.5 - 1.6 -1.7) | D59: =D60+D61-D62-D63-D64-D65-D66 -> -3.368615 | E59: =E60+E61-E62-E63-E64-E65-E66 -> -1.9656285 | F59: =F60+F61-F62-F63-F64-F65-F66 -> 0.026428741 | G59: =G60+G61-G62-G63-G64-G65-G66 -> 0.42688419 | H59: =H60+H61-H62-H63-H64-H65-H66 -> 1.4355424 | I59: =I60+I61-I62-I63-I64-I65-I66 -> 1.8919359 | J59: =J60+J61-J62-J63-J64-J65-J66 -> 2.376359 | K59: =K60+K61-K62-K63-K64-K65-K66 -> 2.4761035 | ... W59: =W60+W61-W62-W63-W64-W65-W66 -> 0.30855746
B60: (1.1) Structural primary balance (before ageing cost) | D60: =D12 -> -4.391969 | E60: =E12 -> -1.706974 | F60: =F12 -> 0.64244146 | G60: =IF(G12="",F60,G12) -> 1.1824415 | H60: =IF(H12="",G60,H12) -> 1.7224415 | I60: =IF(I12="",H60,I12) -> 2.2624415 | J60: =IF(J12="",I60,J12) -> 2.8024415 | K60: =IF(K12="",J60,K12) -> 2.8024415 | L60: =IF(L12="",K60,L12) -> 2.8024415 | M60: =IF(M12="",L60,M12) -> 2.8024415 | N60: =IF(N12="",M60,N12) -> 2.8024415 | ... W60: =IF(W12="",V60,W12) -> 2.8024415
B61: (1.2) Cumulated budgetary effort (in terms of primary balance) | D61: 0 | E61: 0 | F61: 0 | G61: 0 | H61: 0 | I61: 0 | J61: 0 | K61: 0 | L61: 0 | M61: 0 | N61: 0 | O61: 0 | P61: 0 | Q61: 0 | R61: 0 | S61: 0 | T61: 0 | U61: 0 | V61: 0 | W61: 0
B62: (1.3) Cyclical component | D62: =-$C$48*D30 -> -1.023354 | E62: =-$C$48*E30 -> 0.25865453 | F62: =-$C$48*F30 -> 0.61601271 | G62: =-$C$48*G30 -> 0.75555726 | H62: =-$C$48*H30 -> 0.2868991 | I62: =-$C$48*I30 -> 0.37050553 | J62: =-$C$48*J30 -> 0.4260825 | K62: =-$C$48*K30 -> 0.284055 | ... W62: =-$C$48*W30 -> -4.006157e-06
B63: (1.4) One-off and other temporary measures | D63: =-D14 -> 0 | E63: =-E14 -> 0 | F63: =-F14 -> 0 | G63: =-G14 -> 0 | H63: =-H14 -> 0 | I63: =-I14 -> 0 | J63: =-J14 -> 0 | K63: =-K14 -> 0 | ... W63: =-W14 -> 0
B64: (1.5) Cost of ageing | D64: =IF(D$56<=$C$6,0,HLOOKUP(D$56,'Input data'!$C$9:$BB$26,12,FALSE)-HLOOKUP($C$6,'Input data'!$C$9:$BB$26,12,FALSE)) -> 0 | E64: =IF(E$56<=$C$6,0,HLOOKUP(E$56,'Input data'!$C$9:$BB$26,12,FALSE)-HLOOKUP($C$6,'Input data'!$C$9:$BB$26,12,FALSE)) -> 0 | F64: =IF(F$56<=$C$6,0,HLOOKUP(F$56,'Input data'!$C$9:$BB$26,12,FALSE)-HLOOKUP($C$6,'Input data'!$C$9:$BB$26,12,FALSE)) -> 0 | G64: =IF(G$56<=$C$6,0,HLOOKUP(G$56,'Input data'!$C$9:$BB$26,12,FALSE)-HLOOKUP($C$6,'Input data'!$C$9:$BB$26,12,FALSE)) -> 0 | H64: =IF(H$56<=$C$6,0,HLOOKUP(H$56,'Input data'!$C$9:$BB$26,12,FALSE)-HLOOKUP($C$6,'Input data'!$C$9:$BB$26,12,FALSE)) -> 0 | I64: =IF(I$56<=$C$6,0,HLOOKUP(I$56,'Input data'!$C$9:$BB$26,12,FALSE)-HLOOKUP($C$6,'Input data'!$C$9:$BB$26,12,FALSE)) -> 0 | J64: =IF(J$56<=$C$6,0,HLOOKUP(J$56,'Input data'!$C$9:$BB$26,12,FALSE)-HLOOKUP($C$6,'Input data'!$C$9:$BB$26,12,FALSE)) -> 0 | K64: =IF(K$56<=$C$6,0,HLOOKUP(K$56,'Input data'!$C$9:$BB$26,12,FALSE)-HLOOKUP($C$6,'Input data'!$C$9:$BB$26,12,FALSE)) -> 0.01232 | ... W64: =IF(W$56<=$C$6,0,HLOOKUP(W$56,'Input data'!$C$9:$BB$26,12,FALSE)-HLOOKUP($C$6,'Input data'!$C$9:$BB$26,12,FALSE)) -> 2.10437
B65: (1.6) Property incomes | D65: =IF(D$56<=$C$5,0,-HLOOKUP(D$56,'Input data'!$C$9:$BB$26,18,FALSE)+HLOOKUP($C$6,'Input data'!$C$9:$BB$26,18,FALSE)) -> 0 | E65: =IF(E$56<=$C$5,0,-HLOOKUP(E$56,'Input data'!$C$9:$BB$26,18,FALSE)+HLOOKUP($C$6,'Input data'!$C$9:$BB$26,18,FALSE)) -> 0 | F65: =IF(F$56<=$C$5,0,-HLOOKUP(F$56,'Input data'!$C$9:$BB$26,18,FALSE)+HLOOKUP($C$6,'Input data'!$C$9:$BB$26,18,FALSE)) -> 0 | G65: =IF(G$56<=$C$6,0,-HLOOKUP(G$56,'Input data'!$C$9:$BB$26,18,FALSE)+HLOOKUP($C$6,'Input data'!$C$9:$BB$26,18,FALSE)) -> 0 | H65: =IF(H$56<=$C$6,0,-HLOOKUP(H$56,'Input data'!$C$9:$BB$26,18,FALSE)+HLOOKUP($C$6,'Input data'!$C$9:$BB$26,18,FALSE)) -> 0 | I65: =IF(I$56<=$C$6,0,-HLOOKUP(I$56,'Input data'!$C$9:$BB$26,18,FALSE)+HLOOKUP($C$6,'Input data'!$C$9:$BB$26,18,FALSE)) -> 0 | J65: =IF(J$56<=$C$6,0,-HLOOKUP(J$56,'Input data'!$C$9:$BB$26,18,FALSE)+HLOOKUP($C$6,'Input data'!$C$9:$BB$26,18,FALSE)) -> 0 | K65: =IF(K$56<=$C$6,0,-HLOOKUP(K$56,'Input data'!$C$9:$BB$26,18,FALSE)+HLOOKUP($C$6,'Input data'!$C$9:$BB$26,18,FALSE)) -> 0.029963 | L65: =IF(L$56<=$C$6,0,-HLOOKUP(L$56,'Input data'!$C$9:$BB$26,18,FALSE)+HLOOKUP($C$6,'Input data'!$C$9:$BB$26,18,FALSE)) -> 0.059926 | M65: =IF(M$56<=$C$6,0,-HLOOKUP(M$56,'Input data'!$C$9:$BB$26,18,FALSE)+HLOOKUP($C$6,'Input data'!$C$9:$BB$26,18,FALSE)) -> 0.089889 | N65: =IF(N$56<=$C$6,0,-HLOOKUP(N$56,'Input data'!$C$9:$BB$26,18,FALSE)+HLOOKUP($C$6,'Input data'!$C$9:$BB$26,18,FALSE)) -> 0.119852 | ... W65: =IF(W$56<=$C$6,0,-HLOOKUP(W$56,'Input data'!$C$9:$BB$26,18,FALSE)+HLOOKUP($C$6,'Input data'!$C$9:$BB$26,18,FALSE)) -> 0.389518
B66: (1.7) Revenues | D66: 0 | E66: 0 | F66: 0 | G66: 0 | H66: 0 | I66: 0 | J66: 0 | K66: 0 | L66: 0 | M66: 0 | N66: 0 | O66: 0 | P66: 0 | Q66: 0 | R66: 0 | S66: 0 | T66: 0 | U66: 0 | V66: 0 | W66: 0
B67: (2) Snowball effect (2.1 + 2.2 + 2.3) | D67: =SUM(D68:D71) -> -9.284277 | E67: =SUM(E68:E71) -> -4.088016 | F67: =SUM(F68:F71) -> -0.3415279 | G67: =SUM(G68:G71) -> 0.26926648 | H67: =SUM(H68:H71) -> -0.50009587 | I67: =SUM(I68:I71) -> 0.52311653 | J67: =SUM(J68:J71) -> 0.6499358 | K67: =SUM(K68:K71) -> 0.45863829 | ... W67: =SUM(W68:W71) -> 0.86244639
B68: (2.1) Interest expenditure | D68: =C57*D36/100*(1/(1+D33/100)) -> 2.8271173 | E68: =D57*E36/100*(1/(1+E33/100)) -> 4.7401102 | F68: =E57*F36/100*(1/(1+F33/100)) -> 4.9260348 | G68: =F57*G36/100*(1/(1+G33/100)) -> 3.9890456 | H68: =G57*H36/100*(1/(1+H33/100)) -> 3.9021218 | I68: =H57*I36/100*(1/(1+I33/100)) -> 3.9148931 | J68: =I57*J36/100*(1/(1+J33/100)) -> 3.9140644 | K68: =J57*K36/100*(1/(1+K33/100)) -> 3.8647508 | ... W68: =V57*W36/100*(1/(1+W33/100)) -> 3.2905673
B69: (2.2) Growth effect | D69: =-C57*(D24/100)*(1/(1+D33/100)) -> -2.7269286 | E69: =-D57*(E24/100)*(1/(1+E33/100)) -> 0.6157029 | F69: =-E57*(F24/100)*(1/(1+F33/100)) -> -0.3984863 | G69: =-F57*(G24/100)*(1/(1+G33/100)) -> -0.85526304 | H69: =-G57*(H24/100)*(1/(1+H33/100)) -> -1.9280864 | I69: =-H57*(I24/100)*(1/(1+I33/100)) -> -1.0323999 | J69: =-I57*(J24/100)*(1/(1+J33/100)) -> -0.99045461 | K69: =-J57*(K24/100)*(1/(1+K33/100)) -> -1.2280267 | ... W69: =-V57*(W24/100)*(1/(1+W33/100)) -> -0.83741309
B70: (2.3) Inflation effect | D70: =-C57*D42/100*(1/(1+D42/100)) -> -9.4936852 | E70: =-D57*E42/100*(1/(1+E42/100)) -> -9.3889052 | F70: =-E57*F42/100*(1/(1+F42/100)) -> -4.9217051 | G70: =-F57*G42/100*(1/(1+G42/100)) -> -2.8934805 | H70: =-G57*H42/100*(1/(1+H42/100)) -> -2.4741313 | I70: =-H57*I42/100*(1/(1+I42/100)) -> -2.3593766 | J70: =-I57*J42/100*(1/(1+J42/100)) -> -2.273674 | K70: =-J57*K42/100*(1/(1+K42/100)) -> -2.1780858 | ... W70: =-V57*W42/100*(1/(1+W42/100)) -> -1.5907078
B71: (2.4) Exchange rate effect linked to the interest rate | D71: ='Baseline NFPC'!D70 -> 0.10921937 | E71: ='Baseline NFPC'!E70 -> -0.05492389 | F71: ='Baseline NFPC'!F70 -> 0.052628707 | G71: ='Baseline NFPC'!G70 -> 0.028964404 | H71: 0 | I71: 0 | J71: 0 | K71: 0 | L71: 0 | M71: 0 | N71: 0 | O71: 0 | P71: 0 | Q71: 0 | R71: 0 | S71: 0 | T71: 0 | U71: 0 | V71: 0 | W71: 0
B72: (3 ) Stock flow adjustments (3.1 + 3.2) | D72: ='Input data'!D16 -> 3.539191 | E72: ='Input data'!E16 -> 1.717452 | F72: ='Input data'!F16 -> 0.9714689 | G72: ='Input data'!G16 -> -0.3984276 | H72: ='Input data'!H16 -> -0.2505763 | I72: ='Input data'!I16 -> 0 | J72: ='Input data'!J16 -> 0 | K72: ='Input data'!K16 -> 0 | ... W72: ='Input data'!W16 -> 0
B73: (3.1) Base | D73: =D15 -> 1.066777 | E73: =E15 -> 2.471388 | F73: =F15 -> 0.243711 | G73: =G15 -> -0.9088278 | H73: =H15 -> -0.250576 | I73: =I15 -> 0 | J73: =J15 -> 0 | K73: =K15 -> 0 | ... W73: =W15 -> 0
B74: (3.2) Adjustment due to the exchange rate effect linked to debt value | D74: =+D72-D73 -> 2.472414 | E74: =+E72-E73 -> -0.753936 | F74: =+F72-F73 -> 0.7277579 | G74: =+G72-G73 -> 0.5104002 | H74: =+H72-H73 -> -3e-07 | I74: =+I72-I73 -> 0 | J74: =+J72-J73 -> 0 | K74: =+K72-K73 -> 0 | ... W74: =+W72-W73 -> 0
B76: Other budgetary variables
B77: Headline balance | D77: =D59-D68 -> -6.1957323 | E77: =E59-E68 -> -6.7057387 | F77: =F59-F68 -> -4.8996061 | G77: =G59-G68 -> -3.5621614 | H77: =H59-H68 -> -2.4665795 | I77: =I59-I68 -> -2.0229571 | J77: =J59-J68 -> -1.5377055 | K77: =K59-K68 -> -1.3886474 | ... W77: =W59-W68 -> -2.9820098
B78: Structural balance | D78: =D60-D68-D64-D65-D66 -> -7.2190863 | E78: =E60-E68-E64-E65-E66 -> -6.4470842 | F78: =F60-F68-F64-F65-F66 -> -4.2835934 | G78: =G60-G68-G64-G65-G66 -> -2.8066042 | H78: =H60-H68-H64-H65-H66 -> -2.1796804 | I78: =I60-I68-I64-I65-I66 -> -1.6524516 | J78: =J60-J68-J64-J65-J66 -> -1.111623 | K78: =K60-K68-K64-K65-K66 -> -1.1045924 | ... W78: =W60-W68-W64-W65-W66 -> -2.9820139
B79: Net expenditure growth | D79: ='Input data'!D45 -> 22.282169 | E79: ='Input data'!E45 -> 8.9931862 | F79: ='Input data'!F45 -> 4.6 | G79: ='Input data'!G33+G42-(G$12-F$12)/'Input data'!$C$64*100 -> 4.3473229 | H79: ='Input data'!H33+H42-(H$12-G$12)/'Input data'!$C$64*100 -> 3.9515589 | I79: ='Input data'!I33+I42-(I$12-H$12)/'Input data'!$C$64*100 -> 3.8782647 | J79: ='Input data'!J33+J42-(J$12-I$12)/'Input data'!$C$64*100 -> 3.7186626 | K79: ='Input data'!K33+K42-(K$12-J$12)/'Input data'!$C$64*100 -> 4.8725166 | L79: ='Input data'!L33+L42-(L$12-K$12)/'Input data'!$C$64*100 -> 5.0202485 | M79: ='Input data'!M33+M42-(M$12-L$12)/'Input data'!$C$64*100 -> 5.0859394 | N79: ='Input data'!N33+N42-(N$12-M$12)/'Input data'!$C$64*100 -> 5.0307103 | ... W79: ='Input data'!W33+W42-(W$12-V$12)/'Input data'!$C$64*100 -> 4.594632
B81: Average net primary expenditure growth | D81: =AVERAGE(OFFSET($G$79,0,0,1,'Criteria results'!F5)) -> 3.9739523
B83: Debt decreasing? (For criterion 1) | K83: =IF(K57<J57,0,1) -> 0 | L83: =IF(L57<K57,0,1) -> 0 | M83: =IF(M57<L57,0,1) -> 0 | N83: =IF(N57<M57,0,1) -> 0 | O83: =IF(O57<N57,0,1) -> 0 | P83: =IF(P57<O57,0,1) -> 0 | Q83: =IF(Q57<P57,0,1) -> 0 | R83: =IF(R57<Q57,0,1) -> 0 | ... W83: =IF(W57<V57,0,1) -> 1
B85: Debt decomposition and IIR
B87: Auxiliary variable identifying whether debt is increasing | F87: =IF((F92-E92*F43/((1+F24/100)*(1+F42/100)))>0,1,0) -> 1 | G87: =IF((G92-F92*G43/((1+G24/100)*(1+G42/100)))>0,1,0) -> 1 | H87: =IF((H92-G92*H43/((1+H24/100)*(1+H42/100)))>0,1,0) -> 1 | I87: =IF((I92-H92*I43/((1+I24/100)*(1+I42/100)))>0,1,0) -> 1 | J87: =IF((J92-I92*J43/((1+J24/100)*(1+J42/100)))>0,1,0) -> 1 | K87: =IF((K92-J92*K43/((1+K24/100)*(1+K42/100)))>0,1,0) -> 1 | L87: =IF((L92-K92*L43/((1+L24/100)*(1+L42/100)))>0,1,0) -> 1 | M87: =IF((M92-L92*M43/((1+M24/100)*(1+M42/100)))>0,1,0) -> 1 | ... W87: =IF((W92-V92*W43/((1+W24/100)*(1+W42/100)))>0,1,0) -> 1
B88: Auxiliary variable identifying whether some debt is rolled over even though debt is decreasing | F88: =IF(AND(F87=0,ABS(F92-E92*F43/((1+F24/100)*(1+F42/100)))<((E98*E92*F43/((1+F24/100)*(1+F42/100))+(F39*E92*E99*F43/((1+F24/100)*(1+F42/100)))))),1,0) -> 0 | G88: =IF(AND(G87=0,ABS(G92-F92*G43/((1+G24/100)*(1+G42/100)))<((F98*F92*G43/((1+G24/100)*(1+G42/100))+(G39*F92*F99*G43/((1+G24/100)*(1+G42/100)))))),1,0) -> 0 | H88: =IF(AND(H87=0,ABS(H92-G92*H43/((1+H24/100)*(1+H42/100)))<((G98*G92*H43/((1+H24/100)*(1+H42/100))+(H39*G92*G99*H43/((1+H24/100)*(1+H42/100)))))),1,0) -> 0 | I88: =IF(AND(I87=0,ABS(I92-H92*I43/((1+I24/100)*(1+I42/100)))<((H98*H92*I43/((1+I24/100)*(1+I42/100))+(I39*H92*H99*I43/((1+I24/100)*(1+I42/100)))))),1,0) -> 0 | J88: =IF(AND(J87=0,ABS(J92-I92*J43/((1+J24/100)*(1+J42/100)))<((I98*I92*J43/((1+J24/100)*(1+J42/100))+(J39*I92*I99*J43/((1+J24/100)*(1+J42/100)))))),1,0) -> 0 | K88: =IF(AND(K87=0,ABS(K92-J92*K43/((1+K24/100)*(1+K42/100)))<((J98*J92*K43/((1+K24/100)*(1+K42/100))+(K39*J92*J99*K43/((1+K24/100)*(1+K42/100)))))),1,0) -> 0 | L88: =IF(AND(L87=0,ABS(L92-K92*L43/((1+L24/100)*(1+L42/100)))<((K98*K92*L43/((1+L24/100)*(1+L42/100))+(L39*K92*K99*L43/((1+L24/100)*(1+L42/100)))))),1,0) -> 0 | M88: =IF(AND(M87=0,ABS(M92-L92*M43/((1+M24/100)*(1+M42/100)))<((L98*L92*M43/((1+M24/100)*(1+M42/100))+(M39*L92*L99*M43/((1+M24/100)*(1+M42/100)))))),1,0) -> 0 | ... W88: =IF(AND(W87=0,ABS(W92-V92*W43/((1+W24/100)*(1+W42/100)))<((V98*V92*W43/((1+W24/100)*(1+W42/100))+(W39*V92*V99*W43/((1+W24/100)*(1+W42/100)))))),1,0) -> 0
C91: 2021 | D91: 2022 | E91: 2023 | F91: 2024 | G91: 2025 | H91: 2026 | I91: 2027 | J91: 2028 | K91: 2029 | L91: 2030 | M91: 2031 | N91: 2032 | O91: 2033 | P91: 2034 | Q91: 2035 | R91: 2036 | S91: 2037 | T91: 2038 | U91: 2039 | V91: 2040 | W91: 2041
B92: Gross debt | C92: =C57 -> 76.21938 | D92: =D57 -> 73.842909 | E92: =E57 -> 73.437974 | F92: =F57 -> 74.041486 | G92: =G57 -> 73.48544 | H92: =G92*(1+H106/100)*H43-H60-H61+H62+H63+H64+H65+H66+H73 -> 71.299226 | I92: =H92*(1+I106/100)*I43-I60-I61+I62+I63+I64+I65+I66+I73 -> 69.930407 | J92: =I92*(1+J106/100)*J43-J60-J61+J62+J63+J64+J65+J66+J73 -> 68.203984 | K92: =J92*(1+K106/100)*K43-K60-K61+K62+K63+K64+K65+K66+K73 -> 66.186519 | L92: =K92*(1+L106/100)*L43-L60-L61+L62+L63+L64+L65+L66+L73 -> 64.043964 | M92: =L92*(1+M106/100)*M43-M60-M61+M62+M63+M64+M65+M66+M73 -> 61.862434 | N92: =M92*(1+N106/100)*N43-N60-N61+N62+N63+N64+N65+N66+N73 -> 60.070269 | O92: =N92*(1+O106/100)*O43-O60-O61+O62+O63+O64+O65+O66+O73 -> 58.543638 | ... W92: =V92*(1+W106/100)*W43-W60-W61+W62+W63+W64+W65+W66+W73 -> 55.283325
B93: Of which Outstanding debt | E93: ='Input data'!$C$66*E$92 -> 54.96332 | F93: =IF(F92=0,0,IF(F87=1,E92*F43/((1+F24/100)*(1+F42/100))-F94-F95,IF(AND(F87=0,F88=1),(1-E98-F39*E99)*E92*F43/((1+F24/100)*(1+F42/100)),F92))) -> 57.782728 | G93: =IF(G92=0,0,IF(G87=1,F92*G43/((1+G24/100)*(1+G42/100))-G94-G95,IF(AND(G87=0,G88=1),(1-F98-G39*F99)*F92*G43/((1+G24/100)*(1+G42/100)),G92))) -> 59.427396 | H93: =IF(H92=0,0,IF(H87=1,G92*H43/((1+H24/100)*(1+H42/100))-H94-H95,IF(AND(H87=0,H88=1),(1-G98-H39*G99)*G92*H43/((1+H24/100)*(1+H42/100)),H92))) -> 57.951691 | I93: =IF(I92=0,0,IF(I87=1,H92*I43/((1+I24/100)*(1+I42/100))-I94-I95,IF(AND(I87=0,I88=1),(1-H98-I39*H99)*H92*I43/((1+I24/100)*(1+I42/100)),I92))) -> 56.926949 | J93: =IF(J92=0,0,IF(J87=1,I92*J43/((1+J24/100)*(1+J42/100))-J94-J95,IF(AND(J87=0,J88=1),(1-I98-J39*I99)*I92*J43/((1+J24/100)*(1+J42/100)),J92))) -> 55.846119 | K93: =IF(K92=0,0,IF(K87=1,J92*K43/((1+K24/100)*(1+K42/100))-K94-K95,IF(AND(K87=0,K88=1),(1-J98-K39*J99)*J92*K43/((1+K24/100)*(1+K42/100)),K92))) -> 54.236103 | L93: =IF(L92=0,0,IF(L87=1,K92*L43/((1+L24/100)*(1+L42/100))-L94-L95,IF(AND(L87=0,L88=1),(1-K98-L39*K99)*K92*L43/((1+L24/100)*(1+L42/100)),L92))) -> 52.510398 | M93: =IF(M92=0,0,IF(M87=1,L92*M43/((1+M24/100)*(1+M42/100))-M94-M95,IF(AND(M87=0,M88=1),(1-L98-M39*L99)*L92*M43/((1+M24/100)*(1+M42/100)),M92))) -> 50.733046 | ... W93: =IF(W92=0,0,IF(W87=1,V92*W43/((1+W24/100)*(1+W42/100))-W94-W95,IF(AND(W87=0,W88=1),(1-V98-W39*V99)*V92*W43/((1+W24/100)*(1+W42/100)),W92))) -> 43.708928
B94: Rolled over long-term debt | E94: ='Input data'!$C$67*E$92 -> 2.9208599 | F94: =IF(F92=0,0,IF(F87=1,F39*E92*E99*F43/((1+F24/100)*(1+F42/100)),IF(AND(F87=0,F88=1),(F39*E92*E99*F43/((1+F24/100)*(1+F42/100)))*(1-ABS(F92-E92*F43/((1+F24/100)*(1+F42/100)))/((F39*E92*E99*F43/((1+F24/100)*(1+F42/100)))+(E98*E92*F43/((1+F24/100)*(1+F42/100))))),0))) -> 4.1782685 | G94: =IF(G92=0,0,IF(G87=1,G39*F92*F99*G43/((1+G24/100)*(1+G42/100)),IF(AND(G87=0,G88=1),(G39*F92*F99*G43/((1+G24/100)*(1+G42/100)))*(1-ABS(G92-F92*G43/((1+G24/100)*(1+G42/100)))/((G39*F92*F99*G43/((1+G24/100)*(1+G42/100)))+(F98*F92*G43/((1+G24/100)*(1+G42/100))))),0))) -> 4.3699962 | H94: =IF(H92=0,0,IF(H87=1,H39*G92*G99*H43/((1+H24/100)*(1+H42/100)),IF(AND(H87=0,H88=1),(H39*G92*G99*H43/((1+H24/100)*(1+H42/100)))*(1-ABS(H92-G92*H43/((1+H24/100)*(1+H42/100)))/((H39*G92*G99*H43/((1+H24/100)*(1+H42/100)))+(G98*G92*H43/((1+H24/100)*(1+H42/100))))),0))) -> 4.3326364 | I94: =IF(I92=0,0,IF(I87=1,I39*H92*H99*I43/((1+I24/100)*(1+I42/100)),IF(AND(I87=0,I88=1),(I39*H92*H99*I43/((1+I24/100)*(1+I42/100)))*(1-ABS(I92-H92*I43/((1+I24/100)*(1+I42/100)))/((I39*H92*H99*I43/((1+I24/100)*(1+I42/100)))+(H98*H92*I43/((1+I24/100)*(1+I42/100))))),0))) -> 4.3260819 | J94: =IF(J92=0,0,IF(J87=1,J39*I92*I99*J43/((1+J24/100)*(1+J42/100)),IF(AND(J87=0,J88=1),(J39*I92*I99*J43/((1+J24/100)*(1+J42/100)))*(1-ABS(J92-I92*J43/((1+J24/100)*(1+J42/100)))/((J39*I92*I99*J43/((1+J24/100)*(1+J42/100)))+(I98*I92*J43/((1+J24/100)*(1+J42/100))))),0))) -> 4.3128313 | K94: =IF(K92=0,0,IF(K87=1,K39*J92*J99*K43/((1+K24/100)*(1+K42/100)),IF(AND(K87=0,K88=1),(K39*J92*J99*K43/((1+K24/100)*(1+K42/100)))*(1-ABS(K92-J92*K43/((1+K24/100)*(1+K42/100)))/((K39*J92*J99*K43/((1+K24/100)*(1+K42/100)))+(J98*J92*K43/((1+K24/100)*(1+K42/100))))),0))) -> 4.2555478 | L94: =IF(L92=0,0,IF(L87=1,L39*K92*K99*L43/((1+L24/100)*(1+L42/100)),IF(AND(L87=0,L88=1),(L39*K92*K99*L43/((1+L24/100)*(1+L42/100)))*(1-ABS(L92-K92*L43/((1+L24/100)*(1+L42/100)))/((L39*K92*K99*L43/((1+L24/100)*(1+L42/100)))+(K98*K92*L43/((1+L24/100)*(1+L42/100))))),0))) -> 4.185212 | M94: =IF(M92=0,0,IF(M87=1,M39*L92*L99*M43/((1+M24/100)*(1+M42/100)),IF(AND(M87=0,M88=1),(M39*L92*L99*M43/((1+M24/100)*(1+M42/100)))*(1-ABS(M92-L92*M43/((1+M24/100)*(1+M42/100)))/((M39*L92*L99*M43/((1+M24/100)*(1+M42/100)))+(L98*L92*M43/((1+M24/100)*(1+M42/100))))),0))) -> 4.1065636 | ... W94: =IF(W92=0,0,IF(W87=1,W39*V92*V99*W43/((1+W24/100)*(1+W42/100)),IF(AND(W87=0,W88=1),(W39*V92*V99*W43/((1+W24/100)*(1+W42/100)))*(1-ABS(W92-V92*W43/((1+W24/100)*(1+W42/100)))/((W39*V92*V99*W43/((1+W24/100)*(1+W42/100)))+(V98*V92*W43/((1+W24/100)*(1+W42/100))))),0))) -> 3.7016125
B95: Rolled over short-term debt | E95: ='Input data'!$C$68*E$92 -> 6.4315767 | F95: =IF(F92=0,0,IF(F87=1,(1-E99)*E92*F43/((1+F24/100)*(1+F42/100)),IF(AND(F87=0,F88=1),(E98*E92*F43/((1+F24/100)*(1+F42/100)))*(1-ABS(F92-E92*F43/((1+F24/100)*(1+F42/100)))/((F39*E92*E99*F43/((1+F24/100)*(1+F42/100)))+(E98*E92*F43/((1+F24/100)*(1+F42/100))))),0))) -> 6.8845562 | G95: =IF(G92=0,0,IF(G87=1,(1-F99)*F92*G43/((1+G24/100)*(1+G42/100)),IF(AND(G87=0,G88=1),(F98*F92*G43/((1+G24/100)*(1+G42/100)))*(1-ABS(G92-F92*G43/((1+G24/100)*(1+G42/100)))/((G39*F92*F99*G43/((1+G24/100)*(1+G42/100)))+(F98*F92*G43/((1+G24/100)*(1+G42/100))))),0))) -> 7.0046214 | H95: =IF(H92=0,0,IF(H87=1,(1-G99)*G92*H43/((1+H24/100)*(1+H42/100)),IF(AND(H87=0,H88=1),(G98*G92*H43/((1+H24/100)*(1+H42/100)))*(1-ABS(H92-G92*H43/((1+H24/100)*(1+H42/100)))/((H39*G92*G99*H43/((1+H24/100)*(1+H42/100)))+(G98*G92*H43/((1+H24/100)*(1+H42/100))))),0))) -> 6.7988959 | I95: =IF(I92=0,0,IF(I87=1,(1-H99)*H92*I43/((1+I24/100)*(1+I42/100)),IF(AND(I87=0,I88=1),(H98*H92*I43/((1+I24/100)*(1+I42/100)))*(1-ABS(I92-H92*I43/((1+I24/100)*(1+I42/100)))/((I39*H92*H99*I43/((1+I24/100)*(1+I42/100)))+(H98*H92*I43/((1+I24/100)*(1+I42/100))))),0))) -> 6.6544185 | J95: =IF(J92=0,0,IF(J87=1,(1-I99)*I92*J43/((1+J24/100)*(1+J42/100)),IF(AND(J87=0,J88=1),(I98*I92*J43/((1+J24/100)*(1+J42/100)))*(1-ABS(J92-I92*J43/((1+J24/100)*(1+J42/100)))/((J39*I92*I99*J43/((1+J24/100)*(1+J42/100)))+(I98*I92*J43/((1+J24/100)*(1+J42/100))))),0))) -> 6.5073284 | K95: =IF(K92=0,0,IF(K87=1,(1-J99)*J92*K43/((1+K24/100)*(1+K42/100)),IF(AND(K87=0,K88=1),(J98*J92*K43/((1+K24/100)*(1+K42/100)))*(1-ABS(K92-J92*K43/((1+K24/100)*(1+K42/100)))/((K39*J92*J99*K43/((1+K24/100)*(1+K42/100)))+(J98*J92*K43/((1+K24/100)*(1+K42/100))))),0))) -> 6.3062201 | L95: =IF(L92=0,0,IF(L87=1,(1-K99)*K92*L43/((1+L24/100)*(1+L42/100)),IF(AND(L87=0,L88=1),(K98*K92*L43/((1+L24/100)*(1+L42/100)))*(1-ABS(L92-K92*L43/((1+L24/100)*(1+L42/100)))/((L39*K92*K99*L43/((1+L24/100)*(1+L42/100)))+(K98*K92*L43/((1+L24/100)*(1+L42/100))))),0))) -> 6.0942907 | M95: =IF(M92=0,0,IF(M87=1,(1-L99)*L92*M43/((1+M24/100)*(1+M42/100)),IF(AND(M87=0,M88=1),(L98*L92*M43/((1+M24/100)*(1+M42/100)))*(1-ABS(M92-L92*M43/((1+M24/100)*(1+M42/100)))/((M39*L92*L99*M43/((1+M24/100)*(1+M42/100)))+(L98*L92*M43/((1+M24/100)*(1+M42/100))))),0))) -> 5.87863 | ... W95: =IF(W92=0,0,IF(W87=1,(1-V99)*V92*W43/((1+W24/100)*(1+W42/100)),IF(AND(W87=0,W88=1),(V98*V92*W43/((1+W24/100)*(1+W42/100)))*(1-ABS(W92-V92*W43/((1+W24/100)*(1+W42/100)))/((W39*V92*V99*W43/((1+W24/100)*(1+W42/100)))+(V98*V92*W43/((1+W24/100)*(1+W42/100))))),0))) -> 4.8907752
B96: New long-term debt | E96: ='Input data'!$C$69*E$92 -> 8.209995 | F96: =IF(F92=0,0,IF(F87=1,'Input data'!$C$58*(F92-E92*F43/((1+F24/100)*(1+F42/100))),0)) -> 4.755379 | G96: =IF(G92=0,0,IF(G87=1,'Input data'!$C$58*(G92-F92*G43/((1+G24/100)*(1+G42/100))),0)) -> 2.4559041 | H96: =IF(H92=0,0,IF(H87=1,'Input data'!$C$58*(H92-G92*H43/((1+H24/100)*(1+H42/100))),0)) -> 2.0281123 | I96: =IF(I92=0,0,IF(I87=1,'Input data'!$C$58*(I92-H92*I43/((1+I24/100)*(1+I42/100))),0)) -> 1.8514341 | J96: =IF(J92=0,0,IF(J87=1,'Input data'!$C$58*(J92-I92*J43/((1+J24/100)*(1+J42/100))),0)) -> 1.407326 | K96: =IF(K92=0,0,IF(K87=1,'Input data'!$C$58*(K92-J92*K43/((1+K24/100)*(1+K42/100))),0)) -> 1.2709063 | L96: =IF(L92=0,0,IF(L87=1,'Input data'!$C$58*(L92-K92*L43/((1+L24/100)*(1+L42/100))),0)) -> 1.1477338 | M96: =IF(M92=0,0,IF(M87=1,'Input data'!$C$58*(M92-L92*M43/((1+M24/100)*(1+M42/100))),0)) -> 1.0471804 | ... W96: =IF(W92=0,0,IF(W87=1,'Input data'!$C$58*(W92-V92*W43/((1+W24/100)*(1+W42/100))),0)) -> 2.7291703
B97: New short-term debt | E97: ='Input data'!$C$70*E$92 -> 0.91222167 | F97: =IF(F92=0,0,IF(F87=1,'Input data'!$C$57*(F92-E92*F43/((1+F24/100)*(1+F42/100))),0)) -> 0.44055435 | G97: =IF(G92=0,0,IF(G87=1,'Input data'!$C$57*(G92-F92*G43/((1+G24/100)*(1+G42/100))),0)) -> 0.22752324 | H97: =IF(H92=0,0,IF(H87=1,'Input data'!$C$57*(H92-G92*H43/((1+H24/100)*(1+H42/100))),0)) -> 0.18789117 | I97: =IF(I92=0,0,IF(I87=1,'Input data'!$C$57*(I92-H92*I43/((1+I24/100)*(1+I42/100))),0)) -> 0.1715231 | J97: =IF(J92=0,0,IF(J87=1,'Input data'!$C$57*(J92-I92*J43/((1+J24/100)*(1+J42/100))),0)) -> 0.13037943 | K97: =IF(K92=0,0,IF(K87=1,'Input data'!$C$57*(K92-J92*K43/((1+K24/100)*(1+K42/100))),0)) -> 0.11774105 | L97: =IF(L92=0,0,IF(L87=1,'Input data'!$C$57*(L92-K92*L43/((1+L24/100)*(1+L42/100))),0)) -> 0.10632993 | M97: =IF(M92=0,0,IF(M87=1,'Input data'!$C$57*(M92-L92*M43/((1+M24/100)*(1+M42/100))),0)) -> 0.097014321 | ... W97: =IF(W92=0,0,IF(W87=1,'Input data'!$C$57*(W92-V92*W43/((1+W24/100)*(1+W42/100))),0)) -> 0.25283955
B98: Share of short-term debt in total government debt | E98: ='Baseline NFPC'!E$93 -> 0.10000001 | F98: =IF(F92<>0,(F95+F97)/(F93+F94+F95+F96+F97),0) -> 0.098932517 | G98: =IF(G92<>0,(G95+G97)/(G93+G94+G95+G96+G97),0) -> 0.09841602 | H98: =IF(H92<>0,(H95+H97)/(H93+H94+H95+H96+H97),0) -> 0.097992466 | I98: =IF(I92<>0,(I95+I97)/(I93+I94+I95+I96+I97),0) -> 0.097610494 | J98: =IF(J92<>0,(J95+J97)/(J93+J94+J95+J96+J97),0) -> 0.097321409 | K98: =IF(K92<>0,(K95+K97)/(K93+K94+K95+K96+K97),0) -> 0.097058454 | L98: =IF(L92<>0,(L95+L97)/(L93+L94+L95+L96+L97),0) -> 0.096818189 | M98: =IF(M92<>0,(M95+M97)/(M93+M94+M95+M96+M97),0) -> 0.096595686 | ... W98: =IF(W92<>0,(W95+W97)/(W93+W94+W95+W96+W97),0) -> 0.09304098
B99: Share of long-term debt in total government debt | E99: ='Baseline NFPC'!E$94 -> 0.89999999 | F99: =IF(F92<>0,(F93+F94+F96)/(F93+F94+F95+F96+F97),1) -> 0.90106748 | G99: =IF(G92<>0,(G93+G94+G96)/(G93+G94+G95+G96+G97),1) -> 0.90158398 | H99: =IF(H92<>0,(H93+H94+H96)/(H93+H94+H95+H96+H97),1) -> 0.90200753 | I99: =IF(I92<>0,(I93+I94+I96)/(I93+I94+I95+I96+I97),1) -> 0.90238951 | J99: =IF(J92<>0,(J93+J94+J96)/(J93+J94+J95+J96+J97),1) -> 0.90267859 | K99: =IF(K92<>0,(K93+K94+K96)/(K93+K94+K95+K96+K97),1) -> 0.90294155 | L99: =IF(L92<>0,(L93+L94+L96)/(L93+L94+L95+L96+L97),1) -> 0.90318181 | M99: =IF(M92<>0,(M93+M94+M96)/(M93+M94+M95+M96+M97),1) -> 0.90340431 | ... W99: =IF(W92<>0,(W93+W94+W96)/(W93+W94+W95+W96+W97),1) -> 0.90695902
B101: IIR | C101: ='Baseline NFPC'!C96 -> 3.238231 | D101: ='Baseline NFPC'!D96 -> 4.417456 | E101: ='Baseline NFPC'!E96 -> 7.284665 | F101: ='Baseline NFPC'!F96 -> 7.231643 | G101: ='Baseline NFPC'!G96 -> 5.674904 | H101: =H103+H104 -> 5.6484363 | I101: =I103+I104 -> 5.7650421 | J101: =J103+J104 -> 5.8711309 | K101: =K103+K104 -> 5.9643176 | L101: =L103+L104 -> 6.0503547 | M101: =M103+M104 -> 6.1300808 | N101: =N103+N104 -> 6.2043184 | O101: =O103+O104 -> 6.2751747 | ... W101: =W103+W104 -> 6.2915575
B102: Long-term implicit interest rate | F102: =((F36*E92)-(F38*(E95+E97)))/(E93+E94+E96) -> 7.2267647 | G102: =((G36*F92)-(G38*(F95+F97)))/(F93+F94+F96) -> 5.6458541 | H102: =IF(G92>0,(G102*G93+ ('Baseline NFPC'!H$97*(G93+G94+G96)-'Baseline NFPC'!G$97*G93)/(G94+G96) *(G96+G94))/(G93+G94+G96),H37) -> 5.6382136 | I102: =IF(H92>0,(H102*H93+I37*(H96+H94))/(H93+H94+H96),I37) -> 5.7572152 | J102: =IF(I92>0,(I102*I93+J37*(I96+I94))/(I93+I94+I96),J37) -> 5.864537 | K102: =IF(J92>0,(J102*J93+K37*(J96+J94))/(J93+J94+J96),K37) -> 5.9575497 | L102: =IF(K92>0,(K102*K93+L37*(K96+K94))/(K93+K94+K96),L37) -> 6.0426434 | M102: =IF(L92>0,(L102*L93+M37*(L96+L94))/(L93+L94+L96),M37) -> 6.1207531 | N102: =IF(M92>0,(M102*M93+N37*(M96+M94))/(M93+M94+M96),N37) -> 6.1927944 | O102: =IF(N92>0,(N102*N93+O37*(N96+N94))/(N93+N94+N96),O37) -> 6.2611071 | P102: =IF(O92>0,(O102*O93+P37*(O96+O94))/(O93+O94+O96),P37) -> 6.326152 | ... W102: =IF(V92>0,(V102*V93+W37*(V96+V94))/(V93+V94+V96),W37) -> 6.4143354
B103: Nominal implicit interest rate on debt (Excel approximation) | F103: =(F102*(E93+E94+E96)+F38*(E95+E97))/E92 -> 7.231643 | G103: =(G102*(F93+F94+F96)+G38*(F95+F97))/F92 -> 5.674904 | H103: =(H102*(G93+G94+G96)+H38*(G95+G97))/G92 -> 5.6484363 | I103: =(I102*(H93+H94+H96)+I38*(H95+H97))/H92 -> 5.7650421 | J103: =(J102*(I93+I94+I96)+J38*(I95+I97))/I92 -> 5.8711309 | K103: =(K102*(J93+J94+J96)+K38*(J95+J97))/J92 -> 5.9643176 | L103: =(L102*(K93+K94+K96)+L38*(K95+K97))/K92 -> 6.0503547 | M103: =(M102*(L93+L94+L96)+M38*(L95+L97))/L92 -> 6.1300808 | ... W103: =(W102*(V93+V94+V96)+W38*(V95+V97))/V92 -> 6.2915575
B104: Diff. STATA | F104: =IF('Criteria results'!$F$5=4,F115,F120) -> 0 | G104: =IF('Criteria results'!$F$5=4,G115,G120) -> 0 | H104: =IF('Criteria results'!$F$5=4,H115,H120) -> 0 | I104: =IF('Criteria results'!$F$5=4,I115,I120) -> 0 | J104: =IF('Criteria results'!$F$5=4,J115,J120) -> 0 | K104: =IF('Criteria results'!$F$5=4,K115,K120) -> 0 | L104: =IF('Criteria results'!$F$5=4,L115,L120) -> 0 | M104: =IF('Criteria results'!$F$5=4,M115,M120) -> 0 | ... W104: =IF('Criteria results'!$F$5=4,W115,W120) -> 0
B106: (i - g) | C106: =((1+C101/100)/((1+C24/100)*(1+C42/100))-1)*100 -> -9.3034373 | D106: =((1+D101/100)/((1+D24/100)*(1+D42/100))-1)*100 -> -12.324289 | E106: =((1+E101/100)/((1+E24/100)*(1+E42/100))-1)*100 -> -5.4617189 | F106: =((1+F101/100)/((1+F24/100)*(1+F42/100))-1)*100 -> -0.53672043 | G106: =((1+G101/100)/((1+G24/100)*(1+G42/100))-1)*100 -> 0.32455059 | H106: =((1+H101/100)/((1+H24/100)*(1+H42/100))-1)*100 -> -0.68053735 | I106: =((1+I101/100)/((1+I24/100)*(1+I42/100))-1)*100 -> 0.73369173 | J106: =((1+J101/100)/((1+J24/100)*(1+J42/100))-1)*100 -> 0.92940372 | ... W106: =((1+W101/100)/((1+W24/100)*(1+W42/100))-1)*100 -> 1.5758364
B110: Per memo - STATA results
B112: No extension (annual adjustment of 0.7)
B113: Debt | C113: 76.219376 | D113: 73.842926 | E113: 73.438004 | F113: 74.50444 | G113: 74.397163 | H113: 72.634666 | I113: 71.534828 | J113: 69.906372 | K113: 67.829269 | L113: 65.566284 | M113: 63.205242 | N113: 61.282082 | O113: 59.608906 | P113: 58.145325 | Q113: 56.909683 | R113: 55.922897 | S113: 55.186272 | T113: 54.71497 | U113: 54.520069 | V113: 54.602741 | W113: 54.976734
B114: IIR | C114: 3.2382312 | D114: 4.4174557 | E114: 7.2846651 | F114: 7.2316427 | G114: 5.6749029 | H114: 5.6487217 | I114: 5.7687912 | J114: 5.8762255 | K114: 5.9690738 | L114: 6.0543623 | M114: 6.1329751 | N114: 6.2057695 | O114: 6.2752986 | P114: 6.3413439 | Q114: 6.3675203 | R114: 6.3815899 | S114: 6.3842144 | T114: 6.3758793 | U114: 6.3570704 | V114: 6.3282781 | W114: 6.2899971
B115: IIR difference STATA - Excel | E115: 0 | F115: 0 | G115: 0 | H115: 0 | I115: 0 | J115: 0 | K115: 0 | L115: 0 | M115: 0 | N115: 0 | O115: 0 | P115: 0 | Q115: 0 | R115: 0 | S115: 0 | T115: 0 | U115: 0 | V115: 0 | W115: 0
B117: Extension (annual adjustment of 0.44)
B118: Debt | C118: 76.219376 | D118: 73.842926 | E118: 73.438004 | F118: 74.50444 | G118: 74.426231 | H118: 72.949898 | I118: 72.392876 | J118: 71.574944 | K118: 70.436096 | L118: 68.785957 | M118: 66.670364 | N118: 64.365959 | O118: 62.181152 | P118: 60.068867 | Q118: 58.364067 | R118: 56.899921 | S118: 55.677738 | T118: 54.712868 | U118: 54.016319 | V118: 53.589321 | W118: 53.446014
B119: IIR | C119: 3.2382312 | D119: 4.4174557 | E119: 7.2846651 | F119: 7.2316427 | G119: 5.6749029 | H119: 5.6485891 | I119: 5.7737684 | J119: 5.888236 | K119: 5.9898686 | L119: 6.0801187 | M119: 6.1602106 | N119: 6.2311883 | O119: 6.2976294 | P119: 6.3595152 | Q119: 6.3813 | R119: 6.3919482 | S119: 6.3921056 | T119: 6.3822193 | U119: 6.3627028 | V119: 6.33394 | W119: 6.2962885
B120: IIR difference STATA - Excel | G120: 0 | H120: 0 | I120: 0 | J120: 0 | K120: 0 | L120: 0 | M120: 0 | N120: 0 | O120: 0 | P120: 0 | Q120: 0 | R120: 0 | S120: 0 | T120: 0 | U120: 0 | V120: 0 | W120: 0

Sheet Financial stress
B3: Country | C3: ='Input data'!C3 -> HU
B4: Key years
B5: ='Input data'!B5 -> Last year before the adjustment | C5: =+'Input data'!C5 -> 2024
B6: Last year of adjustment | C6: =+C5+'Criteria results'!F5 -> 2028
B7: Last year of no-fiscal-policy-change projections | C7: =C5+'Criteria results'!F5+10 -> 2038
B9: Key assumptions
C10: 2021 | D10: 2022 | E10: 2023 | F10: 2024 | G10: 2025 | H10: 2026 | I10: 2027 | J10: 2028 | K10: 2029 | L10: 2030 | M10: 2031 | N10: 2032 | O10: 2033 | P10: 2034 | Q10: 2035 | R10: 2036 | S10: 2037 | T10: 2038 | U10: 2039 | V10: 2040 | W10: 2041
B11: Fiscal assumptions (% of GDP)
B12: Structural primary balance ('+' means 'surplus') | C12: ='Input data'!C13 -> -5.106841 | D12: ='Input data'!D13 -> -4.391969 | E12: ='Input data'!E13 -> -1.706974 | F12: ='Input data'!F13 -> 0.64244146 | G12: ='Adjust. no safeguard'!G12 -> 1.1824415 | H12: ='Adjust. no safeguard'!H12 -> 1.7224415 | I12: ='Adjust. no safeguard'!I12 -> 2.2624415 | J12: ='Adjust. no safeguard'!J12 -> 2.8024415 | K12: ='Adjust. no safeguard'!K12 -> 2.8024415 | L12: ='Adjust. no safeguard'!L12 -> 2.8024415 | M12: ='Adjust. no safeguard'!M12 -> 2.8024415 | N12: =IF(N10<=$C$6,M12+'Criteria results'!$F$6,M12) -> 2.8024415 | O12: =IF(O10<=$C$6,N12+'Criteria results'!$F$6,N12) -> 2.8024415 | P12: =IF(P10<=$C$6,O12+'Criteria results'!$F$6,O12) -> 2.8024415 | Q12: =IF(Q10<=$C$6,P12+'Criteria results'!$F$6,P12) -> 2.8024415 | R12: =IF(R10<=$C$6,Q12+'Criteria results'!$F$6,Q12) -> 2.8024415 | S12: =IF(S10<=$C$6,R12+'Criteria results'!$F$6,R12) -> 2.8024415 | T12: =IF(T10<=$C$6,S12+'Criteria results'!$F$6,S12) -> 2.8024415 | U12: =IF(U10<=$C$6,T12+'Criteria results'!$F$6,T12) -> 2.8024415 | ... W12: =IF(W10<=$C$6,V12+'Criteria results'!$F$6,V12) -> 2.8024415
B13: One-off and other temporary measures | C13: ='Input data'!C14 -> -0.1079972 | D13: ='Input data'!D14 -> 0 | E13: ='Input data'!E14 -> 0 | F13: ='Input data'!F14 -> 0 | G13: ='Input data'!G14 -> 0 | H13: ='Input data'!H14 -> 0 | I13: ='Input data'!I14 -> 0 | J13: ='Input data'!J14 -> 0 | ... W13: ='Input data'!W14 -> 0
B14: Stock flow adjustments (without exchange rate effect) | C14: ='Input data'!C15 -> -0.1371056 | D14: ='Input data'!D15 -> 1.066777 | E14: ='Input data'!E15 -> 2.471388 | F14: ='Input data'!F15 -> 0.243711 | G14: ='Input data'!G15 -> -0.9088278 | H14: ='Input data'!H15 -> -0.250576 | I14: ='Input data'!I15 -> 0 | J14: ='Input data'!J15 -> 0 | ... W14: ='Input data'!W15 -> 0
B16: ='Input data'!B19 -> Cost of ageing and selected public revenue (based on the Commission-Council 2024 Ageing Report ("AR 2024"))
B17: Total ageing cost (net of taxes on pensions) | C17: ='Input data'!C20 -> 0 | D17: ='Input data'!D20 -> 16.0166 | E17: ='Input data'!E20 -> 16.12175 | F17: ='Input data'!F20 -> 16.12852 | G17: ='Input data'!G20 -> 16.01381 | H17: ='Input data'!H20 -> 15.92993 | I17: ='Input data'!I20 -> 15.87402 | J17: ='Input data'!J20 -> 15.87527 | ... W17: ='Input data'!W20 -> 17.97964
B18: Property income | C18: ='Input data'!C26 -> 0.5353987 | D18: ='Input data'!D26 -> 1.178846 | E18: ='Input data'!E26 -> 2.102853 | F18: ='Input data'!F26 -> 2.07289 | G18: ='Input data'!G26 -> 2.042928 | H18: ='Input data'!H26 -> 2.012965 | I18: ='Input data'!I26 -> 1.983002 | J18: ='Input data'!J26 -> 1.953039 | ... W18: ='Input data'!W26 -> 1.563521
B20: GDP growth assumptions
B21: Actual GDP (real)
B22: Level | C22: ='Input data'!C31 -> 133.9938 | D22: ='Baseline NFPC'!D22 -> 139.70315 | E22: ='Baseline NFPC'!E22 -> 138.38125 | F22: ='Baseline NFPC'!F22 -> 139.19078 | G22: =IF(AND(G49>1,F49>1), G26*(1+('Baseline NFPC'!G$29+G50)/100)-F22*$C$46*(G12-F12)/100, IF(G49=1,G26,F22*(1+G51/100))) -> 140.88433 | H22: =IF(AND(H49>1,G49>1), H26*(1+('Baseline NFPC'!H$29+H50)/100)-G22*$C$46*(H12-G12)/100, IF(H49=1,H26,G22*(1+H51/100))) -> 144.81636 | I22: =IF(AND(I49>1,H49>1), I26*(1+I50/100)-H22*$C$46*(I12-H12)/100, IF(I49=1,I26,H22*(1+I51/100))) -> 147.01801 | J22: =IF(AND(J49>1,I49>1), J26*(1+J50/100)-I22*$C$46*(J12-I12)/100, IF(J49=1,J26,I22*(1+J51/100))) -> 149.20224 | K22: =IF(AND(K49>1,J49>1), K26*(1+K50/100)-J22*$C$46*(K12-J12)/100, IF(K49=1,K26,J22*(1+K51/100))) -> 152.02987 | L22: =IF(AND(L49>1,K49>1), L26*(1+L50/100)-K22*$C$46*(L12-K12)/100, IF(L49=1,L26,K22*(1+L51/100))) -> 155.22905 | M22: =IF(AND(M49>1,L49>1), M26*(1+M50/100)-L22*$C$46*(M12-L12)/100, IF(M49=1,M26,L22*(1+M51/100))) -> 158.69246 | N22: =IF(AND(N49>1,M49>1), N26*(1+N50/100)-M22*$C$46*(N12-M12)/100, IF(N49=1,N26,M22*(1+N51/100))) -> 161.73488 | O22: =IF(AND(O49>1,N49>1), O26*(1+O50/100)-N22*$C$46*(O12-N12)/100, IF(O49=1,O26,N22*(1+O51/100))) -> 164.70182 | P22: =IF(AND(P49>1,O49>1), P26*(1+P50/100)-O22*$C$46*(P12-O12)/100, IF(P49=1,P26,O22*(1+P51/100))) -> 167.75405 | ... W22: =IF(AND(W49>1,V49>1), W26*(1+W50/100)-V22*$C$46*(W12-V12)/100, IF(W49=1,W26,V22*(1+W51/100))) -> 188.86752
B23: Growth rate | C23: =+'Input data'!C30 -> 7.121139 | D23: ='Baseline NFPC'!D23 -> 4.260908 | E23: ='Baseline NFPC'!E23 -> -0.9462205 | F23: ='Baseline NFPC'!F23 -> 0.584996 | G23: =100*(G22/F22-1) -> 1.216716 | H23: =100*(H22/G22-1) -> 2.7909618 | I23: =100*(I22/H22-1) -> 1.5203043 | J23: =100*(J22/I22-1) -> 1.4856906 | K23: =100*(K22/J22-1) -> 1.8951652 | L23: =100*(L22/K22-1) -> 2.1043109 | M23: =100*(M22/L22-1) -> 2.2311598 | N23: =100*(N22/M22-1) -> 1.917179 | ... W23: =100*(W22/V22-1) -> 1.601132
B25: Potential GDP (real)
B26: Level | C26: ='Input data'!C34 -> 132.9781 | D26: =+C26*(1+'Input data'!D33/100) -> 136.6169 | E26: =+D26*(1+'Input data'!E33/100) -> 139.17592 | F26: =+E26*(1+'Input data'!F33/100) -> 141.10966 | G26: =+F26*(1+'Input data'!G33/100) -> 143.274 | H26: =+G26*(1+'Input data'!H33/100) -> 145.73938 | I26: =+H26*(1+'Input data'!I33/100) -> 148.23038 | J26: =+I26*(1+'Input data'!J33/100) -> 150.61893 | K26: =+J26*(1+'Input data'!K33/100) -> 152.9892 | ... W26: =+V26*(1+'Input data'!W33/100) -> 188.8675
B28: Output gap
B29: Output gap | C29: =100*(C22/C26-1) -> 0.76380998 | D29: =100*(D22/D26-1) -> 2.2590596 | E29: =100*(E22/E26-1) -> -0.5709813 | F29: =100*(F22/F26-1) -> -1.3598515 | G29: =100*(G22/G26-1) -> -1.6678968 | H29: =100*(H22/H26-1) -> -0.63333134 | I29: =100*(I22/I26-1) -> -0.81789301 | J29: =100*(J22/J26-1) -> -0.94057946 | ... W29: =100*(W22/W26-1) -> 8.8436136e-06
B31: Actual GDP (nominal, national currency)
B32: Growth rate | C32: =100*((1+C23/100)*(1+C41/100)-1) -> 13.828163 | D32: =100*((1+D23/100)*(1+D41/100)-1) -> 19.095077 | E32: =100*((1+E23/100)*(1+E41/100)-1) -> 13.482775 | F32: =100*((1+F23/100)*(1+F41/100)-1) -> 7.8102828 | G32: =100*((1+G23/100)*(1+G41/100)-1) -> 5.333045 | H32: =100*((1+H23/100)*(1+H41/100)-1) -> 6.3723398 | I32: =100*((1+I23/100)*(1+I41/100)-1) -> 4.9947046 | J32: =100*((1+J23/100)*(1+J41/100)-1) -> 4.8962215 | ... W32: =100*((1+W23/100)*(1+W41/100)-1) -> 4.6425619
B34: Interest rates
B35: Nominal implicit interest rate on debt | C35: ='Input data'!C37 -> 3.238231 | D35: ='Input data'!D37 -> 4.417456 | E35: ='Input data'!E37 -> 7.284665 | F35: ='Input data'!F37 -> 7.231643 | G35: ='Input data'!G37 -> 5.674904 | H35: =H92 -> 5.6484363 | I35: =I92 -> 5.7650421 | J35: =J92 -> 5.8711309 | K35: =K92 -> 6.1455074 | L35: =L92 -> 6.1277064 | M35: =M92 -> 6.2008426 | N35: =N92 -> 6.2690372 | O35: =O92 -> 6.3341921 | ... W35: =W92 -> 6.3152372
B36: Long-term interest rate | D36: ='Input data'!D$39 -> 7.57 | E36: ='Input data'!E$39 -> 7.51 | F36: ='Input data'!F$39 -> 6.52395 | G36: ='Input data'!G$39 -> 6.731379 | H36: ='Input data'!H$39 -> 6.82931 | I36: =H36+($P$36-$H$36)/($P$10-$H$10) -> 6.8414188 | J36: =I36+($P$36-$H$36)/($P$10-$H$10) -> 6.8535275 | K36: =IF('Criteria results'!$F$5=4, IF(J56>90,H36+('Input data'!$C$52-$H$36)/($P$10-$H$10)*(K10-$H$10)+1+0.06*(J56-90), H36+('Input data'!$C$52-$H$36)/($P$10-$H$10)*(K10-$H$10)+1), H36+('Input data'!$C$52-$H$36)/($P$10-$H$10)*(K10-$H$10)) -> 7.8656362 | L36: =$H$36+('Input data'!$C$52-$H$36)/($P$10-$H$10)*(L10-$H$10) -> 6.877745 | M36: =$H$36+('Input data'!$C$52-$H$36)/($P$10-$H$10)*(M10-$H$10) -> 6.8898538 | N36: =IF('Criteria results'!$F$5=7, IF(M56>90,H36+('Input data'!$C$52-$H$36)/($P$10-$H$10)*(N10-$H$10)+1+0.06*(M56-90), H36+('Input data'!$C$52-$H$36)/($P$10-$H$10)*(N10-$H$10)+1), H36+('Input data'!$C$52-$H$36)/($P$10-$H$10)*(N10-$H$10)) -> 6.9019625 | O36: =$H$36+('Input data'!$C$52-$H$36)/($P$10-$H$10)*(O10-$H$10) -> 6.9140712 | P36: ='Baseline NFPC'!P36 -> 6.92618 | Q36: ='Baseline NFPC'!Q36 -> 6.829871 | R36: ='Baseline NFPC'!R36 -> 6.733562 | S36: ='Baseline NFPC'!S36 -> 6.637253 | T36: ='Baseline NFPC'!T36 -> 6.540944 | U36: ='Baseline NFPC'!U36 -> 6.444635 | V36: ='Baseline NFPC'!V36 -> 6.348326 | W36: ='Baseline NFPC'!W36 -> 6.252017
B37: Short-term interest rate | D37: ='Input data'!D$38 -> 10.32 | E37: ='Input data'!E$38 -> 15.97 | F37: ='Input data'!F$38 -> 7.275548 | G37: ='Input data'!G$38 -> 5.939488 | H37: ='Input data'!H$38 -> 5.742086 | I37: =H37+($P$37-$H$37)/($P$10-$H$10) -> 5.8370877 | J37: =I37+($P$37-$H$37)/($P$10-$H$10) -> 5.9320895 | K37: =IF('Criteria results'!$F$5=4, IF(J56>90,H37+('Input data'!$C$53-$H$37)/($P$10-$H$10)*(K10-$H$10)+1+0.06*(J56-90), H37+('Input data'!$C$53-$H$37)/($P$10-$H$10)*(K10-$H$10)+1), H37+('Input data'!$C$53-$H$37)/($P$10-$H$10)*(K10-$H$10)) -> 7.0270912 | L37: =$H$37+('Input data'!$C$53-$H$37)/($P$10-$H$10)*(L10-$H$10) -> 6.122093 | M37: =$H$37+('Input data'!$C$53-$H$37)/($P$10-$H$10)*(M10-$H$10) -> 6.2170948 | N37: =IF('Criteria results'!$F$5=7, IF(M56>90,H37+('Input data'!$C$53-$H$37)/($P$10-$H$10)*(N10-$H$10)+1+0.06*(M56-90), H37+('Input data'!$C$53-$H$37)/($P$10-$H$10)*(N10-$H$10)+1), H37+('Input data'!$C$53-$H$37)/($P$10-$H$10)*(N10-$H$10)) -> 6.3120965 | O37: =$H$37+('Input data'!$C$53-$H$37)/($P$10-$H$10)*(O10-$H$10) -> 6.4070983 | P37: ='Baseline NFPC'!P37 -> 6.5021 | Q37: ='Baseline NFPC'!Q37 -> 6.301995 | R37: ='Baseline NFPC'!R37 -> 6.10189 | S37: ='Baseline NFPC'!S37 -> 5.901785 | T37: ='Baseline NFPC'!T37 -> 5.70168 | U37: ='Baseline NFPC'!U37 -> 5.501575 | V37: ='Baseline NFPC'!V37 -> 5.30147 | W37: ='Baseline NFPC'!W37 -> 5.101365
B38: Share of long-term debt that matures every year | C38: ='Baseline NFPC'!C38 -> 0.07935879 | D38: ='Baseline NFPC'!D38 -> 0.06020197 | E38: ='Baseline NFPC'!E38 -> 0.05046041 | F38: ='Baseline NFPC'!F38 -> 0.06743385 | G38: ='Baseline NFPC'!G38 -> 0.068498038 | H38: ='Baseline NFPC'!H38 -> 0.069562226 | I38: ='Baseline NFPC'!I38 -> 0.070626414 | J38: ='Baseline NFPC'!J38 -> 0.071690602 | ... W38: ='Baseline NFPC'!W38 -> 0.07807573
B40: Inflation and exchange rate
B41: GDP deflator (National currency) | C41: ='Input data'!C42 -> 6.261158 | D41: ='Input data'!D42 -> 14.22793 | E41: ='Input data'!E42 -> 14.56683 | F41: ='Input data'!F42 -> 7.183265 | G41: ='Input data'!G42 -> 4.066847 | H41: ='Input data'!H42 -> 3.484137 | I41: ='Baseline NFPC'!I41 -> 3.4223699 | J41: ='Baseline NFPC'!J41 -> 3.3606027 | K41: ='Baseline NFPC'!K41 -> 3.2988356 | L41: ='Baseline NFPC'!L41 -> 3.2370685 | M41: ='Baseline NFPC'!M41 -> 3.1753014 | N41: ='Baseline NFPC'!N41 -> 3.1135343 | O41: ='Baseline NFPC'!O41 -> 3.0517671 | P41: ='Baseline NFPC'!P41 -> 2.99 | ... W41: ='Baseline NFPC'!W41 -> 2.9935
B42: Exchange rate composite change (weighted by share of debt in each currency) | C42: ='Baseline NFPC'!C42 -> 1.001704 | D42: ='Baseline NFPC'!D42 -> 1.038632 | E42: ='Baseline NFPC'!E42 -> 0.9884134 | F42: ='Baseline NFPC'!F42 -> 1.010684 | G42: ='Baseline NFPC'!G42 -> 1.007245 | H42: ='Baseline NFPC'!H42 -> 1 | I42: ='Baseline NFPC'!I42 -> 1 | J42: ='Baseline NFPC'!J42 -> 1 | ... W42: ='Baseline NFPC'!W42 -> 1
B44: Intermediate calculations (growth rate equation)
B46: Fiscal multiplier | C46: ='Input data'!C49 -> 0.75
B47: Budget balance semi-elasticity | C47: ='Input data'!C50 -> 0.453
B49: Auxiliary variable to control the closure of the output gap | C49: 0 | D49: =IF(AND(ABS((D12-C12)-('Input data'!D13-'Input data'!C13))>0.0001,ABS(D12-C12)>0.0001,D$10>$C$5),4,IF(C49=4,3,IF(C49=3,2,IF(C49=2,1,0)))) -> 0 | E49: =IF(AND(ABS((E12-D12)-('Input data'!E13-'Input data'!D13))>0.0001,ABS(E12-D12)>0.0001,E$10>$C$5),4,IF(D49=4,3,IF(D49=3,2,IF(D49=2,1,0)))) -> 0 | F49: =IF(AND(ABS((F12-E12)-('Input data'!F13-'Input data'!E13))>0.0001,ABS(F12-E12)>0.0001,F$10>$C$5),4,IF(E49=4,3,IF(E49=3,2,IF(E49=2,1,0)))) -> 0 | G49: =IF(AND(ABS((G12-F12)-('Baseline NFPC'!G12-'Baseline NFPC'!F12))>0.0001,ABS(G12-F12)>0.0001,G$10>$C$5),4,IF(F49=4,3,IF(F49=3,2,IF(F49=2,1,0)))) -> 4 | H49: =IF(AND(ABS((H12-G12)-('Baseline NFPC'!H12-'Baseline NFPC'!G12))>0.0001,ABS(H12-G12)>0.0001,H$10>$C$5),4,IF(G49=4,3,IF(G49=3,2,IF(G49=2,1,0)))) -> 4 | I49: =IF(AND(ABS((I12-H12)-('Baseline NFPC'!I12-'Baseline NFPC'!H12))>0.0001,ABS(I12-H12)>0.0001,I$10>$C$5),4,IF(H49=4,3,IF(H49=3,2,IF(H49=2,1,0)))) -> 4 | J49: =IF(AND(ABS((J12-I12)-('Baseline NFPC'!J12-'Baseline NFPC'!I12))>0.0001,ABS(J12-I12)>0.0001,J$10>$C$5),4,IF(I49=4,3,IF(I49=3,2,IF(I49=2,1,0)))) -> 4 | K49: =IF(AND(ABS((K12-J12)-('Baseline NFPC'!K12-'Baseline NFPC'!J12))>0.0001,ABS(K12-J12)>0.0001,K$10>$C$5),4,IF(J49=4,3,IF(J49=3,2,IF(J49=2,1,0)))) -> 3 | L49: =IF(AND(ABS((L12-K12)-('Baseline NFPC'!L12-'Baseline NFPC'!K12))>0.0001,ABS(L12-K12)>0.0001,L$10>$C$5),4,IF(K49=4,3,IF(K49=3,2,IF(K49=2,1,0)))) -> 2 | M49: =IF(AND(ABS((M12-L12)-('Baseline NFPC'!M12-'Baseline NFPC'!L12))>0.0001,ABS(M12-L12)>0.0001,M$10>$C$5),4,IF(L49=4,3,IF(L49=3,2,IF(L49=2,1,0)))) -> 1 | N49: =IF(AND(ABS((N12-M12)-('Baseline NFPC'!N12-'Baseline NFPC'!M12))>0.0001,ABS(N12-M12)>0.0001,N$10>$C$5),4,IF(M49=4,3,IF(M49=3,2,IF(M49=2,1,0)))) -> 0 | ... W49: =IF(AND(ABS((W12-V12)-('Baseline NFPC'!W12-'Baseline NFPC'!V12))>0.0001,ABS(W12-V12)>0.0001,W$10>$C$5),4,IF(V49=4,3,IF(V49=3,2,IF(V49=2,1,0)))) -> 0
B50: OG intermediate auxiliary value | C50: 0 | D50: 0 | E50: =IF(D49=4,2/3*(D29-'Baseline NFPC'!D29),IF(D49=3,1/3*(C29-'Baseline NFPC'!C29),0)) -> 0 | F50: =IF(E49=4,2/3*(E29-'Baseline NFPC'!E29),IF(E49=3,1/3*(D29-'Baseline NFPC'!D29),0)) -> 0 | G50: =IF(F49=4,2/3*(F29-'Baseline NFPC'!F29),IF(F49=3,1/3*(E29-'Baseline NFPC'!E29),0)) -> 0 | H50: =IF(G49=4,2/3*(G29-'Baseline NFPC'!G29),IF(G49=3,1/3*(F29-'Baseline NFPC'!F29),0)) -> -0.26230517 | I50: =IF(H49=4,2/3*H29,IF(H49=3,1/3*G29,0)) -> -0.42222089 | J50: =IF(I49=4,2/3*I29,IF(I49=3,1/3*H29,0)) -> -0.545262 | K50: =IF(J49=4,2/3*J29,IF(J49=3,1/3*I29,0)) -> -0.62705298 | L50: =IF(K49=4,2/3*K29,IF(K49=3,1/3*J29,0)) -> -0.31352649 | M50: =IF(L49=4,2/3*L29,IF(L49=3,1/3*K29,0)) -> 0 | N50: =IF(M49=4,2/3*M29,IF(M49=3,1/3*L29,0)) -> 0 | O50: =IF(N49=4,2/3*N29,IF(N49=3,1/3*M29,0)) -> 0 | P50: =IF(O49=4,2/3*O29,IF(O49=3,1/3*N29,0)) -> 0 | ... W50: =IF(V49=4,2/3*V29,IF(V49=3,1/3*U29,0)) -> 0
B51: GDP intermediate growth rate - only feedback effect and no closure of the OG | D51: ='Input data'!D30-$C$46*((D12-C12)-('Input data'!D13-'Input data'!C13)) -> 4.260908 | E51: ='Input data'!E30-$C$46*((E12-D12)-('Input data'!E13-'Input data'!D13)) -> -0.9462205 | F51: ='Input data'!F30-$C$46*((F12-E12)-('Input data'!F13-'Input data'!E13)) -> 0.584996 | G51: ='Input data'!G30-$C$46*(G12-F12) -> 1.216716 | H51: ='Input data'!H30-$C$46*(H12-G12) -> 2.649951 | I51: ='Input data'!I30-$C$46*(I12-H12) -> 1.29729 | J51: ='Input data'!J30-$C$46*(J12-I12) -> 1.199467 | K51: ='Input data'!K30-$C$46*(K12-J12) -> 1.566761 | L51: ='Input data'!L30-$C$46*(L12-K12) -> 1.78318 | M51: ='Input data'!M30-$C$46*(M12-L12) -> 1.910635 | N51: ='Input data'!N30-$C$46*(N12-M12) -> 1.917179 | ... W51: ='Input data'!W30-$C$46*(W12-V12) -> 1.601132
B53: Debt projections
C55: 2021 | D55: 2022 | E55: 2023 | F55: 2024 | G55: 2025 | H55: 2026 | I55: 2027 | J55: 2028 | K55: 2029 | L55: 2030 | M55: 2031 | N55: 2032 | O55: 2033 | P55: 2034 | Q55: 2035 | R55: 2036 | S55: 2037 | T55: 2038 | U55: 2039 | V55: 2040 | W55: 2041
B56: Gross debt | C56: =+'Input data'!C12 -> 76.21938 | D56: =+C56+D57 -> 73.842909 | E56: =+D56+E57 -> 73.437974 | F56: =+E56+F57 -> 74.041486 | G56: =+F56+G57 -> 73.48544 | H56: =+G56+H57 -> 71.299226 | I56: =+H56+I57 -> 69.930407 | J56: =+I56+J57 -> 68.203983 | K56: =+J56+K57 -> 66.303925 | ... W56: =+V56+W57 -> 55.781508
B57: Change in debt (-1+2+3) | D57: =-D58+D66+D71 -> -2.376471 | E57: =-E58+E66+E71 -> -0.40493547 | F57: =-F58+F66+F71 -> 0.60351226 | G57: =-G58+G66+G71 -> -0.55604531 | H57: =-H58+H66+H71 -> -2.1862145 | I57: =-I58+I66+I71 -> -1.3688194 | J57: =-J58+J66+J71 -> -1.7264232 | K57: =-K58+K66+K71 -> -1.900058 | ... W57: =-W58+W66+W71 -> 0.57391684
B58: (1) Primary balance (1.1 + 1.2 - 1.3 -1.4 -1.5 - 1.6 -1.7) | D58: =D59+D60-D61-D62-D63-D64-D65 -> -3.368615 | E58: =E59+E60-E61-E62-E63-E64-E65 -> -1.9656285 | F58: =F59+F60-F61-F62-F63-F64-F65 -> 0.026428741 | G58: =G59+G60-G61-G62-G63-G64-G65 -> 0.42688419 | H58: =H59+H60-H61-H62-H63-H64-H65 -> 1.4355424 | I58: =I59+I60-I61-I62-I63-I64-I65 -> 1.8919359 | J58: =J59+J60-J61-J62-J63-J64-J65 -> 2.376359 | K58: =K59+K60-K61-K62-K63-K64-K65 -> 2.4761035 | ... W58: =W59+W60-W61-W62-W63-W64-W65 -> 0.30855746
B59: (1.1) Structural primary balance (before ageing cost) | D59: =D12 -> -4.391969 | E59: =E12 -> -1.706974 | F59: =F12 -> 0.64244146 | G59: =IF(G12="",F59,G12) -> 1.1824415 | H59: =IF(H12="",G59,H12) -> 1.7224415 | I59: =IF(I12="",H59,I12) -> 2.2624415 | J59: =IF(J12="",I59,J12) -> 2.8024415 | K59: =IF(K12="",J59,K12) -> 2.8024415 | L59: =IF(L12="",K59,L12) -> 2.8024415 | M59: =IF(M12="",L59,M12) -> 2.8024415 | N59: =IF(N12="",M59,N12) -> 2.8024415 | ... W59: =IF(W12="",V59,W12) -> 2.8024415
B60: (1.2) Cumulated budgetary effort (in terms of primary balance) | D60: 0 | E60: 0 | F60: 0 | G60: 0 | H60: 0 | I60: 0 | J60: 0 | K60: 0 | L60: 0 | M60: 0 | N60: 0 | O60: 0 | P60: 0 | Q60: 0 | R60: 0 | S60: 0 | T60: 0 | U60: 0 | V60: 0 | W60: 0
B61: (1.3) Cyclical component | D61: =-$C$47*D29 -> -1.023354 | E61: =-$C$47*E29 -> 0.25865453 | F61: =-$C$47*F29 -> 0.61601271 | G61: =-$C$47*G29 -> 0.75555726 | H61: =-$C$47*H29 -> 0.2868991 | I61: =-$C$47*I29 -> 0.37050553 | J61: =-$C$47*J29 -> 0.4260825 | K61: =-$C$47*K29 -> 0.284055 | ... W61: =-$C$47*W29 -> -4.006157e-06
B62: (1.4) One-off and other temporary measures | D62: =-D13 -> 0 | E62: =-E13 -> 0 | F62: =-F13 -> 0 | G62: =-G13 -> 0 | H62: =-H13 -> 0 | I62: =-I13 -> 0 | J62: =-J13 -> 0 | K62: =-K13 -> 0 | ... W62: =-W13 -> 0
B63: (1.5) Cost of ageing | D63: =IF(D$55<=$C$6,0,HLOOKUP(D$55,'Input data'!$C$9:$BB$26,12,FALSE)-HLOOKUP($C$6,'Input data'!$C$9:$BB$26,12,FALSE)) -> 0 | E63: =IF(E$55<=$C$6,0,HLOOKUP(E$55,'Input data'!$C$9:$BB$26,12,FALSE)-HLOOKUP($C$6,'Input data'!$C$9:$BB$26,12,FALSE)) -> 0 | F63: =IF(F$55<=$C$6,0,HLOOKUP(F$55,'Input data'!$C$9:$BB$26,12,FALSE)-HLOOKUP($C$6,'Input data'!$C$9:$BB$26,12,FALSE)) -> 0 | G63: =IF(G$55<=$C$6,0,HLOOKUP(G$55,'Input data'!$C$9:$BB$26,12,FALSE)-HLOOKUP($C$6,'Input data'!$C$9:$BB$26,12,FALSE)) -> 0 | H63: =IF(H$55<=$C$6,0,HLOOKUP(H$55,'Input data'!$C$9:$BB$26,12,FALSE)-HLOOKUP($C$6,'Input data'!$C$9:$BB$26,12,FALSE)) -> 0 | I63: =IF(I$55<=$C$6,0,HLOOKUP(I$55,'Input data'!$C$9:$BB$26,12,FALSE)-HLOOKUP($C$6,'Input data'!$C$9:$BB$26,12,FALSE)) -> 0 | J63: =IF(J$55<=$C$6,0,HLOOKUP(J$55,'Input data'!$C$9:$BB$26,12,FALSE)-HLOOKUP($C$6,'Input data'!$C$9:$BB$26,12,FALSE)) -> 0 | K63: =IF(K$55<=$C$6,0,HLOOKUP(K$55,'Input data'!$C$9:$BB$26,12,FALSE)-HLOOKUP($C$6,'Input data'!$C$9:$BB$26,12,FALSE)) -> 0.01232 | ... W63: =IF(W$55<=$C$6,0,HLOOKUP(W$55,'Input data'!$C$9:$BB$26,12,FALSE)-HLOOKUP($C$6,'Input data'!$C$9:$BB$26,12,FALSE)) -> 2.10437
B64: (1.6) Property incomes | D64: =IF(D$55<=$C$5,0,-HLOOKUP(D$55,'Input data'!$C$9:$BB$26,18,FALSE)+HLOOKUP($C$6,'Input data'!$C$9:$BB$26,18,FALSE)) -> 0 | E64: =IF(E$55<=$C$5,0,-HLOOKUP(E$55,'Input data'!$C$9:$BB$26,18,FALSE)+HLOOKUP($C$6,'Input data'!$C$9:$BB$26,18,FALSE)) -> 0 | F64: =IF(F$55<=$C$5,0,-HLOOKUP(F$55,'Input data'!$C$9:$BB$26,18,FALSE)+HLOOKUP($C$6,'Input data'!$C$9:$BB$26,18,FALSE)) -> 0 | G64: =IF(G$55<=$C$6,0,-HLOOKUP(G$55,'Input data'!$C$9:$BB$26,18,FALSE)+HLOOKUP($C$6,'Input data'!$C$9:$BB$26,18,FALSE)) -> 0 | H64: =IF(H$55<=$C$6,0,-HLOOKUP(H$55,'Input data'!$C$9:$BB$26,18,FALSE)+HLOOKUP($C$6,'Input data'!$C$9:$BB$26,18,FALSE)) -> 0 | I64: =IF(I$55<=$C$6,0,-HLOOKUP(I$55,'Input data'!$C$9:$BB$26,18,FALSE)+HLOOKUP($C$6,'Input data'!$C$9:$BB$26,18,FALSE)) -> 0 | J64: =IF(J$55<=$C$6,0,-HLOOKUP(J$55,'Input data'!$C$9:$BB$26,18,FALSE)+HLOOKUP($C$6,'Input data'!$C$9:$BB$26,18,FALSE)) -> 0 | K64: =IF(K$55<=$C$6,0,-HLOOKUP(K$55,'Input data'!$C$9:$BB$26,18,FALSE)+HLOOKUP($C$6,'Input data'!$C$9:$BB$26,18,FALSE)) -> 0.029963 | L64: =IF(L$55<=$C$6,0,-HLOOKUP(L$55,'Input data'!$C$9:$BB$26,18,FALSE)+HLOOKUP($C$6,'Input data'!$C$9:$BB$26,18,FALSE)) -> 0.059926 | M64: =IF(M$55<=$C$6,0,-HLOOKUP(M$55,'Input data'!$C$9:$BB$26,18,FALSE)+HLOOKUP($C$6,'Input data'!$C$9:$BB$26,18,FALSE)) -> 0.089889 | N64: =IF(N$55<=$C$6,0,-HLOOKUP(N$55,'Input data'!$C$9:$BB$26,18,FALSE)+HLOOKUP($C$6,'Input data'!$C$9:$BB$26,18,FALSE)) -> 0.119852 | ... W64: =IF(W$55<=$C$6,0,-HLOOKUP(W$55,'Input data'!$C$9:$BB$26,18,FALSE)+HLOOKUP($C$6,'Input data'!$C$9:$BB$26,18,FALSE)) -> 0.389518
B65: (1.7) Revenues | D65: 0 | E65: 0 | F65: 0 | G65: 0 | H65: 0 | I65: 0 | J65: 0 | K65: 0 | L65: 0 | M65: 0 | N65: 0 | O65: 0 | P65: 0 | Q65: 0 | R65: 0 | S65: 0 | T65: 0 | U65: 0 | V65: 0 | W65: 0
B66: (2) Snowball effect (2.1 + 2.2 + 2.3) | D66: =SUM(D67:D70) -> -9.284277 | E66: =SUM(E67:E70) -> -4.088016 | F66: =SUM(F67:F70) -> -0.3415279 | G66: =SUM(G67:G70) -> 0.26926648 | H66: =SUM(H67:H70) -> -0.50009587 | I66: =SUM(I67:I70) -> 0.52311653 | J66: =SUM(J67:J70) -> 0.6499358 | K66: =SUM(K67:K70) -> 0.57604541 | ... W66: =SUM(W67:W70) -> 0.88247431
B67: (2.1) Interest expenditure | D67: =C56*D35/100*(1/(1+D32/100)) -> 2.8271173 | E67: =D56*E35/100*(1/(1+E32/100)) -> 4.7401102 | F67: =E56*F35/100*(1/(1+F32/100)) -> 4.9260348 | G67: =F56*G35/100*(1/(1+G32/100)) -> 3.9890456 | H67: =G56*H35/100*(1/(1+H32/100)) -> 3.9021218 | I67: =H56*I35/100*(1/(1+I32/100)) -> 3.9148931 | J67: =I56*J35/100*(1/(1+J32/100)) -> 3.9140644 | K67: =J56*K35/100*(1/(1+K32/100)) -> 3.9821579 | ... W67: =V56*W35/100*(1/(1+W32/100)) -> 3.331809
B68: (2.2) Growth effect | D68: =-C56*(D23/100)*(1/(1+D32/100)) -> -2.7269286 | E68: =-D56*(E23/100)*(1/(1+E32/100)) -> 0.6157029 | F68: =-E56*(F23/100)*(1/(1+F32/100)) -> -0.3984863 | G68: =-F56*(G23/100)*(1/(1+G32/100)) -> -0.85526304 | H68: =-G56*(H23/100)*(1/(1+H32/100)) -> -1.9280864 | I68: =-H56*(I23/100)*(1/(1+I32/100)) -> -1.0323999 | J68: =-I56*(J23/100)*(1/(1+J32/100)) -> -0.99045461 | K68: =-J56*(K23/100)*(1/(1+K32/100)) -> -1.2280267 | ... W68: =-V56*(W23/100)*(1/(1+W32/100)) -> -0.84472932
B69: (2.3) Inflation effect | D69: =-C56*D41/100*(1/(1+D41/100)) -> -9.4936852 | E69: =-D56*E41/100*(1/(1+E41/100)) -> -9.3889052 | F69: =-E56*F41/100*(1/(1+F41/100)) -> -4.9217051 | G69: =-F56*G41/100*(1/(1+G41/100)) -> -2.8934805 | H69: =-G56*H41/100*(1/(1+H41/100)) -> -2.4741313 | I69: =-H56*I41/100*(1/(1+I41/100)) -> -2.3593766 | J69: =-I56*J41/100*(1/(1+J41/100)) -> -2.273674 | K69: =-J56*K41/100*(1/(1+K41/100)) -> -2.1780858 | ... W69: =-V56*W41/100*(1/(1+W41/100)) -> -1.6046054
B70: (2.4) Exchange rate effect linked to the interest rate | D70: ='Baseline NFPC'!D70 -> 0.10921937 | E70: ='Baseline NFPC'!E70 -> -0.05492389 | F70: ='Baseline NFPC'!F70 -> 0.052628707 | G70: ='Baseline NFPC'!G70 -> 0.028964404 | H70: ='Baseline NFPC'!H70 -> 0 | I70: ='Baseline NFPC'!I70 -> 0 | J70: ='Baseline NFPC'!J70 -> 0 | K70: ='Baseline NFPC'!K70 -> 0 | ... W70: ='Baseline NFPC'!W70 -> 0
B71: (3 ) Stock flow adjustments (3.1 + 3.2) | D71: ='Input data'!D16 -> 3.539191 | E71: ='Input data'!E16 -> 1.717452 | F71: ='Input data'!F16 -> 0.9714689 | G71: ='Input data'!G16 -> -0.3984276 | H71: ='Input data'!H16 -> -0.2505763 | I71: ='Input data'!I16 -> 0 | J71: ='Input data'!J16 -> 0 | K71: ='Input data'!K16 -> 0 | ... W71: ='Input data'!W16 -> 0
B72: (3.1) Base | D72: =D14 -> 1.066777 | E72: =E14 -> 2.471388 | F72: =F14 -> 0.243711 | G72: =G14 -> -0.9088278 | H72: =H14 -> -0.250576 | I72: =I14 -> 0 | J72: =J14 -> 0 | K72: =K14 -> 0 | ... W72: =W14 -> 0
B73: (3.2) Adjustment due to the exchange rate effect linked to debt value | D73: =+D71-D72 -> 2.472414 | E73: =+E71-E72 -> -0.753936 | F73: =+F71-F72 -> 0.7277579 | G73: =+G71-G72 -> 0.5104002 | H73: =+H71-H72 -> -3e-07 | I73: =+I71-I72 -> 0 | J73: =+J71-J72 -> 0 | K73: =+K71-K72 -> 0 | ... W73: =+W71-W72 -> 0
B75: Debt increasing? (For criterion 1) | K75: =IF(K56<J56,0,1) -> 0 | L75: =IF(L56<K56,0,1) -> 0 | M75: =IF(M56<L56,0,1) -> 0 | N75: =IF(N56<M56,0,1) -> 0 | O75: =IF(O56<N56,0,1) -> 0 | P75: =IF(P56<O56,0,1) -> 0 | Q75: =IF(Q56<P56,0,1) -> 0 | R75: =IF(R56<Q56,0,1) -> 0 | ... W75: =IF(W56<V56,0,1) -> 1
B77: Debt decomposition and IIR
B79: Auxiliary variable identifying whether debt is increasing | F79: =IF((F83-E83*F42/((1+F23/100)*(1+F41/100)))>0,1,0) -> 1 | G79: =IF((G83-F83*G42/((1+G23/100)*(1+G41/100)))>0,1,0) -> 1 | H79: =IF((H83-G83*H42/((1+H23/100)*(1+H41/100)))>0,1,0) -> 1 | I79: =IF((I83-H83*I42/((1+I23/100)*(1+I41/100)))>0,1,0) -> 1 | J79: =IF((J83-I83*J42/((1+J23/100)*(1+J41/100)))>0,1,0) -> 1 | K79: =IF((K83-J83*K42/((1+K23/100)*(1+K41/100)))>0,1,0) -> 1 | L79: =IF((L83-K83*L42/((1+L23/100)*(1+L41/100)))>0,1,0) -> 1 | M79: =IF((M83-L83*M42/((1+M23/100)*(1+M41/100)))>0,1,0) -> 1 | ... W79: =IF((W83-V83*W42/((1+W23/100)*(1+W41/100)))>0,1,0) -> 1
B80: Auxiliary variable identifying whether some debt is rolled over even though debt is decreasing | F80: =IF(AND(F79=0,ABS(F83-E83*F42/((1+F23/100)*(1+F41/100)))<((E89*E83*F42/((1+F23/100)*(1+F41/100))+(F38*E83*E90*F42/((1+F23/100)*(1+F41/100)))))),1,0) -> 0 | G80: =IF(AND(G79=0,ABS(G83-F83*G42/((1+G23/100)*(1+G41/100)))<((F89*F83*G42/((1+G23/100)*(1+G41/100))+(G38*F83*F90*G42/((1+G23/100)*(1+G41/100)))))),1,0) -> 0 | H80: =IF(AND(H79=0,ABS(H83-G83*H42/((1+H23/100)*(1+H41/100)))<((G89*G83*H42/((1+H23/100)*(1+H41/100))+(H38*G83*G90*H42/((1+H23/100)*(1+H41/100)))))),1,0) -> 0 | I80: =IF(AND(I79=0,ABS(I83-H83*I42/((1+I23/100)*(1+I41/100)))<((H89*H83*I42/((1+I23/100)*(1+I41/100))+(I38*H83*H90*I42/((1+I23/100)*(1+I41/100)))))),1,0) -> 0 | J80: =IF(AND(J79=0,ABS(J83-I83*J42/((1+J23/100)*(1+J41/100)))<((I89*I83*J42/((1+J23/100)*(1+J41/100))+(J38*I83*I90*J42/((1+J23/100)*(1+J41/100)))))),1,0) -> 0 | K80: =IF(AND(K79=0,ABS(K83-J83*K42/((1+K23/100)*(1+K41/100)))<((J89*J83*K42/((1+K23/100)*(1+K41/100))+(K38*J83*J90*K42/((1+K23/100)*(1+K41/100)))))),1,0) -> 0 | L80: =IF(AND(L79=0,ABS(L83-K83*L42/((1+L23/100)*(1+L41/100)))<((K89*K83*L42/((1+L23/100)*(1+L41/100))+(L38*K83*K90*L42/((1+L23/100)*(1+L41/100)))))),1,0) -> 0 | M80: =IF(AND(M79=0,ABS(M83-L83*M42/((1+M23/100)*(1+M41/100)))<((L89*L83*M42/((1+M23/100)*(1+M41/100))+(M38*L83*L90*M42/((1+M23/100)*(1+M41/100)))))),1,0) -> 0 | ... W80: =IF(AND(W79=0,ABS(W83-V83*W42/((1+W23/100)*(1+W41/100)))<((V89*V83*W42/((1+W23/100)*(1+W41/100))+(W38*V83*V90*W42/((1+W23/100)*(1+W41/100)))))),1,0) -> 0
C82: 2021 | D82: 2022 | E82: 2023 | F82: 2024 | G82: 2025 | H82: 2026 | I82: 2027 | J82: 2028 | K82: 2029 | L82: 2030 | M82: 2031 | N82: 2032 | O82: 2033 | P82: 2034 | Q82: 2035 | R82: 2036 | S82: 2037 | T82: 2038 | U82: 2039 | V82: 2040 | W82: 2041
B83: Gross debt | C83: =C56 -> 76.21938 | D83: =D56 -> 73.842909 | E83: =E56 -> 73.437974 | F83: =F56 -> 74.041486 | G83: =G56 -> 73.48544 | H83: =G83*(1+H97/100)*H42-H59-H60+H61+H62+H63+H64+H65+H72 -> 71.299226 | I83: =H83*(1+I97/100)*I42-I59-I60+I61+I62+I63+I64+I65+I72 -> 69.930407 | J83: =I83*(1+J97/100)*J42-J59-J60+J61+J62+J63+J64+J65+J72 -> 68.203984 | K83: =J83*(1+K97/100)*K42-K59-K60+K61+K62+K63+K64+K65+K72 -> 66.303926 | L83: =K83*(1+L97/100)*L42-L59-L60+L61+L62+L63+L64+L65+L72 -> 64.21074 | M83: =L83*(1+M97/100)*M42-M59-M60+M61+M62+M63+M64+M65+M72 -> 62.07332 | N83: =M83*(1+N97/100)*N42-N59-N60+N61+N62+N63+N64+N65+N72 -> 60.321617 | O83: =N83*(1+O97/100)*O42-O59-O60+O61+O62+O63+O64+O65+O72 -> 58.832103 | ... W83: =V83*(1+W97/100)*W42-W59-W60+W61+W62+W63+W64+W65+W72 -> 55.781508
B84: Of which Outstanding debt | E84: ='Input data'!$C$66*E$83 -> 54.96332 | F84: =IF(F83=0,0,IF(F79=1,E83*F42/((1+F23/100)*(1+F41/100))-F85-F86,IF(AND(F79=0,F80=1),(1-E89-F38*E90)*E83*F42/((1+F23/100)*(1+F41/100)),F83))) -> 57.782728 | G84: =IF(G83=0,0,IF(G79=1,F83*G42/((1+G23/100)*(1+G41/100))-G85-G86,IF(AND(G79=0,G80=1),(1-F89-G38*F90)*F83*G42/((1+G23/100)*(1+G41/100)),G83))) -> 59.427396 | H84: =IF(H83=0,0,IF(H79=1,G83*H42/((1+H23/100)*(1+H41/100))-H85-H86,IF(AND(H79=0,H80=1),(1-G89-H38*G90)*G83*H42/((1+H23/100)*(1+H41/100)),H83))) -> 57.951691 | I84: =IF(I83=0,0,IF(I79=1,H83*I42/((1+I23/100)*(1+I41/100))-I85-I86,IF(AND(I79=0,I80=1),(1-H89-I38*H90)*H83*I42/((1+I23/100)*(1+I41/100)),I83))) -> 56.926949 | J84: =IF(J83=0,0,IF(J79=1,I83*J42/((1+J23/100)*(1+J41/100))-J85-J86,IF(AND(J79=0,J80=1),(1-I89-J38*I90)*I83*J42/((1+J23/100)*(1+J41/100)),J83))) -> 55.846119 | K84: =IF(K83=0,0,IF(K79=1,J83*K42/((1+K23/100)*(1+K41/100))-K85-K86,IF(AND(K79=0,K80=1),(1-J89-K38*J90)*J83*K42/((1+K23/100)*(1+K41/100)),K83))) -> 54.236103 | L84: =IF(L83=0,0,IF(L79=1,K83*L42/((1+L23/100)*(1+L41/100))-L85-L86,IF(AND(L79=0,L80=1),(1-K89-L38*K90)*K83*L42/((1+L23/100)*(1+L41/100)),L83))) -> 52.604811 | M84: =IF(M83=0,0,IF(M79=1,L83*M42/((1+M23/100)*(1+M41/100))-M85-M86,IF(AND(M79=0,M80=1),(1-L89-M38*L90)*L83*M42/((1+M23/100)*(1+M41/100)),M83))) -> 50.866919 | ... W84: =IF(W83=0,0,IF(W79=1,V83*W42/((1+W23/100)*(1+W41/100))-W85-W86,IF(AND(W79=0,W80=1),(1-V89-W38*V90)*V83*W42/((1+W23/100)*(1+W41/100)),W83))) -> 44.094474
B85: Rolled over long-term debt | E85: ='Input data'!$C$67*E$83 -> 2.9208599 | F85: =IF(F83=0,0,IF(F79=1,F38*E83*E90*F42/((1+F23/100)*(1+F41/100)),IF(AND(F79=0,F80=1),(F38*E83*E90*F42/((1+F23/100)*(1+F41/100)))*(1-ABS(F83-E83*F42/((1+F23/100)*(1+F41/100)))/((F38*E83*E90*F42/((1+F23/100)*(1+F41/100)))+(E89*E83*F42/((1+F23/100)*(1+F41/100))))),0))) -> 4.1782685 | G85: =IF(G83=0,0,IF(G79=1,G38*F83*F90*G42/((1+G23/100)*(1+G41/100)),IF(AND(G79=0,G80=1),(G38*F83*F90*G42/((1+G23/100)*(1+G41/100)))*(1-ABS(G83-F83*G42/((1+G23/100)*(1+G41/100)))/((G38*F83*F90*G42/((1+G23/100)*(1+G41/100)))+(F89*F83*G42/((1+G23/100)*(1+G41/100))))),0))) -> 4.3699962 | H85: =IF(H83=0,0,IF(H79=1,H38*G83*G90*H42/((1+H23/100)*(1+H41/100)),IF(AND(H79=0,H80=1),(H38*G83*G90*H42/((1+H23/100)*(1+H41/100)))*(1-ABS(H83-G83*H42/((1+H23/100)*(1+H41/100)))/((H38*G83*G90*H42/((1+H23/100)*(1+H41/100)))+(G89*G83*H42/((1+H23/100)*(1+H41/100))))),0))) -> 4.3326364 | I85: =IF(I83=0,0,IF(I79=1,I38*H83*H90*I42/((1+I23/100)*(1+I41/100)),IF(AND(I79=0,I80=1),(I38*H83*H90*I42/((1+I23/100)*(1+I41/100)))*(1-ABS(I83-H83*I42/((1+I23/100)*(1+I41/100)))/((I38*H83*H90*I42/((1+I23/100)*(1+I41/100)))+(H89*H83*I42/((1+I23/100)*(1+I41/100))))),0))) -> 4.3260819 | J85: =IF(J83=0,0,IF(J79=1,J38*I83*I90*J42/((1+J23/100)*(1+J41/100)),IF(AND(J79=0,J80=1),(J38*I83*I90*J42/((1+J23/100)*(1+J41/100)))*(1-ABS(J83-I83*J42/((1+J23/100)*(1+J41/100)))/((J38*I83*I90*J42/((1+J23/100)*(1+J41/100)))+(I89*I83*J42/((1+J23/100)*(1+J41/100))))),0))) -> 4.3128313 | K85: =IF(K83=0,0,IF(K79=1,K38*J83*J90*K42/((1+K23/100)*(1+K41/100)),IF(AND(K79=0,K80=1),(K38*J83*J90*K42/((1+K23/100)*(1+K41/100)))*(1-ABS(K83-J83*K42/((1+K23/100)*(1+K41/100)))/((K38*J83*J90*K42/((1+K23/100)*(1+K41/100)))+(J89*J83*K42/((1+K23/100)*(1+K41/100))))),0))) -> 4.2555478 | L85: =IF(L83=0,0,IF(L79=1,L38*K83*K90*L42/((1+L23/100)*(1+L41/100)),IF(AND(L79=0,L80=1),(L38*K83*K90*L42/((1+L23/100)*(1+L41/100)))*(1-ABS(L83-K83*L42/((1+L23/100)*(1+L41/100)))/((L38*K83*K90*L42/((1+L23/100)*(1+L41/100)))+(K89*K83*L42/((1+L23/100)*(1+L41/100))))),0))) -> 4.1927369 | M85: =IF(M83=0,0,IF(M79=1,M38*L83*L90*M42/((1+M23/100)*(1+M41/100)),IF(AND(M79=0,M80=1),(M38*L83*L90*M42/((1+M23/100)*(1+M41/100)))*(1-ABS(M83-L83*M42/((1+M23/100)*(1+M41/100)))/((M38*L83*L90*M42/((1+M23/100)*(1+M41/100)))+(L89*L83*M42/((1+M23/100)*(1+M41/100))))),0))) -> 4.1173999 | ... W85: =IF(W83=0,0,IF(W79=1,W38*V83*V90*W42/((1+W23/100)*(1+W41/100)),IF(AND(W79=0,W80=1),(W38*V83*V90*W42/((1+W23/100)*(1+W41/100)))*(1-ABS(W83-V83*W42/((1+W23/100)*(1+W41/100)))/((W38*V83*V90*W42/((1+W23/100)*(1+W41/100)))+(V89*V83*W42/((1+W23/100)*(1+W41/100))))),0))) -> 3.7342636
B86: Rolled over short-term debt | E86: ='Input data'!$C$68*E$83 -> 6.4315767 | F86: =IF(F83=0,0,IF(F79=1,(1-E90)*E83*F42/((1+F23/100)*(1+F41/100)),IF(AND(F79=0,F80=1),(E89*E83*F42/((1+F23/100)*(1+F41/100)))*(1-ABS(F83-E83*F42/((1+F23/100)*(1+F41/100)))/((F38*E83*E90*F42/((1+F23/100)*(1+F41/100)))+(E89*E83*F42/((1+F23/100)*(1+F41/100))))),0))) -> 6.8845562 | G86: =IF(G83=0,0,IF(G79=1,(1-F90)*F83*G42/((1+G23/100)*(1+G41/100)),IF(AND(G79=0,G80=1),(F89*F83*G42/((1+G23/100)*(1+G41/100)))*(1-ABS(G83-F83*G42/((1+G23/100)*(1+G41/100)))/((G38*F83*F90*G42/((1+G23/100)*(1+G41/100)))+(F89*F83*G42/((1+G23/100)*(1+G41/100))))),0))) -> 7.0046214 | H86: =IF(H83=0,0,IF(H79=1,(1-G90)*G83*H42/((1+H23/100)*(1+H41/100)),IF(AND(H79=0,H80=1),(G89*G83*H42/((1+H23/100)*(1+H41/100)))*(1-ABS(H83-G83*H42/((1+H23/100)*(1+H41/100)))/((H38*G83*G90*H42/((1+H23/100)*(1+H41/100)))+(G89*G83*H42/((1+H23/100)*(1+H41/100))))),0))) -> 6.7988959 | I86: =IF(I83=0,0,IF(I79=1,(1-H90)*H83*I42/((1+I23/100)*(1+I41/100)),IF(AND(I79=0,I80=1),(H89*H83*I42/((1+I23/100)*(1+I41/100)))*(1-ABS(I83-H83*I42/((1+I23/100)*(1+I41/100)))/((I38*H83*H90*I42/((1+I23/100)*(1+I41/100)))+(H89*H83*I42/((1+I23/100)*(1+I41/100))))),0))) -> 6.6544185 | J86: =IF(J83=0,0,IF(J79=1,(1-I90)*I83*J42/((1+J23/100)*(1+J41/100)),IF(AND(J79=0,J80=1),(I89*I83*J42/((1+J23/100)*(1+J41/100)))*(1-ABS(J83-I83*J42/((1+J23/100)*(1+J41/100)))/((J38*I83*I90*J42/((1+J23/100)*(1+J41/100)))+(I89*I83*J42/((1+J23/100)*(1+J41/100))))),0))) -> 6.5073284 | K86: =IF(K83=0,0,IF(K79=1,(1-J90)*J83*K42/((1+K23/100)*(1+K41/100)),IF(AND(K79=0,K80=1),(J89*J83*K42/((1+K23/100)*(1+K41/100)))*(1-ABS(K83-J83*K42/((1+K23/100)*(1+K41/100)))/((K38*J83*J90*K42/((1+K23/100)*(1+K41/100)))+(J89*J83*K42/((1+K23/100)*(1+K41/100))))),0))) -> 6.3062201 | L86: =IF(L83=0,0,IF(L79=1,(1-K90)*K83*L42/((1+L23/100)*(1+L41/100)),IF(AND(L79=0,L80=1),(K89*K83*L42/((1+L23/100)*(1+L41/100)))*(1-ABS(L83-K83*L42/((1+L23/100)*(1+L41/100)))/((L38*K83*K90*L42/((1+L23/100)*(1+L41/100)))+(K89*K83*L42/((1+L23/100)*(1+L41/100))))),0))) -> 6.1037346 | M86: =IF(M83=0,0,IF(M79=1,(1-L90)*L83*M42/((1+M23/100)*(1+M41/100)),IF(AND(M79=0,M80=1),(L89*L83*M42/((1+M23/100)*(1+M41/100)))*(1-ABS(M83-L83*M42/((1+M23/100)*(1+M41/100)))/((M38*L83*L90*M42/((1+M23/100)*(1+M41/100)))+(L89*L83*M42/((1+M23/100)*(1+M41/100))))),0))) -> 5.8920363 | ... W86: =IF(W83=0,0,IF(W79=1,(1-V90)*V83*W42/((1+W23/100)*(1+W41/100)),IF(AND(W79=0,W80=1),(V89*V83*W42/((1+W23/100)*(1+W41/100)))*(1-ABS(W83-V83*W42/((1+W23/100)*(1+W41/100)))/((W38*V83*V90*W42/((1+W23/100)*(1+W41/100)))+(V89*V83*W42/((1+W23/100)*(1+W41/100))))),0))) -> 4.9295185
