Workbook

Sheet Read me
G4: European Commission
G6: Directorate-General for Economic and Financial Affairs
G7: Unit C2 - Sustainability of public finances
G8: ECFIN-Secretariat-C2@ec.europa.eu
C16: FILE DESCRIPTION
C18: Data reported in this file are based on the European Commission (EC) 2024 spring forecast (SF 2024) and macroeconomic and budgetary projections from the joint EC-EPC Ageing Report 2024 (AR 2024).
C22: This file contains a simplified version of the EC model used to calculate the general governement debt ratio dynamics for EU countries under different scenarios. A detailed description of the EC's general governement debt projections can be found in the "Debt Sustainability Monitor 2023" (DSM, March 2024).
C27: HOW TO USE THIS TOOL TO CALCULATE NEW DEBT PROJECTIONS
C29: This tool can be used to calculate debt projections under different macroeconomic and structural primary balance adjustment assumptions. Debt projections for each scenario will update automatically with changes in the macroeconomic assumptions or the adjustment parameters. The fulfilment of DSA-based criteria, the safeguards and the benchmark will be automatically calculated in the sheet "Criteria results". Formulas are fully visible. To assess the impact of alternative fiscal paths or to check the robustness of underlying macroeconomic assumptions, the user can modify the content of key cells in the sheets "Criteria results" and "Input data" (see below). Note that, for a proper functioning of the file, you should make sure that Excel is in "Automatic" computation mode, i.e. in the File menu, Option tab, click on "Formulas", "Calculation Options" and "Automatic".
C31: The spreadsheet is composed of the following elements:
D33: The grey sheet "Criteria results" contains two main types of cells identified by different colours:
F34: Cells with a yellow background and a red frame can be modified to see the impact of a different duration or pace of adjustment.
F35: Cells with a white or pale red (in case the deficit resilience safeguard is binding) background provide results obtained with the adjustment chosen in the yellow cells. To replicate the Commission's calculations, the underlying formulas should not be modified.
D38: "Criteria results" contains five tables. Table 1 "Adjustment input data": the user can set the duration of the plan in cell F5 (4 years without extension or 7 years with extension), the yearly adjustment pace under the scenario that does not take into account the deficit resilience safeguard (F7) and for the scenario that automatically applies that safeguard (F6). Note that the country cell (F4) cannot be changed.
D39: The adjustement in F7 needs to be selected first so that the message on line 13 signals that the two DSA-based criteria are fulfilled. As a second step, the adjustment in F6 can be selected (and cannot be lower than in F7) so that line 12 reports compliance with the requirements.
D40: Table 2 "DSA-based criteria and deficit resilience safeguard" reports whether the chosen adjustment fulfils the DSA-based criteria (cells H12:I13) and whether the deficit resillience safeguard is binding.
D41: Table 3 "Main fiscal variables with automatic deficit resilience safeguard" reports the annual adjustment over the adjustment period, in terms of change in SPB (line 18), level of the structural balance (line 19) and SPB level at the end of the adjustment (line 20). This table reports the results for the scenario that automatically applies the deficit resillience safeguard. For this reason, the SB is highlighted in red if it is lower than -1.5% of GDP.
D42: Table 4 "Main fiscal variables without automatic deficit resilience safeguard" reports the annual adjustment over the adjustment period, in terms of change in SPB (line 25), level of the structural balance (line 26) and SPB level at the end of the adjustment (line 27). This table reports the results for the scenario without the deficit resillience safeguard.
D44: The sheet "Input data" in light blue presents the input data, including fiscal and GDP growth assumptions as well as additional fiscal parameters. Unless stated otherwise below, the user can change all values in this tab.
D45: Coloured cells indicate data sources as follows (this colour-coding holds in the other spreadsheets):
F46: Cells in light grey indicate Commission forecast (available in the AMECO database)
F47: Cells in light blue indicate values from the Ageing Report 2024
F48: Cells in light orange provide parameters needed to compute the decomposition of government debt according to its maturity structure (i.e. short-term and long-term debt, maturing, rolled-over and non-maturing debt). These are fixed shares which the user cannot change.
F49: Cells in dark orange indicate financial market prices.
D50: Non coloured parameters in cells C50:C70 were calibrated based on different data sources. Data sources are given in corresponding cells of column E.
C52: The next spreadsheets present the no-fiscal-policy-change baseline and the adjustment scenario, with and without the impact of the deficit resilience safeguard. Each deterministic projection provides a single path for debt until 2038 or 2041 under certain assumptions for budgetary, macroeconomic and financial variables.
D54: The sheet in blue provides, as a reference, the baseline no-fiscal-policy-change scenario. The background colour coding is the same as in the sheet "Input data".
D56: The sheet in orange presents the scenario that automatically corrects the yearly adjustment path to account for the deficit resillience safeguard.
D58: The sheet in green presents the adjustment scenarios without the deficit resilience safeguard. This scenario is computed automatically based on the yearly adjustment path set in "Criteria results" (see above).
C60: Within the orange sheet and each green sheet, the background of the SPB line has three colours. Each colour corresponds to a specific period of the projections:
E61: Light grey indicates the pre-plan period, corresponding to the EC forecast
E62: Mild grey indicates the period during which the SPB adjusts according to the path set in sheet "Criteria results"
E63: Dark grey indicates the period in which the SPB, net of changes in cost of ageing, remains constant at its value of end of adjustment.
C66: WHERE ARE THE MAIN RESULTS LOCATED?
C67: The fullfilment of the criteria is checked in the sheet "Criteria results". Debt projections can be found in line 57 of each scenario.
D69: The 'FASTOP reporting' sheet in violet provides help for preparing reporting tables. It readily provides all the tables foreseen by the guidance notice on the "Information Requirements for the Medium-Term Fiscal-Structural Plans" once the parameters are set in the rest of this file. This sheet is meant to be an assistance. The need for a thorough scrutiny of the figures before submitting such tables remains.

Sheet Criteria results
U2: 4 | V2: -1.5
D3: Table 1 - Adjustment input data | U3: 7 | V3: -1.48
D4: Country | F4: IE | V4: -1.46
D5: Number of years of adjustment | F5: 4 | V5: -1.44
C6: 2. | D6: Annual adjustment (with safeguard) | F6: 0 | V6: -1.42
C7: 1. | D7: Annual adjustment (without safeguard) | F7: 0 | V7: -1.4
V8: -1.38
H9: Table 2 - DSA-based criteria and deficit resilience safeguard | V9: -1.36
H10: DSA-based criteria | J10: Deficit resilience safeguard | V10: -1.34
H11: Deficit below 3% of GDP | I11: ="Debt below 60% of GDP in T+"&10+F5 -> Debt below 60% of GDP in T+14 | V11: -1.32
C12: 2. | D12: Adjustment scenario with automatic deficit resilience safeguard * (sheet "Adjustment scenario") | H12: =IF(MIN(OFFSET('Adjustment scenario'!$F$77,0,$F$5,1,11))>-3.05,"ok","Not met") -> ok | I12: =IF(OFFSET('Adjustment scenario'!$F$57,0,$F$5+10,1,1)<60,"ok","Not met") -> ok | J12: =IF(AND($F$5=4,COUNTIF(G18:J18,">" & F6)=0),"Not binding",IF(AND($F$5=7,COUNTIF(G18:M18,">" & F6)=0),"Not binding","Binding")) -> Not binding | K12: =IF(OR($H$13="Not met",$I$13="Not met"),"Please adjust cell F7 so that both DSA-based criteria are met", IF($F$6<$F$7,"The adjustment in F6 cannot be lower than in F7", IF(AND($H$12="ok",$I$12="ok",$H$13="ok",$I$13="ok",$F$6>=$F$7, OR(AND($F$5=4,$G$18>=$H$18,$H$18>=$I$18,$I$18>=$J$18,OR($J$18>=0.4,$J$19>-1.55)), AND($F$5=7,$G$18>=$H$18,$H$18>=$I$18,$I$18>=$J$18,$J$18>=$K$18,$K$18>=$L$18,$L$18>=$M$18,OR($M$18>=0.25,$M$19>-1.55)))), "OK"&CHAR(10)&"The adjustment in F6 fulfills all requirements including the deficit resilience safeguard", "NOT OK"&CHAR(10)&"The adjustment in F6 does not fulfill all requirements"))) -> OK The adjustment in F6 fulfills all requirements including the deficit resilience safeguard | V12: -1.3
C13: 1. | D13: Adjustment scenario without deficit resilience safeguard (sheet "Adjust. no safeguard") | H13: =IF(MIN(OFFSET('Adjust. no safeguard'!$F$77,0,$F$5,1,11))>-3.05,"ok","Not met") -> ok | I13: =IF(OFFSET('Adjust. no safeguard'!$F$57,0,$F$5+10,1,1)<60,"ok","Not met") -> ok | K13: =IF(AND($H$13="ok",$I$13="ok"), "OK"&CHAR(10)&"The adjustment in F7 ensures that the debt and deficit remain"&CHAR(10)&"below the Treaty reference values over the medium term", "NOT OK"&CHAR(10)&"The adjustment in F7 does not ensure that the debt and deficit remain"&CHAR(10)&"below the Treaty reference values over the medium term") -> OK The adjustment in F7 ensures that the debt and deficit remain below the Treaty reference values over the medium term | V13: -1.28
D14: * Under a plan without (with) extension, an adjustment of 0.40 pp. (0.25 pp.) of GDP in SPB terms is applied if the structural deficit in the previous year exceeds 1.5% of GDP. | V14: -1.26
V15: -1.24
G16: Table 3 - Main fiscal variables with automatic deficit resilience safeguard * | V16: -1.22
G17: 2025 | H17: 2026 | I17: 2027 | J17: 2028 | K17: 2029 | L17: 2030 | M17: 2031 | V17: -1.2
D18: Annual adjustment (change in SPB) | G18: ='Adjustment scenario'!G12-'Adjustment scenario'!F12 -> 0 | H18: ='Adjustment scenario'!H12-'Adjustment scenario'!G12 -> 0 | I18: ='Adjustment scenario'!I12-'Adjustment scenario'!H12 -> 0 | J18: ='Adjustment scenario'!J12-'Adjustment scenario'!I12 -> 0 | K18: ='Adjustment scenario'!K12-'Adjustment scenario'!J12 -> 0 | L18: ='Adjustment scenario'!L12-'Adjustment scenario'!K12 -> 0 | M18: ='Adjustment scenario'!M12-'Adjustment scenario'!L12 -> 0 | V18: -1.18
D19: Structural balance | G19: ='Adjustment scenario'!G78 -> 1.8496221 | H19: ='Adjustment scenario'!H78 -> 1.829394 | I19: ='Adjustment scenario'!I78 -> 1.8755965 | J19: ='Adjustment scenario'!J78 -> 1.9330204 | K19: ='Adjustment scenario'!K78 -> 1.9066295 | L19: ='Adjustment scenario'!L78 -> 1.8555801 | M19: ='Adjustment scenario'!M78 -> 1.7898307 | V19: -1.16
D20: SPB at the end of the adjustment | J20: =IF(F5=4,'Adjustment scenario'!J12,"") -> 2.528801 | M20: =IF(F5=7,'Adjustment scenario'!M12,"") | V20: -1.14
D21: * The structural balance is flagged in red if it is below -1.5% of GDP. | V21: -1.12
V22: -1.1
G23: Table 4 - Main fiscal variables without automatic deficit resilience safeguard | V23: -1.08
G24: 2025 | H24: 2026 | I24: 2027 | J24: 2028 | K24: 2029 | L24: 2030 | M24: 2031 | V24: -1.06
D25: Annual adjustment (change in SPB) | G25: ='Adjust. no safeguard'!G12-'Adjust. no safeguard'!F12 -> 0 | H25: ='Adjust. no safeguard'!H12-'Adjust. no safeguard'!G12 -> 0 | I25: ='Adjust. no safeguard'!I12-'Adjust. no safeguard'!H12 -> 0 | J25: ='Adjust. no safeguard'!J12-'Adjust. no safeguard'!I12 -> 0 | K25: ='Adjust. no safeguard'!K12-'Adjust. no safeguard'!J12 -> 0 | L25: ='Adjust. no safeguard'!L12-'Adjust. no safeguard'!K12 -> 0 | M25: ='Adjust. no safeguard'!M12-'Adjust. no safeguard'!L12 -> 0 | V25: -1.04
D26: Structural balance | G26: ='Adjust. no safeguard'!G78 -> 1.8496221 | H26: ='Adjust. no safeguard'!H78 -> 1.829394 | I26: ='Adjust. no safeguard'!I78 -> 1.8755965 | J26: ='Adjust. no safeguard'!J78 -> 1.9330204 | K26: ='Adjust. no safeguard'!K78 -> 1.9066295 | L26: ='Adjust. no safeguard'!L78 -> 1.8555801 | M26: ='Adjust. no safeguard'!M78 -> 1.7898307 | V26: -1.02
D27: SPB at the end of the adjustment | J27: =IF(F5=4,'Adjust. no safeguard'!J12,"") -> 2.528801 | M27: =IF(F5=7,'Adjust. no safeguard'!M12,"") | V27: -1
V28: -0.98
V29: -0.96
V30: -0.82
V31: -0.8
V32: -0.78
V33: -0.76
V34: -0.74
V35: -0.72
V36: -0.7
V37: -0.68
V38: -0.66
V39: -0.64
... V146: 1.5

Sheet Input data
B3: Country | C3: IE
B5: Last year before the adjustment | C5: 2024
B6: Last year of adjustment | C6: =C5+'Criteria results'!$F$5 -> 2028
B8: Key assumptions
C9: 2021 | D9: 2022 | E9: 2023 | F9: 2024 | G9: 2025 | H9: 2026 | I9: 2027 | J9: 2028 | K9: 2029 | L9: 2030 | M9: 2031 | N9: 2032 | O9: 2033 | P9: 2034 | Q9: 2035 | R9: 2036 | S9: 2037 | T9: 2038 | U9: 2039 | V9: 2040 | W9: 2041
B10: Fiscal assumptions (% of GDP)
B11: Key fiscal variables (based on the Commission 2024 spring forecast ("SF 2024") T+2 forecast and the June 2024 report prepared under Art. 126(3) of the Treaty)
B12: Debt | C12: 54.39847 | D12: 44.39178 | E12: 43.73044 | F12: 42.48884
B13: Structural primary balance ('+' means 'surplus') | C13: -3.165318 | D13: -2.376722 | E13: 1.712465 | F13: 2.528801
B14: One-off and other temporary measures | C14: 0 | D14: 0 | E14: 0 | F14: 0 | G14: 0 | H14: 0 | I14: 0 | J14: 0 | K14: 0 | L14: 0 | M14: 0 | N14: 0 | O14: 0 | P14: 0 | Q14: 0 | R14: 0 | S14: 0 | T14: 0 | U14: 0 | V14: 0 | W14: 0
B15: Stock-flow adjustments (without exchange rate effect) | C15: 2.690274 | D15: -0.5420614 | E15: 0.8428086 | F15: 1.636568 | G15: 2.20024 | H15: 0 | I15: 0 | J15: 0 | K15: 0 | L15: 0 | M15: 0 | N15: 0 | O15: 0 | P15: 0 | Q15: 0 | R15: 0 | S15: 0 | T15: 0 | U15: 0 | V15: 0 | W15: 0
B16: Stock-flow adjustment (total) | C16: 2.690275 | D16: -0.5420594 | E16: 0.8428066 | F16: 1.636567 | G16: 2.200242 | H16: 0 | I16: 0 | J16: 0 | K16: 0 | L16: 0 | M16: 0 | N16: 0 | O16: 0 | P16: 0 | Q16: 0 | R16: 0 | S16: 0 | T16: 0 | U16: 0 | V16: 0 | W16: 0
B17: Subject to an excessive deficit procedure (EDP) (0-no/1-yes) | D17: 0 | E17: 0 | F17: 0
B19: Cost of ageing and selected public revenue (based on the Commission-Council 2024 Ageing Report ("AR 2024"))
B20: Total ageing cost (net of taxes on pensions) | C20: =(C21+C22+C23+C24-C25) -> 0 | D20: =(D21+D22+D23+D24-D25) -> 11.98063 | E20: =(E21+E22+E23+E24-E25) -> 11.58823 | F20: =(F21+F22+F23+F24-F25) -> 11.59789 | G20: =(G21+G22+G23+G24-G25) -> 11.65158 | H20: =(H21+H22+H23+H24-H25) -> 11.82718 | I20: =(I21+I22+I23+I24-I25) -> 12.01015 | J20: =(J21+J22+J23+J24-J25) -> 12.14108 | ... W20: =(W21+W22+W23+W24-W25) -> 13.69105
B21: of which: Public pensions expenditure | C21: 0 | D21: 3.82109 | E21: 3.61005 | F21: 3.62188 | G21: 3.65895 | H21: 3.80091 | I21: 3.9251 | J21: 4.01587 | K21: 4.06986 | L21: 4.15079 | M21: 4.25426 | N21: 4.41679 | O21: 4.47248 | P21: 4.57121 | Q21: 4.65947 | R21: 4.75886 | S21: 4.87392 | T21: 4.8967 | U21: 4.96666 | V21: 5.04151 | W21: 5.12081
B22: Health care expenditure | C22: 0 | D22: 4.11039 | E22: 4.00607 | F22: 4.05388 | G22: 4.10122 | H22: 4.14568 | I22: 4.18979 | J22: 4.23735 | K22: 4.283 | L22: 4.32876 | M22: 4.37176 | N22: 4.41288 | O22: 4.45283 | P22: 4.49271 | Q22: 4.53085 | R22: 4.56982 | S22: 4.60593 | T22: 4.64352 | U22: 4.6797 | V22: 4.71437 | W22: 4.74969
B23: Long-term care expenditure | C23: 0 | D23: 1.22676 | E23: 1.22151 | F23: 1.23167 | G23: 1.24944 | H23: 1.2728 | I23: 1.31549 | J23: 1.33901 | K23: 1.36255 | L23: 1.38546 | M23: 1.40747 | N23: 1.42945 | O23: 1.4528 | P23: 1.47653 | Q23: 1.50085 | R23: 1.52518 | S23: 1.54983 | T23: 1.57526 | U23: 1.60292 | V23: 1.63104 | W23: 1.65937
B24: Education & unemployment benefits expenditure | C24: 0 | D24: 2.82239 | E24: 2.7506 | F24: 2.69046 | G24: 2.64197 | H24: 2.60779 | I24: 2.57977 | J24: 2.54885 | K24: 2.51158 | L24: 2.47032 | M24: 2.4263 | N24: 2.3837 | O24: 2.34295 | P24: 2.30581 | Q24: 2.27257 | R24: 2.24263 | S24: 2.21659 | T24: 2.19551 | U24: 2.17909 | V24: 2.16772 | W24: 2.16118
B25: Taxes on pensions | C25: 0 | D25: 0 | E25: 0 | F25: 0 | G25: 0 | H25: 0 | I25: 0 | J25: 0 | K25: 0 | L25: 0 | M25: 0 | N25: 0 | O25: 0 | P25: 0 | Q25: 0 | R25: 0 | S25: 0 | T25: 0 | U25: 0 | V25: 0 | W25: 0
B26: Property income | C26: 0.1107195 | D26: 0.132752 | E26: 0.1349502 | F26: 0.1371484 | G26: 0.1393466 | H26: 0.1415448 | I26: 0.143743 | J26: 0.1459412 | K26: 0.1481394 | L26: 0.1503376 | M26: 0.1525358 | N26: 0.154734 | O26: 0.1569322 | P26: 0.1591305 | Q26: 0.1613287 | R26: 0.1635269 | S26: 0.1657251 | T26: 0.1679233 | U26: 0.1701215 | V26: 0.1723197 | W26: 0.1745179
B28: Real GDP growth assumptions (based on SF 2024 T+10 projections and AR 2024 projections)
B29: Actual GDP
B30: Growth rate | C30: 15.12522 | D30: 9.433022 | E30: -3.198788 | F30: 1.243702 | G30: 3.393806 | H30: 3.746114 | I30: 3.802369 | J30: 3.577386 | K30: 3.164204 | L30: 2.938014 | M30: 2.669411 | N30: 2.359786 | O30: 2.013409 | P30: 1.950457 | Q30: 1.887507 | R30: 1.824547 | S30: 1.823224 | T30: 1.784506 | U30: 1.734372 | V30: 1.668214 | W30: 1.571112
B31: Level (billions, national currency) | C31: 410.9464
B32: Potential GDP
B33: Growth rate | C33: 4.349017 | D33: 4.958035 | E33: 4.333524 | F33: 3.615591 | G33: 3.285812 | H33: 3.394844 | I33: 3.335869 | J33: 3.345161 | K33: 3.164205 | L33: 2.938014 | M33: 2.669409 | N33: 2.359784 | O33: 2.01341 | P33: 1.950456 | Q33: 1.887503 | R33: 1.824549 | S33: 1.823226 | T33: 1.784504 | U33: 1.734368 | V33: 1.668211 | W33: 1.571108
B34: Level (billions, national currency) | C34: 392.8036
B36: Interest rates (SF 2024, %)
B37: Nominal implicit interest rate on debt | C37: 1.510173 | D37: 1.408838 | E37: 1.550894 | F37: 1.641526 | G37: 1.684386
B38: Short-term nominal interest rate | D38: 0.35 | E38: 3.43 | F38: 3.564208 | G38: 2.816375
B39: Long-term nominal interest rate | D39: 1.75 | E39: 2.87 | F39: 2.837221 | G39: 2.903685
F40: Bloomberg data, country-specific forward market rates.
B41: Inflation (SF 2024, %)
B42: GDP deflator (national currency) | C42: 0.4774826 | D42: 6.582269 | E42: 2.965217 | F42: 2.574346 | G42: 1.914897
B44: Net primary expenditure growth (SF 2024, %)
B45: Net primary expenditure growth | C45: 6.1387469 | D45: 14.052581 | E45: 13.567155 | F45: 7.3776443
B47: Additional parameters
E48: Sources
B49: Fiscal multiplier | C49: 0.75 | E49: Carnot, N. and de Castro, F. (2015), “The Discretionary Fiscal Effort: an Assessment of Fiscal Policy and its Output Effect”, European Economy, Economic Papers, No. 543.
B50: Budget balance semi-elasticity | C50: 0.522 | E50: Mourre, G. et al. (2019), "The Semi-Elasticities Underlying the Cyclically-Adjusted Budget Balance: An Update and Further Analysis", European Economy, Discussion Paper, No. 098.
B52: Long-term nominal interest rate (T+10 convergence value) | C52: 3.66406 | E52: Bloomberg data, country-specific forward market rates.
B53: Short-term nominal interest rate (T+10 convergence value) | C53: 2.72609 | E53: Bloomberg data, country-specific forward market rates.
B54: Long-term nominal interest rate (T+30 convergence value) | C54: 4 | E54: DSM 2023
B55: Short-term nominal interest rate (T+30 convergence value) | C55: 2 | E55: DSM 2023
B57: Share of short-term debt in total government debt | C57: 0.119508 | E57: Eurostat, average shares over the 3 last available years.
B58: Share of long-term debt in total government debt | C58: =1-C57 -> 0.880492 | E58: Eurostat, average shares over the 3 last available years.
B59: Share of long-term debt that matures every year (T+10 convergence value) | C59: 0.10431984 | E59: ECB, country-specific historical average shares over the 6 last available years. For post-programme countries (CY, El , IE and PT), the redemption profile of official loans has been taken into account for the computation of the share of long-term debt that matures every year. For these countries, changing this parameter would not affect debt projections.
B61: GDP deflator (national currency) (T+10 convergence value) | C61: 2.55 | E61: Bloomberg data, inflation swaps.
B62: GDP deflator (national currency) (T+30 convergence value) | C62: 2 | E62: Central bank inflation target
B64: Share of primary expenditure in GDP in 2024 | C64: 22.752842 | E64: SF24
B66: Share of outstanding debt in total debt in 2022 | C66: 0.84286956 | E66: Derived from the model and made consistent with the short-term forecast.
B67: Share of rolled-over long-term debt in 2022 | C67: 0.05196399 | E67: Derived from the model and made consistent with the short-term forecast.
B68: Share of rolled-over short-term debt in 2022 | C68: 0.10516634 | E68: Derived from the model and made consistent with the short-term forecast.
B69: Share of new long-term debt in 2022 | C69: 0 | E69: Derived from the model and made consistent with the short-term forecast.
B70: Share of new short-term debt in 2022 | C70: 0 | E70: Derived from the model and made consistent with the short-term forecast.

Sheet Baseline NFPC
B3: Country | C3: ='Input data'!C3 -> IE
B4: Key years
B5: ='Input data'!B5 -> Last year before the adjustment | C5: =+'Input data'!C5 -> 2024
B6: Last year of adjustment | C6: =+C5+'Criteria results'!$F$5 -> 2028
B9: Key assumptions
C10: 2021 | D10: 2022 | E10: 2023 | F10: 2024 | G10: 2025 | H10: 2026 | I10: 2027 | J10: 2028 | K10: 2029 | L10: 2030 | M10: 2031 | N10: 2032 | O10: 2033 | P10: 2034 | Q10: 2035 | R10: 2036 | S10: 2037 | T10: 2038 | U10: 2039 | V10: 2040 | W10: 2041
B11: Fiscal assumptions (% of GDP)
B12: Structural primary balance ('+' means 'surplus') | C12: ='Input data'!C13 -> -3.165318 | D12: ='Input data'!D13 -> -2.376722 | E12: ='Input data'!E13 -> 1.712465 | F12: ='Input data'!F13 -> 2.528801 | G12: =F12 -> 2.528801 | H12: =G12 -> 2.528801 | I12: =H12 -> 2.528801 | J12: =I12 -> 2.528801 | K12: =J12 -> 2.528801 | L12: =K12 -> 2.528801 | M12: =L12 -> 2.528801 | N12: =M12 -> 2.528801 | ... W12: =V12 -> 2.528801
B13: One-off and other temporary measures | C13: ='Input data'!C14 -> 0 | D13: ='Input data'!D14 -> 0 | E13: ='Input data'!E14 -> 0 | F13: ='Input data'!F14 -> 0 | G13: ='Input data'!G14 -> 0 | H13: 0 | I13: 0 | J13: 0 | K13: 0 | L13: 0 | M13: 0 | N13: 0 | O13: 0 | P13: 0 | Q13: 0 | R13: 0 | S13: 0 | T13: 0 | U13: 0 | V13: 0 | W13: 0
B14: Stock flow adjustments (without exchange rate effect) | C14: ='Input data'!C15 -> 2.690274 | D14: ='Input data'!D15 -> -0.5420614 | E14: ='Input data'!E15 -> 0.8428086 | F14: ='Input data'!F15 -> 1.636568 | G14: ='Input data'!G15 -> 2.20024 | H14: ='Input data'!H15 -> 0 | I14: ='Input data'!I15 -> 0 | J14: ='Input data'!J15 -> 0 | ... W14: ='Input data'!W15 -> 0
B16: ='Input data'!B19 -> Cost of ageing and selected public revenue (based on the Commission-Council 2024 Ageing Report ("AR 2024"))
B17: Total ageing cost (net of taxes on pensions) | C17: ='Input data'!C20 -> 0 | D17: ='Input data'!D20 -> 11.98063 | E17: ='Input data'!E20 -> 11.58823 | F17: ='Input data'!F20 -> 11.59789 | G17: ='Input data'!G20 -> 11.65158 | H17: ='Input data'!H20 -> 11.82718 | I17: ='Input data'!I20 -> 12.01015 | J17: ='Input data'!J20 -> 12.14108 | ... W17: ='Input data'!W20 -> 13.69105
B18: ='Input data'!B26 -> Property income | C18: ='Input data'!C26 -> 0.1107195 | D18: ='Input data'!D26 -> 0.132752 | E18: ='Input data'!E26 -> 0.1349502 | F18: ='Input data'!F26 -> 0.1371484 | G18: ='Input data'!G26 -> 0.1393466 | H18: ='Input data'!H26 -> 0.1415448 | I18: ='Input data'!I26 -> 0.143743 | ... W18: ='Input data'!W26 -> 0.1745179
B20: GDP growth assumptions
B21: Actual GDP (real)
B22: Level | C22: ='Input data'!C31 -> 410.9464 | D22: =C22*(D23/100+1) -> 449.71106 | E22: =D22*(E23/100+1) -> 435.32576 | F22: =E22*(F23/100+1) -> 440.73992 | G22: =F22*(G23/100+1) -> 455.69777 | H22: =IF(AND(H49>1,G49>1),IF(AND(H49>0,G49>0),H26*(H50/100+1),0)+IF(H49>0,G22*(1+H51/100),0)-G22*(1+'Input data'!H30/100),IF(H49=1,H26,G22*(1+H51/100))) -> 472.76873 | I22: =IF(AND(I49>1,H49>1),IF(AND(I49>0,H49>0),I26*(I50/100+1),0)+IF(I49>0,H22*(1+I51/100),0)-H22*(1+'Input data'!I30/100),IF(I49=1,I26,H22*(1+I51/100))) -> 490.74514 | J22: =IF(AND(J49>1,I49>1),IF(AND(J49>0,I49>0),J26*(J50/100+1),0)+IF(J49>0,I22*(1+J51/100),0)-I22*(1+'Input data'!J30/100),IF(J49=1,J26,I22*(1+J51/100))) -> 508.30099 | K22: =IF(AND(K49>1,J49>1),IF(AND(K49>0,J49>0),K26*(K50/100+1),0)+IF(K49>0,J22*(1+K51/100),0)-J22*(1+'Input data'!K30/100),IF(K49=1,K26,J22*(1+K51/100))) -> 524.38467 | L22: =IF(AND(L49>1,K49>1),IF(AND(L49>0,K49>0),L26*(L50/100+1),0)+IF(L49>0,K22*(1+L51/100),0)-K22*(1+'Input data'!L30/100),IF(L49=1,L26,K22*(1+L51/100))) -> 539.79117 | M22: =IF(AND(M49>1,L49>1),IF(AND(M49>0,L49>0),M26*(M50/100+1),0)+IF(M49>0,L22*(1+M51/100),0)-L22*(1+'Input data'!M30/100),IF(M49=1,M26,L22*(1+M51/100))) -> 554.20041 | N22: =IF(AND(N49>1,M49>1),IF(AND(N49>0,M49>0),N26*(N50/100+1),0)+IF(N49>0,M22*(1+N51/100),0)-M22*(1+'Input data'!N30/100),IF(N49=1,N26,M22*(1+N51/100))) -> 567.27836 | O22: =IF(AND(O49>1,N49>1),IF(AND(O49>0,N49>0),O26*(O50/100+1),0)+IF(O49>0,N22*(1+O51/100),0)-N22*(1+'Input data'!O30/100),IF(O49=1,O26,N22*(1+O51/100))) -> 578.69999 | ... W22: =IF(AND(W49>1,V49>1),IF(AND(W49>0,V49>0),W26*(W50/100+1),0)+IF(W49>0,V22*(1+W51/100),0)-V22*(1+'Input data'!W30/100),IF(W49=1,W26,V22*(1+W51/100))) -> 666.4502
B23: Growth rate | C23: =+'Input data'!C30 -> 15.12522 | D23: =+'Input data'!D30 -> 9.433022 | E23: =+'Input data'!E30 -> -3.198788 | F23: =+'Input data'!F30 -> 1.243702 | G23: =+'Input data'!G30 -> 3.393806 | H23: =100*(H22/G22-1) -> 3.746114 | I23: =100*(I22/H22-1) -> 3.802369 | J23: =100*(J22/I22-1) -> 3.577386 | K23: =100*(K22/J22-1) -> 3.164204 | L23: =100*(L22/K22-1) -> 2.938014 | M23: =100*(M22/L22-1) -> 2.669411 | N23: =100*(N22/M22-1) -> 2.359786 | O23: =100*(O22/N22-1) -> 2.013409 | ... W23: =100*(W22/V22-1) -> 1.571112
B25: Potential GDP (real)
B26: Level | C26: ='Input data'!C34 -> 392.8036 | D26: =+C26*(1+'Input data'!D33/100) -> 412.27894 | E26: =+D26*(1+'Input data'!E33/100) -> 430.14515 | F26: =+E26*(1+'Input data'!F33/100) -> 445.69744 | G26: =+F26*(1+'Input data'!G33/100) -> 460.34222 | H26: =+G26*(1+'Input data'!H33/100) -> 475.97012 | I26: =+H26*(1+'Input data'!I33/100) -> 491.84786 | J26: =+I26*(1+'Input data'!J33/100) -> 508.30096 | K26: =+J26*(1+'Input data'!K33/100) -> 524.38464 | ... W26: =+V26*(1+'Input data'!W33/100) -> 666.45005
B28: Output gap
B29: Output gap | C29: =100*(C22/C26-1) -> 4.6187968 | D29: =100*(D22/D26-1) -> 9.07932 | E29: =100*(E22/E26-1) -> 1.2043874 | F29: =100*(F22/F26-1) -> -1.1123062 | G29: =100*(G22/G26-1) -> -1.0089108 | H29: =100*(H22/H26-1) -> -0.67260192 | I29: =100*(I22/I26-1) -> -0.22419779 | J29: =100*(J22/J26-1) -> 6.5725915e-06 | ... W29: =100*(W22/W26-1) -> 2.2288956e-05
B31: Actual GDP (nominal, national currency)
B32: Growth rate | C32: =100*((1+C23/100)*(1+C41/100)-1) -> 15.674923 | D32: =100*((1+D23/100)*(1+D41/100)-1) -> 16.636198 | E32: =100*((1+E23/100)*(1+E41/100)-1) -> -0.32842201 | F32: =100*((1+F23/100)*(1+F41/100)-1) -> 3.8500652 | G32: =100*((1+G23/100)*(1+G41/100)-1) -> 5.3736909 | H32: =100*((1+H23/100)*(1+H41/100)-1) -> 5.8151071 | I32: =100*((1+I23/100)*(1+I41/100)-1) -> 5.9548904 | J32: =100*((1+J23/100)*(1+J41/100)-1) -> 5.8074699 | ... W32: =100*((1+W23/100)*(1+W41/100)-1) -> 3.9377189
B34: Interest rate
B35: Nominal implicit interest rate on debt | C35: ='Input data'!C37 -> 1.510173 | D35: ='Input data'!D37 -> 1.408838 | E35: ='Input data'!E37 -> 1.550894 | F35: ='Input data'!F37 -> 1.641526 | G35: ='Input data'!G37 -> 1.684386 | H35: =H96 -> 1.7995764 | I35: =I96 -> 1.8573201 | J35: =J96 -> 1.8994082 | K35: =K96 -> 1.9496329 | L35: =L96 -> 2.0061124 | M35: =M96 -> 2.0541018 | N35: =N96 -> 2.1281077 | O35: =O96 -> 2.2116501 | ... W35: =W96 -> 2.6116148
B36: Long-term interest rate | E36: ='Input data'!E39 -> 2.87 | F36: ='Input data'!F39 -> 2.837221 | G36: ='Input data'!G39 -> 2.903685 | H36: =G36+($O$36-$G$36)/($O$10-$G$10) -> 2.9987319 | I36: =H36+($O$36-$G$36)/($O$10-$G$10) -> 3.0937787 | J36: =I36+($O$36-$G$36)/($O$10-$G$10) -> 3.1888256 | K36: =J36+($O$36-$G$36)/($O$10-$G$10) -> 3.2838725 | L36: =K36+($O$36-$G$36)/($O$10-$G$10) -> 3.3789194 | M36: =L36+($O$36-$G$36)/($O$10-$G$10) -> 3.4739662 | N36: =M36+($O$36-$G$36)/($O$10-$G$10) -> 3.5690131 | O36: ='Input data'!$C$52 -> 3.66406 | P36: =$O$36+('Input data'!$C$54-'Input data'!$C$52)/20*('Baseline NFPC'!P$10-2033) -> 3.680857 | Q36: =$O$36+('Input data'!$C$54-'Input data'!$C$52)/20*('Baseline NFPC'!Q$10-2033) -> 3.697654 | R36: =$O$36+('Input data'!$C$54-'Input data'!$C$52)/20*('Baseline NFPC'!R$10-2033) -> 3.714451 | S36: =$O$36+('Input data'!$C$54-'Input data'!$C$52)/20*('Baseline NFPC'!S$10-2033) -> 3.731248 | T36: =$O$36+('Input data'!$C$54-'Input data'!$C$52)/20*('Baseline NFPC'!T$10-2033) -> 3.748045 | U36: =$O$36+('Input data'!$C$54-'Input data'!$C$52)/20*('Baseline NFPC'!U$10-2033) -> 3.764842 | V36: =$O$36+('Input data'!$C$54-'Input data'!$C$52)/20*('Baseline NFPC'!V$10-2033) -> 3.781639 | W36: =$O$36+('Input data'!$C$54-'Input data'!$C$52)/20*('Baseline NFPC'!W$10-2033) -> 3.798436
B37: Short-term interest rate | E37: ='Input data'!E$38 -> 3.43 | F37: ='Input data'!F$38 -> 3.564208 | G37: ='Input data'!G$38 -> 2.816375 | H37: =G37+($O$37-$G$37)/($O$10-$G$10) -> 2.8050894 | I37: =H37+($O$37-$G$37)/($O$10-$G$10) -> 2.7938037 | J37: =I37+($O$37-$G$37)/($O$10-$G$10) -> 2.7825181 | K37: =J37+($O$37-$G$37)/($O$10-$G$10) -> 2.7712325 | L37: =K37+($O$37-$G$37)/($O$10-$G$10) -> 2.7599469 | M37: =L37+($O$37-$G$37)/($O$10-$G$10) -> 2.7486612 | N37: =M37+($O$37-$G$37)/($O$10-$G$10) -> 2.7373756 | O37: ='Input data'!$C$53 -> 2.72609 | P37: =$O$37+('Input data'!$C$55-'Input data'!$C$53)/20*('Baseline NFPC'!P$10-2033) -> 2.6897855 | Q37: =$O$37+('Input data'!$C$55-'Input data'!$C$53)/20*('Baseline NFPC'!Q$10-2033) -> 2.653481 | R37: =$O$37+('Input data'!$C$55-'Input data'!$C$53)/20*('Baseline NFPC'!R$10-2033) -> 2.6171765 | S37: =$O$37+('Input data'!$C$55-'Input data'!$C$53)/20*('Baseline NFPC'!S$10-2033) -> 2.580872 | T37: =$O$37+('Input data'!$C$55-'Input data'!$C$53)/20*('Baseline NFPC'!T$10-2033) -> 2.5445675 | U37: =$O$37+('Input data'!$C$55-'Input data'!$C$53)/20*('Baseline NFPC'!U$10-2033) -> 2.508263 | V37: =$O$37+('Input data'!$C$55-'Input data'!$C$53)/20*('Baseline NFPC'!V$10-2033) -> 2.4719585 | W37: =$O$37+('Input data'!$C$55-'Input data'!$C$53)/20*('Baseline NFPC'!W$10-2033) -> 2.435654
B38: Share of long-term debt that matures every year | C38: 0.001 | D38: 0.07537306 | E38: 0.04688205 | F38: 0.05421672 | G38: =IF(OR($C$3="EL",$C$3="CY",$C$3="IE",$C$3="PT"),VLOOKUP($C$3,$B$110:$T$114,MATCH(G$10,$B$110:$T$110,0),0),$F$38+('Input data'!$C$59-$F$38)/($O$10-$F$10)*(G10-$F$10)) -> 0.06734311 | H38: =IF(OR($C$3="EL",$C$3="CY",$C$3="IE",$C$3="PT"),VLOOKUP($C$3,$B$110:$T$114,MATCH(H$10,$B$110:$T$110,0),0),$F$38+('Input data'!$C$59-$F$38)/($O$10-$F$10)*(H10-$F$10)) -> 0.07328111 | I38: =IF(OR($C$3="EL",$C$3="CY",$C$3="IE",$C$3="PT"),VLOOKUP($C$3,$B$110:$T$114,MATCH(I$10,$B$110:$T$110,0),0),$F$38+('Input data'!$C$59-$F$38)/($O$10-$F$10)*(I10-$F$10)) -> 0.06373561 | J38: =IF(OR($C$3="EL",$C$3="CY",$C$3="IE",$C$3="PT"),VLOOKUP($C$3,$B$110:$T$114,MATCH(J$10,$B$110:$T$110,0),0),$F$38+('Input data'!$C$59-$F$38)/($O$10-$F$10)*(J10-$F$10)) -> 0.07199902 | K38: =IF(OR($C$3="EL",$C$3="CY",$C$3="IE",$C$3="PT"),VLOOKUP($C$3,$B$110:$T$114,MATCH(K$10,$B$110:$T$110,0),0),$F$38+('Input data'!$C$59-$F$38)/($O$10-$F$10)*(K10-$F$10)) -> 0.07792014 | L38: =IF(OR($C$3="EL",$C$3="CY",$C$3="IE",$C$3="PT"),VLOOKUP($C$3,$B$110:$T$114,MATCH(L$10,$B$110:$T$110,0),0),$F$38+('Input data'!$C$59-$F$38)/($O$10-$F$10)*(L10-$F$10)) -> 0.07366593 | M38: =IF(OR($C$3="EL",$C$3="CY",$C$3="IE",$C$3="PT"),VLOOKUP($C$3,$B$110:$T$114,MATCH(M$10,$B$110:$T$110,0),0),$F$38+('Input data'!$C$59-$F$38)/($O$10-$F$10)*(M10-$F$10)) -> 0.09283323 | N38: =IF(OR($C$3="EL",$C$3="CY",$C$3="IE",$C$3="PT"),VLOOKUP($C$3,$B$110:$T$114,MATCH(N$10,$B$110:$T$110,0),0),$F$38+('Input data'!$C$59-$F$38)/($O$10-$F$10)*(N10-$F$10)) -> 0.09749916 | O38: =IF(OR($C$3="EL",$C$3="CY",$C$3="IE",$C$3="PT"),VLOOKUP($C$3,$B$110:$T$114,MATCH(O$10,$B$110:$T$110,0),0),'Input data'!$C$59) -> 0.10431984 | P38: =IF(OR($C$3="EL",$C$3="CY",$C$3="IE",$C$3="PT"),VLOOKUP($C$3,$B$110:$T$114,MATCH(P$10,$B$110:$T$110,0),0),'Input data'!$C$59) -> 0.07769295 | Q38: =IF(OR($C$3="EL",$C$3="CY",$C$3="IE",$C$3="PT"),VLOOKUP($C$3,$B$110:$T$114,MATCH(Q$10,$B$110:$T$110,0),0),'Input data'!$C$59) -> 0.08189674 | R38: =IF(OR($C$3="EL",$C$3="CY",$C$3="IE",$C$3="PT"),VLOOKUP($C$3,$B$110:$T$114,MATCH(R$10,$B$110:$T$110,0),0),'Input data'!$C$59) -> 0.07226059 | S38: =IF(OR($C$3="EL",$C$3="CY",$C$3="IE",$C$3="PT"),VLOOKUP($C$3,$B$110:$T$114,MATCH(S$10,$B$110:$T$110,0),0),'Input data'!$C$59) -> 0.07247516 | T38: =IF(OR($C$3="EL",$C$3="CY",$C$3="IE",$C$3="PT"),VLOOKUP($C$3,$B$110:$T$114,MATCH(T$10,$B$110:$T$110,0),0),'Input data'!$C$59) -> 0.07270425 | U38: =IF(OR($C$3="EL",$C$3="CY",$C$3="IE",$C$3="PT"),VLOOKUP($C$3,$B$110:$W$114,MATCH(U$10,$B$110:$W$110,0),0),'Input data'!$C$59) -> 0.07292216 | V38: =IF(OR($C$3="EL",$C$3="CY",$C$3="IE",$C$3="PT"),VLOOKUP($C$3,$B$110:$W$114,MATCH(V$10,$B$110:$W$110,0),0),'Input data'!$C$59) -> 0.07311259 | W38: =IF(OR($C$3="EL",$C$3="CY",$C$3="IE",$C$3="PT"),VLOOKUP($C$3,$B$110:$W$114,MATCH(W$10,$B$110:$W$110,0),0),'Input data'!$C$59) -> 0.07343585
B40: Inflation and exchange rate
B41: GDP deflator (national currency) | C41: ='Input data'!C42 -> 0.4774826 | D41: ='Input data'!D42 -> 6.582269 | E41: ='Input data'!E42 -> 2.965217 | F41: ='Input data'!F42 -> 2.574346 | G41: ='Input data'!G42 -> 1.914897 | H41: =$G$41+($O$41-$G$41)/($O$10-$G$10)*(H10-$G$10) -> 1.9942849 | I41: =$G$41+($O$41-$G$41)/($O$10-$G$10)*(I10-$G$10) -> 2.0736728 | J41: =$G$41+($O$41-$G$41)/($O$10-$G$10)*(J10-$G$10) -> 2.1530606 | K41: =$G$41+($O$41-$G$41)/($O$10-$G$10)*(K10-$G$10) -> 2.2324485 | L41: =$G$41+($O$41-$G$41)/($O$10-$G$10)*(L10-$G$10) -> 2.3118364 | M41: =$G$41+($O$41-$G$41)/($O$10-$G$10)*(M10-$G$10) -> 2.3912243 | N41: =$G$41+($O$41-$G$41)/($O$10-$G$10)*(N10-$G$10) -> 2.4706121 | O41: ='Input data'!$C$61 -> 2.55 | P41: =$O$41+('Input data'!$C$62-'Input data'!$C$61)/20*(P$10-2033) -> 2.5225 | Q41: =$O$41+('Input data'!$C$62-'Input data'!$C$61)/20*(Q$10-2033) -> 2.495 | R41: =$O$41+('Input data'!$C$62-'Input data'!$C$61)/20*(R$10-2033) -> 2.4675 | S41: =$O$41+('Input data'!$C$62-'Input data'!$C$61)/20*(S$10-2033) -> 2.44 | T41: =$O$41+('Input data'!$C$62-'Input data'!$C$61)/20*(T$10-2033) -> 2.4125 | U41: =$O$41+('Input data'!$C$62-'Input data'!$C$61)/20*(U$10-2033) -> 2.385 | V41: =$O$41+('Input data'!$C$62-'Input data'!$C$61)/20*(V$10-2033) -> 2.3575 | W41: =$O$41+('Input data'!$C$62-'Input data'!$C$61)/20*(W$10-2033) -> 2.33
B42: Exchange rate composite change (weighted by share of debt in each currency) | C42: 1 | D42: 1 | E42: 0.9999999 | F42: 1 | G42: 1 | H42: 1 | I42: 1 | J42: 1 | K42: 1 | L42: 1 | M42: 1 | N42: 1 | O42: 1 | P42: 1 | Q42: 1 | R42: 1 | S42: 1 | T42: 1 | U42: 1 | V42: 1 | W42: 1
B44: Intermediate calculations (growth rate equation)
B46: Fiscal multiplier | C46: ='Input data'!C49 -> 0.75
B47: Budget balance semi-elasticity | C47: ='Input data'!C50 -> 0.522
B49: Auxiliary variable to control the closure of the output gap | D49: =IF(AND(ABS((D12-C12)-('Input data'!D13-'Input data'!C13))>0.0001,ABS(D12-C12)>0.0001,D$10>$C$5),4,IF(C49=4,3,IF(C49=3,2,IF(C49=2,1,0)))) -> 0 | E49: =IF(AND(ABS((E12-D12)-('Input data'!E13-'Input data'!D13))>0.0001,ABS(E12-D12)>0.0001,E$10>$C$5),4,IF(D49=4,3,IF(D49=3,2,IF(D49=2,1,0)))) -> 0 | F49: =IF(AND(ABS((F12-E12)-('Input data'!F13-'Input data'!E13))>0.0001,ABS(F12-E12)>0.0001,F$10>$C$5),4,IF(E49=4,3,IF(E49=3,2,IF(E49=2,1,0)))) -> 0 | G49: =IF(AND(ABS((G12-F12)-('Input data'!G13-'Input data'!F13))>0.0001,ABS(G12-F12)>0.0001,G$10>$C$5),4,IF(F49=4,3,IF(F49=3,2,IF(F49=2,1,0)))) -> 0 | H49: =IF(AND(ABS((H12-G12)-('Input data'!H13-'Input data'!G13))>0.0001,ABS(H12-G12)>0.0001,H$10>$C$5),4,IF(G49=4,3,IF(G49=3,2,IF(G49=2,1,0)))) -> 0 | I49: =IF(AND(ABS((I12-H12)-('Input data'!I13-'Input data'!H13))>0.0001,ABS(I12-H12)>0.0001,I$10>$C$5),4,IF(H49=4,3,IF(H49=3,2,IF(H49=2,1,0)))) -> 0 | J49: =IF(AND(ABS((J12-I12)-('Input data'!J13-'Input data'!I13))>0.0001,ABS(J12-I12)>0.0001,J$10>$C$5),4,IF(I49=4,3,IF(I49=3,2,IF(I49=2,1,0)))) -> 0 | K49: =IF(AND(ABS((K12-J12)-('Input data'!K13-'Input data'!J13))>0.0001,ABS(K12-J12)>0.0001,K$10>$C$5),4,IF(J49=4,3,IF(J49=3,2,IF(J49=2,1,0)))) -> 0 | ... W49: =IF(AND(ABS((W12-V12)-('Input data'!W13-'Input data'!V13))>0.0001,ABS(W12-V12)>0.0001,W$10>$C$5),4,IF(V49=4,3,IF(V49=3,2,IF(V49=2,1,0)))) -> 0
B50: OG intermediate auxiliary value | D50: =IF(C49=4,2/3*C29,IF(C49=3,1/3*B29,0)) -> 0 | E50: =IF(D49=4,2/3*D29,IF(D49=3,1/3*C29,0)) -> 0 | F50: =IF(E49=4,2/3*E29,IF(E49=3,1/3*D29,0)) -> 0 | G50: =IF(F49=4,2/3*F29,IF(F49=3,1/3*E29,0)) -> 0 | H50: =IF(G49=4,2/3*G29,IF(G49=3,1/3*F29,0)) -> 0 | I50: =IF(H49=4,2/3*H29,IF(H49=3,1/3*G29,0)) -> 0 | J50: =IF(I49=4,2/3*I29,IF(I49=3,1/3*H29,0)) -> 0 | K50: =IF(J49=4,2/3*J29,IF(J49=3,1/3*I29,0)) -> 0 | ... W50: =IF(V49=4,2/3*V29,IF(V49=3,1/3*U29,0)) -> 0
B51: GDP intermediate growth rate - only feedback effect and no closure of the OG | D51: ='Input data'!D30-$C$46*((D12-C12)-('Input data'!D13-'Input data'!C13)) -> 9.433022 | E51: ='Input data'!E30-$C$46*((E12-D12)-('Input data'!E13-'Input data'!D13)) -> -3.198788 | F51: ='Input data'!F30-$C$46*((F12-E12)-('Input data'!F13-'Input data'!E13)) -> 1.243702 | G51: ='Input data'!G30-$C$46*((G12-F12)-('Input data'!G13-'Input data'!F13)) -> 1.4972052 | H51: ='Input data'!H30-$C$46*((H12-G12)) -> 3.746114 | I51: ='Input data'!I30-$C$46*((I12-H12)) -> 3.802369 | J51: ='Input data'!J30-$C$46*((J12-I12)) -> 3.577386 | K51: ='Input data'!K30-$C$46*((K12-J12)) -> 3.164204 | L51: ='Input data'!L30-$C$46*((L12-K12)) -> 2.938014 | M51: ='Input data'!M30-$C$46*((M12-L12)) -> 2.669411 | N51: ='Input data'!N30-$C$46*((N12-M12)) -> 2.359786 | O51: ='Input data'!O30-$C$46*((O12-N12)) -> 2.013409 | ... W51: ='Input data'!W30-$C$46*((W12-V12)) -> 1.571112
B53: Debt projections
C55: 2021 | D55: 2022 | E55: 2023 | F55: 2024 | G55: 2025 | H55: 2026 | I55: 2027 | J55: 2028 | K55: 2029 | L55: 2030 | M55: 2031 | N55: 2032 | O55: 2033 | P55: 2034 | Q55: 2035 | R55: 2036 | S55: 2037 | T55: 2038 | U55: 2039 | V55: 2040 | W55: 2041
B56: Gross debt | C56: =+'Input data'!C12 -> 54.39847 | D56: =+C56+D57 -> 44.391772 | E56: =+D56+E57 -> 43.730434 | F56: =+E56+F57 -> 42.488825 | G56: =+F56+G57 -> 41.250806 | H56: =+G56+H57 -> 37.732588 | I56: =+H56+I57 -> 34.267259 | J56: =+I56+J57 -> 31.007171 | K56: =+J56+K57 -> 28.062291 | ... W56: =+V56+W57 -> 9.8184426
B57: Change in debt (-1+2+3) | D57: =-D58+D66+D71 -> -10.006698 | E57: =-E58+E66+E71 -> -0.66133783 | F57: =-F58+F66+F71 -> -1.2416084 | G57: =-G58+G66+G71 -> -1.2380198 | H57: =-H58+H66+H71 -> -3.5182178 | I57: =-I58+I66+I71 -> -3.4653285 | J57: =-J58+J66+J71 -> -3.2600888 | K57: =-K58+K66+K71 -> -2.9448795 | ... W57: =-W58+W66+W71 -> -0.60602417
B58: (1) Primary balance (1.1 + 1.2 - 1.3 -1.4 -1.5 - 1.6 -1.7) | D58: =D59+D60-D61-D62-D63-D64-D65 -> 2.3626831 | E58: =E59+E60-E61-E62-E63-E64-E65 -> 2.3411552 | F58: =F59+F60-F61-F62-F63-F64-F65 -> 1.9481772 | G58: =G59+G60-G61-G62-G63-G64-G65 -> 1.9506578 | H58: =H59+H60-H61-H62-H63-H64-H65 -> 1.9528092 | I58: =I59+I60-I61-I62-I63-I64-I65 -> 2.0061044 | J58: =J59+J60-J61-J62-J63-J64-J65 -> 1.9944072 | K58: =K59+K60-K61-K62-K63-K64-K65 -> 1.9106949 | ... W58: =W59+W60-W61-W62-W63-W64-W65 -> 0.47302213
B59: (1.1) Structural primary balance (before ageing cost) | D59: =D12 -> -2.376722 | E59: =E12 -> 1.712465 | F59: =F12 -> 2.528801 | G59: =IF(G12="",F59,G12) -> 2.528801 | H59: =IF(H12="",G59,H12) -> 2.528801 | I59: =IF(I12="",H59,I12) -> 2.528801 | J59: =IF(J12="",I59,J12) -> 2.528801 | K59: =IF(K12="",J59,K12) -> 2.528801 | L59: =IF(L12="",K59,L12) -> 2.528801 | M59: =IF(M12="",L59,M12) -> 2.528801 | N59: =IF(N12="",M59,N12) -> 2.528801 | ... W59: =IF(W12="",V59,W12) -> 2.528801
B60: (1.2) Cumulated budgetary effort (in terms of primary balance) | D60: 0 | E60: 0 | F60: 0 | G60: 0 | H60: 0 | I60: 0 | J60: 0 | K60: 0 | L60: 0 | M60: 0 | N60: 0 | O60: 0 | P60: 0 | Q60: 0 | R60: 0 | S60: 0 | T60: 0 | U60: 0 | V60: 0 | W60: 0
B61: (1.3) Cyclical component | D61: =-$C$47*D29 -> -4.7394051 | E61: =-$C$47*E29 -> -0.62869023 | F61: =-$C$47*F29 -> 0.58062382 | G61: =-$C$47*G29 -> 0.52665142 | H61: =-$C$47*H29 -> 0.3510982 | I61: =-$C$47*I29 -> 0.11703124 | J61: =-$C$47*J29 -> -3.4308927e-06 | K61: =-$C$47*K29 -> -2.9249033e-06 | ... W61: =-$C$47*W29 -> -1.1634835e-05
B62: (1.4) One-off and other temporary measures | D62: =-D13 -> 0 | E62: =-E13 -> 0 | F62: =-F13 -> 0 | G62: =-G13 -> 0 | H62: =-H13 -> 0 | I62: =-I13 -> 0 | J62: =-J13 -> 0 | K62: =-K13 -> 0 | ... W62: =-W13 -> 0
B63: (1.5) Cost of ageing | D63: =IF(D$55<=$C$5,0,HLOOKUP(D$55,'Input data'!$C$9:$BB$26,12,FALSE)-HLOOKUP($C$5,'Input data'!$C$9:$BB$26,12,FALSE)) -> 0 | E63: =IF(E$55<=$C$5,0,HLOOKUP(E$55,'Input data'!$C$9:$BB$26,12,FALSE)-HLOOKUP($C$5,'Input data'!$C$9:$BB$26,12,FALSE)) -> 0 | F63: =IF(F$55<=$C$5,0,HLOOKUP(F$55,'Input data'!$C$9:$BB$26,12,FALSE)-HLOOKUP($C$5,'Input data'!$C$9:$BB$26,12,FALSE)) -> 0 | G63: =IF(G$55<=$C$5,0,HLOOKUP(G$55,'Input data'!$C$9:$BB$26,12,FALSE)-HLOOKUP($C$5,'Input data'!$C$9:$BB$26,12,FALSE)) -> 0.05369 | H63: =IF(H$55<=$C$5,0,HLOOKUP(H$55,'Input data'!$C$9:$BB$26,12,FALSE)-HLOOKUP($C$5,'Input data'!$C$9:$BB$26,12,FALSE)) -> 0.22929 | I63: =IF(I$55<=$C$5,0,HLOOKUP(I$55,'Input data'!$C$9:$BB$26,12,FALSE)-HLOOKUP($C$5,'Input data'!$C$9:$BB$26,12,FALSE)) -> 0.41226 | J63: =IF(J$55<=$C$5,0,HLOOKUP(J$55,'Input data'!$C$9:$BB$26,12,FALSE)-HLOOKUP($C$5,'Input data'!$C$9:$BB$26,12,FALSE)) -> 0.54319 | K63: =IF(K$55<=$C$5,0,HLOOKUP(K$55,'Input data'!$C$9:$BB$26,12,FALSE)-HLOOKUP($C$5,'Input data'!$C$9:$BB$26,12,FALSE)) -> 0.6291 | ... W63: =IF(W$55<=$C$5,0,HLOOKUP(W$55,'Input data'!$C$9:$BB$26,12,FALSE)-HLOOKUP($C$5,'Input data'!$C$9:$BB$26,12,FALSE)) -> 2.09316
B64: (1.6) Property incomes | D64: =IF(D$55<=$C$5,0,-HLOOKUP(D$55,'Input data'!$C$9:$BB$26,18,FALSE)+HLOOKUP($C$5,'Input data'!$C$9:$BB$26,18,FALSE)) -> 0 | E64: =IF(E$55<=$C$5,0,-HLOOKUP(E$55,'Input data'!$C$9:$BB$26,18,FALSE)+HLOOKUP($C$5,'Input data'!$C$9:$BB$26,18,FALSE)) -> 0 | F64: =IF(F$55<=$C$5,0,-HLOOKUP(F$55,'Input data'!$C$9:$BB$26,18,FALSE)+HLOOKUP($C$5,'Input data'!$C$9:$BB$26,18,FALSE)) -> 0 | G64: =IF(G$55<=$C$5,0,-HLOOKUP(G$55,'Input data'!$C$9:$BB$26,18,FALSE)+HLOOKUP($C$5,'Input data'!$C$9:$BB$26,18,FALSE)) -> -0.0021982 | H64: =IF(H$55<=$C$5,0,-HLOOKUP(H$55,'Input data'!$C$9:$BB$26,18,FALSE)+HLOOKUP($C$5,'Input data'!$C$9:$BB$26,18,FALSE)) -> -0.0043964 | I64: =IF(I$55<=$C$5,0,-HLOOKUP(I$55,'Input data'!$C$9:$BB$26,18,FALSE)+HLOOKUP($C$5,'Input data'!$C$9:$BB$26,18,FALSE)) -> -0.0065946 | J64: =IF(J$55<=$C$5,0,-HLOOKUP(J$55,'Input data'!$C$9:$BB$26,18,FALSE)+HLOOKUP($C$5,'Input data'!$C$9:$BB$26,18,FALSE)) -> -0.0087928 | K64: =IF(K$55<=$C$5,0,-HLOOKUP(K$55,'Input data'!$C$9:$BB$26,18,FALSE)+HLOOKUP($C$5,'Input data'!$C$9:$BB$26,18,FALSE)) -> -0.010991 | ... W64: =IF(W$55<=$C$5,0,-HLOOKUP(W$55,'Input data'!$C$9:$BB$26,18,FALSE)+HLOOKUP($C$5,'Input data'!$C$9:$BB$26,18,FALSE)) -> -0.0373695
B65: (1.7) Revenues | D65: 0 | E65: 0 | F65: 0 | G65: 0 | H65: 0 | I65: 0 | J65: 0 | K65: 0 | L65: 0 | M65: 0 | N65: 0 | O65: 0 | P65: 0 | Q65: 0 | R65: 0 | S65: 0 | T65: 0 | U65: 0 | V65: 0 | W65: 0
B66: (2) Snowball effect (2.1 + 2.2 + 2.3) | D66: =SUM(D67:D70) -> -7.101956 | E66: =SUM(E67:E70) -> 0.8370108 | F66: =SUM(F67:F70) -> -0.9299982 | G66: =SUM(G67:G70) -> -1.487604 | H66: =SUM(H67:H70) -> -1.5654086 | I66: =SUM(I67:I70) -> -1.4592241 | J66: =SUM(J67:J70) -> -1.2656816 | K66: =SUM(K67:K70) -> -1.0341846 | ... W66: =SUM(W67:W70) -> -0.13300203
B67: (2.1) Interest expenditure | D67: =C56*D35/100*(1/(1+D32/100)) -> 0.65707416 | E67: =D56*E35/100*(1/(1+E32/100)) -> 0.69073786 | F67: =E56*F35/100*(1/(1+F32/100)) -> 0.6912335 | G67: =F56*G35/100*(1/(1+G32/100)) -> 0.67917885 | H67: =G56*H35/100*(1/(1+H32/100)) -> 0.70154422 | I67: =H56*I35/100*(1/(1+I32/100)) -> 0.66142763 | J67: =I56*J35/100*(1/(1+J32/100)) -> 0.61515047 | K67: =J56*K35/100*(1/(1+K32/100)) -> 0.57318814 | ... W67: =V56*W35/100*(1/(1+W32/100)) -> 0.26193275
B68: (2.2) Growth effect | D68: =-C56*(D23/100)*(1/(1+D32/100)) -> -4.3995087 | E68: =-D56*(E23/100)*(1/(1+E32/100)) -> 1.4246776 | F68: =-E56*(F23/100)*(1/(1+F32/100)) -> -0.52371299 | G68: =-F56*(G23/100)*(1/(1+G32/100)) -> -1.3684519 | H68: =-G56*(H23/100)*(1/(1+H32/100)) -> -1.4603796 | I68: =-H56*(I23/100)*(1/(1+I32/100)) -> -1.3540972 | J68: =-I56*(J23/100)*(1/(1+J32/100)) -> -1.1585875 | K68: =-J56*(K23/100)*(1/(1+K32/100)) -> -0.93026958 | ... W68: =-V56*(W23/100)*(1/(1+W32/100)) -> -0.15757518
B69: (2.3) Inflation effect | D69: =-C56*D41/100*(1/(1+D41/100)) -> -3.3595209 | E69: =-D56*E41/100*(1/(1+E41/100)) -> -1.2784049 | F69: =-E56*F41/100*(1/(1+F41/100)) -> -1.0975187 | G69: =-F56*G41/100*(1/(1+G41/100)) -> -0.79833004 | H69: =-G56*H41/100*(1/(1+H41/100)) -> -0.80657321 | I69: =-H56*I41/100*(1/(1+I41/100)) -> -0.76655456 | J69: =-I56*J41/100*(1/(1+J41/100)) -> -0.72224451 | K69: =-J56*K41/100*(1/(1+K41/100)) -> -0.67710313 | ... W69: =-V56*W41/100*(1/(1+W41/100)) -> -0.2373596
B70: (2.4) Exchange rate effect linked to the interest rate | D70: -5.6246662e-07 | E70: 2.0516894e-07 | F70: 2.9725664e-08 | G70: -8.8262773e-07 | H70: 0 | I70: 0 | J70: 0 | K70: 0 | L70: 0 | M70: 0 | N70: 0 | O70: 0 | P70: 0 | Q70: 0 | R70: 0 | S70: 0 | T70: 0 | U70: 0 | V70: 0 | W70: 0
B71: (3 ) Stock flow adjustments (3.1 + 3.2) | D71: ='Input data'!D16 -> -0.5420594 | E71: ='Input data'!E16 -> 0.8428066 | F71: ='Input data'!F16 -> 1.636567 | G71: ='Input data'!G16 -> 2.200242 | H71: ='Input data'!H16 -> 0 | I71: ='Input data'!I16 -> 0 | J71: ='Input data'!J16 -> 0 | K71: ='Input data'!K16 -> 0 | ... W71: ='Input data'!W16 -> 0
B72: (3.1) Base | D72: =D14 -> -0.5420614 | E72: =E14 -> 0.8428086 | F72: =F14 -> 1.636568 | G72: =G14 -> 2.20024 | H72: =H14 -> 0 | I72: =I14 -> 0 | J72: =J14 -> 0 | K72: =K14 -> 0 | ... W72: =W14 -> 0
B73: (3.2) Adjustment due to the exchange rate effect linked to debt value | D73: =+D71-D72 -> 2e-06 | E73: =+E71-E72 -> -2e-06 | F73: =+F71-F72 -> -1e-06 | G73: =+G71-G72 -> 2e-06 | H73: =+H71-H72 -> 0 | I73: =+I71-I72 -> 0 | J73: =+J71-J72 -> 0 | K73: =+K71-K72 -> 0 | ... W73: =+W71-W72 -> 0
B75: Other budgetary variables
B76: Headline balance | D76: =D58-D67 -> 1.7056089 | E76: =E58-E67 -> 1.6504174 | F76: =F58-F67 -> 1.2569437 | G76: =G58-G67 -> 1.2714789 | H76: =H58-H67 -> 1.251265 | I76: =I58-I67 -> 1.3446767 | J76: =J58-J67 -> 1.3792568 | K76: =K58-K67 -> 1.3375068 | ... W76: =W58-W67 -> 0.21108939
B77: Structural balance | D77: =D59-D67-D63-D64-D65 -> -3.0337962 | E77: =E59-E67-E63-E64-E65 -> 1.0217271 | F77: =F59-F67-F63-F64-F65 -> 1.8375675 | G77: =G59-G67-G63-G64-G65 -> 1.7981303 | H77: =H59-H67-H63-H64-H65 -> 1.6023632 | I77: =I59-I67-I63-I64-I65 -> 1.461708 | J77: =J59-J67-J63-J64-J65 -> 1.3792533 | K77: =K59-K67-K63-K64-K65 -> 1.3375039 | ... W77: =W59-W67-W63-W64-W65 -> 0.21107775
B78: Net expenditure growth | D78: ='Input data'!D45 -> 14.052581 | E78: ='Input data'!E45 -> 13.567155 | F78: ='Input data'!F45 -> 7.3776443 | G78: ='Input data'!G33+G41-(G$12-F$12)/'Input data'!$C$64*100 -> 5.200709 | H78: ='Input data'!H33+H41-(H$12-G$12)/'Input data'!$C$64*100 -> 5.3891289 | I78: ='Input data'!I33+I41-(I$12-H$12)/'Input data'!$C$64*100 -> 5.4095418 | J78: ='Input data'!J33+J41-(J$12-I$12)/'Input data'!$C$64*100 -> 5.4982216 | K78: ='Input data'!K33+K41-(K$12-J$12)/'Input data'!$C$64*100 -> 5.3966535 | L78: ='Input data'!L33+L41-(L$12-K$12)/'Input data'!$C$64*100 -> 5.2498504 | M78: ='Input data'!M33+M41-(M$12-L$12)/'Input data'!$C$64*100 -> 5.0606333 | N78: ='Input data'!N33+N41-(N$12-M$12)/'Input data'!$C$64*100 -> 4.8303961 | ... W78: ='Input data'!W33+W41-(W$12-V$12)/'Input data'!$C$64*100 -> 3.901108
B81: Debt decomposition and IIR
B83: Auxiliary variable identifying whether debt is increasing | D83: =IF((D87-C87*D42/((1+D23/100)*(1+D41/100)))>0,1,0) -> 0 | E83: =IF((E87-D87*E42/((1+E23/100)*(1+E41/100)))>0,1,0) -> 0 | F83: =IF((F87-E87*F42/((1+F23/100)*(1+F41/100)))>0,1,0) -> 1 | G83: =IF((G87-F87*G42/((1+G23/100)*(1+G41/100)))>0,1,0) -> 1 | H83: =IF((H87-G87*H42/((1+H23/100)*(1+H41/100)))>0,1,0) -> 0 | I83: =IF((I87-H87*I42/((1+I23/100)*(1+I41/100)))>0,1,0) -> 0 | J83: =IF((J87-I87*J42/((1+J23/100)*(1+J41/100)))>0,1,0) -> 0 | K83: =IF((K87-J87*K42/((1+K23/100)*(1+K41/100)))>0,1,0) -> 0 | ... W83: =IF((W87-V87*W42/((1+W23/100)*(1+W41/100)))>0,1,0) -> 0
B84: Auxiliary variable identifying whether some debt is rolled over even though debt is decreasing | D84: =IF(AND(D83=0,ABS(D87-C87*D42/((1+D23/100)*(1+D41/100)))<((C93*C87*D42/((1+D23/100)*(1+D41/100))+(D38*C87*C94*D42/((1+D23/100)*(1+D41/100)))))),1,0) -> 0 | E84: =IF(AND(E83=0,ABS(E87-D87*E42/((1+E23/100)*(1+E41/100)))<((D93*D87*E42/((1+E23/100)*(1+E41/100))+(E38*D87*D94*E42/((1+E23/100)*(1+E41/100)))))),1,0) -> 1 | F84: =IF(AND(F83=0,ABS(F87-E87*F42/((1+F23/100)*(1+F41/100)))<((E93*E87*F42/((1+F23/100)*(1+F41/100))+(F38*E87*E94*F42/((1+F23/100)*(1+F41/100)))))),1,0) -> 0 | G84: =IF(AND(G83=0,ABS(G87-F87*G42/((1+G23/100)*(1+G41/100)))<((F93*F87*G42/((1+G23/100)*(1+G41/100))+(G38*F87*F94*G42/((1+G23/100)*(1+G41/100)))))),1,0) -> 0 | H84: =IF(AND(H83=0,ABS(H87-G87*H42/((1+H23/100)*(1+H41/100)))<((G93*G87*H42/((1+H23/100)*(1+H41/100))+(H38*G87*G94*H42/((1+H23/100)*(1+H41/100)))))),1,0) -> 1 | I84: =IF(AND(I83=0,ABS(I87-H87*I42/((1+I23/100)*(1+I41/100)))<((H93*H87*I42/((1+I23/100)*(1+I41/100))+(I38*H87*H94*I42/((1+I23/100)*(1+I41/100)))))),1,0) -> 1 | J84: =IF(AND(J83=0,ABS(J87-I87*J42/((1+J23/100)*(1+J41/100)))<((I93*I87*J42/((1+J23/100)*(1+J41/100))+(J38*I87*I94*J42/((1+J23/100)*(1+J41/100)))))),1,0) -> 1 | K84: =IF(AND(K83=0,ABS(K87-J87*K42/((1+K23/100)*(1+K41/100)))<((J93*J87*K42/((1+K23/100)*(1+K41/100))+(K38*J87*J94*K42/((1+K23/100)*(1+K41/100)))))),1,0) -> 1 | ... W84: =IF(AND(W83=0,ABS(W87-V87*W42/((1+W23/100)*(1+W41/100)))<((V93*V87*W42/((1+W23/100)*(1+W41/100))+(W38*V87*V94*W42/((1+W23/100)*(1+W41/100)))))),1,0) -> 1
C86: 2021 | D86: 2022 | E86: 2023 | F86: 2024 | G86: 2025 | H86: 2026 | I86: 2027 | J86: 2028 | K86: 2029 | L86: 2030 | M86: 2031 | N86: 2032 | O86: 2033 | P86: 2034 | Q86: 2035 | R86: 2036 | S86: 2037 | T86: 2038 | U86: 2039 | V86: 2040 | W86: 2041
B87: Gross debt | C87: =C56 -> 54.39847 | D87: =D56 -> 44.391772 | E87: =E56 -> 43.730434 | F87: =F56 -> 42.488825 | G87: =G56 -> 41.250806 | H87: =G87*(1+H101/100)*H42-H59-H60+H61+H62+H63+H64+H65+H71 -> 37.732588 | I87: =H87*(1+I101/100)*I42-I59-I60+I61+I62+I63+I64+I65+I71 -> 34.267259 | J87: =I87*(1+J101/100)*J42-J59-J60+J61+J62+J63+J64+J65+J71 -> 31.007171 | K87: =J87*(1+K101/100)*K42-K59-K60+K61+K62+K63+K64+K65+K71 -> 28.062291 | L87: =K87*(1+L101/100)*L42-L59-L60+L61+L62+L63+L64+L65+L71 -> 25.375334 | M87: =L87*(1+M101/100)*M42-M59-M60+M61+M62+M63+M64+M65+M71 -> 22.951906 | N87: =M87*(1+N101/100)*N42-N59-N60+N61+N62+N63+N64+N65+N71 -> 20.846368 | O87: =N87*(1+O101/100)*O42-O59-O60+O61+O62+O63+O64+O65+O71 -> 18.942087 | ... W87: =V87*(1+W101/100)*W42-W59-W60+W61+W62+W63+W64+W65+W71 -> 9.8184426
B88: Of which Outstanding debt | D88: ='Input data'!C66*$D$87 -> 37.416473 | E88: =IF(E87=0,0,IF(E83=1,D87*E42/((1+E23/100)*(1+E41/100))-E89-E90,IF(AND(E83=0,E84=1),(1-D93-E38*D94)*D87*E42/((1+E23/100)*(1+E41/100)),E87))) -> 37.985689 | F88: =IF(F87=0,0,IF(F83=1,E87*F42/((1+F23/100)*(1+F41/100))-F89-F90,IF(AND(F83=0,F84=1),(1-E93-F38*E94)*E87*F42/((1+F23/100)*(1+F41/100)),F87))) -> 36.086221 | G88: =IF(G87=0,0,IF(G83=1,F87*G42/((1+G23/100)*(1+G41/100))-G89-G90,IF(AND(G83=0,G84=1),(1-F93-G38*F94)*F87*G42/((1+G23/100)*(1+G41/100)),G87))) -> 34.066502 | H88: =IF(H87=0,0,IF(H83=1,G87*H42/((1+H23/100)*(1+H41/100))-H89-H90,IF(AND(H83=0,H84=1),(1-G93-H38*G94)*G87*H42/((1+H23/100)*(1+H41/100)),H87))) -> 32.705585 | I88: =IF(I87=0,0,IF(I83=1,H87*I42/((1+I23/100)*(1+I41/100))-I89-I90,IF(AND(I83=0,I84=1),(1-H93-I38*H94)*H87*I42/((1+I23/100)*(1+I41/100)),I87))) -> 30.729943 | J88: =IF(J87=0,0,IF(J83=1,I87*J42/((1+J23/100)*(1+J41/100))-J89-J90,IF(AND(J83=0,J84=1),(1-I93-J38*I94)*I87*J42/((1+J23/100)*(1+J41/100)),J87))) -> 28.281574 | K88: =IF(K87=0,0,IF(K83=1,J87*K42/((1+K23/100)*(1+K41/100))-K89-K90,IF(AND(K83=0,K84=1),(1-J93-K38*J94)*J87*K42/((1+K23/100)*(1+K41/100)),K87))) -> 25.999811 | L88: =IF(L87=0,0,IF(L83=1,K87*L42/((1+L23/100)*(1+L41/100))-L89-L90,IF(AND(L83=0,L84=1),(1-K93-L38*K94)*K87*L42/((1+L23/100)*(1+L41/100)),L87))) -> 24.040696 | ... W88: =IF(W87=0,0,IF(W83=1,V87*W42/((1+W23/100)*(1+W41/100))-W89-W90,IF(AND(W83=0,W84=1),(1-V93-W38*V94)*V87*W42/((1+W23/100)*(1+W41/100)),W87))) -> 9.2929099
B89: Rolled over long-term debt | D89: ='Input data'!C67*$D$87 -> 2.3067736 | E89: =IF(E87=0,0,IF(E83=1,E38*D87*D94*E42/((1+E23/100)*(1+E41/100)),IF(AND(E83=0,E84=1),(E38*D87*D94*E42/((1+E23/100)*(1+E41/100)))*(1-ABS(E87-D87*E42/((1+E23/100)*(1+E41/100)))/((E38*D87*D94*E42/((1+E23/100)*(1+E41/100)))+(D93*D87*E42/((1+E23/100)*(1+E41/100))))),0))) -> 1.6381495 | F89: =IF(F87=0,0,IF(F83=1,F38*E87*E94*F42/((1+F23/100)*(1+F41/100)),IF(AND(F83=0,F84=1),(F38*E87*E94*F42/((1+F23/100)*(1+F41/100)))*(1-ABS(F87-E87*F42/((1+F23/100)*(1+F41/100)))/((F38*E87*E94*F42/((1+F23/100)*(1+F41/100)))+(E93*E87*F42/((1+F23/100)*(1+F41/100))))),0))) -> 2.0686309 | G89: =IF(G87=0,0,IF(G83=1,G38*F87*F94*G42/((1+G23/100)*(1+G41/100)),IF(AND(G83=0,G84=1),(G38*F87*F94*G42/((1+G23/100)*(1+G41/100)))*(1-ABS(G87-F87*G42/((1+G23/100)*(1+G41/100)))/((G38*F87*F94*G42/((1+G23/100)*(1+G41/100)))+(F93*F87*G42/((1+G23/100)*(1+G41/100))))),0))) -> 2.4597944 | H89: =IF(H87=0,0,IF(H83=1,H38*G87*G94*H42/((1+H23/100)*(1+H41/100)),IF(AND(H83=0,H84=1),(H38*G87*G94*H42/((1+H23/100)*(1+H41/100)))*(1-ABS(H87-G87*H42/((1+H23/100)*(1+H41/100)))/((H38*G87*G94*H42/((1+H23/100)*(1+H41/100)))+(G93*G87*H42/((1+H23/100)*(1+H41/100))))),0))) -> 2.0707861 | I89: =IF(I87=0,0,IF(I83=1,I38*H87*H94*I42/((1+I23/100)*(1+I41/100)),IF(AND(I83=0,I84=1),(I38*H87*H94*I42/((1+I23/100)*(1+I41/100)))*(1-ABS(I87-H87*I42/((1+I23/100)*(1+I41/100)))/((I38*H87*H94*I42/((1+I23/100)*(1+I41/100)))+(H93*H87*I42/((1+I23/100)*(1+I41/100))))),0))) -> 1.515731 | J89: =IF(J87=0,0,IF(J83=1,J38*I87*I94*J42/((1+J23/100)*(1+J41/100)),IF(AND(J83=0,J84=1),(J38*I87*I94*J42/((1+J23/100)*(1+J41/100)))*(1-ABS(J87-I87*J42/((1+J23/100)*(1+J41/100)))/((J38*I87*I94*J42/((1+J23/100)*(1+J41/100)))+(I93*I87*J42/((1+J23/100)*(1+J41/100))))),0))) -> 1.4569534 | K89: =IF(K87=0,0,IF(K83=1,K38*J87*J94*K42/((1+K23/100)*(1+K41/100)),IF(AND(K83=0,K84=1),(K38*J87*J94*K42/((1+K23/100)*(1+K41/100)))*(1-ABS(K87-J87*K42/((1+K23/100)*(1+K41/100)))/((K38*J87*J94*K42/((1+K23/100)*(1+K41/100)))+(J93*J87*K42/((1+K23/100)*(1+K41/100))))),0))) -> 1.3327966 | L89: =IF(L87=0,0,IF(L83=1,L38*K87*K94*L42/((1+L23/100)*(1+L41/100)),IF(AND(L83=0,L84=1),(L38*K87*K94*L42/((1+L23/100)*(1+L41/100)))*(1-ABS(L87-K87*L42/((1+L23/100)*(1+L41/100)))/((L38*K87*K94*L42/((1+L23/100)*(1+L41/100)))+(K93*K87*L42/((1+L23/100)*(1+L41/100))))),0))) -> 0.97962372 | ... W89: =IF(W87=0,0,IF(W83=1,W38*V87*V94*W42/((1+W23/100)*(1+W41/100)),IF(AND(W83=0,W84=1),(W38*V87*V94*W42/((1+W23/100)*(1+W41/100)))*(1-ABS(W87-V87*W42/((1+W23/100)*(1+W41/100)))/((W38*V87*V94*W42/((1+W23/100)*(1+W41/100)))+(V93*V87*W42/((1+W23/100)*(1+W41/100))))),0))) -> 0.52545964
B90: Rolled over short-term debt | D90: ='Input data'!C68*$D$87 -> 4.6685201 | E90: =IF(E87=0,0,IF(E83=1,(1-D94)*D87*E42/((1+E23/100)*(1+E41/100)),IF(AND(E83=0,E84=1),(D93*D87*E42/((1+E23/100)*(1+E41/100)))*(1-ABS(E87-D87*E42/((1+E23/100)*(1+E41/100)))/((E38*D87*D94*E42/((1+E23/100)*(1+E41/100)))+(D93*D87*E42/((1+E23/100)*(1+E41/100))))),0))) -> 4.1065954 | F90: =IF(F87=0,0,IF(F83=1,(1-E94)*E87*F42/((1+F23/100)*(1+F41/100)),IF(AND(F83=0,F84=1),(E93*E87*F42/((1+F23/100)*(1+F41/100)))*(1-ABS(F87-E87*F42/((1+F23/100)*(1+F41/100)))/((F38*E87*E94*F42/((1+F23/100)*(1+F41/100)))+(E93*E87*F42/((1+F23/100)*(1+F41/100))))),0))) -> 3.9543503 | G90: =IF(G87=0,0,IF(G83=1,(1-F94)*F87*G42/((1+G23/100)*(1+G41/100)),IF(AND(G83=0,G84=1),(F93*F87*G42/((1+G23/100)*(1+G41/100)))*(1-ABS(G87-F87*G42/((1+G23/100)*(1+G41/100)))/((G38*F87*F94*G42/((1+G23/100)*(1+G41/100)))+(F93*F87*G42/((1+G23/100)*(1+G41/100))))),0))) -> 3.7957467 | H90: =IF(H87=0,0,IF(H83=1,(1-G94)*G87*H42/((1+H23/100)*(1+H41/100)),IF(AND(H83=0,H84=1),(G93*G87*H42/((1+H23/100)*(1+H41/100)))*(1-ABS(H87-G87*H42/((1+H23/100)*(1+H41/100)))/((H38*G87*G94*H42/((1+H23/100)*(1+H41/100)))+(G93*G87*H42/((1+H23/100)*(1+H41/100))))),0))) -> 2.9562166 | I90: =IF(I87=0,0,IF(I83=1,(1-H94)*H87*I42/((1+I23/100)*(1+I41/100)),IF(AND(I83=0,I84=1),(H93*H87*I42/((1+I23/100)*(1+I41/100)))*(1-ABS(I87-H87*I42/((1+I23/100)*(1+I41/100)))/((I38*H87*H94*I42/((1+I23/100)*(1+I41/100)))+(H93*H87*I42/((1+I23/100)*(1+I41/100))))),0))) -> 2.0215848 | J90: =IF(J87=0,0,IF(J83=1,(1-I94)*I87*J42/((1+J23/100)*(1+J41/100)),IF(AND(J83=0,J84=1),(I93*I87*J42/((1+J23/100)*(1+J41/100)))*(1-ABS(J87-I87*J42/((1+J23/100)*(1+J41/100)))/((J38*I87*I94*J42/((1+J23/100)*(1+J41/100)))+(I93*I87*J42/((1+J23/100)*(1+J41/100))))),0))) -> 1.2686435 | K90: =IF(K87=0,0,IF(K83=1,(1-J94)*J87*K42/((1+K23/100)*(1+K41/100)),IF(AND(K83=0,K84=1),(J93*J87*K42/((1+K23/100)*(1+K41/100)))*(1-ABS(K87-J87*K42/((1+K23/100)*(1+K41/100)))/((K38*J87*J94*K42/((1+K23/100)*(1+K41/100)))+(J93*J87*K42/((1+K23/100)*(1+K41/100))))),0))) -> 0.7296831 | L90: =IF(L87=0,0,IF(L83=1,(1-K94)*K87*L42/((1+L23/100)*(1+L41/100)),IF(AND(L83=0,L84=1),(K93*K87*L42/((1+L23/100)*(1+L41/100)))*(1-ABS(L87-K87*L42/((1+L23/100)*(1+L41/100)))/((L38*K87*K94*L42/((1+L23/100)*(1+L41/100)))+(K93*K87*L42/((1+L23/100)*(1+L41/100))))),0))) -> 0.35501429 | ... W90: =IF(W87=0,0,IF(W83=1,(1-V94)*V87*W42/((1+W23/100)*(1+W41/100)),IF(AND(W83=0,W84=1),(V93*V87*W42/((1+W23/100)*(1+W41/100)))*(1-ABS(W87-V87*W42/((1+W23/100)*(1+W41/100)))/((W38*V87*V94*W42/((1+W23/100)*(1+W41/100)))+(V93*V87*W42/((1+W23/100)*(1+W41/100))))),0))) -> 7.3059035e-05
B91: New long-term debt | D91: ='Input data'!C69*$D$87 -> 0 | E91: =IF(E87=0,0,IF(E83=1,'Input data'!$C$58*(E87-D87*E42/((1+E23/100)*(1+E41/100))),0)) -> 0 | F91: =IF(F87=0,0,IF(F83=1,'Input data'!$C$58*(F87-E87*F42/((1+F23/100)*(1+F41/100))),0)) -> 0.33425532 | G91: =IF(G87=0,0,IF(G83=1,'Input data'!$C$58*(G87-F87*G42/((1+G23/100)*(1+G41/100))),0)) -> 0.81776768 | H91: =IF(H87=0,0,IF(H83=1,'Input data'!$C$58*(H87-G87*H42/((1+H23/100)*(1+H41/100))),0)) -> 0 | I91: =IF(I87=0,0,IF(I83=1,'Input data'!$C$58*(I87-H87*I42/((1+I23/100)*(1+I41/100))),0)) -> 0 | J91: =IF(J87=0,0,IF(J83=1,'Input data'!$C$58*(J87-I87*J42/((1+J23/100)*(1+J41/100))),0)) -> 0 | K91: =IF(K87=0,0,IF(K83=1,'Input data'!$C$58*(K87-J87*K42/((1+K23/100)*(1+K41/100))),0)) -> 0 | L91: =IF(L87=0,0,IF(L83=1,'Input data'!$C$58*(L87-K87*L42/((1+L23/100)*(1+L41/100))),0)) -> 0 | ... W91: =IF(W87=0,0,IF(W83=1,'Input data'!$C$58*(W87-V87*W42/((1+W23/100)*(1+W41/100))),0)) -> 0
B92: New short-term debt | D92: ='Input data'!C70*$D$87 -> 0 | E92: =IF(E87=0,0,IF(E83=1,'Input data'!$C$57*(E87-D87*E42/((1+E23/100)*(1+E41/100))),0)) -> 0 | F92: =IF(F87=0,0,IF(F83=1,'Input data'!$C$57*(F87-E87*F42/((1+F23/100)*(1+F41/100))),0)) -> 0.045368027 | G92: =IF(G87=0,0,IF(G83=1,'Input data'!$C$57*(G87-F87*G42/((1+G23/100)*(1+G41/100))),0)) -> 0.11099451 | H92: =IF(H87=0,0,IF(H83=1,'Input data'!$C$57*(H87-G87*H42/((1+H23/100)*(1+H41/100))),0)) -> 0 | I92: =IF(I87=0,0,IF(I83=1,'Input data'!$C$57*(I87-H87*I42/((1+I23/100)*(1+I41/100))),0)) -> 0 | J92: =IF(J87=0,0,IF(J83=1,'Input data'!$C$57*(J87-I87*J42/((1+J23/100)*(1+J41/100))),0)) -> 0 | K92: =IF(K87=0,0,IF(K83=1,'Input data'!$C$57*(K87-J87*K42/((1+K23/100)*(1+K41/100))),0)) -> 0 | L92: =IF(L87=0,0,IF(L83=1,'Input data'!$C$57*(L87-K87*L42/((1+L23/100)*(1+L41/100))),0)) -> 0 | ... W92: =IF(W87=0,0,IF(W83=1,'Input data'!$C$57*(W87-V87*W42/((1+W23/100)*(1+W41/100))),0)) -> 0
B93: Share of short-term debt in total government debt | D93: =1-D94 -> 0.10516645 | E93: =IF(E87<>0,(E90+E92)/(E88+E89+E90+E91+E92),0) -> 0.093907036 | F93: =IF(F87<>0,(F90+F92)/(F88+F89+F90+F91+F92),0) -> 0.094135772 | G93: =IF(G87<>0,(G90+G92)/(G88+G89+G90+G91+G92),0) -> 0.094707027 | H93: =IF(H87<>0,(H90+H92)/(H88+H89+H90+H91+H92),0) -> 0.078346511 | I93: =IF(I87<>0,(I90+I92)/(I88+I89+I90+I91+I92),0) -> 0.058994646 | J93: =IF(J87<>0,(J90+J92)/(J88+J89+J90+J91+J92),0) -> 0.040914519 | K93: =IF(K87<>0,(K90+K92)/(K88+K89+K90+K91+K92),0) -> 0.026002264 | L93: =IF(L87<>0,(L90+L92)/(L88+L89+L90+L91+L92),0) -> 0.013990527 | ... W93: =IF(W87<>0,(W90+W92)/(W88+W89+W90+W91+W92),0) -> 7.4410004e-06
B94: Share of long-term debt in total government debt | D94: =(D88+D89+D91)/D87 -> 0.89483355 | E94: =IF(E87<>0,(E88+E89+E91)/(E88+E89+E90+E91+E92),1) -> 0.90609296 | F94: =IF(F87<>0,(F88+F89+F91)/(F88+F89+F90+F91+F92),1) -> 0.90586423 | G94: =IF(G87<>0,(G88+G89+G91)/(G88+G89+G90+G91+G92),1) -> 0.90529297 | H94: =IF(H87<>0,(H88+H89+H91)/(H88+H89+H90+H91+H92),1) -> 0.92165349 | I94: =IF(I87<>0,(I88+I89+I91)/(I88+I89+I90+I91+I92),1) -> 0.94100535 | J94: =IF(J87<>0,(J88+J89+J91)/(J88+J89+J90+J91+J92),1) -> 0.95908548 | K94: =IF(K87<>0,(K88+K89+K91)/(K88+K89+K90+K91+K92),1) -> 0.97399774 | L94: =IF(L87<>0,(L88+L89+L91)/(L88+L89+L90+L91+L92),1) -> 0.98600947 | ... W94: =IF(W87<>0,(W88+W89+W91)/(W88+W89+W90+W91+W92),1) -> 0.99999256
B96: IIR | C96: =C35 -> 1.510173 | D96: =D35 -> 1.408838 | E96: =E98+E99 -> 1.550894 | F96: =F98+F99 -> 1.641526 | G96: =G98+G99 -> 1.684386 | H96: =H98+H99 -> 1.7995764 | I96: =I98+I99 -> 1.8573201 | J96: =J98+J99 -> 1.8994082 | K96: =K98+K99 -> 1.9496329 | L96: =L98+L99 -> 2.0061124 | ... W96: =W98+W99 -> 2.6116148
B97: Long-term implicit interest rate | E97: =((E35*D87)-(E37*D90+D92))/(D88+D89+D91) -> 1.3300501 | F97: =((F35*E87)-(F37*E90+E92))/(E88+E89+E91) -> 1.4422602 | G97: =((G35*F87)-(G37*F90+F92))/(F88+F89+F91) -> 1.5688928 | H97: =IF(G87>0,(G97*G88+H36*(G91+G89))/(G88+G89+G91),H36) -> 1.6943849 | I97: =IF(H87>0,(H97*H88+I36*(H91+H89))/(H88+H89+H91),I36) -> 1.7777129 | J97: =IF(I87>0,(I97*I88+J36*(I91+I89))/(I88+I89+I91),J36) -> 1.8440433 | K97: =IF(J87>0,(J97*J88+K36*(J91+J89))/(J88+J89+J91),K36) -> 1.9145835 | L97: =IF(K87>0,(K97*K88+L36*(K91+K89))/(K88+K89+K91),L36) -> 1.9859877 | M97: =IF(L87>0,(L97*L88+M36*(L91+L89))/(L88+L89+L91),M36) -> 2.0442467 | N97: =IF(M87>0,(M97*M88+N36*(M91+M89))/(M88+M89+M91),N36) -> 2.1232808 | O97: =IF(N87>0,(N97*N88+O36*(N91+N89))/(N88+N89+N91),O36) -> 2.2093159 | ... W97: =IF(V87>0,(V97*V88+W36*(V91+V89))/(V88+V89+V91),W36) -> 2.6116166
B98: Nominal implicit interest rate on debt (Excel approximation) | E98: =E35 -> 1.550894 | F98: =F35 -> 1.641526 | G98: =G35 -> 1.684386 | H98: =(H97*(G88+G89+G91)+H37*(G90+G92))/G87 -> 1.7995764 | I98: =(I97*(H88+H89+H91)+I37*(H90+H92))/H87 -> 1.8573201 | J98: =(J97*(I88+I89+I91)+J37*(I90+I92))/I87 -> 1.8994082 | K98: =(K97*(J88+J89+J91)+K37*(J90+J92))/J87 -> 1.9496329 | L98: =(L97*(K88+K89+K91)+L37*(K90+K92))/K87 -> 2.0061124 | M98: =(M97*(L88+L89+L91)+M37*(L90+L92))/L87 -> 2.0541018 | N98: =(N97*(M88+M89+M91)+N37*(M90+M92))/M87 -> 2.1281077 | O98: =(O97*(N88+N89+N91)+O37*(N90+N92))/N87 -> 2.2116501 | ... W98: =(W97*(V88+V89+V91)+W37*(V90+V92))/V87 -> 2.6116148
B99: Diff. STATA | E99: =E108 -> 0 | F99: =F108 -> 0 | G99: =G108 -> 0 | H99: =H108 -> 0 | I99: =I108 -> 0 | J99: =J108 -> 0 | K99: =K108 -> 0 | L99: =L108 -> 0 | ... W99: =W108 -> 0
B101: (i - g) | C101: =((1+C96/100)/((1+C23/100)*(1+C41/100))-1)*100 -> -12.245307 | D101: =((1+D96/100)/((1+D23/100)*(1+D41/100))-1)*100 -> -13.055432 | E101: =((1+E96/100)/((1+E23/100)*(1+E41/100))-1)*100 -> 1.8855084 | F101: =((1+F96/100)/((1+F23/100)*(1+F41/100))-1)*100 -> -2.1266613 | G101: =((1+G96/100)/((1+G23/100)*(1+G41/100))-1)*100 -> -3.5011632 | H101: =((1+H96/100)/((1+H23/100)*(1+H41/100))-1)*100 -> -3.7948557 | I101: =((1+I96/100)/((1+I23/100)*(1+I41/100))-1)*100 -> -3.8672782 | J101: =((1+J96/100)/((1+J23/100)*(1+J41/100))-1)*100 -> -3.6935593 | ... W101: =((1+W96/100)/((1+W23/100)*(1+W41/100))-1)*100 -> -1.2758641
B104: Per memo - STATA results
B106: Debt | C106: 54.39847 | D106: 44.39178 | E106: 43.73044 | F106: 42.48884 | G106: 41.25082 | H106: 37.73192 | I106: 34.26601 | J106: 31.00544 | K106: 28.06013 | L106: 25.37282 | M106: 22.94909 | N106: 20.84328 | O106: 18.93877 | P106: 17.2331 | Q106: 15.70119 | R106: 14.35148 | S106: 13.18357 | T106: 12.11302 | U106: 11.18972 | V106: 10.42024 | W106: 9.814148
B107: IIR | C107: 1.510173 | D107: 1.408838 | E107: 1.550894 | F107: 1.641526 | G107: 1.684386 | H107: 1.797808 | I107: 1.855608 | J107: 1.897722 | K107: 1.947976 | L107: 2.004485 | M107: 2.052486 | N107: 2.126529 | O107: 2.210114 | P107: 2.296523 | Q107: 2.340338 | R107: 2.389095 | S107: 2.425899 | T107: 2.468319 | U107: 2.5096 | V107: 2.556067 | W107: 2.610176
B108: IIR difference STATA - Excel | D108: 0 | E108: 0 | F108: 0 | G108: 0 | H108: 0 | I108: 0 | J108: 0 | K108: 0 | L108: 0 | M108: 0 | N108: 0 | O108: 0 | P108: 0 | Q108: 0 | R108: 0 | S108: 0 | T108: 0 | U108: 0 | V108: 0 | W108: 0
B110: Share of long-term debt that matures every year | C110: 2021 | D110: 2022 | E110: 2023 | F110: 2024 | G110: 2025 | H110: 2026 | I110: 2027 | J110: 2028 | K110: 2029 | L110: 2030 | M110: 2031 | N110: 2032 | O110: 2033 | P110: 2034 | Q110: 2035 | R110: 2036 | S110: 2037 | T110: 2038 | U110: 2039 | V110: 2040 | W110: 2041
B111: CY | C111: 0.03801916 | D111: 0.07859744 | E111: 0.05947547 | F111: 0.09687696 | G111: 0.11684023 | H111: 0.13811532 | I111: 0.13659083 | J111: 0.14219136 | K111: 0.1389396 | L111: 0.12512538 | M111: 0.1284918 | N111: 0.07208514 | O111: 0.06868139 | P111: 0.0680495 | Q111: 0.06808078 | R111: 0.06766632 | S111: 0.06922052 | T111: 0.06662979 | U111: 0.06643431 | V111: 0.06639338 | W111: 0.06621254
B112: EL | C112: 0.03033705 | D112: 0.03594311 | E112: 0.04116618 | F112: 0.01594102 | G112: 0.01585014 | H112: 0.03752878 | I112: 0.03405028 | J112: 0.04734439 | K112: 0.04407593 | L112: 0.0508599 | M112: 0.06623794 | N112: 0.06025377 | O112: 0.09003059 | P112: 0.07295239 | Q112: 0.07736666 | R112: 0.09083936 | S112: 0.0996211 | T112: 0.10965455 | U112: 0.09865441 | V112: 0.10313576 | W112: 0.11073873
B113: IE | C113: 0.001 | D113: 0.07537306 | E113: 0.04688205 | F113: 0.05421672 | G113: 0.06734311 | H113: 0.07328111 | I113: 0.06373561 | J113: 0.07199902 | K113: 0.07792014 | L113: 0.07366593 | M113: 0.09283323 | N113: 0.09749916 | O113: 0.10431984 | P113: 0.07769295 | Q113: 0.08189674 | R113: 0.07226059 | S113: 0.07247516 | T113: 0.07270425 | U113: 0.07292216 | V113: 0.07311259 | W113: 0.07343585
B114: PT | C114: 0.08381841 | D114: 0.06939163 | E114: 0.04649241 | F114: 0.04919325 | G114: 0.05671274 | H114: 0.06401188 | I114: 0.0649313 | J114: 0.06391246 | K114: 0.06169361 | L114: 0.05442604 | M114: 0.08556656 | N114: 0.08165381 | O114: 0.07587859 | P114: 0.06135627 | Q114: 0.08179735 | R114: 0.08444232 | S114: 0.06027019 | T114: 0.07297076 | U114: 0.05731596 | V114: 0.06079668 | W114: 0.05729366

Sheet Adjustment scenario
B3: Country | C3: ='Input data'!C3 -> IE
B4: Key years
B5: ='Input data'!B5 -> Last year before the adjustment | C5: =+'Input data'!C5 -> 2024
B6: Last year of adjustment | C6: =+C5+'Criteria results'!$F$5 -> 2028
B7: Last year of no-fiscal-policy-change projections | C7: =C5+'Criteria results'!$F$5+10 -> 2038
B9: Key assumptions
C10: 2021 | D10: 2022 | E10: 2023 | F10: 2024 | G10: 2025 | H10: 2026 | I10: 2027 | J10: 2028 | K10: 2029 | L10: 2030 | M10: 2031 | N10: 2032 | O10: 2033 | P10: 2034 | Q10: 2035 | R10: 2036 | S10: 2037 | T10: 2038 | U10: 2039 | V10: 2040 | W10: 2041
B11: Fiscal assumptions (% of GDP)
B12: Structural primary balance ('+' means 'surplus') | C12: ='Input data'!C13 -> -3.165318 | D12: ='Input data'!D13 -> -2.376722 | E12: ='Input data'!E13 -> 1.712465 | F12: ='Input data'!F13 -> 2.528801 | G12: =IF(G10<=$C$6, IF(AND(F78<=-1.55,'Criteria results'!$F$5=4,'Criteria results'!$F$6<0.4),F12+0.4, IF(AND(F78<=-1.55,'Criteria results'!$F$5=7,'Criteria results'!$F$6<0.25),F12+0.25, F12+'Criteria results'!$F$6)),F12) -> 2.528801 | H12: =IF(H10<=$C$6, IF(AND(G78<=-1.55,'Criteria results'!$F$5=4,'Criteria results'!$F$6<0.4),G12+0.4, IF(AND(G78<=-1.55,'Criteria results'!$F$5=7,'Criteria results'!$F$6<0.25),G12+0.25, G12+'Criteria results'!$F$6)),G12) -> 2.528801 | I12: =IF(I10<=$C$6, IF(AND(H78<=-1.55,'Criteria results'!$F$5=4,'Criteria results'!$F$6<0.4),H12+0.4, IF(AND(H78<=-1.55,'Criteria results'!$F$5=7,'Criteria results'!$F$6<0.25),H12+0.25, H12+'Criteria results'!$F$6)),H12) -> 2.528801 | J12: =IF(J10<=$C$6, IF(AND(I78<=-1.55,'Criteria results'!$F$5=4,'Criteria results'!$F$6<0.4),I12+0.4, IF(AND(I78<=-1.55,'Criteria results'!$F$5=7,'Criteria results'!$F$6<0.25),I12+0.25, I12+'Criteria results'!$F$6)),I12) -> 2.528801 | K12: =IF(K10<=$C$6, IF(AND(J78<=-1.55,'Criteria results'!$F$5=4,'Criteria results'!$F$6<0.4),J12+0.4, IF(AND(J78<=-1.55,'Criteria results'!$F$5=7,'Criteria results'!$F$6<0.25),J12+0.25, J12+'Criteria results'!$F$6)),J12) -> 2.528801 | L12: =IF(L10<=$C$6, IF(AND(K78<=-1.55,'Criteria results'!$F$5=4,'Criteria results'!$F$6<0.4),K12+0.4, IF(AND(K78<=-1.55,'Criteria results'!$F$5=7,'Criteria results'!$F$6<0.25),K12+0.25, K12+'Criteria results'!$F$6)),K12) -> 2.528801 | M12: =IF(M10<=$C$6, IF(AND(L78<=-1.55,'Criteria results'!$F$5=4,'Criteria results'!$F$6<0.4),L12+0.4, IF(AND(L78<=-1.55,'Criteria results'!$F$5=7,'Criteria results'!$F$6<0.25),L12+0.25, L12+'Criteria results'!$F$6)),L12) -> 2.528801 | N12: =M12 -> 2.528801 | O12: =N12 -> 2.528801 | P12: =O12 -> 2.528801 | Q12: =P12 -> 2.528801 | R12: =Q12 -> 2.528801 | S12: =R12 -> 2.528801 | T12: =S12 -> 2.528801 | U12: =T12 -> 2.528801 | ... W12: =V12 -> 2.528801
B13: Annual change in SPB | G13: =G12-F12 -> 0 | H13: =H12-G12 -> 0 | I13: =I12-H12 -> 0 | J13: =J12-I12 -> 0 | K13: =K12-J12 -> 0 | L13: =L12-K12 -> 0 | M13: =M12-L12 -> 0 | N13: =N12-M12 -> 0 | ... W13: =W12-V12 -> 0
B14: One-off and other temporary measures | C14: ='Input data'!C14 -> 0 | D14: ='Input data'!D14 -> 0 | E14: ='Input data'!E14 -> 0 | F14: ='Input data'!F14 -> 0 | G14: ='Input data'!G14 -> 0 | H14: =0 -> 0 | I14: =0 -> 0 | J14: =0 -> 0 | K14: =0 -> 0 | L14: =0 -> 0 | M14: =0 -> 0 | N14: =0 -> 0 | O14: =0 -> 0 | ... W14: =0 -> 0
B15: Stock flow adjustments (without exchange rate effect) | C15: ='Input data'!C15 -> 2.690274 | D15: ='Input data'!D15 -> -0.5420614 | E15: ='Input data'!E15 -> 0.8428086 | F15: ='Input data'!F15 -> 1.636568 | G15: ='Input data'!G15 -> 2.20024 | H15: ='Input data'!H15 -> 0 | I15: ='Input data'!I15 -> 0 | J15: ='Input data'!J15 -> 0 | ... W15: ='Input data'!W15 -> 0
B17: ='Input data'!B19 -> Cost of ageing and selected public revenue (based on the Commission-Council 2024 Ageing Report ("AR 2024"))
B18: Total ageing cost (net of taxes on pensions) | C18: ='Input data'!C20 -> 0 | D18: ='Input data'!D20 -> 11.98063 | E18: ='Input data'!E20 -> 11.58823 | F18: ='Input data'!F20 -> 11.59789 | G18: ='Input data'!G20 -> 11.65158 | H18: ='Input data'!H20 -> 11.82718 | I18: ='Input data'!I20 -> 12.01015 | J18: ='Input data'!J20 -> 12.14108 | ... W18: ='Input data'!W20 -> 13.69105
B19: Property income | C19: ='Input data'!C26 -> 0.1107195 | D19: ='Input data'!D26 -> 0.132752 | E19: ='Input data'!E26 -> 0.1349502 | F19: ='Input data'!F26 -> 0.1371484 | G19: ='Input data'!G26 -> 0.1393466 | H19: ='Input data'!H26 -> 0.1415448 | I19: ='Input data'!I26 -> 0.143743 | J19: ='Input data'!J26 -> 0.1459412 | ... W19: ='Input data'!W26 -> 0.1745179
B21: GDP growth assumptions
B22: Actual GDP (real)
B23: Level | C23: ='Input data'!C31 -> 410.9464 | D23: ='Baseline NFPC'!D22 -> 449.71106 | E23: ='Baseline NFPC'!E22 -> 435.32576 | F23: ='Baseline NFPC'!F22 -> 440.73992 | G23: =IF(AND(G50>1,F50>1),IF(AND(G50>0,F50>0),G27*(G51/100+1),0)+IF(G50>0,F23*(1+G52/100),0)-F23*(1+'Input data'!G30/100),IF(G50=1,G27,F23*(1+G52/100))) -> 455.69777 | H23: =IF(AND(H50>1,G50>1),IF(AND(H50>0,G50>0),H27*(H51/100+1),0)+IF(H50>0,G23*(1+H52/100),0)-G23*(1+'Input data'!H30/100),IF(H50=1,H27,G23*(1+H52/100))) -> 472.76873 | I23: =IF(AND(I50>1,H50>1),IF(AND(I50>0,H50>0),I27*(I51/100+1),0)+IF(I50>0,H23*(1+I52/100),0)-H23*(1+'Input data'!I30/100),IF(I50=1,I27,H23*(1+I52/100))) -> 490.74514 | J23: =IF(AND(J50>1,I50>1),IF(AND(J50>0,I50>0),J27*(J51/100+1),0)+IF(J50>0,I23*(1+J52/100),0)-I23*(1+'Input data'!J30/100),IF(J50=1,J27,I23*(1+J52/100))) -> 508.30099 | K23: =IF(AND(K50>1,J50>1),IF(AND(K50>0,J50>0),K27*(K51/100+1),0)+IF(K50>0,J23*(1+K52/100),0)-J23*(1+'Input data'!K30/100),IF(K50=1,K27,J23*(1+K52/100))) -> 524.38467 | L23: =IF(AND(L50>1,K50>1),IF(AND(L50>0,K50>0),L27*(L51/100+1),0)+IF(L50>0,K23*(1+L52/100),0)-K23*(1+'Input data'!L30/100),IF(L50=1,L27,K23*(1+L52/100))) -> 539.79117 | M23: =IF(AND(M50>1,L50>1),IF(AND(M50>0,L50>0),M27*(M51/100+1),0)+IF(M50>0,L23*(1+M52/100),0)-L23*(1+'Input data'!M30/100),IF(M50=1,M27,L23*(1+M52/100))) -> 554.20041 | N23: =IF(AND(N50>1,M50>1),IF(AND(N50>0,M50>0),N27*(N51/100+1),0)+IF(N50>0,M23*(1+N52/100),0)-M23*(1+'Input data'!N30/100),IF(N50=1,N27,M23*(1+N52/100))) -> 567.27836 | ... W23: =IF(AND(W50>1,V50>1),IF(AND(W50>0,V50>0),W27*(W51/100+1),0)+IF(W50>0,V23*(1+W52/100),0)-V23*(1+'Input data'!W30/100),IF(W50=1,W27,V23*(1+W52/100))) -> 666.4502
B24: Growth rate | C24: =+'Input data'!C30 -> 15.12522 | D24: ='Baseline NFPC'!D23 -> 9.433022 | E24: ='Baseline NFPC'!E23 -> -3.198788 | F24: ='Baseline NFPC'!F23 -> 1.243702 | G24: =100*(G23/F23-1) -> 3.393806 | H24: =100*(H23/G23-1) -> 3.746114 | I24: =100*(I23/H23-1) -> 3.802369 | J24: =100*(J23/I23-1) -> 3.577386 | K24: =100*(K23/J23-1) -> 3.164204 | L24: =100*(L23/K23-1) -> 2.938014 | M24: =100*(M23/L23-1) -> 2.669411 | N24: =100*(N23/M23-1) -> 2.359786 | ... W24: =100*(W23/V23-1) -> 1.571112
B26: Potential GDP (real)
B27: Level | C27: ='Input data'!C34 -> 392.8036 | D27: =+C27*(1+'Input data'!D33/100) -> 412.27894 | E27: =+D27*(1+'Input data'!E33/100) -> 430.14515 | F27: =+E27*(1+'Input data'!F33/100) -> 445.69744 | G27: =+F27*(1+'Input data'!G33/100) -> 460.34222 | H27: =+G27*(1+'Input data'!H33/100) -> 475.97012 | I27: =+H27*(1+'Input data'!I33/100) -> 491.84786 | J27: =+I27*(1+'Input data'!J33/100) -> 508.30096 | K27: =+J27*(1+'Input data'!K33/100) -> 524.38464 | ... W27: =+V27*(1+'Input data'!W33/100) -> 666.45005
B29: Output gap
B30: Output gap | C30: =100*(C23/C27-1) -> 4.6187968 | D30: =100*(D23/D27-1) -> 9.07932 | E30: =100*(E23/E27-1) -> 1.2043874 | F30: =100*(F23/F27-1) -> -1.1123062 | G30: =100*(G23/G27-1) -> -1.0089108 | H30: =100*(H23/H27-1) -> -0.67260192 | I30: =100*(I23/I27-1) -> -0.22419779 | J30: =100*(J23/J27-1) -> 6.5725915e-06 | ... W30: =100*(W23/W27-1) -> 2.2288956e-05
B32: Actual GDP (nominal, national currency)
B33: Growth rate | C33: =100*((1+C24/100)*(1+C42/100)-1) -> 15.674923 | D33: =100*((1+D24/100)*(1+D42/100)-1) -> 16.636198 | E33: =100*((1+E24/100)*(1+E42/100)-1) -> -0.32842201 | F33: =100*((1+F24/100)*(1+F42/100)-1) -> 3.8500652 | G33: =100*((1+G24/100)*(1+G42/100)-1) -> 5.3736909 | H33: =100*((1+H24/100)*(1+H42/100)-1) -> 5.8151071 | I33: =100*((1+I24/100)*(1+I42/100)-1) -> 5.9548904 | J33: =100*((1+J24/100)*(1+J42/100)-1) -> 5.8074699 | ... W33: =100*((1+W24/100)*(1+W42/100)-1) -> 3.9377189
B35: Interest rates
B36: Nominal implicit interest rate on debt | C36: ='Input data'!C37 -> 1.510173 | D36: ='Input data'!D37 -> 1.408838 | E36: ='Input data'!E37 -> 1.550894 | F36: ='Input data'!F37 -> 1.641526 | G36: ='Input data'!G37 -> 1.684386 | H36: =H99 -> 1.7963363 | I36: =I99 -> 1.8477296 | J36: =J99 -> 1.8765133 | K36: =K99 -> 1.9046582 | L36: =L99 -> 1.9309319 | M36: =M99 -> 1.9360734 | N36: =N99 -> 1.9574641 | O36: =O99 -> 1.9793499 | ... W36: =W99 -> 1.9944068
B37: Long-term interest rate | D37: ='Input data'!D$39 -> 1.75 | E37: ='Input data'!E$39 -> 2.87 | F37: ='Input data'!F$39 -> 2.837221 | G37: ='Input data'!G$39 -> 2.903685 | H37: =G37+($O$37-$G$37)/($O$10-$G$10) -> 2.9987319 | I37: =H37+($O$37-$G$37)/($O$10-$G$10) -> 3.0937787 | J37: =I37+($O$37-$G$37)/($O$10-$G$10) -> 3.1888256 | K37: =J37+($O$37-$G$37)/($O$10-$G$10) -> 3.2838725 | L37: =K37+($O$37-$G$37)/($O$10-$G$10) -> 3.3789194 | M37: =L37+($O$37-$G$37)/($O$10-$G$10) -> 3.4739662 | N37: =M37+($O$37-$G$37)/($O$10-$G$10) -> 3.5690131 | O37: ='Input data'!$C$52 -> 3.66406 | P37: ='Baseline NFPC'!P36 -> 3.680857 | Q37: ='Baseline NFPC'!Q36 -> 3.697654 | R37: ='Baseline NFPC'!R36 -> 3.714451 | S37: ='Baseline NFPC'!S36 -> 3.731248 | T37: ='Baseline NFPC'!T36 -> 3.748045 | U37: ='Baseline NFPC'!U36 -> 3.764842 | V37: ='Baseline NFPC'!V36 -> 3.781639 | W37: ='Baseline NFPC'!W36 -> 3.798436
B38: Short-term interest rate | D38: ='Input data'!D$38 -> 0.35 | E38: ='Input data'!E$38 -> 3.43 | F38: ='Input data'!F$38 -> 3.564208 | G38: ='Input data'!G$38 -> 2.816375 | H38: =G38+($O$38-$G$38)/($O$10-$G$10) -> 2.8050894 | I38: =H38+($O$38-$G$38)/($O$10-$G$10) -> 2.7938037 | J38: =I38+($O$38-$G$38)/($O$10-$G$10) -> 2.7825181 | K38: =J38+($O$38-$G$38)/($O$10-$G$10) -> 2.7712325 | L38: =K38+($O$38-$G$38)/($O$10-$G$10) -> 2.7599469 | M38: =L38+($O$38-$G$38)/($O$10-$G$10) -> 2.7486612 | N38: =M38+($O$38-$G$38)/($O$10-$G$10) -> 2.7373756 | O38: ='Input data'!$C$53 -> 2.72609 | P38: ='Baseline NFPC'!P37 -> 2.6897855 | Q38: ='Baseline NFPC'!Q37 -> 2.653481 | R38: ='Baseline NFPC'!R37 -> 2.6171765 | S38: ='Baseline NFPC'!S37 -> 2.580872 | T38: ='Baseline NFPC'!T37 -> 2.5445675 | U38: ='Baseline NFPC'!U37 -> 2.508263 | V38: ='Baseline NFPC'!V37 -> 2.4719585 | W38: ='Baseline NFPC'!W37 -> 2.435654
B39: Share of long-term debt that matures every year | C39: ='Baseline NFPC'!C38 -> 0.001 | D39: ='Baseline NFPC'!D38 -> 0.07537306 | E39: ='Baseline NFPC'!E38 -> 0.04688205 | F39: ='Baseline NFPC'!F38 -> 0.05421672 | G39: ='Baseline NFPC'!G38 -> 0.06734311 | H39: ='Baseline NFPC'!H38 -> 0.07328111 | I39: ='Baseline NFPC'!I38 -> 0.06373561 | J39: ='Baseline NFPC'!J38 -> 0.07199902 | ... W39: ='Baseline NFPC'!W38 -> 0.07343585
B41: Inflation and exchange rate
B42: GDP deflator (National currency) | C42: ='Input data'!C42 -> 0.4774826 | D42: ='Input data'!D42 -> 6.582269 | E42: ='Input data'!E42 -> 2.965217 | F42: ='Input data'!F42 -> 2.574346 | G42: ='Input data'!G42 -> 1.914897 | H42: ='Baseline NFPC'!H41 -> 1.9942849 | I42: ='Baseline NFPC'!I41 -> 2.0736728 | J42: ='Baseline NFPC'!J41 -> 2.1530606 | K42: ='Baseline NFPC'!K41 -> 2.2324485 | L42: ='Baseline NFPC'!L41 -> 2.3118364 | M42: ='Baseline NFPC'!M41 -> 2.3912243 | N42: ='Baseline NFPC'!N41 -> 2.4706121 | O42: ='Baseline NFPC'!O41 -> 2.55 | ... W42: ='Baseline NFPC'!W41 -> 2.33
B43: Exchange rate composite change (weighted by share of debt in each currency) | C43: ='Baseline NFPC'!C42 -> 1 | D43: ='Baseline NFPC'!D42 -> 1 | E43: ='Baseline NFPC'!E42 -> 0.9999999 | F43: ='Baseline NFPC'!F42 -> 1 | G43: ='Baseline NFPC'!G42 -> 1 | H43: ='Baseline NFPC'!H42 -> 1 | I43: ='Baseline NFPC'!I42 -> 1 | J43: ='Baseline NFPC'!J42 -> 1 | ... W43: ='Baseline NFPC'!W42 -> 1
B45: Intermediate calculations (growth rate equation)
B47: Fiscal multiplier | C47: ='Input data'!C49 -> 0.75
B48: Budget balance semi-elasticity | C48: ='Input data'!C50 -> 0.522
B50: Auxiliary variable to control the closure of the output gap | C50: 0 | D50: =IF(AND(ABS((D12-C12)-('Input data'!D13-'Input data'!C13))>0.0001,ABS(D12-C12)>0.0001,D$10>$C$5),4,IF(C50=4,3,IF(C50=3,2,IF(C50=2,1,0)))) -> 0 | E50: =IF(AND(ABS((E12-D12)-('Input data'!E13-'Input data'!D13))>0.0001,ABS(E12-D12)>0.0001,E$10>$C$5),4,IF(D50=4,3,IF(D50=3,2,IF(D50=2,1,0)))) -> 0 | F50: =IF(AND(ABS((F12-E12)-('Input data'!F13-'Input data'!E13))>0.0001,ABS(F12-E12)>0.0001,F$10>$C$5),4,IF(E50=4,3,IF(E50=3,2,IF(E50=2,1,0)))) -> 0 | G50: =IF(AND(ABS((G12-F12)-('Input data'!G13-'Input data'!F13))>0.0001,ABS(G12-F12)>0.0001,G$10>$C$5),4,IF(F50=4,3,IF(F50=3,2,IF(F50=2,1,0)))) -> 0 | H50: =IF(AND(ABS((H12-G12)-('Input data'!H13-'Input data'!G13))>0.0001,ABS(H12-G12)>0.0001,H$10>$C$5),4,IF(G50=4,3,IF(G50=3,2,IF(G50=2,1,0)))) -> 0 | I50: =IF(AND(ABS((I12-H12)-('Input data'!I13-'Input data'!H13))>0.0001,ABS(I12-H12)>0.0001,I$10>$C$5),4,IF(H50=4,3,IF(H50=3,2,IF(H50=2,1,0)))) -> 0 | J50: =IF(AND(ABS((J12-I12)-('Input data'!J13-'Input data'!I13))>0.0001,ABS(J12-I12)>0.0001,J$10>$C$5),4,IF(I50=4,3,IF(I50=3,2,IF(I50=2,1,0)))) -> 0 | K50: =IF(AND(ABS((K12-J12)-('Input data'!K13-'Input data'!J13))>0.0001,ABS(K12-J12)>0.0001,K$10>$C$5),4,IF(J50=4,3,IF(J50=3,2,IF(J50=2,1,0)))) -> 0 | ... W50: =IF(AND(ABS((W12-V12)-('Input data'!W13-'Input data'!V13))>0.0001,ABS(W12-V12)>0.0001,W$10>$C$5),4,IF(V50=4,3,IF(V50=3,2,IF(V50=2,1,0)))) -> 0
B51: OG intermediate auxiliary value | C51: 0 | D51: =IF(C50=4,2/3*C30,IF(C50=3,1/3*B30,0)) -> 0 | E51: =IF(D50=4,2/3*D30,IF(D50=3,1/3*C30,0)) -> 0 | F51: =IF(E50=4,2/3*E30,IF(E50=3,1/3*D30,0)) -> 0 | G51: =IF(F50=4,2/3*F30,IF(F50=3,1/3*E30,0)) -> 0 | H51: =IF(G50=4,2/3*G30,IF(G50=3,1/3*F30,0)) -> 0 | I51: =IF(H50=4,2/3*H30,IF(H50=3,1/3*G30,0)) -> 0 | J51: =IF(I50=4,2/3*I30,IF(I50=3,1/3*H30,0)) -> 0 | K51: =IF(J50=4,2/3*J30,IF(J50=3,1/3*I30,0)) -> 0 | ... W51: =IF(V50=4,2/3*V30,IF(V50=3,1/3*U30,0)) -> 0
B52: GDP intermediate growth rate - only feedback effect and no closure of the OG | D52: ='Input data'!D30-$C$47*((D12-C12)-('Input data'!D13-'Input data'!C13)) -> 9.433022 | E52: ='Input data'!E30-$C$47*((E12-D12)-('Input data'!E13-'Input data'!D13)) -> -3.198788 | F52: ='Input data'!F30-$C$47*((F12-E12)-('Input data'!F13-'Input data'!E13)) -> 1.243702 | G52: ='Input data'!G30-$C$47*((G12-F12)) -> 3.393806 | H52: ='Input data'!H30-$C$47*((H12-G12)) -> 3.746114 | I52: ='Input data'!I30-$C$47*((I12-H12)) -> 3.802369 | J52: ='Input data'!J30-$C$47*((J12-I12)) -> 3.577386 | K52: ='Input data'!K30-$C$47*((K12-J12)) -> 3.164204 | L52: ='Input data'!L30-$C$47*((L12-K12)) -> 2.938014 | M52: ='Input data'!M30-$C$47*((M12-L12)) -> 2.669411 | N52: ='Input data'!N30-$C$47*((N12-M12)) -> 2.359786 | ... W52: ='Input data'!W30-$C$47*((W12-V12)) -> 1.571112
B54: Debt projections
C56: 2021 | D56: 2022 | E56: 2023 | F56: 2024 | G56: 2025 | H56: 2026 | I56: 2027 | J56: 2028 | K56: 2029 | L56: 2030 | M56: 2031 | N56: 2032 | O56: 2033 | P56: 2034 | Q56: 2035 | R56: 2036 | S56: 2037 | T56: 2038 | U56: 2039 | V56: 2040 | W56: 2041
B57: Gross debt | C57: =+'Input data'!C12 -> 54.39847 | D57: =+C57+D58 -> 44.391772 | E57: =+D57+E58 -> 43.730434 | F57: =+E57+F58 -> 42.488825 | G57: =+F57+G58 -> 41.199314 | H57: =+G57+H58 -> 37.456895 | I57: =+H57+I58 -> 33.593172 | J57: =+I57+J58 -> 29.816315 | K57: =+J57+K58 -> 26.364043 | ... W57: =+V57+W58 -> 2.2971951
B58: Change in debt (-1+2+3) | D58: =-D59+D67+D72 -> -10.006698 | E58: =-E59+E67+E72 -> -0.66133783 | F58: =-F59+F67+F72 -> -1.2416084 | G58: =-G59+G67+G72 -> -1.2895116 | H58: =-H59+H67+H72 -> -3.7424189 | I58: =-I59+I67+I72 -> -3.8637225 | J58: =-J59+J67+J72 -> -3.7768572 | K58: =-K59+K67+K72 -> -3.4522727 | ... W58: =-W59+W67+W72 -> -1.0703826
B59: (1) Primary balance (1.1 + 1.2 - 1.3 -1.4 -1.5 - 1.6 -1.7) | D59: =D60+D61-D62-D63-D64-D65-D66 -> 2.3626831 | E59: =E60+E61-E62-E63-E64-E65-E66 -> 2.3411552 | F59: =F60+F61-F62-F63-F64-F65-F66 -> 1.9481772 | G59: =G60+G61-G62-G63-G64-G65-G66 -> 2.0021496 | H59: =H60+H61-H62-H63-H64-H65-H66 -> 2.1777028 | I59: =I60+I61-I62-I63-I64-I65-I66 -> 2.4117698 | J59: =J60+J61-J62-J63-J64-J65-J66 -> 2.5288044 | K59: =K60+K61-K62-K63-K64-K65-K66 -> 2.4450921 | ... W59: =W60+W61-W62-W63-W64-W65-W66 -> 1.0074193
B60: (1.1) Structural primary balance (before ageing cost) | D60: =D12 -> -2.376722 | E60: =E12 -> 1.712465 | F60: =F12 -> 2.528801 | G60: =IF(G12="",F60,G12) -> 2.528801 | H60: =IF(H12="",G60,H12) -> 2.528801 | I60: =IF(I12="",H60,I12) -> 2.528801 | J60: =IF(J12="",I60,J12) -> 2.528801 | K60: =IF(K12="",J60,K12) -> 2.528801 | L60: =IF(L12="",K60,L12) -> 2.528801 | M60: =IF(M12="",L60,M12) -> 2.528801 | N60: =IF(N12="",M60,N12) -> 2.528801 | ... W60: =IF(W12="",V60,W12) -> 2.528801
B61: (1.2) Cumulated budgetary effort (in terms of primary balance) | D61: 0 | E61: 0 | F61: 0 | G61: 0 | H61: 0 | I61: 0 | J61: 0 | K61: 0 | L61: 0 | M61: 0 | N61: 0 | O61: 0 | P61: 0 | Q61: 0 | R61: 0 | S61: 0 | T61: 0 | U61: 0 | V61: 0 | W61: 0
B62: (1.3) Cyclical component | D62: =-$C$48*D30 -> -4.7394051 | E62: =-$C$48*E30 -> -0.62869023 | F62: =-$C$48*F30 -> 0.58062382 | G62: =-$C$48*G30 -> 0.52665142 | H62: =-$C$48*H30 -> 0.3510982 | I62: =-$C$48*I30 -> 0.11703124 | J62: =-$C$48*J30 -> -3.4308927e-06 | K62: =-$C$48*K30 -> -2.9249033e-06 | ... W62: =-$C$48*W30 -> -1.1634835e-05
B63: (1.4) One-off and other temporary measures | D63: =-D14 -> 0 | E63: =-E14 -> 0 | F63: =-F14 -> 0 | G63: =-G14 -> 0 | H63: =-H14 -> 0 | I63: =-I14 -> 0 | J63: =-J14 -> 0 | K63: =-K14 -> 0 | ... W63: =-W14 -> 0
B64: (1.5) Cost of ageing | D64: =IF(D$56<=$C$6,0,HLOOKUP(D$56,'Input data'!$C$9:$BB$26,12,FALSE)-HLOOKUP($C$6,'Input data'!$C$9:$BB$26,12,FALSE)) -> 0 | E64: =IF(E$56<=$C$6,0,HLOOKUP(E$56,'Input data'!$C$9:$BB$26,12,FALSE)-HLOOKUP($C$6,'Input data'!$C$9:$BB$26,12,FALSE)) -> 0 | F64: =IF(F$56<=$C$6,0,HLOOKUP(F$56,'Input data'!$C$9:$BB$26,12,FALSE)-HLOOKUP($C$6,'Input data'!$C$9:$BB$26,12,FALSE)) -> 0 | G64: =IF(G$56<=$C$6,0,HLOOKUP(G$56,'Input data'!$C$9:$BB$26,12,FALSE)-HLOOKUP($C$6,'Input data'!$C$9:$BB$26,12,FALSE)) -> 0 | H64: =IF(H$56<=$C$6,0,HLOOKUP(H$56,'Input data'!$C$9:$BB$26,12,FALSE)-HLOOKUP($C$6,'Input data'!$C$9:$BB$26,12,FALSE)) -> 0 | I64: =IF(I$56<=$C$6,0,HLOOKUP(I$56,'Input data'!$C$9:$BB$26,12,FALSE)-HLOOKUP($C$6,'Input data'!$C$9:$BB$26,12,FALSE)) -> 0 | J64: =IF(J$56<=$C$6,0,HLOOKUP(J$56,'Input data'!$C$9:$BB$26,12,FALSE)-HLOOKUP($C$6,'Input data'!$C$9:$BB$26,12,FALSE)) -> 0 | K64: =IF(K$56<=$C$6,0,HLOOKUP(K$56,'Input data'!$C$9:$BB$26,12,FALSE)-HLOOKUP($C$6,'Input data'!$C$9:$BB$26,12,FALSE)) -> 0.08591 | ... W64: =IF(W$56<=$C$6,0,HLOOKUP(W$56,'Input data'!$C$9:$BB$26,12,FALSE)-HLOOKUP($C$6,'Input data'!$C$9:$BB$26,12,FALSE)) -> 1.54997
B65: (1.6) Property incomes | D65: =IF(D$56<=$C$5,0,-HLOOKUP(D$56,'Input data'!$C$9:$BB$26,18,FALSE)+HLOOKUP($C$6,'Input data'!$C$9:$BB$26,18,FALSE)) -> 0 | E65: =IF(E$56<=$C$5,0,-HLOOKUP(E$56,'Input data'!$C$9:$BB$26,18,FALSE)+HLOOKUP($C$6,'Input data'!$C$9:$BB$26,18,FALSE)) -> 0 | F65: =IF(F$56<=$C$5,0,-HLOOKUP(F$56,'Input data'!$C$9:$BB$26,18,FALSE)+HLOOKUP($C$6,'Input data'!$C$9:$BB$26,18,FALSE)) -> 0 | G65: =IF(G$56<=$C$6,0,-HLOOKUP(G$56,'Input data'!$C$9:$BB$26,18,FALSE)+HLOOKUP($C$6,'Input data'!$C$9:$BB$26,18,FALSE)) -> 0 | H65: =IF(H$56<=$C$6,0,-HLOOKUP(H$56,'Input data'!$C$9:$BB$26,18,FALSE)+HLOOKUP($C$6,'Input data'!$C$9:$BB$26,18,FALSE)) -> 0 | I65: =IF(I$56<=$C$6,0,-HLOOKUP(I$56,'Input data'!$C$9:$BB$26,18,FALSE)+HLOOKUP($C$6,'Input data'!$C$9:$BB$26,18,FALSE)) -> 0 | J65: =IF(J$56<=$C$6,0,-HLOOKUP(J$56,'Input data'!$C$9:$BB$26,18,FALSE)+HLOOKUP($C$6,'Input data'!$C$9:$BB$26,18,FALSE)) -> 0 | K65: =IF(K$56<=$C$6,0,-HLOOKUP(K$56,'Input data'!$C$9:$BB$26,18,FALSE)+HLOOKUP($C$6,'Input data'!$C$9:$BB$26,18,FALSE)) -> -0.0021982 | L65: =IF(L$56<=$C$6,0,-HLOOKUP(L$56,'Input data'!$C$9:$BB$26,18,FALSE)+HLOOKUP($C$6,'Input data'!$C$9:$BB$26,18,FALSE)) -> -0.0043964 | M65: =IF(M$56<=$C$6,0,-HLOOKUP(M$56,'Input data'!$C$9:$BB$26,18,FALSE)+HLOOKUP($C$6,'Input data'!$C$9:$BB$26,18,FALSE)) -> -0.0065946 | N65: =IF(N$56<=$C$6,0,-HLOOKUP(N$56,'Input data'!$C$9:$BB$26,18,FALSE)+HLOOKUP($C$6,'Input data'!$C$9:$BB$26,18,FALSE)) -> -0.0087928 | ... W65: =IF(W$56<=$C$6,0,-HLOOKUP(W$56,'Input data'!$C$9:$BB$26,18,FALSE)+HLOOKUP($C$6,'Input data'!$C$9:$BB$26,18,FALSE)) -> -0.0285767
B66: (1.7) Revenues | D66: 0 | E66: 0 | F66: 0 | G66: 0 | H66: 0 | I66: 0 | J66: 0 | K66: 0 | L66: 0 | M66: 0 | N66: 0 | O66: 0 | P66: 0 | Q66: 0 | R66: 0 | S66: 0 | T66: 0 | U66: 0 | V66: 0 | W66: 0
B67: (2) Snowball effect (2.1 + 2.2 + 2.3) | D67: =SUM(D68:D71) -> -7.101956 | E67: =SUM(E68:E71) -> 0.8370108 | F67: =SUM(F68:F71) -> -0.9299982 | G67: =SUM(G68:G71) -> -1.487604 | H67: =SUM(H68:H71) -> -1.5647161 | I67: =SUM(I68:I71) -> -1.4519527 | J67: =SUM(J68:J71) -> -1.2480528 | K67: =SUM(K68:K71) -> -1.0071805 | ... W67: =SUM(W68:W71) -> -0.062963227
B68: (2.1) Interest expenditure | D68: =C57*D36/100*(1/(1+D33/100)) -> 0.65707416 | E68: =D57*E36/100*(1/(1+E33/100)) -> 0.69073786 | F68: =E57*F36/100*(1/(1+F33/100)) -> 0.6912335 | G68: =F57*G36/100*(1/(1+G33/100)) -> 0.67917885 | H68: =G57*H36/100*(1/(1+H33/100)) -> 0.69940695 | I68: =H57*I36/100*(1/(1+I33/100)) -> 0.6532045 | J68: =I57*J36/100*(1/(1+J33/100)) -> 0.59578056 | K68: =J57*K36/100*(1/(1+K33/100)) -> 0.53845974 | ... W68: =V57*W36/100*(1/(1+W33/100)) -> 0.064618696
B69: (2.2) Growth effect | D69: =-C57*(D24/100)*(1/(1+D33/100)) -> -4.3995087 | E69: =-D57*(E24/100)*(1/(1+E33/100)) -> 1.4246776 | F69: =-E57*(F24/100)*(1/(1+F33/100)) -> -0.52371299 | G69: =-F57*(G24/100)*(1/(1+G33/100)) -> -1.3684519 | H69: =-G57*(H24/100)*(1/(1+H33/100)) -> -1.4585566 | I69: =-H57*(I24/100)*(1/(1+I33/100)) -> -1.3442035 | J69: =-I57*(J24/100)*(1/(1+J33/100)) -> -1.1357964 | K69: =-J57*(K24/100)*(1/(1+K33/100)) -> -0.89454183 | ... W69: =-V57*(W24/100)*(1/(1+W33/100)) -> -0.050903961
B70: (2.3) Inflation effect | D70: =-C57*D42/100*(1/(1+D42/100)) -> -3.3595209 | E70: =-D57*E42/100*(1/(1+E42/100)) -> -1.2784049 | F70: =-E57*F42/100*(1/(1+F42/100)) -> -1.0975187 | G70: =-F57*G42/100*(1/(1+G42/100)) -> -0.79833004 | H70: =-G57*H42/100*(1/(1+H42/100)) -> -0.80556639 | I70: =-H57*I42/100*(1/(1+I42/100)) -> -0.76095373 | J70: =-I57*J42/100*(1/(1+J42/100)) -> -0.7080369 | K70: =-J57*K42/100*(1/(1+K42/100)) -> -0.65109844 | ... W70: =-V57*W42/100*(1/(1+W42/100)) -> -0.076677962
B71: (2.4) Exchange rate effect linked to the interest rate | D71: ='Baseline NFPC'!D70 -> -5.6246662e-07 | E71: ='Baseline NFPC'!E70 -> 2.0516894e-07 | F71: ='Baseline NFPC'!F70 -> 2.9725664e-08 | G71: ='Baseline NFPC'!G70 -> -8.8262773e-07 | H71: 0 | I71: 0 | J71: 0 | K71: 0 | L71: 0 | M71: 0 | N71: 0 | O71: 0 | P71: 0 | Q71: 0 | R71: 0 | S71: 0 | T71: 0 | U71: 0 | V71: 0 | W71: 0
B72: (3 ) Stock flow adjustments (3.1 + 3.2) | D72: ='Input data'!D16 -> -0.5420594 | E72: ='Input data'!E16 -> 0.8428066 | F72: ='Input data'!F16 -> 1.636567 | G72: ='Input data'!G16 -> 2.200242 | H72: ='Input data'!H16 -> 0 | I72: ='Input data'!I16 -> 0 | J72: ='Input data'!J16 -> 0 | K72: ='Input data'!K16 -> 0 | ... W72: ='Input data'!W16 -> 0
B73: (3.1) Base | D73: =D15 -> -0.5420614 | E73: =E15 -> 0.8428086 | F73: =F15 -> 1.636568 | G73: =G15 -> 2.20024 | H73: =H15 -> 0 | I73: =I15 -> 0 | J73: =J15 -> 0 | K73: =K15 -> 0 | ... W73: =W15 -> 0
B74: (3.2) Adjustment due to the exchange rate effect linked to debt value | D74: =+D72-D73 -> 2e-06 | E74: =+E72-E73 -> -2e-06 | F74: =+F72-F73 -> -1e-06 | G74: =+G72-G73 -> 2e-06 | H74: =+H72-H73 -> 0 | I74: =+I72-I73 -> 0 | J74: =+J72-J73 -> 0 | K74: =+K72-K73 -> 0 | ... W74: =+W72-W73 -> 0
B76: Other budgetary variables
B77: Headline balance | D77: =D59-D68 -> 1.7056089 | E77: =E59-E68 -> 1.6504174 | F77: =F59-F68 -> 1.2569437 | G77: =G59-G68 -> 1.3229707 | H77: =H59-H68 -> 1.4782958 | I77: =I59-I68 -> 1.7585653 | J77: =J59-J68 -> 1.9330239 | K77: =K59-K68 -> 1.9066324 | ... W77: =W59-W68 -> 0.94280064
B78: Structural balance | D78: =D60-D68-D64-D65-D66 -> -3.0337962 | E78: =E60-E68-E64-E65-E66 -> 1.0217271 | F78: =F60-F68-F64-F65-F66 -> 1.8375675 | G78: =G60-G68-G64-G65-G66 -> 1.8496221 | H78: =H60-H68-H64-H65-H66 -> 1.829394 | I78: =I60-I68-I64-I65-I66 -> 1.8755965 | J78: =J60-J68-J64-J65-J66 -> 1.9330204 | K78: =K60-K68-K64-K65-K66 -> 1.9066295 | ... W78: =W60-W68-W64-W65-W66 -> 0.942789
B79: Net expenditure growth | D79: ='Input data'!D45 -> 14.052581 | E79: ='Input data'!E45 -> 13.567155 | F79: ='Input data'!F45 -> 7.3776443 | G79: ='Input data'!G33+G42-(G$12-F$12)/'Input data'!$C$64*100 -> 5.200709 | H79: ='Input data'!H33+H42-(H$12-G$12)/'Input data'!$C$64*100 -> 5.3891289 | I79: ='Input data'!I33+I42-(I$12-H$12)/'Input data'!$C$64*100 -> 5.4095418 | J79: ='Input data'!J33+J42-(J$12-I$12)/'Input data'!$C$64*100 -> 5.4982216 | K79: ='Input data'!K33+K42-(K$12-J$12)/'Input data'!$C$64*100 -> 5.3966535 | L79: ='Input data'!L33+L42-(L$12-K$12)/'Input data'!$C$64*100 -> 5.2498504 | M79: ='Input data'!M33+M42-(M$12-L$12)/'Input data'!$C$64*100 -> 5.0606333 | N79: ='Input data'!N33+N42-(N$12-M$12)/'Input data'!$C$64*100 -> 4.8303961 | ... W79: ='Input data'!W33+W42-(W$12-V$12)/'Input data'!$C$64*100 -> 3.901108
B81: Average net primary expenditure growth | D81: =AVERAGE(OFFSET($G$79,0,0,1,'Criteria results'!F5)) -> 5.3744003
B83: Debt decomposition and IIR
B85: Auxiliary variable identifying whether debt is increasing | D85: =IF((D90-C90*D43/((1+D24/100)*(1+D42/100)))>0,1,0) -> 0 | E85: =IF((E90-D90*E43/((1+E24/100)*(1+E42/100)))>0,1,0) -> 0 | F85: =IF((F90-E90*F43/((1+F24/100)*(1+F42/100)))>0,1,0) -> 1 | G85: =IF((G90-F90*G43/((1+G24/100)*(1+G42/100)))>0,1,0) -> 1 | H85: =IF((H90-G90*H43/((1+H24/100)*(1+H42/100)))>0,1,0) -> 0 | I85: =IF((I90-H90*I43/((1+I24/100)*(1+I42/100)))>0,1,0) -> 0 | J85: =IF((J90-I90*J43/((1+J24/100)*(1+J42/100)))>0,1,0) -> 0 | K85: =IF((K90-J90*K43/((1+K24/100)*(1+K42/100)))>0,1,0) -> 0 | ... W85: =IF((W90-V90*W43/((1+W24/100)*(1+W42/100)))>0,1,0) -> 0
B86: Auxiliary variable identifying whether some debt is rolled over even though debt is decreasing | D86: =IF(AND(D85=0,ABS(D90-C90*D43/((1+D24/100)*(1+D42/100)))<((C96*C90*D43/((1+D24/100)*(1+D42/100))+(D39*C90*C97*D43/((1+D24/100)*(1+D42/100)))))),1,0) -> 0 | E86: =IF(AND(E85=0,ABS(E90-D90*E43/((1+E24/100)*(1+E42/100)))<((D96*D90*E43/((1+E24/100)*(1+E42/100))+(E39*D90*D97*E43/((1+E24/100)*(1+E42/100)))))),1,0) -> 1 | F86: =IF(AND(F85=0,ABS(F90-E90*F43/((1+F24/100)*(1+F42/100)))<((E96*E90*F43/((1+F24/100)*(1+F42/100))+(F39*E90*E97*F43/((1+F24/100)*(1+F42/100)))))),1,0) -> 0 | G86: =IF(AND(G85=0,ABS(G90-F90*G43/((1+G24/100)*(1+G42/100)))<((F96*F90*G43/((1+G24/100)*(1+G42/100))+(G39*F90*F97*G43/((1+G24/100)*(1+G42/100)))))),1,0) -> 0 | H86: =IF(AND(H85=0,ABS(H90-G90*H43/((1+H24/100)*(1+H42/100)))<((G96*G90*H43/((1+H24/100)*(1+H42/100))+(H39*G90*G97*H43/((1+H24/100)*(1+H42/100)))))),1,0) -> 1 | I86: =IF(AND(I85=0,ABS(I90-H90*I43/((1+I24/100)*(1+I42/100)))<((H96*H90*I43/((1+I24/100)*(1+I42/100))+(I39*H90*H97*I43/((1+I24/100)*(1+I42/100)))))),1,0) -> 1 | J86: =IF(AND(J85=0,ABS(J90-I90*J43/((1+J24/100)*(1+J42/100)))<((I96*I90*J43/((1+J24/100)*(1+J42/100))+(J39*I90*I97*J43/((1+J24/100)*(1+J42/100)))))),1,0) -> 1 | K86: =IF(AND(K85=0,ABS(K90-J90*K43/((1+K24/100)*(1+K42/100)))<((J96*J90*K43/((1+K24/100)*(1+K42/100))+(K39*J90*J97*K43/((1+K24/100)*(1+K42/100)))))),1,0) -> 1 | ... W86: =IF(AND(W85=0,ABS(W90-V90*W43/((1+W24/100)*(1+W42/100)))<((V96*V90*W43/((1+W24/100)*(1+W42/100))+(W39*V90*V97*W43/((1+W24/100)*(1+W42/100)))))),1,0) -> 0
C89: 2021 | D89: 2022 | E89: 2023 | F89: 2024 | G89: 2025 | H89: 2026 | I89: 2027 | J89: 2028 | K89: 2029 | L89: 2030 | M89: 2031 | N89: 2032 | O89: 2033 | P89: 2034 | Q89: 2035 | R89: 2036 | S89: 2037 | T89: 2038 | U89: 2039 | V89: 2040 | W89: 2041
B90: Gross debt | C90: =C57 -> 54.39847 | D90: =D57 -> 44.391772 | E90: =E57 -> 43.730434 | F90: =F57 -> 42.488825 | G90: =G57 -> 41.199314 | H90: =G90*(1+H103/100)*H43-H60-H61+H62+H63+H64+H65+H66+H72 -> 37.456895 | I90: =H90*(1+I103/100)*I43-I60-I61+I62+I63+I64+I65+I66+I72 -> 33.593172 | J90: =I90*(1+J103/100)*J43-J60-J61+J62+J63+J64+J65+J66+J72 -> 29.816315 | K90: =J90*(1+K103/100)*K43-K60-K61+K62+K63+K64+K65+K66+K72 -> 26.364043 | L90: =K90*(1+L103/100)*L43-L60-L61+L62+L63+L64+L65+L66+L72 -> 23.177269 | M90: =L90*(1+M103/100)*M43-M60-M61+M62+M63+M64+M65+M66+M72 -> 20.25762 | N90: =M90*(1+N103/100)*N43-N60-N61+N62+N63+N64+N65+N66+N72 -> 17.655639 | O90: =N90*(1+O103/100)*O43-O60-O61+O62+O63+O64+O65+O66+O72 -> 15.251051 | ... W90: =V90*(1+W103/100)*W43-W60-W61+W62+W63+W64+W65+W66+W72 -> 2.2971951
B91: Of which Outstanding debt | D91: ='Input data'!C66*$D$90 -> 37.416473 | E91: =IF(E90=0,0,IF(E85=1,D90*E43/((1+E24/100)*(1+E42/100))-E92-E93,IF(AND(E85=0,E86=1),(1-D96-E39*D97)*D90*E43/((1+E24/100)*(1+E42/100)),E90))) -> 37.985689 | F91: =IF(F90=0,0,IF(F85=1,E90*F43/((1+F24/100)*(1+F42/100))-F92-F93,IF(AND(F85=0,F86=1),(1-E96-F39*E97)*E90*F43/((1+F24/100)*(1+F42/100)),F90))) -> 36.086221 | G91: =IF(G90=0,0,IF(G85=1,F90*G43/((1+G24/100)*(1+G42/100))-G92-G93,IF(AND(G85=0,G86=1),(1-F96-G39*F97)*F90*G43/((1+G24/100)*(1+G42/100)),G90))) -> 34.066502 | H91: =IF(H90=0,0,IF(H85=1,G90*H43/((1+H24/100)*(1+H42/100))-H92-H93,IF(AND(H85=0,H86=1),(1-G96-H39*G97)*G90*H43/((1+H24/100)*(1+H42/100)),H90))) -> 32.665878 | I91: =IF(I90=0,0,IF(I85=1,H90*I43/((1+I24/100)*(1+I42/100))-I92-I93,IF(AND(I85=0,I86=1),(1-H96-I39*H97)*H90*I43/((1+I24/100)*(1+I42/100)),I90))) -> 30.609328 | J91: =IF(J90=0,0,IF(J85=1,I90*J43/((1+J24/100)*(1+J42/100))-J92-J93,IF(AND(J85=0,J86=1),(1-I96-J39*I97)*I90*J43/((1+J24/100)*(1+J42/100)),J90))) -> 27.996255 | K91: =IF(K90=0,0,IF(K85=1,J90*K43/((1+K24/100)*(1+K42/100))-K92-K93,IF(AND(K85=0,K86=1),(1-J96-K39*J97)*J90*K43/((1+K24/100)*(1+K42/100)),K90))) -> 25.397506 | L91: =IF(L90=0,0,IF(L85=1,K90*L43/((1+L24/100)*(1+L42/100))-L92-L93,IF(AND(L85=0,L86=1),(1-K96-L39*K97)*K90*L43/((1+L24/100)*(1+L42/100)),L90))) -> 22.973688 | ... W91: =IF(W90=0,0,IF(W85=1,V90*W43/((1+W24/100)*(1+W42/100))-W92-W93,IF(AND(W85=0,W86=1),(1-V96-W39*V97)*V90*W43/((1+W24/100)*(1+W42/100)),W90))) -> 2.2971951
B92: Rolled over long-term debt | D92: ='Input data'!C67*$D$90 -> 2.3067736 | E92: =IF(E90=0,0,IF(E85=1,E39*D90*D97*E43/((1+E24/100)*(1+E42/100)),IF(AND(E85=0,E86=1),(E39*D90*D97*E43/((1+E24/100)*(1+E42/100)))*(1-ABS(E90-D90*E43/((1+E24/100)*(1+E42/100)))/((E39*D90*D97*E43/((1+E24/100)*(1+E42/100)))+(D96*D90*E43/((1+E24/100)*(1+E42/100))))),0))) -> 1.6381495 | F92: =IF(F90=0,0,IF(F85=1,F39*E90*E97*F43/((1+F24/100)*(1+F42/100)),IF(AND(F85=0,F86=1),(F39*E90*E97*F43/((1+F24/100)*(1+F42/100)))*(1-ABS(F90-E90*F43/((1+F24/100)*(1+F42/100)))/((F39*E90*E97*F43/((1+F24/100)*(1+F42/100)))+(E96*E90*F43/((1+F24/100)*(1+F42/100))))),0))) -> 2.0686309 | G92: =IF(G90=0,0,IF(G85=1,G39*F90*F97*G43/((1+G24/100)*(1+G42/100)),IF(AND(G85=0,G86=1),(G39*F90*F97*G43/((1+G24/100)*(1+G42/100)))*(1-ABS(G90-F90*G43/((1+G24/100)*(1+G42/100)))/((G39*F90*F97*G43/((1+G24/100)*(1+G42/100)))+(F96*F90*G43/((1+G24/100)*(1+G42/100))))),0))) -> 2.4597944 | H92: =IF(H90=0,0,IF(H85=1,H39*G90*G97*H43/((1+H24/100)*(1+H42/100)),IF(AND(H85=0,H86=1),(H39*G90*G97*H43/((1+H24/100)*(1+H42/100)))*(1-ABS(H90-G90*H43/((1+H24/100)*(1+H42/100)))/((H39*G90*G97*H43/((1+H24/100)*(1+H42/100)))+(G96*G90*H43/((1+H24/100)*(1+H42/100))))),0))) -> 1.9739953 | I92: =IF(I90=0,0,IF(I85=1,I39*H90*H97*I43/((1+I24/100)*(1+I42/100)),IF(AND(I85=0,I86=1),(I39*H90*H97*I43/((1+I24/100)*(1+I42/100)))*(1-ABS(I90-H90*I43/((1+I24/100)*(1+I42/100)))/((I39*H90*H97*I43/((1+I24/100)*(1+I42/100)))+(H96*H90*I43/((1+I24/100)*(1+I42/100))))),0))) -> 1.3110357 | J92: =IF(J90=0,0,IF(J85=1,J39*I90*I97*J43/((1+J24/100)*(1+J42/100)),IF(AND(J85=0,J86=1),(J39*I90*I97*J43/((1+J24/100)*(1+J42/100)))*(1-ABS(J90-I90*J43/((1+J24/100)*(1+J42/100)))/((J39*I90*I97*J43/((1+J24/100)*(1+J42/100)))+(I96*I90*J43/((1+J24/100)*(1+J42/100))))),0))) -> 1.0533569 | K92: =IF(K90=0,0,IF(K85=1,K39*J90*J97*K43/((1+K24/100)*(1+K42/100)),IF(AND(K85=0,K86=1),(K39*J90*J97*K43/((1+K24/100)*(1+K42/100)))*(1-ABS(K90-J90*K43/((1+K24/100)*(1+K42/100)))/((K39*J90*J97*K43/((1+K24/100)*(1+K42/100)))+(J96*J90*K43/((1+K24/100)*(1+K42/100))))),0))) -> 0.72198685 | L92: =IF(L90=0,0,IF(L85=1,L39*K90*K97*L43/((1+L24/100)*(1+L42/100)),IF(AND(L85=0,L86=1),(L39*K90*K97*L43/((1+L24/100)*(1+L42/100)))*(1-ABS(L90-K90*L43/((1+L24/100)*(1+L42/100)))/((L39*K90*K97*L43/((1+L24/100)*(1+L42/100)))+(K96*K90*L43/((1+L24/100)*(1+L42/100))))),0))) -> 0.18062463 | ... W92: =IF(W90=0,0,IF(W85=1,W39*V90*V97*W43/((1+W24/100)*(1+W42/100)),IF(AND(W85=0,W86=1),(W39*V90*V97*W43/((1+W24/100)*(1+W42/100)))*(1-ABS(W90-V90*W43/((1+W24/100)*(1+W42/100)))/((W39*V90*V97*W43/((1+W24/100)*(1+W42/100)))+(V96*V90*W43/((1+W24/100)*(1+W42/100))))),0))) -> 0
B93: Rolled over short-term debt | D93: ='Input data'!C68*$D$90 -> 4.6685201 | E93: =IF(E90=0,0,IF(E85=1,(1-D97)*D90*E43/((1+E24/100)*(1+E42/100)),IF(AND(E85=0,E86=1),(D96*D90*E43/((1+E24/100)*(1+E42/100)))*(1-ABS(E90-D90*E43/((1+E24/100)*(1+E42/100)))/((E39*D90*D97*E43/((1+E24/100)*(1+E42/100)))+(D96*D90*E43/((1+E24/100)*(1+E42/100))))),0))) -> 4.1065954 | F93: =IF(F90=0,0,IF(F85=1,(1-E97)*E90*F43/((1+F24/100)*(1+F42/100)),IF(AND(F85=0,F86=1),(E96*E90*F43/((1+F24/100)*(1+F42/100)))*(1-ABS(F90-E90*F43/((1+F24/100)*(1+F42/100)))/((F39*E90*E97*F43/((1+F24/100)*(1+F42/100)))+(E96*E90*F43/((1+F24/100)*(1+F42/100))))),0))) -> 3.9543503 | G93: =IF(G90=0,0,IF(G85=1,(1-F97)*F90*G43/((1+G24/100)*(1+G42/100)),IF(AND(G85=0,G86=1),(F96*F90*G43/((1+G24/100)*(1+G42/100)))*(1-ABS(G90-F90*G43/((1+G24/100)*(1+G42/100)))/((G39*F90*F97*G43/((1+G24/100)*(1+G42/100)))+(F96*F90*G43/((1+G24/100)*(1+G42/100))))),0))) -> 3.7957467 | H93: =IF(H90=0,0,IF(H85=1,(1-G97)*G90*H43/((1+H24/100)*(1+H42/100)),IF(AND(H85=0,H86=1),(G96*G90*H43/((1+H24/100)*(1+H42/100)))*(1-ABS(H90-G90*H43/((1+H24/100)*(1+H42/100)))/((H39*G90*G97*H43/((1+H24/100)*(1+H42/100)))+(G96*G90*H43/((1+H24/100)*(1+H42/100))))),0))) -> 2.8170211 | I93: =IF(I90=0,0,IF(I85=1,(1-H97)*H90*I43/((1+I24/100)*(1+I42/100)),IF(AND(I85=0,I86=1),(H96*H90*I43/((1+I24/100)*(1+I42/100)))*(1-ABS(I90-H90*I43/((1+I24/100)*(1+I42/100)))/((I39*H90*H97*I43/((1+I24/100)*(1+I42/100)))+(H96*H90*I43/((1+I24/100)*(1+I42/100))))),0))) -> 1.6728084 | J93: =IF(J90=0,0,IF(J85=1,(1-I97)*I90*J43/((1+J24/100)*(1+J42/100)),IF(AND(J85=0,J86=1),(I96*I90*J43/((1+J24/100)*(1+J42/100)))*(1-ABS(J90-I90*J43/((1+J24/100)*(1+J42/100)))/((J39*I90*I97*J43/((1+J24/100)*(1+J42/100)))+(I96*I90*J43/((1+J24/100)*(1+J42/100))))),0))) -> 0.76670328 | K93: =IF(K90=0,0,IF(K85=1,(1-J97)*J90*K43/((1+K24/100)*(1+K42/100)),IF(AND(K85=0,K86=1),(J96*J90*K43/((1+K24/100)*(1+K42/100)))*(1-ABS(K90-J90*K43/((1+K24/100)*(1+K42/100)))/((K39*J90*J97*K43/((1+K24/100)*(1+K42/100)))+(J96*J90*K43/((1+K24/100)*(1+K42/100))))),0))) -> 0.24454937 | L93: =IF(L90=0,0,IF(L85=1,(1-K97)*K90*L43/((1+L24/100)*(1+L42/100)),IF(AND(L85=0,L86=1),(K96*K90*L43/((1+L24/100)*(1+L42/100)))*(1-ABS(L90-K90*L43/((1+L24/100)*(1+L42/100)))/((L39*K90*K97*L43/((1+L24/100)*(1+L42/100)))+(K96*K90*L43/((1+L24/100)*(1+L42/100))))),0))) -> 0.022956839 | ... W93: =IF(W90=0,0,IF(W85=1,(1-V97)*V90*W43/((1+W24/100)*(1+W42/100)),IF(AND(W85=0,W86=1),(V96*V90*W43/((1+W24/100)*(1+W42/100)))*(1-ABS(W90-V90*W43/((1+W24/100)*(1+W42/100)))/((W39*V90*V97*W43/((1+W24/100)*(1+W42/100)))+(V96*V90*W43/((1+W24/100)*(1+W42/100))))),0))) -> 0
B94: New long-term debt | D94: ='Input data'!C69*$D$90 -> 0 | E94: =IF(E90=0,0,IF(E85=1,'Input data'!$C$58*(E90-D90*E43/((1+E24/100)*(1+E42/100))),0)) -> 0 | F94: =IF(F90=0,0,IF(F85=1,'Input data'!$C$58*(F90-E90*F43/((1+F24/100)*(1+F42/100))),0)) -> 0.33425532 | G94: =IF(G90=0,0,IF(G85=1,'Input data'!$C$58*(G90-F90*G43/((1+G24/100)*(1+G42/100))),0)) -> 0.77242956 | H94: =IF(H90=0,0,IF(H85=1,'Input data'!$C$58*(H90-G90*H43/((1+H24/100)*(1+H42/100))),0)) -> 0 | I94: =IF(I90=0,0,IF(I85=1,'Input data'!$C$58*(I90-H90*I43/((1+I24/100)*(1+I42/100))),0)) -> 0 | J94: =IF(J90=0,0,IF(J85=1,'Input data'!$C$58*(J90-I90*J43/((1+J24/100)*(1+J42/100))),0)) -> 0 | K94: =IF(K90=0,0,IF(K85=1,'Input data'!$C$58*(K90-J90*K43/((1+K24/100)*(1+K42/100))),0)) -> 0 | L94: =IF(L90=0,0,IF(L85=1,'Input data'!$C$58*(L90-K90*L43/((1+L24/100)*(1+L42/100))),0)) -> 0 | ... W94: =IF(W90=0,0,IF(W85=1,'Input data'!$C$58*(W90-V90*W43/((1+W24/100)*(1+W42/100))),0)) -> 0
B95: New short-term debt | D95: ='Input data'!C70*$D$90 -> 0 | E95: =IF(E90=0,0,IF(E85=1,'Input data'!$C$57*(E90-D90*E43/((1+E24/100)*(1+E42/100))),0)) -> 0 | F95: =IF(F90=0,0,IF(F85=1,'Input data'!$C$57*(F90-E90*F43/((1+F24/100)*(1+F42/100))),0)) -> 0.045368027 | G95: =IF(G90=0,0,IF(G85=1,'Input data'!$C$57*(G90-F90*G43/((1+G24/100)*(1+G42/100))),0)) -> 0.10484083 | H95: =IF(H90=0,0,IF(H85=1,'Input data'!$C$57*(H90-G90*H43/((1+H24/100)*(1+H42/100))),0)) -> 0 | I95: =IF(I90=0,0,IF(I85=1,'Input data'!$C$57*(I90-H90*I43/((1+I24/100)*(1+I42/100))),0)) -> 0 | J95: =IF(J90=0,0,IF(J85=1,'Input data'!$C$57*(J90-I90*J43/((1+J24/100)*(1+J42/100))),0)) -> 0 | K95: =IF(K90=0,0,IF(K85=1,'Input data'!$C$57*(K90-J90*K43/((1+K24/100)*(1+K42/100))),0)) -> 0 | L95: =IF(L90=0,0,IF(L85=1,'Input data'!$C$57*(L90-K90*L43/((1+L24/100)*(1+L42/100))),0)) -> 0 | ... W95: =IF(W90=0,0,IF(W85=1,'Input data'!$C$57*(W90-V90*W43/((1+W24/100)*(1+W42/100))),0)) -> 0
B96: Share of short-term debt in total government debt | D96: ='Baseline NFPC'!$D$93 -> 0.10516645 | E96: =IF(E90<>0,(E93+E95)/(E91+E92+E93+E94+E95),0) -> 0.093907036 | F96: =IF(F90<>0,(F93+F95)/(F91+F92+F93+F94+F95),0) -> 0.094135772 | G96: =IF(G90<>0,(G93+G95)/(G91+G92+G93+G94+G95),0) -> 0.094676031 | H96: =IF(H90<>0,(H93+H95)/(H91+H92+H93+H94+H95),0) -> 0.075207012 | I96: =IF(I90<>0,(I93+I95)/(I91+I92+I93+I94+I95),0) -> 0.049796082 | J96: =IF(J90<>0,(J93+J95)/(J91+J92+J93+J94+J95),0) -> 0.02571422 | K96: =IF(K90<>0,(K93+K95)/(K91+K92+K93+K94+K95),0) -> 0.0092758676 | L96: =IF(L90<>0,(L93+L95)/(L91+L92+L93+L94+L95),0) -> 0.00099048936 | ... W96: =IF(W90<>0,(W93+W95)/(W91+W92+W93+W94+W95),0) -> 0
B97: Share of long-term debt in total government debt | D97: ='Baseline NFPC'!$D$94 -> 0.89483355 | E97: =IF(E90<>0,(E91+E92+E94)/(E91+E92+E93+E94+E95),1) -> 0.90609296 | F97: =IF(F90<>0,(F91+F92+F94)/(F91+F92+F93+F94+F95),1) -> 0.90586423 | G97: =IF(G90<>0,(G91+G92+G94)/(G91+G92+G93+G94+G95),1) -> 0.90532397 | H97: =IF(H90<>0,(H91+H92+H94)/(H91+H92+H93+H94+H95),1) -> 0.92479299 | I97: =IF(I90<>0,(I91+I92+I94)/(I91+I92+I93+I94+I95),1) -> 0.95020392 | J97: =IF(J90<>0,(J91+J92+J94)/(J91+J92+J93+J94+J95),1) -> 0.97428578 | K97: =IF(K90<>0,(K91+K92+K94)/(K91+K92+K93+K94+K95),1) -> 0.99072413 | L97: =IF(L90<>0,(L91+L92+L94)/(L91+L92+L93+L94+L95),1) -> 0.99900951 | ... W97: =IF(W90<>0,(W91+W92+W94)/(W91+W92+W93+W94+W95),1) -> 1
B99: IIR | C99: ='Baseline NFPC'!C96 -> 1.510173 | D99: ='Baseline NFPC'!D96 -> 1.408838 | E99: ='Baseline NFPC'!E96 -> 1.550894 | F99: ='Baseline NFPC'!F96 -> 1.641526 | G99: ='Baseline NFPC'!G96 -> 1.684386 | H99: =H101 -> 1.7963363 | I99: =I101 -> 1.8477296 | J99: =J101 -> 1.8765133 | K99: =K101 -> 1.9046582 | L99: =L101 -> 1.9309319 | M99: =M101 -> 1.9360734 | N99: =N101 -> 1.9574641 | O99: =O101 -> 1.9793499 | ... W99: =W101 -> 1.9944068
B100: Long-term implicit interest rate | E100: =((E36*D90)-(E38*(D93+D95)))/(D91+D92+D94) -> 1.3300501 | F100: =((F36*E90)-(F38*(E93+E95)))/(E91+E92+E94) -> 1.4422602 | G100: =((G36*F90)-(G38*(F93+F95)))/(F91+F92+F94) -> 1.5667518 | H100: =IF(G90>0,(G100*G91+H37*(G94+G92))/(G91+G92+G94),H37) -> 1.6908439 | I100: =IF(H90>0,(H100*H91+I37*(H94+H92))/(H91+H92+H94),I37) -> 1.7707919 | J100: =IF(I90>0,(I100*I91+J37*(I94+I92))/(I91+I92+I94),J37) -> 1.8290335 | K100: =IF(J90>0,(J100*J91+K37*(J94+J92))/(J91+J92+J94),K37) -> 1.8817868 | L100: =IF(K90>0,(K100*K91+L37*(K94+K92))/(K91+K92+K94),L37) -> 1.9231701 | M100: =IF(L90>0,(L100*L91+M37*(L94+L92))/(L91+L92+L94),M37) -> 1.9352677 | N100: =IF(M90>0,(M100*M91+N37*(M94+M92))/(M91+M92+M94),N37) -> 1.9573515 | O100: =IF(N90>0,(N100*N91+O37*(N94+N92))/(N91+N92+N94),O37) -> 1.9793357 | ... W100: =IF(V90>0,(V100*V91+W37*(V94+V92))/(V91+V92+V94),W37) -> 1.9944068
B101: Nominal implicit interest rate on debt | E101: =(E100*(D91+D92+D94)+E38*(D93+D95))/D90 -> 1.550894 | F101: =(F100*(E91+E92+E94)+F38*(E93+E95))/E90 -> 1.641526 | G101: =(G100*(F91+F92+F94)+G38*(F93+F95))/F90 -> 1.684386 | H101: =(H100*(G91+G92+G94)+H38*(G93+G95))/G90 -> 1.7963363 | I101: =(I100*(H91+H92+H94)+I38*(H93+H95))/H90 -> 1.8477296 | J101: =(J100*(I91+I92+I94)+J38*(I93+I95))/I90 -> 1.8765133 | K101: =(K100*(J91+J92+J94)+K38*(J93+J95))/J90 -> 1.9046582 | L101: =(L100*(K91+K92+K94)+L38*(K93+K95))/K90 -> 1.9309319 | ... W101: =(W100*(V91+V92+V94)+W38*(V93+V95))/V90 -> 1.9944068
B103: (i - g) | C103: =((1+C99/100)/((1+C24/100)*(1+C42/100))-1)*100 -> -12.245307 | D103: =((1+D99/100)/((1+D24/100)*(1+D42/100))-1)*100 -> -13.055432 | E103: =((1+E99/100)/((1+E24/100)*(1+E42/100))-1)*100 -> 1.8855084 | F103: =((1+F99/100)/((1+F24/100)*(1+F42/100))-1)*100 -> -2.1266613 | G103: =((1+G99/100)/((1+G24/100)*(1+G42/100))-1)*100 -> -3.5011632 | H103: =((1+H99/100)/((1+H24/100)*(1+H42/100))-1)*100 -> -3.7979178 | I103: =((1+I99/100)/((1+I24/100)*(1+I42/100))-1)*100 -> -3.8763297 | J103: =((1+J99/100)/((1+J24/100)*(1+J42/100))-1)*100 -> -3.7151976 | ... W103: =((1+W99/100)/((1+W24/100)*(1+W42/100))-1)*100 -> -1.869689

Sheet Adjust. no safeguard
B3: Country | C3: ='Input data'!C3 -> IE
B4: Key years
B5: ='Input data'!B5 -> Last year before the adjustment | C5: =+'Input data'!C5 -> 2024
B6: Last year of adjustment | C6: =+C5+'Criteria results'!$F$5 -> 2028
B7: Last year of no-fiscal-policy-change projections | C7: =C5+'Criteria results'!$F$5+10 -> 2038
B9: Key assumptions
C10: 2021 | D10: 2022 | E10: 2023 | F10: 2024 | G10: 2025 | H10: 2026 | I10: 2027 | J10: 2028 | K10: 2029 | L10: 2030 | M10: 2031 | N10: 2032 | O10: 2033 | P10: 2034 | Q10: 2035 | R10: 2036 | S10: 2037 | T10: 2038 | U10: 2039 | V10: 2040 | W10: 2041
B11: Fiscal assumptions (% of GDP)
B12: Structural primary balance ('+' means 'surplus') | C12: ='Input data'!C13 -> -3.165318 | D12: ='Input data'!D13 -> -2.376722 | E12: ='Input data'!E13 -> 1.712465 | F12: ='Input data'!F13 -> 2.528801 | G12: =IF(G10<=$C$6,F12+'Criteria results'!$F$7,F12) -> 2.528801 | H12: =IF(H10<=$C$6,G12+'Criteria results'!$F$7,G12) -> 2.528801 | I12: =IF(I10<=$C$6,H12+'Criteria results'!$F$7,H12) -> 2.528801 | J12: =IF(J10<=$C$6,I12+'Criteria results'!$F$7,I12) -> 2.528801 | K12: =IF(K10<=$C$6,J12+'Criteria results'!$F$7,J12) -> 2.528801 | L12: =IF(L10<=$C$6,K12+'Criteria results'!$F$7,K12) -> 2.528801 | M12: =IF(M10<=$C$6,L12+'Criteria results'!$F$7,L12) -> 2.528801 | N12: =M12 -> 2.528801 | O12: =N12 -> 2.528801 | P12: =O12 -> 2.528801 | Q12: =P12 -> 2.528801 | R12: =Q12 -> 2.528801 | S12: =R12 -> 2.528801 | T12: =S12 -> 2.528801 | U12: =T12 -> 2.528801 | ... W12: =V12 -> 2.528801
B13: Annual change in SPB | G13: =G12-F12 -> 0 | H13: =H12-G12 -> 0 | I13: =I12-H12 -> 0 | J13: =J12-I12 -> 0 | K13: =K12-J12 -> 0 | L13: =L12-K12 -> 0 | M13: =M12-L12 -> 0 | N13: =N12-M12 -> 0 | ... W13: =W12-V12 -> 0
B14: One-off and other temporary measures | C14: ='Input data'!C14 -> 0 | D14: ='Input data'!D14 -> 0 | E14: ='Input data'!E14 -> 0 | F14: ='Input data'!F14 -> 0 | G14: ='Input data'!G14 -> 0 | H14: =0 -> 0 | I14: =0 -> 0 | J14: =0 -> 0 | K14: =0 -> 0 | L14: =0 -> 0 | M14: =0 -> 0 | N14: =0 -> 0 | O14: =0 -> 0 | ... W14: =0 -> 0
B15: Stock flow adjustments (without exchange rate effect) | C15: ='Input data'!C15 -> 2.690274 | D15: ='Input data'!D15 -> -0.5420614 | E15: ='Input data'!E15 -> 0.8428086 | F15: ='Input data'!F15 -> 1.636568 | G15: ='Input data'!G15 -> 2.20024 | H15: ='Input data'!H15 -> 0 | I15: ='Input data'!I15 -> 0 | J15: ='Input data'!J15 -> 0 | ... W15: ='Input data'!W15 -> 0
B17: ='Input data'!B19 -> Cost of ageing and selected public revenue (based on the Commission-Council 2024 Ageing Report ("AR 2024"))
B18: Total ageing cost (net of taxes on pensions) | C18: ='Input data'!C20 -> 0 | D18: ='Input data'!D20 -> 11.98063 | E18: ='Input data'!E20 -> 11.58823 | F18: ='Input data'!F20 -> 11.59789 | G18: ='Input data'!G20 -> 11.65158 | H18: ='Input data'!H20 -> 11.82718 | I18: ='Input data'!I20 -> 12.01015 | J18: ='Input data'!J20 -> 12.14108 | ... W18: ='Input data'!W20 -> 13.69105
B19: Property income | C19: ='Input data'!C26 -> 0.1107195 | D19: ='Input data'!D26 -> 0.132752 | E19: ='Input data'!E26 -> 0.1349502 | F19: ='Input data'!F26 -> 0.1371484 | G19: ='Input data'!G26 -> 0.1393466 | H19: ='Input data'!H26 -> 0.1415448 | I19: ='Input data'!I26 -> 0.143743 | J19: ='Input data'!J26 -> 0.1459412 | ... W19: ='Input data'!W26 -> 0.1745179
B21: GDP growth assumptions
B22: Actual GDP (real)
B23: Level | C23: ='Input data'!C31 -> 410.9464 | D23: ='Baseline NFPC'!D22 -> 449.71106 | E23: ='Baseline NFPC'!E22 -> 435.32576 | F23: ='Baseline NFPC'!F22 -> 440.73992 | G23: =IF(AND(G50>1,F50>1),IF(AND(G50>0,F50>0),G27*(G51/100+1),0)+IF(G50>0,F23*(1+G52/100),0)-F23*(1+'Input data'!G30/100),IF(G50=1,G27,F23*(1+G52/100))) -> 455.69777 | H23: =IF(AND(H50>1,G50>1),IF(AND(H50>0,G50>0),H27*(H51/100+1),0)+IF(H50>0,G23*(1+H52/100),0)-G23*(1+'Input data'!H30/100),IF(H50=1,H27,G23*(1+H52/100))) -> 472.76873 | I23: =IF(AND(I50>1,H50>1),IF(AND(I50>0,H50>0),I27*(I51/100+1),0)+IF(I50>0,H23*(1+I52/100),0)-H23*(1+'Input data'!I30/100),IF(I50=1,I27,H23*(1+I52/100))) -> 490.74514 | J23: =IF(AND(J50>1,I50>1),IF(AND(J50>0,I50>0),J27*(J51/100+1),0)+IF(J50>0,I23*(1+J52/100),0)-I23*(1+'Input data'!J30/100),IF(J50=1,J27,I23*(1+J52/100))) -> 508.30099 | K23: =IF(AND(K50>1,J50>1),IF(AND(K50>0,J50>0),K27*(K51/100+1),0)+IF(K50>0,J23*(1+K52/100),0)-J23*(1+'Input data'!K30/100),IF(K50=1,K27,J23*(1+K52/100))) -> 524.38467 | L23: =IF(AND(L50>1,K50>1),IF(AND(L50>0,K50>0),L27*(L51/100+1),0)+IF(L50>0,K23*(1+L52/100),0)-K23*(1+'Input data'!L30/100),IF(L50=1,L27,K23*(1+L52/100))) -> 539.79117 | M23: =IF(AND(M50>1,L50>1),IF(AND(M50>0,L50>0),M27*(M51/100+1),0)+IF(M50>0,L23*(1+M52/100),0)-L23*(1+'Input data'!M30/100),IF(M50=1,M27,L23*(1+M52/100))) -> 554.20041 | N23: =IF(AND(N50>1,M50>1),IF(AND(N50>0,M50>0),N27*(N51/100+1),0)+IF(N50>0,M23*(1+N52/100),0)-M23*(1+'Input data'!N30/100),IF(N50=1,N27,M23*(1+N52/100))) -> 567.27836 | ... W23: =IF(AND(W50>1,V50>1),IF(AND(W50>0,V50>0),W27*(W51/100+1),0)+IF(W50>0,V23*(1+W52/100),0)-V23*(1+'Input data'!W30/100),IF(W50=1,W27,V23*(1+W52/100))) -> 666.4502
B24: Growth rate | C24: =+'Input data'!C30 -> 15.12522 | D24: ='Baseline NFPC'!D23 -> 9.433022 | E24: ='Baseline NFPC'!E23 -> -3.198788 | F24: ='Baseline NFPC'!F23 -> 1.243702 | G24: =100*(G23/F23-1) -> 3.393806 | H24: =100*(H23/G23-1) -> 3.746114 | I24: =100*(I23/H23-1) -> 3.802369 | J24: =100*(J23/I23-1) -> 3.577386 | K24: =100*(K23/J23-1) -> 3.164204 | L24: =100*(L23/K23-1) -> 2.938014 | M24: =100*(M23/L23-1) -> 2.669411 | N24: =100*(N23/M23-1) -> 2.359786 | ... W24: =100*(W23/V23-1) -> 1.571112
B26: Potential GDP (real)
B27: Level | C27: ='Input data'!C34 -> 392.8036 | D27: =+C27*(1+'Input data'!D33/100) -> 412.27894 | E27: =+D27*(1+'Input data'!E33/100) -> 430.14515 | F27: =+E27*(1+'Input data'!F33/100) -> 445.69744 | G27: =+F27*(1+'Input data'!G33/100) -> 460.34222 | H27: =+G27*(1+'Input data'!H33/100) -> 475.97012 | I27: =+H27*(1+'Input data'!I33/100) -> 491.84786 | J27: =+I27*(1+'Input data'!J33/100) -> 508.30096 | K27: =+J27*(1+'Input data'!K33/100) -> 524.38464 | ... W27: =+V27*(1+'Input data'!W33/100) -> 666.45005
B29: Output gap
B30: Output gap | C30: =100*(C23/C27-1) -> 4.6187968 | D30: =100*(D23/D27-1) -> 9.07932 | E30: =100*(E23/E27-1) -> 1.2043874 | F30: =100*(F23/F27-1) -> -1.1123062 | G30: =100*(G23/G27-1) -> -1.0089108 | H30: =100*(H23/H27-1) -> -0.67260192 | I30: =100*(I23/I27-1) -> -0.22419779 | J30: =100*(J23/J27-1) -> 6.5725915e-06 | ... W30: =100*(W23/W27-1) -> 2.2288956e-05
B32: Actual GDP (nominal, national currency)
B33: Growth rate | C33: =100*((1+C24/100)*(1+C42/100)-1) -> 15.674923 | D33: =100*((1+D24/100)*(1+D42/100)-1) -> 16.636198 | E33: =100*((1+E24/100)*(1+E42/100)-1) -> -0.32842201 | F33: =100*((1+F24/100)*(1+F42/100)-1) -> 3.8500652 | G33: =100*((1+G24/100)*(1+G42/100)-1) -> 5.3736909 | H33: =100*((1+H24/100)*(1+H42/100)-1) -> 5.8151071 | I33: =100*((1+I24/100)*(1+I42/100)-1) -> 5.9548904 | J33: =100*((1+J24/100)*(1+J42/100)-1) -> 5.8074699 | ... W33: =100*((1+W24/100)*(1+W42/100)-1) -> 3.9377189
B35: Interest rates
B36: Nominal implicit interest rate on debt | C36: ='Input data'!C37 -> 1.510173 | D36: ='Input data'!D37 -> 1.408838 | E36: ='Input data'!E37 -> 1.550894 | F36: ='Input data'!F37 -> 1.641526 | G36: ='Input data'!G37 -> 1.684386 | H36: =H101 -> 1.7963363 | I36: =I101 -> 1.8477296 | J36: =J101 -> 1.8765133 | K36: =K101 -> 1.9046582 | L36: =L101 -> 1.9309319 | M36: =M101 -> 1.9360734 | N36: =N101 -> 1.9574641 | O36: =O101 -> 1.9793499 | ... W36: =W101 -> 1.9944068
B37: Long-term interest rate | D37: ='Input data'!D$39 -> 1.75 | E37: ='Input data'!E$39 -> 2.87 | F37: ='Input data'!F$39 -> 2.837221 | G37: ='Input data'!G$39 -> 2.903685 | H37: =G37+($O$37-$G$37)/($O$10-$G$10) -> 2.9987319 | I37: =H37+($O$37-$G$37)/($O$10-$G$10) -> 3.0937787 | J37: =I37+($O$37-$G$37)/($O$10-$G$10) -> 3.1888256 | K37: =J37+($O$37-$G$37)/($O$10-$G$10) -> 3.2838725 | L37: =K37+($O$37-$G$37)/($O$10-$G$10) -> 3.3789194 | M37: =L37+($O$37-$G$37)/($O$10-$G$10) -> 3.4739662 | N37: =M37+($O$37-$G$37)/($O$10-$G$10) -> 3.5690131 | O37: ='Input data'!$C$52 -> 3.66406 | P37: ='Baseline NFPC'!P36 -> 3.680857 | Q37: ='Baseline NFPC'!Q36 -> 3.697654 | R37: ='Baseline NFPC'!R36 -> 3.714451 | S37: ='Baseline NFPC'!S36 -> 3.731248 | T37: ='Baseline NFPC'!T36 -> 3.748045 | U37: ='Baseline NFPC'!U36 -> 3.764842 | V37: ='Baseline NFPC'!V36 -> 3.781639 | W37: ='Baseline NFPC'!W36 -> 3.798436
B38: Short-term interest rate | D38: ='Input data'!D$38 -> 0.35 | E38: ='Input data'!E$38 -> 3.43 | F38: ='Input data'!F$38 -> 3.564208 | G38: ='Input data'!G$38 -> 2.816375 | H38: =G38+($O$38-$G$38)/($O$10-$G$10) -> 2.8050894 | I38: =H38+($O$38-$G$38)/($O$10-$G$10) -> 2.7938037 | J38: =I38+($O$38-$G$38)/($O$10-$G$10) -> 2.7825181 | K38: =J38+($O$38-$G$38)/($O$10-$G$10) -> 2.7712325 | L38: =K38+($O$38-$G$38)/($O$10-$G$10) -> 2.7599469 | M38: =L38+($O$38-$G$38)/($O$10-$G$10) -> 2.7486612 | N38: =M38+($O$38-$G$38)/($O$10-$G$10) -> 2.7373756 | O38: ='Input data'!$C$53 -> 2.72609 | P38: ='Baseline NFPC'!P37 -> 2.6897855 | Q38: ='Baseline NFPC'!Q37 -> 2.653481 | R38: ='Baseline NFPC'!R37 -> 2.6171765 | S38: ='Baseline NFPC'!S37 -> 2.580872 | T38: ='Baseline NFPC'!T37 -> 2.5445675 | U38: ='Baseline NFPC'!U37 -> 2.508263 | V38: ='Baseline NFPC'!V37 -> 2.4719585 | W38: ='Baseline NFPC'!W37 -> 2.435654
B39: Share of long-term debt that matures every year | C39: ='Baseline NFPC'!C38 -> 0.001 | D39: ='Baseline NFPC'!D38 -> 0.07537306 | E39: ='Baseline NFPC'!E38 -> 0.04688205 | F39: ='Baseline NFPC'!F38 -> 0.05421672 | G39: ='Baseline NFPC'!G38 -> 0.06734311 | H39: ='Baseline NFPC'!H38 -> 0.07328111 | I39: ='Baseline NFPC'!I38 -> 0.06373561 | J39: ='Baseline NFPC'!J38 -> 0.07199902 | ... W39: ='Baseline NFPC'!W38 -> 0.07343585
B41: Inflation and exchange rate
B42: GDP deflator (National currency) | C42: ='Input data'!C42 -> 0.4774826 | D42: ='Input data'!D42 -> 6.582269 | E42: ='Input data'!E42 -> 2.965217 | F42: ='Input data'!F42 -> 2.574346 | G42: ='Input data'!G42 -> 1.914897 | H42: ='Baseline NFPC'!H41 -> 1.9942849 | I42: ='Baseline NFPC'!I41 -> 2.0736728 | J42: ='Baseline NFPC'!J41 -> 2.1530606 | K42: ='Baseline NFPC'!K41 -> 2.2324485 | L42: ='Baseline NFPC'!L41 -> 2.3118364 | M42: ='Baseline NFPC'!M41 -> 2.3912243 | N42: ='Baseline NFPC'!N41 -> 2.4706121 | O42: ='Baseline NFPC'!O41 -> 2.55 | ... W42: ='Baseline NFPC'!W41 -> 2.33
B43: Exchange rate composite change (weighted by share of debt in each currency) | C43: ='Baseline NFPC'!C42 -> 1 | D43: ='Baseline NFPC'!D42 -> 1 | E43: ='Baseline NFPC'!E42 -> 0.9999999 | F43: ='Baseline NFPC'!F42 -> 1 | G43: ='Baseline NFPC'!G42 -> 1 | H43: ='Baseline NFPC'!H42 -> 1 | I43: ='Baseline NFPC'!I42 -> 1 | J43: ='Baseline NFPC'!J42 -> 1 | ... W43: ='Baseline NFPC'!W42 -> 1
B45: Intermediate calculations (growth rate equation)
B47: Fiscal multiplier | C47: ='Input data'!C49 -> 0.75
B48: Budget balance semi-elasticity | C48: ='Input data'!C50 -> 0.522
B50: Auxiliary variable to control the closure of the output gap | C50: 0 | D50: =IF(AND(ABS((D12-C12)-('Input data'!D13-'Input data'!C13))>0.0001,ABS(D12-C12)>0.0001,D$10>$C$5),4,IF(C50=4,3,IF(C50=3,2,IF(C50=2,1,0)))) -> 0 | E50: =IF(AND(ABS((E12-D12)-('Input data'!E13-'Input data'!D13))>0.0001,ABS(E12-D12)>0.0001,E$10>$C$5),4,IF(D50=4,3,IF(D50=3,2,IF(D50=2,1,0)))) -> 0 | F50: =IF(AND(ABS((F12-E12)-('Input data'!F13-'Input data'!E13))>0.0001,ABS(F12-E12)>0.0001,F$10>$C$5),4,IF(E50=4,3,IF(E50=3,2,IF(E50=2,1,0)))) -> 0 | G50: =IF(AND(ABS((G12-F12)-('Input data'!G13-'Input data'!F13))>0.0001,ABS(G12-F12)>0.0001,G$10>$C$5),4,IF(F50=4,3,IF(F50=3,2,IF(F50=2,1,0)))) -> 0 | H50: =IF(AND(ABS((H12-G12)-('Input data'!H13-'Input data'!G13))>0.0001,ABS(H12-G12)>0.0001,H$10>$C$5),4,IF(G50=4,3,IF(G50=3,2,IF(G50=2,1,0)))) -> 0 | I50: =IF(AND(ABS((I12-H12)-('Input data'!I13-'Input data'!H13))>0.0001,ABS(I12-H12)>0.0001,I$10>$C$5),4,IF(H50=4,3,IF(H50=3,2,IF(H50=2,1,0)))) -> 0 | J50: =IF(AND(ABS((J12-I12)-('Input data'!J13-'Input data'!I13))>0.0001,ABS(J12-I12)>0.0001,J$10>$C$5),4,IF(I50=4,3,IF(I50=3,2,IF(I50=2,1,0)))) -> 0 | K50: =IF(AND(ABS((K12-J12)-('Input data'!K13-'Input data'!J13))>0.0001,ABS(K12-J12)>0.0001,K$10>$C$5),4,IF(J50=4,3,IF(J50=3,2,IF(J50=2,1,0)))) -> 0 | ... W50: =IF(AND(ABS((W12-V12)-('Input data'!W13-'Input data'!V13))>0.0001,ABS(W12-V12)>0.0001,W$10>$C$5),4,IF(V50=4,3,IF(V50=3,2,IF(V50=2,1,0)))) -> 0
B51: OG intermediate auxiliary value | C51: 0 | D51: =IF(C50=4,2/3*C30,IF(C50=3,1/3*B30,0)) -> 0 | E51: =IF(D50=4,2/3*D30,IF(D50=3,1/3*C30,0)) -> 0 | F51: =IF(E50=4,2/3*E30,IF(E50=3,1/3*D30,0)) -> 0 | G51: =IF(F50=4,2/3*F30,IF(F50=3,1/3*E30,0)) -> 0 | H51: =IF(G50=4,2/3*G30,IF(G50=3,1/3*F30,0)) -> 0 | I51: =IF(H50=4,2/3*H30,IF(H50=3,1/3*G30,0)) -> 0 | J51: =IF(I50=4,2/3*I30,IF(I50=3,1/3*H30,0)) -> 0 | K51: =IF(J50=4,2/3*J30,IF(J50=3,1/3*I30,0)) -> 0 | ... W51: =IF(V50=4,2/3*V30,IF(V50=3,1/3*U30,0)) -> 0
B52: GDP intermediate growth rate - only feedback effect and no closure of the OG | D52: ='Input data'!D30-$C$47*((D12-C12)-('Input data'!D13-'Input data'!C13)) -> 9.433022 | E52: ='Input data'!E30-$C$47*((E12-D12)-('Input data'!E13-'Input data'!D13)) -> -3.198788 | F52: ='Input data'!F30-$C$47*((F12-E12)-('Input data'!F13-'Input data'!E13)) -> 1.243702 | G52: ='Input data'!G30-$C$47*((G12-F12)) -> 3.393806 | H52: ='Input data'!H30-$C$47*((H12-G12)) -> 3.746114 | I52: ='Input data'!I30-$C$47*((I12-H12)) -> 3.802369 | J52: ='Input data'!J30-$C$47*((J12-I12)) -> 3.577386 | K52: ='Input data'!K30-$C$47*((K12-J12)) -> 3.164204 | L52: ='Input data'!L30-$C$47*((L12-K12)) -> 2.938014 | M52: ='Input data'!M30-$C$47*((M12-L12)) -> 2.669411 | N52: ='Input data'!N30-$C$47*((N12-M12)) -> 2.359786 | ... W52: ='Input data'!W30-$C$47*((W12-V12)) -> 1.571112
B54: Debt projections
C56: 2021 | D56: 2022 | E56: 2023 | F56: 2024 | G56: 2025 | H56: 2026 | I56: 2027 | J56: 2028 | K56: 2029 | L56: 2030 | M56: 2031 | N56: 2032 | O56: 2033 | P56: 2034 | Q56: 2035 | R56: 2036 | S56: 2037 | T56: 2038 | U56: 2039 | V56: 2040 | W56: 2041
B57: Gross debt | C57: =+'Input data'!C12 -> 54.39847 | D57: =+C57+D58 -> 44.391772 | E57: =+D57+E58 -> 43.730434 | F57: =+E57+F58 -> 42.488825 | G57: =+F57+G58 -> 41.199314 | H57: =+G57+H58 -> 37.456895 | I57: =+H57+I58 -> 33.593172 | J57: =+I57+J58 -> 29.816315 | K57: =+J57+K58 -> 26.364043 | ... W57: =+V57+W58 -> 2.2971951
B58: Change in debt (-1+2+3) | D58: =-D59+D67+D72 -> -10.006698 | E58: =-E59+E67+E72 -> -0.66133783 | F58: =-F59+F67+F72 -> -1.2416084 | G58: =-G59+G67+G72 -> -1.2895116 | H58: =-H59+H67+H72 -> -3.7424189 | I58: =-I59+I67+I72 -> -3.8637225 | J58: =-J59+J67+J72 -> -3.7768572 | K58: =-K59+K67+K72 -> -3.4522727 | ... W58: =-W59+W67+W72 -> -1.0703826
B59: (1) Primary balance (1.1 + 1.2 - 1.3 -1.4 -1.5 - 1.6 -1.7) | D59: =D60+D61-D62-D63-D64-D65-D66 -> 2.3626831 | E59: =E60+E61-E62-E63-E64-E65-E66 -> 2.3411552 | F59: =F60+F61-F62-F63-F64-F65-F66 -> 1.9481772 | G59: =G60+G61-G62-G63-G64-G65-G66 -> 2.0021496 | H59: =H60+H61-H62-H63-H64-H65-H66 -> 2.1777028 | I59: =I60+I61-I62-I63-I64-I65-I66 -> 2.4117698 | J59: =J60+J61-J62-J63-J64-J65-J66 -> 2.5288044 | K59: =K60+K61-K62-K63-K64-K65-K66 -> 2.4450921 | ... W59: =W60+W61-W62-W63-W64-W65-W66 -> 1.0074193
B60: (1.1) Structural primary balance (before ageing cost) | D60: =D12 -> -2.376722 | E60: =E12 -> 1.712465 | F60: =F12 -> 2.528801 | G60: =IF(G12="",F60,G12) -> 2.528801 | H60: =IF(H12="",G60,H12) -> 2.528801 | I60: =IF(I12="",H60,I12) -> 2.528801 | J60: =IF(J12="",I60,J12) -> 2.528801 | K60: =IF(K12="",J60,K12) -> 2.528801 | L60: =IF(L12="",K60,L12) -> 2.528801 | M60: =IF(M12="",L60,M12) -> 2.528801 | N60: =IF(N12="",M60,N12) -> 2.528801 | ... W60: =IF(W12="",V60,W12) -> 2.528801
B61: (1.2) Cumulated budgetary effort (in terms of primary balance) | D61: 0 | E61: 0 | F61: 0 | G61: 0 | H61: 0 | I61: 0 | J61: 0 | K61: 0 | L61: 0 | M61: 0 | N61: 0 | O61: 0 | P61: 0 | Q61: 0 | R61: 0 | S61: 0 | T61: 0 | U61: 0 | V61: 0 | W61: 0
B62: (1.3) Cyclical component | D62: =-$C$48*D30 -> -4.7394051 | E62: =-$C$48*E30 -> -0.62869023 | F62: =-$C$48*F30 -> 0.58062382 | G62: =-$C$48*G30 -> 0.52665142 | H62: =-$C$48*H30 -> 0.3510982 | I62: =-$C$48*I30 -> 0.11703124 | J62: =-$C$48*J30 -> -3.4308927e-06 | K62: =-$C$48*K30 -> -2.9249033e-06 | ... W62: =-$C$48*W30 -> -1.1634835e-05
B63: (1.4) One-off and other temporary measures | D63: =-D14 -> 0 | E63: =-E14 -> 0 | F63: =-F14 -> 0 | G63: =-G14 -> 0 | H63: =-H14 -> 0 | I63: =-I14 -> 0 | J63: =-J14 -> 0 | K63: =-K14 -> 0 | ... W63: =-W14 -> 0
B64: (1.5) Cost of ageing | D64: =IF(D$56<=$C$6,0,HLOOKUP(D$56,'Input data'!$C$9:$BB$26,12,FALSE)-HLOOKUP($C$6,'Input data'!$C$9:$BB$26,12,FALSE)) -> 0 | E64: =IF(E$56<=$C$6,0,HLOOKUP(E$56,'Input data'!$C$9:$BB$26,12,FALSE)-HLOOKUP($C$6,'Input data'!$C$9:$BB$26,12,FALSE)) -> 0 | F64: =IF(F$56<=$C$6,0,HLOOKUP(F$56,'Input data'!$C$9:$BB$26,12,FALSE)-HLOOKUP($C$6,'Input data'!$C$9:$BB$26,12,FALSE)) -> 0 | G64: =IF(G$56<=$C$6,0,HLOOKUP(G$56,'Input data'!$C$9:$BB$26,12,FALSE)-HLOOKUP($C$6,'Input data'!$C$9:$BB$26,12,FALSE)) -> 0 | H64: =IF(H$56<=$C$6,0,HLOOKUP(H$56,'Input data'!$C$9:$BB$26,12,FALSE)-HLOOKUP($C$6,'Input data'!$C$9:$BB$26,12,FALSE)) -> 0 | I64: =IF(I$56<=$C$6,0,HLOOKUP(I$56,'Input data'!$C$9:$BB$26,12,FALSE)-HLOOKUP($C$6,'Input data'!$C$9:$BB$26,12,FALSE)) -> 0 | J64: =IF(J$56<=$C$6,0,HLOOKUP(J$56,'Input data'!$C$9:$BB$26,12,FALSE)-HLOOKUP($C$6,'Input data'!$C$9:$BB$26,12,FALSE)) -> 0 | K64: =IF(K$56<=$C$6,0,HLOOKUP(K$56,'Input data'!$C$9:$BB$26,12,FALSE)-HLOOKUP($C$6,'Input data'!$C$9:$BB$26,12,FALSE)) -> 0.08591 | ... W64: =IF(W$56<=$C$6,0,HLOOKUP(W$56,'Input data'!$C$9:$BB$26,12,FALSE)-HLOOKUP($C$6,'Input data'!$C$9:$BB$26,12,FALSE)) -> 1.54997
B65: (1.6) Property incomes | D65: =IF(D$56<=$C$5,0,-HLOOKUP(D$56,'Input data'!$C$9:$BB$26,18,FALSE)+HLOOKUP($C$6,'Input data'!$C$9:$BB$26,18,FALSE)) -> 0 | E65: =IF(E$56<=$C$5,0,-HLOOKUP(E$56,'Input data'!$C$9:$BB$26,18,FALSE)+HLOOKUP($C$6,'Input data'!$C$9:$BB$26,18,FALSE)) -> 0 | F65: =IF(F$56<=$C$5,0,-HLOOKUP(F$56,'Input data'!$C$9:$BB$26,18,FALSE)+HLOOKUP($C$6,'Input data'!$C$9:$BB$26,18,FALSE)) -> 0 | G65: =IF(G$56<=$C$6,0,-HLOOKUP(G$56,'Input data'!$C$9:$BB$26,18,FALSE)+HLOOKUP($C$6,'Input data'!$C$9:$BB$26,18,FALSE)) -> 0 | H65: =IF(H$56<=$C$6,0,-HLOOKUP(H$56,'Input data'!$C$9:$BB$26,18,FALSE)+HLOOKUP($C$6,'Input data'!$C$9:$BB$26,18,FALSE)) -> 0 | I65: =IF(I$56<=$C$6,0,-HLOOKUP(I$56,'Input data'!$C$9:$BB$26,18,FALSE)+HLOOKUP($C$6,'Input data'!$C$9:$BB$26,18,FALSE)) -> 0 | J65: =IF(J$56<=$C$6,0,-HLOOKUP(J$56,'Input data'!$C$9:$BB$26,18,FALSE)+HLOOKUP($C$6,'Input data'!$C$9:$BB$26,18,FALSE)) -> 0 | K65: =IF(K$56<=$C$6,0,-HLOOKUP(K$56,'Input data'!$C$9:$BB$26,18,FALSE)+HLOOKUP($C$6,'Input data'!$C$9:$BB$26,18,FALSE)) -> -0.0021982 | L65: =IF(L$56<=$C$6,0,-HLOOKUP(L$56,'Input data'!$C$9:$BB$26,18,FALSE)+HLOOKUP($C$6,'Input data'!$C$9:$BB$26,18,FALSE)) -> -0.0043964 | M65: =IF(M$56<=$C$6,0,-HLOOKUP(M$56,'Input data'!$C$9:$BB$26,18,FALSE)+HLOOKUP($C$6,'Input data'!$C$9:$BB$26,18,FALSE)) -> -0.0065946 | N65: =IF(N$56<=$C$6,0,-HLOOKUP(N$56,'Input data'!$C$9:$BB$26,18,FALSE)+HLOOKUP($C$6,'Input data'!$C$9:$BB$26,18,FALSE)) -> -0.0087928 | ... W65: =IF(W$56<=$C$6,0,-HLOOKUP(W$56,'Input data'!$C$9:$BB$26,18,FALSE)+HLOOKUP($C$6,'Input data'!$C$9:$BB$26,18,FALSE)) -> -0.0285767
B66: (1.7) Revenues | D66: 0 | E66: 0 | F66: 0 | G66: 0 | H66: 0 | I66: 0 | J66: 0 | K66: 0 | L66: 0 | M66: 0 | N66: 0 | O66: 0 | P66: 0 | Q66: 0 | R66: 0 | S66: 0 | T66: 0 | U66: 0 | V66: 0 | W66: 0
B67: (2) Snowball effect (2.1 + 2.2 + 2.3) | D67: =SUM(D68:D71) -> -7.101956 | E67: =SUM(E68:E71) -> 0.8370108 | F67: =SUM(F68:F71) -> -0.9299982 | G67: =SUM(G68:G71) -> -1.487604 | H67: =SUM(H68:H71) -> -1.5647161 | I67: =SUM(I68:I71) -> -1.4519527 | J67: =SUM(J68:J71) -> -1.2480528 | K67: =SUM(K68:K71) -> -1.0071805 | ... W67: =SUM(W68:W71) -> -0.062963227
B68: (2.1) Interest expenditure | D68: =C57*D36/100*(1/(1+D33/100)) -> 0.65707416 | E68: =D57*E36/100*(1/(1+E33/100)) -> 0.69073786 | F68: =E57*F36/100*(1/(1+F33/100)) -> 0.6912335 | G68: =F57*G36/100*(1/(1+G33/100)) -> 0.67917885 | H68: =G57*H36/100*(1/(1+H33/100)) -> 0.69940695 | I68: =H57*I36/100*(1/(1+I33/100)) -> 0.6532045 | J68: =I57*J36/100*(1/(1+J33/100)) -> 0.59578056 | K68: =J57*K36/100*(1/(1+K33/100)) -> 0.53845974 | ... W68: =V57*W36/100*(1/(1+W33/100)) -> 0.064618696
B69: (2.2) Growth effect | D69: =-C57*(D24/100)*(1/(1+D33/100)) -> -4.3995087 | E69: =-D57*(E24/100)*(1/(1+E33/100)) -> 1.4246776 | F69: =-E57*(F24/100)*(1/(1+F33/100)) -> -0.52371299 | G69: =-F57*(G24/100)*(1/(1+G33/100)) -> -1.3684519 | H69: =-G57*(H24/100)*(1/(1+H33/100)) -> -1.4585566 | I69: =-H57*(I24/100)*(1/(1+I33/100)) -> -1.3442035 | J69: =-I57*(J24/100)*(1/(1+J33/100)) -> -1.1357964 | K69: =-J57*(K24/100)*(1/(1+K33/100)) -> -0.89454183 | ... W69: =-V57*(W24/100)*(1/(1+W33/100)) -> -0.050903961
B70: (2.3) Inflation effect | D70: =-C57*D42/100*(1/(1+D42/100)) -> -3.3595209 | E70: =-D57*E42/100*(1/(1+E42/100)) -> -1.2784049 | F70: =-E57*F42/100*(1/(1+F42/100)) -> -1.0975187 | G70: =-F57*G42/100*(1/(1+G42/100)) -> -0.79833004 | H70: =-G57*H42/100*(1/(1+H42/100)) -> -0.80556639 | I70: =-H57*I42/100*(1/(1+I42/100)) -> -0.76095373 | J70: =-I57*J42/100*(1/(1+J42/100)) -> -0.7080369 | K70: =-J57*K42/100*(1/(1+K42/100)) -> -0.65109844 | ... W70: =-V57*W42/100*(1/(1+W42/100)) -> -0.076677962
B71: (2.4) Exchange rate effect linked to the interest rate | D71: ='Baseline NFPC'!D70 -> -5.6246662e-07 | E71: ='Baseline NFPC'!E70 -> 2.0516894e-07 | F71: ='Baseline NFPC'!F70 -> 2.9725664e-08 | G71: ='Baseline NFPC'!G70 -> -8.8262773e-07 | H71: 0 | I71: 0 | J71: 0 | K71: 0 | L71: 0 | M71: 0 | N71: 0 | O71: 0 | P71: 0 | Q71: 0 | R71: 0 | S71: 0 | T71: 0 | U71: 0 | V71: 0 | W71: 0
B72: (3 ) Stock flow adjustments (3.1 + 3.2) | D72: ='Input data'!D16 -> -0.5420594 | E72: ='Input data'!E16 -> 0.8428066 | F72: ='Input data'!F16 -> 1.636567 | G72: ='Input data'!G16 -> 2.200242 | H72: ='Input data'!H16 -> 0 | I72: ='Input data'!I16 -> 0 | J72: ='Input data'!J16 -> 0 | K72: ='Input data'!K16 -> 0 | ... W72: ='Input data'!W16 -> 0
B73: (3.1) Base | D73: =D15 -> -0.5420614 | E73: =E15 -> 0.8428086 | F73: =F15 -> 1.636568 | G73: =G15 -> 2.20024 | H73: =H15 -> 0 | I73: =I15 -> 0 | J73: =J15 -> 0 | K73: =K15 -> 0 | ... W73: =W15 -> 0
B74: (3.2) Adjustment due to the exchange rate effect linked to debt value | D74: =+D72-D73 -> 2e-06 | E74: =+E72-E73 -> -2e-06 | F74: =+F72-F73 -> -1e-06 | G74: =+G72-G73 -> 2e-06 | H74: =+H72-H73 -> 0 | I74: =+I72-I73 -> 0 | J74: =+J72-J73 -> 0 | K74: =+K72-K73 -> 0 | ... W74: =+W72-W73 -> 0
B76: Other budgetary variables
B77: Headline balance | D77: =D59-D68 -> 1.7056089 | E77: =E59-E68 -> 1.6504174 | F77: =F59-F68 -> 1.2569437 | G77: =G59-G68 -> 1.3229707 | H77: =H59-H68 -> 1.4782958 | I77: =I59-I68 -> 1.7585653 | J77: =J59-J68 -> 1.9330239 | K77: =K59-K68 -> 1.9066324 | ... W77: =W59-W68 -> 0.94280064
B78: Structural balance | D78: =D60-D68-D64-D65-D66 -> -3.0337962 | E78: =E60-E68-E64-E65-E66 -> 1.0217271 | F78: =F60-F68-F64-F65-F66 -> 1.8375675 | G78: =G60-G68-G64-G65-G66 -> 1.8496221 | H78: =H60-H68-H64-H65-H66 -> 1.829394 | I78: =I60-I68-I64-I65-I66 -> 1.8755965 | J78: =J60-J68-J64-J65-J66 -> 1.9330204 | K78: =K60-K68-K64-K65-K66 -> 1.9066295 | ... W78: =W60-W68-W64-W65-W66 -> 0.942789
B79: Net expenditure growth | D79: ='Input data'!D45 -> 14.052581 | E79: ='Input data'!E45 -> 13.567155 | F79: ='Input data'!F45 -> 7.3776443 | G79: ='Input data'!G33+G42-(G$12-F$12)/'Input data'!$C$64*100 -> 5.200709 | H79: ='Input data'!H33+H42-(H$12-G$12)/'Input data'!$C$64*100 -> 5.3891289 | I79: ='Input data'!I33+I42-(I$12-H$12)/'Input data'!$C$64*100 -> 5.4095418 | J79: ='Input data'!J33+J42-(J$12-I$12)/'Input data'!$C$64*100 -> 5.4982216 | K79: ='Input data'!K33+K42-(K$12-J$12)/'Input data'!$C$64*100 -> 5.3966535 | L79: ='Input data'!L33+L42-(L$12-K$12)/'Input data'!$C$64*100 -> 5.2498504 | M79: ='Input data'!M33+M42-(M$12-L$12)/'Input data'!$C$64*100 -> 5.0606333 | N79: ='Input data'!N33+N42-(N$12-M$12)/'Input data'!$C$64*100 -> 4.8303961 | ... W79: ='Input data'!W33+W42-(W$12-V$12)/'Input data'!$C$64*100 -> 3.901108
B81: Average net primary expenditure growth | D81: =AVERAGE(OFFSET($G$79,0,0,1,'Criteria results'!F5)) -> 5.3744003
B83: Debt decreasing? (For criterion 1) | K83: =IF(K57<J57,0,1) -> 0 | L83: =IF(L57<K57,0,1) -> 0 | M83: =IF(M57<L57,0,1) -> 0 | N83: =IF(N57<M57,0,1) -> 0 | O83: =IF(O57<N57,0,1) -> 0 | P83: =IF(P57<O57,0,1) -> 0 | Q83: =IF(Q57<P57,0,1) -> 0 | R83: =IF(R57<Q57,0,1) -> 0 | ... W83: =IF(W57<V57,0,1) -> 0
B85: Debt decomposition and IIR
B87: Auxiliary variable identifying whether debt is increasing | D87: =IF((D92-C92*D43/((1+D24/100)*(1+D42/100)))>0,1,0) -> 0 | E87: =IF((E92-D92*E43/((1+E24/100)*(1+E42/100)))>0,1,0) -> 0 | F87: =IF((F92-E92*F43/((1+F24/100)*(1+F42/100)))>0,1,0) -> 1 | G87: =IF((G92-F92*G43/((1+G24/100)*(1+G42/100)))>0,1,0) -> 1 | H87: =IF((H92-G92*H43/((1+H24/100)*(1+H42/100)))>0,1,0) -> 0 | I87: =IF((I92-H92*I43/((1+I24/100)*(1+I42/100)))>0,1,0) -> 0 | J87: =IF((J92-I92*J43/((1+J24/100)*(1+J42/100)))>0,1,0) -> 0 | K87: =IF((K92-J92*K43/((1+K24/100)*(1+K42/100)))>0,1,0) -> 0 | ... W87: =IF((W92-V92*W43/((1+W24/100)*(1+W42/100)))>0,1,0) -> 0
B88: Auxiliary variable identifying whether some debt is rolled over even though debt is decreasing | D88: =IF(AND(D87=0,ABS(D92-C92*D43/((1+D24/100)*(1+D42/100)))<((C98*C92*D43/((1+D24/100)*(1+D42/100))+(D39*C92*C99*D43/((1+D24/100)*(1+D42/100)))))),1,0) -> 0 | E88: =IF(AND(E87=0,ABS(E92-D92*E43/((1+E24/100)*(1+E42/100)))<((D98*D92*E43/((1+E24/100)*(1+E42/100))+(E39*D92*D99*E43/((1+E24/100)*(1+E42/100)))))),1,0) -> 1 | F88: =IF(AND(F87=0,ABS(F92-E92*F43/((1+F24/100)*(1+F42/100)))<((E98*E92*F43/((1+F24/100)*(1+F42/100))+(F39*E92*E99*F43/((1+F24/100)*(1+F42/100)))))),1,0) -> 0 | G88: =IF(AND(G87=0,ABS(G92-F92*G43/((1+G24/100)*(1+G42/100)))<((F98*F92*G43/((1+G24/100)*(1+G42/100))+(G39*F92*F99*G43/((1+G24/100)*(1+G42/100)))))),1,0) -> 0 | H88: =IF(AND(H87=0,ABS(H92-G92*H43/((1+H24/100)*(1+H42/100)))<((G98*G92*H43/((1+H24/100)*(1+H42/100))+(H39*G92*G99*H43/((1+H24/100)*(1+H42/100)))))),1,0) -> 1 | I88: =IF(AND(I87=0,ABS(I92-H92*I43/((1+I24/100)*(1+I42/100)))<((H98*H92*I43/((1+I24/100)*(1+I42/100))+(I39*H92*H99*I43/((1+I24/100)*(1+I42/100)))))),1,0) -> 1 | J88: =IF(AND(J87=0,ABS(J92-I92*J43/((1+J24/100)*(1+J42/100)))<((I98*I92*J43/((1+J24/100)*(1+J42/100))+(J39*I92*I99*J43/((1+J24/100)*(1+J42/100)))))),1,0) -> 1 | K88: =IF(AND(K87=0,ABS(K92-J92*K43/((1+K24/100)*(1+K42/100)))<((J98*J92*K43/((1+K24/100)*(1+K42/100))+(K39*J92*J99*K43/((1+K24/100)*(1+K42/100)))))),1,0) -> 1 | ... W88: =IF(AND(W87=0,ABS(W92-V92*W43/((1+W24/100)*(1+W42/100)))<((V98*V92*W43/((1+W24/100)*(1+W42/100))+(W39*V92*V99*W43/((1+W24/100)*(1+W42/100)))))),1,0) -> 0
C91: 2021 | D91: 2022 | E91: 2023 | F91: 2024 | G91: 2025 | H91: 2026 | I91: 2027 | J91: 2028 | K91: 2029 | L91: 2030 | M91: 2031 | N91: 2032 | O91: 2033 | P91: 2034 | Q91: 2035 | R91: 2036 | S91: 2037 | T91: 2038 | U91: 2039 | V91: 2040 | W91: 2041
B92: Gross debt | C92: =C57 -> 54.39847 | D92: =D57 -> 44.391772 | E92: =E57 -> 43.730434 | F92: =F57 -> 42.488825 | G92: =G57 -> 41.199314 | H92: =G92*(1+H106/100)*H43-H60-H61+H62+H63+H64+H65+H66+H72 -> 37.456895 | I92: =H92*(1+I106/100)*I43-I60-I61+I62+I63+I64+I65+I66+I72 -> 33.593172 | J92: =I92*(1+J106/100)*J43-J60-J61+J62+J63+J64+J65+J66+J72 -> 29.816315 | K92: =J92*(1+K106/100)*K43-K60-K61+K62+K63+K64+K65+K66+K72 -> 26.364043 | L92: =K92*(1+L106/100)*L43-L60-L61+L62+L63+L64+L65+L66+L72 -> 23.177269 | M92: =L92*(1+M106/100)*M43-M60-M61+M62+M63+M64+M65+M66+M72 -> 20.25762 | N92: =M92*(1+N106/100)*N43-N60-N61+N62+N63+N64+N65+N66+N72 -> 17.655639 | O92: =N92*(1+O106/100)*O43-O60-O61+O62+O63+O64+O65+O66+O72 -> 15.251051 | ... W92: =V92*(1+W106/100)*W43-W60-W61+W62+W63+W64+W65+W66+W72 -> 2.2971951
B93: Of which Outstanding debt | D93: ='Input data'!C66*$D$92 -> 37.416473 | E93: =IF(E92=0,0,IF(E87=1,D92*E43/((1+E24/100)*(1+E42/100))-E94-E95,IF(AND(E87=0,E88=1),(1-D98-E39*D99)*D92*E43/((1+E24/100)*(1+E42/100)),E92))) -> 37.985689 | F93: =IF(F92=0,0,IF(F87=1,E92*F43/((1+F24/100)*(1+F42/100))-F94-F95,IF(AND(F87=0,F88=1),(1-E98-F39*E99)*E92*F43/((1+F24/100)*(1+F42/100)),F92))) -> 36.086221 | G93: =IF(G92=0,0,IF(G87=1,F92*G43/((1+G24/100)*(1+G42/100))-G94-G95,IF(AND(G87=0,G88=1),(1-F98-G39*F99)*F92*G43/((1+G24/100)*(1+G42/100)),G92))) -> 34.066502 | H93: =IF(H92=0,0,IF(H87=1,G92*H43/((1+H24/100)*(1+H42/100))-H94-H95,IF(AND(H87=0,H88=1),(1-G98-H39*G99)*G92*H43/((1+H24/100)*(1+H42/100)),H92))) -> 32.665878 | I93: =IF(I92=0,0,IF(I87=1,H92*I43/((1+I24/100)*(1+I42/100))-I94-I95,IF(AND(I87=0,I88=1),(1-H98-I39*H99)*H92*I43/((1+I24/100)*(1+I42/100)),I92))) -> 30.609328 | J93: =IF(J92=0,0,IF(J87=1,I92*J43/((1+J24/100)*(1+J42/100))-J94-J95,IF(AND(J87=0,J88=1),(1-I98-J39*I99)*I92*J43/((1+J24/100)*(1+J42/100)),J92))) -> 27.996255 | K93: =IF(K92=0,0,IF(K87=1,J92*K43/((1+K24/100)*(1+K42/100))-K94-K95,IF(AND(K87=0,K88=1),(1-J98-K39*J99)*J92*K43/((1+K24/100)*(1+K42/100)),K92))) -> 25.397506 | L93: =IF(L92=0,0,IF(L87=1,K92*L43/((1+L24/100)*(1+L42/100))-L94-L95,IF(AND(L87=0,L88=1),(1-K98-L39*K99)*K92*L43/((1+L24/100)*(1+L42/100)),L92))) -> 22.973688 | ... W93: =IF(W92=0,0,IF(W87=1,V92*W43/((1+W24/100)*(1+W42/100))-W94-W95,IF(AND(W87=0,W88=1),(1-V98-W39*V99)*V92*W43/((1+W24/100)*(1+W42/100)),W92))) -> 2.2971951
B94: Rolled over long-term debt | D94: ='Input data'!C67*$D$92 -> 2.3067736 | E94: =IF(E92=0,0,IF(E87=1,E39*D92*D99*E43/((1+E24/100)*(1+E42/100)),IF(AND(E87=0,E88=1),(E39*D92*D99*E43/((1+E24/100)*(1+E42/100)))*(1-ABS(E92-D92*E43/((1+E24/100)*(1+E42/100)))/((E39*D92*D99*E43/((1+E24/100)*(1+E42/100)))+(D98*D92*E43/((1+E24/100)*(1+E42/100))))),0))) -> 1.6381495 | F94: =IF(F92=0,0,IF(F87=1,F39*E92*E99*F43/((1+F24/100)*(1+F42/100)),IF(AND(F87=0,F88=1),(F39*E92*E99*F43/((1+F24/100)*(1+F42/100)))*(1-ABS(F92-E92*F43/((1+F24/100)*(1+F42/100)))/((F39*E92*E99*F43/((1+F24/100)*(1+F42/100)))+(E98*E92*F43/((1+F24/100)*(1+F42/100))))),0))) -> 2.0686309 | G94: =IF(G92=0,0,IF(G87=1,G39*F92*F99*G43/((1+G24/100)*(1+G42/100)),IF(AND(G87=0,G88=1),(G39*F92*F99*G43/((1+G24/100)*(1+G42/100)))*(1-ABS(G92-F92*G43/((1+G24/100)*(1+G42/100)))/((G39*F92*F99*G43/((1+G24/100)*(1+G42/100)))+(F98*F92*G43/((1+G24/100)*(1+G42/100))))),0))) -> 2.4597944 | H94: =IF(H92=0,0,IF(H87=1,H39*G92*G99*H43/((1+H24/100)*(1+H42/100)),IF(AND(H87=0,H88=1),(H39*G92*G99*H43/((1+H24/100)*(1+H42/100)))*(1-ABS(H92-G92*H43/((1+H24/100)*(1+H42/100)))/((H39*G92*G99*H43/((1+H24/100)*(1+H42/100)))+(G98*G92*H43/((1+H24/100)*(1+H42/100))))),0))) -> 1.9739953 | I94: =IF(I92=0,0,IF(I87=1,I39*H92*H99*I43/((1+I24/100)*(1+I42/100)),IF(AND(I87=0,I88=1),(I39*H92*H99*I43/((1+I24/100)*(1+I42/100)))*(1-ABS(I92-H92*I43/((1+I24/100)*(1+I42/100)))/((I39*H92*H99*I43/((1+I24/100)*(1+I42/100)))+(H98*H92*I43/((1+I24/100)*(1+I42/100))))),0))) -> 1.3110357 | J94: =IF(J92=0,0,IF(J87=1,J39*I92*I99*J43/((1+J24/100)*(1+J42/100)),IF(AND(J87=0,J88=1),(J39*I92*I99*J43/((1+J24/100)*(1+J42/100)))*(1-ABS(J92-I92*J43/((1+J24/100)*(1+J42/100)))/((J39*I92*I99*J43/((1+J24/100)*(1+J42/100)))+(I98*I92*J43/((1+J24/100)*(1+J42/100))))),0))) -> 1.0533569 | K94: =IF(K92=0,0,IF(K87=1,K39*J92*J99*K43/((1+K24/100)*(1+K42/100)),IF(AND(K87=0,K88=1),(K39*J92*J99*K43/((1+K24/100)*(1+K42/100)))*(1-ABS(K92-J92*K43/((1+K24/100)*(1+K42/100)))/((K39*J92*J99*K43/((1+K24/100)*(1+K42/100)))+(J98*J92*K43/((1+K24/100)*(1+K42/100))))),0))) -> 0.72198685 | L94: =IF(L92=0,0,IF(L87=1,L39*K92*K99*L43/((1+L24/100)*(1+L42/100)),IF(AND(L87=0,L88=1),(L39*K92*K99*L43/((1+L24/100)*(1+L42/100)))*(1-ABS(L92-K92*L43/((1+L24/100)*(1+L42/100)))/((L39*K92*K99*L43/((1+L24/100)*(1+L42/100)))+(K98*K92*L43/((1+L24/100)*(1+L42/100))))),0))) -> 0.18062463 | ... W94: =IF(W92=0,0,IF(W87=1,W39*V92*V99*W43/((1+W24/100)*(1+W42/100)),IF(AND(W87=0,W88=1),(W39*V92*V99*W43/((1+W24/100)*(1+W42/100)))*(1-ABS(W92-V92*W43/((1+W24/100)*(1+W42/100)))/((W39*V92*V99*W43/((1+W24/100)*(1+W42/100)))+(V98*V92*W43/((1+W24/100)*(1+W42/100))))),0))) -> 0
B95: Rolled over short-term debt | D95: ='Input data'!C68*$D$92 -> 4.6685201 | E95: =IF(E92=0,0,IF(E87=1,(1-D99)*D92*E43/((1+E24/100)*(1+E42/100)),IF(AND(E87=0,E88=1),(D98*D92*E43/((1+E24/100)*(1+E42/100)))*(1-ABS(E92-D92*E43/((1+E24/100)*(1+E42/100)))/((E39*D92*D99*E43/((1+E24/100)*(1+E42/100)))+(D98*D92*E43/((1+E24/100)*(1+E42/100))))),0))) -> 4.1065954 | F95: =IF(F92=0,0,IF(F87=1,(1-E99)*E92*F43/((1+F24/100)*(1+F42/100)),IF(AND(F87=0,F88=1),(E98*E92*F43/((1+F24/100)*(1+F42/100)))*(1-ABS(F92-E92*F43/((1+F24/100)*(1+F42/100)))/((F39*E92*E99*F43/((1+F24/100)*(1+F42/100)))+(E98*E92*F43/((1+F24/100)*(1+F42/100))))),0))) -> 3.9543503 | G95: =IF(G92=0,0,IF(G87=1,(1-F99)*F92*G43/((1+G24/100)*(1+G42/100)),IF(AND(G87=0,G88=1),(F98*F92*G43/((1+G24/100)*(1+G42/100)))*(1-ABS(G92-F92*G43/((1+G24/100)*(1+G42/100)))/((G39*F92*F99*G43/((1+G24/100)*(1+G42/100)))+(F98*F92*G43/((1+G24/100)*(1+G42/100))))),0))) -> 3.7957467 | H95: =IF(H92=0,0,IF(H87=1,(1-G99)*G92*H43/((1+H24/100)*(1+H42/100)),IF(AND(H87=0,H88=1),(G98*G92*H43/((1+H24/100)*(1+H42/100)))*(1-ABS(H92-G92*H43/((1+H24/100)*(1+H42/100)))/((H39*G92*G99*H43/((1+H24/100)*(1+H42/100)))+(G98*G92*H43/((1+H24/100)*(1+H42/100))))),0))) -> 2.8170211 | I95: =IF(I92=0,0,IF(I87=1,(1-H99)*H92*I43/((1+I24/100)*(1+I42/100)),IF(AND(I87=0,I88=1),(H98*H92*I43/((1+I24/100)*(1+I42/100)))*(1-ABS(I92-H92*I43/((1+I24/100)*(1+I42/100)))/((I39*H92*H99*I43/((1+I24/100)*(1+I42/100)))+(H98*H92*I43/((1+I24/100)*(1+I42/100))))),0))) -> 1.6728084 | J95: =IF(J92=0,0,IF(J87=1,(1-I99)*I92*J43/((1+J24/100)*(1+J42/100)),IF(AND(J87=0,J88=1),(I98*I92*J43/((1+J24/100)*(1+J42/100)))*(1-ABS(J92-I92*J43/((1+J24/100)*(1+J42/100)))/((J39*I92*I99*J43/((1+J24/100)*(1+J42/100)))+(I98*I92*J43/((1+J24/100)*(1+J42/100))))),0))) -> 0.76670328 | K95: =IF(K92=0,0,IF(K87=1,(1-J99)*J92*K43/((1+K24/100)*(1+K42/100)),IF(AND(K87=0,K88=1),(J98*J92*K43/((1+K24/100)*(1+K42/100)))*(1-ABS(K92-J92*K43/((1+K24/100)*(1+K42/100)))/((K39*J92*J99*K43/((1+K24/100)*(1+K42/100)))+(J98*J92*K43/((1+K24/100)*(1+K42/100))))),0))) -> 0.24454937 | L95: =IF(L92=0,0,IF(L87=1,(1-K99)*K92*L43/((1+L24/100)*(1+L42/100)),IF(AND(L87=0,L88=1),(K98*K92*L43/((1+L24/100)*(1+L42/100)))*(1-ABS(L92-K92*L43/((1+L24/100)*(1+L42/100)))/((L39*K92*K99*L43/((1+L24/100)*(1+L42/100)))+(K98*K92*L43/((1+L24/100)*(1+L42/100))))),0))) -> 0.022956839 | ... W95: =IF(W92=0,0,IF(W87=1,(1-V99)*V92*W43/((1+W24/100)*(1+W42/100)),IF(AND(W87=0,W88=1),(V98*V92*W43/((1+W24/100)*(1+W42/100)))*(1-ABS(W92-V92*W43/((1+W24/100)*(1+W42/100)))/((W39*V92*V99*W43/((1+W24/100)*(1+W42/100)))+(V98*V92*W43/((1+W24/100)*(1+W42/100))))),0))) -> 0
B96: New long-term debt | D96: ='Input data'!C69*$D$92 -> 0 | E96: =IF(E92=0,0,IF(E87=1,'Input data'!$C$58*(E92-D92*E43/((1+E24/100)*(1+E42/100))),0)) -> 0 | F96: =IF(F92=0,0,IF(F87=1,'Input data'!$C$58*(F92-E92*F43/((1+F24/100)*(1+F42/100))),0)) -> 0.33425532 | G96: =IF(G92=0,0,IF(G87=1,'Input data'!$C$58*(G92-F92*G43/((1+G24/100)*(1+G42/100))),0)) -> 0.77242956 | H96: =IF(H92=0,0,IF(H87=1,'Input data'!$C$58*(H92-G92*H43/((1+H24/100)*(1+H42/100))),0)) -> 0 | I96: =IF(I92=0,0,IF(I87=1,'Input data'!$C$58*(I92-H92*I43/((1+I24/100)*(1+I42/100))),0)) -> 0 | J96: =IF(J92=0,0,IF(J87=1,'Input data'!$C$58*(J92-I92*J43/((1+J24/100)*(1+J42/100))),0)) -> 0 | K96: =IF(K92=0,0,IF(K87=1,'Input data'!$C$58*(K92-J92*K43/((1+K24/100)*(1+K42/100))),0)) -> 0 | L96: =IF(L92=0,0,IF(L87=1,'Input data'!$C$58*(L92-K92*L43/((1+L24/100)*(1+L42/100))),0)) -> 0 | ... W96: =IF(W92=0,0,IF(W87=1,'Input data'!$C$58*(W92-V92*W43/((1+W24/100)*(1+W42/100))),0)) -> 0
B97: New short-term debt | D97: ='Input data'!C70*$D$92 -> 0 | E97: =IF(E92=0,0,IF(E87=1,'Input data'!$C$57*(E92-D92*E43/((1+E24/100)*(1+E42/100))),0)) -> 0 | F97: =IF(F92=0,0,IF(F87=1,'Input data'!$C$57*(F92-E92*F43/((1+F24/100)*(1+F42/100))),0)) -> 0.045368027 | G97: =IF(G92=0,0,IF(G87=1,'Input data'!$C$57*(G92-F92*G43/((1+G24/100)*(1+G42/100))),0)) -> 0.10484083 | H97: =IF(H92=0,0,IF(H87=1,'Input data'!$C$57*(H92-G92*H43/((1+H24/100)*(1+H42/100))),0)) -> 0 | I97: =IF(I92=0,0,IF(I87=1,'Input data'!$C$57*(I92-H92*I43/((1+I24/100)*(1+I42/100))),0)) -> 0 | J97: =IF(J92=0,0,IF(J87=1,'Input data'!$C$57*(J92-I92*J43/((1+J24/100)*(1+J42/100))),0)) -> 0 | K97: =IF(K92=0,0,IF(K87=1,'Input data'!$C$57*(K92-J92*K43/((1+K24/100)*(1+K42/100))),0)) -> 0 | L97: =IF(L92=0,0,IF(L87=1,'Input data'!$C$57*(L92-K92*L43/((1+L24/100)*(1+L42/100))),0)) -> 0 | ... W97: =IF(W92=0,0,IF(W87=1,'Input data'!$C$57*(W92-V92*W43/((1+W24/100)*(1+W42/100))),0)) -> 0
B98: Share of short-term debt in total government debt | D98: ='Baseline NFPC'!$D$93 -> 0.10516645 | E98: =IF(E92<>0,(E95+E97)/(E93+E94+E95+E96+E97),0) -> 0.093907036 | F98: =IF(F92<>0,(F95+F97)/(F93+F94+F95+F96+F97),0) -> 0.094135772 | G98: =IF(G92<>0,(G95+G97)/(G93+G94+G95+G96+G97),0) -> 0.094676031 | H98: =IF(H92<>0,(H95+H97)/(H93+H94+H95+H96+H97),0) -> 0.075207012 | I98: =IF(I92<>0,(I95+I97)/(I93+I94+I95+I96+I97),0) -> 0.049796082 | J98: =IF(J92<>0,(J95+J97)/(J93+J94+J95+J96+J97),0) -> 0.02571422 | K98: =IF(K92<>0,(K95+K97)/(K93+K94+K95+K96+K97),0) -> 0.0092758676 | L98: =IF(L92<>0,(L95+L97)/(L93+L94+L95+L96+L97),0) -> 0.00099048936 | ... W98: =IF(W92<>0,(W95+W97)/(W93+W94+W95+W96+W97),0) -> 0
B99: Share of long-term debt in total government debt | D99: ='Baseline NFPC'!$D$94 -> 0.89483355 | E99: =IF(E92<>0,(E93+E94+E96)/(E93+E94+E95+E96+E97),1) -> 0.90609296 | F99: =IF(F92<>0,(F93+F94+F96)/(F93+F94+F95+F96+F97),1) -> 0.90586423 | G99: =IF(G92<>0,(G93+G94+G96)/(G93+G94+G95+G96+G97),1) -> 0.90532397 | H99: =IF(H92<>0,(H93+H94+H96)/(H93+H94+H95+H96+H97),1) -> 0.92479299 | I99: =IF(I92<>0,(I93+I94+I96)/(I93+I94+I95+I96+I97),1) -> 0.95020392 | J99: =IF(J92<>0,(J93+J94+J96)/(J93+J94+J95+J96+J97),1) -> 0.97428578 | K99: =IF(K92<>0,(K93+K94+K96)/(K93+K94+K95+K96+K97),1) -> 0.99072413 | L99: =IF(L92<>0,(L93+L94+L96)/(L93+L94+L95+L96+L97),1) -> 0.99900951 | ... W99: =IF(W92<>0,(W93+W94+W96)/(W93+W94+W95+W96+W97),1) -> 1
B101: IIR | C101: ='Baseline NFPC'!C96 -> 1.510173 | D101: ='Baseline NFPC'!D96 -> 1.408838 | E101: ='Baseline NFPC'!E96 -> 1.550894 | F101: ='Baseline NFPC'!F96 -> 1.641526 | G101: ='Baseline NFPC'!G96 -> 1.684386 | H101: =H103+H104 -> 1.7963363 | I101: =I103+I104 -> 1.8477296 | J101: =J103+J104 -> 1.8765133 | K101: =K103+K104 -> 1.9046582 | L101: =L103+L104 -> 1.9309319 | M101: =M103+M104 -> 1.9360734 | N101: =N103+N104 -> 1.9574641 | O101: =O103+O104 -> 1.9793499 | ... W101: =W103+W104 -> 1.9944068
B102: Long-term implicit interest rate | E102: =((E36*D92)-(E38*(D95+D97)))/(D93+D94+D96) -> 1.3300501 | F102: =((F36*E92)-(F38*(E95+E97)))/(E93+E94+E96) -> 1.4422602 | G102: =((G36*F92)-(G38*(F95+F97)))/(F93+F94+F96) -> 1.5667518 | H102: =IF(G92>0,(G102*G93+H37*(G96+G94))/(G93+G94+G96),H37) -> 1.6908439 | I102: =IF(H92>0,(H102*H93+I37*(H96+H94))/(H93+H94+H96),I37) -> 1.7707919 | J102: =IF(I92>0,(I102*I93+J37*(I96+I94))/(I93+I94+I96),J37) -> 1.8290335 | K102: =IF(J92>0,(J102*J93+K37*(J96+J94))/(J93+J94+J96),K37) -> 1.8817868 | L102: =IF(K92>0,(K102*K93+L37*(K96+K94))/(K93+K94+K96),L37) -> 1.9231701 | M102: =IF(L92>0,(L102*L93+M37*(L96+L94))/(L93+L94+L96),M37) -> 1.9352677 | N102: =IF(M92>0,(M102*M93+N37*(M96+M94))/(M93+M94+M96),N37) -> 1.9573515 | O102: =IF(N92>0,(N102*N93+O37*(N96+N94))/(N93+N94+N96),O37) -> 1.9793357 | ... W102: =IF(V92>0,(V102*V93+W37*(V96+V94))/(V93+V94+V96),W37) -> 1.9944068
B103: Nominal implicit interest rate on debt (Excel approximation) | E103: =(E102*(D93+D94+D96)+E38*(D95+D97))/D92 -> 1.550894 | F103: =(F102*(E93+E94+E96)+F38*(E95+E97))/E92 -> 1.641526 | G103: =(G102*(F93+F94+F96)+G38*(F95+F97))/F92 -> 1.684386 | H103: =(H102*(G93+G94+G96)+H38*(G95+G97))/G92 -> 1.7963363 | I103: =(I102*(H93+H94+H96)+I38*(H95+H97))/H92 -> 1.8477296 | J103: =(J102*(I93+I94+I96)+J38*(I95+I97))/I92 -> 1.8765133 | K103: =(K102*(J93+J94+J96)+K38*(J95+J97))/J92 -> 1.9046582 | L103: =(L102*(K93+K94+K96)+L38*(K95+K97))/K92 -> 1.9309319 | ... W103: =(W102*(V93+V94+V96)+W38*(V95+V97))/V92 -> 1.9944068
B104: Diff. STATA | E104: =IF('Criteria results'!$F$5=4,E115,E120) -> 0 | F104: =IF('Criteria results'!$F$5=4,F115,F120) -> 0 | G104: =IF('Criteria results'!$F$5=4,G115,G120) -> 0 | H104: =IF('Criteria results'!$F$5=4,H115,H120) -> 0 | I104: =IF('Criteria results'!$F$5=4,I115,I120) -> 0 | J104: =IF('Criteria results'!$F$5=4,J115,J120) -> 0 | K104: =IF('Criteria results'!$F$5=4,K115,K120) -> 0 | L104: =IF('Criteria results'!$F$5=4,L115,L120) -> 0 | ... W104: =IF('Criteria results'!$F$5=4,W115,W120) -> 0
B106: (i - g) | C106: =((1+C101/100)/((1+C24/100)*(1+C42/100))-1)*100 -> -12.245307 | D106: =((1+D101/100)/((1+D24/100)*(1+D42/100))-1)*100 -> -13.055432 | E106: =((1+E101/100)/((1+E24/100)*(1+E42/100))-1)*100 -> 1.8855084 | F106: =((1+F101/100)/((1+F24/100)*(1+F42/100))-1)*100 -> -2.1266613 | G106: =((1+G101/100)/((1+G24/100)*(1+G42/100))-1)*100 -> -3.5011632 | H106: =((1+H101/100)/((1+H24/100)*(1+H42/100))-1)*100 -> -3.7979178 | I106: =((1+I101/100)/((1+I24/100)*(1+I42/100))-1)*100 -> -3.8763297 | J106: =((1+J101/100)/((1+J24/100)*(1+J42/100))-1)*100 -> -3.7151976 | ... W106: =((1+W101/100)/((1+W24/100)*(1+W42/100))-1)*100 -> -1.869689
B110: Per memo - STATA results
B112: No extension (annual adjustment of -0.8)
B113: Debt | C113: 54.398468 | D113: 44.391777 | E113: 43.730442 | F113: 42.488838 | G113: 41.462902 | H113: 38.661674 | I113: 36.633694 | J113: 35.368382 | K113: 34.732727 | L113: 34.504211 | M113: 34.700706 | N113: 35.077141 | O113: 35.663364 | P113: 36.440842 | Q113: 37.388653 | R113: 38.520004 | S113: 39.824409 | T113: 41.228771 | U113: 42.789692 | V113: 44.522644 | W113: 46.452255
B114: IIR | C114: 1.5101732 | D114: 1.4088377 | E114: 1.5508943 | F114: 1.6415262 | G114: 1.6843857 | H114: 1.810593 | I114: 1.8917614 | J114: 1.9761521 | K114: 2.091527 | L114: 2.2211409 | M114: 2.351516 | N114: 2.5077391 | O114: 2.6643815 | P114: 2.8055639 | Q114: 2.9088902 | R114: 3.0041041 | S114: 3.0832279 | T114: 3.1544199 | U114: 3.2174096 | V114: 3.2736189 | W114: 3.323797
B115: IIR difference STATA - Excel | E115: 0 | F115: 0 | G115: 0 | H115: 0 | I115: 0 | J115: 0 | K115: 0 | L115: 0 | M115: 0 | N115: 0 | O115: 0 | P115: 0 | Q115: 0 | R115: 0 | S115: 0 | T115: 0 | U115: 0 | V115: 0 | W115: 0
B117: Extension (annual adjustment of -0.44)
B118: Debt | C118: 54.398468 | D118: 44.391777 | E118: 43.730442 | F118: 42.488838 | G118: 41.343952 | H118: 38.119839 | I118: 35.356796 | J118: 33.042496 | K118: 31.24971 | L118: 29.9893 | M118: 29.264046 | N118: 29.087009 | O118: 29.2516 | P118: 29.747686 | Q118: 30.330738 | R118: 31.093307 | S118: 32.028805 | T118: 33.06105 | U118: 34.245243 | V118: 35.594925 | W118: 37.131298
B119: IIR | C119: 1.5101732 | D119: 1.4088377 | E119: 1.5508943 | F119: 1.6415262 | G119: 1.6843857 | H119: 1.8041999 | I119: 1.8723178 | J119: 1.9348419 | K119: 2.0175152 | L119: 2.118664 | M119: 2.227807 | N119: 2.3753383 | O119: 2.5342138 | P119: 2.6870344 | Q119: 2.8031945 | R119: 2.9117846 | S119: 3.0027976 | T119: 3.0854626 | U119: 3.1588612 | V119: 3.2245834 | W119: 3.2833312
B120: IIR difference STATA - Excel | G120: 0 | H120: 0 | I120: 0 | J120: 0 | K120: 0 | L120: 0 | M120: 0 | N120: 0 | O120: 0 | P120: 0 | Q120: 0 | R120: 0 | S120: 0 | T120: 0 | U120: 0 | V120: 0 | W120: 0

Sheet FASTOP reporting
C2: Table 7a: Debt and headline balance projections and key underlying assumptions (under the planned fiscal path)
D4: line | E4: =F4-1 -> 2022 | F4: ='Input data'!$C$5-1 -> 2023 | G4: =F4+1 -> 2024 | H4: =G4+1 -> 2025 | I4: =H4+1 -> 2026 | J4: =I4+1 -> 2027 | K4: =J4+1 -> 2028 | L4: =K4+1 -> 2029 | M4: =L4+1 -> 2030 | N4: =M4+1 -> 2031 | ... X4: =W4+1 -> 2041
B5: 1 | C5: Gross debt | D5: 57 | E5: (% GDP) | F5: =INDEX(OFFSET('Adjustment scenario'!$D$1:$W$1,$D5-1,0),MATCH(F$4,'Adjustment scenario'!$D$10:$W$10,0)) -> 43.730434 | G5: =INDEX(OFFSET('Adjustment scenario'!$D$1:$W$1,$D5-1,0),MATCH(G$4,'Adjustment scenario'!$D$10:$W$10,0)) -> 42.488825 | H5: =INDEX(OFFSET('Adjustment scenario'!$D$1:$W$1,$D5-1,0),MATCH(H$4,'Adjustment scenario'!$D$10:$W$10,0)) -> 41.199314 | I5: =INDEX(OFFSET('Adjustment scenario'!$D$1:$W$1,$D5-1,0),MATCH(I$4,'Adjustment scenario'!$D$10:$W$10,0)) -> 37.456895 | J5: =INDEX(OFFSET('Adjustment scenario'!$D$1:$W$1,$D5-1,0),MATCH(J$4,'Adjustment scenario'!$D$10:$W$10,0)) -> 33.593172 | K5: =INDEX(OFFSET('Adjustment scenario'!$D$1:$W$1,$D5-1,0),MATCH(K$4,'Adjustment scenario'!$D$10:$W$10,0)) -> 29.816315 | L5: =INDEX(OFFSET('Adjustment scenario'!$D$1:$W$1,$D5-1,0),MATCH(L$4,'Adjustment scenario'!$D$10:$W$10,0)) -> 26.364043 | M5: =INDEX(OFFSET('Adjustment scenario'!$D$1:$W$1,$D5-1,0),MATCH(M$4,'Adjustment scenario'!$D$10:$W$10,0)) -> 23.177269 | ... X5: =INDEX(OFFSET('Adjustment scenario'!$D$1:$W$1,$D5-1,0),MATCH(X$4,'Adjustment scenario'!$D$10:$W$10,0)) -> 2.2971951
B6: 2 | C6: General government balance | D6: 77 | E6: (% GDP) | F6: =INDEX(OFFSET('Adjustment scenario'!$D$1:$W$1,$D6-1,0),MATCH(F$4,'Adjustment scenario'!$D$10:$W$10,0)) -> 1.6504174 | G6: =INDEX(OFFSET('Adjustment scenario'!$D$1:$W$1,$D6-1,0),MATCH(G$4,'Adjustment scenario'!$D$10:$W$10,0)) -> 1.2569437 | H6: =INDEX(OFFSET('Adjustment scenario'!$D$1:$W$1,$D6-1,0),MATCH(H$4,'Adjustment scenario'!$D$10:$W$10,0)) -> 1.3229707 | I6: =INDEX(OFFSET('Adjustment scenario'!$D$1:$W$1,$D6-1,0),MATCH(I$4,'Adjustment scenario'!$D$10:$W$10,0)) -> 1.4782958 | J6: =INDEX(OFFSET('Adjustment scenario'!$D$1:$W$1,$D6-1,0),MATCH(J$4,'Adjustment scenario'!$D$10:$W$10,0)) -> 1.7585653 | K6: =INDEX(OFFSET('Adjustment scenario'!$D$1:$W$1,$D6-1,0),MATCH(K$4,'Adjustment scenario'!$D$10:$W$10,0)) -> 1.9330239 | L6: =INDEX(OFFSET('Adjustment scenario'!$D$1:$W$1,$D6-1,0),MATCH(L$4,'Adjustment scenario'!$D$10:$W$10,0)) -> 1.9066324 | M6: =INDEX(OFFSET('Adjustment scenario'!$D$1:$W$1,$D6-1,0),MATCH(M$4,'Adjustment scenario'!$D$10:$W$10,0)) -> 1.855583 | ... X6: =INDEX(OFFSET('Adjustment scenario'!$D$1:$W$1,$D6-1,0),MATCH(X$4,'Adjustment scenario'!$D$10:$W$10,0)) -> 0.94280064
B7: 3 | C7: Structural primary balance | D7: 12 | E7: (% pot. GDP) | F7: =INDEX(OFFSET('Adjustment scenario'!$D$1:$W$1,$D7-1,0),MATCH(F$4,'Adjustment scenario'!$D$10:$W$10,0)) -> 1.712465 | G7: =INDEX(OFFSET('Adjustment scenario'!$D$1:$W$1,$D7-1,0),MATCH(G$4,'Adjustment scenario'!$D$10:$W$10,0)) -> 2.528801 | H7: =INDEX(OFFSET('Adjustment scenario'!$D$1:$W$1,$D7-1,0),MATCH(H$4,'Adjustment scenario'!$D$10:$W$10,0)) -> 2.528801 | I7: =INDEX(OFFSET('Adjustment scenario'!$D$1:$W$1,$D7-1,0),MATCH(I$4,'Adjustment scenario'!$D$10:$W$10,0)) -> 2.528801 | J7: =INDEX(OFFSET('Adjustment scenario'!$D$1:$W$1,$D7-1,0),MATCH(J$4,'Adjustment scenario'!$D$10:$W$10,0)) -> 2.528801 | K7: =INDEX(OFFSET('Adjustment scenario'!$D$1:$W$1,$D7-1,0),MATCH(K$4,'Adjustment scenario'!$D$10:$W$10,0)) -> 2.528801 | L7: =INDEX(OFFSET('Adjustment scenario'!$D$1:$W$1,$D7-1,0),MATCH(L$4,'Adjustment scenario'!$D$10:$W$10,0)) -> 2.528801 | M7: =INDEX(OFFSET('Adjustment scenario'!$D$1:$W$1,$D7-1,0),MATCH(M$4,'Adjustment scenario'!$D$10:$W$10,0)) -> 2.528801 | ... X7: =INDEX(OFFSET('Adjustment scenario'!$D$1:$W$1,$D7-1,0),MATCH(X$4,'Adjustment scenario'!$D$10:$W$10,0)) -> 2.528801
B8: 4 | C8: Cyclical component | D8: 62 | E8: (% pot. GDP) | F8: =INDEX(OFFSET('Adjustment scenario'!$D$1:$W$1,$D8-1,0),MATCH(F$4,'Adjustment scenario'!$D$10:$W$10,0)) -> -0.62869023 | G8: =INDEX(OFFSET('Adjustment scenario'!$D$1:$W$1,$D8-1,0),MATCH(G$4,'Adjustment scenario'!$D$10:$W$10,0)) -> 0.58062382 | H8: =INDEX(OFFSET('Adjustment scenario'!$D$1:$W$1,$D8-1,0),MATCH(H$4,'Adjustment scenario'!$D$10:$W$10,0)) -> 0.52665142 | I8: =INDEX(OFFSET('Adjustment scenario'!$D$1:$W$1,$D8-1,0),MATCH(I$4,'Adjustment scenario'!$D$10:$W$10,0)) -> 0.3510982 | J8: =INDEX(OFFSET('Adjustment scenario'!$D$1:$W$1,$D8-1,0),MATCH(J$4,'Adjustment scenario'!$D$10:$W$10,0)) -> 0.11703124 | K8: =INDEX(OFFSET('Adjustment scenario'!$D$1:$W$1,$D8-1,0),MATCH(K$4,'Adjustment scenario'!$D$10:$W$10,0)) -> -3.4308927e-06 | L8: =INDEX(OFFSET('Adjustment scenario'!$D$1:$W$1,$D8-1,0),MATCH(L$4,'Adjustment scenario'!$D$10:$W$10,0)) -> -2.9249033e-06 | M8: =INDEX(OFFSET('Adjustment scenario'!$D$1:$W$1,$D8-1,0),MATCH(M$4,'Adjustment scenario'!$D$10:$W$10,0)) -> -2.9249033e-06 | ... X8: =INDEX(OFFSET('Adjustment scenario'!$D$1:$W$1,$D8-1,0),MATCH(X$4,'Adjustment scenario'!$D$10:$W$10,0)) -> -1.1634835e-05
B9: 5 | C9: One-off measures | D9: 14 | E9: (% GDP) | F9: =INDEX(OFFSET('Adjustment scenario'!$D$1:$W$1,$D9-1,0),MATCH(F$4,'Adjustment scenario'!$D$10:$W$10,0)) -> 0 | G9: =INDEX(OFFSET('Adjustment scenario'!$D$1:$W$1,$D9-1,0),MATCH(G$4,'Adjustment scenario'!$D$10:$W$10,0)) -> 0 | H9: =INDEX(OFFSET('Adjustment scenario'!$D$1:$W$1,$D9-1,0),MATCH(H$4,'Adjustment scenario'!$D$10:$W$10,0)) -> 0 | I9: =INDEX(OFFSET('Adjustment scenario'!$D$1:$W$1,$D9-1,0),MATCH(I$4,'Adjustment scenario'!$D$10:$W$10,0)) -> 0 | J9: =INDEX(OFFSET('Adjustment scenario'!$D$1:$W$1,$D9-1,0),MATCH(J$4,'Adjustment scenario'!$D$10:$W$10,0)) -> 0 | K9: =INDEX(OFFSET('Adjustment scenario'!$D$1:$W$1,$D9-1,0),MATCH(K$4,'Adjustment scenario'!$D$10:$W$10,0)) -> 0 | L9: =INDEX(OFFSET('Adjustment scenario'!$D$1:$W$1,$D9-1,0),MATCH(L$4,'Adjustment scenario'!$D$10:$W$10,0)) -> 0 | M9: =INDEX(OFFSET('Adjustment scenario'!$D$1:$W$1,$D9-1,0),MATCH(M$4,'Adjustment scenario'!$D$10:$W$10,0)) -> 0 | ... X9: =INDEX(OFFSET('Adjustment scenario'!$D$1:$W$1,$D9-1,0),MATCH(X$4,'Adjustment scenario'!$D$10:$W$10,0)) -> 0
B10: 6 | C10: Interest expenditure | D10: 68 | E10: (% GDP) | F10: =INDEX(OFFSET('Adjustment scenario'!$D$1:$W$1,$D10-1,0),MATCH(F$4,'Adjustment scenario'!$D$10:$W$10,0)) -> 0.69073786 | G10: =INDEX(OFFSET('Adjustment scenario'!$D$1:$W$1,$D10-1,0),MATCH(G$4,'Adjustment scenario'!$D$10:$W$10,0)) -> 0.6912335 | H10: =INDEX(OFFSET('Adjustment scenario'!$D$1:$W$1,$D10-1,0),MATCH(H$4,'Adjustment scenario'!$D$10:$W$10,0)) -> 0.67917885 | I10: =INDEX(OFFSET('Adjustment scenario'!$D$1:$W$1,$D10-1,0),MATCH(I$4,'Adjustment scenario'!$D$10:$W$10,0)) -> 0.69940695 | J10: =INDEX(OFFSET('Adjustment scenario'!$D$1:$W$1,$D10-1,0),MATCH(J$4,'Adjustment scenario'!$D$10:$W$10,0)) -> 0.6532045 | K10: =INDEX(OFFSET('Adjustment scenario'!$D$1:$W$1,$D10-1,0),MATCH(K$4,'Adjustment scenario'!$D$10:$W$10,0)) -> 0.59578056 | L10: =INDEX(OFFSET('Adjustment scenario'!$D$1:$W$1,$D10-1,0),MATCH(L$4,'Adjustment scenario'!$D$10:$W$10,0)) -> 0.53845974 | M10: =INDEX(OFFSET('Adjustment scenario'!$D$1:$W$1,$D10-1,0),MATCH(M$4,'Adjustment scenario'!$D$10:$W$10,0)) -> 0.48336734 | ... X10: =INDEX(OFFSET('Adjustment scenario'!$D$1:$W$1,$D10-1,0),MATCH(X$4,'Adjustment scenario'!$D$10:$W$10,0)) -> 0.064618696
B11: 7 | C11: Long-term interest rate | D11: 37 | E11: (%) | F11: =INDEX(OFFSET('Adjustment scenario'!$D$1:$W$1,$D11-1,0),MATCH(F$4,'Adjustment scenario'!$D$10:$W$10,0)) -> 2.87 | G11: =INDEX(OFFSET('Adjustment scenario'!$D$1:$W$1,$D11-1,0),MATCH(G$4,'Adjustment scenario'!$D$10:$W$10,0)) -> 2.837221 | H11: =INDEX(OFFSET('Adjustment scenario'!$D$1:$W$1,$D11-1,0),MATCH(H$4,'Adjustment scenario'!$D$10:$W$10,0)) -> 2.903685 | I11: =INDEX(OFFSET('Adjustment scenario'!$D$1:$W$1,$D11-1,0),MATCH(I$4,'Adjustment scenario'!$D$10:$W$10,0)) -> 2.9987319 | J11: =INDEX(OFFSET('Adjustment scenario'!$D$1:$W$1,$D11-1,0),MATCH(J$4,'Adjustment scenario'!$D$10:$W$10,0)) -> 3.0937787 | K11: =INDEX(OFFSET('Adjustment scenario'!$D$1:$W$1,$D11-1,0),MATCH(K$4,'Adjustment scenario'!$D$10:$W$10,0)) -> 3.1888256 | L11: =INDEX(OFFSET('Adjustment scenario'!$D$1:$W$1,$D11-1,0),MATCH(L$4,'Adjustment scenario'!$D$10:$W$10,0)) -> 3.2838725 | M11: =INDEX(OFFSET('Adjustment scenario'!$D$1:$W$1,$D11-1,0),MATCH(M$4,'Adjustment scenario'!$D$10:$W$10,0)) -> 3.3789194 | ... X11: =INDEX(OFFSET('Adjustment scenario'!$D$1:$W$1,$D11-1,0),MATCH(X$4,'Adjustment scenario'!$D$10:$W$10,0)) -> 3.798436
B12: 8 | C12: Short-term interest rate | D12: 38 | E12: (%) | F12: =INDEX(OFFSET('Adjustment scenario'!$D$1:$W$1,$D12-1,0),MATCH(F$4,'Adjustment scenario'!$D$10:$W$10,0)) -> 3.43 | G12: =INDEX(OFFSET('Adjustment scenario'!$D$1:$W$1,$D12-1,0),MATCH(G$4,'Adjustment scenario'!$D$10:$W$10,0)) -> 3.564208 | H12: =INDEX(OFFSET('Adjustment scenario'!$D$1:$W$1,$D12-1,0),MATCH(H$4,'Adjustment scenario'!$D$10:$W$10,0)) -> 2.816375 | I12: =INDEX(OFFSET('Adjustment scenario'!$D$1:$W$1,$D12-1,0),MATCH(I$4,'Adjustment scenario'!$D$10:$W$10,0)) -> 2.8050894 | J12: =INDEX(OFFSET('Adjustment scenario'!$D$1:$W$1,$D12-1,0),MATCH(J$4,'Adjustment scenario'!$D$10:$W$10,0)) -> 2.7938037 | K12: =INDEX(OFFSET('Adjustment scenario'!$D$1:$W$1,$D12-1,0),MATCH(K$4,'Adjustment scenario'!$D$10:$W$10,0)) -> 2.7825181 | L12: =INDEX(OFFSET('Adjustment scenario'!$D$1:$W$1,$D12-1,0),MATCH(L$4,'Adjustment scenario'!$D$10:$W$10,0)) -> 2.7712325 | M12: =INDEX(OFFSET('Adjustment scenario'!$D$1:$W$1,$D12-1,0),MATCH(M$4,'Adjustment scenario'!$D$10:$W$10,0)) -> 2.7599469 | ... X12: =INDEX(OFFSET('Adjustment scenario'!$D$1:$W$1,$D12-1,0),MATCH(X$4,'Adjustment scenario'!$D$10:$W$10,0)) -> 2.435654
B13: 9 | C13: Implicit average interest rate | D13: 36 | E13: (%) | F13: =INDEX(OFFSET('Adjustment scenario'!$D$1:$W$1,$D13-1,0),MATCH(F$4,'Adjustment scenario'!$D$10:$W$10,0)) -> 1.550894 | G13: =INDEX(OFFSET('Adjustment scenario'!$D$1:$W$1,$D13-1,0),MATCH(G$4,'Adjustment scenario'!$D$10:$W$10,0)) -> 1.641526 | H13: =INDEX(OFFSET('Adjustment scenario'!$D$1:$W$1,$D13-1,0),MATCH(H$4,'Adjustment scenario'!$D$10:$W$10,0)) -> 1.684386 | I13: =INDEX(OFFSET('Adjustment scenario'!$D$1:$W$1,$D13-1,0),MATCH(I$4,'Adjustment scenario'!$D$10:$W$10,0)) -> 1.7963363 | J13: =INDEX(OFFSET('Adjustment scenario'!$D$1:$W$1,$D13-1,0),MATCH(J$4,'Adjustment scenario'!$D$10:$W$10,0)) -> 1.8477296 | K13: =INDEX(OFFSET('Adjustment scenario'!$D$1:$W$1,$D13-1,0),MATCH(K$4,'Adjustment scenario'!$D$10:$W$10,0)) -> 1.8765133 | L13: =INDEX(OFFSET('Adjustment scenario'!$D$1:$W$1,$D13-1,0),MATCH(L$4,'Adjustment scenario'!$D$10:$W$10,0)) -> 1.9046582 | M13: =INDEX(OFFSET('Adjustment scenario'!$D$1:$W$1,$D13-1,0),MATCH(M$4,'Adjustment scenario'!$D$10:$W$10,0)) -> 1.9309319 | ... X13: =INDEX(OFFSET('Adjustment scenario'!$D$1:$W$1,$D13-1,0),MATCH(X$4,'Adjustment scenario'!$D$10:$W$10,0)) -> 1.9944068
B14: 10 | C14: Stock-flow adjustment | D14: 72 | E14: (% GDP) | F14: =INDEX(OFFSET('Adjustment scenario'!$D$1:$W$1,$D14-1,0),MATCH(F$4,'Adjustment scenario'!$D$10:$W$10,0)) -> 0.8428066 | G14: =INDEX(OFFSET('Adjustment scenario'!$D$1:$W$1,$D14-1,0),MATCH(G$4,'Adjustment scenario'!$D$10:$W$10,0)) -> 1.636567 | H14: =INDEX(OFFSET('Adjustment scenario'!$D$1:$W$1,$D14-1,0),MATCH(H$4,'Adjustment scenario'!$D$10:$W$10,0)) -> 2.200242 | I14: =INDEX(OFFSET('Adjustment scenario'!$D$1:$W$1,$D14-1,0),MATCH(I$4,'Adjustment scenario'!$D$10:$W$10,0)) -> 0 | J14: =INDEX(OFFSET('Adjustment scenario'!$D$1:$W$1,$D14-1,0),MATCH(J$4,'Adjustment scenario'!$D$10:$W$10,0)) -> 0 | K14: =INDEX(OFFSET('Adjustment scenario'!$D$1:$W$1,$D14-1,0),MATCH(K$4,'Adjustment scenario'!$D$10:$W$10,0)) -> 0 | L14: =INDEX(OFFSET('Adjustment scenario'!$D$1:$W$1,$D14-1,0),MATCH(L$4,'Adjustment scenario'!$D$10:$W$10,0)) -> 0 | M14: =INDEX(OFFSET('Adjustment scenario'!$D$1:$W$1,$D14-1,0),MATCH(M$4,'Adjustment scenario'!$D$10:$W$10,0)) -> 0 | ... X14: =INDEX(OFFSET('Adjustment scenario'!$D$1:$W$1,$D14-1,0),MATCH(X$4,'Adjustment scenario'!$D$10:$W$10,0)) -> 0
B15: 11 | C15: Potential GDP | D15: 27 | E15: (growth rate) | F15: =(INDEX(OFFSET('Adjustment scenario'!$D$1:$W$1,$D15-1,0),MATCH(F$4,'Adjustment scenario'!$D$10:$W$10,0))/INDEX(OFFSET('Adjustment scenario'!$D$1:$W$1,$D15-1,0),MATCH(E$4,'Adjustment scenario'!$D$10:$W$10,0))-1)*100 -> 4.333524 | G15: =(INDEX(OFFSET('Adjustment scenario'!$D$1:$W$1,$D15-1,0),MATCH(G$4,'Adjustment scenario'!$D$10:$W$10,0))/INDEX(OFFSET('Adjustment scenario'!$D$1:$W$1,$D15-1,0),MATCH(F$4,'Adjustment scenario'!$D$10:$W$10,0))-1)*100 -> 3.615591 | H15: =(INDEX(OFFSET('Adjustment scenario'!$D$1:$W$1,$D15-1,0),MATCH(H$4,'Adjustment scenario'!$D$10:$W$10,0))/INDEX(OFFSET('Adjustment scenario'!$D$1:$W$1,$D15-1,0),MATCH(G$4,'Adjustment scenario'!$D$10:$W$10,0))-1)*100 -> 3.285812 | I15: =(INDEX(OFFSET('Adjustment scenario'!$D$1:$W$1,$D15-1,0),MATCH(I$4,'Adjustment scenario'!$D$10:$W$10,0))/INDEX(OFFSET('Adjustment scenario'!$D$1:$W$1,$D15-1,0),MATCH(H$4,'Adjustment scenario'!$D$10:$W$10,0))-1)*100 -> 3.394844 | J15: =(INDEX(OFFSET('Adjustment scenario'!$D$1:$W$1,$D15-1,0),MATCH(J$4,'Adjustment scenario'!$D$10:$W$10,0))/INDEX(OFFSET('Adjustment scenario'!$D$1:$W$1,$D15-1,0),MATCH(I$4,'Adjustment scenario'!$D$10:$W$10,0))-1)*100 -> 3.335869 | K15: =(INDEX(OFFSET('Adjustment scenario'!$D$1:$W$1,$D15-1,0),MATCH(K$4,'Adjustment scenario'!$D$10:$W$10,0))/INDEX(OFFSET('Adjustment scenario'!$D$1:$W$1,$D15-1,0),MATCH(J$4,'Adjustment scenario'!$D$10:$W$10,0))-1)*100 -> 3.345161 | L15: =(INDEX(OFFSET('Adjustment scenario'!$D$1:$W$1,$D15-1,0),MATCH(L$4,'Adjustment scenario'!$D$10:$W$10,0))/INDEX(OFFSET('Adjustment scenario'!$D$1:$W$1,$D15-1,0),MATCH(K$4,'Adjustment scenario'!$D$10:$W$10,0))-1)*100 -> 3.164205 | M15: =(INDEX(OFFSET('Adjustment scenario'!$D$1:$W$1,$D15-1,0),MATCH(M$4,'Adjustment scenario'!$D$10:$W$10,0))/INDEX(OFFSET('Adjustment scenario'!$D$1:$W$1,$D15-1,0),MATCH(L$4,'Adjustment scenario'!$D$10:$W$10,0))-1)*100 -> 2.938014 | ... X15: =(INDEX(OFFSET('Adjustment scenario'!$D$1:$W$1,$D15-1,0),MATCH(X$4,'Adjustment scenario'!$D$10:$W$10,0))/INDEX(OFFSET('Adjustment scenario'!$D$1:$W$1,$D15-1,0),MATCH(W$4,'Adjustment scenario'!$D$10:$W$10,0))-1)*100 -> 1.571108
B16: 12 | C16: Real GDP | D16: 24 | E16: (growth rate) | F16: =INDEX(OFFSET('Adjustment scenario'!$D$1:$W$1,$D16-1,0),MATCH(F$4,'Adjustment scenario'!$D$10:$W$10,0)) -> -3.198788 | G16: =INDEX(OFFSET('Adjustment scenario'!$D$1:$W$1,$D16-1,0),MATCH(G$4,'Adjustment scenario'!$D$10:$W$10,0)) -> 1.243702 | H16: =INDEX(OFFSET('Adjustment scenario'!$D$1:$W$1,$D16-1,0),MATCH(H$4,'Adjustment scenario'!$D$10:$W$10,0)) -> 3.393806 | I16: =INDEX(OFFSET('Adjustment scenario'!$D$1:$W$1,$D16-1,0),MATCH(I$4,'Adjustment scenario'!$D$10:$W$10,0)) -> 3.746114 | J16: =INDEX(OFFSET('Adjustment scenario'!$D$1:$W$1,$D16-1,0),MATCH(J$4,'Adjustment scenario'!$D$10:$W$10,0)) -> 3.802369 | K16: =INDEX(OFFSET('Adjustment scenario'!$D$1:$W$1,$D16-1,0),MATCH(K$4,'Adjustment scenario'!$D$10:$W$10,0)) -> 3.577386 | L16: =INDEX(OFFSET('Adjustment scenario'!$D$1:$W$1,$D16-1,0),MATCH(L$4,'Adjustment scenario'!$D$10:$W$10,0)) -> 3.164204 | M16: =INDEX(OFFSET('Adjustment scenario'!$D$1:$W$1,$D16-1,0),MATCH(M$4,'Adjustment scenario'!$D$10:$W$10,0)) -> 2.938014 | ... X16: =INDEX(OFFSET('Adjustment scenario'!$D$1:$W$1,$D16-1,0),MATCH(X$4,'Adjustment scenario'!$D$10:$W$10,0)) -> 1.571112
B17: 13 | C17: GDP deflator | D17: 42 | E17: (growth rate) | F17: =INDEX(OFFSET('Adjustment scenario'!$D$1:$W$1,$D17-1,0),MATCH(F$4,'Adjustment scenario'!$D$10:$W$10,0)) -> 2.965217 | G17: =INDEX(OFFSET('Adjustment scenario'!$D$1:$W$1,$D17-1,0),MATCH(G$4,'Adjustment scenario'!$D$10:$W$10,0)) -> 2.574346 | H17: =INDEX(OFFSET('Adjustment scenario'!$D$1:$W$1,$D17-1,0),MATCH(H$4,'Adjustment scenario'!$D$10:$W$10,0)) -> 1.914897 | I17: =INDEX(OFFSET('Adjustment scenario'!$D$1:$W$1,$D17-1,0),MATCH(I$4,'Adjustment scenario'!$D$10:$W$10,0)) -> 1.9942849 | J17: =INDEX(OFFSET('Adjustment scenario'!$D$1:$W$1,$D17-1,0),MATCH(J$4,'Adjustment scenario'!$D$10:$W$10,0)) -> 2.0736728 | K17: =INDEX(OFFSET('Adjustment scenario'!$D$1:$W$1,$D17-1,0),MATCH(K$4,'Adjustment scenario'!$D$10:$W$10,0)) -> 2.1530606 | L17: =INDEX(OFFSET('Adjustment scenario'!$D$1:$W$1,$D17-1,0),MATCH(L$4,'Adjustment scenario'!$D$10:$W$10,0)) -> 2.2324485 | M17: =INDEX(OFFSET('Adjustment scenario'!$D$1:$W$1,$D17-1,0),MATCH(M$4,'Adjustment scenario'!$D$10:$W$10,0)) -> 2.3118364 | ... X17: =INDEX(OFFSET('Adjustment scenario'!$D$1:$W$1,$D17-1,0),MATCH(X$4,'Adjustment scenario'!$D$10:$W$10,0)) -> 2.33
B18: 14 | C18: Nominal GDP | D18: 33 | E18: (growth rate) | F18: =INDEX(OFFSET('Adjustment scenario'!$D$1:$W$1,$D18-1,0),MATCH(F$4,'Adjustment scenario'!$D$10:$W$10,0)) -> -0.32842201 | G18: =INDEX(OFFSET('Adjustment scenario'!$D$1:$W$1,$D18-1,0),MATCH(G$4,'Adjustment scenario'!$D$10:$W$10,0)) -> 3.8500652 | H18: =INDEX(OFFSET('Adjustment scenario'!$D$1:$W$1,$D18-1,0),MATCH(H$4,'Adjustment scenario'!$D$10:$W$10,0)) -> 5.3736909 | I18: =INDEX(OFFSET('Adjustment scenario'!$D$1:$W$1,$D18-1,0),MATCH(I$4,'Adjustment scenario'!$D$10:$W$10,0)) -> 5.8151071 | J18: =INDEX(OFFSET('Adjustment scenario'!$D$1:$W$1,$D18-1,0),MATCH(J$4,'Adjustment scenario'!$D$10:$W$10,0)) -> 5.9548904 | K18: =INDEX(OFFSET('Adjustment scenario'!$D$1:$W$1,$D18-1,0),MATCH(K$4,'Adjustment scenario'!$D$10:$W$10,0)) -> 5.8074699 | L18: =INDEX(OFFSET('Adjustment scenario'!$D$1:$W$1,$D18-1,0),MATCH(L$4,'Adjustment scenario'!$D$10:$W$10,0)) -> 5.4672917 | M18: =INDEX(OFFSET('Adjustment scenario'!$D$1:$W$1,$D18-1,0),MATCH(M$4,'Adjustment scenario'!$D$10:$W$10,0)) -> 5.3177725 | ... X18: =INDEX(OFFSET('Adjustment scenario'!$D$1:$W$1,$D18-1,0),MATCH(X$4,'Adjustment scenario'!$D$10:$W$10,0)) -> 3.9377189
C20: Table 7b: Debt projections and key stressed variables, deterministic scenarios and stochastic simulations
C22: Financial stress scenario | E22: =F22-1 -> -1
B23: 1 | C23: Gross debt | D23: 56 | E23: (% GDP)
B24: 2 | C24: Long-term interest rate | D24: 36 | E24: (%)
B25: 3 | C25: Short-term interest rate | D25: 37 | E25: (%)
C26: Lower SPB scenario | E26: =F26-1 -> -1
B27: 4 | C27: Gross debt | D27: 56 | E27: (% GDP)
B28: 5 | C28: Structural primary balance | D28: 12 | E28: (% pot. GDP)
C29: Adverse 'r-g' scenario | E29: =F29-1 -> -1
B30: 6 | C30: Gross debt | D30: 57 | E30: (% GDP)
B31: 7 | C31: Long-term interest rate | D31: 37 | E31: (%)
B32: 8 | C32: Short-term interest rate | D32: 38 | E32: (%)
B33: 9 | C33: Real GDP | D33: 23 | E33: (growth rate)
B34: 10 | C34: Potential GDP | D34: 27 | E34: (growth rate)
C35: Stochastic simulations | E35: =F35-1 -> -1
B36: 11 | C36: Probability of debt being below its value in T+4/7 | D36: approximation | E36: (%)
C38: Table 7c: Debt and headline balance projections and underlying assumptions (under 'no-fiscal-policy-change' baseline)
F40: ='Input data'!$C$5-1 -> 2023 | G40: =F40+1 -> 2024 | H40: =G40+1 -> 2025 | I40: =H40+1 -> 2026 | J40: =I40+1 -> 2027 | K40: =J40+1 -> 2028 | L40: =K40+1 -> 2029 | M40: =L40+1 -> 2030 | N40: =M40+1 -> 2031 | ... X40: =W40+1 -> 2041
B41: 1 | C41: Gross debt | D41: 56 | E41: (% GDP) | F41: =INDEX(OFFSET('Baseline NFPC'!$D$1:$W$1,$D41-1,0),MATCH(F$4,'Baseline NFPC'!$D$10:$W$10,0)) -> 43.730434 | G41: =INDEX(OFFSET('Baseline NFPC'!$D$1:$W$1,$D41-1,0),MATCH(G$4,'Baseline NFPC'!$D$10:$W$10,0)) -> 42.488825 | H41: =INDEX(OFFSET('Baseline NFPC'!$D$1:$W$1,$D41-1,0),MATCH(H$4,'Baseline NFPC'!$D$10:$W$10,0)) -> 41.250806 | I41: =INDEX(OFFSET('Baseline NFPC'!$D$1:$W$1,$D41-1,0),MATCH(I$4,'Baseline NFPC'!$D$10:$W$10,0)) -> 37.732588 | J41: =INDEX(OFFSET('Baseline NFPC'!$D$1:$W$1,$D41-1,0),MATCH(J$4,'Baseline NFPC'!$D$10:$W$10,0)) -> 34.267259 | K41: =INDEX(OFFSET('Baseline NFPC'!$D$1:$W$1,$D41-1,0),MATCH(K$4,'Baseline NFPC'!$D$10:$W$10,0)) -> 31.007171 | L41: =INDEX(OFFSET('Baseline NFPC'!$D$1:$W$1,$D41-1,0),MATCH(L$4,'Baseline NFPC'!$D$10:$W$10,0)) -> 28.062291 | M41: =INDEX(OFFSET('Baseline NFPC'!$D$1:$W$1,$D41-1,0),MATCH(M$4,'Baseline NFPC'!$D$10:$W$10,0)) -> 25.375334 | ... X41: =INDEX(OFFSET('Baseline NFPC'!$D$1:$W$1,$D41-1,0),MATCH(X$4,'Baseline NFPC'!$D$10:$W$10,0)) -> 9.8184426
B42: 2 | C42: General government balance | D42: 76 | E42: (% GDP) | F42: =INDEX(OFFSET('Baseline NFPC'!$D$1:$W$1,$D42-1,0),MATCH(F$4,'Baseline NFPC'!$D$10:$W$10,0)) -> 1.6504174 | G42: =INDEX(OFFSET('Baseline NFPC'!$D$1:$W$1,$D42-1,0),MATCH(G$4,'Baseline NFPC'!$D$10:$W$10,0)) -> 1.2569437 | H42: =INDEX(OFFSET('Baseline NFPC'!$D$1:$W$1,$D42-1,0),MATCH(H$4,'Baseline NFPC'!$D$10:$W$10,0)) -> 1.2714789 | I42: =INDEX(OFFSET('Baseline NFPC'!$D$1:$W$1,$D42-1,0),MATCH(I$4,'Baseline NFPC'!$D$10:$W$10,0)) -> 1.251265 | J42: =INDEX(OFFSET('Baseline NFPC'!$D$1:$W$1,$D42-1,0),MATCH(J$4,'Baseline NFPC'!$D$10:$W$10,0)) -> 1.3446767 | K42: =INDEX(OFFSET('Baseline NFPC'!$D$1:$W$1,$D42-1,0),MATCH(K$4,'Baseline NFPC'!$D$10:$W$10,0)) -> 1.3792568 | L42: =INDEX(OFFSET('Baseline NFPC'!$D$1:$W$1,$D42-1,0),MATCH(L$4,'Baseline NFPC'!$D$10:$W$10,0)) -> 1.3375068 | M42: =INDEX(OFFSET('Baseline NFPC'!$D$1:$W$1,$D42-1,0),MATCH(M$4,'Baseline NFPC'!$D$10:$W$10,0)) -> 1.2700174 | ... X42: =INDEX(OFFSET('Baseline NFPC'!$D$1:$W$1,$D42-1,0),MATCH(X$4,'Baseline NFPC'!$D$10:$W$10,0)) -> 0.21108939
B43: 3 | C43: Structural primary balance | D43: 12 | E43: (% pot. GDP) | F43: =INDEX(OFFSET('Baseline NFPC'!$D$1:$W$1,$D43-1,0),MATCH(F$4,'Baseline NFPC'!$D$10:$W$10,0)) -> 1.712465 | G43: =INDEX(OFFSET('Baseline NFPC'!$D$1:$W$1,$D43-1,0),MATCH(G$4,'Baseline NFPC'!$D$10:$W$10,0)) -> 2.528801 | H43: =INDEX(OFFSET('Baseline NFPC'!$D$1:$W$1,$D43-1,0),MATCH(H$4,'Baseline NFPC'!$D$10:$W$10,0)) -> 2.528801 | I43: =INDEX(OFFSET('Baseline NFPC'!$D$1:$W$1,$D43-1,0),MATCH(I$4,'Baseline NFPC'!$D$10:$W$10,0)) -> 2.528801 | J43: =INDEX(OFFSET('Baseline NFPC'!$D$1:$W$1,$D43-1,0),MATCH(J$4,'Baseline NFPC'!$D$10:$W$10,0)) -> 2.528801 | K43: =INDEX(OFFSET('Baseline NFPC'!$D$1:$W$1,$D43-1,0),MATCH(K$4,'Baseline NFPC'!$D$10:$W$10,0)) -> 2.528801 | L43: =INDEX(OFFSET('Baseline NFPC'!$D$1:$W$1,$D43-1,0),MATCH(L$4,'Baseline NFPC'!$D$10:$W$10,0)) -> 2.528801 | M43: =INDEX(OFFSET('Baseline NFPC'!$D$1:$W$1,$D43-1,0),MATCH(M$4,'Baseline NFPC'!$D$10:$W$10,0)) -> 2.528801 | ... X43: =INDEX(OFFSET('Baseline NFPC'!$D$1:$W$1,$D43-1,0),MATCH(X$4,'Baseline NFPC'!$D$10:$W$10,0)) -> 2.528801
B44: 4 | C44: Cyclical component | D44: 61 | E44: (% pot. GDP) | F44: =INDEX(OFFSET('Baseline NFPC'!$D$1:$W$1,$D44-1,0),MATCH(F$4,'Baseline NFPC'!$D$10:$W$10,0)) -> -0.62869023 | G44: =INDEX(OFFSET('Baseline NFPC'!$D$1:$W$1,$D44-1,0),MATCH(G$4,'Baseline NFPC'!$D$10:$W$10,0)) -> 0.58062382 | H44: =INDEX(OFFSET('Baseline NFPC'!$D$1:$W$1,$D44-1,0),MATCH(H$4,'Baseline NFPC'!$D$10:$W$10,0)) -> 0.52665142 | I44: =INDEX(OFFSET('Baseline NFPC'!$D$1:$W$1,$D44-1,0),MATCH(I$4,'Baseline NFPC'!$D$10:$W$10,0)) -> 0.3510982 | J44: =INDEX(OFFSET('Baseline NFPC'!$D$1:$W$1,$D44-1,0),MATCH(J$4,'Baseline NFPC'!$D$10:$W$10,0)) -> 0.11703124 | K44: =INDEX(OFFSET('Baseline NFPC'!$D$1:$W$1,$D44-1,0),MATCH(K$4,'Baseline NFPC'!$D$10:$W$10,0)) -> -3.4308927e-06 | L44: =INDEX(OFFSET('Baseline NFPC'!$D$1:$W$1,$D44-1,0),MATCH(L$4,'Baseline NFPC'!$D$10:$W$10,0)) -> -2.9249033e-06 | M44: =INDEX(OFFSET('Baseline NFPC'!$D$1:$W$1,$D44-1,0),MATCH(M$4,'Baseline NFPC'!$D$10:$W$10,0)) -> -2.9249033e-06 | ... X44: =INDEX(OFFSET('Baseline NFPC'!$D$1:$W$1,$D44-1,0),MATCH(X$4,'Baseline NFPC'!$D$10:$W$10,0)) -> -1.1634835e-05
B45: 5 | C45: Interest expenditure | D45: 67 | E45: (% GDP) | F45: =INDEX(OFFSET('Baseline NFPC'!$D$1:$W$1,$D45-1,0),MATCH(F$4,'Baseline NFPC'!$D$10:$W$10,0)) -> 0.69073786 | G45: =INDEX(OFFSET('Baseline NFPC'!$D$1:$W$1,$D45-1,0),MATCH(G$4,'Baseline NFPC'!$D$10:$W$10,0)) -> 0.6912335 | H45: =INDEX(OFFSET('Baseline NFPC'!$D$1:$W$1,$D45-1,0),MATCH(H$4,'Baseline NFPC'!$D$10:$W$10,0)) -> 0.67917885 | I45: =INDEX(OFFSET('Baseline NFPC'!$D$1:$W$1,$D45-1,0),MATCH(I$4,'Baseline NFPC'!$D$10:$W$10,0)) -> 0.70154422 | J45: =INDEX(OFFSET('Baseline NFPC'!$D$1:$W$1,$D45-1,0),MATCH(J$4,'Baseline NFPC'!$D$10:$W$10,0)) -> 0.66142763 | K45: =INDEX(OFFSET('Baseline NFPC'!$D$1:$W$1,$D45-1,0),MATCH(K$4,'Baseline NFPC'!$D$10:$W$10,0)) -> 0.61515047 | L45: =INDEX(OFFSET('Baseline NFPC'!$D$1:$W$1,$D45-1,0),MATCH(L$4,'Baseline NFPC'!$D$10:$W$10,0)) -> 0.57318814 | M45: =INDEX(OFFSET('Baseline NFPC'!$D$1:$W$1,$D45-1,0),MATCH(M$4,'Baseline NFPC'!$D$10:$W$10,0)) -> 0.5345357 | ... X45: =INDEX(OFFSET('Baseline NFPC'!$D$1:$W$1,$D45-1,0),MATCH(X$4,'Baseline NFPC'!$D$10:$W$10,0)) -> 0.26193275
B46: 6 | C46: Long-term interest rate | D46: 36 | E46: (%) | F46: =INDEX(OFFSET('Baseline NFPC'!$D$1:$W$1,$D46-1,0),MATCH(F$4,'Baseline NFPC'!$D$10:$W$10,0)) -> 2.87 | G46: =INDEX(OFFSET('Baseline NFPC'!$D$1:$W$1,$D46-1,0),MATCH(G$4,'Baseline NFPC'!$D$10:$W$10,0)) -> 2.837221 | H46: =INDEX(OFFSET('Baseline NFPC'!$D$1:$W$1,$D46-1,0),MATCH(H$4,'Baseline NFPC'!$D$10:$W$10,0)) -> 2.903685 | I46: =INDEX(OFFSET('Baseline NFPC'!$D$1:$W$1,$D46-1,0),MATCH(I$4,'Baseline NFPC'!$D$10:$W$10,0)) -> 2.9987319 | J46: =INDEX(OFFSET('Baseline NFPC'!$D$1:$W$1,$D46-1,0),MATCH(J$4,'Baseline NFPC'!$D$10:$W$10,0)) -> 3.0937787 | K46: =INDEX(OFFSET('Baseline NFPC'!$D$1:$W$1,$D46-1,0),MATCH(K$4,'Baseline NFPC'!$D$10:$W$10,0)) -> 3.1888256 | L46: =INDEX(OFFSET('Baseline NFPC'!$D$1:$W$1,$D46-1,0),MATCH(L$4,'Baseline NFPC'!$D$10:$W$10,0)) -> 3.2838725 | M46: =INDEX(OFFSET('Baseline NFPC'!$D$1:$W$1,$D46-1,0),MATCH(M$4,'Baseline NFPC'!$D$10:$W$10,0)) -> 3.3789194 | ... X46: =INDEX(OFFSET('Baseline NFPC'!$D$1:$W$1,$D46-1,0),MATCH(X$4,'Baseline NFPC'!$D$10:$W$10,0)) -> 3.798436
B47: 7 | C47: Short-term interest rate | D47: 37 | E47: (%) | F47: =INDEX(OFFSET('Baseline NFPC'!$D$1:$W$1,$D47-1,0),MATCH(F$4,'Baseline NFPC'!$D$10:$W$10,0)) -> 3.43 | G47: =INDEX(OFFSET('Baseline NFPC'!$D$1:$W$1,$D47-1,0),MATCH(G$4,'Baseline NFPC'!$D$10:$W$10,0)) -> 3.564208 | H47: =INDEX(OFFSET('Baseline NFPC'!$D$1:$W$1,$D47-1,0),MATCH(H$4,'Baseline NFPC'!$D$10:$W$10,0)) -> 2.816375 | I47: =INDEX(OFFSET('Baseline NFPC'!$D$1:$W$1,$D47-1,0),MATCH(I$4,'Baseline NFPC'!$D$10:$W$10,0)) -> 2.8050894 | J47: =INDEX(OFFSET('Baseline NFPC'!$D$1:$W$1,$D47-1,0),MATCH(J$4,'Baseline NFPC'!$D$10:$W$10,0)) -> 2.7938037 | K47: =INDEX(OFFSET('Baseline NFPC'!$D$1:$W$1,$D47-1,0),MATCH(K$4,'Baseline NFPC'!$D$10:$W$10,0)) -> 2.7825181 | L47: =INDEX(OFFSET('Baseline NFPC'!$D$1:$W$1,$D47-1,0),MATCH(L$4,'Baseline NFPC'!$D$10:$W$10,0)) -> 2.7712325 | M47: =INDEX(OFFSET('Baseline NFPC'!$D$1:$W$1,$D47-1,0),MATCH(M$4,'Baseline NFPC'!$D$10:$W$10,0)) -> 2.7599469 | ... X47: =INDEX(OFFSET('Baseline NFPC'!$D$1:$W$1,$D47-1,0),MATCH(X$4,'Baseline NFPC'!$D$10:$W$10,0)) -> 2.435654
B48: 8 | C48: Implicit average interest rate | D48: 35 | E48: (%) | F48: =INDEX(OFFSET('Baseline NFPC'!$D$1:$W$1,$D48-1,0),MATCH(F$4,'Baseline NFPC'!$D$10:$W$10,0)) -> 1.550894 | G48: =INDEX(OFFSET('Baseline NFPC'!$D$1:$W$1,$D48-1,0),MATCH(G$4,'Baseline NFPC'!$D$10:$W$10,0)) -> 1.641526 | H48: =INDEX(OFFSET('Baseline NFPC'!$D$1:$W$1,$D48-1,0),MATCH(H$4,'Baseline NFPC'!$D$10:$W$10,0)) -> 1.684386 | I48: =INDEX(OFFSET('Baseline NFPC'!$D$1:$W$1,$D48-1,0),MATCH(I$4,'Baseline NFPC'!$D$10:$W$10,0)) -> 1.7995764 | J48: =INDEX(OFFSET('Baseline NFPC'!$D$1:$W$1,$D48-1,0),MATCH(J$4,'Baseline NFPC'!$D$10:$W$10,0)) -> 1.8573201 | K48: =INDEX(OFFSET('Baseline NFPC'!$D$1:$W$1,$D48-1,0),MATCH(K$4,'Baseline NFPC'!$D$10:$W$10,0)) -> 1.8994082 | L48: =INDEX(OFFSET('Baseline NFPC'!$D$1:$W$1,$D48-1,0),MATCH(L$4,'Baseline NFPC'!$D$10:$W$10,0)) -> 1.9496329 | M48: =INDEX(OFFSET('Baseline NFPC'!$D$1:$W$1,$D48-1,0),MATCH(M$4,'Baseline NFPC'!$D$10:$W$10,0)) -> 2.0061124 | ... X48: =INDEX(OFFSET('Baseline NFPC'!$D$1:$W$1,$D48-1,0),MATCH(X$4,'Baseline NFPC'!$D$10:$W$10,0)) -> 2.6116148
B49: 9 | C49: Potential GDP | D49: 26 | E49: (growth rate) | F49: =(INDEX(OFFSET('Baseline NFPC'!$D$1:$W$1,$D49-1,0),MATCH(F$4,'Baseline NFPC'!$D$10:$W$10,0))/INDEX(OFFSET('Baseline NFPC'!$D$1:$W$1,$D49-1,0),MATCH(E$4,'Baseline NFPC'!$D$10:$W$10,0))-1)*100 -> 4.333524 | G49: =(INDEX(OFFSET('Baseline NFPC'!$D$1:$W$1,$D49-1,0),MATCH(G$4,'Baseline NFPC'!$D$10:$W$10,0))/INDEX(OFFSET('Baseline NFPC'!$D$1:$W$1,$D49-1,0),MATCH(F$4,'Baseline NFPC'!$D$10:$W$10,0))-1)*100 -> 3.615591 | H49: =(INDEX(OFFSET('Baseline NFPC'!$D$1:$W$1,$D49-1,0),MATCH(H$4,'Baseline NFPC'!$D$10:$W$10,0))/INDEX(OFFSET('Baseline NFPC'!$D$1:$W$1,$D49-1,0),MATCH(G$4,'Baseline NFPC'!$D$10:$W$10,0))-1)*100 -> 3.285812 | I49: =(INDEX(OFFSET('Baseline NFPC'!$D$1:$W$1,$D49-1,0),MATCH(I$4,'Baseline NFPC'!$D$10:$W$10,0))/INDEX(OFFSET('Baseline NFPC'!$D$1:$W$1,$D49-1,0),MATCH(H$4,'Baseline NFPC'!$D$10:$W$10,0))-1)*100 -> 3.394844 | J49: =(INDEX(OFFSET('Baseline NFPC'!$D$1:$W$1,$D49-1,0),MATCH(J$4,'Baseline NFPC'!$D$10:$W$10,0))/INDEX(OFFSET('Baseline NFPC'!$D$1:$W$1,$D49-1,0),MATCH(I$4,'Baseline NFPC'!$D$10:$W$10,0))-1)*100 -> 3.335869 | K49: =(INDEX(OFFSET('Baseline NFPC'!$D$1:$W$1,$D49-1,0),MATCH(K$4,'Baseline NFPC'!$D$10:$W$10,0))/INDEX(OFFSET('Baseline NFPC'!$D$1:$W$1,$D49-1,0),MATCH(J$4,'Baseline NFPC'!$D$10:$W$10,0))-1)*100 -> 3.345161 | L49: =(INDEX(OFFSET('Baseline NFPC'!$D$1:$W$1,$D49-1,0),MATCH(L$4,'Baseline NFPC'!$D$10:$W$10,0))/INDEX(OFFSET('Baseline NFPC'!$D$1:$W$1,$D49-1,0),MATCH(K$4,'Baseline NFPC'!$D$10:$W$10,0))-1)*100 -> 3.164205 | M49: =(INDEX(OFFSET('Baseline NFPC'!$D$1:$W$1,$D49-1,0),MATCH(M$4,'Baseline NFPC'!$D$10:$W$10,0))/INDEX(OFFSET('Baseline NFPC'!$D$1:$W$1,$D49-1,0),MATCH(L$4,'Baseline NFPC'!$D$10:$W$10,0))-1)*100 -> 2.938014 | ... X49: =(INDEX(OFFSET('Baseline NFPC'!$D$1:$W$1,$D49-1,0),MATCH(X$4,'Baseline NFPC'!$D$10:$W$10,0))/INDEX(OFFSET('Baseline NFPC'!$D$1:$W$1,$D49-1,0),MATCH(W$4,'Baseline NFPC'!$D$10:$W$10,0))-1)*100 -> 1.571108
B50: 10 | C50: Real GDP | D50: 23 | E50: (growth rate) | F50: =INDEX(OFFSET('Baseline NFPC'!$D$1:$W$1,$D50-1,0),MATCH(F$4,'Baseline NFPC'!$D$10:$W$10,0)) -> -3.198788 | G50: =INDEX(OFFSET('Baseline NFPC'!$D$1:$W$1,$D50-1,0),MATCH(G$4,'Baseline NFPC'!$D$10:$W$10,0)) -> 1.243702 | H50: =INDEX(OFFSET('Baseline NFPC'!$D$1:$W$1,$D50-1,0),MATCH(H$4,'Baseline NFPC'!$D$10:$W$10,0)) -> 3.393806 | I50: =INDEX(OFFSET('Baseline NFPC'!$D$1:$W$1,$D50-1,0),MATCH(I$4,'Baseline NFPC'!$D$10:$W$10,0)) -> 3.746114 | J50: =INDEX(OFFSET('Baseline NFPC'!$D$1:$W$1,$D50-1,0),MATCH(J$4,'Baseline NFPC'!$D$10:$W$10,0)) -> 3.802369 | K50: =INDEX(OFFSET('Baseline NFPC'!$D$1:$W$1,$D50-1,0),MATCH(K$4,'Baseline NFPC'!$D$10:$W$10,0)) -> 3.577386 | L50: =INDEX(OFFSET('Baseline NFPC'!$D$1:$W$1,$D50-1,0),MATCH(L$4,'Baseline NFPC'!$D$10:$W$10,0)) -> 3.164204 | M50: =INDEX(OFFSET('Baseline NFPC'!$D$1:$W$1,$D50-1,0),MATCH(M$4,'Baseline NFPC'!$D$10:$W$10,0)) -> 2.938014 | ... X50: =INDEX(OFFSET('Baseline NFPC'!$D$1:$W$1,$D50-1,0),MATCH(X$4,'Baseline NFPC'!$D$10:$W$10,0)) -> 1.571112
B51: 11 | C51: GDP deflator | D51: 41 | E51: (growth rate) | F51: =INDEX(OFFSET('Baseline NFPC'!$D$1:$W$1,$D51-1,0),MATCH(F$4,'Baseline NFPC'!$D$10:$W$10,0)) -> 2.965217 | G51: =INDEX(OFFSET('Baseline NFPC'!$D$1:$W$1,$D51-1,0),MATCH(G$4,'Baseline NFPC'!$D$10:$W$10,0)) -> 2.574346 | H51: =INDEX(OFFSET('Baseline NFPC'!$D$1:$W$1,$D51-1,0),MATCH(H$4,'Baseline NFPC'!$D$10:$W$10,0)) -> 1.914897 | I51: =INDEX(OFFSET('Baseline NFPC'!$D$1:$W$1,$D51-1,0),MATCH(I$4,'Baseline NFPC'!$D$10:$W$10,0)) -> 1.9942849 | J51: =INDEX(OFFSET('Baseline NFPC'!$D$1:$W$1,$D51-1,0),MATCH(J$4,'Baseline NFPC'!$D$10:$W$10,0)) -> 2.0736728 | K51: =INDEX(OFFSET('Baseline NFPC'!$D$1:$W$1,$D51-1,0),MATCH(K$4,'Baseline NFPC'!$D$10:$W$10,0)) -> 2.1530606 | L51: =INDEX(OFFSET('Baseline NFPC'!$D$1:$W$1,$D51-1,0),MATCH(L$4,'Baseline NFPC'!$D$10:$W$10,0)) -> 2.2324485 | M51: =INDEX(OFFSET('Baseline NFPC'!$D$1:$W$1,$D51-1,0),MATCH(M$4,'Baseline NFPC'!$D$10:$W$10,0)) -> 2.3118364 | ... X51: =INDEX(OFFSET('Baseline NFPC'!$D$1:$W$1,$D51-1,0),MATCH(X$4,'Baseline NFPC'!$D$10:$W$10,0)) -> 2.33
B52: 12 | C52: Nominal GDP | D52: 32 | E52: (growth rate) | F52: =INDEX(OFFSET('Baseline NFPC'!$D$1:$W$1,$D52-1,0),MATCH(F$4,'Baseline NFPC'!$D$10:$W$10,0)) -> -0.32842201 | G52: =INDEX(OFFSET('Baseline NFPC'!$D$1:$W$1,$D52-1,0),MATCH(G$4,'Baseline NFPC'!$D$10:$W$10,0)) -> 3.8500652 | H52: =INDEX(OFFSET('Baseline NFPC'!$D$1:$W$1,$D52-1,0),MATCH(H$4,'Baseline NFPC'!$D$10:$W$10,0)) -> 5.3736909 | I52: =INDEX(OFFSET('Baseline NFPC'!$D$1:$W$1,$D52-1,0),MATCH(I$4,'Baseline NFPC'!$D$10:$W$10,0)) -> 5.8151071 | J52: =INDEX(OFFSET('Baseline NFPC'!$D$1:$W$1,$D52-1,0),MATCH(J$4,'Baseline NFPC'!$D$10:$W$10,0)) -> 5.9548904 | K52: =INDEX(OFFSET('Baseline NFPC'!$D$1:$W$1,$D52-1,0),MATCH(K$4,'Baseline NFPC'!$D$10:$W$10,0)) -> 5.8074699 | L52: =INDEX(OFFSET('Baseline NFPC'!$D$1:$W$1,$D52-1,0),MATCH(L$4,'Baseline NFPC'!$D$10:$W$10,0)) -> 5.4672917 | M52: =INDEX(OFFSET('Baseline NFPC'!$D$1:$W$1,$D52-1,0),MATCH(M$4,'Baseline NFPC'!$D$10:$W$10,0)) -> 5.3177725 | ... X52: =INDEX(OFFSET('Baseline NFPC'!$D$1:$W$1,$D52-1,0),MATCH(X$4,'Baseline NFPC'!$D$10:$W$10,0)) -> 3.9377189
B53: 13 | C53: Fiscal multiplier | E53: (%) | F53: ='Input data'!$C$49 -> 0.75
C55: Table 7d: Debt projections and additional assumptions (under the planned fiscal path)
F57: ='Input data'!$C$5-1 -> 2023 | G57: =F57+1 -> 2024 | H57: =G57+1 -> 2025 | I57: =H57+1 -> 2026 | J57: =I57+1 -> 2027 | K57: =J57+1 -> 2028 | L57: =K57+1 -> 2029 | M57: =L57+1 -> 2030 | N57: =M57+1 -> 2031 | ... X57: =W57+1 -> 2041
B58: 1 | C58: Gross debt | D58: 90 | E58: (% GDP) | F58: =INDEX(OFFSET('Adjustment scenario'!$D$1:$W$1,$D58-1,0),MATCH(F$4,'Adjustment scenario'!$D$10:$W$10,0)) -> 43.730434 | G58: =INDEX(OFFSET('Adjustment scenario'!$D$1:$W$1,$D58-1,0),MATCH(G$4,'Adjustment scenario'!$D$10:$W$10,0)) -> 42.488825 | H58: =INDEX(OFFSET('Adjustment scenario'!$D$1:$W$1,$D58-1,0),MATCH(H$4,'Adjustment scenario'!$D$10:$W$10,0)) -> 41.199314 | I58: =INDEX(OFFSET('Adjustment scenario'!$D$1:$W$1,$D58-1,0),MATCH(I$4,'Adjustment scenario'!$D$10:$W$10,0)) -> 37.456895 | J58: =INDEX(OFFSET('Adjustment scenario'!$D$1:$W$1,$D58-1,0),MATCH(J$4,'Adjustment scenario'!$D$10:$W$10,0)) -> 33.593172 | K58: =INDEX(OFFSET('Adjustment scenario'!$D$1:$W$1,$D58-1,0),MATCH(K$4,'Adjustment scenario'!$D$10:$W$10,0)) -> 29.816315 | L58: =INDEX(OFFSET('Adjustment scenario'!$D$1:$W$1,$D58-1,0),MATCH(L$4,'Adjustment scenario'!$D$10:$W$10,0)) -> 26.364043 | M58: =INDEX(OFFSET('Adjustment scenario'!$D$1:$W$1,$D58-1,0),MATCH(M$4,'Adjustment scenario'!$D$10:$W$10,0)) -> 23.177269 | ... X58: =INDEX(OFFSET('Adjustment scenario'!$D$1:$W$1,$D58-1,0),MATCH(X$4,'Adjustment scenario'!$D$10:$W$10,0)) -> 2.2971951
B59: =B58+1 -> 2 | C59: Rolled over long-term debt | D59: 92 | E59: (% GDP) | F59: =INDEX(OFFSET('Adjustment scenario'!$D$1:$W$1,$D59-1,0),MATCH(F$4,'Adjustment scenario'!$D$10:$W$10,0)) -> 1.6381495 | G59: =INDEX(OFFSET('Adjustment scenario'!$D$1:$W$1,$D59-1,0),MATCH(G$4,'Adjustment scenario'!$D$10:$W$10,0)) -> 2.0686309 | H59: =INDEX(OFFSET('Adjustment scenario'!$D$1:$W$1,$D59-1,0),MATCH(H$4,'Adjustment scenario'!$D$10:$W$10,0)) -> 2.4597944 | I59: =INDEX(OFFSET('Adjustment scenario'!$D$1:$W$1,$D59-1,0),MATCH(I$4,'Adjustment scenario'!$D$10:$W$10,0)) -> 1.9739953 | J59: =INDEX(OFFSET('Adjustment scenario'!$D$1:$W$1,$D59-1,0),MATCH(J$4,'Adjustment scenario'!$D$10:$W$10,0)) -> 1.3110357 | K59: =INDEX(OFFSET('Adjustment scenario'!$D$1:$W$1,$D59-1,0),MATCH(K$4,'Adjustment scenario'!$D$10:$W$10,0)) -> 1.0533569 | L59: =INDEX(OFFSET('Adjustment scenario'!$D$1:$W$1,$D59-1,0),MATCH(L$4,'Adjustment scenario'!$D$10:$W$10,0)) -> 0.72198685 | M59: =INDEX(OFFSET('Adjustment scenario'!$D$1:$W$1,$D59-1,0),MATCH(M$4,'Adjustment scenario'!$D$10:$W$10,0)) -> 0.18062463 | ... X59: =INDEX(OFFSET('Adjustment scenario'!$D$1:$W$1,$D59-1,0),MATCH(X$4,'Adjustment scenario'!$D$10:$W$10,0)) -> 0
B60: =B59+1 -> 3 | C60: Rolled over short-term debt | D60: 93 | E60: (% GDP) | F60: =INDEX(OFFSET('Adjustment scenario'!$D$1:$W$1,$D60-1,0),MATCH(F$4,'Adjustment scenario'!$D$10:$W$10,0)) -> 4.1065954 | G60: =INDEX(OFFSET('Adjustment scenario'!$D$1:$W$1,$D60-1,0),MATCH(G$4,'Adjustment scenario'!$D$10:$W$10,0)) -> 3.9543503 | H60: =INDEX(OFFSET('Adjustment scenario'!$D$1:$W$1,$D60-1,0),MATCH(H$4,'Adjustment scenario'!$D$10:$W$10,0)) -> 3.7957467 | I60: =INDEX(OFFSET('Adjustment scenario'!$D$1:$W$1,$D60-1,0),MATCH(I$4,'Adjustment scenario'!$D$10:$W$10,0)) -> 2.8170211 | J60: =INDEX(OFFSET('Adjustment scenario'!$D$1:$W$1,$D60-1,0),MATCH(J$4,'Adjustment scenario'!$D$10:$W$10,0)) -> 1.6728084 | K60: =INDEX(OFFSET('Adjustment scenario'!$D$1:$W$1,$D60-1,0),MATCH(K$4,'Adjustment scenario'!$D$10:$W$10,0)) -> 0.76670328 | L60: =INDEX(OFFSET('Adjustment scenario'!$D$1:$W$1,$D60-1,0),MATCH(L$4,'Adjustment scenario'!$D$10:$W$10,0)) -> 0.24454937 | M60: =INDEX(OFFSET('Adjustment scenario'!$D$1:$W$1,$D60-1,0),MATCH(M$4,'Adjustment scenario'!$D$10:$W$10,0)) -> 0.022956839 | ... X60: =INDEX(OFFSET('Adjustment scenario'!$D$1:$W$1,$D60-1,0),MATCH(X$4,'Adjustment scenario'!$D$10:$W$10,0)) -> 0
B61: =B60+1 -> 4 | C61: New long-term debt | D61: 94 | E61: (% GDP) | F61: =INDEX(OFFSET('Adjustment scenario'!$D$1:$W$1,$D61-1,0),MATCH(F$4,'Adjustment scenario'!$D$10:$W$10,0)) -> 0 | G61: =INDEX(OFFSET('Adjustment scenario'!$D$1:$W$1,$D61-1,0),MATCH(G$4,'Adjustment scenario'!$D$10:$W$10,0)) -> 0.33425532 | H61: =INDEX(OFFSET('Adjustment scenario'!$D$1:$W$1,$D61-1,0),MATCH(H$4,'Adjustment scenario'!$D$10:$W$10,0)) -> 0.77242956 | I61: =INDEX(OFFSET('Adjustment scenario'!$D$1:$W$1,$D61-1,0),MATCH(I$4,'Adjustment scenario'!$D$10:$W$10,0)) -> 0 | J61: =INDEX(OFFSET('Adjustment scenario'!$D$1:$W$1,$D61-1,0),MATCH(J$4,'Adjustment scenario'!$D$10:$W$10,0)) -> 0 | K61: =INDEX(OFFSET('Adjustment scenario'!$D$1:$W$1,$D61-1,0),MATCH(K$4,'Adjustment scenario'!$D$10:$W$10,0)) -> 0 | L61: =INDEX(OFFSET('Adjustment scenario'!$D$1:$W$1,$D61-1,0),MATCH(L$4,'Adjustment scenario'!$D$10:$W$10,0)) -> 0 | M61: =INDEX(OFFSET('Adjustment scenario'!$D$1:$W$1,$D61-1,0),MATCH(M$4,'Adjustment scenario'!$D$10:$W$10,0)) -> 0 | ... X61: =INDEX(OFFSET('Adjustment scenario'!$D$1:$W$1,$D61-1,0),MATCH(X$4,'Adjustment scenario'!$D$10:$W$10,0)) -> 0
B62: =B61+1 -> 5 | C62: New short-term debt | D62: 95 | E62: (% GDP) | F62: =INDEX(OFFSET('Adjustment scenario'!$D$1:$W$1,$D62-1,0),MATCH(F$4,'Adjustment scenario'!$D$10:$W$10,0)) -> 0 | G62: =INDEX(OFFSET('Adjustment scenario'!$D$1:$W$1,$D62-1,0),MATCH(G$4,'Adjustment scenario'!$D$10:$W$10,0)) -> 0.045368027 | H62: =INDEX(OFFSET('Adjustment scenario'!$D$1:$W$1,$D62-1,0),MATCH(H$4,'Adjustment scenario'!$D$10:$W$10,0)) -> 0.10484083 | I62: =INDEX(OFFSET('Adjustment scenario'!$D$1:$W$1,$D62-1,0),MATCH(I$4,'Adjustment scenario'!$D$10:$W$10,0)) -> 0 | J62: =INDEX(OFFSET('Adjustment scenario'!$D$1:$W$1,$D62-1,0),MATCH(J$4,'Adjustment scenario'!$D$10:$W$10,0)) -> 0 | K62: =INDEX(OFFSET('Adjustment scenario'!$D$1:$W$1,$D62-1,0),MATCH(K$4,'Adjustment scenario'!$D$10:$W$10,0)) -> 0 | L62: =INDEX(OFFSET('Adjustment scenario'!$D$1:$W$1,$D62-1,0),MATCH(L$4,'Adjustment scenario'!$D$10:$W$10,0)) -> 0 | M62: =INDEX(OFFSET('Adjustment scenario'!$D$1:$W$1,$D62-1,0),MATCH(M$4,'Adjustment scenario'!$D$10:$W$10,0)) -> 0 | ... X62: =INDEX(OFFSET('Adjustment scenario'!$D$1:$W$1,$D62-1,0),MATCH(X$4,'Adjustment scenario'!$D$10:$W$10,0)) -> 0
