Workbook

Sheet Read me
G4: European Commission
G6: Directorate-General for Economic and Financial Affairs
G7: Unit C2 - Sustainability of public finances
G8: ECFIN-Secretariat-C2@ec.europa.eu
C16: FILE DESCRIPTION
C18: Data reported in this file are based on the European Commission (EC) 2024 spring forecast (SF 2024) and macroeconomic and budgetary projections from the joint EC-EPC Ageing Report 2024 (AR 2024).
C22: This file contains a simplified version of the EC model used to calculate the general governement debt ratio dynamics for EU countries under different scenarios. A detailed description of the EC's general governement debt projections can be found in the "Debt Sustainability Monitor 2023" (DSM, March 2024).
C27: HOW TO USE THIS TOOL TO CALCULATE NEW DEBT PROJECTIONS
C29: This tool can be used to calculate debt projections under different macroeconomic and structural primary balance adjustment assumptions. Debt projections for each scenario will update automatically with changes in the macroeconomic assumptions or the adjustment parameters. The fulfilment of DSA-based criteria, the safeguards and the benchmark will be automatically calculated in the sheet "Criteria results". Formulas are fully visible. To assess the impact of alternative adjustment paths compared with the reference trajectory calculated by the EC or to check its robustness to underlying macroeconomic assumptions, the user can modify the content of key cells in the sheets "Criteria results" and "Input data" (see below). Note that, for a proper functioning of the file, you should make sure that Excel is in "Automatic" computation mode, i.e. in the File menu, Option tab, click on "Formulas", "Calculation Options" and "Automatic".
C31: The spreadsheet is composed of the following elements:
D33: The grey sheet "Criteria results" contains three types of cells identified by different colours:
F34: Cells with a yellow background and a red frame can be modified to see the impact of a different duration or pace of adjustment.
F35: Cells with a white or grey background provide results obtained with the adjustment chosen in the yellow cells. To replicate the Commission's calculations, the underlying formulas should not be modified.
F37: Cells with a pale blue background correspond to the Commission's prior guidance provided to the Member State. Those are hard numbers that do not depend on the adjustment chosen in the file.
D39: The sheet "Criteria results" contains six tables: Table 1 "Adjustment input data": the user can set the duration of the plan (4 years under no extension or 7 years under extension) and the yearly adjustment pace in cells F5 and F6 in yellow. Note that the country cell (F4) cannot be changed.
D40: To the right of Table 1, a message automatically signals whether the chosen adjustment is sufficient to fulfill all the requirements, summarising the results from Tables 2 and 3.
D41: Table 2 "DSA-based criteria" reports whether the chosen adjustment fulfils each of the DSA-based criteria.
D42: Table 3 "Safeguards and benchmark" reports whether (i) the chosen adjustment ensures that the debt sustainability safeguard is met, (ii) the 'deficit benchmark', i.e. the minimum adjustment of 0.5 pp. of GDP as a benchmark when the country is in EDP and/or the deficit exceeds 3% of GDP, is binding, and (iii) the deficit resilience safeguard is binding.
D43: Table 4 "Main fiscal variables" reports the annual adjustment over the adjustment period, in terms of change in SPB (line 19) and net primary expenditure growth (line 20). The table also reports the headline balance, the structural balance and debt (lines 21 to 23). The average annual adjustment is reported in cells G24 (average change in SPB over the 4-year plan period), G25 (average change in SPB over the 4-year or 7-year adjustment period), G26 (average net primary expenditure growth over the plan period) and G27 (average net primary expenditure growth over the adjustment period).
D44: Table 5 "DSA-based adjustment" summarises the key characteristics of the adjustment path that complies with the DSA-based criteria before applying the safeguards and benchmark, for a plan both with and without extension.
D45: Table 6 "Reference trajectory" reports the net expenditure growth and the corresponding annual change in SPB that are consistent with all requirements including the safeguards and benchmark, both without and with extension.
D47: The sheet "Input data" in light blue presents the input data, including fiscal and GDP growth assumptions as well as additional fiscal parameters. Unless stated otherwise below, the user can change all values in this tab.
D48: Coloured cells indicate data sources as follows (this colour-coding holds in the other spreadsheets):
F49: Cells in light grey indicate a Commission forecast (available in the AMECO database)
F50: Cells in light red indicate whether the country is subject to an ongoing excessive deficit procedure (EDP) or whether the Commission's June 2024 report under Art. 126(3) of the Treaty recommends opening an EDP. If neither of these conditions are met, the deficit benchmark is not relevant and therefore not applied.
F51: Cells in light blue indicate values from the Ageing Report 2024
F52: Cells in light orange provide parameters needed to compute the decomposition of government debt according to its maturity structure (i.e. short-term and long-term debt, maturing, rolled-over and non-maturing debt). These are fixed shares which the user cannot change.
F53: Cells in dark orange indicate financial market prices.
D54: Non-coloured parameters in cells C49:C70 were calibrated based on different data sources. The data sources are indicated in the corresponding cells of column E. The last part of the sheet "Input data" (cells C73:G77) provides the parameters measuring the size of the cone of the fanchart that results from the stochastic analysis. For reproducibility reasons, these parameters are kept constant.
C56: The next spreadsheets present the deterministic and stochastic projections. Each deterministic projection provides a single path for debt until 2038 or 2041 under certain assumptions for budgetary, macroeconomic and financial variables, while the outcome of the stochastic projections is a distribution of debt paths resulting from a wide set of shocks. The sheets are grouped in four blocs, identified by their colour coding:
D58: The sheet in blue provides, as a reference, the baseline no-fiscal-policy-change scenario. The background colour coding is the same as in the sheet "Input data".
D60: The sheet in orange presents the scenario that automatically corrects the yearly adjustment path to account for the deficit benchmark and the deficit resillience safeguard. By contrast, the yearly adjustment profile is not automatically adjusted to ensure that the debt sustainability safeguard is met. However, the sheet "Criteria results" indicates whether that safeguard is met.
D62: The sheets in green present the deterministic projections that are used to compute the DSA-based requirements (in the sheet "Criteria results"). They include four scenarios:
D63: · Adjustment scenario without safeguard and benchmark
D64: · Financial stress scenario
D65: · Lower SPB scenario
D66: · Adverse 'r-g' scenario
D68: Each scenario is computed automatically based on the yearly adjustment path set in "Criteria results" (see above).
D70: The sheet in dark green presents the stochastic projections surrounding the adjustment scenario without safeguard and benchmark .
C72: Within the orange sheet and each green sheet, the background of the SPB line has three colours. Each colour corresponds to a specific period of the projections:
E73: Light grey indicates the pre-plan period, corresponding to the EC forecast
E74: Mild grey indicates the period during which the SPB adjusts according to the path set in sheet "Criteria results"
E75: Dark grey indicates the period in which the SPB, net of changes in cost of ageing, remains constant at its value of end of adjustment.
D77: In the sheets associated with the stress-test scenarios, i.e. "Financial stress", "Lower SPB" and "Adverse (r-g)", initial shocks are identified as follows:
E78: All variables that are shocked turn very dark grey.
E79: Additionally, for the lower SPB scenario, the cells get thick black borders in the years when the SPB is gradually reduced.
C81: WHERE ARE THE MAIN RESULTS LOCATED?
C82: Debt projections can be found in line 56 or 57 of each scenario. The corresponding net expenditure growth is located in line 79 or 80 in the baseline and adjustment scenario (and Adj. no safeguard) sheets. The average net expenditure growth over the adjustment period is computed in cell D81 of the sheet "Adjustment scenario". As a reminder, these numbers are also available in Table 4 in "Criteria results".
D84: The 'FASTOP reporting' sheet in violet provides help for preparing reporting tables. It readily provides all the tables envisaged in the guidance notice on the "Information Requirements for the Medium-Term Fiscal-Structural Plans" once the parameters are set in the rest of this file. Note that the probability of a declining debt ratio in table 7c derived from the stochastic simulations is only an approximation since the stochastic analysis is not an integral part of this Excel file. For a precise figure, the simulations need to be run. This sheet is therefore only meant to provide assistance. The figures still need to be thoroughly scrutinised before submitting the tables.

Sheet Criteria results
U2: 4 | V2: 0
D3: Table 1 - Adjustment input data | H3: =IF(OR(AND($G$12="ok",$G$13="ok",$G$14="ok",$G$15="ok",$H$12="ok",$I$12="ok",$L$12<>"Not met"), AND($I$12="ok",$J$12="ok",$J$13="ok",$J$14="ok",$J$15="ok",$L$12<>"Not met")), "OK"&CHAR(10)&"adjustment"&CHAR(10)&"complies with all requirements", "NOT OK"&CHAR(10)&"adjustment does not"&CHAR(10)&"comply with all requirements") -> OK adjustment complies with all requirements | U3: 7 | V3: 0.02
D4: Country | F4: MT | V4: 0.04
D5: Number of years of adjustment | F5: 4 | V5: 0.06
D6: Annual adjustment (when benchmark not binding) | F6: 0.44 | V6: 0.08
V7: 0.1
V8: 0.12
G9: Table 2 - DSA-based criteria | L9: Table 3 - Safeguards and benchmark | V9: 0.14
L10: Debt sustainability safeguard * | N10: Deficit benchmark ** | P10: Deficit resilience safeguard | V10: 0.16
G11: Criterion 1 (Debt decreasing under deterministic scenarios) | H11: Criterion 2 * (Debt declining with sufficient probability) | I11: Criterion 3 (Deficit below 3% of GDP) | J11: ="Debt below 60% of GDP in T+"&10+F5&" **" -> Debt below 60% of GDP in T+14 ** | L11: Debt declines by 1pp (0.5pp) of GDP on average as long as debt exceeds 90% (60%) of GDP | M11: Average change in debt | N11: 0.5 pp. of GDP adjustment if deficit in previous year > 3% of GDP | O11: Number of years the benchmark applies | P11: 0.40 pp. (0.25 pp.) of GDP adjustment under plan without (with) extension if structural deficit in previous year > 1.5% of GDP | Q11: Number of years the deficit resilience safeguard applies (over the adjustment horizon) | V11: 0.18
D12: Adjustment scenario | G12: =IF(OR('Adjust. no safeguard'!F57>60,'Adjust. no safeguard'!F77<-3),IF(SUM(OFFSET('Adjust. no safeguard'!$F$83,0,$F$5+1,1,10))=0,"ok","Not met"),"") -> Not met | H12: =IF(OR('Adjust. no safeguard'!F57>60,'Adjust. no safeguard'!F77<-3),IF($F$5=4,IF(Stochastic!$O$17<Stochastic!$J$17,"ok","Not met"),IF(Stochastic!$R$17<Stochastic!$M$17,"ok","Not met")),"") -> Not met | I12: =IF(MIN(OFFSET('Adjust. no safeguard'!$F$77,0,$F$5,1,11))>-3.05,"ok","Not met") -> ok | J12: =IF(OFFSET('Adjust. no safeguard'!$F$57,0,$F$5+10,1,1)<60,"ok","Not met") -> ok | L12: =_xlfn.LET(_xlpm.debtChange,OFFSET('Adjustment scenario'!F58,0,1,1,$F$5), _xlpm.debt6090,OFFSET('Adjustment scenario'!F85,0,1,1,$F$5), _xlpm.debt90,OFFSET('Adjustment scenario'!F84,0,1,1,$F$5), _xlpm.EDP,OFFSET('Adjustment scenario'!F87,0,1,1,$F$5), IF(AND(MAX(_xlpm.debt90)=0,MAX(_xlpm.debt6090)=0),"Debt below 60% of GDP over the adjustment period", IF(MIN(_xlpm.EDP)=1,"Not applicable, reference year is the last year of adjustment", IF(AND(MAX(_xlpm.debt90)=0,MAX(_xlpm.debt6090)=1),IF(AVERAGEIFS(_xlpm.debtChange,_xlpm.debt6090,1,_xlpm.EDP,0)<-0.5,"ok","Not met"), IF(AND(MAX(_xlpm.debt90)=1,MAX(_xlpm.debt6090)=0),IF(AVERAGEIFS(_xlpm.debtChange,_xlpm.EDP,0)<-1,"ok","Not met"), IF(AND(MAX(_xlpm.debt90)=1,MAX(_xlpm.debt6090)=1),IF(AND(AVERAGEIFS(_xlpm.debtChange,_xlpm.debt90,1,_xlpm.EDP,0)<-1,AVERAGEIFS(_xlpm.debtChange,_xlpm.debt6090,1,_xlpm.EDP,0)<-0.5),"ok","Not met"))))))) -> Debt below 60% of GDP over the adjustment period | M12: =_xlfn.LET(_xlpm.debtChange,OFFSET('Adjustment scenario'!F58,0,1,1,$F$5), _xlpm.debt60,OFFSET('Adjustment scenario'!F86,0,1,1,$F$5), _xlpm.debt6090,OFFSET('Adjustment scenario'!F85,0,1,1,$F$5), _xlpm.debt90,OFFSET('Adjustment scenario'!F84,0,1,1,$F$5), _xlpm.EDP,OFFSET('Adjustment scenario'!F87,0,1,1,$F$5), IF(AND(MAX(_xlpm.debt90)=0,MAX(_xlpm.debt6090)=0),"Debt below 60% of GDP over the adjustment period", IF(MIN(_xlpm.EDP)=1,"Not applicable, reference year is the last year of adjustment", IF(AND(MAX(_xlpm.debt90)=0,MAX(_xlpm.debt6090)=1),AVERAGEIFS(_xlpm.debtChange,_xlpm.debt60,1,_xlpm.EDP,0), IF(AND(MAX(_xlpm.debt90)=1,MAX(_xlpm.debt6090)=0),AVERAGEIFS(_xlpm.debtChange,_xlpm.EDP,0), IF(AND(MAX(_xlpm.debt90)=1,MAX(_xlpm.debt6090)=1),AVERAGEIFS(_xlpm.debtChange,_xlpm.debt60,1,_xlpm.EDP,0))))))) -> Debt below 60% of GDP over the adjustment period | N12: =IF(AND(O12=0,F6<0.5),"not relevant","ok") -> ok | O12: =IF(F6<0.5,COUNTIFS('Adjustment scenario'!F77:H77,"<"&-3.049),0)+IF(AND(F5=4,J19>0.5,J19>F6),1,COUNTIFS(J19:M19,">" & F6,J19:M19,">"&0.5)) -> 4 | P12: =IF(OR(AND(F5=4,Q12=0,F6<0.4),AND(F5=7,Q12=0,F6<0.25)),"not relevant, (over the adjustment horizon)","ok") -> ok | Q12: =IF(AND('Criteria results'!$F$5=4,'Criteria results'!$F$6<=0.4),COUNTIFS('Adjustment scenario'!G13:J13,0.4,'Adjustment scenario'!F88:I88,0),IF(AND('Criteria results'!$F$5=7,'Criteria results'!$F$6<=0.25),COUNTIFS('Adjustment scenario'!G13:M13,0.25,'Adjustment scenario'!F88:L88,0),0)) -> 0 | V12: 0.2
D13: Financial stress scenario | G13: =IF(OR('Adjustment scenario'!F57>60,'Adjustment scenario'!F77<-3),IF(SUM(OFFSET('Financial stress'!$F$75,0,$F$5+1,1,10))=0,"ok","Not met"),"") -> Not met | J13: =IF(OR('Adjustment scenario'!F57>60,'Adjustment scenario'!F77<-3),IF(OFFSET('Financial stress'!$F$56,0,$F$5+10,1,1)<60,"ok","Not met"),"") -> ok | V13: 0.22
D14: Lower SPB scenario | G14: =IF(OR('Adjustment scenario'!F57>60,'Adjustment scenario'!F77<-3),IF(SUM(OFFSET('Lower SPB'!$F$75,0,$F$5+1,1,10))=0,"ok","Not met"),"") -> Not met | J14: =IF(OR('Adjustment scenario'!F57>60,'Adjustment scenario'!F77<-3),IF(OFFSET('Lower SPB'!$F$56,0,$F$5+10,1,1)<60,"ok","Not met"),"") -> ok | V14: 0.24
D15: Adverse r-g scenario | G15: =IF(OR('Adjustment scenario'!F57>60,'Adjustment scenario'!F77<-3),IF(SUM(OFFSET('Adverse (r-g)'!$F$76,0,$F$5+1,1,10))=0,"ok","Not met"),"") -> Not met | J15: =IF(OR('Adjustment scenario'!F57>60,'Adjustment scenario'!F77<-3),IF(OFFSET('Adverse (r-g)'!$F$57,0,$F$5+10,1,1)<60,"ok","Not met"),"") -> ok | V15: 0.26
D16: * The stochastic simulations are provided mainly for information, as the Excel worksheet only allows for an approximation of what is done in the Commission's Stata model. Indeed, in this Excel worksheet, the size of the cone of the fanchart is assumed to be constant over different adjustment paths. In ther Stata model, it is a non linear function of the level of debt, as shocks (in particular interest rate shocks) have different impacts according to the level of debt ratio. ** In case a smaller adjustment than the one implied by criterion 1 and criterion 2 is sufficient to ensure that debt is brought (and/or remains) below 60% of GDP under the adjustment scenario and all deterministic stress tests while ensuring that the criterion 3 is met, then that smaller, 'eased-up' adjustment is chosen. | L16: * The average change in debt is computed from the year before the start of the reference trajectory or the year in which the excessive deficit procedure is projected to be abrogated, whichever occurs last, until the end of the adjustment period. ** The deficit benchmark is applied in terms of change in SPB during the transitory period of 2025-2027 and in terms of change in SB thereafter. | V16: 0.28
G17: Table 4 - Main fiscal variables | V17: 0.3
G18: 2025 | H18: 2026 | I18: 2027 | J18: 2028 | K18: 2029 | L18: 2030 | M18: 2031 | V18: 0.32
D19: Annual adjustment (change in SPB) | G19: ='Adjustment scenario'!G12-'Adjustment scenario'!F12 -> 0.5 | H19: ='Adjustment scenario'!H12-'Adjustment scenario'!G12 -> 0.5 | I19: ='Adjustment scenario'!I12-'Adjustment scenario'!H12 -> 0.5 | J19: ='Adjustment scenario'!J12-'Adjustment scenario'!I12 -> 0.53092026 | K19: ='Adjustment scenario'!K12-'Adjustment scenario'!J12 -> 0 | L19: ='Adjustment scenario'!L12-'Adjustment scenario'!K12 -> 0 | M19: ='Adjustment scenario'!M12-'Adjustment scenario'!L12 -> 0 | V19: 0.34
D20: Net primary expenditure growth | G20: ='Adjustment scenario'!G79 -> 6.0362927 | H20: ='Adjustment scenario'!H79 -> 5.8465578 | I20: ='Adjustment scenario'!I79 -> 5.8786849 | J20: ='Adjustment scenario'!J79 -> 5.7334207 | K20: ='Adjustment scenario'!K79 -> 7.1401375 | L20: ='Adjustment scenario'!L79 -> 7.0482306 | M20: ='Adjustment scenario'!M79 -> 6.8942157 | V20: 0.36
D21: Headline balance | G21: ='Adjustment scenario'!G77 -> -4.0758413 | H21: ='Adjustment scenario'!H77 -> -3.6908327 | I21: ='Adjustment scenario'!I77 -> -3.2702742 | J21: ='Adjustment scenario'!J77 -> -2.8034928 | K21: ='Adjustment scenario'!K77 -> -2.5954043 | L21: ='Adjustment scenario'!L77 -> -2.3851764 | M21: ='Adjustment scenario'!M77 -> -2.1778649 | V21: 0.38
D22: Structural balance | G22: ='Adjustment scenario'!G78 -> -3.7272734 | H22: ='Adjustment scenario'!H78 -> -3.288104 | I22: ='Adjustment scenario'!I78 -> -2.8316814 | J22: ='Adjustment scenario'!J78 -> -2.3304991 | K22: ='Adjustment scenario'!K78 -> -2.2800751 | L22: ='Adjustment scenario'!L78 -> -2.2275118 | M22: ='Adjustment scenario'!M78 -> -2.1778649 | V22: 0.4
D23: Debt | G23: ='Adjustment scenario'!G57 -> 52.712875 | H23: ='Adjustment scenario'!H57 -> 52.858887 | I23: ='Adjustment scenario'!I57 -> 52.540436 | J23: ='Adjustment scenario'!J57 -> 51.80375 | K23: ='Adjustment scenario'!K57 -> 50.734076 | L23: ='Adjustment scenario'!L57 -> 49.571815 | M23: ='Adjustment scenario'!M57 -> 48.352048 | V23: 0.42
D24: Average annual adjustment over the plan period | G24: =AVERAGE(G19:J19) -> 0.50773007 | V24: 0.44
D25: Average annual adjustment over the adjustment period | G25: =IF(F5=4,AVERAGE(G19:J19),AVERAGE(G19:M19)) -> 0.50773007 | V25: 0.46
D26: Average net primary expenditure growth over the plan period | G26: =AVERAGE(G20:J20) -> 5.873739 | V26: 0.48
D27: Average net primary expenditure growth over the adjustment period | G27: =IF(F5=4,AVERAGE(G20:J20),AVERAGE(G20:M20)) -> 5.873739 | V27: 0.5
D28: In case of a plan with no extension, both the plan period and the adjustment period last 4 years. In case of a plan with extension, the plan period remains 4 years while the adjustment period lasts 7 years. Morever, in case of extension, if neither the deficit benchmark nor the deficit resilience safeguard are binding, the values in G24 and G25 (and G26 and G27) are the same. However, if the benchmark or the safeguard is binding, the values in those cells can be different. | V28: 0.52
V29: 0.54
G30: Table 5 - DSA-based adjustment * | V30: 0.56
G31: No extension | H31: Extension | V31: 0.58
D32: Number of years of adjustment | G32: 4 | H32: 7 | V32: 0.6
D33: Annual adjustment | G33: 0.44 | H33: 0.28 | V33: 0.62
D34: Probability that debt decreases | G34: 60.049999 | H34: 55.830002 | V34: 0.64
D35: * The adjustment in this table does not account for the minimum adjustment of 0.5 pp. of GDP as a benchmark nor for the debt sustainability and deficit resillience safeguards. | V35: 0.66
V36: 0.68
H37: Table 6 - Reference trajectory | V37: 0.7
G38: Average (2025-28) | H38: 2025 | I38: 2026 | J38: 2027 | K38: 2028 | L38: 2029 | M38: 2030 | N38: 2031 | V38: 0.72
D39: Adjustment in a plan without extension | V39: 0.74
D40: Net primary expenditure growth | G40: 5.873739 | H40: 6.0362927 | I40: 5.8465578 | J40: 5.8786849 | K40: 5.7334207 | V40: 0.76
D41: Annual change in SPB | G41: 0.50773007 | H41: 0.5 | I41: 0.5 | J41: 0.5 | K41: 0.53092026 | V41: 0.78
D42: Adjustment in a plan with extension | V42: 0.8
D43: Net primary expenditure growth | G43: 5.873739 | H43: 6.0362927 | I43: 5.8465578 | J43: 5.8786849 | K43: 5.7334207 | L43: 6.3747954 | M43: 6.2828885 | N43: 6.1288736 | V43: 0.82
D44: Annual change in SPB | G44: 0.50773007 | H44: 0.5 | I44: 0.5 | J44: 0.5 | K44: 0.53092026 | L44: 0.28 | M44: 0.28 | N44: 0.28 | V44: 0.84
V45: 0.86
V46: 0.88
V47: 0.9
V48: 0.92
V49: 0.94
V50: 0.96
V51: 0.98
V52: 1
V53: 1.02
V54: 1.04
V55: 1.06
V56: 1.08
... V82: 1.6

Sheet Input data
B3: Country | C3: MT
B5: Last year before the adjustment | C5: 2024
B6: Last year of adjustment | C6: =C5+'Criteria results'!$F$5 -> 2028
B8: Key assumptions
C9: 2021 | D9: 2022 | E9: 2023 | F9: 2024 | G9: 2025 | H9: 2026 | I9: 2027 | J9: 2028 | K9: 2029 | L9: 2030 | M9: 2031 | N9: 2032 | O9: 2033 | P9: 2034 | Q9: 2035 | R9: 2036 | S9: 2037 | T9: 2038 | U9: 2039 | V9: 2040 | W9: 2041
B10: Fiscal assumptions (% of GDP)
B11: Key fiscal variables (based on the Commission 2024 spring forecast ("SF 2024") T+2 forecast and the June 2024 report prepared under Art. 126(3) of the Treaty)
B12: Debt | C12: 53.92565 | D12: 51.62644 | E12: 50.39661 | F12: 52.02717
B13: Structural primary balance ('+' means 'surplus') | C13: -5.650948 | D13: -4.355204 | E13: -3.790994 | F13: -2.897243
B14: One-off and other temporary measures | C14: 0 | D14: 0 | E14: 0 | F14: 0 | G14: 0 | H14: 0 | I14: 0 | J14: 0 | K14: 0 | L14: 0 | M14: 0 | N14: 0 | O14: 0 | P14: 0 | Q14: 0 | R14: 0 | S14: 0 | T14: 0 | U14: 0 | V14: 0 | W14: 0
B15: Stock-flow adjustments (without exchange rate effect) | C15: 0.8044612 | D15: -1.310275 | E15: -0.9404473 | F15: 1.185197 | G15: 0.0667276 | H15: 0 | I15: 0 | J15: 0 | K15: 0 | L15: 0 | M15: 0 | N15: 0 | O15: 0 | P15: 0 | Q15: 0 | R15: 0 | S15: 0 | T15: 0 | U15: 0 | V15: 0 | W15: 0
B16: Stock-flow adjustment (total) | C16: 0.8044617 | D16: -1.310275 | E16: -0.940448 | F16: 1.185199 | G16: 0.0667244 | H16: 0 | I16: 0 | J16: 0 | K16: 0 | L16: 0 | M16: 0 | N16: 0 | O16: 0 | P16: 0 | Q16: 0 | R16: 0 | S16: 0 | T16: 0 | U16: 0 | V16: 0 | W16: 0
B17: Subject to an excessive deficit procedure (EDP) (0-no/1-yes) | D17: 0 | E17: 0 | F17: 1
B19: Cost of ageing and selected public revenue (based on the Commission-Council 2024 Ageing Report ("AR 2024"))
B20: Total ageing cost (net of taxes on pensions) | C20: =(C21+C22+C23+C24-C25) -> 0 | D20: =(D21+D22+D23+D24-D25) -> 16.93779 | E20: =(E21+E22+E23+E24-E25) -> 16.70416 | F20: =(F21+F22+F23+F24-F25) -> 16.66552 | G20: =(G21+G22+G23+G24-G25) -> 16.60096 | H20: =(H21+H22+H23+H24-H25) -> 16.33519 | I20: =(I21+I22+I23+I24-I25) -> 16.23882 | J20: =(J21+J22+J23+J24-J25) -> 16.15621 | ... W20: =(W21+W22+W23+W24-W25) -> 16.22383
B21: of which: Public pensions expenditure | C21: 0 | D21: 6.15371 | E21: 6.09795 | F21: 6.08687 | G21: 6.00425 | H21: 5.80539 | I21: 5.70283 | J21: 5.60481 | K21: 5.51349 | L21: 5.42252 | M21: 5.33926 | N21: 5.26656 | O21: 5.2159 | P21: 5.17276 | Q21: 5.14267 | R21: 5.12868 | S21: 5.1284 | T21: 5.13779 | U21: 5.1628 | V21: 5.20522 | W21: 5.26226
B22: Health care expenditure | C22: 0 | D22: 5.12169 | E22: 5.0423 | F22: 5.07449 | G22: 5.11459 | H22: 5.06796 | I22: 5.0936 | J22: 5.11895 | K22: 5.14656 | L22: 5.17165 | M22: 5.19882 | N22: 5.2257 | O22: 5.25414 | P22: 5.28374 | Q22: 5.31158 | R22: 5.34077 | S22: 5.36878 | T22: 5.39487 | U22: 5.42025 | V22: 5.44458 | W22: 5.46881
B23: Long-term care expenditure | C23: 0 | D23: 1.16699 | E23: 1.17897 | F23: 1.19932 | G23: 1.23734 | H23: 1.26842 | I23: 1.29737 | J23: 1.32267 | K23: 1.35671 | L23: 1.39339 | M23: 1.42621 | N23: 1.45625 | O23: 1.48419 | P23: 1.51361 | Q23: 1.54132 | R23: 1.56501 | S23: 1.58707 | T23: 1.60587 | U23: 1.62209 | V23: 1.63843 | W23: 1.65457
B24: Education & unemployment benefits expenditure | C24: 0 | D24: 4.4954 | E24: 4.38494 | F24: 4.30484 | G24: 4.24478 | H24: 4.19342 | I24: 4.14502 | J24: 4.10978 | K24: 4.0776 | L24: 4.04751 | M24: 4.01825 | N24: 3.99225 | O24: 3.96234 | P24: 3.93775 | Q24: 3.9192 | R24: 3.90152 | S24: 3.88271 | T24: 3.86701 | U24: 3.85467 | V24: 3.84457 | W24: 3.83819
B25: Taxes on pensions | C25: 0 | D25: 0 | E25: 0 | F25: 0 | G25: 0 | H25: 0 | I25: 0 | J25: 0 | K25: 0 | L25: 0 | M25: 0 | N25: 0 | O25: 0 | P25: 0 | Q25: 0 | R25: 0 | S25: 0 | T25: 0 | U25: 0 | V25: 0 | W25: 0
B26: Property income | C26: 0.5214214 | D26: 0.4365457 | E26: 0.4337021 | F26: 0.4308586 | G26: 0.428015 | H26: 0.4251715 | I26: 0.4223279 | J26: 0.4194843 | K26: 0.4166408 | L26: 0.4137973 | M26: 0.4109537 | N26: 0.4081101 | O26: 0.4052666 | P26: 0.4024231 | Q26: 0.3995795 | R26: 0.396736 | S26: 0.3938924 | T26: 0.3910489 | U26: 0.3882053 | V26: 0.3853618 | W26: 0.3825183
B28: Real GDP growth assumptions (based on SF 2024 T+10 projections and AR 2024 projections)
B29: Actual GDP
B30: Growth rate | C30: 12.51395 | D30: 8.075569 | E30: 5.613926 | F30: 4.57228 | G30: 4.845198 | H30: 4.807363 | I30: 4.880684 | J30: 4.731095 | K30: 4.59818 | L30: 4.504259 | M30: 4.348238 | N30: 4.170129 | O30: 4.115924 | P30: 3.776726 | Q30: 3.437526 | R30: 3.098332 | S30: 2.986427 | T30: 2.845796 | U30: 2.678466 | V30: 2.518222 | W30: 2.369435
B31: Level (billions, national currency) | C31: 13.62455
B32: Potential GDP
B33: Growth rate | C33: 3.858198 | D33: 6.663338 | E33: 5.106291 | F33: 4.918544 | G33: 4.869064 | H33: 4.677318 | I33: 4.707434 | J33: 4.644675 | K33: 4.598182 | L33: 4.504264 | M33: 4.348238 | N33: 4.170125 | O33: 4.115922 | P33: 3.776724 | Q33: 3.437526 | R33: 3.098329 | S33: 2.986424 | T33: 2.845797 | U33: 2.678468 | V33: 2.518225 | W33: 2.369437
B34: Level (billions, national currency) | C34: 13.87421
B36: Interest rates (SF 2024, %)
B37: Nominal implicit interest rate on debt | C37: 2.40894 | D37: 1.98347 | E37: 2.37675 | F37: 2.749095 | G37: 2.738361
B38: Short-term nominal interest rate | D38: 0.35 | E38: 3.43 | F38: 3.564208 | G38: 2.816375
B39: Long-term nominal interest rate | D39: 2.41 | E39: 3.71 | F39: 3.497002 | G39: 3.505358
F40: Bloomberg data, country-specific forward market rates.
B41: Inflation (SF 2024, %)
B42: GDP deflator (national currency) | C42: 2.005253 | D42: 5.261471 | E42: 5.273616 | F42: 3.642343 | G42: 2.533911
B44: Net primary expenditure growth (SF 2024, %)
B45: Net primary expenditure growth | C45: 19.796114 | D45: 13.084528 | E45: 9.2925168 | F45: 5.4768547
B47: Additional parameters
E48: Sources
B49: Fiscal multiplier | C49: 0.75 | E49: Carnot, N. and de Castro, F. (2015), “The Discretionary Fiscal Effort: an Assessment of Fiscal Policy and its Output Effect”, European Economy, Economic Papers, No. 543.
B50: Budget balance semi-elasticity | C50: 0.479 | E50: Mourre, G. et al. (2019), "The Semi-Elasticities Underlying the Cyclically-Adjusted Budget Balance: An Update and Further Analysis", European Economy, Discussion Paper, No. 098.
B52: Long-term nominal interest rate (T+10 convergence value) | C52: 4.14195 | E52: Bloomberg data, country-specific forward market rates.
B53: Short-term nominal interest rate (T+10 convergence value) | C53: 2.72609 | E53: Bloomberg data, country-specific forward market rates.
B54: Long-term nominal interest rate (T+30 convergence value) | C54: 4 | E54: DSM 2023
B55: Short-term nominal interest rate (T+30 convergence value) | C55: 2 | E55: DSM 2023
B57: Share of short-term debt in total government debt | C57: 0.1301843 | E57: Eurostat, average shares over the 3 last available years.
B58: Share of long-term debt in total government debt | C58: =1-C57 -> 0.8698157 | E58: Eurostat, average shares over the 3 last available years.
B59: Share of long-term debt that matures every year (T+10 convergence value) | C59: 0.06099826 | E59: ECB, country-specific historical average shares over the 6 last available years. For post-programme countries (CY, El , IE and PT), the redemption profile of official loans has been taken into account for the computation of the share of long-term debt that matures every year. For these countries, changing this parameter would not affect debt projections.
B61: GDP deflator (national currency) (T+10 convergence value) | C61: 2.55 | E61: Bloomberg data, inflation swaps.
B62: GDP deflator (national currency) (T+30 convergence value) | C62: 2 | E62: Central bank inflation target
B64: Share of primary expenditure in GDP in 2024 | C64: 36.584946 | E64: SF24
B66: Share of outstanding debt in total debt in 2022 | C66: 0.78646407 | E66: Derived from the model and made consistent with the short-term forecast.
B67: Share of rolled-over long-term debt in 2022 | C67: 0.00078725165 | E67: Derived from the model and made consistent with the short-term forecast.
B68: Share of rolled-over short-term debt in 2022 | C68: 0.13092518 | E68: Derived from the model and made consistent with the short-term forecast.
B69: Share of new long-term debt in 2022 | C69: 0.070156009 | E69: Derived from the model and made consistent with the short-term forecast.
B70: Share of new short-term debt in 2022 | C70: 0.011667415 | E70: Derived from the model and made consistent with the short-term forecast.
B72: Stochastic projections: ranges around adjustment scenario
C73: T+1 | D73: T+2 | E73: T+3 | F73: T+4 | G73: T+5
B74: Difference between debt level in 50th and 10th percentiles of the distribution | C74: -8.9614487 | D74: -12.30304 | E74: -14.644211 | F74: -16.357548 | G74: -17.975323
B75: Difference between debt level in 50th and 30th percentiles of the distribution | C75: -3.5068588 | D75: -5.1395798 | E75: -6.1448288 | F75: -6.91325 | G75: -7.4928703
B76: Difference between debt level in 70th and 50th percentiles of the distribution | C76: 3.7307816 | D76: 5.0288773 | E76: 6.0887032 | F76: 7.1095352 | G76: 8.1417656
B77: Difference between debt level in 90th and 50th percentiles of the distribution | C77: 9.0808449 | D77: 12.68605 | E77: 15.469322 | F77: 17.759151 | G77: 19.545589

Sheet Baseline NFPC
B3: Country | C3: ='Input data'!C3 -> MT
B4: Key years
B5: ='Input data'!B5 -> Last year before the adjustment | C5: =+'Input data'!C5 -> 2024
B6: Last year of adjustment | C6: =+C5+'Criteria results'!$F$5 -> 2028
B9: Key assumptions
C10: 2021 | D10: 2022 | E10: 2023 | F10: 2024 | G10: 2025 | H10: 2026 | I10: 2027 | J10: 2028 | K10: 2029 | L10: 2030 | M10: 2031 | N10: 2032 | O10: 2033 | P10: 2034 | Q10: 2035 | R10: 2036 | S10: 2037 | T10: 2038 | U10: 2039 | V10: 2040 | W10: 2041
B11: Fiscal assumptions (% of GDP)
B12: Structural primary balance ('+' means 'surplus') | C12: ='Input data'!C13 -> -5.650948 | D12: ='Input data'!D13 -> -4.355204 | E12: ='Input data'!E13 -> -3.790994 | F12: ='Input data'!F13 -> -2.897243 | G12: =F12 -> -2.897243 | H12: =G12 -> -2.897243 | I12: =H12 -> -2.897243 | J12: =I12 -> -2.897243 | K12: =J12 -> -2.897243 | L12: =K12 -> -2.897243 | M12: =L12 -> -2.897243 | N12: =M12 -> -2.897243 | ... W12: =V12 -> -2.897243
B13: One-off and other temporary measures | C13: ='Input data'!C14 -> 0 | D13: ='Input data'!D14 -> 0 | E13: ='Input data'!E14 -> 0 | F13: ='Input data'!F14 -> 0 | G13: ='Input data'!G14 -> 0 | H13: 0 | I13: 0 | J13: 0 | K13: 0 | L13: 0 | M13: 0 | N13: 0 | O13: 0 | P13: 0 | Q13: 0 | R13: 0 | S13: 0 | T13: 0 | U13: 0 | V13: 0 | W13: 0
B14: Stock flow adjustments (without exchange rate effect) | C14: ='Input data'!C15 -> 0.8044612 | D14: ='Input data'!D15 -> -1.310275 | E14: ='Input data'!E15 -> -0.9404473 | F14: ='Input data'!F15 -> 1.185197 | G14: ='Input data'!G15 -> 0.0667276 | H14: ='Input data'!H15 -> 0 | I14: ='Input data'!I15 -> 0 | J14: ='Input data'!J15 -> 0 | ... W14: ='Input data'!W15 -> 0
B16: ='Input data'!B19 -> Cost of ageing and selected public revenue (based on the Commission-Council 2024 Ageing Report ("AR 2024"))
B17: Total ageing cost (net of taxes on pensions) | C17: ='Input data'!C20 -> 0 | D17: ='Input data'!D20 -> 16.93779 | E17: ='Input data'!E20 -> 16.70416 | F17: ='Input data'!F20 -> 16.66552 | G17: ='Input data'!G20 -> 16.60096 | H17: ='Input data'!H20 -> 16.33519 | I17: ='Input data'!I20 -> 16.23882 | J17: ='Input data'!J20 -> 16.15621 | ... W17: ='Input data'!W20 -> 16.22383
B18: ='Input data'!B26 -> Property income | C18: ='Input data'!C26 -> 0.5214214 | D18: ='Input data'!D26 -> 0.4365457 | E18: ='Input data'!E26 -> 0.4337021 | F18: ='Input data'!F26 -> 0.4308586 | G18: ='Input data'!G26 -> 0.428015 | H18: ='Input data'!H26 -> 0.4251715 | I18: ='Input data'!I26 -> 0.4223279 | ... W18: ='Input data'!W26 -> 0.3825183
B20: GDP growth assumptions
B21: Actual GDP (real)
B22: Level | C22: ='Input data'!C31 -> 13.62455 | D22: =C22*(D23/100+1) -> 14.72481 | E22: =D22*(E23/100+1) -> 15.55145 | F22: =E22*(F23/100+1) -> 16.262506 | G22: =F22*(G23/100+1) -> 17.050456 | H22: =IF(AND(H49>1,G49>1),IF(AND(H49>0,G49>0),H26*(H50/100+1),0)+IF(H49>0,G22*(1+H51/100),0)-G22*(1+'Input data'!H30/100),IF(H49=1,H26,G22*(1+H51/100))) -> 17.870134 | I22: =IF(AND(I49>1,H49>1),IF(AND(I49>0,H49>0),I26*(I50/100+1),0)+IF(I49>0,H22*(1+I51/100),0)-H22*(1+'Input data'!I30/100),IF(I49=1,I26,H22*(1+I51/100))) -> 18.742318 | J22: =IF(AND(J49>1,I49>1),IF(AND(J49>0,I49>0),J26*(J50/100+1),0)+IF(J49>0,I22*(1+J51/100),0)-I22*(1+'Input data'!J30/100),IF(J49=1,J26,I22*(1+J51/100))) -> 19.629035 | K22: =IF(AND(K49>1,J49>1),IF(AND(K49>0,J49>0),K26*(K50/100+1),0)+IF(K49>0,J22*(1+K51/100),0)-J22*(1+'Input data'!K30/100),IF(K49=1,K26,J22*(1+K51/100))) -> 20.531614 | L22: =IF(AND(L49>1,K49>1),IF(AND(L49>0,K49>0),L26*(L50/100+1),0)+IF(L49>0,K22*(1+L51/100),0)-K22*(1+'Input data'!L30/100),IF(L49=1,L26,K22*(1+L51/100))) -> 21.456411 | M22: =IF(AND(M49>1,L49>1),IF(AND(M49>0,L49>0),M26*(M50/100+1),0)+IF(M49>0,L22*(1+M51/100),0)-L22*(1+'Input data'!M30/100),IF(M49=1,M26,L22*(1+M51/100))) -> 22.389387 | N22: =IF(AND(N49>1,M49>1),IF(AND(N49>0,M49>0),N26*(N50/100+1),0)+IF(N49>0,M22*(1+N51/100),0)-M22*(1+'Input data'!N30/100),IF(N49=1,N26,M22*(1+N51/100))) -> 23.323053 | O22: =IF(AND(O49>1,N49>1),IF(AND(O49>0,N49>0),O26*(O50/100+1),0)+IF(O49>0,N22*(1+O51/100),0)-N22*(1+'Input data'!O30/100),IF(O49=1,O26,N22*(1+O51/100))) -> 24.283012 | ... W22: =IF(AND(W49>1,V49>1),IF(AND(W49>0,V49>0),W26*(W50/100+1),0)+IF(W49>0,V22*(1+W51/100),0)-V22*(1+'Input data'!W30/100),IF(W49=1,W26,V22*(1+W51/100))) -> 30.672527
B23: Growth rate | C23: =+'Input data'!C30 -> 12.51395 | D23: =+'Input data'!D30 -> 8.075569 | E23: =+'Input data'!E30 -> 5.613926 | F23: =+'Input data'!F30 -> 4.57228 | G23: =+'Input data'!G30 -> 4.845198 | H23: =100*(H22/G22-1) -> 4.807363 | I23: =100*(I22/H22-1) -> 4.880684 | J23: =100*(J22/I22-1) -> 4.731095 | K23: =100*(K22/J22-1) -> 4.59818 | L23: =100*(L22/K22-1) -> 4.504259 | M23: =100*(M22/L22-1) -> 4.348238 | N23: =100*(N22/M22-1) -> 4.170129 | O23: =100*(O22/N22-1) -> 4.115924 | ... W23: =100*(W22/V22-1) -> 2.369435
B25: Potential GDP (real)
B26: Level | C26: ='Input data'!C34 -> 13.87421 | D26: =+C26*(1+'Input data'!D33/100) -> 14.798696 | E26: =+D26*(1+'Input data'!E33/100) -> 15.55436 | F26: =+E26*(1+'Input data'!F33/100) -> 16.319408 | G26: =+F26*(1+'Input data'!G33/100) -> 17.11401 | H26: =+G26*(1+'Input data'!H33/100) -> 17.914487 | I26: =+H26*(1+'Input data'!I33/100) -> 18.7578 | J26: =+I26*(1+'Input data'!J33/100) -> 19.629039 | K26: =+J26*(1+'Input data'!K33/100) -> 20.531618 | ... W26: =+V26*(1+'Input data'!W33/100) -> 30.672533
B28: Output gap
B29: Output gap | C29: =100*(C22/C26-1) -> -1.7994538 | D29: =100*(D22/D26-1) -> -0.49927084 | E29: =100*(E22/E26-1) -> -0.018709187 | F29: =100*(F22/F26-1) -> -0.34867871 | G29: =100*(G22/G26-1) -> -0.37135726 | H29: =100*(H22/H26-1) -> -0.24758444 | I29: =100*(I22/I26-1) -> -0.082533063 | J29: =100*(J22/J26-1) -> -1.6991809e-05 | ... W29: =100*(W22/W26-1) -> -1.7977685e-05
B31: Actual GDP (nominal, national currency)
B32: Growth rate | C32: =100*((1+C23/100)*(1+C41/100)-1) -> 14.770139 | D32: =100*((1+D23/100)*(1+D41/100)-1) -> 13.761934 | E32: =100*((1+E23/100)*(1+E41/100)-1) -> 11.183599 | F32: =100*((1+F23/100)*(1+F41/100)-1) -> 8.3811611 | G32: =100*((1+G23/100)*(1+G41/100)-1) -> 7.501882 | H32: =100*((1+H23/100)*(1+H41/100)-1) -> 7.4651961 | I32: =100*((1+I23/100)*(1+I41/100)-1) -> 7.5424858 | J32: =100*((1+J23/100)*(1+J41/100)-1) -> 7.3912066 | ... W32: =100*((1+W23/100)*(1+W41/100)-1) -> 4.7546428
B34: Interest rate
B35: Nominal implicit interest rate on debt | C35: ='Input data'!C37 -> 2.40894 | D35: ='Input data'!D37 -> 1.98347 | E35: ='Input data'!E37 -> 2.37675 | F35: ='Input data'!F37 -> 2.749095 | G35: ='Input data'!G37 -> 2.738361 | H35: =H96 -> 2.8541319 | I35: =I96 -> 2.9384591 | J35: =J96 -> 3.01999 | K35: =K96 -> 3.0997302 | L35: =L96 -> 3.1785659 | M35: =M96 -> 3.2566136 | N35: =N96 -> 3.3340054 | O35: =O96 -> 3.4108901 | ... W35: =W96 -> 3.7130399
B36: Long-term interest rate | E36: ='Input data'!E39 -> 3.71 | F36: ='Input data'!F39 -> 3.497002 | G36: ='Input data'!G39 -> 3.505358 | H36: =G36+($O$36-$G$36)/($O$10-$G$10) -> 3.584932 | I36: =H36+($O$36-$G$36)/($O$10-$G$10) -> 3.664506 | J36: =I36+($O$36-$G$36)/($O$10-$G$10) -> 3.74408 | K36: =J36+($O$36-$G$36)/($O$10-$G$10) -> 3.823654 | L36: =K36+($O$36-$G$36)/($O$10-$G$10) -> 3.903228 | M36: =L36+($O$36-$G$36)/($O$10-$G$10) -> 3.982802 | N36: =M36+($O$36-$G$36)/($O$10-$G$10) -> 4.062376 | O36: ='Input data'!$C$52 -> 4.14195 | P36: =$O$36+('Input data'!$C$54-'Input data'!$C$52)/20*('Baseline NFPC'!P$10-2033) -> 4.1348525 | Q36: =$O$36+('Input data'!$C$54-'Input data'!$C$52)/20*('Baseline NFPC'!Q$10-2033) -> 4.127755 | R36: =$O$36+('Input data'!$C$54-'Input data'!$C$52)/20*('Baseline NFPC'!R$10-2033) -> 4.1206575 | S36: =$O$36+('Input data'!$C$54-'Input data'!$C$52)/20*('Baseline NFPC'!S$10-2033) -> 4.11356 | T36: =$O$36+('Input data'!$C$54-'Input data'!$C$52)/20*('Baseline NFPC'!T$10-2033) -> 4.1064625 | U36: =$O$36+('Input data'!$C$54-'Input data'!$C$52)/20*('Baseline NFPC'!U$10-2033) -> 4.099365 | V36: =$O$36+('Input data'!$C$54-'Input data'!$C$52)/20*('Baseline NFPC'!V$10-2033) -> 4.0922675 | W36: =$O$36+('Input data'!$C$54-'Input data'!$C$52)/20*('Baseline NFPC'!W$10-2033) -> 4.08517
B37: Short-term interest rate | E37: ='Input data'!E$38 -> 3.43 | F37: ='Input data'!F$38 -> 3.564208 | G37: ='Input data'!G$38 -> 2.816375 | H37: =G37+($O$37-$G$37)/($O$10-$G$10) -> 2.8050894 | I37: =H37+($O$37-$G$37)/($O$10-$G$10) -> 2.7938037 | J37: =I37+($O$37-$G$37)/($O$10-$G$10) -> 2.7825181 | K37: =J37+($O$37-$G$37)/($O$10-$G$10) -> 2.7712325 | L37: =K37+($O$37-$G$37)/($O$10-$G$10) -> 2.7599469 | M37: =L37+($O$37-$G$37)/($O$10-$G$10) -> 2.7486612 | N37: =M37+($O$37-$G$37)/($O$10-$G$10) -> 2.7373756 | O37: ='Input data'!$C$53 -> 2.72609 | P37: =$O$37+('Input data'!$C$55-'Input data'!$C$53)/20*('Baseline NFPC'!P$10-2033) -> 2.6897855 | Q37: =$O$37+('Input data'!$C$55-'Input data'!$C$53)/20*('Baseline NFPC'!Q$10-2033) -> 2.653481 | R37: =$O$37+('Input data'!$C$55-'Input data'!$C$53)/20*('Baseline NFPC'!R$10-2033) -> 2.6171765 | S37: =$O$37+('Input data'!$C$55-'Input data'!$C$53)/20*('Baseline NFPC'!S$10-2033) -> 2.580872 | T37: =$O$37+('Input data'!$C$55-'Input data'!$C$53)/20*('Baseline NFPC'!T$10-2033) -> 2.5445675 | U37: =$O$37+('Input data'!$C$55-'Input data'!$C$53)/20*('Baseline NFPC'!U$10-2033) -> 2.508263 | V37: =$O$37+('Input data'!$C$55-'Input data'!$C$53)/20*('Baseline NFPC'!V$10-2033) -> 2.4719585 | W37: =$O$37+('Input data'!$C$55-'Input data'!$C$53)/20*('Baseline NFPC'!W$10-2033) -> 2.435654
B38: Share of long-term debt that matures every year | C38: 0.08190323 | D38: 0.001 | E38: 0.04901889 | F38: 0.04747952 | G38: =IF(OR($C$3="EL",$C$3="CY",$C$3="IE",$C$3="PT"),VLOOKUP($C$3,$B$110:$T$114,MATCH(G$10,$B$110:$T$110,0),0),$F$38+('Input data'!$C$59-$F$38)/($O$10-$F$10)*(G10-$F$10)) -> 0.048981602 | H38: =IF(OR($C$3="EL",$C$3="CY",$C$3="IE",$C$3="PT"),VLOOKUP($C$3,$B$110:$T$114,MATCH(H$10,$B$110:$T$110,0),0),$F$38+('Input data'!$C$59-$F$38)/($O$10-$F$10)*(H10-$F$10)) -> 0.050483684 | I38: =IF(OR($C$3="EL",$C$3="CY",$C$3="IE",$C$3="PT"),VLOOKUP($C$3,$B$110:$T$114,MATCH(I$10,$B$110:$T$110,0),0),$F$38+('Input data'!$C$59-$F$38)/($O$10-$F$10)*(I10-$F$10)) -> 0.051985767 | J38: =IF(OR($C$3="EL",$C$3="CY",$C$3="IE",$C$3="PT"),VLOOKUP($C$3,$B$110:$T$114,MATCH(J$10,$B$110:$T$110,0),0),$F$38+('Input data'!$C$59-$F$38)/($O$10-$F$10)*(J10-$F$10)) -> 0.053487849 | K38: =IF(OR($C$3="EL",$C$3="CY",$C$3="IE",$C$3="PT"),VLOOKUP($C$3,$B$110:$T$114,MATCH(K$10,$B$110:$T$110,0),0),$F$38+('Input data'!$C$59-$F$38)/($O$10-$F$10)*(K10-$F$10)) -> 0.054989931 | L38: =IF(OR($C$3="EL",$C$3="CY",$C$3="IE",$C$3="PT"),VLOOKUP($C$3,$B$110:$T$114,MATCH(L$10,$B$110:$T$110,0),0),$F$38+('Input data'!$C$59-$F$38)/($O$10-$F$10)*(L10-$F$10)) -> 0.056492013 | M38: =IF(OR($C$3="EL",$C$3="CY",$C$3="IE",$C$3="PT"),VLOOKUP($C$3,$B$110:$T$114,MATCH(M$10,$B$110:$T$110,0),0),$F$38+('Input data'!$C$59-$F$38)/($O$10-$F$10)*(M10-$F$10)) -> 0.057994096 | N38: =IF(OR($C$3="EL",$C$3="CY",$C$3="IE",$C$3="PT"),VLOOKUP($C$3,$B$110:$T$114,MATCH(N$10,$B$110:$T$110,0),0),$F$38+('Input data'!$C$59-$F$38)/($O$10-$F$10)*(N10-$F$10)) -> 0.059496178 | O38: =IF(OR($C$3="EL",$C$3="CY",$C$3="IE",$C$3="PT"),VLOOKUP($C$3,$B$110:$T$114,MATCH(O$10,$B$110:$T$110,0),0),'Input data'!$C$59) -> 0.06099826 | P38: =IF(OR($C$3="EL",$C$3="CY",$C$3="IE",$C$3="PT"),VLOOKUP($C$3,$B$110:$T$114,MATCH(P$10,$B$110:$T$110,0),0),'Input data'!$C$59) -> 0.06099826 | Q38: =IF(OR($C$3="EL",$C$3="CY",$C$3="IE",$C$3="PT"),VLOOKUP($C$3,$B$110:$T$114,MATCH(Q$10,$B$110:$T$110,0),0),'Input data'!$C$59) -> 0.06099826 | R38: =IF(OR($C$3="EL",$C$3="CY",$C$3="IE",$C$3="PT"),VLOOKUP($C$3,$B$110:$T$114,MATCH(R$10,$B$110:$T$110,0),0),'Input data'!$C$59) -> 0.06099826 | S38: =IF(OR($C$3="EL",$C$3="CY",$C$3="IE",$C$3="PT"),VLOOKUP($C$3,$B$110:$T$114,MATCH(S$10,$B$110:$T$110,0),0),'Input data'!$C$59) -> 0.06099826 | T38: =IF(OR($C$3="EL",$C$3="CY",$C$3="IE",$C$3="PT"),VLOOKUP($C$3,$B$110:$T$114,MATCH(T$10,$B$110:$T$110,0),0),'Input data'!$C$59) -> 0.06099826 | U38: =IF(OR($C$3="EL",$C$3="CY",$C$3="IE",$C$3="PT"),VLOOKUP($C$3,$B$110:$W$114,MATCH(U$10,$B$110:$W$110,0),0),'Input data'!$C$59) -> 0.06099826 | V38: =IF(OR($C$3="EL",$C$3="CY",$C$3="IE",$C$3="PT"),VLOOKUP($C$3,$B$110:$W$114,MATCH(V$10,$B$110:$W$110,0),0),'Input data'!$C$59) -> 0.06099826 | W38: =IF(OR($C$3="EL",$C$3="CY",$C$3="IE",$C$3="PT"),VLOOKUP($C$3,$B$110:$W$114,MATCH(W$10,$B$110:$W$110,0),0),'Input data'!$C$59) -> 0.06099826
B40: Inflation and exchange rate
B41: GDP deflator (national currency) | C41: ='Input data'!C42 -> 2.005253 | D41: ='Input data'!D42 -> 5.261471 | E41: ='Input data'!E42 -> 5.273616 | F41: ='Input data'!F42 -> 3.642343 | G41: ='Input data'!G42 -> 2.533911 | H41: =$G$41+($O$41-$G$41)/($O$10-$G$10)*(H10-$G$10) -> 2.5359221 | I41: =$G$41+($O$41-$G$41)/($O$10-$G$10)*(I10-$G$10) -> 2.5379333 | J41: =$G$41+($O$41-$G$41)/($O$10-$G$10)*(J10-$G$10) -> 2.5399444 | K41: =$G$41+($O$41-$G$41)/($O$10-$G$10)*(K10-$G$10) -> 2.5419555 | L41: =$G$41+($O$41-$G$41)/($O$10-$G$10)*(L10-$G$10) -> 2.5439666 | M41: =$G$41+($O$41-$G$41)/($O$10-$G$10)*(M10-$G$10) -> 2.5459777 | N41: =$G$41+($O$41-$G$41)/($O$10-$G$10)*(N10-$G$10) -> 2.5479889 | O41: ='Input data'!$C$61 -> 2.55 | P41: =$O$41+('Input data'!$C$62-'Input data'!$C$61)/20*(P$10-2033) -> 2.5225 | Q41: =$O$41+('Input data'!$C$62-'Input data'!$C$61)/20*(Q$10-2033) -> 2.495 | R41: =$O$41+('Input data'!$C$62-'Input data'!$C$61)/20*(R$10-2033) -> 2.4675 | S41: =$O$41+('Input data'!$C$62-'Input data'!$C$61)/20*(S$10-2033) -> 2.44 | T41: =$O$41+('Input data'!$C$62-'Input data'!$C$61)/20*(T$10-2033) -> 2.4125 | U41: =$O$41+('Input data'!$C$62-'Input data'!$C$61)/20*(U$10-2033) -> 2.385 | V41: =$O$41+('Input data'!$C$62-'Input data'!$C$61)/20*(V$10-2033) -> 2.3575 | W41: =$O$41+('Input data'!$C$62-'Input data'!$C$61)/20*(W$10-2033) -> 2.33
B42: Exchange rate composite change (weighted by share of debt in each currency) | C42: 1 | D42: 1 | E42: 1 | F42: 1 | G42: 0.9999999 | H42: 1 | I42: 1 | J42: 1 | K42: 1 | L42: 1 | M42: 1 | N42: 1 | O42: 1 | P42: 1 | Q42: 1 | R42: 1 | S42: 1 | T42: 1 | U42: 1 | V42: 1 | W42: 1
B44: Intermediate calculations (growth rate equation)
B46: Fiscal multiplier | C46: ='Input data'!C49 -> 0.75
B47: Budget balance semi-elasticity | C47: ='Input data'!C50 -> 0.479
B49: Auxiliary variable to control the closure of the output gap | D49: =IF(AND(ABS((D12-C12)-('Input data'!D13-'Input data'!C13))>0.0001,ABS(D12-C12)>0.0001,D$10>$C$5),4,IF(C49=4,3,IF(C49=3,2,IF(C49=2,1,0)))) -> 0 | E49: =IF(AND(ABS((E12-D12)-('Input data'!E13-'Input data'!D13))>0.0001,ABS(E12-D12)>0.0001,E$10>$C$5),4,IF(D49=4,3,IF(D49=3,2,IF(D49=2,1,0)))) -> 0 | F49: =IF(AND(ABS((F12-E12)-('Input data'!F13-'Input data'!E13))>0.0001,ABS(F12-E12)>0.0001,F$10>$C$5),4,IF(E49=4,3,IF(E49=3,2,IF(E49=2,1,0)))) -> 0 | G49: =IF(AND(ABS((G12-F12)-('Input data'!G13-'Input data'!F13))>0.0001,ABS(G12-F12)>0.0001,G$10>$C$5),4,IF(F49=4,3,IF(F49=3,2,IF(F49=2,1,0)))) -> 0 | H49: =IF(AND(ABS((H12-G12)-('Input data'!H13-'Input data'!G13))>0.0001,ABS(H12-G12)>0.0001,H$10>$C$5),4,IF(G49=4,3,IF(G49=3,2,IF(G49=2,1,0)))) -> 0 | I49: =IF(AND(ABS((I12-H12)-('Input data'!I13-'Input data'!H13))>0.0001,ABS(I12-H12)>0.0001,I$10>$C$5),4,IF(H49=4,3,IF(H49=3,2,IF(H49=2,1,0)))) -> 0 | J49: =IF(AND(ABS((J12-I12)-('Input data'!J13-'Input data'!I13))>0.0001,ABS(J12-I12)>0.0001,J$10>$C$5),4,IF(I49=4,3,IF(I49=3,2,IF(I49=2,1,0)))) -> 0 | K49: =IF(AND(ABS((K12-J12)-('Input data'!K13-'Input data'!J13))>0.0001,ABS(K12-J12)>0.0001,K$10>$C$5),4,IF(J49=4,3,IF(J49=3,2,IF(J49=2,1,0)))) -> 0 | ... W49: =IF(AND(ABS((W12-V12)-('Input data'!W13-'Input data'!V13))>0.0001,ABS(W12-V12)>0.0001,W$10>$C$5),4,IF(V49=4,3,IF(V49=3,2,IF(V49=2,1,0)))) -> 0
B50: OG intermediate auxiliary value | D50: =IF(C49=4,2/3*C29,IF(C49=3,1/3*B29,0)) -> 0 | E50: =IF(D49=4,2/3*D29,IF(D49=3,1/3*C29,0)) -> 0 | F50: =IF(E49=4,2/3*E29,IF(E49=3,1/3*D29,0)) -> 0 | G50: =IF(F49=4,2/3*F29,IF(F49=3,1/3*E29,0)) -> 0 | H50: =IF(G49=4,2/3*G29,IF(G49=3,1/3*F29,0)) -> 0 | I50: =IF(H49=4,2/3*H29,IF(H49=3,1/3*G29,0)) -> 0 | J50: =IF(I49=4,2/3*I29,IF(I49=3,1/3*H29,0)) -> 0 | K50: =IF(J49=4,2/3*J29,IF(J49=3,1/3*I29,0)) -> 0 | ... W50: =IF(V49=4,2/3*V29,IF(V49=3,1/3*U29,0)) -> 0
B51: GDP intermediate growth rate - only feedback effect and no closure of the OG | D51: ='Input data'!D30-$C$46*((D12-C12)-('Input data'!D13-'Input data'!C13)) -> 8.075569 | E51: ='Input data'!E30-$C$46*((E12-D12)-('Input data'!E13-'Input data'!D13)) -> 5.613926 | F51: ='Input data'!F30-$C$46*((F12-E12)-('Input data'!F13-'Input data'!E13)) -> 4.57228 | G51: ='Input data'!G30-$C$46*((G12-F12)-('Input data'!G13-'Input data'!F13)) -> 7.0181303 | H51: ='Input data'!H30-$C$46*((H12-G12)) -> 4.807363 | I51: ='Input data'!I30-$C$46*((I12-H12)) -> 4.880684 | J51: ='Input data'!J30-$C$46*((J12-I12)) -> 4.731095 | K51: ='Input data'!K30-$C$46*((K12-J12)) -> 4.59818 | L51: ='Input data'!L30-$C$46*((L12-K12)) -> 4.504259 | M51: ='Input data'!M30-$C$46*((M12-L12)) -> 4.348238 | N51: ='Input data'!N30-$C$46*((N12-M12)) -> 4.170129 | O51: ='Input data'!O30-$C$46*((O12-N12)) -> 4.115924 | ... W51: ='Input data'!W30-$C$46*((W12-V12)) -> 2.369435
B53: Debt projections
C55: 2021 | D55: 2022 | E55: 2023 | F55: 2024 | G55: 2025 | H55: 2026 | I55: 2027 | J55: 2028 | K55: 2029 | L55: 2030 | M55: 2031 | N55: 2032 | O55: 2033 | P55: 2034 | Q55: 2035 | R55: 2036 | S55: 2037 | T55: 2038 | U55: 2039 | V55: 2040 | W55: 2041
B56: Gross debt | C56: =+'Input data'!C12 -> 53.92565 | D56: =+C56+D57 -> 51.62648 | E56: =+D56+E57 -> 50.396658 | F56: =+E56+F57 -> 52.027241 | G56: =+F56+G57 -> 52.801993 | H56: =+G56+H57 -> 53.227584 | I56: =+H56+I57 -> 53.467452 | J56: =+I56+J57 -> 53.690446 | K56: =+J56+K57 -> 53.94971 | ... W56: =+V56+W57 -> 65.588764
B57: Change in debt (-1+2+3) | D57: =-D58+D66+D71 -> -2.2991703 | E57: =-E58+E66+E71 -> -1.2298213 | F57: =-F58+F66+F71 -> 1.6305821 | G57: =-G58+G66+G71 -> 0.77475213 | H57: =-H58+H66+H71 -> 0.42559091 | I57: =-I58+I66+I71 -> 0.23986842 | J57: =-J58+J66+J71 -> 0.22299378 | K57: =-K58+K66+K71 -> 0.25926472 | ... W57: =-W58+W66+W71 -> 1.8703328
B58: (1) Primary balance (1.1 + 1.2 - 1.3 -1.4 -1.5 - 1.6 -1.7) | D58: =D59+D60-D61-D62-D63-D64-D65 -> -4.5943547 | E58: =E59+E60-E61-E62-E63-E64-E65 -> -3.7999557 | F58: =F59+F60-F61-F62-F63-F64-F65 -> -3.0642601 | G58: =G59+G60-G61-G62-G63-G64-G65 -> -3.0134067 | H58: =H59+H60-H61-H62-H63-H64-H65 -> -2.691193 | I58: =I59+I60-I61-I62-I63-I64-I65 -> -2.518607 | J58: =J59+J60-J61-J62-J63-J64-J65 -> -2.3993154 | K58: =K59+K60-K61-K62-K63-K64-K65 -> -2.3403099 | ... W58: =W59+W60-W61-W62-W63-W64-W65 -> -2.5039019
B59: (1.1) Structural primary balance (before ageing cost) | D59: =D12 -> -4.355204 | E59: =E12 -> -3.790994 | F59: =F12 -> -2.897243 | G59: =IF(G12="",F59,G12) -> -2.897243 | H59: =IF(H12="",G59,H12) -> -2.897243 | I59: =IF(I12="",H59,I12) -> -2.897243 | J59: =IF(J12="",I59,J12) -> -2.897243 | K59: =IF(K12="",J59,K12) -> -2.897243 | L59: =IF(L12="",K59,L12) -> -2.897243 | M59: =IF(M12="",L59,M12) -> -2.897243 | N59: =IF(N12="",M59,N12) -> -2.897243 | ... W59: =IF(W12="",V59,W12) -> -2.897243
B60: (1.2) Cumulated budgetary effort (in terms of primary balance) | D60: 0 | E60: 0 | F60: 0 | G60: 0 | H60: 0 | I60: 0 | J60: 0 | K60: 0 | L60: 0 | M60: 0 | N60: 0 | O60: 0 | P60: 0 | Q60: 0 | R60: 0 | S60: 0 | T60: 0 | U60: 0 | V60: 0 | W60: 0
B61: (1.3) Cyclical component | D61: =-$C$47*D29 -> 0.23915073 | E61: =-$C$47*E29 -> 0.0089617005 | F61: =-$C$47*F29 -> 0.1670171 | G61: =-$C$47*G29 -> 0.17788013 | H61: =-$C$47*H29 -> 0.11859295 | I61: =-$C$47*I29 -> 0.039533337 | J61: =-$C$47*J29 -> 8.1390764e-06 | K61: =-$C$47*K29 -> 9.0549621e-06 | ... W61: =-$C$47*W29 -> 8.6113111e-06
B62: (1.4) One-off and other temporary measures | D62: =-D13 -> 0 | E62: =-E13 -> 0 | F62: =-F13 -> 0 | G62: =-G13 -> 0 | H62: =-H13 -> 0 | I62: =-I13 -> 0 | J62: =-J13 -> 0 | K62: =-K13 -> 0 | ... W62: =-W13 -> 0
B63: (1.5) Cost of ageing | D63: =IF(D$55<=$C$5,0,HLOOKUP(D$55,'Input data'!$C$9:$BB$26,12,FALSE)-HLOOKUP($C$5,'Input data'!$C$9:$BB$26,12,FALSE)) -> 0 | E63: =IF(E$55<=$C$5,0,HLOOKUP(E$55,'Input data'!$C$9:$BB$26,12,FALSE)-HLOOKUP($C$5,'Input data'!$C$9:$BB$26,12,FALSE)) -> 0 | F63: =IF(F$55<=$C$5,0,HLOOKUP(F$55,'Input data'!$C$9:$BB$26,12,FALSE)-HLOOKUP($C$5,'Input data'!$C$9:$BB$26,12,FALSE)) -> 0 | G63: =IF(G$55<=$C$5,0,HLOOKUP(G$55,'Input data'!$C$9:$BB$26,12,FALSE)-HLOOKUP($C$5,'Input data'!$C$9:$BB$26,12,FALSE)) -> -0.06456 | H63: =IF(H$55<=$C$5,0,HLOOKUP(H$55,'Input data'!$C$9:$BB$26,12,FALSE)-HLOOKUP($C$5,'Input data'!$C$9:$BB$26,12,FALSE)) -> -0.33033 | I63: =IF(I$55<=$C$5,0,HLOOKUP(I$55,'Input data'!$C$9:$BB$26,12,FALSE)-HLOOKUP($C$5,'Input data'!$C$9:$BB$26,12,FALSE)) -> -0.4267 | J63: =IF(J$55<=$C$5,0,HLOOKUP(J$55,'Input data'!$C$9:$BB$26,12,FALSE)-HLOOKUP($C$5,'Input data'!$C$9:$BB$26,12,FALSE)) -> -0.50931 | K63: =IF(K$55<=$C$5,0,HLOOKUP(K$55,'Input data'!$C$9:$BB$26,12,FALSE)-HLOOKUP($C$5,'Input data'!$C$9:$BB$26,12,FALSE)) -> -0.57116 | ... W63: =IF(W$55<=$C$5,0,HLOOKUP(W$55,'Input data'!$C$9:$BB$26,12,FALSE)-HLOOKUP($C$5,'Input data'!$C$9:$BB$26,12,FALSE)) -> -0.44169
B64: (1.6) Property incomes | D64: =IF(D$55<=$C$5,0,-HLOOKUP(D$55,'Input data'!$C$9:$BB$26,18,FALSE)+HLOOKUP($C$5,'Input data'!$C$9:$BB$26,18,FALSE)) -> 0 | E64: =IF(E$55<=$C$5,0,-HLOOKUP(E$55,'Input data'!$C$9:$BB$26,18,FALSE)+HLOOKUP($C$5,'Input data'!$C$9:$BB$26,18,FALSE)) -> 0 | F64: =IF(F$55<=$C$5,0,-HLOOKUP(F$55,'Input data'!$C$9:$BB$26,18,FALSE)+HLOOKUP($C$5,'Input data'!$C$9:$BB$26,18,FALSE)) -> 0 | G64: =IF(G$55<=$C$5,0,-HLOOKUP(G$55,'Input data'!$C$9:$BB$26,18,FALSE)+HLOOKUP($C$5,'Input data'!$C$9:$BB$26,18,FALSE)) -> 0.0028436 | H64: =IF(H$55<=$C$5,0,-HLOOKUP(H$55,'Input data'!$C$9:$BB$26,18,FALSE)+HLOOKUP($C$5,'Input data'!$C$9:$BB$26,18,FALSE)) -> 0.0056871 | I64: =IF(I$55<=$C$5,0,-HLOOKUP(I$55,'Input data'!$C$9:$BB$26,18,FALSE)+HLOOKUP($C$5,'Input data'!$C$9:$BB$26,18,FALSE)) -> 0.0085307 | J64: =IF(J$55<=$C$5,0,-HLOOKUP(J$55,'Input data'!$C$9:$BB$26,18,FALSE)+HLOOKUP($C$5,'Input data'!$C$9:$BB$26,18,FALSE)) -> 0.0113743 | K64: =IF(K$55<=$C$5,0,-HLOOKUP(K$55,'Input data'!$C$9:$BB$26,18,FALSE)+HLOOKUP($C$5,'Input data'!$C$9:$BB$26,18,FALSE)) -> 0.0142178 | ... W64: =IF(W$55<=$C$5,0,-HLOOKUP(W$55,'Input data'!$C$9:$BB$26,18,FALSE)+HLOOKUP($C$5,'Input data'!$C$9:$BB$26,18,FALSE)) -> 0.0483403
B65: (1.7) Revenues | D65: 0 | E65: 0 | F65: 0 | G65: 0 | H65: 0 | I65: 0 | J65: 0 | K65: 0 | L65: 0 | M65: 0 | N65: 0 | O65: 0 | P65: 0 | Q65: 0 | R65: 0 | S65: 0 | T65: 0 | U65: 0 | V65: 0 | W65: 0
B66: (2) Snowball effect (2.1 + 2.2 + 2.3) | D66: =SUM(D67:D70) -> -5.58325 | E66: =SUM(E67:E70) -> -4.089329 | F66: =SUM(F67:F70) -> -2.618877 | G66: =SUM(G67:G70) -> -2.305379 | H66: =SUM(H67:H70) -> -2.2656021 | I66: =SUM(I67:I70) -> -2.2787386 | J66: =SUM(J67:J70) -> -2.1763217 | K66: =SUM(K67:K70) -> -2.0810451 | ... W66: =SUM(W67:W70) -> -0.63356912
B67: (2.1) Interest expenditure | D67: =C56*D35/100*(1/(1+D32/100)) -> 0.94020825 | E67: =D56*E35/100*(1/(1+E32/100)) -> 1.1036091 | F67: =E56*F35/100*(1/(1+F32/100)) -> 1.2783144 | G67: =F56*G35/100*(1/(1+G32/100)) -> 1.3252732 | H67: =G56*H35/100*(1/(1+H32/100)) -> 1.4023503 | I67: =H56*I35/100*(1/(1+I32/100)) -> 1.4543747 | J67: =I56*J35/100*(1/(1+J32/100)) -> 1.5035791 | K67: =J56*K35/100*(1/(1+K32/100)) -> 1.5516551 | ... W67: =V56*W35/100*(1/(1+W32/100)) -> 2.2585068
B68: (2.2) Growth effect | D68: =-C56*(D23/100)*(1/(1+D32/100)) -> -3.8279967 | E68: =-D56*(E23/100)*(1/(1+E32/100)) -> -2.6067445 | F68: =-E56*(F23/100)*(1/(1+F32/100)) -> -2.1260857 | G68: =-F56*(G23/100)*(1/(1+G32/100)) -> -2.3449104 | H68: =-G56*(H23/100)*(1/(1+H32/100)) -> -2.3620517 | I68: =-H56*(I23/100)*(1/(1+I32/100)) -> -2.4156687 | J68: =-I56*(J23/100)*(1/(1+J32/100)) -> -2.3554963 | K68: =-J56*(K23/100)*(1/(1+K32/100)) -> -2.3017452 | ... W68: =-V56*(W23/100)*(1/(1+W32/100)) -> -1.441241
B69: (2.3) Inflation effect | D69: =-C56*D41/100*(1/(1+D41/100)) -> -2.6954615 | E69: =-D56*E41/100*(1/(1+E41/100)) -> -2.5861962 | F69: =-E56*F41/100*(1/(1+F41/100)) -> -1.7711093 | G69: =-F56*G41/100*(1/(1+G41/100)) -> -1.2857444 | H69: =-G56*H41/100*(1/(1+H41/100)) -> -1.3059008 | I69: =-H56*I41/100*(1/(1+I41/100)) -> -1.3174447 | J69: =-I56*J41/100*(1/(1+J41/100)) -> -1.3244044 | K69: =-J56*K41/100*(1/(1+K41/100)) -> -1.330955 | ... W69: =-V56*W41/100*(1/(1+W41/100)) -> -1.450835
B70: (2.4) Exchange rate effect linked to the interest rate | D70: -3.7714402e-08 | E70: 2.6165035e-06 | F70: 3.5287289e-06 | G70: 2.5290586e-06 | H70: 0 | I70: 0 | J70: 0 | K70: 0 | L70: 0 | M70: 0 | N70: 0 | O70: 0 | P70: 0 | Q70: 0 | R70: 0 | S70: 0 | T70: 0 | U70: 0 | V70: 0 | W70: 0
B71: (3 ) Stock flow adjustments (3.1 + 3.2) | D71: ='Input data'!D16 -> -1.310275 | E71: ='Input data'!E16 -> -0.940448 | F71: ='Input data'!F16 -> 1.185199 | G71: ='Input data'!G16 -> 0.0667244 | H71: ='Input data'!H16 -> 0 | I71: ='Input data'!I16 -> 0 | J71: ='Input data'!J16 -> 0 | K71: ='Input data'!K16 -> 0 | ... W71: ='Input data'!W16 -> 0
B72: (3.1) Base | D72: =D14 -> -1.310275 | E72: =E14 -> -0.9404473 | F72: =F14 -> 1.185197 | G72: =G14 -> 0.0667276 | H72: =H14 -> 0 | I72: =I14 -> 0 | J72: =J14 -> 0 | K72: =K14 -> 0 | ... W72: =W14 -> 0
B73: (3.2) Adjustment due to the exchange rate effect linked to debt value | D73: =+D71-D72 -> 0 | E73: =+E71-E72 -> -7e-07 | F73: =+F71-F72 -> 2e-06 | G73: =+G71-G72 -> -3.2e-06 | H73: =+H71-H72 -> 0 | I73: =+I71-I72 -> 0 | J73: =+J71-J72 -> 0 | K73: =+K71-K72 -> 0 | ... W73: =+W71-W72 -> 0
B75: Other budgetary variables
B76: Headline balance | D76: =D58-D67 -> -5.534563 | E76: =E58-E67 -> -4.9035648 | F76: =F58-F67 -> -4.3425745 | G76: =G58-G67 -> -4.33868 | H76: =H58-H67 -> -4.0935434 | I76: =I58-I67 -> -3.9729818 | J76: =J58-J67 -> -3.9028945 | K76: =K58-K67 -> -3.8919649 | ... W76: =W58-W67 -> -4.7624087
B77: Structural balance | D77: =D59-D67-D63-D64-D65 -> -5.2954123 | E77: =E59-E67-E63-E64-E65 -> -4.8946031 | F77: =F59-F67-F63-F64-F65 -> -4.1755574 | G77: =G59-G67-G63-G64-G65 -> -4.1607998 | H77: =H59-H67-H63-H64-H65 -> -3.9749504 | I77: =I59-I67-I63-I64-I65 -> -3.9334484 | J77: =J59-J67-J63-J64-J65 -> -3.9028864 | K77: =K59-K67-K63-K64-K65 -> -3.8919559 | ... W77: =W59-W67-W63-W64-W65 -> -4.7624001
B78: Net expenditure growth | D78: ='Input data'!D45 -> 13.084528 | E78: ='Input data'!E45 -> 9.2925168 | F78: ='Input data'!F45 -> 5.4768547 | G78: ='Input data'!G33+G41-(G$12-F$12)/'Input data'!$C$64*100 -> 7.402975 | H78: ='Input data'!H33+H41-(H$12-G$12)/'Input data'!$C$64*100 -> 7.2132401 | I78: ='Input data'!I33+I41-(I$12-H$12)/'Input data'!$C$64*100 -> 7.2453673 | J78: ='Input data'!J33+J41-(J$12-I$12)/'Input data'!$C$64*100 -> 7.1846194 | K78: ='Input data'!K33+K41-(K$12-J$12)/'Input data'!$C$64*100 -> 7.1401375 | L78: ='Input data'!L33+L41-(L$12-K$12)/'Input data'!$C$64*100 -> 7.0482306 | M78: ='Input data'!M33+M41-(M$12-L$12)/'Input data'!$C$64*100 -> 6.8942157 | N78: ='Input data'!N33+N41-(N$12-M$12)/'Input data'!$C$64*100 -> 6.7181139 | ... W78: ='Input data'!W33+W41-(W$12-V$12)/'Input data'!$C$64*100 -> 4.699437
B81: Debt decomposition and IIR
B83: Auxiliary variable identifying whether debt is increasing | D83: =IF((D87-C87*D42/((1+D23/100)*(1+D41/100)))>0,1,0) -> 1 | E83: =IF((E87-D87*E42/((1+E23/100)*(1+E41/100)))>0,1,0) -> 1 | F83: =IF((F87-E87*F42/((1+F23/100)*(1+F41/100)))>0,1,0) -> 1 | G83: =IF((G87-F87*G42/((1+G23/100)*(1+G41/100)))>0,1,0) -> 1 | H83: =IF((H87-G87*H42/((1+H23/100)*(1+H41/100)))>0,1,0) -> 1 | I83: =IF((I87-H87*I42/((1+I23/100)*(1+I41/100)))>0,1,0) -> 1 | J83: =IF((J87-I87*J42/((1+J23/100)*(1+J41/100)))>0,1,0) -> 1 | K83: =IF((K87-J87*K42/((1+K23/100)*(1+K41/100)))>0,1,0) -> 1 | ... W83: =IF((W87-V87*W42/((1+W23/100)*(1+W41/100)))>0,1,0) -> 1
B84: Auxiliary variable identifying whether some debt is rolled over even though debt is decreasing | D84: =IF(AND(D83=0,ABS(D87-C87*D42/((1+D23/100)*(1+D41/100)))<((C93*C87*D42/((1+D23/100)*(1+D41/100))+(D38*C87*C94*D42/((1+D23/100)*(1+D41/100)))))),1,0) -> 0 | E84: =IF(AND(E83=0,ABS(E87-D87*E42/((1+E23/100)*(1+E41/100)))<((D93*D87*E42/((1+E23/100)*(1+E41/100))+(E38*D87*D94*E42/((1+E23/100)*(1+E41/100)))))),1,0) -> 0 | F84: =IF(AND(F83=0,ABS(F87-E87*F42/((1+F23/100)*(1+F41/100)))<((E93*E87*F42/((1+F23/100)*(1+F41/100))+(F38*E87*E94*F42/((1+F23/100)*(1+F41/100)))))),1,0) -> 0 | G84: =IF(AND(G83=0,ABS(G87-F87*G42/((1+G23/100)*(1+G41/100)))<((F93*F87*G42/((1+G23/100)*(1+G41/100))+(G38*F87*F94*G42/((1+G23/100)*(1+G41/100)))))),1,0) -> 0 | H84: =IF(AND(H83=0,ABS(H87-G87*H42/((1+H23/100)*(1+H41/100)))<((G93*G87*H42/((1+H23/100)*(1+H41/100))+(H38*G87*G94*H42/((1+H23/100)*(1+H41/100)))))),1,0) -> 0 | I84: =IF(AND(I83=0,ABS(I87-H87*I42/((1+I23/100)*(1+I41/100)))<((H93*H87*I42/((1+I23/100)*(1+I41/100))+(I38*H87*H94*I42/((1+I23/100)*(1+I41/100)))))),1,0) -> 0 | J84: =IF(AND(J83=0,ABS(J87-I87*J42/((1+J23/100)*(1+J41/100)))<((I93*I87*J42/((1+J23/100)*(1+J41/100))+(J38*I87*I94*J42/((1+J23/100)*(1+J41/100)))))),1,0) -> 0 | K84: =IF(AND(K83=0,ABS(K87-J87*K42/((1+K23/100)*(1+K41/100)))<((J93*J87*K42/((1+K23/100)*(1+K41/100))+(K38*J87*J94*K42/((1+K23/100)*(1+K41/100)))))),1,0) -> 0 | ... W84: =IF(AND(W83=0,ABS(W87-V87*W42/((1+W23/100)*(1+W41/100)))<((V93*V87*W42/((1+W23/100)*(1+W41/100))+(W38*V87*V94*W42/((1+W23/100)*(1+W41/100)))))),1,0) -> 0
C86: 2021 | D86: 2022 | E86: 2023 | F86: 2024 | G86: 2025 | H86: 2026 | I86: 2027 | J86: 2028 | K86: 2029 | L86: 2030 | M86: 2031 | N86: 2032 | O86: 2033 | P86: 2034 | Q86: 2035 | R86: 2036 | S86: 2037 | T86: 2038 | U86: 2039 | V86: 2040 | W86: 2041
B87: Gross debt | C87: =C56 -> 53.92565 | D87: =D56 -> 51.62648 | E87: =E56 -> 50.396658 | F87: =F56 -> 52.027241 | G87: =G56 -> 52.801993 | H87: =G87*(1+H101/100)*H42-H59-H60+H61+H62+H63+H64+H65+H71 -> 53.227584 | I87: =H87*(1+I101/100)*I42-I59-I60+I61+I62+I63+I64+I65+I71 -> 53.467452 | J87: =I87*(1+J101/100)*J42-J59-J60+J61+J62+J63+J64+J65+J71 -> 53.690446 | K87: =J87*(1+K101/100)*K42-K59-K60+K61+K62+K63+K64+K65+K71 -> 53.94971 | L87: =K87*(1+L101/100)*L42-L59-L60+L61+L62+L63+L64+L65+L71 -> 54.22776 | M87: =L87*(1+M101/100)*M42-M59-M60+M61+M62+M63+M64+M65+M71 -> 54.562378 | N87: =M87*(1+N101/100)*N42-N59-N60+N61+N62+N63+N64+N65+N71 -> 54.974855 | O87: =N87*(1+O101/100)*O42-O59-O60+O61+O62+O63+O64+O65+O71 -> 55.418736 | ... W87: =V87*(1+W101/100)*W42-W59-W60+W61+W62+W63+W64+W65+W71 -> 65.588764
B88: Of which Outstanding debt | D88: ='Input data'!C66*$D$87 -> 40.602371 | E88: =IF(E87=0,0,IF(E83=1,D87*E42/((1+E23/100)*(1+E41/100))-E89-E90,IF(AND(E83=0,E84=1),(1-D93-E38*D94)*D87*E42/((1+E23/100)*(1+E41/100)),E87))) -> 37.860894 | F88: =IF(F87=0,0,IF(F83=1,E87*F42/((1+F23/100)*(1+F41/100))-F89-F90,IF(AND(F83=0,F84=1),(1-E93-F38*E94)*E87*F42/((1+F23/100)*(1+F41/100)),F87))) -> 38.019239 | G88: =IF(G87=0,0,IF(G83=1,F87*G42/((1+G23/100)*(1+G41/100))-G89-G90,IF(AND(G83=0,G84=1),(1-F93-G38*F94)*F87*G42/((1+G23/100)*(1+G41/100)),G87))) -> 39.563881 | H88: =IF(H87=0,0,IF(H83=1,G87*H42/((1+H23/100)*(1+H41/100))-H89-H90,IF(AND(H83=0,H84=1),(1-G93-H38*G94)*G87*H42/((1+H23/100)*(1+H41/100)),H87))) -> 40.143081 | I88: =IF(I87=0,0,IF(I83=1,H87*I42/((1+I23/100)*(1+I41/100))-I89-I90,IF(AND(I83=0,I84=1),(1-H93-I38*H94)*H87*I42/((1+I23/100)*(1+I41/100)),I87))) -> 40.407382 | J88: =IF(J87=0,0,IF(J83=1,I87*J42/((1+J23/100)*(1+J41/100))-J89-J90,IF(AND(J83=0,J84=1),(1-I93-J38*I94)*I87*J42/((1+J23/100)*(1+J41/100)),J87))) -> 40.612524 | K88: =IF(K87=0,0,IF(K83=1,J87*K42/((1+K23/100)*(1+K41/100))-K89-K90,IF(AND(K83=0,K84=1),(1-J93-K38*J94)*J87*K42/((1+K23/100)*(1+K41/100)),K87))) -> 40.795644 | L88: =IF(L87=0,0,IF(L83=1,K87*L42/((1+L23/100)*(1+L41/100))-L89-L90,IF(AND(L83=0,L84=1),(1-K93-L38*K94)*K87*L42/((1+L23/100)*(1+L41/100)),L87))) -> 40.988893 | ... W88: =IF(W87=0,0,IF(W83=1,V87*W42/((1+W23/100)*(1+W41/100))-W89-W90,IF(AND(W83=0,W84=1),(1-V93-W38*V94)*V87*W42/((1+W23/100)*(1+W41/100)),W87))) -> 49.506142
B89: Rolled over long-term debt | D89: ='Input data'!C67*$D$87 -> 0.040643031 | E89: =IF(E87=0,0,IF(E83=1,E38*D87*D94*E42/((1+E23/100)*(1+E41/100)),IF(AND(E83=0,E84=1),(E38*D87*D94*E42/((1+E23/100)*(1+E41/100)))*(1-ABS(E87-D87*E42/((1+E23/100)*(1+E41/100)))/((E38*D87*D94*E42/((1+E23/100)*(1+E41/100)))+(D93*D87*E42/((1+E23/100)*(1+E41/100))))),0))) -> 1.9515624 | F89: =IF(F87=0,0,IF(F83=1,F38*E87*E94*F42/((1+F23/100)*(1+F41/100)),IF(AND(F83=0,F84=1),(F38*E87*E94*F42/((1+F23/100)*(1+F41/100)))*(1-ABS(F87-E87*F42/((1+F23/100)*(1+F41/100)))/((F38*E87*E94*F42/((1+F23/100)*(1+F41/100)))+(E93*E87*F42/((1+F23/100)*(1+F41/100))))),0))) -> 1.8951144 | G89: =IF(G87=0,0,IF(G83=1,G38*F87*F94*G42/((1+G23/100)*(1+G41/100)),IF(AND(G83=0,G84=1),(G38*F87*F94*G42/((1+G23/100)*(1+G41/100)))*(1-ABS(G87-F87*G42/((1+G23/100)*(1+G41/100)))/((G38*F87*F94*G42/((1+G23/100)*(1+G41/100)))+(F93*F87*G42/((1+G23/100)*(1+G41/100))))),0))) -> 2.0377127 | H89: =IF(H87=0,0,IF(H83=1,H38*G87*G94*H42/((1+H23/100)*(1+H41/100)),IF(AND(H83=0,H84=1),(H38*G87*G94*H42/((1+H23/100)*(1+H41/100)))*(1-ABS(H87-G87*H42/((1+H23/100)*(1+H41/100)))/((H38*G87*G94*H42/((1+H23/100)*(1+H41/100)))+(G93*G87*H42/((1+H23/100)*(1+H41/100))))),0))) -> 2.1343189 | I89: =IF(I87=0,0,IF(I83=1,I38*H87*H94*I42/((1+I23/100)*(1+I41/100)),IF(AND(I83=0,I84=1),(I38*H87*H94*I42/((1+I23/100)*(1+I41/100)))*(1-ABS(I87-H87*I42/((1+I23/100)*(1+I41/100)))/((I38*H87*H94*I42/((1+I23/100)*(1+I41/100)))+(H93*H87*I42/((1+I23/100)*(1+I41/100))))),0))) -> 2.2157987 | J89: =IF(J87=0,0,IF(J83=1,J38*I87*I94*J42/((1+J23/100)*(1+J41/100)),IF(AND(J83=0,J84=1),(J38*I87*I94*J42/((1+J23/100)*(1+J41/100)))*(1-ABS(J87-I87*J42/((1+J23/100)*(1+J41/100)))/((J38*I87*I94*J42/((1+J23/100)*(1+J41/100)))+(I93*I87*J42/((1+J23/100)*(1+J41/100))))),0))) -> 2.2950329 | K89: =IF(K87=0,0,IF(K83=1,K38*J87*J94*K42/((1+K23/100)*(1+K41/100)),IF(AND(K83=0,K84=1),(K38*J87*J94*K42/((1+K23/100)*(1+K41/100)))*(1-ABS(K87-J87*K42/((1+K23/100)*(1+K41/100)))/((K38*J87*J94*K42/((1+K23/100)*(1+K41/100)))+(J93*J87*K42/((1+K23/100)*(1+K41/100))))),0))) -> 2.3738897 | L89: =IF(L87=0,0,IF(L83=1,L38*K87*K94*L42/((1+L23/100)*(1+L41/100)),IF(AND(L83=0,L84=1),(L38*K87*K94*L42/((1+L23/100)*(1+L41/100)))*(1-ABS(L87-K87*L42/((1+L23/100)*(1+L41/100)))/((L38*K87*K94*L42/((1+L23/100)*(1+L41/100)))+(K93*K87*L42/((1+L23/100)*(1+L41/100))))),0))) -> 2.454187 | ... W89: =IF(W87=0,0,IF(W83=1,W38*V87*V94*W42/((1+W23/100)*(1+W41/100)),IF(AND(W83=0,W84=1),(W38*V87*V94*W42/((1+W23/100)*(1+W41/100)))*(1-ABS(W87-V87*W42/((1+W23/100)*(1+W41/100)))/((W38*V87*V94*W42/((1+W23/100)*(1+W41/100)))+(V93*V87*W42/((1+W23/100)*(1+W41/100))))),0))) -> 3.2159562
B90: Rolled over short-term debt | D90: ='Input data'!C68*$D$87 -> 6.7592062 | E90: =IF(E87=0,0,IF(E83=1,(1-D94)*D87*E42/((1+E23/100)*(1+E41/100)),IF(AND(E83=0,E84=1),(D93*D87*E42/((1+E23/100)*(1+E41/100)))*(1-ABS(E87-D87*E42/((1+E23/100)*(1+E41/100)))/((E38*D87*D94*E42/((1+E23/100)*(1+E41/100)))+(D93*D87*E42/((1+E23/100)*(1+E41/100))))),0))) -> 6.6210824 | F90: =IF(F87=0,0,IF(F83=1,(1-E94)*E87*F42/((1+F23/100)*(1+F41/100)),IF(AND(F83=0,F84=1),(E93*E87*F42/((1+F23/100)*(1+F41/100)))*(1-ABS(F87-E87*F42/((1+F23/100)*(1+F41/100)))/((F38*E87*E94*F42/((1+F23/100)*(1+F41/100)))+(E93*E87*F42/((1+F23/100)*(1+F41/100))))),0))) -> 6.5851097 | G90: =IF(G87=0,0,IF(G83=1,(1-F94)*F87*G42/((1+G23/100)*(1+G41/100)),IF(AND(G83=0,G84=1),(F93*F87*G42/((1+G23/100)*(1+G41/100)))*(1-ABS(G87-F87*G42/((1+G23/100)*(1+G41/100)))/((G38*F87*F94*G42/((1+G23/100)*(1+G41/100)))+(F93*F87*G42/((1+G23/100)*(1+G41/100))))),0))) -> 6.7949868 | H90: =IF(H87=0,0,IF(H83=1,(1-G94)*G87*H42/((1+H23/100)*(1+H41/100)),IF(AND(H83=0,H84=1),(G93*G87*H42/((1+H23/100)*(1+H41/100)))*(1-ABS(H87-G87*H42/((1+H23/100)*(1+H41/100)))/((H38*G87*G94*H42/((1+H23/100)*(1+H41/100)))+(G93*G87*H42/((1+H23/100)*(1+H41/100))))),0))) -> 6.8566406 | I90: =IF(I87=0,0,IF(I83=1,(1-H94)*H87*I42/((1+I23/100)*(1+I41/100)),IF(AND(I83=0,I84=1),(H93*H87*I42/((1+I23/100)*(1+I41/100)))*(1-ABS(I87-H87*I42/((1+I23/100)*(1+I41/100)))/((I38*H87*H94*I42/((1+I23/100)*(1+I41/100)))+(H93*H87*I42/((1+I23/100)*(1+I41/100))))),0))) -> 6.8712896 | J90: =IF(J87=0,0,IF(J83=1,(1-I94)*I87*J42/((1+J23/100)*(1+J41/100)),IF(AND(J83=0,J84=1),(I93*I87*J42/((1+J23/100)*(1+J41/100)))*(1-ABS(J87-I87*J42/((1+J23/100)*(1+J41/100)))/((J38*I87*I94*J42/((1+J23/100)*(1+J41/100)))+(I93*I87*J42/((1+J23/100)*(1+J41/100))))),0))) -> 6.8799948 | K90: =IF(K87=0,0,IF(K83=1,(1-J94)*J87*K42/((1+K23/100)*(1+K41/100)),IF(AND(K83=0,K84=1),(J93*J87*K42/((1+K23/100)*(1+K41/100)))*(1-ABS(K87-J87*K42/((1+K23/100)*(1+K41/100)))/((K38*J87*J94*K42/((1+K23/100)*(1+K41/100)))+(J93*J87*K42/((1+K23/100)*(1+K41/100))))),0))) -> 6.8882116 | L90: =IF(L87=0,0,IF(L83=1,(1-K94)*K87*L42/((1+L23/100)*(1+L41/100)),IF(AND(L83=0,L84=1),(K93*K87*L42/((1+L23/100)*(1+L41/100)))*(1-ABS(L87-K87*L42/((1+L23/100)*(1+L41/100)))/((L38*K87*K94*L42/((1+L23/100)*(1+L41/100)))+(K93*K87*L42/((1+L23/100)*(1+L41/100))))),0))) -> 6.9006068 | ... W90: =IF(W87=0,0,IF(W83=1,(1-V94)*V87*W42/((1+W23/100)*(1+W41/100)),IF(AND(W83=0,W84=1),(V93*V87*W42/((1+W23/100)*(1+W41/100)))*(1-ABS(W87-V87*W42/((1+W23/100)*(1+W41/100)))/((W38*V87*V94*W42/((1+W23/100)*(1+W41/100)))+(V93*V87*W42/((1+W23/100)*(1+W41/100))))),0))) -> 8.1042573
B91: New long-term debt | D91: ='Input data'!C69*$D$87 -> 3.6219078 | E91: =IF(E87=0,0,IF(E83=1,'Input data'!$C$58*(E87-D87*E42/((1+E23/100)*(1+E41/100))),0)) -> 3.4471835 | F91: =IF(F87=0,0,IF(F83=1,'Input data'!$C$58*(F87-E87*F42/((1+F23/100)*(1+F41/100))),0)) -> 4.8081473 | G91: =IF(G87=0,0,IF(G83=1,'Input data'!$C$58*(G87-F87*G42/((1+G23/100)*(1+G41/100))),0)) -> 3.8318963 | H91: =IF(H87=0,0,IF(H83=1,'Input data'!$C$58*(H87-G87*H42/((1+H23/100)*(1+H41/100))),0)) -> 3.5606283 | I91: =IF(I87=0,0,IF(I83=1,'Input data'!$C$58*(I87-H87*I42/((1+I23/100)*(1+I41/100))),0)) -> 3.4557619 | J91: =IF(J87=0,0,IF(J83=1,'Input data'!$C$58*(J87-I87*J42/((1+J23/100)*(1+J41/100))),0)) -> 3.3947989 | K91: =IF(K87=0,0,IF(K83=1,'Input data'!$C$58*(K87-J87*K42/((1+K23/100)*(1+K41/100))),0)) -> 3.3852922 | L91: =IF(L87=0,0,IF(L83=1,'Input data'!$C$58*(L87-K87*L42/((1+L23/100)*(1+L41/100))),0)) -> 3.3784276 | ... W91: =IF(W87=0,0,IF(W83=1,'Input data'!$C$58*(W87-V87*W42/((1+W23/100)*(1+W41/100))),0)) -> 4.1424179
B92: New short-term debt | D92: ='Input data'!C70*$D$87 -> 0.60234756 | E92: =IF(E87=0,0,IF(E83=1,'Input data'!$C$57*(E87-D87*E42/((1+E23/100)*(1+E41/100))),0)) -> 0.51593593 | F92: =IF(F87=0,0,IF(F83=1,'Input data'!$C$57*(F87-E87*F42/((1+F23/100)*(1+F41/100))),0)) -> 0.71962979 | G92: =IF(G87=0,0,IF(G83=1,'Input data'!$C$57*(G87-F87*G42/((1+G23/100)*(1+G41/100))),0)) -> 0.57351544 | H92: =IF(H87=0,0,IF(H83=1,'Input data'!$C$57*(H87-G87*H42/((1+H23/100)*(1+H41/100))),0)) -> 0.53291508 | I92: =IF(I87=0,0,IF(I83=1,'Input data'!$C$57*(I87-H87*I42/((1+I23/100)*(1+I41/100))),0)) -> 0.51721985 | J92: =IF(J87=0,0,IF(J83=1,'Input data'!$C$57*(J87-I87*J42/((1+J23/100)*(1+J41/100))),0)) -> 0.50809559 | K92: =IF(K87=0,0,IF(K83=1,'Input data'!$C$57*(K87-J87*K42/((1+K23/100)*(1+K41/100))),0)) -> 0.50667273 | L92: =IF(L87=0,0,IF(L83=1,'Input data'!$C$57*(L87-K87*L42/((1+L23/100)*(1+L41/100))),0)) -> 0.50564531 | ... W92: =IF(W87=0,0,IF(W83=1,'Input data'!$C$57*(W87-V87*W42/((1+W23/100)*(1+W41/100))),0)) -> 0.61999085
B93: Share of short-term debt in total government debt | D93: =1-D94 -> 0.14259267 | E93: =IF(E87<>0,(E90+E92)/(E88+E89+E90+E91+E92),0) -> 0.1416169 | F93: =IF(F87<>0,(F90+F92)/(F88+F89+F90+F91+F92),0) -> 0.14040221 | G93: =IF(G87<>0,(G90+G92)/(G88+G89+G90+G91+G92),0) -> 0.1395497 | H93: =IF(H87<>0,(H90+H92)/(H88+H89+H90+H91+H92),0) -> 0.13882944 | I93: =IF(I87<>0,(I90+I92)/(I88+I89+I90+I91+I92),0) -> 0.13818705 | J93: =IF(J87<>0,(J90+J92)/(J88+J89+J90+J91+J92),0) -> 0.13760531 | K93: =IF(K87<>0,(K90+K92)/(K88+K89+K90+K91+K92),0) -> 0.13706995 | L93: =IF(L87<>0,(L90+L92)/(L88+L89+L90+L91+L92),0) -> 0.13657677 | ... W93: =IF(W87<>0,(W90+W92)/(W88+W89+W90+W91+W92),0) -> 0.13301437
B94: Share of long-term debt in total government debt | D94: =(D88+D89+D91)/D87 -> 0.85740733 | E94: =IF(E87<>0,(E88+E89+E91)/(E88+E89+E90+E91+E92),1) -> 0.8583831 | F94: =IF(F87<>0,(F88+F89+F91)/(F88+F89+F90+F91+F92),1) -> 0.85959779 | G94: =IF(G87<>0,(G88+G89+G91)/(G88+G89+G90+G91+G92),1) -> 0.8604503 | H94: =IF(H87<>0,(H88+H89+H91)/(H88+H89+H90+H91+H92),1) -> 0.86117056 | I94: =IF(I87<>0,(I88+I89+I91)/(I88+I89+I90+I91+I92),1) -> 0.86181295 | J94: =IF(J87<>0,(J88+J89+J91)/(J88+J89+J90+J91+J92),1) -> 0.86239469 | K94: =IF(K87<>0,(K88+K89+K91)/(K88+K89+K90+K91+K92),1) -> 0.86293005 | L94: =IF(L87<>0,(L88+L89+L91)/(L88+L89+L90+L91+L92),1) -> 0.86342323 | ... W94: =IF(W87<>0,(W88+W89+W91)/(W88+W89+W90+W91+W92),1) -> 0.86698563
B96: IIR | C96: =C35 -> 2.40894 | D96: =D35 -> 1.98347 | E96: =E98+E99 -> 2.37675 | F96: =F98+F99 -> 2.749095 | G96: =G98+G99 -> 2.738361 | H96: =H98+H99 -> 2.8541319 | I96: =I98+I99 -> 2.9384591 | J96: =J98+J99 -> 3.01999 | K96: =K98+K99 -> 3.0997302 | L96: =L98+L99 -> 3.1785659 | ... W96: =W98+W99 -> 3.7130399
B97: Long-term implicit interest rate | E97: =((E35*D87)-(E37*D90+D92))/(D88+D89+D91) -> 2.2346546 | F97: =((F35*E87)-(F37*E90+E92))/(E88+E89+E91) -> 2.6451989 | G97: =((G35*F87)-(G37*F90+F92))/(F88+F89+F91) -> 2.7548459 | H97: =IF(G87>0,(G97*G88+H36*(G91+G89))/(G88+G89+G91),H36) -> 2.8620857 | I97: =IF(H87>0,(H97*H88+I36*(H91+H89))/(H88+H89+H91),I36) -> 2.961779 | J97: =IF(I87>0,(I97*I88+J36*(I91+I89))/(I88+I89+I91),J36) -> 3.0580674 | K97: =IF(J87>0,(J97*J88+K36*(J91+J89))/(J88+J89+J91),K36) -> 3.1521459 | L97: =IF(K87>0,(K97*K88+L36*(K91+K89))/(K88+K89+K91),L36) -> 3.2450604 | M97: =IF(L87>0,(L97*L88+M36*(L91+L89))/(L88+L89+L91),M36) -> 3.3369618 | N97: =IF(M87>0,(M97*M88+N36*(M91+M89))/(M88+M89+M91),N36) -> 3.4280165 | O97: =IF(N87>0,(N97*N88+O36*(N91+N89))/(N88+N89+N91),O36) -> 3.5184082 | ... W97: =IF(V87>0,(V97*V88+W36*(V91+V89))/(V88+V89+V91),W36) -> 3.9093952
B98: Nominal implicit interest rate on debt (Excel approximation) | E98: =E35 -> 2.37675 | F98: =F35 -> 2.749095 | G98: =G35 -> 2.738361 | H98: =(H97*(G88+G89+G91)+H37*(G90+G92))/G87 -> 2.8541319 | I98: =(I97*(H88+H89+H91)+I37*(H90+H92))/H87 -> 2.9384591 | J98: =(J97*(I88+I89+I91)+J37*(I90+I92))/I87 -> 3.01999 | K98: =(K97*(J88+J89+J91)+K37*(J90+J92))/J87 -> 3.0997302 | L98: =(L97*(K88+K89+K91)+L37*(K90+K92))/K87 -> 3.1785659 | M98: =(M97*(L88+L89+L91)+M37*(L90+L92))/L87 -> 3.2566136 | N98: =(N97*(M88+M89+M91)+N37*(M90+M92))/M87 -> 3.3340054 | O98: =(O97*(N88+N89+N91)+O37*(N90+N92))/N87 -> 3.4108901 | ... W98: =(W97*(V88+V89+V91)+W37*(V90+V92))/V87 -> 3.7130399
B99: Diff. STATA | E99: =E108 -> 0 | F99: =F108 -> 0 | G99: =G108 -> 0 | H99: =H108 -> 0 | I99: =I108 -> 0 | J99: =J108 -> 0 | K99: =K108 -> 0 | L99: =L108 -> 0 | ... W99: =W108 -> 0
B101: (i - g) | C101: =((1+C96/100)/((1+C23/100)*(1+C41/100))-1)*100 -> -10.770397 | D101: =((1+D96/100)/((1+D23/100)*(1+D41/100))-1)*100 -> -10.353607 | E101: =((1+E96/100)/((1+E23/100)*(1+E41/100))-1)*100 -> -7.9209964 | F101: =((1+F96/100)/((1+F23/100)*(1+F41/100))-1)*100 -> -5.1965361 | G101: =((1+G96/100)/((1+G23/100)*(1+G41/100))-1)*100 -> -4.4311048 | H101: =((1+H96/100)/((1+H23/100)*(1+H41/100))-1)*100 -> -4.2907512 | I101: =((1+I96/100)/((1+I23/100)*(1+I41/100))-1)*100 -> -4.2811235 | J101: =((1+J96/100)/((1+J23/100)*(1+J41/100))-1)*100 -> -4.0703673 | ... W101: =((1+W96/100)/((1+W23/100)*(1+W41/100))-1)*100 -> -0.9943263
B104: Per memo - STATA results
B106: Debt | C106: 53.92565 | D106: 51.62644 | E106: 50.39661 | F106: 52.02717 | G106: 52.80192 | H106: 53.21674 | I106: 53.4475 | J106: 53.6628 | K106: 53.91559 | L106: 54.18821 | M106: 54.5183 | N106: 54.92697 | O106: 55.36772 | P106: 56.01208 | Q106: 56.87087 | R106: 57.95635 | S106: 59.15305 | T106: 60.48338 | U106: 61.9784 | V106: 63.65392 | W106: 65.52304
B107: IIR | C107: 2.40894 | D107: 1.98347 | E107: 2.37675 | F107: 2.749095 | G107: 2.738361 | H107: 2.832232 | I107: 2.919137 | J107: 3.002928 | K107: 3.08467 | L107: 3.165291 | M107: 3.244929 | N107: 3.323737 | O107: 3.401882 | P107: 3.466624 | Q107: 3.521774 | R107: 3.568568 | S107: 3.608069 | T107: 3.641207 | U107: 3.668776 | V107: 3.691498 | W107: 3.71
B108: IIR difference STATA - Excel | D108: 0 | E108: 0 | F108: 0 | G108: 0 | H108: 0 | I108: 0 | J108: 0 | K108: 0 | L108: 0 | M108: 0 | N108: 0 | O108: 0 | P108: 0 | Q108: 0 | R108: 0 | S108: 0 | T108: 0 | U108: 0 | V108: 0 | W108: 0
B110: Share of long-term debt that matures every year | C110: 2021 | D110: 2022 | E110: 2023 | F110: 2024 | G110: 2025 | H110: 2026 | I110: 2027 | J110: 2028 | K110: 2029 | L110: 2030 | M110: 2031 | N110: 2032 | O110: 2033 | P110: 2034 | Q110: 2035 | R110: 2036 | S110: 2037 | T110: 2038 | U110: 2039 | V110: 2040 | W110: 2041
B111: CY | C111: 0.03801916 | D111: 0.07859744 | E111: 0.05947547 | F111: 0.09687696 | G111: 0.11684023 | H111: 0.13811532 | I111: 0.13659083 | J111: 0.14219136 | K111: 0.1389396 | L111: 0.12512538 | M111: 0.1284918 | N111: 0.07208514 | O111: 0.06868139 | P111: 0.0680495 | Q111: 0.06808078 | R111: 0.06766632 | S111: 0.06922052 | T111: 0.06662979 | U111: 0.06643431 | V111: 0.06639338 | W111: 0.06621254
B112: EL | C112: 0.03033705 | D112: 0.03594311 | E112: 0.04116618 | F112: 0.01594102 | G112: 0.01585014 | H112: 0.03752878 | I112: 0.03405028 | J112: 0.04734439 | K112: 0.04407593 | L112: 0.0508599 | M112: 0.06623794 | N112: 0.06025377 | O112: 0.09003059 | P112: 0.07295239 | Q112: 0.07736666 | R112: 0.09083936 | S112: 0.0996211 | T112: 0.10965455 | U112: 0.09865441 | V112: 0.10313576 | W112: 0.11073873
B113: IE | C113: 0.001 | D113: 0.07537306 | E113: 0.04688205 | F113: 0.05421672 | G113: 0.06734311 | H113: 0.07328111 | I113: 0.06373561 | J113: 0.07199902 | K113: 0.07792014 | L113: 0.07366593 | M113: 0.09283323 | N113: 0.09749916 | O113: 0.10431984 | P113: 0.07769295 | Q113: 0.08189674 | R113: 0.07226059 | S113: 0.07247516 | T113: 0.07270425 | U113: 0.07292216 | V113: 0.07311259 | W113: 0.07343585
B114: PT | C114: 0.08381841 | D114: 0.06939163 | E114: 0.04649241 | F114: 0.04919325 | G114: 0.05671274 | H114: 0.06401188 | I114: 0.0649313 | J114: 0.06391246 | K114: 0.06169361 | L114: 0.05442604 | M114: 0.08556656 | N114: 0.08165381 | O114: 0.07587859 | P114: 0.06135627 | Q114: 0.08179735 | R114: 0.08444232 | S114: 0.06027019 | T114: 0.07297076 | U114: 0.05731596 | V114: 0.06079668 | W114: 0.05729366

Sheet Adjustment scenario
B3: Country | C3: ='Input data'!C3 -> MT
B4: Key years
B5: ='Input data'!B5 -> Last year before the adjustment | C5: =+'Input data'!C5 -> 2024
B6: Last year of adjustment | C6: =+C5+'Criteria results'!$F$5 -> 2028
B7: Last year of no-fiscal-policy-change projections | C7: =C5+'Criteria results'!$F$5+10 -> 2038
B9: Key assumptions
C10: 2021 | D10: 2022 | E10: 2023 | F10: 2024 | G10: 2025 | H10: 2026 | I10: 2027 | J10: 2028 | K10: 2029 | L10: 2030 | M10: 2031 | N10: 2032 | O10: 2033 | P10: 2034 | Q10: 2035 | R10: 2036 | S10: 2037 | T10: 2038 | U10: 2039 | V10: 2040 | W10: 2041
B11: Fiscal assumptions (% of GDP)
B12: Structural primary balance ('+' means 'surplus') | C12: ='Input data'!C13 -> -5.650948 | D12: ='Input data'!D13 -> -4.355204 | E12: ='Input data'!E13 -> -3.790994 | F12: ='Input data'!F13 -> -2.897243 | G12: =IF(G10<=$C$6, IF(AND(F87=1,F77<=-3.05,'Criteria results'!$F$6<0.5),F12+0.5, IF(AND(F78<=-1.55,'Criteria results'!$F$5=4,'Criteria results'!$F$6<0.4),F12+0.4, IF(AND(F78<=-1.55,'Criteria results'!$F$5=7,'Criteria results'!$F$6<0.25),F12+0.25, F12+'Criteria results'!$F$6))),F12) -> -2.397243 | H12: =IF(H10<=$C$6, IF(AND(G87=1,G77<=-3.05,'Criteria results'!$F$6<0.5),G12+0.5, IF(AND(G78<=-1.55,'Criteria results'!$F$5=4,'Criteria results'!$F$6<0.4),G12+0.4, IF(AND(G78<=-1.55,'Criteria results'!$F$5=7,'Criteria results'!$F$6<0.25),G12+0.25, G12+'Criteria results'!$F$6))),G12) -> -1.897243 | I12: =IF(I10<=$C$6, IF(AND(H87=1,H77<=-3.05,'Criteria results'!$F$6<0.5),H12+0.5, IF(AND(H78<=-1.55,'Criteria results'!$F$5=4,'Criteria results'!$F$6<0.4),H12+0.4, IF(AND(H78<=-1.55,'Criteria results'!$F$5=7,'Criteria results'!$F$6<0.25),H12+0.25, H12+'Criteria results'!$F$6))),H12) -> -1.397243 | J12: =IF(J10<=$C$6, IF(AND(I87=1,I77<=-3.05,'Criteria results'!$F$6<0.5+J91),I12+0.5+J91, IF(AND(I78<=-1.55,'Criteria results'!$F$5=4,'Criteria results'!$F$6<0.4),I12+0.4, IF(AND(I78<=-1.55,'Criteria results'!$F$5=7,'Criteria results'!$F$6<0.25),I12+0.25, I12+'Criteria results'!$F$6))),I12) -> -0.86632274 | K12: =IF(K10<=$C$6, IF(AND(J87=1,J77<=-3.05,'Criteria results'!$F$6<0.5+K91),J12+0.5+K91, IF(AND(J78<=-1.55,'Criteria results'!$F$5=4,'Criteria results'!$F$6<0.4),J12+0.4, IF(AND(J78<=-1.55,'Criteria results'!$F$5=7,'Criteria results'!$F$6<0.25),J12+0.25, J12+'Criteria results'!$F$6))),J12) -> -0.86632274 | L12: =IF(L10<=$C$6, IF(AND(K87=1,K77<=-3.05,'Criteria results'!$F$6<0.5+L91),K12+0.5+L91, IF(AND(K78<=-1.55,'Criteria results'!$F$5=4,'Criteria results'!$F$6<0.4),K12+0.4, IF(AND(K78<=-1.55,'Criteria results'!$F$5=7,'Criteria results'!$F$6<0.25),K12+0.25, K12+'Criteria results'!$F$6))),K12) -> -0.86632274 | M12: =IF(M10<=$C$6, IF(AND(L87=1,L77<=-3.05,'Criteria results'!$F$6<0.5+M91),L12+0.5+M91, IF(AND(L78<=-1.55,'Criteria results'!$F$5=4,'Criteria results'!$F$6<0.4),L12+0.4, IF(AND(L78<=-1.55,'Criteria results'!$F$5=7,'Criteria results'!$F$6<0.25),L12+0.25, L12+'Criteria results'!$F$6))),L12) -> -0.86632274 | N12: =M12 -> -0.86632274 | O12: =N12 -> -0.86632274 | P12: =O12 -> -0.86632274 | Q12: =P12 -> -0.86632274 | R12: =Q12 -> -0.86632274 | S12: =R12 -> -0.86632274 | T12: =S12 -> -0.86632274 | U12: =T12 -> -0.86632274 | ... W12: =V12 -> -0.86632274
B13: Annual change in SPB | G13: =G12-F12 -> 0.5 | H13: =H12-G12 -> 0.5 | I13: =I12-H12 -> 0.5 | J13: =J12-I12 -> 0.53092026 | K13: =K12-J12 -> 0 | L13: =L12-K12 -> 0 | M13: =M12-L12 -> 0 | N13: =N12-M12 -> 0 | ... W13: =W12-V12 -> 0
B14: One-off and other temporary measures | C14: ='Input data'!C14 -> 0 | D14: ='Input data'!D14 -> 0 | E14: ='Input data'!E14 -> 0 | F14: ='Input data'!F14 -> 0 | G14: ='Input data'!G14 -> 0 | H14: =0 -> 0 | I14: =0 -> 0 | J14: =0 -> 0 | K14: =0 -> 0 | L14: =0 -> 0 | M14: =0 -> 0 | N14: =0 -> 0 | O14: =0 -> 0 | ... W14: =0 -> 0
B15: Stock flow adjustments (without exchange rate effect) | C15: ='Input data'!C15 -> 0.8044612 | D15: ='Input data'!D15 -> -1.310275 | E15: ='Input data'!E15 -> -0.9404473 | F15: ='Input data'!F15 -> 1.185197 | G15: ='Input data'!G15 -> 0.0667276 | H15: ='Input data'!H15 -> 0 | I15: ='Input data'!I15 -> 0 | J15: ='Input data'!J15 -> 0 | ... W15: ='Input data'!W15 -> 0
B17: ='Input data'!B19 -> Cost of ageing and selected public revenue (based on the Commission-Council 2024 Ageing Report ("AR 2024"))
B18: Total ageing cost (net of taxes on pensions) | C18: ='Input data'!C20 -> 0 | D18: ='Input data'!D20 -> 16.93779 | E18: ='Input data'!E20 -> 16.70416 | F18: ='Input data'!F20 -> 16.66552 | G18: ='Input data'!G20 -> 16.60096 | H18: ='Input data'!H20 -> 16.33519 | I18: ='Input data'!I20 -> 16.23882 | J18: ='Input data'!J20 -> 16.15621 | ... W18: ='Input data'!W20 -> 16.22383
B19: Property income | C19: ='Input data'!C26 -> 0.5214214 | D19: ='Input data'!D26 -> 0.4365457 | E19: ='Input data'!E26 -> 0.4337021 | F19: ='Input data'!F26 -> 0.4308586 | G19: ='Input data'!G26 -> 0.428015 | H19: ='Input data'!H26 -> 0.4251715 | I19: ='Input data'!I26 -> 0.4223279 | J19: ='Input data'!J26 -> 0.4194843 | ... W19: ='Input data'!W26 -> 0.3825183
B21: GDP growth assumptions
B22: Actual GDP (real)
B23: Level | C23: ='Input data'!C31 -> 13.62455 | D23: ='Baseline NFPC'!D22 -> 14.72481 | E23: ='Baseline NFPC'!E22 -> 15.55145 | F23: ='Baseline NFPC'!F22 -> 16.262506 | G23: =IF(AND(G50>1,F50>1),IF(AND(G50>0,F50>0),G27*(G51/100+1),0)+IF(G50>0,F23*(1+G52/100),0)-F23*(1+'Input data'!G30/100),IF(G50=1,G27,F23*(1+G52/100))) -> 16.989472 | H23: =IF(AND(H50>1,G50>1),IF(AND(H50>0,G50>0),H27*(H51/100+1),0)+IF(H50>0,G23*(1+H52/100),0)-G23*(1+'Input data'!H30/100),IF(H50=1,H27,G23*(1+H52/100))) -> 17.763868 | I23: =IF(AND(I50>1,H50>1),IF(AND(I50>0,H50>0),I27*(I51/100+1),0)+IF(I50>0,H23*(1+I52/100),0)-H23*(1+'Input data'!I30/100),IF(I50=1,I27,H23*(1+I52/100))) -> 18.586045 | J23: =IF(AND(J50>1,I50>1),IF(AND(J50>0,I50>0),J27*(J51/100+1),0)+IF(J50>0,I23*(1+J52/100),0)-I23*(1+'Input data'!J30/100),IF(J50=1,J27,I23*(1+J52/100))) -> 19.43521 | K23: =IF(AND(K50>1,J50>1),IF(AND(K50>0,J50>0),K27*(K51/100+1),0)+IF(K50>0,J23*(1+K52/100),0)-J23*(1+'Input data'!K30/100),IF(K50=1,K27,J23*(1+K52/100))) -> 20.396456 | L23: =IF(AND(L50>1,K50>1),IF(AND(L50>0,K50>0),L27*(L51/100+1),0)+IF(L50>0,K23*(1+L52/100),0)-K23*(1+'Input data'!L30/100),IF(L50=1,L27,K23*(1+L52/100))) -> 21.385791 | M23: =IF(AND(M50>1,L50>1),IF(AND(M50>0,L50>0),M27*(M51/100+1),0)+IF(M50>0,L23*(1+M52/100),0)-L23*(1+'Input data'!M30/100),IF(M50=1,M27,L23*(1+M52/100))) -> 22.389392 | N23: =IF(AND(N50>1,M50>1),IF(AND(N50>0,M50>0),N27*(N51/100+1),0)+IF(N50>0,M23*(1+N52/100),0)-M23*(1+'Input data'!N30/100),IF(N50=1,N27,M23*(1+N52/100))) -> 23.323058 | ... W23: =IF(AND(W50>1,V50>1),IF(AND(W50>0,V50>0),W27*(W51/100+1),0)+IF(W50>0,V23*(1+W52/100),0)-V23*(1+'Input data'!W30/100),IF(W50=1,W27,V23*(1+W52/100))) -> 30.672534
B24: Growth rate | C24: =+'Input data'!C30 -> 12.51395 | D24: ='Baseline NFPC'!D23 -> 8.075569 | E24: ='Baseline NFPC'!E23 -> 5.613926 | F24: ='Baseline NFPC'!F23 -> 4.57228 | G24: =100*(G23/F23-1) -> 4.470198 | H24: =100*(H23/G23-1) -> 4.5580913 | I24: =100*(I23/H23-1) -> 4.6283716 | J24: =100*(J23/I23-1) -> 4.5688268 | K24: =100*(K23/J23-1) -> 4.9459043 | L24: =100*(L23/K23-1) -> 4.850523 | M24: =100*(M23/L23-1) -> 4.6928382 | N24: =100*(N23/M23-1) -> 4.170129 | ... W24: =100*(W23/V23-1) -> 2.369435
B26: Potential GDP (real)
B27: Level | C27: ='Input data'!C34 -> 13.87421 | D27: =+C27*(1+'Input data'!D33/100) -> 14.798696 | E27: =+D27*(1+'Input data'!E33/100) -> 15.55436 | F27: =+E27*(1+'Input data'!F33/100) -> 16.319408 | G27: =+F27*(1+'Input data'!G33/100) -> 17.11401 | H27: =+G27*(1+'Input data'!H33/100) -> 17.914487 | I27: =+H27*(1+'Input data'!I33/100) -> 18.7578 | J27: =+I27*(1+'Input data'!J33/100) -> 19.629039 | K27: =+J27*(1+'Input data'!K33/100) -> 20.531618 | ... W27: =+V27*(1+'Input data'!W33/100) -> 30.672533
B29: Output gap
B30: Output gap | C30: =100*(C23/C27-1) -> -1.7994538 | D30: =100*(D23/D27-1) -> -0.49927084 | E30: =100*(E23/E27-1) -> -0.018709187 | F30: =100*(F23/F27-1) -> -0.34867871 | G30: =100*(G23/G27-1) -> -0.7276992 | H30: =100*(H23/H27-1) -> -0.84076966 | I30: =100*(I23/I27-1) -> -0.91564273 | J30: =100*(J23/J27-1) -> -0.98746076 | ... W30: =100*(W23/W27-1) -> 5.7106968e-06
B32: Actual GDP (nominal, national currency)
B33: Growth rate | C33: =100*((1+C24/100)*(1+C42/100)-1) -> 14.770139 | D33: =100*((1+D24/100)*(1+D42/100)-1) -> 13.761934 | E33: =100*((1+E24/100)*(1+E42/100)-1) -> 11.183599 | F33: =100*((1+F24/100)*(1+F42/100)-1) -> 8.3811611 | G33: =100*((1+G24/100)*(1+G42/100)-1) -> 7.1173798 | H33: =100*((1+H24/100)*(1+H42/100)-1) -> 7.209603 | I33: =100*((1+I24/100)*(1+I42/100)-1) -> 7.2837698 | J33: =100*((1+J24/100)*(1+J42/100)-1) -> 7.2248168 | ... W33: =100*((1+W24/100)*(1+W42/100)-1) -> 4.7546428
B35: Interest rates
B36: Nominal implicit interest rate on debt | C36: ='Input data'!C37 -> 2.40894 | D36: ='Input data'!D37 -> 1.98347 | E36: ='Input data'!E37 -> 2.37675 | F36: ='Input data'!F37 -> 2.749095 | G36: ='Input data'!G37 -> 2.738361 | H36: =H109 -> 2.82879 | I36: =I109 -> 2.9113734 | J36: =J109 -> 2.9880994 | K36: =K109 -> 3.059409 | L36: =L109 -> 3.1293648 | M36: =M109 -> 3.1980675 | N36: =N109 -> 3.2656344 | O36: =O109 -> 3.3342651 | ... W36: =W109 -> 3.6452522
B37: Long-term interest rate | D37: ='Input data'!D$39 -> 2.41 | E37: ='Input data'!E$39 -> 3.71 | F37: ='Input data'!F$39 -> 3.497002 | G37: ='Input data'!G$39 -> 3.505358 | H37: =G37+($O$37-$G$37)/($O$10-$G$10) -> 3.584932 | I37: =H37+($O$37-$G$37)/($O$10-$G$10) -> 3.664506 | J37: =I37+($O$37-$G$37)/($O$10-$G$10) -> 3.74408 | K37: =J37+($O$37-$G$37)/($O$10-$G$10) -> 3.823654 | L37: =K37+($O$37-$G$37)/($O$10-$G$10) -> 3.903228 | M37: =L37+($O$37-$G$37)/($O$10-$G$10) -> 3.982802 | N37: =M37+($O$37-$G$37)/($O$10-$G$10) -> 4.062376 | O37: ='Input data'!$C$52 -> 4.14195 | P37: ='Baseline NFPC'!P36 -> 4.1348525 | Q37: ='Baseline NFPC'!Q36 -> 4.127755 | R37: ='Baseline NFPC'!R36 -> 4.1206575 | S37: ='Baseline NFPC'!S36 -> 4.11356 | T37: ='Baseline NFPC'!T36 -> 4.1064625 | U37: ='Baseline NFPC'!U36 -> 4.099365 | V37: ='Baseline NFPC'!V36 -> 4.0922675 | W37: ='Baseline NFPC'!W36 -> 4.08517
B38: Short-term interest rate | D38: ='Input data'!D$38 -> 0.35 | E38: ='Input data'!E$38 -> 3.43 | F38: ='Input data'!F$38 -> 3.564208 | G38: ='Input data'!G$38 -> 2.816375 | H38: =G38+($O$38-$G$38)/($O$10-$G$10) -> 2.8050894 | I38: =H38+($O$38-$G$38)/($O$10-$G$10) -> 2.7938037 | J38: =I38+($O$38-$G$38)/($O$10-$G$10) -> 2.7825181 | K38: =J38+($O$38-$G$38)/($O$10-$G$10) -> 2.7712325 | L38: =K38+($O$38-$G$38)/($O$10-$G$10) -> 2.7599469 | M38: =L38+($O$38-$G$38)/($O$10-$G$10) -> 2.7486612 | N38: =M38+($O$38-$G$38)/($O$10-$G$10) -> 2.7373756 | O38: ='Input data'!$C$53 -> 2.72609 | P38: ='Baseline NFPC'!P37 -> 2.6897855 | Q38: ='Baseline NFPC'!Q37 -> 2.653481 | R38: ='Baseline NFPC'!R37 -> 2.6171765 | S38: ='Baseline NFPC'!S37 -> 2.580872 | T38: ='Baseline NFPC'!T37 -> 2.5445675 | U38: ='Baseline NFPC'!U37 -> 2.508263 | V38: ='Baseline NFPC'!V37 -> 2.4719585 | W38: ='Baseline NFPC'!W37 -> 2.435654
B39: Share of long-term debt that matures every year | C39: ='Baseline NFPC'!C38 -> 0.08190323 | D39: ='Baseline NFPC'!D38 -> 0.001 | E39: ='Baseline NFPC'!E38 -> 0.04901889 | F39: ='Baseline NFPC'!F38 -> 0.04747952 | G39: ='Baseline NFPC'!G38 -> 0.048981602 | H39: ='Baseline NFPC'!H38 -> 0.050483684 | I39: ='Baseline NFPC'!I38 -> 0.051985767 | J39: ='Baseline NFPC'!J38 -> 0.053487849 | ... W39: ='Baseline NFPC'!W38 -> 0.06099826
B41: Inflation and exchange rate
B42: GDP deflator (National currency) | C42: ='Input data'!C42 -> 2.005253 | D42: ='Input data'!D42 -> 5.261471 | E42: ='Input data'!E42 -> 5.273616 | F42: ='Input data'!F42 -> 3.642343 | G42: ='Input data'!G42 -> 2.533911 | H42: ='Baseline NFPC'!H41 -> 2.5359221 | I42: ='Baseline NFPC'!I41 -> 2.5379333 | J42: ='Baseline NFPC'!J41 -> 2.5399444 | K42: ='Baseline NFPC'!K41 -> 2.5419555 | L42: ='Baseline NFPC'!L41 -> 2.5439666 | M42: ='Baseline NFPC'!M41 -> 2.5459777 | N42: ='Baseline NFPC'!N41 -> 2.5479889 | O42: ='Baseline NFPC'!O41 -> 2.55 | ... W42: ='Baseline NFPC'!W41 -> 2.33
B43: Exchange rate composite change (weighted by share of debt in each currency) | C43: ='Baseline NFPC'!C42 -> 1 | D43: ='Baseline NFPC'!D42 -> 1 | E43: ='Baseline NFPC'!E42 -> 1 | F43: ='Baseline NFPC'!F42 -> 1 | G43: ='Baseline NFPC'!G42 -> 0.9999999 | H43: ='Baseline NFPC'!H42 -> 1 | I43: ='Baseline NFPC'!I42 -> 1 | J43: ='Baseline NFPC'!J42 -> 1 | ... W43: ='Baseline NFPC'!W42 -> 1
B45: Intermediate calculations (growth rate equation)
B47: Fiscal multiplier | C47: ='Input data'!C49 -> 0.75
B48: Budget balance semi-elasticity | C48: ='Input data'!C50 -> 0.479
B50: Auxiliary variable to control the closure of the output gap | C50: 0 | D50: =IF(AND(ABS((D12-C12)-('Input data'!D13-'Input data'!C13))>0.0001,ABS(D12-C12)>0.0001,D$10>$C$5),4,IF(C50=4,3,IF(C50=3,2,IF(C50=2,1,0)))) -> 0 | E50: =IF(AND(ABS((E12-D12)-('Input data'!E13-'Input data'!D13))>0.0001,ABS(E12-D12)>0.0001,E$10>$C$5),4,IF(D50=4,3,IF(D50=3,2,IF(D50=2,1,0)))) -> 0 | F50: =IF(AND(ABS((F12-E12)-('Input data'!F13-'Input data'!E13))>0.0001,ABS(F12-E12)>0.0001,F$10>$C$5),4,IF(E50=4,3,IF(E50=3,2,IF(E50=2,1,0)))) -> 0 | G50: =IF(AND(ABS((G12-F12)-('Input data'!G13-'Input data'!F13))>0.0001,ABS(G12-F12)>0.0001,G$10>$C$5),4,IF(F50=4,3,IF(F50=3,2,IF(F50=2,1,0)))) -> 4 | H50: =IF(AND(ABS((H12-G12)-('Input data'!H13-'Input data'!G13))>0.0001,ABS(H12-G12)>0.0001,H$10>$C$5),4,IF(G50=4,3,IF(G50=3,2,IF(G50=2,1,0)))) -> 4 | I50: =IF(AND(ABS((I12-H12)-('Input data'!I13-'Input data'!H13))>0.0001,ABS(I12-H12)>0.0001,I$10>$C$5),4,IF(H50=4,3,IF(H50=3,2,IF(H50=2,1,0)))) -> 4 | J50: =IF(AND(ABS((J12-I12)-('Input data'!J13-'Input data'!I13))>0.0001,ABS(J12-I12)>0.0001,J$10>$C$5),4,IF(I50=4,3,IF(I50=3,2,IF(I50=2,1,0)))) -> 4 | K50: =IF(AND(ABS((K12-J12)-('Input data'!K13-'Input data'!J13))>0.0001,ABS(K12-J12)>0.0001,K$10>$C$5),4,IF(J50=4,3,IF(J50=3,2,IF(J50=2,1,0)))) -> 3 | ... W50: =IF(AND(ABS((W12-V12)-('Input data'!W13-'Input data'!V13))>0.0001,ABS(W12-V12)>0.0001,W$10>$C$5),4,IF(V50=4,3,IF(V50=3,2,IF(V50=2,1,0)))) -> 0
B51: OG intermediate auxiliary value | C51: 0 | D51: =IF(C50=4,2/3*C30,IF(C50=3,1/3*B30,0)) -> 0 | E51: =IF(D50=4,2/3*D30,IF(D50=3,1/3*C30,0)) -> 0 | F51: =IF(E50=4,2/3*E30,IF(E50=3,1/3*D30,0)) -> 0 | G51: =IF(F50=4,2/3*F30,IF(F50=3,1/3*E30,0)) -> 0 | H51: =IF(G50=4,2/3*G30,IF(G50=3,1/3*F30,0)) -> -0.4851328 | I51: =IF(H50=4,2/3*H30,IF(H50=3,1/3*G30,0)) -> -0.56051311 | J51: =IF(I50=4,2/3*I30,IF(I50=3,1/3*H30,0)) -> -0.61042848 | K51: =IF(J50=4,2/3*J30,IF(J50=3,1/3*I30,0)) -> -0.65830717 | ... W51: =IF(V50=4,2/3*V30,IF(V50=3,1/3*U30,0)) -> 0
B52: GDP intermediate growth rate - only feedback effect and no closure of the OG | D52: ='Input data'!D30-$C$47*((D12-C12)-('Input data'!D13-'Input data'!C13)) -> 8.075569 | E52: ='Input data'!E30-$C$47*((E12-D12)-('Input data'!E13-'Input data'!D13)) -> 5.613926 | F52: ='Input data'!F30-$C$47*((F12-E12)-('Input data'!F13-'Input data'!E13)) -> 4.57228 | G52: ='Input data'!G30-$C$47*((G12-F12)) -> 4.470198 | H52: ='Input data'!H30-$C$47*((H12-G12)) -> 4.432363 | I52: ='Input data'!I30-$C$47*((I12-H12)) -> 4.505684 | J52: ='Input data'!J30-$C$47*((J12-I12)) -> 4.3329048 | K52: ='Input data'!K30-$C$47*((K12-J12)) -> 4.59818 | L52: ='Input data'!L30-$C$47*((L12-K12)) -> 4.504259 | M52: ='Input data'!M30-$C$47*((M12-L12)) -> 4.348238 | N52: ='Input data'!N30-$C$47*((N12-M12)) -> 4.170129 | ... W52: ='Input data'!W30-$C$47*((W12-V12)) -> 2.369435
B54: Debt projections
C56: 2021 | D56: 2022 | E56: 2023 | F56: 2024 | G56: 2025 | H56: 2026 | I56: 2027 | J56: 2028 | K56: 2029 | L56: 2030 | M56: 2031 | N56: 2032 | O56: 2033 | P56: 2034 | Q56: 2035 | R56: 2036 | S56: 2037 | T56: 2038 | U56: 2039 | V56: 2040 | W56: 2041
B57: Gross debt | C57: =+'Input data'!C12 -> 53.92565 | D57: =+C57+D58 -> 51.62648 | E57: =+D57+E58 -> 50.396658 | F57: =+E57+F58 -> 52.027241 | G57: =+F57+G58 -> 52.712875 | H57: =+G57+H58 -> 52.858887 | I57: =+H57+I58 -> 52.540436 | J57: =+I57+J58 -> 51.80375 | K57: =+J57+K58 -> 50.734076 | ... W57: =+V57+W58 -> 45.918674
B58: Change in debt (-1+2+3) | D58: =-D59+D67+D72 -> -2.2991703 | E58: =-E59+E67+E72 -> -1.2298213 | F58: =-F59+F67+F72 -> 1.6305821 | G58: =-G59+G67+G72 -> 0.68563494 | H58: =-H59+H67+H72 -> 0.14601116 | I58: =-I59+I67+I72 -> -0.31845091 | J58: =-J59+J67+J72 -> -0.73668598 | K58: =-K59+K67+K72 -> -1.0696733 | ... W58: =-W59+W67+W72 -> 0.4897973
B59: (1) Primary balance (1.1 + 1.2 - 1.3 -1.4 -1.5 - 1.6 -1.7) | D59: =D60+D61-D62-D63-D64-D65-D66 -> -4.5943547 | E59: =E60+E61-E62-E63-E64-E65-E66 -> -3.7999557 | F59: =F60+F61-F62-F63-F64-F65-F66 -> -3.0642601 | G59: =G60+G61-G62-G63-G64-G65-G66 -> -2.7458109 | H59: =H60+H61-H62-H63-H64-H65-H66 -> -2.2999717 | I59: =I60+I61-I62-I63-I64-I65-I66 -> -1.8358359 | J59: =J60+J61-J62-J63-J64-J65-J66 -> -1.3393164 | K59: =K60+K61-K62-K63-K64-K65-K66 -> -1.1226454 | ... W59: =W60+W61-W62-W63-W64-W65-W66 -> -0.970906
B60: (1.1) Structural primary balance (before ageing cost) | D60: =D12 -> -4.355204 | E60: =E12 -> -3.790994 | F60: =F12 -> -2.897243 | G60: =IF(G12="",F60,G12) -> -2.397243 | H60: =IF(H12="",G60,H12) -> -1.897243 | I60: =IF(I12="",H60,I12) -> -1.397243 | J60: =IF(J12="",I60,J12) -> -0.86632274 | K60: =IF(K12="",J60,K12) -> -0.86632274 | L60: =IF(L12="",K60,L12) -> -0.86632274 | M60: =IF(M12="",L60,M12) -> -0.86632274 | N60: =IF(N12="",M60,N12) -> -0.86632274 | ... W60: =IF(W12="",V60,W12) -> -0.86632274
B61: (1.2) Cumulated budgetary effort (in terms of primary balance) | D61: 0 | E61: 0 | F61: 0 | G61: 0 | H61: 0 | I61: 0 | J61: 0 | K61: 0 | L61: 0 | M61: 0 | N61: 0 | O61: 0 | P61: 0 | Q61: 0 | R61: 0 | S61: 0 | T61: 0 | U61: 0 | V61: 0 | W61: 0
B62: (1.3) Cyclical component | D62: =-$C$48*D30 -> 0.23915073 | E62: =-$C$48*E30 -> 0.0089617005 | F62: =-$C$48*F30 -> 0.1670171 | G62: =-$C$48*G30 -> 0.34856792 | H62: =-$C$48*H30 -> 0.40272867 | I62: =-$C$48*I30 -> 0.43859287 | J62: =-$C$48*J30 -> 0.4729937 | K62: =-$C$48*K30 -> 0.31532914 | ... W62: =-$C$48*W30 -> -2.7354238e-06
B63: (1.4) One-off and other temporary measures | D63: =-D14 -> 0 | E63: =-E14 -> 0 | F63: =-F14 -> 0 | G63: =-G14 -> 0 | H63: =-H14 -> 0 | I63: =-I14 -> 0 | J63: =-J14 -> 0 | K63: =-K14 -> 0 | ... W63: =-W14 -> 0
B64: (1.5) Cost of ageing | D64: =IF(D$56<=$C$6,0,HLOOKUP(D$56,'Input data'!$C$9:$BB$26,12,FALSE)-HLOOKUP($C$6,'Input data'!$C$9:$BB$26,12,FALSE)) -> 0 | E64: =IF(E$56<=$C$6,0,HLOOKUP(E$56,'Input data'!$C$9:$BB$26,12,FALSE)-HLOOKUP($C$6,'Input data'!$C$9:$BB$26,12,FALSE)) -> 0 | F64: =IF(F$56<=$C$6,0,HLOOKUP(F$56,'Input data'!$C$9:$BB$26,12,FALSE)-HLOOKUP($C$6,'Input data'!$C$9:$BB$26,12,FALSE)) -> 0 | G64: =IF(G$56<=$C$6,0,HLOOKUP(G$56,'Input data'!$C$9:$BB$26,12,FALSE)-HLOOKUP($C$6,'Input data'!$C$9:$BB$26,12,FALSE)) -> 0 | H64: =IF(H$56<=$C$6,0,HLOOKUP(H$56,'Input data'!$C$9:$BB$26,12,FALSE)-HLOOKUP($C$6,'Input data'!$C$9:$BB$26,12,FALSE)) -> 0 | I64: =IF(I$56<=$C$6,0,HLOOKUP(I$56,'Input data'!$C$9:$BB$26,12,FALSE)-HLOOKUP($C$6,'Input data'!$C$9:$BB$26,12,FALSE)) -> 0 | J64: =IF(J$56<=$C$6,0,HLOOKUP(J$56,'Input data'!$C$9:$BB$26,12,FALSE)-HLOOKUP($C$6,'Input data'!$C$9:$BB$26,12,FALSE)) -> 0 | K64: =IF(K$56<=$C$6,0,HLOOKUP(K$56,'Input data'!$C$9:$BB$26,12,FALSE)-HLOOKUP($C$6,'Input data'!$C$9:$BB$26,12,FALSE)) -> -0.06185 | ... W64: =IF(W$56<=$C$6,0,HLOOKUP(W$56,'Input data'!$C$9:$BB$26,12,FALSE)-HLOOKUP($C$6,'Input data'!$C$9:$BB$26,12,FALSE)) -> 0.06762
B65: (1.6) Property incomes | D65: =IF(D$56<=$C$5,0,-HLOOKUP(D$56,'Input data'!$C$9:$BB$26,18,FALSE)+HLOOKUP($C$6,'Input data'!$C$9:$BB$26,18,FALSE)) -> 0 | E65: =IF(E$56<=$C$5,0,-HLOOKUP(E$56,'Input data'!$C$9:$BB$26,18,FALSE)+HLOOKUP($C$6,'Input data'!$C$9:$BB$26,18,FALSE)) -> 0 | F65: =IF(F$56<=$C$5,0,-HLOOKUP(F$56,'Input data'!$C$9:$BB$26,18,FALSE)+HLOOKUP($C$6,'Input data'!$C$9:$BB$26,18,FALSE)) -> 0 | G65: =IF(G$56<=$C$6,0,-HLOOKUP(G$56,'Input data'!$C$9:$BB$26,18,FALSE)+HLOOKUP($C$6,'Input data'!$C$9:$BB$26,18,FALSE)) -> 0 | H65: =IF(H$56<=$C$6,0,-HLOOKUP(H$56,'Input data'!$C$9:$BB$26,18,FALSE)+HLOOKUP($C$6,'Input data'!$C$9:$BB$26,18,FALSE)) -> 0 | I65: =IF(I$56<=$C$6,0,-HLOOKUP(I$56,'Input data'!$C$9:$BB$26,18,FALSE)+HLOOKUP($C$6,'Input data'!$C$9:$BB$26,18,FALSE)) -> 0 | J65: =IF(J$56<=$C$6,0,-HLOOKUP(J$56,'Input data'!$C$9:$BB$26,18,FALSE)+HLOOKUP($C$6,'Input data'!$C$9:$BB$26,18,FALSE)) -> 0 | K65: =IF(K$56<=$C$6,0,-HLOOKUP(K$56,'Input data'!$C$9:$BB$26,18,FALSE)+HLOOKUP($C$6,'Input data'!$C$9:$BB$26,18,FALSE)) -> 0.0028435 | L65: =IF(L$56<=$C$6,0,-HLOOKUP(L$56,'Input data'!$C$9:$BB$26,18,FALSE)+HLOOKUP($C$6,'Input data'!$C$9:$BB$26,18,FALSE)) -> 0.005687 | M65: =IF(M$56<=$C$6,0,-HLOOKUP(M$56,'Input data'!$C$9:$BB$26,18,FALSE)+HLOOKUP($C$6,'Input data'!$C$9:$BB$26,18,FALSE)) -> 0.0085306 | N65: =IF(N$56<=$C$6,0,-HLOOKUP(N$56,'Input data'!$C$9:$BB$26,18,FALSE)+HLOOKUP($C$6,'Input data'!$C$9:$BB$26,18,FALSE)) -> 0.0113742 | ... W65: =IF(W$56<=$C$6,0,-HLOOKUP(W$56,'Input data'!$C$9:$BB$26,18,FALSE)+HLOOKUP($C$6,'Input data'!$C$9:$BB$26,18,FALSE)) -> 0.036966
B66: (1.7) Revenues | D66: 0 | E66: 0 | F66: 0 | G66: 0 | H66: 0 | I66: 0 | J66: 0 | K66: 0 | L66: 0 | M66: 0 | N66: 0 | O66: 0 | P66: 0 | Q66: 0 | R66: 0 | S66: 0 | T66: 0 | U66: 0 | V66: 0 | W66: 0
B67: (2) Snowball effect (2.1 + 2.2 + 2.3) | D67: =SUM(D68:D71) -> -5.58325 | E67: =SUM(E68:E71) -> -4.089329 | F67: =SUM(F68:F71) -> -2.618877 | G67: =SUM(G68:G71) -> -2.1269004 | H67: =SUM(H68:H71) -> -2.1539605 | I67: =SUM(I68:I71) -> -2.1542868 | J67: =SUM(J68:J71) -> -2.0760024 | K67: =SUM(K68:K71) -> -2.1923186 | ... W67: =SUM(W68:W71) -> -0.4811087
B68: (2.1) Interest expenditure | D68: =C57*D36/100*(1/(1+D33/100)) -> 0.94020825 | E68: =D57*E36/100*(1/(1+E33/100)) -> 1.1036091 | F68: =E57*F36/100*(1/(1+F33/100)) -> 1.2783144 | G68: =F57*G36/100*(1/(1+G33/100)) -> 1.3300304 | H68: =G57*H36/100*(1/(1+H33/100)) -> 1.390861 | I68: =H57*I36/100*(1/(1+I33/100)) -> 1.4344384 | J68: =I57*J36/100*(1/(1+J33/100)) -> 1.4641764 | K68: =J57*K36/100*(1/(1+K33/100)) -> 1.4727589 | ... W68: =V57*W36/100*(1/(1+W33/100)) -> 1.5808341
B69: (2.2) Growth effect | D69: =-C57*(D24/100)*(1/(1+D33/100)) -> -3.8279967 | E69: =-D57*(E24/100)*(1/(1+E33/100)) -> -2.6067445 | F69: =-E57*(F24/100)*(1/(1+F33/100)) -> -2.1260857 | G69: =-F57*(G24/100)*(1/(1+G33/100)) -> -2.1711889 | H69: =-G57*(H24/100)*(1/(1+H33/100)) -> -2.2411248 | I69: =-H57*(I24/100)*(1/(1+I33/100)) -> -2.2804062 | J69: =-I57*(J24/100)*(1/(1+J33/100)) -> -2.2387368 | K69: =-J57*(K24/100)*(1/(1+K33/100)) -> -2.3808927 | ... W69: =-V57*(W24/100)*(1/(1+W33/100)) -> -1.0275513
B70: (2.3) Inflation effect | D70: =-C57*D42/100*(1/(1+D42/100)) -> -2.6954615 | E70: =-D57*E42/100*(1/(1+E42/100)) -> -2.5861962 | F70: =-E57*F42/100*(1/(1+F42/100)) -> -1.7711093 | G70: =-F57*G42/100*(1/(1+G42/100)) -> -1.2857444 | H70: =-G57*H42/100*(1/(1+H42/100)) -> -1.3036967 | I70: =-H57*I42/100*(1/(1+I42/100)) -> -1.308319 | J70: =-I57*J42/100*(1/(1+J42/100)) -> -1.3014419 | K70: =-J57*K42/100*(1/(1+K42/100)) -> -1.2841849 | ... W70: =-V57*W42/100*(1/(1+W42/100)) -> -1.0343915
B71: (2.4) Exchange rate effect linked to the interest rate | D71: ='Baseline NFPC'!D70 -> -3.7714402e-08 | E71: ='Baseline NFPC'!E70 -> 2.6165035e-06 | F71: ='Baseline NFPC'!F70 -> 3.5287289e-06 | G71: ='Baseline NFPC'!G70 -> 2.5290586e-06 | H71: 0 | I71: 0 | J71: 0 | K71: 0 | L71: 0 | M71: 0 | N71: 0 | O71: 0 | P71: 0 | Q71: 0 | R71: 0 | S71: 0 | T71: 0 | U71: 0 | V71: 0 | W71: 0
B72: (3 ) Stock flow adjustments (3.1 + 3.2) | D72: ='Input data'!D16 -> -1.310275 | E72: ='Input data'!E16 -> -0.940448 | F72: ='Input data'!F16 -> 1.185199 | G72: ='Input data'!G16 -> 0.0667244 | H72: ='Input data'!H16 -> 0 | I72: ='Input data'!I16 -> 0 | J72: ='Input data'!J16 -> 0 | K72: ='Input data'!K16 -> 0 | ... W72: ='Input data'!W16 -> 0
B73: (3.1) Base | D73: =D15 -> -1.310275 | E73: =E15 -> -0.9404473 | F73: =F15 -> 1.185197 | G73: =G15 -> 0.0667276 | H73: =H15 -> 0 | I73: =I15 -> 0 | J73: =J15 -> 0 | K73: =K15 -> 0 | ... W73: =W15 -> 0
B74: (3.2) Adjustment due to the exchange rate effect linked to debt value | D74: =+D72-D73 -> 0 | E74: =+E72-E73 -> -7e-07 | F74: =+F72-F73 -> 2e-06 | G74: =+G72-G73 -> -3.2e-06 | H74: =+H72-H73 -> 0 | I74: =+I72-I73 -> 0 | J74: =+J72-J73 -> 0 | K74: =+K72-K73 -> 0 | ... W74: =+W72-W73 -> 0
B76: Other budgetary variables
B77: Headline balance | D77: =D59-D68 -> -5.534563 | E77: =E59-E68 -> -4.9035648 | F77: =F59-F68 -> -4.3425745 | G77: =G59-G68 -> -4.0758413 | H77: =H59-H68 -> -3.6908327 | I77: =I59-I68 -> -3.2702742 | J77: =J59-J68 -> -2.8034928 | K77: =K59-K68 -> -2.5954043 | ... W77: =W59-W68 -> -2.5517401
B78: Structural balance | D78: =D60-D68-D64-D65-D66 -> -5.2954123 | E78: =E60-E68-E64-E65-E66 -> -4.8946031 | F78: =F60-F68-F64-F65-F66 -> -4.1755574 | G78: =G60-G68-G64-G65-G66 -> -3.7272734 | H78: =H60-H68-H64-H65-H66 -> -3.288104 | I78: =I60-I68-I64-I65-I66 -> -2.8316814 | J78: =J60-J68-J64-J65-J66 -> -2.3304991 | K78: =K60-K68-K64-K65-K66 -> -2.2800751 | ... W78: =W60-W68-W64-W65-W66 -> -2.5517429
B79: Net expenditure growth | D79: ='Input data'!D45 -> 13.084528 | E79: ='Input data'!E45 -> 9.2925168 | F79: ='Input data'!F45 -> 5.4768547 | G79: ='Input data'!G33+G42-(G$12-F$12)/'Input data'!$C$64*100 -> 6.0362927 | H79: ='Input data'!H33+H42-(H$12-G$12)/'Input data'!$C$64*100 -> 5.8465578 | I79: ='Input data'!I33+I42-(I$12-H$12)/'Input data'!$C$64*100 -> 5.8786849 | J79: ='Input data'!J33+J42-(J$12-I$12)/'Input data'!$C$64*100 -> 5.7334207 | K79: ='Input data'!K33+K42-(K$12-J$12)/'Input data'!$C$64*100 -> 7.1401375 | L79: ='Input data'!L33+L42-(L$12-K$12)/'Input data'!$C$64*100 -> 7.0482306 | M79: ='Input data'!M33+M42-(M$12-L$12)/'Input data'!$C$64*100 -> 6.8942157 | N79: ='Input data'!N33+N42-(N$12-M$12)/'Input data'!$C$64*100 -> 6.7181139 | ... W79: ='Input data'!W33+W42-(W$12-V$12)/'Input data'!$C$64*100 -> 4.699437
B81: Average net primary expenditure growth | D81: =AVERAGE(OFFSET($G$79,0,0,1,'Criteria results'!F5)) -> 5.873739
B83: Debt increasing? (For criterion 1) | K83: =IF(K57<J57,0,1) -> 0 | L83: =IF(L57<K57,0,1) -> 0 | M83: =IF(M57<L57,0,1) -> 0 | N83: =IF(N57<M57,0,1) -> 0 | O83: =IF(O57<N57,0,1) -> 0 | P83: =IF(P57<O57,0,1) -> 0 | Q83: =IF(Q57<P57,0,1) -> 0 | R83: =IF(R57<Q57,0,1) -> 0 | ... W83: =IF(W57<V57,0,1) -> 1
B84: Debt above 90% (for debt sustainability safeguard) | F84: =IF(F57>90,1,0) -> 0 | G84: =IF(G57>90,1,0) -> 0 | H84: =IF(H57>90,1,0) -> 0 | I84: =IF(I57>90,1,0) -> 0 | J84: =IF(J57>90,1,0) -> 0 | K84: =IF(K57>90,1,0) -> 0 | L84: =IF(L57>90,1,0) -> 0 | M84: =IF(M57>90,1,0) -> 0 | ... W84: =IF(W57>90,1,0) -> 0
B85: Debt between 60% and 90% (for debt sustainability safeguard) | F85: =IF(AND(F57>60,F57<=90),1,0) -> 0 | G85: =IF(AND(G57>60,G57<=90),1,0) -> 0 | H85: =IF(AND(H57>60,H57<=90),1,0) -> 0 | I85: =IF(AND(I57>60,I57<=90),1,0) -> 0 | J85: =IF(AND(J57>60,J57<=90),1,0) -> 0 | K85: =IF(AND(K57>60,K57<=90),1,0) -> 0 | L85: =IF(AND(L57>60,L57<=90),1,0) -> 0 | M85: =IF(AND(M57>60,M57<=90),1,0) -> 0 | ... W85: =IF(AND(W57>60,W57<=90),1,0) -> 0
B86: Debt above 60% (for debt sustainability safeguard) | F86: =IF(F57>60,1,0) -> 0 | G86: =IF(G57>60,1,0) -> 0 | H86: =IF(H57>60,1,0) -> 0 | I86: =IF(I57>60,1,0) -> 0 | J86: =IF(J57>60,1,0) -> 0 | K86: =IF(K57>60,1,0) -> 0 | L86: =IF(L57>60,1,0) -> 0 | M86: =IF(M57>60,1,0) -> 0 | ... W86: =IF(W57>60,1,0) -> 0
B87: Deficit exceeding 3% / under EDP (for deficit benchmark and debt sustainability safeguard) | F87: ='Input data'!F17 -> 1 | G87: =IF(F87=0,0,IF(AND(E77>-3.05,F77>-3.05),0,1)) -> 1 | H87: =IF(G87=0,0,IF(AND(F77>-3.05,G77>-3.05),0,1)) -> 1 | I87: =IF(H87=0,0,IF(AND(G77>-3.05,H77>-3.05),0,1)) -> 1 | J87: =IF(I87=0,0,IF(AND(H77>-3.05,I77>-3.05),0,1)) -> 1 | K87: =IF(J87=0,0,IF(AND(I77>-3.05,J77>-3.05),0,1)) -> 1 | L87: =IF(K87=0,0,IF(AND(J77>-3.05,K77>-3.05),0,1)) -> 0 | M87: =IF(L87=0,0,IF(AND(K77>-3.05,L77>-3.05),0,1)) -> 0 | N87: =IF(M87=0,0,IF(AND(L77>-3.05,M77>-3.05),0,1)) -> 0 | ... W87: =IF(V87=0,0,IF(AND(U77>-3.05,V77>-3.05),0,1)) -> 0
B88: Structural balance ensuring safety margin (for deficit resilience safeguard) | F88: =IF(F78>=-1.55,1,0) -> 0 | G88: =IF(G78>=-1.55,1,0) -> 0 | H88: =IF(H78>=-1.55,1,0) -> 0 | I88: =IF(I78>=-1.55,1,0) -> 0 | J88: =IF(J78>=-1.55,1,0) -> 0 | K88: =IF(K78>=-1.55,1,0) -> 0 | L88: =IF(L78>=-1.55,1,0) -> 0 | M88: =IF(M78>=-1.55,1,0) -> 0 | ... W88: =IF(W78>=-1.55,1,0) -> 0
B90: Approximation of interest payments in % GDP | F90: =E57*F36/100*(1/((1+'Input data'!F30/100)*(1+F42/100))) -> 1.2783144 | G90: =F57*G36/100*(1/((1+'Input data'!G30/100)*(1+G42/100))) -> 1.3252732 | H90: =G57*H36/100*(1/((1+'Input data'!H30/100)*(1+H42/100))) -> 1.387553 | I90: =H57*I36/100*(1/((1+'Input data'!I30/100)*(1+I42/100))) -> 1.4309875 | J90: =I57*J36/100*(1/((1+'Input data'!J30/100)*(1+J42/100))) -> 1.4619078 | K90: =J57*K36/100*(1/((1+'Input data'!K30/100)*(1+K42/100))) -> 1.4776549 | L90: =K57*L36/100*(1/((1+'Input data'!L30/100)*(1+L42/100))) -> 1.4815348 | M90: =L57*M36/100*(1/((1+'Input data'!M30/100)*(1+M42/100))) -> 1.4815581 | ... W90: =V57*W36/100*(1/((1+'Input data'!W30/100)*(1+W42/100))) -> 1.5808341
B91: Change in interest payments (for deficit benchmark in SB terms from 2028 onwards) | G91: =G90-F90 -> 0.046958805 | H91: =H90-G90 -> 0.062279771 | I91: =I90-H90 -> 0.04343454 | J91: =J90-I90 -> 0.030920263 | K91: =K90-J90 -> 0.015747097 | L91: =L90-K90 -> 0.0038798623 | M91: =M90-L90 -> 2.338415e-05 | N91: =N90-M90 -> -0.003430019 | ... W91: =W90-V90 -> 0.02339561
B93: Debt decomposition and IIR
B95: Auxiliary variable identifying whether debt is increasing | D95: =IF((D100-C100*D43/((1+D24/100)*(1+D42/100)))>0,1,0) -> 1 | E95: =IF((E100-D100*E43/((1+E24/100)*(1+E42/100)))>0,1,0) -> 1 | F95: =IF((F100-E100*F43/((1+F24/100)*(1+F42/100)))>0,1,0) -> 1 | G95: =IF((G100-F100*G43/((1+G24/100)*(1+G42/100)))>0,1,0) -> 1 | H95: =IF((H100-G100*H43/((1+H24/100)*(1+H42/100)))>0,1,0) -> 1 | I95: =IF((I100-H100*I43/((1+I24/100)*(1+I42/100)))>0,1,0) -> 1 | J95: =IF((J100-I100*J43/((1+J24/100)*(1+J42/100)))>0,1,0) -> 1 | K95: =IF((K100-J100*K43/((1+K24/100)*(1+K42/100)))>0,1,0) -> 1 | ... W95: =IF((W100-V100*W43/((1+W24/100)*(1+W42/100)))>0,1,0) -> 1
B96: Auxiliary variable identifying whether some debt is rolled over even though debt is decreasing | D96: =IF(AND(D95=0,ABS(D100-C100*D43/((1+D24/100)*(1+D42/100)))<((C106*C100*D43/((1+D24/100)*(1+D42/100))+(D39*C100*C107*D43/((1+D24/100)*(1+D42/100)))))),1,0) -> 0 | E96: =IF(AND(E95=0,ABS(E100-D100*E43/((1+E24/100)*(1+E42/100)))<((D106*D100*E43/((1+E24/100)*(1+E42/100))+(E39*D100*D107*E43/((1+E24/100)*(1+E42/100)))))),1,0) -> 0 | F96: =IF(AND(F95=0,ABS(F100-E100*F43/((1+F24/100)*(1+F42/100)))<((E106*E100*F43/((1+F24/100)*(1+F42/100))+(F39*E100*E107*F43/((1+F24/100)*(1+F42/100)))))),1,0) -> 0 | G96: =IF(AND(G95=0,ABS(G100-F100*G43/((1+G24/100)*(1+G42/100)))<((F106*F100*G43/((1+G24/100)*(1+G42/100))+(G39*F100*F107*G43/((1+G24/100)*(1+G42/100)))))),1,0) -> 0 | H96: =IF(AND(H95=0,ABS(H100-G100*H43/((1+H24/100)*(1+H42/100)))<((G106*G100*H43/((1+H24/100)*(1+H42/100))+(H39*G100*G107*H43/((1+H24/100)*(1+H42/100)))))),1,0) -> 0 | I96: =IF(AND(I95=0,ABS(I100-H100*I43/((1+I24/100)*(1+I42/100)))<((H106*H100*I43/((1+I24/100)*(1+I42/100))+(I39*H100*H107*I43/((1+I24/100)*(1+I42/100)))))),1,0) -> 0 | J96: =IF(AND(J95=0,ABS(J100-I100*J43/((1+J24/100)*(1+J42/100)))<((I106*I100*J43/((1+J24/100)*(1+J42/100))+(J39*I100*I107*J43/((1+J24/100)*(1+J42/100)))))),1,0) -> 0 | K96: =IF(AND(K95=0,ABS(K100-J100*K43/((1+K24/100)*(1+K42/100)))<((J106*J100*K43/((1+K24/100)*(1+K42/100))+(K39*J100*J107*K43/((1+K24/100)*(1+K42/100)))))),1,0) -> 0 | ... W96: =IF(AND(W95=0,ABS(W100-V100*W43/((1+W24/100)*(1+W42/100)))<((V106*V100*W43/((1+W24/100)*(1+W42/100))+(W39*V100*V107*W43/((1+W24/100)*(1+W42/100)))))),1,0) -> 0
C99: 2021 | D99: 2022 | E99: 2023 | F99: 2024 | G99: 2025 | H99: 2026 | I99: 2027 | J99: 2028 | K99: 2029 | L99: 2030 | M99: 2031 | N99: 2032 | O99: 2033 | P99: 2034 | Q99: 2035 | R99: 2036 | S99: 2037 | T99: 2038 | U99: 2039 | V99: 2040 | W99: 2041
B100: Gross debt | C100: =C57 -> 53.92565 | D100: =D57 -> 51.62648 | E100: =E57 -> 50.396658 | F100: =F57 -> 52.027241 | G100: =G57 -> 52.712875 | H100: =G100*(1+H113/100)*H43-H60-H61+H62+H63+H64+H65+H66+H72 -> 52.858887 | I100: =H100*(1+I113/100)*I43-I60-I61+I62+I63+I64+I65+I66+I72 -> 52.540436 | J100: =I100*(1+J113/100)*J43-J60-J61+J62+J63+J64+J65+J66+J72 -> 51.80375 | K100: =J100*(1+K113/100)*K43-K60-K61+K62+K63+K64+K65+K66+K72 -> 50.734076 | L100: =K100*(1+L113/100)*L43-L60-L61+L62+L63+L64+L65+L66+L72 -> 49.571815 | M100: =L100*(1+M113/100)*M43-M60-M61+M62+M63+M64+M65+M66+M72 -> 48.352048 | N100: =M100*(1+N113/100)*N43-N60-N61+N62+N63+N64+N65+N66+N72 -> 47.403497 | O100: =N100*(1+O113/100)*O43-O60-O61+O62+O63+O64+O65+O66+O72 -> 46.518627 | ... W100: =V100*(1+W113/100)*W43-W60-W61+W62+W63+W64+W65+W66+W72 -> 45.918674
B101: Of which Outstanding debt | D101: ='Input data'!C66*$D$100 -> 40.602371 | E101: =IF(E100=0,0,IF(E95=1,D100*E43/((1+E24/100)*(1+E42/100))-E102-E103,IF(AND(E95=0,E96=1),(1-D106-E39*D107)*D100*E43/((1+E24/100)*(1+E42/100)),E100))) -> 37.860894 | F101: =IF(F100=0,0,IF(F95=1,E100*F43/((1+F24/100)*(1+F42/100))-F102-F103,IF(AND(F95=0,F96=1),(1-E106-F39*E107)*E100*F43/((1+F24/100)*(1+F42/100)),F100))) -> 38.019239 | G101: =IF(G100=0,0,IF(G95=1,F100*G43/((1+G24/100)*(1+G42/100))-G102-G103,IF(AND(G95=0,G96=1),(1-F106-G39*F107)*F100*G43/((1+G24/100)*(1+G42/100)),G100))) -> 39.705898 | H101: =IF(H100=0,0,IF(H95=1,G100*H43/((1+H24/100)*(1+H42/100))-H102-H103,IF(AND(H95=0,H96=1),(1-G106-H39*G107)*G100*H43/((1+H24/100)*(1+H42/100)),H100))) -> 40.168559 | I101: =IF(I100=0,0,IF(I95=1,H100*I43/((1+I24/100)*(1+I42/100))-I102-I103,IF(AND(I95=0,I96=1),(1-H106-I39*H107)*H100*I43/((1+I24/100)*(1+I42/100)),I100))) -> 40.219007 | J101: =IF(J100=0,0,IF(J95=1,I100*J43/((1+J24/100)*(1+J42/100))-J102-J103,IF(AND(J95=0,J96=1),(1-I106-J39*I107)*I100*J43/((1+J24/100)*(1+J42/100)),J100))) -> 39.96059 | K101: =IF(K100=0,0,IF(K95=1,J100*K43/((1+K24/100)*(1+K42/100))-K102-K103,IF(AND(K95=0,K96=1),(1-J106-K39*J107)*J100*K43/((1+K24/100)*(1+K42/100)),K100))) -> 39.215869 | L101: =IF(L100=0,0,IF(L95=1,K100*L43/((1+L24/100)*(1+L42/100))-L102-L103,IF(AND(L95=0,L96=1),(1-K106-L39*K107)*K100*L43/((1+L24/100)*(1+L42/100)),L100))) -> 38.396893 | ... W101: =IF(W100=0,0,IF(W95=1,V100*W43/((1+W24/100)*(1+W42/100))-W102-W103,IF(AND(W95=0,W96=1),(1-V106-W39*V107)*V100*W43/((1+W24/100)*(1+W42/100)),W100))) -> 35.246012
B102: Rolled over long-term debt | D102: ='Input data'!C67*$D$100 -> 0.040643031 | E102: =IF(E100=0,0,IF(E95=1,E39*D100*D107*E43/((1+E24/100)*(1+E42/100)),IF(AND(E95=0,E96=1),(E39*D100*D107*E43/((1+E24/100)*(1+E42/100)))*(1-ABS(E100-D100*E43/((1+E24/100)*(1+E42/100)))/((E39*D100*D107*E43/((1+E24/100)*(1+E42/100)))+(D106*D100*E43/((1+E24/100)*(1+E42/100))))),0))) -> 1.9515624 | F102: =IF(F100=0,0,IF(F95=1,F39*E100*E107*F43/((1+F24/100)*(1+F42/100)),IF(AND(F95=0,F96=1),(F39*E100*E107*F43/((1+F24/100)*(1+F42/100)))*(1-ABS(F100-E100*F43/((1+F24/100)*(1+F42/100)))/((F39*E100*E107*F43/((1+F24/100)*(1+F42/100)))+(E106*E100*F43/((1+F24/100)*(1+F42/100))))),0))) -> 1.8951144 | G102: =IF(G100=0,0,IF(G95=1,G39*F100*F107*G43/((1+G24/100)*(1+G42/100)),IF(AND(G95=0,G96=1),(G39*F100*F107*G43/((1+G24/100)*(1+G42/100)))*(1-ABS(G100-F100*G43/((1+G24/100)*(1+G42/100)))/((G39*F100*F107*G43/((1+G24/100)*(1+G42/100)))+(F106*F100*G43/((1+G24/100)*(1+G42/100))))),0))) -> 2.0450272 | H102: =IF(H100=0,0,IF(H95=1,H39*G100*G107*H43/((1+H24/100)*(1+H42/100)),IF(AND(H95=0,H96=1),(H39*G100*G107*H43/((1+H24/100)*(1+H42/100)))*(1-ABS(H100-G100*H43/((1+H24/100)*(1+H42/100)))/((H39*G100*G107*H43/((1+H24/100)*(1+H42/100)))+(G106*G100*H43/((1+H24/100)*(1+H42/100))))),0))) -> 2.1356735 | I102: =IF(I100=0,0,IF(I95=1,I39*H100*H107*I43/((1+I24/100)*(1+I42/100)),IF(AND(I95=0,I96=1),(I39*H100*H107*I43/((1+I24/100)*(1+I42/100)))*(1-ABS(I100-H100*I43/((1+I24/100)*(1+I42/100)))/((I39*H100*H107*I43/((1+I24/100)*(1+I42/100)))+(H106*H100*I43/((1+I24/100)*(1+I42/100))))),0))) -> 2.2054689 | J102: =IF(J100=0,0,IF(J95=1,J39*I100*I107*J43/((1+J24/100)*(1+J42/100)),IF(AND(J95=0,J96=1),(J39*I100*I107*J43/((1+J24/100)*(1+J42/100)))*(1-ABS(J100-I100*J43/((1+J24/100)*(1+J42/100)))/((J39*I100*I107*J43/((1+J24/100)*(1+J42/100)))+(I106*I100*J43/((1+J24/100)*(1+J42/100))))),0))) -> 2.2581918 | K102: =IF(K100=0,0,IF(K95=1,K39*J100*J107*K43/((1+K24/100)*(1+K42/100)),IF(AND(K95=0,K96=1),(K39*J100*J107*K43/((1+K24/100)*(1+K42/100)))*(1-ABS(K100-J100*K43/((1+K24/100)*(1+K42/100)))/((K39*J100*J107*K43/((1+K24/100)*(1+K42/100)))+(J106*J100*K43/((1+K24/100)*(1+K42/100))))),0))) -> 2.2819629 | L102: =IF(L100=0,0,IF(L95=1,L39*K100*K107*L43/((1+L24/100)*(1+L42/100)),IF(AND(L95=0,L96=1),(L39*K100*K107*L43/((1+L24/100)*(1+L42/100)))*(1-ABS(L100-K100*L43/((1+L24/100)*(1+L42/100)))/((L39*K100*K107*L43/((1+L24/100)*(1+L42/100)))+(K106*K100*L43/((1+L24/100)*(1+L42/100))))),0))) -> 2.2989925 | ... W102: =IF(W100=0,0,IF(W95=1,W39*V100*V107*W43/((1+W24/100)*(1+W42/100)),IF(AND(W95=0,W96=1),(W39*V100*V107*W43/((1+W24/100)*(1+W42/100)))*(1-ABS(W100-V100*W43/((1+W24/100)*(1+W42/100)))/((W39*V100*V107*W43/((1+W24/100)*(1+W42/100)))+(V106*V100*W43/((1+W24/100)*(1+W42/100))))),0))) -> 2.2896075
B103: Rolled over short-term debt | D103: ='Input data'!C68*$D$100 -> 6.7592062 | E103: =IF(E100=0,0,IF(E95=1,(1-D107)*D100*E43/((1+E24/100)*(1+E42/100)),IF(AND(E95=0,E96=1),(D106*D100*E43/((1+E24/100)*(1+E42/100)))*(1-ABS(E100-D100*E43/((1+E24/100)*(1+E42/100)))/((E39*D100*D107*E43/((1+E24/100)*(1+E42/100)))+(D106*D100*E43/((1+E24/100)*(1+E42/100))))),0))) -> 6.6210824 | F103: =IF(F100=0,0,IF(F95=1,(1-E107)*E100*F43/((1+F24/100)*(1+F42/100)),IF(AND(F95=0,F96=1),(E106*E100*F43/((1+F24/100)*(1+F42/100)))*(1-ABS(F100-E100*F43/((1+F24/100)*(1+F42/100)))/((F39*E100*E107*F43/((1+F24/100)*(1+F42/100)))+(E106*E100*F43/((1+F24/100)*(1+F42/100))))),0))) -> 6.5851097 | G103: =IF(G100=0,0,IF(G95=1,(1-F107)*F100*G43/((1+G24/100)*(1+G42/100)),IF(AND(G95=0,G96=1),(F106*F100*G43/((1+G24/100)*(1+G42/100)))*(1-ABS(G100-F100*G43/((1+G24/100)*(1+G42/100)))/((G39*F100*F107*G43/((1+G24/100)*(1+G42/100)))+(F106*F100*G43/((1+G24/100)*(1+G42/100))))),0))) -> 6.8193777 | H103: =IF(H100=0,0,IF(H95=1,(1-G107)*G100*H43/((1+H24/100)*(1+H42/100)),IF(AND(H95=0,H96=1),(G106*G100*H43/((1+H24/100)*(1+H42/100)))*(1-ABS(H100-G100*H43/((1+H24/100)*(1+H42/100)))/((H39*G100*G107*H43/((1+H24/100)*(1+H42/100)))+(G106*G100*H43/((1+H24/100)*(1+H42/100))))),0))) -> 6.8638214 | I103: =IF(I100=0,0,IF(I95=1,(1-H107)*H100*I43/((1+I24/100)*(1+I42/100)),IF(AND(I95=0,I96=1),(H106*H100*I43/((1+I24/100)*(1+I42/100)))*(1-ABS(I100-H100*I43/((1+I24/100)*(1+I42/100)))/((I39*H100*H107*I43/((1+I24/100)*(1+I42/100)))+(H106*H100*I43/((1+I24/100)*(1+I42/100))))),0))) -> 6.8456859 | J103: =IF(J100=0,0,IF(J95=1,(1-I107)*I100*J43/((1+J24/100)*(1+J42/100)),IF(AND(J95=0,J96=1),(I106*I100*J43/((1+J24/100)*(1+J42/100)))*(1-ABS(J100-I100*J43/((1+J24/100)*(1+J42/100)))/((J39*I100*I107*J43/((1+J24/100)*(1+J42/100)))+(I106*I100*J43/((1+J24/100)*(1+J42/100))))),0))) -> 6.7814751 | K103: =IF(K100=0,0,IF(K95=1,(1-J107)*J100*K43/((1+K24/100)*(1+K42/100)),IF(AND(K95=0,K96=1),(J106*J100*K43/((1+K24/100)*(1+K42/100)))*(1-ABS(K100-J100*K43/((1+K24/100)*(1+K42/100)))/((K39*J100*J107*K43/((1+K24/100)*(1+K42/100)))+(J106*J100*K43/((1+K24/100)*(1+K42/100))))),0))) -> 6.64084 | L103: =IF(L100=0,0,IF(L95=1,(1-K107)*K100*L43/((1+L24/100)*(1+L42/100)),IF(AND(L95=0,L96=1),(K106*K100*L43/((1+L24/100)*(1+L42/100)))*(1-ABS(L100-K100*L43/((1+L24/100)*(1+L42/100)))/((L39*K100*K107*L43/((1+L24/100)*(1+L42/100)))+(K106*K100*L43/((1+L24/100)*(1+L42/100))))),0))) -> 6.4907535 | ... W103: =IF(W100=0,0,IF(W95=1,(1-V107)*V100*W43/((1+W24/100)*(1+W42/100)),IF(AND(W95=0,W96=1),(V106*V100*W43/((1+W24/100)*(1+W42/100)))*(1-ABS(W100-V100*W43/((1+W24/100)*(1+W42/100)))/((W39*V100*V107*W43/((1+W24/100)*(1+W42/100)))+(V106*V100*W43/((1+W24/100)*(1+W42/100))))),0))) -> 5.8313148
B104: New long-term debt | D104: ='Input data'!C69*$D$100 -> 3.6219078 | E104: =IF(E100=0,0,IF(E95=1,'Input data'!$C$58*(E100-D100*E43/((1+E24/100)*(1+E42/100))),0)) -> 3.4471835 | F104: =IF(F100=0,0,IF(F95=1,'Input data'!$C$58*(F100-E100*F43/((1+F24/100)*(1+F42/100))),0)) -> 4.8081473 | G104: =IF(G100=0,0,IF(G95=1,'Input data'!$C$58*(G100-F100*G43/((1+G24/100)*(1+G42/100))),0)) -> 3.6032751 | H104: =IF(H100=0,0,IF(H95=1,'Input data'!$C$58*(H100-G100*H43/((1+H24/100)*(1+H42/100))),0)) -> 3.2103442 | I104: =IF(I100=0,0,IF(I95=1,'Input data'!$C$58*(I100-H100*I43/((1+I24/100)*(1+I42/100))),0)) -> 2.8445359 | J104: =IF(J100=0,0,IF(J95=1,'Input data'!$C$58*(J100-I100*J43/((1+J24/100)*(1+J42/100))),0)) -> 2.4385221 | K104: =IF(K100=0,0,IF(K95=1,'Input data'!$C$58*(K100-J100*K43/((1+K24/100)*(1+K42/100))),0)) -> 2.2575234 | L104: =IF(L100=0,0,IF(L95=1,'Input data'!$C$58*(L100-K100*L43/((1+L24/100)*(1+L42/100))),0)) -> 2.0746639 | ... W104: =IF(W100=0,0,IF(W95=1,'Input data'!$C$58*(W100-V100*W43/((1+W24/100)*(1+W42/100))),0)) -> 2.2195436
B105: New short-term debt | D105: ='Input data'!C70*$D$100 -> 0.60234756 | E105: =IF(E100=0,0,IF(E95=1,'Input data'!$C$57*(E100-D100*E43/((1+E24/100)*(1+E42/100))),0)) -> 0.51593593 | F105: =IF(F100=0,0,IF(F95=1,'Input data'!$C$57*(F100-E100*F43/((1+F24/100)*(1+F42/100))),0)) -> 0.71962979 | G105: =IF(G100=0,0,IF(G95=1,'Input data'!$C$57*(G100-F100*G43/((1+G24/100)*(1+G42/100))),0)) -> 0.53929797 | H105: =IF(H100=0,0,IF(H95=1,'Input data'!$C$57*(H100-G100*H43/((1+H24/100)*(1+H42/100))),0)) -> 0.48048847 | I105: =IF(I100=0,0,IF(I95=1,'Input data'!$C$57*(I100-H100*I43/((1+I24/100)*(1+I42/100))),0)) -> 0.42573836 | J105: =IF(J100=0,0,IF(J95=1,'Input data'!$C$57*(J100-I100*J43/((1+J24/100)*(1+J42/100))),0)) -> 0.36497075 | K105: =IF(K100=0,0,IF(K95=1,'Input data'!$C$57*(K100-J100*K43/((1+K24/100)*(1+K42/100))),0)) -> 0.33788089 | L105: =IF(L100=0,0,IF(L95=1,'Input data'!$C$57*(L100-K100*L43/((1+L24/100)*(1+L42/100))),0)) -> 0.31051252 | ... W105: =IF(W100=0,0,IF(W95=1,'Input data'!$C$57*(W100-V100*W43/((1+W24/100)*(1+W42/100))),0)) -> 0.3321965
B106: Share of short-term debt in total government debt | D106: ='Baseline NFPC'!$D$93 -> 0.14259267 | E106: =IF(E100<>0,(E103+E105)/(E101+E102+E103+E104+E105),0) -> 0.1416169 | F106: =IF(F100<>0,(F103+F105)/(F101+F102+F103+F104+F105),0) -> 0.14040221 | G106: =IF(G100<>0,(G103+G105)/(G101+G102+G103+G104+G105),0) -> 0.13959921 | H106: =IF(H100<>0,(H103+H105)/(H101+H102+H103+H104+H105),0) -> 0.13894182 | I106: =IF(I100<>0,(I103+I105)/(I101+I102+I103+I104+I105),0) -> 0.13839672 | J106: =IF(J100<>0,(J103+J105)/(J101+J102+J103+J104+J105),0) -> 0.13795229 | K106: =IF(K100<>0,(K103+K105)/(K101+K102+K103+K104+K105),0) -> 0.1375549 | L106: =IF(L100<>0,(L103+L105)/(L101+L102+L103+L104+L105),0) -> 0.13720026 | ... W106: =IF(W100<>0,(W103+W105)/(W101+W102+W103+W104+W105),0) -> 0.13422668
B107: Share of long-term debt in total government debt | D107: ='Baseline NFPC'!$D$94 -> 0.85740733 | E107: =IF(E100<>0,(E101+E102+E104)/(E101+E102+E103+E104+E105),1) -> 0.8583831 | F107: =IF(F100<>0,(F101+F102+F104)/(F101+F102+F103+F104+F105),1) -> 0.85959779 | G107: =IF(G100<>0,(G101+G102+G104)/(G101+G102+G103+G104+G105),1) -> 0.86040079 | H107: =IF(H100<>0,(H101+H102+H104)/(H101+H102+H103+H104+H105),1) -> 0.86105818 | I107: =IF(I100<>0,(I101+I102+I104)/(I101+I102+I103+I104+I105),1) -> 0.86160328 | J107: =IF(J100<>0,(J101+J102+J104)/(J101+J102+J103+J104+J105),1) -> 0.86204771 | K107: =IF(K100<>0,(K101+K102+K104)/(K101+K102+K103+K104+K105),1) -> 0.8624451 | L107: =IF(L100<>0,(L101+L102+L104)/(L101+L102+L103+L104+L105),1) -> 0.86279974 | ... W107: =IF(W100<>0,(W101+W102+W104)/(W101+W102+W103+W104+W105),1) -> 0.86577332
B109: IIR | C109: ='Baseline NFPC'!C96 -> 2.40894 | D109: ='Baseline NFPC'!D96 -> 1.98347 | E109: ='Baseline NFPC'!E96 -> 2.37675 | F109: ='Baseline NFPC'!F96 -> 2.749095 | G109: ='Baseline NFPC'!G96 -> 2.738361 | H109: =H111 -> 2.82879 | I109: =I111 -> 2.9113734 | J109: =J111 -> 2.9880994 | K109: =K111 -> 3.059409 | L109: =L111 -> 3.1293648 | M109: =M111 -> 3.1980675 | N109: =N111 -> 3.2656344 | O109: =O111 -> 3.3342651 | ... W109: =W111 -> 3.6452522
B110: Long-term implicit interest rate | E110: =((E36*D100)-(E38*(D103+D105)))/(D101+D102+D104) -> 2.2015877 | F110: =((F36*E100)-(F38*(E103+E105)))/(E101+E102+E104) -> 2.6146168 | G110: =((G36*F100)-(G38*(F103+F105)))/(F101+F102+F104) -> 2.7256186 | H110: =IF(G100>0,(G110*G101+H37*(G104+G102))/(G101+G102+G104),H37) -> 2.8326354 | I110: =IF(H100>0,(H110*H101+I37*(H104+H102))/(H101+H102+H104),I37) -> 2.9303447 | J110: =IF(I100>0,(I110*I101+J37*(I104+I102))/(I101+I102+I104),J37) -> 3.0211213 | K110: =IF(J100>0,(J110*J101+K37*(J104+J102))/(J101+J102+J104),K37) -> 3.1055255 | L110: =IF(K100>0,(K110*K101+L37*(K104+K102))/(K101+K102+K104),L37) -> 3.1882848 | M110: =IF(L100>0,(L110*L101+M37*(L104+L102))/(L101+L102+L104),M37) -> 3.269531 | N110: =IF(M100>0,(M110*M101+N37*(M104+M102))/(M101+M102+M104),N37) -> 3.3494126 | O110: =IF(N100>0,(N110*N101+O37*(N104+N102))/(N101+N102+N104),O37) -> 3.4304707 | ... W110: =IF(V100>0,(V110*V101+W37*(V104+V102))/(V101+V102+V104),W37) -> 3.8331683
B111: Nominal implicit interest rate on debt | E111: =(E110*(D101+D102+D104)+E38*(D103+D105))/D100 -> 2.37675 | F111: =(F110*(E101+E102+E104)+F38*(E103+E105))/E100 -> 2.749095 | G111: =(G110*(F101+F102+F104)+G38*(F103+F105))/F100 -> 2.738361 | H111: =(H110*(G101+G102+G104)+H38*(G103+G105))/G100 -> 2.82879 | I111: =(I110*(H101+H102+H104)+I38*(H103+H105))/H100 -> 2.9113734 | J111: =(J110*(I101+I102+I104)+J38*(I103+I105))/I100 -> 2.9880994 | K111: =(K110*(J101+J102+J104)+K38*(J103+J105))/J100 -> 3.059409 | L111: =(L110*(K101+K102+K104)+L38*(K103+K105))/K100 -> 3.1293648 | ... W111: =(W110*(V101+V102+V104)+W38*(V103+V105))/V100 -> 3.6452522
B113: (i - g) | C113: =((1+C109/100)/((1+C24/100)*(1+C42/100))-1)*100 -> -10.770397 | D113: =((1+D109/100)/((1+D24/100)*(1+D42/100))-1)*100 -> -10.353607 | E113: =((1+E109/100)/((1+E24/100)*(1+E42/100))-1)*100 -> -7.9209964 | F113: =((1+F109/100)/((1+F24/100)*(1+F42/100))-1)*100 -> -5.1965361 | G113: =((1+G109/100)/((1+G24/100)*(1+G42/100))-1)*100 -> -4.0880563 | H113: =((1+H109/100)/((1+H24/100)*(1+H42/100))-1)*100 -> -4.0862133 | I113: =((1+I109/100)/((1+I24/100)*(1+I42/100))-1)*100 -> -4.0755432 | J113: =((1+J109/100)/((1+J24/100)*(1+J42/100))-1)*100 -> -3.9512471 | ... W113: =((1+W109/100)/((1+W24/100)*(1+W42/100))-1)*100 -> -1.0590372

Sheet Adjust. no safeguard
B3: Country | C3: ='Input data'!C3 -> MT
B4: Key years
B5: ='Input data'!B5 -> Last year before the adjustment | C5: =+'Input data'!C5 -> 2024
B6: Last year of adjustment | C6: =+C5+'Criteria results'!$F$5 -> 2028
B7: Last year of no-fiscal-policy-change projections | C7: =C5+'Criteria results'!$F$5+10 -> 2038
B9: Key assumptions
C10: 2021 | D10: 2022 | E10: 2023 | F10: 2024 | G10: 2025 | H10: 2026 | I10: 2027 | J10: 2028 | K10: 2029 | L10: 2030 | M10: 2031 | N10: 2032 | O10: 2033 | P10: 2034 | Q10: 2035 | R10: 2036 | S10: 2037 | T10: 2038 | U10: 2039 | V10: 2040 | W10: 2041
B11: Fiscal assumptions (% of GDP)
B12: Structural primary balance ('+' means 'surplus') | C12: ='Input data'!C13 -> -5.650948 | D12: ='Input data'!D13 -> -4.355204 | E12: ='Input data'!E13 -> -3.790994 | F12: ='Input data'!F13 -> -2.897243 | G12: =IF(G10<=$C$6,F12+'Criteria results'!$F$6,F12) -> -2.457243 | H12: =IF(H10<=$C$6,G12+'Criteria results'!$F$6,G12) -> -2.017243 | I12: =IF(I10<=$C$6,H12+'Criteria results'!$F$6,H12) -> -1.577243 | J12: =IF(J10<=$C$6,I12+'Criteria results'!$F$6,I12) -> -1.137243 | K12: =IF(K10<=$C$6,J12+'Criteria results'!$F$6,J12) -> -1.137243 | L12: =IF(L10<=$C$6,K12+'Criteria results'!$F$6,K12) -> -1.137243 | M12: =IF(M10<=$C$6,L12+'Criteria results'!$F$6,L12) -> -1.137243 | N12: =M12 -> -1.137243 | O12: =N12 -> -1.137243 | P12: =O12 -> -1.137243 | Q12: =P12 -> -1.137243 | R12: =Q12 -> -1.137243 | S12: =R12 -> -1.137243 | T12: =S12 -> -1.137243 | U12: =T12 -> -1.137243 | ... W12: =V12 -> -1.137243
B13: Annual change in SPB | G13: =G12-F12 -> 0.44 | H13: =H12-G12 -> 0.44 | I13: =I12-H12 -> 0.44 | J13: =J12-I12 -> 0.44 | K13: =K12-J12 -> 0 | L13: =L12-K12 -> 0 | M13: =M12-L12 -> 0 | N13: =N12-M12 -> 0 | ... W13: =W12-V12 -> 0
B14: One-off and other temporary measures | C14: ='Input data'!C14 -> 0 | D14: ='Input data'!D14 -> 0 | E14: ='Input data'!E14 -> 0 | F14: ='Input data'!F14 -> 0 | G14: ='Input data'!G14 -> 0 | H14: =0 -> 0 | I14: =0 -> 0 | J14: =0 -> 0 | K14: =0 -> 0 | L14: =0 -> 0 | M14: =0 -> 0 | N14: =0 -> 0 | O14: =0 -> 0 | ... W14: =0 -> 0
B15: Stock flow adjustments (without exchange rate effect) | C15: ='Input data'!C15 -> 0.8044612 | D15: ='Input data'!D15 -> -1.310275 | E15: ='Input data'!E15 -> -0.9404473 | F15: ='Input data'!F15 -> 1.185197 | G15: ='Input data'!G15 -> 0.0667276 | H15: ='Input data'!H15 -> 0 | I15: ='Input data'!I15 -> 0 | J15: ='Input data'!J15 -> 0 | ... W15: ='Input data'!W15 -> 0
B17: ='Input data'!B19 -> Cost of ageing and selected public revenue (based on the Commission-Council 2024 Ageing Report ("AR 2024"))
B18: Total ageing cost (net of taxes on pensions) | C18: ='Input data'!C20 -> 0 | D18: ='Input data'!D20 -> 16.93779 | E18: ='Input data'!E20 -> 16.70416 | F18: ='Input data'!F20 -> 16.66552 | G18: ='Input data'!G20 -> 16.60096 | H18: ='Input data'!H20 -> 16.33519 | I18: ='Input data'!I20 -> 16.23882 | J18: ='Input data'!J20 -> 16.15621 | ... W18: ='Input data'!W20 -> 16.22383
B19: Property income | C19: ='Input data'!C26 -> 0.5214214 | D19: ='Input data'!D26 -> 0.4365457 | E19: ='Input data'!E26 -> 0.4337021 | F19: ='Input data'!F26 -> 0.4308586 | G19: ='Input data'!G26 -> 0.428015 | H19: ='Input data'!H26 -> 0.4251715 | I19: ='Input data'!I26 -> 0.4223279 | J19: ='Input data'!J26 -> 0.4194843 | ... W19: ='Input data'!W26 -> 0.3825183
B21: GDP growth assumptions
B22: Actual GDP (real)
B23: Level | C23: ='Input data'!C31 -> 13.62455 | D23: ='Baseline NFPC'!D22 -> 14.72481 | E23: ='Baseline NFPC'!E22 -> 15.55145 | F23: ='Baseline NFPC'!F22 -> 16.262506 | G23: =IF(AND(G50>1,F50>1),IF(AND(G50>0,F50>0),G27*(G51/100+1),0)+IF(G50>0,F23*(1+G52/100),0)-F23*(1+'Input data'!G30/100),IF(G50=1,G27,F23*(1+G52/100))) -> 16.99679 | H23: =IF(AND(H50>1,G50>1),IF(AND(H50>0,G50>0),H27*(H51/100+1),0)+IF(H50>0,G23*(1+H52/100),0)-G23*(1+'Input data'!H30/100),IF(H50=1,H27,G23*(1+H52/100))) -> 17.776596 | I23: =IF(AND(I50>1,H50>1),IF(AND(I50>0,H50>0),I27*(I51/100+1),0)+IF(I50>0,H23*(1+I52/100),0)-H23*(1+'Input data'!I30/100),IF(I50=1,I27,H23*(1+I52/100))) -> 18.602882 | J23: =IF(AND(J50>1,I50>1),IF(AND(J50>0,I50>0),J27*(J51/100+1),0)+IF(J50>0,I23*(1+J52/100),0)-I23*(1+'Input data'!J30/100),IF(J50=1,J27,I23*(1+J52/100))) -> 19.459574 | K23: =IF(AND(K50>1,J50>1),IF(AND(K50>0,J50>0),K27*(K51/100+1),0)+IF(K50>0,J23*(1+K52/100),0)-J23*(1+'Input data'!K30/100),IF(K50=1,K27,J23*(1+K52/100))) -> 20.413446 | L23: =IF(AND(L50>1,K50>1),IF(AND(L50>0,K50>0),L27*(L51/100+1),0)+IF(L50>0,K23*(1+L52/100),0)-K23*(1+'Input data'!L30/100),IF(L50=1,L27,K23*(1+L52/100))) -> 21.394669 | M23: =IF(AND(M50>1,L50>1),IF(AND(M50>0,L50>0),M27*(M51/100+1),0)+IF(M50>0,L23*(1+M52/100),0)-L23*(1+'Input data'!M30/100),IF(M50=1,M27,L23*(1+M52/100))) -> 22.389392 | N23: =IF(AND(N50>1,M50>1),IF(AND(N50>0,M50>0),N27*(N51/100+1),0)+IF(N50>0,M23*(1+N52/100),0)-M23*(1+'Input data'!N30/100),IF(N50=1,N27,M23*(1+N52/100))) -> 23.323058 | ... W23: =IF(AND(W50>1,V50>1),IF(AND(W50>0,V50>0),W27*(W51/100+1),0)+IF(W50>0,V23*(1+W52/100),0)-V23*(1+'Input data'!W30/100),IF(W50=1,W27,V23*(1+W52/100))) -> 30.672534
B24: Growth rate | C24: =+'Input data'!C30 -> 12.51395 | D24: ='Baseline NFPC'!D23 -> 8.075569 | E24: ='Baseline NFPC'!E23 -> 5.613926 | F24: ='Baseline NFPC'!F23 -> 4.57228 | G24: =100*(G23/F23-1) -> 4.515198 | H24: =100*(H23/G23-1) -> 4.5879579 | I24: =100*(I23/H23-1) -> 4.6481695 | J24: =100*(J23/I23-1) -> 4.6051556 | K24: =100*(K23/J23-1) -> 4.9018155 | L24: =100*(L23/K23-1) -> 4.8067468 | M24: =100*(M23/L23-1) -> 4.6493975 | N24: =100*(N23/M23-1) -> 4.170129 | ... W24: =100*(W23/V23-1) -> 2.369435
B26: Potential GDP (real)
B27: Level | C27: ='Input data'!C34 -> 13.87421 | D27: =+C27*(1+'Input data'!D33/100) -> 14.798696 | E27: =+D27*(1+'Input data'!E33/100) -> 15.55436 | F27: =+E27*(1+'Input data'!F33/100) -> 16.319408 | G27: =+F27*(1+'Input data'!G33/100) -> 17.11401 | H27: =+G27*(1+'Input data'!H33/100) -> 17.914487 | I27: =+H27*(1+'Input data'!I33/100) -> 18.7578 | J27: =+I27*(1+'Input data'!J33/100) -> 19.629039 | K27: =+J27*(1+'Input data'!K33/100) -> 20.531618 | ... W27: =+V27*(1+'Input data'!W33/100) -> 30.672533
B29: Output gap
B30: Output gap | C30: =100*(C23/C27-1) -> -1.7994538 | D30: =100*(D23/D27-1) -> -0.49927084 | E30: =100*(E23/E27-1) -> -0.018709187 | F30: =100*(F23/F27-1) -> -0.34867871 | G30: =100*(G23/G27-1) -> -0.68493816 | H30: =100*(H23/H27-1) -> -0.76972069 | I30: =100*(I23/I27-1) -> -0.82588511 | J30: =100*(J23/J27-1) -> -0.86333851 | ... W30: =100*(W23/W27-1) -> 5.7106968e-06
B32: Actual GDP (nominal, national currency)
B33: Growth rate | C33: =100*((1+C24/100)*(1+C42/100)-1) -> 14.770139 | D33: =100*((1+D24/100)*(1+D42/100)-1) -> 13.761934 | E33: =100*((1+E24/100)*(1+E42/100)-1) -> 11.183599 | F33: =100*((1+F24/100)*(1+F42/100)-1) -> 8.3811611 | G33: =100*((1+G24/100)*(1+G42/100)-1) -> 7.1635201 | H33: =100*((1+H24/100)*(1+H42/100)-1) -> 7.240227 | I33: =100*((1+I24/100)*(1+I42/100)-1) -> 7.3040702 | J33: =100*((1+J24/100)*(1+J42/100)-1) -> 7.2620684 | ... W33: =100*((1+W24/100)*(1+W42/100)-1) -> 4.7546428
B35: Interest rates
B36: Nominal implicit interest rate on debt | C36: ='Input data'!C37 -> 2.40894 | D36: ='Input data'!D37 -> 1.98347 | E36: ='Input data'!E37 -> 2.37675 | F36: ='Input data'!F37 -> 2.749095 | G36: ='Input data'!G37 -> 2.738361 | H36: =H101 -> 2.8292956 | I36: =I101 -> 2.9128598 | J36: =J101 -> 2.9910328 | K36: =K101 -> 3.0645257 | L36: =L101 -> 3.1366702 | M36: =M101 -> 3.2076071 | N36: =N101 -> 3.2774921 | O36: =O101 -> 3.3482015 | ... W36: =W101 -> 3.6603738
B37: Long-term interest rate | D37: ='Input data'!D$39 -> 2.41 | E37: ='Input data'!E$39 -> 3.71 | F37: ='Input data'!F$39 -> 3.497002 | G37: ='Input data'!G$39 -> 3.505358 | H37: =G37+($O$37-$G$37)/($O$10-$G$10) -> 3.584932 | I37: =H37+($O$37-$G$37)/($O$10-$G$10) -> 3.664506 | J37: =I37+($O$37-$G$37)/($O$10-$G$10) -> 3.74408 | K37: =J37+($O$37-$G$37)/($O$10-$G$10) -> 3.823654 | L37: =K37+($O$37-$G$37)/($O$10-$G$10) -> 3.903228 | M37: =L37+($O$37-$G$37)/($O$10-$G$10) -> 3.982802 | N37: =M37+($O$37-$G$37)/($O$10-$G$10) -> 4.062376 | O37: ='Input data'!$C$52 -> 4.14195 | P37: ='Baseline NFPC'!P36 -> 4.1348525 | Q37: ='Baseline NFPC'!Q36 -> 4.127755 | R37: ='Baseline NFPC'!R36 -> 4.1206575 | S37: ='Baseline NFPC'!S36 -> 4.11356 | T37: ='Baseline NFPC'!T36 -> 4.1064625 | U37: ='Baseline NFPC'!U36 -> 4.099365 | V37: ='Baseline NFPC'!V36 -> 4.0922675 | W37: ='Baseline NFPC'!W36 -> 4.08517
B38: Short-term interest rate | D38: ='Input data'!D$38 -> 0.35 | E38: ='Input data'!E$38 -> 3.43 | F38: ='Input data'!F$38 -> 3.564208 | G38: ='Input data'!G$38 -> 2.816375 | H38: =G38+($O$38-$G$38)/($O$10-$G$10) -> 2.8050894 | I38: =H38+($O$38-$G$38)/($O$10-$G$10) -> 2.7938037 | J38: =I38+($O$38-$G$38)/($O$10-$G$10) -> 2.7825181 | K38: =J38+($O$38-$G$38)/($O$10-$G$10) -> 2.7712325 | L38: =K38+($O$38-$G$38)/($O$10-$G$10) -> 2.7599469 | M38: =L38+($O$38-$G$38)/($O$10-$G$10) -> 2.7486612 | N38: =M38+($O$38-$G$38)/($O$10-$G$10) -> 2.7373756 | O38: ='Input data'!$C$53 -> 2.72609 | P38: ='Baseline NFPC'!P37 -> 2.6897855 | Q38: ='Baseline NFPC'!Q37 -> 2.653481 | R38: ='Baseline NFPC'!R37 -> 2.6171765 | S38: ='Baseline NFPC'!S37 -> 2.580872 | T38: ='Baseline NFPC'!T37 -> 2.5445675 | U38: ='Baseline NFPC'!U37 -> 2.508263 | V38: ='Baseline NFPC'!V37 -> 2.4719585 | W38: ='Baseline NFPC'!W37 -> 2.435654
B39: Share of long-term debt that matures every year | C39: ='Baseline NFPC'!C38 -> 0.08190323 | D39: ='Baseline NFPC'!D38 -> 0.001 | E39: ='Baseline NFPC'!E38 -> 0.04901889 | F39: ='Baseline NFPC'!F38 -> 0.04747952 | G39: ='Baseline NFPC'!G38 -> 0.048981602 | H39: ='Baseline NFPC'!H38 -> 0.050483684 | I39: ='Baseline NFPC'!I38 -> 0.051985767 | J39: ='Baseline NFPC'!J38 -> 0.053487849 | ... W39: ='Baseline NFPC'!W38 -> 0.06099826
B41: Inflation and exchange rate
B42: GDP deflator (National currency) | C42: ='Input data'!C42 -> 2.005253 | D42: ='Input data'!D42 -> 5.261471 | E42: ='Input data'!E42 -> 5.273616 | F42: ='Input data'!F42 -> 3.642343 | G42: ='Input data'!G42 -> 2.533911 | H42: ='Baseline NFPC'!H41 -> 2.5359221 | I42: ='Baseline NFPC'!I41 -> 2.5379333 | J42: ='Baseline NFPC'!J41 -> 2.5399444 | K42: ='Baseline NFPC'!K41 -> 2.5419555 | L42: ='Baseline NFPC'!L41 -> 2.5439666 | M42: ='Baseline NFPC'!M41 -> 2.5459777 | N42: ='Baseline NFPC'!N41 -> 2.5479889 | O42: ='Baseline NFPC'!O41 -> 2.55 | ... W42: ='Baseline NFPC'!W41 -> 2.33
B43: Exchange rate composite change (weighted by share of debt in each currency) | C43: ='Baseline NFPC'!C42 -> 1 | D43: ='Baseline NFPC'!D42 -> 1 | E43: ='Baseline NFPC'!E42 -> 1 | F43: ='Baseline NFPC'!F42 -> 1 | G43: ='Baseline NFPC'!G42 -> 0.9999999 | H43: ='Baseline NFPC'!H42 -> 1 | I43: ='Baseline NFPC'!I42 -> 1 | J43: ='Baseline NFPC'!J42 -> 1 | ... W43: ='Baseline NFPC'!W42 -> 1
B45: Intermediate calculations (growth rate equation)
B47: Fiscal multiplier | C47: ='Input data'!C49 -> 0.75
B48: Budget balance semi-elasticity | C48: ='Input data'!C50 -> 0.479
B50: Auxiliary variable to control the closure of the output gap | C50: 0 | D50: =IF(AND(ABS((D12-C12)-('Input data'!D13-'Input data'!C13))>0.0001,ABS(D12-C12)>0.0001,D$10>$C$5),4,IF(C50=4,3,IF(C50=3,2,IF(C50=2,1,0)))) -> 0 | E50: =IF(AND(ABS((E12-D12)-('Input data'!E13-'Input data'!D13))>0.0001,ABS(E12-D12)>0.0001,E$10>$C$5),4,IF(D50=4,3,IF(D50=3,2,IF(D50=2,1,0)))) -> 0 | F50: =IF(AND(ABS((F12-E12)-('Input data'!F13-'Input data'!E13))>0.0001,ABS(F12-E12)>0.0001,F$10>$C$5),4,IF(E50=4,3,IF(E50=3,2,IF(E50=2,1,0)))) -> 0 | G50: =IF(AND(ABS((G12-F12)-('Input data'!G13-'Input data'!F13))>0.0001,ABS(G12-F12)>0.0001,G$10>$C$5),4,IF(F50=4,3,IF(F50=3,2,IF(F50=2,1,0)))) -> 4 | H50: =IF(AND(ABS((H12-G12)-('Input data'!H13-'Input data'!G13))>0.0001,ABS(H12-G12)>0.0001,H$10>$C$5),4,IF(G50=4,3,IF(G50=3,2,IF(G50=2,1,0)))) -> 4 | I50: =IF(AND(ABS((I12-H12)-('Input data'!I13-'Input data'!H13))>0.0001,ABS(I12-H12)>0.0001,I$10>$C$5),4,IF(H50=4,3,IF(H50=3,2,IF(H50=2,1,0)))) -> 4 | J50: =IF(AND(ABS((J12-I12)-('Input data'!J13-'Input data'!I13))>0.0001,ABS(J12-I12)>0.0001,J$10>$C$5),4,IF(I50=4,3,IF(I50=3,2,IF(I50=2,1,0)))) -> 4 | K50: =IF(AND(ABS((K12-J12)-('Input data'!K13-'Input data'!J13))>0.0001,ABS(K12-J12)>0.0001,K$10>$C$5),4,IF(J50=4,3,IF(J50=3,2,IF(J50=2,1,0)))) -> 3 | ... W50: =IF(AND(ABS((W12-V12)-('Input data'!W13-'Input data'!V13))>0.0001,ABS(W12-V12)>0.0001,W$10>$C$5),4,IF(V50=4,3,IF(V50=3,2,IF(V50=2,1,0)))) -> 0
B51: OG intermediate auxiliary value | C51: 0 | D51: =IF(C50=4,2/3*C30,IF(C50=3,1/3*B30,0)) -> 0 | E51: =IF(D50=4,2/3*D30,IF(D50=3,1/3*C30,0)) -> 0 | F51: =IF(E50=4,2/3*E30,IF(E50=3,1/3*D30,0)) -> 0 | G51: =IF(F50=4,2/3*F30,IF(F50=3,1/3*E30,0)) -> 0 | H51: =IF(G50=4,2/3*G30,IF(G50=3,1/3*F30,0)) -> -0.45662544 | I51: =IF(H50=4,2/3*H30,IF(H50=3,1/3*G30,0)) -> -0.51314712 | J51: =IF(I50=4,2/3*I30,IF(I50=3,1/3*H30,0)) -> -0.55059007 | K51: =IF(J50=4,2/3*J30,IF(J50=3,1/3*I30,0)) -> -0.575559 | ... W51: =IF(V50=4,2/3*V30,IF(V50=3,1/3*U30,0)) -> 0
B52: GDP intermediate growth rate - only feedback effect and no closure of the OG | D52: ='Input data'!D30-$C$47*((D12-C12)-('Input data'!D13-'Input data'!C13)) -> 8.075569 | E52: ='Input data'!E30-$C$47*((E12-D12)-('Input data'!E13-'Input data'!D13)) -> 5.613926 | F52: ='Input data'!F30-$C$47*((F12-E12)-('Input data'!F13-'Input data'!E13)) -> 4.57228 | G52: ='Input data'!G30-$C$47*((G12-F12)) -> 4.515198 | H52: ='Input data'!H30-$C$47*((H12-G12)) -> 4.477363 | I52: ='Input data'!I30-$C$47*((I12-H12)) -> 4.550684 | J52: ='Input data'!J30-$C$47*((J12-I12)) -> 4.401095 | K52: ='Input data'!K30-$C$47*((K12-J12)) -> 4.59818 | L52: ='Input data'!L30-$C$47*((L12-K12)) -> 4.504259 | M52: ='Input data'!M30-$C$47*((M12-L12)) -> 4.348238 | N52: ='Input data'!N30-$C$47*((N12-M12)) -> 4.170129 | ... W52: ='Input data'!W30-$C$47*((W12-V12)) -> 2.369435
B54: Debt projections
C56: 2021 | D56: 2022 | E56: 2023 | F56: 2024 | G56: 2025 | H56: 2026 | I56: 2027 | J56: 2028 | K56: 2029 | L56: 2030 | M56: 2031 | N56: 2032 | O56: 2033 | P56: 2034 | Q56: 2035 | R56: 2036 | S56: 2037 | T56: 2038 | U56: 2039 | V56: 2040 | W56: 2041
B57: Gross debt | C57: =+'Input data'!C12 -> 53.92565 | D57: =+C57+D58 -> 51.62648 | E57: =+D57+E58 -> 50.396658 | F57: =+E57+F58 -> 52.027241 | G57: =+F57+G58 -> 52.730908 | H57: =+G57+H58 -> 52.947956 | I57: =+H57+I58 -> 52.754005 | J57: =+I57+J58 -> 52.204192 | K57: =+J57+K58 -> 51.372351 | ... W57: =+V57+W58 -> 49.432125
B58: Change in debt (-1+2+3) | D58: =-D59+D67+D72 -> -2.2991703 | E58: =-E59+E67+E72 -> -1.2298213 | F58: =-F59+F67+F72 -> 1.6305821 | G58: =-G59+G67+G72 -> 0.70366735 | H58: =-H59+H67+H72 -> 0.2170477 | I58: =-I59+I67+I72 -> -0.19395013 | J58: =-J59+J67+J72 -> -0.54981352 | K58: =-K59+K67+K72 -> -0.8318406 | ... W58: =-W59+W67+W72 -> 0.73311545
B59: (1) Primary balance (1.1 + 1.2 - 1.3 -1.4 -1.5 - 1.6 -1.7) | D59: =D60+D61-D62-D63-D64-D65-D66 -> -4.5943547 | E59: =E60+E61-E62-E63-E64-E65-E66 -> -3.7999557 | F59: =F60+F61-F62-F63-F64-F65-F66 -> -3.0642601 | G59: =G60+G61-G62-G63-G64-G65-G66 -> -2.7853284 | H59: =H60+H61-H62-H63-H64-H65-H66 -> -2.3859392 | I59: =I60+I61-I62-I63-I64-I65-I66 -> -1.972842 | J59: =J60+J61-J62-J63-J64-J65-J66 -> -1.5507821 | K59: =K60+K61-K62-K63-K64-K65-K66 -> -1.3539293 | ... W59: =W60+W61-W62-W63-W64-W65-W66 -> -1.2418263
B60: (1.1) Structural primary balance (before ageing cost) | D60: =D12 -> -4.355204 | E60: =E12 -> -3.790994 | F60: =F12 -> -2.897243 | G60: =IF(G12="",F60,G12) -> -2.457243 | H60: =IF(H12="",G60,H12) -> -2.017243 | I60: =IF(I12="",H60,I12) -> -1.577243 | J60: =IF(J12="",I60,J12) -> -1.137243 | K60: =IF(K12="",J60,K12) -> -1.137243 | L60: =IF(L12="",K60,L12) -> -1.137243 | M60: =IF(M12="",L60,M12) -> -1.137243 | N60: =IF(N12="",M60,N12) -> -1.137243 | ... W60: =IF(W12="",V60,W12) -> -1.137243
B61: (1.2) Cumulated budgetary effort (in terms of primary balance) | D61: 0 | E61: 0 | F61: 0 | G61: 0 | H61: 0 | I61: 0 | J61: 0 | K61: 0 | L61: 0 | M61: 0 | N61: 0 | O61: 0 | P61: 0 | Q61: 0 | R61: 0 | S61: 0 | T61: 0 | U61: 0 | V61: 0 | W61: 0
B62: (1.3) Cyclical component | D62: =-$C$48*D30 -> 0.23915073 | E62: =-$C$48*E30 -> 0.0089617005 | F62: =-$C$48*F30 -> 0.1670171 | G62: =-$C$48*G30 -> 0.32808538 | H62: =-$C$48*H30 -> 0.36869621 | I62: =-$C$48*I30 -> 0.39559897 | J62: =-$C$48*J30 -> 0.41353914 | K62: =-$C$48*K30 -> 0.27569276 | ... W62: =-$C$48*W30 -> -2.7354238e-06
B63: (1.4) One-off and other temporary measures | D63: =-D14 -> 0 | E63: =-E14 -> 0 | F63: =-F14 -> 0 | G63: =-G14 -> 0 | H63: =-H14 -> 0 | I63: =-I14 -> 0 | J63: =-J14 -> 0 | K63: =-K14 -> 0 | ... W63: =-W14 -> 0
B64: (1.5) Cost of ageing | D64: =IF(D$56<=$C$6,0,HLOOKUP(D$56,'Input data'!$C$9:$BB$26,12,FALSE)-HLOOKUP($C$6,'Input data'!$C$9:$BB$26,12,FALSE)) -> 0 | E64: =IF(E$56<=$C$6,0,HLOOKUP(E$56,'Input data'!$C$9:$BB$26,12,FALSE)-HLOOKUP($C$6,'Input data'!$C$9:$BB$26,12,FALSE)) -> 0 | F64: =IF(F$56<=$C$6,0,HLOOKUP(F$56,'Input data'!$C$9:$BB$26,12,FALSE)-HLOOKUP($C$6,'Input data'!$C$9:$BB$26,12,FALSE)) -> 0 | G64: =IF(G$56<=$C$6,0,HLOOKUP(G$56,'Input data'!$C$9:$BB$26,12,FALSE)-HLOOKUP($C$6,'Input data'!$C$9:$BB$26,12,FALSE)) -> 0 | H64: =IF(H$56<=$C$6,0,HLOOKUP(H$56,'Input data'!$C$9:$BB$26,12,FALSE)-HLOOKUP($C$6,'Input data'!$C$9:$BB$26,12,FALSE)) -> 0 | I64: =IF(I$56<=$C$6,0,HLOOKUP(I$56,'Input data'!$C$9:$BB$26,12,FALSE)-HLOOKUP($C$6,'Input data'!$C$9:$BB$26,12,FALSE)) -> 0 | J64: =IF(J$56<=$C$6,0,HLOOKUP(J$56,'Input data'!$C$9:$BB$26,12,FALSE)-HLOOKUP($C$6,'Input data'!$C$9:$BB$26,12,FALSE)) -> 0 | K64: =IF(K$56<=$C$6,0,HLOOKUP(K$56,'Input data'!$C$9:$BB$26,12,FALSE)-HLOOKUP($C$6,'Input data'!$C$9:$BB$26,12,FALSE)) -> -0.06185 | ... W64: =IF(W$56<=$C$6,0,HLOOKUP(W$56,'Input data'!$C$9:$BB$26,12,FALSE)-HLOOKUP($C$6,'Input data'!$C$9:$BB$26,12,FALSE)) -> 0.06762
B65: (1.6) Property incomes | D65: =IF(D$56<=$C$5,0,-HLOOKUP(D$56,'Input data'!$C$9:$BB$26,18,FALSE)+HLOOKUP($C$6,'Input data'!$C$9:$BB$26,18,FALSE)) -> 0 | E65: =IF(E$56<=$C$5,0,-HLOOKUP(E$56,'Input data'!$C$9:$BB$26,18,FALSE)+HLOOKUP($C$6,'Input data'!$C$9:$BB$26,18,FALSE)) -> 0 | F65: =IF(F$56<=$C$5,0,-HLOOKUP(F$56,'Input data'!$C$9:$BB$26,18,FALSE)+HLOOKUP($C$6,'Input data'!$C$9:$BB$26,18,FALSE)) -> 0 | G65: =IF(G$56<=$C$6,0,-HLOOKUP(G$56,'Input data'!$C$9:$BB$26,18,FALSE)+HLOOKUP($C$6,'Input data'!$C$9:$BB$26,18,FALSE)) -> 0 | H65: =IF(H$56<=$C$6,0,-HLOOKUP(H$56,'Input data'!$C$9:$BB$26,18,FALSE)+HLOOKUP($C$6,'Input data'!$C$9:$BB$26,18,FALSE)) -> 0 | I65: =IF(I$56<=$C$6,0,-HLOOKUP(I$56,'Input data'!$C$9:$BB$26,18,FALSE)+HLOOKUP($C$6,'Input data'!$C$9:$BB$26,18,FALSE)) -> 0 | J65: =IF(J$56<=$C$6,0,-HLOOKUP(J$56,'Input data'!$C$9:$BB$26,18,FALSE)+HLOOKUP($C$6,'Input data'!$C$9:$BB$26,18,FALSE)) -> 0 | K65: =IF(K$56<=$C$6,0,-HLOOKUP(K$56,'Input data'!$C$9:$BB$26,18,FALSE)+HLOOKUP($C$6,'Input data'!$C$9:$BB$26,18,FALSE)) -> 0.0028435 | L65: =IF(L$56<=$C$6,0,-HLOOKUP(L$56,'Input data'!$C$9:$BB$26,18,FALSE)+HLOOKUP($C$6,'Input data'!$C$9:$BB$26,18,FALSE)) -> 0.005687 | M65: =IF(M$56<=$C$6,0,-HLOOKUP(M$56,'Input data'!$C$9:$BB$26,18,FALSE)+HLOOKUP($C$6,'Input data'!$C$9:$BB$26,18,FALSE)) -> 0.0085306 | N65: =IF(N$56<=$C$6,0,-HLOOKUP(N$56,'Input data'!$C$9:$BB$26,18,FALSE)+HLOOKUP($C$6,'Input data'!$C$9:$BB$26,18,FALSE)) -> 0.0113742 | ... W65: =IF(W$56<=$C$6,0,-HLOOKUP(W$56,'Input data'!$C$9:$BB$26,18,FALSE)+HLOOKUP($C$6,'Input data'!$C$9:$BB$26,18,FALSE)) -> 0.036966
B66: (1.7) Revenues | D66: 0 | E66: 0 | F66: 0 | G66: 0 | H66: 0 | I66: 0 | J66: 0 | K66: 0 | L66: 0 | M66: 0 | N66: 0 | O66: 0 | P66: 0 | Q66: 0 | R66: 0 | S66: 0 | T66: 0 | U66: 0 | V66: 0 | W66: 0
B67: (2) Snowball effect (2.1 + 2.2 + 2.3) | D67: =SUM(D68:D71) -> -5.58325 | E67: =SUM(E68:E71) -> -4.089329 | F67: =SUM(F68:F71) -> -2.618877 | G67: =SUM(G68:G71) -> -2.1483854 | H67: =SUM(H68:H71) -> -2.1688915 | I67: =SUM(I68:I71) -> -2.1667921 | J67: =SUM(J68:J71) -> -2.1005957 | K67: =SUM(K68:K71) -> -2.1857699 | ... W67: =SUM(W68:W71) -> -0.50871081
B68: (2.1) Interest expenditure | D68: =C57*D36/100*(1/(1+D33/100)) -> 0.94020825 | E68: =D57*E36/100*(1/(1+E33/100)) -> 1.1036091 | F68: =E57*F36/100*(1/(1+F33/100)) -> 1.2783144 | G68: =F57*G36/100*(1/(1+G33/100)) -> 1.3294577 | H68: =G57*H36/100*(1/(1+H33/100)) -> 1.3911881 | I68: =H57*I36/100*(1/(1+I33/100)) -> 1.4373171 | J68: =I57*J36/100*(1/(1+J33/100)) -> 1.4710602 | K68: =J57*K36/100*(1/(1+K33/100)) -> 1.4872502 | ... W68: =V57*W36/100*(1/(1+W33/100)) -> 1.701658
B69: (2.2) Growth effect | D69: =-C57*(D24/100)*(1/(1+D33/100)) -> -3.8279967 | E69: =-D57*(E24/100)*(1/(1+E33/100)) -> -2.6067445 | F69: =-E57*(F24/100)*(1/(1+F33/100)) -> -2.1260857 | G69: =-F57*(G24/100)*(1/(1+G33/100)) -> -2.1921013 | H69: =-G57*(H24/100)*(1/(1+H33/100)) -> -2.2559369 | I69: =-H57*(I24/100)*(1/(1+I33/100)) -> -2.2935856 | J69: =-I57*(J24/100)*(1/(1+J33/100)) -> -2.2649237 | K69: =-J57*(K24/100)*(1/(1+K33/100)) -> -2.3789085 | ... W69: =-V57*(W24/100)*(1/(1+W33/100)) -> -1.1015181
B70: (2.3) Inflation effect | D70: =-C57*D42/100*(1/(1+D42/100)) -> -2.6954615 | E70: =-D57*E42/100*(1/(1+E42/100)) -> -2.5861962 | F70: =-E57*F42/100*(1/(1+F42/100)) -> -1.7711093 | G70: =-F57*G42/100*(1/(1+G42/100)) -> -1.2857444 | H70: =-G57*H42/100*(1/(1+H42/100)) -> -1.3041427 | I70: =-H57*I42/100*(1/(1+I42/100)) -> -1.3105236 | J70: =-I57*J42/100*(1/(1+J42/100)) -> -1.3067321 | K70: =-J57*K42/100*(1/(1+K42/100)) -> -1.2941116 | ... W70: =-V57*W42/100*(1/(1+W42/100)) -> -1.1088507
B71: (2.4) Exchange rate effect linked to the interest rate | D71: ='Baseline NFPC'!D70 -> -3.7714402e-08 | E71: ='Baseline NFPC'!E70 -> 2.6165035e-06 | F71: ='Baseline NFPC'!F70 -> 3.5287289e-06 | G71: ='Baseline NFPC'!G70 -> 2.5290586e-06 | H71: 0 | I71: 0 | J71: 0 | K71: 0 | L71: 0 | M71: 0 | N71: 0 | O71: 0 | P71: 0 | Q71: 0 | R71: 0 | S71: 0 | T71: 0 | U71: 0 | V71: 0 | W71: 0
B72: (3 ) Stock flow adjustments (3.1 + 3.2) | D72: ='Input data'!D16 -> -1.310275 | E72: ='Input data'!E16 -> -0.940448 | F72: ='Input data'!F16 -> 1.185199 | G72: ='Input data'!G16 -> 0.0667244 | H72: ='Input data'!H16 -> 0 | I72: ='Input data'!I16 -> 0 | J72: ='Input data'!J16 -> 0 | K72: ='Input data'!K16 -> 0 | ... W72: ='Input data'!W16 -> 0
B73: (3.1) Base | D73: =D15 -> -1.310275 | E73: =E15 -> -0.9404473 | F73: =F15 -> 1.185197 | G73: =G15 -> 0.0667276 | H73: =H15 -> 0 | I73: =I15 -> 0 | J73: =J15 -> 0 | K73: =K15 -> 0 | ... W73: =W15 -> 0
B74: (3.2) Adjustment due to the exchange rate effect linked to debt value | D74: =+D72-D73 -> 0 | E74: =+E72-E73 -> -7e-07 | F74: =+F72-F73 -> 2e-06 | G74: =+G72-G73 -> -3.2e-06 | H74: =+H72-H73 -> 0 | I74: =+I72-I73 -> 0 | J74: =+J72-J73 -> 0 | K74: =+K72-K73 -> 0 | ... W74: =+W72-W73 -> 0
B76: Other budgetary variables
B77: Headline balance | D77: =D59-D68 -> -5.534563 | E77: =E59-E68 -> -4.9035648 | F77: =F59-F68 -> -4.3425745 | G77: =G59-G68 -> -4.1147861 | H77: =H59-H68 -> -3.7771273 | I77: =I59-I68 -> -3.410159 | J77: =J59-J68 -> -3.0218423 | K77: =K59-K68 -> -2.8411795 | ... W77: =W59-W68 -> -2.9434843
B78: Structural balance | D78: =D60-D68-D64-D65-D66 -> -5.2954123 | E78: =E60-E68-E64-E65-E66 -> -4.8946031 | F78: =F60-F68-F64-F65-F66 -> -4.1755574 | G78: =G60-G68-G64-G65-G66 -> -3.7867007 | H78: =H60-H68-H64-H65-H66 -> -3.4084311 | I78: =I60-I68-I64-I65-I66 -> -3.0145601 | J78: =J60-J68-J64-J65-J66 -> -2.6083032 | K78: =K60-K68-K64-K65-K66 -> -2.5654867 | ... W78: =W60-W68-W64-W65-W66 -> -2.943487
B79: Net expenditure growth | D79: ='Input data'!D45 -> 13.084528 | E79: ='Input data'!E45 -> 9.2925168 | F79: ='Input data'!F45 -> 5.4768547 | G79: ='Input data'!G33+G42-(G$12-F$12)/'Input data'!$C$64*100 -> 6.2002945 | H79: ='Input data'!H33+H42-(H$12-G$12)/'Input data'!$C$64*100 -> 6.0105597 | I79: ='Input data'!I33+I42-(I$12-H$12)/'Input data'!$C$64*100 -> 6.0426868 | J79: ='Input data'!J33+J42-(J$12-I$12)/'Input data'!$C$64*100 -> 5.9819389 | K79: ='Input data'!K33+K42-(K$12-J$12)/'Input data'!$C$64*100 -> 7.1401375 | L79: ='Input data'!L33+L42-(L$12-K$12)/'Input data'!$C$64*100 -> 7.0482306 | M79: ='Input data'!M33+M42-(M$12-L$12)/'Input data'!$C$64*100 -> 6.8942157 | N79: ='Input data'!N33+N42-(N$12-M$12)/'Input data'!$C$64*100 -> 6.7181139 | ... W79: ='Input data'!W33+W42-(W$12-V$12)/'Input data'!$C$64*100 -> 4.699437
B81: Average net primary expenditure growth | D81: =AVERAGE(OFFSET($G$79,0,0,1,'Criteria results'!F5)) -> 6.05887
B83: Debt decreasing? (For criterion 1) | K83: =IF(K57<J57,0,1) -> 0 | L83: =IF(L57<K57,0,1) -> 0 | M83: =IF(M57<L57,0,1) -> 0 | N83: =IF(N57<M57,0,1) -> 0 | O83: =IF(O57<N57,0,1) -> 0 | P83: =IF(P57<O57,0,1) -> 0 | Q83: =IF(Q57<P57,0,1) -> 0 | R83: =IF(R57<Q57,0,1) -> 0 | ... W83: =IF(W57<V57,0,1) -> 1
B85: Debt decomposition and IIR
B87: Auxiliary variable identifying whether debt is increasing | D87: =IF((D92-C92*D43/((1+D24/100)*(1+D42/100)))>0,1,0) -> 1 | E87: =IF((E92-D92*E43/((1+E24/100)*(1+E42/100)))>0,1,0) -> 1 | F87: =IF((F92-E92*F43/((1+F24/100)*(1+F42/100)))>0,1,0) -> 1 | G87: =IF((G92-F92*G43/((1+G24/100)*(1+G42/100)))>0,1,0) -> 1 | H87: =IF((H92-G92*H43/((1+H24/100)*(1+H42/100)))>0,1,0) -> 1 | I87: =IF((I92-H92*I43/((1+I24/100)*(1+I42/100)))>0,1,0) -> 1 | J87: =IF((J92-I92*J43/((1+J24/100)*(1+J42/100)))>0,1,0) -> 1 | K87: =IF((K92-J92*K43/((1+K24/100)*(1+K42/100)))>0,1,0) -> 1 | ... W87: =IF((W92-V92*W43/((1+W24/100)*(1+W42/100)))>0,1,0) -> 1
B88: Auxiliary variable identifying whether some debt is rolled over even though debt is decreasing | D88: =IF(AND(D87=0,ABS(D92-C92*D43/((1+D24/100)*(1+D42/100)))<((C98*C92*D43/((1+D24/100)*(1+D42/100))+(D39*C92*C99*D43/((1+D24/100)*(1+D42/100)))))),1,0) -> 0 | E88: =IF(AND(E87=0,ABS(E92-D92*E43/((1+E24/100)*(1+E42/100)))<((D98*D92*E43/((1+E24/100)*(1+E42/100))+(E39*D92*D99*E43/((1+E24/100)*(1+E42/100)))))),1,0) -> 0 | F88: =IF(AND(F87=0,ABS(F92-E92*F43/((1+F24/100)*(1+F42/100)))<((E98*E92*F43/((1+F24/100)*(1+F42/100))+(F39*E92*E99*F43/((1+F24/100)*(1+F42/100)))))),1,0) -> 0 | G88: =IF(AND(G87=0,ABS(G92-F92*G43/((1+G24/100)*(1+G42/100)))<((F98*F92*G43/((1+G24/100)*(1+G42/100))+(G39*F92*F99*G43/((1+G24/100)*(1+G42/100)))))),1,0) -> 0 | H88: =IF(AND(H87=0,ABS(H92-G92*H43/((1+H24/100)*(1+H42/100)))<((G98*G92*H43/((1+H24/100)*(1+H42/100))+(H39*G92*G99*H43/((1+H24/100)*(1+H42/100)))))),1,0) -> 0 | I88: =IF(AND(I87=0,ABS(I92-H92*I43/((1+I24/100)*(1+I42/100)))<((H98*H92*I43/((1+I24/100)*(1+I42/100))+(I39*H92*H99*I43/((1+I24/100)*(1+I42/100)))))),1,0) -> 0 | J88: =IF(AND(J87=0,ABS(J92-I92*J43/((1+J24/100)*(1+J42/100)))<((I98*I92*J43/((1+J24/100)*(1+J42/100))+(J39*I92*I99*J43/((1+J24/100)*(1+J42/100)))))),1,0) -> 0 | K88: =IF(AND(K87=0,ABS(K92-J92*K43/((1+K24/100)*(1+K42/100)))<((J98*J92*K43/((1+K24/100)*(1+K42/100))+(K39*J92*J99*K43/((1+K24/100)*(1+K42/100)))))),1,0) -> 0 | ... W88: =IF(AND(W87=0,ABS(W92-V92*W43/((1+W24/100)*(1+W42/100)))<((V98*V92*W43/((1+W24/100)*(1+W42/100))+(W39*V92*V99*W43/((1+W24/100)*(1+W42/100)))))),1,0) -> 0
C91: 2021 | D91: 2022 | E91: 2023 | F91: 2024 | G91: 2025 | H91: 2026 | I91: 2027 | J91: 2028 | K91: 2029 | L91: 2030 | M91: 2031 | N91: 2032 | O91: 2033 | P91: 2034 | Q91: 2035 | R91: 2036 | S91: 2037 | T91: 2038 | U91: 2039 | V91: 2040 | W91: 2041
B92: Gross debt | C92: =C57 -> 53.92565 | D92: =D57 -> 51.62648 | E92: =E57 -> 50.396658 | F92: =F57 -> 52.027241 | G92: =G57 -> 52.730908 | H92: =G92*(1+H106/100)*H43-H60-H61+H62+H63+H64+H65+H66+H72 -> 52.947956 | I92: =H92*(1+I106/100)*I43-I60-I61+I62+I63+I64+I65+I66+I72 -> 52.754005 | J92: =I92*(1+J106/100)*J43-J60-J61+J62+J63+J64+J65+J66+J72 -> 52.204192 | K92: =J92*(1+K106/100)*K43-K60-K61+K62+K63+K64+K65+K66+K72 -> 51.372351 | L92: =K92*(1+L106/100)*L43-L60-L61+L62+L63+L64+L65+L66+L72 -> 50.459214 | M92: =L92*(1+M106/100)*M43-M60-M61+M62+M63+M64+M65+M66+M72 -> 49.500599 | N92: =M92*(1+N106/100)*N43-N60-N61+N62+N63+N64+N65+N66+N72 -> 48.7902 | O92: =N92*(1+O106/100)*O43-O60-O61+O62+O63+O64+O65+O66+O72 -> 48.137985 | ... W92: =V92*(1+W106/100)*W43-W60-W61+W62+W63+W64+W65+W66+W72 -> 49.432125
B93: Of which Outstanding debt | D93: ='Input data'!C66*$D$92 -> 40.602371 | E93: =IF(E92=0,0,IF(E87=1,D92*E43/((1+E24/100)*(1+E42/100))-E94-E95,IF(AND(E87=0,E88=1),(1-D98-E39*D99)*D92*E43/((1+E24/100)*(1+E42/100)),E92))) -> 37.860894 | F93: =IF(F92=0,0,IF(F87=1,E92*F43/((1+F24/100)*(1+F42/100))-F94-F95,IF(AND(F87=0,F88=1),(1-E98-F39*E99)*E92*F43/((1+F24/100)*(1+F42/100)),F92))) -> 38.019239 | G93: =IF(G92=0,0,IF(G87=1,F92*G43/((1+G24/100)*(1+G42/100))-G94-G95,IF(AND(G87=0,G88=1),(1-F98-G39*F99)*F92*G43/((1+G24/100)*(1+G42/100)),G92))) -> 39.688802 | H93: =IF(H92=0,0,IF(H87=1,G92*H43/((1+H24/100)*(1+H42/100))-H94-H95,IF(AND(H87=0,H88=1),(1-G98-H39*G99)*G92*H43/((1+H24/100)*(1+H42/100)),H92))) -> 40.171165 | I93: =IF(I92=0,0,IF(I87=1,H92*I43/((1+I24/100)*(1+I42/100))-I94-I95,IF(AND(I87=0,I88=1),(1-H98-I39*H99)*H92*I43/((1+I24/100)*(1+I42/100)),I92))) -> 40.280137 | J93: =IF(J92=0,0,IF(J87=1,I92*J43/((1+J24/100)*(1+J42/100))-J94-J95,IF(AND(J87=0,J88=1),(1-I98-J39*I99)*I92*J43/((1+J24/100)*(1+J42/100)),J92))) -> 40.110982 | K93: =IF(K92=0,0,IF(K87=1,J92*K43/((1+K24/100)*(1+K42/100))-K94-K95,IF(AND(K87=0,K88=1),(1-J98-K39*J99)*J92*K43/((1+K24/100)*(1+K42/100)),K92))) -> 39.538792 | L93: =IF(L92=0,0,IF(L87=1,K92*L43/((1+L24/100)*(1+L42/100))-L94-L95,IF(AND(L87=0,L88=1),(1-K98-L39*K99)*K92*L43/((1+L24/100)*(1+L42/100)),L92))) -> 38.900599 | ... W93: =IF(W92=0,0,IF(W87=1,V92*W43/((1+W24/100)*(1+W42/100))-W94-W95,IF(AND(W87=0,W88=1),(1-V98-W39*V99)*V92*W43/((1+W24/100)*(1+W42/100)),W92))) -> 37.795692
B94: Rolled over long-term debt | D94: ='Input data'!C67*$D$92 -> 0.040643031 | E94: =IF(E92=0,0,IF(E87=1,E39*D92*D99*E43/((1+E24/100)*(1+E42/100)),IF(AND(E87=0,E88=1),(E39*D92*D99*E43/((1+E24/100)*(1+E42/100)))*(1-ABS(E92-D92*E43/((1+E24/100)*(1+E42/100)))/((E39*D92*D99*E43/((1+E24/100)*(1+E42/100)))+(D98*D92*E43/((1+E24/100)*(1+E42/100))))),0))) -> 1.9515624 | F94: =IF(F92=0,0,IF(F87=1,F39*E92*E99*F43/((1+F24/100)*(1+F42/100)),IF(AND(F87=0,F88=1),(F39*E92*E99*F43/((1+F24/100)*(1+F42/100)))*(1-ABS(F92-E92*F43/((1+F24/100)*(1+F42/100)))/((F39*E92*E99*F43/((1+F24/100)*(1+F42/100)))+(E98*E92*F43/((1+F24/100)*(1+F42/100))))),0))) -> 1.8951144 | G94: =IF(G92=0,0,IF(G87=1,G39*F92*F99*G43/((1+G24/100)*(1+G42/100)),IF(AND(G87=0,G88=1),(G39*F92*F99*G43/((1+G24/100)*(1+G42/100)))*(1-ABS(G92-F92*G43/((1+G24/100)*(1+G42/100)))/((G39*F92*F99*G43/((1+G24/100)*(1+G42/100)))+(F98*F92*G43/((1+G24/100)*(1+G42/100))))),0))) -> 2.0441467 | H94: =IF(H92=0,0,IF(H87=1,H39*G92*G99*H43/((1+H24/100)*(1+H42/100)),IF(AND(H87=0,H88=1),(H39*G92*G99*H43/((1+H24/100)*(1+H42/100)))*(1-ABS(H92-G92*H43/((1+H24/100)*(1+H42/100)))/((H39*G92*G99*H43/((1+H24/100)*(1+H42/100)))+(G98*G92*H43/((1+H24/100)*(1+H42/100))))),0))) -> 2.1358121 | I94: =IF(I92=0,0,IF(I87=1,I39*H92*H99*I43/((1+I24/100)*(1+I42/100)),IF(AND(I87=0,I88=1),(I39*H92*H99*I43/((1+I24/100)*(1+I42/100)))*(1-ABS(I92-H92*I43/((1+I24/100)*(1+I42/100)))/((I39*H92*H99*I43/((1+I24/100)*(1+I42/100)))+(H98*H92*I43/((1+I24/100)*(1+I42/100))))),0))) -> 2.2088211 | J94: =IF(J92=0,0,IF(J87=1,J39*I92*I99*J43/((1+J24/100)*(1+J42/100)),IF(AND(J87=0,J88=1),(J39*I92*I99*J43/((1+J24/100)*(1+J42/100)))*(1-ABS(J92-I92*J43/((1+J24/100)*(1+J42/100)))/((J39*I92*I99*J43/((1+J24/100)*(1+J42/100)))+(I98*I92*J43/((1+J24/100)*(1+J42/100))))),0))) -> 2.2666906 | K94: =IF(K92=0,0,IF(K87=1,K39*J92*J99*K43/((1+K24/100)*(1+K42/100)),IF(AND(K87=0,K88=1),(K39*J92*J99*K43/((1+K24/100)*(1+K42/100)))*(1-ABS(K92-J92*K43/((1+K24/100)*(1+K42/100)))/((K39*J92*J99*K43/((1+K24/100)*(1+K42/100)))+(J98*J92*K43/((1+K24/100)*(1+K42/100))))),0))) -> 2.3007537 | L94: =IF(L92=0,0,IF(L87=1,L39*K92*K99*L43/((1+L24/100)*(1+L42/100)),IF(AND(L87=0,L88=1),(L39*K92*K99*L43/((1+L24/100)*(1+L42/100)))*(1-ABS(L92-K92*L43/((1+L24/100)*(1+L42/100)))/((L39*K92*K99*L43/((1+L24/100)*(1+L42/100)))+(K98*K92*L43/((1+L24/100)*(1+L42/100))))),0))) -> 2.3291516 | ... W94: =IF(W92=0,0,IF(W87=1,W39*V92*V99*W43/((1+W24/100)*(1+W42/100)),IF(AND(W87=0,W88=1),(W39*V92*V99*W43/((1+W24/100)*(1+W42/100)))*(1-ABS(W92-V92*W43/((1+W24/100)*(1+W42/100)))/((W39*V92*V99*W43/((1+W24/100)*(1+W42/100)))+(V98*V92*W43/((1+W24/100)*(1+W42/100))))),0))) -> 2.4552366
B95: Rolled over short-term debt | D95: ='Input data'!C68*$D$92 -> 6.7592062 | E95: =IF(E92=0,0,IF(E87=1,(1-D99)*D92*E43/((1+E24/100)*(1+E42/100)),IF(AND(E87=0,E88=1),(D98*D92*E43/((1+E24/100)*(1+E42/100)))*(1-ABS(E92-D92*E43/((1+E24/100)*(1+E42/100)))/((E39*D92*D99*E43/((1+E24/100)*(1+E42/100)))+(D98*D92*E43/((1+E24/100)*(1+E42/100))))),0))) -> 6.6210824 | F95: =IF(F92=0,0,IF(F87=1,(1-E99)*E92*F43/((1+F24/100)*(1+F42/100)),IF(AND(F87=0,F88=1),(E98*E92*F43/((1+F24/100)*(1+F42/100)))*(1-ABS(F92-E92*F43/((1+F24/100)*(1+F42/100)))/((F39*E92*E99*F43/((1+F24/100)*(1+F42/100)))+(E98*E92*F43/((1+F24/100)*(1+F42/100))))),0))) -> 6.5851097 | G95: =IF(G92=0,0,IF(G87=1,(1-F99)*F92*G43/((1+G24/100)*(1+G42/100)),IF(AND(G87=0,G88=1),(F98*F92*G43/((1+G24/100)*(1+G42/100)))*(1-ABS(G92-F92*G43/((1+G24/100)*(1+G42/100)))/((G39*F92*F99*G43/((1+G24/100)*(1+G42/100)))+(F98*F92*G43/((1+G24/100)*(1+G42/100))))),0))) -> 6.8164415 | H95: =IF(H92=0,0,IF(H87=1,(1-G99)*G92*H43/((1+H24/100)*(1+H42/100)),IF(AND(H87=0,H88=1),(G98*G92*H43/((1+H24/100)*(1+H42/100)))*(1-ABS(H92-G92*H43/((1+H24/100)*(1+H42/100)))/((H39*G92*G99*H43/((1+H24/100)*(1+H42/100)))+(G98*G92*H43/((1+H24/100)*(1+H42/100))))),0))) -> 6.8638511 | I95: =IF(I92=0,0,IF(I87=1,(1-H99)*H92*I43/((1+I24/100)*(1+I42/100)),IF(AND(I87=0,I88=1),(H98*H92*I43/((1+I24/100)*(1+I42/100)))*(1-ABS(I92-H92*I43/((1+I24/100)*(1+I42/100)))/((I39*H92*H99*I43/((1+I24/100)*(1+I42/100)))+(H98*H92*I43/((1+I24/100)*(1+I42/100))))),0))) -> 6.854888 | J95: =IF(J92=0,0,IF(J87=1,(1-I99)*I92*J43/((1+J24/100)*(1+J42/100)),IF(AND(J87=0,J88=1),(I98*I92*J43/((1+J24/100)*(1+J42/100)))*(1-ABS(J92-I92*J43/((1+J24/100)*(1+J42/100)))/((J39*I92*I99*J43/((1+J24/100)*(1+J42/100)))+(I98*I92*J43/((1+J24/100)*(1+J42/100))))),0))) -> 6.8046768 | K95: =IF(K92=0,0,IF(K87=1,(1-J99)*J92*K43/((1+K24/100)*(1+K42/100)),IF(AND(K87=0,K88=1),(J98*J92*K43/((1+K24/100)*(1+K42/100)))*(1-ABS(K92-J92*K43/((1+K24/100)*(1+K42/100)))/((K39*J92*J99*K43/((1+K24/100)*(1+K42/100)))+(J98*J92*K43/((1+K24/100)*(1+K42/100))))),0))) -> 6.6916261 | L95: =IF(L92=0,0,IF(L87=1,(1-K99)*K92*L43/((1+L24/100)*(1+L42/100)),IF(AND(L87=0,L88=1),(K98*K92*L43/((1+L24/100)*(1+L42/100)))*(1-ABS(L92-K92*L43/((1+L24/100)*(1+L42/100)))/((L39*K92*K99*L43/((1+L24/100)*(1+L42/100)))+(K98*K92*L43/((1+L24/100)*(1+L42/100))))),0))) -> 6.5704906 | ... W95: =IF(W92=0,0,IF(W87=1,(1-V99)*V92*W43/((1+W24/100)*(1+W42/100)),IF(AND(W87=0,W88=1),(V98*V92*W43/((1+W24/100)*(1+W42/100)))*(1-ABS(W92-V92*W43/((1+W24/100)*(1+W42/100)))/((W39*V92*V99*W43/((1+W24/100)*(1+W42/100)))+(V98*V92*W43/((1+W24/100)*(1+W42/100))))),0))) -> 6.237712
B96: New long-term debt | D96: ='Input data'!C69*$D$92 -> 3.6219078 | E96: =IF(E92=0,0,IF(E87=1,'Input data'!$C$58*(E92-D92*E43/((1+E24/100)*(1+E42/100))),0)) -> 3.4471835 | F96: =IF(F92=0,0,IF(F87=1,'Input data'!$C$58*(F92-E92*F43/((1+F24/100)*(1+F42/100))),0)) -> 4.8081473 | G96: =IF(G92=0,0,IF(G87=1,'Input data'!$C$58*(G92-F92*G43/((1+G24/100)*(1+G42/100))),0)) -> 3.6371499 | H96: =IF(H92=0,0,IF(H87=1,'Input data'!$C$58*(H92-G92*H43/((1+H24/100)*(1+H42/100))),0)) -> 3.2854046 | I96: =IF(I92=0,0,IF(I87=1,'Input data'!$C$58*(I92-H92*I43/((1+I24/100)*(1+I42/100))),0)) -> 2.9662099 | J96: =IF(J92=0,0,IF(J87=1,'Input data'!$C$58*(J92-I92*J43/((1+J24/100)*(1+J42/100))),0)) -> 2.6284459 | K96: =IF(K92=0,0,IF(K87=1,'Input data'!$C$58*(K92-J92*K43/((1+K24/100)*(1+K42/100))),0)) -> 2.4713025 | L96: =IF(L92=0,0,IF(L87=1,'Input data'!$C$58*(L92-K92*L43/((1+L24/100)*(1+L42/100))),0)) -> 2.3128159 | ... W96: =IF(W92=0,0,IF(W87=1,'Input data'!$C$58*(W92-V92*W43/((1+W24/100)*(1+W42/100))),0)) -> 2.5602888
B97: New short-term debt | D97: ='Input data'!C70*$D$92 -> 0.60234756 | E97: =IF(E92=0,0,IF(E87=1,'Input data'!$C$57*(E92-D92*E43/((1+E24/100)*(1+E42/100))),0)) -> 0.51593593 | F97: =IF(F92=0,0,IF(F87=1,'Input data'!$C$57*(F92-E92*F43/((1+F24/100)*(1+F42/100))),0)) -> 0.71962979 | G97: =IF(G92=0,0,IF(G87=1,'Input data'!$C$57*(G92-F92*G43/((1+G24/100)*(1+G42/100))),0)) -> 0.54436798 | H97: =IF(H92=0,0,IF(H87=1,'Input data'!$C$57*(H92-G92*H43/((1+H24/100)*(1+H42/100))),0)) -> 0.49172267 | I97: =IF(I92=0,0,IF(I87=1,'Input data'!$C$57*(I92-H92*I43/((1+I24/100)*(1+I42/100))),0)) -> 0.44394917 | J97: =IF(J92=0,0,IF(J87=1,'Input data'!$C$57*(J92-I92*J43/((1+J24/100)*(1+J42/100))),0)) -> 0.39339643 | K97: =IF(K92=0,0,IF(K87=1,'Input data'!$C$57*(K92-J92*K43/((1+K24/100)*(1+K42/100))),0)) -> 0.36987696 | L97: =IF(L92=0,0,IF(L87=1,'Input data'!$C$57*(L92-K92*L43/((1+L24/100)*(1+L42/100))),0)) -> 0.34615645 | ... W97: =IF(W92=0,0,IF(W87=1,'Input data'!$C$57*(W92-V92*W43/((1+W24/100)*(1+W42/100))),0)) -> 0.38319544
B98: Share of short-term debt in total government debt | D98: ='Baseline NFPC'!$D$93 -> 0.14259267 | E98: =IF(E92<>0,(E95+E97)/(E93+E94+E95+E96+E97),0) -> 0.1416169 | F98: =IF(F92<>0,(F95+F97)/(F93+F94+F95+F96+F97),0) -> 0.14040221 | G98: =IF(G92<>0,(G95+G97)/(G93+G94+G95+G96+G97),0) -> 0.13959194 | H98: =IF(H92<>0,(H95+H97)/(H93+H94+H95+H96+H97),0) -> 0.13892083 | I98: =IF(I92<>0,(I95+I97)/(I93+I94+I95+I96+I97),0) -> 0.13835607 | J98: =IF(J92<>0,(J95+J97)/(J93+J94+J95+J96+J97),0) -> 0.13788305 | K98: =IF(K92<>0,(K95+K97)/(K93+K94+K95+K96+K97),0) -> 0.13745727 | L98: =IF(L92<>0,(L95+L97)/(L93+L94+L95+L96+L97),0) -> 0.13707401 | ... W98: =IF(W92<>0,(W95+W97)/(W93+W94+W95+W96+W97),0) -> 0.13393936
B99: Share of long-term debt in total government debt | D99: ='Baseline NFPC'!$D$94 -> 0.85740733 | E99: =IF(E92<>0,(E93+E94+E96)/(E93+E94+E95+E96+E97),1) -> 0.8583831 | F99: =IF(F92<>0,(F93+F94+F96)/(F93+F94+F95+F96+F97),1) -> 0.85959779 | G99: =IF(G92<>0,(G93+G94+G96)/(G93+G94+G95+G96+G97),1) -> 0.86040806 | H99: =IF(H92<>0,(H93+H94+H96)/(H93+H94+H95+H96+H97),1) -> 0.86107917 | I99: =IF(I92<>0,(I93+I94+I96)/(I93+I94+I95+I96+I97),1) -> 0.86164393 | J99: =IF(J92<>0,(J93+J94+J96)/(J93+J94+J95+J96+J97),1) -> 0.86211695 | K99: =IF(K92<>0,(K93+K94+K96)/(K93+K94+K95+K96+K97),1) -> 0.86254273 | L99: =IF(L92<>0,(L93+L94+L96)/(L93+L94+L95+L96+L97),1) -> 0.86292599 | ... W99: =IF(W92<>0,(W93+W94+W96)/(W93+W94+W95+W96+W97),1) -> 0.86606064
B101: IIR | C101: ='Baseline NFPC'!C96 -> 2.40894 | D101: ='Baseline NFPC'!D96 -> 1.98347 | E101: ='Baseline NFPC'!E96 -> 2.37675 | F101: ='Baseline NFPC'!F96 -> 2.749095 | G101: ='Baseline NFPC'!G96 -> 2.738361 | H101: =H103+H104 -> 2.8292956 | I101: =I103+I104 -> 2.9128598 | J101: =J103+J104 -> 2.9910328 | K101: =K103+K104 -> 3.0645257 | L101: =L103+L104 -> 3.1366702 | M101: =M103+M104 -> 3.2076071 | N101: =N103+N104 -> 3.2774921 | O101: =O103+O104 -> 3.3482015 | ... W101: =W103+W104 -> 3.6603738
B102: Long-term implicit interest rate | E102: =((E36*D92)-(E38*(D95+D97)))/(D93+D94+D96) -> 2.2015877 | F102: =((F36*E92)-(F38*(E95+E97)))/(E93+E94+E96) -> 2.6146168 | G102: =((G36*F92)-(G38*(F95+F97)))/(F93+F94+F96) -> 2.7256186 | H102: =IF(G92>0,(G102*G93+H37*(G96+G94))/(G93+G94+G96),H37) -> 2.8332228 | I102: =IF(H92>0,(H102*H93+I37*(H96+H94))/(H93+H94+H96),I37) -> 2.9320675 | J102: =IF(I92>0,(I102*I93+J37*(I96+I94))/(I93+I94+I96),J37) -> 3.0245145 | K102: =IF(J92>0,(J102*J93+K37*(J96+J94))/(J93+J94+J96),K37) -> 3.1114337 | L102: =IF(K92>0,(K102*K93+L37*(K96+K94))/(K93+K94+K96),L37) -> 3.196706 | M102: =IF(L92>0,(L102*L93+M37*(L96+L94))/(L93+L94+L96),M37) -> 3.2805098 | N102: =IF(M92>0,(M102*M93+N37*(M96+M94))/(M93+M94+M96),N37) -> 3.3630381 | O102: =IF(N92>0,(N102*N93+O37*(N96+N94))/(N93+N94+N96),O37) -> 3.4464599 | ... W102: =IF(V92>0,(V102*V93+W37*(V96+V94))/(V93+V94+V96),W37) -> 3.8501694
B103: Nominal implicit interest rate on debt (Excel approximation) | E103: =(E102*(D93+D94+D96)+E38*(D95+D97))/D92 -> 2.37675 | F103: =(F102*(E93+E94+E96)+F38*(E95+E97))/E92 -> 2.749095 | G103: =(G102*(F93+F94+F96)+G38*(F95+F97))/F92 -> 2.738361 | H103: =(H102*(G93+G94+G96)+H38*(G95+G97))/G92 -> 2.8292956 | I103: =(I102*(H93+H94+H96)+I38*(H95+H97))/H92 -> 2.9128598 | J103: =(J102*(I93+I94+I96)+J38*(I95+I97))/I92 -> 2.9910328 | K103: =(K102*(J93+J94+J96)+K38*(J95+J97))/J92 -> 3.0645257 | L103: =(L102*(K93+K94+K96)+L38*(K95+K97))/K92 -> 3.1366702 | ... W103: =(W102*(V93+V94+V96)+W38*(V95+V97))/V92 -> 3.6603738
B104: Diff. STATA | E104: =IF('Criteria results'!$F$5=4,E115,E120) -> 0 | F104: =IF('Criteria results'!$F$5=4,F115,F120) -> 0 | G104: =IF('Criteria results'!$F$5=4,G115,G120) -> 0 | H104: =IF('Criteria results'!$F$5=4,H115,H120) -> 0 | I104: =IF('Criteria results'!$F$5=4,I115,I120) -> 0 | J104: =IF('Criteria results'!$F$5=4,J115,J120) -> 0 | K104: =IF('Criteria results'!$F$5=4,K115,K120) -> 0 | L104: =IF('Criteria results'!$F$5=4,L115,L120) -> 0 | ... W104: =IF('Criteria results'!$F$5=4,W115,W120) -> 0
B106: (i - g) | C106: =((1+C101/100)/((1+C24/100)*(1+C42/100))-1)*100 -> -10.770397 | D106: =((1+D101/100)/((1+D24/100)*(1+D42/100))-1)*100 -> -10.353607 | E106: =((1+E101/100)/((1+E24/100)*(1+E42/100))-1)*100 -> -7.9209964 | F106: =((1+F101/100)/((1+F24/100)*(1+F42/100))-1)*100 -> -5.1965361 | G106: =((1+G101/100)/((1+G24/100)*(1+G42/100))-1)*100 -> -4.1293521 | H106: =((1+H101/100)/((1+H24/100)*(1+H42/100))-1)*100 -> -4.1131314 | I106: =((1+I101/100)/((1+I24/100)*(1+I42/100))-1)*100 -> -4.0923055 | J106: =((1+J101/100)/((1+J24/100)*(1+J42/100))-1)*100 -> -3.9818695 | ... W106: =((1+W101/100)/((1+W24/100)*(1+W42/100))-1)*100 -> -1.044602
B110: Per memo - STATA results
B112: No extension (annual adjustment of 0.44)
B113: Debt | C113: 53.925648 | D113: 51.626442 | E113: 50.396606 | F113: 52.02718 | G113: 52.730839 | H113: 52.947887 | I113: 52.753933 | J113: 52.204117 | K113: 51.372284 | L113: 50.459145 | M113: 49.500549 | N113: 48.790165 | O113: 48.137959 | P113: 47.692822 | Q113: 47.458111 | R113: 47.43869 | S113: 47.534573 | T113: 47.762207 | U113: 48.146076 | V113: 48.699059 | W113: 49.432182
B114: IIR | C114: 2.4089398 | D114: 1.9834704 | E114: 2.3767505 | F114: 2.7490947 | G114: 2.7383611 | H114: 2.8292954 | I114: 2.9128597 | J114: 2.9910326 | K114: 3.0645256 | L114: 3.1366701 | M114: 3.207607 | N114: 3.2774923 | O114: 3.3482018 | P114: 3.4082854 | Q114: 3.4609866 | R114: 3.5071096 | S114: 3.5473466 | T114: 3.582289 | U114: 3.612448 | V114: 3.6383269 | W114: 3.6603739
B115: IIR difference STATA - Excel | E115: 0 | F115: 0 | G115: 0 | H115: 0 | I115: 0 | J115: 0 | K115: 0 | L115: 0 | M115: 0 | N115: 0 | O115: 0 | P115: 0 | Q115: 0 | R115: 0 | S115: 0 | T115: 0 | U115: 0 | V115: 0 | W115: 0
B117: Extension (annual adjustment of 0.28)
B118: Debt | C118: 53.925648 | D118: 51.626442 | E118: 50.396606 | F118: 52.02718 | G118: 52.779011 | H118: 53.18536 | I118: 53.323013 | J118: 53.246349 | K118: 52.95409 | L118: 52.475807 | M118: 51.846275 | N118: 51.122524 | O118: 50.365894 | P118: 49.733654 | Q118: 49.421368 | R118: 49.332935 | S118: 49.363605 | T118: 49.530067 | U118: 49.856987 | V118: 50.356838 | W118: 51.040218
B119: IIR | C119: 2.4089398 | D119: 1.9834704 | E119: 2.3767505 | F119: 2.7490947 | G119: 2.7383611 | H119: 2.830642 | I119: 2.9167967 | J119: 2.9987335 | K119: 3.0771399 | L119: 3.1525538 | M119: 3.2253819 | N119: 3.2959249 | O119: 3.3661091 | P119: 3.4245605 | Q119: 3.4748919 | R119: 3.5189598 | S119: 3.5574172 | T119: 3.5908213 | U119: 3.6196563 | V119: 3.6443968 | W119: 3.6654663
B120: IIR difference STATA - Excel | G120: 0 | H120: 0 | I120: 0 | J120: 0 | K120: 0 | L120: 0 | M120: 0 | N120: 0 | O120: 0 | P120: 0 | Q120: 0 | R120: 0 | S120: 0 | T120: 0 | U120: 0 | V120: 0 | W120: 0

Sheet Financial stress
B3: Country | C3: ='Input data'!C3 -> MT
B4: Key years
B5: ='Input data'!B5 -> Last year before the adjustment | C5: =+'Input data'!C5 -> 2024
B6: Last year of adjustment | C6: =+C5+'Criteria results'!F5 -> 2028
B7: Last year of no-fiscal-policy-change projections | C7: =C5+'Criteria results'!F5+10 -> 2038
B9: Key assumptions
C10: 2021 | D10: 2022 | E10: 2023 | F10: 2024 | G10: 2025 | H10: 2026 | I10: 2027 | J10: 2028 | K10: 2029 | L10: 2030 | M10: 2031 | N10: 2032 | O10: 2033 | P10: 2034 | Q10: 2035 | R10: 2036 | S10: 2037 | T10: 2038 | U10: 2039 | V10: 2040 | W10: 2041
B11: Fiscal assumptions (% of GDP)
B12: Structural primary balance ('+' means 'surplus') | C12: ='Input data'!C13 -> -5.650948 | D12: ='Input data'!D13 -> -4.355204 | E12: ='Input data'!E13 -> -3.790994 | F12: ='Input data'!F13 -> -2.897243 | G12: ='Adjust. no safeguard'!G12 -> -2.457243 | H12: ='Adjust. no safeguard'!H12 -> -2.017243 | I12: ='Adjust. no safeguard'!I12 -> -1.577243 | J12: ='Adjust. no safeguard'!J12 -> -1.137243 | K12: ='Adjust. no safeguard'!K12 -> -1.137243 | L12: ='Adjust. no safeguard'!L12 -> -1.137243 | M12: ='Adjust. no safeguard'!M12 -> -1.137243 | N12: =IF(N10<=$C$6,M12+'Criteria results'!$F$6,M12) -> -1.137243 | O12: =IF(O10<=$C$6,N12+'Criteria results'!$F$6,N12) -> -1.137243 | P12: =IF(P10<=$C$6,O12+'Criteria results'!$F$6,O12) -> -1.137243 | Q12: =IF(Q10<=$C$6,P12+'Criteria results'!$F$6,P12) -> -1.137243 | R12: =IF(R10<=$C$6,Q12+'Criteria results'!$F$6,Q12) -> -1.137243 | S12: =IF(S10<=$C$6,R12+'Criteria results'!$F$6,R12) -> -1.137243 | T12: =IF(T10<=$C$6,S12+'Criteria results'!$F$6,S12) -> -1.137243 | U12: =IF(U10<=$C$6,T12+'Criteria results'!$F$6,T12) -> -1.137243 | ... W12: =IF(W10<=$C$6,V12+'Criteria results'!$F$6,V12) -> -1.137243
B13: One-off and other temporary measures | C13: ='Input data'!C14 -> 0 | D13: ='Input data'!D14 -> 0 | E13: ='Input data'!E14 -> 0 | F13: ='Input data'!F14 -> 0 | G13: ='Input data'!G14 -> 0 | H13: =0 -> 0 | I13: =0 -> 0 | J13: =0 -> 0 | K13: =0 -> 0 | L13: =0 -> 0 | M13: =0 -> 0 | N13: =0 -> 0 | O13: =0 -> 0 | ... W13: =0 -> 0
B14: Stock flow adjustments (without exchange rate effect) | C14: ='Input data'!C15 -> 0.8044612 | D14: ='Input data'!D15 -> -1.310275 | E14: ='Input data'!E15 -> -0.9404473 | F14: ='Input data'!F15 -> 1.185197 | G14: ='Input data'!G15 -> 0.0667276 | H14: ='Input data'!H15 -> 0 | I14: ='Input data'!I15 -> 0 | J14: ='Input data'!J15 -> 0 | ... W14: ='Input data'!W15 -> 0
B16: ='Input data'!B19 -> Cost of ageing and selected public revenue (based on the Commission-Council 2024 Ageing Report ("AR 2024"))
B17: Total ageing cost (net of taxes on pensions) | C17: ='Input data'!C20 -> 0 | D17: ='Input data'!D20 -> 16.93779 | E17: ='Input data'!E20 -> 16.70416 | F17: ='Input data'!F20 -> 16.66552 | G17: ='Input data'!G20 -> 16.60096 | H17: ='Input data'!H20 -> 16.33519 | I17: ='Input data'!I20 -> 16.23882 | J17: ='Input data'!J20 -> 16.15621 | ... W17: ='Input data'!W20 -> 16.22383
B18: Property income | C18: ='Input data'!C26 -> 0.5214214 | D18: ='Input data'!D26 -> 0.4365457 | E18: ='Input data'!E26 -> 0.4337021 | F18: ='Input data'!F26 -> 0.4308586 | G18: ='Input data'!G26 -> 0.428015 | H18: ='Input data'!H26 -> 0.4251715 | I18: ='Input data'!I26 -> 0.4223279 | J18: ='Input data'!J26 -> 0.4194843 | ... W18: ='Input data'!W26 -> 0.3825183
B20: GDP growth assumptions
B21: Actual GDP (real)
B22: Level | C22: ='Input data'!C31 -> 13.62455 | D22: ='Baseline NFPC'!D22 -> 14.72481 | E22: ='Baseline NFPC'!E22 -> 15.55145 | F22: ='Baseline NFPC'!F22 -> 16.262506 | G22: =IF(AND(G49>1,F49>1),IF(AND(G49>0,F49>0),G26*(G50/100+1),0)+IF(G49>0,F22*(1+G51/100),0)-F22*(1+'Input data'!G30/100),IF(G49=1,G26,F22*(1+G51/100))) -> 16.99679 | H22: =IF(AND(H49>1,G49>1),IF(AND(H49>0,G49>0),H26*(H50/100+1),0)+IF(H49>0,G22*(1+H51/100),0)-G22*(1+'Input data'!H30/100),IF(H49=1,H26,G22*(1+H51/100))) -> 17.776596 | I22: =IF(AND(I49>1,H49>1),IF(AND(I49>0,H49>0),I26*(I50/100+1),0)+IF(I49>0,H22*(1+I51/100),0)-H22*(1+'Input data'!I30/100),IF(I49=1,I26,H22*(1+I51/100))) -> 18.602882 | J22: =IF(AND(J49>1,I49>1),IF(AND(J49>0,I49>0),J26*(J50/100+1),0)+IF(J49>0,I22*(1+J51/100),0)-I22*(1+'Input data'!J30/100),IF(J49=1,J26,I22*(1+J51/100))) -> 19.459574 | K22: =IF(AND(K49>1,J49>1),IF(AND(K49>0,J49>0),K26*(K50/100+1),0)+IF(K49>0,J22*(1+K51/100),0)-J22*(1+'Input data'!K30/100),IF(K49=1,K26,J22*(1+K51/100))) -> 20.413446 | L22: =IF(AND(L49>1,K49>1),IF(AND(L49>0,K49>0),L26*(L50/100+1),0)+IF(L49>0,K22*(1+L51/100),0)-K22*(1+'Input data'!L30/100),IF(L49=1,L26,K22*(1+L51/100))) -> 21.394669 | M22: =IF(AND(M49>1,L49>1),IF(AND(M49>0,L49>0),M26*(M50/100+1),0)+IF(M49>0,L22*(1+M51/100),0)-L22*(1+'Input data'!M30/100),IF(M49=1,M26,L22*(1+M51/100))) -> 22.389392 | N22: =IF(AND(N49>1,M49>1),IF(AND(N49>0,M49>0),N26*(N50/100+1),0)+IF(N49>0,M22*(1+N51/100),0)-M22*(1+'Input data'!N30/100),IF(N49=1,N26,M22*(1+N51/100))) -> 23.323058 | ... W22: =IF(AND(W49>1,V49>1),IF(AND(W49>0,V49>0),W26*(W50/100+1),0)+IF(W49>0,V22*(1+W51/100),0)-V22*(1+'Input data'!W30/100),IF(W49=1,W26,V22*(1+W51/100))) -> 30.672534
B23: Growth rate | C23: =+'Input data'!C30 -> 12.51395 | D23: ='Baseline NFPC'!D23 -> 8.075569 | E23: ='Baseline NFPC'!E23 -> 5.613926 | F23: ='Baseline NFPC'!F23 -> 4.57228 | G23: =100*(G22/F22-1) -> 4.515198 | H23: =100*(H22/G22-1) -> 4.5879579 | I23: =100*(I22/H22-1) -> 4.6481695 | J23: =100*(J22/I22-1) -> 4.6051556 | K23: =100*(K22/J22-1) -> 4.9018155 | L23: =100*(L22/K22-1) -> 4.8067468 | M23: =100*(M22/L22-1) -> 4.6493975 | N23: =100*(N22/M22-1) -> 4.170129 | ... W23: =100*(W22/V22-1) -> 2.369435
B25: Potential GDP (real)
B26: Level | C26: ='Input data'!C34 -> 13.87421 | D26: =+C26*(1+'Input data'!D33/100) -> 14.798696 | E26: =+D26*(1+'Input data'!E33/100) -> 15.55436 | F26: =+E26*(1+'Input data'!F33/100) -> 16.319408 | G26: =+F26*(1+'Input data'!G33/100) -> 17.11401 | H26: =+G26*(1+'Input data'!H33/100) -> 17.914487 | I26: =+H26*(1+'Input data'!I33/100) -> 18.7578 | J26: =+I26*(1+'Input data'!J33/100) -> 19.629039 | K26: =+J26*(1+'Input data'!K33/100) -> 20.531618 | ... W26: =+V26*(1+'Input data'!W33/100) -> 30.672533
B28: Output gap
B29: Output gap | C29: =100*(C22/C26-1) -> -1.7994538 | D29: =100*(D22/D26-1) -> -0.49927084 | E29: =100*(E22/E26-1) -> -0.018709187 | F29: =100*(F22/F26-1) -> -0.34867871 | G29: =100*(G22/G26-1) -> -0.68493816 | H29: =100*(H22/H26-1) -> -0.76972069 | I29: =100*(I22/I26-1) -> -0.82588511 | J29: =100*(J22/J26-1) -> -0.86333851 | ... W29: =100*(W22/W26-1) -> 5.7106968e-06
B31: Actual GDP (nominal, national currency)
B32: Growth rate | C32: =100*((1+C23/100)*(1+C41/100)-1) -> 14.770139 | D32: =100*((1+D23/100)*(1+D41/100)-1) -> 13.761934 | E32: =100*((1+E23/100)*(1+E41/100)-1) -> 11.183599 | F32: =100*((1+F23/100)*(1+F41/100)-1) -> 8.3811611 | G32: =100*((1+G23/100)*(1+G41/100)-1) -> 7.1635201 | H32: =100*((1+H23/100)*(1+H41/100)-1) -> 7.240227 | I32: =100*((1+I23/100)*(1+I41/100)-1) -> 7.3040702 | J32: =100*((1+J23/100)*(1+J41/100)-1) -> 7.2620684 | ... W32: =100*((1+W23/100)*(1+W41/100)-1) -> 4.7546428
B34: Interest rates
B35: Nominal implicit interest rate on debt | C35: ='Input data'!C37 -> 2.40894 | D35: ='Input data'!D37 -> 1.98347 | E35: ='Input data'!E37 -> 2.37675 | F35: ='Input data'!F37 -> 2.749095 | G35: ='Input data'!G37 -> 2.738361 | H35: =H92 -> 2.8292956 | I35: =I92 -> 2.9128598 | J35: =J92 -> 2.9910328 | K35: =K92 -> 3.2961778 | L35: =L92 -> 3.2215482 | M35: =M92 -> 3.2838772 | N35: =N92 -> 3.3461031 | O35: =O92 -> 3.409809 | ... W35: =W92 -> 3.6847868
B36: Long-term interest rate | D36: ='Input data'!D$39 -> 2.41 | E36: ='Input data'!E$39 -> 3.71 | F36: ='Input data'!F$39 -> 3.497002 | G36: ='Input data'!G$39 -> 3.505358 | H36: =G36+($O$36-$G$36)/($O$10-$G$10) -> 3.584932 | I36: =H36+($O$36-$G$36)/($O$10-$G$10) -> 3.664506 | J36: =I36+($O$36-$G$36)/($O$10-$G$10) -> 3.74408 | K36: =IF('Criteria results'!$F$5=4,IF(J56>90,G36+('Input data'!$C$52-$G$36)/($O$10-$G$10)*(K10-$G$10)+1+0.06*(J56-90),G36+('Input data'!$C$52-$G$36)/($O$10-$G$10)*(K10-$G$10)+1),G36+('Input data'!$C$52-$G$36)/($O$10-$G$10)*(K10-$G$10)) -> 4.823654 | L36: =$G$36+('Input data'!$C$52-$G$36)/($O$10-$G$10)*(L10-$G$10) -> 3.903228 | M36: =$G$36+('Input data'!$C$52-$G$36)/($O$10-$G$10)*(M10-$G$10) -> 3.982802 | N36: =IF('Criteria results'!$F$5=7,IF(M56>90,G36+('Input data'!$C$52-$G$36)/($O$10-$G$10)*(N10-$G$10)+1+0.06*(M56-90),G36+('Input data'!$C$52-$G$36)/($O$10-$G$10)*(N10-$G$10)+1),G36+('Input data'!$C$52-$G$36)/($O$10-$G$10)*(N10-$G$10)) -> 4.062376 | O36: ='Baseline NFPC'!O36 -> 4.14195 | P36: ='Baseline NFPC'!P36 -> 4.1348525 | Q36: ='Baseline NFPC'!Q36 -> 4.127755 | R36: ='Baseline NFPC'!R36 -> 4.1206575 | S36: ='Baseline NFPC'!S36 -> 4.11356 | T36: ='Baseline NFPC'!T36 -> 4.1064625 | U36: ='Baseline NFPC'!U36 -> 4.099365 | V36: ='Baseline NFPC'!V36 -> 4.0922675 | W36: ='Baseline NFPC'!W36 -> 4.08517
B37: Short-term interest rate | D37: ='Input data'!D$38 -> 0.35 | E37: ='Input data'!E$38 -> 3.43 | F37: ='Input data'!F$38 -> 3.564208 | G37: ='Input data'!G$38 -> 2.816375 | H37: =G37+($O$37-$G$37)/($O$10-$G$10) -> 2.8050894 | I37: =H37+($O$37-$G$37)/($O$10-$G$10) -> 2.7938037 | J37: =I37+($O$37-$G$37)/($O$10-$G$10) -> 2.7825181 | K37: =IF('Criteria results'!$F$5=4,IF(J56>90,G37+('Input data'!$C$53-$G$37)/($O$10-$G$10)*(K10-$G$10)+1+0.06*(J56-90),G37+('Input data'!$C$53-$G$37)/($O$10-$G$10)*(K10-$G$10)+1),G37+('Input data'!$C$53-$G$37)/($O$10-$G$10)*(K10-$G$10)) -> 3.7712325 | L37: =$G$37+('Input data'!$C$53-$G$37)/($O$10-$G$10)*(L10-$G$10) -> 2.7599469 | M37: =$G$37+('Input data'!$C$53-$G$37)/($O$10-$G$10)*(M10-$G$10) -> 2.7486613 | N37: =IF('Criteria results'!$F$5=7,IF(M56>90,G37+('Input data'!$C$53-$G$37)/($O$10-$G$10)*(N10-$G$10)+1+0.06*(M56-90),G37+('Input data'!$C$53-$G$37)/($O$10-$G$10)*(N10-$G$10)+1),G37+('Input data'!$C$53-$G$37)/($O$10-$G$10)*(N10-$G$10)) -> 2.7373756 | O37: ='Baseline NFPC'!O37 -> 2.72609 | P37: ='Baseline NFPC'!P37 -> 2.6897855 | Q37: ='Baseline NFPC'!Q37 -> 2.653481 | R37: ='Baseline NFPC'!R37 -> 2.6171765 | S37: ='Baseline NFPC'!S37 -> 2.580872 | T37: ='Baseline NFPC'!T37 -> 2.5445675 | U37: ='Baseline NFPC'!U37 -> 2.508263 | V37: ='Baseline NFPC'!V37 -> 2.4719585 | W37: ='Baseline NFPC'!W37 -> 2.435654
B38: Share of long-term debt that matures every year | C38: ='Baseline NFPC'!C38 -> 0.08190323 | D38: ='Baseline NFPC'!D38 -> 0.001 | E38: ='Baseline NFPC'!E38 -> 0.04901889 | F38: ='Baseline NFPC'!F38 -> 0.04747952 | G38: ='Baseline NFPC'!G38 -> 0.048981602 | H38: ='Baseline NFPC'!H38 -> 0.050483684 | I38: ='Baseline NFPC'!I38 -> 0.051985767 | J38: ='Baseline NFPC'!J38 -> 0.053487849 | ... W38: ='Baseline NFPC'!W38 -> 0.06099826
B40: Inflation and exchange rate
B41: GDP deflator (National currency) | C41: ='Input data'!C42 -> 2.005253 | D41: ='Input data'!D42 -> 5.261471 | E41: ='Input data'!E42 -> 5.273616 | F41: ='Input data'!F42 -> 3.642343 | G41: ='Input data'!G42 -> 2.533911 | H41: ='Baseline NFPC'!H41 -> 2.5359221 | I41: ='Baseline NFPC'!I41 -> 2.5379333 | J41: ='Baseline NFPC'!J41 -> 2.5399444 | K41: ='Baseline NFPC'!K41 -> 2.5419555 | L41: ='Baseline NFPC'!L41 -> 2.5439666 | M41: ='Baseline NFPC'!M41 -> 2.5459777 | N41: ='Baseline NFPC'!N41 -> 2.5479889 | O41: ='Baseline NFPC'!O41 -> 2.55 | ... W41: ='Baseline NFPC'!W41 -> 2.33
B42: Exchange rate composite change (weighted by share of debt in each currency) | C42: ='Baseline NFPC'!C42 -> 1 | D42: ='Baseline NFPC'!D42 -> 1 | E42: ='Baseline NFPC'!E42 -> 1 | F42: ='Baseline NFPC'!F42 -> 1 | G42: ='Baseline NFPC'!G42 -> 0.9999999 | H42: ='Baseline NFPC'!H42 -> 1 | I42: ='Baseline NFPC'!I42 -> 1 | J42: ='Baseline NFPC'!J42 -> 1 | ... W42: ='Baseline NFPC'!W42 -> 1
B44: Intermediate calculations (growth rate equation)
B46: Fiscal multiplier | C46: ='Input data'!C49 -> 0.75
B47: Budget balance semi-elasticity | C47: ='Input data'!C50 -> 0.479
B49: Auxiliary variable to control the closure of the output gap | C49: 0 | D49: =IF(AND(ABS((D12-C12)-('Input data'!D13-'Input data'!C13))>0.0001,ABS(D12-C12)>0.0001,D$10>$C$5),4,IF(C49=4,3,IF(C49=3,2,IF(C49=2,1,0)))) -> 0 | E49: =IF(AND(ABS((E12-D12)-('Input data'!E13-'Input data'!D13))>0.0001,ABS(E12-D12)>0.0001,E$10>$C$5),4,IF(D49=4,3,IF(D49=3,2,IF(D49=2,1,0)))) -> 0 | F49: =IF(AND(ABS((F12-E12)-('Input data'!F13-'Input data'!E13))>0.0001,ABS(F12-E12)>0.0001,F$10>$C$5),4,IF(E49=4,3,IF(E49=3,2,IF(E49=2,1,0)))) -> 0 | G49: =IF(AND(ABS((G12-F12)-('Input data'!G13-'Input data'!F13))>0.0001,ABS(G12-F12)>0.0001,G$10>$C$5),4,IF(F49=4,3,IF(F49=3,2,IF(F49=2,1,0)))) -> 4 | H49: =IF(AND(ABS((H12-G12)-('Input data'!H13-'Input data'!G13))>0.0001,ABS(H12-G12)>0.0001,H$10>$C$5),4,IF(G49=4,3,IF(G49=3,2,IF(G49=2,1,0)))) -> 4 | I49: =IF(AND(ABS((I12-H12)-('Input data'!I13-'Input data'!H13))>0.0001,ABS(I12-H12)>0.0001,I$10>$C$5),4,IF(H49=4,3,IF(H49=3,2,IF(H49=2,1,0)))) -> 4 | J49: =IF(AND(ABS((J12-I12)-('Input data'!J13-'Input data'!I13))>0.0001,ABS(J12-I12)>0.0001,J$10>$C$5),4,IF(I49=4,3,IF(I49=3,2,IF(I49=2,1,0)))) -> 4 | K49: =IF(AND(ABS((K12-J12)-('Input data'!K13-'Input data'!J13))>0.0001,ABS(K12-J12)>0.0001,K$10>$C$5),4,IF(J49=4,3,IF(J49=3,2,IF(J49=2,1,0)))) -> 3 | ... W49: =IF(AND(ABS((W12-V12)-('Input data'!W13-'Input data'!V13))>0.0001,ABS(W12-V12)>0.0001,W$10>$C$5),4,IF(V49=4,3,IF(V49=3,2,IF(V49=2,1,0)))) -> 0
B50: OG intermediate auxiliary value | C50: 0 | D50: =IF(C49=4,2/3*C29,IF(C49=3,1/3*B29,0)) -> 0 | E50: =IF(D49=4,2/3*D29,IF(D49=3,1/3*C29,0)) -> 0 | F50: =IF(E49=4,2/3*E29,IF(E49=3,1/3*D29,0)) -> 0 | G50: =IF(F49=4,2/3*F29,IF(F49=3,1/3*E29,0)) -> 0 | H50: =IF(G49=4,2/3*G29,IF(G49=3,1/3*F29,0)) -> -0.45662544 | I50: =IF(H49=4,2/3*H29,IF(H49=3,1/3*G29,0)) -> -0.51314712 | J50: =IF(I49=4,2/3*I29,IF(I49=3,1/3*H29,0)) -> -0.55059007 | K50: =IF(J49=4,2/3*J29,IF(J49=3,1/3*I29,0)) -> -0.575559 | ... W50: =IF(V49=4,2/3*V29,IF(V49=3,1/3*U29,0)) -> 0
B51: GDP intermediate growth rate - only feedback effect and no closure of the OG | D51: ='Input data'!D30-$C$46*((D12-C12)-('Input data'!D13-'Input data'!C13)) -> 8.075569 | E51: ='Input data'!E30-$C$46*((E12-D12)-('Input data'!E13-'Input data'!D13)) -> 5.613926 | F51: ='Input data'!F30-$C$46*((F12-E12)-('Input data'!F13-'Input data'!E13)) -> 4.57228 | G51: ='Input data'!G30-$C$46*((G12-F12)) -> 4.515198 | H51: ='Input data'!H30-$C$46*((H12-G12)) -> 4.477363 | I51: ='Input data'!I30-$C$46*((I12-H12)) -> 4.550684 | J51: ='Input data'!J30-$C$46*((J12-I12)) -> 4.401095 | K51: ='Input data'!K30-$C$46*((K12-J12)) -> 4.59818 | L51: ='Input data'!L30-$C$46*((L12-K12)) -> 4.504259 | M51: ='Input data'!M30-$C$46*((M12-L12)) -> 4.348238 | N51: ='Input data'!N30-$C$46*((N12-M12)) -> 4.170129 | ... W51: ='Input data'!W30-$C$46*((W12-V12)) -> 2.369435
B53: Debt projections
C55: 2021 | D55: 2022 | E55: 2023 | F55: 2024 | G55: 2025 | H55: 2026 | I55: 2027 | J55: 2028 | K55: 2029 | L55: 2030 | M55: 2031 | N55: 2032 | O55: 2033 | P55: 2034 | Q55: 2035 | R55: 2036 | S55: 2037 | T55: 2038 | U55: 2039 | V55: 2040 | W55: 2041
B56: Gross debt | C56: =+'Input data'!C12 -> 53.92565 | D56: =+C56+D57 -> 51.62648 | E56: =+D56+E57 -> 50.396658 | F56: =+E56+F57 -> 52.027241 | G56: =+F56+G57 -> 52.730908 | H56: =+G56+H57 -> 52.947956 | I56: =+H56+I57 -> 52.754005 | J56: =+I56+J57 -> 52.204192 | K56: =+J56+K57 -> 51.484775 | ... W56: =+V56+W57 -> 49.758965
B57: Change in debt (-1+2+3) | D57: =-D58+D66+D71 -> -2.2991703 | E57: =-E58+E66+E71 -> -1.2298213 | F57: =-F58+F66+F71 -> 1.6305821 | G57: =-G58+G66+G71 -> 0.70366735 | H57: =-H58+H66+H71 -> 0.2170477 | I57: =-I58+I66+I71 -> -0.19395013 | J57: =-J58+J66+J71 -> -0.54981352 | K57: =-K58+K66+K71 -> -0.71941713 | ... W57: =-W58+W66+W71 -> 0.74120939
B58: (1) Primary balance (1.1 + 1.2 - 1.3 -1.4 -1.5 - 1.6 -1.7) | D58: =D59+D60-D61-D62-D63-D64-D65 -> -4.5943547 | E58: =E59+E60-E61-E62-E63-E64-E65 -> -3.7999557 | F58: =F59+F60-F61-F62-F63-F64-F65 -> -3.0642601 | G58: =G59+G60-G61-G62-G63-G64-G65 -> -2.7853284 | H58: =H59+H60-H61-H62-H63-H64-H65 -> -2.3859392 | I58: =I59+I60-I61-I62-I63-I64-I65 -> -1.972842 | J58: =J59+J60-J61-J62-J63-J64-J65 -> -1.5507821 | K58: =K59+K60-K61-K62-K63-K64-K65 -> -1.3539293 | ... W58: =W59+W60-W61-W62-W63-W64-W65 -> -1.2418263
B59: (1.1) Structural primary balance (before ageing cost) | D59: =D12 -> -4.355204 | E59: =E12 -> -3.790994 | F59: =F12 -> -2.897243 | G59: =IF(G12="",F59,G12) -> -2.457243 | H59: =IF(H12="",G59,H12) -> -2.017243 | I59: =IF(I12="",H59,I12) -> -1.577243 | J59: =IF(J12="",I59,J12) -> -1.137243 | K59: =IF(K12="",J59,K12) -> -1.137243 | L59: =IF(L12="",K59,L12) -> -1.137243 | M59: =IF(M12="",L59,M12) -> -1.137243 | N59: =IF(N12="",M59,N12) -> -1.137243 | ... W59: =IF(W12="",V59,W12) -> -1.137243
B60: (1.2) Cumulated budgetary effort (in terms of primary balance) | D60: 0 | E60: 0 | F60: 0 | G60: 0 | H60: 0 | I60: 0 | J60: 0 | K60: 0 | L60: 0 | M60: 0 | N60: 0 | O60: 0 | P60: 0 | Q60: 0 | R60: 0 | S60: 0 | T60: 0 | U60: 0 | V60: 0 | W60: 0
B61: (1.3) Cyclical component | D61: =-$C$47*D29 -> 0.23915073 | E61: =-$C$47*E29 -> 0.0089617005 | F61: =-$C$47*F29 -> 0.1670171 | G61: =-$C$47*G29 -> 0.32808538 | H61: =-$C$47*H29 -> 0.36869621 | I61: =-$C$47*I29 -> 0.39559897 | J61: =-$C$47*J29 -> 0.41353914 | K61: =-$C$47*K29 -> 0.27569276 | ... W61: =-$C$47*W29 -> -2.7354238e-06
B62: (1.4) One-off and other temporary measures | D62: =-D13 -> 0 | E62: =-E13 -> 0 | F62: =-F13 -> 0 | G62: =-G13 -> 0 | H62: =-H13 -> 0 | I62: =-I13 -> 0 | J62: =-J13 -> 0 | K62: =-K13 -> 0 | ... W62: =-W13 -> 0
B63: (1.5) Cost of ageing | D63: =IF(D$55<=$C$6,0,HLOOKUP(D$55,'Input data'!$C$9:$BB$26,12,FALSE)-HLOOKUP($C$6,'Input data'!$C$9:$BB$26,12,FALSE)) -> 0 | E63: =IF(E$55<=$C$6,0,HLOOKUP(E$55,'Input data'!$C$9:$BB$26,12,FALSE)-HLOOKUP($C$6,'Input data'!$C$9:$BB$26,12,FALSE)) -> 0 | F63: =IF(F$55<=$C$6,0,HLOOKUP(F$55,'Input data'!$C$9:$BB$26,12,FALSE)-HLOOKUP($C$6,'Input data'!$C$9:$BB$26,12,FALSE)) -> 0 | G63: =IF(G$55<=$C$6,0,HLOOKUP(G$55,'Input data'!$C$9:$BB$26,12,FALSE)-HLOOKUP($C$6,'Input data'!$C$9:$BB$26,12,FALSE)) -> 0 | H63: =IF(H$55<=$C$6,0,HLOOKUP(H$55,'Input data'!$C$9:$BB$26,12,FALSE)-HLOOKUP($C$6,'Input data'!$C$9:$BB$26,12,FALSE)) -> 0 | I63: =IF(I$55<=$C$6,0,HLOOKUP(I$55,'Input data'!$C$9:$BB$26,12,FALSE)-HLOOKUP($C$6,'Input data'!$C$9:$BB$26,12,FALSE)) -> 0 | J63: =IF(J$55<=$C$6,0,HLOOKUP(J$55,'Input data'!$C$9:$BB$26,12,FALSE)-HLOOKUP($C$6,'Input data'!$C$9:$BB$26,12,FALSE)) -> 0 | K63: =IF(K$55<=$C$6,0,HLOOKUP(K$55,'Input data'!$C$9:$BB$26,12,FALSE)-HLOOKUP($C$6,'Input data'!$C$9:$BB$26,12,FALSE)) -> -0.06185 | ... W63: =IF(W$55<=$C$6,0,HLOOKUP(W$55,'Input data'!$C$9:$BB$26,12,FALSE)-HLOOKUP($C$6,'Input data'!$C$9:$BB$26,12,FALSE)) -> 0.06762
B64: (1.6) Property incomes | D64: =IF(D$55<=$C$5,0,-HLOOKUP(D$55,'Input data'!$C$9:$BB$26,18,FALSE)+HLOOKUP($C$6,'Input data'!$C$9:$BB$26,18,FALSE)) -> 0 | E64: =IF(E$55<=$C$5,0,-HLOOKUP(E$55,'Input data'!$C$9:$BB$26,18,FALSE)+HLOOKUP($C$6,'Input data'!$C$9:$BB$26,18,FALSE)) -> 0 | F64: =IF(F$55<=$C$5,0,-HLOOKUP(F$55,'Input data'!$C$9:$BB$26,18,FALSE)+HLOOKUP($C$6,'Input data'!$C$9:$BB$26,18,FALSE)) -> 0 | G64: =IF(G$55<=$C$6,0,-HLOOKUP(G$55,'Input data'!$C$9:$BB$26,18,FALSE)+HLOOKUP($C$6,'Input data'!$C$9:$BB$26,18,FALSE)) -> 0 | H64: =IF(H$55<=$C$6,0,-HLOOKUP(H$55,'Input data'!$C$9:$BB$26,18,FALSE)+HLOOKUP($C$6,'Input data'!$C$9:$BB$26,18,FALSE)) -> 0 | I64: =IF(I$55<=$C$6,0,-HLOOKUP(I$55,'Input data'!$C$9:$BB$26,18,FALSE)+HLOOKUP($C$6,'Input data'!$C$9:$BB$26,18,FALSE)) -> 0 | J64: =IF(J$55<=$C$6,0,-HLOOKUP(J$55,'Input data'!$C$9:$BB$26,18,FALSE)+HLOOKUP($C$6,'Input data'!$C$9:$BB$26,18,FALSE)) -> 0 | K64: =IF(K$55<=$C$6,0,-HLOOKUP(K$55,'Input data'!$C$9:$BB$26,18,FALSE)+HLOOKUP($C$6,'Input data'!$C$9:$BB$26,18,FALSE)) -> 0.0028435 | L64: =IF(L$55<=$C$6,0,-HLOOKUP(L$55,'Input data'!$C$9:$BB$26,18,FALSE)+HLOOKUP($C$6,'Input data'!$C$9:$BB$26,18,FALSE)) -> 0.005687 | M64: =IF(M$55<=$C$6,0,-HLOOKUP(M$55,'Input data'!$C$9:$BB$26,18,FALSE)+HLOOKUP($C$6,'Input data'!$C$9:$BB$26,18,FALSE)) -> 0.0085306 | N64: =IF(N$55<=$C$6,0,-HLOOKUP(N$55,'Input data'!$C$9:$BB$26,18,FALSE)+HLOOKUP($C$6,'Input data'!$C$9:$BB$26,18,FALSE)) -> 0.0113742 | ... W64: =IF(W$55<=$C$6,0,-HLOOKUP(W$55,'Input data'!$C$9:$BB$26,18,FALSE)+HLOOKUP($C$6,'Input data'!$C$9:$BB$26,18,FALSE)) -> 0.036966
B65: (1.7) Revenues | D65: 0 | E65: 0 | F65: 0 | G65: 0 | H65: 0 | I65: 0 | J65: 0 | K65: 0 | L65: 0 | M65: 0 | N65: 0 | O65: 0 | P65: 0 | Q65: 0 | R65: 0 | S65: 0 | T65: 0 | U65: 0 | V65: 0 | W65: 0
B66: (2) Snowball effect (2.1 + 2.2 + 2.3) | D66: =SUM(D67:D70) -> -5.58325 | E66: =SUM(E67:E70) -> -4.089329 | F66: =SUM(F67:F70) -> -2.618877 | G66: =SUM(G67:G70) -> -2.1483854 | H66: =SUM(H67:H70) -> -2.1688915 | I66: =SUM(I67:I70) -> -2.1667921 | J66: =SUM(J67:J70) -> -2.1005957 | K66: =SUM(K67:K70) -> -2.0733464 | ... W66: =SUM(W67:W70) -> -0.50061687
B67: (2.1) Interest expenditure | D67: =C56*D35/100*(1/(1+D32/100)) -> 0.94020825 | E67: =D56*E35/100*(1/(1+E32/100)) -> 1.1036091 | F67: =E56*F35/100*(1/(1+F32/100)) -> 1.2783144 | G67: =F56*G35/100*(1/(1+G32/100)) -> 1.3294577 | H67: =G56*H35/100*(1/(1+H32/100)) -> 1.3911881 | I67: =H56*I35/100*(1/(1+I32/100)) -> 1.4373171 | J67: =I56*J35/100*(1/(1+J32/100)) -> 1.4710602 | K67: =J56*K35/100*(1/(1+K32/100)) -> 1.5996737 | ... W67: =V56*W35/100*(1/(1+W32/100)) -> 1.7242193
B68: (2.2) Growth effect | D68: =-C56*(D23/100)*(1/(1+D32/100)) -> -3.8279967 | E68: =-D56*(E23/100)*(1/(1+E32/100)) -> -2.6067445 | F68: =-E56*(F23/100)*(1/(1+F32/100)) -> -2.1260857 | G68: =-F56*(G23/100)*(1/(1+G32/100)) -> -2.1921013 | H68: =-G56*(H23/100)*(1/(1+H32/100)) -> -2.2559369 | I68: =-H56*(I23/100)*(1/(1+I32/100)) -> -2.2935856 | J68: =-I56*(J23/100)*(1/(1+J32/100)) -> -2.2649237 | K68: =-J56*(K23/100)*(1/(1+K32/100)) -> -2.3789085 | ... W68: =-V56*(W23/100)*(1/(1+W32/100)) -> -1.1087278
B69: (2.3) Inflation effect | D69: =-C56*D41/100*(1/(1+D41/100)) -> -2.6954615 | E69: =-D56*E41/100*(1/(1+E41/100)) -> -2.5861962 | F69: =-E56*F41/100*(1/(1+F41/100)) -> -1.7711093 | G69: =-F56*G41/100*(1/(1+G41/100)) -> -1.2857444 | H69: =-G56*H41/100*(1/(1+H41/100)) -> -1.3041427 | I69: =-H56*I41/100*(1/(1+I41/100)) -> -1.3105236 | J69: =-I56*J41/100*(1/(1+J41/100)) -> -1.3067321 | K69: =-J56*K41/100*(1/(1+K41/100)) -> -1.2941116 | ... W69: =-V56*W41/100*(1/(1+W41/100)) -> -1.1161084
B70: (2.4) Exchange rate effect linked to the interest rate | D70: ='Baseline NFPC'!D70 -> -3.7714402e-08 | E70: ='Baseline NFPC'!E70 -> 2.6165035e-06 | F70: ='Baseline NFPC'!F70 -> 3.5287289e-06 | G70: ='Baseline NFPC'!G70 -> 2.5290586e-06 | H70: ='Baseline NFPC'!H70 -> 0 | I70: ='Baseline NFPC'!I70 -> 0 | J70: ='Baseline NFPC'!J70 -> 0 | K70: ='Baseline NFPC'!K70 -> 0 | ... W70: ='Baseline NFPC'!W70 -> 0
B71: (3 ) Stock flow adjustments (3.1 + 3.2) | D71: ='Input data'!D16 -> -1.310275 | E71: ='Input data'!E16 -> -0.940448 | F71: ='Input data'!F16 -> 1.185199 | G71: ='Input data'!G16 -> 0.0667244 | H71: ='Input data'!H16 -> 0 | I71: ='Input data'!I16 -> 0 | J71: ='Input data'!J16 -> 0 | K71: ='Input data'!K16 -> 0 | ... W71: ='Input data'!W16 -> 0
B72: (3.1) Base | D72: =D14 -> -1.310275 | E72: =E14 -> -0.9404473 | F72: =F14 -> 1.185197 | G72: =G14 -> 0.0667276 | H72: =H14 -> 0 | I72: =I14 -> 0 | J72: =J14 -> 0 | K72: =K14 -> 0 | ... W72: =W14 -> 0
B73: (3.2) Adjustment due to the exchange rate effect linked to debt value | D73: =+D71-D72 -> 0 | E73: =+E71-E72 -> -7e-07 | F73: =+F71-F72 -> 2e-06 | G73: =+G71-G72 -> -3.2e-06 | H73: =+H71-H72 -> 0 | I73: =+I71-I72 -> 0 | J73: =+J71-J72 -> 0 | K73: =+K71-K72 -> 0 | ... W73: =+W71-W72 -> 0
B75: Debt increasing? (For criterion 1) | K75: =IF(K56<J56,0,1) -> 0 | L75: =IF(L56<K56,0,1) -> 0 | M75: =IF(M56<L56,0,1) -> 0 | N75: =IF(N56<M56,0,1) -> 0 | O75: =IF(O56<N56,0,1) -> 0 | P75: =IF(P56<O56,0,1) -> 0 | Q75: =IF(Q56<P56,0,1) -> 0 | R75: =IF(R56<Q56,0,1) -> 0 | ... W75: =IF(W56<V56,0,1) -> 1
B77: Debt decomposition and IIR
B79: Auxiliary variable identifying whether debt is increasing | E79: =IF((E83-D83*E42/((1+E23/100)*(1+E41/100)))>0,1,0) -> 1 | F79: =IF((F83-E83*F42/((1+F23/100)*(1+F41/100)))>0,1,0) -> 1 | G79: =IF((G83-F83*G42/((1+G23/100)*(1+G41/100)))>0,1,0) -> 1 | H79: =IF((H83-G83*H42/((1+H23/100)*(1+H41/100)))>0,1,0) -> 1 | I79: =IF((I83-H83*I42/((1+I23/100)*(1+I41/100)))>0,1,0) -> 1 | J79: =IF((J83-I83*J42/((1+J23/100)*(1+J41/100)))>0,1,0) -> 1 | K79: =IF((K83-J83*K42/((1+K23/100)*(1+K41/100)))>0,1,0) -> 1 | L79: =IF((L83-K83*L42/((1+L23/100)*(1+L41/100)))>0,1,0) -> 1 | ... W79: =IF((W83-V83*W42/((1+W23/100)*(1+W41/100)))>0,1,0) -> 1
B80: Auxiliary variable identifying whether some debt is rolled over even though debt is decreasing | E80: =IF(AND(E79=0,ABS(E83-D83*E42/((1+E23/100)*(1+E41/100)))<((D89*D83*E42/((1+E23/100)*(1+E41/100))+(E38*D83*D90*E42/((1+E23/100)*(1+E41/100)))))),1,0) -> 0 | F80: =IF(AND(F79=0,ABS(F83-E83*F42/((1+F23/100)*(1+F41/100)))<((E89*E83*F42/((1+F23/100)*(1+F41/100))+(F38*E83*E90*F42/((1+F23/100)*(1+F41/100)))))),1,0) -> 0 | G80: =IF(AND(G79=0,ABS(G83-F83*G42/((1+G23/100)*(1+G41/100)))<((F89*F83*G42/((1+G23/100)*(1+G41/100))+(G38*F83*F90*G42/((1+G23/100)*(1+G41/100)))))),1,0) -> 0 | H80: =IF(AND(H79=0,ABS(H83-G83*H42/((1+H23/100)*(1+H41/100)))<((G89*G83*H42/((1+H23/100)*(1+H41/100))+(H38*G83*G90*H42/((1+H23/100)*(1+H41/100)))))),1,0) -> 0 | I80: =IF(AND(I79=0,ABS(I83-H83*I42/((1+I23/100)*(1+I41/100)))<((H89*H83*I42/((1+I23/100)*(1+I41/100))+(I38*H83*H90*I42/((1+I23/100)*(1+I41/100)))))),1,0) -> 0 | J80: =IF(AND(J79=0,ABS(J83-I83*J42/((1+J23/100)*(1+J41/100)))<((I89*I83*J42/((1+J23/100)*(1+J41/100))+(J38*I83*I90*J42/((1+J23/100)*(1+J41/100)))))),1,0) -> 0 | K80: =IF(AND(K79=0,ABS(K83-J83*K42/((1+K23/100)*(1+K41/100)))<((J89*J83*K42/((1+K23/100)*(1+K41/100))+(K38*J83*J90*K42/((1+K23/100)*(1+K41/100)))))),1,0) -> 0 | L80: =IF(AND(L79=0,ABS(L83-K83*L42/((1+L23/100)*(1+L41/100)))<((K89*K83*L42/((1+L23/100)*(1+L41/100))+(L38*K83*K90*L42/((1+L23/100)*(1+L41/100)))))),1,0) -> 0 | ... W80: =IF(AND(W79=0,ABS(W83-V83*W42/((1+W23/100)*(1+W41/100)))<((V89*V83*W42/((1+W23/100)*(1+W41/100))+(W38*V83*V90*W42/((1+W23/100)*(1+W41/100)))))),1,0) -> 0
C82: 2021 | D82: 2022 | E82: 2023 | F82: 2024 | G82: 2025 | H82: 2026 | I82: 2027 | J82: 2028 | K82: 2029 | L82: 2030 | M82: 2031 | N82: 2032 | O82: 2033 | P82: 2034 | Q82: 2035 | R82: 2036 | S82: 2037 | T82: 2038 | U82: 2039 | V82: 2040 | W82: 2041
B83: Gross debt | C83: =C56 -> 53.92565 | D83: =D56 -> 51.62648 | E83: =E56 -> 50.396658 | F83: =F56 -> 52.027241 | G83: =G56 -> 52.730908 | H83: =G83*(1+H97/100)*H42-H59-H60+H61+H62+H63+H64+H65+H71 -> 52.947956 | I83: =H83*(1+I97/100)*I42-I59-I60+I61+I62+I63+I64+I65+I71 -> 52.754005 | J83: =I83*(1+J97/100)*J42-J59-J60+J61+J62+J63+J64+J65+J71 -> 52.204192 | K83: =J83*(1+K97/100)*K42-K59-K60+K61+K62+K63+K64+K65+K71 -> 51.484775 | L83: =K83*(1+L97/100)*L42-L59-L60+L61+L62+L63+L64+L65+L71 -> 50.607762 | M83: =L83*(1+M97/100)*M42-M59-M60+M61+M62+M63+M64+M65+M71 -> 49.679431 | N83: =M83*(1+N97/100)*N42-N59-N60+N61+N62+N63+N64+N65+N71 -> 48.995003 | O83: =N83*(1+O97/100)*O42-O59-O60+O61+O62+O63+O64+O65+O71 -> 48.364493 | ... W83: =V83*(1+W97/100)*W42-W59-W60+W61+W62+W63+W64+W65+W71 -> 49.758965
B84: Of which Outstanding debt | D84: ='Input data'!C66*$D$83 -> 40.602371 | E84: =IF(E83=0,0,IF(E79=1,D83*E42/((1+E23/100)*(1+E41/100))-E85-E86,IF(AND(E79=0,E80=1),(1-D89-E38*D90)*D83*E42/((1+E23/100)*(1+E41/100)),E83))) -> 37.860894 | F84: =IF(F83=0,0,IF(F79=1,E83*F42/((1+F23/100)*(1+F41/100))-F85-F86,IF(AND(F79=0,F80=1),(1-E89-F38*E90)*E83*F42/((1+F23/100)*(1+F41/100)),F83))) -> 38.019239 | G84: =IF(G83=0,0,IF(G79=1,F83*G42/((1+G23/100)*(1+G41/100))-G85-G86,IF(AND(G79=0,G80=1),(1-F89-G38*F90)*F83*G42/((1+G23/100)*(1+G41/100)),G83))) -> 39.688802 | H84: =IF(H83=0,0,IF(H79=1,G83*H42/((1+H23/100)*(1+H41/100))-H85-H86,IF(AND(H79=0,H80=1),(1-G89-H38*G90)*G83*H42/((1+H23/100)*(1+H41/100)),H83))) -> 40.171165 | I84: =IF(I83=0,0,IF(I79=1,H83*I42/((1+I23/100)*(1+I41/100))-I85-I86,IF(AND(I79=0,I80=1),(1-H89-I38*H90)*H83*I42/((1+I23/100)*(1+I41/100)),I83))) -> 40.280137 | J84: =IF(J83=0,0,IF(J79=1,I83*J42/((1+J23/100)*(1+J41/100))-J85-J86,IF(AND(J79=0,J80=1),(1-I89-J38*I90)*I83*J42/((1+J23/100)*(1+J41/100)),J83))) -> 40.110982 | K84: =IF(K83=0,0,IF(K79=1,J83*K42/((1+K23/100)*(1+K41/100))-K85-K86,IF(AND(K79=0,K80=1),(1-J89-K38*J90)*J83*K42/((1+K23/100)*(1+K41/100)),K83))) -> 39.538792 | L84: =IF(L83=0,0,IF(L79=1,K83*L42/((1+L23/100)*(1+L41/100))-L85-L86,IF(AND(L79=0,L80=1),(1-K89-L38*K90)*K83*L42/((1+L23/100)*(1+L41/100)),L83))) -> 38.986447 | ... W84: =IF(W83=0,0,IF(W79=1,V83*W42/((1+W23/100)*(1+W41/100))-W85-W86,IF(AND(W79=0,W80=1),(1-V89-W38*V90)*V83*W42/((1+W23/100)*(1+W41/100)),W83))) -> 38.044215
B85: Rolled over long-term debt | D85: ='Input data'!C67*$D$83 -> 0.040643031 | E85: =IF(E83=0,0,IF(E79=1,E38*D83*D90*E42/((1+E23/100)*(1+E41/100)),IF(AND(E79=0,E80=1),(E38*D83*D90*E42/((1+E23/100)*(1+E41/100)))*(1-ABS(E83-D83*E42/((1+E23/100)*(1+E41/100)))/((E38*D83*D90*E42/((1+E23/100)*(1+E41/100)))+(D89*D83*E42/((1+E23/100)*(1+E41/100))))),0))) -> 1.9515624 | F85: =IF(F83=0,0,IF(F79=1,F38*E83*E90*F42/((1+F23/100)*(1+F41/100)),IF(AND(F79=0,F80=1),(F38*E83*E90*F42/((1+F23/100)*(1+F41/100)))*(1-ABS(F83-E83*F42/((1+F23/100)*(1+F41/100)))/((F38*E83*E90*F42/((1+F23/100)*(1+F41/100)))+(E89*E83*F42/((1+F23/100)*(1+F41/100))))),0))) -> 1.8951144 | G85: =IF(G83=0,0,IF(G79=1,G38*F83*F90*G42/((1+G23/100)*(1+G41/100)),IF(AND(G79=0,G80=1),(G38*F83*F90*G42/((1+G23/100)*(1+G41/100)))*(1-ABS(G83-F83*G42/((1+G23/100)*(1+G41/100)))/((G38*F83*F90*G42/((1+G23/100)*(1+G41/100)))+(F89*F83*G42/((1+G23/100)*(1+G41/100))))),0))) -> 2.0441467 | H85: =IF(H83=0,0,IF(H79=1,H38*G83*G90*H42/((1+H23/100)*(1+H41/100)),IF(AND(H79=0,H80=1),(H38*G83*G90*H42/((1+H23/100)*(1+H41/100)))*(1-ABS(H83-G83*H42/((1+H23/100)*(1+H41/100)))/((H38*G83*G90*H42/((1+H23/100)*(1+H41/100)))+(G89*G83*H42/((1+H23/100)*(1+H41/100))))),0))) -> 2.1358121 | I85: =IF(I83=0,0,IF(I79=1,I38*H83*H90*I42/((1+I23/100)*(1+I41/100)),IF(AND(I79=0,I80=1),(I38*H83*H90*I42/((1+I23/100)*(1+I41/100)))*(1-ABS(I83-H83*I42/((1+I23/100)*(1+I41/100)))/((I38*H83*H90*I42/((1+I23/100)*(1+I41/100)))+(H89*H83*I42/((1+I23/100)*(1+I41/100))))),0))) -> 2.2088211 | J85: =IF(J83=0,0,IF(J79=1,J38*I83*I90*J42/((1+J23/100)*(1+J41/100)),IF(AND(J79=0,J80=1),(J38*I83*I90*J42/((1+J23/100)*(1+J41/100)))*(1-ABS(J83-I83*J42/((1+J23/100)*(1+J41/100)))/((J38*I83*I90*J42/((1+J23/100)*(1+J41/100)))+(I89*I83*J42/((1+J23/100)*(1+J41/100))))),0))) -> 2.2666906 | K85: =IF(K83=0,0,IF(K79=1,K38*J83*J90*K42/((1+K23/100)*(1+K41/100)),IF(AND(K79=0,K80=1),(K38*J83*J90*K42/((1+K23/100)*(1+K41/100)))*(1-ABS(K83-J83*K42/((1+K23/100)*(1+K41/100)))/((K38*J83*J90*K42/((1+K23/100)*(1+K41/100)))+(J89*J83*K42/((1+K23/100)*(1+K41/100))))),0))) -> 2.3007537 | L85: =IF(L83=0,0,IF(L79=1,L38*K83*K90*L42/((1+L23/100)*(1+L41/100)),IF(AND(L79=0,L80=1),(L38*K83*K90*L42/((1+L23/100)*(1+L41/100)))*(1-ABS(L83-K83*L42/((1+L23/100)*(1+L41/100)))/((L38*K83*K90*L42/((1+L23/100)*(1+L41/100)))+(K89*K83*L42/((1+L23/100)*(1+L41/100))))),0))) -> 2.3342917 | ... W85: =IF(W83=0,0,IF(W79=1,W38*V83*V90*W42/((1+W23/100)*(1+W41/100)),IF(AND(W79=0,W80=1),(W38*V83*V90*W42/((1+W23/100)*(1+W41/100)))*(1-ABS(W83-V83*W42/((1+W23/100)*(1+W41/100)))/((W38*V83*V90*W42/((1+W23/100)*(1+W41/100)))+(V89*V83*W42/((1+W23/100)*(1+W41/100))))),0))) -> 2.4713808
