Workbook

Sheet Read me
G4: European Commission
G6: Directorate-General for Economic and Financial Affairs
G7: Unit C2 - Sustainability of public finances
G8: ECFIN-Secretariat-C2@ec.europa.eu
C16: FILE DESCRIPTION
C18: Data reported in this file are based on the European Commission (EC) 2025 autumn forecast (AF 2025) and macroeconomic and budgetary projections from the joint EC-EPC Ageing Report 2024 (AR 2024).
C22: This file contains a simplified version of the EC model used to calculate the general governement debt ratio dynamics for EU countries under different scenarios. A detailed description of the EC's general governement debt projections can be found in the "Debt Sustainability Monitor 2023" (DSM, March 2024).
C27: HOW TO USE THIS TOOL TO CALCULATE NEW DEBT PROJECTIONS
C29: This tool can be used to calculate debt projections under different macroeconomic and structural primary balance adjustment assumptions. Debt projections for each scenario will update automatically with changes in the macroeconomic assumptions or the adjustment parameters. The fulfilment of DSA-based criteria, the safeguards and the benchmark will be automatically calculated in the sheet "Criteria results". Formulas are fully visible. To assess the impact of alternative fiscal paths or to check the robustness of underlying macroeconomic assumptions, the user can modify the content of key cells in the sheets "Criteria results" and "Input data" (see below). Note that, for a proper functioning of the file, you should make sure that Excel is in "Automatic" computation mode, i.e. in the File menu, Option tab, click on "Formulas", "Calculation Options" and "Automatic".
C31: The spreadsheet is composed of the following elements:
D33: The grey sheet "Criteria results" contains three types of cells identified by different colours:
F34: Cells with a yellow background and a red frame can be modified to see the impact of a different duration or pace of adjustment.
F35: Cells with a white or pale red (in case the deficit resilience safeguard is binding) background provide results obtained with the adjustment chosen in the yellow cells. To replicate the Commission's calculations, the underlying formulas should not be modified.
F37: Cells with a pale blue background correspond to the Commission's prior guidance provided to the Member State. Those are hard numbers that do not depend on the adjustment chosen in the file.
D39: "Criteria results" contains five tables. Table 1 "Adjustment input data": the user can set the duration of the plan in cell F5 (4 years without extension or 7 years with extension), the yearly adjustment pace under the scenario that does not take into account the deficit resilience safeguard (F7) and for the scenario that automatically applies that safeguard (F6). Note that the country cell (F4) cannot be changed.
D40: The adjustement in F7 needs to be selected first so that the message on line 13 signals that the two DSA-based criteria are fulfilled. As a second step, the adjustment in F6 can be selected (and cannot be lower than in F7) so that line 12 reports compliance with the requirements.
D41: Table 2 "DSA-based criteria and deficit resilience safeguard" reports whether the chosen adjustment fulfils the DSA-based criteria (cells H12:I13) and whether the deficit resillience safeguard is binding.
D42: Table 3 "Main fiscal variables with automatic deficit resilience safeguard" reports the annual adjustment over the adjustment period, in terms of change in SPB (line 18), level of the structural balance (line 19) and SPB level at the end of the adjustment (line 20). This table reports the results for the scenario that automatically applies the deficit resillience safeguard. For this reason, the SB is highlighted in red if it is lower than -1.5% of GDP.
D43: Table 4 "Main fiscal variables without automatic deficit resilience safeguard" reports the annual adjustment over the adjustment period, in terms of change in SPB (line 25), level of the structural balance (line 26) and SPB level at the end of the adjustment (line 27). This table reports the results for the scenario without the deficit resillience safeguard.
D44: Table 5 "Technical information" reports the SPB level at the end of the adjustment period that fulfils the DSA-based criteria and takes into account the deficit resilience safeguard, both without and with extension.
D46: The sheet "Input data" in light blue presents the input data, including fiscal and GDP growth assumptions as well as additional fiscal parameters. Unless stated otherwise below, the user can change all values in this tab.
D47: Coloured cells indicate data sources as follows (this colour-coding holds in the other spreadsheets):
F48: Cells in light grey indicate Commission forecast (available in the AMECO database)
F49: Cells in light blue indicate values from the Ageing Report 2024
F50: Cells in light orange provide parameters needed to compute the decomposition of government debt according to its maturity structure (i.e. short-term and long-term debt, maturing, rolled-over and non-maturing debt). These are fixed shares which the user cannot change.
F51: Cells in dark orange indicate financial market prices.
D52: Non coloured parameters in cells C50:C70 were calibrated based on different data sources. Data sources are given in corresponding cells of column E.
C54: The next spreadsheets present the no-fiscal-policy-change baseline and the adjustment scenario, with and without the impact of the deficit resilience safeguard. Each deterministic projection provides a single path for debt until 2039 or 2042 under certain assumptions for budgetary, macroeconomic and financial variables.
D56: The sheet in blue provides, as a reference, the baseline no-fiscal-policy-change scenario. The background colour coding is the same as in the sheet "Input data".
D58: The sheet in orange presents the scenario that automatically corrects the yearly adjustment path to account for the deficit resillience safeguard.
D60: The sheet in green presents the adjustment scenarios without the deficit resilience safeguard. This scenario is computed automatically based on the yearly adjustment path set in "Criteria results" (see above).
C62: Within the orange sheet and each green sheet, the background of the SPB line has three colours. Each colour corresponds to a specific period of the projections:
E63: Light grey indicates the pre-plan period, corresponding to the EC forecast
E64: Mild grey indicates the period during which the SPB adjusts according to the path set in sheet "Criteria results"
E65: Dark grey indicates the period in which the SPB, net of changes in cost of ageing, remains constant at its value of end of adjustment.
C68: WHERE ARE THE MAIN RESULTS LOCATED?
C69: The fullfilment of the criteria is checked in the sheet "Criteria results". Debt projections can be found in line 57 of each scenario.
D71: The 'FASTOP reporting' sheet in violet provides help for preparing reporting tables. It readily provides all the tables foreseen by the guidance notice on the "Information Requirements for the Medium-Term Fiscal-Structural Plans" once the parameters are set in the rest of this file. This sheet is meant to be an assistance. The need for a thorough scrutiny of the figures before submitting such tables remains.

Sheet Criteria results
U2: 4 | V2: -1.5
D3: Table 1 - Adjustment input data | U3: 7 | V3: -1.48
D4: Country | F4: NL | V4: -1.46
D5: Number of years of adjustment | F5: 4 | V5: -1.44
C6: 2. | D6: Annual adjustment (with safeguard) | F6: 0 | V6: -1.42
C7: 1. | D7: Annual adjustment (without safeguard) | F7: 0 | V7: -1.4
V8: -1.38
H9: Table 2 - DSA-based criteria and deficit resilience safeguard | V9: -1.36
H10: DSA-based criteria | J10: Deficit resilience safeguard | V10: -1.34
H11: Deficit below 3% of GDP | I11: ="Debt below 60% of GDP in T+"&10+F5 -> Debt below 60% of GDP in T+14 | V11: -1.32
C12: 2. | D12: Adjustment scenario with automatic deficit resilience safeguard * (sheet "Adjustment scenario") | H12: =IF(MIN(OFFSET('Adjustment scenario'!$D$77,0,$F$5,1,11))>-3.05,"ok","Not met") -> Not met | I12: =IF(OFFSET('Adjustment scenario'!$D$57,0,$F$5+10,1,1)<60,"ok","Not met") -> ok | J12: =IF(AND($F$5=4,COUNTIF(G18:J18,">" & F6)=0),"Not binding",IF(AND($F$5=7,COUNTIF(G18:M18,">" & F6)=0),"Not binding","Binding")) -> Not binding | K12: =IF(OR($H$13="Not met",$I$13="Not met"),"Please adjust cell F7 so that both DSA-based criteria are met", IF($F$6<$F$7,"The adjustment in F6 cannot be lower than in F7", IF(AND($H$12="ok",$I$12="ok",$H$13="ok",$I$13="ok",$F$6>=$F$7, OR(AND($F$5=4,$G$18>=$H$18,$H$18>=$I$18,$I$18>=$J$18,OR($J$18>=0.4,$J$19>-1.55)), AND($F$5=7,$G$18>=$H$18,$H$18>=$I$18,$I$18>=$J$18,$J$18>=$K$18,$K$18>=$L$18,$L$18>=$M$18,OR($M$18>=0.25,$M$19>-1.55)))), "OK"&CHAR(10)&"The adjustment in F6 fulfills all requirements including the deficit resilience safeguard", "NOT OK"&CHAR(10)&"The adjustment in F6 does not fulfill all requirements"))) -> Please adjust cell F7 so that both DSA-based criteria are met | V12: -1.3
C13: 1. | D13: Adjustment scenario without deficit resilience safeguard (sheet "Adjust. no safeguard") | H13: =IF(MIN(OFFSET('Adjust. no safeguard'!$D$77,0,$F$5,1,11))>-3.05,"ok","Not met") -> Not met | I13: =IF(OFFSET('Adjust. no safeguard'!$D$57,0,$F$5+10,1,1)<60,"ok","Not met") -> ok | K13: =IF(AND($H$13="ok",$I$13="ok"), "OK"&CHAR(10)&"The adjustment in F7 ensures that the debt and deficit remain"&CHAR(10)&"below the Treaty reference values over the medium term", "NOT OK"&CHAR(10)&"The adjustment in F7 does not ensure that the debt and deficit remain"&CHAR(10)&"below the Treaty reference values over the medium term") -> NOT OK The adjustment in F7 does not ensure that the debt and deficit remain below the Treaty reference values over the medium term | V13: -1.28
D14: * Under a plan without (with) extension, an adjustment of 0.40 pp. (0.25 pp.) of GDP in SPB terms is applied if the structural deficit in the previous year exceeds 1.5% of GDP. | V14: -1.26
V15: -1.24
G16: Table 3 - Main fiscal variables with automatic deficit resilience safeguard * | V16: -1.22
G17: ='Input data'!$C$5+1 -> 2026 | H17: =G17+1 -> 2027 | I17: =H17+1 -> 2028 | J17: =I17+1 -> 2029 | K17: =J17+1 -> 2030 | L17: =K17+1 -> 2031 | M17: =L17+1 -> 2032 | V17: -1.2
D18: Annual adjustment (change in SPB) | G18: ='Adjustment scenario'!E12-'Adjustment scenario'!D12 -> 0 | H18: ='Adjustment scenario'!F12-'Adjustment scenario'!E12 -> 0 | I18: ='Adjustment scenario'!G12-'Adjustment scenario'!F12 -> 0 | J18: ='Adjustment scenario'!H12-'Adjustment scenario'!G12 -> 0 | K18: ='Adjustment scenario'!I12-'Adjustment scenario'!H12 -> 0 | L18: ='Adjustment scenario'!J12-'Adjustment scenario'!I12 -> 0 | M18: ='Adjustment scenario'!K12-'Adjustment scenario'!J12 -> 0 | V18: -1.18
D19: Structural balance | G19: ='Adjustment scenario'!E78 -> -1.3057584 | H19: ='Adjustment scenario'!F78 -> -1.4003147 | I19: ='Adjustment scenario'!G78 -> -1.4672003 | J19: ='Adjustment scenario'!H78 -> -1.5328785 | K19: ='Adjustment scenario'!I78 -> -1.701993 | L19: ='Adjustment scenario'!J78 -> -2.0752787 | M19: ='Adjustment scenario'!K78 -> -2.3623048 | V19: -1.16
D20: SPB at the end of the adjustment | J20: =IF(F5=4,'Adjustment scenario'!H12,"") -> -0.5577395 | M20: =IF(F5=7,'Adjustment scenario'!K12,"") | V20: -1.14
D21: * The structural balance is flagged in red if it is below -1.5% of GDP. | V21: -1.12
V22: -1.1
G23: Table 4 - Main fiscal variables without automatic deficit resilience safeguard | V23: -1.08
G24: ='Input data'!$C$5+1 -> 2026 | H24: =G24+1 -> 2027 | I24: =H24+1 -> 2028 | J24: =I24+1 -> 2029 | K24: =J24+1 -> 2030 | L24: =K24+1 -> 2031 | M24: =L24+1 -> 2032 | V24: -1.06
D25: Annual adjustment (change in SPB) | G25: ='Adjust. no safeguard'!E12-'Adjust. no safeguard'!D12 -> 0 | H25: ='Adjust. no safeguard'!F12-'Adjust. no safeguard'!E12 -> 0 | I25: ='Adjust. no safeguard'!G12-'Adjust. no safeguard'!F12 -> 0 | J25: ='Adjust. no safeguard'!H12-'Adjust. no safeguard'!G12 -> 0 | K25: ='Adjust. no safeguard'!I12-'Adjust. no safeguard'!H12 -> 0 | L25: ='Adjust. no safeguard'!J12-'Adjust. no safeguard'!I12 -> 0 | M25: ='Adjust. no safeguard'!K12-'Adjust. no safeguard'!J12 -> 0 | V25: -1.04
D26: Structural balance | G26: ='Adjust. no safeguard'!E78 -> -1.3057584 | H26: ='Adjust. no safeguard'!F78 -> -1.4003147 | I26: ='Adjust. no safeguard'!G78 -> -1.4672003 | J26: ='Adjust. no safeguard'!H78 -> -1.5328785 | K26: ='Adjust. no safeguard'!I78 -> -1.701993 | L26: ='Adjust. no safeguard'!J78 -> -2.0752787 | M26: ='Adjust. no safeguard'!K78 -> -2.3623048 | V26: -1.02
D27: SPB at the end of the adjustment | J27: =IF(F5=4,'Adjust. no safeguard'!H12,"") -> -0.5577395 | M27: =IF(F5=7,'Adjust. no safeguard'!K12,"") | V27: -1
V28: -0.98
V29: -0.96
V30: -0.94
G31: Table 5 - Technical information* | V31: -0.92
G32: Without extension | H32: With extension | V32: -0.9
D33: Number of years of adjustment | G33: 4 | H33: 7 | V33: -0.88
D34: SPB at the end of the adjustment | G34: 0.0822605 | H34: 0.0022605 | V34: -0.86
D35: * The technical information provides the structural primary balance necessary to ensure that the deficit remains below 3% of GDP and debt remains below 60% of GDP over the medium term in the absence of additional fiscal measures beyond the adjustment period. In line with the deficit resilience safeguard, and when necessary, an adjustment of 0.4 pp of GDP (0.25 pp. in case of extension) in structural primary terms is applied until the structural balance is at least equal to -1.5% of GDP. Note that the SPB at the end of the adjustment period may be lower than the SPB at the beginning of the plan, indicating that the Member State does not need to adjust. | V35: -0.84
V36: -0.82
V37: -0.8
V38: -0.78
V39: -0.76
V40: -0.74
V41: -0.72
V42: -0.7
V43: -0.68
V44: -0.66
V45: -0.64
V46: -0.62
V47: -0.6
... V152: 1.5

Sheet Input data
B3: Country | C3: NL
B5: Last year before the adjustment | C5: 2025
B6: Last year of adjustment | C6: =C5+'Criteria results'!$F$5 -> 2029
B8: Key assumptions
C9: 2024 | D9: 2025 | E9: 2026 | F9: 2027 | G9: 2028 | H9: 2029 | I9: 2030 | J9: 2031 | K9: 2032 | L9: 2033 | M9: 2034 | N9: 2035 | O9: 2036 | P9: 2037 | Q9: 2038 | R9: 2039 | S9: 2040 | T9: 2041 | U9: 2042
B10: Fiscal assumptions (% of GDP)
B11: Key fiscal variables (based on the Commission 2025 autumn forecast ("AF 2025"))
B12: Debt | C12: 43.74815 | D12: 45.1576
B13: Structural primary balance ('+' means 'surplus') | C13: 0.386237 | D13: -0.5577395
B14: One-off and other temporary measures | C14: -0.026727 | D14: -0.0254775 | E14: -0.6901042 | F14: 0 | G14: 0 | H14: 0 | I14: 0 | J14: 0 | K14: 0 | L14: 0 | M14: 0 | N14: 0 | O14: 0 | P14: 0 | Q14: 0 | R14: 0 | S14: 0 | T14: 0 | U14: 0
B15: Stock-flow adjustments (without exchange rate effect) | C15: -0.0919396 | D15: 1.579996 | E15: 2.014675 | F15: 0 | G15: 0 | H15: 0 | I15: 0 | J15: 0 | K15: 0 | L15: 0 | M15: 0 | N15: 0 | O15: 0 | P15: 0 | Q15: 0 | R15: 0 | S15: 0 | T15: 0 | U15: 0
B16: Stock-flow adjustment (total) | C16: -0.091941 | D16: 1.579997 | E16: 2.014677 | F16: -2.05e-06 | G16: 0 | H16: 0 | I16: 0 | J16: 0 | K16: 0 | L16: 0 | M16: 0 | N16: 0 | O16: 0 | P16: 0 | Q16: 0 | R16: 0 | S16: 0 | T16: 0 | U16: 0
B17: Subject to an excessive deficit procedure (EDP) (0-no/1-yes) | C17: 0 | D17: 0
B19: Cost of ageing and selected public revenue (based on the Commission-Council 2024 Ageing Report ("AR 2024"))
B20: Total ageing cost (net of taxes on pensions) | C20: =(C21+C22+C23+C24-C25) -> 18.2 | D20: =(D21+D22+D23+D24-D25) -> 18.1 | E20: =(E21+E22+E23+E24-E25) -> 18.1 | F20: =(F21+F22+F23+F24-F25) -> 18.3 | G20: =(G21+G22+G23+G24-G25) -> 18.4 | H20: =(H21+H22+H23+H24-H25) -> 18.5 | I20: =(I21+I22+I23+I24-I25) -> 18.6 | J20: =(J21+J22+J23+J24-J25) -> 18.9 | ... U20: =(U21+U22+U23+U24-U25) -> 20.2
B21: of which: Public pensions expenditure | C21: 6.8 | D21: 6.8 | E21: 6.9 | F21: 7 | G21: 7.1 | H21: 7.2 | I21: 7.3 | J21: 7.4 | K21: 7.5 | L21: 7.6 | M21: 7.7 | N21: 7.7 | O21: 7.8 | P21: 7.9 | Q21: 7.9 | R21: 7.9 | S21: 8 | T21: 8 | U21: 8
B22: Health care expenditure | C22: 5.8 | D22: 5.8 | E22: 5.8 | F22: 5.9 | G22: 5.9 | H22: 5.9 | I22: 5.9 | J22: 6 | K22: 6 | L22: 6 | M22: 6 | N22: 6.1 | O22: 6.1 | P22: 6.1 | Q22: 6.1 | R22: 6.1 | S22: 6.1 | T22: 6.2 | U22: 6.2
B23: Long-term care expenditure | C23: 3.9 | D23: 3.9 | E23: 3.9 | F23: 4.1 | G23: 4.1 | H23: 4.2 | I23: 4.2 | J23: 4.3 | K23: 4.4 | L23: 4.4 | M23: 4.5 | N23: 4.5 | O23: 4.6 | P23: 4.7 | Q23: 4.7 | R23: 4.8 | S23: 4.8 | T23: 4.9 | U23: 4.9
B24: Education & unemployment benefits expenditure | C24: 4.6 | D24: 4.5 | E24: 4.4 | F24: 4.3 | G24: 4.3 | H24: 4.2 | I24: 4.2 | J24: 4.2 | K24: 4.2 | L24: 4.2 | M24: 4.2 | N24: 4.2 | O24: 4.2 | P24: 4.2 | Q24: 4.2 | R24: 4.2 | S24: 4.2 | T24: 4.2 | U24: 4.2
B25: Taxes on pensions | C25: 2.9 | D25: 2.9 | E25: 2.9 | F25: 3 | G25: 3 | H25: 3 | I25: 3 | J25: 3 | K25: 3 | L25: 3 | M25: 3.1 | N25: 3.1 | O25: 3.1 | P25: 3.1 | Q25: 3.1 | R25: 3.1 | S25: 3.1 | T25: 3.1 | U25: 3.1
B26: Property income | C26: 0.6265708 | D26: 0.6208305 | E26: 0.6150902 | F26: 0.6093498 | G26: 0.6036096 | H26: 0.5978693 | I26: 0.5921289 | J26: 0.5863886 | K26: 0.5806483 | L26: 0.574908 | M26: 0.5691677 | N26: 0.5634273 | O26: 0.557687 | P26: 0.5519468 | Q26: 0.5462064 | R26: 0.5404661 | S26: 0.5347258 | T26: 0.5289855 | U26: 0.5232452
B28: Real GDP growth assumptions (based on AF 2025 T+10 projections and AR 2024 projections)
B29: Actual GDP
B30: Growth rate | C30: 1.081005 | D30: 1.69667 | E30: 1.273747 | F30: 1.581865 | G30: 1.521399 | H30: 1.41368 | I30: 1.393831 | J30: 1.069126 | K30: 1.03431 | L30: 1.012531 | M30: 1.026592 | N30: 1.054951 | O30: 1.133299 | P30: 1.211654 | Q30: 1.290001 | R30: 1.450001 | S30: 1.609996 | T30: 1.659995 | U30: 1.710004
B31: Level (EUR bn) | C31: 915.5005
B32: Potential GDP
B33: Growth rate | C33: 1.824226 | D33: 1.656294 | E33: 1.426257 | F33: 1.292883 | G33: 1.24374 | H33: 1.137065 | I33: 1.118027 | J33: 1.069128 | K33: 1.03431 | L33: 1.01253 | M33: 1.026594 | N33: 1.054945 | O33: 1.133297 | P33: 1.211648 | Q33: 1.29 | R33: 1.45 | S33: 1.61 | T33: 1.66 | U33: 1.71
B34: Level (EUR bn) | C34: 924.6414
B36: Interest rates (AF 2025, %)
B37: Nominal implicit interest rate on debt | C37: 1.646586 | D37: 1.72 | E37: 1.732298 | F37: 1.826186
B38: Short-term nominal interest rate | C38: 3.570833 | D38: 2.172583 | E38: 1.91225 | F38: 2.024375
B39: Long-term nominal interest rate | C39: 2.6205 | D39: 2.78965 | E39: 2.894953 | F39: 3.081676
D40: Bloomberg data, country-specific forward market rates.
B41: Inflation (AF 2025, %)
B42: GDP deflator (national currency) | C42: 5.744214 | D42: 3.154387 | E42: 3.262934 | F42: 2.103313
B44: Net primary expenditure growth (AF 2025, %)
B45: Net primary expenditure growth | C45: 6.2115937 | D45: 7.2645885
B47: Additional parameters
E48: Sources
B49: Fiscal multiplier | C49: 0.6
B50: Budget balance semi-elasticity | C50: 0.605 | E50: Mourre, G. et al. (2019), "The Semi-Elasticities Underlying the Cyclically-Adjusted Budget Balance: An Update and Further Analysis", European Economy, Discussion Paper, No. 098.
B52: Long-term nominal interest rate (T+10 convergence value) | C52: 3.93762 | E52: Bloomberg data, country-specific forward market rates.
B53: Short-term nominal interest rate (T+10 convergence value) | C53: 3.25683 | E53: Bloomberg data, country-specific forward market rates.
B54: Long-term nominal interest rate (T+30 convergence value) | C54: 4 | E54: DSM 2024
B55: Short-term nominal interest rate (T+30 convergence value) | C55: 2 | E55: DSM 2024
B57: Share of short-term debt in total government debt | C57: 0.093996 | E57: Eurostat, average shares over the 3 last available years.
B58: Share of long-term debt in total government debt | C58: =1-C57 -> 0.906004 | E58: Eurostat, average shares over the 3 last available years.
B59: Share of long-term debt that matures every year (T+10 convergence value) | C59: 0.08815357 | E59: ECB, country-specific historical average shares over the 6 last available years. For post-programme countries (CY, El , IE and PT), the redemption profile of official loans has been taken into account for the computation of the share of long-term debt that matures every year. For these countries, changing this parameter would not affect debt projections.
B61: GDP deflator (national currency) (T+10 convergence value) | C61: 2.28 | E61: Bloomberg data, inflation swaps.
B62: GDP deflator (national currency) (T+30 convergence value) | C62: 2 | E62: Central bank inflation target
B64: Share of primary expenditure in GDP in 2025 | C64: 44.279356 | E64: AF25
B66: Share of outstanding debt in total debt in 2024 | C66: 0.81968518 | E66: Derived from the model and made consistent with the short-term forecast.
B67: Share of rolled-over long-term debt in 2024 | C67: 0.079466103 | E67: Derived from the model and made consistent with the short-term forecast.
B68: Share of rolled-over short-term debt in 2024 | C68: 0.081351783 | E68: Derived from the model and made consistent with the short-term forecast.
B69: Share of new long-term debt in 2024 | C69: 0.017879195 | E69: Derived from the model and made consistent with the short-term forecast.
B70: Share of new short-term debt in 2024 | C70: 0.001617641 | E70: Derived from the model and made consistent with the short-term forecast.

Sheet Baseline NFPC
B3: Country | C3: ='Input data'!C3 -> NL
B4: Key years
B5: ='Input data'!B5 -> Last year before the adjustment | C5: =+'Input data'!C5 -> 2025
B6: Last year of adjustment | C6: =+C5+'Criteria results'!$F$5 -> 2029
B9: Key assumptions
C10: ='Input data'!$C$5-1 -> 2024 | D10: =C10+1 -> 2025 | E10: =D10+1 -> 2026 | F10: =E10+1 -> 2027 | G10: =F10+1 -> 2028 | H10: =G10+1 -> 2029 | I10: =H10+1 -> 2030 | J10: =I10+1 -> 2031 | K10: =J10+1 -> 2032 | ... U10: =T10+1 -> 2042
B11: Fiscal assumptions (% of GDP)
B12: Structural primary balance ('+' means 'surplus') | C12: ='Input data'!C13 -> 0.386237 | D12: ='Input data'!D13 -> -0.5577395 | E12: =D12 -> -0.5577395 | F12: =E12 -> -0.5577395 | G12: =F12 -> -0.5577395 | H12: =G12 -> -0.5577395 | I12: =H12 -> -0.5577395 | J12: =I12 -> -0.5577395 | K12: =J12 -> -0.5577395 | L12: =K12 -> -0.5577395 | ... U12: =T12 -> -0.5577395
B13: One-off and other temporary measures | C13: ='Input data'!C14 -> -0.026727 | D13: ='Input data'!D14 -> -0.0254775 | E13: ='Input data'!E14 -> -0.6901042 | F13: ='Input data'!F14 -> 0 | G13: ='Input data'!G14 -> 0 | H13: ='Input data'!H14 -> 0 | I13: ='Input data'!I14 -> 0 | J13: ='Input data'!J14 -> 0 | ... U13: ='Input data'!U14 -> 0
B14: Stock flow adjustments (without exchange rate effect) | C14: ='Input data'!C15 -> -0.0919396 | D14: ='Input data'!D15 -> 1.579996 | E14: ='Input data'!E15 -> 2.014675 | F14: ='Input data'!F15 -> 0 | G14: ='Input data'!G15 -> 0 | H14: ='Input data'!H15 -> 0 | I14: ='Input data'!I15 -> 0 | J14: ='Input data'!J15 -> 0 | ... U14: ='Input data'!U15 -> 0
B16: ='Input data'!B19 -> Cost of ageing and selected public revenue (based on the Commission-Council 2024 Ageing Report ("AR 2024"))
B17: Total ageing cost (net of taxes on pensions) | C17: ='Input data'!C20 -> 18.2 | D17: ='Input data'!D20 -> 18.1 | E17: ='Input data'!E20 -> 18.1 | F17: ='Input data'!F20 -> 18.3 | G17: ='Input data'!G20 -> 18.4 | H17: ='Input data'!H20 -> 18.5 | I17: ='Input data'!I20 -> 18.6 | J17: ='Input data'!J20 -> 18.9 | ... U17: ='Input data'!U20 -> 20.2
B18: ='Input data'!B26 -> Property income | C18: ='Input data'!C26 -> 0.6265708 | D18: ='Input data'!D26 -> 0.6208305 | E18: ='Input data'!E26 -> 0.6150902 | F18: ='Input data'!F26 -> 0.6093498 | G18: ='Input data'!G26 -> 0.6036096 | H18: ='Input data'!H26 -> 0.5978693 | I18: ='Input data'!I26 -> 0.5921289 | ... U18: ='Input data'!U26 -> 0.5232452
B20: GDP growth assumptions
B21: Actual GDP (real)
B22: Level | C22: ='Input data'!C31 -> 915.5005 | D22: =C22*(D23/100+1) -> 931.03352 | E22: =D22*(E23/100+1) -> 942.89253 | F22: =E22*(F23/100+1) -> 957.80782 | G22: =F22*(G23/100+1) -> 972.3799 | H22: =G22*(H23/100+1) -> 986.12624 | I22: =H22*(I23/100+1) -> 999.87117 | J22: =I22*(J23/100+1) -> 1010.5611 | K22: =J22*(K23/100+1) -> 1021.0134 | ... U22: =T22*(U23/100+1) -> 1163.5727
B23: Growth rate | C23: =+'Input data'!C30 -> 1.081005 | D23: =+'Input data'!D30 -> 1.69667 | E23: =+'Input data'!E30 -> 1.273747 | F23: =+'Input data'!F30 -> 1.581865 | G23: =+'Input data'!G30 -> 1.521399 | H23: =+'Input data'!H30 -> 1.41368 | I23: =+'Input data'!I30 -> 1.393831 | J23: =+'Input data'!J30 -> 1.069126 | ... U23: =+'Input data'!U30 -> 1.710004
B25: Potential GDP (real)
B26: Level | C26: ='Input data'!C34 -> 924.6414 | D26: =+C26*(1+'Input data'!D33/100) -> 939.95618 | E26: =+D26*(1+'Input data'!E33/100) -> 953.36237 | F26: =+E26*(1+'Input data'!F33/100) -> 965.68823 | G26: =+F26*(1+'Input data'!G33/100) -> 977.69888 | H26: =+G26*(1+'Input data'!H33/100) -> 988.81595 | I26: =+H26*(1+'Input data'!I33/100) -> 999.87118 | J26: =+I26*(1+'Input data'!J33/100) -> 1010.5611 | K26: =+J26*(1+'Input data'!K33/100) -> 1021.0134 | ... U26: =+T26*(1+'Input data'!U33/100) -> 1163.5726
B28: Output gap
B29: Output gap | C29: =100*(C22/C26-1) -> -0.98858866 | D29: =100*(D22/D26-1) -> -0.94926316 | E29: =100*(E22/E26-1) -> -1.0982012 | F29: =100*(F22/F26-1) -> -0.8160408 | G29: =100*(G22/G26-1) -> -0.54403071 | H29: =100*(H22/H26-1) -> -0.27201359 | I29: =100*(I22/I26-1) -> -9.9246313e-07 | J29: =100*(J22/J26-1) -> -2.9713068e-06 | ... U29: =100*(U22/U26-1) -> 6.9328616e-06
B31: Actual GDP (nominal, national currency)
B32: Growth rate | C32: =100*((1+C23/100)*(1+C41/100)-1) -> 6.8873142 | D32: =100*((1+D23/100)*(1+D41/100)-1) -> 4.9045765 | E32: =100*((1+E23/100)*(1+E41/100)-1) -> 4.5782425 | F32: =100*((1+F23/100)*(1+F41/100)-1) -> 3.7184496 | G32: =100*((1+G23/100)*(1+G41/100)-1) -> 3.6791337 | H32: =100*((1+H23/100)*(1+H41/100)-1) -> 3.5915233 | I32: =100*((1+I23/100)*(1+I41/100)-1) -> 3.5936418 | J32: =100*((1+J23/100)*(1+J41/100)-1) -> 3.2842141 | ... U32: =100*((1+U23/100)*(1+U41/100)-1) -> 3.9293163
B34: Interest rate
B35: Nominal implicit interest rate on debt | C35: ='Input data'!C37 -> 1.646586 | D35: ='Input data'!D37 -> 1.72 | E35: ='Input data'!E37 -> 1.732298 | F35: ='Input data'!F37 -> 1.826186 | G35: =G96 -> 1.9680346 | H35: =H96 -> 2.1106557 | I35: =I96 -> 2.2537821 | J35: =J96 -> 2.3971883 | K35: =K96 -> 2.5478088 | L35: =L96 -> 2.7018156 | M35: =M96 -> 2.8561372 | N35: =N96 -> 3.0100965 | ... U35: =U96 -> 3.5677364
B36: Long-term interest rate | C36: ='Input data'!C39 -> 2.6205 | D36: ='Input data'!D39 -> 2.78965 | E36: ='Input data'!E39 -> 2.894953 | F36: ='Input data'!F39 -> 3.081676 | G36: =F36+($N$36-$F$36)/($N$10-$F$10) -> 3.188669 | H36: =G36+($N$36-$F$36)/($N$10-$F$10) -> 3.295662 | I36: =H36+($N$36-$F$36)/($N$10-$F$10) -> 3.402655 | J36: =I36+($N$36-$F$36)/($N$10-$F$10) -> 3.509648 | K36: =J36+($N$36-$F$36)/($N$10-$F$10) -> 3.616641 | L36: =K36+($N$36-$F$36)/($N$10-$F$10) -> 3.723634 | M36: =L36+($N$36-$F$36)/($N$10-$F$10) -> 3.830627 | N36: ='Input data'!$C$52 -> 3.93762 | O36: =$N$36+('Input data'!$C$54-'Input data'!$C$52)/20*(O$10-$N$10) -> 3.940739 | P36: =$N$36+('Input data'!$C$54-'Input data'!$C$52)/20*(P$10-$N$10) -> 3.943858 | Q36: =$N$36+('Input data'!$C$54-'Input data'!$C$52)/20*(Q$10-$N$10) -> 3.946977 | R36: =$N$36+('Input data'!$C$54-'Input data'!$C$52)/20*(R$10-$N$10) -> 3.950096 | S36: =$N$36+('Input data'!$C$54-'Input data'!$C$52)/20*(S$10-$N$10) -> 3.953215 | T36: =$N$36+('Input data'!$C$54-'Input data'!$C$52)/20*(T$10-$N$10) -> 3.956334 | U36: =$N$36+('Input data'!$C$54-'Input data'!$C$52)/20*(U$10-$N$10) -> 3.959453
B37: Short-term interest rate | C37: ='Input data'!C$38 -> 3.570833 | D37: ='Input data'!D$38 -> 2.172583 | E37: ='Input data'!E$38 -> 1.91225 | F37: ='Input data'!F$38 -> 2.024375 | G37: =F37+($N$37-$F$37)/($N$10-$F$10) -> 2.1784319 | H37: =G37+($N$37-$F$37)/($N$10-$F$10) -> 2.3324888 | I37: =H37+($N$37-$F$37)/($N$10-$F$10) -> 2.4865456 | J37: =I37+($N$37-$F$37)/($N$10-$F$10) -> 2.6406025 | K37: =J37+($N$37-$F$37)/($N$10-$F$10) -> 2.7946594 | L37: =K37+($N$37-$F$37)/($N$10-$F$10) -> 2.9487163 | M37: =L37+($N$37-$F$37)/($N$10-$F$10) -> 3.1027731 | N37: ='Input data'!$C$53 -> 3.25683 | O37: =$N$37+('Input data'!$C$55-'Input data'!$C$53)/20*(O$10-$N$10) -> 3.1939885 | P37: =$N$37+('Input data'!$C$55-'Input data'!$C$53)/20*(P$10-$N$10) -> 3.131147 | Q37: =$N$37+('Input data'!$C$55-'Input data'!$C$53)/20*(Q$10-$N$10) -> 3.0683055 | R37: =$N$37+('Input data'!$C$55-'Input data'!$C$53)/20*(R$10-$N$10) -> 3.005464 | S37: =$N$37+('Input data'!$C$55-'Input data'!$C$53)/20*(S$10-$N$10) -> 2.9426225 | T37: =$N$37+('Input data'!$C$55-'Input data'!$C$53)/20*(T$10-$N$10) -> 2.879781 | U37: =$N$37+('Input data'!$C$55-'Input data'!$C$53)/20*(U$10-$N$10) -> 2.8169395
B38: Share of long-term debt that matures every year | C38: 0.08837902 | D38: 0.05460046 | E38: 0.05795577 | F38: =IF(OR($C$3="EL",$C$3="CY",$C$3="IE",$C$3="PT"),VLOOKUP($C$3,$B$110:$R$114,MATCH(F$10,$B$110:$R$110,0),0),$E$38+('Input data'!$C$59-$E$38)/($N$10-$E$10)*(F10-$E$10)) -> 0.061311081 | G38: =IF(OR($C$3="EL",$C$3="CY",$C$3="IE",$C$3="PT"),VLOOKUP($C$3,$B$110:$R$114,MATCH(G$10,$B$110:$R$110,0),0),$E$38+('Input data'!$C$59-$E$38)/($N$10-$E$10)*(G10-$E$10)) -> 0.064666392 | H38: =IF(OR($C$3="EL",$C$3="CY",$C$3="IE",$C$3="PT"),VLOOKUP($C$3,$B$110:$R$114,MATCH(H$10,$B$110:$R$110,0),0),$E$38+('Input data'!$C$59-$E$38)/($N$10-$E$10)*(H10-$E$10)) -> 0.068021703 | I38: =IF(OR($C$3="EL",$C$3="CY",$C$3="IE",$C$3="PT"),VLOOKUP($C$3,$B$110:$R$114,MATCH(I$10,$B$110:$R$110,0),0),$E$38+('Input data'!$C$59-$E$38)/($N$10-$E$10)*(I10-$E$10)) -> 0.071377014 | J38: =IF(OR($C$3="EL",$C$3="CY",$C$3="IE",$C$3="PT"),VLOOKUP($C$3,$B$110:$R$114,MATCH(J$10,$B$110:$R$110,0),0),$E$38+('Input data'!$C$59-$E$38)/($N$10-$E$10)*(J10-$E$10)) -> 0.074732326 | K38: =IF(OR($C$3="EL",$C$3="CY",$C$3="IE",$C$3="PT"),VLOOKUP($C$3,$B$110:$R$114,MATCH(K$10,$B$110:$R$110,0),0),$E$38+('Input data'!$C$59-$E$38)/($N$10-$E$10)*(K10-$E$10)) -> 0.078087637 | L38: =IF(OR($C$3="EL",$C$3="CY",$C$3="IE",$C$3="PT"),VLOOKUP($C$3,$B$110:$R$114,MATCH(L$10,$B$110:$R$110,0),0),$E$38+('Input data'!$C$59-$E$38)/($N$10-$E$10)*(L10-$E$10)) -> 0.081442948 | M38: =IF(OR($C$3="EL",$C$3="CY",$C$3="IE",$C$3="PT"),VLOOKUP($C$3,$B$110:$R$114,MATCH(M$10,$B$110:$R$110,0),0),$E$38+('Input data'!$C$59-$E$38)/($N$10-$E$10)*(M10-$E$10)) -> 0.084798259 | N38: =IF(OR($C$3="EL",$C$3="CY",$C$3="IE",$C$3="PT"),VLOOKUP($C$3,$B$110:$R$114,MATCH(N$10,$B$110:$R$110,0),0),'Input data'!$C$59) -> 0.08815357 | O38: =IF(OR($C$3="EL",$C$3="CY",$C$3="IE",$C$3="PT"),VLOOKUP($C$3,$B$110:$R$114,MATCH(O$10,$B$110:$R$110,0),0),'Input data'!$C$59) -> 0.08815357 | P38: =IF(OR($C$3="EL",$C$3="CY",$C$3="IE",$C$3="PT"),VLOOKUP($C$3,$B$110:$R$114,MATCH(P$10,$B$110:$R$110,0),0),'Input data'!$C$59) -> 0.08815357 | Q38: =IF(OR($C$3="EL",$C$3="CY",$C$3="IE",$C$3="PT"),VLOOKUP($C$3,$B$110:$R$114,MATCH(Q$10,$B$110:$R$110,0),0),'Input data'!$C$59) -> 0.08815357 | R38: =IF(OR($C$3="EL",$C$3="CY",$C$3="IE",$C$3="PT"),VLOOKUP($C$3,$B$110:$R$114,MATCH(R$10,$B$110:$R$110,0),0),'Input data'!$C$59) -> 0.08815357 | S38: =IF(OR($C$3="EL",$C$3="CY",$C$3="IE",$C$3="PT"),VLOOKUP($C$3,$B$110:$U$114,MATCH(S$10,$B$110:$U$110,0),0),'Input data'!$C$59) -> 0.08815357 | T38: =IF(OR($C$3="EL",$C$3="CY",$C$3="IE",$C$3="PT"),VLOOKUP($C$3,$B$110:$U$114,MATCH(T$10,$B$110:$U$110,0),0),'Input data'!$C$59) -> 0.08815357 | U38: =IF(OR($C$3="EL",$C$3="CY",$C$3="IE",$C$3="PT"),VLOOKUP($C$3,$B$110:$U$114,MATCH(U$10,$B$110:$U$110,0),0),'Input data'!$C$59) -> 0.08815357
B40: Inflation and exchange rate
B41: GDP deflator (national currency) | C41: ='Input data'!C42 -> 5.744214 | D41: ='Input data'!D42 -> 3.154387 | E41: ='Input data'!E42 -> 3.262934 | F41: ='Input data'!F42 -> 2.103313 | G41: =$F$41+($N$41-$F$41)/($N$10-$F$10)*(G10-$F$10) -> 2.1253989 | H41: =$F$41+($N$41-$F$41)/($N$10-$F$10)*(H10-$F$10) -> 2.1474847 | I41: =$F$41+($N$41-$F$41)/($N$10-$F$10)*(I10-$F$10) -> 2.1695706 | J41: =$F$41+($N$41-$F$41)/($N$10-$F$10)*(J10-$F$10) -> 2.1916565 | K41: =$F$41+($N$41-$F$41)/($N$10-$F$10)*(K10-$F$10) -> 2.2137424 | L41: =$F$41+($N$41-$F$41)/($N$10-$F$10)*(L10-$F$10) -> 2.2358282 | M41: =$F$41+($N$41-$F$41)/($N$10-$F$10)*(M10-$F$10) -> 2.2579141 | N41: ='Input data'!$C$61 -> 2.28 | O41: =$N$41+('Input data'!$C$62-'Input data'!$C$61)/20*(O$10-$N$10) -> 2.266 | P41: =$N$41+('Input data'!$C$62-'Input data'!$C$61)/20*(P$10-$N$10) -> 2.252 | Q41: =$N$41+('Input data'!$C$62-'Input data'!$C$61)/20*(Q$10-$N$10) -> 2.238 | R41: =$N$41+('Input data'!$C$62-'Input data'!$C$61)/20*(R$10-$N$10) -> 2.224 | S41: =$N$41+('Input data'!$C$62-'Input data'!$C$61)/20*(S$10-$N$10) -> 2.21 | T41: =$N$41+('Input data'!$C$62-'Input data'!$C$61)/20*(T$10-$N$10) -> 2.196 | U41: =$N$41+('Input data'!$C$62-'Input data'!$C$61)/20*(U$10-$N$10) -> 2.182
B42: Exchange rate composite change (weighted by share of debt in each currency) | C42: 0.9999999 | D42: 1 | E42: 1 | F42: 0.9999999 | G42: 1 | H42: 1 | I42: 1 | J42: 1 | K42: 1 | L42: 1 | M42: 1 | N42: 1 | O42: 1 | P42: 1 | Q42: 1 | R42: 1 | S42: 1 | T42: 1 | U42: 1
B44: Intermediate calculations (growth rate equation)
B46: Fiscal multiplier | C46: ='Input data'!C49 -> 0.6
B47: Budget balance semi-elasticity | C47: ='Input data'!C50 -> 0.605
B49: Auxiliary variable to control the closure of the output gap | C49: 0 | D49: =IF(AND(ABS((D12-C12)-('Input data'!D13-'Input data'!C13))>0.0001,ABS(D12-C12)>0.0001,D$10>$C$5),4,IF(C49=4,3,IF(C49=3,2,IF(C49=2,1,0)))) -> 0 | E49: =IF(AND(ABS(E12-D12)>0.0001,E$10>$C$5),4,IF(D49=4,3,IF(D49=3,2,IF(D49=2,1,0)))) -> 0 | F49: =IF(AND(ABS(F12-E12)>0.0001,F$10>$C$5),4,IF(E49=4,3,IF(E49=3,2,IF(E49=2,1,0)))) -> 0 | G49: =IF(AND(ABS(G12-F12)>0.0001,G$10>$C$5),4,IF(F49=4,3,IF(F49=3,2,IF(F49=2,1,0)))) -> 0 | H49: =IF(AND(ABS(H12-G12)>0.0001,H$10>$C$5),4,IF(G49=4,3,IF(G49=3,2,IF(G49=2,1,0)))) -> 0 | I49: =IF(AND(ABS(I12-H12)>0.0001,I$10>$C$5),4,IF(H49=4,3,IF(H49=3,2,IF(H49=2,1,0)))) -> 0 | J49: =IF(AND(ABS(J12-I12)>0.0001,J$10>$C$5),4,IF(I49=4,3,IF(I49=3,2,IF(I49=2,1,0)))) -> 0 | K49: =IF(AND(ABS(K12-J12)>0.0001,K$10>$C$5),4,IF(J49=4,3,IF(J49=3,2,IF(J49=2,1,0)))) -> 0 | L49: =IF(AND(ABS(L12-K12)>0.0001,L$10>$C$5),4,IF(K49=4,3,IF(K49=3,2,IF(K49=2,1,0)))) -> 0 | ... U49: =IF(AND(ABS(U12-T12)>0.0001,U$10>$C$5),4,IF(T49=4,3,IF(T49=3,2,IF(T49=2,1,0)))) -> 0
B50: OG intermediate auxiliary value | C50: 0 | D50: =IF(C49=4,2/3*C29,IF(C49=3,1/3*#REF!,0)) -> 0 | E50: =IF(D49=4,2/3*D29,IF(D49=3,1/3*C29,0)) -> 0 | F50: =IF(E49=4,2/3*E29,IF(E49=3,1/3*D29,0)) -> 0 | G50: =IF(F49=4,2/3*F29,IF(F49=3,1/3*E29,0)) -> 0 | H50: =IF(G49=4,2/3*G29,IF(G49=3,1/3*F29,0)) -> 0 | I50: =IF(H49=4,2/3*H29,IF(H49=3,1/3*G29,0)) -> 0 | J50: =IF(I49=4,2/3*I29,IF(I49=3,1/3*H29,0)) -> 0 | K50: =IF(J49=4,2/3*J29,IF(J49=3,1/3*I29,0)) -> 0 | L50: =IF(K49=4,2/3*K29,IF(K49=3,1/3*J29,0)) -> 0 | ... U50: =IF(T49=4,2/3*T29,IF(T49=3,1/3*S29,0)) -> 0
B51: GDP intermediate growth rate - only feedback effect and no closure of the OG | C51: 0 | D51: ='Input data'!D30-$C$46*((D12-C12)-('Input data'!D13-'Input data'!C13)) -> 1.69667 | E51: ='Input data'!E30-$C$46*((E12-D12)-('Input data'!E13-'Input data'!D13)) -> 1.6083907 | F51: ='Input data'!F30-$C$46*((F12-E12)) -> 1.581865 | G51: ='Input data'!G30-$C$46*((G12-F12)) -> 1.521399 | H51: ='Input data'!H30-$C$46*((H12-G12)) -> 1.41368 | I51: ='Input data'!I30-$C$46*((I12-H12)) -> 1.393831 | J51: ='Input data'!J30-$C$46*((J12-I12)) -> 1.069126 | K51: ='Input data'!K30-$C$46*((K12-J12)) -> 1.03431 | L51: ='Input data'!L30-$C$46*((L12-K12)) -> 1.012531 | M51: ='Input data'!M30-$C$46*((M12-L12)) -> 1.026592 | ... U51: ='Input data'!U30-$C$46*((U12-T12)) -> 1.710004
B53: Debt projections
C55: ='Input data'!$C$5-1 -> 2024 | D55: =C55+1 -> 2025 | E55: =D55+1 -> 2026 | F55: =E55+1 -> 2027 | G55: =F55+1 -> 2028 | H55: =G55+1 -> 2029 | I55: =H55+1 -> 2030 | J55: =I55+1 -> 2031 | K55: =J55+1 -> 2032 | ... U55: =T55+1 -> 2042
B56: Gross debt | C56: =+'Input data'!C12 -> 43.74815 | D56: =+C56+D57 -> 45.15761 | E56: =+D56+E57 -> 47.861385 | F56: =+E56+F57 -> 48.251114 | G56: =+F56+G57 -> 48.658886 | H56: =+G56+H57 -> 49.108564 | I56: =+H56+I57 -> 49.559845 | J56: =+I56+J57 -> 50.526398 | K56: =+J56+K57 -> 51.770518 | ... U56: =+T56+U57 -> 72.409633
B57: Change in debt (-1+2+3) | D57: =-D58+D66+D71 -> 1.4094602 | E57: =-E58+E66+E71 -> 2.7037747 | F57: =-F58+F66+F71 -> 0.38972884 | G57: =-G58+G66+G71 -> 0.40777253 | H57: =-H58+H66+H71 -> 0.44967757 | I57: =-I58+I66+I71 -> 0.45128126 | J57: =-J58+J66+J71 -> 0.96655322 | K57: =-K58+K66+K71 -> 1.2441194 | ... U57: =-U58+U66+U71 -> 2.5121407
B58: (1) Primary balance (1.1 + 1.2 - 1.3 -1.4 -1.5 - 1.6 -1.7) | D58: =D59+D60-D61-D62-D63-D64-D65 -> -1.1575212 | E58: =E59+E60-E61-E62-E63-E64-E65 -> -1.9179957 | F58: =F59+F60-F61-F62-F63-F64-F65 -> -1.2629249 | G58: =G59+G60-G61-G62-G63-G64-G65 -> -1.204099 | H58: =H59+H60-H61-H62-H63-H64-H65 -> -1.1452689 | I58: =I59+I60-I61-I62-I63-I64-I65 -> -1.0864417 | J58: =J59+J60-J61-J62-J63-J64-J65 -> -1.3921832 | K58: =K59+K60-K61-K62-K63-K64-K65 -> -1.5979235 | ... U58: =U59+U60-U61-U62-U63-U64-U65 -> -2.7553206
B59: (1.1) Structural primary balance (before ageing cost) | D59: =D12 -> -0.5577395 | E59: =IF(E12="",D59,E12) -> -0.5577395 | F59: =IF(F12="",E59,F12) -> -0.5577395 | G59: =IF(G12="",F59,G12) -> -0.5577395 | H59: =IF(H12="",G59,H12) -> -0.5577395 | I59: =IF(I12="",H59,I12) -> -0.5577395 | J59: =IF(J12="",I59,J12) -> -0.5577395 | K59: =IF(K12="",J59,K12) -> -0.5577395 | L59: =IF(L12="",K59,L12) -> -0.5577395 | ... U59: =IF(U12="",T59,U12) -> -0.5577395
B60: (1.2) Cumulated budgetary effort (in terms of primary balance) | D60: 0 | E60: 0 | F60: 0 | G60: 0 | H60: 0 | I60: 0 | J60: 0 | K60: 0 | L60: 0 | M60: 0 | N60: 0 | O60: 0 | P60: 0 | Q60: 0 | R60: 0 | S60: 0 | T60: 0 | U60: 0
B61: (1.3) Cyclical component | D61: =-$C$47*D29 -> 0.57430421 | E61: =-$C$47*E29 -> 0.66441172 | F61: =-$C$47*F29 -> 0.49370469 | G61: =-$C$47*G29 -> 0.32913858 | H61: =-$C$47*H29 -> 0.16456822 | I61: =-$C$47*I29 -> 6.004402e-07 | J61: =-$C$47*J29 -> 1.7976406e-06 | K61: =-$C$47*K29 -> 1.7976406e-06 | ... U61: =-$C$47*U29 -> -4.1943813e-06
B62: (1.4) One-off and other temporary measures | D62: =-D13 -> 0.0254775 | E62: =-E13 -> 0.6901042 | F62: =-F13 -> 0 | G62: =-G13 -> 0 | H62: =-H13 -> 0 | I62: =-I13 -> 0 | J62: =-J13 -> 0 | K62: =-K13 -> 0 | ... U62: =-U13 -> 0
B63: (1.5) Cost of ageing | D63: =IF(D$55<=$C$5,0,HLOOKUP(D$55,'Input data'!$C$9:$AZ$26,12,FALSE)-HLOOKUP($C$5,'Input data'!$C$9:$AZ$26,12,FALSE)) -> 0 | E63: =IF(E$55<=$C$5,0,HLOOKUP(E$55,'Input data'!$C$9:$AZ$26,12,FALSE)-HLOOKUP($C$5,'Input data'!$C$9:$AZ$26,12,FALSE)) -> 0 | F63: =IF(F$55<=$C$5,0,HLOOKUP(F$55,'Input data'!$C$9:$AZ$26,12,FALSE)-HLOOKUP($C$5,'Input data'!$C$9:$AZ$26,12,FALSE)) -> 0.2 | G63: =IF(G$55<=$C$5,0,HLOOKUP(G$55,'Input data'!$C$9:$AZ$26,12,FALSE)-HLOOKUP($C$5,'Input data'!$C$9:$AZ$26,12,FALSE)) -> 0.3 | H63: =IF(H$55<=$C$5,0,HLOOKUP(H$55,'Input data'!$C$9:$AZ$26,12,FALSE)-HLOOKUP($C$5,'Input data'!$C$9:$AZ$26,12,FALSE)) -> 0.4 | I63: =IF(I$55<=$C$5,0,HLOOKUP(I$55,'Input data'!$C$9:$AZ$26,12,FALSE)-HLOOKUP($C$5,'Input data'!$C$9:$AZ$26,12,FALSE)) -> 0.5 | J63: =IF(J$55<=$C$5,0,HLOOKUP(J$55,'Input data'!$C$9:$AZ$26,12,FALSE)-HLOOKUP($C$5,'Input data'!$C$9:$AZ$26,12,FALSE)) -> 0.8 | K63: =IF(K$55<=$C$5,0,HLOOKUP(K$55,'Input data'!$C$9:$AZ$26,12,FALSE)-HLOOKUP($C$5,'Input data'!$C$9:$AZ$26,12,FALSE)) -> 1 | ... U63: =IF(U$55<=$C$5,0,HLOOKUP(U$55,'Input data'!$C$9:$AZ$26,12,FALSE)-HLOOKUP($C$5,'Input data'!$C$9:$AZ$26,12,FALSE)) -> 2.1
B64: (1.6) Property incomes | D64: =IF(D$55<=$C$5,0,-HLOOKUP(D$55,'Input data'!$C$9:$AZ$26,18,FALSE)+HLOOKUP($C$5,'Input data'!$C$9:$AZ$26,18,FALSE)) -> 0 | E64: =IF(E$55<=$C$5,0,-HLOOKUP(E$55,'Input data'!$C$9:$AZ$26,18,FALSE)+HLOOKUP($C$5,'Input data'!$C$9:$AZ$26,18,FALSE)) -> 0.0057403 | F64: =IF(F$55<=$C$5,0,-HLOOKUP(F$55,'Input data'!$C$9:$AZ$26,18,FALSE)+HLOOKUP($C$5,'Input data'!$C$9:$AZ$26,18,FALSE)) -> 0.0114807 | G64: =IF(G$55<=$C$5,0,-HLOOKUP(G$55,'Input data'!$C$9:$AZ$26,18,FALSE)+HLOOKUP($C$5,'Input data'!$C$9:$AZ$26,18,FALSE)) -> 0.0172209 | H64: =IF(H$55<=$C$5,0,-HLOOKUP(H$55,'Input data'!$C$9:$AZ$26,18,FALSE)+HLOOKUP($C$5,'Input data'!$C$9:$AZ$26,18,FALSE)) -> 0.0229612 | I64: =IF(I$55<=$C$5,0,-HLOOKUP(I$55,'Input data'!$C$9:$AZ$26,18,FALSE)+HLOOKUP($C$5,'Input data'!$C$9:$AZ$26,18,FALSE)) -> 0.0287016 | J64: =IF(J$55<=$C$5,0,-HLOOKUP(J$55,'Input data'!$C$9:$AZ$26,18,FALSE)+HLOOKUP($C$5,'Input data'!$C$9:$AZ$26,18,FALSE)) -> 0.0344419 | K64: =IF(K$55<=$C$5,0,-HLOOKUP(K$55,'Input data'!$C$9:$AZ$26,18,FALSE)+HLOOKUP($C$5,'Input data'!$C$9:$AZ$26,18,FALSE)) -> 0.0401822 | ... U64: =IF(U$55<=$C$5,0,-HLOOKUP(U$55,'Input data'!$C$9:$AZ$26,18,FALSE)+HLOOKUP($C$5,'Input data'!$C$9:$AZ$26,18,FALSE)) -> 0.0975853
B65: (1.7) Revenues | D65: 0 | E65: 0 | F65: 0 | G65: 0 | H65: 0 | I65: 0 | J65: 0 | K65: 0 | L65: 0 | M65: 0 | N65: 0 | O65: 0 | P65: 0 | Q65: 0 | R65: 0 | S65: 0 | T65: 0 | U65: 0
B66: (2) Snowball effect (2.1 + 2.2 + 2.3) | D66: =SUM(D67:D70) -> -1.328058 | E66: =SUM(E67:E70) -> -1.228898 | F66: =SUM(F67:F70) -> -0.873194 | G66: =SUM(G67:G70) -> -0.79632645 | H66: =SUM(H67:H70) -> -0.69559135 | I66: =SUM(I67:I70) -> -0.63516044 | J66: =SUM(J67:J70) -> -0.42562998 | K66: =SUM(K67:K70) -> -0.35380413 | ... U66: =SUM(U67:U70) -> -0.24317993
B67: (2.1) Interest expenditure | D67: =C56*D35/100*(1/(1+D32/100)) -> 0.71728823 | E67: =D56*E35/100*(1/(1+E32/100)) -> 0.74801829 | F67: =E56*F35/100*(1/(1+F32/100)) -> 0.84270245 | G67: =F56*G35/100*(1/(1+G32/100)) -> 0.91590137 | H67: =G56*H35/100*(1/(1+H32/100)) -> 0.99141468 | I67: =H56*I35/100*(1/(1+I32/100)) -> 1.0684054 | J67: =I56*J35/100*(1/(1+J32/100)) -> 1.1502656 | K67: =J56*K35/100*(1/(1+K32/100)) -> 1.2465422 | ... U67: =T56*U35/100*(1/(1+U32/100)) -> 2.3994753
B68: (2.2) Growth effect | D68: =-C56*(D23/100)*(1/(1+D32/100)) -> -0.70755897 | E68: =-D56*(E23/100)*(1/(1+E32/100)) -> -0.55001279 | F68: =-E56*(F23/100)*(1/(1+F32/100)) -> -0.72995933 | G68: =-F56*(G23/100)*(1/(1+G32/100)) -> -0.70804215 | H68: =-G56*(H23/100)*(1/(1+H32/100)) -> -0.66403208 | I68: =-H56*(I23/100)*(1/(1+I32/100)) -> -0.66074556 | J68: =-I56*(J23/100)*(1/(1+J32/100)) -> -0.51300888 | K68: =-J56*(K23/100)*(1/(1+K32/100)) -> -0.50604705 | ... U68: =-T56*(U23/100)*(1/(1+U32/100)) -> -1.1500604
B69: (2.3) Inflation effect | D69: =-C56*D41/100*(1/(1+D41/100)) -> -1.337787 | E69: =-D56*E41/100*(1/(1+E41/100)) -> -1.4269041 | F69: =-E56*F41/100*(1/(1+F41/100)) -> -0.98593738 | G69: =-F56*G41/100*(1/(1+G41/100)) -> -1.0041857 | H69: =-G56*H41/100*(1/(1+H41/100)) -> -1.022974 | I69: =-H56*I41/100*(1/(1+I41/100)) -> -1.0428203 | J69: =-I56*J41/100*(1/(1+J41/100)) -> -1.0628867 | K69: =-J56*K41/100*(1/(1+K41/100)) -> -1.0942993 | ... U69: =-T56*U41/100*(1/(1+U41/100)) -> -1.4925949
B70: (2.4) Exchange rate effect linked to the interest rate | D70: -2.8636209e-07 | E70: 5.7763161e-07 | F70: 2.6384936e-07 | G70: 0 | H70: 0 | I70: 0 | J70: 0 | K70: 0 | L70: 0 | M70: 0 | N70: 0 | O70: 0 | P70: 0 | Q70: 0 | R70: 0 | S70: 0 | T70: 0 | U70: 0
B71: (3 ) Stock flow adjustments (3.1 + 3.2) | D71: ='Input data'!D16 -> 1.579997 | E71: ='Input data'!E16 -> 2.014677 | F71: ='Input data'!F16 -> -2.05e-06 | G71: ='Input data'!G16 -> 0 | H71: ='Input data'!H16 -> 0 | I71: ='Input data'!I16 -> 0 | J71: ='Input data'!J16 -> 0 | K71: ='Input data'!K16 -> 0 | ... U71: ='Input data'!U16 -> 0
B72: (3.1) Base | D72: =D14 -> 1.579996 | E72: =E14 -> 2.014675 | F72: =F14 -> 0 | G72: =G14 -> 0 | H72: =H14 -> 0 | I72: =I14 -> 0 | J72: =J14 -> 0 | K72: =K14 -> 0 | ... U72: =U14 -> 0
B73: (3.2) Adjustment due to the exchange rate effect linked to debt value | D73: =+D71-D72 -> 1e-06 | E73: =+E71-E72 -> 2e-06 | F73: =+F71-F72 -> -2.05e-06 | G73: =+G71-G72 -> 0 | H73: =+H71-H72 -> 0 | I73: =+I71-I72 -> 0 | J73: =+J71-J72 -> 0 | K73: =+K71-K72 -> 0 | ... U73: =+U71-U72 -> 0
B75: Other budgetary variables
B76: Headline balance | C76: -0.9448897 | D76: =D58-D67-D70 -> -1.8748092 | E76: =E58-E67-E70 -> -2.6660146 | F76: =F58-F67-F70 -> -2.1056276 | G76: =G58-G67-G70 -> -2.1200004 | H76: =H58-H67-H70 -> -2.1366836 | I76: =I58-I67-I70 -> -2.1548471 | J76: =J58-J67-J70 -> -2.5424488 | K76: =K58-K67-K70 -> -2.8444657 | ... U76: =U58-U67-U70 -> -5.1547959
B77: Structural balance | C77: -0.3200694 | D77: =D59-D67-D70-D63-D64-D65 -> -1.2750274 | E77: =E59-E67-E70-E63-E64-E65 -> -1.3114987 | F77: =F59-F67-F70-F63-F64-F65 -> -1.6119229 | G77: =G59-G67-G70-G63-G64-G65 -> -1.7908618 | H77: =H59-H67-H70-H63-H64-H65 -> -1.9721154 | I77: =I59-I67-I70-I63-I64-I65 -> -2.1548465 | J77: =J59-J67-J70-J63-J64-J65 -> -2.542447 | K77: =K59-K67-K70-K63-K64-K65 -> -2.8444639 | ... U77: =U59-U67-U70-U63-U64-U65 -> -5.1548001
B78: Net expenditure growth | C78: ='Input data'!C45 -> 6.2115937 | D78: ='Input data'!D45 -> 7.2645885 | E78: ='Input data'!E33+E41-(E$12-D$12)/'Input data'!$C$64*100 -> 4.689191 | F78: ='Input data'!F33+F41-(F$12-E$12)/'Input data'!$C$64*100 -> 3.396196 | G78: ='Input data'!G33+G41-(G$12-F$12)/'Input data'!$C$64*100 -> 3.3691389 | H78: ='Input data'!H33+H41-(H$12-G$12)/'Input data'!$C$64*100 -> 3.2845498 | I78: ='Input data'!I33+I41-(I$12-H$12)/'Input data'!$C$64*100 -> 3.2875976 | J78: ='Input data'!J33+J41-(J$12-I$12)/'Input data'!$C$64*100 -> 3.2607845 | K78: ='Input data'!K33+K41-(K$12-J$12)/'Input data'!$C$64*100 -> 3.2480524 | L78: ='Input data'!L33+L41-(L$12-K$12)/'Input data'!$C$64*100 -> 3.2483582 | ... U78: ='Input data'!U33+U41-(U$12-T$12)/'Input data'!$C$64*100 -> 3.892
B81: Debt decomposition and IIR
B83: Auxiliary variable identifying whether debt is increasing | E83: =IF((E87-D87*E42/((1+E23/100)*(1+E41/100)))>0,1,0) -> 1 | F83: =IF((F87-E87*F42/((1+F23/100)*(1+F41/100)))>0,1,0) -> 1 | G83: =IF((G87-F87*G42/((1+G23/100)*(1+G41/100)))>0,1,0) -> 1 | H83: =IF((H87-G87*H42/((1+H23/100)*(1+H41/100)))>0,1,0) -> 1 | I83: =IF((I87-H87*I42/((1+I23/100)*(1+I41/100)))>0,1,0) -> 1 | J83: =IF((J87-I87*J42/((1+J23/100)*(1+J41/100)))>0,1,0) -> 1 | K83: =IF((K87-J87*K42/((1+K23/100)*(1+K41/100)))>0,1,0) -> 1 | L83: =IF((L87-K87*L42/((1+L23/100)*(1+L41/100)))>0,1,0) -> 1 | ... U83: =IF((U87-T87*U42/((1+U23/100)*(1+U41/100)))>0,1,0) -> 1
B84: Auxiliary variable identifying whether some debt is rolled over even though debt is decreasing | E84: =IF(AND(E83=0,ABS(E87-D87*E42/((1+E23/100)*(1+E41/100)))<((D93*D87*E42/((1+E23/100)*(1+E41/100))+(E38*D87*D94*E42/((1+E23/100)*(1+E41/100)))))),1,0) -> 0 | F84: =IF(AND(F83=0,ABS(F87-E87*F42/((1+F23/100)*(1+F41/100)))<((E93*E87*F42/((1+F23/100)*(1+F41/100))+(F38*E87*E94*F42/((1+F23/100)*(1+F41/100)))))),1,0) -> 0 | G84: =IF(AND(G83=0,ABS(G87-F87*G42/((1+G23/100)*(1+G41/100)))<((F93*F87*G42/((1+G23/100)*(1+G41/100))+(G38*F87*F94*G42/((1+G23/100)*(1+G41/100)))))),1,0) -> 0 | H84: =IF(AND(H83=0,ABS(H87-G87*H42/((1+H23/100)*(1+H41/100)))<((G93*G87*H42/((1+H23/100)*(1+H41/100))+(H38*G87*G94*H42/((1+H23/100)*(1+H41/100)))))),1,0) -> 0 | I84: =IF(AND(I83=0,ABS(I87-H87*I42/((1+I23/100)*(1+I41/100)))<((H93*H87*I42/((1+I23/100)*(1+I41/100))+(I38*H87*H94*I42/((1+I23/100)*(1+I41/100)))))),1,0) -> 0 | J84: =IF(AND(J83=0,ABS(J87-I87*J42/((1+J23/100)*(1+J41/100)))<((I93*I87*J42/((1+J23/100)*(1+J41/100))+(J38*I87*I94*J42/((1+J23/100)*(1+J41/100)))))),1,0) -> 0 | K84: =IF(AND(K83=0,ABS(K87-J87*K42/((1+K23/100)*(1+K41/100)))<((J93*J87*K42/((1+K23/100)*(1+K41/100))+(K38*J87*J94*K42/((1+K23/100)*(1+K41/100)))))),1,0) -> 0 | L84: =IF(AND(L83=0,ABS(L87-K87*L42/((1+L23/100)*(1+L41/100)))<((K93*K87*L42/((1+L23/100)*(1+L41/100))+(L38*K87*K94*L42/((1+L23/100)*(1+L41/100)))))),1,0) -> 0 | ... U84: =IF(AND(U83=0,ABS(U87-T87*U42/((1+U23/100)*(1+U41/100)))<((T93*T87*U42/((1+U23/100)*(1+U41/100))+(U38*T87*T94*U42/((1+U23/100)*(1+U41/100)))))),1,0) -> 0
C86: ='Input data'!$C$5-1 -> 2024 | D86: =C86+1 -> 2025 | E86: =D86+1 -> 2026 | F86: =E86+1 -> 2027 | G86: =F86+1 -> 2028 | H86: =G86+1 -> 2029 | I86: =H86+1 -> 2030 | J86: =I86+1 -> 2031 | K86: =J86+1 -> 2032 | ... U86: =T86+1 -> 2042
B87: Gross debt | C87: =C56 -> 43.74815 | D87: =D56 -> 45.15761 | E87: =D87*(1+E101/100)*E42-E59-E60+E61+E62+E63+E64+E65+E72 -> 47.861382 | F87: =E87*(1+F101/100)*F42-F59-F60+F61+F62+F63+F64+F65+F72 -> 48.251108 | G87: =F87*(1+G101/100)*G42-G59-G60+G61+G62+G63+G64+G65+G72 -> 48.658881 | H87: =G87*(1+H101/100)*H42-H59-H60+H61+H62+H63+H64+H65+H72 -> 49.108559 | I87: =H87*(1+I101/100)*I42-I59-I60+I61+I62+I63+I64+I65+I72 -> 49.55984 | J87: =I87*(1+J101/100)*J42-J59-J60+J61+J62+J63+J64+J65+J72 -> 50.526393 | K87: =J87*(1+K101/100)*K42-K59-K60+K61+K62+K63+K64+K65+K72 -> 51.770513 | L87: =K87*(1+L101/100)*L42-L59-L60+L61+L62+L63+L64+L65+L72 -> 53.188841 | ... U87: =T87*(1+U101/100)*U42-U59-U60+U61+U62+U63+U64+U65+U72 -> 72.409628
B88: Of which Outstanding debt | D88: ='Input data'!$C$66*D$87 -> 37.015024 | E88: =IF(E87=0,0,IF(E83=1,D87*E42/((1+E23/100)*(1+E41/100))-E89-E90,IF(AND(E83=0,E84=1),(1-D93-E38*D94)*D87*E42/((1+E23/100)*(1+E41/100)),E87))) -> 37.303082 | F88: =IF(F87=0,0,IF(F83=1,E87*F42/((1+F23/100)*(1+F41/100))-F89-F90,IF(AND(F83=0,F84=1),(1-E93-F38*E94)*E87*F42/((1+F23/100)*(1+F41/100)),F87))) -> 39.675616 | G88: =IF(G87=0,0,IF(G83=1,F87*G42/((1+G23/100)*(1+G41/100))-G89-G90,IF(AND(G83=0,G84=1),(1-F93-G38*F94)*F87*G42/((1+G23/100)*(1+G41/100)),G87))) -> 39.851933 | H88: =IF(H87=0,0,IF(H83=1,G87*H42/((1+H23/100)*(1+H41/100))-H89-H90,IF(AND(H83=0,H84=1),(1-G93-H38*G94)*G87*H42/((1+H23/100)*(1+H41/100)),H87))) -> 40.060276 | I88: =IF(I87=0,0,IF(I83=1,H87*I42/((1+I23/100)*(1+I41/100))-I89-I90,IF(AND(I83=0,I84=1),(1-H93-I38*H94)*H87*I42/((1+I23/100)*(1+I41/100)),I87))) -> 40.26668 | J88: =IF(J87=0,0,IF(J83=1,I87*J42/((1+J23/100)*(1+J41/100))-J89-J90,IF(AND(J83=0,J84=1),(1-I93-J38*I94)*I87*J42/((1+J23/100)*(1+J41/100)),J87))) -> 40.594382 | K88: =IF(K87=0,0,IF(K83=1,J87*K42/((1+K23/100)*(1+K41/100))-K89-K90,IF(AND(K83=0,K84=1),(1-J93-K38*J94)*J87*K42/((1+K23/100)*(1+K41/100)),K87))) -> 41.222406 | L88: =IF(L87=0,0,IF(L83=1,K87*L42/((1+L23/100)*(1+L41/100))-L89-L90,IF(AND(L83=0,L84=1),(1-K93-L38*K94)*K87*L42/((1+L23/100)*(1+L41/100)),L87))) -> 42.063685 | ... U88: =IF(U87=0,0,IF(U83=1,T87*U42/((1+U23/100)*(1+U41/100))-U89-U90,IF(AND(U83=0,U84=1),(1-T93-U38*T94)*T87*U42/((1+U23/100)*(1+U41/100)),U87))) -> 55.809821
B89: Rolled over long-term debt | D89: ='Input data'!$C$67*D$87 -> 3.5884993 | E89: =IF(E87=0,0,IF(E83=1,E38*D87*D94*E42/((1+E23/100)*(1+E41/100)),IF(AND(E83=0,E84=1),(E38*D87*D94*E42/((1+E23/100)*(1+E41/100)))*(1-ABS(E87-D87*E42/((1+E23/100)*(1+E41/100)))/((E38*D87*D94*E42/((1+E23/100)*(1+E41/100)))+(D93*D87*E42/((1+E23/100)*(1+E41/100))))),0))) -> 2.2949335 | F89: =IF(F87=0,0,IF(F83=1,F38*E87*E94*F42/((1+F23/100)*(1+F41/100)),IF(AND(F83=0,F84=1),(F38*E87*E94*F42/((1+F23/100)*(1+F41/100)))*(1-ABS(F87-E87*F42/((1+F23/100)*(1+F41/100)))/((F38*E87*E94*F42/((1+F23/100)*(1+F41/100)))+(E93*E87*F42/((1+F23/100)*(1+F41/100))))),0))) -> 2.5914388 | G89: =IF(G87=0,0,IF(G83=1,G38*F87*F94*G42/((1+G23/100)*(1+G41/100)),IF(AND(G83=0,G84=1),(G38*F87*F94*G42/((1+G23/100)*(1+G41/100)))*(1-ABS(G87-F87*G42/((1+G23/100)*(1+G41/100)))/((G38*F87*F94*G42/((1+G23/100)*(1+G41/100)))+(F93*F87*G42/((1+G23/100)*(1+G41/100))))),0))) -> 2.755253 | H89: =IF(H87=0,0,IF(H83=1,H38*G87*G94*H42/((1+H23/100)*(1+H41/100)),IF(AND(H83=0,H84=1),(H38*G87*G94*H42/((1+H23/100)*(1+H41/100)))*(1-ABS(H87-G87*H42/((1+H23/100)*(1+H41/100)))/((H38*G87*G94*H42/((1+H23/100)*(1+H41/100)))+(G93*G87*H42/((1+H23/100)*(1+H41/100))))),0))) -> 2.9238537 | I89: =IF(I87=0,0,IF(I83=1,I38*H87*H94*I42/((1+I23/100)*(1+I41/100)),IF(AND(I83=0,I84=1),(I38*H87*H94*I42/((1+I23/100)*(1+I41/100)))*(1-ABS(I87-H87*I42/((1+I23/100)*(1+I41/100)))/((I38*H87*H94*I42/((1+I23/100)*(1+I41/100)))+(H93*H87*I42/((1+I23/100)*(1+I41/100))))),0))) -> 3.0950294 | J89: =IF(J87=0,0,IF(J83=1,J38*I87*I94*J42/((1+J23/100)*(1+J41/100)),IF(AND(J83=0,J84=1),(J38*I87*I94*J42/((1+J23/100)*(1+J41/100)))*(1-ABS(J87-I87*J42/((1+J23/100)*(1+J41/100)))/((J38*I87*I94*J42/((1+J23/100)*(1+J41/100)))+(I93*I87*J42/((1+J23/100)*(1+J41/100))))),0))) -> 3.2787404 | K89: =IF(K87=0,0,IF(K83=1,K38*J87*J94*K42/((1+K23/100)*(1+K41/100)),IF(AND(K83=0,K84=1),(K38*J87*J94*K42/((1+K23/100)*(1+K41/100)))*(1-ABS(K87-J87*K42/((1+K23/100)*(1+K41/100)))/((K38*J87*J94*K42/((1+K23/100)*(1+K41/100)))+(J93*J87*K42/((1+K23/100)*(1+K41/100))))),0))) -> 3.491612 | L89: =IF(L87=0,0,IF(L83=1,L38*K87*K94*L42/((1+L23/100)*(1+L41/100)),IF(AND(L83=0,L84=1),(L38*K87*K94*L42/((1+L23/100)*(1+L41/100)))*(1-ABS(L87-K87*L42/((1+L23/100)*(1+L41/100)))/((L38*K87*K94*L42/((1+L23/100)*(1+L41/100)))+(K93*K87*L42/((1+L23/100)*(1+L41/100))))),0))) -> 3.7295348 | ... U89: =IF(U87=0,0,IF(U83=1,U38*T87*T94*U42/((1+U23/100)*(1+U41/100)),IF(AND(U83=0,U84=1),(U38*T87*T94*U42/((1+U23/100)*(1+U41/100)))*(1-ABS(U87-T87*U42/((1+U23/100)*(1+U41/100)))/((U38*T87*T94*U42/((1+U23/100)*(1+U41/100)))+(T93*T87*U42/((1+U23/100)*(1+U41/100))))),0))) -> 5.3954644
B90: Rolled over short-term debt | D90: ='Input data'!$C$68*D$87 -> 3.6736521 | E90: =IF(E87=0,0,IF(E83=1,(1-D94)*D87*E42/((1+E23/100)*(1+E41/100)),IF(AND(E83=0,E84=1),(D93*D87*E42/((1+E23/100)*(1+E41/100)))*(1-ABS(E87-D87*E42/((1+E23/100)*(1+E41/100)))/((E38*D87*D94*E42/((1+E23/100)*(1+E41/100)))+(D93*D87*E42/((1+E23/100)*(1+E41/100))))),0))) -> 3.5826776 | F90: =IF(F87=0,0,IF(F83=1,(1-E94)*E87*F42/((1+F23/100)*(1+F41/100)),IF(AND(F83=0,F84=1),(E93*E87*F42/((1+F23/100)*(1+F41/100)))*(1-ABS(F87-E87*F42/((1+F23/100)*(1+F41/100)))/((F38*E87*E94*F42/((1+F23/100)*(1+F41/100)))+(E93*E87*F42/((1+F23/100)*(1+F41/100))))),0))) -> 3.8784259 | G90: =IF(G87=0,0,IF(G83=1,(1-F94)*F87*G42/((1+G23/100)*(1+G41/100)),IF(AND(G83=0,G84=1),(F93*F87*G42/((1+G23/100)*(1+G41/100)))*(1-ABS(G87-F87*G42/((1+G23/100)*(1+G41/100)))/((G38*F87*F94*G42/((1+G23/100)*(1+G41/100)))+(F93*F87*G42/((1+G23/100)*(1+G41/100))))),0))) -> 3.9316942 | H90: =IF(H87=0,0,IF(H83=1,(1-G94)*G87*H42/((1+H23/100)*(1+H41/100)),IF(AND(H83=0,H84=1),(G93*G87*H42/((1+H23/100)*(1+H41/100)))*(1-ABS(H87-G87*H42/((1+H23/100)*(1+H41/100)))/((H38*G87*G94*H42/((1+H23/100)*(1+H41/100)))+(G93*G87*H42/((1+H23/100)*(1+H41/100))))),0))) -> 3.9877449 | I90: =IF(I87=0,0,IF(I83=1,(1-H94)*H87*I42/((1+I23/100)*(1+I41/100)),IF(AND(I83=0,I84=1),(H93*H87*I42/((1+I23/100)*(1+I41/100)))*(1-ABS(I87-H87*I42/((1+I23/100)*(1+I41/100)))/((I38*H87*H94*I42/((1+I23/100)*(1+I41/100)))+(H93*H87*I42/((1+I23/100)*(1+I41/100))))),0))) -> 4.0432835 | J90: =IF(J87=0,0,IF(J83=1,(1-I94)*I87*J42/((1+J23/100)*(1+J41/100)),IF(AND(J83=0,J84=1),(I93*I87*J42/((1+J23/100)*(1+J41/100)))*(1-ABS(J87-I87*J42/((1+J23/100)*(1+J41/100)))/((J38*I87*I94*J42/((1+J23/100)*(1+J41/100)))+(I93*I87*J42/((1+J23/100)*(1+J41/100))))),0))) -> 4.1108223 | K90: =IF(K87=0,0,IF(K83=1,(1-J94)*J87*K42/((1+K23/100)*(1+K41/100)),IF(AND(K83=0,K84=1),(J93*J87*K42/((1+K23/100)*(1+K41/100)))*(1-ABS(K87-J87*K42/((1+K23/100)*(1+K41/100)))/((K38*J87*J94*K42/((1+K23/100)*(1+K41/100)))+(J93*J87*K42/((1+K23/100)*(1+K41/100))))),0))) -> 4.212029 | L90: =IF(L87=0,0,IF(L83=1,(1-K94)*K87*L42/((1+L23/100)*(1+L41/100)),IF(AND(L83=0,L84=1),(K93*K87*L42/((1+L23/100)*(1+L41/100)))*(1-ABS(L87-K87*L42/((1+L23/100)*(1+L41/100)))/((L38*K87*K94*L42/((1+L23/100)*(1+L41/100)))+(K93*K87*L42/((1+L23/100)*(1+L41/100))))),0))) -> 4.3375173 | ... U90: =IF(U87=0,0,IF(U83=1,(1-T94)*T87*U42/((1+U23/100)*(1+U41/100)),IF(AND(U83=0,U84=1),(T93*T87*U42/((1+U23/100)*(1+U41/100)))*(1-ABS(U87-T87*U42/((1+U23/100)*(1+U41/100)))/((U38*T87*T94*U42/((1+U23/100)*(1+U41/100)))+(T93*T87*U42/((1+U23/100)*(1+U41/100))))),0))) -> 6.0495465
B91: New long-term debt | D91: ='Input data'!$C$69*D$87 -> 0.80738171 | E91: =IF(E87=0,0,IF(E83=1,'Input data'!$C$58*(E87-D87*E42/((1+E23/100)*(1+E41/100))),0)) -> 4.240723 | F91: =IF(F87=0,0,IF(F83=1,'Input data'!$C$58*(F87-E87*F42/((1+F23/100)*(1+F41/100))),0)) -> 1.9077067 | G91: =IF(G87=0,0,IF(G83=1,'Input data'!$C$58*(G87-F87*G42/((1+G23/100)*(1+G41/100))),0)) -> 1.9207287 | H91: =IF(H87=0,0,IF(H83=1,'Input data'!$C$58*(H87-G87*H42/((1+H23/100)*(1+H41/100))),0)) -> 1.9358438 | I91: =IF(I87=0,0,IF(I83=1,'Input data'!$C$58*(I87-H87*I42/((1+I23/100)*(1+I41/100))),0)) -> 1.9523 | J91: =IF(J87=0,0,IF(J83=1,'Input data'!$C$58*(J87-I87*J42/((1+J23/100)*(1+J41/100))),0)) -> 2.3034687 | K91: =IF(K87=0,0,IF(K83=1,'Input data'!$C$58*(K87-J87*K42/((1+K23/100)*(1+K41/100))),0)) -> 2.5770972 | L91: =IF(L87=0,0,IF(L83=1,'Input data'!$C$58*(L87-K87*L42/((1+L23/100)*(1+L41/100))),0)) -> 2.7706538 | ... U91: =IF(U87=0,0,IF(U83=1,'Input data'!$C$58*(U87-T87*U42/((1+U23/100)*(1+U41/100))),0)) -> 4.6702656
B92: New short-term debt | D92: ='Input data'!$C$70*D$87 -> 0.073048801 | E92: =IF(E87=0,0,IF(E83=1,'Input data'!$C$57*(E87-D87*E42/((1+E23/100)*(1+E41/100))),0)) -> 0.43996604 | F92: =IF(F87=0,0,IF(F83=1,'Input data'!$C$57*(F87-E87*F42/((1+F23/100)*(1+F41/100))),0)) -> 0.19792053 | G92: =IF(G87=0,0,IF(G83=1,'Input data'!$C$57*(G87-F87*G42/((1+G23/100)*(1+G41/100))),0)) -> 0.19927154 | H92: =IF(H87=0,0,IF(H83=1,'Input data'!$C$57*(H87-G87*H42/((1+H23/100)*(1+H41/100))),0)) -> 0.2008397 | I92: =IF(I87=0,0,IF(I83=1,'Input data'!$C$57*(I87-H87*I42/((1+I23/100)*(1+I41/100))),0)) -> 0.20254699 | J92: =IF(J87=0,0,IF(J83=1,'Input data'!$C$57*(J87-I87*J42/((1+J23/100)*(1+J41/100))),0)) -> 0.23898001 | K92: =IF(K87=0,0,IF(K83=1,'Input data'!$C$57*(K87-J87*K42/((1+K23/100)*(1+K41/100))),0)) -> 0.26736839 | L92: =IF(L87=0,0,IF(L83=1,'Input data'!$C$57*(L87-K87*L42/((1+L23/100)*(1+L41/100))),0)) -> 0.28744948 | ... U92: =IF(U87=0,0,IF(U83=1,'Input data'!$C$57*(U87-T87*U42/((1+U23/100)*(1+U41/100))),0)) -> 0.48453018
B93: Share of short-term debt in total government debt | D93: =IF(D87<>0,(D90+D92)/(D88+D89+D90+D91+D92),0) -> 0.082969432 | E93: =IF(E87<>0,(E90+E92)/(E88+E89+E90+E91+E92),0) -> 0.084047795 | F93: =IF(F87<>0,(F90+F92)/(F88+F89+F90+F91+F92),0) -> 0.084481924 | G93: =IF(G87<>0,(G90+G92)/(G88+G89+G90+G91+G92),0) -> 0.084896439 | H93: =IF(H87<>0,(H90+H92)/(H88+H89+H90+H91+H92),0) -> 0.085292356 | I93: =IF(I87<>0,(I90+I92)/(I88+I89+I90+I91+I92),0) -> 0.085670788 | J93: =IF(J87<>0,(J90+J92)/(J88+J89+J90+J91+J92),0) -> 0.086089706 | K93: =IF(K87<>0,(K90+K92)/(K88+K89+K90+K91+K92),0) -> 0.086524107 | ... U93: =IF(U87<>0,(U90+U92)/(U88+U89+U90+U91+U92),0) -> 0.090237678
B94: Share of long-term debt in total government debt | D94: =IF(D87<>0,(D88+D89+D91)/(D88+D89+D90+D91+D92),1) -> 0.91703057 | E94: =IF(E87<>0,(E88+E89+E91)/(E88+E89+E90+E91+E92),1) -> 0.9159522 | F94: =IF(F87<>0,(F88+F89+F91)/(F88+F89+F90+F91+F92),1) -> 0.91551808 | G94: =IF(G87<>0,(G88+G89+G91)/(G88+G89+G90+G91+G92),1) -> 0.91510356 | H94: =IF(H87<>0,(H88+H89+H91)/(H88+H89+H90+H91+H92),1) -> 0.91470764 | I94: =IF(I87<>0,(I88+I89+I91)/(I88+I89+I90+I91+I92),1) -> 0.91432921 | J94: =IF(J87<>0,(J88+J89+J91)/(J88+J89+J90+J91+J92),1) -> 0.91391029 | K94: =IF(K87<>0,(K88+K89+K91)/(K88+K89+K90+K91+K92),1) -> 0.91347589 | ... U94: =IF(U87<>0,(U88+U89+U91)/(U88+U89+U90+U91+U92),1) -> 0.90976232
B96: IIR | C96: =C35 -> 1.646586 | D96: =D35 -> 1.72 | E96: =E98+E99 -> 1.732298 | F96: =F98+F99 -> 1.826186 | G96: =G98+G99 -> 1.9680346 | H96: =H98+H99 -> 2.1106557 | I96: =I98+I99 -> 2.2537821 | J96: =J98+J99 -> 2.3971883 | K96: =K98+K99 -> 2.5478088 | L96: =L98+L99 -> 2.7018156 | ... U96: =U98+U99 -> 3.5677364
B97: Long-term implicit interest rate | E97: =((E35*D87)-(E37*(D90+D92)))/(D88+D89+D91) -> 1.7160168 | F97: =((F35*E87)-(F37*(E90+E92)))/(E88+E89+E91) -> 1.8080002 | G97: =IF(F87>0,(F97*F88+G36*(F91+F89))/(F88+F89+F91),G36) -> 1.9486196 | H97: =IF(G87>0,(G97*G88+H36*(G91+G89))/(G88+G89+G91),H36) -> 2.0900757 | I97: =IF(H87>0,(H97*H88+I36*(H91+H89))/(H88+H89+H91),I36) -> 2.232078 | J97: =IF(I87>0,(I97*I88+J36*(I91+I89))/(I88+I89+I91),J36) -> 2.3743809 | K97: =IF(J87>0,(J97*J88+K36*(J91+J89))/(J88+J89+J91),K36) -> 2.5245556 | L97: =IF(K87>0,(K97*K88+L36*(K91+K89))/(K88+K89+K91),L36) -> 2.6784293 | M97: =IF(L87>0,(L97*L88+M36*(L91+L89))/(L88+L89+L91),M36) -> 2.8326489 | N97: =IF(M87>0,(M97*M88+N36*(M91+M89))/(M88+M89+M91),N36) -> 2.986474 | ... U97: =IF(T87>0,(T97*T88+U36*(T91+T89))/(T88+T89+T91),U36) -> 3.6419454
B98: Nominal implicit interest rate on debt (Excel approximation) | E98: =E35 -> 1.732298 | F98: =F35 -> 1.826186 | G98: =(G97*(F88+F89+F91)+G37*(F90+F92))/F87 -> 1.9680346 | H98: =(H97*(G88+G89+G91)+H37*(G90+G92))/G87 -> 2.1106557 | I98: =(I97*(H88+H89+H91)+I37*(H90+H92))/H87 -> 2.2537821 | J98: =(J97*(I88+I89+I91)+J37*(I90+I92))/I87 -> 2.3971883 | K98: =(K97*(J88+J89+J91)+K37*(J90+J92))/J87 -> 2.5478088 | L98: =(L97*(K88+K89+K91)+L37*(K90+K92))/K87 -> 2.7018156 | M98: =(M97*(L88+L89+L91)+M37*(L90+L92))/L87 -> 2.8561372 | N98: =(N97*(M88+M89+M91)+N37*(M90+M92))/M87 -> 3.0100965 | ... U98: =(U97*(T88+T89+T91)+U37*(T90+T92))/T87 -> 3.5677364
B99: Diff. STATA | E99: =E108 -> 0 | F99: =F108 -> 0 | G99: =G108 -> 0 | H99: =H108 -> 0 | I99: =I108 -> 0 | J99: =J108 -> 0 | K99: =K108 -> 0 | L99: =L108 -> 0 | ... U99: =U108 -> 0
B101: (i - g) | C101: =((1+C96/100)/((1+C23/100)*(1+C41/100))-1)*100 -> -4.9030404 | D101: =((1+D96/100)/((1+D23/100)*(1+D41/100))-1)*100 -> -3.0356889 | E101: =((1+E96/100)/((1+E23/100)*(1+E41/100))-1)*100 -> -2.7213543 | F101: =((1+F96/100)/((1+F23/100)*(1+F41/100))-1)*100 -> -1.8244233 | G101: =((1+G96/100)/((1+G23/100)*(1+G41/100))-1)*100 -> -1.6503794 | H101: =((1+H96/100)/((1+H23/100)*(1+H41/100))-1)*100 -> -1.4295258 | I101: =((1+I96/100)/((1+I23/100)*(1+I41/100))-1)*100 -> -1.2933802 | J101: =((1+J96/100)/((1+J23/100)*(1+J41/100))-1)*100 -> -0.85882024 | ... U101: =((1+U96/100)/((1+U23/100)*(1+U41/100))-1)*100 -> -0.34790938
B104: Per memo - STATA results
B106: Debt | C106: 43.74815 | D106: 45.1576 | E106: 47.86137 | F106: 48.2511 | G106: 48.6589 | H106: 49.10862 | I106: 49.55998 | J106: 50.52662 | K106: 51.77084 | L106: 53.18928 | M106: 54.76633 | N106: 56.49673 | O106: 58.4568 | P106: 60.63898 | Q106: 62.83595 | R106: 65.08957 | S106: 67.3895 | T106: 69.8982 | U106: 72.41024
B107: IIR | C107: 1.646586 | D107: 1.72 | E107: 1.732298 | F107: 1.826186 | G107: 1.968095 | H107: 2.110767 | I107: 2.253937 | J107: 2.397379 | K107: 2.548027 | L107: 2.702054 | M107: 2.856389 | N107: 3.010357 | O107: 3.130574 | P107: 3.235227 | Q107: 3.325646 | R107: 3.401768 | S107: 3.466397 | T107: 3.521078 | U107: 3.567581
B108: IIR difference STATA - Excel | C108: 0 | D108: 0 | E108: 0 | F108: 0 | G108: 0 | H108: 0 | I108: 0 | J108: 0 | K108: 0 | L108: 0 | M108: 0 | N108: 0 | O108: 0 | P108: 0 | Q108: 0 | R108: 0 | S108: 0 | T108: 0 | U108: 0
B110: Share of long-term debt that matures every year | C110: 2024 | D110: 2025 | E110: 2026 | F110: 2027 | G110: 2028 | H110: 2029 | I110: 2030 | J110: 2031 | K110: 2032 | L110: 2033 | M110: 2034 | N110: 2035 | O110: 2036 | P110: 2037 | Q110: 2038 | R110: 2039 | S110: 2040 | T110: 2041 | U110: 2042
B111: CY | C111: 0.08487931 | D111: 0.0769344 | E111: 0.13354815 | F111: 0.13562493 | G111: 0.14684963 | H111: 0.14741722 | I111: 0.13492288 | J111: 0.14362449 | K111: 0.07467558 | L111: 0.07310075 | M111: 0.0711524 | N111: 0.06906617 | O111: 0.06860895 | P111: 0.07141245 | Q111: 0.06724809 | R111: 0.06704172 | S111: 0.06713814 | T111: 0.06694167 | U111: 0.06669118
B112: EL | C112: 0.03552199 | D112: 0.02405701 | E112: 0.02509384 | F112: 0.02604183 | G112: 0.03561506 | H112: 0.03741933 | I112: 0.04395068 | J112: 0.05486258 | K112: 0.05768945 | L112: 0.08553542 | M112: 0.07344287 | N112: 0.08832139 | O112: 0.0864061 | P112: 0.10192441 | Q112: 0.11969403 | R112: 0.10295368 | S112: 0.11310902 | T112: 0.1178079 | U112: 0.12795295
B113: IE | C113: 0.05420534 | D113: 0.07887117 | E113: 0.07759969 | F113: 0.07603595 | G113: 0.07466063 | H113: 0.07325804 | I113: 0.07175373 | J113: 0.07046832 | K113: 0.06904033 | L113: 0.06762434 | M113: 0.06595626 | N113: 0.06453752 | O113: 0.06458406 | P113: 0.06457946 | Q113: 0.06457418 | R113: 0.06456769 | S113: 0.0645614 | T113: 0.06455814 | U113: 0.06455011
B114: PT | C114: 0.0491371 | D114: 0.06577118 | E114: 0.07819698 | F114: 0.07733638 | G114: 0.07491418 | H114: 0.07134426 | I114: 0.06298139 | J114: 0.0990989 | K114: 0.07821122 | L114: 0.07902062 | M114: 0.06478691 | N114: 0.08320267 | O114: 0.08569031 | P114: 0.06335123 | Q114: 0.07488801 | R114: 0.06062613 | S114: 0.06374597 | T114: 0.06058587 | U114: 0.06443196

Sheet Adjustment scenario
B3: Country | C3: ='Input data'!C3 -> NL
B4: Key years
B5: ='Input data'!B5 -> Last year before the adjustment | C5: =+'Input data'!C5 -> 2025
B6: Last year of adjustment | C6: =+C5+'Criteria results'!$F$5 -> 2029
B7: Last year of no-fiscal-policy-change projections | C7: =C5+'Criteria results'!$F$5+10 -> 2039
B9: Key assumptions
C10: ='Input data'!$C$5-1 -> 2024 | D10: =C10+1 -> 2025 | E10: =D10+1 -> 2026 | F10: =E10+1 -> 2027 | G10: =F10+1 -> 2028 | H10: =G10+1 -> 2029 | I10: =H10+1 -> 2030 | J10: =I10+1 -> 2031 | K10: =J10+1 -> 2032 | ... U10: =T10+1 -> 2042
B11: Fiscal assumptions (% of GDP)
B12: Structural primary balance ('+' means 'surplus') | C12: ='Input data'!C13 -> 0.386237 | D12: ='Input data'!D13 -> -0.5577395 | E12: =IF(E10<=$C$6, IF(AND(D78<=-1.55,'Criteria results'!$F$5=4,'Criteria results'!$F$6<0.4),D12+0.4, IF(AND(D78<=-1.55,'Criteria results'!$F$5=7,'Criteria results'!$F$6<0.25),D12+0.25, D12+'Criteria results'!$F$6)),D12) -> -0.5577395 | F12: =IF(F10<=$C$6, IF(AND(E78<=-1.55,'Criteria results'!$F$5=4,'Criteria results'!$F$6<0.4),E12+0.4, IF(AND(E78<=-1.55,'Criteria results'!$F$5=7,'Criteria results'!$F$6<0.25),E12+0.25, E12+'Criteria results'!$F$6)),E12) -> -0.5577395 | G12: =IF(G10<=$C$6, IF(AND(F78<=-1.55,'Criteria results'!$F$5=4,'Criteria results'!$F$6<0.4),F12+0.4, IF(AND(F78<=-1.55,'Criteria results'!$F$5=7,'Criteria results'!$F$6<0.25),F12+0.25, F12+'Criteria results'!$F$6)),F12) -> -0.5577395 | H12: =IF(H10<=$C$6, IF(AND(G78<=-1.55,'Criteria results'!$F$5=4,'Criteria results'!$F$6<0.4),G12+0.4, IF(AND(G78<=-1.55,'Criteria results'!$F$5=7,'Criteria results'!$F$6<0.25),G12+0.25, G12+'Criteria results'!$F$6)),G12) -> -0.5577395 | I12: =IF(I10<=$C$6, IF(AND(H78<=-1.55,'Criteria results'!$F$5=4,'Criteria results'!$F$6<0.4),H12+0.4, IF(AND(H78<=-1.55,'Criteria results'!$F$5=7,'Criteria results'!$F$6<0.25),H12+0.25, H12+'Criteria results'!$F$6)),H12) -> -0.5577395 | J12: =IF(J10<=$C$6, IF(AND(I78<=-1.55,'Criteria results'!$F$5=4,'Criteria results'!$F$6<0.4),I12+0.4, IF(AND(I78<=-1.55,'Criteria results'!$F$5=7,'Criteria results'!$F$6<0.25),I12+0.25, I12+'Criteria results'!$F$6)),I12) -> -0.5577395 | K12: =IF(K10<=$C$6, IF(AND(J78<=-1.55,'Criteria results'!$F$5=4,'Criteria results'!$F$6<0.4),J12+0.4, IF(AND(J78<=-1.55,'Criteria results'!$F$5=7,'Criteria results'!$F$6<0.25),J12+0.25, J12+'Criteria results'!$F$6)),J12) -> -0.5577395 | L12: =K12 -> -0.5577395 | M12: =L12 -> -0.5577395 | N12: =M12 -> -0.5577395 | O12: =N12 -> -0.5577395 | P12: =O12 -> -0.5577395 | Q12: =P12 -> -0.5577395 | R12: =Q12 -> -0.5577395 | S12: =R12 -> -0.5577395 | ... U12: =T12 -> -0.5577395
B13: Annual change in SPB | E13: =E12-D12 -> 0 | F13: =F12-E12 -> 0 | G13: =G12-F12 -> 0 | H13: =H12-G12 -> 0 | I13: =I12-H12 -> 0 | J13: =J12-I12 -> 0 | K13: =K12-J12 -> 0 | L13: =L12-K12 -> 0 | ... U13: =U12-T12 -> 0
B14: One-off and other temporary measures | C14: ='Input data'!C14 -> -0.026727 | D14: ='Input data'!D14 -> -0.0254775 | E14: ='Input data'!E14 -> -0.6901042 | F14: ='Input data'!F14 -> 0 | G14: ='Input data'!G14 -> 0 | H14: ='Input data'!H14 -> 0 | I14: ='Input data'!I14 -> 0 | J14: ='Input data'!J14 -> 0 | ... U14: ='Input data'!U14 -> 0
B15: Stock flow adjustments (without exchange rate effect) | C15: ='Input data'!C15 -> -0.0919396 | D15: ='Input data'!D15 -> 1.579996 | E15: ='Input data'!E15 -> 2.014675 | F15: ='Input data'!F15 -> 0 | G15: ='Input data'!G15 -> 0 | H15: ='Input data'!H15 -> 0 | I15: ='Input data'!I15 -> 0 | J15: ='Input data'!J15 -> 0 | ... U15: ='Input data'!U15 -> 0
B17: ='Input data'!B19 -> Cost of ageing and selected public revenue (based on the Commission-Council 2024 Ageing Report ("AR 2024"))
B18: Total ageing cost (net of taxes on pensions) | C18: ='Input data'!C20 -> 18.2 | D18: ='Input data'!D20 -> 18.1 | E18: ='Input data'!E20 -> 18.1 | F18: ='Input data'!F20 -> 18.3 | G18: ='Input data'!G20 -> 18.4 | H18: ='Input data'!H20 -> 18.5 | I18: ='Input data'!I20 -> 18.6 | J18: ='Input data'!J20 -> 18.9 | ... U18: ='Input data'!U20 -> 20.2
B19: Property income | C19: ='Input data'!C26 -> 0.6265708 | D19: ='Input data'!D26 -> 0.6208305 | E19: ='Input data'!E26 -> 0.6150902 | F19: ='Input data'!F26 -> 0.6093498 | G19: ='Input data'!G26 -> 0.6036096 | H19: ='Input data'!H26 -> 0.5978693 | I19: ='Input data'!I26 -> 0.5921289 | J19: ='Input data'!J26 -> 0.5863886 | ... U19: ='Input data'!U26 -> 0.5232452
B21: GDP growth assumptions
B22: Actual GDP (real)
B23: Level | C23: ='Baseline NFPC'!C22 -> 915.5005 | D23: ='Baseline NFPC'!D22 -> 931.03352 | E23: =IF(AND(E50>1,D50>1), E27*(1+('Baseline NFPC'!E$29+E51)/100)-D23*$C$47*(E12-D12)/100, IF(E50=1,E27,D23*(1+E52/100))) -> 942.89253 | F23: =IF(AND(F50>1,E50>1), F27*(1+('Baseline NFPC'!F$29+F51)/100)-E23*$C$47*(F12-E12)/100, IF(F50=1,F27,E23*(1+F52/100))) -> 957.80782 | G23: =IF(AND(G50>1,F50>1), G27*(1+G51/100)-F23*$C$47*(G12-F12)/100, IF(G50=1,G27,F23*(1+G52/100))) -> 972.3799 | H23: =IF(AND(H50>1,G50>1), H27*(1+H51/100)-G23*$C$47*(H12-G12)/100, IF(H50=1,H27,G23*(1+H52/100))) -> 986.12624 | I23: =IF(AND(I50>1,H50>1), I27*(1+I51/100)-H23*$C$47*(I12-H12)/100, IF(I50=1,I27,H23*(1+I52/100))) -> 999.87117 | J23: =IF(AND(J50>1,I50>1), J27*(1+J51/100)-I23*$C$47*(J12-I12)/100, IF(J50=1,J27,I23*(1+J52/100))) -> 1010.5611 | K23: =IF(AND(K50>1,J50>1), K27*(1+K51/100)-J23*$C$47*(K12-J12)/100, IF(K50=1,K27,J23*(1+K52/100))) -> 1021.0134 | L23: =IF(AND(L50>1,K50>1), L27*(1+L51/100)-K23*$C$47*(L12-K12)/100, IF(L50=1,L27,K23*(1+L52/100))) -> 1031.3515 | M23: =IF(AND(M50>1,L50>1), M27*(1+M51/100)-L23*$C$47*(M12-L12)/100, IF(M50=1,M27,L23*(1+M52/100))) -> 1041.9392 | N23: =IF(AND(N50>1,M50>1), N27*(1+N51/100)-M23*$C$47*(N12-M12)/100, IF(N50=1,N27,M23*(1+N52/100))) -> 1052.9312 | ... U23: =IF(AND(U50>1,T50>1), U27*(1+U51/100)-T23*$C$47*(U12-T12)/100, IF(U50=1,U27,T23*(1+U52/100))) -> 1163.5727
B24: Growth rate | C24: ='Baseline NFPC'!C23 -> 1.081005 | D24: ='Baseline NFPC'!D23 -> 1.69667 | E24: =100*(E23/D23-1) -> 1.273747 | F24: =100*(F23/E23-1) -> 1.581865 | G24: =100*(G23/F23-1) -> 1.521399 | H24: =100*(H23/G23-1) -> 1.41368 | I24: =100*(I23/H23-1) -> 1.393831 | J24: =100*(J23/I23-1) -> 1.069126 | K24: =100*(K23/J23-1) -> 1.03431 | L24: =100*(L23/K23-1) -> 1.012531 | ... U24: =100*(U23/T23-1) -> 1.710004
B26: Potential GDP (real)
B27: Level | C27: ='Input data'!C34 -> 924.6414 | D27: =+C27*(1+'Input data'!D33/100) -> 939.95618 | E27: =+D27*(1+'Input data'!E33/100) -> 953.36237 | F27: =+E27*(1+'Input data'!F33/100) -> 965.68823 | G27: =+F27*(1+'Input data'!G33/100) -> 977.69888 | H27: =+G27*(1+'Input data'!H33/100) -> 988.81595 | I27: =+H27*(1+'Input data'!I33/100) -> 999.87118 | J27: =+I27*(1+'Input data'!J33/100) -> 1010.5611 | K27: =+J27*(1+'Input data'!K33/100) -> 1021.0134 | ... U27: =+T27*(1+'Input data'!U33/100) -> 1163.5726
B29: Output gap
B30: Output gap | C30: =100*(C23/C27-1) -> -0.98858866 | D30: =100*(D23/D27-1) -> -0.94926316 | E30: =100*(E23/E27-1) -> -1.0982012 | F30: =100*(F23/F27-1) -> -0.8160408 | G30: =100*(G23/G27-1) -> -0.54403071 | H30: =100*(H23/H27-1) -> -0.27201359 | I30: =100*(I23/I27-1) -> -9.9246313e-07 | J30: =100*(J23/J27-1) -> -2.9713068e-06 | ... U30: =100*(U23/U27-1) -> 6.9328616e-06
B32: Actual GDP (nominal, national currency)
B33: Growth rate | C33: =100*((1+C24/100)*(1+C42/100)-1) -> 6.8873142 | D33: =100*((1+D24/100)*(1+D42/100)-1) -> 4.9045765 | E33: =100*((1+E24/100)*(1+E42/100)-1) -> 4.5782425 | F33: =100*((1+F24/100)*(1+F42/100)-1) -> 3.7184496 | G33: =100*((1+G24/100)*(1+G42/100)-1) -> 3.6791337 | H33: =100*((1+H24/100)*(1+H42/100)-1) -> 3.5915233 | I33: =100*((1+I24/100)*(1+I42/100)-1) -> 3.5936418 | J33: =100*((1+J24/100)*(1+J42/100)-1) -> 3.2842141 | ... U33: =100*((1+U24/100)*(1+U42/100)-1) -> 3.9293163
B35: Interest rates
B36: Nominal implicit interest rate on debt | C36: ='Input data'!C37 -> 1.646586 | D36: ='Input data'!D37 -> 1.72 | E36: ='Input data'!E37 -> 1.732298 | F36: =F99 -> 1.8261287 | G36: =G99 -> 1.9630297 | H36: =H99 -> 2.0990021 | I36: =I99 -> 2.234119 | J36: =J99 -> 2.3707683 | K36: =K99 -> 2.5163135 | L36: =L99 -> 2.6668445 | M36: =M99 -> 2.8190428 | ... U36: =U99 -> 3.5460259
B37: Long-term interest rate | C37: ='Input data'!C$39 -> 2.6205 | D37: ='Input data'!D$39 -> 2.78965 | E37: ='Input data'!E$39 -> 2.894953 | F37: ='Input data'!F$39 -> 3.081676 | G37: ='Baseline NFPC'!G36 -> 3.188669 | H37: ='Baseline NFPC'!H36 -> 3.295662 | I37: ='Baseline NFPC'!I36 -> 3.402655 | J37: ='Baseline NFPC'!J36 -> 3.509648 | K37: ='Baseline NFPC'!K36 -> 3.616641 | L37: ='Baseline NFPC'!L36 -> 3.723634 | M37: ='Baseline NFPC'!M36 -> 3.830627 | N37: ='Baseline NFPC'!N36 -> 3.93762 | ... U37: ='Baseline NFPC'!U36 -> 3.959453
B38: Short-term interest rate | C38: ='Input data'!C$38 -> 3.570833 | D38: ='Input data'!D$38 -> 2.172583 | E38: ='Input data'!E$38 -> 1.91225 | F38: ='Input data'!F$38 -> 2.024375 | G38: ='Baseline NFPC'!G37 -> 2.1784319 | H38: ='Baseline NFPC'!H37 -> 2.3324888 | I38: ='Baseline NFPC'!I37 -> 2.4865456 | J38: ='Baseline NFPC'!J37 -> 2.6406025 | K38: ='Baseline NFPC'!K37 -> 2.7946594 | L38: ='Baseline NFPC'!L37 -> 2.9487163 | M38: ='Baseline NFPC'!M37 -> 3.1027731 | N38: ='Baseline NFPC'!N37 -> 3.25683 | ... U38: ='Baseline NFPC'!U37 -> 2.8169395
B39: Share of long-term debt that matures every year | C39: ='Baseline NFPC'!C38 -> 0.08837902 | D39: ='Baseline NFPC'!D38 -> 0.05460046 | E39: ='Baseline NFPC'!E38 -> 0.05795577 | F39: ='Baseline NFPC'!F38 -> 0.061311081 | G39: ='Baseline NFPC'!G38 -> 0.064666392 | H39: ='Baseline NFPC'!H38 -> 0.068021703 | I39: ='Baseline NFPC'!I38 -> 0.071377014 | J39: ='Baseline NFPC'!J38 -> 0.074732326 | ... U39: ='Baseline NFPC'!U38 -> 0.08815357
B41: Inflation and exchange rate
B42: GDP deflator (National currency) | C42: ='Input data'!C42 -> 5.744214 | D42: ='Input data'!D42 -> 3.154387 | E42: ='Input data'!E42 -> 3.262934 | F42: ='Input data'!F42 -> 2.103313 | G42: ='Baseline NFPC'!G41 -> 2.1253989 | H42: ='Baseline NFPC'!H41 -> 2.1474847 | I42: ='Baseline NFPC'!I41 -> 2.1695706 | J42: ='Baseline NFPC'!J41 -> 2.1916565 | K42: ='Baseline NFPC'!K41 -> 2.2137424 | L42: ='Baseline NFPC'!L41 -> 2.2358282 | M42: ='Baseline NFPC'!M41 -> 2.2579141 | N42: ='Baseline NFPC'!N41 -> 2.28 | ... U42: ='Baseline NFPC'!U41 -> 2.182
B43: Exchange rate composite change (weighted by share of debt in each currency) | C43: ='Baseline NFPC'!C42 -> 0.9999999 | D43: ='Baseline NFPC'!D42 -> 1 | E43: ='Baseline NFPC'!E42 -> 1 | F43: ='Baseline NFPC'!F42 -> 0.9999999 | G43: ='Baseline NFPC'!G42 -> 1 | H43: ='Baseline NFPC'!H42 -> 1 | I43: ='Baseline NFPC'!I42 -> 1 | J43: ='Baseline NFPC'!J42 -> 1 | ... U43: ='Baseline NFPC'!U42 -> 1
B45: Intermediate calculations (growth rate equation)
B47: Fiscal multiplier | C47: ='Input data'!C49 -> 0.6
B48: Budget balance semi-elasticity | C48: ='Input data'!C50 -> 0.605
B50: Auxiliary variable to control the closure of the output gap | C50: 0 | D50: =IF(AND(ABS((D12-C12)-('Input data'!D13-'Input data'!C13))>0.0001,ABS(D12-C12)>0.0001,D$10>$C$5),4,IF(C50=4,3,IF(C50=3,2,IF(C50=2,1,0)))) -> 0 | E50: =IF(AND(ABS((E12-D12)-('Baseline NFPC'!E12-'Baseline NFPC'!D12))>0.0001,ABS(E12-D12)>0.0001,E$10>$C$5),4,IF(D50=4,3,IF(D50=3,2,IF(D50=2,1,0)))) -> 0 | F50: =IF(AND(ABS((F12-E12)-('Baseline NFPC'!F12-'Baseline NFPC'!E12))>0.0001,ABS(F12-E12)>0.0001,F$10>$C$5),4,IF(E50=4,3,IF(E50=3,2,IF(E50=2,1,0)))) -> 0 | G50: =IF(AND(ABS((G12-F12)-('Baseline NFPC'!G12-'Baseline NFPC'!F12))>0.0001,ABS(G12-F12)>0.0001,G$10>$C$5),4,IF(F50=4,3,IF(F50=3,2,IF(F50=2,1,0)))) -> 0 | H50: =IF(AND(ABS((H12-G12)-('Baseline NFPC'!H12-'Baseline NFPC'!G12))>0.0001,ABS(H12-G12)>0.0001,H$10>$C$5),4,IF(G50=4,3,IF(G50=3,2,IF(G50=2,1,0)))) -> 0 | I50: =IF(AND(ABS((I12-H12)-('Baseline NFPC'!I12-'Baseline NFPC'!H12))>0.0001,ABS(I12-H12)>0.0001,I$10>$C$5),4,IF(H50=4,3,IF(H50=3,2,IF(H50=2,1,0)))) -> 0 | J50: =IF(AND(ABS((J12-I12)-('Baseline NFPC'!J12-'Baseline NFPC'!I12))>0.0001,ABS(J12-I12)>0.0001,J$10>$C$5),4,IF(I50=4,3,IF(I50=3,2,IF(I50=2,1,0)))) -> 0 | K50: =IF(AND(ABS((K12-J12)-('Baseline NFPC'!K12-'Baseline NFPC'!J12))>0.0001,ABS(K12-J12)>0.0001,K$10>$C$5),4,IF(J50=4,3,IF(J50=3,2,IF(J50=2,1,0)))) -> 0 | L50: =IF(AND(ABS((L12-K12)-('Baseline NFPC'!L12-'Baseline NFPC'!K12))>0.0001,ABS(L12-K12)>0.0001,L$10>$C$5),4,IF(K50=4,3,IF(K50=3,2,IF(K50=2,1,0)))) -> 0 | ... U50: =IF(AND(ABS((U12-T12)-('Baseline NFPC'!U12-'Baseline NFPC'!T12))>0.0001,ABS(U12-T12)>0.0001,U$10>$C$5),4,IF(T50=4,3,IF(T50=3,2,IF(T50=2,1,0)))) -> 0
B51: OG intermediate auxiliary value | C51: 0 | D51: =IF(C50=4,2/3*(C30-'Baseline NFPC'!C29),IF(C50=3,1/3*(#REF!-'Baseline NFPC'!#REF!),0)) -> 0 | E51: =IF(D50=4,2/3*(D30-'Baseline NFPC'!D29),IF(D50=3,1/3*(C30-'Baseline NFPC'!C29),0)) -> 0 | F51: =IF(E50=4,2/3*(E30-'Baseline NFPC'!E29),IF(E50=3,1/3*(D30-'Baseline NFPC'!D29),0)) -> 0 | G51: =IF(F50=4,2/3*F30,IF(F50=3,1/3*E30,0)) -> 0 | H51: =IF(G50=4,2/3*G30,IF(G50=3,1/3*F30,0)) -> 0 | I51: =IF(H50=4,2/3*H30,IF(H50=3,1/3*G30,0)) -> 0 | J51: =IF(I50=4,2/3*I30,IF(I50=3,1/3*H30,0)) -> 0 | K51: =IF(J50=4,2/3*J30,IF(J50=3,1/3*I30,0)) -> 0 | L51: =IF(K50=4,2/3*K30,IF(K50=3,1/3*J30,0)) -> 0 | M51: =IF(L50=4,2/3*L30,IF(L50=3,1/3*K30,0)) -> 0 | N51: =IF(M50=4,2/3*M30,IF(M50=3,1/3*L30,0)) -> 0 | ... U51: =IF(T50=4,2/3*T30,IF(T50=3,1/3*S30,0)) -> 0
B52: GDP intermediate growth rate - only feedback effect and no closure of the OG | C52: 0 | D52: ='Input data'!D30-$C$47*((D12-C12)-('Input data'!D13-'Input data'!C13)) -> 1.69667 | E52: ='Input data'!E30-$C$47*(E12-D12) -> 1.273747 | F52: ='Input data'!F30-$C$47*(F12-E12) -> 1.581865 | G52: ='Input data'!G30-$C$47*(G12-F12) -> 1.521399 | H52: ='Input data'!H30-$C$47*(H12-G12) -> 1.41368 | I52: ='Input data'!I30-$C$47*(I12-H12) -> 1.393831 | J52: ='Input data'!J30-$C$47*(J12-I12) -> 1.069126 | K52: ='Input data'!K30-$C$47*(K12-J12) -> 1.03431 | L52: ='Input data'!L30-$C$47*(L12-K12) -> 1.012531 | ... U52: ='Input data'!U30-$C$47*(U12-T12) -> 1.710004
B54: Debt projections
C56: ='Input data'!$C$5-1 -> 2024 | D56: =C56+1 -> 2025 | E56: =D56+1 -> 2026 | F56: =E56+1 -> 2027 | G56: =F56+1 -> 2028 | H56: =G56+1 -> 2029 | I56: =H56+1 -> 2030 | J56: =I56+1 -> 2031 | K56: =J56+1 -> 2032 | ... U56: =T56+1 -> 2042
B57: Gross debt | C57: =+'Input data'!C12 -> 43.74815 | D57: =+C57+D58 -> 45.15761 | E57: =+D57+E58 -> 47.855645 | F57: =+E57+F58 -> 48.033971 | G57: =+F57+G58 -> 48.125788 | H57: =+G57+H58 -> 48.154711 | I57: =+H57+I58 -> 48.186228 | J57: =+I57+J58 -> 48.72929 | K57: =+J57+K58 -> 49.548171 | ... U57: =+T57+U58 -> 65.925998
B58: Change in debt (-1+2+3) | D58: =-D59+D67+D72 -> 1.4094602 | E58: =-E59+E67+E72 -> 2.6980344 | F58: =-F59+F67+F72 -> 0.17832642 | G58: =-G59+G67+G72 -> 0.091816569 | H58: =-H59+H67+H72 -> 0.028923207 | I58: =-I59+I67+I72 -> 0.031516731 | J58: =-J59+J67+J72 -> 0.5430629 | K58: =-K59+K67+K72 -> 0.81888086 | ... U58: =-U59+U67+U72 -> 2.0969585
B59: (1) Primary balance (1.1 + 1.2 - 1.3 -1.4 -1.5 - 1.6 -1.7) | D59: =D60+D61-D62-D63-D64-D65-D66 -> -1.1575212 | E59: =E60+E61-E62-E63-E64-E65-E66 -> -1.9122554 | F59: =F60+F61-F62-F63-F64-F65-F66 -> -1.0514442 | G59: =G60+G61-G62-G63-G64-G65-G66 -> -0.88687808 | H59: =H60+H61-H62-H63-H64-H65-H66 -> -0.72230772 | I59: =I60+I61-I62-I63-I64-I65-I66 -> -0.6634805 | J59: =J60+J61-J62-J63-J64-J65-J66 -> -0.969222 | K59: =K60+K61-K62-K63-K64-K65-K66 -> -1.1749623 | ... U59: =U60+U61-U62-U63-U64-U65-U66 -> -2.3323594
B60: (1.1) Structural primary balance (before ageing cost) | D60: =D12 -> -0.5577395 | E60: =IF(E12="",D60,E12) -> -0.5577395 | F60: =IF(F12="",E60,F12) -> -0.5577395 | G60: =IF(G12="",F60,G12) -> -0.5577395 | H60: =IF(H12="",G60,H12) -> -0.5577395 | I60: =IF(I12="",H60,I12) -> -0.5577395 | J60: =IF(J12="",I60,J12) -> -0.5577395 | K60: =IF(K12="",J60,K12) -> -0.5577395 | L60: =IF(L12="",K60,L12) -> -0.5577395 | ... U60: =IF(U12="",T60,U12) -> -0.5577395
B61: (1.2) Cumulated budgetary effort (in terms of primary balance) | D61: 0 | E61: 0 | F61: 0 | G61: 0 | H61: 0 | I61: 0 | J61: 0 | K61: 0 | L61: 0 | M61: 0 | N61: 0 | O61: 0 | P61: 0 | Q61: 0 | R61: 0 | S61: 0 | T61: 0 | U61: 0
B62: (1.3) Cyclical component | D62: =-$C$48*D30 -> 0.57430421 | E62: =-$C$48*E30 -> 0.66441172 | F62: =-$C$48*F30 -> 0.49370469 | G62: =-$C$48*G30 -> 0.32913858 | H62: =-$C$48*H30 -> 0.16456822 | I62: =-$C$48*I30 -> 6.004402e-07 | J62: =-$C$48*J30 -> 1.7976406e-06 | K62: =-$C$48*K30 -> 1.7976406e-06 | ... U62: =-$C$48*U30 -> -4.1943813e-06
B63: (1.4) One-off and other temporary measures | D63: =-D14 -> 0.0254775 | E63: =-E14 -> 0.6901042 | F63: =-F14 -> 0 | G63: =-G14 -> 0 | H63: =-H14 -> 0 | I63: =-I14 -> 0 | J63: =-J14 -> 0 | K63: =-K14 -> 0 | ... U63: =-U14 -> 0
B64: (1.5) Cost of ageing | D64: =IF(D$56<=$C$6,0,HLOOKUP(D$56,'Input data'!$C$9:$AZ$26,12,FALSE)-HLOOKUP($C$6,'Input data'!$C$9:$AZ$26,12,FALSE)) -> 0 | E64: =IF(E$56<=$C$6,0,HLOOKUP(E$56,'Input data'!$C$9:$AZ$26,12,FALSE)-HLOOKUP($C$6,'Input data'!$C$9:$AZ$26,12,FALSE)) -> 0 | F64: =IF(F$56<=$C$6,0,HLOOKUP(F$56,'Input data'!$C$9:$AZ$26,12,FALSE)-HLOOKUP($C$6,'Input data'!$C$9:$AZ$26,12,FALSE)) -> 0 | G64: =IF(G$56<=$C$6,0,HLOOKUP(G$56,'Input data'!$C$9:$AZ$26,12,FALSE)-HLOOKUP($C$6,'Input data'!$C$9:$AZ$26,12,FALSE)) -> 0 | H64: =IF(H$56<=$C$6,0,HLOOKUP(H$56,'Input data'!$C$9:$AZ$26,12,FALSE)-HLOOKUP($C$6,'Input data'!$C$9:$AZ$26,12,FALSE)) -> 0 | I64: =IF(I$56<=$C$6,0,HLOOKUP(I$56,'Input data'!$C$9:$AZ$26,12,FALSE)-HLOOKUP($C$6,'Input data'!$C$9:$AZ$26,12,FALSE)) -> 0.1 | J64: =IF(J$56<=$C$6,0,HLOOKUP(J$56,'Input data'!$C$9:$AZ$26,12,FALSE)-HLOOKUP($C$6,'Input data'!$C$9:$AZ$26,12,FALSE)) -> 0.4 | K64: =IF(K$56<=$C$6,0,HLOOKUP(K$56,'Input data'!$C$9:$AZ$26,12,FALSE)-HLOOKUP($C$6,'Input data'!$C$9:$AZ$26,12,FALSE)) -> 0.6 | ... U64: =IF(U$56<=$C$6,0,HLOOKUP(U$56,'Input data'!$C$9:$AZ$26,12,FALSE)-HLOOKUP($C$6,'Input data'!$C$9:$AZ$26,12,FALSE)) -> 1.7
B65: (1.6) Property incomes | D65: =IF(D$56<=$C$5,0,-HLOOKUP(D$56,'Input data'!$C$9:$AZ$26,18,FALSE)+HLOOKUP($C$6,'Input data'!$C$9:$AZ$26,18,FALSE)) -> 0 | E65: =IF(E$56<=$C$6,0,-HLOOKUP(E$56,'Input data'!$C$9:$AZ$26,18,FALSE)+HLOOKUP($C$6,'Input data'!$C$9:$AZ$26,18,FALSE)) -> 0 | F65: =IF(F$56<=$C$6,0,-HLOOKUP(F$56,'Input data'!$C$9:$AZ$26,18,FALSE)+HLOOKUP($C$6,'Input data'!$C$9:$AZ$26,18,FALSE)) -> 0 | G65: =IF(G$56<=$C$6,0,-HLOOKUP(G$56,'Input data'!$C$9:$AZ$26,18,FALSE)+HLOOKUP($C$6,'Input data'!$C$9:$AZ$26,18,FALSE)) -> 0 | H65: =IF(H$56<=$C$6,0,-HLOOKUP(H$56,'Input data'!$C$9:$AZ$26,18,FALSE)+HLOOKUP($C$6,'Input data'!$C$9:$AZ$26,18,FALSE)) -> 0 | I65: =IF(I$56<=$C$6,0,-HLOOKUP(I$56,'Input data'!$C$9:$AZ$26,18,FALSE)+HLOOKUP($C$6,'Input data'!$C$9:$AZ$26,18,FALSE)) -> 0.0057404 | J65: =IF(J$56<=$C$6,0,-HLOOKUP(J$56,'Input data'!$C$9:$AZ$26,18,FALSE)+HLOOKUP($C$6,'Input data'!$C$9:$AZ$26,18,FALSE)) -> 0.0114807 | K65: =IF(K$56<=$C$6,0,-HLOOKUP(K$56,'Input data'!$C$9:$AZ$26,18,FALSE)+HLOOKUP($C$6,'Input data'!$C$9:$AZ$26,18,FALSE)) -> 0.017221 | L65: =IF(L$56<=$C$6,0,-HLOOKUP(L$56,'Input data'!$C$9:$AZ$26,18,FALSE)+HLOOKUP($C$6,'Input data'!$C$9:$AZ$26,18,FALSE)) -> 0.0229613 | ... U65: =IF(U$56<=$C$6,0,-HLOOKUP(U$56,'Input data'!$C$9:$AZ$26,18,FALSE)+HLOOKUP($C$6,'Input data'!$C$9:$AZ$26,18,FALSE)) -> 0.0746241
B66: (1.7) Revenues | D66: 0 | E66: 0 | F66: 0 | G66: 0 | H66: 0 | I66: 0 | J66: 0 | K66: 0 | L66: 0 | M66: 0 | N66: 0 | O66: 0 | P66: 0 | Q66: 0 | R66: 0 | S66: 0 | T66: 0 | U66: 0
B67: (2) Snowball effect (2.1 + 2.2 + 2.3) | D67: =SUM(D68:D71) -> -1.328058 | E67: =SUM(E68:E71) -> -1.228898 | F67: =SUM(F68:F71) -> -0.87311572 | G67: =SUM(G68:G71) -> -0.79506151 | H67: =SUM(H68:H71) -> -0.69338452 | I67: =SUM(I68:I71) -> -0.63196377 | J67: =SUM(J68:J71) -> -0.4261591 | K67: =SUM(K68:K71) -> -0.35608144 | ... U67: =SUM(U68:U71) -> -0.23540094
B68: (2.1) Interest expenditure | D68: =C57*D36/100*(1/(1+D33/100)) -> 0.71728823 | E68: =D57*E36/100*(1/(1+E33/100)) -> 0.74801829 | F68: =E57*F36/100*(1/(1+F33/100)) -> 0.84257493 | G68: =F57*G36/100*(1/(1+G33/100)) -> 0.90946084 | H68: =G57*H36/100*(1/(1+H33/100)) -> 0.97513896 | I68: =H57*I36/100*(1/(1+I33/100)) -> 1.0385131 | J68: =I57*J36/100*(1/(1+J33/100)) -> 1.1060585 | K68: =J57*K36/100*(1/(1+K33/100)) -> 1.1873443 | ... U68: =T57*U36/100*(1/(1+U33/100)) -> 2.1778208
B69: (2.2) Growth effect | D69: =-C57*(D24/100)*(1/(1+D33/100)) -> -0.70755897 | E69: =-D57*(E24/100)*(1/(1+E33/100)) -> -0.55001279 | F69: =-E57*(F24/100)*(1/(1+F33/100)) -> -0.72987178 | G69: =-F57*(G24/100)*(1/(1+G33/100)) -> -0.70485577 | H69: =-G57*(H24/100)*(1/(1+H33/100)) -> -0.65675705 | I69: =-H57*(I24/100)*(1/(1+I33/100)) -> -0.64791166 | J69: =-I57*(J24/100)*(1/(1+J33/100)) -> -0.49879015 | K69: =-J57*(K24/100)*(1/(1+K33/100)) -> -0.48804812 | ... U69: =-T57*(U24/100)*(1/(1+U33/100)) -> -1.0502129
B70: (2.3) Inflation effect | D70: =-C57*D42/100*(1/(1+D42/100)) -> -1.337787 | E70: =-D57*E42/100*(1/(1+E42/100)) -> -1.4269041 | F70: =-E57*F42/100*(1/(1+F42/100)) -> -0.98581913 | G70: =-F57*G42/100*(1/(1+G42/100)) -> -0.99966658 | H70: =-G57*H42/100*(1/(1+H42/100)) -> -1.0117664 | I70: =-H57*I42/100*(1/(1+I42/100)) -> -1.0225652 | J70: =-I57*J42/100*(1/(1+J42/100)) -> -1.0334274 | K70: =-J57*K42/100*(1/(1+K42/100)) -> -1.0553776 | ... U70: =-T57*U42/100*(1/(1+U42/100)) -> -1.3630088
B71: (2.4) Exchange rate effect linked to the interest rate | D71: ='Baseline NFPC'!D70 -> -2.8636209e-07 | E71: ='Baseline NFPC'!E70 -> 5.7763161e-07 | F71: ='Baseline NFPC'!F70 -> 2.6384936e-07 | G71: 0 | H71: 0 | I71: 0 | J71: 0 | K71: 0 | L71: 0 | M71: 0 | N71: 0 | O71: 0 | P71: 0 | Q71: 0 | R71: 0 | S71: 0 | T71: 0 | U71: 0
B72: (3 ) Stock flow adjustments (3.1 + 3.2) | D72: ='Input data'!D16 -> 1.579997 | E72: ='Input data'!E16 -> 2.014677 | F72: ='Input data'!F16 -> -2.05e-06 | G72: ='Input data'!G16 -> 0 | H72: ='Input data'!H16 -> 0 | I72: ='Input data'!I16 -> 0 | J72: ='Input data'!J16 -> 0 | K72: ='Input data'!K16 -> 0 | ... U72: ='Input data'!U16 -> 0
B73: (3.1) Base | D73: =D15 -> 1.579996 | E73: =E15 -> 2.014675 | F73: =F15 -> 0 | G73: =G15 -> 0 | H73: =H15 -> 0 | I73: =I15 -> 0 | J73: =J15 -> 0 | K73: =K15 -> 0 | ... U73: =U15 -> 0
B74: (3.2) Adjustment due to the exchange rate effect linked to debt value | D74: =+D72-D73 -> 1e-06 | E74: =+E72-E73 -> 2e-06 | F74: =+F72-F73 -> -2.05e-06 | G74: =+G72-G73 -> 0 | H74: =+H72-H73 -> 0 | I74: =+I72-I73 -> 0 | J74: =+J72-J73 -> 0 | K74: =+K72-K73 -> 0 | ... U74: =+U72-U73 -> 0
B76: Other budgetary variables
B77: Headline balance | C77: ='Baseline NFPC'!C76 -> -0.9448897 | D77: =D59-D68-D71 -> -1.8748092 | E77: =E59-E68-E71 -> -2.6602743 | F77: =F59-F68-F71 -> -1.8940194 | G77: =G59-G68-G71 -> -1.7963389 | H77: =H59-H68-H71 -> -1.6974467 | I77: =I59-I68-I71 -> -1.7019936 | J77: =J59-J68-J71 -> -2.0752805 | K77: =K59-K68-K71 -> -2.3623066 | ... U77: =U59-U68-U71 -> -4.5101802
B78: Structural balance | C78: ='Baseline NFPC'!C77 -> -0.3200694 | D78: =D60-D68-D71-D64-D65-D66 -> -1.2750274 | E78: =E60-E68-E71-E64-E65-E66 -> -1.3057584 | F78: =F60-F68-F71-F64-F65-F66 -> -1.4003147 | G78: =G60-G68-G71-G64-G65-G66 -> -1.4672003 | H78: =H60-H68-H71-H64-H65-H66 -> -1.5328785 | I78: =I60-I68-I71-I64-I65-I66 -> -1.701993 | J78: =J60-J68-J71-J64-J65-J66 -> -2.0752787 | K78: =K60-K68-K71-K64-K65-K66 -> -2.3623048 | ... U78: =U60-U68-U71-U64-U65-U66 -> -4.5101844
B79: Net expenditure growth | C79: ='Input data'!C45 -> 6.2115937 | D79: ='Input data'!D45 -> 7.2645885 | E79: ='Input data'!E33+E42-(E$12-D$12)/'Input data'!$C$64*100 -> 4.689191 | F79: ='Input data'!F33+F42-(F$12-E$12)/'Input data'!$C$64*100 -> 3.396196 | G79: ='Input data'!G33+G42-(G$12-F$12)/'Input data'!$C$64*100 -> 3.3691389 | H79: ='Input data'!H33+H42-(H$12-G$12)/'Input data'!$C$64*100 -> 3.2845498 | I79: ='Input data'!I33+I42-(I$12-H$12)/'Input data'!$C$64*100 -> 3.2875976 | J79: ='Input data'!J33+J42-(J$12-I$12)/'Input data'!$C$64*100 -> 3.2607845 | K79: ='Input data'!K33+K42-(K$12-J$12)/'Input data'!$C$64*100 -> 3.2480524 | L79: ='Input data'!L33+L42-(L$12-K$12)/'Input data'!$C$64*100 -> 3.2483582 | ... U79: ='Input data'!U33+U42-(U$12-T$12)/'Input data'!$C$64*100 -> 3.892
B81: Average net primary expenditure growth
B83: Debt decomposition and IIR
B85: Auxiliary variable identifying whether debt is increasing | D85: =IF((D90-C90*D43/((1+D24/100)*(1+D42/100)))>0,1,0) -> 1 | E85: =IF((E90-D90*E43/((1+E24/100)*(1+E42/100)))>0,1,0) -> 1 | F85: =IF((F90-E90*F43/((1+F24/100)*(1+F42/100)))>0,1,0) -> 1 | G85: =IF((G90-F90*G43/((1+G24/100)*(1+G42/100)))>0,1,0) -> 1 | H85: =IF((H90-G90*H43/((1+H24/100)*(1+H42/100)))>0,1,0) -> 1 | I85: =IF((I90-H90*I43/((1+I24/100)*(1+I42/100)))>0,1,0) -> 1 | J85: =IF((J90-I90*J43/((1+J24/100)*(1+J42/100)))>0,1,0) -> 1 | K85: =IF((K90-J90*K43/((1+K24/100)*(1+K42/100)))>0,1,0) -> 1 | ... U85: =IF((U90-T90*U43/((1+U24/100)*(1+U42/100)))>0,1,0) -> 1
B86: Auxiliary variable identifying whether some debt is rolled over even though debt is decreasing | D86: =IF(AND(D85=0,ABS(D90-C90*D43/((1+D24/100)*(1+D42/100)))<((C96*C90*D43/((1+D24/100)*(1+D42/100))+(D39*C90*C97*D43/((1+D24/100)*(1+D42/100)))))),1,0) -> 0 | E86: =IF(AND(E85=0,ABS(E90-D90*E43/((1+E24/100)*(1+E42/100)))<((D96*D90*E43/((1+E24/100)*(1+E42/100))+(E39*D90*D97*E43/((1+E24/100)*(1+E42/100)))))),1,0) -> 0 | F86: =IF(AND(F85=0,ABS(F90-E90*F43/((1+F24/100)*(1+F42/100)))<((E96*E90*F43/((1+F24/100)*(1+F42/100))+(F39*E90*E97*F43/((1+F24/100)*(1+F42/100)))))),1,0) -> 0 | G86: =IF(AND(G85=0,ABS(G90-F90*G43/((1+G24/100)*(1+G42/100)))<((F96*F90*G43/((1+G24/100)*(1+G42/100))+(G39*F90*F97*G43/((1+G24/100)*(1+G42/100)))))),1,0) -> 0 | H86: =IF(AND(H85=0,ABS(H90-G90*H43/((1+H24/100)*(1+H42/100)))<((G96*G90*H43/((1+H24/100)*(1+H42/100))+(H39*G90*G97*H43/((1+H24/100)*(1+H42/100)))))),1,0) -> 0 | I86: =IF(AND(I85=0,ABS(I90-H90*I43/((1+I24/100)*(1+I42/100)))<((H96*H90*I43/((1+I24/100)*(1+I42/100))+(I39*H90*H97*I43/((1+I24/100)*(1+I42/100)))))),1,0) -> 0 | J86: =IF(AND(J85=0,ABS(J90-I90*J43/((1+J24/100)*(1+J42/100)))<((I96*I90*J43/((1+J24/100)*(1+J42/100))+(J39*I90*I97*J43/((1+J24/100)*(1+J42/100)))))),1,0) -> 0 | K86: =IF(AND(K85=0,ABS(K90-J90*K43/((1+K24/100)*(1+K42/100)))<((J96*J90*K43/((1+K24/100)*(1+K42/100))+(K39*J90*J97*K43/((1+K24/100)*(1+K42/100)))))),1,0) -> 0 | ... U86: =IF(AND(U85=0,ABS(U90-T90*U43/((1+U24/100)*(1+U42/100)))<((T96*T90*U43/((1+U24/100)*(1+U42/100))+(U39*T90*T97*U43/((1+U24/100)*(1+U42/100)))))),1,0) -> 0
C89: ='Input data'!$C$5-1 -> 2024 | D89: =C89+1 -> 2025 | E89: =D89+1 -> 2026 | F89: =E89+1 -> 2027 | G89: =F89+1 -> 2028 | H89: =G89+1 -> 2029 | I89: =H89+1 -> 2030 | J89: =I89+1 -> 2031 | K89: =J89+1 -> 2032 | ... U89: =T89+1 -> 2042
B90: Gross debt | C90: =C57 -> 43.74815 | D90: =D57 -> 45.15761 | E90: =D90*(1+E104/100)*E43-E60-E61+E62+E63+E64+E65+E66+E73 -> 47.855642 | F90: =E90*(1+F104/100)*F43-F60-F61+F62+F63+F64+F65+F66+F73 -> 48.033966 | G90: =F90*(1+G104/100)*G43-G60-G61+G62+G63+G64+G65+G66+G73 -> 48.125782 | H90: =G90*(1+H104/100)*H43-H60-H61+H62+H63+H64+H65+H66+H73 -> 48.154706 | I90: =H90*(1+I104/100)*I43-I60-I61+I62+I63+I64+I65+I66+I73 -> 48.186222 | J90: =I90*(1+J104/100)*J43-J60-J61+J62+J63+J64+J65+J66+J73 -> 48.729285 | K90: =J90*(1+K104/100)*K43-K60-K61+K62+K63+K64+K65+K66+K73 -> 49.548166 | L90: =K90*(1+L104/100)*L43-L60-L61+L62+L63+L64+L65+L66+L73 -> 50.539003 | ... U90: =T90*(1+U104/100)*U43-U60-U61+U62+U63+U64+U65+U66+U73 -> 65.925993
B91: Of which Outstanding debt | D91: ='Input data'!$C$66*D$90 -> 37.015024 | E91: =IF(E90=0,0,IF(E85=1,D90*E43/((1+E24/100)*(1+E42/100))-E92-E93,IF(AND(E85=0,E86=1),(1-D96-E39*D97)*D90*E43/((1+E24/100)*(1+E42/100)),E90))) -> 37.303082 | F91: =IF(F90=0,0,IF(F85=1,E90*F43/((1+F24/100)*(1+F42/100))-F92-F93,IF(AND(F85=0,F86=1),(1-E96-F39*E97)*E90*F43/((1+F24/100)*(1+F42/100)),F90))) -> 39.670909 | G91: =IF(G90=0,0,IF(G85=1,F90*G43/((1+G24/100)*(1+G42/100))-G92-G93,IF(AND(G85=0,G86=1),(1-F96-G39*F97)*F90*G43/((1+G24/100)*(1+G42/100)),G90))) -> 39.674453 | H91: =IF(H90=0,0,IF(H85=1,G90*H43/((1+H24/100)*(1+H42/100))-H92-H93,IF(AND(H85=0,H86=1),(1-G96-H39*G97)*G90*H43/((1+H24/100)*(1+H42/100)),H90))) -> 39.625747 | I91: =IF(I90=0,0,IF(I85=1,H90*I43/((1+I24/100)*(1+I42/100))-I92-I93,IF(AND(I85=0,I86=1),(1-H96-I39*H97)*H90*I43/((1+I24/100)*(1+I42/100)),I90))) -> 39.492008 | J91: =IF(J90=0,0,IF(J85=1,I90*J43/((1+J24/100)*(1+J42/100))-J92-J93,IF(AND(J85=0,J86=1),(1-I96-J39*I97)*I90*J43/((1+J24/100)*(1+J42/100)),J90))) -> 39.479498 | K91: =IF(K90=0,0,IF(K85=1,J90*K43/((1+K24/100)*(1+K42/100))-K92-K93,IF(AND(K85=0,K86=1),(1-J96-K39*J97)*J90*K43/((1+K24/100)*(1+K42/100)),K90))) -> 39.768904 | L91: =IF(L90=0,0,IF(L85=1,K90*L43/((1+L24/100)*(1+L42/100))-L92-L93,IF(AND(L85=0,L86=1),(1-K96-L39*K97)*K90*L43/((1+L24/100)*(1+L42/100)),L90))) -> 40.272792 | ... U91: =IF(U90=0,0,IF(U85=1,T90*U43/((1+U24/100)*(1+U42/100))-U92-U93,IF(AND(U85=0,U86=1),(1-T96-U39*T97)*T90*U43/((1+U24/100)*(1+U42/100)),U90))) -> 50.985994
B92: Rolled over long-term debt | D92: ='Input data'!$C$67*D$90 -> 3.5884993 | E92: =IF(E90=0,0,IF(E85=1,E39*D90*D97*E43/((1+E24/100)*(1+E42/100)),IF(AND(E85=0,E86=1),(E39*D90*D97*E43/((1+E24/100)*(1+E42/100)))*(1-ABS(E90-D90*E43/((1+E24/100)*(1+E42/100)))/((E39*D90*D97*E43/((1+E24/100)*(1+E42/100)))+(D96*D90*E43/((1+E24/100)*(1+E42/100))))),0))) -> 2.2949335 | F92: =IF(F90=0,0,IF(F85=1,F39*E90*E97*F43/((1+F24/100)*(1+F42/100)),IF(AND(F85=0,F86=1),(F39*E90*E97*F43/((1+F24/100)*(1+F42/100)))*(1-ABS(F90-E90*F43/((1+F24/100)*(1+F42/100)))/((F39*E90*E97*F43/((1+F24/100)*(1+F42/100)))+(E96*E90*F43/((1+F24/100)*(1+F42/100))))),0))) -> 2.5911314 | G92: =IF(G90=0,0,IF(G85=1,G39*F90*F97*G43/((1+G24/100)*(1+G42/100)),IF(AND(G85=0,G86=1),(G39*F90*F97*G43/((1+G24/100)*(1+G42/100)))*(1-ABS(G90-F90*G43/((1+G24/100)*(1+G42/100)))/((G39*F90*F97*G43/((1+G24/100)*(1+G42/100)))+(F96*F90*G43/((1+G24/100)*(1+G42/100))))),0))) -> 2.7429825 | H92: =IF(H90=0,0,IF(H85=1,H39*G90*G97*H43/((1+H24/100)*(1+H42/100)),IF(AND(H85=0,H86=1),(H39*G90*G97*H43/((1+H24/100)*(1+H42/100)))*(1-ABS(H90-G90*H43/((1+H24/100)*(1+H42/100)))/((H39*G90*G97*H43/((1+H24/100)*(1+H42/100)))+(G96*G90*H43/((1+H24/100)*(1+H42/100))))),0))) -> 2.892139 | I92: =IF(I90=0,0,IF(I85=1,I39*H90*H97*I43/((1+I24/100)*(1+I42/100)),IF(AND(I85=0,I86=1),(I39*H90*H97*I43/((1+I24/100)*(1+I42/100)))*(1-ABS(I90-H90*I43/((1+I24/100)*(1+I42/100)))/((I39*H90*H97*I43/((1+I24/100)*(1+I42/100)))+(H96*H90*I43/((1+I24/100)*(1+I42/100))))),0))) -> 3.0354855 | J92: =IF(J90=0,0,IF(J85=1,J39*I90*I97*J43/((1+J24/100)*(1+J42/100)),IF(AND(J85=0,J86=1),(J39*I90*I97*J43/((1+J24/100)*(1+J42/100)))*(1-ABS(J90-I90*J43/((1+J24/100)*(1+J42/100)))/((J39*I90*I97*J43/((1+J24/100)*(1+J42/100)))+(I96*I90*J43/((1+J24/100)*(1+J42/100))))),0))) -> 3.1886932 | K92: =IF(K90=0,0,IF(K85=1,K39*J90*J97*K43/((1+K24/100)*(1+K42/100)),IF(AND(K85=0,K86=1),(K39*J90*J97*K43/((1+K24/100)*(1+K42/100)))*(1-ABS(K90-J90*K43/((1+K24/100)*(1+K42/100)))/((K39*J90*J97*K43/((1+K24/100)*(1+K42/100)))+(J96*J90*K43/((1+K24/100)*(1+K42/100))))),0))) -> 3.3684977 | L92: =IF(L90=0,0,IF(L85=1,L39*K90*K97*L43/((1+L24/100)*(1+L42/100)),IF(AND(L85=0,L86=1),(L39*K90*K97*L43/((1+L24/100)*(1+L42/100)))*(1-ABS(L90-K90*L43/((1+L24/100)*(1+L42/100)))/((L39*K90*K97*L43/((1+L24/100)*(1+L42/100)))+(K96*K90*L43/((1+L24/100)*(1+L42/100))))),0))) -> 3.5707471 | ... U92: =IF(U90=0,0,IF(U85=1,U39*T90*T97*U43/((1+U24/100)*(1+U42/100)),IF(AND(U85=0,U86=1),(U39*T90*T97*U43/((1+U24/100)*(1+U42/100)))*(1-ABS(U90-T90*U43/((1+U24/100)*(1+U42/100)))/((U39*T90*T97*U43/((1+U24/100)*(1+U42/100)))+(T96*T90*U43/((1+U24/100)*(1+U42/100))))),0))) -> 4.9291166
B93: Rolled over short-term debt | D93: ='Input data'!$C$68*D$90 -> 3.6736521 | E93: =IF(E90=0,0,IF(E85=1,(1-D97)*D90*E43/((1+E24/100)*(1+E42/100)),IF(AND(E85=0,E86=1),(D96*D90*E43/((1+E24/100)*(1+E42/100)))*(1-ABS(E90-D90*E43/((1+E24/100)*(1+E42/100)))/((E39*D90*D97*E43/((1+E24/100)*(1+E42/100)))+(D96*D90*E43/((1+E24/100)*(1+E42/100))))),0))) -> 3.5826776 | F93: =IF(F90=0,0,IF(F85=1,(1-E97)*E90*F43/((1+F24/100)*(1+F42/100)),IF(AND(F85=0,F86=1),(E96*E90*F43/((1+F24/100)*(1+F42/100)))*(1-ABS(F90-E90*F43/((1+F24/100)*(1+F42/100)))/((F39*E90*E97*F43/((1+F24/100)*(1+F42/100)))+(E96*E90*F43/((1+F24/100)*(1+F42/100))))),0))) -> 3.8779057 | G93: =IF(G90=0,0,IF(G85=1,(1-F97)*F90*G43/((1+G24/100)*(1+G42/100)),IF(AND(G85=0,G86=1),(F96*F90*G43/((1+G24/100)*(1+G42/100)))*(1-ABS(G90-F90*G43/((1+G24/100)*(1+G42/100)))/((G39*F90*F97*G43/((1+G24/100)*(1+G42/100)))+(F96*F90*G43/((1+G24/100)*(1+G42/100))))),0))) -> 3.9120079 | H93: =IF(H90=0,0,IF(H85=1,(1-G97)*G90*H43/((1+H24/100)*(1+H42/100)),IF(AND(H85=0,H86=1),(G96*G90*H43/((1+H24/100)*(1+H42/100)))*(1-ABS(H90-G90*H43/((1+H24/100)*(1+H42/100)))/((H39*G90*G97*H43/((1+H24/100)*(1+H42/100)))+(G96*G90*H43/((1+H24/100)*(1+H42/100))))),0))) -> 3.9393731 | I93: =IF(I90=0,0,IF(I85=1,(1-H97)*H90*I43/((1+I24/100)*(1+I42/100)),IF(AND(I85=0,I86=1),(H96*H90*I43/((1+I24/100)*(1+I42/100)))*(1-ABS(I90-H90*I43/((1+I24/100)*(1+I42/100)))/((I39*H90*H97*I43/((1+I24/100)*(1+I42/100)))+(H96*H90*I43/((1+I24/100)*(1+I42/100))))),0))) -> 3.9567354 | J93: =IF(J90=0,0,IF(J85=1,(1-I97)*I90*J43/((1+J24/100)*(1+J42/100)),IF(AND(J85=0,J86=1),(I96*I90*J43/((1+J24/100)*(1+J42/100)))*(1-ABS(J90-I90*J43/((1+J24/100)*(1+J42/100)))/((J39*I90*I97*J43/((1+J24/100)*(1+J42/100)))+(I96*I90*J43/((1+J24/100)*(1+J42/100))))),0))) -> 3.9858133 | K93: =IF(K90=0,0,IF(K85=1,(1-J97)*J90*K43/((1+K24/100)*(1+K42/100)),IF(AND(K85=0,K86=1),(J96*J90*K43/((1+K24/100)*(1+K42/100)))*(1-ABS(K90-J90*K43/((1+K24/100)*(1+K42/100)))/((K39*J90*J97*K43/((1+K24/100)*(1+K42/100)))+(J96*J90*K43/((1+K24/100)*(1+K42/100))))),0))) -> 4.0484584 | L93: =IF(L90=0,0,IF(L85=1,(1-K97)*K90*L43/((1+L24/100)*(1+L42/100)),IF(AND(L85=0,L86=1),(K96*K90*L43/((1+L24/100)*(1+L42/100)))*(1-ABS(L90-K90*L43/((1+L24/100)*(1+L42/100)))/((L39*K90*K97*L43/((1+L24/100)*(1+L42/100)))+(K96*K90*L43/((1+L24/100)*(1+L42/100))))),0))) -> 4.135242 | ... U93: =IF(U90=0,0,IF(U85=1,(1-T97)*T90*U43/((1+U24/100)*(1+U42/100)),IF(AND(U85=0,U86=1),(T96*T90*U43/((1+U24/100)*(1+U42/100)))*(1-ABS(U90-T90*U43/((1+U24/100)*(1+U42/100)))/((U39*T90*T97*U43/((1+U24/100)*(1+U42/100)))+(T96*T90*U43/((1+U24/100)*(1+U42/100))))),0))) -> 5.5007021
B94: New long-term debt | D94: ='Input data'!$C$69*D$90 -> 0.80738171 | E94: =IF(E90=0,0,IF(E85=1,'Input data'!$C$58*(E90-D90*E43/((1+E24/100)*(1+E42/100))),0)) -> 4.2355222 | F94: =IF(F90=0,0,IF(F85=1,'Input data'!$C$58*(F90-E90*F43/((1+F24/100)*(1+F42/100))),0)) -> 1.7159888 | G94: =IF(G90=0,0,IF(G85=1,'Input data'!$C$58*(G90-F90*G43/((1+G24/100)*(1+G42/100))),0)) -> 1.6274901 | H94: =IF(H90=0,0,IF(H85=1,'Input data'!$C$58*(H90-G90*H43/((1+H24/100)*(1+H42/100))),0)) -> 1.5378934 | I94: =IF(I90=0,0,IF(I85=1,'Input data'!$C$58*(I90-H90*I43/((1+I24/100)*(1+I42/100))),0)) -> 1.5420129 | J94: =IF(J90=0,0,IF(J85=1,'Input data'!$C$58*(J90-I90*J43/((1+J24/100)*(1+J42/100))),0)) -> 1.8802123 | K94: =IF(K90=0,0,IF(K85=1,'Input data'!$C$58*(K90-J90*K43/((1+K24/100)*(1+K42/100))),0)) -> 2.1402591 | L94: =IF(L90=0,0,IF(L85=1,'Input data'!$C$58*(L90-K90*L43/((1+L24/100)*(1+L42/100))),0)) -> 2.3195709 | ... U94: =IF(U90=0,0,IF(U85=1,'Input data'!$C$58*(U90-T90*U43/((1+U24/100)*(1+U42/100))),0)) -> 4.0862411
B95: New short-term debt | D95: ='Input data'!$C$70*D$90 -> 0.073048801 | E95: =IF(E90=0,0,IF(E85=1,'Input data'!$C$57*(E90-D90*E43/((1+E24/100)*(1+E42/100))),0)) -> 0.43942648 | F95: =IF(F90=0,0,IF(F85=1,'Input data'!$C$57*(F90-E90*F43/((1+F24/100)*(1+F42/100))),0)) -> 0.17803021 | G95: =IF(G90=0,0,IF(G85=1,'Input data'!$C$57*(G90-F90*G43/((1+G24/100)*(1+G42/100))),0)) -> 0.16884866 | H95: =IF(H90=0,0,IF(H85=1,'Input data'!$C$57*(H90-G90*H43/((1+H24/100)*(1+H42/100))),0)) -> 0.15955319 | I95: =IF(I90=0,0,IF(I85=1,'Input data'!$C$57*(I90-H90*I43/((1+I24/100)*(1+I42/100))),0)) -> 0.15998058 | J95: =IF(J90=0,0,IF(J85=1,'Input data'!$C$57*(J90-I90*J43/((1+J24/100)*(1+J42/100))),0)) -> 0.19506805 | K95: =IF(K90=0,0,IF(K85=1,'Input data'!$C$57*(K90-J90*K43/((1+K24/100)*(1+K42/100))),0)) -> 0.22204736 | L95: =IF(L90=0,0,IF(L85=1,'Input data'!$C$57*(L90-K90*L43/((1+L24/100)*(1+L42/100))),0)) -> 0.24065058 | ... U95: =IF(U90=0,0,IF(U85=1,'Input data'!$C$57*(U90-T90*U43/((1+U24/100)*(1+U42/100))),0)) -> 0.42393888
B96: Share of short-term debt in total government debt | D96: =IF(D90<>0,(D93+D95)/(D91+D92+D93+D94+D95),0) -> 0.082969432 | E96: =IF(E90<>0,(E93+E95)/(E91+E92+E93+E94+E95),0) -> 0.084046602 | F96: =IF(F90<>0,(F93+F95)/(F91+F92+F93+F94+F95),0) -> 0.084438915 | G96: =IF(G90<>0,(G93+G95)/(G91+G92+G93+G94+G95),0) -> 0.084795642 | H96: =IF(H90<>0,(H93+H95)/(H91+H92+H93+H94+H95),0) -> 0.085119953 | I96: =IF(I90<>0,(I93+I95)/(I91+I92+I93+I94+I95),0) -> 0.085433465 | J96: =IF(J90<>0,(J93+J95)/(J91+J92+J93+J94+J95),0) -> 0.085798126 | K96: =IF(K90<>0,(K93+K95)/(K91+K92+K93+K94+K95),0) -> 0.086188976 | ... U96: =IF(U90<>0,(U93+U95)/(U91+U92+U93+U94+U95),0) -> 0.089868058
B97: Share of long-term debt in total government debt | D97: =IF(D90<>0,(D91+D92+D94)/(D91+D92+D93+D94+D95),1) -> 0.91703057 | E97: =IF(E90<>0,(E91+E92+E94)/(E91+E92+E93+E94+E95),1) -> 0.9159534 | F97: =IF(F90<>0,(F91+F92+F94)/(F91+F92+F93+F94+F95),1) -> 0.91556109 | G97: =IF(G90<>0,(G91+G92+G94)/(G91+G92+G93+G94+G95),1) -> 0.91520436 | H97: =IF(H90<>0,(H91+H92+H94)/(H91+H92+H93+H94+H95),1) -> 0.91488005 | I97: =IF(I90<>0,(I91+I92+I94)/(I91+I92+I93+I94+I95),1) -> 0.91456653 | J97: =IF(J90<>0,(J91+J92+J94)/(J91+J92+J93+J94+J95),1) -> 0.91420187 | K97: =IF(K90<>0,(K91+K92+K94)/(K91+K92+K93+K94+K95),1) -> 0.91381102 | ... U97: =IF(U90<>0,(U91+U92+U94)/(U91+U92+U93+U94+U95),1) -> 0.91013194
B99: IIR | C99: ='Baseline NFPC'!C96 -> 1.646586 | D99: ='Baseline NFPC'!D96 -> 1.72 | E99: ='Baseline NFPC'!E96 -> 1.732298 | F99: =F101+F102 -> 1.8261287 | G99: =G101+G102 -> 1.9630297 | H99: =H101+H102 -> 2.0990021 | I99: =I101+I102 -> 2.234119 | J99: =J101+J102 -> 2.3707683 | K99: =K101+K102 -> 2.5163135 | L99: =L101+L102 -> 2.6668445 | M99: =M101+M102 -> 2.8190428 | ... U99: =U101+U102 -> 3.5460259
B100: Long-term implicit interest rate | E100: =((E36*D90)-(E38*(D93+D95)))/(D91+D92+D94) -> 1.7160168 | F100: =IF(E90>0,(E100*E91+ ('Baseline NFPC'!F97*('Baseline NFPC'!E88+'Baseline NFPC'!E89+'Baseline NFPC'!E91)-'Baseline NFPC'!E97*'Baseline NFPC'!E88)/('Baseline NFPC'!E89+'Baseline NFPC'!E91) *(E94+E92))/(E91+E92+E94),F37) -> 1.8079379 | G100: =IF(F90>0,(F100*F91+G37*(F94+F92))/(F91+F92+F94),G37) -> 1.9431639 | H100: =IF(G90>0,(G100*G91+H37*(G94+G92))/(G91+G92+G94),H37) -> 2.0773691 | I100: =IF(H90>0,(H100*H91+I37*(H94+H92))/(H91+H92+H94),I37) -> 2.2106333 | J100: =IF(I90>0,(I100*I91+J37*(I94+I92))/(I91+I92+I94),J37) -> 2.3455619 | K100: =IF(J90>0,(J100*J91+K37*(J94+J92))/(J91+J92+J94),K37) -> 2.4901907 | L100: =IF(K90>0,(K100*K91+L37*(K94+K92))/(K91+K92+K94),L37) -> 2.6402589 | M100: =IF(L90>0,(L100*L91+M37*(L94+L92))/(L91+L92+L94),M37) -> 2.7921474 | N100: =IF(M90>0,(M100*M91+N37*(M94+M92))/(M91+M92+M94),N37) -> 2.9449432 | ... U100: =IF(T90>0,(T100*T91+U37*(T94+T92))/(T91+T92+T94),U37) -> 3.6177504
B101: Nominal implicit interest rate on debt (Excel approximation) | E101: =(E100*(D91+D92+D94)+E38*(D93+D95))/D90 -> 1.732298 | F101: =(F100*(E91+E92+E94)+F38*(E93+E95))/E90 -> 1.8261287 | G101: =(G100*(F91+F92+F94)+G38*(F93+F95))/F90 -> 1.9630297 | H101: =(H100*(G91+G92+G94)+H38*(G93+G95))/G90 -> 2.0990021 | I101: =(I100*(H91+H92+H94)+I38*(H93+H95))/H90 -> 2.234119 | J101: =(J100*(I91+I92+I94)+J38*(I93+I95))/I90 -> 2.3707683 | K101: =(K100*(J91+J92+J94)+K38*(J93+J95))/J90 -> 2.5163135 | L101: =(L100*(K91+K92+K94)+L38*(K93+K95))/K90 -> 2.6668445 | ... U101: =(U100*(T91+T92+T94)+U38*(T93+T95))/T90 -> 3.5460259
B102: Diff. STATA | E102: ='Adjust. no safeguard'!E104 -> 0 | F102: ='Adjust. no safeguard'!F104 -> 0 | G102: ='Adjust. no safeguard'!G104 -> 0 | H102: ='Adjust. no safeguard'!H104 -> 0 | I102: ='Adjust. no safeguard'!I104 -> 0 | J102: ='Adjust. no safeguard'!J104 -> 0 | K102: ='Adjust. no safeguard'!K104 -> 0 | L102: ='Adjust. no safeguard'!L104 -> 0 | ... U102: ='Adjust. no safeguard'!U104 -> 0
B104: (i - g) | C104: =((1+C99/100)/((1+C24/100)*(1+C42/100))-1)*100 -> -4.9030404 | D104: =((1+D99/100)/((1+D24/100)*(1+D42/100))-1)*100 -> -3.0356889 | E104: =((1+E99/100)/((1+E24/100)*(1+E42/100))-1)*100 -> -2.7213543 | F104: =((1+F99/100)/((1+F24/100)*(1+F42/100))-1)*100 -> -1.8244786 | G104: =((1+G99/100)/((1+G24/100)*(1+G42/100))-1)*100 -> -1.6552067 | H104: =((1+H99/100)/((1+H24/100)*(1+H42/100))-1)*100 -> -1.4407754 | I104: =((1+I99/100)/((1+I24/100)*(1+I42/100))-1)*100 -> -1.3123613 | J104: =((1+J99/100)/((1+J24/100)*(1+J42/100))-1)*100 -> -0.88440021 | ... U104: =((1+U99/100)/((1+U24/100)*(1+U42/100))-1)*100 -> -0.36879912

Sheet Adjust. no safeguard
B3: Country | C3: ='Input data'!C3 -> NL
B4: Key years
B5: ='Input data'!B5 -> Last year before the adjustment | C5: =+'Input data'!C5 -> 2025
B6: Last year of adjustment | C6: =+C5+'Criteria results'!$F$5 -> 2029
B7: Last year of no-fiscal-policy-change projections | C7: =C5+'Criteria results'!$F$5+10 -> 2039
B9: Key assumptions
C10: ='Input data'!$C$5-1 -> 2024 | D10: =C10+1 -> 2025 | E10: =D10+1 -> 2026 | F10: =E10+1 -> 2027 | G10: =F10+1 -> 2028 | H10: =G10+1 -> 2029 | I10: =H10+1 -> 2030 | J10: =I10+1 -> 2031 | K10: =J10+1 -> 2032 | ... U10: =T10+1 -> 2042
B11: Fiscal assumptions (% of GDP)
B12: Structural primary balance ('+' means 'surplus') | C12: ='Input data'!C13 -> 0.386237 | D12: ='Input data'!D13 -> -0.5577395 | E12: =IF(E10<=$C$6,D12+'Criteria results'!$F$7,D12) -> -0.5577395 | F12: =IF(F10<=$C$6,E12+'Criteria results'!$F$7,E12) -> -0.5577395 | G12: =IF(G10<=$C$6,F12+'Criteria results'!$F$7,F12) -> -0.5577395 | H12: =IF(H10<=$C$6,G12+'Criteria results'!$F$7,G12) -> -0.5577395 | I12: =IF(I10<=$C$6,H12+'Criteria results'!$F$7,H12) -> -0.5577395 | J12: =IF(J10<=$C$6,I12+'Criteria results'!$F$7,I12) -> -0.5577395 | K12: =IF(K10<=$C$6,J12+'Criteria results'!$F$7,J12) -> -0.5577395 | L12: =K12 -> -0.5577395 | M12: =L12 -> -0.5577395 | N12: =M12 -> -0.5577395 | O12: =N12 -> -0.5577395 | P12: =O12 -> -0.5577395 | Q12: =P12 -> -0.5577395 | R12: =Q12 -> -0.5577395 | S12: =R12 -> -0.5577395 | ... U12: =T12 -> -0.5577395
B13: Annual change in SPB | E13: =E12-D12 -> 0 | F13: =F12-E12 -> 0 | G13: =G12-F12 -> 0 | H13: =H12-G12 -> 0 | I13: =I12-H12 -> 0 | J13: =J12-I12 -> 0 | K13: =K12-J12 -> 0 | L13: =L12-K12 -> 0 | ... U13: =U12-T12 -> 0
B14: One-off and other temporary measures | C14: ='Input data'!C14 -> -0.026727 | D14: ='Input data'!D14 -> -0.0254775 | E14: ='Input data'!E14 -> -0.6901042 | F14: ='Input data'!F14 -> 0 | G14: ='Input data'!G14 -> 0 | H14: ='Input data'!H14 -> 0 | I14: ='Input data'!I14 -> 0 | J14: ='Input data'!J14 -> 0 | ... U14: ='Input data'!U14 -> 0
B15: Stock flow adjustments (without exchange rate effect) | C15: ='Input data'!C15 -> -0.0919396 | D15: ='Input data'!D15 -> 1.579996 | E15: ='Input data'!E15 -> 2.014675 | F15: ='Input data'!F15 -> 0 | G15: ='Input data'!G15 -> 0 | H15: ='Input data'!H15 -> 0 | I15: ='Input data'!I15 -> 0 | J15: ='Input data'!J15 -> 0 | ... U15: ='Input data'!U15 -> 0
B17: ='Input data'!B19 -> Cost of ageing and selected public revenue (based on the Commission-Council 2024 Ageing Report ("AR 2024"))
B18: Total ageing cost (net of taxes on pensions) | C18: ='Input data'!C20 -> 18.2 | D18: ='Input data'!D20 -> 18.1 | E18: ='Input data'!E20 -> 18.1 | F18: ='Input data'!F20 -> 18.3 | G18: ='Input data'!G20 -> 18.4 | H18: ='Input data'!H20 -> 18.5 | I18: ='Input data'!I20 -> 18.6 | J18: ='Input data'!J20 -> 18.9 | ... U18: ='Input data'!U20 -> 20.2
B19: Property income | C19: ='Input data'!C26 -> 0.6265708 | D19: ='Input data'!D26 -> 0.6208305 | E19: ='Input data'!E26 -> 0.6150902 | F19: ='Input data'!F26 -> 0.6093498 | G19: ='Input data'!G26 -> 0.6036096 | H19: ='Input data'!H26 -> 0.5978693 | I19: ='Input data'!I26 -> 0.5921289 | J19: ='Input data'!J26 -> 0.5863886 | ... U19: ='Input data'!U26 -> 0.5232452
B21: GDP growth assumptions
B22: Actual GDP (real)
B23: Level | C23: ='Baseline NFPC'!C22 -> 915.5005 | D23: ='Baseline NFPC'!D22 -> 931.03352 | E23: =IF(AND(E50>1,D50>1), E27*(1+('Baseline NFPC'!E$29+E51)/100)-D23*$C$47*(E12-D12)/100, IF(E50=1,E27,D23*(1+E52/100))) -> 942.89253 | F23: =IF(AND(F50>1,E50>1), F27*(1+('Baseline NFPC'!F$29+F51)/100)-E23*$C$47*(F12-E12)/100, IF(F50=1,F27,E23*(1+F52/100))) -> 957.80782 | G23: =IF(AND(G50>1,F50>1), G27*(1+G51/100)-F23*$C$47*(G12-F12)/100, IF(G50=1,G27,F23*(1+G52/100))) -> 972.3799 | H23: =IF(AND(H50>1,G50>1), H27*(1+H51/100)-G23*$C$47*(H12-G12)/100, IF(H50=1,H27,G23*(1+H52/100))) -> 986.12624 | I23: =IF(AND(I50>1,H50>1), I27*(1+I51/100)-H23*$C$47*(I12-H12)/100, IF(I50=1,I27,H23*(1+I52/100))) -> 999.87117 | J23: =IF(AND(J50>1,I50>1), J27*(1+J51/100)-I23*$C$47*(J12-I12)/100, IF(J50=1,J27,I23*(1+J52/100))) -> 1010.5611 | K23: =IF(AND(K50>1,J50>1), K27*(1+K51/100)-J23*$C$47*(K12-J12)/100, IF(K50=1,K27,J23*(1+K52/100))) -> 1021.0134 | L23: =IF(AND(L50>1,K50>1), L27*(1+L51/100)-K23*$C$47*(L12-K12)/100, IF(L50=1,L27,K23*(1+L52/100))) -> 1031.3515 | M23: =IF(AND(M50>1,L50>1), M27*(1+M51/100)-L23*$C$47*(M12-L12)/100, IF(M50=1,M27,L23*(1+M52/100))) -> 1041.9392 | N23: =IF(AND(N50>1,M50>1), N27*(1+N51/100)-M23*$C$47*(N12-M12)/100, IF(N50=1,N27,M23*(1+N52/100))) -> 1052.9312 | ... U23: =IF(AND(U50>1,T50>1), U27*(1+U51/100)-T23*$C$47*(U12-T12)/100, IF(U50=1,U27,T23*(1+U52/100))) -> 1163.5727
B24: Growth rate | C24: ='Baseline NFPC'!C23 -> 1.081005 | D24: ='Baseline NFPC'!D23 -> 1.69667 | E24: =100*(E23/D23-1) -> 1.273747 | F24: =100*(F23/E23-1) -> 1.581865 | G24: =100*(G23/F23-1) -> 1.521399 | H24: =100*(H23/G23-1) -> 1.41368 | I24: =100*(I23/H23-1) -> 1.393831 | J24: =100*(J23/I23-1) -> 1.069126 | K24: =100*(K23/J23-1) -> 1.03431 | L24: =100*(L23/K23-1) -> 1.012531 | ... U24: =100*(U23/T23-1) -> 1.710004
B26: Potential GDP (real)
B27: Level | C27: ='Input data'!C34 -> 924.6414 | D27: =+C27*(1+'Input data'!D33/100) -> 939.95618 | E27: =+D27*(1+'Input data'!E33/100) -> 953.36237 | F27: =+E27*(1+'Input data'!F33/100) -> 965.68823 | G27: =+F27*(1+'Input data'!G33/100) -> 977.69888 | H27: =+G27*(1+'Input data'!H33/100) -> 988.81595 | I27: =+H27*(1+'Input data'!I33/100) -> 999.87118 | J27: =+I27*(1+'Input data'!J33/100) -> 1010.5611 | K27: =+J27*(1+'Input data'!K33/100) -> 1021.0134 | ... U27: =+T27*(1+'Input data'!U33/100) -> 1163.5726
B29: Output gap
B30: Output gap | C30: =100*(C23/C27-1) -> -0.98858866 | D30: =100*(D23/D27-1) -> -0.94926316 | E30: =100*(E23/E27-1) -> -1.0982012 | F30: =100*(F23/F27-1) -> -0.8160408 | G30: =100*(G23/G27-1) -> -0.54403071 | H30: =100*(H23/H27-1) -> -0.27201359 | I30: =100*(I23/I27-1) -> -9.9246313e-07 | J30: =100*(J23/J27-1) -> -2.9713068e-06 | ... U30: =100*(U23/U27-1) -> 6.9328616e-06
B32: Actual GDP (nominal, national currency)
B33: Growth rate | C33: =100*((1+C24/100)*(1+C42/100)-1) -> 6.8873142 | D33: =100*((1+D24/100)*(1+D42/100)-1) -> 4.9045765 | E33: =100*((1+E24/100)*(1+E42/100)-1) -> 4.5782425 | F33: =100*((1+F24/100)*(1+F42/100)-1) -> 3.7184496 | G33: =100*((1+G24/100)*(1+G42/100)-1) -> 3.6791337 | H33: =100*((1+H24/100)*(1+H42/100)-1) -> 3.5915233 | I33: =100*((1+I24/100)*(1+I42/100)-1) -> 3.5936418 | J33: =100*((1+J24/100)*(1+J42/100)-1) -> 3.2842141 | ... U33: =100*((1+U24/100)*(1+U42/100)-1) -> 3.9293163
B35: Interest rates
B36: Nominal implicit interest rate on debt | C36: ='Input data'!C37 -> 1.646586 | D36: ='Input data'!D37 -> 1.72 | E36: ='Input data'!E37 -> 1.732298 | F36: =F101 -> 1.8261287 | G36: =G101 -> 1.9630297 | H36: =H101 -> 2.0990021 | I36: =I101 -> 2.234119 | J36: =J101 -> 2.3707683 | K36: =K101 -> 2.5163135 | L36: =L101 -> 2.6668445 | M36: =M101 -> 2.8190428 | ... U36: =U101 -> 3.5460259
B37: Long-term interest rate | C37: ='Input data'!C$39 -> 2.6205 | D37: ='Input data'!D$39 -> 2.78965 | E37: ='Input data'!E$39 -> 2.894953 | F37: ='Input data'!F$39 -> 3.081676 | G37: ='Baseline NFPC'!G36 -> 3.188669 | H37: ='Baseline NFPC'!H36 -> 3.295662 | I37: ='Baseline NFPC'!I36 -> 3.402655 | J37: ='Baseline NFPC'!J36 -> 3.509648 | K37: ='Baseline NFPC'!K36 -> 3.616641 | L37: ='Baseline NFPC'!L36 -> 3.723634 | M37: ='Baseline NFPC'!M36 -> 3.830627 | N37: ='Baseline NFPC'!N36 -> 3.93762 | ... U37: ='Baseline NFPC'!U36 -> 3.959453
B38: Short-term interest rate | C38: ='Input data'!C$38 -> 3.570833 | D38: ='Input data'!D$38 -> 2.172583 | E38: ='Input data'!E$38 -> 1.91225 | F38: ='Input data'!F$38 -> 2.024375 | G38: ='Baseline NFPC'!G37 -> 2.1784319 | H38: ='Baseline NFPC'!H37 -> 2.3324888 | I38: ='Baseline NFPC'!I37 -> 2.4865456 | J38: ='Baseline NFPC'!J37 -> 2.6406025 | K38: ='Baseline NFPC'!K37 -> 2.7946594 | L38: ='Baseline NFPC'!L37 -> 2.9487163 | M38: ='Baseline NFPC'!M37 -> 3.1027731 | N38: ='Baseline NFPC'!N37 -> 3.25683 | ... U38: ='Baseline NFPC'!U37 -> 2.8169395
B39: Share of long-term debt that matures every year | C39: ='Baseline NFPC'!C38 -> 0.08837902 | D39: ='Baseline NFPC'!D38 -> 0.05460046 | E39: ='Baseline NFPC'!E38 -> 0.05795577 | F39: ='Baseline NFPC'!F38 -> 0.061311081 | G39: ='Baseline NFPC'!G38 -> 0.064666392 | H39: ='Baseline NFPC'!H38 -> 0.068021703 | I39: ='Baseline NFPC'!I38 -> 0.071377014 | J39: ='Baseline NFPC'!J38 -> 0.074732326 | ... U39: ='Baseline NFPC'!U38 -> 0.08815357
B41: Inflation and exchange rate
B42: GDP deflator (National currency) | C42: ='Input data'!C42 -> 5.744214 | D42: ='Input data'!D42 -> 3.154387 | E42: ='Input data'!E42 -> 3.262934 | F42: ='Input data'!F42 -> 2.103313 | G42: ='Baseline NFPC'!G41 -> 2.1253989 | H42: ='Baseline NFPC'!H41 -> 2.1474847 | I42: ='Baseline NFPC'!I41 -> 2.1695706 | J42: ='Baseline NFPC'!J41 -> 2.1916565 | K42: ='Baseline NFPC'!K41 -> 2.2137424 | L42: ='Baseline NFPC'!L41 -> 2.2358282 | M42: ='Baseline NFPC'!M41 -> 2.2579141 | N42: ='Baseline NFPC'!N41 -> 2.28 | ... U42: ='Baseline NFPC'!U41 -> 2.182
B43: Exchange rate composite change (weighted by share of debt in each currency) | C43: ='Baseline NFPC'!C42 -> 0.9999999 | D43: ='Baseline NFPC'!D42 -> 1 | E43: ='Baseline NFPC'!E42 -> 1 | F43: ='Baseline NFPC'!F42 -> 0.9999999 | G43: ='Baseline NFPC'!G42 -> 1 | H43: ='Baseline NFPC'!H42 -> 1 | I43: ='Baseline NFPC'!I42 -> 1 | J43: ='Baseline NFPC'!J42 -> 1 | ... U43: ='Baseline NFPC'!U42 -> 1
B45: Intermediate calculations (growth rate equation)
B47: Fiscal multiplier | C47: ='Input data'!C49 -> 0.6
B48: Budget balance semi-elasticity | C48: ='Input data'!C50 -> 0.605
B50: Auxiliary variable to control the closure of the output gap | C50: 0 | D50: =IF(AND(ABS((D12-C12)-('Input data'!D13-'Input data'!C13))>0.0001,ABS(D12-C12)>0.0001,D$10>$C$5),4,IF(C50=4,3,IF(C50=3,2,IF(C50=2,1,0)))) -> 0 | E50: =IF(AND(ABS((E12-D12)-('Baseline NFPC'!E12-'Baseline NFPC'!D12))>0.0001,ABS(E12-D12)>0.0001,E$10>$C$5),4,IF(D50=4,3,IF(D50=3,2,IF(D50=2,1,0)))) -> 0 | F50: =IF(AND(ABS((F12-E12)-('Baseline NFPC'!F12-'Baseline NFPC'!E12))>0.0001,ABS(F12-E12)>0.0001,F$10>$C$5),4,IF(E50=4,3,IF(E50=3,2,IF(E50=2,1,0)))) -> 0 | G50: =IF(AND(ABS((G12-F12)-('Baseline NFPC'!G12-'Baseline NFPC'!F12))>0.0001,ABS(G12-F12)>0.0001,G$10>$C$5),4,IF(F50=4,3,IF(F50=3,2,IF(F50=2,1,0)))) -> 0 | H50: =IF(AND(ABS((H12-G12)-('Baseline NFPC'!H12-'Baseline NFPC'!G12))>0.0001,ABS(H12-G12)>0.0001,H$10>$C$5),4,IF(G50=4,3,IF(G50=3,2,IF(G50=2,1,0)))) -> 0 | I50: =IF(AND(ABS((I12-H12)-('Baseline NFPC'!I12-'Baseline NFPC'!H12))>0.0001,ABS(I12-H12)>0.0001,I$10>$C$5),4,IF(H50=4,3,IF(H50=3,2,IF(H50=2,1,0)))) -> 0 | J50: =IF(AND(ABS((J12-I12)-('Baseline NFPC'!J12-'Baseline NFPC'!I12))>0.0001,ABS(J12-I12)>0.0001,J$10>$C$5),4,IF(I50=4,3,IF(I50=3,2,IF(I50=2,1,0)))) -> 0 | K50: =IF(AND(ABS((K12-J12)-('Baseline NFPC'!K12-'Baseline NFPC'!J12))>0.0001,ABS(K12-J12)>0.0001,K$10>$C$5),4,IF(J50=4,3,IF(J50=3,2,IF(J50=2,1,0)))) -> 0 | L50: =IF(AND(ABS((L12-K12)-('Baseline NFPC'!L12-'Baseline NFPC'!K12))>0.0001,ABS(L12-K12)>0.0001,L$10>$C$5),4,IF(K50=4,3,IF(K50=3,2,IF(K50=2,1,0)))) -> 0 | ... U50: =IF(AND(ABS((U12-T12)-('Baseline NFPC'!U12-'Baseline NFPC'!T12))>0.0001,ABS(U12-T12)>0.0001,U$10>$C$5),4,IF(T50=4,3,IF(T50=3,2,IF(T50=2,1,0)))) -> 0
B51: OG intermediate auxiliary value | C51: 0 | D51: =IF(C50=4,2/3*(C30-'Baseline NFPC'!C29),IF(C50=3,1/3*(#REF!-'Baseline NFPC'!#REF!),0)) -> 0 | E51: =IF(D50=4,2/3*(D30-'Baseline NFPC'!D29),IF(D50=3,1/3*(C30-'Baseline NFPC'!C29),0)) -> 0 | F51: =IF(E50=4,2/3*(E30-'Baseline NFPC'!E29),IF(E50=3,1/3*(D30-'Baseline NFPC'!D29),0)) -> 0 | G51: =IF(F50=4,2/3*F30,IF(F50=3,1/3*E30,0)) -> 0 | H51: =IF(G50=4,2/3*G30,IF(G50=3,1/3*F30,0)) -> 0 | I51: =IF(H50=4,2/3*H30,IF(H50=3,1/3*G30,0)) -> 0 | J51: =IF(I50=4,2/3*I30,IF(I50=3,1/3*H30,0)) -> 0 | K51: =IF(J50=4,2/3*J30,IF(J50=3,1/3*I30,0)) -> 0 | L51: =IF(K50=4,2/3*K30,IF(K50=3,1/3*J30,0)) -> 0 | M51: =IF(L50=4,2/3*L30,IF(L50=3,1/3*K30,0)) -> 0 | N51: =IF(M50=4,2/3*M30,IF(M50=3,1/3*L30,0)) -> 0 | ... U51: =IF(T50=4,2/3*T30,IF(T50=3,1/3*S30,0)) -> 0
B52: GDP intermediate growth rate - only feedback effect and no closure of the OG | C52: 0 | D52: ='Input data'!D30-$C$47*((D12-C12)-('Input data'!D13-'Input data'!C13)) -> 1.69667 | E52: ='Input data'!E30-$C$47*(E12-D12) -> 1.273747 | F52: ='Input data'!F30-$C$47*(F12-E12) -> 1.581865 | G52: ='Input data'!G30-$C$47*(G12-F12) -> 1.521399 | H52: ='Input data'!H30-$C$47*(H12-G12) -> 1.41368 | I52: ='Input data'!I30-$C$47*(I12-H12) -> 1.393831 | J52: ='Input data'!J30-$C$47*(J12-I12) -> 1.069126 | K52: ='Input data'!K30-$C$47*(K12-J12) -> 1.03431 | L52: ='Input data'!L30-$C$47*(L12-K12) -> 1.012531 | ... U52: ='Input data'!U30-$C$47*(U12-T12) -> 1.710004
B54: Debt projections
C56: ='Input data'!$C$5-1 -> 2024 | D56: =C56+1 -> 2025 | E56: =D56+1 -> 2026 | F56: =E56+1 -> 2027 | G56: =F56+1 -> 2028 | H56: =G56+1 -> 2029 | I56: =H56+1 -> 2030 | J56: =I56+1 -> 2031 | K56: =J56+1 -> 2032 | ... U56: =T56+1 -> 2042
B57: Gross debt | C57: =+'Input data'!C12 -> 43.74815 | D57: =+C57+D58 -> 45.15761 | E57: =+D57+E58 -> 47.855645 | F57: =+E57+F58 -> 48.033971 | G57: =+F57+G58 -> 48.125788 | H57: =+G57+H58 -> 48.154711 | I57: =+H57+I58 -> 48.186228 | J57: =+I57+J58 -> 48.72929 | K57: =+J57+K58 -> 49.548171 | ... U57: =+T57+U58 -> 65.925998
B58: Change in debt (-1+2+3) | D58: =-D59+D67+D72 -> 1.4094602 | E58: =-E59+E67+E72 -> 2.6980344 | F58: =-F59+F67+F72 -> 0.17832642 | G58: =-G59+G67+G72 -> 0.091816569 | H58: =-H59+H67+H72 -> 0.028923207 | I58: =-I59+I67+I72 -> 0.031516731 | J58: =-J59+J67+J72 -> 0.5430629 | K58: =-K59+K67+K72 -> 0.81888086 | ... U58: =-U59+U67+U72 -> 2.0969585
B59: (1) Primary balance (1.1 + 1.2 - 1.3 -1.4 -1.5 - 1.6 -1.7) | D59: =D60+D61-D62-D63-D64-D65-D66 -> -1.1575212 | E59: =E60+E61-E62-E63-E64-E65-E66 -> -1.9122554 | F59: =F60+F61-F62-F63-F64-F65-F66 -> -1.0514442 | G59: =G60+G61-G62-G63-G64-G65-G66 -> -0.88687808 | H59: =H60+H61-H62-H63-H64-H65-H66 -> -0.72230772 | I59: =I60+I61-I62-I63-I64-I65-I66 -> -0.6634805 | J59: =J60+J61-J62-J63-J64-J65-J66 -> -0.969222 | K59: =K60+K61-K62-K63-K64-K65-K66 -> -1.1749623 | ... U59: =U60+U61-U62-U63-U64-U65-U66 -> -2.3323594
B60: (1.1) Structural primary balance (before ageing cost) | D60: =D12 -> -0.5577395 | E60: =IF(E12="",D60,E12) -> -0.5577395 | F60: =IF(F12="",E60,F12) -> -0.5577395 | G60: =IF(G12="",F60,G12) -> -0.5577395 | H60: =IF(H12="",G60,H12) -> -0.5577395 | I60: =IF(I12="",H60,I12) -> -0.5577395 | J60: =IF(J12="",I60,J12) -> -0.5577395 | K60: =IF(K12="",J60,K12) -> -0.5577395 | L60: =IF(L12="",K60,L12) -> -0.5577395 | ... U60: =IF(U12="",T60,U12) -> -0.5577395
B61: (1.2) Cumulated budgetary effort (in terms of primary balance) | D61: 0 | E61: 0 | F61: 0 | G61: 0 | H61: 0 | I61: 0 | J61: 0 | K61: 0 | L61: 0 | M61: 0 | N61: 0 | O61: 0 | P61: 0 | Q61: 0 | R61: 0 | S61: 0 | T61: 0 | U61: 0
B62: (1.3) Cyclical component | D62: =-$C$48*D30 -> 0.57430421 | E62: =-$C$48*E30 -> 0.66441172 | F62: =-$C$48*F30 -> 0.49370469 | G62: =-$C$48*G30 -> 0.32913858 | H62: =-$C$48*H30 -> 0.16456822 | I62: =-$C$48*I30 -> 6.004402e-07 | J62: =-$C$48*J30 -> 1.7976406e-06 | K62: =-$C$48*K30 -> 1.7976406e-06 | ... U62: =-$C$48*U30 -> -4.1943813e-06
B63: (1.4) One-off and other temporary measures | D63: =-D14 -> 0.0254775 | E63: =-E14 -> 0.6901042 | F63: =-F14 -> 0 | G63: =-G14 -> 0 | H63: =-H14 -> 0 | I63: =-I14 -> 0 | J63: =-J14 -> 0 | K63: =-K14 -> 0 | ... U63: =-U14 -> 0
B64: (1.5) Cost of ageing | D64: =IF(D$56<=$C$6,0,HLOOKUP(D$56,'Input data'!$C$9:$AZ$26,12,FALSE)-HLOOKUP($C$6,'Input data'!$C$9:$AZ$26,12,FALSE)) -> 0 | E64: =IF(E$56<=$C$6,0,HLOOKUP(E$56,'Input data'!$C$9:$AZ$26,12,FALSE)-HLOOKUP($C$6,'Input data'!$C$9:$AZ$26,12,FALSE)) -> 0 | F64: =IF(F$56<=$C$6,0,HLOOKUP(F$56,'Input data'!$C$9:$AZ$26,12,FALSE)-HLOOKUP($C$6,'Input data'!$C$9:$AZ$26,12,FALSE)) -> 0 | G64: =IF(G$56<=$C$6,0,HLOOKUP(G$56,'Input data'!$C$9:$AZ$26,12,FALSE)-HLOOKUP($C$6,'Input data'!$C$9:$AZ$26,12,FALSE)) -> 0 | H64: =IF(H$56<=$C$6,0,HLOOKUP(H$56,'Input data'!$C$9:$AZ$26,12,FALSE)-HLOOKUP($C$6,'Input data'!$C$9:$AZ$26,12,FALSE)) -> 0 | I64: =IF(I$56<=$C$6,0,HLOOKUP(I$56,'Input data'!$C$9:$AZ$26,12,FALSE)-HLOOKUP($C$6,'Input data'!$C$9:$AZ$26,12,FALSE)) -> 0.1 | J64: =IF(J$56<=$C$6,0,HLOOKUP(J$56,'Input data'!$C$9:$AZ$26,12,FALSE)-HLOOKUP($C$6,'Input data'!$C$9:$AZ$26,12,FALSE)) -> 0.4 | K64: =IF(K$56<=$C$6,0,HLOOKUP(K$56,'Input data'!$C$9:$AZ$26,12,FALSE)-HLOOKUP($C$6,'Input data'!$C$9:$AZ$26,12,FALSE)) -> 0.6 | ... U64: =IF(U$56<=$C$6,0,HLOOKUP(U$56,'Input data'!$C$9:$AZ$26,12,FALSE)-HLOOKUP($C$6,'Input data'!$C$9:$AZ$26,12,FALSE)) -> 1.7
B65: (1.6) Property incomes | D65: =IF(D$56<=$C$5,0,-HLOOKUP(D$56,'Input data'!$C$9:$AZ$26,18,FALSE)+HLOOKUP($C$6,'Input data'!$C$9:$AZ$26,18,FALSE)) -> 0 | E65: =IF(E$56<=$C$6,0,-HLOOKUP(E$56,'Input data'!$C$9:$AZ$26,18,FALSE)+HLOOKUP($C$6,'Input data'!$C$9:$AZ$26,18,FALSE)) -> 0 | F65: =IF(F$56<=$C$6,0,-HLOOKUP(F$56,'Input data'!$C$9:$AZ$26,18,FALSE)+HLOOKUP($C$6,'Input data'!$C$9:$AZ$26,18,FALSE)) -> 0 | G65: =IF(G$56<=$C$6,0,-HLOOKUP(G$56,'Input data'!$C$9:$AZ$26,18,FALSE)+HLOOKUP($C$6,'Input data'!$C$9:$AZ$26,18,FALSE)) -> 0 | H65: =IF(H$56<=$C$6,0,-HLOOKUP(H$56,'Input data'!$C$9:$AZ$26,18,FALSE)+HLOOKUP($C$6,'Input data'!$C$9:$AZ$26,18,FALSE)) -> 0 | I65: =IF(I$56<=$C$6,0,-HLOOKUP(I$56,'Input data'!$C$9:$AZ$26,18,FALSE)+HLOOKUP($C$6,'Input data'!$C$9:$AZ$26,18,FALSE)) -> 0.0057404 | J65: =IF(J$56<=$C$6,0,-HLOOKUP(J$56,'Input data'!$C$9:$AZ$26,18,FALSE)+HLOOKUP($C$6,'Input data'!$C$9:$AZ$26,18,FALSE)) -> 0.0114807 | K65: =IF(K$56<=$C$6,0,-HLOOKUP(K$56,'Input data'!$C$9:$AZ$26,18,FALSE)+HLOOKUP($C$6,'Input data'!$C$9:$AZ$26,18,FALSE)) -> 0.017221 | L65: =IF(L$56<=$C$6,0,-HLOOKUP(L$56,'Input data'!$C$9:$AZ$26,18,FALSE)+HLOOKUP($C$6,'Input data'!$C$9:$AZ$26,18,FALSE)) -> 0.0229613 | ... U65: =IF(U$56<=$C$6,0,-HLOOKUP(U$56,'Input data'!$C$9:$AZ$26,18,FALSE)+HLOOKUP($C$6,'Input data'!$C$9:$AZ$26,18,FALSE)) -> 0.0746241
B66: (1.7) Revenues | D66: 0 | E66: 0 | F66: 0 | G66: 0 | H66: 0 | I66: 0 | J66: 0 | K66: 0 | L66: 0 | M66: 0 | N66: 0 | O66: 0 | P66: 0 | Q66: 0 | R66: 0 | S66: 0 | T66: 0 | U66: 0
B67: (2) Snowball effect (2.1 + 2.2 + 2.3) | D67: =SUM(D68:D71) -> -1.328058 | E67: =SUM(E68:E71) -> -1.228898 | F67: =SUM(F68:F71) -> -0.87311572 | G67: =SUM(G68:G71) -> -0.79506151 | H67: =SUM(H68:H71) -> -0.69338452 | I67: =SUM(I68:I71) -> -0.63196377 | J67: =SUM(J68:J71) -> -0.4261591 | K67: =SUM(K68:K71) -> -0.35608144 | ... U67: =SUM(U68:U71) -> -0.23540094
B68: (2.1) Interest expenditure | D68: =C57*D36/100*(1/(1+D33/100)) -> 0.71728823 | E68: =D57*E36/100*(1/(1+E33/100)) -> 0.74801829 | F68: =E57*F36/100*(1/(1+F33/100)) -> 0.84257493 | G68: =F57*G36/100*(1/(1+G33/100)) -> 0.90946084 | H68: =G57*H36/100*(1/(1+H33/100)) -> 0.97513896 | I68: =H57*I36/100*(1/(1+I33/100)) -> 1.0385131 | J68: =I57*J36/100*(1/(1+J33/100)) -> 1.1060585 | K68: =J57*K36/100*(1/(1+K33/100)) -> 1.1873443 | ... U68: =T57*U36/100*(1/(1+U33/100)) -> 2.1778208
B69: (2.2) Growth effect | D69: =-C57*(D24/100)*(1/(1+D33/100)) -> -0.70755897 | E69: =-D57*(E24/100)*(1/(1+E33/100)) -> -0.55001279 | F69: =-E57*(F24/100)*(1/(1+F33/100)) -> -0.72987178 | G69: =-F57*(G24/100)*(1/(1+G33/100)) -> -0.70485577 | H69: =-G57*(H24/100)*(1/(1+H33/100)) -> -0.65675705 | I69: =-H57*(I24/100)*(1/(1+I33/100)) -> -0.64791166 | J69: =-I57*(J24/100)*(1/(1+J33/100)) -> -0.49879015 | K69: =-J57*(K24/100)*(1/(1+K33/100)) -> -0.48804812 | ... U69: =-T57*(U24/100)*(1/(1+U33/100)) -> -1.0502129
B70: (2.3) Inflation effect | D70: =-C57*D42/100*(1/(1+D42/100)) -> -1.337787 | E70: =-D57*E42/100*(1/(1+E42/100)) -> -1.4269041 | F70: =-E57*F42/100*(1/(1+F42/100)) -> -0.98581913 | G70: =-F57*G42/100*(1/(1+G42/100)) -> -0.99966658 | H70: =-G57*H42/100*(1/(1+H42/100)) -> -1.0117664 | I70: =-H57*I42/100*(1/(1+I42/100)) -> -1.0225652 | J70: =-I57*J42/100*(1/(1+J42/100)) -> -1.0334274 | K70: =-J57*K42/100*(1/(1+K42/100)) -> -1.0553776 | ... U70: =-T57*U42/100*(1/(1+U42/100)) -> -1.3630088
B71: (2.4) Exchange rate effect linked to the interest rate | D71: ='Baseline NFPC'!D70 -> -2.8636209e-07 | E71: ='Baseline NFPC'!E70 -> 5.7763161e-07 | F71: ='Baseline NFPC'!F70 -> 2.6384936e-07 | G71: 0 | H71: 0 | I71: 0 | J71: 0 | K71: 0 | L71: 0 | M71: 0 | N71: 0 | O71: 0 | P71: 0 | Q71: 0 | R71: 0 | S71: 0 | T71: 0 | U71: 0
B72: (3 ) Stock flow adjustments (3.1 + 3.2) | D72: ='Input data'!D16 -> 1.579997 | E72: ='Input data'!E16 -> 2.014677 | F72: ='Input data'!F16 -> -2.05e-06 | G72: ='Input data'!G16 -> 0 | H72: ='Input data'!H16 -> 0 | I72: ='Input data'!I16 -> 0 | J72: ='Input data'!J16 -> 0 | K72: ='Input data'!K16 -> 0 | ... U72: ='Input data'!U16 -> 0
B73: (3.1) Base | D73: =D15 -> 1.579996 | E73: =E15 -> 2.014675 | F73: =F15 -> 0 | G73: =G15 -> 0 | H73: =H15 -> 0 | I73: =I15 -> 0 | J73: =J15 -> 0 | K73: =K15 -> 0 | ... U73: =U15 -> 0
B74: (3.2) Adjustment due to the exchange rate effect linked to debt value | D74: =+D72-D73 -> 1e-06 | E74: =+E72-E73 -> 2e-06 | F74: =+F72-F73 -> -2.05e-06 | G74: =+G72-G73 -> 0 | H74: =+H72-H73 -> 0 | I74: =+I72-I73 -> 0 | J74: =+J72-J73 -> 0 | K74: =+K72-K73 -> 0 | ... U74: =+U72-U73 -> 0
B76: Other budgetary variables
B77: Headline balance | C77: ='Baseline NFPC'!C76 -> -0.9448897 | D77: =D59-D68-D71 -> -1.8748092 | E77: =E59-E68-E71 -> -2.6602743 | F77: =F59-F68-F71 -> -1.8940194 | G77: =G59-G68-G71 -> -1.7963389 | H77: =H59-H68-H71 -> -1.6974467 | I77: =I59-I68-I71 -> -1.7019936 | J77: =J59-J68-J71 -> -2.0752805 | K77: =K59-K68-K71 -> -2.3623066 | ... U77: =U59-U68-U71 -> -4.5101802
B78: Structural balance | C78: ='Baseline NFPC'!C77 -> -0.3200694 | D78: =D60-D68-D71-D64-D65-D66 -> -1.2750274 | E78: =E60-E68-E71-E64-E65-E66 -> -1.3057584 | F78: =F60-F68-F71-F64-F65-F66 -> -1.4003147 | G78: =G60-G68-G71-G64-G65-G66 -> -1.4672003 | H78: =H60-H68-H71-H64-H65-H66 -> -1.5328785 | I78: =I60-I68-I71-I64-I65-I66 -> -1.701993 | J78: =J60-J68-J71-J64-J65-J66 -> -2.0752787 | K78: =K60-K68-K71-K64-K65-K66 -> -2.3623048 | ... U78: =U60-U68-U71-U64-U65-U66 -> -4.5101844
B79: Net expenditure growth | C79: ='Input data'!C45 -> 6.2115937 | D79: ='Input data'!D45 -> 7.2645885 | E79: ='Input data'!E33+E42-(E$12-D$12)/'Input data'!$C$64*100 -> 4.689191 | F79: ='Input data'!F33+F42-(F$12-E$12)/'Input data'!$C$64*100 -> 3.396196 | G79: ='Input data'!G33+G42-(G$12-F$12)/'Input data'!$C$64*100 -> 3.3691389 | H79: ='Input data'!H33+H42-(H$12-G$12)/'Input data'!$C$64*100 -> 3.2845498 | I79: ='Input data'!I33+I42-(I$12-H$12)/'Input data'!$C$64*100 -> 3.2875976 | J79: ='Input data'!J33+J42-(J$12-I$12)/'Input data'!$C$64*100 -> 3.2607845 | K79: ='Input data'!K33+K42-(K$12-J$12)/'Input data'!$C$64*100 -> 3.2480524 | L79: ='Input data'!L33+L42-(L$12-K$12)/'Input data'!$C$64*100 -> 3.2483582 | ... U79: ='Input data'!U33+U42-(U$12-T$12)/'Input data'!$C$64*100 -> 3.892
B81: Average net primary expenditure growth
B83: Debt decreasing? (For criterion 1) | I83: =IF(I57<H57,0,1) -> 1 | J83: =IF(J57<I57,0,1) -> 1 | K83: =IF(K57<J57,0,1) -> 1 | L83: =IF(L57<K57,0,1) -> 1 | M83: =IF(M57<L57,0,1) -> 1 | N83: =IF(N57<M57,0,1) -> 1 | O83: =IF(O57<N57,0,1) -> 1 | P83: =IF(P57<O57,0,1) -> 1 | ... U83: =IF(U57<T57,0,1) -> 1
B85: Debt decomposition and IIR
B87: Auxiliary variable identifying whether debt is increasing | D87: =IF((D92-C92*D43/((1+D24/100)*(1+D42/100)))>0,1,0) -> 1 | E87: =IF((E92-D92*E43/((1+E24/100)*(1+E42/100)))>0,1,0) -> 1 | F87: =IF((F92-E92*F43/((1+F24/100)*(1+F42/100)))>0,1,0) -> 1 | G87: =IF((G92-F92*G43/((1+G24/100)*(1+G42/100)))>0,1,0) -> 1 | H87: =IF((H92-G92*H43/((1+H24/100)*(1+H42/100)))>0,1,0) -> 1 | I87: =IF((I92-H92*I43/((1+I24/100)*(1+I42/100)))>0,1,0) -> 1 | J87: =IF((J92-I92*J43/((1+J24/100)*(1+J42/100)))>0,1,0) -> 1 | K87: =IF((K92-J92*K43/((1+K24/100)*(1+K42/100)))>0,1,0) -> 1 | ... U87: =IF((U92-T92*U43/((1+U24/100)*(1+U42/100)))>0,1,0) -> 1
B88: Auxiliary variable identifying whether some debt is rolled over even though debt is decreasing | D88: =IF(AND(D87=0,ABS(D92-C92*D43/((1+D24/100)*(1+D42/100)))<((C98*C92*D43/((1+D24/100)*(1+D42/100))+(D39*C92*C99*D43/((1+D24/100)*(1+D42/100)))))),1,0) -> 0 | E88: =IF(AND(E87=0,ABS(E92-D92*E43/((1+E24/100)*(1+E42/100)))<((D98*D92*E43/((1+E24/100)*(1+E42/100))+(E39*D92*D99*E43/((1+E24/100)*(1+E42/100)))))),1,0) -> 0 | F88: =IF(AND(F87=0,ABS(F92-E92*F43/((1+F24/100)*(1+F42/100)))<((E98*E92*F43/((1+F24/100)*(1+F42/100))+(F39*E92*E99*F43/((1+F24/100)*(1+F42/100)))))),1,0) -> 0 | G88: =IF(AND(G87=0,ABS(G92-F92*G43/((1+G24/100)*(1+G42/100)))<((F98*F92*G43/((1+G24/100)*(1+G42/100))+(G39*F92*F99*G43/((1+G24/100)*(1+G42/100)))))),1,0) -> 0 | H88: =IF(AND(H87=0,ABS(H92-G92*H43/((1+H24/100)*(1+H42/100)))<((G98*G92*H43/((1+H24/100)*(1+H42/100))+(H39*G92*G99*H43/((1+H24/100)*(1+H42/100)))))),1,0) -> 0 | I88: =IF(AND(I87=0,ABS(I92-H92*I43/((1+I24/100)*(1+I42/100)))<((H98*H92*I43/((1+I24/100)*(1+I42/100))+(I39*H92*H99*I43/((1+I24/100)*(1+I42/100)))))),1,0) -> 0 | J88: =IF(AND(J87=0,ABS(J92-I92*J43/((1+J24/100)*(1+J42/100)))<((I98*I92*J43/((1+J24/100)*(1+J42/100))+(J39*I92*I99*J43/((1+J24/100)*(1+J42/100)))))),1,0) -> 0 | K88: =IF(AND(K87=0,ABS(K92-J92*K43/((1+K24/100)*(1+K42/100)))<((J98*J92*K43/((1+K24/100)*(1+K42/100))+(K39*J92*J99*K43/((1+K24/100)*(1+K42/100)))))),1,0) -> 0 | ... U88: =IF(AND(U87=0,ABS(U92-T92*U43/((1+U24/100)*(1+U42/100)))<((T98*T92*U43/((1+U24/100)*(1+U42/100))+(U39*T92*T99*U43/((1+U24/100)*(1+U42/100)))))),1,0) -> 0
C91: ='Input data'!$C$5-1 -> 2024 | D91: =C91+1 -> 2025 | E91: =D91+1 -> 2026 | F91: =E91+1 -> 2027 | G91: =F91+1 -> 2028 | H91: =G91+1 -> 2029 | I91: =H91+1 -> 2030 | J91: =I91+1 -> 2031 | K91: =J91+1 -> 2032 | ... U91: =T91+1 -> 2042
B92: Gross debt | C92: =C57 -> 43.74815 | D92: =D57 -> 45.15761 | E92: =D92*(1+E106/100)*E43-E60-E61+E62+E63+E64+E65+E66+E73 -> 47.855642 | F92: =E92*(1+F106/100)*F43-F60-F61+F62+F63+F64+F65+F66+F73 -> 48.033966 | G92: =F92*(1+G106/100)*G43-G60-G61+G62+G63+G64+G65+G66+G73 -> 48.125782 | H92: =G92*(1+H106/100)*H43-H60-H61+H62+H63+H64+H65+H66+H73 -> 48.154706 | I92: =H92*(1+I106/100)*I43-I60-I61+I62+I63+I64+I65+I66+I73 -> 48.186222 | J92: =I92*(1+J106/100)*J43-J60-J61+J62+J63+J64+J65+J66+J73 -> 48.729285 | K92: =J92*(1+K106/100)*K43-K60-K61+K62+K63+K64+K65+K66+K73 -> 49.548166 | L92: =K92*(1+L106/100)*L43-L60-L61+L62+L63+L64+L65+L66+L73 -> 50.539003 | ... U92: =T92*(1+U106/100)*U43-U60-U61+U62+U63+U64+U65+U66+U73 -> 65.925993
B93: Of which Outstanding debt | D93: ='Input data'!$C$66*D$92 -> 37.015024 | E93: =IF(E92=0,0,IF(E87=1,D92*E43/((1+E24/100)*(1+E42/100))-E94-E95,IF(AND(E87=0,E88=1),(1-D98-E39*D99)*D92*E43/((1+E24/100)*(1+E42/100)),E92))) -> 37.303082 | F93: =IF(F92=0,0,IF(F87=1,E92*F43/((1+F24/100)*(1+F42/100))-F94-F95,IF(AND(F87=0,F88=1),(1-E98-F39*E99)*E92*F43/((1+F24/100)*(1+F42/100)),F92))) -> 39.670909 | G93: =IF(G92=0,0,IF(G87=1,F92*G43/((1+G24/100)*(1+G42/100))-G94-G95,IF(AND(G87=0,G88=1),(1-F98-G39*F99)*F92*G43/((1+G24/100)*(1+G42/100)),G92))) -> 39.674453 | H93: =IF(H92=0,0,IF(H87=1,G92*H43/((1+H24/100)*(1+H42/100))-H94-H95,IF(AND(H87=0,H88=1),(1-G98-H39*G99)*G92*H43/((1+H24/100)*(1+H42/100)),H92))) -> 39.625747 | I93: =IF(I92=0,0,IF(I87=1,H92*I43/((1+I24/100)*(1+I42/100))-I94-I95,IF(AND(I87=0,I88=1),(1-H98-I39*H99)*H92*I43/((1+I24/100)*(1+I42/100)),I92))) -> 39.492008 | J93: =IF(J92=0,0,IF(J87=1,I92*J43/((1+J24/100)*(1+J42/100))-J94-J95,IF(AND(J87=0,J88=1),(1-I98-J39*I99)*I92*J43/((1+J24/100)*(1+J42/100)),J92))) -> 39.479498 | K93: =IF(K92=0,0,IF(K87=1,J92*K43/((1+K24/100)*(1+K42/100))-K94-K95,IF(AND(K87=0,K88=1),(1-J98-K39*J99)*J92*K43/((1+K24/100)*(1+K42/100)),K92))) -> 39.768904 | L93: =IF(L92=0,0,IF(L87=1,K92*L43/((1+L24/100)*(1+L42/100))-L94-L95,IF(AND(L87=0,L88=1),(1-K98-L39*K99)*K92*L43/((1+L24/100)*(1+L42/100)),L92))) -> 40.272792 | ... U93: =IF(U92=0,0,IF(U87=1,T92*U43/((1+U24/100)*(1+U42/100))-U94-U95,IF(AND(U87=0,U88=1),(1-T98-U39*T99)*T92*U43/((1+U24/100)*(1+U42/100)),U92))) -> 50.985994
B94: Rolled over long-term debt | D94: ='Input data'!$C$67*D$92 -> 3.5884993 | E94: =IF(E92=0,0,IF(E87=1,E39*D92*D99*E43/((1+E24/100)*(1+E42/100)),IF(AND(E87=0,E88=1),(E39*D92*D99*E43/((1+E24/100)*(1+E42/100)))*(1-ABS(E92-D92*E43/((1+E24/100)*(1+E42/100)))/((E39*D92*D99*E43/((1+E24/100)*(1+E42/100)))+(D98*D92*E43/((1+E24/100)*(1+E42/100))))),0))) -> 2.2949335 | F94: =IF(F92=0,0,IF(F87=1,F39*E92*E99*F43/((1+F24/100)*(1+F42/100)),IF(AND(F87=0,F88=1),(F39*E92*E99*F43/((1+F24/100)*(1+F42/100)))*(1-ABS(F92-E92*F43/((1+F24/100)*(1+F42/100)))/((F39*E92*E99*F43/((1+F24/100)*(1+F42/100)))+(E98*E92*F43/((1+F24/100)*(1+F42/100))))),0))) -> 2.5911314 | G94: =IF(G92=0,0,IF(G87=1,G39*F92*F99*G43/((1+G24/100)*(1+G42/100)),IF(AND(G87=0,G88=1),(G39*F92*F99*G43/((1+G24/100)*(1+G42/100)))*(1-ABS(G92-F92*G43/((1+G24/100)*(1+G42/100)))/((G39*F92*F99*G43/((1+G24/100)*(1+G42/100)))+(F98*F92*G43/((1+G24/100)*(1+G42/100))))),0))) -> 2.7429825 | H94: =IF(H92=0,0,IF(H87=1,H39*G92*G99*H43/((1+H24/100)*(1+H42/100)),IF(AND(H87=0,H88=1),(H39*G92*G99*H43/((1+H24/100)*(1+H42/100)))*(1-ABS(H92-G92*H43/((1+H24/100)*(1+H42/100)))/((H39*G92*G99*H43/((1+H24/100)*(1+H42/100)))+(G98*G92*H43/((1+H24/100)*(1+H42/100))))),0))) -> 2.892139 | I94: =IF(I92=0,0,IF(I87=1,I39*H92*H99*I43/((1+I24/100)*(1+I42/100)),IF(AND(I87=0,I88=1),(I39*H92*H99*I43/((1+I24/100)*(1+I42/100)))*(1-ABS(I92-H92*I43/((1+I24/100)*(1+I42/100)))/((I39*H92*H99*I43/((1+I24/100)*(1+I42/100)))+(H98*H92*I43/((1+I24/100)*(1+I42/100))))),0))) -> 3.0354855 | J94: =IF(J92=0,0,IF(J87=1,J39*I92*I99*J43/((1+J24/100)*(1+J42/100)),IF(AND(J87=0,J88=1),(J39*I92*I99*J43/((1+J24/100)*(1+J42/100)))*(1-ABS(J92-I92*J43/((1+J24/100)*(1+J42/100)))/((J39*I92*I99*J43/((1+J24/100)*(1+J42/100)))+(I98*I92*J43/((1+J24/100)*(1+J42/100))))),0))) -> 3.1886932 | K94: =IF(K92=0,0,IF(K87=1,K39*J92*J99*K43/((1+K24/100)*(1+K42/100)),IF(AND(K87=0,K88=1),(K39*J92*J99*K43/((1+K24/100)*(1+K42/100)))*(1-ABS(K92-J92*K43/((1+K24/100)*(1+K42/100)))/((K39*J92*J99*K43/((1+K24/100)*(1+K42/100)))+(J98*J92*K43/((1+K24/100)*(1+K42/100))))),0))) -> 3.3684977 | L94: =IF(L92=0,0,IF(L87=1,L39*K92*K99*L43/((1+L24/100)*(1+L42/100)),IF(AND(L87=0,L88=1),(L39*K92*K99*L43/((1+L24/100)*(1+L42/100)))*(1-ABS(L92-K92*L43/((1+L24/100)*(1+L42/100)))/((L39*K92*K99*L43/((1+L24/100)*(1+L42/100)))+(K98*K92*L43/((1+L24/100)*(1+L42/100))))),0))) -> 3.5707471 | ... U94: =IF(U92=0,0,IF(U87=1,U39*T92*T99*U43/((1+U24/100)*(1+U42/100)),IF(AND(U87=0,U88=1),(U39*T92*T99*U43/((1+U24/100)*(1+U42/100)))*(1-ABS(U92-T92*U43/((1+U24/100)*(1+U42/100)))/((U39*T92*T99*U43/((1+U24/100)*(1+U42/100)))+(T98*T92*U43/((1+U24/100)*(1+U42/100))))),0))) -> 4.9291166
B95: Rolled over short-term debt | D95: ='Input data'!$C$68*D$92 -> 3.6736521 | E95: =IF(E92=0,0,IF(E87=1,(1-D99)*D92*E43/((1+E24/100)*(1+E42/100)),IF(AND(E87=0,E88=1),(D98*D92*E43/((1+E24/100)*(1+E42/100)))*(1-ABS(E92-D92*E43/((1+E24/100)*(1+E42/100)))/((E39*D92*D99*E43/((1+E24/100)*(1+E42/100)))+(D98*D92*E43/((1+E24/100)*(1+E42/100))))),0))) -> 3.5826776 | F95: =IF(F92=0,0,IF(F87=1,(1-E99)*E92*F43/((1+F24/100)*(1+F42/100)),IF(AND(F87=0,F88=1),(E98*E92*F43/((1+F24/100)*(1+F42/100)))*(1-ABS(F92-E92*F43/((1+F24/100)*(1+F42/100)))/((F39*E92*E99*F43/((1+F24/100)*(1+F42/100)))+(E98*E92*F43/((1+F24/100)*(1+F42/100))))),0))) -> 3.8779057 | G95: =IF(G92=0,0,IF(G87=1,(1-F99)*F92*G43/((1+G24/100)*(1+G42/100)),IF(AND(G87=0,G88=1),(F98*F92*G43/((1+G24/100)*(1+G42/100)))*(1-ABS(G92-F92*G43/((1+G24/100)*(1+G42/100)))/((G39*F92*F99*G43/((1+G24/100)*(1+G42/100)))+(F98*F92*G43/((1+G24/100)*(1+G42/100))))),0))) -> 3.9120079 | H95: =IF(H92=0,0,IF(H87=1,(1-G99)*G92*H43/((1+H24/100)*(1+H42/100)),IF(AND(H87=0,H88=1),(G98*G92*H43/((1+H24/100)*(1+H42/100)))*(1-ABS(H92-G92*H43/((1+H24/100)*(1+H42/100)))/((H39*G92*G99*H43/((1+H24/100)*(1+H42/100)))+(G98*G92*H43/((1+H24/100)*(1+H42/100))))),0))) -> 3.9393731 | I95: =IF(I92=0,0,IF(I87=1,(1-H99)*H92*I43/((1+I24/100)*(1+I42/100)),IF(AND(I87=0,I88=1),(H98*H92*I43/((1+I24/100)*(1+I42/100)))*(1-ABS(I92-H92*I43/((1+I24/100)*(1+I42/100)))/((I39*H92*H99*I43/((1+I24/100)*(1+I42/100)))+(H98*H92*I43/((1+I24/100)*(1+I42/100))))),0))) -> 3.9567354 | J95: =IF(J92=0,0,IF(J87=1,(1-I99)*I92*J43/((1+J24/100)*(1+J42/100)),IF(AND(J87=0,J88=1),(I98*I92*J43/((1+J24/100)*(1+J42/100)))*(1-ABS(J92-I92*J43/((1+J24/100)*(1+J42/100)))/((J39*I92*I99*J43/((1+J24/100)*(1+J42/100)))+(I98*I92*J43/((1+J24/100)*(1+J42/100))))),0))) -> 3.9858133 | K95: =IF(K92=0,0,IF(K87=1,(1-J99)*J92*K43/((1+K24/100)*(1+K42/100)),IF(AND(K87=0,K88=1),(J98*J92*K43/((1+K24/100)*(1+K42/100)))*(1-ABS(K92-J92*K43/((1+K24/100)*(1+K42/100)))/((K39*J92*J99*K43/((1+K24/100)*(1+K42/100)))+(J98*J92*K43/((1+K24/100)*(1+K42/100))))),0))) -> 4.0484584 | L95: =IF(L92=0,0,IF(L87=1,(1-K99)*K92*L43/((1+L24/100)*(1+L42/100)),IF(AND(L87=0,L88=1),(K98*K92*L43/((1+L24/100)*(1+L42/100)))*(1-ABS(L92-K92*L43/((1+L24/100)*(1+L42/100)))/((L39*K92*K99*L43/((1+L24/100)*(1+L42/100)))+(K98*K92*L43/((1+L24/100)*(1+L42/100))))),0))) -> 4.135242 | ... U95: =IF(U92=0,0,IF(U87=1,(1-T99)*T92*U43/((1+U24/100)*(1+U42/100)),IF(AND(U87=0,U88=1),(T98*T92*U43/((1+U24/100)*(1+U42/100)))*(1-ABS(U92-T92*U43/((1+U24/100)*(1+U42/100)))/((U39*T92*T99*U43/((1+U24/100)*(1+U42/100)))+(T98*T92*U43/((1+U24/100)*(1+U42/100))))),0))) -> 5.5007021
B96: New long-term debt | D96: ='Input data'!$C$69*D$92 -> 0.80738171 | E96: =IF(E92=0,0,IF(E87=1,'Input data'!$C$58*(E92-D92*E43/((1+E24/100)*(1+E42/100))),0)) -> 4.2355222 | F96: =IF(F92=0,0,IF(F87=1,'Input data'!$C$58*(F92-E92*F43/((1+F24/100)*(1+F42/100))),0)) -> 1.7159888 | G96: =IF(G92=0,0,IF(G87=1,'Input data'!$C$58*(G92-F92*G43/((1+G24/100)*(1+G42/100))),0)) -> 1.6274901 | H96: =IF(H92=0,0,IF(H87=1,'Input data'!$C$58*(H92-G92*H43/((1+H24/100)*(1+H42/100))),0)) -> 1.5378934 | I96: =IF(I92=0,0,IF(I87=1,'Input data'!$C$58*(I92-H92*I43/((1+I24/100)*(1+I42/100))),0)) -> 1.5420129 | J96: =IF(J92=0,0,IF(J87=1,'Input data'!$C$58*(J92-I92*J43/((1+J24/100)*(1+J42/100))),0)) -> 1.8802123 | K96: =IF(K92=0,0,IF(K87=1,'Input data'!$C$58*(K92-J92*K43/((1+K24/100)*(1+K42/100))),0)) -> 2.1402591 | L96: =IF(L92=0,0,IF(L87=1,'Input data'!$C$58*(L92-K92*L43/((1+L24/100)*(1+L42/100))),0)) -> 2.3195709 | ... U96: =IF(U92=0,0,IF(U87=1,'Input data'!$C$58*(U92-T92*U43/((1+U24/100)*(1+U42/100))),0)) -> 4.0862411
B97: New short-term debt | D97: ='Input data'!$C$70*D$92 -> 0.073048801 | E97: =IF(E92=0,0,IF(E87=1,'Input data'!$C$57*(E92-D92*E43/((1+E24/100)*(1+E42/100))),0)) -> 0.43942648 | F97: =IF(F92=0,0,IF(F87=1,'Input data'!$C$57*(F92-E92*F43/((1+F24/100)*(1+F42/100))),0)) -> 0.17803021 | G97: =IF(G92=0,0,IF(G87=1,'Input data'!$C$57*(G92-F92*G43/((1+G24/100)*(1+G42/100))),0)) -> 0.16884866 | H97: =IF(H92=0,0,IF(H87=1,'Input data'!$C$57*(H92-G92*H43/((1+H24/100)*(1+H42/100))),0)) -> 0.15955319 | I97: =IF(I92=0,0,IF(I87=1,'Input data'!$C$57*(I92-H92*I43/((1+I24/100)*(1+I42/100))),0)) -> 0.15998058 | J97: =IF(J92=0,0,IF(J87=1,'Input data'!$C$57*(J92-I92*J43/((1+J24/100)*(1+J42/100))),0)) -> 0.19506805 | K97: =IF(K92=0,0,IF(K87=1,'Input data'!$C$57*(K92-J92*K43/((1+K24/100)*(1+K42/100))),0)) -> 0.22204736 | L97: =IF(L92=0,0,IF(L87=1,'Input data'!$C$57*(L92-K92*L43/((1+L24/100)*(1+L42/100))),0)) -> 0.24065058 | ... U97: =IF(U92=0,0,IF(U87=1,'Input data'!$C$57*(U92-T92*U43/((1+U24/100)*(1+U42/100))),0)) -> 0.42393888
B98: Share of short-term debt in total government debt | D98: =IF(D92<>0,(D95+D97)/(D93+D94+D95+D96+D97),0) -> 0.082969432 | E98: =IF(E92<>0,(E95+E97)/(E93+E94+E95+E96+E97),0) -> 0.084046602 | F98: =IF(F92<>0,(F95+F97)/(F93+F94+F95+F96+F97),0) -> 0.084438915 | G98: =IF(G92<>0,(G95+G97)/(G93+G94+G95+G96+G97),0) -> 0.084795642 | H98: =IF(H92<>0,(H95+H97)/(H93+H94+H95+H96+H97),0) -> 0.085119953 | I98: =IF(I92<>0,(I95+I97)/(I93+I94+I95+I96+I97),0) -> 0.085433465 | J98: =IF(J92<>0,(J95+J97)/(J93+J94+J95+J96+J97),0) -> 0.085798126 | K98: =IF(K92<>0,(K95+K97)/(K93+K94+K95+K96+K97),0) -> 0.086188976 | ... U98: =IF(U92<>0,(U95+U97)/(U93+U94+U95+U96+U97),0) -> 0.089868058
B99: Share of long-term debt in total government debt | D99: =IF(D92<>0,(D93+D94+D96)/(D93+D94+D95+D96+D97),1) -> 0.91703057 | E99: =IF(E92<>0,(E93+E94+E96)/(E93+E94+E95+E96+E97),1) -> 0.9159534 | F99: =IF(F92<>0,(F93+F94+F96)/(F93+F94+F95+F96+F97),1) -> 0.91556109 | G99: =IF(G92<>0,(G93+G94+G96)/(G93+G94+G95+G96+G97),1) -> 0.91520436 | H99: =IF(H92<>0,(H93+H94+H96)/(H93+H94+H95+H96+H97),1) -> 0.91488005 | I99: =IF(I92<>0,(I93+I94+I96)/(I93+I94+I95+I96+I97),1) -> 0.91456653 | J99: =IF(J92<>0,(J93+J94+J96)/(J93+J94+J95+J96+J97),1) -> 0.91420187 | K99: =IF(K92<>0,(K93+K94+K96)/(K93+K94+K95+K96+K97),1) -> 0.91381102 | ... U99: =IF(U92<>0,(U93+U94+U96)/(U93+U94+U95+U96+U97),1) -> 0.91013194
B101: IIR | C101: ='Baseline NFPC'!C96 -> 1.646586 | D101: ='Baseline NFPC'!D96 -> 1.72 | E101: ='Baseline NFPC'!E96 -> 1.732298 | F101: =F103+F104 -> 1.8261287 | G101: =G103+G104 -> 1.9630297 | H101: =H103+H104 -> 2.0990021 | I101: =I103+I104 -> 2.234119 | J101: =J103+J104 -> 2.3707683 | K101: =K103+K104 -> 2.5163135 | L101: =L103+L104 -> 2.6668445 | M101: =M103+M104 -> 2.8190428 | ... U101: =U103+U104 -> 3.5460259
B102: Long-term implicit interest rate | E102: =((E36*D92)-(E38*(D95+D97)))/(D93+D94+D96) -> 1.7160168 | F102: =IF(E92>0,(E102*E93+ ('Baseline NFPC'!F97*('Baseline NFPC'!E88+'Baseline NFPC'!E89+'Baseline NFPC'!E91)-'Baseline NFPC'!E97*'Baseline NFPC'!E88)/('Baseline NFPC'!E89+'Baseline NFPC'!E91) *(E96+E94))/(E93+E94+E96),F37) -> 1.8079379 | G102: =IF(F92>0,(F102*F93+G37*(F96+F94))/(F93+F94+F96),G37) -> 1.9431639 | H102: =IF(G92>0,(G102*G93+H37*(G96+G94))/(G93+G94+G96),H37) -> 2.0773691 | I102: =IF(H92>0,(H102*H93+I37*(H96+H94))/(H93+H94+H96),I37) -> 2.2106333 | J102: =IF(I92>0,(I102*I93+J37*(I96+I94))/(I93+I94+I96),J37) -> 2.3455619 | K102: =IF(J92>0,(J102*J93+K37*(J96+J94))/(J93+J94+J96),K37) -> 2.4901907 | L102: =IF(K92>0,(K102*K93+L37*(K96+K94))/(K93+K94+K96),L37) -> 2.6402589 | M102: =IF(L92>0,(L102*L93+M37*(L96+L94))/(L93+L94+L96),M37) -> 2.7921474 | N102: =IF(M92>0,(M102*M93+N37*(M96+M94))/(M93+M94+M96),N37) -> 2.9449432 | ... U102: =IF(T92>0,(T102*T93+U37*(T96+T94))/(T93+T94+T96),U37) -> 3.6177504
B103: Nominal implicit interest rate on debt (Excel approximation) | E103: =(E102*(D93+D94+D96)+E38*(D95+D97))/D92 -> 1.732298 | F103: =(F102*(E93+E94+E96)+F38*(E95+E97))/E92 -> 1.8261287 | G103: =(G102*(F93+F94+F96)+G38*(F95+F97))/F92 -> 1.9630297 | H103: =(H102*(G93+G94+G96)+H38*(G95+G97))/G92 -> 2.0990021 | I103: =(I102*(H93+H94+H96)+I38*(H95+H97))/H92 -> 2.234119 | J103: =(J102*(I93+I94+I96)+J38*(I95+I97))/I92 -> 2.3707683 | K103: =(K102*(J93+J94+J96)+K38*(J95+J97))/J92 -> 2.5163135 | L103: =(L102*(K93+K94+K96)+L38*(K95+K97))/K92 -> 2.6668445 | ... U103: =(U102*(T93+T94+T96)+U38*(T95+T97))/T92 -> 3.5460259
B104: Diff. STATA | D104: =IF('Criteria results'!$F$5=4,D115,D120) -> 0 | E104: =IF('Criteria results'!$F$5=4,E115,E120) -> 0 | F104: =IF('Criteria results'!$F$5=4,F115,F120) -> 0 | G104: =IF('Criteria results'!$F$5=4,G115,G120) -> 0 | H104: =IF('Criteria results'!$F$5=4,H115,H120) -> 0 | I104: =IF('Criteria results'!$F$5=4,I115,I120) -> 0 | J104: =IF('Criteria results'!$F$5=4,J115,J120) -> 0 | K104: =IF('Criteria results'!$F$5=4,K115,K120) -> 0 | ... U104: =IF('Criteria results'!$F$5=4,U115,U120) -> 0
B106: (i - g) | C106: =((1+C101/100)/((1+C24/100)*(1+C42/100))-1)*100 -> -4.9030404 | D106: =((1+D101/100)/((1+D24/100)*(1+D42/100))-1)*100 -> -3.0356889 | E106: =((1+E101/100)/((1+E24/100)*(1+E42/100))-1)*100 -> -2.7213543 | F106: =((1+F101/100)/((1+F24/100)*(1+F42/100))-1)*100 -> -1.8244786 | G106: =((1+G101/100)/((1+G24/100)*(1+G42/100))-1)*100 -> -1.6552067 | H106: =((1+H101/100)/((1+H24/100)*(1+H42/100))-1)*100 -> -1.4407754 | I106: =((1+I101/100)/((1+I24/100)*(1+I42/100))-1)*100 -> -1.3123613 | J106: =((1+J101/100)/((1+J24/100)*(1+J42/100))-1)*100 -> -0.88440021 | ... U106: =((1+U101/100)/((1+U24/100)*(1+U42/100))-1)*100 -> -0.36879912
B110: Per memo - STATA results
B112: No extension (annual adjustment of 0.16)
B113: Debt | C113: 43.74815 | D113: 45.1576 | E113: 47.79403 | F113: 47.77689 | G113: 47.52948 | H113: 47.16806 | I113: 46.83461 | J113: 46.76366 | K113: 46.84879 | L113: 47.19448 | M113: 47.69369 | N113: 48.34108 | O113: 49.21658 | P113: 50.3143 | Q113: 51.42855 | R113: 52.61197 | S113: 53.85753 | T113: 55.31623 | U113: 56.78359
B114: IIR | C114: 1.646586 | D114: 1.72 | E114: 1.732298 | F114: 1.82506 | G114: 1.956788 | H114: 2.085044 | I114: 2.211248 | J114: 2.341118 | K114: 2.478733 | L114: 2.620689 | M114: 2.76649 | N114: 2.915191 | O114: 3.034691 | P114: 3.142016 | Q114: 3.23752 | R114: 3.319656 | S114: 3.391042 | T114: 3.452789 | U114: 3.506567
B115: IIR difference STATA - Excel | C115: 0 | D115: 0 | E115: 0 | F115: 0 | G115: 0 | H115: 0 | I115: 0 | J115: 0 | K115: 0 | L115: 0 | M115: 0 | N115: 0 | O115: 0 | P115: 0 | Q115: 0 | R115: 0 | S115: 0 | T115: 0 | U115: 0
B117: Extension (annual adjustment of 0.08)
B118: Debt | C118: 43.74815 | D118: 45.1576 | E118: 47.82483 | F118: 47.90544 | G118: 47.82772 | H118: 47.71061 | I118: 47.53349 | J118: 47.32415 | K118: 47.08503 | L118: 46.95089 | M118: 46.92034 | N118: 46.9875 | O118: 47.31881 | P118: 47.87145 | Q118: 48.44042 | R118: 49.08151 | S118: 49.78926 | T118: 50.71185 | U118: 51.6452
B119: IIR | C119: 1.646586 | D119: 1.72 | E119: 1.732298 | F119: 1.825595 | G119: 1.959948 | H119: 2.092126 | I119: 2.223512 | J119: 2.354915 | K119: 2.486767 | L119: 2.619259 | M119: 2.755813 | N119: 2.89574 | O119: 3.008128 | P119: 3.110818 | Q119: 3.203799 | R119: 3.284861 | S119: 3.356389 | T119: 3.419181 | U119: 3.474766
B120: IIR difference STATA - Excel | D120: 0 | E120: 0 | F120: 0 | G120: 0 | H120: 0 | I120: 0 | J120: 0 | K120: 0 | L120: 0 | M120: 0 | N120: 0 | O120: 0 | P120: 0 | Q120: 0 | R120: 0 | S120: 0 | T120: 0 | U120: 0

Sheet FASTOP reporting
C2: Table 7a: Debt and headline balance projections and key underlying assumptions (under the planned fiscal path)
D4: line | E4: =F4-1 -> 2023 | F4: ='Input data'!$C$5-1 -> 2024 | G4: =F4+1 -> 2025 | H4: =G4+1 -> 2026 | I4: =H4+1 -> 2027 | J4: =I4+1 -> 2028 | K4: =J4+1 -> 2029 | L4: =K4+1 -> 2030 | M4: =L4+1 -> 2031 | N4: =M4+1 -> 2032 | ... X4: =W4+1 -> 2042
B5: 1 | C5: Gross debt | D5: 57 | E5: (% GDP) | F5: =INDEX(OFFSET('Adjustment scenario'!$C$1:$U$1,$D5-1,0),MATCH(F$4,'Adjustment scenario'!$C$10:$U$10,0)) -> 43.74815 | G5: =INDEX(OFFSET('Adjustment scenario'!$C$1:$U$1,$D5-1,0),MATCH(G$4,'Adjustment scenario'!$C$10:$U$10,0)) -> 45.15761 | H5: =INDEX(OFFSET('Adjustment scenario'!$C$1:$U$1,$D5-1,0),MATCH(H$4,'Adjustment scenario'!$C$10:$U$10,0)) -> 47.855645 | I5: =INDEX(OFFSET('Adjustment scenario'!$C$1:$U$1,$D5-1,0),MATCH(I$4,'Adjustment scenario'!$C$10:$U$10,0)) -> 48.033971 | J5: =INDEX(OFFSET('Adjustment scenario'!$C$1:$U$1,$D5-1,0),MATCH(J$4,'Adjustment scenario'!$C$10:$U$10,0)) -> 48.125788 | K5: =INDEX(OFFSET('Adjustment scenario'!$C$1:$U$1,$D5-1,0),MATCH(K$4,'Adjustment scenario'!$C$10:$U$10,0)) -> 48.154711 | L5: =INDEX(OFFSET('Adjustment scenario'!$C$1:$U$1,$D5-1,0),MATCH(L$4,'Adjustment scenario'!$C$10:$U$10,0)) -> 48.186228 | M5: =INDEX(OFFSET('Adjustment scenario'!$C$1:$U$1,$D5-1,0),MATCH(M$4,'Adjustment scenario'!$C$10:$U$10,0)) -> 48.72929 | ... X5: =INDEX(OFFSET('Adjustment scenario'!$C$1:$U$1,$D5-1,0),MATCH(X$4,'Adjustment scenario'!$C$10:$U$10,0)) -> 65.925998
B6: 2 | C6: General government balance | D6: 77 | E6: (% GDP) | F6: =INDEX(OFFSET('Adjustment scenario'!$C$1:$U$1,$D6-1,0),MATCH(F$4,'Adjustment scenario'!$C$10:$U$10,0)) -> -0.9448897 | G6: =INDEX(OFFSET('Adjustment scenario'!$C$1:$U$1,$D6-1,0),MATCH(G$4,'Adjustment scenario'!$C$10:$U$10,0)) -> -1.8748092 | H6: =INDEX(OFFSET('Adjustment scenario'!$C$1:$U$1,$D6-1,0),MATCH(H$4,'Adjustment scenario'!$C$10:$U$10,0)) -> -2.6602743 | I6: =INDEX(OFFSET('Adjustment scenario'!$C$1:$U$1,$D6-1,0),MATCH(I$4,'Adjustment scenario'!$C$10:$U$10,0)) -> -1.8940194 | J6: =INDEX(OFFSET('Adjustment scenario'!$C$1:$U$1,$D6-1,0),MATCH(J$4,'Adjustment scenario'!$C$10:$U$10,0)) -> -1.7963389 | K6: =INDEX(OFFSET('Adjustment scenario'!$C$1:$U$1,$D6-1,0),MATCH(K$4,'Adjustment scenario'!$C$10:$U$10,0)) -> -1.6974467 | L6: =INDEX(OFFSET('Adjustment scenario'!$C$1:$U$1,$D6-1,0),MATCH(L$4,'Adjustment scenario'!$C$10:$U$10,0)) -> -1.7019936 | M6: =INDEX(OFFSET('Adjustment scenario'!$C$1:$U$1,$D6-1,0),MATCH(M$4,'Adjustment scenario'!$C$10:$U$10,0)) -> -2.0752805 | ... X6: =INDEX(OFFSET('Adjustment scenario'!$C$1:$U$1,$D6-1,0),MATCH(X$4,'Adjustment scenario'!$C$10:$U$10,0)) -> -4.5101802
B7: 3 | C7: Structural primary balance | D7: 12 | E7: (% pot. GDP) | F7: =INDEX(OFFSET('Adjustment scenario'!$C$1:$U$1,$D7-1,0),MATCH(F$4,'Adjustment scenario'!$C$10:$U$10,0)) -> 0.386237 | G7: =INDEX(OFFSET('Adjustment scenario'!$C$1:$U$1,$D7-1,0),MATCH(G$4,'Adjustment scenario'!$C$10:$U$10,0)) -> -0.5577395 | H7: =INDEX(OFFSET('Adjustment scenario'!$C$1:$U$1,$D7-1,0),MATCH(H$4,'Adjustment scenario'!$C$10:$U$10,0)) -> -0.5577395 | I7: =INDEX(OFFSET('Adjustment scenario'!$C$1:$U$1,$D7-1,0),MATCH(I$4,'Adjustment scenario'!$C$10:$U$10,0)) -> -0.5577395 | J7: =INDEX(OFFSET('Adjustment scenario'!$C$1:$U$1,$D7-1,0),MATCH(J$4,'Adjustment scenario'!$C$10:$U$10,0)) -> -0.5577395 | K7: =INDEX(OFFSET('Adjustment scenario'!$C$1:$U$1,$D7-1,0),MATCH(K$4,'Adjustment scenario'!$C$10:$U$10,0)) -> -0.5577395 | L7: =INDEX(OFFSET('Adjustment scenario'!$C$1:$U$1,$D7-1,0),MATCH(L$4,'Adjustment scenario'!$C$10:$U$10,0)) -> -0.5577395 | M7: =INDEX(OFFSET('Adjustment scenario'!$C$1:$U$1,$D7-1,0),MATCH(M$4,'Adjustment scenario'!$C$10:$U$10,0)) -> -0.5577395 | ... X7: =INDEX(OFFSET('Adjustment scenario'!$C$1:$U$1,$D7-1,0),MATCH(X$4,'Adjustment scenario'!$C$10:$U$10,0)) -> -0.5577395
B8: 4 | C8: Cyclical component | D8: 62 | E8: (% pot. GDP) | F8: =INDEX(OFFSET('Adjustment scenario'!$C$1:$U$1,$D8-1,0),MATCH(F$4,'Adjustment scenario'!$C$10:$U$10,0)) -> 0 | G8: =INDEX(OFFSET('Adjustment scenario'!$C$1:$U$1,$D8-1,0),MATCH(G$4,'Adjustment scenario'!$C$10:$U$10,0)) -> 0.57430421 | H8: =INDEX(OFFSET('Adjustment scenario'!$C$1:$U$1,$D8-1,0),MATCH(H$4,'Adjustment scenario'!$C$10:$U$10,0)) -> 0.66441172 | I8: =INDEX(OFFSET('Adjustment scenario'!$C$1:$U$1,$D8-1,0),MATCH(I$4,'Adjustment scenario'!$C$10:$U$10,0)) -> 0.49370469 | J8: =INDEX(OFFSET('Adjustment scenario'!$C$1:$U$1,$D8-1,0),MATCH(J$4,'Adjustment scenario'!$C$10:$U$10,0)) -> 0.32913858 | K8: =INDEX(OFFSET('Adjustment scenario'!$C$1:$U$1,$D8-1,0),MATCH(K$4,'Adjustment scenario'!$C$10:$U$10,0)) -> 0.16456822 | L8: =INDEX(OFFSET('Adjustment scenario'!$C$1:$U$1,$D8-1,0),MATCH(L$4,'Adjustment scenario'!$C$10:$U$10,0)) -> 6.004402e-07 | M8: =INDEX(OFFSET('Adjustment scenario'!$C$1:$U$1,$D8-1,0),MATCH(M$4,'Adjustment scenario'!$C$10:$U$10,0)) -> 1.7976406e-06 | ... X8: =INDEX(OFFSET('Adjustment scenario'!$C$1:$U$1,$D8-1,0),MATCH(X$4,'Adjustment scenario'!$C$10:$U$10,0)) -> -4.1943813e-06
B9: 5 | C9: One-off measures | D9: 14 | E9: (% GDP) | F9: =INDEX(OFFSET('Adjustment scenario'!$C$1:$U$1,$D9-1,0),MATCH(F$4,'Adjustment scenario'!$C$10:$U$10,0)) -> -0.026727 | G9: =INDEX(OFFSET('Adjustment scenario'!$C$1:$U$1,$D9-1,0),MATCH(G$4,'Adjustment scenario'!$C$10:$U$10,0)) -> -0.0254775 | H9: =INDEX(OFFSET('Adjustment scenario'!$C$1:$U$1,$D9-1,0),MATCH(H$4,'Adjustment scenario'!$C$10:$U$10,0)) -> -0.6901042 | I9: =INDEX(OFFSET('Adjustment scenario'!$C$1:$U$1,$D9-1,0),MATCH(I$4,'Adjustment scenario'!$C$10:$U$10,0)) -> 0 | J9: =INDEX(OFFSET('Adjustment scenario'!$C$1:$U$1,$D9-1,0),MATCH(J$4,'Adjustment scenario'!$C$10:$U$10,0)) -> 0 | K9: =INDEX(OFFSET('Adjustment scenario'!$C$1:$U$1,$D9-1,0),MATCH(K$4,'Adjustment scenario'!$C$10:$U$10,0)) -> 0 | L9: =INDEX(OFFSET('Adjustment scenario'!$C$1:$U$1,$D9-1,0),MATCH(L$4,'Adjustment scenario'!$C$10:$U$10,0)) -> 0 | M9: =INDEX(OFFSET('Adjustment scenario'!$C$1:$U$1,$D9-1,0),MATCH(M$4,'Adjustment scenario'!$C$10:$U$10,0)) -> 0 | ... X9: =INDEX(OFFSET('Adjustment scenario'!$C$1:$U$1,$D9-1,0),MATCH(X$4,'Adjustment scenario'!$C$10:$U$10,0)) -> 0
B10: 6 | C10: Interest expenditure | D10: 68 | E10: (% GDP) | F10: =INDEX(OFFSET('Adjustment scenario'!$C$1:$U$1,$D10-1,0),MATCH(F$4,'Adjustment scenario'!$C$10:$U$10,0)) -> 0 | G10: =INDEX(OFFSET('Adjustment scenario'!$C$1:$U$1,$D10-1,0),MATCH(G$4,'Adjustment scenario'!$C$10:$U$10,0)) -> 0.71728823 | H10: =INDEX(OFFSET('Adjustment scenario'!$C$1:$U$1,$D10-1,0),MATCH(H$4,'Adjustment scenario'!$C$10:$U$10,0)) -> 0.74801829 | I10: =INDEX(OFFSET('Adjustment scenario'!$C$1:$U$1,$D10-1,0),MATCH(I$4,'Adjustment scenario'!$C$10:$U$10,0)) -> 0.84257493 | J10: =INDEX(OFFSET('Adjustment scenario'!$C$1:$U$1,$D10-1,0),MATCH(J$4,'Adjustment scenario'!$C$10:$U$10,0)) -> 0.90946084 | K10: =INDEX(OFFSET('Adjustment scenario'!$C$1:$U$1,$D10-1,0),MATCH(K$4,'Adjustment scenario'!$C$10:$U$10,0)) -> 0.97513896 | L10: =INDEX(OFFSET('Adjustment scenario'!$C$1:$U$1,$D10-1,0),MATCH(L$4,'Adjustment scenario'!$C$10:$U$10,0)) -> 1.0385131 | M10: =INDEX(OFFSET('Adjustment scenario'!$C$1:$U$1,$D10-1,0),MATCH(M$4,'Adjustment scenario'!$C$10:$U$10,0)) -> 1.1060585 | ... X10: =INDEX(OFFSET('Adjustment scenario'!$C$1:$U$1,$D10-1,0),MATCH(X$4,'Adjustment scenario'!$C$10:$U$10,0)) -> 2.1778208
B11: 7 | C11: Long-term interest rate | D11: 37 | E11: (%) | F11: =INDEX(OFFSET('Adjustment scenario'!$C$1:$U$1,$D11-1,0),MATCH(F$4,'Adjustment scenario'!$C$10:$U$10,0)) -> 2.6205 | G11: =INDEX(OFFSET('Adjustment scenario'!$C$1:$U$1,$D11-1,0),MATCH(G$4,'Adjustment scenario'!$C$10:$U$10,0)) -> 2.78965 | H11: =INDEX(OFFSET('Adjustment scenario'!$C$1:$U$1,$D11-1,0),MATCH(H$4,'Adjustment scenario'!$C$10:$U$10,0)) -> 2.894953 | I11: =INDEX(OFFSET('Adjustment scenario'!$C$1:$U$1,$D11-1,0),MATCH(I$4,'Adjustment scenario'!$C$10:$U$10,0)) -> 3.081676 | J11: =INDEX(OFFSET('Adjustment scenario'!$C$1:$U$1,$D11-1,0),MATCH(J$4,'Adjustment scenario'!$C$10:$U$10,0)) -> 3.188669 | K11: =INDEX(OFFSET('Adjustment scenario'!$C$1:$U$1,$D11-1,0),MATCH(K$4,'Adjustment scenario'!$C$10:$U$10,0)) -> 3.295662 | L11: =INDEX(OFFSET('Adjustment scenario'!$C$1:$U$1,$D11-1,0),MATCH(L$4,'Adjustment scenario'!$C$10:$U$10,0)) -> 3.402655 | M11: =INDEX(OFFSET('Adjustment scenario'!$C$1:$U$1,$D11-1,0),MATCH(M$4,'Adjustment scenario'!$C$10:$U$10,0)) -> 3.509648 | ... X11: =INDEX(OFFSET('Adjustment scenario'!$C$1:$U$1,$D11-1,0),MATCH(X$4,'Adjustment scenario'!$C$10:$U$10,0)) -> 3.959453
B12: 8 | C12: Short-term interest rate | D12: 38 | E12: (%) | F12: =INDEX(OFFSET('Adjustment scenario'!$C$1:$U$1,$D12-1,0),MATCH(F$4,'Adjustment scenario'!$C$10:$U$10,0)) -> 3.570833 | G12: =INDEX(OFFSET('Adjustment scenario'!$C$1:$U$1,$D12-1,0),MATCH(G$4,'Adjustment scenario'!$C$10:$U$10,0)) -> 2.172583 | H12: =INDEX(OFFSET('Adjustment scenario'!$C$1:$U$1,$D12-1,0),MATCH(H$4,'Adjustment scenario'!$C$10:$U$10,0)) -> 1.91225 | I12: =INDEX(OFFSET('Adjustment scenario'!$C$1:$U$1,$D12-1,0),MATCH(I$4,'Adjustment scenario'!$C$10:$U$10,0)) -> 2.024375 | J12: =INDEX(OFFSET('Adjustment scenario'!$C$1:$U$1,$D12-1,0),MATCH(J$4,'Adjustment scenario'!$C$10:$U$10,0)) -> 2.1784319 | K12: =INDEX(OFFSET('Adjustment scenario'!$C$1:$U$1,$D12-1,0),MATCH(K$4,'Adjustment scenario'!$C$10:$U$10,0)) -> 2.3324888 | L12: =INDEX(OFFSET('Adjustment scenario'!$C$1:$U$1,$D12-1,0),MATCH(L$4,'Adjustment scenario'!$C$10:$U$10,0)) -> 2.4865456 | M12: =INDEX(OFFSET('Adjustment scenario'!$C$1:$U$1,$D12-1,0),MATCH(M$4,'Adjustment scenario'!$C$10:$U$10,0)) -> 2.6406025 | ... X12: =INDEX(OFFSET('Adjustment scenario'!$C$1:$U$1,$D12-1,0),MATCH(X$4,'Adjustment scenario'!$C$10:$U$10,0)) -> 2.8169395
B13: 9 | C13: Implicit average interest rate | D13: 36 | E13: (%) | F13: =INDEX(OFFSET('Adjustment scenario'!$C$1:$U$1,$D13-1,0),MATCH(F$4,'Adjustment scenario'!$C$10:$U$10,0)) -> 1.646586 | G13: =INDEX(OFFSET('Adjustment scenario'!$C$1:$U$1,$D13-1,0),MATCH(G$4,'Adjustment scenario'!$C$10:$U$10,0)) -> 1.72 | H13: =INDEX(OFFSET('Adjustment scenario'!$C$1:$U$1,$D13-1,0),MATCH(H$4,'Adjustment scenario'!$C$10:$U$10,0)) -> 1.732298 | I13: =INDEX(OFFSET('Adjustment scenario'!$C$1:$U$1,$D13-1,0),MATCH(I$4,'Adjustment scenario'!$C$10:$U$10,0)) -> 1.8261287 | J13: =INDEX(OFFSET('Adjustment scenario'!$C$1:$U$1,$D13-1,0),MATCH(J$4,'Adjustment scenario'!$C$10:$U$10,0)) -> 1.9630297 | K13: =INDEX(OFFSET('Adjustment scenario'!$C$1:$U$1,$D13-1,0),MATCH(K$4,'Adjustment scenario'!$C$10:$U$10,0)) -> 2.0990021 | L13: =INDEX(OFFSET('Adjustment scenario'!$C$1:$U$1,$D13-1,0),MATCH(L$4,'Adjustment scenario'!$C$10:$U$10,0)) -> 2.234119 | M13: =INDEX(OFFSET('Adjustment scenario'!$C$1:$U$1,$D13-1,0),MATCH(M$4,'Adjustment scenario'!$C$10:$U$10,0)) -> 2.3707683 | ... X13: =INDEX(OFFSET('Adjustment scenario'!$C$1:$U$1,$D13-1,0),MATCH(X$4,'Adjustment scenario'!$C$10:$U$10,0)) -> 3.5460259
B14: 10 | C14: Stock-flow adjustment | D14: 72 | E14: (% GDP) | F14: =INDEX(OFFSET('Adjustment scenario'!$C$1:$U$1,$D14-1,0),MATCH(F$4,'Adjustment scenario'!$C$10:$U$10,0)) -> 0 | G14: =INDEX(OFFSET('Adjustment scenario'!$C$1:$U$1,$D14-1,0),MATCH(G$4,'Adjustment scenario'!$C$10:$U$10,0)) -> 1.579997 | H14: =INDEX(OFFSET('Adjustment scenario'!$C$1:$U$1,$D14-1,0),MATCH(H$4,'Adjustment scenario'!$C$10:$U$10,0)) -> 2.014677 | I14: =INDEX(OFFSET('Adjustment scenario'!$C$1:$U$1,$D14-1,0),MATCH(I$4,'Adjustment scenario'!$C$10:$U$10,0)) -> -2.05e-06 | J14: =INDEX(OFFSET('Adjustment scenario'!$C$1:$U$1,$D14-1,0),MATCH(J$4,'Adjustment scenario'!$C$10:$U$10,0)) -> 0 | K14: =INDEX(OFFSET('Adjustment scenario'!$C$1:$U$1,$D14-1,0),MATCH(K$4,'Adjustment scenario'!$C$10:$U$10,0)) -> 0 | L14: =INDEX(OFFSET('Adjustment scenario'!$C$1:$U$1,$D14-1,0),MATCH(L$4,'Adjustment scenario'!$C$10:$U$10,0)) -> 0 | M14: =INDEX(OFFSET('Adjustment scenario'!$C$1:$U$1,$D14-1,0),MATCH(M$4,'Adjustment scenario'!$C$10:$U$10,0)) -> 0 | ... X14: =INDEX(OFFSET('Adjustment scenario'!$C$1:$U$1,$D14-1,0),MATCH(X$4,'Adjustment scenario'!$C$10:$U$10,0)) -> 0
B15: 11 | C15: Potential GDP | D15: 27 | E15: (growth rate) | F15: ='Input data'!C$33 -> 1.824226 | G15: =(INDEX(OFFSET('Adjustment scenario'!$C$1:$U$1,$D15-1,0),MATCH(G$4,'Adjustment scenario'!$C$10:$U$10,0))/INDEX(OFFSET('Adjustment scenario'!$C$1:$U$1,$D15-1,0),MATCH(F$4,'Adjustment scenario'!$C$10:$U$10,0))-1)*100 -> 1.656294 | H15: =(INDEX(OFFSET('Adjustment scenario'!$C$1:$U$1,$D15-1,0),MATCH(H$4,'Adjustment scenario'!$C$10:$U$10,0))/INDEX(OFFSET('Adjustment scenario'!$C$1:$U$1,$D15-1,0),MATCH(G$4,'Adjustment scenario'!$C$10:$U$10,0))-1)*100 -> 1.426257 | I15: =(INDEX(OFFSET('Adjustment scenario'!$C$1:$U$1,$D15-1,0),MATCH(I$4,'Adjustment scenario'!$C$10:$U$10,0))/INDEX(OFFSET('Adjustment scenario'!$C$1:$U$1,$D15-1,0),MATCH(H$4,'Adjustment scenario'!$C$10:$U$10,0))-1)*100 -> 1.292883 | J15: =(INDEX(OFFSET('Adjustment scenario'!$C$1:$U$1,$D15-1,0),MATCH(J$4,'Adjustment scenario'!$C$10:$U$10,0))/INDEX(OFFSET('Adjustment scenario'!$C$1:$U$1,$D15-1,0),MATCH(I$4,'Adjustment scenario'!$C$10:$U$10,0))-1)*100 -> 1.24374 | K15: =(INDEX(OFFSET('Adjustment scenario'!$C$1:$U$1,$D15-1,0),MATCH(K$4,'Adjustment scenario'!$C$10:$U$10,0))/INDEX(OFFSET('Adjustment scenario'!$C$1:$U$1,$D15-1,0),MATCH(J$4,'Adjustment scenario'!$C$10:$U$10,0))-1)*100 -> 1.137065 | L15: =(INDEX(OFFSET('Adjustment scenario'!$C$1:$U$1,$D15-1,0),MATCH(L$4,'Adjustment scenario'!$C$10:$U$10,0))/INDEX(OFFSET('Adjustment scenario'!$C$1:$U$1,$D15-1,0),MATCH(K$4,'Adjustment scenario'!$C$10:$U$10,0))-1)*100 -> 1.118027 | M15: =(INDEX(OFFSET('Adjustment scenario'!$C$1:$U$1,$D15-1,0),MATCH(M$4,'Adjustment scenario'!$C$10:$U$10,0))/INDEX(OFFSET('Adjustment scenario'!$C$1:$U$1,$D15-1,0),MATCH(L$4,'Adjustment scenario'!$C$10:$U$10,0))-1)*100 -> 1.069128 | N15: =(INDEX(OFFSET('Adjustment scenario'!$C$1:$U$1,$D15-1,0),MATCH(N$4,'Adjustment scenario'!$C$10:$U$10,0))/INDEX(OFFSET('Adjustment scenario'!$C$1:$U$1,$D15-1,0),MATCH(M$4,'Adjustment scenario'!$C$10:$U$10,0))-1)*100 -> 1.03431 | ... X15: =(INDEX(OFFSET('Adjustment scenario'!$C$1:$U$1,$D15-1,0),MATCH(X$4,'Adjustment scenario'!$C$10:$U$10,0))/INDEX(OFFSET('Adjustment scenario'!$C$1:$U$1,$D15-1,0),MATCH(W$4,'Adjustment scenario'!$C$10:$U$10,0))-1)*100 -> 1.71
B16: 12 | C16: Real GDP | D16: 24 | E16: (growth rate) | F16: =INDEX(OFFSET('Adjustment scenario'!$C$1:$U$1,$D16-1,0),MATCH(F$4,'Adjustment scenario'!$C$10:$U$10,0)) -> 1.081005 | G16: =INDEX(OFFSET('Adjustment scenario'!$C$1:$U$1,$D16-1,0),MATCH(G$4,'Adjustment scenario'!$C$10:$U$10,0)) -> 1.69667 | H16: =INDEX(OFFSET('Adjustment scenario'!$C$1:$U$1,$D16-1,0),MATCH(H$4,'Adjustment scenario'!$C$10:$U$10,0)) -> 1.273747 | I16: =INDEX(OFFSET('Adjustment scenario'!$C$1:$U$1,$D16-1,0),MATCH(I$4,'Adjustment scenario'!$C$10:$U$10,0)) -> 1.581865 | J16: =INDEX(OFFSET('Adjustment scenario'!$C$1:$U$1,$D16-1,0),MATCH(J$4,'Adjustment scenario'!$C$10:$U$10,0)) -> 1.521399 | K16: =INDEX(OFFSET('Adjustment scenario'!$C$1:$U$1,$D16-1,0),MATCH(K$4,'Adjustment scenario'!$C$10:$U$10,0)) -> 1.41368 | L16: =INDEX(OFFSET('Adjustment scenario'!$C$1:$U$1,$D16-1,0),MATCH(L$4,'Adjustment scenario'!$C$10:$U$10,0)) -> 1.393831 | M16: =INDEX(OFFSET('Adjustment scenario'!$C$1:$U$1,$D16-1,0),MATCH(M$4,'Adjustment scenario'!$C$10:$U$10,0)) -> 1.069126 | ... X16: =INDEX(OFFSET('Adjustment scenario'!$C$1:$U$1,$D16-1,0),MATCH(X$4,'Adjustment scenario'!$C$10:$U$10,0)) -> 1.710004
B17: 13 | C17: GDP deflator | D17: 42 | E17: (growth rate) | F17: =INDEX(OFFSET('Adjustment scenario'!$C$1:$U$1,$D17-1,0),MATCH(F$4,'Adjustment scenario'!$C$10:$U$10,0)) -> 5.744214 | G17: =INDEX(OFFSET('Adjustment scenario'!$C$1:$U$1,$D17-1,0),MATCH(G$4,'Adjustment scenario'!$C$10:$U$10,0)) -> 3.154387 | H17: =INDEX(OFFSET('Adjustment scenario'!$C$1:$U$1,$D17-1,0),MATCH(H$4,'Adjustment scenario'!$C$10:$U$10,0)) -> 3.262934 | I17: =INDEX(OFFSET('Adjustment scenario'!$C$1:$U$1,$D17-1,0),MATCH(I$4,'Adjustment scenario'!$C$10:$U$10,0)) -> 2.103313 | J17: =INDEX(OFFSET('Adjustment scenario'!$C$1:$U$1,$D17-1,0),MATCH(J$4,'Adjustment scenario'!$C$10:$U$10,0)) -> 2.1253989 | K17: =INDEX(OFFSET('Adjustment scenario'!$C$1:$U$1,$D17-1,0),MATCH(K$4,'Adjustment scenario'!$C$10:$U$10,0)) -> 2.1474847 | L17: =INDEX(OFFSET('Adjustment scenario'!$C$1:$U$1,$D17-1,0),MATCH(L$4,'Adjustment scenario'!$C$10:$U$10,0)) -> 2.1695706 | M17: =INDEX(OFFSET('Adjustment scenario'!$C$1:$U$1,$D17-1,0),MATCH(M$4,'Adjustment scenario'!$C$10:$U$10,0)) -> 2.1916565 | ... X17: =INDEX(OFFSET('Adjustment scenario'!$C$1:$U$1,$D17-1,0),MATCH(X$4,'Adjustment scenario'!$C$10:$U$10,0)) -> 2.182
B18: 14 | C18: Nominal GDP | D18: 33 | E18: (growth rate) | F18: =INDEX(OFFSET('Adjustment scenario'!$C$1:$U$1,$D18-1,0),MATCH(F$4,'Adjustment scenario'!$C$10:$U$10,0)) -> 6.8873142 | G18: =INDEX(OFFSET('Adjustment scenario'!$C$1:$U$1,$D18-1,0),MATCH(G$4,'Adjustment scenario'!$C$10:$U$10,0)) -> 4.9045765 | H18: =INDEX(OFFSET('Adjustment scenario'!$C$1:$U$1,$D18-1,0),MATCH(H$4,'Adjustment scenario'!$C$10:$U$10,0)) -> 4.5782425 | I18: =INDEX(OFFSET('Adjustment scenario'!$C$1:$U$1,$D18-1,0),MATCH(I$4,'Adjustment scenario'!$C$10:$U$10,0)) -> 3.7184496 | J18: =INDEX(OFFSET('Adjustment scenario'!$C$1:$U$1,$D18-1,0),MATCH(J$4,'Adjustment scenario'!$C$10:$U$10,0)) -> 3.6791337 | K18: =INDEX(OFFSET('Adjustment scenario'!$C$1:$U$1,$D18-1,0),MATCH(K$4,'Adjustment scenario'!$C$10:$U$10,0)) -> 3.5915233 | L18: =INDEX(OFFSET('Adjustment scenario'!$C$1:$U$1,$D18-1,0),MATCH(L$4,'Adjustment scenario'!$C$10:$U$10,0)) -> 3.5936418 | M18: =INDEX(OFFSET('Adjustment scenario'!$C$1:$U$1,$D18-1,0),MATCH(M$4,'Adjustment scenario'!$C$10:$U$10,0)) -> 3.2842141 | ... X18: =INDEX(OFFSET('Adjustment scenario'!$C$1:$U$1,$D18-1,0),MATCH(X$4,'Adjustment scenario'!$C$10:$U$10,0)) -> 3.9293163
C20: Table 7b: Debt projections and key stressed variables, deterministic scenarios and stochastic simulations
C22: Financial stress scenario | E22: =F22-1 -> -1
B23: 1 | C23: Gross debt | D23: 56 | E23: (% GDP)
B24: 2 | C24: Long-term interest rate | D24: 36 | E24: (%)
B25: 3 | C25: Short-term interest rate | D25: 37 | E25: (%)
C26: Lower SPB scenario | E26: =F26-1 -> -1
B27: 4 | C27: Gross debt | D27: 56 | E27: (% GDP)
B28: 5 | C28: Structural primary balance | D28: 12 | E28: (% pot. GDP)
C29: Adverse 'r-g' scenario | E29: =F29-1 -> -1
B30: 6 | C30: Gross debt | D30: 57 | E30: (% GDP)
B31: 7 | C31: Long-term interest rate | D31: 37 | E31: (%)
B32: 8 | C32: Short-term interest rate | D32: 38 | E32: (%)
B33: 9 | C33: Real GDP | D33: 23 | E33: (growth rate)
B34: 10 | C34: Potential GDP | D34: 27 | E34: (growth rate)
C35: Stochastic simulations | E35: =F35-1 -> -1
B36: 11 | C36: Probability of debt being below its value in T+4/7 | D36: approximation | E36: (%)
C38: Table 7c: Debt and headline balance projections and underlying assumptions (under 'no-fiscal-policy-change' baseline)
F40: ='Input data'!$C$5-1 -> 2024 | G40: =F40+1 -> 2025 | H40: =G40+1 -> 2026 | I40: =H40+1 -> 2027 | J40: =I40+1 -> 2028 | K40: =J40+1 -> 2029 | L40: =K40+1 -> 2030 | M40: =L40+1 -> 2031 | N40: =M40+1 -> 2032 | ... X40: =W40+1 -> 2042
B41: 1 | C41: Gross debt | D41: 56 | E41: (% GDP) | F41: =INDEX(OFFSET('Baseline NFPC'!$C$1:$U$1,$D41-1,0),MATCH(F$4,'Baseline NFPC'!$C$10:$U$10,0)) -> 43.74815 | G41: =INDEX(OFFSET('Baseline NFPC'!$C$1:$U$1,$D41-1,0),MATCH(G$4,'Baseline NFPC'!$C$10:$U$10,0)) -> 45.15761 | H41: =INDEX(OFFSET('Baseline NFPC'!$C$1:$U$1,$D41-1,0),MATCH(H$4,'Baseline NFPC'!$C$10:$U$10,0)) -> 47.861385 | I41: =INDEX(OFFSET('Baseline NFPC'!$C$1:$U$1,$D41-1,0),MATCH(I$4,'Baseline NFPC'!$C$10:$U$10,0)) -> 48.251114 | J41: =INDEX(OFFSET('Baseline NFPC'!$C$1:$U$1,$D41-1,0),MATCH(J$4,'Baseline NFPC'!$C$10:$U$10,0)) -> 48.658886 | K41: =INDEX(OFFSET('Baseline NFPC'!$C$1:$U$1,$D41-1,0),MATCH(K$4,'Baseline NFPC'!$C$10:$U$10,0)) -> 49.108564 | L41: =INDEX(OFFSET('Baseline NFPC'!$C$1:$U$1,$D41-1,0),MATCH(L$4,'Baseline NFPC'!$C$10:$U$10,0)) -> 49.559845 | M41: =INDEX(OFFSET('Baseline NFPC'!$C$1:$U$1,$D41-1,0),MATCH(M$4,'Baseline NFPC'!$C$10:$U$10,0)) -> 50.526398 | ... X41: =INDEX(OFFSET('Baseline NFPC'!$C$1:$U$1,$D41-1,0),MATCH(X$4,'Baseline NFPC'!$C$10:$U$10,0)) -> 72.409633
B42: 2 | C42: General government balance | D42: 76 | E42: (% GDP) | F42: =INDEX(OFFSET('Baseline NFPC'!$C$1:$U$1,$D42-1,0),MATCH(F$4,'Baseline NFPC'!$C$10:$U$10,0)) -> -0.9448897 | G42: =INDEX(OFFSET('Baseline NFPC'!$C$1:$U$1,$D42-1,0),MATCH(G$4,'Baseline NFPC'!$C$10:$U$10,0)) -> -1.8748092 | H42: =INDEX(OFFSET('Baseline NFPC'!$C$1:$U$1,$D42-1,0),MATCH(H$4,'Baseline NFPC'!$C$10:$U$10,0)) -> -2.6660146 | I42: =INDEX(OFFSET('Baseline NFPC'!$C$1:$U$1,$D42-1,0),MATCH(I$4,'Baseline NFPC'!$C$10:$U$10,0)) -> -2.1056276 | J42: =INDEX(OFFSET('Baseline NFPC'!$C$1:$U$1,$D42-1,0),MATCH(J$4,'Baseline NFPC'!$C$10:$U$10,0)) -> -2.1200004 | K42: =INDEX(OFFSET('Baseline NFPC'!$C$1:$U$1,$D42-1,0),MATCH(K$4,'Baseline NFPC'!$C$10:$U$10,0)) -> -2.1366836 | L42: =INDEX(OFFSET('Baseline NFPC'!$C$1:$U$1,$D42-1,0),MATCH(L$4,'Baseline NFPC'!$C$10:$U$10,0)) -> -2.1548471 | M42: =INDEX(OFFSET('Baseline NFPC'!$C$1:$U$1,$D42-1,0),MATCH(M$4,'Baseline NFPC'!$C$10:$U$10,0)) -> -2.5424488 | ... X42: =INDEX(OFFSET('Baseline NFPC'!$C$1:$U$1,$D42-1,0),MATCH(X$4,'Baseline NFPC'!$C$10:$U$10,0)) -> -5.1547959
B43: 3 | C43: Structural primary balance | D43: 12 | E43: (% pot. GDP) | F43: =INDEX(OFFSET('Baseline NFPC'!$C$1:$U$1,$D43-1,0),MATCH(F$4,'Baseline NFPC'!$C$10:$U$10,0)) -> 0.386237 | G43: =INDEX(OFFSET('Baseline NFPC'!$C$1:$U$1,$D43-1,0),MATCH(G$4,'Baseline NFPC'!$C$10:$U$10,0)) -> -0.5577395 | H43: =INDEX(OFFSET('Baseline NFPC'!$C$1:$U$1,$D43-1,0),MATCH(H$4,'Baseline NFPC'!$C$10:$U$10,0)) -> -0.5577395 | I43: =INDEX(OFFSET('Baseline NFPC'!$C$1:$U$1,$D43-1,0),MATCH(I$4,'Baseline NFPC'!$C$10:$U$10,0)) -> -0.5577395 | J43: =INDEX(OFFSET('Baseline NFPC'!$C$1:$U$1,$D43-1,0),MATCH(J$4,'Baseline NFPC'!$C$10:$U$10,0)) -> -0.5577395 | K43: =INDEX(OFFSET('Baseline NFPC'!$C$1:$U$1,$D43-1,0),MATCH(K$4,'Baseline NFPC'!$C$10:$U$10,0)) -> -0.5577395 | L43: =INDEX(OFFSET('Baseline NFPC'!$C$1:$U$1,$D43-1,0),MATCH(L$4,'Baseline NFPC'!$C$10:$U$10,0)) -> -0.5577395 | M43: =INDEX(OFFSET('Baseline NFPC'!$C$1:$U$1,$D43-1,0),MATCH(M$4,'Baseline NFPC'!$C$10:$U$10,0)) -> -0.5577395 | ... X43: =INDEX(OFFSET('Baseline NFPC'!$C$1:$U$1,$D43-1,0),MATCH(X$4,'Baseline NFPC'!$C$10:$U$10,0)) -> -0.5577395
B44: 4 | C44: Cyclical component | D44: 61 | E44: (% pot. GDP) | F44: =INDEX(OFFSET('Baseline NFPC'!$C$1:$U$1,$D44-1,0),MATCH(F$4,'Baseline NFPC'!$C$10:$U$10,0)) -> 0 | G44: =INDEX(OFFSET('Baseline NFPC'!$C$1:$U$1,$D44-1,0),MATCH(G$4,'Baseline NFPC'!$C$10:$U$10,0)) -> 0.57430421 | H44: =INDEX(OFFSET('Baseline NFPC'!$C$1:$U$1,$D44-1,0),MATCH(H$4,'Baseline NFPC'!$C$10:$U$10,0)) -> 0.66441172 | I44: =INDEX(OFFSET('Baseline NFPC'!$C$1:$U$1,$D44-1,0),MATCH(I$4,'Baseline NFPC'!$C$10:$U$10,0)) -> 0.49370469 | J44: =INDEX(OFFSET('Baseline NFPC'!$C$1:$U$1,$D44-1,0),MATCH(J$4,'Baseline NFPC'!$C$10:$U$10,0)) -> 0.32913858 | K44: =INDEX(OFFSET('Baseline NFPC'!$C$1:$U$1,$D44-1,0),MATCH(K$4,'Baseline NFPC'!$C$10:$U$10,0)) -> 0.16456822 | L44: =INDEX(OFFSET('Baseline NFPC'!$C$1:$U$1,$D44-1,0),MATCH(L$4,'Baseline NFPC'!$C$10:$U$10,0)) -> 6.004402e-07 | M44: =INDEX(OFFSET('Baseline NFPC'!$C$1:$U$1,$D44-1,0),MATCH(M$4,'Baseline NFPC'!$C$10:$U$10,0)) -> 1.7976406e-06 | ... X44: =INDEX(OFFSET('Baseline NFPC'!$C$1:$U$1,$D44-1,0),MATCH(X$4,'Baseline NFPC'!$C$10:$U$10,0)) -> -4.1943813e-06
B45: 5 | C45: Interest expenditure | D45: 67 | E45: (% GDP) | F45: =INDEX(OFFSET('Baseline NFPC'!$C$1:$U$1,$D45-1,0),MATCH(F$4,'Baseline NFPC'!$C$10:$U$10,0)) -> 0 | G45: =INDEX(OFFSET('Baseline NFPC'!$C$1:$U$1,$D45-1,0),MATCH(G$4,'Baseline NFPC'!$C$10:$U$10,0)) -> 0.71728823 | H45: =INDEX(OFFSET('Baseline NFPC'!$C$1:$U$1,$D45-1,0),MATCH(H$4,'Baseline NFPC'!$C$10:$U$10,0)) -> 0.74801829 | I45: =INDEX(OFFSET('Baseline NFPC'!$C$1:$U$1,$D45-1,0),MATCH(I$4,'Baseline NFPC'!$C$10:$U$10,0)) -> 0.84270245 | J45: =INDEX(OFFSET('Baseline NFPC'!$C$1:$U$1,$D45-1,0),MATCH(J$4,'Baseline NFPC'!$C$10:$U$10,0)) -> 0.91590137 | K45: =INDEX(OFFSET('Baseline NFPC'!$C$1:$U$1,$D45-1,0),MATCH(K$4,'Baseline NFPC'!$C$10:$U$10,0)) -> 0.99141468 | L45: =INDEX(OFFSET('Baseline NFPC'!$C$1:$U$1,$D45-1,0),MATCH(L$4,'Baseline NFPC'!$C$10:$U$10,0)) -> 1.0684054 | M45: =INDEX(OFFSET('Baseline NFPC'!$C$1:$U$1,$D45-1,0),MATCH(M$4,'Baseline NFPC'!$C$10:$U$10,0)) -> 1.1502656 | ... X45: =INDEX(OFFSET('Baseline NFPC'!$C$1:$U$1,$D45-1,0),MATCH(X$4,'Baseline NFPC'!$C$10:$U$10,0)) -> 2.3994753
B46: 6 | C46: Long-term interest rate | D46: 36 | E46: (%) | F46: =INDEX(OFFSET('Baseline NFPC'!$C$1:$U$1,$D46-1,0),MATCH(F$4,'Baseline NFPC'!$C$10:$U$10,0)) -> 2.6205 | G46: =INDEX(OFFSET('Baseline NFPC'!$C$1:$U$1,$D46-1,0),MATCH(G$4,'Baseline NFPC'!$C$10:$U$10,0)) -> 2.78965 | H46: =INDEX(OFFSET('Baseline NFPC'!$C$1:$U$1,$D46-1,0),MATCH(H$4,'Baseline NFPC'!$C$10:$U$10,0)) -> 2.894953 | I46: =INDEX(OFFSET('Baseline NFPC'!$C$1:$U$1,$D46-1,0),MATCH(I$4,'Baseline NFPC'!$C$10:$U$10,0)) -> 3.081676 | J46: =INDEX(OFFSET('Baseline NFPC'!$C$1:$U$1,$D46-1,0),MATCH(J$4,'Baseline NFPC'!$C$10:$U$10,0)) -> 3.188669 | K46: =INDEX(OFFSET('Baseline NFPC'!$C$1:$U$1,$D46-1,0),MATCH(K$4,'Baseline NFPC'!$C$10:$U$10,0)) -> 3.295662 | L46: =INDEX(OFFSET('Baseline NFPC'!$C$1:$U$1,$D46-1,0),MATCH(L$4,'Baseline NFPC'!$C$10:$U$10,0)) -> 3.402655 | M46: =INDEX(OFFSET('Baseline NFPC'!$C$1:$U$1,$D46-1,0),MATCH(M$4,'Baseline NFPC'!$C$10:$U$10,0)) -> 3.509648 | ... X46: =INDEX(OFFSET('Baseline NFPC'!$C$1:$U$1,$D46-1,0),MATCH(X$4,'Baseline NFPC'!$C$10:$U$10,0)) -> 3.959453
B47: 7 | C47: Short-term interest rate | D47: 37 | E47: (%) | F47: =INDEX(OFFSET('Baseline NFPC'!$C$1:$U$1,$D47-1,0),MATCH(F$4,'Baseline NFPC'!$C$10:$U$10,0)) -> 3.570833 | G47: =INDEX(OFFSET('Baseline NFPC'!$C$1:$U$1,$D47-1,0),MATCH(G$4,'Baseline NFPC'!$C$10:$U$10,0)) -> 2.172583 | H47: =INDEX(OFFSET('Baseline NFPC'!$C$1:$U$1,$D47-1,0),MATCH(H$4,'Baseline NFPC'!$C$10:$U$10,0)) -> 1.91225 | I47: =INDEX(OFFSET('Baseline NFPC'!$C$1:$U$1,$D47-1,0),MATCH(I$4,'Baseline NFPC'!$C$10:$U$10,0)) -> 2.024375 | J47: =INDEX(OFFSET('Baseline NFPC'!$C$1:$U$1,$D47-1,0),MATCH(J$4,'Baseline NFPC'!$C$10:$U$10,0)) -> 2.1784319 | K47: =INDEX(OFFSET('Baseline NFPC'!$C$1:$U$1,$D47-1,0),MATCH(K$4,'Baseline NFPC'!$C$10:$U$10,0)) -> 2.3324888 | L47: =INDEX(OFFSET('Baseline NFPC'!$C$1:$U$1,$D47-1,0),MATCH(L$4,'Baseline NFPC'!$C$10:$U$10,0)) -> 2.4865456 | M47: =INDEX(OFFSET('Baseline NFPC'!$C$1:$U$1,$D47-1,0),MATCH(M$4,'Baseline NFPC'!$C$10:$U$10,0)) -> 2.6406025 | ... X47: =INDEX(OFFSET('Baseline NFPC'!$C$1:$U$1,$D47-1,0),MATCH(X$4,'Baseline NFPC'!$C$10:$U$10,0)) -> 2.8169395
B48: 8 | C48: Implicit average interest rate | D48: 35 | E48: (%) | F48: =INDEX(OFFSET('Baseline NFPC'!$C$1:$U$1,$D48-1,0),MATCH(F$4,'Baseline NFPC'!$C$10:$U$10,0)) -> 1.646586 | G48: =INDEX(OFFSET('Baseline NFPC'!$C$1:$U$1,$D48-1,0),MATCH(G$4,'Baseline NFPC'!$C$10:$U$10,0)) -> 1.72 | H48: =INDEX(OFFSET('Baseline NFPC'!$C$1:$U$1,$D48-1,0),MATCH(H$4,'Baseline NFPC'!$C$10:$U$10,0)) -> 1.732298 | I48: =INDEX(OFFSET('Baseline NFPC'!$C$1:$U$1,$D48-1,0),MATCH(I$4,'Baseline NFPC'!$C$10:$U$10,0)) -> 1.826186 | J48: =INDEX(OFFSET('Baseline NFPC'!$C$1:$U$1,$D48-1,0),MATCH(J$4,'Baseline NFPC'!$C$10:$U$10,0)) -> 1.9680346 | K48: =INDEX(OFFSET('Baseline NFPC'!$C$1:$U$1,$D48-1,0),MATCH(K$4,'Baseline NFPC'!$C$10:$U$10,0)) -> 2.1106557 | L48: =INDEX(OFFSET('Baseline NFPC'!$C$1:$U$1,$D48-1,0),MATCH(L$4,'Baseline NFPC'!$C$10:$U$10,0)) -> 2.2537821 | M48: =INDEX(OFFSET('Baseline NFPC'!$C$1:$U$1,$D48-1,0),MATCH(M$4,'Baseline NFPC'!$C$10:$U$10,0)) -> 2.3971883 | ... X48: =INDEX(OFFSET('Baseline NFPC'!$C$1:$U$1,$D48-1,0),MATCH(X$4,'Baseline NFPC'!$C$10:$U$10,0)) -> 3.5677364
B49: 9 | C49: Potential GDP | D49: 26 | E49: (growth rate) | F49: ='Input data'!C$33 -> 1.824226 | G49: =(INDEX(OFFSET('Baseline NFPC'!$C$1:$U$1,$D49-1,0),MATCH(G$4,'Baseline NFPC'!$C$10:$U$10,0))/INDEX(OFFSET('Baseline NFPC'!$C$1:$U$1,$D49-1,0),MATCH(F$4,'Baseline NFPC'!$C$10:$U$10,0))-1)*100 -> 1.656294 | H49: =(INDEX(OFFSET('Baseline NFPC'!$C$1:$U$1,$D49-1,0),MATCH(H$4,'Baseline NFPC'!$C$10:$U$10,0))/INDEX(OFFSET('Baseline NFPC'!$C$1:$U$1,$D49-1,0),MATCH(G$4,'Baseline NFPC'!$C$10:$U$10,0))-1)*100 -> 1.426257 | I49: =(INDEX(OFFSET('Baseline NFPC'!$C$1:$U$1,$D49-1,0),MATCH(I$4,'Baseline NFPC'!$C$10:$U$10,0))/INDEX(OFFSET('Baseline NFPC'!$C$1:$U$1,$D49-1,0),MATCH(H$4,'Baseline NFPC'!$C$10:$U$10,0))-1)*100 -> 1.292883 | J49: =(INDEX(OFFSET('Baseline NFPC'!$C$1:$U$1,$D49-1,0),MATCH(J$4,'Baseline NFPC'!$C$10:$U$10,0))/INDEX(OFFSET('Baseline NFPC'!$C$1:$U$1,$D49-1,0),MATCH(I$4,'Baseline NFPC'!$C$10:$U$10,0))-1)*100 -> 1.24374 | K49: =(INDEX(OFFSET('Baseline NFPC'!$C$1:$U$1,$D49-1,0),MATCH(K$4,'Baseline NFPC'!$C$10:$U$10,0))/INDEX(OFFSET('Baseline NFPC'!$C$1:$U$1,$D49-1,0),MATCH(J$4,'Baseline NFPC'!$C$10:$U$10,0))-1)*100 -> 1.137065 | L49: =(INDEX(OFFSET('Baseline NFPC'!$C$1:$U$1,$D49-1,0),MATCH(L$4,'Baseline NFPC'!$C$10:$U$10,0))/INDEX(OFFSET('Baseline NFPC'!$C$1:$U$1,$D49-1,0),MATCH(K$4,'Baseline NFPC'!$C$10:$U$10,0))-1)*100 -> 1.118027 | M49: =(INDEX(OFFSET('Baseline NFPC'!$C$1:$U$1,$D49-1,0),MATCH(M$4,'Baseline NFPC'!$C$10:$U$10,0))/INDEX(OFFSET('Baseline NFPC'!$C$1:$U$1,$D49-1,0),MATCH(L$4,'Baseline NFPC'!$C$10:$U$10,0))-1)*100 -> 1.069128 | N49: =(INDEX(OFFSET('Baseline NFPC'!$C$1:$U$1,$D49-1,0),MATCH(N$4,'Baseline NFPC'!$C$10:$U$10,0))/INDEX(OFFSET('Baseline NFPC'!$C$1:$U$1,$D49-1,0),MATCH(M$4,'Baseline NFPC'!$C$10:$U$10,0))-1)*100 -> 1.03431 | ... X49: =(INDEX(OFFSET('Baseline NFPC'!$C$1:$U$1,$D49-1,0),MATCH(X$4,'Baseline NFPC'!$C$10:$U$10,0))/INDEX(OFFSET('Baseline NFPC'!$C$1:$U$1,$D49-1,0),MATCH(W$4,'Baseline NFPC'!$C$10:$U$10,0))-1)*100 -> 1.71
B50: 10 | C50: Real GDP | D50: 23 | E50: (growth rate) | F50: =INDEX(OFFSET('Baseline NFPC'!$C$1:$U$1,$D50-1,0),MATCH(F$4,'Baseline NFPC'!$C$10:$U$10,0)) -> 1.081005 | G50: =INDEX(OFFSET('Baseline NFPC'!$C$1:$U$1,$D50-1,0),MATCH(G$4,'Baseline NFPC'!$C$10:$U$10,0)) -> 1.69667 | H50: =INDEX(OFFSET('Baseline NFPC'!$C$1:$U$1,$D50-1,0),MATCH(H$4,'Baseline NFPC'!$C$10:$U$10,0)) -> 1.273747 | I50: =INDEX(OFFSET('Baseline NFPC'!$C$1:$U$1,$D50-1,0),MATCH(I$4,'Baseline NFPC'!$C$10:$U$10,0)) -> 1.581865 | J50: =INDEX(OFFSET('Baseline NFPC'!$C$1:$U$1,$D50-1,0),MATCH(J$4,'Baseline NFPC'!$C$10:$U$10,0)) -> 1.521399 | K50: =INDEX(OFFSET('Baseline NFPC'!$C$1:$U$1,$D50-1,0),MATCH(K$4,'Baseline NFPC'!$C$10:$U$10,0)) -> 1.41368 | L50: =INDEX(OFFSET('Baseline NFPC'!$C$1:$U$1,$D50-1,0),MATCH(L$4,'Baseline NFPC'!$C$10:$U$10,0)) -> 1.393831 | M50: =INDEX(OFFSET('Baseline NFPC'!$C$1:$U$1,$D50-1,0),MATCH(M$4,'Baseline NFPC'!$C$10:$U$10,0)) -> 1.069126 | ... X50: =INDEX(OFFSET('Baseline NFPC'!$C$1:$U$1,$D50-1,0),MATCH(X$4,'Baseline NFPC'!$C$10:$U$10,0)) -> 1.710004
B51: 11 | C51: GDP deflator | D51: 41 | E51: (growth rate) | F51: =INDEX(OFFSET('Baseline NFPC'!$C$1:$U$1,$D51-1,0),MATCH(F$4,'Baseline NFPC'!$C$10:$U$10,0)) -> 5.744214 | G51: =INDEX(OFFSET('Baseline NFPC'!$C$1:$U$1,$D51-1,0),MATCH(G$4,'Baseline NFPC'!$C$10:$U$10,0)) -> 3.154387 | H51: =INDEX(OFFSET('Baseline NFPC'!$C$1:$U$1,$D51-1,0),MATCH(H$4,'Baseline NFPC'!$C$10:$U$10,0)) -> 3.262934 | I51: =INDEX(OFFSET('Baseline NFPC'!$C$1:$U$1,$D51-1,0),MATCH(I$4,'Baseline NFPC'!$C$10:$U$10,0)) -> 2.103313 | J51: =INDEX(OFFSET('Baseline NFPC'!$C$1:$U$1,$D51-1,0),MATCH(J$4,'Baseline NFPC'!$C$10:$U$10,0)) -> 2.1253989 | K51: =INDEX(OFFSET('Baseline NFPC'!$C$1:$U$1,$D51-1,0),MATCH(K$4,'Baseline NFPC'!$C$10:$U$10,0)) -> 2.1474847 | L51: =INDEX(OFFSET('Baseline NFPC'!$C$1:$U$1,$D51-1,0),MATCH(L$4,'Baseline NFPC'!$C$10:$U$10,0)) -> 2.1695706 | M51: =INDEX(OFFSET('Baseline NFPC'!$C$1:$U$1,$D51-1,0),MATCH(M$4,'Baseline NFPC'!$C$10:$U$10,0)) -> 2.1916565 | ... X51: =INDEX(OFFSET('Baseline NFPC'!$C$1:$U$1,$D51-1,0),MATCH(X$4,'Baseline NFPC'!$C$10:$U$10,0)) -> 2.182
B52: 12 | C52: Nominal GDP | D52: 32 | E52: (growth rate) | F52: =INDEX(OFFSET('Baseline NFPC'!$C$1:$U$1,$D52-1,0),MATCH(F$4,'Baseline NFPC'!$C$10:$U$10,0)) -> 6.8873142 | G52: =INDEX(OFFSET('Baseline NFPC'!$C$1:$U$1,$D52-1,0),MATCH(G$4,'Baseline NFPC'!$C$10:$U$10,0)) -> 4.9045765 | H52: =INDEX(OFFSET('Baseline NFPC'!$C$1:$U$1,$D52-1,0),MATCH(H$4,'Baseline NFPC'!$C$10:$U$10,0)) -> 4.5782425 | I52: =INDEX(OFFSET('Baseline NFPC'!$C$1:$U$1,$D52-1,0),MATCH(I$4,'Baseline NFPC'!$C$10:$U$10,0)) -> 3.7184496 | J52: =INDEX(OFFSET('Baseline NFPC'!$C$1:$U$1,$D52-1,0),MATCH(J$4,'Baseline NFPC'!$C$10:$U$10,0)) -> 3.6791337 | K52: =INDEX(OFFSET('Baseline NFPC'!$C$1:$U$1,$D52-1,0),MATCH(K$4,'Baseline NFPC'!$C$10:$U$10,0)) -> 3.5915233 | L52: =INDEX(OFFSET('Baseline NFPC'!$C$1:$U$1,$D52-1,0),MATCH(L$4,'Baseline NFPC'!$C$10:$U$10,0)) -> 3.5936418 | M52: =INDEX(OFFSET('Baseline NFPC'!$C$1:$U$1,$D52-1,0),MATCH(M$4,'Baseline NFPC'!$C$10:$U$10,0)) -> 3.2842141 | ... X52: =INDEX(OFFSET('Baseline NFPC'!$C$1:$U$1,$D52-1,0),MATCH(X$4,'Baseline NFPC'!$C$10:$U$10,0)) -> 3.9293163
B53: 13 | C53: Fiscal multiplier | E53: (%) | F53: ='Input data'!$C$49 -> 0.6
C55: Table 7d: Debt projections and additional assumptions (under the planned fiscal path)
F57: ='Input data'!$C$5-1 -> 2024 | G57: =F57+1 -> 2025 | H57: =G57+1 -> 2026 | I57: =H57+1 -> 2027 | J57: =I57+1 -> 2028 | K57: =J57+1 -> 2029 | L57: =K57+1 -> 2030 | M57: =L57+1 -> 2031 | N57: =M57+1 -> 2032 | ... X57: =W57+1 -> 2042
B58: 1 | C58: Gross debt | D58: 90 | E58: (% GDP) | F58: =INDEX(OFFSET('Adjustment scenario'!$C$1:$U$1,$D58-1,0),MATCH(F$4,'Adjustment scenario'!$C$10:$U$10,0)) -> 43.74815 | G58: =INDEX(OFFSET('Adjustment scenario'!$C$1:$U$1,$D58-1,0),MATCH(G$4,'Adjustment scenario'!$C$10:$U$10,0)) -> 45.15761 | H58: =INDEX(OFFSET('Adjustment scenario'!$C$1:$U$1,$D58-1,0),MATCH(H$4,'Adjustment scenario'!$C$10:$U$10,0)) -> 47.855642 | I58: =INDEX(OFFSET('Adjustment scenario'!$C$1:$U$1,$D58-1,0),MATCH(I$4,'Adjustment scenario'!$C$10:$U$10,0)) -> 48.033966 | J58: =INDEX(OFFSET('Adjustment scenario'!$C$1:$U$1,$D58-1,0),MATCH(J$4,'Adjustment scenario'!$C$10:$U$10,0)) -> 48.125782 | K58: =INDEX(OFFSET('Adjustment scenario'!$C$1:$U$1,$D58-1,0),MATCH(K$4,'Adjustment scenario'!$C$10:$U$10,0)) -> 48.154706 | L58: =INDEX(OFFSET('Adjustment scenario'!$C$1:$U$1,$D58-1,0),MATCH(L$4,'Adjustment scenario'!$C$10:$U$10,0)) -> 48.186222 | M58: =INDEX(OFFSET('Adjustment scenario'!$C$1:$U$1,$D58-1,0),MATCH(M$4,'Adjustment scenario'!$C$10:$U$10,0)) -> 48.729285 | ... X58: =INDEX(OFFSET('Adjustment scenario'!$C$1:$U$1,$D58-1,0),MATCH(X$4,'Adjustment scenario'!$C$10:$U$10,0)) -> 65.925993
B59: =B58+1 -> 2 | C59: Rolled over long-term debt | D59: 92 | E59: (% GDP) | F59: =INDEX(OFFSET('Adjustment scenario'!$C$1:$U$1,$D59-1,0),MATCH(F$4,'Adjustment scenario'!$C$10:$U$10,0)) -> 0 | G59: =INDEX(OFFSET('Adjustment scenario'!$C$1:$U$1,$D59-1,0),MATCH(G$4,'Adjustment scenario'!$C$10:$U$10,0)) -> 3.5884993 | H59: =INDEX(OFFSET('Adjustment scenario'!$C$1:$U$1,$D59-1,0),MATCH(H$4,'Adjustment scenario'!$C$10:$U$10,0)) -> 2.2949335 | I59: =INDEX(OFFSET('Adjustment scenario'!$C$1:$U$1,$D59-1,0),MATCH(I$4,'Adjustment scenario'!$C$10:$U$10,0)) -> 2.5911314 | J59: =INDEX(OFFSET('Adjustment scenario'!$C$1:$U$1,$D59-1,0),MATCH(J$4,'Adjustment scenario'!$C$10:$U$10,0)) -> 2.7429825 | K59: =INDEX(OFFSET('Adjustment scenario'!$C$1:$U$1,$D59-1,0),MATCH(K$4,'Adjustment scenario'!$C$10:$U$10,0)) -> 2.892139 | L59: =INDEX(OFFSET('Adjustment scenario'!$C$1:$U$1,$D59-1,0),MATCH(L$4,'Adjustment scenario'!$C$10:$U$10,0)) -> 3.0354855 | M59: =INDEX(OFFSET('Adjustment scenario'!$C$1:$U$1,$D59-1,0),MATCH(M$4,'Adjustment scenario'!$C$10:$U$10,0)) -> 3.1886932 | ... X59: =INDEX(OFFSET('Adjustment scenario'!$C$1:$U$1,$D59-1,0),MATCH(X$4,'Adjustment scenario'!$C$10:$U$10,0)) -> 4.9291166
B60: =B59+1 -> 3 | C60: Rolled over short-term debt | D60: 93 | E60: (% GDP) | F60: =INDEX(OFFSET('Adjustment scenario'!$C$1:$U$1,$D60-1,0),MATCH(F$4,'Adjustment scenario'!$C$10:$U$10,0)) -> 0 | G60: =INDEX(OFFSET('Adjustment scenario'!$C$1:$U$1,$D60-1,0),MATCH(G$4,'Adjustment scenario'!$C$10:$U$10,0)) -> 3.6736521 | H60: =INDEX(OFFSET('Adjustment scenario'!$C$1:$U$1,$D60-1,0),MATCH(H$4,'Adjustment scenario'!$C$10:$U$10,0)) -> 3.5826776 | I60: =INDEX(OFFSET('Adjustment scenario'!$C$1:$U$1,$D60-1,0),MATCH(I$4,'Adjustment scenario'!$C$10:$U$10,0)) -> 3.8779057 | J60: =INDEX(OFFSET('Adjustment scenario'!$C$1:$U$1,$D60-1,0),MATCH(J$4,'Adjustment scenario'!$C$10:$U$10,0)) -> 3.9120079 | K60: =INDEX(OFFSET('Adjustment scenario'!$C$1:$U$1,$D60-1,0),MATCH(K$4,'Adjustment scenario'!$C$10:$U$10,0)) -> 3.9393731 | L60: =INDEX(OFFSET('Adjustment scenario'!$C$1:$U$1,$D60-1,0),MATCH(L$4,'Adjustment scenario'!$C$10:$U$10,0)) -> 3.9567354 | M60: =INDEX(OFFSET('Adjustment scenario'!$C$1:$U$1,$D60-1,0),MATCH(M$4,'Adjustment scenario'!$C$10:$U$10,0)) -> 3.9858133 | ... X60: =INDEX(OFFSET('Adjustment scenario'!$C$1:$U$1,$D60-1,0),MATCH(X$4,'Adjustment scenario'!$C$10:$U$10,0)) -> 5.5007021
B61: =B60+1 -> 4 | C61: New long-term debt | D61: 94 | E61: (% GDP) | F61: =INDEX(OFFSET('Adjustment scenario'!$C$1:$U$1,$D61-1,0),MATCH(F$4,'Adjustment scenario'!$C$10:$U$10,0)) -> 0 | G61: =INDEX(OFFSET('Adjustment scenario'!$C$1:$U$1,$D61-1,0),MATCH(G$4,'Adjustment scenario'!$C$10:$U$10,0)) -> 0.80738171 | H61: =INDEX(OFFSET('Adjustment scenario'!$C$1:$U$1,$D61-1,0),MATCH(H$4,'Adjustment scenario'!$C$10:$U$10,0)) -> 4.2355222 | I61: =INDEX(OFFSET('Adjustment scenario'!$C$1:$U$1,$D61-1,0),MATCH(I$4,'Adjustment scenario'!$C$10:$U$10,0)) -> 1.7159888 | J61: =INDEX(OFFSET('Adjustment scenario'!$C$1:$U$1,$D61-1,0),MATCH(J$4,'Adjustment scenario'!$C$10:$U$10,0)) -> 1.6274901 | K61: =INDEX(OFFSET('Adjustment scenario'!$C$1:$U$1,$D61-1,0),MATCH(K$4,'Adjustment scenario'!$C$10:$U$10,0)) -> 1.5378934 | L61: =INDEX(OFFSET('Adjustment scenario'!$C$1:$U$1,$D61-1,0),MATCH(L$4,'Adjustment scenario'!$C$10:$U$10,0)) -> 1.5420129 | M61: =INDEX(OFFSET('Adjustment scenario'!$C$1:$U$1,$D61-1,0),MATCH(M$4,'Adjustment scenario'!$C$10:$U$10,0)) -> 1.8802123 | ... X61: =INDEX(OFFSET('Adjustment scenario'!$C$1:$U$1,$D61-1,0),MATCH(X$4,'Adjustment scenario'!$C$10:$U$10,0)) -> 4.0862411
B62: =B61+1 -> 5 | C62: New short-term debt | D62: 95 | E62: (% GDP) | F62: =INDEX(OFFSET('Adjustment scenario'!$C$1:$U$1,$D62-1,0),MATCH(F$4,'Adjustment scenario'!$C$10:$U$10,0)) -> 0 | G62: =INDEX(OFFSET('Adjustment scenario'!$C$1:$U$1,$D62-1,0),MATCH(G$4,'Adjustment scenario'!$C$10:$U$10,0)) -> 0.073048801 | H62: =INDEX(OFFSET('Adjustment scenario'!$C$1:$U$1,$D62-1,0),MATCH(H$4,'Adjustment scenario'!$C$10:$U$10,0)) -> 0.43942648 | I62: =INDEX(OFFSET('Adjustment scenario'!$C$1:$U$1,$D62-1,0),MATCH(I$4,'Adjustment scenario'!$C$10:$U$10,0)) -> 0.17803021 | J62: =INDEX(OFFSET('Adjustment scenario'!$C$1:$U$1,$D62-1,0),MATCH(J$4,'Adjustment scenario'!$C$10:$U$10,0)) -> 0.16884866 | K62: =INDEX(OFFSET('Adjustment scenario'!$C$1:$U$1,$D62-1,0),MATCH(K$4,'Adjustment scenario'!$C$10:$U$10,0)) -> 0.15955319 | L62: =INDEX(OFFSET('Adjustment scenario'!$C$1:$U$1,$D62-1,0),MATCH(L$4,'Adjustment scenario'!$C$10:$U$10,0)) -> 0.15998058 | M62: =INDEX(OFFSET('Adjustment scenario'!$C$1:$U$1,$D62-1,0),MATCH(M$4,'Adjustment scenario'!$C$10:$U$10,0)) -> 0.19506805 | ... X62: =INDEX(OFFSET('Adjustment scenario'!$C$1:$U$1,$D62-1,0),MATCH(X$4,'Adjustment scenario'!$C$10:$U$10,0)) -> 0.42393888

Sheet FASTOP rep. no safeguard
C2: Table 7a: Debt and headline balance projections and key underlying assumptions (under the planned fiscal path)
D4: line | E4: =F4-1 -> 2023 | F4: ='Input data'!$C$5-1 -> 2024 | G4: =F4+1 -> 2025 | H4: =G4+1 -> 2026 | I4: =H4+1 -> 2027 | J4: =I4+1 -> 2028 | K4: =J4+1 -> 2029 | L4: =K4+1 -> 2030 | M4: =L4+1 -> 2031 | N4: =M4+1 -> 2032 | ... X4: =W4+1 -> 2042
B5: 1 | C5: Gross debt | D5: 57 | E5: (% GDP) | F5: =INDEX(OFFSET('Adjust. no safeguard'!$C$1:$U$1,$D5-1,0),MATCH(F$4,'Adjust. no safeguard'!$C$10:$U$10,0)) -> 43.74815 | G5: =INDEX(OFFSET('Adjust. no safeguard'!$C$1:$U$1,$D5-1,0),MATCH(G$4,'Adjust. no safeguard'!$C$10:$U$10,0)) -> 45.15761 | H5: =INDEX(OFFSET('Adjust. no safeguard'!$C$1:$U$1,$D5-1,0),MATCH(H$4,'Adjust. no safeguard'!$C$10:$U$10,0)) -> 47.855645 | I5: =INDEX(OFFSET('Adjust. no safeguard'!$C$1:$U$1,$D5-1,0),MATCH(I$4,'Adjust. no safeguard'!$C$10:$U$10,0)) -> 48.033971 | J5: =INDEX(OFFSET('Adjust. no safeguard'!$C$1:$U$1,$D5-1,0),MATCH(J$4,'Adjust. no safeguard'!$C$10:$U$10,0)) -> 48.125788 | K5: =INDEX(OFFSET('Adjust. no safeguard'!$C$1:$U$1,$D5-1,0),MATCH(K$4,'Adjust. no safeguard'!$C$10:$U$10,0)) -> 48.154711 | L5: =INDEX(OFFSET('Adjust. no safeguard'!$C$1:$U$1,$D5-1,0),MATCH(L$4,'Adjust. no safeguard'!$C$10:$U$10,0)) -> 48.186228 | M5: =INDEX(OFFSET('Adjust. no safeguard'!$C$1:$U$1,$D5-1,0),MATCH(M$4,'Adjust. no safeguard'!$C$10:$U$10,0)) -> 48.72929 | ... X5: =INDEX(OFFSET('Adjust. no safeguard'!$C$1:$U$1,$D5-1,0),MATCH(X$4,'Adjust. no safeguard'!$C$10:$U$10,0)) -> 65.925998
B6: 2 | C6: General government balance | D6: 77 | E6: (% GDP) | F6: =INDEX(OFFSET('Adjust. no safeguard'!$C$1:$U$1,$D6-1,0),MATCH(F$4,'Adjust. no safeguard'!$C$10:$U$10,0)) -> -0.9448897 | G6: =INDEX(OFFSET('Adjust. no safeguard'!$C$1:$U$1,$D6-1,0),MATCH(G$4,'Adjust. no safeguard'!$C$10:$U$10,0)) -> -1.8748092 | H6: =INDEX(OFFSET('Adjust. no safeguard'!$C$1:$U$1,$D6-1,0),MATCH(H$4,'Adjust. no safeguard'!$C$10:$U$10,0)) -> -2.6602743 | I6: =INDEX(OFFSET('Adjust. no safeguard'!$C$1:$U$1,$D6-1,0),MATCH(I$4,'Adjust. no safeguard'!$C$10:$U$10,0)) -> -1.8940194 | J6: =INDEX(OFFSET('Adjust. no safeguard'!$C$1:$U$1,$D6-1,0),MATCH(J$4,'Adjust. no safeguard'!$C$10:$U$10,0)) -> -1.7963389 | K6: =INDEX(OFFSET('Adjust. no safeguard'!$C$1:$U$1,$D6-1,0),MATCH(K$4,'Adjust. no safeguard'!$C$10:$U$10,0)) -> -1.6974467 | L6: =INDEX(OFFSET('Adjust. no safeguard'!$C$1:$U$1,$D6-1,0),MATCH(L$4,'Adjust. no safeguard'!$C$10:$U$10,0)) -> -1.7019936 | M6: =INDEX(OFFSET('Adjust. no safeguard'!$C$1:$U$1,$D6-1,0),MATCH(M$4,'Adjust. no safeguard'!$C$10:$U$10,0)) -> -2.0752805 | ... X6: =INDEX(OFFSET('Adjust. no safeguard'!$C$1:$U$1,$D6-1,0),MATCH(X$4,'Adjust. no safeguard'!$C$10:$U$10,0)) -> -4.5101802
B7: 3 | C7: Structural primary balance | D7: 12 | E7: (% pot. GDP) | F7: =INDEX(OFFSET('Adjust. no safeguard'!$C$1:$U$1,$D7-1,0),MATCH(F$4,'Adjust. no safeguard'!$C$10:$U$10,0)) -> 0.386237 | G7: =INDEX(OFFSET('Adjust. no safeguard'!$C$1:$U$1,$D7-1,0),MATCH(G$4,'Adjust. no safeguard'!$C$10:$U$10,0)) -> -0.5577395 | H7: =INDEX(OFFSET('Adjust. no safeguard'!$C$1:$U$1,$D7-1,0),MATCH(H$4,'Adjust. no safeguard'!$C$10:$U$10,0)) -> -0.5577395 | I7: =INDEX(OFFSET('Adjust. no safeguard'!$C$1:$U$1,$D7-1,0),MATCH(I$4,'Adjust. no safeguard'!$C$10:$U$10,0)) -> -0.5577395 | J7: =INDEX(OFFSET('Adjust. no safeguard'!$C$1:$U$1,$D7-1,0),MATCH(J$4,'Adjust. no safeguard'!$C$10:$U$10,0)) -> -0.5577395 | K7: =INDEX(OFFSET('Adjust. no safeguard'!$C$1:$U$1,$D7-1,0),MATCH(K$4,'Adjust. no safeguard'!$C$10:$U$10,0)) -> -0.5577395 | L7: =INDEX(OFFSET('Adjust. no safeguard'!$C$1:$U$1,$D7-1,0),MATCH(L$4,'Adjust. no safeguard'!$C$10:$U$10,0)) -> -0.5577395 | M7: =INDEX(OFFSET('Adjust. no safeguard'!$C$1:$U$1,$D7-1,0),MATCH(M$4,'Adjust. no safeguard'!$C$10:$U$10,0)) -> -0.5577395 | ... X7: =INDEX(OFFSET('Adjust. no safeguard'!$C$1:$U$1,$D7-1,0),MATCH(X$4,'Adjust. no safeguard'!$C$10:$U$10,0)) -> -0.5577395
B8: 4 | C8: Cyclical component | D8: 62 | E8: (% pot. GDP) | F8: =INDEX(OFFSET('Adjust. no safeguard'!$C$1:$U$1,$D8-1,0),MATCH(F$4,'Adjust. no safeguard'!$C$10:$U$10,0)) -> 0 | G8: =INDEX(OFFSET('Adjust. no safeguard'!$C$1:$U$1,$D8-1,0),MATCH(G$4,'Adjust. no safeguard'!$C$10:$U$10,0)) -> 0.57430421 | H8: =INDEX(OFFSET('Adjust. no safeguard'!$C$1:$U$1,$D8-1,0),MATCH(H$4,'Adjust. no safeguard'!$C$10:$U$10,0)) -> 0.66441172 | I8: =INDEX(OFFSET('Adjust. no safeguard'!$C$1:$U$1,$D8-1,0),MATCH(I$4,'Adjust. no safeguard'!$C$10:$U$10,0)) -> 0.49370469 | J8: =INDEX(OFFSET('Adjust. no safeguard'!$C$1:$U$1,$D8-1,0),MATCH(J$4,'Adjust. no safeguard'!$C$10:$U$10,0)) -> 0.32913858 | K8: =INDEX(OFFSET('Adjust. no safeguard'!$C$1:$U$1,$D8-1,0),MATCH(K$4,'Adjust. no safeguard'!$C$10:$U$10,0)) -> 0.16456822 | L8: =INDEX(OFFSET('Adjust. no safeguard'!$C$1:$U$1,$D8-1,0),MATCH(L$4,'Adjust. no safeguard'!$C$10:$U$10,0)) -> 6.004402e-07 | M8: =INDEX(OFFSET('Adjust. no safeguard'!$C$1:$U$1,$D8-1,0),MATCH(M$4,'Adjust. no safeguard'!$C$10:$U$10,0)) -> 1.7976406e-06 | ... X8: =INDEX(OFFSET('Adjust. no safeguard'!$C$1:$U$1,$D8-1,0),MATCH(X$4,'Adjust. no safeguard'!$C$10:$U$10,0)) -> -4.1943813e-06
B9: 5 | C9: One-off measures | D9: 14 | E9: (% GDP) | F9: =INDEX(OFFSET('Adjust. no safeguard'!$C$1:$U$1,$D9-1,0),MATCH(F$4,'Adjust. no safeguard'!$C$10:$U$10,0)) -> -0.026727 | G9: =INDEX(OFFSET('Adjust. no safeguard'!$C$1:$U$1,$D9-1,0),MATCH(G$4,'Adjust. no safeguard'!$C$10:$U$10,0)) -> -0.0254775 | H9: =INDEX(OFFSET('Adjust. no safeguard'!$C$1:$U$1,$D9-1,0),MATCH(H$4,'Adjust. no safeguard'!$C$10:$U$10,0)) -> -0.6901042 | I9: =INDEX(OFFSET('Adjust. no safeguard'!$C$1:$U$1,$D9-1,0),MATCH(I$4,'Adjust. no safeguard'!$C$10:$U$10,0)) -> 0 | J9: =INDEX(OFFSET('Adjust. no safeguard'!$C$1:$U$1,$D9-1,0),MATCH(J$4,'Adjust. no safeguard'!$C$10:$U$10,0)) -> 0 | K9: =INDEX(OFFSET('Adjust. no safeguard'!$C$1:$U$1,$D9-1,0),MATCH(K$4,'Adjust. no safeguard'!$C$10:$U$10,0)) -> 0 | L9: =INDEX(OFFSET('Adjust. no safeguard'!$C$1:$U$1,$D9-1,0),MATCH(L$4,'Adjust. no safeguard'!$C$10:$U$10,0)) -> 0 | M9: =INDEX(OFFSET('Adjust. no safeguard'!$C$1:$U$1,$D9-1,0),MATCH(M$4,'Adjust. no safeguard'!$C$10:$U$10,0)) -> 0 | ... X9: =INDEX(OFFSET('Adjust. no safeguard'!$C$1:$U$1,$D9-1,0),MATCH(X$4,'Adjust. no safeguard'!$C$10:$U$10,0)) -> 0
B10: 6 | C10: Interest expenditure | D10: 68 | E10: (% GDP) | F10: =INDEX(OFFSET('Adjust. no safeguard'!$C$1:$U$1,$D10-1,0),MATCH(F$4,'Adjust. no safeguard'!$C$10:$U$10,0)) -> 0 | G10: =INDEX(OFFSET('Adjust. no safeguard'!$C$1:$U$1,$D10-1,0),MATCH(G$4,'Adjust. no safeguard'!$C$10:$U$10,0)) -> 0.71728823 | H10: =INDEX(OFFSET('Adjust. no safeguard'!$C$1:$U$1,$D10-1,0),MATCH(H$4,'Adjust. no safeguard'!$C$10:$U$10,0)) -> 0.74801829 | I10: =INDEX(OFFSET('Adjust. no safeguard'!$C$1:$U$1,$D10-1,0),MATCH(I$4,'Adjust. no safeguard'!$C$10:$U$10,0)) -> 0.84257493 | J10: =INDEX(OFFSET('Adjust. no safeguard'!$C$1:$U$1,$D10-1,0),MATCH(J$4,'Adjust. no safeguard'!$C$10:$U$10,0)) -> 0.90946084 | K10: =INDEX(OFFSET('Adjust. no safeguard'!$C$1:$U$1,$D10-1,0),MATCH(K$4,'Adjust. no safeguard'!$C$10:$U$10,0)) -> 0.97513896 | L10: =INDEX(OFFSET('Adjust. no safeguard'!$C$1:$U$1,$D10-1,0),MATCH(L$4,'Adjust. no safeguard'!$C$10:$U$10,0)) -> 1.0385131 | M10: =INDEX(OFFSET('Adjust. no safeguard'!$C$1:$U$1,$D10-1,0),MATCH(M$4,'Adjust. no safeguard'!$C$10:$U$10,0)) -> 1.1060585 | ... X10: =INDEX(OFFSET('Adjust. no safeguard'!$C$1:$U$1,$D10-1,0),MATCH(X$4,'Adjust. no safeguard'!$C$10:$U$10,0)) -> 2.1778208
B11: 7 | C11: Long-term interest rate | D11: 37 | E11: (%) | F11: =INDEX(OFFSET('Adjust. no safeguard'!$C$1:$U$1,$D11-1,0),MATCH(F$4,'Adjust. no safeguard'!$C$10:$U$10,0)) -> 2.6205 | G11: =INDEX(OFFSET('Adjust. no safeguard'!$C$1:$U$1,$D11-1,0),MATCH(G$4,'Adjust. no safeguard'!$C$10:$U$10,0)) -> 2.78965 | H11: =INDEX(OFFSET('Adjust. no safeguard'!$C$1:$U$1,$D11-1,0),MATCH(H$4,'Adjust. no safeguard'!$C$10:$U$10,0)) -> 2.894953 | I11: =INDEX(OFFSET('Adjust. no safeguard'!$C$1:$U$1,$D11-1,0),MATCH(I$4,'Adjust. no safeguard'!$C$10:$U$10,0)) -> 3.081676 | J11: =INDEX(OFFSET('Adjust. no safeguard'!$C$1:$U$1,$D11-1,0),MATCH(J$4,'Adjust. no safeguard'!$C$10:$U$10,0)) -> 3.188669 | K11: =INDEX(OFFSET('Adjust. no safeguard'!$C$1:$U$1,$D11-1,0),MATCH(K$4,'Adjust. no safeguard'!$C$10:$U$10,0)) -> 3.295662 | L11: =INDEX(OFFSET('Adjust. no safeguard'!$C$1:$U$1,$D11-1,0),MATCH(L$4,'Adjust. no safeguard'!$C$10:$U$10,0)) -> 3.402655 | M11: =INDEX(OFFSET('Adjust. no safeguard'!$C$1:$U$1,$D11-1,0),MATCH(M$4,'Adjust. no safeguard'!$C$10:$U$10,0)) -> 3.509648 | ... X11: =INDEX(OFFSET('Adjust. no safeguard'!$C$1:$U$1,$D11-1,0),MATCH(X$4,'Adjust. no safeguard'!$C$10:$U$10,0)) -> 3.959453
B12: 8 | C12: Short-term interest rate | D12: 38 | E12: (%) | F12: =INDEX(OFFSET('Adjust. no safeguard'!$C$1:$U$1,$D12-1,0),MATCH(F$4,'Adjust. no safeguard'!$C$10:$U$10,0)) -> 3.570833 | G12: =INDEX(OFFSET('Adjust. no safeguard'!$C$1:$U$1,$D12-1,0),MATCH(G$4,'Adjust. no safeguard'!$C$10:$U$10,0)) -> 2.172583 | H12: =INDEX(OFFSET('Adjust. no safeguard'!$C$1:$U$1,$D12-1,0),MATCH(H$4,'Adjust. no safeguard'!$C$10:$U$10,0)) -> 1.91225 | I12: =INDEX(OFFSET('Adjust. no safeguard'!$C$1:$U$1,$D12-1,0),MATCH(I$4,'Adjust. no safeguard'!$C$10:$U$10,0)) -> 2.024375 | J12: =INDEX(OFFSET('Adjust. no safeguard'!$C$1:$U$1,$D12-1,0),MATCH(J$4,'Adjust. no safeguard'!$C$10:$U$10,0)) -> 2.1784319 | K12: =INDEX(OFFSET('Adjust. no safeguard'!$C$1:$U$1,$D12-1,0),MATCH(K$4,'Adjust. no safeguard'!$C$10:$U$10,0)) -> 2.3324888 | L12: =INDEX(OFFSET('Adjust. no safeguard'!$C$1:$U$1,$D12-1,0),MATCH(L$4,'Adjust. no safeguard'!$C$10:$U$10,0)) -> 2.4865456 | M12: =INDEX(OFFSET('Adjust. no safeguard'!$C$1:$U$1,$D12-1,0),MATCH(M$4,'Adjust. no safeguard'!$C$10:$U$10,0)) -> 2.6406025 | ... X12: =INDEX(OFFSET('Adjust. no safeguard'!$C$1:$U$1,$D12-1,0),MATCH(X$4,'Adjust. no safeguard'!$C$10:$U$10,0)) -> 2.8169395
B13: 9 | C13: Implicit average interest rate | D13: 36 | E13: (%) | F13: =INDEX(OFFSET('Adjust. no safeguard'!$C$1:$U$1,$D13-1,0),MATCH(F$4,'Adjust. no safeguard'!$C$10:$U$10,0)) -> 1.646586 | G13: =INDEX(OFFSET('Adjust. no safeguard'!$C$1:$U$1,$D13-1,0),MATCH(G$4,'Adjust. no safeguard'!$C$10:$U$10,0)) -> 1.72 | H13: =INDEX(OFFSET('Adjust. no safeguard'!$C$1:$U$1,$D13-1,0),MATCH(H$4,'Adjust. no safeguard'!$C$10:$U$10,0)) -> 1.732298 | I13: =INDEX(OFFSET('Adjust. no safeguard'!$C$1:$U$1,$D13-1,0),MATCH(I$4,'Adjust. no safeguard'!$C$10:$U$10,0)) -> 1.8261287 | J13: =INDEX(OFFSET('Adjust. no safeguard'!$C$1:$U$1,$D13-1,0),MATCH(J$4,'Adjust. no safeguard'!$C$10:$U$10,0)) -> 1.9630297 | K13: =INDEX(OFFSET('Adjust. no safeguard'!$C$1:$U$1,$D13-1,0),MATCH(K$4,'Adjust. no safeguard'!$C$10:$U$10,0)) -> 2.0990021 | L13: =INDEX(OFFSET('Adjust. no safeguard'!$C$1:$U$1,$D13-1,0),MATCH(L$4,'Adjust. no safeguard'!$C$10:$U$10,0)) -> 2.234119 | M13: =INDEX(OFFSET('Adjust. no safeguard'!$C$1:$U$1,$D13-1,0),MATCH(M$4,'Adjust. no safeguard'!$C$10:$U$10,0)) -> 2.3707683 | ... X13: =INDEX(OFFSET('Adjust. no safeguard'!$C$1:$U$1,$D13-1,0),MATCH(X$4,'Adjust. no safeguard'!$C$10:$U$10,0)) -> 3.5460259
B14: 10 | C14: Stock-flow adjustment | D14: 72 | E14: (% GDP) | F14: =INDEX(OFFSET('Adjust. no safeguard'!$C$1:$U$1,$D14-1,0),MATCH(F$4,'Adjust. no safeguard'!$C$10:$U$10,0)) -> 0 | G14: =INDEX(OFFSET('Adjust. no safeguard'!$C$1:$U$1,$D14-1,0),MATCH(G$4,'Adjust. no safeguard'!$C$10:$U$10,0)) -> 1.579997 | H14: =INDEX(OFFSET('Adjust. no safeguard'!$C$1:$U$1,$D14-1,0),MATCH(H$4,'Adjust. no safeguard'!$C$10:$U$10,0)) -> 2.014677 | I14: =INDEX(OFFSET('Adjust. no safeguard'!$C$1:$U$1,$D14-1,0),MATCH(I$4,'Adjust. no safeguard'!$C$10:$U$10,0)) -> -2.05e-06 | J14: =INDEX(OFFSET('Adjust. no safeguard'!$C$1:$U$1,$D14-1,0),MATCH(J$4,'Adjust. no safeguard'!$C$10:$U$10,0)) -> 0 | K14: =INDEX(OFFSET('Adjust. no safeguard'!$C$1:$U$1,$D14-1,0),MATCH(K$4,'Adjust. no safeguard'!$C$10:$U$10,0)) -> 0 | L14: =INDEX(OFFSET('Adjust. no safeguard'!$C$1:$U$1,$D14-1,0),MATCH(L$4,'Adjust. no safeguard'!$C$10:$U$10,0)) -> 0 | M14: =INDEX(OFFSET('Adjust. no safeguard'!$C$1:$U$1,$D14-1,0),MATCH(M$4,'Adjust. no safeguard'!$C$10:$U$10,0)) -> 0 | ... X14: =INDEX(OFFSET('Adjust. no safeguard'!$C$1:$U$1,$D14-1,0),MATCH(X$4,'Adjust. no safeguard'!$C$10:$U$10,0)) -> 0
